{
  "type": "Feature",
  "properties": {
    "addr:full":"Sognepr\u00e6st: Erik Langkjer (K/B), Pr\u00e6stek\u00e6ret 15, P\u00e5by Kolding Danmark 6000",
    "addr:housenumber":"15",
    "addr:postcode":"6000",
    "addr:street":"Paaby",
    "iso:country":"DK",
    "sg:address":"Sognepr\u00e6st: Erik Langkjer (K/B), Pr\u00e6stek\u00e6ret 15, P\u00e5by",
    "sg:city":"Kolding",
    "sg:orig_category":"Kirkesogne",
    "sg:phone":"+45 75 53 01 91",
    "sg:postcode":"6000",
    "sg:province":"Danmark",
    "wof:name":"Harte sogn",
    "wof:placetype":"venue"
},
  "geometry": {"coordinates":[9.4733953476,55.4863586426],"type":"Point"}
}