{
  "type": "Feature",
  "properties": {
    "addr:full":"Vester S\u00f8gade 10 K\u00f8benhavn Danmark 1601",
    "addr:housenumber":"10;1601",
    "addr:street":"Sogade",
    "iso:country":"DK",
    "sg:address":"Vester S\u00f8gade 10",
    "sg:city":"K\u00f8benhavn",
    "sg:orig_category":"Flyselskaber",
    "sg:phone":"+45 70 10 50 68",
    "sg:postcode":"1601",
    "sg:province":"Danmark",
    "sg:website":"www.qualiflyer.com",
    "wof:name":"TAP Air Portugal",
    "wof:placetype":"venue"
},
  "geometry": {"coordinates":[-85.2299499512,37.1363105774],"type":"Point"}
}