{
  "type": "Feature",
  "properties": {
    "addr:full":"Nyvej 7 C Skibby Danmark 4050",
    "addr:housenumber":"7 c",
    "addr:postcode":"4050",
    "addr:street":"Nyvej",
    "iso:country":"DK",
    "sg:address":"Nyvej 7 C",
    "sg:city":"Skibby",
    "sg:orig_category":"Biblioteker",
    "sg:phone":"+45 47 59 59 60",
    "sg:postcode":"4050",
    "sg:province":"Danmark",
    "sg:website":"www.bibliotek.skibby.dk",
    "wof:name":"Skibby Bibliotek",
    "wof:placetype":"venue"
},
  "geometry": {"coordinates":[11.9541893005,55.7486801147],"type":"Point"}
}