{
  "type": "Feature",
  "properties": {
    "addr:full":"Fmd.: Frank Staun, Grydstedvej 53, Tyrrestrup Nibe Danmark 9240",
    "addr:housenumber":"53",
    "addr:postcode":"9240",
    "addr:street":"Grydstedvej;Tyrrestrup",
    "iso:country":"DK",
    "sg:address":"Fmd.: Frank Staun, Grydstedvej 53, Tyrrestrup",
    "sg:city":"Nibe",
    "sg:orig_category":"Hobbybetonede foreninger",
    "sg:phone":"+45 98 35 70 12",
    "sg:postcode":"9240",
    "sg:province":"Danmark",
    "wof:name":"Nibe By's Og Omegns Skydeselskab",
    "wof:placetype":"venue"
},
  "geometry": {"coordinates":[9.6393280029,56.982421875],"type":"Point"}
}