{
  "type": "Feature",
  "properties": {
    "addr:full":"v/ Randi Jensen, Grimsbyvej 13 \u00d8lstykke Danmark 3650",
    "addr:housenumber":"13",
    "addr:postcode":"3650",
    "addr:street":"Grimsbyvej",
    "iso:country":"DK",
    "sg:address":"v/ Randi Jensen, Grimsbyvej 13",
    "sg:city":"\u00d8lstykke",
    "sg:orig_category":"Spejderkorps",
    "sg:phone":"+45 47 17 71 02",
    "sg:postcode":"3650",
    "sg:province":"Danmark",
    "wof:name":"KFUK-Spejderne",
    "wof:placetype":"venue"
},
  "geometry": {"coordinates":[-109.33489990229999,40.3696899414],"type":"Point"}
}