{
  "type": "Feature",
  "properties": {
    "iso:country":"DK",
    "sg:address":"Stefansgade 45",
    "sg:city":"K\u00f8benhavn N",
    "sg:orig_category":"Solcentre",
    "sg:phone":"+45 35 85 24 06",
    "sg:postcode":"2200",
    "sg:province":"Danmark",
    "wof:name":"Fris\u00f8r & Sol",
    "wof:placetype":"venue"
},
  "geometry": {"coordinates":[-97.7965927124,47.7011795044],"type":"Point"}
}