{
  "type": "Feature",
  "properties": {
    "iso:country":"DK",
    "sg:address":"Strandvejen 164, Vejlby",
    "sg:city":"Harbo\u00f8re",
    "sg:orig_category":"Sommerhusudlejning",
    "sg:phone":"+45 97 83 77 00",
    "sg:postcode":"7673",
    "sg:province":"Danmark",
    "wof:name":"Sol og Strand Feriehusudlejning",
    "wof:placetype":"venue"
},
  "geometry": {"coordinates":[8.1534700394,56.6043395996],"type":"Point"}
}