{
  "type": "Feature",
  "properties": {
    "addr:full":"Gr\u00f8nttorvet 104 Valby Danmark 2500",
    "addr:housenumber":"104",
    "addr:postcode":"2500",
    "iso:country":"DK",
    "sg:address":"Gr\u00f8nttorvet 104",
    "sg:city":"Valby",
    "sg:orig_category":"Frugt en gros",
    "sg:phone":"+45 36 46 70 18",
    "sg:postcode":"2500",
    "sg:province":"Danmark",
    "wof:name":"Ibenholt, F.A.",
    "wof:placetype":"venue"
},
  "geometry": {"coordinates":[12.502450943,55.6567955017],"type":"Point"}
}