{
  "type": "Feature",
  "properties": {
    "addr:full":"v/ Lone Busk, Voerm\u00f8llevej 15, Lyng\u00e5 Hadsten Danmark 8370",
    "addr:housenumber":"15",
    "addr:postcode":"8370",
    "addr:street":"Voermollevej;Lyngaa",
    "iso:country":"DK",
    "sg:address":"v/ Lone Busk, Voerm\u00f8llevej 15, Lyng\u00e5",
    "sg:city":"Hadsten",
    "sg:orig_category":"Borger- og beboerforeninger",
    "sg:phone":"+45 86 98 34 47",
    "sg:postcode":"8370",
    "sg:province":"Danmark",
    "wof:name":"Lyng\u00e5 borgerforening",
    "wof:placetype":"venue"
},
  "geometry": {"coordinates":[10.047659874,56.3287239075],"type":"Point"}
}