{
  "type": "Feature",
  "properties": {
    "addr:full":"Hvidelvej 5 Herning Danmark 7400",
    "addr:housenumber":"5",
    "addr:postcode":"7400",
    "addr:street":"Hvidelvej",
    "iso:country":"DK",
    "sg:address":"Hvidelvej 5",
    "sg:city":"Herning",
    "sg:orig_category":"Industrilakering",
    "sg:phone":"+45 97 12 26 66",
    "sg:postcode":"7400",
    "sg:province":"Danmark",
    "wof:name":"OB Industrilak ApS",
    "wof:placetype":"venue"
},
  "geometry": {"coordinates":[8.9322013855,56.1263275146],"type":"Point"}
}