{
  "type": "Feature",
  "properties": {
    "iso:country":"DK",
    "sg:address":"Kontaktpers.: B\u00f8rge Porup, Hjortevej 9, S\u00f8ften",
    "sg:city":"Hinnerup",
    "sg:orig_category":"Spejderkorps",
    "sg:phone":"+45 86 91 14 91",
    "sg:postcode":"8382",
    "sg:province":"Danmark",
    "wof:name":"KFUM-Spejderne, Frijsenborg Division Vestlige \u00c5rhus",
    "wof:placetype":"venue"
},
  "geometry": {"coordinates":[10.0614156723,56.2650604248],"type":"Point"}
}