{
  "type": "Feature",
  "properties": {
    "addr:full":"Genner Bygade 44, Genner R\u00f8dekro Danmark 6230",
    "addr:housenumber":"44",
    "addr:postcode":"6230",
    "addr:street":"Genner Bygade",
    "iso:country":"DK",
    "sg:address":"Genner Bygade 44, Genner",
    "sg:city":"R\u00f8dekro",
    "sg:orig_category":"Autoreparation og -service",
    "sg:phone":"+45 74 69 89 44",
    "sg:postcode":"6230",
    "sg:province":"Danmark",
    "wof:name":"Genner Bil-Center",
    "wof:placetype":"venue"
},
  "geometry": {"coordinates":[9.307510376,55.0235786438],"type":"Point"}
}