{
  "type": "Feature",
  "properties": {
    "addr:full":"Skar\u00f8 - Drej\u00f8ruten, Havnepladsen 2 Svendborg Danmark 5700",
    "addr:housenumber":"2",
    "addr:postcode":"5700",
    "addr:street":"Havnepladsen",
    "iso:country":"DK",
    "sg:address":"Skar\u00f8 - Drej\u00f8ruten, Havnepladsen 2",
    "sg:city":"Svendborg",
    "sg:orig_category":"Rederier",
    "sg:phone":"+45 62 21 02 62",
    "sg:postcode":"5700",
    "sg:province":"Danmark",
    "wof:name":"Rederiet H\u00f8jestene - F\u00e6rgekontoret",
    "wof:placetype":"venue"
},
  "geometry": {"coordinates":[10.6065101624,55.0595970154],"type":"Point"}
}