{
  "type": "Feature",
  "properties": {
    "iso:country":"DK",
    "sg:address":"v/ Gerda Sonne, \u00d8stre Pennehavevej 12",
    "sg:city":"Rungsted Kyst",
    "sg:orig_category":"Spejderkorps",
    "sg:phone":"+45 45 86 28 14",
    "sg:postcode":"2960",
    "sg:province":"Danmark",
    "sg:website":"www.bentbyg.dk",
    "wof:name":"DDS, Bent Byg Gruppe (drenge og piger)",
    "wof:placetype":"venue"
},
  "geometry": {"coordinates":[12.5300750732,55.883846283],"type":"Point"}
}