{
  "type": "Feature",
  "properties": {
    "addr:full":"Rugmarken 13 Farum Danmark 3520",
    "addr:housenumber":"13",
    "addr:postcode":"3520",
    "addr:street":"Rugmarken",
    "iso:country":"DK",
    "sg:address":"Rugmarken 13",
    "sg:city":"Farum",
    "sg:orig_category":"Autolakering",
    "sg:phone":"+45 44 95 66 51",
    "sg:postcode":"3520",
    "sg:province":"Danmark",
    "wof:name":"Farum Autolakering",
    "wof:placetype":"venue"
},
  "geometry": {"coordinates":[12.3721179962,55.8169136047],"type":"Point"}
}