{
  "type": "Feature",
  "properties": {
    "addr:full":"N\u00f8rgaardsvej 2 Kongens Lyngby Danmark 2800",
    "addr:housenumber":"2",
    "addr:postcode":"2800",
    "addr:street":"Norgaardsvej",
    "iso:country":"DK",
    "sg:address":"N\u00f8rgaardsvej 2",
    "sg:city":"Kongens Lyngby",
    "sg:classifiers":[
        {
            "category":"Banks & Credit Unions",
            "subcategory":"Bank",
            "type":"Services"
        }
    ],
    "sg:phone":"+45 45 93 22 00",
    "sg:postcode":"2800",
    "sg:province":"Danmark",
    "sg:tags":[
        "banker"
    ],
    "wof:name":"Nordea",
    "wof:placetype":"venue"
},
  "geometry": {"coordinates":[12.53683,55.794991],"type":"Point"}
}