{
  "type": "Feature",
  "properties": {
    "iso:country":"DK",
    "sg:address":"Pr\u00e6st\u00f8vej 27",
    "sg:city":"Fakse",
    "sg:orig_category":"Servicestationer",
    "sg:phone":"+45 56 71 37 50",
    "sg:postcode":"4640",
    "sg:province":"Danmark",
    "wof:name":"Q8 Service",
    "wof:placetype":"venue"
},
  "geometry": {"coordinates":[12.1141176224,55.2525482178],"type":"Point"}
}