{
  "type": "Feature",
  "properties": {
    "addr:full":"Sognepr\u00e6st: Anders Juul Fuglsang (K/B), Marie Curtz Vej 3, Vium Kjellerup Danmark 8620",
    "addr:housenumber":"b;3",
    "addr:postcode":"8620",
    "addr:street":"Marie Curtz Vej",
    "iso:country":"DK",
    "sg:address":"Sognepr\u00e6st: Anders Juul Fuglsang (K/B), Marie Curtz Vej 3, Vium",
    "sg:city":"Kjellerup",
    "sg:orig_category":"Kirkesogne",
    "sg:phone":"+45 86 66 74 29",
    "sg:postcode":"8620",
    "sg:province":"Danmark",
    "wof:name":"Vium Sogn",
    "wof:placetype":"venue"
},
  "geometry": {"coordinates":[9.430934906,56.2877655029],"type":"Point"}
}