{
  "type": "Feature",
  "properties": {
    "addr:full":"R\u00f8dkilde M\u00f8llevej 1  Svendborg Danmark 5700",
    "addr:housenumber":"1",
    "addr:postcode":"5700",
    "addr:street":"Mollevej",
    "iso:country":"DK",
    "sg:address":"R\u00f8dkilde M\u00f8llevej 1 ",
    "sg:city":"Svendborg",
    "sg:classifiers":[
        {
            "category":"Food & Beverages",
            "subcategory":"Dairy",
            "type":"Retail Goods"
        }
    ],
    "sg:phone":"+45 62 21 02 03",
    "sg:postcode":"5700",
    "sg:province":"Danmark",
    "sg:tags":[
        "product"
    ],
    "wof:name":"KIRKEBY CHEESE EXPORT A/S",
    "wof:placetype":"venue"
},
  "geometry": {"coordinates":[10.6065101624,55.0595970154],"type":"Point"}
}