{
  "type": "Feature",
  "properties": {
    "addr:full":"Nybodalen 4 Holstebro Danmark 7500",
    "addr:housenumber":"4",
    "addr:postcode":"7500",
    "addr:street":"Nybodalen",
    "iso:country":"DK",
    "sg:address":"Nybodalen 4",
    "sg:city":"Holstebro",
    "sg:orig_category":"Rustbeskyttelse",
    "sg:phone":"+45 97 42 26 72",
    "sg:postcode":"7500",
    "sg:province":"Danmark",
    "wof:name":"Undervognstunellen",
    "wof:placetype":"venue"
},
  "geometry": {"coordinates":[8.632768631,56.3433876038],"type":"Point"}
}