{
  "type": "Feature",
  "properties": {
    "addr:full":"Bohrsvej 1 Ribe Danmark 6760",
    "addr:housenumber":"1",
    "addr:postcode":"6760",
    "addr:street":"Bohrsvej",
    "iso:country":"DK",
    "sg:address":"Bohrsvej 1",
    "sg:city":"Ribe",
    "sg:orig_category":"Autoforhandlere",
    "sg:phone":"+45 75 42 04 33",
    "sg:postcode":"6760",
    "sg:province":"Danmark",
    "wof:name":"Auto-Cramer A/S",
    "wof:placetype":"venue"
},
  "geometry": {"coordinates":[8.7785692215,55.3519592285],"type":"Point"}
}