{
  "type": "Feature",
  "properties": {
    "addr:full":"Vestre Havnevej 34, Havnebyen Sj\u00e6llands Odde Danmark 4583",
    "addr:housenumber":"34",
    "addr:postcode":"4583",
    "addr:street":"Vestre Havnevej;Sjaellands",
    "iso:country":"DK",
    "sg:address":"Vestre Havnevej 34, Havnebyen",
    "sg:city":"Sj\u00e6llands Odde",
    "sg:classifiers":[
        {
            "category":"Restaurant",
            "type":"Food & Drink"
        }
    ],
    "sg:phone":"+45 59 32 63 86",
    "sg:postcode":"4583",
    "sg:province":"Danmark",
    "sg:website":"www.dengyldnehane.dk",
    "wof:name":"Gyldne Hane, Den",
    "wof:placetype":"venue"
},
  "geometry": {"coordinates":[11.3198680878,55.9799728394],"type":"Point"}
}