{
  "type": "Feature",
  "properties": {
    "addr:full":"Teglg\u00e5rdsvej 27 Charlottenlund Danmark 2920",
    "addr:housenumber":"27",
    "addr:postcode":"2920",
    "addr:street":"Teglgaardsvej",
    "iso:country":"DK",
    "sg:address":"Teglg\u00e5rdsvej 27",
    "sg:city":"Charlottenlund",
    "sg:orig_category":"INGENI\u00c3\u02dcRER",
    "sg:phone":"+45 39 63 51 08",
    "sg:postcode":"2920",
    "sg:province":"Danmark",
    "wof:name":"Garmin International Emballage R\u00e5dgivning ApS, Kurt H.",
    "wof:placetype":"venue"
},
  "geometry": {"coordinates":[12.5909023285,55.7614936829],"type":"Point"}
}