{
  "type": "Feature",
  "properties": {
    "iso:country":"DK",
    "sg:address":"Vassinger\u00f8dvej 89",
    "sg:city":"Lynge",
    "sg:orig_category":"Serigrafi",
    "sg:phone":"+45 48 18 76 48",
    "sg:postcode":"3540",
    "sg:province":"Danmark",
    "sg:website":"www.dalgaard.dk",
    "wof:name":"Dalgaard Serigrafi ApS",
    "wof:placetype":"venue"
},
  "geometry": {"coordinates":[12.309411,55.830616],"type":"Point"}
}