{
  "type": "Feature",
  "properties": {
    "addr:full":"Fmd.: Lis Basse, Lakseruten 3 Svaneke Danmark 3740",
    "addr:housenumber":"3",
    "addr:postcode":"3740",
    "addr:street":"Fmd. Lis Basse Lakseruten",
    "iso:country":"DK",
    "sg:address":"Fmd.: Lis Basse, Lakseruten 3",
    "sg:city":"Svaneke",
    "sg:orig_category":"Teatre",
    "sg:phone":"+45 56 49 92 49",
    "sg:postcode":"3740",
    "sg:province":"Danmark",
    "wof:name":"Svaneke Akt\u00f8rerne",
    "wof:placetype":"venue"
},
  "geometry": {"coordinates":[15.140504837,55.1364555359],"type":"Point"}
}