{
  "type": "Feature",
  "properties": {
    "addr:full":"Hadsundvej 65 Aalborg Danmark 9000",
    "addr:housenumber":"65",
    "addr:postcode":"9000",
    "addr:street":"Hadsundvej",
    "iso:country":"DK",
    "sg:address":"Hadsundvej 65",
    "sg:city":"Aalborg",
    "sg:orig_category":"Boligselskaber",
    "sg:phone":"+45 98 10 23 50",
    "sg:postcode":"9000",
    "sg:province":"Danmark",
    "wof:name":"Aalborg Boligadministration ApS",
    "wof:placetype":"venue"
},
  "geometry": {"coordinates":[9.9528007507,57.0386314392],"type":"Point"}
}