{
  "type": "Feature",
  "properties": {
    "addr:full":"Klostermarken 3 Mariager Danmark 9550",
    "addr:housenumber":"3",
    "addr:postcode":"9550",
    "addr:street":"Klostermarken",
    "iso:country":"DK",
    "sg:address":"Klostermarken 3",
    "sg:city":"Mariager",
    "sg:classifiers":[
        {
            "category":"Wholesale",
            "subcategory":"Chemicals & Plastics",
            "type":"Manufacturing & Wholesale Goods"
        }
    ],
    "sg:phone":"+45 98 54 16 55",
    "sg:postcode":"9550",
    "sg:province":"Danmark",
    "wof:name":"Larsen ApS, Aage Vestergaard",
    "wof:placetype":"venue"
},
  "geometry": {"coordinates":[9.9724750519,56.635635376],"type":"Point"}
}