{
  "type": "Feature",
  "properties": {
    "addr:full":"Rug\u00e5rdsvej 516 A, Korup Odense NV Danmark 5210",
    "addr:housenumber":"516 a",
    "addr:postcode":"5210",
    "addr:street":"Rugaardsvej;Korup",
    "iso:country":"DK",
    "sg:address":"Rug\u00e5rdsvej 516 A, Korup",
    "sg:city":"Odense NV",
    "sg:orig_category":"Hushold.apparater, service af",
    "sg:phone":"+45 65 94 31 03",
    "sg:postcode":"5210",
    "sg:province":"Danmark",
    "wof:name":"Fyns Elservice",
    "wof:placetype":"venue"
},
  "geometry": {"coordinates":[10.274764061,55.4303321838],"type":"Point"}
}