{
  "type": "Feature",
  "properties": {
    "addr:full":"Fmd.: Henning Mortensen, Hovg\u00e5rdsparken 21, 1. th., Postboks 41 Esperg\u00e6rde Danmark 3060",
    "addr:housenumber":"21 1 th.;41",
    "addr:postcode":"3060",
    "addr:street":"Hovgaardsparken;Postboks",
    "iso:country":"DK",
    "sg:address":"Fmd.: Henning Mortensen, Hovg\u00e5rdsparken 21, 1. th., Postboks 41",
    "sg:city":"Esperg\u00e6rde",
    "sg:orig_category":"Politiske foreninger, \u00c3\u02dcvrige",
    "sg:phone":"+45 49 17 09 50",
    "sg:postcode":"3060",
    "sg:province":"Danmark",
    "sg:website":"www.folkebevaegelsen.dk",
    "wof:name":"Helsing\u00f8r-komit\u00e9en mod EU",
    "wof:placetype":"venue"
},
  "geometry": {"coordinates":[11.6512403488,47.8390617371],"type":"Point"}
}