{
  "type": "Feature",
  "properties": {
    "addr:full":"Jens Gr\u00f8ns Vej 15-17 Vejle Danmark 7100",
    "addr:postcode":"15-17;7100",
    "addr:street":"Grons Vej",
    "iso:country":"DK",
    "sg:address":"Jens Gr\u00f8ns Vej 15-17",
    "sg:city":"Vejle",
    "sg:orig_category":"Medicinalvareindustri",
    "sg:phone":"+45 75 85 90 44",
    "sg:postcode":"7100",
    "sg:province":"Danmark",
    "wof:name":"Pedersen Medical A/S",
    "wof:placetype":"venue"
},
  "geometry": {"coordinates":[9.5492420197,55.6852760315],"type":"Point"}
}