{
  "type": "Feature",
  "properties": {
    "addr:full":"Skuldelevvej 63 Skibby Danmark 4050",
    "addr:housenumber":"63",
    "addr:postcode":"4050",
    "addr:street":"Skuldelevvej",
    "iso:country":"DK",
    "sg:address":"Skuldelevvej 63",
    "sg:city":"Skibby",
    "sg:orig_category":"Autoreparation og -service",
    "sg:phone":"+45 47 52 08 51",
    "sg:postcode":"4050",
    "sg:province":"Danmark",
    "wof:name":"Skuldelev Auto",
    "wof:placetype":"venue"
},
  "geometry": {"coordinates":[12.0086984634,55.7749977112],"type":"Point"}
}