{
  "type": "Feature",
  "properties": {
    "iso:country":"DK",
    "sg:address":"Nyvangen 49",
    "sg:city":"Silkeborg",
    "sg:orig_category":"Heste, Behandling af",
    "sg:phone":"+45 20 22 71 17",
    "sg:postcode":"8600",
    "sg:province":"Danmark",
    "wof:name":"S\u00f8gaard, Karina",
    "wof:placetype":"venue"
},
  "geometry": {"coordinates":[9.535071373,56.1796455383],"type":"Point"}
}