{
  "type": "Feature",
  "properties": {
    "addr:full":"N\u00f8rregade 13, 1. tv. Skive Danmark 7800",
    "addr:housenumber":"13 1 tv.",
    "addr:postcode":"7800",
    "addr:street":"Norregade",
    "iso:country":"DK",
    "sg:address":"N\u00f8rregade 13, 1. tv.",
    "sg:city":"Skive",
    "sg:orig_category":"Advokater",
    "sg:phone":"+45 97 52 61 66",
    "sg:postcode":"7800",
    "sg:province":"Danmark",
    "wof:name":"Jensen, Knud Borup",
    "wof:placetype":"venue"
},
  "geometry": {"coordinates":[9.0320358276,56.5666427612],"type":"Point"}
}