{
  "type": "Feature",
  "properties": {
    "iso:country":"DK",
    "sg:address":"Gundevej 2",
    "sg:city":"Thisted",
    "sg:orig_category":"Zoneterapeuter",
    "sg:phone":"+45 97 92 20 44",
    "sg:postcode":"7700",
    "sg:province":"Danmark",
    "wof:name":"Skammelsen, Else Marie",
    "wof:placetype":"venue"
},
  "geometry": {"coordinates":[8.6730241776,56.9575233459],"type":"Point"}
}