{
  "type": "Feature",
  "properties": {
    "addr:full":"Industrivej 14 Aabybro Danmark 9440",
    "addr:housenumber":"14",
    "addr:postcode":"9440",
    "addr:street":"Industrivej",
    "iso:country":"DK",
    "sg:address":"Industrivej 14",
    "sg:city":"Aabybro",
    "sg:orig_category":"Flytteforretninger",
    "sg:phone":"+45 98 24 45 73",
    "sg:postcode":"9440",
    "sg:province":"Danmark",
    "wof:name":"Dansk Discount Flyt",
    "wof:placetype":"venue"
},
  "geometry": {"coordinates":[9.7457084656,57.1530838013],"type":"Point"}
}