{
  "type": "Feature",
  "properties": {
    "addr:full":"Dalkildeg\u00e5rdsalle 1 Faaborg Danmark 5600",
    "addr:housenumber":"1",
    "addr:postcode":"5600",
    "addr:street":"Dalkildegaardsalle",
    "iso:country":"DK",
    "sg:address":"Dalkildeg\u00e5rdsalle 1",
    "sg:city":"Faaborg",
    "sg:orig_category":"Golfudstyr",
    "sg:phone":"+45 62 61 75 39",
    "sg:postcode":"5600",
    "sg:province":"Danmark",
    "wof:name":"F\u00e5borg Proshop",
    "wof:placetype":"venue"
},
  "geometry": {"coordinates":[10.2531557083,55.1363639832],"type":"Point"}
}