{
  "type": "Feature",
  "properties": {
    "addr:full":"Kokholm 5 Kolding Danmark 6000",
    "addr:housenumber":"5",
    "addr:postcode":"6000",
    "addr:street":"Kokholm",
    "iso:country":"DK",
    "sg:address":"Kokholm 5",
    "sg:city":"Kolding",
    "sg:orig_category":"Autoruder",
    "sg:phone":"+45 75 56 98 11",
    "sg:postcode":"6000",
    "sg:province":"Danmark",
    "wof:name":"Pilkington Automotive",
    "wof:placetype":"venue"
},
  "geometry": {"coordinates":[9.4738693237,55.5371589661],"type":"Point"}
}