{
  "type": "Feature",
  "properties": {
    "addr:full":"Borups Plads 26 K\u00f8benhavn N Danmark 2200",
    "addr:housenumber":"26",
    "addr:postcode":"2200",
    "addr:street":"Borups Plads;N Danmark",
    "iso:country":"DK",
    "sg:address":"Borups Plads 26",
    "sg:city":"K\u00f8benhavn N",
    "sg:orig_category":"Bodegaer",
    "sg:phone":"+45 38 19 42 42",
    "sg:postcode":"2200",
    "sg:province":"Danmark",
    "wof:name":"Cafe Knejpen",
    "wof:placetype":"venue"
},
  "geometry": {"coordinates":[-94.05847167970001,47.7522468567],"type":"Point"}
}