{
  "type": "Feature",
  "properties": {
    "addr:full":"Bredgade 200 Br\u00f8nderslev Danmark 9700",
    "addr:housenumber":"200",
    "addr:postcode":"9700",
    "addr:street":"Bredgade",
    "iso:country":"DK",
    "sg:address":"Bredgade 200",
    "sg:city":"Br\u00f8nderslev",
    "sg:orig_category":"Autolakering",
    "sg:phone":"+45 98 80 06 11",
    "sg:postcode":"9700",
    "sg:province":"Danmark",
    "wof:name":"Bredgades ny Autolakering",
    "wof:placetype":"venue"
},
  "geometry": {"coordinates":[9.967007637,57.2671051025],"type":"Point"}
}