{
  "type": "Feature",
  "properties": {
    "addr:full":"Koldingvej 61, Vester Nebel Egtved Danmark 6040",
    "addr:housenumber":"61",
    "addr:postcode":"6040",
    "addr:street":"Koldingvej;Nebel",
    "iso:country":"DK",
    "sg:address":"Koldingvej 61, Vester Nebel",
    "sg:city":"Egtved",
    "sg:orig_category":"Maskinfabrikker",
    "sg:phone":"+45 75 55 39 13",
    "sg:postcode":"6040",
    "sg:province":"Danmark",
    "wof:name":"Verner's Maskinfabrik",
    "wof:placetype":"venue"
},
  "geometry": {"coordinates":[9.3087482452,55.6161613464],"type":"Point"}
}