{
  "type": "Feature",
  "properties": {
    "iso:country":"DK",
    "sg:address":"Lundevej 6",
    "sg:city":"Svendborg",
    "sg:orig_category":"Glarmestre og glarmagere",
    "sg:phone":"+45 62 21 16 31",
    "sg:postcode":"5700",
    "sg:province":"Danmark",
    "wof:name":"Stender, Glarmester Mogens",
    "wof:placetype":"venue"
},
  "geometry": {"coordinates":[10.6060199738,55.0584449768],"type":"Point"}
}