{
  "type": "Feature",
  "properties": {
    "addr:full":"Plast & Ide, Tibberup M\u00f8llevej 8 Esperg\u00e6rde Danmark 3060",
    "addr:housenumber":"8",
    "addr:postcode":"3060",
    "addr:street":"Mollevej",
    "iso:country":"DK",
    "sg:address":"Plast & Ide, Tibberup M\u00f8llevej 8",
    "sg:city":"Esperg\u00e6rde",
    "sg:orig_category":"Plastvarer",
    "sg:phone":"+45 49 13 31 44",
    "sg:postcode":"3060",
    "sg:province":"Danmark",
    "wof:name":"Brinck & Kj\u00e6r",
    "wof:placetype":"venue"
},
  "geometry": {"coordinates":[12.2715101242,55.9925613403],"type":"Point"}
}