{
  "type": "Feature",
  "properties": {
    "addr:full":"Midtballe 1, Skelde Broager Danmark 6310",
    "addr:housenumber":"1",
    "addr:postcode":"6310",
    "addr:street":"Midtballe;Skelde",
    "iso:country":"DK",
    "sg:address":"Midtballe 1, Skelde",
    "sg:city":"Broager",
    "sg:orig_category":"Diners transportables",
    "sg:phone":"+45 74 44 14 19",
    "sg:postcode":"6310",
    "sg:province":"Danmark",
    "wof:name":"Felipe's Buffet",
    "wof:placetype":"venue"
},
  "geometry": {"coordinates":[9.6673240662,54.8893623352],"type":"Point"}
}