{
  "type": "Feature",
  "properties": {
    "addr:full":"Njalsgade 55 K\u00f8benhavn S Danmark 2300",
    "addr:housenumber":"55",
    "addr:postcode":"2300",
    "addr:street":"Njalsgade;Kobenhavn S Danmark",
    "iso:country":"DK",
    "sg:address":"Njalsgade 55",
    "sg:city":"K\u00f8benhavn S",
    "sg:orig_category":"Vaskerier",
    "sg:phone":"+45 32 57 13 26",
    "sg:postcode":"2300",
    "sg:province":"Danmark",
    "wof:name":"Ny vask",
    "wof:placetype":"venue"
},
  "geometry": {"coordinates":[-98.6707077026,48.2092018127],"type":"Point"}
}