{
  "type": "Feature",
  "properties": {
    "addr:full":"Adelgade 22 Skive Danmark 7800",
    "addr:housenumber":"22",
    "addr:postcode":"7800",
    "addr:street":"Adelgade",
    "iso:country":"DK",
    "sg:address":"Adelgade 22",
    "sg:city":"Skive",
    "sg:orig_category":"Optikere",
    "sg:phone":"+45 97 52 47 61",
    "sg:postcode":"7800",
    "sg:province":"Danmark",
    "wof:name":"Synoptik",
    "wof:placetype":"venue"
},
  "geometry": {"coordinates":[9.0256528854,56.565776825],"type":"Point"}
}