{
  "type": "Feature",
  "properties": {
    "addr:full":"Oddesundvej 304 Hurup Danmark 7760",
    "addr:housenumber":"304",
    "addr:postcode":"7760",
    "addr:street":"Oddesundvej",
    "iso:country":"DK",
    "sg:address":"Oddesundvej 304",
    "sg:city":"Hurup",
    "sg:orig_category":"Forsikringer",
    "sg:phone":"+45 97 95 61 57",
    "sg:postcode":"7760",
    "sg:province":"Danmark",
    "wof:name":"Pedersen, Ole",
    "wof:placetype":"venue"
},
  "geometry": {"coordinates":[8.412569046,56.7081108093],"type":"Point"}
}