{
  "type": "Feature",
  "properties": {
    "addr:full":"N\u00f8rregade 20 Skive Danmark 7800",
    "addr:housenumber":"20",
    "addr:postcode":"7800",
    "addr:street":"Norregade",
    "iso:country":"DK",
    "sg:address":"N\u00f8rregade 20",
    "sg:city":"Skive",
    "sg:orig_category":"Sportsartikler",
    "sg:phone":"+45 97 52 27 27",
    "sg:postcode":"7800",
    "sg:province":"Danmark",
    "wof:name":"Sport Master",
    "wof:placetype":"venue"
},
  "geometry": {"coordinates":[9.0270557404,56.5679779053],"type":"Point"}
}