{
  "type": "Feature",
  "properties": {
    "iso:country":"DK",
    "sg:address":"Odinsvej 5, Postboks 224",
    "sg:city":"Ringsted",
    "sg:orig_category":"Web- og Internetdesign",
    "sg:phone":"+45 57 67 67 70",
    "sg:postcode":"4100",
    "sg:province":"Danmark",
    "sg:website":"www.domainet.dk",
    "wof:name":"Domainet ApS",
    "wof:placetype":"venue"
},
  "geometry": {"coordinates":[11.7875862122,55.4458961487],"type":"Point"}
}