{
  "type": "Feature",
  "properties": {
    "addr:full":"Grupper\u00e5dsfmd.: Eva Pedersen, Nyhusvej 9, Vollerslev Bj\u00e6verskov Danmark 4632",
    "addr:housenumber":"9",
    "addr:postcode":"4632",
    "addr:street":"Nyhusvej",
    "iso:country":"DK",
    "sg:address":"Grupper\u00e5dsfmd.: Eva Pedersen, Nyhusvej 9, Vollerslev",
    "sg:city":"Bj\u00e6verskov",
    "sg:orig_category":"Spejderkorps",
    "sg:phone":"+45 56 87 93 46",
    "sg:postcode":"4632",
    "sg:province":"Danmark",
    "wof:name":"S\u00f8lvb\u00e6k Gruppe KFUM-spejderne i G\u00f8rslev",
    "wof:placetype":"venue"
},
  "geometry": {"coordinates":[12.032699585,55.461265564],"type":"Point"}
}