{
  "type": "Feature",
  "properties": {
    "iso:country":"DK",
    "sg:address":"Kirkevej 4",
    "sg:city":"Gesten",
    "sg:orig_category":"Autoreparation og -service",
    "sg:phone":"+45 75 55 72 68",
    "sg:postcode":"6621",
    "sg:province":"Danmark",
    "wof:name":"B\u00f8rges Auto",
    "wof:placetype":"venue"
},
  "geometry": {"coordinates":[9.1913051605,55.5241508484],"type":"Point"}
}