{
  "type": "Feature",
  "properties": {
    "addr:full":"Nygade 7 Nyk\u00f8bing Danmark 7900",
    "addr:housenumber":"7",
    "addr:postcode":"7900",
    "addr:street":"Nygade",
    "iso:country":"DK",
    "sg:address":"Nygade 7",
    "sg:city":"Nyk\u00f8bing",
    "sg:classifiers":[
        {
            "category":"Restaurant",
            "type":"Food & Drink"
        }
    ],
    "sg:phone":"+45 97 71 00 80",
    "sg:postcode":"7900",
    "sg:province":"Danmark",
    "wof:name":"Blue Corner",
    "wof:placetype":"venue"
},
  "geometry": {"coordinates":[8.8630752563,56.7945251465],"type":"Point"}
}