{
  "type": "Feature",
  "properties": {
    "addr:full":"Strandvejen 1 Fakse Ladeplads Danmark 4654",
    "addr:housenumber":"1",
    "addr:postcode":"4654",
    "addr:street":"Strandvejen",
    "iso:country":"DK",
    "sg:address":"Strandvejen 1",
    "sg:city":"Fakse Ladeplads",
    "sg:orig_category":"Havne",
    "sg:phone":"+45 56 71 62 32",
    "sg:postcode":"4654",
    "sg:province":"Danmark",
    "wof:name":"Fakse Ladeplads Fiskeri- og Lystb\u00e5dehavn A.m.b.a.",
    "wof:placetype":"venue"
},
  "geometry": {"coordinates":[12.159113884,55.2139549255],"type":"Point"}
}