{
  "type": "Feature",
  "properties": {
    "addr:full":"Kastanievej 11 Br\u00f8nderslev Danmark 9700",
    "addr:housenumber":"11",
    "addr:postcode":"9700",
    "addr:street":"Kastanievej",
    "iso:country":"DK",
    "sg:address":"Kastanievej 11",
    "sg:city":"Br\u00f8nderslev",
    "sg:orig_category":"Menighedshuse",
    "sg:phone":"+45 98 81 12 69",
    "sg:postcode":"9700",
    "sg:province":"Danmark",
    "wof:name":"\u00d8. Br\u00f8nderslev Missionshus",
    "wof:placetype":"venue"
},
  "geometry": {"coordinates":[9.9978647232,57.2500228882],"type":"Point"}
}