{
  "type": "Feature",
  "properties": {
    "addr:full":"Dronning Margrethes Vej 75 Aabenraa Danmark 6200",
    "addr:housenumber":"75",
    "addr:postcode":"6200",
    "addr:street":"Dronning Margrethes Vej",
    "iso:country":"DK",
    "sg:address":"Dronning Margrethes Vej 75",
    "sg:city":"Aabenraa",
    "sg:orig_category":"Karrosserifabrikker",
    "sg:phone":"+45 73 32 32 32",
    "sg:postcode":"6200",
    "sg:province":"Danmark",
    "wof:name":"Aabenraa Karrosseri A/S",
    "wof:placetype":"venue"
},
  "geometry": {"coordinates":[9.4133501053,55.0408592224],"type":"Point"}
}