{
  "type": "Feature",
  "properties": {
    "iso:country":"DK",
    "sg:address":"Fmd.: Kurt Terkelsen, Venslev Huse 6",
    "sg:city":"Skibby",
    "sg:orig_category":"Soldaterforeninger",
    "sg:phone":"+45 47 52 99 46",
    "sg:postcode":"4050",
    "sg:province":"Danmark",
    "wof:name":"De Danske Forsvarsbr\u00f8dre",
    "wof:placetype":"venue"
},
  "geometry": {"coordinates":[11.9594116211,55.7502975464],"type":"Point"}
}