{
  "type": "Feature",
  "properties": {
    "addr:full":"Klintebjergvej 76, \u00d8strup Otterup Danmark 5450",
    "addr:housenumber":"76",
    "addr:postcode":"5450",
    "addr:street":"Klintebjergvej",
    "iso:country":"DK",
    "sg:address":"Klintebjergvej 76, \u00d8strup",
    "sg:city":"Otterup",
    "sg:orig_category":"Hospitalsudstyr",
    "sg:phone":"+45 64 82 36 22",
    "sg:postcode":"5450",
    "sg:province":"Danmark",
    "wof:name":"F-Lab",
    "wof:placetype":"venue"
},
  "geometry": {"coordinates":[10.4545049667,55.5641746521],"type":"Point"}
}