{
  "type": "Feature",
  "properties": {
    "addr:full":"Fmd.: Lars Franyo, Bag Fortet 8 Herlev Danmark 2730",
    "addr:housenumber":"8",
    "addr:postcode":"2730",
    "addr:street":"Fortet",
    "iso:country":"DK",
    "sg:address":"Fmd.: Lars Franyo, Bag Fortet 8",
    "sg:city":"Herlev",
    "sg:orig_category":"Politiske foreninger, \u00c3\u02dcvrige",
    "sg:phone":"+45 44 94 76 40",
    "sg:postcode":"2730",
    "sg:province":"Danmark",
    "sg:website":"www.fpu.dk",
    "wof:name":"Fremskridtspartiets Ungdom, FPU",
    "wof:placetype":"venue"
},
  "geometry": {"coordinates":[12.4382095337,55.7250595093],"type":"Point"}
}