{
  "type": "Feature",
  "properties": {
    "iso:country":"DK",
    "sg:address":"Gr\u00f8nlandsvej 69",
    "sg:city":"Nyk\u00f8bing",
    "sg:orig_category":"Hudpleje",
    "sg:phone":"+45 54 82 94 64",
    "sg:postcode":"4800",
    "sg:province":"Danmark",
    "wof:name":"Nyk\u00f8bing's Alternative Hudplejeklinik",
    "wof:placetype":"venue"
},
  "geometry": {"coordinates":[-114.0768203735,46.4432411194],"type":"Point"}
}