{
  "type": "Feature",
  "properties": {
    "addr:full":"Slettervej 27 Fej\u00f8 Danmark 4944",
    "addr:housenumber":"27",
    "addr:postcode":"4944",
    "addr:street":"Slettervej",
    "iso:country":"DK",
    "sg:address":"Slettervej 27",
    "sg:city":"Fej\u00f8",
    "sg:orig_category":"Frugtplantager",
    "sg:phone":"+45 54 71 34 66",
    "sg:postcode":"4944",
    "sg:province":"Danmark",
    "wof:name":"Fej\u00f8 Fors\u00f8gsplantage",
    "wof:placetype":"venue"
},
  "geometry": {"coordinates":[11.4447479248,54.9477806091],"type":"Point"}
}