{
  "type": "Feature",
  "properties": {
    "addr:full":"\u00d8stergade 51 Faaborg Danmark 5600",
    "addr:housenumber":"51",
    "addr:postcode":"5600",
    "addr:street":"Ostergade",
    "iso:country":"DK",
    "sg:address":"\u00d8stergade 51",
    "sg:city":"Faaborg",
    "sg:orig_category":"Motorkontorer",
    "sg:phone":"+45 62 61 14 48",
    "sg:postcode":"5600",
    "sg:province":"Danmark",
    "wof:name":"Motorkontoret i Faaborg",
    "wof:placetype":"venue"
},
  "geometry": {"coordinates":[10.2467136383,55.0940208435],"type":"Point"}
}