{
  "type": "Feature",
  "properties": {
    "addr:full":"Udbyh\u00f8jvej 50 Randers Danmark 8900",
    "addr:housenumber":"50",
    "addr:postcode":"8900",
    "addr:street":"Udbyhojvej",
    "iso:country":"DK",
    "sg:address":"Udbyh\u00f8jvej 50",
    "sg:city":"Randers",
    "sg:orig_category":"Autoreparation og -service",
    "sg:phone":"+45 86 42 68 01",
    "sg:postcode":"8900",
    "sg:province":"Danmark",
    "wof:name":"Randers Lavpris V\u00e6rksted",
    "wof:placetype":"venue"
},
  "geometry": {"coordinates":[10.0430164337,56.4628677368],"type":"Point"}
}