{
  "type": "Feature",
  "properties": {
    "addr:full":"H\u00f8jbro 19, K\u00f8ng Lundby Danmark 4750",
    "addr:housenumber":"19",
    "addr:postcode":"4750",
    "addr:street":"Hojbro;Kong",
    "iso:country":"DK",
    "sg:address":"H\u00f8jbro 19, K\u00f8ng",
    "sg:city":"Lundby",
    "sg:orig_category":"Handicapboliger",
    "sg:phone":"+45 55 76 97 30",
    "sg:postcode":"4750",
    "sg:province":"Danmark",
    "wof:name":"Bo- og Naboskabet Vordingborg Nord",
    "wof:placetype":"venue"
},
  "geometry": {"coordinates":[11.8101682663,55.1197814941],"type":"Point"}
}