{
  "type": "Feature",
  "properties": {
    "addr:full":"Holmbladsgade 25 K\u00f8benhavn S Danmark 2300",
    "addr:housenumber":"25",
    "addr:postcode":"2300",
    "addr:street":"Holmbladsgade;S Danmark",
    "iso:country":"DK",
    "sg:address":"Holmbladsgade 25",
    "sg:city":"K\u00f8benhavn S",
    "sg:orig_category":"Farvehandlere",
    "sg:phone":"+45 32 54 73 33",
    "sg:postcode":"2300",
    "sg:province":"Danmark",
    "wof:name":"Fl\u00fcgger Farver",
    "wof:placetype":"venue"
},
  "geometry": {"coordinates":[12.6146497726,55.6666908264],"type":"Point"}
}