{
  "type": "Feature",
  "properties": {
    "addr:full":"Fmd.: Grethe Mosg\u00e5rd, Tingskovvej 10 Brovst Danmark 9460",
    "addr:housenumber":"10",
    "addr:postcode":"9460",
    "addr:street":"Tingskovvej",
    "iso:country":"DK",
    "sg:address":"Fmd.: Grethe Mosg\u00e5rd, Tingskovvej 10",
    "sg:city":"Brovst",
    "sg:orig_category":"Kirkelige foreninger",
    "sg:phone":"+45 98 23 22 80",
    "sg:postcode":"9460",
    "sg:province":"Danmark",
    "wof:name":"Skovsg\u00e5rd KFUM og KFUK",
    "wof:placetype":"venue"
},
  "geometry": {"coordinates":[9.5220241547,57.097366333],"type":"Point"}
}