{
  "type": "Feature",
  "properties": {
    "addr:full":"Nordre Kystagervej 12 Hvidovre Danmark 2650",
    "addr:housenumber":"12",
    "addr:postcode":"2650",
    "addr:street":"Nordre Kystagervej",
    "iso:country":"DK",
    "sg:address":"Nordre Kystagervej 12",
    "sg:city":"Hvidovre",
    "sg:orig_category":"Reproanstalter",
    "sg:phone":"+45 36 78 60 15",
    "sg:postcode":"2650",
    "sg:province":"Danmark",
    "wof:name":"VK Repro A/S",
    "wof:placetype":"venue"
},
  "geometry": {"coordinates":[12.5016422272,55.6377677917],"type":"Point"}
}