{
  "type": "Feature",
  "properties": {
    "addr:full":"Centervej 4 Kolind Danmark 8560",
    "addr:housenumber":"4",
    "addr:postcode":"8560",
    "addr:street":"Centervej",
    "iso:country":"DK",
    "sg:address":"Centervej 4",
    "sg:city":"Kolind",
    "sg:orig_category":"Autoreparation og -service",
    "sg:phone":"+45 86 39 24 66",
    "sg:postcode":"8560",
    "sg:province":"Danmark",
    "wof:name":"HN Autocenter",
    "wof:placetype":"venue"
},
  "geometry": {"coordinates":[10.5712366104,56.3543930054],"type":"Point"}
}