{
  "type": "Feature",
  "properties": {
    "iso:country":"DK",
    "sg:address":"Sviegade 4 B, St. Darum",
    "sg:city":"Bramming",
    "sg:orig_category":"Kirker",
    "sg:postcode":"6740",
    "sg:province":"Danmark",
    "wof:name":"Darum Kirke",
    "wof:placetype":"venue"
},
  "geometry": {"coordinates":[8.6974096298,55.4655303955],"type":"Point"}
}