{
  "type": "Feature",
  "properties": {
    "addr:full":"Glostrup Butikstorv, Diget 52 Glostrup Danmark 2600",
    "addr:housenumber":"52",
    "addr:postcode":"2600",
    "addr:street":"Butikstorv Diget",
    "iso:country":"DK",
    "sg:address":"Glostrup Butikstorv, Diget 52",
    "sg:city":"Glostrup",
    "sg:orig_category":"Husholdningsapparater",
    "sg:phone":"+45 43 42 42 53",
    "sg:postcode":"2600",
    "sg:province":"Danmark",
    "wof:name":"Skousen Husholdningsmaskiner",
    "wof:placetype":"venue"
},
  "geometry": {"coordinates":[12.3957901001,55.6654663086],"type":"Point"}
}