{
  "type": "Feature",
  "properties": {
    "iso:country":"DK",
    "sg:address":"Fabriksvej 16, V. Lyby",
    "sg:city":"Skive",
    "sg:orig_category":"Jern- og Metalvareindustri",
    "sg:phone":"+45 70 26 71 88",
    "sg:postcode":"7800",
    "sg:province":"Danmark",
    "wof:name":"Grameta A/S",
    "wof:placetype":"venue"
},
  "geometry": {"coordinates":[9.0320358276,56.5666427612],"type":"Point"}
}