{
  "type": "Feature",
  "properties": {
    "addr:full":"S\u00f8ndergade 43 Horsens Danmark 8700",
    "addr:housenumber":"43",
    "addr:postcode":"8700",
    "addr:street":"Sondergade",
    "iso:country":"DK",
    "sg:address":"S\u00f8ndergade 43",
    "sg:city":"Horsens",
    "sg:orig_category":"Tandteknikere, Kliniske",
    "sg:phone":"+45 75 62 13 87",
    "sg:postcode":"8700",
    "sg:province":"Danmark",
    "wof:name":"Hansen, Ole Pleidrup",
    "wof:placetype":"venue"
},
  "geometry": {"coordinates":[9.8502006531,55.861946106],"type":"Point"}
}