{
  "type": "Feature",
  "properties": {
    "iso:country":"DK",
    "sg:address":"Dalvej 4, V. Nebel",
    "sg:city":"Egtved",
    "sg:orig_category":"Automater",
    "sg:phone":"+45 75 55 41 05",
    "sg:postcode":"6040",
    "sg:province":"Danmark",
    "wof:name":"Trekantens Automater ApS",
    "wof:placetype":"venue"
},
  "geometry": {"coordinates":[9.3087482452,55.6161613464],"type":"Point"}
}