{
  "type": "Feature",
  "properties": {
    "iso:country":"DK",
    "sg:address":"Sognepr\u00e6st: Egon Lausen (K/B), Kertevej 56, Kerte",
    "sg:city":"Aarup",
    "sg:orig_category":"Kirkesogne",
    "sg:phone":"+45 64 43 12 47",
    "sg:postcode":"5560",
    "sg:province":"Danmark",
    "wof:name":"Kerte sogn",
    "wof:placetype":"venue"
},
  "geometry": {"coordinates":[10.0490245819,55.3808059692],"type":"Point"}
}