{
  "type": "Feature",
  "properties": {
    "addr:full":"N\u00f8rregade 36 Odense C Danmark 5000",
    "addr:housenumber":"36",
    "addr:postcode":"5000",
    "addr:street":"Norregade",
    "iso:country":"DK",
    "sg:address":"N\u00f8rregade 36",
    "sg:city":"Odense C",
    "sg:orig_category":"Faglige organisationer og foreninger",
    "sg:phone":"+45 66 11 90 00",
    "sg:postcode":"5000",
    "sg:province":"Danmark",
    "wof:name":"Foreningen Af Statsamtsjurister",
    "wof:placetype":"venue"
},
  "geometry": {"coordinates":[10.3877258301,55.3987388611],"type":"Point"}
}