{
  "type": "Feature",
  "properties": {
    "iso:country":"DK",
    "sg:address":"Fmd.: Hans Pedersen, Bovangen 68",
    "sg:city":"Store Heddinge",
    "sg:orig_category":"Hobbybetonede foreninger",
    "sg:phone":"+45 56 50 39 27",
    "sg:postcode":"4660",
    "sg:province":"Danmark",
    "wof:name":"Stevns Frim\u00e6rkeklub",
    "wof:placetype":"venue"
},
  "geometry": {"coordinates":[12.3895797729,55.3113174438],"type":"Point"}
}