{
  "type": "Feature",
  "properties": {
    "iso:country":"DK",
    "sg:address":"Nordmarksvej 90",
    "sg:city":"Kastrup",
    "sg:orig_category":"\u00c3\u2020ldrecentre",
    "sg:phone":"+45 32 52 95 00",
    "sg:postcode":"2770",
    "sg:province":"Danmark",
    "wof:name":"Pensionistcentret Solg\u00e5rden",
    "wof:placetype":"venue"
},
  "geometry": {"coordinates":[12.6382694244,55.6381797791],"type":"Point"}
}