{
  "type": "Feature",
  "properties": {
    "iso:country":"DK",
    "sg:address":"Degnetoften 17, Led\u00f8je",
    "sg:city":"Sm\u00f8rum",
    "sg:classifiers":[
        {
            "category":"Building & Trades",
            "subcategory":"Electrical",
            "type":"Services"
        }
    ],
    "sg:phone":"+45 70 20 43 46",
    "sg:postcode":"2765",
    "sg:province":"Danmark",
    "sg:tags":[
        "distributor"
    ],
    "wof:name":"Svoriscan",
    "wof:placetype":"venue"
},
  "geometry": {"coordinates":[-89.99810791020001,38.1321372986],"type":"Point"}
}