{
  "type": "Feature",
  "properties": {
    "iso:country":"DK",
    "sg:address":"Postvej 33, Foldby",
    "sg:city":"Hinnerup",
    "sg:orig_category":"Brugsforeninger",
    "sg:phone":"+45 86 98 60 04",
    "sg:postcode":"8382",
    "sg:province":"Danmark",
    "sg:website":"www.fdb.dk",
    "wof:name":"Lokal Brugsen Foldby",
    "wof:placetype":"venue"
},
  "geometry": {"coordinates":[10.0614156723,56.2650604248],"type":"Point"}
}