{
  "type": "Feature",
  "properties": {
    "addr:full":"v/ Johanne J\u00f8rgensen, R\u00f8dhus, Holmeg\u00e5rdsvej 2 Hiller\u00f8d Danmark 3400",
    "addr:housenumber":"2",
    "addr:postcode":"3400",
    "addr:street":"Holmegaardsvej",
    "iso:country":"DK",
    "sg:address":"v/ Johanne J\u00f8rgensen, R\u00f8dhus, Holmeg\u00e5rdsvej 2",
    "sg:city":"Hiller\u00f8d",
    "sg:orig_category":"Politiske foreninger, \u00c3\u02dcvrige",
    "sg:phone":"+45 48 25 13 99",
    "sg:postcode":"3400",
    "sg:province":"Danmark",
    "wof:name":"Socialistisk Ungdomsfront - SUF-Hiller\u00f8d",
    "wof:placetype":"venue"
},
  "geometry": {"coordinates":[82.0155715942,24.8934593201],"type":"Point"}
}