{
  "type": "Feature",
  "properties": {
    "iso:country":"DK",
    "sg:address":"Platanbuen 10",
    "sg:city":"Ballerup",
    "sg:orig_category":"Ungdomsklubber",
    "sg:phone":"+45 44 77 32 32",
    "sg:postcode":"2750",
    "sg:province":"Danmark",
    "wof:name":"Fritids- og ungdomsklubben",
    "wof:placetype":"venue"
},
  "geometry": {"coordinates":[12.3458404541,55.72631073],"type":"Point"}
}