{
  "type": "Feature",
  "properties": {
    "iso:country":"DK",
    "sg:address":"Kongevejen 252, 3.",
    "sg:city":"Virum",
    "sg:orig_category":"\u00c3\u02dcvrige institutioner",
    "sg:phone":"+45 45 83 38 00",
    "sg:postcode":"2830",
    "sg:province":"Danmark",
    "sg:website":"www.vcddh.dk",
    "wof:name":"Videnscenter for D\u00f8vblevne, D\u00f8ve og H\u00f8reh\u00e6mmede",
    "wof:placetype":"venue"
},
  "geometry": {"coordinates":[12.4823188782,55.7981529236],"type":"Point"}
}