{
  "type": "Feature",
  "properties": {
    "iso:country":"DK",
    "sg:address":"S\u00f8ndergade 6",
    "sg:city":"Randers",
    "sg:orig_category":"Selskabslokaler",
    "sg:phone":"+45 86 41 19 70",
    "sg:postcode":"8900",
    "sg:province":"Danmark",
    "wof:name":"Tante Olga",
    "wof:placetype":"venue"
},
  "geometry": {"coordinates":[10.038832,56.457233],"type":"Point"}
}