{
  "type": "Feature",
  "properties": {
    "addr:full":"Hedebovej 15, Heden Ringe Danmark 5750",
    "addr:housenumber":"15",
    "addr:postcode":"5750",
    "addr:street":"Hedebovej",
    "iso:country":"DK",
    "sg:address":"Hedebovej 15, Heden",
    "sg:city":"Ringe",
    "sg:orig_category":"Motorcykler",
    "sg:phone":"+45 62 66 16 29",
    "sg:postcode":"5750",
    "sg:province":"Danmark",
    "wof:name":"Fyns Nimbus Center",
    "wof:placetype":"venue"
},
  "geometry": {"coordinates":[10.4781074524,55.2356643677],"type":"Point"}
}