{
  "type": "Feature",
  "properties": {
    "addr:full":"Fjordk\u00e6r 105, Vester J\u00f8lby Erslev Danmark 7950",
    "addr:housenumber":"105",
    "addr:postcode":"7950",
    "addr:street":"Vester Jolby",
    "iso:country":"DK",
    "sg:address":"Fjordk\u00e6r 105, Vester J\u00f8lby",
    "sg:city":"Erslev",
    "sg:orig_category":"Engros handel",
    "sg:phone":"+45 97 74 12 16",
    "sg:postcode":"7950",
    "sg:province":"Danmark",
    "wof:name":"L\u00f8vgreen",
    "wof:placetype":"venue"
},
  "geometry": {"coordinates":[8.7200698853,56.8354682922],"type":"Point"}
}