{
  "type": "Feature",
  "properties": {
    "iso:country":"DK",
    "sg:address":"Hegnedevejen 15, Pedersker",
    "sg:city":"Aakirkeby",
    "sg:orig_category":"Tekstiler",
    "sg:phone":"+45 56 97 82 95",
    "sg:postcode":"3720",
    "sg:province":"Danmark",
    "wof:name":"Dam, Karen",
    "wof:placetype":"venue"
},
  "geometry": {"coordinates":[14.9202880859,55.070110321],"type":"Point"}
}