{
  "type": "Feature",
  "properties": {
    "addr:full":"Herningvej 49 Aalborg \u00d8 Danmark 9220",
    "addr:housenumber":"49",
    "addr:postcode":"9220",
    "addr:street":"Herningvej;Danmark",
    "iso:country":"DK",
    "sg:address":"Herningvej 49",
    "sg:city":"Aalborg \u00d8",
    "sg:classifiers":[
        {
            "category":"Food & Beverages",
            "subcategory":"Liquor & Beverages",
            "type":"Retail Goods"
        }
    ],
    "sg:phone":"+45 98 15 78 72",
    "sg:postcode":"9220",
    "sg:province":"Danmark",
    "sg:tags":[
        "vin"
    ],
    "wof:name":"Nordjysk Vinhandel",
    "wof:placetype":"venue"
},
  "geometry": {"coordinates":[9.9850187302,57.0255088806],"type":"Point"}
}