{
  "type": "Feature",
  "properties": {
    "addr:full":"Frederikssundsvej 304 A Br\u00f8nsh\u00f8j Danmark 2700",
    "addr:housenumber":"304 a",
    "addr:postcode":"2700",
    "addr:street":"Frederikssundsvej",
    "iso:country":"DK",
    "sg:address":"Frederikssundsvej 304 A",
    "sg:city":"Br\u00f8nsh\u00f8j",
    "sg:orig_category":"Fritidsorganisationer og -foreninger",
    "sg:phone":"+45 38 28 87 50",
    "sg:postcode":"2700",
    "sg:province":"Danmark",
    "wof:name":"Kolonihaveforbundet For Danmark",
    "wof:placetype":"venue"
},
  "geometry": {"coordinates":[-65.6866531372,-23.1981296539],"type":"Point"}
}