{
  "type": "Feature",
  "properties": {
    "addr:full":"Vejlevej 12 Fredericia Danmark 7000",
    "addr:housenumber":"12",
    "addr:postcode":"7000",
    "addr:street":"Vejlevej",
    "iso:country":"DK",
    "sg:address":"Vejlevej 12",
    "sg:city":"Fredericia",
    "sg:orig_category":"Boligselskaber",
    "sg:phone":"+45 75 92 36 33",
    "sg:postcode":"7000",
    "sg:province":"Danmark",
    "sg:website":"www.bolab.dk",
    "wof:name":"Boligselskabet LAB",
    "wof:placetype":"venue"
},
  "geometry": {"coordinates":[9.7307548523,55.569568634],"type":"Point"}
}