{
  "type": "Feature",
  "properties": {
    "addr:full":"H\u00f8jvangen 10 Fredensborg Danmark 3480",
    "addr:housenumber":"10",
    "addr:postcode":"3480",
    "addr:street":"Hojvangen",
    "iso:country":"DK",
    "sg:address":"H\u00f8jvangen 10",
    "sg:city":"Fredensborg",
    "sg:orig_category":"Hobbyartikler",
    "sg:phone":"+45 48 48 14 44",
    "sg:postcode":"3480",
    "sg:province":"Danmark",
    "wof:name":"Panduro Hobby A/S",
    "wof:placetype":"venue"
},
  "geometry": {"coordinates":[12.4020547867,55.9782943726],"type":"Point"}
}