{
  "type": "Feature",
  "properties": {
    "addr:full":"R\u00e6vedalsvej 5, Ferslev Svenstrup Danmark 9230",
    "addr:housenumber":"5",
    "addr:postcode":"9230",
    "addr:street":"Raevedalsvej",
    "iso:country":"DK",
    "sg:address":"R\u00e6vedalsvej 5, Ferslev",
    "sg:city":"Svenstrup",
    "sg:orig_category":"Skolefritidsordninger",
    "sg:phone":"+45 96 37 62 23",
    "sg:postcode":"9230",
    "sg:province":"Danmark",
    "wof:name":"DUS Spor A-B - Ferslev Skole",
    "wof:placetype":"venue"
},
  "geometry": {"coordinates":[9.8525295258,56.9723396301],"type":"Point"}
}