{
  "type": "Feature",
  "properties": {
    "addr:full":"Vellingvej 8, Smidstrup Fredericia Danmark 7000",
    "addr:housenumber":"8",
    "addr:postcode":"7000",
    "addr:street":"Vellingvej;Smidstrup",
    "iso:country":"DK",
    "sg:address":"Vellingvej 8, Smidstrup",
    "sg:city":"Fredericia",
    "sg:orig_category":"Dyreklinikker og -hospitaler",
    "sg:phone":"+45 75 86 00 45",
    "sg:postcode":"7000",
    "sg:province":"Danmark",
    "wof:name":"Dyrl\u00e6gehuset i Smidstrup I/S",
    "wof:placetype":"venue"
},
  "geometry": {"coordinates":[9.7591047287,55.566368103],"type":"Point"}
}