{
  "type": "Feature",
  "properties": {
    "addr:full":"Industrivej 1 Give Danmark 7323",
    "addr:housenumber":"1",
    "addr:postcode":"7323",
    "addr:street":"Industrivej",
    "iso:country":"DK",
    "sg:address":"Industrivej 1",
    "sg:city":"Give",
    "sg:orig_category":"Autoreparation og -service",
    "sg:phone":"+45 75 73 18 88",
    "sg:postcode":"7323",
    "sg:province":"Danmark",
    "wof:name":"Bach og S\u00f8n, N.",
    "wof:placetype":"venue"
},
  "geometry": {"coordinates":[9.2276363373,55.8446960449],"type":"Point"}
}