{
  "type": "Feature",
  "properties": {
    "addr:full":"Fmd.: Steen Noes, Yderbygade 5, Yderby Sj\u00e6llands Odde Danmark 4583",
    "addr:housenumber":"5",
    "addr:postcode":"4583",
    "addr:street":"Yderbygade;Sjaellands Odde Danmark",
    "iso:country":"DK",
    "sg:address":"Fmd.: Steen Noes, Yderbygade 5, Yderby",
    "sg:city":"Sj\u00e6llands Odde",
    "sg:orig_category":"Grundejerforeninger",
    "sg:phone":"+45 59 32 70 58",
    "sg:postcode":"4583",
    "sg:province":"Danmark",
    "wof:name":"Strandlodsejerforeningen i Danmark",
    "wof:placetype":"venue"
},
  "geometry": {"coordinates":[11.3198680878,55.9799728394],"type":"Point"}
}