{
  "type": "Feature",
  "properties": {
    "addr:full":"Vestergade 11 A Faaborg Danmark 5600",
    "addr:housenumber":"11 a",
    "addr:postcode":"5600",
    "addr:street":"Vestergade",
    "iso:country":"DK",
    "sg:address":"Vestergade 11 A",
    "sg:city":"Faaborg",
    "sg:orig_category":"Gallerier",
    "sg:phone":"+45 62 61 18 68",
    "sg:postcode":"5600",
    "sg:province":"Danmark",
    "wof:name":"Klein Atelier",
    "wof:placetype":"venue"
},
  "geometry": {"coordinates":[10.2395048141,55.0966796875],"type":"Point"}
}