{
  "type": "Feature",
  "properties": {
    "iso:country":"DK",
    "sg:address":"Virkevej 5",
    "sg:city":"Bedsted",
    "sg:orig_category":"Oliefyr og service",
    "sg:phone":"+45 97 94 40 20",
    "sg:postcode":"7755",
    "sg:province":"Danmark",
    "wof:name":"Thy Varmeteknik A/S",
    "wof:placetype":"venue"
},
  "geometry": {"coordinates":[8.412946701,56.8085289001],"type":"Point"}
}