{
  "type": "Feature",
  "properties": {
    "addr:full":"Gammel Lundtoftevej 36 Kongens Lyngby Danmark 2800",
    "addr:housenumber":"36",
    "addr:postcode":"2800",
    "addr:street":"Gammel Lundtoftevej",
    "iso:country":"DK",
    "sg:address":"Gammel Lundtoftevej 36",
    "sg:city":"Kongens Lyngby",
    "sg:orig_category":"Arkitekter",
    "sg:phone":"+45 45 87 42 16",
    "sg:postcode":"2800",
    "sg:province":"Danmark",
    "wof:name":"Thomasen Arkitekt MAA, Kim",
    "wof:placetype":"venue"
},
  "geometry": {"coordinates":[12.5056371689,55.777053833],"type":"Point"}
}