{
  "type": "Feature",
  "properties": {
    "addr:full":"T\u00e5rsvej Saksk\u00f8bing Danmark 4990",
    "addr:postcode":"4990",
    "addr:street":"Taarsvej;Danmark",
    "iso:country":"DK",
    "sg:address":"T\u00e5rsvej",
    "sg:city":"Saksk\u00f8bing",
    "sg:orig_category":"Kirker",
    "sg:postcode":"4990",
    "sg:province":"Danmark",
    "wof:name":"T\u00e5rs Kirke",
    "wof:placetype":"venue"
},
  "geometry": {"coordinates":[-114.0767440796,46.4432487488],"type":"Point"}
}