{
  "type": "Feature",
  "properties": {
    "addr:full":"Chr. Hansens Vej 2 Hanstholm Danmark 7730",
    "addr:housenumber":"2",
    "addr:postcode":"7730",
    "addr:street":"Chr. Hansens Vej",
    "iso:country":"DK",
    "sg:address":"Chr. Hansens Vej 2",
    "sg:city":"Hanstholm",
    "sg:classifiers":[
        {
            "category":"Restaurant",
            "type":"Food & Drink"
        }
    ],
    "sg:phone":"+45 97 96 10 44",
    "sg:postcode":"7730",
    "sg:province":"Danmark",
    "sg:website":"www.hotel-hanstholm.dk",
    "wof:name":"Hanstholm, Hotel",
    "wof:placetype":"venue"
},
  "geometry": {"coordinates":[8.6056680679,57.1161193848],"type":"Point"}
}