{
  "type": "Feature",
  "properties": {
    "addr:full":"Stalmosevej 2, Simmelk\u00e6r Sunds Danmark 7451",
    "addr:housenumber":"2",
    "addr:postcode":"7451",
    "addr:street":"Stalmosevej",
    "iso:country":"DK",
    "sg:address":"Stalmosevej 2, Simmelk\u00e6r",
    "sg:city":"Sunds",
    "sg:orig_category":"Kolonial en gros",
    "sg:phone":"+45 97 14 33 51",
    "sg:postcode":"7451",
    "sg:province":"Danmark",
    "wof:name":"Nile-Dan",
    "wof:placetype":"venue"
},
  "geometry": {"coordinates":[9.0151100159,56.2057800293],"type":"Point"}
}