{
  "type": "Feature",
  "properties": {
    "iso:country":"DK",
    "sg:address":"Himmerlandsgade 73",
    "sg:city":"Aars",
    "sg:classifiers":[
        {
            "category":"Banks & Credit Unions",
            "subcategory":"Bank",
            "type":"Services"
        }
    ],
    "sg:phone":"+45 96 98 08 20",
    "sg:postcode":"9600",
    "sg:province":"Danmark",
    "sg:tags":[
        "banker"
    ],
    "sg:website":"www.danskebank.dk",
    "wof:name":"Danske Bank",
    "wof:placetype":"venue"
},
  "geometry": {"coordinates":[9.517589,56.80312],"type":"Point"}
}