{
  "type": "Feature",
  "properties": {
    "addr:full":"Nitrisk\u00e6rvej 12 Agerskov Danmark 6534",
    "addr:housenumber":"12",
    "addr:postcode":"6534",
    "addr:street":"Nitriskaervej",
    "iso:country":"DK",
    "sg:address":"Nitrisk\u00e6rvej 12",
    "sg:city":"Agerskov",
    "sg:orig_category":"Zoneterapeuter",
    "sg:phone":"+45 74 83 35 67",
    "sg:postcode":"6534",
    "sg:province":"Danmark",
    "wof:name":"Schmidt Zone- & el-Terapi, Boythin",
    "wof:placetype":"venue"
},
  "geometry": {"coordinates":[9.1360368729,55.1430511475],"type":"Point"}
}