{
  "type": "Feature",
  "properties": {
    "iso:country":"DK",
    "sg:address":"S\u00e6tersdalgade 15",
    "sg:city":"K\u00f8benhavn S",
    "sg:orig_category":"Integrerede institutioner",
    "sg:phone":"+45 32 84 23 23",
    "sg:postcode":"2300",
    "sg:province":"Danmark",
    "wof:name":"Pr\u00e6stev\u00e6ngets Fritidscenter",
    "wof:placetype":"venue"
},
  "geometry": {"coordinates":[-82.5692062378,38.4656143188],"type":"Point"}
}