{
  "type": "Feature",
  "properties": {
    "addr:full":"Bytorvet 18 Hedensted Danmark 8722",
    "addr:housenumber":"18",
    "addr:postcode":"8722",
    "addr:street":"Bytorvet",
    "iso:country":"DK",
    "sg:address":"Bytorvet 18",
    "sg:city":"Hedensted",
    "sg:orig_category":"Forsamlingshuse",
    "sg:phone":"+45 75 89 11 58",
    "sg:postcode":"8722",
    "sg:province":"Danmark",
    "wof:name":"Hedensted Sogneg\u00e5rd",
    "wof:placetype":"venue"
},
  "geometry": {"coordinates":[9.6999597549,55.7685699463],"type":"Point"}
}