{
  "type": "Feature",
  "properties": {
    "iso:country":"DK",
    "sg:address":"Gammel Egebjergvej 18 ",
    "sg:city":"Horsens",
    "sg:classifiers":[
        {
            "category":"Sports & Exercise",
            "subcategory":"Playing Field",
            "type":"Entertainment"
        }
    ],
    "sg:phone":"+45 75 65 66 11",
    "sg:postcode":"8700",
    "sg:province":"Danmark",
    "sg:tags":[
        "game"
    ],
    "wof:name":"MAX HORSENS A/S",
    "wof:placetype":"venue"
},
  "geometry": {"coordinates":[9.8379449844,55.9085960388],"type":"Point"}
}