{
  "type": "Feature",
  "properties": {
    "iso:country":"DK",
    "sg:address":"Dronningemaen 34",
    "sg:city":"Svendborg",
    "sg:orig_category":"Benzinstationer",
    "sg:phone":"+45 62 22 82 43",
    "sg:postcode":"5700",
    "sg:province":"Danmark",
    "wof:name":"Dronningemaens Servicecenter ApS",
    "wof:placetype":"venue"
},
  "geometry": {"coordinates":[10.606366,55.063553],"type":"Point"}
}