{
  "type": "Feature",
  "properties": {
    "iso:country":"DK",
    "sg:address":"Nytorv 8",
    "sg:city":"Sk\u00e6lsk\u00f8r",
    "sg:orig_category":"Bagere",
    "sg:phone":"+45 58 19 43 78",
    "sg:postcode":"4230",
    "sg:province":"Danmark",
    "wof:name":"Nytorvs Konditori",
    "wof:placetype":"venue"
},
  "geometry": {"coordinates":[11.191504,55.211975],"type":"Point"}
}