{
  "type": "Feature",
  "properties": {
    "addr:full":"Sognepr\u00e6st: Hanne Marie Houkj\u00e6r (K/B), Knebel Bygade 2 Knebel Danmark 8420",
    "addr:housenumber":"b;2",
    "addr:postcode":"8420",
    "addr:street":"Knebel Bygade",
    "iso:country":"DK",
    "sg:address":"Sognepr\u00e6st: Hanne Marie Houkj\u00e6r (K/B), Knebel Bygade 2",
    "sg:city":"Knebel",
    "sg:orig_category":"Kirkesogne",
    "sg:phone":"+45 86 35 10 58",
    "sg:postcode":"8420",
    "sg:province":"Danmark",
    "wof:name":"Knebel og Rols\u00f8 Sogne",
    "wof:placetype":"venue"
},
  "geometry": {"coordinates":[10.3770122528,56.1816596985],"type":"Point"}
}