{
  "type": "Feature",
  "properties": {
    "addr:full":"Allingvej 20 Lemming Danmark 8632",
    "addr:housenumber":"20",
    "addr:postcode":"8632",
    "addr:street":"Allingvej",
    "iso:country":"DK",
    "sg:address":"Allingvej 20",
    "sg:city":"Lemming",
    "sg:orig_category":"Skovbrug",
    "sg:phone":"+45 86 85 99 09",
    "sg:postcode":"8632",
    "sg:province":"Danmark",
    "wof:name":"Rasmussen, Ren\u00e9 Hankinh",
    "wof:placetype":"venue"
},
  "geometry": {"coordinates":[9.5795030594,56.2492141724],"type":"Point"}
}