{
  "type": "Feature",
  "properties": {
    "addr:full":"Fmd.: Brita Uldum, Rosenalle 23 Videb\u00e6k Danmark 6920",
    "addr:housenumber":"23",
    "addr:postcode":"6920",
    "addr:street":"Rosenalle",
    "iso:country":"DK",
    "sg:address":"Fmd.: Brita Uldum, Rosenalle 23",
    "sg:city":"Videb\u00e6k",
    "sg:orig_category":"Kolonihaveforeninger",
    "sg:phone":"+45 97 17 20 19",
    "sg:postcode":"6920",
    "sg:province":"Danmark",
    "wof:name":"Videb\u00e6k og Omegns Havekreds",
    "wof:placetype":"venue"
},
  "geometry": {"coordinates":[8.7436800003,55.9904136658],"type":"Point"}
}