{
  "type": "Feature",
  "properties": {
    "iso:country":"DK",
    "sg:address":"Fmd.: Lisbeth Fredslund, \u00c6r\u00f8vej 16, Starup",
    "sg:city":"Haderslev",
    "sg:orig_category":"Hobbybetonede foreninger",
    "sg:phone":"+45 74 53 01 04",
    "sg:postcode":"6100",
    "sg:province":"Danmark",
    "sg:website":"www.haveselskab.dk",
    "wof:name":"Det Jydske Haveselskab, Haderslev Kreds",
    "wof:placetype":"venue"
},
  "geometry": {"coordinates":[9.4879703522,55.2505493164],"type":"Point"}
}