{
  "type": "Feature",
  "properties": {
    "addr:full":"Hornevej 13 Kastrup Danmark 2770",
    "addr:housenumber":"13",
    "addr:postcode":"2770",
    "addr:street":"Hornevej",
    "iso:country":"DK",
    "sg:address":"Hornevej 13",
    "sg:city":"Kastrup",
    "sg:orig_category":"Naturgas install. og -service",
    "sg:phone":"+45 32 51 45 59",
    "sg:postcode":"2770",
    "sg:province":"Danmark",
    "wof:name":"Finlow VVS A/S",
    "wof:placetype":"venue"
},
  "geometry": {"coordinates":[12.5972166061,55.6249694824],"type":"Point"}
}