{
  "type": "Feature",
  "properties": {
    "iso:country":"DK",
    "sg:address":"Vassinger\u00f8dvej 15, Postboks 30",
    "sg:city":"Lynge",
    "sg:orig_category":"El-en gros",
    "sg:phone":"+45 48 16 36 00",
    "sg:postcode":"3540",
    "sg:province":"Danmark",
    "wof:name":"Nordisk Solar Compagni A/S",
    "wof:placetype":"venue"
},
  "geometry": {"coordinates":[12.2734966278,55.834186554],"type":"Point"}
}