{
  "type": "Feature",
  "properties": {
    "iso:country":"DK",
    "sg:address":"Kokbjerg 14 ",
    "sg:city":"Kolding",
    "sg:classifiers":[
        {
            "category":"Shopping",
            "subcategory":"Clothing, Apparel, & Fashions",
            "type":"Retail Goods"
        }
    ],
    "sg:phone":"+45 76 35 35 35",
    "sg:postcode":"6000",
    "sg:province":"Danmark",
    "sg:tags":[
        "clothes"
    ],
    "wof:name":"B-YOUNG A/S",
    "wof:placetype":"venue"
},
  "geometry": {"coordinates":[9.4743728638,55.5346832275],"type":"Point"}
}