{
  "type": "Feature",
  "properties": {
    "addr:full":"H\u00f8rg\u00e5rdsvej 17 Risskov Danmark 8240",
    "addr:housenumber":"17",
    "addr:postcode":"8240",
    "addr:street":"Horgaardsvej",
    "iso:country":"DK",
    "sg:address":"H\u00f8rg\u00e5rdsvej 17",
    "sg:city":"Risskov",
    "sg:orig_category":"Lokalcentre",
    "sg:phone":"+45 86 17 71 55",
    "sg:postcode":"8240",
    "sg:province":"Danmark",
    "wof:name":"Lokalcenter H\u00f8rg\u00e5rden",
    "wof:placetype":"venue"
},
  "geometry": {"coordinates":[10.2244901657,56.1874389648],"type":"Point"}
}