{
  "type": "Feature",
  "properties": {
    "iso:country":"DK",
    "sg:address":"Rybergsvej 40, S\u00f8nderby",
    "sg:city":"Ebberup",
    "sg:orig_category":"Glarmestre og glarmagere",
    "sg:phone":"+45 64 74 12 66",
    "sg:postcode":"5631",
    "sg:province":"Danmark",
    "wof:name":"Madsen, Per",
    "wof:placetype":"venue"
},
  "geometry": {"coordinates":[9.9818639755,55.2415733337],"type":"Point"}
}