{
  "type": "Feature",
  "properties": {
    "addr:full":"Lejrvej 43, Kr. V\u00e6rl\u00f8se V\u00e6rl\u00f8se Danmark 3500",
    "addr:housenumber":"43 kr.",
    "addr:postcode":"3500",
    "addr:street":"Lejrvej",
    "iso:country":"DK",
    "sg:address":"Lejrvej 43, Kr. V\u00e6rl\u00f8se",
    "sg:city":"V\u00e6rl\u00f8se",
    "sg:orig_category":"Betonvarefabrikker",
    "sg:phone":"+45 44 48 08 96",
    "sg:postcode":"3500",
    "sg:province":"Danmark",
    "wof:name":"EK Beton & Flisefabrik A/S",
    "wof:placetype":"venue"
},
  "geometry": {"coordinates":[127.8501663208,36.4481506348],"type":"Point"}
}