{
  "type": "Feature",
  "properties": {
    "addr:full":"Skjoldh\u00f8jvej 38, Lading Sabro Danmark 8471",
    "addr:housenumber":"38",
    "addr:postcode":"8471",
    "addr:street":"Skjoldhojvej",
    "iso:country":"DK",
    "sg:address":"Skjoldh\u00f8jvej 38, Lading",
    "sg:city":"Sabro",
    "sg:orig_category":"Korn og foderstoffer",
    "sg:phone":"+45 86 94 92 77",
    "sg:postcode":"8471",
    "sg:province":"Danmark",
    "sg:website":"www.lhfoder.dk",
    "wof:name":"L-H Foder ApS",
    "wof:placetype":"venue"
},
  "geometry": {"coordinates":[10.0375204086,56.2109718323],"type":"Point"}
}