{
  "type": "Feature",
  "properties": {
    "addr:full":"Hannerupvej 267, Hvilsom Hobro Danmark 9500",
    "addr:housenumber":"267",
    "addr:postcode":"9500",
    "addr:street":"Hannerupvej;Hvilsom",
    "iso:country":"DK",
    "sg:address":"Hannerupvej 267, Hvilsom",
    "sg:city":"Hobro",
    "sg:classifiers":[
        {
            "category":"Banks & Credit Unions",
            "subcategory":"Bank",
            "type":"Services"
        }
    ],
    "sg:phone":"+45 98 54 84 44",
    "sg:postcode":"9500",
    "sg:province":"Danmark",
    "sg:tags":[
        "banker"
    ],
    "wof:name":"Hvilsom Andelskasse",
    "wof:placetype":"venue"
},
  "geometry": {"coordinates":[9.79466,56.638279],"type":"Point"}
}