{
  "type": "Feature",
  "properties": {
    "addr:full":"City Centret 7 - 9 St\u00f8vring Danmark 9530",
    "addr:housenumber":"7 9",
    "addr:postcode":"9530",
    "addr:street":"City Centret",
    "iso:country":"DK",
    "sg:address":"City Centret 7 - 9",
    "sg:city":"St\u00f8vring",
    "sg:classifiers":[
        {
            "category":"Banks & Credit Unions",
            "subcategory":"Bank",
            "type":"Services"
        }
    ],
    "sg:phone":"+45 96 86 82 00",
    "sg:postcode":"9530",
    "sg:province":"Danmark",
    "sg:tags":[
        "banker"
    ],
    "sg:website":"www.danskebank.dk",
    "wof:name":"Danske Bank",
    "wof:placetype":"venue"
},
  "geometry": {"coordinates":[-103.38104199999999,34.361462],"type":"Point"}
}