{
  "type": "Feature",
  "properties": {
    "iso:country":"DK",
    "sg:address":"H\u00e5ndv\u00e6rkervej 1, Givskud",
    "sg:city":"Give",
    "sg:orig_category":"Undervognsbehandling",
    "sg:phone":"+45 75 73 02 55",
    "sg:postcode":"7323",
    "sg:province":"Danmark",
    "wof:name":"Bilbeskytteren",
    "wof:placetype":"venue"
},
  "geometry": {"coordinates":[9.2362060547,55.845413208],"type":"Point"}
}