{
  "type": "Feature",
  "properties": {
    "iso:country":"DK",
    "sg:address":"Tr\u00f8nningevej 1 B-C, Kundby",
    "sg:city":"Svinninge",
    "sg:orig_category":"Integrerede institutioner",
    "sg:postcode":"4520",
    "sg:province":"Danmark",
    "wof:name":"Kundby B\u00f8rnehus",
    "wof:placetype":"venue"
},
  "geometry": {"coordinates":[11.4649095535,55.7226104736],"type":"Point"}
}