{
  "type": "Feature",
  "properties": {
    "addr:full":"Store Kongensgade 77 K\u00f8benhavn Danmark 1264",
    "addr:housenumber":"77;1264",
    "addr:street":"Store Kongensgade",
    "iso:country":"DK",
    "sg:address":"Store Kongensgade 77",
    "sg:city":"K\u00f8benhavn",
    "sg:orig_category":"Pizzeriaer",
    "sg:phone":"+45 33 11 42 74",
    "sg:postcode":"1264",
    "sg:province":"Danmark",
    "wof:name":"La Grillade",
    "wof:placetype":"venue"
},
  "geometry": {"coordinates":[12.5923995972,55.6865005493],"type":"Point"}
}