{
  "type": "Feature",
  "properties": {
    "addr:full":"Eriksmindevej 13, Over Randlev Odder Danmark 8300",
    "addr:housenumber":"13",
    "addr:postcode":"8300",
    "addr:street":"Eriksmindevej;Randlev",
    "iso:country":"DK",
    "sg:address":"Eriksmindevej 13, Over Randlev",
    "sg:city":"Odder",
    "sg:orig_category":"Kommunale folkeskoler",
    "sg:phone":"+45 87 80 38 65",
    "sg:postcode":"8300",
    "sg:province":"Danmark",
    "wof:name":"Randlev-Bjerager Centralskole",
    "wof:placetype":"venue"
},
  "geometry": {"coordinates":[10.1497612,55.9733161926],"type":"Point"}
}