{
  "type": "Feature",
  "properties": {
    "addr:full":"Skalkendrupvej 10, Skalkendrup Nyborg Danmark 5800",
    "addr:housenumber":"10",
    "addr:postcode":"5800",
    "addr:street":"Skalkendrupvej;Skalkendrup",
    "iso:country":"DK",
    "sg:address":"Skalkendrupvej 10, Skalkendrup",
    "sg:city":"Nyborg",
    "sg:orig_category":"Faglige organisationer og foreninger",
    "sg:phone":"+45 63 36 14 10",
    "sg:postcode":"5800",
    "sg:province":"Danmark",
    "wof:name":"Dansk Vagt-Forbund, Region Fyn",
    "wof:placetype":"venue"
},
  "geometry": {"coordinates":[10.7923851013,55.3111801147],"type":"Point"}
}