{
  "type": "Feature",
  "properties": {
    "addr:full":"Volmersgade 27 Vordingborg Danmark 4760",
    "addr:housenumber":"27",
    "addr:postcode":"4760",
    "addr:street":"Volmersgade",
    "iso:country":"DK",
    "sg:address":"Volmersgade 27",
    "sg:city":"Vordingborg",
    "sg:orig_category":"Pizzeriaer",
    "sg:phone":"+45 55 34 40 16",
    "sg:postcode":"4760",
    "sg:province":"Danmark",
    "wof:name":"Costa Del Sol, Pizzaria",
    "wof:placetype":"venue"
},
  "geometry": {"coordinates":[11.8951482773,54.9996414185],"type":"Point"}
}