{
  "type": "Feature",
  "properties": {
    "iso:country":"DK",
    "sg:address":"Fmd.: Tage Thomas Buch, Umanakvej 88",
    "sg:city":"Esbjerg N",
    "sg:orig_category":"Soldaterforeninger",
    "sg:phone":"+45 75 15 53 13",
    "sg:postcode":"6715",
    "sg:province":"Danmark",
    "wof:name":"FN-Soldaterforeningen De Bl\u00e5 Baretter",
    "wof:placetype":"venue"
},
  "geometry": {"coordinates":[8.4780550003,55.535610199],"type":"Point"}
}