{
  "type": "Feature",
  "properties": {
    "addr:full":"Fyensgade 25 Aalborg Danmark 9000",
    "addr:housenumber":"25",
    "addr:postcode":"9000",
    "addr:street":"Fyensgade",
    "iso:country":"DK",
    "sg:address":"Fyensgade 25",
    "sg:city":"Aalborg",
    "sg:orig_category":"Fodterapeuter",
    "sg:phone":"+45 98 11 51 44",
    "sg:postcode":"9000",
    "sg:province":"Danmark",
    "wof:name":"Petersen, Karen",
    "wof:placetype":"venue"
},
  "geometry": {"coordinates":[9.9353628159,57.0427360535],"type":"Point"}
}