{
  "type": "Feature",
  "properties": {
    "addr:full":"Hovedgaden 58 D Borup Danmark 4140",
    "addr:housenumber":"58 d",
    "addr:postcode":"4140",
    "addr:street":"Hovedgaden",
    "iso:country":"DK",
    "sg:address":"Hovedgaden 58 D",
    "sg:city":"Borup",
    "sg:orig_category":"Grillbarer",
    "sg:phone":"+45 57 52 33 32",
    "sg:postcode":"4140",
    "sg:province":"Danmark",
    "wof:name":"Centergrill & Kebab House",
    "wof:placetype":"venue"
},
  "geometry": {"coordinates":[11.9761857986,55.4980545044],"type":"Point"}
}