{
  "type": "Feature",
  "properties": {
    "addr:full":"Jernbanegade 16 Langeskov Danmark 5550",
    "addr:housenumber":"16",
    "addr:postcode":"5550",
    "addr:street":"Jernbanegade",
    "iso:country":"DK",
    "sg:address":"Jernbanegade 16",
    "sg:city":"Langeskov",
    "sg:orig_category":"Sko",
    "sg:phone":"+45 65 38 11 65",
    "sg:postcode":"5550",
    "sg:province":"Danmark",
    "wof:name":"Alex Sko",
    "wof:placetype":"venue"
},
  "geometry": {"coordinates":[10.5915460587,55.3598861694],"type":"Point"}
}