{
  "type": "Feature",
  "properties": {
    "addr:full":"L\u00e6s\u00f8vej 8 Viborg Danmark 8800",
    "addr:housenumber":"8",
    "addr:postcode":"8800",
    "addr:street":"Laesovej",
    "iso:country":"DK",
    "sg:address":"L\u00e6s\u00f8vej 8",
    "sg:city":"Viborg",
    "sg:orig_category":"Maskinfabrikker",
    "sg:phone":"+45 86 61 16 44",
    "sg:postcode":"8800",
    "sg:province":"Danmark",
    "wof:name":"Skelh\u00f8je Maskinfabrik",
    "wof:placetype":"venue"
},
  "geometry": {"coordinates":[9.4071502686,56.452671051],"type":"Point"}
}