{
  "type": "Feature",
  "properties": {
    "addr:full":"Mindegade 8 \u00c5rhus C Danmark 8000",
    "addr:housenumber":"8",
    "addr:postcode":"8000",
    "addr:street":"Mindegade",
    "iso:country":"DK",
    "sg:address":"Mindegade 8",
    "sg:city":"\u00c5rhus C",
    "sg:orig_category":"Vuggestuer",
    "sg:phone":"+45 86 12 09 85",
    "sg:postcode":"8000",
    "sg:province":"Danmark",
    "wof:name":"Mindegade, Vuggestue",
    "wof:placetype":"venue"
},
  "geometry": {"coordinates":[4.717400074,49.7588005066],"type":"Point"}
}