{
  "type": "Feature",
  "properties": {
    "addr:full":"Formervangen 44 Glostrup Danmark 2600",
    "addr:housenumber":"44",
    "addr:postcode":"2600",
    "addr:street":"Formervangen",
    "iso:country":"DK",
    "sg:address":"Formervangen 44",
    "sg:city":"Glostrup",
    "sg:orig_category":"Rustbeskyttelse",
    "sg:phone":"+45 43 45 71 01",
    "sg:postcode":"2600",
    "sg:province":"Danmark",
    "wof:name":"Dansk Rustbeskyttelse ApS",
    "wof:placetype":"venue"
},
  "geometry": {"coordinates":[12.3715763092,55.6827087402],"type":"Point"}
}