{
  "type": "Feature",
  "properties": {
    "addr:full":"Vestergade 23 Nyk\u00f8bing Danmark 7900",
    "addr:housenumber":"23",
    "addr:postcode":"7900",
    "addr:street":"Vestergade",
    "iso:country":"DK",
    "sg:address":"Vestergade 23",
    "sg:city":"Nyk\u00f8bing",
    "sg:orig_category":"Servicestationer",
    "sg:phone":"+45 97 72 09 80",
    "sg:postcode":"7900",
    "sg:province":"Danmark",
    "wof:name":"Shell Service",
    "wof:placetype":"venue"
},
  "geometry": {"coordinates":[9.5455904007,56.1682090759],"type":"Point"}
}