{
  "type": "Feature",
  "properties": {
    "addr:full":"Fyrrestien 18, Birgittelyst Viborg Danmark 8800",
    "addr:housenumber":"18",
    "addr:postcode":"8800",
    "addr:street":"Fyrrestien",
    "iso:country":"DK",
    "sg:address":"Fyrrestien 18, Birgittelyst",
    "sg:city":"Viborg",
    "sg:orig_category":"Murermestre",
    "sg:phone":"+45 86 63 83 14",
    "sg:postcode":"8800",
    "sg:province":"Danmark",
    "wof:name":"Pedersen, Poul Nautrup",
    "wof:placetype":"venue"
},
  "geometry": {"coordinates":[9.4071502686,56.452671051],"type":"Point"}
}