{
  "type": "Feature",
  "properties": {
    "addr:full":"Sm\u00e5lodsvej 41 A  Ringsted Danmark 4100",
    "addr:housenumber":"41 a",
    "addr:postcode":"4100",
    "addr:street":"Smaalodsvej",
    "iso:country":"DK",
    "sg:address":"Sm\u00e5lodsvej 41 A ",
    "sg:city":"Ringsted",
    "sg:classifiers":[
        {
            "category":"Real Estate",
            "subcategory":"Surveying",
            "type":"Services"
        }
    ],
    "sg:phone":"+45 57 67 00 19",
    "sg:postcode":"4100",
    "sg:province":"Danmark",
    "sg:tags":[
        "equipment",
        "material",
        "good",
        "-",
        "handling"
    ],
    "wof:name":"B\u00d8GERIS INDUSTRIGUMMI APS",
    "wof:placetype":"venue"
},
  "geometry": {"coordinates":[11.7946996689,55.4679336548],"type":"Point"}
}