{
  "type": "Feature",
  "properties": {
    "addr:full":"v/ Elise Lauridsen, \u00d8re-Ager 8, Udsholt Gr\u00e6sted Danmark 3230",
    "addr:housenumber":"8",
    "addr:postcode":"3230",
    "addr:street":"Ore-Ager;Udsholt Graested Danmark",
    "iso:country":"DK",
    "sg:address":"v/ Elise Lauridsen, \u00d8re-Ager 8, Udsholt",
    "sg:city":"Gr\u00e6sted",
    "sg:orig_category":"Grundejerforeninger",
    "sg:phone":"+45 48 71 65 63",
    "sg:postcode":"3230",
    "sg:province":"Danmark",
    "wof:name":"Grundejerforeningen Boelsmosegaard",
    "wof:placetype":"venue"
},
  "geometry": {"coordinates":[-78.6975326538,35.0151481628],"type":"Point"}
}