{
  "type": "Feature",
  "properties": {
    "addr:full":"Gammeltoftevej 9 Karlslunde Danmark 2690",
    "addr:housenumber":"9",
    "addr:postcode":"2690",
    "addr:street":"Gammeltoftevej",
    "iso:country":"DK",
    "sg:address":"Gammeltoftevej 9",
    "sg:city":"Karlslunde",
    "sg:orig_category":"Rideskoler",
    "sg:phone":"+45 46 15 04 25",
    "sg:postcode":"2690",
    "sg:province":"Danmark",
    "wof:name":"Gammeltoft Rideklub",
    "wof:placetype":"venue"
},
  "geometry": {"coordinates":[12.1963262558,55.5694351196],"type":"Point"}
}