{
  "type": "Feature",
  "properties": {
    "addr:full":"Fmd.: Leo Hallund Jensen, Thistedvej 11 N\u00f8rresundby Danmark 9400",
    "addr:housenumber":"11",
    "addr:postcode":"9400",
    "addr:street":"Thistedvej",
    "iso:country":"DK",
    "sg:address":"Fmd.: Leo Hallund Jensen, Thistedvej 11",
    "sg:city":"N\u00f8rresundby",
    "sg:orig_category":"Hobbybetonede foreninger",
    "sg:phone":"+45 98 17 45 38",
    "sg:postcode":"9400",
    "sg:province":"Danmark",
    "wof:name":"Brevdueforeningen Vejgaard/ K\u00e6rsholm",
    "wof:placetype":"venue"
},
  "geometry": {"coordinates":[9.9049549103,57.0654602051],"type":"Point"}
}