{
  "type": "Feature",
  "properties": {
    "addr:full":"Hejnsvigvej 12 Billund Danmark 7190",
    "addr:housenumber":"12",
    "addr:postcode":"7190",
    "addr:street":"Hejnsvigvej",
    "iso:country":"DK",
    "sg:address":"Hejnsvigvej 12",
    "sg:city":"Billund",
    "sg:orig_category":"Betonboring",
    "sg:phone":"+45 75 33 17 99",
    "sg:postcode":"7190",
    "sg:province":"Danmark",
    "wof:name":"Midtjydsk Betonboring A/S",
    "wof:placetype":"venue"
},
  "geometry": {"coordinates":[9.0664463043,55.7242393494],"type":"Point"}
}