{
  "type": "Feature",
  "properties": {
    "addr:full":"Egtved Alle 3 Kolding Danmark 6000",
    "addr:housenumber":"3",
    "addr:postcode":"6000",
    "addr:street":"Egtved Alle",
    "iso:country":"DK",
    "sg:address":"Egtved Alle 3",
    "sg:city":"Kolding",
    "sg:orig_category":"Babyudstyr",
    "sg:phone":"+45 75 52 26 44",
    "sg:postcode":"6000",
    "sg:province":"Danmark",
    "wof:name":"BabySam",
    "wof:placetype":"venue"
},
  "geometry": {"coordinates":[9.461295,55.516193],"type":"Point"}
}