{
  "type": "Feature",
  "properties": {
    "addr:full":"Pileg\u00e5rd Alle 39 Kastrup Danmark 2770",
    "addr:housenumber":"39",
    "addr:postcode":"2770",
    "addr:street":"Pilegaard Alle",
    "iso:country":"DK",
    "sg:address":"Pileg\u00e5rd Alle 39",
    "sg:city":"Kastrup",
    "sg:classifiers":[
        {
            "category":"Restaurant",
            "type":"Food & Drink"
        }
    ],
    "sg:phone":"+45 32 50 46 24",
    "sg:postcode":"2770",
    "sg:province":"Danmark",
    "wof:name":"Tobano, Restaurant Pizzeria",
    "wof:placetype":"venue"
},
  "geometry": {"coordinates":[12.586063385,55.616065979],"type":"Point"}
}