{
  "type": "Feature",
  "properties": {
    "addr:full":"\u00d8rstedsgade 18 Rudk\u00f8bing Danmark 5900",
    "addr:housenumber":"18",
    "addr:postcode":"5900",
    "addr:street":"Orstedsgade",
    "iso:country":"DK",
    "sg:address":"\u00d8rstedsgade 18",
    "sg:city":"Rudk\u00f8bing",
    "sg:orig_category":"Aviser",
    "sg:phone":"+45 62 51 10 40",
    "sg:postcode":"5900",
    "sg:province":"Danmark",
    "wof:name":"Langelands Avis",
    "wof:placetype":"venue"
},
  "geometry": {"coordinates":[-89.24946594239999,39.2174491882],"type":"Point"}
}