{
  "type": "Feature",
  "properties": {
    "iso:country":"DK",
    "sg:address":"Letb\u00e6kvej 4, Hodde",
    "sg:city":"Tistrup",
    "sg:orig_category":"Cykler",
    "sg:phone":"+45 75 29 93 03",
    "sg:postcode":"6862",
    "sg:province":"Danmark",
    "wof:name":"Hodde Cykelforretning",
    "wof:placetype":"venue"
},
  "geometry": {"coordinates":[8.6105747223,55.7163848877],"type":"Point"}
}