{
  "type": "Feature",
  "properties": {
    "addr:full":"Ny \u00d8stergade 12, 5 K\u00f8benhavn Danmark 1101",
    "addr:housenumber":"12 5;1101",
    "addr:street":"Ostergade",
    "iso:country":"DK",
    "sg:address":"Ny \u00d8stergade 12, 5",
    "sg:city":"K\u00f8benhavn",
    "sg:orig_category":"Designere",
    "sg:phone":"+45 33 16 10 33",
    "sg:postcode":"1101",
    "sg:province":"Danmark",
    "sg:website":"etcetera-design.dk",
    "wof:name":"Etcetera Design",
    "wof:placetype":"venue"
},
  "geometry": {"coordinates":[-76.50189208979999,42.8563194275],"type":"Point"}
}