{
  "type": "Feature",
  "properties": {
    "addr:full":"Filstruplund 23 Haarby Danmark 5683",
    "addr:housenumber":"23",
    "addr:postcode":"5683",
    "addr:street":"Filstruplund",
    "iso:country":"DK",
    "sg:address":"Filstruplund 23",
    "sg:city":"Haarby",
    "sg:orig_category":"Landbrug",
    "sg:phone":"+45 64 73 23 64",
    "sg:postcode":"5683",
    "sg:province":"Danmark",
    "wof:name":"Filstruplund Maskinstation",
    "wof:placetype":"venue"
},
  "geometry": {"coordinates":[10.1525993347,55.2391548157],"type":"Point"}
}