{
  "type": "Feature",
  "properties": {
    "iso:country":"DK",
    "sg:address":"\u00d8stergade 109",
    "sg:city":"Aabybro",
    "sg:orig_category":"Landbrugsmaskiner",
    "sg:phone":"+45 96 96 25 00",
    "sg:postcode":"9440",
    "sg:province":"Danmark",
    "sg:website":"www.lh-agro.com",
    "wof:name":"LH Technologies Denmark ApS",
    "wof:placetype":"venue"
},
  "geometry": {"coordinates":[9.7424640656,57.1534538269],"type":"Point"}
}