{
  "type": "Feature",
  "properties": {
    "addr:full":"Lillemarken 2, Gevninge Roskilde Danmark 4000",
    "addr:housenumber":"2",
    "addr:postcode":"4000",
    "addr:street":"Lillemarken;Gevninge",
    "iso:country":"DK",
    "sg:address":"Lillemarken 2, Gevninge",
    "sg:city":"Roskilde",
    "sg:classifiers":[
        {
            "category":"Home & Garden",
            "subcategory":"Home Furnishings",
            "type":"Retail Goods"
        }
    ],
    "sg:phone":"+45 46 40 25 11",
    "sg:postcode":"4000",
    "sg:province":"Danmark",
    "sg:tags":[
        "gardiner"
    ],
    "wof:name":"Gardin-Experten",
    "wof:placetype":"venue"
},
  "geometry": {"coordinates":[12.0909376144,55.6404838562],"type":"Point"}
}