{
  "type": "Feature",
  "properties": {
    "addr:full":"Birkelunden 20 Melby Danmark 3370",
    "addr:housenumber":"20",
    "addr:postcode":"3370",
    "addr:street":"Birkelunden",
    "iso:country":"DK",
    "sg:address":"Birkelunden 20",
    "sg:city":"Melby",
    "sg:orig_category":"Malermestre",
    "sg:phone":"+45 47 98 82 44",
    "sg:postcode":"3370",
    "sg:province":"Danmark",
    "wof:name":"Br\u00f8sch, Flemming",
    "wof:placetype":"venue"
},
  "geometry": {"coordinates":[11.9353551865,56.0004348755],"type":"Point"}
}