{
  "type": "Feature",
  "properties": {
    "addr:full":"Hedenstedvej 49 Stenderup Danmark 8781",
    "addr:housenumber":"49",
    "addr:postcode":"8781",
    "addr:street":"Hedenstedvej",
    "iso:country":"DK",
    "sg:address":"Hedenstedvej 49",
    "sg:city":"Stenderup",
    "sg:orig_category":"Hunde",
    "sg:phone":"+45 75 68 14 00",
    "sg:postcode":"8781",
    "sg:province":"Danmark",
    "wof:name":"Gravmand, Kennel",
    "wof:placetype":"venue"
},
  "geometry": {"coordinates":[9.7798900604,55.7890586853],"type":"Point"}
}