{
  "type": "Feature",
  "properties": {
    "addr:full":"Sognepr\u00e6st: Peter \u00d8sterby-J\u00f8rgensen (K/B), Efterskolevej 3, Galtrup Erslev Danmark 7950",
    "addr:housenumber":"3",
    "addr:postcode":"7950",
    "addr:street":"Efterskolevej;Galtrup",
    "iso:country":"DK",
    "sg:address":"Sognepr\u00e6st: Peter \u00d8sterby-J\u00f8rgensen (K/B), Efterskolevej 3, Galtrup",
    "sg:city":"Erslev",
    "sg:orig_category":"Kirkesogne",
    "sg:phone":"+45 97 74 10 76",
    "sg:postcode":"7950",
    "sg:province":"Danmark",
    "wof:name":"Galtrup-\u00d8ster J\u00f8lby-Erslev Sogne",
    "wof:placetype":"venue"
},
  "geometry": {"coordinates":[8.7200698853,56.8354682922],"type":"Point"}
}