{
  "type": "Feature",
  "properties": {
    "addr:full":"Vindingevej 7-11 Nyborg Danmark 5800",
    "addr:housenumber":"7-11",
    "addr:postcode":"5800",
    "addr:street":"Vindingevej",
    "iso:country":"DK",
    "sg:address":"Vindingevej 7-11",
    "sg:city":"Nyborg",
    "sg:orig_category":"Skolefritidsordninger",
    "sg:phone":"+45 65 31 50 16",
    "sg:postcode":"5800",
    "sg:province":"Danmark",
    "wof:name":"Nyborg Friskoles Skolefritidsordning",
    "wof:placetype":"venue"
},
  "geometry": {"coordinates":[10.7834749222,55.3093109131],"type":"Point"}
}