{
  "type": "Feature",
  "properties": {
    "addr:full":"Bygaden 20, St\u00f8dov Knebel Danmark 8420",
    "addr:housenumber":"20",
    "addr:postcode":"8420",
    "addr:street":"Bygaden",
    "iso:country":"DK",
    "sg:address":"Bygaden 20, St\u00f8dov",
    "sg:city":"Knebel",
    "sg:orig_category":"Fodplejere",
    "sg:phone":"+45 86 35 62 03",
    "sg:postcode":"8420",
    "sg:province":"Danmark",
    "wof:name":"Inges Fodpleje",
    "wof:placetype":"venue"
},
  "geometry": {"coordinates":[10.3770122528,56.1816596985],"type":"Point"}
}