{
  "type": "Feature",
  "properties": {
    "iso:country":"DK",
    "sg:address":"Gerdasgade 35",
    "sg:city":"Valby",
    "sg:classifiers":[
        {
            "category":"Communications",
            "type":"Services"
        }
    ],
    "sg:phone":"+45 70 11 90 00",
    "sg:postcode":"2500",
    "sg:province":"Danmark",
    "sg:tags":[
        "radio-",
        "og",
        "tv-stationer"
    ],
    "sg:website":"info@r2.dk",
    "wof:name":"Radio 2 & Radio Uptown",
    "wof:placetype":"venue"
},
  "geometry": {"coordinates":[12.5144643784,55.6582374573],"type":"Point"}
}