{
  "type": "Feature",
  "properties": {
    "addr:full":"Sct. Mathias Gade 25 Viborg Danmark 8800",
    "addr:housenumber":"25",
    "addr:postcode":"8800",
    "addr:street":"Sct. Mathias Gade",
    "iso:country":"DK",
    "sg:address":"Sct. Mathias Gade 25",
    "sg:city":"Viborg",
    "sg:orig_category":"Forsikringer",
    "sg:phone":"+45 87 25 14 00",
    "sg:postcode":"8800",
    "sg:province":"Danmark",
    "sg:website":"www.almbrand.dk",
    "wof:name":"Alm. Brand",
    "wof:placetype":"venue"
},
  "geometry": {"coordinates":[9.40599823,56.4493713379],"type":"Point"}
}