{
  "type": "Feature",
  "properties": {
    "addr:full":"Saltumvej 33, 1. tv Aalborg \u00d8 Danmark 9220",
    "addr:housenumber":"33 1",
    "addr:postcode":"9220",
    "addr:street":"Saltumvej;Tv Aalborg O Danmark",
    "iso:country":"DK",
    "sg:address":"Saltumvej 33, 1. tv",
    "sg:city":"Aalborg \u00d8",
    "sg:classifiers":[
        {
            "category":"Restaurant",
            "type":"Food & Drink"
        }
    ],
    "sg:phone":"+45 98 99 01 11",
    "sg:postcode":"9220",
    "sg:province":"Danmark",
    "wof:name":"L\u00f8kken Pizza Grill House",
    "wof:placetype":"venue"
},
  "geometry": {"coordinates":[10.0031700134,57.0515899658],"type":"Point"}
}