{
  "type": "Feature",
  "properties": {
    "addr:full":"Thrigesvej 10 Silkeborg Danmark 8600",
    "addr:housenumber":"10",
    "addr:postcode":"8600",
    "addr:street":"Thrigesvej",
    "iso:country":"DK",
    "sg:address":"Thrigesvej 10",
    "sg:city":"Silkeborg",
    "sg:orig_category":"El-artikler",
    "sg:phone":"+45 86 81 13 08",
    "sg:postcode":"8600",
    "sg:province":"Danmark",
    "wof:name":"Sk\u00e6rmtrolden",
    "wof:placetype":"venue"
},
  "geometry": {"coordinates":[9.5618581772,56.1966934204],"type":"Point"}
}