{
  "type": "Feature",
  "properties": {
    "addr:full":"c/o SAS, Hammerichsgade 1 - 5 K\u00f8benhavn Danmark 1611",
    "addr:housenumber":"1 5",
    "addr:postcode":"1611",
    "addr:street":"C;Hammerichsgade",
    "iso:country":"DK",
    "sg:address":"c/o SAS, Hammerichsgade 1 - 5",
    "sg:city":"K\u00f8benhavn",
    "sg:orig_category":"Flyvning",
    "sg:phone":"+45 70 10 20 00",
    "sg:postcode":"1611",
    "sg:province":"Danmark",
    "wof:name":"Lufthansa",
    "wof:placetype":"venue"
},
  "geometry": {"coordinates":[12.5649003983,55.6758003235],"type":"Point"}
}