{
  "type": "Feature",
  "properties": {
    "addr:full":"Kirkegade 4, 1. Esbjerg Danmark 6700",
    "addr:housenumber":"4 1",
    "addr:postcode":"6700",
    "addr:street":"Kirkegade",
    "iso:country":"DK",
    "sg:address":"Kirkegade 4, 1.",
    "sg:city":"Esbjerg",
    "sg:orig_category":"Databehandling",
    "sg:phone":"+45 75 13 20 60",
    "sg:postcode":"6700",
    "sg:province":"Danmark",
    "wof:name":"Armstrong IT Consulting",
    "wof:placetype":"venue"
},
  "geometry": {"coordinates":[8.4482774734,55.4651756287],"type":"Point"}
}