{
  "type": "Feature",
  "properties": {
    "addr:full":"Daug\u00e5rdvej 20, Hedensted Skov Daug\u00e5rd Danmark 8721",
    "addr:housenumber":"20",
    "addr:postcode":"8721",
    "addr:street":"Daugaardvej;Skov",
    "iso:country":"DK",
    "sg:address":"Daug\u00e5rdvej 20, Hedensted Skov",
    "sg:city":"Daug\u00e5rd",
    "sg:orig_category":"Forsikringer",
    "sg:phone":"+45 75 89 60 98",
    "sg:postcode":"8721",
    "sg:province":"Danmark",
    "wof:name":"Alm. Brand",
    "wof:placetype":"venue"
},
  "geometry": {"coordinates":[9.6996278763,55.7356300354],"type":"Point"}
}