{
  "type": "Feature",
  "properties": {
    "addr:full":"Fmd.: Henning Storm, Assensvej 172 Faaborg Danmark 5600",
    "addr:housenumber":"172",
    "addr:postcode":"5600",
    "addr:street":"Assensvej",
    "iso:country":"DK",
    "sg:address":"Fmd.: Henning Storm, Assensvej 172",
    "sg:city":"Faaborg",
    "sg:orig_category":"Folkedans",
    "sg:phone":"+45 62 61 95 22",
    "sg:postcode":"5600",
    "sg:province":"Danmark",
    "wof:name":"Faaborg og omegns folkedansere",
    "wof:placetype":"venue"
},
  "geometry": {"coordinates":[10.2400531769,55.0950622559],"type":"Point"}
}