{
  "type": "Feature",
  "properties": {
    "addr:full":"Dalgas Avenue 35 \u00c5rhus C Danmark 8000",
    "addr:housenumber":"35",
    "addr:postcode":"8000",
    "addr:street":"Dalgas Avenue",
    "iso:country":"DK",
    "sg:address":"Dalgas Avenue 35",
    "sg:city":"\u00c5rhus C",
    "sg:orig_category":"Revisorer",
    "sg:phone":"+45 86 12 60 22",
    "sg:postcode":"8000",
    "sg:province":"Danmark",
    "sg:website":"www.rda.dk",
    "wof:name":"Revisorerne Dalgas Avenue, A/S",
    "wof:placetype":"venue"
},
  "geometry": {"coordinates":[-66.94068145750001,-27.6476192474],"type":"Point"}
}