{
  "type": "Feature",
  "properties": {
    "addr:full":"Kornbuen 6, \u00d8verup N\u00e6stved Danmark 4700",
    "addr:housenumber":"6",
    "addr:postcode":"4700",
    "addr:street":"Kornbuen",
    "iso:country":"DK",
    "sg:address":"Kornbuen 6, \u00d8verup",
    "sg:city":"N\u00e6stved",
    "sg:orig_category":"Rustbeskyttelse",
    "sg:phone":"+45 55 77 37 37",
    "sg:postcode":"4700",
    "sg:province":"Danmark",
    "wof:name":"TekTrol Anti Rust",
    "wof:placetype":"venue"
},
  "geometry": {"coordinates":[11.7542486191,55.2315444946],"type":"Point"}
}