{
  "type": "Feature",
  "properties": {
    "iso:country":"DK",
    "sg:address":"v/ Anne-lise Jensen, Strandfogedvej 38, Henneby",
    "sg:city":"Henne",
    "sg:orig_category":"Kulturelle foreninger",
    "sg:phone":"+45 75 25 54 07",
    "sg:postcode":"6854",
    "sg:province":"Danmark",
    "wof:name":"Staus\u00f8 Sogneforening",
    "wof:placetype":"venue"
},
  "geometry": {"coordinates":[8.2223901749,55.7346534729],"type":"Point"}
}