{
  "type": "Feature",
  "properties": {
    "iso:country":"DK",
    "sg:address":"Blegdamsvej 12 B, 2.th.",
    "sg:city":"K\u00f8benhavn N",
    "sg:orig_category":"Alternativ behandling",
    "sg:phone":"+45 35 37 42 12",
    "sg:postcode":"2200",
    "sg:province":"Danmark",
    "sg:website":"www.inspiravisions.dk",
    "wof:name":"Hansen, Bitten Leth",
    "wof:placetype":"venue"
},
  "geometry": {"coordinates":[77.2480392456,14.1354398727],"type":"Point"}
}