{
  "type": "Feature",
  "properties": {
    "addr:full":"Kogleaksvej 33 K\u00f8ge Danmark 4600",
    "addr:housenumber":"33",
    "addr:postcode":"4600",
    "addr:street":"Kogleaksvej",
    "iso:country":"DK",
    "sg:address":"Kogleaksvej 33",
    "sg:city":"K\u00f8ge",
    "sg:orig_category":"Vikarbureauer",
    "sg:phone":"+45 56 63 21 02",
    "sg:postcode":"4600",
    "sg:province":"Danmark",
    "sg:website":"www.cadwork.dk",
    "wof:name":"Cadwork",
    "wof:placetype":"venue"
},
  "geometry": {"coordinates":[12.1524858475,55.444026947],"type":"Point"}
}