{
  "type": "Feature",
  "properties": {
    "addr:full":"Sct. Knudsgade 2B Ringsted Danmark 4100",
    "addr:housenumber":"2b",
    "addr:postcode":"4100",
    "addr:street":"Sct. Knudsgade",
    "iso:country":"DK",
    "sg:address":"Sct. Knudsgade 2B",
    "sg:city":"Ringsted",
    "sg:orig_category":"Revisorer",
    "sg:phone":"+45 57 61 84 44",
    "sg:postcode":"4100",
    "sg:province":"Danmark",
    "sg:website":"www.reviring.dk",
    "wof:name":"\u00d8hauge A/S, Revisionsfirmaet Carsten",
    "wof:placetype":"venue"
},
  "geometry": {"coordinates":[11.789525032,55.4456748962],"type":"Point"}
}