{
  "type": "Feature",
  "properties": {
    "iso:country":"DK",
    "sg:address":"Hjejlevej 99",
    "sg:city":"Nyborg",
    "sg:orig_category":"Campingpladser",
    "sg:phone":"+45 65 31 02 56",
    "sg:postcode":"5800",
    "sg:province":"Danmark",
    "sg:website":"www.strandcamping.dk",
    "wof:name":"Nyborg StrandCamping",
    "wof:placetype":"venue"
},
  "geometry": {"coordinates":[10.8257169724,55.304145813],"type":"Point"}
}