{
  "type": "Feature",
  "properties": {
    "addr:full":"Store R\u00f8ttingevej 2, St. R\u00f8ttinge Tappern\u00f8je Danmark 4733",
    "addr:housenumber":"2",
    "addr:postcode":"4733",
    "addr:street":"Rottingevej",
    "iso:country":"DK",
    "sg:address":"Store R\u00f8ttingevej 2, St. R\u00f8ttinge",
    "sg:city":"Tappern\u00f8je",
    "sg:orig_category":"Helsekost",
    "sg:phone":"+45 55 96 61 40",
    "sg:postcode":"4733",
    "sg:province":"Danmark",
    "wof:name":"Gamle Stue, Den",
    "wof:placetype":"venue"
},
  "geometry": {"coordinates":[15.3213195801,46.2218589783],"type":"Point"}
}