{
  "type": "Feature",
  "properties": {
    "iso:country":"DK",
    "sg:address":"Risingsvej 2",
    "sg:city":"Odense C",
    "sg:orig_category":"Maskinudlejning",
    "sg:phone":"+45 65 91 12 14",
    "sg:postcode":"5000",
    "sg:province":"Danmark",
    "wof:name":"Olsen ApS, Bille",
    "wof:placetype":"venue"
},
  "geometry": {"coordinates":[10.4103889465,55.410900116],"type":"Point"}
}