{
  "type": "Feature",
  "properties": {
    "addr:full":"Strandvejen 781 Klampenborg Danmark 2930",
    "addr:housenumber":"781",
    "addr:postcode":"2930",
    "addr:street":"Strandvejen",
    "iso:country":"DK",
    "sg:address":"Strandvejen 781",
    "sg:city":"Klampenborg",
    "sg:classifiers":[
        {
            "category":"Professional",
            "subcategory":"Advertising",
            "type":"Services"
        }
    ],
    "sg:phone":"+45 39 96 01 00",
    "sg:postcode":"2930",
    "sg:province":"Danmark",
    "sg:tags":[
        "marketing"
    ],
    "wof:name":"Aston CRM Solutions A/S",
    "wof:placetype":"venue"
},
  "geometry": {"coordinates":[12.5881729126,55.7983055115],"type":"Point"}
}