{
  "type": "Feature",
  "properties": {
    "addr:full":"R\u00f8nningevej 38 Langeskov Danmark 5550",
    "addr:housenumber":"38",
    "addr:postcode":"5550",
    "addr:street":"Ronningevej",
    "iso:country":"DK",
    "sg:address":"R\u00f8nningevej 38",
    "sg:city":"Langeskov",
    "sg:orig_category":"Skolefritidsordninger",
    "sg:phone":"+45 63 38 29 43",
    "sg:postcode":"5550",
    "sg:province":"Danmark",
    "wof:name":"Bakkeg\u00e5rdsskolens fritidsordning",
    "wof:placetype":"venue"
},
  "geometry": {"coordinates":[10.6015319824,55.3553123474],"type":"Point"}
}