{
  "type": "Feature",
  "properties": {
    "addr:full":"Odensevej 10, Hjallese Odense S Danmark 5260",
    "addr:housenumber":"10",
    "addr:postcode":"5260",
    "addr:street":"Odensevej;Hjallese",
    "iso:country":"DK",
    "sg:address":"Odensevej 10, Hjallese",
    "sg:city":"Odense S",
    "sg:orig_category":"Brugsforeninger",
    "sg:phone":"+45 63 17 61 81",
    "sg:postcode":"5260",
    "sg:province":"Danmark",
    "wof:name":"Super Brugsen",
    "wof:placetype":"venue"
},
  "geometry": {"coordinates":[10.3157806396,55.3122825623],"type":"Point"}
}