{
  "type": "Feature",
  "properties": {
    "iso:country":"DK",
    "sg:address":"Gentoftegade 50, st.",
    "sg:city":"Gentofte",
    "sg:classifiers":[
        {
            "category":"Banks & Credit Unions",
            "subcategory":"Bank",
            "type":"Services"
        }
    ],
    "sg:phone":"+45 39 75 07 00",
    "sg:postcode":"2820",
    "sg:province":"Danmark",
    "sg:tags":[
        "banker"
    ],
    "sg:website":"www.danskebank.dk",
    "wof:name":"Danske Bank",
    "wof:placetype":"venue"
},
  "geometry": {"coordinates":[12.540917,55.748272],"type":"Point"}
}