{
  "type": "Feature",
  "properties": {
    "addr:full":"Kirketorvet 10 - 16 Vejle Danmark 7100",
    "addr:housenumber":"10 16",
    "addr:postcode":"7100",
    "addr:street":"Kirketorvet",
    "iso:country":"DK",
    "sg:address":"Kirketorvet 10 - 16",
    "sg:city":"Vejle",
    "sg:orig_category":"HOTELS: OG MOTELLER",
    "sg:phone":"+45 79 42 79 00",
    "sg:postcode":"7100",
    "sg:province":"Danmark",
    "wof:name":"Torvehallerne",
    "wof:placetype":"venue"
},
  "geometry": {"coordinates":[9.5335674286,55.7074203491],"type":"Point"}
}