{
  "type": "Feature",
  "properties": {
    "addr:full":"Fmd.: Rune Andersen, Pr\u00e6steg\u00e5rdsvej 41 Kirke Hvals\u00f8 Danmark 4330",
    "addr:housenumber":"41",
    "addr:postcode":"4330",
    "addr:street":"Praestegaardsvej",
    "iso:country":"DK",
    "sg:address":"Fmd.: Rune Andersen, Pr\u00e6steg\u00e5rdsvej 41",
    "sg:city":"Kirke Hvals\u00f8",
    "sg:orig_category":"Andelsboligforeninger",
    "sg:phone":"+45 46 40 80 24",
    "sg:postcode":"4330",
    "sg:province":"Danmark",
    "wof:name":"Andelsboligforeningen Pr\u00e6stehaven II",
    "wof:placetype":"venue"
},
  "geometry": {"coordinates":[-122.61585998539999,45.6801795959],"type":"Point"}
}