{
  "type": "Feature",
  "properties": {
    "iso:country":"DK",
    "sg:address":"Lyn\u00e6s Havnevej 15 B",
    "sg:city":"Hundested",
    "sg:orig_category":"Havne",
    "sg:phone":"+45 47 93 91 19",
    "sg:postcode":"3390",
    "sg:province":"Danmark",
    "wof:name":"Lyn\u00e6s Havn",
    "wof:placetype":"venue"
},
  "geometry": {"coordinates":[11.8642206192,55.9432258606],"type":"Point"}
}