{
  "type": "Feature",
  "properties": {
    "addr:full":"Ole Borchs Vej 45 Valby Danmark 2500",
    "addr:housenumber":"45",
    "addr:postcode":"2500",
    "addr:street":"Ole Borchs Vej",
    "iso:country":"DK",
    "sg:address":"Ole Borchs Vej 45",
    "sg:city":"Valby",
    "sg:orig_category":"Psykologer, praktiserende",
    "sg:phone":"+45 36 46 85 19",
    "sg:postcode":"2500",
    "sg:province":"Danmark",
    "wof:name":"Vrang, Birgit Heine",
    "wof:placetype":"venue"
},
  "geometry": {"coordinates":[12.4947872162,55.6623535156],"type":"Point"}
}