{
  "type": "Feature",
  "properties": {
    "addr:full":"Industrivej 1, Gr\u00f8nnemose Aarup Danmark 5560",
    "addr:housenumber":"1",
    "addr:postcode":"5560",
    "addr:street":"Industrivej",
    "iso:country":"DK",
    "sg:address":"Industrivej 1, Gr\u00f8nnemose",
    "sg:city":"Aarup",
    "sg:orig_category":"Korn og foderstoffer",
    "sg:phone":"+45 64 43 12 12",
    "sg:postcode":"5560",
    "sg:province":"Danmark",
    "wof:name":"F. A. F.",
    "wof:placetype":"venue"
},
  "geometry": {"coordinates":[10.0490245819,55.3808059692],"type":"Point"}
}