{
  "type": "Feature",
  "properties": {
    "addr:full":"\u00c6rtebjergvej 38 Hvidovre Danmark 2650",
    "addr:housenumber":"38",
    "addr:postcode":"2650",
    "addr:street":"Aertebjergvej",
    "iso:country":"DK",
    "sg:address":"\u00c6rtebjergvej 38",
    "sg:city":"Hvidovre",
    "sg:classifiers":[
        {
            "category":"Communications",
            "type":"Services"
        }
    ],
    "sg:phone":"+45 36 78 85 68",
    "sg:postcode":"2650",
    "sg:province":"Danmark",
    "sg:tags":[
        "og",
        "tv",
        "radio"
    ],
    "wof:name":"Phone Computer Records",
    "wof:placetype":"venue"
},
  "geometry": {"coordinates":[12.4630813599,55.6362380981],"type":"Point"}
}