{
  "type": "Feature",
  "properties": {
    "iso:country":"DK",
    "sg:address":"Ryvej 31",
    "sg:city":"Virum",
    "sg:orig_category":"Autoforhandlere",
    "sg:phone":"+45 45 83 18 02",
    "sg:postcode":"2830",
    "sg:province":"Danmark",
    "wof:name":"Krogh Automobil A/S, Allan",
    "wof:placetype":"venue"
},
  "geometry": {"coordinates":[12.4640407562,55.8002738953],"type":"Point"}
}