{
  "type": "Feature",
  "properties": {
    "addr:full":"Industrivej 7, Gr\u00f8nnemose Aarup Danmark 5560",
    "addr:housenumber":"7",
    "addr:postcode":"5560",
    "addr:street":"Industrivej",
    "iso:country":"DK",
    "sg:address":"Industrivej 7, Gr\u00f8nnemose",
    "sg:city":"Aarup",
    "sg:orig_category":"Industrilakering",
    "sg:phone":"+45 64 43 13 03",
    "sg:postcode":"5560",
    "sg:province":"Danmark",
    "wof:name":"L C Lakering",
    "wof:placetype":"venue"
},
  "geometry": {"coordinates":[10.0490245819,55.3808059692],"type":"Point"}
}