{
  "type": "Feature",
  "properties": {
    "addr:full":"Jyllingecentret 31 Jyllinge Danmark 4040",
    "addr:housenumber":"31",
    "addr:postcode":"4040",
    "addr:street":"Jyllingecentret",
    "iso:country":"DK",
    "sg:address":"Jyllingecentret 31",
    "sg:city":"Jyllinge",
    "sg:orig_category":"Apoteker og -udsalg",
    "sg:phone":"+45 46 73 13 88",
    "sg:postcode":"4040",
    "sg:province":"Danmark",
    "wof:name":"Jyllinge Apoteksudsalg",
    "wof:placetype":"venue"
},
  "geometry": {"coordinates":[12.1085252762,55.7502670288],"type":"Point"}
}