{
  "type": "Feature",
  "properties": {
    "iso:country":"DK",
    "sg:address":"B\u00f8nderg\u00e5rdsvej 2-4",
    "sg:city":"Esbjerg",
    "sg:orig_category":"Integrerede institutioner",
    "sg:phone":"+45 75 12 17 73",
    "sg:postcode":"6700",
    "sg:province":"Danmark",
    "wof:name":"Trianglen, Aldersintegreret",
    "wof:placetype":"venue"
},
  "geometry": {"coordinates":[8.456905365,55.465221405],"type":"Point"}
}