{
  "type": "Feature",
  "properties": {
    "addr:full":"Storegade 227 A Esbjerg \u00d8 Danmark 6705",
    "addr:housenumber":"227 a",
    "addr:postcode":"6705",
    "addr:street":"Storegade;Danmark",
    "iso:country":"DK",
    "sg:address":"Storegade 227 A",
    "sg:city":"Esbjerg \u00d8",
    "sg:classifiers":[
        {
            "category":"Restaurant",
            "type":"Food & Drink"
        }
    ],
    "sg:phone":"+45 75 14 58 75",
    "sg:postcode":"6705",
    "sg:province":"Danmark",
    "wof:name":"McDonalds",
    "wof:placetype":"venue"
},
  "geometry": {"coordinates":[8.4955377579,55.4795303345],"type":"Point"}
}