{
  "type": "Feature",
  "properties": {
    "addr:full":"M\u00f8ller Andersens Vej 3, Hammersh\u00f8j Tjele Danmark 8830",
    "addr:housenumber":"3",
    "addr:postcode":"8830",
    "addr:street":"Moller Andersens Vej;Hammershoj",
    "iso:country":"DK",
    "sg:address":"M\u00f8ller Andersens Vej 3, Hammersh\u00f8j",
    "sg:city":"Tjele",
    "sg:classifiers":[
        {
            "category":"Taxi",
            "type":"Transportation"
        }
    ],
    "sg:phone":"+45 86 45 19 09",
    "sg:postcode":"8830",
    "sg:province":"Danmark",
    "wof:name":"Hammersh\u00f8j Taxi",
    "wof:placetype":"venue"
},
  "geometry": {"coordinates":[9.6264801025,56.4818611145],"type":"Point"}
}