{
  "type": "Feature",
  "properties": {
    "addr:full":"Vestervigvej 178, Hassing Bedsted Danmark 7755",
    "addr:housenumber":"178",
    "addr:postcode":"7755",
    "addr:street":"Vestervigvej",
    "iso:country":"DK",
    "sg:address":"Vestervigvej 178, Hassing",
    "sg:city":"Bedsted",
    "sg:orig_category":"Non-Classified Establishments",
    "sg:phone":"+45 97 94 62 01",
    "sg:postcode":"7755",
    "sg:province":"Danmark",
    "sg:website":"www.poda.dk",
    "wof:name":"Poda Hegn",
    "wof:placetype":"venue"
},
  "geometry": {"coordinates":[8.4905691147,56.8179664612],"type":"Point"}
}