{
  "type": "Feature",
  "properties": {
    "addr:full":"Tj\u00f8rnev\u00e6nget 1, Hald Ege Viborg Danmark 8800",
    "addr:housenumber":"1",
    "addr:postcode":"8800",
    "addr:street":"Tjornevaenget;Hald Ege",
    "iso:country":"DK",
    "sg:address":"Tj\u00f8rnev\u00e6nget 1, Hald Ege",
    "sg:city":"Viborg",
    "sg:orig_category":"Autoforhandlere",
    "sg:phone":"+45 86 63 81 76",
    "sg:postcode":"8800",
    "sg:province":"Danmark",
    "wof:name":"OC Biler",
    "wof:placetype":"venue"
},
  "geometry": {"coordinates":[9.4071502686,56.452671051],"type":"Point"}
}