{
  "type": "Feature",
  "properties": {
    "iso:country":"DK",
    "sg:address":"I. H. Mundts Vej 8 B",
    "sg:city":"Virum",
    "sg:orig_category":"\u00c3\u02dcvrig fritidsundervisning",
    "sg:phone":"+45 45 85 77 70",
    "sg:postcode":"2830",
    "sg:province":"Danmark",
    "wof:name":"Trivselsskolen",
    "wof:placetype":"venue"
},
  "geometry": {"coordinates":[12.4826774597,55.7801971436],"type":"Point"}
}