{
  "type": "Feature",
  "properties": {
    "addr:full":"Bromb\u00e6rv\u00e6nget 8 Thisted Danmark 7700",
    "addr:housenumber":"8",
    "addr:postcode":"7700",
    "addr:street":"Brombaervaenget",
    "iso:country":"DK",
    "sg:address":"Bromb\u00e6rv\u00e6nget 8",
    "sg:city":"Thisted",
    "sg:orig_category":"Murermestre",
    "sg:phone":"+45 96 19 31 18",
    "sg:postcode":"7700",
    "sg:province":"Danmark",
    "wof:name":"Bang, Axel",
    "wof:placetype":"venue"
},
  "geometry": {"coordinates":[8.6919784546,56.9556121826],"type":"Point"}
}