{
  "type": "Feature",
  "properties": {
    "addr:full":"Egedal 1 A Karlslunde Danmark 2690",
    "addr:housenumber":"1 a",
    "addr:postcode":"2690",
    "addr:street":"Egedal",
    "iso:country":"DK",
    "sg:address":"Egedal 1 A",
    "sg:city":"Karlslunde",
    "sg:orig_category":"Alternativ behandling",
    "sg:phone":"+45 46 15 50 15",
    "sg:postcode":"2690",
    "sg:province":"Danmark",
    "wof:name":"Body Self Developments Systems A/S",
    "wof:placetype":"venue"
},
  "geometry": {"coordinates":[12.2527780533,55.5677070618],"type":"Point"}
}