{
  "type": "Feature",
  "properties": {
    "iso:country":"DK",
    "sg:address":"\u00d8sterbrogade 8",
    "sg:city":"Grenaa",
    "sg:orig_category":"Servicestationer",
    "sg:phone":"+45 86 32 11 50",
    "sg:postcode":"8500",
    "sg:province":"Danmark",
    "wof:name":"Shell Service",
    "wof:placetype":"venue"
},
  "geometry": {"coordinates":[10.8860273361,56.41381073],"type":"Point"}
}