{
  "type": "Feature",
  "properties": {
    "addr:full":"Teglv\u00e6nget 18, Hvalpsund Fars\u00f8 Danmark 9640",
    "addr:housenumber":"18",
    "addr:postcode":"9640",
    "addr:street":"Teglvaenget",
    "iso:country":"DK",
    "sg:address":"Teglv\u00e6nget 18, Hvalpsund",
    "sg:city":"Fars\u00f8",
    "sg:orig_category":"Autoreparation og -service",
    "sg:phone":"+45 98 63 80 91",
    "sg:postcode":"9640",
    "sg:province":"Danmark",
    "wof:name":"Ole's Autov\u00e6rksted",
    "wof:placetype":"venue"
},
  "geometry": {"coordinates":[9.1937885284,56.6945037842],"type":"Point"}
}