{
  "type": "Feature",
  "properties": {
    "addr:full":"v/ Keld Trelborg Hansen, Jernbanegade 60 B Roskilde Danmark 4000",
    "addr:housenumber":"60 b",
    "addr:postcode":"4000",
    "addr:street":"Jernbanegade",
    "iso:country":"DK",
    "sg:address":"v/ Keld Trelborg Hansen, Jernbanegade 60 B",
    "sg:city":"Roskilde",
    "sg:orig_category":"Kirkelige foreninger",
    "sg:phone":"+45 46 35 54 09",
    "sg:postcode":"4000",
    "sg:province":"Danmark",
    "wof:name":"Indre Mission Greve",
    "wof:placetype":"venue"
},
  "geometry": {"coordinates":[12.0909376144,55.6404838562],"type":"Point"}
}