{
  "type": "Feature",
  "properties": {
    "addr:full":"v/Knud Kristensen, Rosenkrantzvej 1 Hornslet Danmark 8543",
    "addr:housenumber":"1",
    "addr:postcode":"8543",
    "addr:street":"Kristensen Rosenkrantzvej",
    "iso:country":"DK",
    "sg:address":"v/Knud Kristensen, Rosenkrantzvej 1",
    "sg:city":"Hornslet",
    "sg:orig_category":"\u00c3\u02dcvrig fritidsundervisning",
    "sg:phone":"+45 86 99 63 45",
    "sg:postcode":"8543",
    "sg:province":"Danmark",
    "wof:name":"K.V.H. Aftenskole",
    "wof:placetype":"venue"
},
  "geometry": {"coordinates":[10.3180999756,56.3159866333],"type":"Point"}
}