{
  "type": "Feature",
  "properties": {
    "iso:country":"DK",
    "sg:address":"Lerchenborgvej 31",
    "sg:city":"Kalundborg",
    "sg:orig_category":"Stilladser",
    "sg:phone":"+45 59 56 06 00",
    "sg:postcode":"4400",
    "sg:province":"Danmark",
    "wof:name":"Stjerne Stilladser A/S",
    "wof:placetype":"venue"
},
  "geometry": {"coordinates":[11.110833168,55.6677856445],"type":"Point"}
}