{
  "type": "Feature",
  "properties": {
    "addr:full":"Torvegade 2 A Auning Danmark 8963",
    "addr:housenumber":"2 a",
    "addr:postcode":"8963",
    "addr:street":"Torvegade",
    "iso:country":"DK",
    "sg:address":"Torvegade 2 A",
    "sg:city":"Auning",
    "sg:orig_category":"Advokater",
    "sg:phone":"+45 86 48 33 22",
    "sg:postcode":"8963",
    "sg:province":"Danmark",
    "wof:name":"Meilvang, Lars",
    "wof:placetype":"venue"
},
  "geometry": {"coordinates":[10.3764228821,56.430103302],"type":"Point"}
}