{
  "type": "Feature",
  "properties": {
    "addr:full":"Horsensvej 90, Tebstrup Skanderborg Danmark 8660",
    "addr:housenumber":"90",
    "addr:postcode":"8660",
    "addr:street":"Horsensvej",
    "iso:country":"DK",
    "sg:address":"Horsensvej 90, Tebstrup",
    "sg:city":"Skanderborg",
    "sg:orig_category":"Autoreparation og -service",
    "sg:phone":"+45 86 53 87 77",
    "sg:postcode":"8660",
    "sg:province":"Danmark",
    "wof:name":"Tebstrup Auto",
    "wof:placetype":"venue"
},
  "geometry": {"coordinates":[9.929974556,56.0380249023],"type":"Point"}
}