{
  "type": "Feature",
  "properties": {
    "addr:full":"v/ Solveig Kj\u00e6rsgaard, Fyrrebakken 22 Vejby Danmark 3210",
    "addr:housenumber":"22",
    "addr:postcode":"3210",
    "addr:street":"Fyrrebakken",
    "iso:country":"DK",
    "sg:address":"v/ Solveig Kj\u00e6rsgaard, Fyrrebakken 22",
    "sg:city":"Vejby",
    "sg:orig_category":"Grundejerforeninger",
    "sg:phone":"+45 48 70 15 12",
    "sg:postcode":"3210",
    "sg:province":"Danmark",
    "wof:name":"Fyrrebakken Grundejerforening",
    "wof:placetype":"venue"
},
  "geometry": {"coordinates":[12.1534852982,56.0930938721],"type":"Point"}
}