{
  "type": "Feature",
  "properties": {
    "iso:country":"DK",
    "sg:address":"v/Frederikshavn Bibliotek, Parallelvej 16",
    "sg:city":"Frederikshavn",
    "sg:orig_category":"Bogbusordning",
    "sg:phone":"+45 96 22 56 50",
    "sg:postcode":"9900",
    "sg:province":"Danmark",
    "wof:name":"Bogbusordningen",
    "wof:placetype":"venue"
},
  "geometry": {"coordinates":[10.5362997055,57.4396400452],"type":"Point"}
}