{
  "type": "Feature",
  "properties": {
    "iso:country":"DK",
    "sg:address":"Auktionsgade 3",
    "sg:city":"Esbjerg",
    "sg:orig_category":"Iscreme",
    "sg:phone":"+45 76 10 61 00",
    "sg:postcode":"6700",
    "sg:province":"Danmark",
    "sg:website":"www.hjem-is.dk",
    "wof:name":"Hjem-IS A/S",
    "wof:placetype":"venue"
},
  "geometry": {"coordinates":[8.4287004471,55.4724464417],"type":"Point"}
}