{
  "type": "Feature",
  "properties": {
    "addr:full":"v/ Esther D. Jensen, Kratbakken 11, Tofterup Grindsted Danmark 7200",
    "addr:housenumber":"11",
    "addr:postcode":"7200",
    "addr:street":"Kratbakken;Tofterup",
    "iso:country":"DK",
    "sg:address":"v/ Esther D. Jensen, Kratbakken 11, Tofterup",
    "sg:city":"Grindsted",
    "sg:orig_category":"Spejderkorps",
    "sg:phone":"+45 75 33 72 46",
    "sg:postcode":"7200",
    "sg:province":"Danmark",
    "wof:name":"Det danske Spejderkorps, Starup gruppe",
    "wof:placetype":"venue"
},
  "geometry": {"coordinates":[8.9288702011,55.7560272217],"type":"Point"}
}