{
  "type": "Feature",
  "properties": {
    "addr:full":"Lindevangs Alle 7 Frederiksberg Danmark 2000",
    "addr:housenumber":"7",
    "addr:postcode":"2000",
    "addr:street":"Lindevangs Alle",
    "iso:country":"DK",
    "sg:address":"Lindevangs Alle 7",
    "sg:city":"Frederiksberg",
    "sg:orig_category":"Botilbud",
    "sg:phone":"+45 38 86 40 61",
    "sg:postcode":"2000",
    "sg:province":"Danmark",
    "wof:name":"Lindevangen Herberg",
    "wof:placetype":"venue"
},
  "geometry": {"coordinates":[12.5176029205,55.680393219],"type":"Point"}
}