{
  "type": "Feature",
  "properties": {
    "iso:country":"DK",
    "sg:address":"S\u00f8ndergade 1",
    "sg:city":"Herning",
    "sg:orig_category":"Ejendomshandel",
    "sg:phone":"+45 96 27 24 44",
    "sg:postcode":"7400",
    "sg:province":"Danmark",
    "wof:name":"Midtbolig",
    "wof:placetype":"venue"
},
  "geometry": {"coordinates":[9.0166101456,56.1348342896],"type":"Point"}
}