{
  "type": "Feature",
  "properties": {
    "addr:full":"Vibevej 8, Ellinge Lyng Vig Danmark 4560",
    "addr:housenumber":"8",
    "addr:postcode":"4560",
    "addr:street":"Vibevej;Ellinge Lyng",
    "iso:country":"DK",
    "sg:address":"Vibevej 8, Ellinge Lyng",
    "sg:city":"Vig",
    "sg:orig_category":"Vinduespolering",
    "sg:phone":"+45 59 30 56 46",
    "sg:postcode":"4560",
    "sg:province":"Danmark",
    "wof:name":"Lyngens Vinduespolering",
    "wof:placetype":"venue"
},
  "geometry": {"coordinates":[11.5269098282,55.858795166],"type":"Point"}
}