{
  "type": "Feature",
  "properties": {
    "addr:full":"Arres\u00f8vej 18 B Risskov Danmark 8240",
    "addr:housenumber":"18 b",
    "addr:postcode":"8240",
    "addr:street":"Arresovej",
    "iso:country":"DK",
    "sg:address":"Arres\u00f8vej 18 B",
    "sg:city":"Risskov",
    "sg:orig_category":"Skilte",
    "sg:phone":"+45 86 17 37 34",
    "sg:postcode":"8240",
    "sg:province":"Danmark",
    "wof:name":"Neon Flex",
    "wof:placetype":"venue"
},
  "geometry": {"coordinates":[10.2328176498,56.202960968],"type":"Point"}
}