{
  "type": "Feature",
  "properties": {
    "addr:full":"Mariendalsvej 32 Frederiksberg Danmark 2000",
    "addr:housenumber":"32",
    "addr:postcode":"2000",
    "addr:street":"Mariendalsvej",
    "iso:country":"DK",
    "sg:address":"Mariendalsvej 32",
    "sg:city":"Frederiksberg",
    "sg:orig_category":"Rammer",
    "sg:phone":"+45 38 88 38 81",
    "sg:postcode":"2000",
    "sg:province":"Danmark",
    "wof:name":"Danposter ApS",
    "wof:placetype":"venue"
},
  "geometry": {"coordinates":[12.536860466,55.6896286011],"type":"Point"}
}