{
  "type": "Feature",
  "properties": {
    "addr:full":"Vester Farimagsgade 1, 3. K\u00f8benhavn Danmark 1606",
    "addr:housenumber":"1 3",
    "addr:postcode":"1606",
    "addr:street":"Vester Farimagsgade",
    "iso:country":"DK",
    "sg:address":"Vester Farimagsgade 1, 3.",
    "sg:city":"K\u00f8benhavn",
    "sg:orig_category":"Flyvning",
    "sg:phone":"+45 33 91 76 74",
    "sg:postcode":"1606",
    "sg:province":"Danmark",
    "sg:website":"www.pulkovo.dk",
    "wof:name":"Pulkovo Airlines",
    "wof:placetype":"venue"
},
  "geometry": {"coordinates":[12.5636997223,55.6749992371],"type":"Point"}
}