{
  "type": "Feature",
  "properties": {
    "addr:full":"Vandv\u00e6rksvej 2, Rostrup Arden Danmark 9510",
    "addr:housenumber":"2",
    "addr:postcode":"9510",
    "addr:street":"Vandvaerksvej",
    "iso:country":"DK",
    "sg:address":"Vandv\u00e6rksvej 2, Rostrup",
    "sg:city":"Arden",
    "sg:orig_category":"Kostumeudlejning",
    "sg:phone":"+45 98 56 65 56",
    "sg:postcode":"9510",
    "sg:province":"Danmark",
    "wof:name":"Mardi Gras",
    "wof:placetype":"venue"
},
  "geometry": {"coordinates":[9.8580989838,56.7683296204],"type":"Point"}
}