{
  "type": "Feature",
  "properties": {
    "addr:full":"Glimvej 12, Glim Roskilde Danmark 4000",
    "addr:housenumber":"12",
    "addr:postcode":"4000",
    "addr:street":"Glimvej",
    "iso:country":"DK",
    "sg:address":"Glimvej 12, Glim",
    "sg:city":"Roskilde",
    "sg:orig_category":"Fabrikker",
    "sg:phone":"+45 46 48 04 95",
    "sg:postcode":"4000",
    "sg:province":"Danmark",
    "wof:name":"Glim Plastic Industri ApS",
    "wof:placetype":"venue"
},
  "geometry": {"coordinates":[12.0909376144,55.6404838562],"type":"Point"}
}