{
  "type": "Feature",
  "properties": {
    "iso:country":"DK",
    "sg:address":"Skjernvej 49 C",
    "sg:city":"Tarm",
    "sg:orig_category":"Babyudstyr",
    "sg:phone":"+45 97 37 30 55",
    "sg:postcode":"6880",
    "sg:province":"Danmark",
    "wof:name":"Baby-Vest",
    "wof:placetype":"venue"
},
  "geometry": {"coordinates":[8.518087,55.915459],"type":"Point"}
}