{
  "type": "Feature",
  "properties": {
    "addr:full":"Solsikkevej 9 Haderslev Danmark 6100",
    "addr:housenumber":"9",
    "addr:postcode":"6100",
    "addr:street":"Solsikkevej",
    "iso:country":"DK",
    "sg:address":"Solsikkevej 9",
    "sg:city":"Haderslev",
    "sg:orig_category":"Revisorer",
    "sg:phone":"+45 74 53 22 99",
    "sg:postcode":"6100",
    "sg:province":"Danmark",
    "sg:website":"www.altrev.dk",
    "wof:name":"Alternativ revision ApS",
    "wof:placetype":"venue"
},
  "geometry": {"coordinates":[9.4993152618,55.2323303223],"type":"Point"}
}