{
  "type": "Feature",
  "properties": {
    "iso:country":"DK",
    "sg:address":"Thyrasvej 9",
    "sg:city":"Herning",
    "sg:orig_category":"Ungdomsklubber",
    "sg:phone":"+45 97 12 87 56",
    "sg:postcode":"7400",
    "sg:province":"Danmark",
    "wof:name":"Holtbjerg Ungdomsklub",
    "wof:placetype":"venue"
},
  "geometry": {"coordinates":[8.9965353012,56.1329460144],"type":"Point"}
}