{
  "type": "Feature",
  "properties": {
    "iso:country":"DK",
    "sg:address":"Havmosevej 19",
    "sg:city":"Silkeborg",
    "sg:orig_category":"Walkie-talkie udstyr",
    "sg:phone":"+45 86 84 61 62",
    "sg:postcode":"8600",
    "sg:province":"Danmark",
    "wof:name":"Sejs Walkie-Talkie",
    "wof:placetype":"venue"
},
  "geometry": {"coordinates":[9.5969400406,56.1401443481],"type":"Point"}
}