{
  "type": "Feature",
  "properties": {
    "addr:full":"Stjernegade 4, Stryn\u00f8 Rudk\u00f8bing Danmark 5900",
    "addr:housenumber":"4",
    "addr:postcode":"5900",
    "addr:street":"Stjernegade",
    "iso:country":"DK",
    "sg:address":"Stjernegade 4, Stryn\u00f8",
    "sg:city":"Rudk\u00f8bing",
    "sg:orig_category":"RESTAURANTS: CAFEER",
    "sg:phone":"+45 62 51 53 00",
    "sg:postcode":"5900",
    "sg:province":"Danmark",
    "wof:name":"Stryn\u00f8 Kro",
    "wof:placetype":"venue"
},
  "geometry": {"coordinates":[-114.0767440796,46.4432487488],"type":"Point"}
}