{
  "type": "Feature",
  "properties": {
    "iso:country":"DK",
    "sg:address":"B\u00f8dkervej 18",
    "sg:city":"Holb\u00e6k",
    "sg:orig_category":"Bolte",
    "sg:phone":"+45 59 44 64 14",
    "sg:postcode":"4300",
    "sg:province":"Danmark",
    "sg:website":"www.sfs-online.com",
    "wof:name":"SFS intec A/S",
    "wof:placetype":"venue"
},
  "geometry": {"coordinates":[76.3070983887,14.277130127],"type":"Point"}
}