{
  "type": "Feature",
  "properties": {
    "addr:full":"Holte Midtpunkt 20, 3. Holte Danmark 2840",
    "addr:housenumber":"20 3",
    "addr:postcode":"2840",
    "addr:street":"Holte Midtpunkt",
    "iso:country":"DK",
    "sg:address":"Holte Midtpunkt 20, 3.",
    "sg:city":"Holte",
    "sg:orig_category":"Statslige direktorater og styrelser",
    "sg:phone":"+45 45 46 11 00",
    "sg:postcode":"2840",
    "sg:province":"Danmark",
    "wof:name":"Rejseanken\u00e6vnet",
    "wof:placetype":"venue"
},
  "geometry": {"coordinates":[12.4706087112,55.8110733032],"type":"Point"}
}