{
  "type": "Feature",
  "properties": {
    "addr:full":"Byvejen 39, K\u00f8ng Glamsbjerg Danmark 5620",
    "addr:housenumber":"39",
    "addr:postcode":"5620",
    "addr:street":"Byvejen;Kong",
    "iso:country":"DK",
    "sg:address":"Byvejen 39, K\u00f8ng",
    "sg:city":"Glamsbjerg",
    "sg:orig_category":"Forsamlingshuse",
    "sg:phone":"+45 64 72 17 68",
    "sg:postcode":"5620",
    "sg:province":"Danmark",
    "wof:name":"K\u00f8ng Forsamlingshus",
    "wof:placetype":"venue"
},
  "geometry": {"coordinates":[10.1052503586,55.2783317566],"type":"Point"}
}