{
  "type": "Feature",
  "properties": {
    "addr:full":"Hyldeg\u00e5rdsvej 53 - 61 Charlottenlund Danmark 2920",
    "addr:housenumber":"53 61",
    "addr:postcode":"2920",
    "addr:street":"Hyldegaardsvej",
    "iso:country":"DK",
    "sg:address":"Hyldeg\u00e5rdsvej 53 - 61",
    "sg:city":"Charlottenlund",
    "sg:orig_category":"Autoforhandlere",
    "sg:phone":"+45 39 64 27 00",
    "sg:postcode":"2920",
    "sg:province":"Danmark",
    "sg:website":"www.johan-dahl.dk",
    "wof:name":"Dahl Automobiler A/S, Johan",
    "wof:placetype":"venue"
},
  "geometry": {"coordinates":[12.5837678909,55.7601013184],"type":"Point"}
}