{
  "type": "Feature",
  "properties": {
    "addr:full":"S\u00f8ndergade 33 Karise Danmark 4653",
    "addr:housenumber":"33",
    "addr:postcode":"4653",
    "addr:street":"Sondergade",
    "iso:country":"DK",
    "sg:address":"S\u00f8ndergade 33",
    "sg:city":"Karise",
    "sg:classifiers":[
        {
            "category":"Food & Beverages",
            "subcategory":"Liquor & Beverages",
            "type":"Retail Goods"
        }
    ],
    "sg:phone":"+45 56 78 72 28",
    "sg:postcode":"4653",
    "sg:province":"Danmark",
    "sg:tags":[
        "vin"
    ],
    "wof:name":"Vinkunsten",
    "wof:placetype":"venue"
},
  "geometry": {"coordinates":[12.1981678009,55.3040466309],"type":"Point"}
}