{
  "type": "Feature",
  "properties": {
    "addr:full":"Reberbansgade 8 Aalborg Danmark 9000",
    "addr:housenumber":"8",
    "addr:postcode":"9000",
    "addr:street":"Reberbansgade",
    "iso:country":"DK",
    "sg:address":"Reberbansgade 8",
    "sg:city":"Aalborg",
    "sg:orig_category":"Pizzeriaer",
    "sg:phone":"+45 98 11 14 22",
    "sg:postcode":"9000",
    "sg:province":"Danmark",
    "wof:name":"Stavros Pizza",
    "wof:placetype":"venue"
},
  "geometry": {"coordinates":[9.9141130447,57.0494918823],"type":"Point"}
}