{
  "type": "Feature",
  "properties": {
    "addr:full":"Sdr. Stationsvej 6-10 Slagelse Danmark 4200",
    "addr:housenumber":"6-10",
    "addr:postcode":"4200",
    "addr:street":"Sdr. Stationsvej",
    "iso:country":"DK",
    "sg:address":"Sdr. Stationsvej 6-10",
    "sg:city":"Slagelse",
    "sg:orig_category":"Plejecentre",
    "sg:phone":"+45 58 56 12 93",
    "sg:postcode":"4200",
    "sg:province":"Danmark",
    "wof:name":"Plejecentret Alliancehaven",
    "wof:placetype":"venue"
},
  "geometry": {"coordinates":[11.3517999649,55.4067611694],"type":"Point"}
}