{
  "type": "Feature",
  "properties": {
    "addr:full":"Industrivej 15 Grindsted Danmark 7200",
    "addr:housenumber":"15",
    "addr:postcode":"7200",
    "addr:street":"Industrivej",
    "iso:country":"DK",
    "sg:address":"Industrivej 15",
    "sg:city":"Grindsted",
    "sg:orig_category":"Elektronik",
    "sg:phone":"+45 75 31 09 36",
    "sg:postcode":"7200",
    "sg:province":"Danmark",
    "wof:name":"LBJ Electronic",
    "wof:placetype":"venue"
},
  "geometry": {"coordinates":[9.0227127075,55.8156738281],"type":"Point"}
}