{
  "type": "Feature",
  "properties": {
    "addr:full":"H\u00f8jvangsalle 20 Horsens Danmark 8700",
    "addr:housenumber":"20",
    "addr:postcode":"8700",
    "addr:street":"Hojvangsalle",
    "iso:country":"DK",
    "sg:address":"H\u00f8jvangsalle 20",
    "sg:city":"Horsens",
    "sg:orig_category":"Kommunale folkeskoler",
    "sg:phone":"+45 75 64 44 33",
    "sg:postcode":"8700",
    "sg:province":"Danmark",
    "wof:name":"H\u00f8jvangskolen",
    "wof:placetype":"venue"
},
  "geometry": {"coordinates":[9.8568954468,55.8360939026],"type":"Point"}
}