{
  "type": "Feature",
  "properties": {
    "iso:country":"DK",
    "sg:address":"Torvet 11",
    "sg:city":"Nyk\u00f8bing",
    "sg:orig_category":"Bagere",
    "sg:phone":"+45 54 85 58 77",
    "sg:postcode":"4800",
    "sg:province":"Danmark",
    "wof:name":"Bj\u00f8rnebageren",
    "wof:placetype":"venue"
},
  "geometry": {"coordinates":[10.6905498505,59.8094596863],"type":"Point"}
}