{
  "type": "Feature",
  "properties": {
    "iso:country":"DK",
    "sg:address":"Store Gr\u00e5br\u00f8drestr\u00e6de 11",
    "sg:city":"Odense C",
    "sg:orig_category":"Videobutikker og -klubber",
    "sg:phone":"+45 66 19 05 33",
    "sg:postcode":"5000",
    "sg:province":"Danmark",
    "wof:name":"Videoshoppen",
    "wof:placetype":"venue"
},
  "geometry": {"coordinates":[10.3846979141,55.396282196],"type":"Point"}
}