{
  "type": "Feature",
  "properties": {
    "iso:country":"DK",
    "sg:address":"Nygade 19",
    "sg:city":"Silkeborg",
    "sg:orig_category":"Bogtrykkerier",
    "sg:phone":"+45 86 82 01 44",
    "sg:postcode":"8600",
    "sg:province":"Danmark",
    "wof:name":"Eksprestrykkeriet",
    "wof:placetype":"venue"
},
  "geometry": {"coordinates":[9.5478668213,56.1672363281],"type":"Point"}
}