{
  "type": "Feature",
  "properties": {
    "addr:full":"F\u00e6rgevej 34, Kragn\u00e6s Marstal Danmark 5960",
    "addr:housenumber":"34",
    "addr:postcode":"5960",
    "addr:street":"Faergevej;Kragnaes",
    "iso:country":"DK",
    "sg:address":"F\u00e6rgevej 34, Kragn\u00e6s",
    "sg:city":"Marstal",
    "sg:orig_category":"Murermestre",
    "sg:phone":"+45 62 53 22 62",
    "sg:postcode":"5960",
    "sg:province":"Danmark",
    "wof:name":"Elholm, John",
    "wof:placetype":"venue"
},
  "geometry": {"coordinates":[10.5212097168,54.8543815613],"type":"Point"}
}