{
  "type": "Feature",
  "properties": {
    "addr:full":"Fmd.: Torben M\u00f8lgaard, Roskildev\u00e6nget 36, 1.tv. Roskilde Danmark 4000",
    "addr:housenumber":"36",
    "addr:postcode":"1.tv;4000",
    "addr:street":"Roskildevaenget",
    "iso:country":"DK",
    "sg:address":"Fmd.: Torben M\u00f8lgaard, Roskildev\u00e6nget 36, 1.tv.",
    "sg:city":"Roskilde",
    "sg:orig_category":"Lejerforeninger",
    "sg:phone":"+45 46 36 52 70",
    "sg:postcode":"4000",
    "sg:province":"Danmark",
    "wof:name":"Lejerforeningen Roskildehave",
    "wof:placetype":"venue"
},
  "geometry": {"coordinates":[12.0909376144,55.6404838562],"type":"Point"}
}