{
  "type": "Feature",
  "properties": {
    "addr:full":"Engg\u00e5rdvej 15  Herning Danmark 7400",
    "addr:housenumber":"15",
    "addr:postcode":"7400",
    "addr:street":"Enggaardvej",
    "iso:country":"DK",
    "sg:address":"Engg\u00e5rdvej 15 ",
    "sg:city":"Herning",
    "sg:classifiers":[
        {
            "category":"Manufacturing",
            "subcategory":"Lumber",
            "type":"Manufacturing & Wholesale Goods"
        }
    ],
    "sg:phone":"+45 97 16 15 55",
    "sg:postcode":"7400",
    "sg:province":"Danmark",
    "sg:tags":[
        "wood"
    ],
    "wof:name":"HB TRAPPER OG ST\u00c5L A/S",
    "wof:placetype":"venue"
},
  "geometry": {"coordinates":[8.9122533798,56.1330947876],"type":"Point"}
}