{
  "type": "Feature",
  "properties": {
    "iso:country":"DK",
    "sg:address":"Seestvej 1, Seest",
    "sg:city":"Kolding",
    "sg:classifiers":[
        {
            "category":"Banks & Credit Unions",
            "subcategory":"Bank",
            "type":"Services"
        }
    ],
    "sg:phone":"+45 76 33 36 00",
    "sg:postcode":"6000",
    "sg:province":"Danmark",
    "sg:tags":[
        "banker"
    ],
    "wof:name":"BG Bank, Seest",
    "wof:placetype":"venue"
},
  "geometry": {"coordinates":[9.473395,55.486359],"type":"Point"}
}