{
  "type": "Feature",
  "properties": {
    "iso:country":"DK",
    "sg:address":"Jernbanevej 4",
    "sg:city":"Klemensker",
    "sg:orig_category":"Ungdomsklubber",
    "sg:phone":"+45 56 96 68 86",
    "sg:postcode":"3782",
    "sg:province":"Danmark",
    "wof:name":"Klemensker Fritidshus",
    "wof:placetype":"venue"
},
  "geometry": {"coordinates":[14.8074455261,55.1753501892],"type":"Point"}
}