{
  "type": "Feature",
  "properties": {
    "addr:full":"Planteskolevej 26, Holmstrup Odense SV Danmark 5250",
    "addr:housenumber":"26",
    "addr:postcode":"5250",
    "addr:street":"Planteskolevej;Holmstrup",
    "iso:country":"DK",
    "sg:address":"Planteskolevej 26, Holmstrup",
    "sg:city":"Odense SV",
    "sg:orig_category":"INGENI\u00c3\u02dcRER",
    "sg:phone":"+45 65 96 21 00",
    "sg:postcode":"5250",
    "sg:province":"Danmark",
    "wof:name":"FA elektronik",
    "wof:placetype":"venue"
},
  "geometry": {"coordinates":[10.3153953552,55.3362998962],"type":"Point"}
}