{
  "type": "Feature",
  "properties": {
    "addr:full":"v/ Egon Knudsen, Kirkegade 17 Bramming Danmark 6740",
    "addr:housenumber":"17",
    "addr:postcode":"6740",
    "addr:street":"Kirkegade",
    "iso:country":"DK",
    "sg:address":"v/ Egon Knudsen, Kirkegade 17",
    "sg:city":"Bramming",
    "sg:orig_category":"Antenneforeninger",
    "sg:phone":"+45 75 17 41 54",
    "sg:postcode":"6740",
    "sg:province":"Danmark",
    "wof:name":"Antenneforeningen Vest",
    "wof:placetype":"venue"
},
  "geometry": {"coordinates":[8.6974096298,55.4655303955],"type":"Point"}
}