{
  "type": "Feature",
  "properties": {
    "addr:full":"N\u00f8rregade 19 Vejen Danmark 6600",
    "addr:housenumber":"19",
    "addr:postcode":"6600",
    "addr:street":"Norregade",
    "iso:country":"DK",
    "sg:address":"N\u00f8rregade 19",
    "sg:city":"Vejen",
    "sg:orig_category":"Fotografer",
    "sg:phone":"+45 75 36 03 22",
    "sg:postcode":"6600",
    "sg:province":"Danmark",
    "wof:name":"Lindals Foto",
    "wof:placetype":"venue"
},
  "geometry": {"coordinates":[9.1383104324,55.4776077271],"type":"Point"}
}