{
  "type": "Feature",
  "properties": {
    "addr:full":"Falkevej 23 Viborg Danmark 8800",
    "addr:housenumber":"23",
    "addr:postcode":"8800",
    "addr:street":"Falkevej",
    "iso:country":"DK",
    "sg:address":"Falkevej 23",
    "sg:city":"Viborg",
    "sg:orig_category":"Autoforhandlere",
    "sg:phone":"+45 86 62 46 00",
    "sg:postcode":"8800",
    "sg:province":"Danmark",
    "sg:website":"www.soelvsten.dk",
    "wof:name":"S\u00f8lvsten Automobiler A/S",
    "wof:placetype":"venue"
},
  "geometry": {"coordinates":[9.3880605698,56.4445419312],"type":"Point"}
}