{
  "type": "Feature",
  "properties": {
    "addr:full":"Skolegade 50 Holsted Danmark 6670",
    "addr:housenumber":"50",
    "addr:postcode":"6670",
    "addr:street":"Skolegade",
    "iso:country":"DK",
    "sg:address":"Skolegade 50",
    "sg:city":"Holsted",
    "sg:orig_category":"Planteskoler",
    "sg:phone":"+45 75 39 22 99",
    "sg:postcode":"6670",
    "sg:province":"Danmark",
    "wof:name":"Nielsens Planteskole",
    "wof:placetype":"venue"
},
  "geometry": {"coordinates":[8.9097032547,55.513885498],"type":"Point"}
}