{
  "type": "Feature",
  "properties": {
    "addr:full":"Fmd.: Aage M\u00f8ller, Dybdevej 30, Bolbro Odense V Danmark 5200",
    "addr:housenumber":"30",
    "addr:postcode":"5200",
    "addr:street":"Aage Moller Dybdevej;Bolbro",
    "iso:country":"DK",
    "sg:address":"Fmd.: Aage M\u00f8ller, Dybdevej 30, Bolbro",
    "sg:city":"Odense V",
    "sg:orig_category":"\u00c3\u2020ldreorganisationer og klubber",
    "sg:phone":"+45 66 16 60 80",
    "sg:postcode":"5200",
    "sg:province":"Danmark",
    "wof:name":"Bolbro Seniorklub",
    "wof:placetype":"venue"
},
  "geometry": {"coordinates":[10.2629547119,55.4070854187],"type":"Point"}
}