{
  "type": "Feature",
  "properties": {
    "addr:full":"Boulevarden 58 Vejle Danmark 7100",
    "addr:housenumber":"58",
    "addr:postcode":"7100",
    "addr:street":"Boulevarden",
    "iso:country":"DK",
    "sg:address":"Boulevarden 58",
    "sg:city":"Vejle",
    "sg:orig_category":"Autoforhandlere",
    "sg:phone":"+45 75 82 60 00",
    "sg:postcode":"7100",
    "sg:province":"Danmark",
    "wof:name":"B\u00f8je & Br\u00f8chner A/S",
    "wof:placetype":"venue"
},
  "geometry": {"coordinates":[9.5222406387,55.7072372437],"type":"Point"}
}