{
  "type": "Feature",
  "properties": {
    "addr:full":"Elmevej 1 Skanderborg Danmark 8660",
    "addr:housenumber":"1",
    "addr:postcode":"8660",
    "addr:street":"Elmevej",
    "iso:country":"DK",
    "sg:address":"Elmevej 1",
    "sg:city":"Skanderborg",
    "sg:orig_category":"Forsikringer",
    "sg:phone":"+45 86 52 18 20",
    "sg:postcode":"8660",
    "sg:province":"Danmark",
    "wof:name":"Alm. Brand",
    "wof:placetype":"venue"
},
  "geometry": {"coordinates":[9.9482660294,56.0387573242],"type":"Point"}
}