{
  "type": "Feature",
  "properties": {
    "addr:full":"Vangvej 16, Klitm\u00f8ller Thisted Danmark 7700",
    "addr:housenumber":"16",
    "addr:postcode":"7700",
    "addr:street":"Vangvej;Klitmoller",
    "iso:country":"DK",
    "sg:address":"Vangvej 16, Klitm\u00f8ller",
    "sg:city":"Thisted",
    "sg:orig_category":"Campingpladser",
    "sg:phone":"+45 97 97 50 20",
    "sg:postcode":"7700",
    "sg:province":"Danmark",
    "sg:website":"www.home12.inet.tele.dk/klitcamp/",
    "wof:name":"Klitm\u00f8ller Camping & Motel",
    "wof:placetype":"venue"
},
  "geometry": {"coordinates":[8.6919784546,56.9556121826],"type":"Point"}
}