{
  "type": "Feature",
  "properties": {
    "iso:country":"DK",
    "sg:address":"Baneg\u00e5rdsgade 3",
    "sg:city":"Odder",
    "sg:classifiers":[
        {
            "category":"Restaurant",
            "type":"Food & Drink"
        }
    ],
    "sg:phone":"+45 86 54 01 86",
    "sg:postcode":"8300",
    "sg:province":"Danmark",
    "wof:name":"Baneg\u00e5rdsrestaurationen",
    "wof:placetype":"venue"
},
  "geometry": {"coordinates":[10.1498603821,55.9722251892],"type":"Point"}
}