{
  "type": "Feature",
  "properties": {
    "addr:full":"Rosenlunden 17 Odense C Danmark 5000",
    "addr:housenumber":"17",
    "addr:postcode":"5000",
    "addr:street":"Rosenlunden",
    "iso:country":"DK",
    "sg:address":"Rosenlunden 17",
    "sg:city":"Odense C",
    "sg:orig_category":"Forlag",
    "sg:phone":"+45 66 14 83 31",
    "sg:postcode":"5000",
    "sg:province":"Danmark",
    "wof:name":"Morgenstjernen",
    "wof:placetype":"venue"
},
  "geometry": {"coordinates":[10.3936462402,55.3900909424],"type":"Point"}
}