{
  "type": "Feature",
  "properties": {
    "addr:full":"Torvegade 26 Esbjerg Danmark 6700",
    "addr:housenumber":"26",
    "addr:postcode":"6700",
    "addr:street":"Torvegade",
    "iso:country":"DK",
    "sg:address":"Torvegade 26",
    "sg:city":"Esbjerg",
    "sg:classifiers":[
        {
            "category":"Home & Garden",
            "subcategory":"Home Furnishings",
            "type":"Retail Goods"
        }
    ],
    "sg:phone":"+45 75 13 44 12",
    "sg:postcode":"6700",
    "sg:province":"Danmark",
    "sg:tags":[
        "gardiner"
    ],
    "wof:name":"Fjord Gardin Fagmanden",
    "wof:placetype":"venue"
},
  "geometry": {"coordinates":[8.4521770477,55.4678115845],"type":"Point"}
}