{
  "type": "Feature",
  "properties": {
    "addr:full":"Tejnvej 8 Allinge Danmark 3770",
    "addr:housenumber":"8",
    "addr:postcode":"3770",
    "addr:street":"Tejnvej",
    "iso:country":"DK",
    "sg:address":"Tejnvej 8",
    "sg:city":"Allinge",
    "sg:orig_category":"Fodterapeuter",
    "sg:phone":"+45 56 48 23 55",
    "sg:postcode":"3770",
    "sg:province":"Danmark",
    "wof:name":"Irene Steinlein",
    "wof:placetype":"venue"
},
  "geometry": {"coordinates":[14.800866127,55.270740509],"type":"Point"}
}