{
  "type": "Feature",
  "properties": {
    "addr:full":"v/ Mogens Sigerstr\u00f8m, Nymarksvej 84 Nyborg Danmark 5800",
    "addr:housenumber":"84",
    "addr:postcode":"5800",
    "addr:street":"Nymarksvej",
    "iso:country":"DK",
    "sg:address":"v/ Mogens Sigerstr\u00f8m, Nymarksvej 84",
    "sg:city":"Nyborg",
    "sg:orig_category":"Musik og sang",
    "sg:phone":"+45 65 31 61 51",
    "sg:postcode":"5800",
    "sg:province":"Danmark",
    "wof:name":"Tyrolerorkestret fra Nyborg",
    "wof:placetype":"venue"
},
  "geometry": {"coordinates":[10.7923851013,55.3111801147],"type":"Point"}
}