{
  "type": "Feature",
  "properties": {
    "addr:full":"Vordingborgvej 204 Tureby Danmark 4682",
    "addr:housenumber":"204",
    "addr:postcode":"4682",
    "addr:street":"Vordingborgvej",
    "iso:country":"DK",
    "sg:address":"Vordingborgvej 204",
    "sg:city":"Tureby",
    "sg:orig_category":"Grillbarer",
    "sg:phone":"+45 56 28 34 44",
    "sg:postcode":"4682",
    "sg:province":"Danmark",
    "wof:name":"Lilleskov, Miniteriet",
    "wof:placetype":"venue"
},
  "geometry": {"coordinates":[12.118229866,55.3967094421],"type":"Point"}
}