{
  "type": "Feature",
  "properties": {
    "iso:country":"DK",
    "sg:address":"Tinkerup Strandvej 32",
    "sg:city":"Gilleleje",
    "sg:orig_category":"Sommerhusudlejning",
    "sg:phone":"+45 48 35 57 76",
    "sg:postcode":"3250",
    "sg:province":"Danmark",
    "wof:name":"DanCenter Nordsj\u00e6lland",
    "wof:placetype":"venue"
},
  "geometry": {"coordinates":[12.2606201172,56.1234397888],"type":"Point"}
}