{
  "type": "Feature",
  "properties": {
    "addr:full":"Skt. Ann\u00e6 Plads 16 K\u00f8benhavn Danmark 1250",
    "addr:housenumber":"16;1250",
    "addr:street":"Skt. Annae Plads",
    "iso:country":"DK",
    "sg:address":"Skt. Ann\u00e6 Plads 16",
    "sg:city":"K\u00f8benhavn",
    "sg:orig_category":"Faglige organisationer og -foreninger",
    "sg:phone":"+45 35 36 49 24",
    "sg:postcode":"1250",
    "sg:province":"Danmark",
    "wof:name":"K\u00f8benhavns Kommunale Maskinmesterforening",
    "wof:placetype":"venue"
},
  "geometry": {"coordinates":[76.3070983887,14.277130127],"type":"Point"}
}