{
  "type": "Feature",
  "properties": {
    "addr:full":"Bornholmsvej 6 Slagelse Danmark 4200",
    "addr:housenumber":"6",
    "addr:postcode":"4200",
    "addr:street":"Bornholmsvej",
    "iso:country":"DK",
    "sg:address":"Bornholmsvej 6",
    "sg:city":"Slagelse",
    "sg:orig_category":"Telte",
    "sg:phone":"+45 58 50 61 51",
    "sg:postcode":"4200",
    "sg:province":"Danmark",
    "sg:website":"www.showtech.dk",
    "wof:name":"ShowTech",
    "wof:placetype":"venue"
},
  "geometry": {"coordinates":[11.3412733078,55.395236969],"type":"Point"}
}