{
  "type": "Feature",
  "properties": {
    "iso:country":"DK",
    "sg:address":"Torvegade 1",
    "sg:city":"Randers",
    "sg:orig_category":"Bandagister",
    "sg:phone":"+45 86 42 62 62",
    "sg:postcode":"8900",
    "sg:province":"Danmark",
    "wof:name":"M\u00e6rsk-Andersens Eftf. A/S, C.",
    "wof:placetype":"venue"
},
  "geometry": {"coordinates":[10.036876,56.460514],"type":"Point"}
}