{
  "type": "Feature",
  "properties": {
    "iso:country":"DK",
    "sg:address":"Lilleh\u00f8jvej 15 ",
    "sg:city":"Silkeborg",
    "sg:classifiers":[
        {
            "category":"Autos & Motor Vehicles",
            "subcategory":"Automobile Sales",
            "type":"Retail Goods"
        }
    ],
    "sg:phone":"+45 86 82 12 11",
    "sg:postcode":"8600",
    "sg:province":"Danmark",
    "sg:tags":[
        "industrial"
    ],
    "wof:name":"J HVIDTVED LARSEN A/S",
    "wof:placetype":"venue"
},
  "geometry": {"coordinates":[9.5698003769,56.1886520386],"type":"Point"}
}