{
  "type": "Feature",
  "properties": {
    "addr:full":"Vemmedrupvej 195, Vemmedrup Bj\u00e6verskov Danmark 4632",
    "addr:housenumber":"195",
    "addr:postcode":"4632",
    "addr:street":"Vemmedrupvej",
    "iso:country":"DK",
    "sg:address":"Vemmedrupvej 195, Vemmedrup",
    "sg:city":"Bj\u00e6verskov",
    "sg:orig_category":"Elektronik",
    "sg:phone":"+45 56 87 10 16",
    "sg:postcode":"4632",
    "sg:province":"Danmark",
    "wof:name":"CMK Elektronik",
    "wof:placetype":"venue"
},
  "geometry": {"coordinates":[12.032699585,55.461265564],"type":"Point"}
}