{
  "type": "Feature",
  "properties": {
    "addr:full":"Skelvej 1 A Frederikssund Danmark 3600",
    "addr:housenumber":"1 a",
    "addr:postcode":"3600",
    "addr:street":"Skelvej",
    "iso:country":"DK",
    "sg:address":"Skelvej 1 A",
    "sg:city":"Frederikssund",
    "sg:orig_category":"Alternativ behandling",
    "sg:phone":"+45 47 31 14 34",
    "sg:postcode":"3600",
    "sg:province":"Danmark",
    "sg:website":"www.sitecenter.dk/repstock",
    "wof:name":"Repstock, Bente Andersen",
    "wof:placetype":"venue"
},
  "geometry": {"coordinates":[12.0723733902,55.8316726685],"type":"Point"}
}