{
  "type": "Feature",
  "properties": {
    "addr:full":"v/ Kell Raaschou, Sj\u00e6l\u00f8r Boulevard 57 K\u00f8benhavn SV Danmark 2450",
    "addr:housenumber":"57",
    "addr:postcode":"2450",
    "addr:street":"Boulevard",
    "iso:country":"DK",
    "sg:address":"v/ Kell Raaschou, Sj\u00e6l\u00f8r Boulevard 57",
    "sg:city":"K\u00f8benhavn SV",
    "sg:orig_category":"Grundejerforeninger",
    "sg:postcode":"2450",
    "sg:province":"Danmark",
    "wof:name":"Vesterg\u00e5rd Grundejerforening",
    "wof:placetype":"venue"
},
  "geometry": {"coordinates":[-88.90352630620001,38.4917907715],"type":"Point"}
}