{
  "type": "Feature",
  "properties": {
    "addr:full":"Emborgvej 173 Skanderborg Danmark 8660",
    "addr:housenumber":"173",
    "addr:postcode":"8660",
    "addr:street":"Emborgvej",
    "iso:country":"DK",
    "sg:address":"Emborgvej 173",
    "sg:city":"Skanderborg",
    "sg:orig_category":"Autoreparation og -service",
    "sg:phone":"+45 86 57 72 19",
    "sg:postcode":"8660",
    "sg:province":"Danmark",
    "wof:name":"Alken Gl. Smedie",
    "wof:placetype":"venue"
},
  "geometry": {"coordinates":[9.8653802872,56.0555801392],"type":"Point"}
}