{
  "type": "Feature",
  "properties": {
    "addr:full":"Snerlevej 22 Stoholm Danmark 7850",
    "addr:housenumber":"22",
    "addr:postcode":"7850",
    "addr:street":"Snerlevej",
    "iso:country":"DK",
    "sg:address":"Snerlevej 22",
    "sg:city":"Stoholm",
    "sg:orig_category":"Vinduespolering",
    "sg:phone":"+45 97 54 19 81",
    "sg:postcode":"7850",
    "sg:province":"Danmark",
    "wof:name":"J.T. Vinduespolering",
    "wof:placetype":"venue"
},
  "geometry": {"coordinates":[9.1350946426,56.4891586304],"type":"Point"}
}