{
  "type": "Feature",
  "properties": {
    "iso:country":"DK",
    "sg:address":"Hyrdestr\u00e6de 1",
    "sg:city":"Kolding",
    "sg:orig_category":"Tandteknikere, Kliniske",
    "sg:phone":"+45 75 52 42 16",
    "sg:postcode":"6000",
    "sg:province":"Danmark",
    "wof:name":"Eva J\u00f8rgensen",
    "wof:placetype":"venue"
},
  "geometry": {"coordinates":[9.4733953476,55.4863586426],"type":"Point"}
}