{
  "type": "Feature",
  "properties": {
    "addr:full":"Skibsbyggerkaj 4 Hirtshals Danmark 9850",
    "addr:housenumber":"4",
    "addr:postcode":"9850",
    "addr:street":"Skibsbyggerkaj",
    "iso:country":"DK",
    "sg:address":"Skibsbyggerkaj 4",
    "sg:city":"Hirtshals",
    "sg:orig_category":"Hydraulik",
    "sg:phone":"+45 98 94 59 97",
    "sg:postcode":"9850",
    "sg:province":"Danmark",
    "wof:name":"Skibsservice",
    "wof:placetype":"venue"
},
  "geometry": {"coordinates":[9.9591798782,57.5931053162],"type":"Point"}
}