{
  "type": "Feature",
  "properties": {
    "iso:country":"DK",
    "sg:address":"Kalvebod Brygge 59, Butik 245",
    "sg:city":"K\u00f8benhavn",
    "sg:orig_category":"Sportsartikler",
    "sg:phone":"+45 33 11 99 00",
    "sg:postcode":"1560",
    "sg:province":"Danmark",
    "wof:name":"Sportmaster",
    "wof:placetype":"venue"
},
  "geometry": {"coordinates":[12.5678701401,55.6656112671],"type":"Point"}
}