{
  "type": "Feature",
  "properties": {
    "addr:full":"Fmd.: Hanne Andersen, Gl.Hovedvej 76, Gr\u00f8nnemose Aarup Danmark 5560",
    "addr:housenumber":"76",
    "addr:postcode":"5560",
    "addr:street":"Gl.Hovedvej",
    "iso:country":"DK",
    "sg:address":"Fmd.: Hanne Andersen, Gl.Hovedvej 76, Gr\u00f8nnemose",
    "sg:city":"Aarup",
    "sg:orig_category":"Spejderkorps",
    "sg:phone":"+45 64 88 14 80",
    "sg:postcode":"5560",
    "sg:province":"Danmark",
    "wof:name":"FDF R\u00f8rup",
    "wof:placetype":"venue"
},
  "geometry": {"coordinates":[10.0490245819,55.3808059692],"type":"Point"}
}