{
  "type": "Feature",
  "properties": {
    "addr:full":"S\u00f8ndervangs Alle 40 Viby Danmark 8260",
    "addr:housenumber":"40",
    "addr:postcode":"8260",
    "addr:street":"Sondervangs Alle",
    "iso:country":"DK",
    "sg:address":"S\u00f8ndervangs Alle 40",
    "sg:city":"Viby",
    "sg:orig_category":"Kommunale folkeskoler",
    "sg:phone":"+45 86 29 09 11",
    "sg:postcode":"8260",
    "sg:province":"Danmark",
    "sg:website":"www.soendervangskolen.dk",
    "wof:name":"S\u00f8ndervangskolen",
    "wof:placetype":"venue"
},
  "geometry": {"coordinates":[10.1497020721,56.1111831665],"type":"Point"}
}