{
  "type": "Feature",
  "properties": {
    "addr:full":"Hobro Idr\u00e6tscenter, Amerikavej 22 Hobro Danmark 9500",
    "addr:housenumber":"22",
    "addr:postcode":"9500",
    "addr:street":"Amerikavej",
    "iso:country":"DK",
    "sg:address":"Hobro Idr\u00e6tscenter, Amerikavej 22",
    "sg:city":"Hobro",
    "sg:orig_category":"Diners transportables",
    "sg:phone":"+45 98 51 19 50",
    "sg:postcode":"9500",
    "sg:province":"Danmark",
    "wof:name":"Cafeteriet",
    "wof:placetype":"venue"
},
  "geometry": {"coordinates":[9.7946596146,56.6382789612],"type":"Point"}
}