{
  "type": "Feature",
  "properties": {
    "iso:country":"DK",
    "sg:address":"v/ Lokalomr\u00e5de \u00d8st, Prinsensvej 10",
    "sg:city":"Ringsted",
    "sg:orig_category":"\u00c3\u2020ldreorganisationer og klubber",
    "sg:phone":"+45 57 61 20 61",
    "sg:postcode":"4100",
    "sg:province":"Danmark",
    "wof:name":"Pensionistforeningen \u00d8st",
    "wof:placetype":"venue"
},
  "geometry": {"coordinates":[11.7875862122,55.4458961487],"type":"Point"}
}