{
  "type": "Feature",
  "properties": {
    "iso:country":"DK",
    "sg:address":"M\u00f8llergade 89",
    "sg:city":"Svendborg",
    "sg:orig_category":"Vaskerier",
    "sg:phone":"+45 30 63 21 56",
    "sg:postcode":"5700",
    "sg:province":"Danmark",
    "wof:name":"M\u00f8llergades M\u00f8ntvask",
    "wof:placetype":"venue"
},
  "geometry": {"coordinates":[10.6131038666,55.0639686584],"type":"Point"}
}