{
  "type": "Feature",
  "properties": {
    "addr:full":"Oxford Alle 26, st. K\u00f8benhavn S Danmark 2300",
    "addr:housenumber":"26",
    "addr:postcode":"2300",
    "addr:street":"Oxford Alle;Danmark",
    "iso:country":"DK",
    "sg:address":"Oxford Alle 26, st.",
    "sg:city":"K\u00f8benhavn S",
    "sg:orig_category":"Ejendomshandel",
    "sg:phone":"+45 32 58 51 61",
    "sg:postcode":"2300",
    "sg:province":"Danmark",
    "wof:name":"L.S.D.'s Ejendomsm\u00e6glerfirma",
    "wof:placetype":"venue"
},
  "geometry": {"coordinates":[-78.1299133301,36.7267417908],"type":"Point"}
}