{
  "type": "Feature",
  "properties": {
    "addr:full":"Vigerslev Alle 122 Valby Danmark 2500",
    "addr:housenumber":"122",
    "addr:postcode":"2500",
    "addr:street":"Vigerslev Alle",
    "iso:country":"DK",
    "sg:address":"Vigerslev Alle 122",
    "sg:city":"Valby",
    "sg:orig_category":"Pizzeriaer",
    "sg:phone":"+45 36 16 31 30",
    "sg:postcode":"2500",
    "sg:province":"Danmark",
    "wof:name":"Pappa's Pizza",
    "wof:placetype":"venue"
},
  "geometry": {"coordinates":[12.5052309036,55.6610946655],"type":"Point"}
}