{
  "type": "Feature",
  "properties": {
    "addr:full":"Skrejrupvej 2, Skrejrup R\u00f8nde Danmark 8410",
    "addr:housenumber":"2",
    "addr:postcode":"8410",
    "addr:street":"Skrejrupvej;Ronde Danmark",
    "iso:country":"DK",
    "sg:address":"Skrejrupvej 2, Skrejrup",
    "sg:city":"R\u00f8nde",
    "sg:orig_category":"Faglige organisationer og foreninger",
    "sg:phone":"+45 86 37 13 99",
    "sg:postcode":"8410",
    "sg:province":"Danmark",
    "wof:name":"Syddjurslands Husmandsforening",
    "wof:placetype":"venue"
},
  "geometry": {"coordinates":[10.4288892746,56.295917511],"type":"Point"}
}