{
  "type": "Feature",
  "properties": {
    "addr:full":"Havnebyvej 114, Kongsmark R\u00f8m\u00f8 Danmark 6792",
    "addr:housenumber":"114",
    "addr:postcode":"6792",
    "addr:street":"Havnebyvej",
    "iso:country":"DK",
    "sg:address":"Havnebyvej 114, Kongsmark",
    "sg:city":"R\u00f8m\u00f8",
    "sg:orig_category":"Genbrugspladser",
    "sg:phone":"+45 74 75 56 22",
    "sg:postcode":"6792",
    "sg:province":"Danmark",
    "wof:name":"Genbrugspladsen p\u00e5 R\u00f8m\u00f8",
    "wof:placetype":"venue"
},
  "geometry": {"coordinates":[8.5544652939,55.0871963501],"type":"Point"}
}