{
  "type": "Feature",
  "properties": {
    "addr:full":"Danmarksgade 50 Fredericia Danmark 7000",
    "addr:housenumber":"50",
    "addr:postcode":"7000",
    "addr:street":"Danmarksgade",
    "iso:country":"DK",
    "sg:address":"Danmarksgade 50",
    "sg:city":"Fredericia",
    "sg:orig_category":"Pizzeriaer",
    "sg:phone":"+45 75 92 99 66",
    "sg:postcode":"7000",
    "sg:province":"Danmark",
    "wof:name":"Halis Pizza og Kebab Expres",
    "wof:placetype":"venue"
},
  "geometry": {"coordinates":[9.7602386475,55.5669593811],"type":"Point"}
}