{
  "type": "Feature",
  "properties": {
    "addr:full":"Hindegade 5 K\u00f8benhavn Danmark 1303",
    "addr:housenumber":"5;1303",
    "addr:street":"Hindegade",
    "iso:country":"DK",
    "sg:address":"Hindegade 5",
    "sg:city":"K\u00f8benhavn",
    "sg:orig_category":"Boghandlere",
    "sg:phone":"+45 33 11 93 02",
    "sg:postcode":"1303",
    "sg:province":"Danmark",
    "wof:name":"Eurobooks",
    "wof:placetype":"venue"
},
  "geometry": {"coordinates":[12.589799881,55.6851005554],"type":"Point"}
}