{
  "type": "Feature",
  "properties": {
    "addr:full":"Fmd.: Erik Folkmann, \u00d8lsemaglevej 29 K\u00f8ge Danmark 4600",
    "addr:housenumber":"29",
    "addr:postcode":"4600",
    "addr:street":"Olsemaglevej",
    "iso:country":"DK",
    "sg:address":"Fmd.: Erik Folkmann, \u00d8lsemaglevej 29",
    "sg:city":"K\u00f8ge",
    "sg:orig_category":"Hobbybetonede foreninger",
    "sg:phone":"+45 56 65 42 27",
    "sg:postcode":"4600",
    "sg:province":"Danmark",
    "wof:name":"Rish\u00f8jhallens Venner",
    "wof:placetype":"venue"
},
  "geometry": {"coordinates":[36.5102996826,50.728099823],"type":"Point"}
}