{
  "type": "Feature",
  "properties": {
    "addr:full":"Nordre Ringvej 56 Kerteminde Danmark 5300",
    "addr:housenumber":"56",
    "addr:postcode":"5300",
    "addr:street":"Nordre Ringvej",
    "iso:country":"DK",
    "sg:address":"Nordre Ringvej 56",
    "sg:city":"Kerteminde",
    "sg:orig_category":"Autoforhandlere",
    "sg:phone":"+45 65 32 13 44",
    "sg:postcode":"5300",
    "sg:province":"Danmark",
    "wof:name":"Autohuset Kerteminde ApS",
    "wof:placetype":"venue"
},
  "geometry": {"coordinates":[10.6532840729,55.4566230774],"type":"Point"}
}