{
  "type": "Feature",
  "properties": {
    "iso:country":"DK",
    "sg:address":"Ledere: Hanna og Kresten Jensen, Tofteg\u00e5rdsv\u00e6nget 317",
    "sg:city":"Fredensborg",
    "sg:orig_category":"Kirkelige foreninger",
    "sg:phone":"+45 48 48 35 46",
    "sg:postcode":"3480",
    "sg:province":"Danmark",
    "wof:name":"Evangelisk B\u00f8rnemission",
    "wof:placetype":"venue"
},
  "geometry": {"coordinates":[12.4020547867,55.9782943726],"type":"Point"}
}