{
  "type": "Feature",
  "properties": {
    "addr:full":"Fmd.: Else Marie Hansen, Vesterhavsgade 26 Thybor\u00f8n Danmark 7680",
    "addr:housenumber":"26",
    "addr:postcode":"7680",
    "addr:street":"Vesterhavsgade",
    "iso:country":"DK",
    "sg:address":"Fmd.: Else Marie Hansen, Vesterhavsgade 26",
    "sg:city":"Thybor\u00f8n",
    "sg:orig_category":"Faglige organisationer og foreninger",
    "sg:phone":"+45 97 83 16 55",
    "sg:postcode":"7680",
    "sg:province":"Danmark",
    "wof:name":"Danmarks L\u00e6rerforening, Kreds 124",
    "wof:placetype":"venue"
},
  "geometry": {"coordinates":[-76.4168395996,37.452419281],"type":"Point"}
}