{
  "type": "Feature",
  "properties": {
    "addr:full":"H\u00f8je Gladsaxe Torv 2 B, 9. S\u00f8borg Danmark 2860",
    "addr:housenumber":"2 b 9",
    "addr:postcode":"2860",
    "addr:street":"Gladsaxe Torv",
    "iso:country":"DK",
    "sg:address":"H\u00f8je Gladsaxe Torv 2 B, 9.",
    "sg:city":"S\u00f8borg",
    "sg:orig_category":"Boligselskaber",
    "sg:phone":"+45 39 69 25 44",
    "sg:postcode":"2860",
    "sg:province":"Danmark",
    "wof:name":"Arbejdernes Boligselskab i Gladsaxe",
    "wof:placetype":"venue"
},
  "geometry": {"coordinates":[12.498497963,55.7300491333],"type":"Point"}
}