{
  "type": "Feature",
  "properties": {
    "addr:full":"V\u00e6rnedamsvej 3 A Frederiksberg Danmark 1819",
    "addr:housenumber":"3 a;1819",
    "addr:street":"Vaernedamsvej",
    "iso:country":"DK",
    "sg:address":"V\u00e6rnedamsvej 3 A",
    "sg:city":"Frederiksberg",
    "sg:orig_category":"Designere",
    "sg:phone":"+45 33 31 17 99",
    "sg:postcode":"1819",
    "sg:province":"Danmark",
    "wof:name":"B\u00f6\u00f6k, Mia",
    "wof:placetype":"venue"
},
  "geometry": {"coordinates":[12.5496616364,55.6737937927],"type":"Point"}
}