{
  "type": "Feature",
  "properties": {
    "addr:full":"Skovvej 8, Kragelund L\u00f8sning Danmark 8723",
    "addr:housenumber":"8",
    "addr:postcode":"8723",
    "addr:street":"Skovvej",
    "iso:country":"DK",
    "sg:address":"Skovvej 8, Kragelund",
    "sg:city":"L\u00f8sning",
    "sg:orig_category":"Fotografer",
    "sg:phone":"+45 21 62 03 19",
    "sg:postcode":"8723",
    "sg:province":"Danmark",
    "wof:name":"Adventure Photos",
    "wof:placetype":"venue"
},
  "geometry": {"coordinates":[9.7620611191,55.8105201721],"type":"Point"}
}