{
  "type": "Feature",
  "properties": {
    "addr:full":"\u00d8sterbo 9 Hejnsvig Danmark 7250",
    "addr:housenumber":"9",
    "addr:postcode":"7250",
    "addr:street":"Osterbo",
    "iso:country":"DK",
    "sg:address":"\u00d8sterbo 9",
    "sg:city":"Hejnsvig",
    "sg:orig_category":"Elektronik",
    "sg:phone":"+45 75 33 57 63",
    "sg:postcode":"7250",
    "sg:province":"Danmark",
    "wof:name":"Grej-shoppen",
    "wof:placetype":"venue"
},
  "geometry": {"coordinates":[8.9989995956,55.6979751587],"type":"Point"}
}