{
  "type": "Feature",
  "properties": {
    "addr:full":"Kordilgade 56 Kalundborg Danmark 4400",
    "addr:housenumber":"56",
    "addr:postcode":"4400",
    "addr:street":"Kordilgade",
    "iso:country":"DK",
    "sg:address":"Kordilgade 56",
    "sg:city":"Kalundborg",
    "sg:classifiers":[
        {
            "category":"Home & Garden",
            "subcategory":"Home Furnishings",
            "type":"Retail Goods"
        }
    ],
    "sg:phone":"+45 59 51 09 77",
    "sg:postcode":"4400",
    "sg:province":"Danmark",
    "sg:tags":[
        "gardiner"
    ],
    "wof:name":"\u00d8ens Farvehandel",
    "wof:placetype":"venue"
},
  "geometry": {"coordinates":[11.0926370621,55.6799545288],"type":"Point"}
}