{
  "type": "Feature",
  "properties": {
    "addr:full":"Korsgade 4 Aarup Danmark 5560",
    "addr:housenumber":"4",
    "addr:postcode":"5560",
    "addr:street":"Korsgade",
    "iso:country":"DK",
    "sg:address":"Korsgade 4",
    "sg:city":"Aarup",
    "sg:orig_category":"Revisorer",
    "sg:phone":"+45 64 43 20 01",
    "sg:postcode":"5560",
    "sg:province":"Danmark",
    "wof:name":"Andersen, Jens Ole",
    "wof:placetype":"venue"
},
  "geometry": {"coordinates":[10.0498638153,55.3809623718],"type":"Point"}
}