{
  "type": "Feature",
  "properties": {
    "addr:full":"Fmd.: Niels Peter Andersen, Fasanvej 57 Vandel Danmark 7184",
    "addr:housenumber":"57",
    "addr:postcode":"7184",
    "addr:street":"Fasanvej",
    "iso:country":"DK",
    "sg:address":"Fmd.: Niels Peter Andersen, Fasanvej 57",
    "sg:city":"Vandel",
    "sg:orig_category":"Borger- og beboerforeninger",
    "sg:phone":"+45 75 88 54 23",
    "sg:postcode":"7184",
    "sg:province":"Danmark",
    "wof:name":"Vandel Borgerforening",
    "wof:placetype":"venue"
},
  "geometry": {"coordinates":[9.2151947021,55.708984375],"type":"Point"}
}