{
  "type": "Feature",
  "properties": {
    "addr:full":"Hyldeg\u00e5rds Tv\u00e6rvej 43 Charlottenlund Danmark 2920",
    "addr:housenumber":"43",
    "addr:postcode":"2920",
    "addr:street":"Tvaervej",
    "iso:country":"DK",
    "sg:address":"Hyldeg\u00e5rds Tv\u00e6rvej 43",
    "sg:city":"Charlottenlund",
    "sg:orig_category":"Renserier",
    "sg:phone":"+45 44 48 09 75",
    "sg:postcode":"2920",
    "sg:province":"Danmark",
    "wof:name":"M\u00f8ntvask og Rens",
    "wof:placetype":"venue"
},
  "geometry": {"coordinates":[12.5802812576,55.7631416321],"type":"Point"}
}