{
  "type": "Feature",
  "properties": {
    "addr:full":"Kirke V\u00e6rl\u00f8sevej 18 C V\u00e6rl\u00f8se Danmark 3500",
    "addr:housenumber":"18 c",
    "addr:postcode":"3500",
    "addr:street":"Vaerlosevej",
    "iso:country":"DK",
    "sg:address":"Kirke V\u00e6rl\u00f8sevej 18 C",
    "sg:city":"V\u00e6rl\u00f8se",
    "sg:orig_category":"Fodterapeuter",
    "sg:phone":"+45 44 48 35 81",
    "sg:postcode":"3500",
    "sg:province":"Danmark",
    "wof:name":"Henriksen, Mona",
    "wof:placetype":"venue"
},
  "geometry": {"coordinates":[11.1919002533,62.5022697449],"type":"Point"}
}