{
  "type": "Feature",
  "properties": {
    "iso:country":"DK",
    "sg:address":"Store Gr\u00e5br\u00f8drestr\u00e6de 19",
    "sg:city":"Odense C",
    "sg:orig_category":"Reklamebureauer",
    "sg:phone":"+45 66 11 08 48",
    "sg:postcode":"5000",
    "sg:province":"Danmark",
    "wof:name":"Id\u00e9 Bureauet Reklame og Marketing A/S",
    "wof:placetype":"venue"
},
  "geometry": {"coordinates":[10.3842773438,55.3969078064],"type":"Point"}
}