{
  "type": "Feature",
  "properties": {
    "iso:country":"DK",
    "sg:address":"Frederik IX's Plads 3",
    "sg:city":"Fars\u00f8",
    "sg:orig_category":"Biblioteker",
    "sg:phone":"+45 96 49 22 90",
    "sg:postcode":"9640",
    "sg:province":"Danmark",
    "wof:name":"Fars\u00f8 Bibliotek",
    "wof:placetype":"venue"
},
  "geometry": {"coordinates":[-109.448318,42.106236],"type":"Point"}
}