{
  "type": "Feature",
  "properties": {
    "addr:full":"Leder: Louise Sahl Nielsen, Algade 3, 2. Ringk\u00f8bing Danmark 6950",
    "addr:housenumber":"3 2",
    "addr:postcode":"6950",
    "addr:street":"Algade",
    "iso:country":"DK",
    "sg:address":"Leder: Louise Sahl Nielsen, Algade 3, 2.",
    "sg:city":"Ringk\u00f8bing",
    "sg:orig_category":"Ungdomsklubber",
    "sg:phone":"+45 97 32 37 57",
    "sg:postcode":"6950",
    "sg:province":"Danmark",
    "wof:name":"Rindum Ungdomsklub",
    "wof:placetype":"venue"
},
  "geometry": {"coordinates":[-114.0767440796,46.4432487488],"type":"Point"}
}