{
  "type": "Feature",
  "properties": {
    "addr:full":"Halmtorvet 1 K\u00f8benhavn Danmark 1700",
    "addr:housenumber":"1",
    "addr:postcode":"1700",
    "addr:street":"Halmtorvet",
    "iso:country":"DK",
    "sg:address":"Halmtorvet 1",
    "sg:city":"K\u00f8benhavn",
    "sg:classifiers":[
        {
            "category":"Restaurant",
            "type":"Food & Drink"
        }
    ],
    "sg:phone":"+45 33 31 08 53",
    "sg:postcode":"1700",
    "sg:province":"Danmark",
    "wof:name":"Caf\u00e9 Sj\u00e6lland",
    "wof:placetype":"venue"
},
  "geometry": {"coordinates":[12.5607004166,55.6691017151],"type":"Point"}
}