{
  "type": "Feature",
  "properties": {
    "addr:full":"Idr\u00e6tsvej 14, Skelund Hadsund Danmark 9560",
    "addr:housenumber":"14",
    "addr:postcode":"9560",
    "addr:street":"Idraetsvej;Skelund",
    "iso:country":"DK",
    "sg:address":"Idr\u00e6tsvej 14, Skelund",
    "sg:city":"Hadsund",
    "sg:orig_category":"Korn og foderstoffer",
    "sg:phone":"+45 98 58 54 00",
    "sg:postcode":"9560",
    "sg:province":"Danmark",
    "wof:name":"Hedegaard Skelund",
    "wof:placetype":"venue"
},
  "geometry": {"coordinates":[10.115904808,56.7150764465],"type":"Point"}
}