{
  "type": "Feature",
  "properties": {
    "addr:full":"Tinglevvej 18 Gentofte Danmark 2820",
    "addr:housenumber":"18",
    "addr:postcode":"2820",
    "addr:street":"Tinglevvej",
    "iso:country":"DK",
    "sg:address":"Tinglevvej 18",
    "sg:city":"Gentofte",
    "sg:orig_category":"Malermestre",
    "sg:phone":"+45 39 65 38 76",
    "sg:postcode":"2820",
    "sg:province":"Danmark",
    "wof:name":"S\u00f8rensen, Michael",
    "wof:placetype":"venue"
},
  "geometry": {"coordinates":[12.5316848755,55.7636489868],"type":"Point"}
}