{
  "type": "Feature",
  "properties": {
    "addr:full":"Fmd.: Chr. Schmidt, Agervej 11 B, Borris Skjern Danmark 6900",
    "addr:housenumber":"11 b",
    "addr:postcode":"6900",
    "addr:street":"Agervej;Borris",
    "iso:country":"DK",
    "sg:address":"Fmd.: Chr. Schmidt, Agervej 11 B, Borris",
    "sg:city":"Skjern",
    "sg:orig_category":"Andelsboligforeninger",
    "sg:phone":"+45 97 36 61 17",
    "sg:postcode":"6900",
    "sg:province":"Danmark",
    "wof:name":"Agerleddet Andelsboligforening, Borris",
    "wof:placetype":"venue"
},
  "geometry": {"coordinates":[8.492972374,55.9485740662],"type":"Point"}
}