{
  "type": "Feature",
  "properties": {
    "addr:full":"Vonsb\u00e6kvej 84 Haderslev Danmark 6100",
    "addr:housenumber":"84",
    "addr:postcode":"6100",
    "addr:street":"Vonsbaekvej",
    "iso:country":"DK",
    "sg:address":"Vonsb\u00e6kvej 84",
    "sg:city":"Haderslev",
    "sg:orig_category":"Puljeinstitutioner",
    "sg:phone":"+45 74 57 91 19",
    "sg:postcode":"6100",
    "sg:province":"Danmark",
    "wof:name":"Vonsb\u00e6k B\u00f8rnehus",
    "wof:placetype":"venue"
},
  "geometry": {"coordinates":[9.6173057556,55.2914009094],"type":"Point"}
}