{
  "type": "Feature",
  "properties": {
    "addr:full":"v/ B. Kammersgaard, \u00d8stergade 8 Padborg Danmark 6330",
    "addr:housenumber":"8",
    "addr:postcode":"6330",
    "addr:street":"Ostergade",
    "iso:country":"DK",
    "sg:address":"v/ B. Kammersgaard, \u00d8stergade 8",
    "sg:city":"Padborg",
    "sg:orig_category":"Hobbybetonede foreninger",
    "sg:phone":"+45 74 67 37 66",
    "sg:postcode":"6330",
    "sg:province":"Danmark",
    "wof:name":"Radioklubben Cuba",
    "wof:placetype":"venue"
},
  "geometry": {"coordinates":[9.3618345261,54.8222312927],"type":"Point"}
}