{
  "type": "Feature",
  "properties": {
    "addr:full":"Skanseparken 71 Ebeltoft Danmark 8400",
    "addr:housenumber":"71",
    "addr:postcode":"8400",
    "addr:street":"Skanseparken",
    "iso:country":"DK",
    "sg:address":"Skanseparken 71",
    "sg:city":"Ebeltoft",
    "sg:orig_category":"Boligselskaber",
    "sg:phone":"+45 86 34 52 33",
    "sg:postcode":"8400",
    "sg:province":"Danmark",
    "wof:name":"Ebeltoft Boligselskab",
    "wof:placetype":"venue"
},
  "geometry": {"coordinates":[10.6783428192,56.1924362183],"type":"Point"}
}