{
  "type": "Feature",
  "properties": {
    "iso:country":"DK",
    "sg:address":"v/ Kurt Jensen, Sandg\u00e5rdsvej 38",
    "sg:city":"Tarm",
    "sg:orig_category":"Borger- og beboerforeninger",
    "sg:phone":"+45 97 37 22 83",
    "sg:postcode":"6880",
    "sg:province":"Danmark",
    "wof:name":"Sandparken",
    "wof:placetype":"venue"
},
  "geometry": {"coordinates":[8.5200052261,55.9060554504],"type":"Point"}
}