{
  "type": "Feature",
  "properties": {
    "iso:country":"DK",
    "sg:address":"Holb\u00e6kvej 14",
    "sg:city":"Jyderup",
    "sg:orig_category":"Begravelsesforretninger",
    "sg:phone":"+45 59 27 50 07",
    "sg:postcode":"4450",
    "sg:province":"Danmark",
    "wof:name":"M\u00f8rk\u00f8v-Jyderup Begravelsesforretning",
    "wof:placetype":"venue"
},
  "geometry": {"coordinates":[11.402766,55.659973],"type":"Point"}
}