{
  "type": "Feature",
  "properties": {
    "addr:full":"Tofte-\u00c5sen 4 A, R\u00e5geleje Vejby Danmark 3210",
    "addr:housenumber":"4 a",
    "addr:postcode":"3210",
    "addr:street":"Tofte-Aasen;Raageleje",
    "iso:country":"DK",
    "sg:address":"Tofte-\u00c5sen 4 A, R\u00e5geleje",
    "sg:city":"Vejby",
    "sg:orig_category":"Malermestre",
    "sg:phone":"+45 48 71 75 87",
    "sg:postcode":"3210",
    "sg:province":"Danmark",
    "sg:website":"www.dahmhuse.dk",
    "wof:name":"Dahm Huse ApS",
    "wof:placetype":"venue"
},
  "geometry": {"coordinates":[12.1534852982,56.0930938721],"type":"Point"}
}