{
  "type": "Feature",
  "properties": {
    "iso:country":"DK",
    "sg:address":"Lundby Hovedgade 118",
    "sg:city":"Lundby",
    "sg:orig_category":"Kompost",
    "sg:phone":"+45 55 76 75 51",
    "sg:postcode":"4750",
    "sg:province":"Danmark",
    "wof:name":"Karlsen ApS, Henning",
    "wof:placetype":"venue"
},
  "geometry": {"coordinates":[11.8864793777,55.1112709045],"type":"Point"}
}