{
  "type": "Feature",
  "properties": {
    "addr:full":"B\u00e6kvej 11 Nakskov Danmark 4900",
    "addr:housenumber":"11",
    "addr:postcode":"4900",
    "addr:street":"Baekvej",
    "iso:country":"DK",
    "sg:address":"B\u00e6kvej 11",
    "sg:city":"Nakskov",
    "sg:orig_category":"Rideskoler",
    "sg:phone":"+45 54 92 05 88",
    "sg:postcode":"4900",
    "sg:province":"Danmark",
    "wof:name":"Damg\u00e5rd's Rideskole",
    "wof:placetype":"venue"
},
  "geometry": {"coordinates":[11.1676988602,54.865486145],"type":"Point"}
}