{
  "type": "Feature",
  "properties": {
    "addr:full":"Bjelkes Alle 16, Postboks 711 K\u00f8benhavn N Danmark 2200",
    "addr:housenumber":"16;711",
    "addr:postcode":"2200",
    "addr:street":"Bjelkes Alle;Kobenhavn N Danmark",
    "iso:country":"DK",
    "sg:address":"Bjelkes Alle 16, Postboks 711",
    "sg:city":"K\u00f8benhavn N",
    "sg:orig_category":"Advokater",
    "sg:phone":"+45 35 82 60 45",
    "sg:postcode":"2200",
    "sg:province":"Danmark",
    "sg:website":"www.Legatregistret.dk",
    "wof:name":"LegatRegistret",
    "wof:placetype":"venue"
},
  "geometry": {"coordinates":[-76.4168395996,37.452419281],"type":"Point"}
}