{
  "type": "Feature",
  "properties": {
    "iso:country":"DK",
    "sg:address":"Bygmestervej 2",
    "sg:city":"Ringe",
    "sg:orig_category":"Benzinstationer",
    "sg:phone":"+45 62 62 28 55",
    "sg:postcode":"5750",
    "sg:province":"Danmark",
    "wof:name":"Haahr Benzin Fyn A/S",
    "wof:placetype":"venue"
},
  "geometry": {"coordinates":[10.488483,55.2365],"type":"Point"}
}