{
  "type": "Feature",
  "properties": {
    "addr:full":"H. H. Seedorffs Str\u00e6de 9, 3. \u00c5rhus C Danmark 8000",
    "addr:housenumber":"9 3",
    "addr:postcode":"8000",
    "addr:street":"Straede",
    "iso:country":"DK",
    "sg:address":"H. H. Seedorffs Str\u00e6de 9, 3.",
    "sg:city":"\u00c5rhus C",
    "sg:orig_category":"Malermestre",
    "sg:phone":"+45 86 13 91 30",
    "sg:postcode":"8000",
    "sg:province":"Danmark",
    "wof:name":"Jensen, Morten Kj\u00e6r",
    "wof:placetype":"venue"
},
  "geometry": {"coordinates":[4.717400074,49.7588005066],"type":"Point"}
}