{
  "type": "Feature",
  "properties": {
    "iso:country":"DK",
    "sg:address":"Gilleleje Hovedgade 28",
    "sg:city":"Gilleleje",
    "sg:orig_category":"Cykler",
    "sg:phone":"+45 48 30 32 80",
    "sg:postcode":"3250",
    "sg:province":"Danmark",
    "sg:website":"www.belinda-cykler.dk",
    "wof:name":"Belinda Cykler",
    "wof:placetype":"venue"
},
  "geometry": {"coordinates":[12.3095121384,56.1230583191],"type":"Point"}
}