{
  "type": "Feature",
  "properties": {
    "addr:full":"Enghavevej 6, Lendum Sindal Danmark 9870",
    "addr:housenumber":"6",
    "addr:postcode":"9870",
    "addr:street":"Enghavevej",
    "iso:country":"DK",
    "sg:address":"Enghavevej 6, Lendum",
    "sg:city":"Sindal",
    "sg:orig_category":"Skolefritidsordninger",
    "sg:phone":"+45 98 47 34 42",
    "sg:postcode":"9870",
    "sg:province":"Danmark",
    "wof:name":"Lendum Skole SFO",
    "wof:placetype":"venue"
},
  "geometry": {"coordinates":[10.2032299042,57.470916748],"type":"Point"}
}