{
  "type": "Feature",
  "properties": {
    "addr:full":"Fmd.: Kirsten Astrup, Kl\u00f8vbakken 62 Outrup Danmark 6855",
    "addr:housenumber":"62",
    "addr:postcode":"6855",
    "addr:street":"Klovbakken",
    "iso:country":"DK",
    "sg:address":"Fmd.: Kirsten Astrup, Kl\u00f8vbakken 62",
    "sg:city":"Outrup",
    "sg:orig_category":"Musik og sang",
    "sg:phone":"+45 75 25 10 18",
    "sg:postcode":"6855",
    "sg:province":"Danmark",
    "wof:name":"Bl\u00e5bjerg Musikforening",
    "wof:placetype":"venue"
},
  "geometry": {"coordinates":[8.3423900604,55.7216491699],"type":"Point"}
}