{
  "type": "Feature",
  "properties": {
    "addr:full":"Skovvangen 42, Kolding Storcenter Kolding Danmark 6000",
    "addr:housenumber":"42",
    "addr:postcode":"6000",
    "addr:street":"Skovvangen;Storcenter",
    "iso:country":"DK",
    "sg:address":"Skovvangen 42, Kolding Storcenter",
    "sg:city":"Kolding",
    "sg:classifiers":[
        {
            "category":"Banks & Credit Unions",
            "subcategory":"Bank",
            "type":"Services"
        }
    ],
    "sg:phone":"+45 76 30 87 70",
    "sg:postcode":"6000",
    "sg:province":"Danmark",
    "sg:tags":[
        "banker"
    ],
    "wof:name":"BG Bank",
    "wof:placetype":"venue"
},
  "geometry": {"coordinates":[9.473395,55.486359],"type":"Point"}
}