{
  "type": "Feature",
  "properties": {
    "iso:country":"DK",
    "sg:address":"Gemsevej 19, Ejby",
    "sg:city":"Lille Skensved",
    "sg:orig_category":"Distriktsbiblioteker",
    "sg:phone":"+45 56 82 02 80",
    "sg:postcode":"4623",
    "sg:province":"Danmark",
    "wof:name":"Ejby Bibliotek",
    "wof:placetype":"venue"
},
  "geometry": {"coordinates":[12.0822563171,55.4889717102],"type":"Point"}
}