{
  "type": "Feature",
  "properties": {
    "iso:country":"DK",
    "sg:address":"Skippergade 2",
    "sg:city":"Svaneke",
    "sg:orig_category":"Aktivitetscentre",
    "sg:phone":"+45 56 49 73 72",
    "sg:postcode":"3740",
    "sg:province":"Danmark",
    "sg:website":"www.svanekegaarden.dk",
    "wof:name":"Svanekeg\u00e5rden",
    "wof:placetype":"venue"
},
  "geometry": {"coordinates":[15.1437397003,55.1371154785],"type":"Point"}
}