{
  "type": "Feature",
  "properties": {
    "addr:full":"Tingvej 16 Hornslet Danmark 8543",
    "addr:housenumber":"16",
    "addr:postcode":"8543",
    "addr:street":"Tingvej",
    "iso:country":"DK",
    "sg:address":"Tingvej 16",
    "sg:city":"Hornslet",
    "sg:classifiers":[
        {
            "category":"Communications",
            "type":"Services"
        }
    ],
    "sg:phone":"+45 86 99 41 83",
    "sg:postcode":"8543",
    "sg:province":"Danmark",
    "sg:tags":[
        "og",
        "tv",
        "radio"
    ],
    "sg:website":"www.cc-radio-foto.dk",
    "wof:name":"Hornslet Radio og Foto",
    "wof:placetype":"venue"
},
  "geometry": {"coordinates":[10.3170166016,56.3173103333],"type":"Point"}
}