{
  "type": "Feature",
  "properties": {
    "addr:full":"Jernbanegade 4 Br\u00f8rup Danmark 6650",
    "addr:housenumber":"4",
    "addr:postcode":"6650",
    "addr:street":"Jernbanegade",
    "iso:country":"DK",
    "sg:address":"Jernbanegade 4",
    "sg:city":"Br\u00f8rup",
    "sg:orig_category":"Malermestre",
    "sg:phone":"+45 75 38 16 37",
    "sg:postcode":"6650",
    "sg:province":"Danmark",
    "wof:name":"Jensen ApS, Malerfirma Finn",
    "wof:placetype":"venue"
},
  "geometry": {"coordinates":[9.0166873932,55.4832077026],"type":"Point"}
}