{
  "type": "Feature",
  "properties": {
    "addr:full":"Solsortvej 111 Frederiksberg Danmark 2000",
    "addr:housenumber":"111",
    "addr:postcode":"2000",
    "addr:street":"Solsortvej",
    "iso:country":"DK",
    "sg:address":"Solsortvej 111",
    "sg:city":"Frederiksberg",
    "sg:classifiers":[
        {
            "category":"Professional",
            "subcategory":"Business Services",
            "type":"Services"
        }
    ],
    "sg:phone":"+45 38 86 37 47",
    "sg:postcode":"2000",
    "sg:province":"Danmark",
    "sg:tags":[
        "import",
        "vin"
    ],
    "sg:website":"www.adriatvinimport.dk",
    "wof:name":"Adriat Vinimport ApS",
    "wof:placetype":"venue"
},
  "geometry": {"coordinates":[12.5258750916,55.6938934326],"type":"Point"}
}