{
  "type": "Feature",
  "properties": {
    "addr:full":"Lyngvej 2 Aalborg Danmark 9000",
    "addr:housenumber":"2",
    "addr:postcode":"9000",
    "addr:street":"Lyngvej",
    "iso:country":"DK",
    "sg:address":"Lyngvej 2",
    "sg:city":"Aalborg",
    "sg:orig_category":"Non-Classified Establishments",
    "sg:phone":"+45 98 18 12 77",
    "sg:postcode":"9000",
    "sg:province":"Danmark",
    "wof:name":"Jyden Konfektion A/S",
    "wof:placetype":"venue"
},
  "geometry": {"coordinates":[9.8963747025,57.0236701965],"type":"Point"}
}