{
  "type": "Feature",
  "properties": {
    "addr:full":"Torvet 7 Frederikssund Danmark 3600",
    "addr:housenumber":"7",
    "addr:postcode":"3600",
    "addr:street":"Torvet",
    "iso:country":"DK",
    "sg:address":"Torvet 7",
    "sg:city":"Frederikssund",
    "sg:classifiers":[
        {
            "category":"Banks & Credit Unions",
            "subcategory":"Bank",
            "type":"Services"
        }
    ],
    "sg:phone":"+45 47 36 07 00",
    "sg:postcode":"3600",
    "sg:province":"Danmark",
    "sg:tags":[
        "banker"
    ],
    "sg:website":"www.lokalbanken.dk",
    "wof:name":"Lokalbanken",
    "wof:placetype":"venue"
},
  "geometry": {"coordinates":[12.0609073639,55.83959198],"type":"Point"}
}