{
  "type": "Feature",
  "properties": {
    "iso:country":"DK",
    "sg:address":"Torstedalle 2 C",
    "sg:city":"Horsens",
    "sg:orig_category":"Naturgas install. og -service",
    "sg:phone":"+45 75 64 71 11",
    "sg:postcode":"8700",
    "sg:province":"Danmark",
    "wof:name":"Nielsen VVS & Maskinservice A/S, Hans Orla",
    "wof:placetype":"venue"
},
  "geometry": {"coordinates":[9.8156299591,55.8515205383],"type":"Point"}
}