{
  "type": "Feature",
  "properties": {
    "addr:full":"Borgergade 6 Lang\u00e5 Danmark 8870",
    "addr:housenumber":"6",
    "addr:postcode":"8870",
    "addr:street":"Borgergade",
    "iso:country":"DK",
    "sg:address":"Borgergade 6",
    "sg:city":"Lang\u00e5",
    "sg:orig_category":"Varmeforsyning",
    "sg:phone":"+45 86 46 20 44",
    "sg:postcode":"8870",
    "sg:province":"Danmark",
    "wof:name":"Lang\u00e5 Varmev\u00e6rk og Lang\u00e5 Kraftvarmev\u00e6rk I/S",
    "wof:placetype":"venue"
},
  "geometry": {"coordinates":[9.8959445953,56.3919944763],"type":"Point"}
}