{
  "type": "Feature",
  "properties": {
    "addr:full":"Rosenvej 1, Als Hadsund Danmark 9560",
    "addr:housenumber":"1",
    "addr:postcode":"9560",
    "addr:street":"Rosenvej;Als",
    "iso:country":"DK",
    "sg:address":"Rosenvej 1, Als",
    "sg:city":"Hadsund",
    "sg:orig_category":"Skolefritidsordninger",
    "sg:phone":"+45 98 58 19 10",
    "sg:postcode":"9560",
    "sg:province":"Danmark",
    "wof:name":"Skolefritidsordningen Als Skole",
    "wof:placetype":"venue"
},
  "geometry": {"coordinates":[10.115904808,56.7150764465],"type":"Point"}
}