{
  "type": "Feature",
  "properties": {
    "addr:full":"Landevejen 41, S\u00f8nderho Fan\u00f8 Danmark 6720",
    "addr:housenumber":"41",
    "addr:postcode":"6720",
    "addr:street":"Landevejen",
    "iso:country":"DK",
    "sg:address":"Landevejen 41, S\u00f8nderho",
    "sg:city":"Fan\u00f8",
    "sg:orig_category":"Filialbiblioteker",
    "sg:phone":"+45 75 16 40 36",
    "sg:postcode":"6720",
    "sg:province":"Danmark",
    "wof:name":"S\u00f8nderho Bibliotek",
    "wof:placetype":"venue"
},
  "geometry": {"coordinates":[-119.1350784302,36.3733062744],"type":"Point"}
}