{
  "type": "Feature",
  "properties": {
    "addr:full":"Vik\u00e6r Toften 2 A Risskov Danmark 8240",
    "addr:housenumber":"2 a",
    "addr:postcode":"8240",
    "addr:street":"Vikaer Toften",
    "iso:country":"DK",
    "sg:address":"Vik\u00e6r Toften 2 A",
    "sg:city":"Risskov",
    "sg:orig_category":"Integrerede institutioner",
    "sg:phone":"+45 86 21 69 00",
    "sg:postcode":"8240",
    "sg:province":"Danmark",
    "wof:name":"Gadek\u00e6ret, Integreret Inst.",
    "wof:placetype":"venue"
},
  "geometry": {"coordinates":[10.2160778046,56.1942634583],"type":"Point"}
}