{
  "type": "Feature",
  "properties": {
    "addr:full":"Stenalderen 78, Fl\u00f8ng Hedehusene Danmark 2640",
    "addr:housenumber":"78",
    "addr:postcode":"2640",
    "addr:street":"Stenalderen;Flong",
    "iso:country":"DK",
    "sg:address":"Stenalderen 78, Fl\u00f8ng",
    "sg:city":"Hedehusene",
    "sg:orig_category":"Malermestre",
    "sg:phone":"+45 46 56 49 66",
    "sg:postcode":"2640",
    "sg:province":"Danmark",
    "wof:name":"Kalfner, Uffe",
    "wof:placetype":"venue"
},
  "geometry": {"coordinates":[12.1993551254,55.6496009827],"type":"Point"}
}