{
  "type": "Feature",
  "properties": {
    "addr:full":"Vesterhavsvej 25 Billum Danmark 6852",
    "addr:housenumber":"25",
    "addr:postcode":"6852",
    "addr:street":"Vesterhavsvej",
    "iso:country":"DK",
    "sg:address":"Vesterhavsvej 25",
    "sg:city":"Billum",
    "sg:orig_category":"HOTELS: OG MOTELLER",
    "sg:phone":"+45 75 25 82 00",
    "sg:postcode":"6852",
    "sg:province":"Danmark",
    "wof:name":"Billum Kro ApS",
    "wof:placetype":"venue"
},
  "geometry": {"coordinates":[8.3305664062,55.6175727844],"type":"Point"}
}