{
  "type": "Feature",
  "properties": {
    "iso:country":"DK",
    "sg:address":"\u00d8rritslev Gade 50",
    "sg:city":"Otterup",
    "sg:orig_category":"Kirker",
    "sg:postcode":"5450",
    "sg:province":"Danmark",
    "wof:name":"Skeby Kirke",
    "wof:placetype":"venue"
},
  "geometry": {"coordinates":[10.4328546524,55.5162811279],"type":"Point"}
}