{
  "type": "Feature",
  "properties": {
    "iso:country":"DK",
    "sg:address":"Slagterivej 18",
    "sg:city":"Grindsted",
    "sg:orig_category":"Blikkenslagere",
    "sg:phone":"+45 75 32 21 84",
    "sg:postcode":"7200",
    "sg:province":"Danmark",
    "wof:name":"S K Tagrender & R\u00f8r",
    "wof:placetype":"venue"
},
  "geometry": {"coordinates":[8.938072,55.760605],"type":"Point"}
}