{
  "type": "Feature",
  "properties": {
    "iso:country":"DK",
    "sg:address":"Slettebjergvej 13",
    "sg:city":"Ballerup",
    "sg:orig_category":"Hunde",
    "sg:phone":"+45 44 65 06 39",
    "sg:postcode":"2750",
    "sg:province":"Danmark",
    "wof:name":"Susans Hundesalon",
    "wof:placetype":"venue"
},
  "geometry": {"coordinates":[12.3686656952,55.7295265198],"type":"Point"}
}