{
  "type": "Feature",
  "properties": {
    "addr:full":"Nordre Fovrfeldvej 54 Esbjerg V Danmark 6710",
    "addr:housenumber":"54",
    "addr:postcode":"6710",
    "addr:street":"Nordre Fovrfeldvej",
    "iso:country":"DK",
    "sg:address":"Nordre Fovrfeldvej 54",
    "sg:city":"Esbjerg V",
    "sg:orig_category":"Elektro",
    "sg:phone":"+45 75 15 58 11",
    "sg:postcode":"6710",
    "sg:province":"Danmark",
    "wof:name":"Con - X Engineering A/S",
    "wof:placetype":"venue"
},
  "geometry": {"coordinates":[8.4145002365,55.5033378601],"type":"Point"}
}