{
  "type": "Feature",
  "properties": {
    "addr:full":"L\u00e6hegnet 95 Vestbjerg Danmark 9380",
    "addr:housenumber":"95",
    "addr:postcode":"9380",
    "addr:street":"Laehegnet",
    "iso:country":"DK",
    "sg:address":"L\u00e6hegnet 95",
    "sg:city":"Vestbjerg",
    "sg:orig_category":"Revisorer",
    "sg:phone":"+45 98 29 62 04",
    "sg:postcode":"9380",
    "sg:province":"Danmark",
    "wof:name":"Larsen, Find",
    "wof:placetype":"venue"
},
  "geometry": {"coordinates":[9.9589071274,57.1337432861],"type":"Point"}
}