{
  "type": "Feature",
  "properties": {
    "addr:full":"Rosenborggade 6 , 4. tv K\u00f8benhavn Danmark 1130",
    "addr:housenumber":"6 4 tv",
    "addr:postcode":"1130",
    "addr:street":"Rosenborggade",
    "iso:country":"DK",
    "sg:address":"Rosenborggade 6 , 4. tv",
    "sg:city":"K\u00f8benhavn",
    "sg:orig_category":"Fotografer",
    "sg:phone":"+45 26 18 36 20",
    "sg:postcode":"1130",
    "sg:province":"Danmark",
    "wof:name":"Dybdal, Martin",
    "wof:placetype":"venue"
},
  "geometry": {"coordinates":[12.5761995316,55.6829986572],"type":"Point"}
}