{
  "type": "Feature",
  "properties": {
    "addr:full":"Palmealle 2 Kolding Danmark 6000",
    "addr:housenumber":"2",
    "addr:postcode":"6000",
    "addr:street":"Palmealle",
    "iso:country":"DK",
    "sg:address":"Palmealle 2",
    "sg:city":"Kolding",
    "sg:orig_category":"Vuggestuer",
    "sg:phone":"+45 75 52 40 35",
    "sg:postcode":"6000",
    "sg:province":"Danmark",
    "wof:name":"Vuggestuen",
    "wof:placetype":"venue"
},
  "geometry": {"coordinates":[9.4555492401,55.501449585],"type":"Point"}
}