{
  "type": "Feature",
  "properties": {
    "addr:full":"Vadg\u00e5rdsvej 244 S\u00f8borg Danmark 2860",
    "addr:housenumber":"244",
    "addr:postcode":"2860",
    "addr:street":"Vadgaardsvej",
    "iso:country":"DK",
    "sg:address":"Vadg\u00e5rdsvej 244",
    "sg:city":"S\u00f8borg",
    "sg:orig_category":"Psykoanalyse",
    "sg:phone":"+45 39 66 40 50",
    "sg:postcode":"2860",
    "sg:province":"Danmark",
    "wof:name":"Neuchs, Lise Lotte",
    "wof:placetype":"venue"
},
  "geometry": {"coordinates":[-101.39041900629999,35.6679611206],"type":"Point"}
}