{
  "type": "Feature",
  "properties": {
    "addr:full":"Navervej 3 Hinnerup Danmark 8382",
    "addr:housenumber":"3",
    "addr:postcode":"8382",
    "addr:street":"Navervej",
    "iso:country":"DK",
    "sg:address":"Navervej 3",
    "sg:city":"Hinnerup",
    "sg:orig_category":"INGENI\u00c3\u02dcRER",
    "sg:phone":"+45 86 98 70 04",
    "sg:postcode":"8382",
    "sg:province":"Danmark",
    "wof:name":"Arent Jensen ApS, E.",
    "wof:placetype":"venue"
},
  "geometry": {"coordinates":[10.0724010468,56.2540473938],"type":"Point"}
}