{
  "type": "Feature",
  "properties": {
    "iso:country":"DK",
    "sg:address":"Lokalcenter Roseng\u00e5rd, \u00d8rb\u00e6kvej 150",
    "sg:city":"Odense S\u00d8",
    "sg:orig_category":"Dagcentre",
    "sg:phone":"+45 66 13 13 72",
    "sg:postcode":"5220",
    "sg:province":"Danmark",
    "wof:name":"Tr\u00e6ningscentret",
    "wof:placetype":"venue"
},
  "geometry": {"coordinates":[10.4583454132,55.3316917419],"type":"Point"}
}