{
  "type": "Feature",
  "properties": {
    "addr:full":"Halg\u00e5rdvej 1, Mejdal Holstebro Danmark 7500",
    "addr:housenumber":"1",
    "addr:postcode":"7500",
    "addr:street":"Halgaardvej;Mejdal",
    "iso:country":"DK",
    "sg:address":"Halg\u00e5rdvej 1, Mejdal",
    "sg:city":"Holstebro",
    "sg:orig_category":"Tandklinikker, Kommunale",
    "sg:phone":"+45 96 11 58 89",
    "sg:postcode":"7500",
    "sg:province":"Danmark",
    "wof:name":"Tandklinikken v/ Halg\u00e5rd skole",
    "wof:placetype":"venue"
},
  "geometry": {"coordinates":[8.6202583313,56.3625221252],"type":"Point"}
}