{
  "type": "Feature",
  "properties": {
    "iso:country":"DK",
    "sg:address":"S\u00f8borg Hovedgade 61",
    "sg:city":"S\u00f8borg",
    "sg:classifiers":[
        {
            "category":"Communications",
            "type":"Services"
        }
    ],
    "sg:phone":"+45 39 69 20 21",
    "sg:postcode":"2860",
    "sg:province":"Danmark",
    "sg:tags":[
        "og",
        "tv",
        "radio"
    ],
    "wof:name":"Expert S\u00f8borg",
    "wof:placetype":"venue"
},
  "geometry": {"coordinates":[-101.39041900629999,35.6679611206],"type":"Point"}
}