{
  "type": "Feature",
  "properties": {
    "iso:country":"DK",
    "sg:address":"Stadsbibliotekar: Marianne Aastrup, Holte Midtpunkt 23, 3.",
    "sg:city":"Holte",
    "sg:orig_category":"Biblioteker",
    "sg:phone":"+45 45 46 66 00",
    "sg:postcode":"2840",
    "sg:province":"Danmark",
    "sg:website":"www.sollerod.dk/bibliotek",
    "wof:name":"Biblioteksadministrationen",
    "wof:placetype":"venue"
},
  "geometry": {"coordinates":[12.470655,55.812237],"type":"Point"}
}