{
  "type": "Feature",
  "properties": {
    "addr:full":"Prinsensgade 75, Postboks 27 Fredericia Danmark 7000",
    "addr:housenumber":"75;27",
    "addr:postcode":"7000",
    "addr:street":"Prinsensgade",
    "iso:country":"DK",
    "sg:address":"Prinsensgade 75, Postboks 27",
    "sg:city":"Fredericia",
    "sg:orig_category":"Undervisningsinventar",
    "sg:phone":"+45 75 92 43 22",
    "sg:postcode":"7000",
    "sg:province":"Danmark",
    "sg:website":"www.totalinventar.dk",
    "wof:name":"TOTAL INVENTAR",
    "wof:placetype":"venue"
},
  "geometry": {"coordinates":[9.7591047287,55.566368103],"type":"Point"}
}