{
  "type": "Feature",
  "properties": {
    "iso:country":"DK",
    "sg:address":"Vejlevej 82",
    "sg:city":"Horsens",
    "sg:orig_category":"Servicestationer",
    "sg:phone":"+45 75 64 65 53",
    "sg:postcode":"8700",
    "sg:province":"Danmark",
    "wof:name":"DK Benzin",
    "wof:placetype":"venue"
},
  "geometry": {"coordinates":[9.820779,55.843327],"type":"Point"}
}