{
  "type": "Feature",
  "properties": {
    "addr:full":"Fmd.: Ole Hoff-Clausen, R\u00f8dtj\u00f8rnevej 9 Sor\u00f8 Danmark 4180",
    "addr:housenumber":"9",
    "addr:postcode":"4180",
    "addr:street":"Rodtjornevej",
    "iso:country":"DK",
    "sg:address":"Fmd.: Ole Hoff-Clausen, R\u00f8dtj\u00f8rnevej 9",
    "sg:city":"Sor\u00f8",
    "sg:orig_category":"Hobbybetonede foreninger",
    "sg:postcode":"4180",
    "sg:province":"Danmark",
    "wof:name":"Sor\u00f8 og Omegns Filatelistklub",
    "wof:placetype":"venue"
},
  "geometry": {"coordinates":[-102.94467926030001,45.4534721375],"type":"Point"}
}