{
  "type": "Feature",
  "properties": {
    "addr:full":"Nyhavnsgade 12  Esbjerg Danmark 6700",
    "addr:housenumber":"12",
    "addr:postcode":"6700",
    "addr:street":"Nyhavnsgade",
    "iso:country":"DK",
    "sg:address":"Nyhavnsgade 12 ",
    "sg:city":"Esbjerg",
    "sg:classifiers":[
        {
            "category":"Autos & Motor Vehicles",
            "subcategory":"Boat Sales",
            "type":"Retail Goods"
        }
    ],
    "sg:phone":"+45 75 12 33 25",
    "sg:postcode":"6700",
    "sg:province":"Danmark",
    "wof:name":"ALKAB PLADE- OG SVEJSEV\u00c6RKSTED APS",
    "wof:placetype":"venue"
},
  "geometry": {"coordinates":[8.4334821701,55.4727745056],"type":"Point"}
}