{
  "type": "Feature",
  "properties": {
    "addr:full":"Mindevej 20 Egernsund Danmark 6320",
    "addr:housenumber":"20",
    "addr:postcode":"6320",
    "addr:street":"Mindevej",
    "iso:country":"DK",
    "sg:address":"Mindevej 20",
    "sg:city":"Egernsund",
    "sg:orig_category":"Havne",
    "sg:phone":"+45 74 44 07 10",
    "sg:postcode":"6320",
    "sg:province":"Danmark",
    "sg:website":"www.marinaminde.com",
    "wof:name":"Marina Minde",
    "wof:placetype":"venue"
},
  "geometry": {"coordinates":[9.6169395447,54.9005508423],"type":"Point"}
}