{
  "type": "Feature",
  "properties": {
    "addr:full":"Bulskovvej 3, \u00d8. Karleby Nakskov Danmark 4900",
    "addr:housenumber":"3 o.",
    "addr:postcode":"4900",
    "addr:street":"Bulskovvej",
    "iso:country":"DK",
    "sg:address":"Bulskovvej 3, \u00d8. Karleby",
    "sg:city":"Nakskov",
    "sg:orig_category":"Zoneterapeuter",
    "sg:phone":"+45 54 93 90 52",
    "sg:postcode":"4900",
    "sg:province":"Danmark",
    "wof:name":"Knak, Jytte",
    "wof:placetype":"venue"
},
  "geometry": {"coordinates":[11.1359500885,54.8330116272],"type":"Point"}
}