{
  "type": "Feature",
  "properties": {
    "iso:country":"DK",
    "sg:address":"Randersvej 384, Lisbjerg",
    "sg:city":"\u00c5rhus N",
    "sg:orig_category":"Lokalarkiver",
    "sg:postcode":"8200",
    "sg:province":"Danmark",
    "wof:name":"Lisbjerg-Skejby-Terp Lokalarkiv",
    "wof:placetype":"venue"
},
  "geometry": {"coordinates":[10.1661300659,56.2195892334],"type":"Point"}
}