{
  "type": "Feature",
  "properties": {
    "addr:full":"Storegade 17 Stege Danmark 4780",
    "addr:housenumber":"17",
    "addr:postcode":"4780",
    "addr:street":"Storegade",
    "iso:country":"DK",
    "sg:address":"Storegade 17",
    "sg:city":"Stege",
    "sg:orig_category":"Blomsterhandlere",
    "sg:phone":"+45 55 81 15 35",
    "sg:postcode":"4780",
    "sg:province":"Danmark",
    "wof:name":"Lene",
    "wof:placetype":"venue"
},
  "geometry": {"coordinates":[12.2847204208,54.983707428],"type":"Point"}
}