{
  "type": "Feature",
  "properties": {
    "addr:full":"Bejsebakkevej 18 Aalborg Danmark 9000",
    "addr:housenumber":"18",
    "addr:postcode":"9000",
    "addr:street":"Bejsebakkevej",
    "iso:country":"DK",
    "sg:address":"Bejsebakkevej 18",
    "sg:city":"Aalborg",
    "sg:orig_category":"Arkitekter",
    "sg:phone":"+45 98 13 72 08",
    "sg:postcode":"9000",
    "sg:province":"Danmark",
    "wof:name":"K\u00e6rsgaard, Poul",
    "wof:placetype":"venue"
},
  "geometry": {"coordinates":[9.8999929428,57.0370597839],"type":"Point"}
}