{
  "type": "Feature",
  "properties": {
    "addr:full":"Egestr\u00e6de 16 Store Heddinge Danmark 4660",
    "addr:housenumber":"16",
    "addr:postcode":"4660",
    "addr:street":"Egestraede",
    "iso:country":"DK",
    "sg:address":"Egestr\u00e6de 16",
    "sg:city":"Store Heddinge",
    "sg:orig_category":"Skolefritidsordninger",
    "sg:phone":"+45 56 50 46 05",
    "sg:postcode":"4660",
    "sg:province":"Danmark",
    "wof:name":"Sismofytten, SFO",
    "wof:placetype":"venue"
},
  "geometry": {"coordinates":[12.3895797729,55.3113174438],"type":"Point"}
}