{
  "type": "Feature",
  "properties": {
    "iso:country":"DK",
    "sg:address":"Storegade 6 - 10",
    "sg:city":"Tarm",
    "sg:classifiers":[
        {
            "category":"Banks & Credit Unions",
            "subcategory":"Bank",
            "type":"Services"
        }
    ],
    "sg:phone":"+45 97 37 14 11",
    "sg:postcode":"6880",
    "sg:province":"Danmark",
    "sg:tags":[
        "banker"
    ],
    "sg:website":"www.tarmbank.dk",
    "wof:name":"Tarm Bank A/S",
    "wof:placetype":"venue"
},
  "geometry": {"coordinates":[8.521272,55.908291],"type":"Point"}
}