{
  "type": "Feature",
  "properties": {
    "addr:full":"Rugv\u00e6nget 10 Ballerup Danmark 2750",
    "addr:housenumber":"10",
    "addr:postcode":"2750",
    "addr:street":"Rugvaenget",
    "iso:country":"DK",
    "sg:address":"Rugv\u00e6nget 10",
    "sg:city":"Ballerup",
    "sg:orig_category":"Kommunale folkeskoler",
    "sg:phone":"+45 44 77 32 77",
    "sg:postcode":"2750",
    "sg:province":"Danmark",
    "wof:name":"Rugv\u00e6ngets Skole",
    "wof:placetype":"venue"
},
  "geometry": {"coordinates":[12.361000061,55.7301216125],"type":"Point"}
}