{
  "type": "Feature",
  "properties": {
    "addr:full":"Viborgvej 856, Lading Sabro Danmark 8471",
    "addr:housenumber":"856",
    "addr:postcode":"8471",
    "addr:street":"Viborgvej",
    "iso:country":"DK",
    "sg:address":"Viborgvej 856, Lading",
    "sg:city":"Sabro",
    "sg:orig_category":"Kemisk industri",
    "sg:phone":"+45 86 94 99 00",
    "sg:postcode":"8471",
    "sg:province":"Danmark",
    "wof:name":"Alpha Kemi ApS",
    "wof:placetype":"venue"
},
  "geometry": {"coordinates":[10.0375204086,56.2109718323],"type":"Point"}
}