{
  "type": "Feature",
  "properties": {
    "addr:full":"\u00c5gade 6 Bindslev Danmark 9881",
    "addr:housenumber":"6",
    "addr:postcode":"9881",
    "addr:street":"Aagade",
    "iso:country":"DK",
    "sg:address":"\u00c5gade 6",
    "sg:city":"Bindslev",
    "sg:orig_category":"Engros handel",
    "sg:phone":"+45 98 93 87 43",
    "sg:postcode":"9881",
    "sg:province":"Danmark",
    "wof:name":"OT Trading",
    "wof:placetype":"venue"
},
  "geometry": {"coordinates":[10.1995372772,57.5395622253],"type":"Point"}
}