{
  "type": "Feature",
  "properties": {
    "addr:full":"Elmelunden 9 Sor\u00f8 Danmark 4180",
    "addr:housenumber":"9",
    "addr:postcode":"4180",
    "addr:street":"Elmelunden",
    "iso:country":"DK",
    "sg:address":"Elmelunden 9",
    "sg:city":"Sor\u00f8",
    "sg:orig_category":"Vinduespolering",
    "sg:phone":"+45 57 83 47 98",
    "sg:postcode":"4180",
    "sg:province":"Danmark",
    "wof:name":"Clean Vinduespolering",
    "wof:placetype":"venue"
},
  "geometry": {"coordinates":[-102.94467926030001,45.4534721375],"type":"Point"}
}