{
  "type": "Feature",
  "properties": {
    "addr:full":"S\u00f8ndergade 7 - 15 Viby Sj\u00e6lland Danmark 4130",
    "addr:housenumber":"7 15",
    "addr:postcode":"4130",
    "addr:street":"Sondergade",
    "iso:country":"DK",
    "sg:address":"S\u00f8ndergade 7 - 15",
    "sg:city":"Viby Sj\u00e6lland",
    "sg:orig_category":"Fabrikker",
    "sg:phone":"+45 46 19 33 62",
    "sg:postcode":"4130",
    "sg:province":"Danmark",
    "wof:name":"Pharmacosmos A/S",
    "wof:placetype":"venue"
},
  "geometry": {"coordinates":[12.024274826,55.5473709106],"type":"Point"}
}