{
  "type": "Feature",
  "properties": {
    "addr:full":"Marsvej 13 Randers Danmark 8900",
    "addr:housenumber":"13",
    "addr:postcode":"8900",
    "addr:street":"Marsvej",
    "iso:country":"DK",
    "sg:address":"Marsvej 13",
    "sg:city":"Randers",
    "sg:orig_category":"Dyr, artikler for",
    "sg:phone":"+45 86 44 72 22",
    "sg:postcode":"8900",
    "sg:province":"Danmark",
    "wof:name":"Farmland ApS",
    "wof:placetype":"venue"
},
  "geometry": {"coordinates":[10.0357952118,56.4593734741],"type":"Point"}
}