{
  "type": "Feature",
  "properties": {
    "iso:country":"DK",
    "sg:address":"N\u00f8rrelundsvej 2, Dreslette",
    "sg:city":"Haarby",
    "sg:orig_category":"Arkitekter",
    "sg:phone":"+45 64 77 11 50",
    "sg:postcode":"5683",
    "sg:province":"Danmark",
    "wof:name":"Andersen, Lars",
    "wof:placetype":"venue"
},
  "geometry": {"coordinates":[10.1234750748,55.2234535217],"type":"Point"}
}