{
  "type": "Feature",
  "properties": {
    "addr:full":"Jyllandsgade 39 Fredericia Danmark 7000",
    "addr:housenumber":"39",
    "addr:postcode":"7000",
    "addr:street":"Jyllandsgade",
    "iso:country":"DK",
    "sg:address":"Jyllandsgade 39",
    "sg:city":"Fredericia",
    "sg:orig_category":"Non-Classified Establishments",
    "sg:phone":"+45 75 92 07 31",
    "sg:postcode":"7000",
    "sg:province":"Danmark",
    "wof:name":"Ostejyden",
    "wof:placetype":"venue"
},
  "geometry": {"coordinates":[9.757270813,55.565788269],"type":"Point"}
}