{
  "type": "Feature",
  "properties": {
    "iso:country":"DK",
    "sg:address":"Myntevej 1, Postboks 520",
    "sg:city":"Vestbjerg",
    "sg:orig_category":"Dag- og distriktsblade",
    "sg:phone":"+45 98 29 70 86",
    "sg:postcode":"9380",
    "sg:province":"Danmark",
    "sg:website":"www.bt.dk",
    "wof:name":"B.T. Nordjyllands Redaktion Repotage",
    "wof:placetype":"venue"
},
  "geometry": {"coordinates":[9.9697885513,57.1300506592],"type":"Point"}
}