{
  "type": "Feature",
  "properties": {
    "iso:country":"DK",
    "sg:address":"Fmd.: Niels Borup, Sagavej 20",
    "sg:city":"Slagelse",
    "sg:orig_category":"Hobbybetonede foreninger",
    "sg:phone":"+45 58 50 48 68",
    "sg:postcode":"4200",
    "sg:province":"Danmark",
    "sg:website":"www.televej.dk/frimaerke",
    "wof:name":"Slagelse Frim\u00e6rkeklub",
    "wof:placetype":"venue"
},
  "geometry": {"coordinates":[11.3569850922,55.4050865173],"type":"Point"}
}