{
  "type": "Feature",
  "properties": {
    "addr:full":"S\u00f8nderg\u00e5rden 9  Fars\u00f8 Danmark 9640",
    "addr:housenumber":"9",
    "addr:postcode":"9640",
    "addr:street":"Sondergaarden",
    "iso:country":"DK",
    "sg:address":"S\u00f8nderg\u00e5rden 9 ",
    "sg:city":"Fars\u00f8",
    "sg:classifiers":[
        {
            "category":"Home & Garden",
            "subcategory":"Home Furnishings",
            "type":"Retail Goods"
        }
    ],
    "sg:phone":"+45 98 63 15 11",
    "sg:postcode":"9640",
    "sg:province":"Danmark",
    "sg:tags":[
        "household"
    ],
    "wof:name":"DEGNE LIMTR\u00c6 A/S",
    "wof:placetype":"venue"
},
  "geometry": {"coordinates":[-109.44831848139999,42.1062355042],"type":"Point"}
}