{
  "type": "Feature",
  "properties": {
    "addr:full":"President: Evo Ronald J\u00f8rgensen, Nordre Industrivej 18 R\u00f8dding Danmark 6630",
    "addr:housenumber":"18",
    "addr:postcode":"6630",
    "addr:street":"President;Ronald;Nordre Industrivej",
    "iso:country":"DK",
    "sg:address":"President: Evo Ronald J\u00f8rgensen, Nordre Industrivej 18",
    "sg:city":"R\u00f8dding",
    "sg:orig_category":"Hobbybetonede foreninger",
    "sg:postcode":"6630",
    "sg:province":"Danmark",
    "sg:website":"www.chieftains.dk",
    "wof:name":"Chieftains Motorcycle Club",
    "wof:placetype":"venue"
},
  "geometry": {"coordinates":[12.035369873,60.8038711548],"type":"Point"}
}