{
  "type": "Feature",
  "properties": {
    "addr:full":"Rish\u00f8jvej 5 K\u00f8ge Danmark 4600",
    "addr:housenumber":"5",
    "addr:postcode":"4600",
    "addr:street":"Rishojvej",
    "iso:country":"DK",
    "sg:address":"Rish\u00f8jvej 5",
    "sg:city":"K\u00f8ge",
    "sg:orig_category":"Skolefritidsordninger",
    "sg:phone":"+45 56 65 62 36",
    "sg:postcode":"4600",
    "sg:province":"Danmark",
    "wof:name":"Basen SFO I",
    "wof:placetype":"venue"
},
  "geometry": {"coordinates":[12.1789512634,55.4923973083],"type":"Point"}
}