{
  "type": "Feature",
  "properties": {
    "addr:full":"Toldbodvej 9 Svendborg Danmark 5700",
    "addr:housenumber":"9",
    "addr:postcode":"5700",
    "addr:street":"Toldbodvej",
    "iso:country":"DK",
    "sg:address":"Toldbodvej 9",
    "sg:city":"Svendborg",
    "sg:orig_category":"Advokater",
    "sg:phone":"+45 62 21 22 42",
    "sg:postcode":"5700",
    "sg:province":"Danmark",
    "wof:name":"Advokaterne Ole J\u00f8rgensen & Claus Olsen",
    "wof:placetype":"venue"
},
  "geometry": {"coordinates":[10.612112999,55.061000824],"type":"Point"}
}