{
  "type": "Feature",
  "properties": {
    "addr:full":"S\u00f8ndre Kajgade 2 Grenaa Danmark 8500",
    "addr:housenumber":"2",
    "addr:postcode":"8500",
    "addr:street":"Sondre Kajgade",
    "iso:country":"DK",
    "sg:address":"S\u00f8ndre Kajgade 2",
    "sg:city":"Grenaa",
    "sg:orig_category":"Kiosker",
    "sg:phone":"+45 86 32 13 16",
    "sg:postcode":"8500",
    "sg:province":"Danmark",
    "wof:name":"Turistkiosken",
    "wof:placetype":"venue"
},
  "geometry": {"coordinates":[10.9203948975,56.408870697],"type":"Point"}
}