{
  "type": "Feature",
  "properties": {
    "addr:full":"Rennebjergvej 182 Boeslunde Danmark 4242",
    "addr:housenumber":"182",
    "addr:postcode":"4242",
    "addr:street":"Rennebjergvej",
    "iso:country":"DK",
    "sg:address":"Rennebjergvej 182",
    "sg:city":"Boeslunde",
    "sg:orig_category":"Maskinfabrikker",
    "sg:phone":"+45 58 14 02 05",
    "sg:postcode":"4242",
    "sg:province":"Danmark",
    "wof:name":"Ehrhardts Metalvarefabrik ApS",
    "wof:placetype":"venue"
},
  "geometry": {"coordinates":[11.2607011795,55.2980461121],"type":"Point"}
}