{
  "type": "Feature",
  "properties": {
    "iso:country":"DK",
    "sg:address":"Haslevvej 8",
    "sg:city":"Ringsted",
    "sg:orig_category":"Glasfiberindustri",
    "sg:phone":"+45 57 67 07 09",
    "sg:postcode":"4100",
    "sg:province":"Danmark",
    "wof:name":"Monomex A/S",
    "wof:placetype":"venue"
},
  "geometry": {"coordinates":[11.801243782,55.4354476929],"type":"Point"}
}