{
  "type": "Feature",
  "properties": {
    "addr:full":"Bryggergade 10 Herning Danmark 7400",
    "addr:housenumber":"10",
    "addr:postcode":"7400",
    "addr:street":"Bryggergade",
    "iso:country":"DK",
    "sg:address":"Bryggergade 10",
    "sg:city":"Herning",
    "sg:orig_category":"Industribyggeri",
    "sg:phone":"+45 97 12 65 44",
    "sg:postcode":"7400",
    "sg:province":"Danmark",
    "wof:name":"Midtjysk Totalbyg A/S",
    "wof:placetype":"venue"
},
  "geometry": {"coordinates":[8.9729690552,56.1353569031],"type":"Point"}
}