{
  "type": "Feature",
  "properties": {
    "addr:full":"Roholmsvej 10 A Albertslund Danmark 2620",
    "addr:housenumber":"10 a",
    "addr:postcode":"2620",
    "addr:street":"Roholmsvej",
    "iso:country":"DK",
    "sg:address":"Roholmsvej 10 A",
    "sg:city":"Albertslund",
    "sg:orig_category":"Reklamegaver",
    "sg:phone":"+45 43 62 42 42",
    "sg:postcode":"2620",
    "sg:province":"Danmark",
    "wof:name":"Hoffmann Soul A/S",
    "wof:placetype":"venue"
},
  "geometry": {"coordinates":[12.3604001999,55.6669082642],"type":"Point"}
}