{
  "type": "Feature",
  "properties": {
    "addr:full":"Skolegade 51, Lunde N\u00f8rre Nebel Danmark 6830",
    "addr:housenumber":"51",
    "addr:postcode":"6830",
    "addr:street":"Skolegade",
    "iso:country":"DK",
    "sg:address":"Skolegade 51, Lunde",
    "sg:city":"N\u00f8rre Nebel",
    "sg:orig_category":"Forsamlingshuse",
    "sg:phone":"+45 75 28 20 84",
    "sg:postcode":"6830",
    "sg:province":"Danmark",
    "wof:name":"Lunde Forsamlingshus",
    "wof:placetype":"venue"
},
  "geometry": {"coordinates":[8.2399549484,55.7888755798],"type":"Point"}
}