{
  "type": "Feature",
  "properties": {
    "iso:country":"DK",
    "sg:address":"Kobbelkildevej 2, Vollerup",
    "sg:city":"Askeby",
    "sg:orig_category":"Antikviteter",
    "sg:phone":"+45 55 81 73 18",
    "sg:postcode":"4792",
    "sg:province":"Danmark",
    "wof:name":"Kongslund Krambod",
    "wof:placetype":"venue"
},
  "geometry": {"coordinates":[12.1452455521,54.8838500977],"type":"Point"}
}