{
  "type": "Feature",
  "properties": {
    "addr:full":"Karlslunde Strandvej 82 Karlslunde Danmark 2690",
    "addr:housenumber":"82",
    "addr:postcode":"2690",
    "addr:street":"Karlslunde Strandvej",
    "iso:country":"DK",
    "sg:address":"Karlslunde Strandvej 82",
    "sg:city":"Karlslunde",
    "sg:orig_category":"Bagere",
    "sg:phone":"+45 46 15 03 11",
    "sg:postcode":"2690",
    "sg:province":"Danmark",
    "wof:name":"Prebens Bageri",
    "wof:placetype":"venue"
},
  "geometry": {"coordinates":[12.257776,55.558853],"type":"Point"}
}