{
  "type": "Feature",
  "properties": {
    "iso:country":"DK",
    "sg:address":"N\u00f8rreport 4",
    "sg:city":"Ebeltoft",
    "sg:orig_category":"Bandagister",
    "sg:phone":"+45 86 34 57 66",
    "sg:postcode":"8400",
    "sg:province":"Danmark",
    "wof:name":"Byens Bandagist",
    "wof:placetype":"venue"
},
  "geometry": {"coordinates":[10.681249,56.202297],"type":"Point"}
}