{
  "type": "Feature",
  "properties": {
    "addr:full":"Gravene 9 Viborg Danmark 8800",
    "addr:housenumber":"9",
    "addr:postcode":"8800",
    "addr:street":"Gravene",
    "iso:country":"DK",
    "sg:address":"Gravene 9",
    "sg:city":"Viborg",
    "sg:orig_category":"Sygeplejeartikler",
    "sg:phone":"+45 86 62 08 86",
    "sg:postcode":"8800",
    "sg:province":"Danmark",
    "wof:name":"Sygeplejeforretningen",
    "wof:placetype":"venue"
},
  "geometry": {"coordinates":[9.4052562714,56.450466156],"type":"Point"}
}