{
  "type": "Feature",
  "properties": {
    "iso:country":"DK",
    "sg:address":"Adelgade 29",
    "sg:city":"Hobro",
    "sg:orig_category":"Lingeri",
    "sg:phone":"+45 98 52 01 68",
    "sg:postcode":"9500",
    "sg:province":"Danmark",
    "wof:name":"Anita",
    "wof:placetype":"venue"
},
  "geometry": {"coordinates":[9.7940940857,56.638458252],"type":"Point"}
}