{
  "type": "Feature",
  "properties": {
    "addr:full":"v/ Per Smedegaard, Strandv\u00e6nget 4 Asaa Danmark 9340",
    "addr:housenumber":"4",
    "addr:postcode":"9340",
    "addr:street":"Strandvaenget",
    "iso:country":"DK",
    "sg:address":"v/ Per Smedegaard, Strandv\u00e6nget 4",
    "sg:city":"Asaa",
    "sg:orig_category":"Grundejerforeninger",
    "sg:phone":"+45 98 85 16 61",
    "sg:postcode":"9340",
    "sg:province":"Danmark",
    "wof:name":"Beboerforeningen Ger\u00e5 Engvej og Strandv\u00e6nget",
    "wof:placetype":"venue"
},
  "geometry": {"coordinates":[10.4039297104,57.1481704712],"type":"Point"}
}