{
  "type": "Feature",
  "properties": {
    "addr:full":"v/ B\u00f8rge Christensen, Strandengen 10, Plejeruphuse Grevinge Danmark 4571",
    "addr:housenumber":"10",
    "addr:postcode":"4571",
    "addr:street":"Strandengen;Plejeruphuse",
    "iso:country":"DK",
    "sg:address":"v/ B\u00f8rge Christensen, Strandengen 10, Plejeruphuse",
    "sg:city":"Grevinge",
    "sg:orig_category":"Folkedans",
    "sg:phone":"+45 59 65 96 73",
    "sg:postcode":"4571",
    "sg:province":"Danmark",
    "sg:website":"www.countrysquaredancers.dk",
    "wof:name":"Country Square Dancers",
    "wof:placetype":"venue"
},
  "geometry": {"coordinates":[11.5593652725,55.7873153687],"type":"Point"}
}