{
  "type": "Feature",
  "properties": {
    "addr:full":"Vestergade 12 K\u00f8benhavn Danmark 1456",
    "addr:housenumber":"12;1456",
    "addr:street":"Vestergade",
    "iso:country":"DK",
    "sg:address":"Vestergade 12",
    "sg:city":"K\u00f8benhavn",
    "sg:orig_category":"Tobak",
    "sg:phone":"+45 33 12 98 12",
    "sg:postcode":"1456",
    "sg:province":"Danmark",
    "wof:name":"Tre Hjorter",
    "wof:placetype":"venue"
},
  "geometry": {"coordinates":[9.5455904007,56.1682090759],"type":"Point"}
}