{
  "type": "Feature",
  "properties": {
    "addr:full":"Vestergade 11 Aabenraa Danmark 6200",
    "addr:housenumber":"11",
    "addr:postcode":"6200",
    "addr:street":"Vestergade",
    "iso:country":"DK",
    "sg:address":"Vestergade 11",
    "sg:city":"Aabenraa",
    "sg:orig_category":"Psykologer, praktiserende",
    "sg:phone":"+45 74 62 83 20",
    "sg:postcode":"6200",
    "sg:province":"Danmark",
    "wof:name":"Psykologhuset Aabenraa",
    "wof:placetype":"venue"
},
  "geometry": {"coordinates":[9.4175481796,55.0422744751],"type":"Point"}
}