{
  "type": "Feature",
  "properties": {
    "addr:full":"Fmd.: Morten St\u00e6hr, Brogade 97 Bjerringbro Danmark 8850",
    "addr:housenumber":"97",
    "addr:postcode":"8850",
    "addr:street":"Morten Staehr Brogade",
    "iso:country":"DK",
    "sg:address":"Fmd.: Morten St\u00e6hr, Brogade 97",
    "sg:city":"Bjerringbro",
    "sg:orig_category":"Kirkelige foreninger",
    "sg:phone":"+45 25 36 06 32",
    "sg:postcode":"8850",
    "sg:province":"Danmark",
    "wof:name":"Indre Missions Ungdom",
    "wof:placetype":"venue"
},
  "geometry": {"coordinates":[9.6546850204,56.3754692078],"type":"Point"}
}