{
  "type": "Feature",
  "properties": {
    "addr:full":"Storegade 2, over g\u00e5rden Nordborg Danmark 6430",
    "addr:housenumber":"2",
    "addr:postcode":"6430",
    "addr:street":"Storegade;Over Gaarden",
    "iso:country":"DK",
    "sg:address":"Storegade 2, over g\u00e5rden",
    "sg:city":"Nordborg",
    "sg:orig_category":"Mobiltelefoner",
    "sg:phone":"+45 74 45 00 36",
    "sg:postcode":"6430",
    "sg:province":"Danmark",
    "wof:name":"HH Teleservice",
    "wof:placetype":"venue"
},
  "geometry": {"coordinates":[9.7496232986,55.0542755127],"type":"Point"}
}