{
  "type": "Feature",
  "properties": {
    "addr:full":"Helgesvej 9 Frederiksberg Danmark 2000",
    "addr:housenumber":"9",
    "addr:postcode":"2000",
    "addr:street":"Helgesvej",
    "iso:country":"DK",
    "sg:address":"Helgesvej 9",
    "sg:city":"Frederiksberg",
    "sg:orig_category":"Personaleudvikling",
    "sg:phone":"+45 38 16 12 13",
    "sg:postcode":"2000",
    "sg:province":"Danmark",
    "sg:website":"www.arkaden.dk",
    "wof:name":"Arkadien",
    "wof:placetype":"venue"
},
  "geometry": {"coordinates":[12.535399437,55.6837310791],"type":"Point"}
}