{
  "type": "Feature",
  "properties": {
    "addr:full":"Fmd.: Anna Margrethe Andersen, Oblingvej 9, Sdr. Bork Hemmet Danmark 6893",
    "addr:housenumber":"9",
    "addr:postcode":"6893",
    "addr:street":"Anna Margrethe Andersen Oblingvej;Sdr. Bork",
    "iso:country":"DK",
    "sg:address":"Fmd.: Anna Margrethe Andersen, Oblingvej 9, Sdr. Bork",
    "sg:city":"Hemmet",
    "sg:orig_category":"Hobbybetonede foreninger",
    "sg:phone":"+45 75 20 01 29",
    "sg:postcode":"6893",
    "sg:province":"Danmark",
    "wof:name":"Tarm og Omegns Havekreds",
    "wof:placetype":"venue"
},
  "geometry": {"coordinates":[8.2862300873,55.8409957886],"type":"Point"}
}