{
  "type": "Feature",
  "properties": {
    "addr:full":"Storegade 19 A Thisted Danmark 7700",
    "addr:housenumber":"19 a",
    "addr:postcode":"7700",
    "addr:street":"Storegade",
    "iso:country":"DK",
    "sg:address":"Storegade 19 A",
    "sg:city":"Thisted",
    "sg:orig_category":"Arbejdsformidling",
    "sg:phone":"+45 97 92 10 93",
    "sg:postcode":"7700",
    "sg:province":"Danmark",
    "wof:name":"Job Butikken",
    "wof:placetype":"venue"
},
  "geometry": {"coordinates":[8.6932172775,56.9549713135],"type":"Point"}
}