{
  "type": "Feature",
  "properties": {
    "addr:full":"Kraghave Gaabensevej 82, Kraghave Nyk\u00f8bing Danmark 4800",
    "addr:housenumber":"82",
    "addr:postcode":"4800",
    "addr:street":"Kraghave Gaabensevej;Kraghave Nykobing Danmark",
    "iso:country":"DK",
    "sg:address":"Kraghave Gaabensevej 82, Kraghave",
    "sg:city":"Nyk\u00f8bing",
    "sg:orig_category":"Oliefyr og service",
    "sg:phone":"+45 54 85 83 15",
    "sg:postcode":"4800",
    "sg:province":"Danmark",
    "wof:name":"Juul-Mortensen, Hans Otto",
    "wof:placetype":"venue"
},
  "geometry": {"coordinates":[11.8678541183,54.769241333],"type":"Point"}
}