{
  "type": "Feature",
  "properties": {
    "addr:full":"v/ Leif Andersen, Aaparken 23, st. th. Odder Danmark 8300",
    "addr:housenumber":"23",
    "addr:postcode":"8300",
    "addr:street":"Aaparken;St. Th.",
    "iso:country":"DK",
    "sg:address":"v/ Leif Andersen, Aaparken 23, st. th.",
    "sg:city":"Odder",
    "sg:orig_category":"\u00c3\u2020ldreorganisationer og klubber",
    "sg:phone":"+45 86 54 25 80",
    "sg:postcode":"8300",
    "sg:province":"Danmark",
    "wof:name":"LO Senior",
    "wof:placetype":"venue"
},
  "geometry": {"coordinates":[10.1497612,55.9733161926],"type":"Point"}
}