{
  "type": "Feature",
  "properties": {
    "addr:full":"Fugleg\u00e5rdsvej 6, Astrup Arden Danmark 9510",
    "addr:housenumber":"6",
    "addr:postcode":"9510",
    "addr:street":"Fuglegaardsvej",
    "iso:country":"DK",
    "sg:address":"Fugleg\u00e5rdsvej 6, Astrup",
    "sg:city":"Arden",
    "sg:orig_category":"Revisorer",
    "sg:phone":"+45 98 58 92 00",
    "sg:postcode":"9510",
    "sg:province":"Danmark",
    "wof:name":"Launa, Bent",
    "wof:placetype":"venue"
},
  "geometry": {"coordinates":[9.8580989838,56.7683296204],"type":"Point"}
}