{
  "type": "Feature",
  "properties": {
    "iso:country":"DK",
    "sg:address":"Fmd.: Henri Holm, Havnegade 2, 2.",
    "sg:city":"Nakskov",
    "sg:orig_category":"Soldaterforeninger",
    "sg:phone":"+45 54 92 06 02",
    "sg:postcode":"4900",
    "sg:province":"Danmark",
    "sg:website":"www.marine-nakskov.dk",
    "wof:name":"Marineforeningen",
    "wof:placetype":"venue"
},
  "geometry": {"coordinates":[11.1359500885,54.8330116272],"type":"Point"}
}