{
  "type": "Feature",
  "properties": {
    "addr:full":"Vodbindervej 2 Hirtshals Danmark 9850",
    "addr:housenumber":"2",
    "addr:postcode":"9850",
    "addr:street":"Vodbindervej",
    "iso:country":"DK",
    "sg:address":"Vodbindervej 2",
    "sg:city":"Hirtshals",
    "sg:orig_category":"Vodbinderier",
    "sg:phone":"+45 98 94 21 11",
    "sg:postcode":"9850",
    "sg:province":"Danmark",
    "wof:name":"Ray's Vod- og Trawlbinderi",
    "wof:placetype":"venue"
},
  "geometry": {"coordinates":[9.952837944,57.5917358398],"type":"Point"}
}