{
  "type": "Feature",
  "properties": {
    "addr:full":"\u00d8rstedsvej 35 B Ribe Danmark 6760",
    "addr:housenumber":"35 b",
    "addr:postcode":"6760",
    "addr:street":"Orstedsvej",
    "iso:country":"DK",
    "sg:address":"\u00d8rstedsvej 35 B",
    "sg:city":"Ribe",
    "sg:orig_category":"Flaskecentraler",
    "sg:phone":"+45 75 42 24 55",
    "sg:postcode":"6760",
    "sg:province":"Danmark",
    "wof:name":"Ribe Flaskecentral",
    "wof:placetype":"venue"
},
  "geometry": {"coordinates":[8.7710294724,55.3504829407],"type":"Point"}
}