{
  "type": "Feature",
  "properties": {
    "addr:full":"Nygade 9 N\u00e6stved Danmark 4700",
    "addr:housenumber":"9",
    "addr:postcode":"4700",
    "addr:street":"Nygade",
    "iso:country":"DK",
    "sg:address":"Nygade 9",
    "sg:city":"N\u00e6stved",
    "sg:orig_category":"Advokater",
    "sg:phone":"+45 55 75 85 00",
    "sg:postcode":"4700",
    "sg:province":"Danmark",
    "wof:name":"Lichtenberg, Hans Henrik de",
    "wof:placetype":"venue"
},
  "geometry": {"coordinates":[11.7542486191,55.2315444946],"type":"Point"}
}