{
  "type": "Feature",
  "properties": {
    "addr:full":"Jernbanegade 5 Bramming Danmark 6740",
    "addr:housenumber":"5",
    "addr:postcode":"6740",
    "addr:street":"Jernbanegade",
    "iso:country":"DK",
    "sg:address":"Jernbanegade 5",
    "sg:city":"Bramming",
    "sg:orig_category":"Kiosker",
    "sg:phone":"+45 75 17 21 89",
    "sg:postcode":"6740",
    "sg:province":"Danmark",
    "wof:name":"DSB Kiosken",
    "wof:placetype":"venue"
},
  "geometry": {"coordinates":[8.7045431137,55.4645385742],"type":"Point"}
}