{
  "type": "Feature",
  "properties": {
    "addr:full":"N\u00f8rreagervej 20 Tinglev Danmark 6360",
    "addr:housenumber":"20",
    "addr:postcode":"6360",
    "addr:street":"Norreagervej",
    "iso:country":"DK",
    "sg:address":"N\u00f8rreagervej 20",
    "sg:city":"Tinglev",
    "sg:orig_category":"Fritidsklubber",
    "sg:phone":"+45 74 64 24 72",
    "sg:postcode":"6360",
    "sg:province":"Danmark",
    "wof:name":"Tinglev Danske Fritidsklub",
    "wof:placetype":"venue"
},
  "geometry": {"coordinates":[9.2526016235,54.9382171631],"type":"Point"}
}