{
  "type": "Feature",
  "properties": {
    "iso:country":"DK",
    "sg:address":"Engholm Alle 7",
    "sg:city":"Hvidovre",
    "sg:classifiers":[
        {
            "category":"Personal",
            "subcategory":"Massage",
            "type":"Services"
        }
    ],
    "sg:phone":"+45 36 49 76 89",
    "sg:postcode":"2650",
    "sg:province":"Danmark",
    "wof:name":"Elmgren, Britta",
    "wof:placetype":"venue"
},
  "geometry": {"coordinates":[12.4698543549,55.6230888367],"type":"Point"}
}