{
  "type": "Feature",
  "properties": {
    "addr:full":"Vestergade 0 R\u00f8dby Danmark 4970",
    "addr:housenumber":"0",
    "addr:postcode":"4970",
    "addr:street":"Vestergade",
    "iso:country":"DK",
    "sg:address":"Vestergade 0",
    "sg:city":"R\u00f8dby",
    "sg:orig_category":"Kirker",
    "sg:postcode":"4970",
    "sg:province":"Danmark",
    "wof:name":"R\u00f8dby Kirke",
    "wof:placetype":"venue"
},
  "geometry": {"coordinates":[9.5455904007,56.1682090759],"type":"Point"}
}