{
  "type": "Feature",
  "properties": {
    "addr:full":"Hasselvej 2, B. Stege Danmark 4780",
    "addr:housenumber":"2 b.",
    "addr:postcode":"4780",
    "addr:street":"Hasselvej",
    "iso:country":"DK",
    "sg:address":"Hasselvej 2, B.",
    "sg:city":"Stege",
    "sg:classifiers":[
        {
            "category":"Taxi",
            "type":"Transportation"
        }
    ],
    "sg:phone":"+45 55 81 79 13",
    "sg:postcode":"4780",
    "sg:province":"Danmark",
    "wof:name":"Taxi 7 * 9 * 13",
    "wof:placetype":"venue"
},
  "geometry": {"coordinates":[12.2863149643,54.998500824],"type":"Point"}
}