{
  "type": "Feature",
  "properties": {
    "addr:full":"Sindalvej 20 Hirtshals Danmark 9850",
    "addr:housenumber":"20",
    "addr:postcode":"9850",
    "addr:street":"Sindalvej",
    "iso:country":"DK",
    "sg:address":"Sindalvej 20",
    "sg:city":"Hirtshals",
    "sg:orig_category":"Fiskeeksport",
    "sg:phone":"+45 98 94 21 88",
    "sg:postcode":"9850",
    "sg:province":"Danmark",
    "wof:name":"Hausgaard A/S, N.O.",
    "wof:placetype":"venue"
},
  "geometry": {"coordinates":[9.9745893478,57.5898933411],"type":"Point"}
}