{
  "type": "Feature",
  "properties": {
    "addr:full":"\u00d8stergade 38 Assens Danmark 5610",
    "addr:housenumber":"38",
    "addr:postcode":"5610",
    "addr:street":"Ostergade",
    "iso:country":"DK",
    "sg:address":"\u00d8stergade 38",
    "sg:city":"Assens",
    "sg:classifiers":[
        {
            "category":"Restaurant",
            "type":"Food & Drink"
        }
    ],
    "sg:phone":"+45 64 71 31 41",
    "sg:postcode":"5610",
    "sg:province":"Danmark",
    "wof:name":"Asia, Restaurant",
    "wof:placetype":"venue"
},
  "geometry": {"coordinates":[9.8968048096,55.269859314],"type":"Point"}
}