{
  "type": "Feature",
  "properties": {
    "addr:full":"Fredenslundvej 24 Vildbjerg Danmark 7480",
    "addr:housenumber":"24",
    "addr:postcode":"7480",
    "addr:street":"Fredenslundvej",
    "iso:country":"DK",
    "sg:address":"Fredenslundvej 24",
    "sg:city":"Vildbjerg",
    "sg:orig_category":"Lotterikollektioner",
    "sg:phone":"+45 97 13 20 85",
    "sg:postcode":"7480",
    "sg:province":"Danmark",
    "wof:name":"Landbrug/Varelotteri",
    "wof:placetype":"venue"
},
  "geometry": {"coordinates":[8.7641992569,56.1919059753],"type":"Point"}
}