{
  "type": "Feature",
  "properties": {
    "addr:full":"Nygade 18 C Aalestrup Danmark 9620",
    "addr:housenumber":"18 c",
    "addr:postcode":"9620",
    "addr:street":"Nygade",
    "iso:country":"DK",
    "sg:address":"Nygade 18 C",
    "sg:city":"Aalestrup",
    "sg:orig_category":"Selskabslokaler",
    "sg:phone":"+45 98 64 23 86",
    "sg:postcode":"9620",
    "sg:province":"Danmark",
    "sg:website":"www.rosenparken.dk",
    "wof:name":"Rosenparkens Pavillon",
    "wof:placetype":"venue"
},
  "geometry": {"coordinates":[9.4977416992,56.6921081543],"type":"Point"}
}