{
  "type": "Feature",
  "properties": {
    "addr:full":"M\u00f8lbakvej 56, Skelund Hadsund Danmark 9560",
    "addr:housenumber":"56",
    "addr:postcode":"9560",
    "addr:street":"Molbakvej",
    "iso:country":"DK",
    "sg:address":"M\u00f8lbakvej 56, Skelund",
    "sg:city":"Hadsund",
    "sg:orig_category":"Skilte",
    "sg:phone":"+45 98 57 57 57",
    "sg:postcode":"9560",
    "sg:province":"Danmark",
    "sg:website":"www.pjskiltecenter.dk",
    "wof:name":"PJ Skiltecenter",
    "wof:placetype":"venue"
},
  "geometry": {"coordinates":[10.115904808,56.7150764465],"type":"Point"}
}