{
  "type": "Feature",
  "properties": {
    "addr:full":"Vestre Havnevej 2 Bogense Danmark 5400",
    "addr:housenumber":"2",
    "addr:postcode":"5400",
    "addr:street":"Vestre Havnevej",
    "iso:country":"DK",
    "sg:address":"Vestre Havnevej 2",
    "sg:city":"Bogense",
    "sg:classifiers":[
        {
            "category":"Restaurant",
            "type":"Food & Drink"
        }
    ],
    "sg:phone":"+45 64 81 12 04",
    "sg:postcode":"5400",
    "sg:province":"Danmark",
    "wof:name":"Leo's Cafe og Bistro",
    "wof:placetype":"venue"
},
  "geometry": {"coordinates":[10.0841617584,55.5664520264],"type":"Point"}
}