{
  "type": "Feature",
  "properties": {
    "addr:full":"v/ J\u00f8rgen Godiksen, Nellikevej 34, Nors Thisted Danmark 7700",
    "addr:housenumber":"34",
    "addr:postcode":"7700",
    "addr:street":"Nellikevej;Nors",
    "iso:country":"DK",
    "sg:address":"v/ J\u00f8rgen Godiksen, Nellikevej 34, Nors",
    "sg:city":"Thisted",
    "sg:orig_category":"Soldaterforeninger",
    "sg:phone":"+45 97 98 15 84",
    "sg:postcode":"7700",
    "sg:province":"Danmark",
    "wof:name":"Thisted Amts Garderforening Skyttelaug",
    "wof:placetype":"venue"
},
  "geometry": {"coordinates":[8.6919784546,56.9556121826],"type":"Point"}
}