{
  "type": "Feature",
  "properties": {
    "addr:full":"Boulevarden 6 A Vordingborg Danmark 4760",
    "addr:housenumber":"6 a",
    "addr:postcode":"4760",
    "addr:street":"Boulevarden",
    "iso:country":"DK",
    "sg:address":"Boulevarden 6 A",
    "sg:city":"Vordingborg",
    "sg:orig_category":"Pizzeriaer",
    "sg:phone":"+45 55 37 22 20",
    "sg:postcode":"4760",
    "sg:province":"Danmark",
    "wof:name":"Verona Pizzaria",
    "wof:placetype":"venue"
},
  "geometry": {"coordinates":[11.9033613205,55.0126724243],"type":"Point"}
}