{
  "type": "Feature",
  "properties": {
    "iso:country":"DK",
    "sg:address":"Kegn\u00e6svej 39, Skovby",
    "sg:city":"Sydals",
    "sg:orig_category":"Bagere",
    "sg:phone":"+45 74 40 45 06",
    "sg:postcode":"6470",
    "sg:province":"Danmark",
    "wof:name":"Skovby Bageri",
    "wof:placetype":"venue"
},
  "geometry": {"coordinates":[9.892463,54.910538],"type":"Point"}
}