{
  "type": "Feature",
  "properties": {
    "addr:full":"Fredbjergvej 130, Fredbjerg Fars\u00f8 Danmark 9640",
    "addr:housenumber":"130",
    "addr:postcode":"9640",
    "addr:street":"Fredbjergvej",
    "iso:country":"DK",
    "sg:address":"Fredbjergvej 130, Fredbjerg",
    "sg:city":"Fars\u00f8",
    "sg:orig_category":"Maskinfabrikker",
    "sg:phone":"+45 98 63 21 22",
    "sg:postcode":"9640",
    "sg:province":"Danmark",
    "wof:name":"Fransg\u00e5rd Maskinfabrik A/S",
    "wof:placetype":"venue"
},
  "geometry": {"coordinates":[9.1937885284,56.6945037842],"type":"Point"}
}