{
  "type": "Feature",
  "properties": {
    "addr:full":"Gammel Kongevej 41 B, ST. K\u00f8benhavn Danmark 1610",
    "addr:housenumber":"41",
    "addr:postcode":"1610",
    "addr:street":"Gammel Kongevej;B St.;Danmark",
    "iso:country":"DK",
    "sg:address":"Gammel Kongevej 41 B, ST.",
    "sg:city":"K\u00f8benhavn",
    "sg:classifiers":[
        {
            "category":"Restaurant",
            "type":"Food & Drink"
        }
    ],
    "sg:phone":"+45 33 24 53 08",
    "sg:postcode":"1610",
    "sg:province":"Danmark",
    "wof:name":"Topkapi",
    "wof:placetype":"venue"
},
  "geometry": {"coordinates":[12.543299675,55.6758003235],"type":"Point"}
}