{
  "type": "Feature",
  "properties": {
    "addr:full":"\u00d8stergade 5, 1.. Herning Danmark 7400",
    "addr:housenumber":"5 1 ..",
    "addr:postcode":"7400",
    "addr:street":"Ostergade",
    "iso:country":"DK",
    "sg:address":"\u00d8stergade 5, 1..",
    "sg:city":"Herning",
    "sg:orig_category":"Faglige organisationer og foreninger",
    "sg:phone":"+45 97 22 30 66",
    "sg:postcode":"7400",
    "sg:province":"Danmark",
    "wof:name":"DA Konsulentkontor Herning",
    "wof:placetype":"venue"
},
  "geometry": {"coordinates":[8.9766521454,56.1363449097],"type":"Point"}
}