{
  "type": "Feature",
  "properties": {
    "addr:full":"Jessens Mole 17 Svendborg Danmark 5700",
    "addr:housenumber":"17",
    "addr:postcode":"5700",
    "addr:street":"Jessens Mole",
    "iso:country":"DK",
    "sg:address":"Jessens Mole 17",
    "sg:city":"Svendborg",
    "sg:orig_category":"RESTAURANTS: CAFEER",
    "sg:phone":"+45 62 22 42 45",
    "sg:postcode":"5700",
    "sg:province":"Danmark",
    "sg:website":"www.la-buca.dk",
    "wof:name":"La Buca",
    "wof:placetype":"venue"
},
  "geometry": {"coordinates":[10.6138410568,55.0608673096],"type":"Point"}
}