{
  "type": "Feature",
  "properties": {
    "addr:full":"Vibberstoftvej 13 Snedsted Danmark 7752",
    "addr:housenumber":"13",
    "addr:postcode":"7752",
    "addr:street":"Vibberstoftvej",
    "iso:country":"DK",
    "sg:address":"Vibberstoftvej 13",
    "sg:city":"Snedsted",
    "sg:orig_category":"\u00c3\u2020g",
    "sg:phone":"+45 97 93 63 89",
    "sg:postcode":"7752",
    "sg:province":"Danmark",
    "wof:name":"Vibberstoft \u00c6g",
    "wof:placetype":"venue"
},
  "geometry": {"coordinates":[8.5136137009,56.8217887878],"type":"Point"}
}