{
  "type": "Feature",
  "properties": {
    "addr:full":"Holme\u00e5s 34 Greve Danmark 2670",
    "addr:housenumber":"34",
    "addr:postcode":"2670",
    "addr:street":"Holmeaas",
    "iso:country":"DK",
    "sg:address":"Holme\u00e5s 34",
    "sg:city":"Greve",
    "sg:orig_category":"Trykkerier",
    "sg:phone":"+45 43 90 48 43",
    "sg:postcode":"2670",
    "sg:province":"Danmark",
    "sg:website":"www.actryk.dk",
    "wof:name":"A.C. Tryk",
    "wof:placetype":"venue"
},
  "geometry": {"coordinates":[12.2801532745,55.5803451538],"type":"Point"}
}