{
  "type": "Feature",
  "properties": {
    "addr:full":"Solbakkevej 26, Dalby J\u00e6gerspris Danmark 3630",
    "addr:housenumber":"26",
    "addr:postcode":"3630",
    "addr:street":"Solbakkevej",
    "iso:country":"DK",
    "sg:address":"Solbakkevej 26, Dalby",
    "sg:city":"J\u00e6gerspris",
    "sg:orig_category":"Tandklinikker, Kommunale",
    "sg:phone":"+45 47 52 16 83",
    "sg:postcode":"3630",
    "sg:province":"Danmark",
    "wof:name":"Solbakkeskolens Tandklinik",
    "wof:placetype":"venue"
},
  "geometry": {"coordinates":[11.9136800766,55.9269866943],"type":"Point"}
}