{
  "type": "Feature",
  "properties": {
    "addr:full":"Ny Kongensgade 9 K\u00f8benhavn Danmark 1472",
    "addr:housenumber":"9",
    "addr:postcode":"1472",
    "addr:street":"Kongensgade",
    "iso:country":"DK",
    "sg:address":"Ny Kongensgade 9",
    "sg:city":"K\u00f8benhavn",
    "sg:classifiers":[
        {
            "category":"Professional",
            "subcategory":"Computer Services",
            "type":"Services"
        }
    ],
    "sg:phone":"+45 33 36 90 36",
    "sg:postcode":"1472",
    "sg:province":"Danmark",
    "sg:tags":[
        "edb",
        "-",
        "software"
    ],
    "sg:website":"www.no-panic.dk",
    "wof:name":"No Panic A/S",
    "wof:placetype":"venue"
},
  "geometry": {"coordinates":[12.5766000748,55.6721000671],"type":"Point"}
}