{
  "type": "Feature",
  "properties": {
    "addr:full":"Bollegade 38 Dronninglund Danmark 9330",
    "addr:housenumber":"38",
    "addr:postcode":"9330",
    "addr:street":"Bollegade",
    "iso:country":"DK",
    "sg:address":"Bollegade 38",
    "sg:city":"Dronninglund",
    "sg:orig_category":"Forsikringer",
    "sg:phone":"+45 98 84 15 43",
    "sg:postcode":"9330",
    "sg:province":"Danmark",
    "wof:name":"Stausb\u00f8ll Assurance Forsikringsm\u00e6gler",
    "wof:placetype":"venue"
},
  "geometry": {"coordinates":[10.2585840225,57.1332740784],"type":"Point"}
}