{
  "type": "Feature",
  "properties": {
    "addr:full":"Fmd.: John Christiansen, Strandvejen 9 Thisted Danmark 7700",
    "addr:housenumber":"9",
    "addr:postcode":"7700",
    "addr:street":"Strandvejen",
    "iso:country":"DK",
    "sg:address":"Fmd.: John Christiansen, Strandvejen 9",
    "sg:city":"Thisted",
    "sg:orig_category":"Faglige organisationer og foreninger",
    "sg:phone":"+45 97 91 16 24",
    "sg:postcode":"7700",
    "sg:province":"Danmark",
    "wof:name":"LO, Mors",
    "wof:placetype":"venue"
},
  "geometry": {"coordinates":[8.6919784546,56.9556121826],"type":"Point"}
}