{
  "type": "Feature",
  "properties": {
    "iso:country":"DK",
    "sg:address":"Sandgaardsvej 9, Birk",
    "sg:city":"Herning",
    "sg:orig_category":"Stoffer en gros",
    "sg:phone":"+45 97 21 65 44",
    "sg:postcode":"7400",
    "sg:province":"Danmark",
    "wof:name":"Thomsen Impex",
    "wof:placetype":"venue"
},
  "geometry": {"coordinates":[8.9768896103,56.1374168396],"type":"Point"}
}