{
  "type": "Feature",
  "properties": {
    "addr:full":"Sj\u00e6llandsgade 62 \u00c5rhus C Danmark 8000",
    "addr:housenumber":"62",
    "addr:postcode":"8000",
    "addr:street":"Sjaellandsgade",
    "iso:country":"DK",
    "sg:address":"Sj\u00e6llandsgade 62",
    "sg:city":"\u00c5rhus C",
    "sg:orig_category":"Autoreparation og -service",
    "sg:phone":"+45 86 12 89 40",
    "sg:postcode":"8000",
    "sg:province":"Danmark",
    "wof:name":"Petersens Eftf., Anders",
    "wof:placetype":"venue"
},
  "geometry": {"coordinates":[4.717400074,49.7588005066],"type":"Point"}
}