{
  "type": "Feature",
  "properties": {
    "addr:full":"Jernbanegade 31 B Esbjerg Danmark 6700",
    "addr:housenumber":"31 b",
    "addr:postcode":"6700",
    "addr:street":"Jernbanegade",
    "iso:country":"DK",
    "sg:address":"Jernbanegade 31 B",
    "sg:city":"Esbjerg",
    "sg:orig_category":"Kiosker",
    "sg:phone":"+45 75 13 64 80",
    "sg:postcode":"6700",
    "sg:province":"Danmark",
    "wof:name":"DSB Kioskmarked",
    "wof:placetype":"venue"
},
  "geometry": {"coordinates":[8.4580583572,55.4679832458],"type":"Point"}
}