{
  "type": "Feature",
  "properties": {
    "addr:full":"Skippervej 10, Liv\u00f8 Ranum Danmark 9681",
    "addr:housenumber":"10",
    "addr:postcode":"9681",
    "addr:street":"Skippervej",
    "iso:country":"DK",
    "sg:address":"Skippervej 10, Liv\u00f8",
    "sg:city":"Ranum",
    "sg:orig_category":"Feriecentre",
    "sg:phone":"+45 98 67 63 62",
    "sg:postcode":"9681",
    "sg:province":"Danmark",
    "sg:website":"www.livo.dk",
    "wof:name":"Liv\u00f8 Feriecenter",
    "wof:placetype":"venue"
},
  "geometry": {"coordinates":[9.2287597656,56.8980484009],"type":"Point"}
}