{
  "type": "Feature",
  "properties": {
    "addr:full":"Torvegade 52 Esbjerg Danmark 6700",
    "addr:housenumber":"52",
    "addr:postcode":"6700",
    "addr:street":"Torvegade",
    "iso:country":"DK",
    "sg:address":"Torvegade 52",
    "sg:city":"Esbjerg",
    "sg:orig_category":"Genbrugsbutikker",
    "sg:phone":"+45 75 12 32 63",
    "sg:postcode":"6700",
    "sg:province":"Danmark",
    "wof:name":"I. M. Genbrugsbutik",
    "wof:placetype":"venue"
},
  "geometry": {"coordinates":[8.4528779984,55.4697914124],"type":"Point"}
}