{
  "type": "Feature",
  "properties": {
    "addr:full":"Kj\u00e6rgaardsvej 12 Nyk\u00f8bing Danmark 7900",
    "addr:housenumber":"12",
    "addr:postcode":"7900",
    "addr:street":"Kjaergaardsvej",
    "iso:country":"DK",
    "sg:address":"Kj\u00e6rgaardsvej 12",
    "sg:city":"Nyk\u00f8bing",
    "sg:orig_category":"Hobbyartikler",
    "sg:phone":"+45 97 72 51 16",
    "sg:postcode":"7900",
    "sg:province":"Danmark",
    "wof:name":"Caboosen",
    "wof:placetype":"venue"
},
  "geometry": {"coordinates":[-114.0768203735,46.4432411194],"type":"Point"}
}