{
  "type": "Feature",
  "properties": {
    "addr:full":"Drosselvej 3 Struer Danmark 7600",
    "addr:housenumber":"3",
    "addr:postcode":"7600",
    "addr:street":"Drosselvej",
    "iso:country":"DK",
    "sg:address":"Drosselvej 3",
    "sg:city":"Struer",
    "sg:orig_category":"Skolefritidsordninger",
    "sg:phone":"+45 96 84 09 16",
    "sg:postcode":"7600",
    "sg:province":"Danmark",
    "wof:name":"Kolibrien v/Bremdal Skole",
    "wof:placetype":"venue"
},
  "geometry": {"coordinates":[8.5946903229,56.491191864],"type":"Point"}
}