{
  "type": "Feature",
  "properties": {
    "addr:full":"Kokholm 6 Kolding Danmark 6000",
    "addr:housenumber":"6",
    "addr:postcode":"6000",
    "addr:street":"Kokholm",
    "iso:country":"DK",
    "sg:address":"Kokholm 6",
    "sg:city":"Kolding",
    "sg:orig_category":"Blomster en gros",
    "sg:phone":"+45 76 31 00 76",
    "sg:postcode":"6000",
    "sg:province":"Danmark",
    "sg:website":"www.borgejensen.dk",
    "wof:name":"Jensen A/S, B\u00f8rge",
    "wof:placetype":"venue"
},
  "geometry": {"coordinates":[9.4731216431,55.5327339172],"type":"Point"}
}