{
  "type": "Feature",
  "properties": {
    "addr:full":"Leder: Birthe Geertsen, Langsvej 34, Radsted Saksk\u00f8bing Danmark 4990",
    "addr:housenumber":"34",
    "addr:postcode":"4990",
    "addr:street":"Langsvej",
    "iso:country":"DK",
    "sg:address":"Leder: Birthe Geertsen, Langsvej 34, Radsted",
    "sg:city":"Saksk\u00f8bing",
    "sg:orig_category":"Kulturelle foreninger",
    "sg:phone":"+45 54 70 53 69",
    "sg:postcode":"4990",
    "sg:province":"Danmark",
    "wof:name":"Radsted Aftenh\u00f8jskole",
    "wof:placetype":"venue"
},
  "geometry": {"coordinates":[11.6875448227,54.7894821167],"type":"Point"}
}