{
  "type": "Feature",
  "properties": {
    "iso:country":"DK",
    "sg:address":"Skagen Landevej 82, Bjergby",
    "sg:city":"Hj\u00f8rring",
    "sg:orig_category":"Bagere",
    "sg:phone":"+45 98 97 10 51",
    "sg:postcode":"9800",
    "sg:province":"Danmark",
    "wof:name":"Bjergby Bageri",
    "wof:placetype":"venue"
},
  "geometry": {"coordinates":[9.988539,57.459476],"type":"Point"}
}