{
  "type": "Feature",
  "properties": {
    "addr:full":"Tv\u00e6rbommen 6 Gentofte Danmark 2820",
    "addr:housenumber":"6",
    "addr:postcode":"2820",
    "addr:street":"Tvaerbommen",
    "iso:country":"DK",
    "sg:address":"Tv\u00e6rbommen 6",
    "sg:city":"Gentofte",
    "sg:orig_category":"Dagcentre",
    "sg:phone":"+45 39 68 10 16",
    "sg:postcode":"2820",
    "sg:province":"Danmark",
    "wof:name":"Tv\u00e6rbommen Dagcenter",
    "wof:placetype":"venue"
},
  "geometry": {"coordinates":[12.5213804245,55.7503395081],"type":"Point"}
}