{
  "type": "Feature",
  "properties": {
    "iso:country":"DK",
    "sg:address":"Krokusv\u00e6nget 3",
    "sg:city":"Ullerslev",
    "sg:orig_category":"Revisorer",
    "sg:phone":"+45 65 35 24 48",
    "sg:postcode":"5540",
    "sg:province":"Danmark",
    "wof:name":"PH Revision Ullerslev",
    "wof:placetype":"venue"
},
  "geometry": {"coordinates":[10.6675348282,55.3605728149],"type":"Point"}
}