{
  "type": "Feature",
  "properties": {
    "addr:full":"Vesterbro 85 Aalborg Danmark 9000",
    "addr:housenumber":"85",
    "addr:postcode":"9000",
    "addr:street":"Vesterbro",
    "iso:country":"DK",
    "sg:address":"Vesterbro 85",
    "sg:city":"Aalborg",
    "sg:orig_category":"Optikere",
    "sg:phone":"+45 98 12 33 88",
    "sg:postcode":"9000",
    "sg:province":"Danmark",
    "wof:name":"Anni Optik",
    "wof:placetype":"venue"
},
  "geometry": {"coordinates":[9.9160461426,57.0490722656],"type":"Point"}
}