{
  "type": "Feature",
  "properties": {
    "addr:full":"Amlundvej 4, Lindeballe Gadbjerg Danmark 7321",
    "addr:housenumber":"4",
    "addr:postcode":"7321",
    "addr:street":"Amlundvej",
    "iso:country":"DK",
    "sg:address":"Amlundvej 4, Lindeballe",
    "sg:city":"Gadbjerg",
    "sg:orig_category":"Fotografer",
    "sg:phone":"+45 75 88 54 54",
    "sg:postcode":"7321",
    "sg:province":"Danmark",
    "wof:name":"Benthe's Foto",
    "wof:placetype":"venue"
},
  "geometry": {"coordinates":[9.3234148026,55.7708015442],"type":"Point"}
}