{
  "type": "Feature",
  "properties": {
    "addr:full":"Ellek\u00e6r 5C Herlev Danmark 2730",
    "addr:housenumber":"5c",
    "addr:postcode":"2730",
    "addr:street":"Ellekaer",
    "iso:country":"DK",
    "sg:address":"Ellek\u00e6r 5C",
    "sg:city":"Herlev",
    "sg:orig_category":"Autoforhandlere",
    "sg:phone":"+45 44 94 77 66",
    "sg:postcode":"2730",
    "sg:province":"Danmark",
    "wof:name":"Pava Herlev",
    "wof:placetype":"venue"
},
  "geometry": {"coordinates":[12.4382095337,55.7250595093],"type":"Point"}
}