{
  "type": "Feature",
  "properties": {
    "iso:country":"DK",
    "sg:address":"Slogsherredsvej 39, Bylderup",
    "sg:city":"Bylderup-Bov",
    "sg:orig_category":"Cafeterier",
    "sg:phone":"+45 74 76 29 39",
    "sg:postcode":"6372",
    "sg:province":"Danmark",
    "wof:name":"Bylderup Idr\u00e6tscenter Cafeteria",
    "wof:placetype":"venue"
},
  "geometry": {"coordinates":[9.0861902237,54.941783905],"type":"Point"}
}