{
  "type": "Feature",
  "properties": {
    "addr:full":"Apotekerbakken 16 Hornsyld Danmark 8783",
    "addr:housenumber":"16",
    "addr:postcode":"8783",
    "addr:street":"Apotekerbakken",
    "iso:country":"DK",
    "sg:address":"Apotekerbakken 16",
    "sg:city":"Hornsyld",
    "sg:orig_category":"Arkitekter",
    "sg:phone":"+45 75 68 81 88",
    "sg:postcode":"8783",
    "sg:province":"Danmark",
    "wof:name":"Schmidt, S\u00f8ren",
    "wof:placetype":"venue"
},
  "geometry": {"coordinates":[9.8533763885,55.7551193237],"type":"Point"}
}