{
  "type": "Feature",
  "properties": {
    "iso:country":"DK",
    "sg:address":"Horsens Sygehus, Bygning E, Sundvej 32",
    "sg:city":"Horsens",
    "sg:orig_category":"Jordemodercentre",
    "sg:phone":"+45 79 27 46 26",
    "sg:postcode":"8700",
    "sg:province":"Danmark",
    "wof:name":"Jordemodercentret",
    "wof:placetype":"venue"
},
  "geometry": {"coordinates":[9.8432445526,55.8621063232],"type":"Point"}
}