{
  "type": "Feature",
  "properties": {
    "addr:full":"v/ Niels Knudsen, Kirkeltevej 163 Kokkedal Danmark 2980",
    "addr:housenumber":"163",
    "addr:postcode":"2980",
    "addr:street":"Kirkeltevej",
    "iso:country":"DK",
    "sg:address":"v/ Niels Knudsen, Kirkeltevej 163",
    "sg:city":"Kokkedal",
    "sg:orig_category":"\u00c3\u02dcvrige foreninger",
    "sg:phone":"+45 48 28 02 78",
    "sg:postcode":"2980",
    "sg:province":"Danmark",
    "wof:name":"Gunder\u00f8d Sammenslutningen",
    "wof:placetype":"venue"
},
  "geometry": {"coordinates":[12.4769096375,55.9091339111],"type":"Point"}
}