{
  "type": "Feature",
  "properties": {
    "addr:full":"Torvegade 16, Tommerup St Tommerup Danmark 5690",
    "addr:housenumber":"16",
    "addr:postcode":"5690",
    "addr:street":"Torvegade;St",
    "iso:country":"DK",
    "sg:address":"Torvegade 16, Tommerup St",
    "sg:city":"Tommerup",
    "sg:orig_category":"Vinduespolering",
    "sg:phone":"+45 64 76 11 99",
    "sg:postcode":"5690",
    "sg:province":"Danmark",
    "wof:name":"Grevens Vinduespolering",
    "wof:placetype":"venue"
},
  "geometry": {"coordinates":[10.2489509583,55.3236503601],"type":"Point"}
}