{
  "type": "Feature",
  "properties": {
    "addr:full":"Politiass. J\u00f8rgen Overgaard, Ballevej 39 Bredsten Danmark 7182",
    "addr:housenumber":"39",
    "addr:postcode":"7182",
    "addr:street":"Ballevej",
    "iso:country":"DK",
    "sg:address":"Politiass. J\u00f8rgen Overgaard, Ballevej 39",
    "sg:city":"Bredsten",
    "sg:orig_category":"Politi",
    "sg:phone":"+45 75 88 20 80",
    "sg:postcode":"7182",
    "sg:province":"Danmark",
    "wof:name":"Politikontoret i Bredsten",
    "wof:placetype":"venue"
},
  "geometry": {"coordinates":[9.3807411194,55.702331543],"type":"Point"}
}