{
  "type": "Feature",
  "properties": {
    "addr:full":"Vester Farimagsgade 6, 1 sal K\u00f8benhavn Danmark 1606",
    "addr:housenumber":"6 1 sal",
    "addr:postcode":"1606",
    "addr:street":"Vester Farimagsgade",
    "iso:country":"DK",
    "sg:address":"Vester Farimagsgade 6, 1 sal",
    "sg:city":"K\u00f8benhavn",
    "sg:orig_category":"Rejsebureauer",
    "sg:phone":"+45 70 10 62 77",
    "sg:postcode":"1606",
    "sg:province":"Danmark",
    "sg:website":"www.hellas-travel.dk",
    "wof:name":"Hellas Travel",
    "wof:placetype":"venue"
},
  "geometry": {"coordinates":[12.5636997223,55.6749992371],"type":"Point"}
}