{
  "type": "Feature",
  "properties": {
    "iso:country":"DK",
    "sg:address":"Algade 20",
    "sg:city":"Vordingborg",
    "sg:orig_category":"Ejendomshandel",
    "sg:phone":"+45 55 37 11 95",
    "sg:postcode":"4760",
    "sg:province":"Danmark",
    "sg:website":"www.home.dk",
    "wof:name":"Home - Henrik Ejby ApS & Per E. Hansen",
    "wof:placetype":"venue"
},
  "geometry": {"coordinates":[11.9030771255,55.0117530823],"type":"Point"}
}