{
  "type": "Feature",
  "properties": {
    "addr:full":"Dysseg\u00e5rdsvej 32 Gadstrup Danmark 4621",
    "addr:housenumber":"32",
    "addr:postcode":"4621",
    "addr:street":"Dyssegaardsvej",
    "iso:country":"DK",
    "sg:address":"Dysseg\u00e5rdsvej 32",
    "sg:city":"Gadstrup",
    "sg:orig_category":"Brugsforeninger",
    "sg:phone":"+45 46 19 00 03",
    "sg:postcode":"4621",
    "sg:province":"Danmark",
    "wof:name":"Gadstrup SuperBrugsen",
    "wof:placetype":"venue"
},
  "geometry": {"coordinates":[12.0932292938,55.5681724548],"type":"Point"}
}