{
  "type": "Feature",
  "properties": {
    "addr:full":"Kirketerpvej 48, Kirketerp Suldrup Danmark 9541",
    "addr:housenumber":"48",
    "addr:postcode":"9541",
    "addr:street":"Kirketerpvej",
    "iso:country":"DK",
    "sg:address":"Kirketerpvej 48, Kirketerp",
    "sg:city":"Suldrup",
    "sg:orig_category":"Autoreparation og -service",
    "sg:phone":"+45 98 38 71 76",
    "sg:postcode":"9541",
    "sg:province":"Danmark",
    "wof:name":"Kirketerp Auto- & Traktorservice",
    "wof:placetype":"venue"
},
  "geometry": {"coordinates":[9.701379776,56.8489303589],"type":"Point"}
}