{
  "type": "Feature",
  "properties": {
    "addr:full":"Langegade 18 Kerteminde Danmark 5300",
    "addr:housenumber":"18",
    "addr:postcode":"5300",
    "addr:street":"Langegade",
    "iso:country":"DK",
    "sg:address":"Langegade 18",
    "sg:city":"Kerteminde",
    "sg:orig_category":"Blomsterhandlere",
    "sg:phone":"+45 65 32 15 62",
    "sg:postcode":"5300",
    "sg:province":"Danmark",
    "wof:name":"Torvebutikken",
    "wof:placetype":"venue"
},
  "geometry": {"coordinates":[10.6580247879,55.4502449036],"type":"Point"}
}