{
  "type": "Feature",
  "properties": {
    "iso:country":"DK",
    "sg:address":"H. P. Hanssens Gade 5",
    "sg:city":"Aabenraa",
    "sg:orig_category":"Turistbureau og -information",
    "sg:phone":"+45 74 62 35 00",
    "sg:postcode":"6200",
    "sg:province":"Danmark",
    "wof:name":"Aabenraa Turistbureau",
    "wof:placetype":"venue"
},
  "geometry": {"coordinates":[9.4197635651,55.0480041504],"type":"Point"}
}