{
  "type": "Feature",
  "properties": {
    "iso:country":"DK",
    "sg:address":"S\u00f8ndergade 62 C",
    "sg:city":"Frederikshavn",
    "sg:orig_category":"Hudplejeklinikker",
    "sg:phone":"+45 98 43 41 22",
    "sg:postcode":"9900",
    "sg:province":"Danmark",
    "wof:name":"Fod- og Hudplejeklinikken",
    "wof:placetype":"venue"
},
  "geometry": {"coordinates":[10.528834343,57.433719635],"type":"Point"}
}