{
  "type": "Feature",
  "properties": {
    "iso:country":"DK",
    "sg:address":"Hobrovej 46",
    "sg:city":"Nibe",
    "sg:orig_category":"Varmeforsyning",
    "sg:phone":"+45 98 35 14 09",
    "sg:postcode":"9240",
    "sg:province":"Danmark",
    "wof:name":"Nibe varmev\u00e6rk A.m.b.A.",
    "wof:placetype":"venue"
},
  "geometry": {"coordinates":[9.655538559,56.97631073],"type":"Point"}
}