{
  "type": "Feature",
  "properties": {
    "addr:full":"Vestre Ringgade 150 \u00c5rhus C Danmark 8000",
    "addr:housenumber":"150",
    "addr:postcode":"8000",
    "addr:street":"Vestre Ringgade",
    "iso:country":"DK",
    "sg:address":"Vestre Ringgade 150",
    "sg:city":"\u00c5rhus C",
    "sg:orig_category":"Revisorer",
    "sg:phone":"+45 86 13 16 00",
    "sg:postcode":"8000",
    "sg:province":"Danmark",
    "wof:name":"Benjaminsen, Gunnar",
    "wof:placetype":"venue"
},
  "geometry": {"coordinates":[6.8762898445,62.4602813721],"type":"Point"}
}