{
  "type": "Feature",
  "properties": {
    "addr:full":"Teglv\u00e6rksvej 3 Gudbjerg Danmark 5892",
    "addr:housenumber":"3",
    "addr:postcode":"5892",
    "addr:street":"Teglvaerksvej",
    "iso:country":"DK",
    "sg:address":"Teglv\u00e6rksvej 3",
    "sg:city":"Gudbjerg",
    "sg:orig_category":"Brugsforeninger",
    "sg:phone":"+45 62 25 17 07",
    "sg:postcode":"5892",
    "sg:province":"Danmark",
    "wof:name":"Brugsen, Gudbjerg",
    "wof:placetype":"venue"
},
  "geometry": {"coordinates":[10.6741666794,55.154586792],"type":"Point"}
}