{
  "type": "Feature",
  "properties": {
    "addr:full":"Badstuegade 2 B Ribe Danmark 6760",
    "addr:housenumber":"2 b",
    "addr:postcode":"6760",
    "addr:street":"Badstuegade",
    "iso:country":"DK",
    "sg:address":"Badstuegade 2 B",
    "sg:city":"Ribe",
    "sg:orig_category":"Indramning",
    "sg:phone":"+45 75 42 03 17",
    "sg:postcode":"6760",
    "sg:province":"Danmark",
    "wof:name":"Lauridsen og S\u00f8ns Eftf., Asberg",
    "wof:placetype":"venue"
},
  "geometry": {"coordinates":[8.7636041641,55.3273620605],"type":"Point"}
}