{
  "type": "Feature",
  "properties": {
    "addr:full":"\u00d8stre Alle 6 C Gilleleje Danmark 3250",
    "addr:housenumber":"6 c",
    "addr:postcode":"3250",
    "addr:street":"Ostre Alle",
    "iso:country":"DK",
    "sg:address":"\u00d8stre Alle 6 C",
    "sg:city":"Gilleleje",
    "sg:orig_category":"Murermestre",
    "sg:phone":"+45 48 30 09 01",
    "sg:postcode":"3250",
    "sg:province":"Danmark",
    "wof:name":"Andersen & S\u00f8n, Julius",
    "wof:placetype":"venue"
},
  "geometry": {"coordinates":[12.3148555756,56.1215858459],"type":"Point"}
}