{
  "type": "Feature",
  "properties": {
    "addr:full":"M\u00f8llegade 12 H\u00f8jer Danmark 6280",
    "addr:housenumber":"12",
    "addr:postcode":"6280",
    "addr:street":"Mollegade",
    "iso:country":"DK",
    "sg:address":"M\u00f8llegade 12",
    "sg:city":"H\u00f8jer",
    "sg:orig_category":"Museer",
    "sg:phone":"+45 74 78 92 22",
    "sg:postcode":"6280",
    "sg:province":"Danmark",
    "sg:website":"www.sns.dk/lindet",
    "wof:name":"T\u00f8ndermarskens NaturCenter",
    "wof:placetype":"venue"
},
  "geometry": {"coordinates":[-2.1972899437,49.2049789429],"type":"Point"}
}