{
  "type": "Feature",
  "properties": {
    "addr:full":"Anemonevej 6 Nakskov Danmark 4900",
    "addr:housenumber":"6",
    "addr:postcode":"4900",
    "addr:street":"Anemonevej",
    "iso:country":"DK",
    "sg:address":"Anemonevej 6",
    "sg:city":"Nakskov",
    "sg:orig_category":"Integrerede institutioner",
    "sg:phone":"+45 54 92 32 56",
    "sg:postcode":"4900",
    "sg:province":"Danmark",
    "sg:website":"www.nakskov.dk",
    "wof:name":"Dagcenter Falken",
    "wof:placetype":"venue"
},
  "geometry": {"coordinates":[11.1350545883,54.8420677185],"type":"Point"}
}