{
  "type": "Feature",
  "properties": {
    "addr:full":"Fmd.: Jimmy Thomsen, Hybenv\u00e6nget 12, Vellerup Skibby Danmark 4050",
    "addr:housenumber":"12",
    "addr:postcode":"4050",
    "addr:street":"Hybenvaenget",
    "iso:country":"DK",
    "sg:address":"Fmd.: Jimmy Thomsen, Hybenv\u00e6nget 12, Vellerup",
    "sg:city":"Skibby",
    "sg:orig_category":"Politiske foreninger, \u00c3\u02dcvrige",
    "sg:phone":"+45 47 52 96 10",
    "sg:postcode":"4050",
    "sg:province":"Danmark",
    "wof:name":"Konservativ Ungdom",
    "wof:placetype":"venue"
},
  "geometry": {"coordinates":[11.9594116211,55.7502975464],"type":"Point"}
}