{
  "type": "Feature",
  "properties": {
    "iso:country":"DK",
    "sg:address":"Alstrup Alle 9",
    "sg:city":"Hasselager",
    "sg:orig_category":"Adgangskontrolsystemer",
    "sg:phone":"+45 86 28 00 77",
    "sg:postcode":"8361",
    "sg:province":"Danmark",
    "sg:website":"www.faci.dk",
    "wof:name":"Faci A/S",
    "wof:placetype":"venue"
},
  "geometry": {"coordinates":[10.095334053,56.1029624939],"type":"Point"}
}