{
  "type": "Feature",
  "properties": {
    "iso:country":"DK",
    "sg:address":"v/ Lanni Rindahl, Lundh\u00f8jvej 3, Everdrup",
    "sg:city":"Tappern\u00f8je",
    "sg:orig_category":"Grundejerforeninger",
    "sg:phone":"+45 55 56 58 60",
    "sg:postcode":"4733",
    "sg:province":"Danmark",
    "wof:name":"Grundejerforeningen Kildelund",
    "wof:placetype":"venue"
},
  "geometry": {"coordinates":[11.9756202698,55.1781692505],"type":"Point"}
}