{
  "type": "Feature",
  "properties": {
    "addr:full":"Reberbanen 61 Marstal Danmark 5960",
    "addr:housenumber":"61",
    "addr:postcode":"5960",
    "addr:street":"Reberbanen",
    "iso:country":"DK",
    "sg:address":"Reberbanen 61",
    "sg:city":"Marstal",
    "sg:orig_category":"Autoreparation og -service",
    "sg:phone":"+45 62 53 17 20",
    "sg:postcode":"5960",
    "sg:province":"Danmark",
    "wof:name":"Autog\u00e5rden",
    "wof:placetype":"venue"
},
  "geometry": {"coordinates":[10.5010299683,54.8498268127],"type":"Point"}
}