{
  "type": "Feature",
  "properties": {
    "addr:full":"Viborgvej 16 Holstebro Danmark 7500",
    "addr:housenumber":"16",
    "addr:postcode":"7500",
    "addr:street":"Viborgvej",
    "iso:country":"DK",
    "sg:address":"Viborgvej 16",
    "sg:city":"Holstebro",
    "sg:orig_category":"Begravelsesforretninger",
    "sg:phone":"+45 97 42 09 11",
    "sg:postcode":"7500",
    "sg:province":"Danmark",
    "sg:website":"www.gaardhoeje.dk",
    "wof:name":"Gaardh\u00f8je Begravelsesforretning",
    "wof:placetype":"venue"
},
  "geometry": {"coordinates":[8.631364,56.358974],"type":"Point"}
}