{
  "type": "Feature",
  "properties": {
    "addr:full":"Vangedevej 132 Gentofte Danmark 2820",
    "addr:housenumber":"132",
    "addr:postcode":"2820",
    "addr:street":"Vangedevej",
    "iso:country":"DK",
    "sg:address":"Vangedevej 132",
    "sg:city":"Gentofte",
    "sg:orig_category":"Servicestationer",
    "sg:phone":"+45 39 67 84 50",
    "sg:postcode":"2820",
    "sg:province":"Danmark",
    "wof:name":"Q8 Service",
    "wof:placetype":"venue"
},
  "geometry": {"coordinates":[12.5232582092,55.7407073975],"type":"Point"}
}