{
  "type": "Feature",
  "properties": {
    "addr:full":"Skovvejen 34 B Bjerringbro Danmark 8850",
    "addr:housenumber":"34 b",
    "addr:postcode":"8850",
    "addr:street":"Skovvejen",
    "iso:country":"DK",
    "sg:address":"Skovvejen 34 B",
    "sg:city":"Bjerringbro",
    "sg:orig_category":"Psykologer, praktiserende",
    "sg:phone":"+45 86 68 00 19",
    "sg:postcode":"8850",
    "sg:province":"Danmark",
    "wof:name":"Kruse, Lykke",
    "wof:placetype":"venue"
},
  "geometry": {"coordinates":[9.6523609161,56.3775558472],"type":"Point"}
}