{
  "type": "Feature",
  "properties": {
    "addr:full":"Alsgade 3 S\u00f8nderborg Danmark 6400",
    "addr:housenumber":"3",
    "addr:postcode":"6400",
    "addr:street":"Alsgade",
    "iso:country":"DK",
    "sg:address":"Alsgade 3",
    "sg:city":"S\u00f8nderborg",
    "sg:orig_category":"Blomsterhandlere",
    "sg:phone":"+45 74 42 23 19",
    "sg:postcode":"6400",
    "sg:province":"Danmark",
    "wof:name":"Blomsterhj\u00f8rnet",
    "wof:placetype":"venue"
},
  "geometry": {"coordinates":[9.7968263626,54.9142570496],"type":"Point"}
}