{
  "type": "Feature",
  "properties": {
    "iso:country":"DK",
    "sg:address":"Fabriksvej 1",
    "sg:city":"Vamdrup",
    "sg:orig_category":"Blikkenslagere",
    "sg:phone":"+45 75 58 24 01",
    "sg:postcode":"6580",
    "sg:province":"Danmark",
    "wof:name":"E. K. Blik",
    "wof:placetype":"venue"
},
  "geometry": {"coordinates":[9.298152,55.432732],"type":"Point"}
}