{
  "type": "Feature",
  "properties": {
    "addr:full":"Nakskovvej 1 Herning Danmark 7400",
    "addr:housenumber":"1",
    "addr:postcode":"7400",
    "addr:street":"Nakskovvej",
    "iso:country":"DK",
    "sg:address":"Nakskovvej 1",
    "sg:city":"Herning",
    "sg:orig_category":"Tekstilindustri",
    "sg:phone":"+45 96 26 32 00",
    "sg:postcode":"7400",
    "sg:province":"Danmark",
    "wof:name":"Clipper A/S",
    "wof:placetype":"venue"
},
  "geometry": {"coordinates":[8.9910793304,56.1525344849],"type":"Point"}
}