{
  "type": "Feature",
  "properties": {
    "addr:full":"Kongensvej 7 Frederiksberg Danmark 2000",
    "addr:housenumber":"7",
    "addr:postcode":"2000",
    "addr:street":"Kongensvej",
    "iso:country":"DK",
    "sg:address":"Kongensvej 7",
    "sg:city":"Frederiksberg",
    "sg:orig_category":"Virksomhedskonsulenter",
    "sg:phone":"+45 20 70 40 55",
    "sg:postcode":"2000",
    "sg:province":"Danmark",
    "wof:name":"Holte, Michael",
    "wof:placetype":"venue"
},
  "geometry": {"coordinates":[12.518872261,55.6769142151],"type":"Point"}
}