{
  "type": "Feature",
  "properties": {
    "iso:country":"DK",
    "sg:address":"S\u00f8ndergade 17",
    "sg:city":"Haslev",
    "sg:orig_category":"Vinduespolering",
    "sg:phone":"+45 40 68 63 20",
    "sg:postcode":"4690",
    "sg:province":"Danmark",
    "wof:name":"Renohvidt",
    "wof:placetype":"venue"
},
  "geometry": {"coordinates":[11.9578924179,55.3248786926],"type":"Point"}
}