{
  "type": "Feature",
  "properties": {
    "addr:full":"Jyllandsgade 30, 1. Aalborg Danmark 9000",
    "addr:housenumber":"30 1",
    "addr:postcode":"9000",
    "addr:street":"Jyllandsgade",
    "iso:country":"DK",
    "sg:address":"Jyllandsgade 30, 1.",
    "sg:city":"Aalborg",
    "sg:orig_category":"Motionscentre",
    "sg:phone":"+45 98 13 06 11",
    "sg:postcode":"9000",
    "sg:province":"Danmark",
    "wof:name":"fitness dk",
    "wof:placetype":"venue"
},
  "geometry": {"coordinates":[9.9295148849,57.042339325],"type":"Point"}
}