{
  "type": "Feature",
  "properties": {
    "addr:full":"Stenmarksvej 26, Hune Blokhus Danmark 9492",
    "addr:housenumber":"26",
    "addr:postcode":"9492",
    "addr:street":"Stenmarksvej;Hune",
    "iso:country":"DK",
    "sg:address":"Stenmarksvej 26, Hune",
    "sg:city":"Blokhus",
    "sg:orig_category":"Genbrugspladser",
    "sg:postcode":"9492",
    "sg:province":"Danmark",
    "wof:name":"Hune N\u00e6rgenbrugsplads",
    "wof:placetype":"venue"
},
  "geometry": {"coordinates":[9.5916996002,57.250995636],"type":"Point"}
}