{
  "type": "Feature",
  "properties": {
    "iso:country":"DK",
    "sg:address":"Kannikegade 14, 1.",
    "sg:city":"\u00c5rhus C",
    "sg:orig_category":"Advokater",
    "sg:phone":"+45 86 13 88 33",
    "sg:postcode":"8000",
    "sg:province":"Danmark",
    "sg:website":"www.advokat-balle.dk",
    "wof:name":"Balle, Torben",
    "wof:placetype":"venue"
},
  "geometry": {"coordinates":[4.717400074,49.7588005066],"type":"Point"}
}