{
  "type": "Feature",
  "properties": {
    "addr:full":"Murervej 10 Esbjerg V Danmark 6710",
    "addr:housenumber":"10",
    "addr:postcode":"6710",
    "addr:street":"Murervej",
    "iso:country":"DK",
    "sg:address":"Murervej 10",
    "sg:city":"Esbjerg V",
    "sg:orig_category":"Reklamebureauer",
    "sg:phone":"+45 75 15 10 00",
    "sg:postcode":"6710",
    "sg:province":"Danmark",
    "wof:name":"Prehn Grafisk Tegnestue",
    "wof:placetype":"venue"
},
  "geometry": {"coordinates":[8.4130849838,55.5067749023],"type":"Point"}
}