{
  "type": "Feature",
  "properties": {
    "addr:full":"Langelinie 98 Odense M Danmark 5230",
    "addr:housenumber":"98",
    "addr:postcode":"5230",
    "addr:street":"Langelinie",
    "iso:country":"DK",
    "sg:address":"Langelinie 98",
    "sg:city":"Odense M",
    "sg:orig_category":"Arkitekter",
    "sg:phone":"+45 65 91 53 80",
    "sg:postcode":"5230",
    "sg:province":"Danmark",
    "wof:name":"Madsen, Carsten Dam",
    "wof:placetype":"venue"
},
  "geometry": {"coordinates":[10.3769741058,55.3792266846],"type":"Point"}
}