{
  "type": "Feature",
  "properties": {
    "addr:full":"Skivevej 103 Viborg Danmark 8800",
    "addr:housenumber":"103",
    "addr:postcode":"8800",
    "addr:street":"Skivevej",
    "iso:country":"DK",
    "sg:address":"Skivevej 103",
    "sg:city":"Viborg",
    "sg:orig_category":"Revisorer",
    "sg:phone":"+45 86 62 12 88",
    "sg:postcode":"8800",
    "sg:province":"Danmark",
    "wof:name":"Revicon, Revisionsfirmaet",
    "wof:placetype":"venue"
},
  "geometry": {"coordinates":[9.3735027313,56.4833374023],"type":"Point"}
}