{
  "type": "Feature",
  "properties": {
    "addr:full":"Fmd.: Helge Jansson, Egebjergvej 55 Ballerup Danmark 2750",
    "addr:housenumber":"55",
    "addr:postcode":"2750",
    "addr:street":"Egebjergvej",
    "iso:country":"DK",
    "sg:address":"Fmd.: Helge Jansson, Egebjergvej 55",
    "sg:city":"Ballerup",
    "sg:orig_category":"\u00c3\u2020ldreorganisationer og klubber",
    "sg:phone":"+45 44 97 79 08",
    "sg:postcode":"2750",
    "sg:province":"Danmark",
    "wof:name":"Eftermiddagsklubben Egebjerg",
    "wof:placetype":"venue"
},
  "geometry": {"coordinates":[12.361000061,55.7301216125],"type":"Point"}
}