{
  "type": "Feature",
  "properties": {
    "iso:country":"DK",
    "sg:address":"Vesselbjergvej 8",
    "sg:city":"Hadsten",
    "sg:orig_category":"Apoteker og -udsalg",
    "sg:phone":"+45 86 98 11 22",
    "sg:postcode":"8370",
    "sg:province":"Danmark",
    "wof:name":"Hadsten Apotek",
    "wof:placetype":"venue"
},
  "geometry": {"coordinates":[10.0495023727,56.327999115],"type":"Point"}
}