{
  "type": "Feature",
  "properties": {
    "addr:full":"Centerpladsen 11 Tinglev Danmark 6360",
    "addr:housenumber":"11",
    "addr:postcode":"6360",
    "addr:street":"Centerpladsen",
    "iso:country":"DK",
    "sg:address":"Centerpladsen 11",
    "sg:city":"Tinglev",
    "sg:orig_category":"Farve og tapet",
    "sg:phone":"+45 74 64 42 18",
    "sg:postcode":"6360",
    "sg:province":"Danmark",
    "wof:name":"Vor Malers Farvehandel",
    "wof:placetype":"venue"
},
  "geometry": {"coordinates":[9.254160881,54.93724823],"type":"Point"}
}