{
  "type": "Feature",
  "properties": {
    "addr:full":"T\u00e5rsvej 90 Harpelunde Danmark 4912",
    "addr:housenumber":"90",
    "addr:postcode":"4912",
    "addr:street":"Taarsvej",
    "iso:country":"DK",
    "sg:address":"T\u00e5rsvej 90",
    "sg:city":"Harpelunde",
    "sg:orig_category":"Integrerede institutioner",
    "sg:phone":"+45 54 93 13 19",
    "sg:postcode":"4912",
    "sg:province":"Danmark",
    "wof:name":"Snurretoppen",
    "wof:placetype":"venue"
},
  "geometry": {"coordinates":[11.0755901337,54.879322052],"type":"Point"}
}