{
  "type": "Feature",
  "properties": {
    "iso:country":"DK",
    "sg:address":"Kanalens Kvarter 98",
    "sg:city":"Albertslund",
    "sg:orig_category":"Borger- og beboerforeninger",
    "sg:phone":"+45 43 64 61 84",
    "sg:postcode":"2620",
    "sg:province":"Danmark",
    "wof:name":"Albertslund Boligselskabs Beboerr\u00e5dgivning",
    "wof:placetype":"venue"
},
  "geometry": {"coordinates":[12.3438529968,55.6541404724],"type":"Point"}
}