{
  "type": "Feature",
  "properties": {
    "addr:full":"Vestergade 4 Faaborg Danmark 5600",
    "addr:housenumber":"4",
    "addr:postcode":"5600",
    "addr:street":"Vestergade",
    "iso:country":"DK",
    "sg:address":"Vestergade 4",
    "sg:city":"Faaborg",
    "sg:classifiers":[
        {
            "category":"Banks & Credit Unions",
            "subcategory":"Bank",
            "type":"Services"
        }
    ],
    "sg:phone":"+45 63 61 22 00",
    "sg:postcode":"5600",
    "sg:province":"Danmark",
    "sg:tags":[
        "banker"
    ],
    "wof:name":"BG Bank",
    "wof:placetype":"venue"
},
  "geometry": {"coordinates":[10.241191,55.096386],"type":"Point"}
}