{
  "type": "Feature",
  "properties": {
    "iso:country":"DK",
    "sg:address":"Svanningevej 10",
    "sg:city":"Aalborg \u00d8",
    "sg:orig_category":"Vaskeriservice",
    "sg:phone":"+45 98 15 45 55",
    "sg:postcode":"9220",
    "sg:province":"Danmark",
    "wof:name":"Berendtsen Textil Service A/S",
    "wof:placetype":"venue"
},
  "geometry": {"coordinates":[10.0246219635,57.0358848572],"type":"Point"}
}