{
  "type": "Feature",
  "properties": {
    "iso:country":"DK",
    "sg:address":"Gasv\u00e6rksvej 48",
    "sg:city":"Aalborg",
    "sg:orig_category":"Rederier",
    "sg:postcode":"9000",
    "sg:province":"Danmark",
    "wof:name":"Fajal, K/S",
    "wof:placetype":"venue"
},
  "geometry": {"coordinates":[9.9595775604,57.0528907776],"type":"Point"}
}