{
  "type": "Feature",
  "properties": {
    "iso:country":"DK",
    "sg:address":"Nytorv 7, 4.",
    "sg:city":"Aalborg",
    "sg:orig_category":"Advokater",
    "sg:phone":"+45 96 31 20 10",
    "sg:postcode":"9000",
    "sg:province":"Danmark",
    "wof:name":"Advokaterne",
    "wof:placetype":"venue"
},
  "geometry": {"coordinates":[9.9229660034,57.0484924316],"type":"Point"}
}