{
  "type": "Feature",
  "properties": {
    "addr:full":"Fmd.. Ruth Wilken Pedersen, N\u00f8rre Boulevard 2, st. Nyk\u00f8bing Danmark 4800",
    "addr:housenumber":"2",
    "addr:postcode":"4800",
    "addr:street":"Norre Boulevard",
    "iso:country":"DK",
    "sg:address":"Fmd.. Ruth Wilken Pedersen, N\u00f8rre Boulevard 2, st.",
    "sg:city":"Nyk\u00f8bing",
    "sg:orig_category":"Musik og sang",
    "sg:phone":"+45 54 85 01 13",
    "sg:postcode":"4800",
    "sg:province":"Danmark",
    "wof:name":"Egnskoret, Nyk\u00f8bing F.",
    "wof:placetype":"venue"
},
  "geometry": {"coordinates":[-59.9538612366,-24.6677494049],"type":"Point"}
}