{
  "type": "Feature",
  "properties": {
    "addr:full":"Danasvej 2 Frederiksberg Danmark 1910",
    "addr:housenumber":"2",
    "addr:postcode":"1910",
    "addr:street":"Danasvej",
    "iso:country":"DK",
    "sg:address":"Danasvej 2",
    "sg:city":"Frederiksberg",
    "sg:orig_category":"Designere",
    "sg:phone":"+45 33 25 15 88",
    "sg:postcode":"1910",
    "sg:province":"Danmark",
    "wof:name":"5C, Tegnestuen",
    "wof:placetype":"venue"
},
  "geometry": {"coordinates":[12.5561294556,55.6782646179],"type":"Point"}
}