{
  "type": "Feature",
  "properties": {
    "addr:full":"Hovvej 26 Esperg\u00e6rde Danmark 3060",
    "addr:housenumber":"26",
    "addr:postcode":"3060",
    "addr:street":"Hovvej",
    "iso:country":"DK",
    "sg:address":"Hovvej 26",
    "sg:city":"Esperg\u00e6rde",
    "sg:orig_category":"Benzinstationer",
    "sg:phone":"+45 49 13 19 78",
    "sg:postcode":"3060",
    "sg:province":"Danmark",
    "wof:name":"Q8",
    "wof:placetype":"venue"
},
  "geometry": {"coordinates":[11.65124,47.839062],"type":"Point"}
}