{
  "type": "Feature",
  "properties": {
    "iso:country":"DK",
    "sg:address":"Fmd.: Karen Schmidt, Kobbelled 2, Kegn\u00e6s",
    "sg:city":"Sydals",
    "sg:orig_category":"Kirkelige foreninger",
    "sg:phone":"+45 74 40 52 23",
    "sg:postcode":"6470",
    "sg:province":"Danmark",
    "wof:name":"Indre Mission, Kegn\u00e6s",
    "wof:placetype":"venue"
},
  "geometry": {"coordinates":[9.8924627304,54.9105377197],"type":"Point"}
}