{
  "type": "Feature",
  "properties": {
    "addr:full":"Skibhusvej 105 Odense C Danmark 5000",
    "addr:housenumber":"105",
    "addr:postcode":"5000",
    "addr:street":"Skibhusvej",
    "iso:country":"DK",
    "sg:address":"Skibhusvej 105",
    "sg:city":"Odense C",
    "sg:orig_category":"Erhvervslokaler, Udlejning af",
    "sg:postcode":"5000",
    "sg:province":"Danmark",
    "wof:name":"Ejendommen Skibshusvej 105",
    "wof:placetype":"venue"
},
  "geometry": {"coordinates":[10.3937540054,55.4090614319],"type":"Point"}
}