{
  "type": "Feature",
  "properties": {
    "addr:full":"Vinkelvej 18 Sor\u00f8 Danmark 4180",
    "addr:housenumber":"18",
    "addr:postcode":"4180",
    "addr:street":"Vinkelvej",
    "iso:country":"DK",
    "sg:address":"Vinkelvej 18",
    "sg:city":"Sor\u00f8",
    "sg:orig_category":"Psykoterapi",
    "sg:phone":"+45 23 62 37 67",
    "sg:postcode":"4180",
    "sg:province":"Danmark",
    "wof:name":"Olsen, Per G.",
    "wof:placetype":"venue"
},
  "geometry": {"coordinates":[-102.94467926030001,45.4534721375],"type":"Point"}
}