{
  "type": "Feature",
  "properties": {
    "addr:full":"Vester\u00e5 1, 2 Aalborg Danmark 9000",
    "addr:housenumber":"1 2",
    "addr:postcode":"9000",
    "addr:street":"Vesteraa",
    "iso:country":"DK",
    "sg:address":"Vester\u00e5 1, 2",
    "sg:city":"Aalborg",
    "sg:orig_category":"Faglige organisationer og foreninger",
    "sg:phone":"+45 98 16 85 00",
    "sg:postcode":"9000",
    "sg:province":"Danmark",
    "wof:name":"FTF-A Nordjylland",
    "wof:placetype":"venue"
},
  "geometry": {"coordinates":[9.9174890518,57.0495643616],"type":"Point"}
}