{
  "type": "Feature",
  "properties": {
    "addr:full":"Kirkebjergvej 2, Tved Knebel Danmark 8420",
    "addr:housenumber":"2",
    "addr:postcode":"8420",
    "addr:street":"Kirkebjergvej;Tved",
    "iso:country":"DK",
    "sg:address":"Kirkebjergvej 2, Tved",
    "sg:city":"Knebel",
    "sg:orig_category":"Astrologi",
    "sg:phone":"+45 87 52 55 60",
    "sg:postcode":"8420",
    "sg:province":"Danmark",
    "wof:name":"Titanis, Helle",
    "wof:placetype":"venue"
},
  "geometry": {"coordinates":[10.3770122528,56.1816596985],"type":"Point"}
}