{
  "type": "Feature",
  "properties": {
    "addr:full":"St\u00e6rmoseg\u00e5rdsvej 6 Odense M Danmark 5230",
    "addr:housenumber":"6",
    "addr:postcode":"5230",
    "addr:street":"Staermosegaardsvej",
    "iso:country":"DK",
    "sg:address":"St\u00e6rmoseg\u00e5rdsvej 6",
    "sg:city":"Odense M",
    "sg:orig_category":"Forskningscentre",
    "sg:phone":"+45 65 57 20 00",
    "sg:postcode":"5230",
    "sg:province":"Danmark",
    "wof:name":"MDS Protana A/S",
    "wof:placetype":"venue"
},
  "geometry": {"coordinates":[10.3966598511,55.3816184998],"type":"Point"}
}