{
  "type": "Feature",
  "properties": {
    "iso:country":"DK",
    "sg:address":"Storegade 225",
    "sg:city":"Esbjerg \u00d8",
    "sg:orig_category":"Servicestationer",
    "sg:phone":"+45 75 12 44 00",
    "sg:postcode":"6705",
    "sg:province":"Danmark",
    "wof:name":"Q8 Service",
    "wof:placetype":"venue"
},
  "geometry": {"coordinates":[8.4925470352,55.4786262512],"type":"Point"}
}