{
  "type": "Feature",
  "properties": {
    "iso:country":"DK",
    "sg:address":"\u00d8stergade 25",
    "sg:city":"Kolding",
    "sg:orig_category":"Sko",
    "sg:phone":"+45 75 52 60 60",
    "sg:postcode":"6000",
    "sg:province":"Danmark",
    "wof:name":"Bianco Footwear",
    "wof:placetype":"venue"
},
  "geometry": {"coordinates":[9.5337152481,55.5046882629],"type":"Point"}
}