{
  "type": "Feature",
  "properties": {
    "addr:full":"Kildebovej 16 Ringsted Danmark 4100",
    "addr:housenumber":"16",
    "addr:postcode":"4100",
    "addr:street":"Kildebovej",
    "iso:country":"DK",
    "sg:address":"Kildebovej 16",
    "sg:city":"Ringsted",
    "sg:orig_category":"Vuggestuer",
    "sg:phone":"+45 57 62 71 60",
    "sg:postcode":"4100",
    "sg:province":"Danmark",
    "wof:name":"F\u00e6lleshuset \u00c5kanden",
    "wof:placetype":"venue"
},
  "geometry": {"coordinates":[11.814031601,55.4435310364],"type":"Point"}
}