{
  "type": "Feature",
  "properties": {
    "addr:full":"Sofiendalsvej 11 Aalborg SV Danmark 9200",
    "addr:housenumber":"11",
    "addr:postcode":"9200",
    "addr:street":"Sofiendalsvej",
    "iso:country":"DK",
    "sg:address":"Sofiendalsvej 11",
    "sg:city":"Aalborg SV",
    "sg:orig_category":"Revisorer",
    "sg:phone":"+45 98 18 77 11",
    "sg:postcode":"9200",
    "sg:province":"Danmark",
    "sg:website":"www.palsgaard-hansen.dk",
    "wof:name":"Palsgaard & Hansen",
    "wof:placetype":"venue"
},
  "geometry": {"coordinates":[9.8875236511,57.0212440491],"type":"Point"}
}