{
  "type": "Feature",
  "properties": {
    "iso:country":"DK",
    "sg:address":"Kirketoften 60, L\u00f8jt Kirkeby",
    "sg:city":"Aabenraa",
    "sg:orig_category":"\u00c3\u2020ldrecentre",
    "sg:phone":"+45 74 61 84 91",
    "sg:postcode":"6200",
    "sg:province":"Danmark",
    "wof:name":"Kirketoftens \u00c6ldrecenter",
    "wof:placetype":"venue"
},
  "geometry": {"coordinates":[9.4213867188,55.0449562073],"type":"Point"}
}