{
  "type": "Feature",
  "properties": {
    "addr:full":"Lille Kirkestr\u00e6de 2 Stege Danmark 4780",
    "addr:housenumber":"2",
    "addr:postcode":"4780",
    "iso:country":"DK",
    "sg:address":"Lille Kirkestr\u00e6de 2",
    "sg:city":"Stege",
    "sg:orig_category":"Trykkerier",
    "sg:phone":"+45 55 81 81 82",
    "sg:postcode":"4780",
    "sg:province":"Danmark",
    "sg:website":"www.nymedia.dk",
    "wof:name":"Nymedia / M\u00f8ns Bogtrykkeri",
    "wof:placetype":"venue"
},
  "geometry": {"coordinates":[12.284696579,54.9840431213],"type":"Point"}
}