{
  "type": "Feature",
  "properties": {
    "iso:country":"DK",
    "sg:address":"Christian Sonnes Vej 33",
    "sg:city":"Odense M",
    "sg:orig_category":"Maskinfabrikker",
    "sg:phone":"+45 66 11 27 23",
    "sg:postcode":"5230",
    "sg:province":"Danmark",
    "wof:name":"Acituan Maskinfabrik ApS",
    "wof:placetype":"venue"
},
  "geometry": {"coordinates":[10.4024057388,55.3836021423],"type":"Point"}
}