{
  "type": "Feature",
  "properties": {
    "iso:country":"DK",
    "sg:address":"Lindalsvej 15, st. th.",
    "sg:city":"Hadsund",
    "sg:orig_category":"Sundhedspleje",
    "sg:postcode":"9560",
    "sg:province":"Danmark",
    "wof:name":"Sundhedscenter Hadsund",
    "wof:placetype":"venue"
},
  "geometry": {"coordinates":[10.115904808,56.7150764465],"type":"Point"}
}