{
  "type": "Feature",
  "properties": {
    "iso:country":"DK",
    "sg:address":"Peter Bangs Vej 76",
    "sg:city":"Frederiksberg",
    "sg:orig_category":"Konditorier",
    "sg:phone":"+45 38 88 88 07",
    "sg:postcode":"2000",
    "sg:province":"Danmark",
    "wof:name":"Konditoriet",
    "wof:placetype":"venue"
},
  "geometry": {"coordinates":[12.505941391,55.6788444519],"type":"Point"}
}