{
  "type": "Feature",
  "properties": {
    "addr:full":"Vestergade 25, D\u00e5strup Viby Sj\u00e6lland Danmark 4130",
    "addr:housenumber":"25",
    "addr:postcode":"4130",
    "addr:street":"Vestergade",
    "iso:country":"DK",
    "sg:address":"Vestergade 25, D\u00e5strup",
    "sg:city":"Viby Sj\u00e6lland",
    "sg:orig_category":"Betonelementer",
    "sg:phone":"+45 46 14 22 00",
    "sg:postcode":"4130",
    "sg:province":"Danmark",
    "wof:name":"Betonelement a/s",
    "wof:placetype":"venue"
},
  "geometry": {"coordinates":[12.024275,55.547371],"type":"Point"}
}