{
  "type": "Feature",
  "properties": {
    "addr:full":"Skotteparken 186 Ballerup Danmark 2750",
    "addr:housenumber":"186",
    "addr:postcode":"2750",
    "addr:street":"Skotteparken",
    "iso:country":"DK",
    "sg:address":"Skotteparken 186",
    "sg:city":"Ballerup",
    "sg:orig_category":"Boligselskaber",
    "sg:phone":"+45 44 97 77 30",
    "sg:postcode":"2750",
    "sg:province":"Danmark",
    "wof:name":"A/B S\u00f8brinken",
    "wof:placetype":"venue"
},
  "geometry": {"coordinates":[12.3745002747,55.7469787598],"type":"Point"}
}