{
  "type": "Feature",
  "properties": {
    "iso:country":"DK",
    "sg:address":"Landvadh\u00f8j 4",
    "sg:city":"Hjallerup",
    "sg:classifiers":[
        {
            "category":"Personal",
            "subcategory":"Massage",
            "type":"Services"
        }
    ],
    "sg:phone":"+45 98 28 43 01",
    "sg:postcode":"9320",
    "sg:province":"Danmark",
    "sg:website":"www.muskelknuden.dk",
    "wof:name":"Muskel Knuden",
    "wof:placetype":"venue"
},
  "geometry": {"coordinates":[10.2070903778,57.2120170593],"type":"Point"}
}