{
  "type": "Feature",
  "properties": {
    "addr:full":"B\u00f8stofte 26, Kv\u00e6rkeby Ringsted Danmark 4100",
    "addr:housenumber":"26",
    "addr:postcode":"4100",
    "addr:street":"Bostofte;Kvaerkeby",
    "iso:country":"DK",
    "sg:address":"B\u00f8stofte 26, Kv\u00e6rkeby",
    "sg:city":"Ringsted",
    "sg:orig_category":"INGENI\u00c3\u02dcRER",
    "sg:phone":"+45 57 53 34 03",
    "sg:postcode":"4100",
    "sg:province":"Danmark",
    "wof:name":"Ingeni\u00f8rg\u00e5rden",
    "wof:placetype":"venue"
},
  "geometry": {"coordinates":[11.7875862122,55.4458961487],"type":"Point"}
}