{
  "type": "Feature",
  "properties": {
    "addr:full":"Bispegade 8 Haderslev Danmark 6100",
    "addr:housenumber":"8",
    "addr:postcode":"6100",
    "addr:street":"Bispegade",
    "iso:country":"DK",
    "sg:address":"Bispegade 8",
    "sg:city":"Haderslev",
    "sg:orig_category":"Husholdningsapparater",
    "sg:phone":"+45 74 52 53 63",
    "sg:postcode":"6100",
    "sg:province":"Danmark",
    "wof:name":"Kroul Husholdningsmaskiner",
    "wof:placetype":"venue"
},
  "geometry": {"coordinates":[9.4865226746,55.2501983643],"type":"Point"}
}