{
  "type": "Feature",
  "properties": {
    "addr:full":"Vestervej 70 Holeby Danmark 4960",
    "addr:housenumber":"70",
    "addr:postcode":"4960",
    "addr:street":"Vestervej",
    "iso:country":"DK",
    "sg:address":"Vestervej 70",
    "sg:city":"Holeby",
    "sg:orig_category":"Biblioteker",
    "sg:phone":"+45 54 60 62 63",
    "sg:postcode":"4960",
    "sg:province":"Danmark",
    "wof:name":"Holeby bibliotek",
    "wof:placetype":"venue"
},
  "geometry": {"coordinates":[11.4651126862,54.7104568481],"type":"Point"}
}