{
  "type": "Feature",
  "properties": {
    "iso:country":"DK",
    "sg:address":"Vittenvej 54, Vitten",
    "sg:city":"Hinnerup",
    "sg:orig_category":"Bogtrykkerier",
    "sg:phone":"+45 86 91 09 99",
    "sg:postcode":"8382",
    "sg:province":"Danmark",
    "sg:website":"vittenbogtryk.dk",
    "wof:name":"Vitten Bogtryk",
    "wof:placetype":"venue"
},
  "geometry": {"coordinates":[10.0614156723,56.2650604248],"type":"Point"}
}