{
  "type": "Feature",
  "properties": {
    "addr:full":"Egeskov Bygade 15, Egeskov Fredericia Danmark 7000",
    "addr:housenumber":"15",
    "addr:postcode":"7000",
    "addr:street":"Egeskov Bygade;Egeskov",
    "iso:country":"DK",
    "sg:address":"Egeskov Bygade 15, Egeskov",
    "sg:city":"Fredericia",
    "sg:orig_category":"Kirkesogne",
    "sg:phone":"+45 75 95 77 44",
    "sg:postcode":"7000",
    "sg:province":"Danmark",
    "wof:name":"Vejlby sogn",
    "wof:placetype":"venue"
},
  "geometry": {"coordinates":[9.7591047287,55.566368103],"type":"Point"}
}