{
  "type": "Feature",
  "properties": {
    "iso:country":"DK",
    "sg:address":"Sj\u00e6llandsgade 14",
    "sg:city":"Ringsted",
    "sg:orig_category":"Bagere",
    "sg:phone":"+45 57 61 12 44",
    "sg:postcode":"4100",
    "sg:province":"Danmark",
    "wof:name":"Bageriet Munkeg\u00e5rden",
    "wof:placetype":"venue"
},
  "geometry": {"coordinates":[11.788276,55.440765],"type":"Point"}
}