{
  "type": "Feature",
  "properties": {
    "addr:full":"v/ August Juhler, S\u00f8ndre Alle 33, Stepping Christiansfeld Danmark 6070",
    "addr:housenumber":"33",
    "addr:postcode":"6070",
    "addr:street":"Sondre Alle",
    "iso:country":"DK",
    "sg:address":"v/ August Juhler, S\u00f8ndre Alle 33, Stepping",
    "sg:city":"Christiansfeld",
    "sg:orig_category":"Redningsberedskab",
    "sg:phone":"+45 74 56 81 43",
    "sg:postcode":"6070",
    "sg:province":"Danmark",
    "wof:name":"Stepping Frivillig Brandv\u00e6rn",
    "wof:placetype":"venue"
},
  "geometry": {"coordinates":[9.4834346771,55.3550567627],"type":"Point"}
}