{
  "type": "Feature",
  "properties": {
    "addr:full":"Grupper\u00e5dsfmd.: Eigil Vangsted, Flyvbjergvej 195 Jerslev Danmark 9740",
    "addr:housenumber":"195",
    "addr:postcode":"9740",
    "addr:street":"Flyvbjergvej",
    "iso:country":"DK",
    "sg:address":"Grupper\u00e5dsfmd.: Eigil Vangsted, Flyvbjergvej 195",
    "sg:city":"Jerslev",
    "sg:orig_category":"Spejderkorps",
    "sg:phone":"+45 98 83 16 64",
    "sg:postcode":"9740",
    "sg:province":"Danmark",
    "wof:name":"KFUM - Spejderne i Jerslev",
    "wof:placetype":"venue"
},
  "geometry": {"coordinates":[10.0921697617,57.2887115479],"type":"Point"}
}