{
  "type": "Feature",
  "properties": {
    "addr:full":"Vestergade 2 Grindsted Danmark 7200",
    "addr:housenumber":"2",
    "addr:postcode":"7200",
    "addr:street":"Vestergade",
    "iso:country":"DK",
    "sg:address":"Vestergade 2",
    "sg:city":"Grindsted",
    "sg:orig_category":"Rideudstyr",
    "sg:phone":"+45 75 32 51 01",
    "sg:postcode":"7200",
    "sg:province":"Danmark",
    "wof:name":"S\u00f8nderby's Rideudstyr",
    "wof:placetype":"venue"
},
  "geometry": {"coordinates":[8.927195549,55.7574653625],"type":"Point"}
}