{
  "type": "Feature",
  "properties": {
    "addr:full":"S\u00f8nderg\u00e5rden 4 Fars\u00f8 Danmark 9640",
    "addr:housenumber":"4",
    "addr:postcode":"9640",
    "addr:street":"Sondergaarden",
    "iso:country":"DK",
    "sg:address":"S\u00f8nderg\u00e5rden 4",
    "sg:city":"Fars\u00f8",
    "sg:orig_category":"Genbrugspladser",
    "sg:postcode":"9640",
    "sg:province":"Danmark",
    "wof:name":"Genbrugsplads",
    "wof:placetype":"venue"
},
  "geometry": {"coordinates":[-109.3746795654,42.1460418701],"type":"Point"}
}