{
  "type": "Feature",
  "properties": {
    "addr:full":"Fmd.: Anne Dorte Kristensen, Rolighed 12, 1. Sor\u00f8 Danmark 4180",
    "addr:housenumber":"12 1",
    "addr:postcode":"4180",
    "addr:street":"Rolighed",
    "iso:country":"DK",
    "sg:address":"Fmd.: Anne Dorte Kristensen, Rolighed 12, 1.",
    "sg:city":"Sor\u00f8",
    "sg:orig_category":"\u00c3\u2020ldreorganisationer og klubber",
    "sg:phone":"+45 57 82 11 54",
    "sg:postcode":"4180",
    "sg:province":"Danmark",
    "wof:name":"Os Yngre Pensionister",
    "wof:placetype":"venue"
},
  "geometry": {"coordinates":[-102.94467926030001,45.4534721375],"type":"Point"}
}