{
  "type": "Feature",
  "properties": {
    "addr:full":"Fmd.: Jens J\u00f8rgen N\u00f8rgaard, Klosterhedevej 13, \u00d8lby Struer Danmark 7600",
    "addr:housenumber":"13",
    "addr:postcode":"7600",
    "addr:street":"Klosterhedevej",
    "iso:country":"DK",
    "sg:address":"Fmd.: Jens J\u00f8rgen N\u00f8rgaard, Klosterhedevej 13, \u00d8lby",
    "sg:city":"Struer",
    "sg:orig_category":"Hobbybetonede foreninger",
    "sg:phone":"+45 97 86 58 58",
    "sg:postcode":"7600",
    "sg:province":"Danmark",
    "wof:name":"Ringk\u00f8bing-Ulfborg-Vemb Kaninavlerforening",
    "wof:placetype":"venue"
},
  "geometry": {"coordinates":[8.5946903229,56.491191864],"type":"Point"}
}