{
  "type": "Feature",
  "properties": {
    "iso:country":"DK",
    "sg:address":"Fmd.: J\u00f8rgen Torgny Nielsen, Gerlevvej 9",
    "sg:city":"Br\u00f8nsh\u00f8j",
    "sg:orig_category":"Grundejerforeninger",
    "sg:phone":"+45 38 28 06 77",
    "sg:postcode":"2700",
    "sg:province":"Danmark",
    "wof:name":"Krathaven",
    "wof:placetype":"venue"
},
  "geometry": {"coordinates":[5.4739699364,49.508140564],"type":"Point"}
}