{
  "type": "Feature",
  "properties": {
    "addr:full":"Fmd.: Kjeld Nielsen, Levetoftevej 3 Haslev Danmark 4690",
    "addr:housenumber":"3",
    "addr:postcode":"4690",
    "addr:street":"Kjeld;Levetoftevej",
    "iso:country":"DK",
    "sg:address":"Fmd.: Kjeld Nielsen, Levetoftevej 3",
    "sg:city":"Haslev",
    "sg:orig_category":"Erhvervs- og brancheforeninger",
    "sg:phone":"+45 56 38 05 02",
    "sg:postcode":"4690",
    "sg:province":"Danmark",
    "wof:name":"Midtsj\u00e6llands vognmandsforening",
    "wof:placetype":"venue"
},
  "geometry": {"coordinates":[11.9678049088,55.3230895996],"type":"Point"}
}