{
  "type": "Feature",
  "properties": {
    "addr:full":"Adelgade 7 Skive Danmark 7800",
    "addr:housenumber":"7",
    "addr:postcode":"7800",
    "addr:street":"Adelgade",
    "iso:country":"DK",
    "sg:address":"Adelgade 7",
    "sg:city":"Skive",
    "sg:orig_category":"Apoteker og -udsalg",
    "sg:phone":"+45 97 52 41 66",
    "sg:postcode":"7800",
    "sg:province":"Danmark",
    "wof:name":"L\u00f8ve Apoteket",
    "wof:placetype":"venue"
},
  "geometry": {"coordinates":[9.0263185501,56.5660591125],"type":"Point"}
}