{
  "type": "Feature",
  "properties": {
    "addr:full":"Murervej 9 Varde Danmark 6800",
    "addr:housenumber":"9",
    "addr:postcode":"6800",
    "addr:street":"Murervej",
    "iso:country":"DK",
    "sg:address":"Murervej 9",
    "sg:city":"Varde",
    "sg:orig_category":"Autoreparation og -service",
    "sg:phone":"+45 75 22 22 60",
    "sg:postcode":"6800",
    "sg:province":"Danmark",
    "wof:name":"N\u00f8rrevold Auto - Varde Syd",
    "wof:placetype":"venue"
},
  "geometry": {"coordinates":[8.5042657852,55.6067962646],"type":"Point"}
}