{
  "type": "Feature",
  "properties": {
    "addr:full":"Fmd.: Thomas Kj\u00e6rgaard, Gr\u00f8nnegade 117, 2. tv. \u00c5rhus C Danmark 8000",
    "addr:housenumber":"117 2 tv.",
    "addr:postcode":"8000",
    "addr:street":"Gronnegade",
    "iso:country":"DK",
    "sg:address":"Fmd.: Thomas Kj\u00e6rgaard, Gr\u00f8nnegade 117, 2. tv.",
    "sg:city":"\u00c5rhus C",
    "sg:orig_category":"Kolonihaveforeninger",
    "sg:phone":"+45 86 18 74 23",
    "sg:postcode":"8000",
    "sg:province":"Danmark",
    "wof:name":"Haveforeningen \u00c5brinken",
    "wof:placetype":"venue"
},
  "geometry": {"coordinates":[4.717400074,49.7588005066],"type":"Point"}
}