{
  "type": "Feature",
  "properties": {
    "addr:full":"Hammelvej 247, Houlbjerg Lang\u00e5 Danmark 8870",
    "addr:housenumber":"247",
    "addr:postcode":"8870",
    "addr:street":"Hammelvej",
    "iso:country":"DK",
    "sg:address":"Hammelvej 247, Houlbjerg",
    "sg:city":"Lang\u00e5",
    "sg:orig_category":"Revisorer",
    "sg:phone":"+45 86 96 45 00",
    "sg:postcode":"8870",
    "sg:province":"Danmark",
    "wof:name":"Servicekontoret",
    "wof:placetype":"venue"
},
  "geometry": {"coordinates":[9.8955049515,56.3900756836],"type":"Point"}
}