{
  "type": "Feature",
  "properties": {
    "addr:full":"Storstr\u00f8msvej 4 Esbjerg N Danmark 6715",
    "addr:housenumber":"4",
    "addr:postcode":"6715",
    "addr:street":"Storstromsvej",
    "iso:country":"DK",
    "sg:address":"Storstr\u00f8msvej 4",
    "sg:city":"Esbjerg N",
    "sg:orig_category":"Autoforhandlere",
    "sg:phone":"+45 76 14 06 00",
    "sg:postcode":"6715",
    "sg:province":"Danmark",
    "wof:name":"P.T.N. Biler A/S",
    "wof:placetype":"venue"
},
  "geometry": {"coordinates":[8.4723653793,55.5071334839],"type":"Point"}
}