{
  "type": "Feature",
  "properties": {
    "iso:country":"DK",
    "sg:address":"V/ Villy Nielsen, Skyggevej 50 A",
    "sg:city":"Bording",
    "sg:orig_category":"Hobbybetonede foreninger",
    "sg:phone":"+45 86 86 23 29",
    "sg:postcode":"7441",
    "sg:province":"Danmark",
    "sg:website":"www.image.dk/~wn",
    "wof:name":"Guden\u00e5 Expressen - Silkeborg Modeljernbaneklub",
    "wof:placetype":"venue"
},
  "geometry": {"coordinates":[9.2792396545,56.1449508667],"type":"Point"}
}