{
  "type": "Feature",
  "properties": {
    "addr:full":"Nr \u00d8kse Engvej 1, Arentsminde Brovst Danmark 9460",
    "addr:housenumber":"1",
    "addr:postcode":"9460",
    "addr:street":"Nr Okse Engvej",
    "iso:country":"DK",
    "sg:address":"Nr \u00d8kse Engvej 1, Arentsminde",
    "sg:city":"Brovst",
    "sg:orig_category":"Kirker",
    "sg:postcode":"9460",
    "sg:province":"Danmark",
    "wof:name":"Langeslund Kirke",
    "wof:placetype":"venue"
},
  "geometry": {"coordinates":[9.5220241547,57.097366333],"type":"Point"}
}