{
  "type": "Feature",
  "properties": {
    "addr:full":"\u00d8rb\u00e6kvej 3 Ferritslev Danmark 5863",
    "addr:housenumber":"3",
    "addr:postcode":"5863",
    "addr:street":"Orbaekvej",
    "iso:country":"DK",
    "sg:address":"\u00d8rb\u00e6kvej 3",
    "sg:city":"Ferritslev",
    "sg:orig_category":"Gartnerier",
    "sg:phone":"+45 65 98 11 61",
    "sg:postcode":"5863",
    "sg:province":"Danmark",
    "wof:name":"Ravnholt Gartneri",
    "wof:placetype":"venue"
},
  "geometry": {"coordinates":[10.5689496994,55.3201446533],"type":"Point"}
}