{
  "type": "Feature",
  "properties": {
    "addr:full":"Dronningensgade 23 K\u00f8benhavn Danmark 1420",
    "addr:housenumber":"23",
    "addr:postcode":"1420",
    "addr:street":"Dronningensgade",
    "iso:country":"DK",
    "sg:address":"Dronningensgade 23",
    "sg:city":"K\u00f8benhavn",
    "sg:orig_category":"Landskabsarkitekter",
    "sg:phone":"+45 32 57 85 93",
    "sg:postcode":"1420",
    "sg:province":"Danmark",
    "wof:name":"Fog-M\u00f8ller, Henrik",
    "wof:placetype":"venue"
},
  "geometry": {"coordinates":[12.5927000046,55.6703987122],"type":"Point"}
}