{
  "type": "Feature",
  "properties": {
    "addr:full":"Jernhytvej 13 Vojens Danmark 6500",
    "addr:housenumber":"13",
    "addr:postcode":"6500",
    "addr:street":"Jernhytvej",
    "iso:country":"DK",
    "sg:address":"Jernhytvej 13",
    "sg:city":"Vojens",
    "sg:orig_category":"Snedkermestre",
    "sg:phone":"+45 74 54 31 25",
    "sg:postcode":"6500",
    "sg:province":"Danmark",
    "wof:name":"Vagns Snedkerforretning",
    "wof:placetype":"venue"
},
  "geometry": {"coordinates":[9.3141260147,55.2472038269],"type":"Point"}
}