{
  "type": "Feature",
  "properties": {
    "addr:full":"Fmd.: Kay Henning Hansen, Fornbyvej 31 Padborg Danmark 6330",
    "addr:housenumber":"31",
    "addr:postcode":"6330",
    "addr:street":"Fornbyvej",
    "iso:country":"DK",
    "sg:address":"Fmd.: Kay Henning Hansen, Fornbyvej 31",
    "sg:city":"Padborg",
    "sg:orig_category":"Musik og sang",
    "sg:phone":"+45 74 67 35 31",
    "sg:postcode":"6330",
    "sg:province":"Danmark",
    "wof:name":"Gr\u00e6nsekvadrillen Folkedansere og Spillem\u00e6nd",
    "wof:placetype":"venue"
},
  "geometry": {"coordinates":[9.3618345261,54.8222312927],"type":"Point"}
}