{
  "type": "Feature",
  "properties": {
    "addr:full":"Holmebuen 12 Karlslunde Danmark 2690",
    "addr:housenumber":"12",
    "addr:postcode":"2690",
    "addr:street":"Holmebuen",
    "iso:country":"DK",
    "sg:address":"Holmebuen 12",
    "sg:city":"Karlslunde",
    "sg:orig_category":"Autoreservedele",
    "sg:phone":"+45 46 15 23 69",
    "sg:postcode":"2690",
    "sg:province":"Danmark",
    "wof:name":"Classic Auto Parts ApS",
    "wof:placetype":"venue"
},
  "geometry": {"coordinates":[12.2445259094,55.5614051819],"type":"Point"}
}