{
  "type": "Feature",
  "properties": {
    "addr:full":"G\u00f8rdingvej 5  Gredstedbro Danmark 6771",
    "addr:housenumber":"5",
    "addr:postcode":"6771",
    "addr:street":"Gordingvej",
    "iso:country":"DK",
    "sg:address":"G\u00f8rdingvej 5 ",
    "sg:city":"Gredstedbro",
    "sg:classifiers":[
        {
            "category":"Home & Garden",
            "subcategory":"Home Furnishings",
            "type":"Retail Goods"
        }
    ],
    "sg:phone":"+45 75 43 51 11",
    "sg:postcode":"6771",
    "sg:province":"Danmark",
    "sg:tags":[
        "household"
    ],
    "wof:name":"TREKANTEN-HESTB\u00c6K A/S",
    "wof:placetype":"venue"
},
  "geometry": {"coordinates":[8.7970981598,55.4214363098],"type":"Point"}
}