{
  "type": "Feature",
  "properties": {
    "addr:full":"Fmd.: Henry Fabricius, Sulkendrupvej 14, Sulkendrup Nyborg Danmark 5800",
    "addr:housenumber":"14",
    "addr:postcode":"5800",
    "addr:street":"Sulkendrupvej;Sulkendrup",
    "iso:country":"DK",
    "sg:address":"Fmd.: Henry Fabricius, Sulkendrupvej 14, Sulkendrup",
    "sg:city":"Nyborg",
    "sg:orig_category":"Musik og sang",
    "sg:phone":"+45 65 31 55 69",
    "sg:postcode":"5800",
    "sg:province":"Danmark",
    "wof:name":"Danehofkvadrillen",
    "wof:placetype":"venue"
},
  "geometry": {"coordinates":[10.7923851013,55.3111801147],"type":"Point"}
}