{
  "type": "Feature",
  "properties": {
    "addr:full":"Vitus Berings Plads 11 Horsens Danmark 8700",
    "addr:housenumber":"11",
    "addr:postcode":"8700",
    "addr:street":"Vitus Berings Plads",
    "iso:country":"DK",
    "sg:address":"Vitus Berings Plads 11",
    "sg:city":"Horsens",
    "sg:orig_category":"Grillbarer",
    "sg:phone":"+45 75 62 79 85",
    "sg:postcode":"8700",
    "sg:province":"Danmark",
    "wof:name":"Kaffevognen",
    "wof:placetype":"venue"
},
  "geometry": {"coordinates":[9.8418636322,55.861618042],"type":"Point"}
}