{
  "type": "Feature",
  "properties": {
    "iso:country":"DK",
    "sg:address":"Gormsgade 7",
    "sg:city":"Jelling",
    "sg:orig_category":"Solcentre",
    "sg:phone":"+45 75 87 11 10",
    "sg:postcode":"7300",
    "sg:province":"Danmark",
    "wof:name":"M\u00f8llers Dame- & Herresalon",
    "wof:placetype":"venue"
},
  "geometry": {"coordinates":[9.4189043045,55.7555656433],"type":"Point"}
}