{
  "type": "Feature",
  "properties": {
    "addr:full":"L\u00e6ss\u00f8esgade 5, 1. sal K\u00f8benhavn N Danmark 2200",
    "addr:housenumber":"5 1 sal",
    "addr:postcode":"2200",
    "addr:street":"Laessoesgade;Kobenhavn N Danmark",
    "iso:country":"DK",
    "sg:address":"L\u00e6ss\u00f8esgade 5, 1. sal",
    "sg:city":"K\u00f8benhavn N",
    "sg:orig_category":"Musik- og solistbureauer",
    "sg:phone":"+45 35 37 01 82",
    "sg:postcode":"2200",
    "sg:province":"Danmark",
    "wof:name":"Cirkus-Cirkus/Fantastica Events",
    "wof:placetype":"venue"
},
  "geometry": {"coordinates":[-76.4168395996,37.452419281],"type":"Point"}
}