{
  "type": "Feature",
  "properties": {
    "addr:full":"Traneb\u00e6rvej 1 Silkeborg Danmark 8600",
    "addr:housenumber":"1",
    "addr:postcode":"8600",
    "addr:street":"Tranebaervej",
    "iso:country":"DK",
    "sg:address":"Traneb\u00e6rvej 1",
    "sg:city":"Silkeborg",
    "sg:orig_category":"Non-Classified Establishments",
    "sg:phone":"+45 86 84 62 33",
    "sg:postcode":"8600",
    "sg:province":"Danmark",
    "wof:name":"Andersen, Lars Langberg",
    "wof:placetype":"venue"
},
  "geometry": {"coordinates":[9.6077651978,56.1393852234],"type":"Point"}
}