{
  "type": "Feature",
  "properties": {
    "addr:full":"Viby Ringvej 19 Viby Danmark 8260",
    "addr:housenumber":"19",
    "addr:postcode":"8260",
    "addr:street":"Viby Ringvej",
    "iso:country":"DK",
    "sg:address":"Viby Ringvej 19",
    "sg:city":"Viby",
    "sg:classifiers":[
        {
            "category":"Restaurant",
            "type":"Food & Drink"
        }
    ],
    "sg:phone":"+45 86 11 66 66",
    "sg:postcode":"8260",
    "sg:province":"Danmark",
    "wof:name":"McDonald's",
    "wof:placetype":"venue"
},
  "geometry": {"coordinates":[10.1607503891,56.1293525696],"type":"Point"}
}