{
  "type": "Feature",
  "properties": {
    "addr:full":"Kongelysvej 4 Viborg Danmark 8800",
    "addr:housenumber":"4",
    "addr:postcode":"8800",
    "addr:street":"Kongelysvej",
    "iso:country":"DK",
    "sg:address":"Kongelysvej 4",
    "sg:city":"Viborg",
    "sg:orig_category":"Pressebureauer",
    "sg:phone":"+45 86 60 16 61",
    "sg:postcode":"8800",
    "sg:province":"Danmark",
    "wof:name":"Rahbek, Niels",
    "wof:placetype":"venue"
},
  "geometry": {"coordinates":[9.3910493851,56.4392738342],"type":"Point"}
}