{
  "type": "Feature",
  "properties": {
    "addr:full":"Nibevej 23 Aars Danmark 9600",
    "addr:housenumber":"23",
    "addr:postcode":"9600",
    "addr:street":"Nibevej",
    "iso:country":"DK",
    "sg:address":"Nibevej 23",
    "sg:city":"Aars",
    "sg:orig_category":"Fagforbund og fagforeninger",
    "sg:phone":"+45 98 62 20 32",
    "sg:postcode":"9600",
    "sg:province":"Danmark",
    "wof:name":"Dansk Teknisk L\u00e6rerforening DTL",
    "wof:placetype":"venue"
},
  "geometry": {"coordinates":[9.5111379623,56.8063697815],"type":"Point"}
}