{
  "type": "Feature",
  "properties": {
    "addr:full":"Skjoldg\u00e5rdsvej 2 Charlottenlund Danmark 2920",
    "addr:housenumber":"2",
    "addr:postcode":"2920",
    "addr:street":"Skjoldgaardsvej",
    "iso:country":"DK",
    "sg:address":"Skjoldg\u00e5rdsvej 2",
    "sg:city":"Charlottenlund",
    "sg:orig_category":"Arkitekter",
    "sg:phone":"+45 39 63 21 15",
    "sg:postcode":"2920",
    "sg:province":"Danmark",
    "wof:name":"Clante, Thorkil",
    "wof:placetype":"venue"
},
  "geometry": {"coordinates":[12.5828895569,55.7551841736],"type":"Point"}
}