{
  "type": "Feature",
  "properties": {
    "iso:country":"DK",
    "sg:address":"S\u00f8rens M\u00f8llevej 31, Asserballeskov",
    "sg:city":"Augustenborg",
    "sg:orig_category":"Blikkenslagere",
    "sg:phone":"+45 74 47 46 33",
    "sg:postcode":"6440",
    "sg:province":"Danmark",
    "wof:name":"Augustenborg - H\u00f8rup Blik & VVS",
    "wof:placetype":"venue"
},
  "geometry": {"coordinates":[9.872775,54.945904],"type":"Point"}
}