{
  "type": "Feature",
  "properties": {
    "iso:country":"DK",
    "sg:address":"Borupvang 2 D",
    "sg:city":"Ballerup",
    "sg:classifiers":[
        {
            "category":"Professional",
            "subcategory":"Computer Services",
            "type":"Services"
        }
    ],
    "sg:phone":"+45 44 68 22 00",
    "sg:postcode":"2750",
    "sg:province":"Danmark",
    "sg:tags":[
        "edb",
        "-",
        "software"
    ],
    "wof:name":"BMC Software A/S",
    "wof:placetype":"venue"
},
  "geometry": {"coordinates":[12.386516571,55.7330627441],"type":"Point"}
}