{
  "type": "Feature",
  "properties": {
    "addr:full":"Gartnervej 16 Holmegaard Danmark 4684",
    "addr:housenumber":"16",
    "addr:postcode":"4684",
    "addr:street":"Gartnervej",
    "iso:country":"DK",
    "sg:address":"Gartnervej 16",
    "sg:city":"Holmegaard",
    "sg:orig_category":"Maskinudlejning",
    "sg:phone":"+45 55 56 25 11",
    "sg:postcode":"4684",
    "sg:province":"Danmark",
    "wof:name":"CRAMO A/S",
    "wof:placetype":"venue"
},
  "geometry": {"coordinates":[11.8593578339,55.2623710632],"type":"Point"}
}