{
  "type": "Feature",
  "properties": {
    "addr:full":"Niv\u00e5 Center 74 Niv\u00e5 Danmark 2990",
    "addr:housenumber":"74",
    "addr:postcode":"2990",
    "iso:country":"DK",
    "sg:address":"Niv\u00e5 Center 74",
    "sg:city":"Niv\u00e5",
    "sg:orig_category":"Ejendomshandel",
    "sg:phone":"+45 49 14 90 73",
    "sg:postcode":"2990",
    "sg:province":"Danmark",
    "wof:name":"EDC M\u00e6glerne",
    "wof:placetype":"venue"
},
  "geometry": {"coordinates":[12.5052623749,55.9351081848],"type":"Point"}
}