{
  "type": "Feature",
  "properties": {
    "addr:full":"Langebjerg 23 D Roskilde Danmark 4000",
    "addr:housenumber":"23 d",
    "addr:postcode":"4000",
    "addr:street":"Langebjerg",
    "iso:country":"DK",
    "sg:address":"Langebjerg 23 D",
    "sg:city":"Roskilde",
    "sg:orig_category":"Hospital, udstyr til",
    "sg:phone":"+45 46 74 00 30",
    "sg:postcode":"4000",
    "sg:province":"Danmark",
    "wof:name":"Tamro Medlab AS",
    "wof:placetype":"venue"
},
  "geometry": {"coordinates":[12.1464509964,55.6459884644],"type":"Point"}
}