{
  "type": "Feature",
  "properties": {
    "addr:full":"Overgaden Neden Vandet 49 K\u00f8benhavn Danmark 1414",
    "addr:housenumber":"49",
    "addr:postcode":"1414",
    "addr:street":"Overgaden Neden Vandet",
    "iso:country":"DK",
    "sg:address":"Overgaden Neden Vandet 49",
    "sg:city":"K\u00f8benhavn",
    "sg:orig_category":"Tegnere og tegnestuer",
    "sg:phone":"+45 32 95 12 09",
    "sg:postcode":"1414",
    "sg:province":"Danmark",
    "wof:name":"Christiansen, Niels",
    "wof:placetype":"venue"
},
  "geometry": {"coordinates":[12.5897798538,55.6723518372],"type":"Point"}
}