{
  "type": "Feature",
  "properties": {
    "addr:full":"Fmd.: Thomas Linding, Gunderupvej 65, Horne Varde Danmark 6800",
    "addr:housenumber":"65",
    "addr:postcode":"6800",
    "addr:street":"Gunderupvej;Horne",
    "iso:country":"DK",
    "sg:address":"Fmd.: Thomas Linding, Gunderupvej 65, Horne",
    "sg:city":"Varde",
    "sg:orig_category":"Hobbybetonede foreninger",
    "sg:phone":"+45 75 26 01 16",
    "sg:postcode":"6800",
    "sg:province":"Danmark",
    "wof:name":"Gamle Danses V\u00e6rn",
    "wof:placetype":"venue"
},
  "geometry": {"coordinates":[8.482629776,55.6220741272],"type":"Point"}
}