{
  "type": "Feature",
  "properties": {
    "addr:full":"\u00d8stre Stationsvej 33 Odense C Danmark 5000",
    "addr:housenumber":"33",
    "addr:postcode":"5000",
    "addr:street":"Ostre Stationsvej",
    "iso:country":"DK",
    "sg:address":"\u00d8stre Stationsvej 33",
    "sg:city":"Odense C",
    "sg:orig_category":"Cykler",
    "sg:phone":"+45 66 17 77 36",
    "sg:postcode":"5000",
    "sg:province":"Danmark",
    "wof:name":"Rolsted Cykel",
    "wof:placetype":"venue"
},
  "geometry": {"coordinates":[10.3834323883,55.4006729126],"type":"Point"}
}