{
  "type": "Feature",
  "properties": {
    "addr:full":"Hagemannsvej 7 Silkeborg Danmark 8600",
    "addr:housenumber":"7",
    "addr:postcode":"8600",
    "addr:street":"Hagemannsvej",
    "iso:country":"DK",
    "sg:address":"Hagemannsvej 7",
    "sg:city":"Silkeborg",
    "sg:orig_category":"Engros handel",
    "sg:phone":"+45 86 82 00 66",
    "sg:postcode":"8600",
    "sg:province":"Danmark",
    "wof:name":"Agimex A/S",
    "wof:placetype":"venue"
},
  "geometry": {"coordinates":[9.5681371689,56.1992835999],"type":"Point"}
}