{
  "type": "Feature",
  "properties": {
    "addr:full":"Hovedgaden 46 Tinglev Danmark 6360",
    "addr:housenumber":"46",
    "addr:postcode":"6360",
    "addr:street":"Hovedgaden",
    "iso:country":"DK",
    "sg:address":"Hovedgaden 46",
    "sg:city":"Tinglev",
    "sg:orig_category":"Kirkelige foreninger",
    "sg:phone":"+45 74 64 40 34",
    "sg:postcode":"6360",
    "sg:province":"Danmark",
    "sg:website":"www.kirche.dk",
    "wof:name":"Nordschleswigsche Gemeinde, Kirkekontor",
    "wof:placetype":"venue"
},
  "geometry": {"coordinates":[9.2509307861,54.9365234375],"type":"Point"}
}