{
  "type": "Feature",
  "properties": {
    "iso:country":"DK",
    "sg:address":"Gugvej 134",
    "sg:city":"Aalborg S\u00d8",
    "sg:orig_category":"Beslag",
    "sg:phone":"+45 98 14 68 88",
    "sg:postcode":"9210",
    "sg:province":"Danmark",
    "wof:name":"Nordjysk Beslag A/S",
    "wof:placetype":"venue"
},
  "geometry": {"coordinates":[9.924967,57.017536],"type":"Point"}
}