{
  "type": "Feature",
  "properties": {
    "iso:country":"DK",
    "sg:address":"Kongevejen 79",
    "sg:city":"Holte",
    "sg:orig_category":"INGENI\u00c3\u02dcRER",
    "sg:phone":"+45 45 41 45 31",
    "sg:postcode":"2840",
    "sg:province":"Danmark",
    "sg:website":"www.fritzboger.dk",
    "wof:name":"Fritzb\u00f8ger A/S, K.",
    "wof:placetype":"venue"
},
  "geometry": {"coordinates":[12.4696063995,55.8153495789],"type":"Point"}
}