{
  "type": "Feature",
  "properties": {
    "addr:full":"Midtg\u00e5rdsvej 1, Stenderup F\u00f8vling Danmark 6683",
    "addr:housenumber":"1",
    "addr:postcode":"6683",
    "addr:street":"Midtgaardsvej",
    "iso:country":"DK",
    "sg:address":"Midtg\u00e5rdsvej 1, Stenderup",
    "sg:city":"F\u00f8vling",
    "sg:orig_category":"Regnskabsassistance",
    "sg:phone":"+45 75 39 82 41",
    "sg:postcode":"6683",
    "sg:province":"Danmark",
    "wof:name":"MH-regnskabshj\u00e6lp",
    "wof:placetype":"venue"
},
  "geometry": {"coordinates":[8.891289711,55.4169082642],"type":"Point"}
}