{
  "type": "Feature",
  "properties": {
    "addr:full":"Fmd.: Uffe T\u00f8nning, \u00c5vangen 96 Ringe Danmark 5750",
    "addr:housenumber":"96",
    "addr:postcode":"5750",
    "addr:street":"Aavangen",
    "iso:country":"DK",
    "sg:address":"Fmd.: Uffe T\u00f8nning, \u00c5vangen 96",
    "sg:city":"Ringe",
    "sg:orig_category":"\u00c3\u02dcvrige skoler",
    "sg:phone":"+45 62 62 37 54",
    "sg:postcode":"5750",
    "sg:province":"Danmark",
    "wof:name":"Bogbinderskolen Ringe",
    "wof:placetype":"venue"
},
  "geometry": {"coordinates":[10.4781074524,55.2356643677],"type":"Point"}
}