{
  "type": "Feature",
  "properties": {
    "addr:full":"Lundingsvej 17 Fredericia Danmark 7000",
    "addr:housenumber":"17",
    "addr:postcode":"7000",
    "addr:street":"Lundingsvej",
    "iso:country":"DK",
    "sg:address":"Lundingsvej 17",
    "sg:city":"Fredericia",
    "sg:orig_category":"Plejehjem",
    "sg:phone":"+45 72 10 62 62",
    "sg:postcode":"7000",
    "sg:province":"Danmark",
    "wof:name":"Omr\u00e5de 2 - Hybyhus Omr\u00e5det",
    "wof:placetype":"venue"
},
  "geometry": {"coordinates":[9.7717933655,55.571395874],"type":"Point"}
}