{
  "type": "Feature",
  "properties": {
    "addr:full":"Tulstrup Have 3, Tulstrup Hiller\u00f8d Danmark 3400",
    "addr:housenumber":"3",
    "addr:postcode":"3400",
    "addr:street":"Tulstrup Have",
    "iso:country":"DK",
    "sg:address":"Tulstrup Have 3, Tulstrup",
    "sg:city":"Hiller\u00f8d",
    "sg:orig_category":"Integrerede institutioner",
    "sg:phone":"+45 48 28 69 25",
    "sg:postcode":"3400",
    "sg:province":"Danmark",
    "wof:name":"Tulstrup B\u00f8rnehus",
    "wof:placetype":"venue"
},
  "geometry": {"coordinates":[12.3056097031,55.9288215637],"type":"Point"}
}