{
  "type": "Feature",
  "properties": {
    "addr:full":"S\u00f8borg Hovedgade 150 S\u00f8borg Danmark 2860",
    "addr:housenumber":"150",
    "addr:postcode":"2860",
    "addr:street":"Soborg Hovedgade",
    "iso:country":"DK",
    "sg:address":"S\u00f8borg Hovedgade 150",
    "sg:city":"S\u00f8borg",
    "sg:orig_category":"Autoforhandlere",
    "sg:phone":"+45 39 67 28 28",
    "sg:postcode":"2860",
    "sg:province":"Danmark",
    "wof:name":"Auto Gren",
    "wof:placetype":"venue"
},
  "geometry": {"coordinates":[-101.39041900629999,35.6679611206],"type":"Point"}
}