{
  "type": "Feature",
  "properties": {
    "iso:country":"DK",
    "sg:address":"Neergaards All\u00e9 1",
    "sg:city":"Hvidovre",
    "sg:orig_category":"Bagere",
    "sg:phone":"+45 36 49 26 79",
    "sg:postcode":"2650",
    "sg:province":"Danmark",
    "wof:name":"Basseriet",
    "wof:placetype":"venue"
},
  "geometry": {"coordinates":[12.478899,55.638817],"type":"Point"}
}