{
  "type": "Feature",
  "properties": {
    "iso:country":"DK",
    "sg:address":"Valbyvej 11",
    "sg:city":"Slagelse",
    "sg:orig_category":"Bagere",
    "sg:phone":"+45 58 53 58 02",
    "sg:postcode":"4200",
    "sg:province":"Danmark",
    "wof:name":"Hellig Anders Konditoriet",
    "wof:placetype":"venue"
},
  "geometry": {"coordinates":[11.351869,55.409359],"type":"Point"}
}