{
  "type": "Feature",
  "properties": {
    "addr:full":"Kontaktpers. (HA): Johnny S\u00f8rensen, Skovbrynet 9 Skjern Danmark 6900",
    "addr:housenumber":"9",
    "addr:postcode":"6900",
    "addr:street":"Kontaktpers.;Johnny;Skovbrynet",
    "iso:country":"DK",
    "sg:address":"Kontaktpers. (HA): Johnny S\u00f8rensen, Skovbrynet 9",
    "sg:city":"Skjern",
    "sg:orig_category":"Kirkelige foreninger",
    "sg:phone":"+45 40 84 59 99",
    "sg:postcode":"6900",
    "sg:province":"Danmark",
    "wof:name":"KFUM og K, Skjern",
    "wof:placetype":"venue"
},
  "geometry": {"coordinates":[8.492972374,55.9485740662],"type":"Point"}
}