{
  "type": "Feature",
  "properties": {
    "iso:country":"DK",
    "sg:address":"Hovedgaden 532 C",
    "sg:city":"Hedehusene",
    "sg:orig_category":"Strikvarer",
    "sg:phone":"+45 46 56 48 14",
    "sg:postcode":"2640",
    "sg:province":"Danmark",
    "wof:name":"Chriswear Strik",
    "wof:placetype":"venue"
},
  "geometry": {"coordinates":[12.1896333694,55.6488685608],"type":"Point"}
}