{
  "type": "Feature",
  "properties": {
    "addr:full":"Lindevangs Alle 2 Frederiksberg Danmark 2000",
    "addr:housenumber":"2",
    "addr:postcode":"2000",
    "addr:street":"Lindevangs Alle",
    "iso:country":"DK",
    "sg:address":"Lindevangs Alle 2",
    "sg:city":"Frederiksberg",
    "sg:orig_category":"Faglige organisationer og foreninger",
    "sg:phone":"+45 38 88 22 33",
    "sg:postcode":"2000",
    "sg:province":"Danmark",
    "sg:website":"www.bf.dk",
    "wof:name":"Bibliotekarforbundet",
    "wof:placetype":"venue"
},
  "geometry": {"coordinates":[12.5175609589,55.6793670654],"type":"Point"}
}