{
  "type": "Feature",
  "properties": {
    "iso:country":"DK",
    "sg:address":"Hans Jensens Vej 4",
    "sg:city":"Billund",
    "sg:orig_category":"Kirker",
    "sg:phone":"+45 75 33 17 69",
    "sg:postcode":"7190",
    "sg:province":"Danmark",
    "wof:name":"Billund Kirke",
    "wof:placetype":"venue"
},
  "geometry": {"coordinates":[9.1174888611,55.7305526733],"type":"Point"}
}