{
  "type": "Feature",
  "properties": {
    "iso:country":"DK",
    "sg:address":"v/Hasle Lokalcenter, Rymarken 118, Hasle",
    "sg:city":"\u00c5rhus V",
    "sg:orig_category":"Kulturelle foreninger",
    "sg:phone":"+45 86 75 01 66",
    "sg:postcode":"8210",
    "sg:province":"Danmark",
    "wof:name":"Hasle Kunstforening",
    "wof:placetype":"venue"
},
  "geometry": {"coordinates":[14.7065896988,55.1830787659],"type":"Point"}
}