{
  "type": "Feature",
  "properties": {
    "addr:full":"Georg Jensens Vej 5 Hj\u00f8rring Danmark 9800",
    "addr:housenumber":"5",
    "addr:postcode":"9800",
    "addr:street":"Georg Jensens Vej",
    "iso:country":"DK",
    "sg:address":"Georg Jensens Vej 5",
    "sg:city":"Hj\u00f8rring",
    "sg:classifiers":[
        {
            "category":"Wholesale",
            "subcategory":"Chemicals & Plastics",
            "type":"Manufacturing & Wholesale Goods"
        }
    ],
    "sg:phone":"+45 98 92 21 22",
    "sg:postcode":"9800",
    "sg:province":"Danmark",
    "sg:website":"www.expo-net.dk",
    "wof:name":"Expo-Net Danmark A/S",
    "wof:placetype":"venue"
},
  "geometry": {"coordinates":[-79.0252990723,33.5882987976],"type":"Point"}
}