{
  "type": "Feature",
  "properties": {
    "addr:full":"Kummelefort 14, Kollund Krus\u00e5 Danmark 6340",
    "addr:housenumber":"14",
    "addr:postcode":"6340",
    "addr:street":"Kummelefort",
    "iso:country":"DK",
    "sg:address":"Kummelefort 14, Kollund",
    "sg:city":"Krus\u00e5",
    "sg:orig_category":"Campingpladser",
    "sg:phone":"+45 74 67 88 30",
    "sg:postcode":"6340",
    "sg:province":"Danmark",
    "wof:name":"Frig\u00e5rd Camping & Hytteudlejning",
    "wof:placetype":"venue"
},
  "geometry": {"coordinates":[9.3991203308,54.8500900269],"type":"Point"}
}