{
  "type": "Feature",
  "properties": {
    "addr:full":"Valdemarsvej 2 Randers Danmark 8900",
    "addr:housenumber":"2",
    "addr:postcode":"8900",
    "addr:street":"Valdemarsvej",
    "iso:country":"DK",
    "sg:address":"Valdemarsvej 2",
    "sg:city":"Randers",
    "sg:orig_category":"Kiosker",
    "sg:phone":"+45 86 43 80 83",
    "sg:postcode":"8900",
    "sg:province":"Danmark",
    "wof:name":"Kristrup D\u00f8gner",
    "wof:placetype":"venue"
},
  "geometry": {"coordinates":[10.054807663,56.4474525452],"type":"Point"}
}