{
  "type": "Feature",
  "properties": {
    "iso:country":"DK",
    "sg:address":"Toldbodgade 14",
    "sg:city":"Roskilde",
    "sg:orig_category":"Begravelsesforretninger",
    "sg:phone":"+45 46 35 08 82",
    "sg:postcode":"4000",
    "sg:province":"Danmark",
    "sg:website":"www.wismann.dk",
    "wof:name":"A/S Wismann's Begravelsesforretning",
    "wof:placetype":"venue"
},
  "geometry": {"coordinates":[12.084249,55.638287],"type":"Point"}
}