{
  "type": "Feature",
  "properties": {
    "iso:country":"DK",
    "sg:address":"Vestergade 60",
    "sg:city":"Randers",
    "sg:orig_category":"Internet, programmering",
    "sg:phone":"+45 70 10 76 00",
    "sg:postcode":"8900",
    "sg:province":"Danmark",
    "sg:website":"www.infoserv.dk",
    "wof:name":"Infoserv ApS, Webbureauet",
    "wof:placetype":"venue"
},
  "geometry": {"coordinates":[10.0256853104,56.4617958069],"type":"Point"}
}