{
  "type": "Feature",
  "properties": {
    "addr:full":"Bredgade 30 Herning Danmark 7400",
    "addr:housenumber":"30",
    "addr:postcode":"7400",
    "addr:street":"Bredgade",
    "iso:country":"DK",
    "sg:address":"Bredgade 30",
    "sg:city":"Herning",
    "sg:orig_category":"Optikere",
    "sg:phone":"+45 97 12 48 22",
    "sg:postcode":"7400",
    "sg:province":"Danmark",
    "wof:name":"Profil Optik",
    "wof:placetype":"venue"
},
  "geometry": {"coordinates":[8.9707555771,56.1363868713],"type":"Point"}
}