{
  "type": "Feature",
  "properties": {
    "addr:full":"N\u00f8rregade 46 Vejen Danmark 6600",
    "addr:housenumber":"46",
    "addr:postcode":"6600",
    "addr:street":"Norregade",
    "iso:country":"DK",
    "sg:address":"N\u00f8rregade 46",
    "sg:city":"Vejen",
    "sg:orig_category":"Ure og urmagere",
    "sg:phone":"+45 75 36 66 00",
    "sg:postcode":"6600",
    "sg:province":"Danmark",
    "wof:name":"Anytime",
    "wof:placetype":"venue"
},
  "geometry": {"coordinates":[9.1391992569,55.4785423279],"type":"Point"}
}