{
  "type": "Feature",
  "properties": {
    "addr:full":"Brynet 68, Bramdrupdam Kolding Danmark 6000",
    "addr:housenumber":"68",
    "addr:postcode":"6000",
    "addr:street":"Brynet;Bramdrupdam",
    "iso:country":"DK",
    "sg:address":"Brynet 68, Bramdrupdam",
    "sg:city":"Kolding",
    "sg:orig_category":"Musik- og sangundervisning",
    "sg:phone":"+45 75 56 83 13",
    "sg:postcode":"6000",
    "sg:province":"Danmark",
    "wof:name":"Griechen, Kurt",
    "wof:placetype":"venue"
},
  "geometry": {"coordinates":[9.4733953476,55.4863586426],"type":"Point"}
}