{
  "type": "Feature",
  "properties": {
    "iso:country":"DK",
    "sg:address":"Kirketorvet 22",
    "sg:city":"Vejle",
    "sg:orig_category":"Tandklinikker, Kommunale",
    "sg:phone":"+45 75 82 71 66",
    "sg:postcode":"7100",
    "sg:province":"Danmark",
    "wof:name":"Tandreguleringsklinik",
    "wof:placetype":"venue"
},
  "geometry": {"coordinates":[9.5351409912,55.7072639465],"type":"Point"}
}