{
  "type": "Feature",
  "properties": {
    "addr:full":"v/Hans Chr. Svendsen, Gr\u00f8nkj\u00e6rsvej 48, Errits\u00f8 Fredericia Danmark 7000",
    "addr:housenumber":"48",
    "addr:postcode":"7000",
    "addr:street":"Gronkjaersvej",
    "iso:country":"DK",
    "sg:address":"v/Hans Chr. Svendsen, Gr\u00f8nkj\u00e6rsvej 48, Errits\u00f8",
    "sg:city":"Fredericia",
    "sg:orig_category":"Musik og sang",
    "sg:phone":"+45 75 94 31 09",
    "sg:postcode":"7000",
    "sg:province":"Danmark",
    "wof:name":"Lilleb\u00e6lt Jazz",
    "wof:placetype":"venue"
},
  "geometry": {"coordinates":[9.7591047287,55.566368103],"type":"Point"}
}