{
  "type": "Feature",
  "properties": {
    "addr:full":"F\u00e6lledvej 16, st. K\u00f8benhavn N Danmark 2200",
    "addr:housenumber":"16",
    "addr:postcode":"2200",
    "addr:street":"Faelledvej",
    "iso:country":"DK",
    "sg:address":"F\u00e6lledvej 16, st.",
    "sg:city":"K\u00f8benhavn N",
    "sg:orig_category":"Slagter og viktualie",
    "sg:phone":"+45 35 37 05 32",
    "sg:postcode":"2200",
    "sg:province":"Danmark",
    "wof:name":"Islamisk Slagteri Tajbat Slagteri",
    "wof:placetype":"venue"
},
  "geometry": {"coordinates":[-69.97273254389999,-38.6255493164],"type":"Point"}
}