{
  "type": "Feature",
  "properties": {
    "addr:full":"Parkvej 2 Herning Danmark 7400",
    "addr:housenumber":"2",
    "addr:postcode":"7400",
    "addr:street":"Parkvej",
    "iso:country":"DK",
    "sg:address":"Parkvej 2",
    "sg:city":"Herning",
    "sg:orig_category":"Fritidsklubber",
    "sg:phone":"+45 97 12 26 99",
    "sg:postcode":"7400",
    "sg:province":"Danmark",
    "wof:name":"Juniorklubben Mejsen",
    "wof:placetype":"venue"
},
  "geometry": {"coordinates":[8.9884977341,56.1375312805],"type":"Point"}
}