{
  "type": "Feature",
  "properties": {
    "iso:country":"DK",
    "sg:address":"Elverdamsvej 308",
    "sg:city":"Kirke Hyllinge",
    "sg:orig_category":"Servicestationer",
    "sg:phone":"+45 46 40 41 11",
    "sg:postcode":"4070",
    "sg:province":"Danmark",
    "wof:name":"Hydro Texaco Benzin",
    "wof:placetype":"venue"
},
  "geometry": {"coordinates":[11.8672895432,55.6932983398],"type":"Point"}
}