{
  "type": "Feature",
  "properties": {
    "addr:full":"Fmd.: Kurt Pedersen, N\u00f8rretorp 154, Gjellerup Herning Danmark 7400",
    "addr:housenumber":"154",
    "addr:postcode":"7400",
    "addr:street":"Gjellerup",
    "iso:country":"DK",
    "sg:address":"Fmd.: Kurt Pedersen, N\u00f8rretorp 154, Gjellerup",
    "sg:city":"Herning",
    "sg:orig_category":"Hobbybetonede foreninger",
    "sg:phone":"+45 97 11 62 07",
    "sg:postcode":"7400",
    "sg:province":"Danmark",
    "wof:name":"Gjellerup Sogns Havekreds",
    "wof:placetype":"venue"
},
  "geometry": {"coordinates":[8.9768896103,56.1374168396],"type":"Point"}
}