{
  "type": "Feature",
  "properties": {
    "addr:full":"Ballerup-Centret 1 sal Ballerup Danmark 2750",
    "addr:housenumber":"1",
    "addr:postcode":"2750",
    "addr:street":"Ballerup-Centret",
    "iso:country":"DK",
    "sg:address":"Ballerup-Centret 1 sal",
    "sg:city":"Ballerup",
    "sg:orig_category":"Fotohandlere",
    "sg:phone":"+45 44 65 35 05",
    "sg:postcode":"2750",
    "sg:province":"Danmark",
    "sg:website":"www.bingo-foto.dk",
    "wof:name":"Bingo Foto",
    "wof:placetype":"venue"
},
  "geometry": {"coordinates":[12.361000061,55.7301216125],"type":"Point"}
}