{
  "type": "Feature",
  "properties": {
    "addr:full":"Heimdalsvej 14 Grindsted Danmark 7200",
    "addr:housenumber":"14",
    "addr:postcode":"7200",
    "addr:street":"Heimdalsvej",
    "iso:country":"DK",
    "sg:address":"Heimdalsvej 14",
    "sg:city":"Grindsted",
    "sg:orig_category":"Autoforhandlere",
    "sg:phone":"+45 75 32 34 00",
    "sg:postcode":"7200",
    "sg:province":"Danmark",
    "wof:name":"VesterBiler A/S",
    "wof:placetype":"venue"
},
  "geometry": {"coordinates":[8.9642467499,55.7552604675],"type":"Point"}
}