{
  "type": "Feature",
  "properties": {
    "addr:full":"Suensonsvej 1 Frederikshavn Danmark 9900",
    "addr:housenumber":"1",
    "addr:postcode":"9900",
    "addr:street":"Suensonsvej",
    "iso:country":"DK",
    "sg:address":"Suensonsvej 1",
    "sg:city":"Frederikshavn",
    "sg:orig_category":"Vuggestuer",
    "sg:phone":"+45 98 42 39 44",
    "sg:postcode":"9900",
    "sg:province":"Danmark",
    "wof:name":"Storkereden, Vuggestuen",
    "wof:placetype":"venue"
},
  "geometry": {"coordinates":[10.5145893097,57.4419364929],"type":"Point"}
}