{
  "type": "Feature",
  "properties": {
    "addr:full":"Rodstrupvej 22, Rodstrup Nibe Danmark 9240",
    "addr:housenumber":"22",
    "addr:postcode":"9240",
    "addr:street":"Rodstrupvej;Rodstrup",
    "iso:country":"DK",
    "sg:address":"Rodstrupvej 22, Rodstrup",
    "sg:city":"Nibe",
    "sg:orig_category":"Maskinstationer",
    "sg:phone":"+45 98 35 17 03",
    "sg:postcode":"9240",
    "sg:province":"Danmark",
    "wof:name":"Rostrup Maskinstation I/S",
    "wof:placetype":"venue"
},
  "geometry": {"coordinates":[9.6393280029,56.982421875],"type":"Point"}
}