{
  "type": "Feature",
  "properties": {
    "addr:full":"Slagelse Landevej 34, Gyldenholm Slagelse Danmark 4200",
    "addr:housenumber":"34",
    "addr:postcode":"4200",
    "addr:street":"Slagelse Landevej;Gyldenholm",
    "iso:country":"DK",
    "sg:address":"Slagelse Landevej 34, Gyldenholm",
    "sg:city":"Slagelse",
    "sg:orig_category":"Rideskoler",
    "sg:phone":"+45 58 54 55 81",
    "sg:postcode":"4200",
    "sg:province":"Danmark",
    "wof:name":"Houmarken Ridecenter",
    "wof:placetype":"venue"
},
  "geometry": {"coordinates":[11.3569850922,55.4050865173],"type":"Point"}
}