{
  "type": "Feature",
  "properties": {
    "iso:country":"DK",
    "sg:address":"Sparmarked, Skelbyvej 55, Skelby",
    "sg:city":"Herlufmagle",
    "sg:orig_category":"Apoteker og -udsalg",
    "sg:phone":"+45 55 45 00 11",
    "sg:postcode":"4160",
    "sg:province":"Danmark",
    "wof:name":"Glums\u00f8 Apotek H\u00e5ndk\u00f8bsudsalg",
    "wof:placetype":"venue"
},
  "geometry": {"coordinates":[11.7522201538,55.3147735596],"type":"Point"}
}