{
  "type": "Feature",
  "properties": {
    "addr:full":"Strandvejen 895  Klampenborg Danmark 2930",
    "addr:housenumber":"895",
    "addr:postcode":"2930",
    "addr:street":"Strandvejen",
    "iso:country":"DK",
    "sg:address":"Strandvejen 895 ",
    "sg:city":"Klampenborg",
    "sg:classifiers":[
        {
            "category":"Wholesale",
            "subcategory":"Drugs",
            "type":"Manufacturing & Wholesale Goods"
        }
    ],
    "sg:phone":"+45 45 80 30 05",
    "sg:postcode":"2930",
    "sg:province":"Danmark",
    "sg:tags":[
        "chemical",
        "pharmaceutical"
    ],
    "wof:name":"STRANDM\u00d8LLEBN INDRUSTRIGAS A/S",
    "wof:placetype":"venue"
},
  "geometry": {"coordinates":[12.581199646,55.8079795837],"type":"Point"}
}