{
  "type": "Feature",
  "properties": {
    "addr:full":"Lundby Hovedgade 35 - 37 Lundby Danmark 4750",
    "addr:housenumber":"35 37",
    "addr:postcode":"4750",
    "addr:street":"Lundby Hovedgade",
    "iso:country":"DK",
    "sg:address":"Lundby Hovedgade 35 - 37",
    "sg:city":"Lundby",
    "sg:orig_category":"Maskinfabrikker",
    "sg:phone":"+45 55 76 73 90",
    "sg:postcode":"4750",
    "sg:province":"Danmark",
    "wof:name":"Ansh\u00f8j Maskinfabrik",
    "wof:placetype":"venue"
},
  "geometry": {"coordinates":[11.8656520844,55.109336853],"type":"Point"}
}