{
  "type": "Feature",
  "properties": {
    "iso:country":"DK",
    "sg:address":"Birketvej 94 D",
    "sg:city":"Bandholm",
    "sg:orig_category":"Integrerede institutioner",
    "sg:phone":"+45 54 78 81 48",
    "sg:postcode":"4941",
    "sg:province":"Danmark",
    "wof:name":"Bandholm B\u00f8rnehus",
    "wof:placetype":"venue"
},
  "geometry": {"coordinates":[11.4618177414,54.8396377563],"type":"Point"}
}