{
  "type": "Feature",
  "properties": {
    "addr:full":"Fmd.: Birte Jensen, H\u00e5strupvej 126, H\u00e5strup Fredericia Danmark 7000",
    "addr:housenumber":"126",
    "addr:postcode":"7000",
    "addr:street":"Haastrupvej;Haastrup",
    "iso:country":"DK",
    "sg:address":"Fmd.: Birte Jensen, H\u00e5strupvej 126, H\u00e5strup",
    "sg:city":"Fredericia",
    "sg:orig_category":"Husflidsforeninger",
    "sg:phone":"+45 75 86 06 46",
    "sg:postcode":"7000",
    "sg:province":"Danmark",
    "wof:name":"Smidstrup Husholdningsforening",
    "wof:placetype":"venue"
},
  "geometry": {"coordinates":[9.7591047287,55.566368103],"type":"Point"}
}