{
  "type": "Feature",
  "properties": {
    "iso:country":"DK",
    "sg:address":"Frenderupgade 2, Nr. Frenderup",
    "sg:city":"Stege",
    "sg:orig_category":"Biopater",
    "sg:phone":"+45 55 81 43 71",
    "sg:postcode":"4780",
    "sg:province":"Danmark",
    "wof:name":"Breitenstein, Lillian",
    "wof:placetype":"venue"
},
  "geometry": {"coordinates":[12.287527,54.985516],"type":"Point"}
}