{
  "type": "Feature",
  "properties": {
    "addr:full":"R\u00f8nnestvej 15 B Frederikshavn Danmark 9900",
    "addr:housenumber":"15 b",
    "addr:postcode":"9900",
    "addr:street":"Ronnestvej",
    "iso:country":"DK",
    "sg:address":"R\u00f8nnestvej 15 B",
    "sg:city":"Frederikshavn",
    "sg:orig_category":"Autoforhandlere",
    "sg:phone":"+45 20 66 70 70",
    "sg:postcode":"9900",
    "sg:province":"Danmark",
    "wof:name":"TK Auto",
    "wof:placetype":"venue"
},
  "geometry": {"coordinates":[10.5248241425,57.420955658],"type":"Point"}
}