{
  "type": "Feature",
  "properties": {
    "addr:full":"Skejbyvej 503 \u00c5rhus N Danmark 8200",
    "addr:housenumber":"503",
    "addr:postcode":"8200",
    "addr:street":"Skejbyvej",
    "iso:country":"DK",
    "sg:address":"Skejbyvej 503",
    "sg:city":"\u00c5rhus N",
    "sg:classifiers":[
        {
            "category":"Home & Garden",
            "subcategory":"Home Furnishings",
            "type":"Retail Goods"
        }
    ],
    "sg:phone":"+45 87 41 21 15",
    "sg:postcode":"8200",
    "sg:province":"Danmark",
    "sg:tags":[
        "gardiner"
    ],
    "wof:name":"A. I. Gardiner ApS",
    "wof:placetype":"venue"
},
  "geometry": {"coordinates":[4.9393601418,49.7092018127],"type":"Point"}
}