{
  "type": "Feature",
  "properties": {
    "iso:country":"DK",
    "sg:address":"Torvet 18",
    "sg:city":"Dianalund",
    "sg:orig_category":"Slagter og viktualie",
    "sg:phone":"+45 58 26 40 47",
    "sg:postcode":"4293",
    "sg:province":"Danmark",
    "wof:name":"Henrik Slagter",
    "wof:placetype":"venue"
},
  "geometry": {"coordinates":[11.4972038269,55.5266456604],"type":"Point"}
}