{
  "type": "Feature",
  "properties": {
    "addr:full":"Lysh\u00f8j M\u00f8llevej 2, Udbyover Havndal Danmark 8970",
    "addr:housenumber":"2",
    "addr:postcode":"8970",
    "addr:street":"Mollevej",
    "iso:country":"DK",
    "sg:address":"Lysh\u00f8j M\u00f8llevej 2, Udbyover",
    "sg:city":"Havndal",
    "sg:classifiers":[
        {
            "category":"Taxi",
            "type":"Transportation"
        }
    ],
    "sg:phone":"+45 86 47 06 84",
    "sg:postcode":"8970",
    "sg:province":"Danmark",
    "wof:name":"Havndal Taxi",
    "wof:placetype":"venue"
},
  "geometry": {"coordinates":[10.1937646866,56.6534461975],"type":"Point"}
}