{
  "type": "Feature",
  "properties": {
    "addr:full":"Lystrupvej 238 Lystrup Danmark 8520",
    "addr:housenumber":"238",
    "addr:postcode":"8520",
    "addr:street":"Lystrupvej",
    "iso:country":"DK",
    "sg:address":"Lystrupvej 238",
    "sg:city":"Lystrup",
    "sg:orig_category":"Cykler",
    "sg:phone":"+45 86 22 82 66",
    "sg:postcode":"8520",
    "sg:province":"Danmark",
    "wof:name":"Lystrup Cykel Center",
    "wof:placetype":"venue"
},
  "geometry": {"coordinates":[10.2316951752,56.2317199707],"type":"Point"}
}