{
  "type": "Feature",
  "properties": {
    "addr:full":"Pyrus Alle 20 Kastrup Danmark 2770",
    "addr:housenumber":"20",
    "addr:postcode":"2770",
    "addr:street":"Pyrus Alle",
    "iso:country":"DK",
    "sg:address":"Pyrus Alle 20",
    "sg:city":"Kastrup",
    "sg:orig_category":"Fabrikker",
    "sg:phone":"+45 32 51 19 28",
    "sg:postcode":"2770",
    "sg:province":"Danmark",
    "wof:name":"S\u00f8rensens Metalvarefabr., P.",
    "wof:placetype":"venue"
},
  "geometry": {"coordinates":[12.626953125,55.6378097534],"type":"Point"}
}