{
  "type": "Feature",
  "properties": {
    "addr:full":"Kongensgade 98 - 2 Ringsted Danmark 4100",
    "addr:housenumber":"98 2",
    "addr:postcode":"4100",
    "addr:street":"Kongensgade",
    "iso:country":"DK",
    "sg:address":"Kongensgade 98 - 2",
    "sg:city":"Ringsted",
    "sg:orig_category":"\u00c3\u02dcvrige institutioner",
    "sg:phone":"+45 57 61 90 33",
    "sg:postcode":"4100",
    "sg:province":"Danmark",
    "wof:name":"Bof\u00e6llesskab M\u00f8lleparken",
    "wof:placetype":"venue"
},
  "geometry": {"coordinates":[11.7986707687,55.4433174133],"type":"Point"}
}