{
  "type": "Feature",
  "properties": {
    "iso:country":"DK",
    "sg:address":"Kirkev\u00e6nget 2 A, Magleby",
    "sg:city":"Klippinge",
    "sg:orig_category":"Kirker",
    "sg:postcode":"4672",
    "sg:province":"Danmark",
    "wof:name":"Magleby Kirke",
    "wof:placetype":"venue"
},
  "geometry": {"coordinates":[12.3291807175,55.3516769409],"type":"Point"}
}