{
  "type": "Feature",
  "properties": {
    "addr:full":"Kirke Alle 1, Ramsing Sp\u00f8ttrup Danmark 7860",
    "addr:housenumber":"1",
    "addr:postcode":"7860",
    "addr:street":"Kirke Alle",
    "iso:country":"DK",
    "sg:address":"Kirke Alle 1, Ramsing",
    "sg:city":"Sp\u00f8ttrup",
    "sg:orig_category":"Dagplejeformidling",
    "sg:phone":"+45 96 83 44 00",
    "sg:postcode":"7860",
    "sg:province":"Danmark",
    "wof:name":"Dagplejeformidlingen i Sp\u00f8ttrup Kommune",
    "wof:placetype":"venue"
},
  "geometry": {"coordinates":[8.7428588867,56.5733261108],"type":"Point"}
}