{
  "type": "Feature",
  "properties": {
    "iso:country":"DK",
    "sg:address":"Tranegilde Bygade 8",
    "sg:city":"Ish\u00f8j",
    "sg:orig_category":"Malermestre",
    "sg:phone":"+45 43 54 93 36",
    "sg:postcode":"2635",
    "sg:province":"Danmark",
    "wof:name":"Poulsen, Steen",
    "wof:placetype":"venue"
},
  "geometry": {"coordinates":[12.3472137451,55.6250686646],"type":"Point"}
}