{
  "type": "Feature",
  "properties": {
    "addr:full":"Sognepr\u00e6st: Keld Balmer Hansen (K/B), Pr\u00e6stevejen 8, \u00d8strup Otterup Danmark 5450",
    "addr:housenumber":"8",
    "addr:postcode":"5450",
    "addr:street":"Praestevejen",
    "iso:country":"DK",
    "sg:address":"Sognepr\u00e6st: Keld Balmer Hansen (K/B), Pr\u00e6stevejen 8, \u00d8strup",
    "sg:city":"Otterup",
    "sg:orig_category":"Kirkesogne",
    "sg:phone":"+45 64 82 13 07",
    "sg:postcode":"5450",
    "sg:province":"Danmark",
    "wof:name":"\u00d8strup og Skeby sogne (herunder Gerskov kirke)",
    "wof:placetype":"venue"
},
  "geometry": {"coordinates":[10.4545049667,55.5641746521],"type":"Point"}
}