{
  "type": "Feature",
  "properties": {
    "addr:full":"Bredgade 67 Herning Danmark 7400",
    "addr:housenumber":"67",
    "addr:postcode":"7400",
    "addr:street":"Bredgade",
    "iso:country":"DK",
    "sg:address":"Bredgade 67",
    "sg:city":"Herning",
    "sg:orig_category":"Dyreklinikker og -hospitaler",
    "sg:phone":"+45 97 22 27 28",
    "sg:postcode":"7400",
    "sg:province":"Danmark",
    "wof:name":"Herning Dyrehospitals Dyreklinik",
    "wof:placetype":"venue"
},
  "geometry": {"coordinates":[8.9670295715,56.1362686157],"type":"Point"}
}