{
  "type": "Feature",
  "properties": {
    "iso:country":"DK",
    "sg:address":"Smedev\u00e6nget 15, Stenstrup",
    "sg:city":"N\u00e6stved",
    "sg:orig_category":"Maskinudlejning",
    "sg:phone":"+45 70 15 22 22",
    "sg:postcode":"4700",
    "sg:province":"Danmark",
    "wof:name":"Altima Maskinudlejning A/S",
    "wof:placetype":"venue"
},
  "geometry": {"coordinates":[11.7542486191,55.2315444946],"type":"Point"}
}