{
  "type": "Feature",
  "properties": {
    "addr:full":"F\u00e6lledvej 17 Struer Danmark 7600",
    "addr:housenumber":"17",
    "addr:postcode":"7600",
    "addr:street":"Faelledvej",
    "iso:country":"DK",
    "sg:address":"F\u00e6lledvej 17",
    "sg:city":"Struer",
    "sg:orig_category":"Telekommunikation",
    "sg:phone":"+45 97 86 90 22",
    "sg:postcode":"7600",
    "sg:province":"Danmark",
    "wof:name":"Ericsson Diax A/S",
    "wof:placetype":"venue"
},
  "geometry": {"coordinates":[8.5821609497,56.4768943787],"type":"Point"}
}