{
  "type": "Feature",
  "properties": {
    "addr:full":"Aaby Centret 12 Aabybro Danmark 9440",
    "addr:housenumber":"12",
    "addr:postcode":"9440",
    "addr:street":"Aaby Centret",
    "iso:country":"DK",
    "sg:address":"Aaby Centret 12",
    "sg:city":"Aabybro",
    "sg:classifiers":[
        {
            "category":"Banks & Credit Unions",
            "subcategory":"Bank",
            "type":"Services"
        }
    ],
    "sg:phone":"+45 96 96 20 80",
    "sg:postcode":"9440",
    "sg:province":"Danmark",
    "sg:tags":[
        "banker"
    ],
    "sg:website":"www.danskebank.dk",
    "wof:name":"Danske Bank",
    "wof:placetype":"venue"
},
  "geometry": {"coordinates":[9.7354221344,57.1594276428],"type":"Point"}
}