{
  "type": "Feature",
  "properties": {
    "iso:country":"DK",
    "sg:address":"Kalvehavevej 7",
    "sg:city":"Mern",
    "sg:orig_category":"Autoreparation og -service",
    "sg:phone":"+45 55 99 70 99",
    "sg:postcode":"4735",
    "sg:province":"Danmark",
    "wof:name":"Mern Karosseri",
    "wof:placetype":"venue"
},
  "geometry": {"coordinates":[12.0613861084,55.0474357605],"type":"Point"}
}