{
  "type": "Feature",
  "properties": {
    "addr:full":"N\u00f8rretorv 2 H Vejle Danmark 7100",
    "addr:housenumber":"2 h",
    "addr:postcode":"7100",
    "addr:street":"Norretorv",
    "iso:country":"DK",
    "sg:address":"N\u00f8rretorv 2 H",
    "sg:city":"Vejle",
    "sg:orig_category":"Ejendomshandel",
    "sg:phone":"+45 75 82 25 22",
    "sg:postcode":"7100",
    "sg:province":"Danmark",
    "wof:name":"Klinkby, EDC-M\u00e6glerne Kaj",
    "wof:placetype":"venue"
},
  "geometry": {"coordinates":[9.5368051529,55.7113952637],"type":"Point"}
}