{
  "type": "Feature",
  "properties": {
    "addr:full":"Pileg\u00e5rdsvej 21, st. tv. Herlev Danmark 2730",
    "addr:housenumber":"21 st. tv.",
    "addr:postcode":"2730",
    "addr:street":"Pilegaardsvej",
    "iso:country":"DK",
    "sg:address":"Pileg\u00e5rdsvej 21, st. tv.",
    "sg:city":"Herlev",
    "sg:orig_category":"Fodterapeuter",
    "sg:phone":"+45 40 11 51 15",
    "sg:postcode":"2730",
    "sg:province":"Danmark",
    "wof:name":"Fodterapi",
    "wof:placetype":"venue"
},
  "geometry": {"coordinates":[12.4382095337,55.7250595093],"type":"Point"}
}