{
  "type": "Feature",
  "properties": {
    "iso:country":"DK",
    "sg:address":"Vall\u00f8esgade 22",
    "sg:city":"Vejle",
    "sg:orig_category":"Gulvafslibning",
    "sg:phone":"+45 75 82 47 23",
    "sg:postcode":"7100",
    "sg:province":"Danmark",
    "wof:name":"Hummel Gulvafslibning",
    "wof:placetype":"venue"
},
  "geometry": {"coordinates":[9.5484523773,55.7107849121],"type":"Point"}
}