{
  "type": "Feature",
  "properties": {
    "addr:full":"M\u00f8llev\u00e6nget 7, Baghuset, Vor Frue Roskilde Danmark 4000",
    "addr:housenumber":"7",
    "addr:postcode":"4000",
    "addr:street":"Mollevaenget;Vor Frue",
    "iso:country":"DK",
    "sg:address":"M\u00f8llev\u00e6nget 7, Baghuset, Vor Frue",
    "sg:city":"Roskilde",
    "sg:orig_category":"Antikviteter",
    "sg:phone":"+45 40 63 10 66",
    "sg:postcode":"4000",
    "sg:province":"Danmark",
    "wof:name":"Andersen, Hans H.",
    "wof:placetype":"venue"
},
  "geometry": {"coordinates":[12.0909376144,55.6404838562],"type":"Point"}
}