{
  "type": "Feature",
  "properties": {
    "addr:full":"E. Schous Alle 5 Juelsminde Danmark 7130",
    "addr:housenumber":"5",
    "addr:postcode":"7130",
    "addr:street":"E. Schous Alle",
    "iso:country":"DK",
    "sg:address":"E. Schous Alle 5",
    "sg:city":"Juelsminde",
    "sg:orig_category":"Kopiering",
    "sg:phone":"+45 75 69 30 69",
    "sg:postcode":"7130",
    "sg:province":"Danmark",
    "wof:name":"Tekst Butikken",
    "wof:placetype":"venue"
},
  "geometry": {"coordinates":[10.0086040497,55.7148017883],"type":"Point"}
}