{
  "type": "Feature",
  "properties": {
    "addr:full":"Bredel\u00f8kkevej 9, Raaby Store Heddinge Danmark 4660",
    "addr:housenumber":"9",
    "addr:postcode":"4660",
    "addr:street":"Bredelokkevej",
    "iso:country":"DK",
    "sg:address":"Bredel\u00f8kkevej 9, Raaby",
    "sg:city":"Store Heddinge",
    "sg:orig_category":"Skilte",
    "sg:phone":"+45 21 68 68 82",
    "sg:postcode":"4660",
    "sg:province":"Danmark",
    "wof:name":"Prima Skilte",
    "wof:placetype":"venue"
},
  "geometry": {"coordinates":[12.3895797729,55.3113174438],"type":"Point"}
}