{
  "type": "Feature",
  "properties": {
    "addr:full":"Teestrup Bygade 7 Haslev Danmark 4690",
    "addr:housenumber":"7",
    "addr:postcode":"4690",
    "addr:street":"Teestrup Bygade",
    "iso:country":"DK",
    "sg:address":"Teestrup Bygade 7",
    "sg:city":"Haslev",
    "sg:orig_category":"\u00c3\u2020ldrecentre",
    "sg:phone":"+45 56 36 07 40",
    "sg:postcode":"4690",
    "sg:province":"Danmark",
    "wof:name":"Teestrupomr\u00e5det",
    "wof:placetype":"venue"
},
  "geometry": {"coordinates":[11.8815641403,55.327003479],"type":"Point"}
}