{
  "type": "Feature",
  "properties": {
    "addr:full":"Klampenborgvej 14 Svendborg Danmark 5700",
    "addr:housenumber":"14",
    "addr:postcode":"5700",
    "addr:street":"Klampenborgvej",
    "iso:country":"DK",
    "sg:address":"Klampenborgvej 14",
    "sg:city":"Svendborg",
    "sg:orig_category":"Teatre",
    "sg:phone":"+45 62 21 04 42",
    "sg:postcode":"5700",
    "sg:province":"Danmark",
    "wof:name":"Teaterxpressen",
    "wof:placetype":"venue"
},
  "geometry": {"coordinates":[10.6365909576,55.0619163513],"type":"Point"}
}