{
  "type": "Feature",
  "properties": {
    "addr:full":"Hyldeg\u00e5rdsvej 2 Charlottenlund Danmark 2920",
    "addr:housenumber":"2",
    "addr:postcode":"2920",
    "addr:street":"Hyldegaardsvej",
    "iso:country":"DK",
    "sg:address":"Hyldeg\u00e5rdsvej 2",
    "sg:city":"Charlottenlund",
    "sg:orig_category":"Sprogskoler",
    "sg:phone":"+45 39 64 23 20",
    "sg:postcode":"2920",
    "sg:province":"Danmark",
    "sg:website":"www.babel-sprog.dk",
    "wof:name":"Babel Sprogtr\u00e6ning",
    "wof:placetype":"venue"
},
  "geometry": {"coordinates":[12.5740423203,55.761177063],"type":"Point"}
}