{
  "type": "Feature",
  "properties": {
    "addr:full":"Kapelvej 47 K\u00f8benhavn N Danmark 2200",
    "addr:housenumber":"47",
    "addr:postcode":"2200",
    "addr:street":"Kapelvej;Kobenhavn N Danmark",
    "iso:country":"DK",
    "sg:address":"Kapelvej 47",
    "sg:city":"K\u00f8benhavn N",
    "sg:orig_category":"Sundhedscentre",
    "sg:phone":"+45 35 35 77 79",
    "sg:postcode":"2200",
    "sg:province":"Danmark",
    "wof:name":"Sund By-butikken, Indre N\u00f8rrebro",
    "wof:placetype":"venue"
},
  "geometry": {"coordinates":[-97.83954620359999,47.6792755127],"type":"Point"}
}