{
  "type": "Feature",
  "properties": {
    "addr:full":"Gl. Landevej 80, Errits\u00f8 Fredericia Danmark 7000",
    "addr:housenumber":"80",
    "addr:postcode":"7000",
    "addr:street":"Gl. Landevej",
    "iso:country":"DK",
    "sg:address":"Gl. Landevej 80, Errits\u00f8",
    "sg:city":"Fredericia",
    "sg:orig_category":"Termografi",
    "sg:phone":"+45 75 94 24 44",
    "sg:postcode":"7000",
    "sg:province":"Danmark",
    "sg:website":"www.bjeld-lauridsen.dk",
    "wof:name":"Bjeld & Lauridsen A/S",
    "wof:placetype":"venue"
},
  "geometry": {"coordinates":[9.7591047287,55.566368103],"type":"Point"}
}