{
  "type": "Feature",
  "properties": {
    "iso:country":"DK",
    "sg:address":"Kongevejen 29",
    "sg:city":"Holte",
    "sg:orig_category":"Antikviteter",
    "sg:phone":"+45 45 42 15 53",
    "sg:postcode":"2840",
    "sg:province":"Danmark",
    "wof:name":"Casa Antica",
    "wof:placetype":"venue"
},
  "geometry": {"coordinates":[12.4712400436,55.812789917],"type":"Point"}
}