{
  "type": "Feature",
  "properties": {
    "addr:full":"Snaptun Strandvej 9 Horsens Danmark 8700",
    "addr:housenumber":"9",
    "addr:postcode":"8700",
    "addr:street":"Snaptun Strandvej",
    "iso:country":"DK",
    "sg:address":"Snaptun Strandvej 9",
    "sg:city":"Horsens",
    "sg:orig_category":"Grillbarer",
    "sg:phone":"+45 75 68 37 88",
    "sg:postcode":"8700",
    "sg:province":"Danmark",
    "wof:name":"Havne Bistro",
    "wof:placetype":"venue"
},
  "geometry": {"coordinates":[10.050775528,55.8219680786],"type":"Point"}
}