{
  "type": "Feature",
  "properties": {
    "addr:full":"Annexg\u00e5rdsparken 13, Kr. V\u00e6rl\u00f8se V\u00e6rl\u00f8se Danmark 3500",
    "addr:housenumber":"13 kr.",
    "addr:postcode":"3500",
    "addr:street":"Annexgaardsparken",
    "iso:country":"DK",
    "sg:address":"Annexg\u00e5rdsparken 13, Kr. V\u00e6rl\u00f8se",
    "sg:city":"V\u00e6rl\u00f8se",
    "sg:orig_category":"Emballage",
    "sg:phone":"+45 44 48 88 80",
    "sg:postcode":"3500",
    "sg:province":"Danmark",
    "sg:website":"www.borkelectronic.dk",
    "wof:name":"J\u00f8rgen Bork Electronic ApS",
    "wof:placetype":"venue"
},
  "geometry": {"coordinates":[127.8501663208,36.4481506348],"type":"Point"}
}