{
  "type": "Feature",
  "properties": {
    "addr:full":"Uhre Skovvej 30 Jordrup Danmark 6064",
    "addr:housenumber":"30",
    "addr:postcode":"6064",
    "addr:street":"Uhre Skovvej",
    "iso:country":"DK",
    "sg:address":"Uhre Skovvej 30",
    "sg:city":"Jordrup",
    "sg:orig_category":"Murermestre",
    "sg:phone":"+45 75 55 62 04",
    "sg:postcode":"6064",
    "sg:province":"Danmark",
    "wof:name":"Schilling, Erling",
    "wof:placetype":"venue"
},
  "geometry": {"coordinates":[9.3534793854,55.5535736084],"type":"Point"}
}