{
  "type": "Feature",
  "properties": {
    "addr:full":"Hellestrupvej 42, S Asmindrup Vipper\u00f8d Danmark 4390",
    "addr:housenumber":"42",
    "addr:postcode":"4390",
    "addr:street":"Hellestrupvej;S Asmindrup;Danmark",
    "iso:country":"DK",
    "sg:address":"Hellestrupvej 42, S Asmindrup",
    "sg:city":"Vipper\u00f8d",
    "sg:orig_category":"Isolering",
    "sg:phone":"+45 59 18 26 14",
    "sg:postcode":"4390",
    "sg:province":"Danmark",
    "wof:name":"I.H. Isolering",
    "wof:placetype":"venue"
},
  "geometry": {"coordinates":[11.770031929,55.6723098755],"type":"Point"}
}