{
  "type": "Feature",
  "properties": {
    "addr:full":"Solbjerg Plads 3 Frederiksberg Danmark 2000",
    "addr:housenumber":"3",
    "addr:postcode":"2000",
    "addr:street":"Solbjerg Plads",
    "iso:country":"DK",
    "sg:address":"Solbjerg Plads 3",
    "sg:city":"Frederiksberg",
    "sg:orig_category":"Politiske foreninger, \u00c3\u02dcvrige",
    "sg:phone":"+45 38 15 39 39",
    "sg:postcode":"2000",
    "sg:province":"Danmark",
    "wof:name":"Moderate Studenter",
    "wof:placetype":"venue"
},
  "geometry": {"coordinates":[12.5306367874,55.6818237305],"type":"Point"}
}