{
  "type": "Feature",
  "properties": {
    "iso:country":"DK",
    "sg:address":"S\u00f8ren M\u00f8llers Gade 5 B",
    "sg:city":"Randers",
    "sg:orig_category":"Botilbud",
    "sg:phone":"+45 86 41 24 33",
    "sg:postcode":"8900",
    "sg:province":"Danmark",
    "wof:name":"Hj\u00f8rnestenen, Kirkens Korsh\u00e6rs Institutionstilbud",
    "wof:placetype":"venue"
},
  "geometry": {"coordinates":[10.0285778046,56.4624023438],"type":"Point"}
}