{
  "type": "Feature",
  "properties": {
    "addr:full":"Svirrebom 4, 1. Lemvig Danmark 7620",
    "addr:housenumber":"4 1",
    "addr:postcode":"7620",
    "addr:street":"Svirrebom",
    "iso:country":"DK",
    "sg:address":"Svirrebom 4, 1.",
    "sg:city":"Lemvig",
    "sg:orig_category":"Revisorer",
    "sg:phone":"+45 97 81 05 66",
    "sg:postcode":"7620",
    "sg:province":"Danmark",
    "wof:name":"HB Revision I/S",
    "wof:placetype":"venue"
},
  "geometry": {"coordinates":[8.3083953857,56.5497245789],"type":"Point"}
}