{
  "type": "Feature",
  "properties": {
    "addr:full":"Mikkel Vibes Gade 1,St.tv. K\u00f8benhavn Danmark 1417",
    "addr:housenumber":"1",
    "addr:postcode":"1417",
    "addr:street":"Mikkel Vibes Gade",
    "iso:country":"DK",
    "sg:address":"Mikkel Vibes Gade 1,St.tv.",
    "sg:city":"K\u00f8benhavn",
    "sg:orig_category":"Arkitekter",
    "sg:phone":"+45 32 57 27 33",
    "sg:postcode":"1417",
    "sg:province":"Danmark",
    "wof:name":"Pires, Francisco Serrano",
    "wof:placetype":"venue"
},
  "geometry": {"coordinates":[12.5923299789,55.6726989746],"type":"Point"}
}