{
  "type": "Feature",
  "properties": {
    "addr:full":"Kastrupvej 51 K\u00f8benhavn S Danmark 2300",
    "addr:housenumber":"51",
    "addr:postcode":"2300",
    "addr:street":"Kastrupvej;Kobenhavn S Danmark",
    "iso:country":"DK",
    "sg:address":"Kastrupvej 51",
    "sg:city":"K\u00f8benhavn S",
    "sg:orig_category":"Stenhuggere",
    "sg:phone":"+45 32 59 14 76",
    "sg:postcode":"2300",
    "sg:province":"Danmark",
    "wof:name":"Nielsen's Stenhuggeri, E.",
    "wof:placetype":"venue"
},
  "geometry": {"coordinates":[-98.4802474976,36.0598182678],"type":"Point"}
}