{
  "type": "Feature",
  "properties": {
    "addr:full":"Hestedamsgade 14 Horsens Danmark 8700",
    "addr:housenumber":"14",
    "addr:postcode":"8700",
    "addr:street":"Hestedamsgade",
    "iso:country":"DK",
    "sg:address":"Hestedamsgade 14",
    "sg:city":"Horsens",
    "sg:orig_category":"Blomsterhandlere",
    "sg:phone":"+45 75 62 70 10",
    "sg:postcode":"8700",
    "sg:province":"Danmark",
    "wof:name":"Anna Kristine",
    "wof:placetype":"venue"
},
  "geometry": {"coordinates":[9.8455219269,55.8626098633],"type":"Point"}
}