{
  "type": "Feature",
  "properties": {
    "addr:full":"Tingvej 55, Tostrup M\u00f8ldrup Danmark 9632",
    "addr:housenumber":"55",
    "addr:postcode":"9632",
    "addr:street":"Tingvej",
    "iso:country":"DK",
    "sg:address":"Tingvej 55, Tostrup",
    "sg:city":"M\u00f8ldrup",
    "sg:orig_category":"Murermestre",
    "sg:phone":"+45 86 69 12 47",
    "sg:postcode":"9632",
    "sg:province":"Danmark",
    "wof:name":"Tostrup Murerforretning ApS",
    "wof:placetype":"venue"
},
  "geometry": {"coordinates":[9.4993553162,56.5840339661],"type":"Point"}
}