{
  "type": "Feature",
  "properties": {
    "addr:full":"Storegade 52 Brande Danmark 7330",
    "addr:housenumber":"52",
    "addr:postcode":"7330",
    "addr:street":"Storegade",
    "iso:country":"DK",
    "sg:address":"Storegade 52",
    "sg:city":"Brande",
    "sg:classifiers":[
        {
            "category":"Restaurant",
            "type":"Food & Drink"
        }
    ],
    "sg:phone":"+45 97 18 39 51",
    "sg:postcode":"7330",
    "sg:province":"Danmark",
    "wof:name":"Peking Grill",
    "wof:placetype":"venue"
},
  "geometry": {"coordinates":[9.1287603378,55.9420700073],"type":"Point"}
}