{
  "type": "Feature",
  "properties": {
    "addr:full":"Alumevangen 37, Smidstrup Gilleleje Danmark 3250",
    "addr:housenumber":"37",
    "addr:postcode":"3250",
    "addr:street":"Alumevangen",
    "iso:country":"DK",
    "sg:address":"Alumevangen 37, Smidstrup",
    "sg:city":"Gilleleje",
    "sg:orig_category":"Vinduespolering",
    "sg:phone":"+45 48 31 98 90",
    "sg:postcode":"3250",
    "sg:province":"Danmark",
    "wof:name":"Smidstrup Vinduespolering",
    "wof:placetype":"venue"
},
  "geometry": {"coordinates":[12.3087387085,56.123462677],"type":"Point"}
}