{
  "type": "Feature",
  "properties": {
    "addr:full":"Stavnsholtvej 43 Farum Danmark 3520",
    "addr:housenumber":"43",
    "addr:postcode":"3520",
    "addr:street":"Stavnsholtvej",
    "iso:country":"DK",
    "sg:address":"Stavnsholtvej 43",
    "sg:city":"Farum",
    "sg:orig_category":"Tandklinikker, Kommunale",
    "sg:phone":"+45 77 43 44 70",
    "sg:postcode":"3520",
    "sg:province":"Danmark",
    "wof:name":"Stavnsholtskolens Tandklinik",
    "wof:placetype":"venue"
},
  "geometry": {"coordinates":[12.3956241608,55.8145523071],"type":"Point"}
}