{
  "type": "Feature",
  "properties": {
    "addr:full":"Frederikskildevej 6 Aalborg Danmark 9000",
    "addr:housenumber":"6",
    "addr:postcode":"9000",
    "addr:street":"Frederikskildevej",
    "iso:country":"DK",
    "sg:address":"Frederikskildevej 6",
    "sg:city":"Aalborg",
    "sg:orig_category":"Kulturcentre",
    "sg:phone":"+45 98 11 73 11",
    "sg:postcode":"9000",
    "sg:province":"Danmark",
    "wof:name":"Kildev\u00e6ld, Kunstnerv\u00e6rksted",
    "wof:placetype":"venue"
},
  "geometry": {"coordinates":[9.8960227966,57.0434494019],"type":"Point"}
}