{
  "type": "Feature",
  "properties": {
    "addr:full":"N\u00e6ssundvej 327, V. Hvidbjerg Karby Danmark 7960",
    "addr:housenumber":"327 v.",
    "addr:postcode":"7960",
    "addr:street":"Naessundvej;Hvidbjerg",
    "iso:country":"DK",
    "sg:address":"N\u00e6ssundvej 327, V. Hvidbjerg",
    "sg:city":"Karby",
    "sg:orig_category":"Varmeforsyning",
    "sg:phone":"+45 97 76 25 33",
    "sg:postcode":"7960",
    "sg:province":"Danmark",
    "wof:name":"Sdr. Herreds Kraftvarmev\u00e6rker A.m.b.a.",
    "wof:placetype":"venue"
},
  "geometry": {"coordinates":[8.5592756271,56.7536697388],"type":"Point"}
}