{
  "type": "Feature",
  "properties": {
    "addr:full":"Orte Byvej 16, Orte Aarup Danmark 5560",
    "addr:housenumber":"16",
    "addr:postcode":"5560",
    "addr:street":"Orte Byvej",
    "iso:country":"DK",
    "sg:address":"Orte Byvej 16, Orte",
    "sg:city":"Aarup",
    "sg:orig_category":"Kirker",
    "sg:postcode":"5560",
    "sg:province":"Danmark",
    "wof:name":"Orte Kirke",
    "wof:placetype":"venue"
},
  "geometry": {"coordinates":[10.0490245819,55.3808059692],"type":"Point"}
}