{
  "type": "Feature",
  "properties": {
    "addr:full":"Rosenborgtoften 11 Silkeborg Danmark 8600",
    "addr:housenumber":"11",
    "addr:postcode":"8600",
    "addr:street":"Rosenborgtoften",
    "iso:country":"DK",
    "sg:address":"Rosenborgtoften 11",
    "sg:city":"Silkeborg",
    "sg:orig_category":"Databehandling",
    "sg:phone":"+45 86 83 64 38",
    "sg:postcode":"8600",
    "sg:province":"Danmark",
    "wof:name":"Maiko Data",
    "wof:placetype":"venue"
},
  "geometry": {"coordinates":[9.554268837,56.1328277588],"type":"Point"}
}