{
  "type": "Feature",
  "properties": {
    "iso:country":"DK",
    "sg:address":"\u00d8stergade 54",
    "sg:city":"Rudk\u00f8bing",
    "sg:orig_category":"Blomsterhandlere",
    "sg:phone":"+45 62 51 55 55",
    "sg:postcode":"5900",
    "sg:province":"Danmark",
    "wof:name":"Blomster Binderiet",
    "wof:placetype":"venue"
},
  "geometry": {"coordinates":[-114.0767440796,46.4432487488],"type":"Point"}
}