{
  "type": "Feature",
  "properties": {
    "iso:country":"DK",
    "sg:address":"Voldum-Rud Vej 175, Rud",
    "sg:city":"Hadsten",
    "sg:orig_category":"Kirker",
    "sg:postcode":"8370",
    "sg:province":"Danmark",
    "wof:name":"Rud Kirke",
    "wof:placetype":"venue"
},
  "geometry": {"coordinates":[10.047659874,56.3287239075],"type":"Point"}
}