{
  "type": "Feature",
  "properties": {
    "addr:full":"v/ J\u00f8rn Lundtoft Christensen, \u00d8sterbyvej 46, Vostrup Tarm Danmark 6880",
    "addr:housenumber":"46",
    "addr:postcode":"6880",
    "addr:street":"Osterbyvej",
    "iso:country":"DK",
    "sg:address":"v/ J\u00f8rn Lundtoft Christensen, \u00d8sterbyvej 46, Vostrup",
    "sg:city":"Tarm",
    "sg:orig_category":"Forsamlingshuse",
    "sg:phone":"+45 97 37 42 09",
    "sg:postcode":"6880",
    "sg:province":"Danmark",
    "wof:name":"Vostrup Forsamlingshus",
    "wof:placetype":"venue"
},
  "geometry": {"coordinates":[8.5200052261,55.9060554504],"type":"Point"}
}