{
  "type": "Feature",
  "properties": {
    "addr:full":"H\u00e5bets Alle 8 Br\u00f8nsh\u00f8j Danmark 2700",
    "addr:housenumber":"8",
    "addr:postcode":"2700",
    "addr:street":"Haabets Alle",
    "iso:country":"DK",
    "sg:address":"H\u00e5bets Alle 8",
    "sg:city":"Br\u00f8nsh\u00f8j",
    "sg:orig_category":"Malermestre",
    "sg:phone":"+45 38 28 08 38",
    "sg:postcode":"2700",
    "sg:province":"Danmark",
    "wof:name":"Pedersen A/S, Roar",
    "wof:placetype":"venue"
},
  "geometry": {"coordinates":[-65.6866531372,-23.1981296539],"type":"Point"}
}