{
  "type": "Feature",
  "properties": {
    "addr:full":"Klintevej 8, Klokkerholm Hjallerup Danmark 9320",
    "addr:housenumber":"8",
    "addr:postcode":"9320",
    "addr:street":"Klintevej;Klokkerholm",
    "iso:country":"DK",
    "sg:address":"Klintevej 8, Klokkerholm",
    "sg:city":"Hjallerup",
    "sg:orig_category":"Distriktsbiblioteker",
    "sg:phone":"+45 98 28 45 99",
    "sg:postcode":"9320",
    "sg:province":"Danmark",
    "wof:name":"Klokkerholm bibliotek",
    "wof:placetype":"venue"
},
  "geometry": {"coordinates":[10.1444702148,57.1677742004],"type":"Point"}
}