{
  "type": "Feature",
  "properties": {
    "addr:full":"Fmd.: Else Nielsen, Klostervej 128 Ry Danmark 8680",
    "addr:housenumber":"128",
    "addr:postcode":"8680",
    "addr:street":"Klostervej",
    "iso:country":"DK",
    "sg:address":"Fmd.: Else Nielsen, Klostervej 128",
    "sg:city":"Ry",
    "sg:orig_category":"Kulturelle foreninger",
    "sg:phone":"+45 86 89 13 77",
    "sg:postcode":"8680",
    "sg:province":"Danmark",
    "wof:name":"Ry Kunstforening",
    "wof:placetype":"venue"
},
  "geometry": {"coordinates":[9.7593002319,56.0920562744],"type":"Point"}
}