{
  "type": "Feature",
  "properties": {
    "addr:full":"Fmd.: Finn Justesen, Clarasvej 13 Glostrup Danmark 2600",
    "addr:housenumber":"13",
    "addr:postcode":"2600",
    "addr:street":"Clarasvej",
    "iso:country":"DK",
    "sg:address":"Fmd.: Finn Justesen, Clarasvej 13",
    "sg:city":"Glostrup",
    "sg:orig_category":"Grundejerforeninger",
    "sg:phone":"+45 43 96 53 23",
    "sg:postcode":"2600",
    "sg:province":"Danmark",
    "wof:name":"Hortensiav\u00e6nget",
    "wof:placetype":"venue"
},
  "geometry": {"coordinates":[12.3957901001,55.6654663086],"type":"Point"}
}