{
  "type": "Feature",
  "properties": {
    "addr:full":"Rollosvej 23, Bolbro Odense V Danmark 5200",
    "addr:housenumber":"23",
    "addr:postcode":"5200",
    "addr:street":"Rollosvej;Bolbro",
    "iso:country":"DK",
    "sg:address":"Rollosvej 23, Bolbro",
    "sg:city":"Odense V",
    "sg:orig_category":"Solcentre",
    "sg:phone":"+45 65 92 31 00",
    "sg:postcode":"5200",
    "sg:province":"Danmark",
    "wof:name":"AZA Sun Center",
    "wof:placetype":"venue"
},
  "geometry": {"coordinates":[10.2629547119,55.4070854187],"type":"Point"}
}