{
  "type": "Feature",
  "properties": {
    "addr:full":"Oliekajen 3 Skagen Danmark 9990",
    "addr:housenumber":"3",
    "addr:postcode":"9990",
    "addr:street":"Oliekajen",
    "iso:country":"DK",
    "sg:address":"Oliekajen 3",
    "sg:city":"Skagen",
    "sg:orig_category":"Fiskeindustri",
    "sg:phone":"+45 98 44 29 13",
    "sg:postcode":"9990",
    "sg:province":"Danmark",
    "sg:website":"www.ff-of-denmark.com",
    "wof:name":"FF Fiskesortering",
    "wof:placetype":"venue"
},
  "geometry": {"coordinates":[10.5934200287,57.7196502686],"type":"Point"}
}