{
  "type": "Feature",
  "properties": {
    "iso:country":"DK",
    "sg:address":"Katrinebjergvej 89 A",
    "sg:city":"\u00c5rhus N",
    "sg:orig_category":"Non-Classified Establishments",
    "sg:phone":"+45 70 20 50 40",
    "sg:postcode":"8200",
    "sg:province":"Danmark",
    "sg:website":"www.informationsteknik.com",
    "wof:name":"Informationsteknik Scandinavia A/S",
    "wof:placetype":"venue"
},
  "geometry": {"coordinates":[4.9393601418,49.7092018127],"type":"Point"}
}