{
  "type": "Feature",
  "properties": {
    "addr:full":"Frostvej 14, Postboks 2550 Vejle Danmark 7100",
    "addr:housenumber":"14",
    "addr:postcode":"2550;7100",
    "addr:street":"Frostvej",
    "iso:country":"DK",
    "sg:address":"Frostvej 14, Postboks 2550",
    "sg:city":"Vejle",
    "sg:orig_category":"Godstransport",
    "sg:phone":"+45 75 72 78 00",
    "sg:postcode":"7100",
    "sg:province":"Danmark",
    "wof:name":"DTC Frost",
    "wof:placetype":"venue"
},
  "geometry": {"coordinates":[9.5368051529,55.7113952637],"type":"Point"}
}