{
  "type": "Feature",
  "properties": {
    "addr:full":"Kirkepold 4, Ullerup S\u00f8nderborg Danmark 6400",
    "addr:housenumber":"4",
    "addr:postcode":"6400",
    "addr:street":"Kirkepold",
    "iso:country":"DK",
    "sg:address":"Kirkepold 4, Ullerup",
    "sg:city":"S\u00f8nderborg",
    "sg:orig_category":"Beslagsmede",
    "sg:phone":"+45 74 46 18 49",
    "sg:postcode":"6400",
    "sg:province":"Danmark",
    "wof:name":"Freeland, John W.",
    "wof:placetype":"venue"
},
  "geometry": {"coordinates":[9.7899465561,54.9100151062],"type":"Point"}
}