{
  "type": "Feature",
  "properties": {
    "addr:full":"Rigssalen, N\u00f8rre Alle 7 Fredericia Danmark 7000",
    "addr:housenumber":"7",
    "addr:postcode":"7000",
    "addr:street":"Norre Alle",
    "iso:country":"DK",
    "sg:address":"Rigssalen, N\u00f8rre Alle 7",
    "sg:city":"Fredericia",
    "sg:orig_category":"Trossamfund uden for folkekirken",
    "sg:phone":"+45 75 92 74 37",
    "sg:postcode":"7000",
    "sg:province":"Danmark",
    "wof:name":"Jehovas Vidner",
    "wof:placetype":"venue"
},
  "geometry": {"coordinates":[9.7591047287,55.566368103],"type":"Point"}
}