{
  "type": "Feature",
  "properties": {
    "addr:full":"Dronningg\u00e5rds Alle 1 A Holte Danmark 2840",
    "addr:housenumber":"1 a",
    "addr:postcode":"2840",
    "addr:street":"Dronninggaards Alle",
    "iso:country":"DK",
    "sg:address":"Dronningg\u00e5rds Alle 1 A",
    "sg:city":"Holte",
    "sg:orig_category":"Blomsterhandlere",
    "sg:phone":"+45 45 42 12 51",
    "sg:postcode":"2840",
    "sg:province":"Danmark",
    "sg:website":"www.binderiet.dk",
    "wof:name":"Binderiet Dronninggaard",
    "wof:placetype":"venue"
},
  "geometry": {"coordinates":[12.471411705,55.812297821],"type":"Point"}
}