{
  "type": "Feature",
  "properties": {
    "addr:full":"Havnepladsen 14, \u00d8ster Hurup Hadsund Danmark 9560",
    "addr:housenumber":"14",
    "addr:postcode":"9560",
    "addr:street":"Havnepladsen",
    "iso:country":"DK",
    "sg:address":"Havnepladsen 14, \u00d8ster Hurup",
    "sg:city":"Hadsund",
    "sg:orig_category":"Gallerier",
    "sg:phone":"+45 98 31 05 42",
    "sg:postcode":"9560",
    "sg:province":"Danmark",
    "wof:name":"Lille Galleri, Det",
    "wof:placetype":"venue"
},
  "geometry": {"coordinates":[10.115904808,56.7150764465],"type":"Point"}
}