{
  "type": "Feature",
  "properties": {
    "addr:full":"Kongegade 10 Nyborg Danmark 5800",
    "addr:housenumber":"10",
    "addr:postcode":"5800",
    "addr:street":"Kongegade",
    "iso:country":"DK",
    "sg:address":"Kongegade 10",
    "sg:city":"Nyborg",
    "sg:orig_category":"Sko",
    "sg:phone":"+45 65 31 16 40",
    "sg:postcode":"5800",
    "sg:province":"Danmark",
    "wof:name":"Roto Sko Nyborg ApS",
    "wof:placetype":"venue"
},
  "geometry": {"coordinates":[10.7903232574,55.3114433289],"type":"Point"}
}