{
  "type": "Feature",
  "properties": {
    "iso:country":"DK",
    "sg:address":"Th. Brorsens Vej 3 C",
    "sg:city":"Nordborg",
    "sg:orig_category":"Non-Classified Establishments",
    "sg:phone":"+45 74 66 24 15",
    "sg:postcode":"6430",
    "sg:province":"Danmark",
    "wof:name":"Nissen, Erik A",
    "wof:placetype":"venue"
},
  "geometry": {"coordinates":[9.7441444397,55.0609283447],"type":"Point"}
}