{
  "type": "Feature",
  "properties": {
    "addr:full":"Tigervej 7 Randers Danmark 8900",
    "addr:housenumber":"7",
    "addr:postcode":"8900",
    "addr:street":"Tigervej",
    "iso:country":"DK",
    "sg:address":"Tigervej 7",
    "sg:city":"Randers",
    "sg:orig_category":"Flytteforretninger",
    "sg:phone":"+45 86 40 10 30",
    "sg:postcode":"8900",
    "sg:province":"Danmark",
    "wof:name":"Bording Flytteforretning ApS",
    "wof:placetype":"venue"
},
  "geometry": {"coordinates":[10.0602684021,56.4498672485],"type":"Point"}
}