{
  "type": "Feature",
  "properties": {
    "addr:full":"Bygaden 35 B, K\u00f8ng Lundby Danmark 4750",
    "addr:housenumber":"35 b",
    "addr:postcode":"4750",
    "addr:street":"Bygaden;Kong",
    "iso:country":"DK",
    "sg:address":"Bygaden 35 B, K\u00f8ng",
    "sg:city":"Lundby",
    "sg:orig_category":"Gulvafslibning",
    "sg:phone":"+45 55 76 41 39",
    "sg:postcode":"4750",
    "sg:province":"Danmark",
    "wof:name":"Bruno's Gulvservice",
    "wof:placetype":"venue"
},
  "geometry": {"coordinates":[11.8101682663,55.1197814941],"type":"Point"}
}