{
  "type": "Feature",
  "properties": {
    "addr:full":"Hjerting Skovvej 7 R\u00f8dding Danmark 6630",
    "addr:housenumber":"7",
    "addr:postcode":"6630",
    "addr:street":"Hjerting Skovvej",
    "iso:country":"DK",
    "sg:address":"Hjerting Skovvej 7",
    "sg:city":"R\u00f8dding",
    "sg:orig_category":"Havearkitekter",
    "sg:phone":"+45 74 84 26 81",
    "sg:postcode":"6630",
    "sg:province":"Danmark",
    "wof:name":"Andreasen, Alice & Niels",
    "wof:placetype":"venue"
},
  "geometry": {"coordinates":[9.0534009933,55.4001426697],"type":"Point"}
}