{
  "type": "Feature",
  "properties": {
    "iso:country":"DK",
    "sg:address":"S\u00f8bylundvej 18",
    "sg:city":"Herning",
    "sg:orig_category":"Brudekjoler",
    "sg:phone":"+45 97 14 71 70",
    "sg:postcode":"7400",
    "sg:province":"Danmark",
    "wof:name":"Andreas Brudestue",
    "wof:placetype":"venue"
},
  "geometry": {"coordinates":[9.1020698547,56.0377235413],"type":"Point"}
}