{
  "type": "Feature",
  "properties": {
    "iso:country":"DK",
    "sg:address":"Parallelvej 5",
    "sg:city":"Sindal",
    "sg:orig_category":"Databehandling",
    "sg:phone":"+45 96 78 04 44",
    "sg:postcode":"9870",
    "sg:province":"Danmark",
    "wof:name":"DataReady ApS",
    "wof:placetype":"venue"
},
  "geometry": {"coordinates":[10.2036218643,57.4779815674],"type":"Point"}
}