{
  "type": "Feature",
  "properties": {
    "addr:full":"Tanderupvej 73, Tanderup Gelsted Danmark 5591",
    "addr:housenumber":"73",
    "addr:postcode":"5591",
    "addr:street":"Tanderupvej",
    "iso:country":"DK",
    "sg:address":"Tanderupvej 73, Tanderup",
    "sg:city":"Gelsted",
    "sg:orig_category":"Kirker",
    "sg:postcode":"5591",
    "sg:province":"Danmark",
    "wof:name":"Tanderup Kirke",
    "wof:placetype":"venue"
},
  "geometry": {"coordinates":[9.9734048843,55.3995094299],"type":"Point"}
}