{
  "type": "Feature",
  "properties": {
    "iso:country":"DK",
    "sg:address":"\u00d8stergade 5",
    "sg:city":"Struer",
    "sg:orig_category":"Blomsterhandlere",
    "sg:phone":"+45 97 85 49 05",
    "sg:postcode":"7600",
    "sg:province":"Danmark",
    "wof:name":"Valmuen",
    "wof:placetype":"venue"
},
  "geometry": {"coordinates":[8.5926580429,56.492313385],"type":"Point"}
}