{
  "type": "Feature",
  "properties": {
    "addr:full":"Alsvej 9 Middelfart Danmark 5500",
    "addr:housenumber":"9",
    "addr:postcode":"5500",
    "addr:street":"Alsvej",
    "iso:country":"DK",
    "sg:address":"Alsvej 9",
    "sg:city":"Middelfart",
    "sg:orig_category":"Genbrugspladser",
    "sg:phone":"+45 64 41 28 83",
    "sg:postcode":"5500",
    "sg:province":"Danmark",
    "wof:name":"Genbrugsstationen",
    "wof:placetype":"venue"
},
  "geometry": {"coordinates":[9.7624073029,55.5008087158],"type":"Point"}
}