{
  "type": "Feature",
  "properties": {
    "addr:full":"Asmildklostervej 9 Viborg Danmark 8800",
    "addr:housenumber":"9",
    "addr:postcode":"8800",
    "addr:street":"Asmildklostervej",
    "iso:country":"DK",
    "sg:address":"Asmildklostervej 9",
    "sg:city":"Viborg",
    "sg:orig_category":"Landboorganisationer",
    "sg:phone":"+45 87 28 18 40",
    "sg:postcode":"8800",
    "sg:province":"Danmark",
    "wof:name":"Region Viborg Landboungdom og 4H, Ungdomskontoret",
    "wof:placetype":"venue"
},
  "geometry": {"coordinates":[9.4309253693,56.4491653442],"type":"Point"}
}