{
  "type": "Feature",
  "properties": {
    "addr:full":"Roligheden 11, Kv\u00e6rkeby Ringsted Danmark 4100",
    "addr:housenumber":"11",
    "addr:postcode":"4100",
    "addr:street":"Roligheden;Kvaerkeby",
    "iso:country":"DK",
    "sg:address":"Roligheden 11, Kv\u00e6rkeby",
    "sg:city":"Ringsted",
    "sg:orig_category":"Internet, udbydere",
    "sg:phone":"+45 57 53 31 02",
    "sg:postcode":"4100",
    "sg:province":"Danmark",
    "sg:website":"www.hoelstad.net",
    "wof:name":"hoelstad.dk",
    "wof:placetype":"venue"
},
  "geometry": {"coordinates":[11.7875862122,55.4458961487],"type":"Point"}
}