{
  "type": "Feature",
  "properties": {
    "addr:full":"\u00c5kandehaven 148, Sm\u00f8rumnedre Sm\u00f8rum Danmark 2765",
    "addr:housenumber":"148",
    "addr:postcode":"2765",
    "addr:street":"Aakandehaven",
    "iso:country":"DK",
    "sg:address":"\u00c5kandehaven 148, Sm\u00f8rumnedre",
    "sg:city":"Sm\u00f8rum",
    "sg:orig_category":"Psykologer, praktiserende",
    "sg:phone":"+45 44 65 08 23",
    "sg:postcode":"2765",
    "sg:province":"Danmark",
    "wof:name":"Nielsen, Ole Gunner",
    "wof:placetype":"venue"
},
  "geometry": {"coordinates":[-89.99810791020001,38.1321372986],"type":"Point"}
}