{
  "type": "Feature",
  "properties": {
    "addr:full":"Nytorv 1 Thisted Danmark 7700",
    "addr:housenumber":"1",
    "addr:postcode":"7700",
    "addr:street":"Nytorv",
    "iso:country":"DK",
    "sg:address":"Nytorv 1",
    "sg:city":"Thisted",
    "sg:orig_category":"Musikinstrumenter",
    "sg:phone":"+45 97 92 51 10",
    "sg:postcode":"7700",
    "sg:province":"Danmark",
    "wof:name":"Thy Musik Center",
    "wof:placetype":"venue"
},
  "geometry": {"coordinates":[8.6925115585,56.9558296204],"type":"Point"}
}