{
  "type": "Feature",
  "properties": {
    "iso:country":"DK",
    "sg:address":"Fmd.: Ingrid Hansen, \u00c5parken 80",
    "sg:city":"Uldum",
    "sg:orig_category":"\u00c3\u2020ldreorganisationer og klubber",
    "sg:phone":"+45 75 67 87 08",
    "sg:postcode":"7171",
    "sg:province":"Danmark",
    "wof:name":"Uldum Pensionistforening",
    "wof:placetype":"venue"
},
  "geometry": {"coordinates":[9.5898447037,55.8469467163],"type":"Point"}
}