{
  "type": "Feature",
  "properties": {
    "addr:full":"Langk\u00e6r 14 Haderslev Danmark 6100",
    "addr:housenumber":"14",
    "addr:postcode":"6100",
    "addr:street":"Langkaer",
    "iso:country":"DK",
    "sg:address":"Langk\u00e6r 14",
    "sg:city":"Haderslev",
    "sg:orig_category":"Autolakering",
    "sg:phone":"+45 74 52 33 10",
    "sg:postcode":"6100",
    "sg:province":"Danmark",
    "wof:name":"Boysen Autolakering",
    "wof:placetype":"venue"
},
  "geometry": {"coordinates":[9.6105461121,55.3253250122],"type":"Point"}
}