{
  "type": "Feature",
  "properties": {
    "addr:full":"Fmd.: Holger Thygesen, Allingg\u00e5rdsvej 42, Svostrup Silkeborg Danmark 8600",
    "addr:housenumber":"42",
    "addr:postcode":"8600",
    "addr:street":"Allinggaardsvej",
    "iso:country":"DK",
    "sg:address":"Fmd.: Holger Thygesen, Allingg\u00e5rdsvej 42, Svostrup",
    "sg:city":"Silkeborg",
    "sg:orig_category":"\u00c3\u2020ldreorganisationer og klubber",
    "sg:phone":"+45 86 87 72 12",
    "sg:postcode":"8600",
    "sg:province":"Danmark",
    "wof:name":"Grauballe Pensionistforening",
    "wof:placetype":"venue"
},
  "geometry": {"coordinates":[9.5524425507,56.1693305969],"type":"Point"}
}