{
  "type": "Feature",
  "properties": {
    "addr:full":"H\u00e5rupvej 3 Silkeborg Danmark 8600",
    "addr:housenumber":"3",
    "addr:postcode":"8600",
    "addr:street":"Haarupvej",
    "iso:country":"DK",
    "sg:address":"H\u00e5rupvej 3",
    "sg:city":"Silkeborg",
    "sg:classifiers":[
        {
            "category":"Manufacturing",
            "subcategory":"Metals",
            "type":"Manufacturing & Wholesale Goods"
        }
    ],
    "sg:phone":"+45 86 82 83 22",
    "sg:postcode":"8600",
    "sg:province":"Danmark",
    "sg:tags":[
        "aluminium"
    ],
    "wof:name":"Aluminium Smeden",
    "wof:placetype":"venue"
},
  "geometry": {"coordinates":[9.6468095779,56.1582603455],"type":"Point"}
}