{
  "type": "Feature",
  "properties": {
    "addr:full":"S\u00f8lystgade 27, 4. \u00c5rhus C Danmark 8000",
    "addr:housenumber":"27 4",
    "addr:postcode":"8000",
    "addr:street":"Solystgade",
    "iso:country":"DK",
    "sg:address":"S\u00f8lystgade 27, 4.",
    "sg:city":"\u00c5rhus C",
    "sg:orig_category":"Fotografer",
    "sg:phone":"+45 86 19 53 25",
    "sg:postcode":"8000",
    "sg:province":"Danmark",
    "wof:name":"Ersted Fotografi",
    "wof:placetype":"venue"
},
  "geometry": {"coordinates":[4.717400074,49.7588005066],"type":"Point"}
}