{
  "type": "Feature",
  "properties": {
    "addr:full":"Frederiksbjerg Torv 2 \u00c5rhus C Danmark 8000",
    "addr:housenumber":"2",
    "addr:postcode":"8000",
    "addr:street":"Frederiksbjerg Torv",
    "iso:country":"DK",
    "sg:address":"Frederiksbjerg Torv 2",
    "sg:city":"\u00c5rhus C",
    "sg:orig_category":"Posthuse",
    "sg:phone":"+45 89 35 80 00",
    "sg:postcode":"8000",
    "sg:province":"Danmark",
    "wof:name":"Post Danmark, Frederiksbjerg Torv Posthus",
    "wof:placetype":"venue"
},
  "geometry": {"coordinates":[10.1930303574,56.1461410522],"type":"Point"}
}