{
  "type": "Feature",
  "properties": {
    "addr:full":"Askelundsvej 2 Frederikssund Danmark 3600",
    "addr:housenumber":"2",
    "addr:postcode":"3600",
    "addr:street":"Askelundsvej",
    "iso:country":"DK",
    "sg:address":"Askelundsvej 2",
    "sg:city":"Frederikssund",
    "sg:orig_category":"Genbrugsbutikker",
    "sg:phone":"+45 47 31 72 73",
    "sg:postcode":"3600",
    "sg:province":"Danmark",
    "wof:name":"Frederikssund Genbrug, Transport & Flytteforretning",
    "wof:placetype":"venue"
},
  "geometry": {"coordinates":[12.0744991302,55.844039917],"type":"Point"}
}