{
  "type": "Feature",
  "properties": {
    "addr:full":"Sct. Clemens Vej 42 Skagen Danmark 9990",
    "addr:housenumber":"42",
    "addr:postcode":"9990",
    "addr:street":"Sct. Clemens Vej",
    "iso:country":"DK",
    "sg:address":"Sct. Clemens Vej 42",
    "sg:city":"Skagen",
    "sg:orig_category":"Autoforhandlere",
    "sg:phone":"+45 40 40 40 87",
    "sg:postcode":"9990",
    "sg:province":"Danmark",
    "wof:name":"V\u00f8lding A/S, Berg",
    "wof:placetype":"venue"
},
  "geometry": {"coordinates":[10.5801239014,57.7218894958],"type":"Point"}
}