{
  "type": "Feature",
  "properties": {
    "addr:full":"Mindet 3 Skanderborg Danmark 8660",
    "addr:housenumber":"3",
    "addr:postcode":"8660",
    "addr:street":"Mindet",
    "iso:country":"DK",
    "sg:address":"Mindet 3",
    "sg:city":"Skanderborg",
    "sg:orig_category":"Fodterapeuter",
    "sg:phone":"+45 86 51 25 11",
    "sg:postcode":"8660",
    "sg:province":"Danmark",
    "wof:name":"Simonsen, Mette",
    "wof:placetype":"venue"
},
  "geometry": {"coordinates":[9.9292802811,56.038936615],"type":"Point"}
}