{
  "type": "Feature",
  "properties": {
    "addr:full":"Fmd.: Kaj Hansen, Vestervangen 23, Nr. Lyndelse \u00c5rslev Danmark 5792",
    "addr:housenumber":"23",
    "addr:postcode":"5792",
    "addr:street":"Fmd. Kaj Hansen Vestervangen",
    "iso:country":"DK",
    "sg:address":"Fmd.: Kaj Hansen, Vestervangen 23, Nr. Lyndelse",
    "sg:city":"\u00c5rslev",
    "sg:orig_category":"Kirkesogne",
    "sg:phone":"+45 65 90 23 24",
    "sg:postcode":"5792",
    "sg:province":"Danmark",
    "wof:name":"Nr. Lyndelse Sogns Menighedsr\u00e5d",
    "wof:placetype":"venue"
},
  "geometry": {"coordinates":[166.9221496582,-0.5282999873],"type":"Point"}
}