{
  "type": "Feature",
  "properties": {
    "addr:full":"Sct. Laurentii Vej 37 Skagen Danmark 9990",
    "addr:housenumber":"37",
    "addr:postcode":"9990",
    "addr:street":"Sct. Laurentii Vej",
    "iso:country":"DK",
    "sg:address":"Sct. Laurentii Vej 37",
    "sg:city":"Skagen",
    "sg:orig_category":"Fotografer",
    "sg:phone":"+45 98 44 25 95",
    "sg:postcode":"9990",
    "sg:province":"Danmark",
    "wof:name":"Fotoatelieret",
    "wof:placetype":"venue"
},
  "geometry": {"coordinates":[10.5924186707,57.7234306335],"type":"Point"}
}