{
  "type": "Feature",
  "properties": {
    "addr:full":"\u00d8ster Vedsted Vej 50 Ribe Danmark 6760",
    "addr:housenumber":"50",
    "addr:postcode":"6760",
    "addr:street":"Oster Vedsted Vej",
    "iso:country":"DK",
    "sg:address":"\u00d8ster Vedsted Vej 50",
    "sg:city":"Ribe",
    "sg:orig_category":"Snedkermestre",
    "sg:phone":"+45 75 41 04 41",
    "sg:postcode":"6760",
    "sg:province":"Danmark",
    "wof:name":"Bygnings Snedkeren Ribe ApS",
    "wof:placetype":"venue"
},
  "geometry": {"coordinates":[8.7038412094,55.2895812988],"type":"Point"}
}