{
  "type": "Feature",
  "properties": {
    "addr:full":"Fmd.: Christian Tortzen, Helsing\u00f8rsvej 18 Fredensborg Danmark 3480",
    "addr:housenumber":"18",
    "addr:postcode":"3480",
    "addr:street":"Helsingorsvej",
    "iso:country":"DK",
    "sg:address":"Fmd.: Christian Tortzen, Helsing\u00f8rsvej 18",
    "sg:city":"Fredensborg",
    "sg:orig_category":"Politiske foreninger, \u00c3\u02dcvrige",
    "sg:phone":"+45 48 48 46 67",
    "sg:postcode":"3480",
    "sg:province":"Danmark",
    "wof:name":"Venstres Ungdom, VU",
    "wof:placetype":"venue"
},
  "geometry": {"coordinates":[12.4020547867,55.9782943726],"type":"Point"}
}