{
  "type": "Feature",
  "properties": {
    "addr:full":"Trunderup Gade 5 Kv\u00e6rndrup Danmark 5772",
    "addr:housenumber":"5",
    "addr:postcode":"5772",
    "addr:street":"Trunderup Gade",
    "iso:country":"DK",
    "sg:address":"Trunderup Gade 5",
    "sg:city":"Kv\u00e6rndrup",
    "sg:orig_category":"Fritidsklubber",
    "sg:phone":"+45 62 27 22 66",
    "sg:postcode":"5772",
    "sg:province":"Danmark",
    "wof:name":"Vulkan Trunderup Friskoles SFO",
    "wof:placetype":"venue"
},
  "geometry": {"coordinates":[10.541677475,55.1927757263],"type":"Point"}
}