{
  "type": "Feature",
  "properties": {
    "addr:full":"Holtvej 17, Holt Vamdrup Danmark 6580",
    "addr:housenumber":"17",
    "addr:postcode":"6580",
    "addr:street":"Holtvej",
    "iso:country":"DK",
    "sg:address":"Holtvej 17, Holt",
    "sg:city":"Vamdrup",
    "sg:orig_category":"Hudpleje",
    "sg:phone":"+45 75 58 17 47",
    "sg:postcode":"6580",
    "sg:province":"Danmark",
    "wof:name":"A.L. Marketing",
    "wof:placetype":"venue"
},
  "geometry": {"coordinates":[9.2839107513,55.4266548157],"type":"Point"}
}