{
  "type": "Feature",
  "properties": {
    "addr:full":"Thorsvej 5 C, Rindum Ringk\u00f8bing Danmark 6950",
    "addr:housenumber":"5 c",
    "addr:postcode":"6950",
    "addr:street":"Thorsvej;Rindum Ringkobing Danmark",
    "iso:country":"DK",
    "sg:address":"Thorsvej 5 C, Rindum",
    "sg:city":"Ringk\u00f8bing",
    "sg:orig_category":"Autoreparation og -service",
    "sg:phone":"+45 97 32 10 98",
    "sg:postcode":"6950",
    "sg:province":"Danmark",
    "wof:name":"S\u00f8rensen, S\u00f8ren",
    "wof:placetype":"venue"
},
  "geometry": {"coordinates":[-114.0767440796,46.4432487488],"type":"Point"}
}