{
  "type": "Feature",
  "properties": {
    "addr:full":"Dronning Margrethes Vej 34 Roskilde Danmark 4000",
    "addr:housenumber":"34",
    "addr:postcode":"4000",
    "addr:street":"Dronning Margrethes Vej",
    "iso:country":"DK",
    "sg:address":"Dronning Margrethes Vej 34",
    "sg:city":"Roskilde",
    "sg:orig_category":"Kirurgi",
    "sg:phone":"+45 46 35 90 69",
    "sg:postcode":"4000",
    "sg:province":"Danmark",
    "wof:name":"Lauritzen, J.B.",
    "wof:placetype":"venue"
},
  "geometry": {"coordinates":[12.0930967331,55.6423530579],"type":"Point"}
}