{
  "type": "Feature",
  "properties": {
    "addr:full":"Fan\u00f8vej 13 Grindsted Danmark 7200",
    "addr:housenumber":"13",
    "addr:postcode":"7200",
    "addr:street":"Fanovej",
    "iso:country":"DK",
    "sg:address":"Fan\u00f8vej 13",
    "sg:city":"Grindsted",
    "sg:orig_category":"Skovbrug",
    "sg:phone":"+45 75 32 42 93",
    "sg:postcode":"7200",
    "sg:province":"Danmark",
    "wof:name":"Grydedal Plantage",
    "wof:placetype":"venue"
},
  "geometry": {"coordinates":[8.9053697586,55.767036438],"type":"Point"}
}