{
  "type": "Feature",
  "properties": {
    "addr:full":"v/ Spar, Tisvildevej 4 Vejby Danmark 3210",
    "addr:housenumber":"4",
    "addr:postcode":"3210",
    "addr:street":"Tisvildevej",
    "iso:country":"DK",
    "sg:address":"v/ Spar, Tisvildevej 4",
    "sg:city":"Vejby",
    "sg:orig_category":"Posthuse",
    "sg:phone":"+45 48 10 34 50",
    "sg:postcode":"3210",
    "sg:province":"Danmark",
    "wof:name":"Post Danmark, Vejby Kundeservice",
    "wof:placetype":"venue"
},
  "geometry": {"coordinates":[12.1534852982,56.0930938721],"type":"Point"}
}