{
  "type": "Feature",
  "properties": {
    "iso:country":"DK",
    "sg:address":"Odinsvej 1",
    "sg:city":"Fakse",
    "sg:orig_category":"Betonvarefabrikker",
    "sg:phone":"+45 56 71 32 76",
    "sg:postcode":"4640",
    "sg:province":"Danmark",
    "wof:name":"Faxe Betonvarefabrik",
    "wof:placetype":"venue"
},
  "geometry": {"coordinates":[12.11069,55.256416],"type":"Point"}
}