{
  "type": "Feature",
  "properties": {
    "iso:country":"DK",
    "sg:address":"Lillevangsvej 94",
    "sg:city":"Greve",
    "sg:orig_category":"Beboerhuse",
    "sg:phone":"+45 43 90 79 97",
    "sg:postcode":"2670",
    "sg:province":"Danmark",
    "wof:name":"Greve Borgerhus",
    "wof:placetype":"venue"
},
  "geometry": {"coordinates":[12.299605,55.588333],"type":"Point"}
}