{
  "type": "Feature",
  "properties": {
    "addr:full":"Fabriksvej 2  Pandrup Danmark 9490",
    "addr:housenumber":"2",
    "addr:postcode":"9490",
    "addr:street":"Fabriksvej",
    "iso:country":"DK",
    "sg:address":"Fabriksvej 2 ",
    "sg:city":"Pandrup",
    "sg:classifiers":[
        {
            "category":"Manufacturing",
            "subcategory":"Rubber & Plastics",
            "type":"Manufacturing & Wholesale Goods"
        }
    ],
    "sg:phone":"+45 98 24 78 33",
    "sg:postcode":"9490",
    "sg:province":"Danmark",
    "wof:name":"VISLI APS",
    "wof:placetype":"venue"
},
  "geometry": {"coordinates":[9.6775093079,57.2064857483],"type":"Point"}
}