{
  "type": "Feature",
  "properties": {
    "addr:full":"Smidstrupparken 1, Smidstrup Fredericia Danmark 7000",
    "addr:housenumber":"1",
    "addr:postcode":"7000",
    "addr:street":"Smidstrupparken;Smidstrup",
    "iso:country":"DK",
    "sg:address":"Smidstrupparken 1, Smidstrup",
    "sg:city":"Fredericia",
    "sg:orig_category":"\u00c3\u2020ldrecentre",
    "sg:phone":"+45 75 86 03 35",
    "sg:postcode":"7000",
    "sg:province":"Danmark",
    "wof:name":"Smidstrupparken",
    "wof:placetype":"venue"
},
  "geometry": {"coordinates":[9.7591047287,55.566368103],"type":"Point"}
}