{
  "type": "Feature",
  "properties": {
    "addr:full":"Nordmarksvej 8 Billund Danmark 7190",
    "addr:housenumber":"8",
    "addr:postcode":"7190",
    "addr:street":"Nordmarksvej",
    "iso:country":"DK",
    "sg:address":"Nordmarksvej 8",
    "sg:city":"Billund",
    "sg:orig_category":"HOTELS: OG MOTELLER",
    "sg:phone":"+45 75 33 28 33",
    "sg:postcode":"7190",
    "sg:province":"Danmark",
    "wof:name":"Hotel Svanen",
    "wof:placetype":"venue"
},
  "geometry": {"coordinates":[9.1329030991,55.729183197],"type":"Point"}
}