{
  "type": "Feature",
  "properties": {
    "iso:country":"DK",
    "sg:address":"Bryggervangen 1",
    "sg:city":"Vejle \u00d8",
    "sg:orig_category":"Designere",
    "sg:phone":"+45 75 81 66 05",
    "sg:postcode":"7120",
    "sg:province":"Danmark",
    "wof:name":"Design Palle",
    "wof:placetype":"venue"
},
  "geometry": {"coordinates":[9.607175827,55.7211227417],"type":"Point"}
}