{
  "type": "Feature",
  "properties": {
    "addr:full":"Sintrupvej 50 Brabrand Danmark 8220",
    "addr:housenumber":"50",
    "addr:postcode":"8220",
    "addr:street":"Sintrupvej",
    "iso:country":"DK",
    "sg:address":"Sintrupvej 50",
    "sg:city":"Brabrand",
    "sg:orig_category":"Engros handel",
    "sg:phone":"+45 87 45 15 45",
    "sg:postcode":"8220",
    "sg:province":"Danmark",
    "wof:name":"Rheinzink Danmark AS",
    "wof:placetype":"venue"
},
  "geometry": {"coordinates":[10.1021709442,56.1679191589],"type":"Point"}
}