{
  "type": "Feature",
  "properties": {
    "iso:country":"DK",
    "sg:address":"Slotsvej 54",
    "sg:city":"Gram",
    "sg:orig_category":"Landbrug",
    "sg:phone":"+45 74 82 13 14",
    "sg:postcode":"6510",
    "sg:province":"Danmark",
    "wof:name":"Gram og Nyb\u00f8l Godser A/S",
    "wof:placetype":"venue"
},
  "geometry": {"coordinates":[9.0559873581,55.2953453064],"type":"Point"}
}