{
  "type": "Feature",
  "properties": {
    "addr:full":"Guldborgvej 15, Veddelev Roskilde Danmark 4000",
    "addr:housenumber":"15",
    "addr:postcode":"4000",
    "addr:street":"Guldborgvej;Veddelev",
    "iso:country":"DK",
    "sg:address":"Guldborgvej 15, Veddelev",
    "sg:city":"Roskilde",
    "sg:classifiers":[
        {
            "category":"Professional",
            "subcategory":"Computer Services",
            "type":"Services"
        }
    ],
    "sg:phone":"+45 46 75 59 00",
    "sg:postcode":"4000",
    "sg:province":"Danmark",
    "sg:tags":[
        "edb",
        "-",
        "software"
    ],
    "wof:name":"AN Data Design ApS",
    "wof:placetype":"venue"
},
  "geometry": {"coordinates":[12.0909376144,55.6404838562],"type":"Point"}
}