{
  "type": "Feature",
  "properties": {
    "addr:full":"Att.: Carsten Matzen, Ahlefeldvej 1 A Gr\u00e5sten Danmark 6300",
    "addr:housenumber":"1 a",
    "addr:postcode":"6300",
    "addr:street":"Ahlefeldvej",
    "iso:country":"DK",
    "sg:address":"Att.: Carsten Matzen, Ahlefeldvej 1 A",
    "sg:city":"Gr\u00e5sten",
    "sg:orig_category":"Posthuse",
    "sg:phone":"+45 74 43 62 00",
    "sg:postcode":"6300",
    "sg:province":"Danmark",
    "wof:name":"Post Danmark, Gr\u00e5sten Posthus",
    "wof:placetype":"venue"
},
  "geometry": {"coordinates":[-120.4220733643,37.956325531],"type":"Point"}
}