{
  "type": "Feature",
  "properties": {
    "addr:full":"Hersted\u00f8stervej 27 -29  Albertslund Danmark 2620",
    "addr:housenumber":"27 -29",
    "addr:postcode":"2620",
    "addr:street":"Herstedostervej",
    "iso:country":"DK",
    "sg:address":"Hersted\u00f8stervej 27 -29 ",
    "sg:city":"Albertslund",
    "sg:classifiers":[
        {
            "category":"Wholesale",
            "subcategory":"Drugs",
            "type":"Manufacturing & Wholesale Goods"
        }
    ],
    "sg:phone":"+45 43 29 09 99",
    "sg:postcode":"2620",
    "sg:province":"Danmark",
    "sg:tags":[
        "chemical",
        "pharmaceutical"
    ],
    "wof:name":"SCHERING AS",
    "wof:placetype":"venue"
},
  "geometry": {"coordinates":[12.3700857162,55.6702842712],"type":"Point"}
}