{
  "type": "Feature",
  "properties": {
    "addr:full":"Jernbanegade 6 B Roskilde Danmark 4000",
    "addr:housenumber":"6 b",
    "addr:postcode":"4000",
    "addr:street":"Jernbanegade",
    "iso:country":"DK",
    "sg:address":"Jernbanegade 6 B",
    "sg:city":"Roskilde",
    "sg:orig_category":"Arkitekter",
    "sg:phone":"+45 46 36 76 66",
    "sg:postcode":"4000",
    "sg:province":"Danmark",
    "wof:name":"nielsens tegnestue a/s, tage",
    "wof:placetype":"venue"
},
  "geometry": {"coordinates":[12.0863676071,55.6386184692],"type":"Point"}
}