{
  "type": "Feature",
  "properties": {
    "addr:full":"\u00d8stergade 61 Maribo Danmark 4930",
    "addr:housenumber":"61",
    "addr:postcode":"4930",
    "addr:street":"Ostergade",
    "iso:country":"DK",
    "sg:address":"\u00d8stergade 61",
    "sg:city":"Maribo",
    "sg:orig_category":"Skolefritidsordninger",
    "sg:phone":"+45 54 76 01 99",
    "sg:postcode":"4930",
    "sg:province":"Danmark",
    "sg:website":"www.sanktbirgitta.dk",
    "wof:name":"Sankt Birgitta Skoles skolefritidsordning",
    "wof:placetype":"venue"
},
  "geometry": {"coordinates":[11.5095281601,54.7745475769],"type":"Point"}
}