{
  "type": "Feature",
  "properties": {
    "iso:country":"DK",
    "sg:address":"Stationsparken 25 ",
    "sg:city":"Glostrup",
    "sg:classifiers":[
        {
            "category":"Farming",
            "subcategory":"Livestock Farm",
            "type":"Manufacturing & Wholesale Goods"
        }
    ],
    "sg:phone":"+45 43 28 42 00",
    "sg:postcode":"2600",
    "sg:province":"Danmark",
    "sg:tags":[
        "agriculture"
    ],
    "wof:name":"FRISKO IS A/S",
    "wof:placetype":"venue"
},
  "geometry": {"coordinates":[12.3981723785,55.661819458],"type":"Point"}
}