{
  "type": "Feature",
  "properties": {
    "addr:full":"Fmd.: Elin Kristiansen, Sj\u00e6llandsgade 15 Aulum Danmark 7490",
    "addr:housenumber":"15",
    "addr:postcode":"7490",
    "addr:street":"Sjaellandsgade",
    "iso:country":"DK",
    "sg:address":"Fmd.: Elin Kristiansen, Sj\u00e6llandsgade 15",
    "sg:city":"Aulum",
    "sg:orig_category":"Kulturelle foreninger",
    "sg:phone":"+45 97 47 28 04",
    "sg:postcode":"7490",
    "sg:province":"Danmark",
    "sg:website":"www.hosekraemmerne.dk",
    "wof:name":"Marchforeningen Hosekr\u00e6mmerne",
    "wof:placetype":"venue"
},
  "geometry": {"coordinates":[8.7971401215,56.2653999329],"type":"Point"}
}