{
  "type": "Feature",
  "properties": {
    "iso:country":"DK",
    "sg:address":"Nordre Parkvej 4",
    "sg:city":"Helsinge",
    "sg:orig_category":"Revisorer",
    "sg:phone":"+45 48 79 98 50",
    "sg:postcode":"3200",
    "sg:province":"Danmark",
    "wof:name":"Lundmerco",
    "wof:placetype":"venue"
},
  "geometry": {"coordinates":[12.1940593719,56.0262641907],"type":"Point"}
}