{
  "type": "Feature",
  "properties": {
    "addr:full":"Tune Center 11 A, Tune Roskilde Danmark 4000",
    "addr:housenumber":"11 a",
    "addr:postcode":"4000",
    "addr:street":"Tune Center",
    "iso:country":"DK",
    "sg:address":"Tune Center 11 A, Tune",
    "sg:city":"Roskilde",
    "sg:orig_category":"Pizzeriaer",
    "sg:phone":"+45 46 13 60 60",
    "sg:postcode":"4000",
    "sg:province":"Danmark",
    "wof:name":"Tune Pizza og Burgerbar",
    "wof:placetype":"venue"
},
  "geometry": {"coordinates":[12.0909376144,55.6404838562],"type":"Point"}
}