{
  "type": "Feature",
  "properties": {
    "addr:full":"Fmd.: Bjarne Klarskov, H\u00f8bj\u00e6rgvej 60, Nr. Eskilstrup T\u00f8ll\u00f8se Danmark 4340",
    "addr:housenumber":"60",
    "addr:postcode":"4340",
    "addr:street":"Hobjaergvej",
    "iso:country":"DK",
    "sg:address":"Fmd.: Bjarne Klarskov, H\u00f8bj\u00e6rgvej 60, Nr. Eskilstrup",
    "sg:city":"T\u00f8ll\u00f8se",
    "sg:orig_category":"Musik og sang",
    "sg:phone":"+45 59 18 66 12",
    "sg:postcode":"4340",
    "sg:province":"Danmark",
    "wof:name":"T\u00f8ll\u00f8se Brass Band",
    "wof:placetype":"venue"
},
  "geometry": {"coordinates":[11.5867519379,55.6034011841],"type":"Point"}
}