{
  "type": "Feature",
  "properties": {
    "addr:full":"N\u00f8rregade 9, Hvidbjerg Thyholm Danmark 7790",
    "addr:housenumber":"9",
    "addr:postcode":"7790",
    "addr:street":"Norregade;Hvidbjerg",
    "iso:country":"DK",
    "sg:address":"N\u00f8rregade 9, Hvidbjerg",
    "sg:city":"Thyholm",
    "sg:orig_category":"Sparekasser",
    "sg:phone":"+45 97 87 11 77",
    "sg:postcode":"7790",
    "sg:province":"Danmark",
    "sg:website":"www.thyholmsparekasse.dk",
    "wof:name":"Thyholm Sparekasse",
    "wof:placetype":"venue"
},
  "geometry": {"coordinates":[8.525765419,56.6507072449],"type":"Point"}
}