{
  "type": "Feature",
  "properties": {
    "iso:country":"DK",
    "sg:address":"Hobrovej 461",
    "sg:city":"Aalborg SV",
    "sg:orig_category":"Arbejdstilsyn",
    "sg:phone":"+45 96 34 79 49",
    "sg:postcode":"9200",
    "sg:province":"Danmark",
    "wof:name":"Arbejdstilsynet.",
    "wof:placetype":"venue"
},
  "geometry": {"coordinates":[9.8812389374,57.0041923523],"type":"Point"}
}