{
  "type": "Feature",
  "properties": {
    "addr:full":"Energivej 12 Ballerup Danmark 2750",
    "addr:housenumber":"12",
    "addr:postcode":"2750",
    "addr:street":"Energivej",
    "iso:country":"DK",
    "sg:address":"Energivej 12",
    "sg:city":"Ballerup",
    "sg:orig_category":"Autoforhandlere",
    "sg:phone":"+45 44 86 15 00",
    "sg:postcode":"2750",
    "sg:province":"Danmark",
    "sg:website":"www.tangholm.dk",
    "wof:name":"Tangholm A/S",
    "wof:placetype":"venue"
},
  "geometry": {"coordinates":[12.3818922043,55.7242622375],"type":"Point"}
}