{
  "type": "Feature",
  "properties": {
    "iso:country":"DK",
    "sg:address":"Mads Clausens Vej 2",
    "sg:city":"Nordborg",
    "sg:orig_category":"Autoforhandlere",
    "sg:phone":"+45 74 49 19 20",
    "sg:postcode":"6430",
    "sg:province":"Danmark",
    "wof:name":"Auto-Jensen",
    "wof:placetype":"venue"
},
  "geometry": {"coordinates":[9.757686615,55.0536231995],"type":"Point"}
}