{
  "type": "Feature",
  "properties": {
    "addr:full":"Halmtorvet 10 K\u00f8benhavn Danmark 1700",
    "addr:housenumber":"10",
    "addr:postcode":"1700",
    "addr:street":"Halmtorvet",
    "iso:country":"DK",
    "sg:address":"Halmtorvet 10",
    "sg:city":"K\u00f8benhavn",
    "sg:classifiers":[
        {
            "category":"Restaurant",
            "type":"Food & Drink"
        }
    ],
    "sg:phone":"+45 33 31 21 83",
    "sg:postcode":"1700",
    "sg:province":"Danmark",
    "wof:name":"Cafe Hj\u00f8rnet Aps",
    "wof:placetype":"venue"
},
  "geometry": {"coordinates":[12.5607004166,55.6691017151],"type":"Point"}
}