{
  "type": "Feature",
  "properties": {
    "addr:full":"Pihls Alle 9 Klemensker Danmark 3782",
    "addr:housenumber":"9",
    "addr:postcode":"3782",
    "addr:street":"Pihls Alle",
    "iso:country":"DK",
    "sg:address":"Pihls Alle 9",
    "sg:city":"Klemensker",
    "sg:orig_category":"Murermestre",
    "sg:phone":"+45 56 96 67 31",
    "sg:postcode":"3782",
    "sg:province":"Danmark",
    "wof:name":"Kelds Byggeforretning",
    "wof:placetype":"venue"
},
  "geometry": {"coordinates":[14.8093366623,55.1747703552],"type":"Point"}
}