{
  "type": "Feature",
  "properties": {
    "iso:country":"DK",
    "sg:address":"Leder: Conny \u00d8stergaard, R\u00f8nvangen 2",
    "sg:city":"Hinnerup",
    "sg:orig_category":"\u00c3\u02dcvrig fritidsundervisning",
    "sg:phone":"+45 86 98 88 07",
    "sg:postcode":"8382",
    "sg:province":"Danmark",
    "wof:name":"Gigtforeningens Oplysningskreds i Hinnerup - GOK",
    "wof:placetype":"venue"
},
  "geometry": {"coordinates":[10.0614156723,56.2650604248],"type":"Point"}
}