{
  "type": "Feature",
  "properties": {
    "addr:full":"Torvet 8, 2. Nex\u00f8 Danmark 3730",
    "addr:housenumber":"8 2",
    "addr:postcode":"3730",
    "addr:street":"Torvet",
    "iso:country":"DK",
    "sg:address":"Torvet 8, 2.",
    "sg:city":"Nex\u00f8",
    "sg:orig_category":"Ungdomsboliger og -hybler",
    "sg:phone":"+45 56 49 39 17",
    "sg:postcode":"3730",
    "sg:province":"Danmark",
    "wof:name":"Ungdomsboliger, Det almennyttige Boligselskab",
    "wof:placetype":"venue"
},
  "geometry": {"coordinates":[15.1321878433,55.0631561279],"type":"Point"}
}