{
  "type": "Feature",
  "properties": {
    "addr:full":"Munkegade 7 Kolding Danmark 6000",
    "addr:housenumber":"7",
    "addr:postcode":"6000",
    "addr:street":"Munkegade",
    "iso:country":"DK",
    "sg:address":"Munkegade 7",
    "sg:city":"Kolding",
    "sg:classifiers":[
        {
            "category":"Restaurant",
            "type":"Food & Drink"
        }
    ],
    "sg:phone":"+45 75 52 05 91",
    "sg:postcode":"6000",
    "sg:province":"Danmark",
    "sg:website":"www.rest-valentino.dk",
    "wof:name":"Valentino",
    "wof:placetype":"venue"
},
  "geometry": {"coordinates":[9.4774246216,55.48960495],"type":"Point"}
}