{
  "type": "Feature",
  "properties": {
    "addr:full":"Frederiksberg 26 Sveb\u00f8lle Danmark 4470",
    "addr:housenumber":"26",
    "addr:postcode":"4470",
    "addr:street":"Frederiksberg",
    "iso:country":"DK",
    "sg:address":"Frederiksberg 26",
    "sg:city":"Sveb\u00f8lle",
    "sg:orig_category":"Maskinstationer",
    "sg:phone":"+45 59 29 39 84",
    "sg:postcode":"4470",
    "sg:province":"Danmark",
    "wof:name":"Sveb\u00f8lle Maskincentral",
    "wof:placetype":"venue"
},
  "geometry": {"coordinates":[11.29829216,55.6555976868],"type":"Point"}
}