{
  "type": "Feature",
  "properties": {
    "addr:full":"Lysabildgade 28, Lysabild Sydals Danmark 6470",
    "addr:housenumber":"28",
    "addr:postcode":"6470",
    "addr:street":"Lysabildgade;Lysabild",
    "iso:country":"DK",
    "sg:address":"Lysabildgade 28, Lysabild",
    "sg:city":"Sydals",
    "sg:orig_category":"Forsamlingshuse",
    "sg:phone":"+45 74 40 40 26",
    "sg:postcode":"6470",
    "sg:province":"Danmark",
    "wof:name":"Lysabild Forsamlingsg\u00e5rd",
    "wof:placetype":"venue"
},
  "geometry": {"coordinates":[9.8924627304,54.9105377197],"type":"Point"}
}