{
  "type": "Feature",
  "properties": {
    "iso:country":"DK",
    "sg:address":"Sk\u00e6rs\u00f8vej 21",
    "sg:city":"Egtved",
    "sg:orig_category":"Vandbehandling",
    "sg:phone":"+45 76 64 01 33",
    "sg:postcode":"6040",
    "sg:province":"Danmark",
    "wof:name":"A.H. Vandteknik ApS",
    "wof:placetype":"venue"
},
  "geometry": {"coordinates":[9.2770557404,55.5887565613],"type":"Point"}
}