{
  "type": "Feature",
  "properties": {
    "iso:country":"DK",
    "sg:address":"Hans Schacksvej 2",
    "sg:city":"Kerteminde",
    "sg:orig_category":"Brugsforeninger",
    "sg:phone":"+45 65 32 11 71",
    "sg:postcode":"5300",
    "sg:province":"Danmark",
    "wof:name":"Super Brugsen, Kerteminde",
    "wof:placetype":"venue"
},
  "geometry": {"coordinates":[10.6603221893,55.4507522583],"type":"Point"}
}