{
  "type": "Feature",
  "properties": {
    "addr:full":"Dr. Sells Vej 35 A Dianalund Danmark 4293",
    "addr:housenumber":"35 a",
    "addr:postcode":"4293",
    "addr:street":"Sells Vej",
    "iso:country":"DK",
    "sg:address":"Dr. Sells Vej 35 A",
    "sg:city":"Dianalund",
    "sg:orig_category":"Offentlige sygehuse",
    "sg:phone":"+45 58 26 44 11",
    "sg:postcode":"4293",
    "sg:province":"Danmark",
    "wof:name":"Psykiatrisk Center",
    "wof:placetype":"venue"
},
  "geometry": {"coordinates":[11.512304306,55.5284767151],"type":"Point"}
}