{
  "type": "Feature",
  "properties": {
    "addr:full":"Adelgade 62 Nysted Danmark 4880",
    "addr:housenumber":"62",
    "addr:postcode":"4880",
    "addr:street":"Adelgade",
    "iso:country":"DK",
    "sg:address":"Adelgade 62",
    "sg:city":"Nysted",
    "sg:orig_category":"Antikviteter",
    "sg:phone":"+45 54 87 13 86",
    "sg:postcode":"4880",
    "sg:province":"Danmark",
    "wof:name":"Tinghuset",
    "wof:placetype":"venue"
},
  "geometry": {"coordinates":[11.7292804718,54.6662025452],"type":"Point"}
}