{
  "type": "Feature",
  "properties": {
    "addr:full":"Gl. Kirkevej 45-47 Horsens Danmark 8700",
    "addr:postcode":"45-47;8700",
    "addr:street":"Gl. Kirkevej",
    "iso:country":"DK",
    "sg:address":"Gl. Kirkevej 45-47",
    "sg:city":"Horsens",
    "sg:orig_category":"Handicapboliger",
    "sg:phone":"+45 75 65 66 44",
    "sg:postcode":"8700",
    "sg:province":"Danmark",
    "wof:name":"Bo-Horsens, Egebjergkollegiet",
    "wof:placetype":"venue"
},
  "geometry": {"coordinates":[9.995759964,55.8096694946],"type":"Point"}
}