{
  "type": "Feature",
  "properties": {
    "addr:full":"Videbechs Alle 6 Viborg Danmark 8800",
    "addr:housenumber":"6",
    "addr:postcode":"8800",
    "addr:street":"Videbechs Alle",
    "iso:country":"DK",
    "sg:address":"Videbechs Alle 6",
    "sg:city":"Viborg",
    "sg:orig_category":"Efterskoler",
    "sg:phone":"+45 86 63 82 55",
    "sg:postcode":"8800",
    "sg:province":"Danmark",
    "wof:name":"Hald Ege Efterskole",
    "wof:placetype":"venue"
},
  "geometry": {"coordinates":[9.3465595245,56.4127807617],"type":"Point"}
}