{
  "type": "Feature",
  "properties": {
    "iso:country":"DK",
    "sg:address":"Tangevej 6",
    "sg:city":"Ribe",
    "sg:orig_category":"Jordemodercentre",
    "sg:phone":"+45 75 42 40 84",
    "sg:postcode":"6760",
    "sg:province":"Danmark",
    "wof:name":"Jordemoderkonsultationen i Ribe",
    "wof:placetype":"venue"
},
  "geometry": {"coordinates":[8.7781400681,55.3277168274],"type":"Point"}
}