{
  "type": "Feature",
  "properties": {
    "addr:full":"Varmingvej 3, Seem Ribe Danmark 6760",
    "addr:housenumber":"3",
    "addr:postcode":"6760",
    "addr:street":"Varmingvej;Seem",
    "iso:country":"DK",
    "sg:address":"Varmingvej 3, Seem",
    "sg:city":"Ribe",
    "sg:orig_category":"Skolefritidsordninger",
    "sg:phone":"+45 75 44 13 43",
    "sg:postcode":"6760",
    "sg:province":"Danmark",
    "wof:name":"Geseemsen Skolefritidsordning - Seem Skole",
    "wof:placetype":"venue"
},
  "geometry": {"coordinates":[8.7656240463,55.3297042847],"type":"Point"}
}