{
  "type": "Feature",
  "properties": {
    "iso:country":"DK",
    "sg:address":"Toftelunden 5",
    "sg:city":"Hasle",
    "sg:orig_category":"Dagcentre",
    "sg:phone":"+45 56 96 46 11",
    "sg:postcode":"3790",
    "sg:province":"Danmark",
    "wof:name":"Dagcenteret Tofteg\u00e5rden",
    "wof:placetype":"venue"
},
  "geometry": {"coordinates":[14.7156429291,55.1788368225],"type":"Point"}
}