{
  "type": "Feature",
  "properties": {
    "iso:country":"DK",
    "sg:address":"Preislers Plads 3",
    "sg:city":"Viborg",
    "sg:orig_category":"Solcentre",
    "sg:phone":"+45 86 62 07 39",
    "sg:postcode":"8800",
    "sg:province":"Danmark",
    "wof:name":"Fun & Sun House",
    "wof:placetype":"venue"
},
  "geometry": {"coordinates":[9.406411171,56.4504051208],"type":"Point"}
}