{
  "type": "Feature",
  "properties": {
    "addr:full":"Bj\u00e6lkerupvej 34 A Store Heddinge Danmark 4660",
    "addr:housenumber":"34 a",
    "addr:postcode":"4660",
    "addr:street":"Bjaelkerupvej",
    "iso:country":"DK",
    "sg:address":"Bj\u00e6lkerupvej 34 A",
    "sg:city":"Store Heddinge",
    "sg:orig_category":"Jordemodercentre",
    "sg:phone":"+45 56 50 21 22",
    "sg:postcode":"4660",
    "sg:province":"Danmark",
    "wof:name":"Jordemodercentret",
    "wof:placetype":"venue"
},
  "geometry": {"coordinates":[12.3836326599,55.3176727295],"type":"Point"}
}