{
  "type": "Feature",
  "properties": {
    "iso:country":"DK",
    "sg:address":"Fmd.: Lisbeth Kj\u00e6rsgaard, \u00c5lborgvej 176, Kistrup",
    "sg:city":"Tjele",
    "sg:orig_category":"Husflidsforeninger",
    "sg:phone":"+45 86 69 91 25",
    "sg:postcode":"8830",
    "sg:province":"Danmark",
    "wof:name":"L\u00f8vel Aktive M/K",
    "wof:placetype":"venue"
},
  "geometry": {"coordinates":[9.6264801025,56.4818611145],"type":"Point"}
}