{
  "type": "Feature",
  "properties": {
    "addr:full":"Fmd.: Holger Rasmussen, Plantagevej 5, K\u00f8belev Nakskov Danmark 4900",
    "addr:housenumber":"5",
    "addr:postcode":"4900",
    "addr:street":"Plantagevej",
    "iso:country":"DK",
    "sg:address":"Fmd.: Holger Rasmussen, Plantagevej 5, K\u00f8belev",
    "sg:city":"Nakskov",
    "sg:orig_category":"\u00c3\u2020ldreorganisationer og klubber",
    "sg:phone":"+45 54 93 23 04",
    "sg:postcode":"4900",
    "sg:province":"Danmark",
    "wof:name":"Pensionistforeningen K\u00f8belev",
    "wof:placetype":"venue"
},
  "geometry": {"coordinates":[11.1359500885,54.8330116272],"type":"Point"}
}