{
  "type": "Feature",
  "properties": {
    "addr:full":"Vonge Skovvej 3 Vonge Danmark 7173",
    "addr:housenumber":"3",
    "addr:postcode":"7173",
    "addr:street":"Vonge Skovvej",
    "iso:country":"DK",
    "sg:address":"Vonge Skovvej 3",
    "sg:city":"Vonge",
    "sg:orig_category":"Zoneterapeuter",
    "sg:phone":"+45 75 80 36 16",
    "sg:postcode":"7173",
    "sg:province":"Danmark",
    "wof:name":"Healing Hands",
    "wof:placetype":"venue"
},
  "geometry": {"coordinates":[9.4237537384,55.8605804443],"type":"Point"}
}