{
  "type": "Feature",
  "properties": {
    "addr:full":"Godth\u00e5bsvej 4 Frederiksberg Danmark 2000",
    "addr:housenumber":"4",
    "addr:postcode":"2000",
    "addr:street":"Godthaabsvej",
    "iso:country":"DK",
    "sg:address":"Godth\u00e5bsvej 4",
    "sg:city":"Frederiksberg",
    "sg:classifiers":[
        {
            "category":"Restaurant",
            "type":"Food & Drink"
        }
    ],
    "sg:phone":"+45 38 10 06 42",
    "sg:postcode":"2000",
    "sg:province":"Danmark",
    "sg:website":"www.londonpub.dk",
    "wof:name":"London Pub",
    "wof:placetype":"venue"
},
  "geometry": {"coordinates":[12.5379581451,55.6856155396],"type":"Point"}
}