{
  "type": "Feature",
  "properties": {
    "addr:full":"Bl\u00e5vandvej 29 B Bl\u00e5vand Danmark 6857",
    "addr:housenumber":"29 b",
    "addr:postcode":"6857",
    "addr:street":"Blaavandvej",
    "iso:country":"DK",
    "sg:address":"Bl\u00e5vandvej 29 B",
    "sg:city":"Bl\u00e5vand",
    "sg:orig_category":"Sko",
    "sg:phone":"+45 75 27 95 33",
    "sg:postcode":"6857",
    "sg:province":"Danmark",
    "sg:website":"www.blaavandsko.dk",
    "wof:name":"Bl\u00e5vand Sko - Din Gr\u00f8nne Skobutik",
    "wof:placetype":"venue"
},
  "geometry": {"coordinates":[-121.969581604,38.2857437134],"type":"Point"}
}