{
  "type": "Feature",
  "properties": {
    "addr:full":"Vejers Havvej 15 Vejers Strand Danmark 6853",
    "addr:housenumber":"15",
    "addr:postcode":"6853",
    "addr:street":"Vejers Havvej",
    "iso:country":"DK",
    "sg:address":"Vejers Havvej 15",
    "sg:city":"Vejers Strand",
    "sg:orig_category":"Campingpladser",
    "sg:phone":"+45 75 27 70 36",
    "sg:postcode":"6853",
    "sg:province":"Danmark",
    "wof:name":"Schl\u00fcters Camping",
    "wof:placetype":"venue"
},
  "geometry": {"coordinates":[8.1355810165,55.6194458008],"type":"Point"}
}