{
  "type": "Feature",
  "properties": {
    "addr:full":"Bredgade 63 Hejnsvig Danmark 7250",
    "addr:housenumber":"63",
    "addr:postcode":"7250",
    "addr:street":"Bredgade",
    "iso:country":"DK",
    "sg:address":"Bredgade 63",
    "sg:city":"Hejnsvig",
    "sg:orig_category":"Posthuse",
    "sg:phone":"+45 75 33 53 00",
    "sg:postcode":"7250",
    "sg:province":"Danmark",
    "wof:name":"Post Danmark, Hejnsvig Postbutik",
    "wof:placetype":"venue"
},
  "geometry": {"coordinates":[8.9978933334,55.6944541931],"type":"Point"}
}