{
  "type": "Feature",
  "properties": {
    "addr:full":"Korsn\u00e6bsvej 61 R\u00f8dvig Stevns Danmark 4673",
    "addr:housenumber":"61",
    "addr:postcode":"4673",
    "addr:street":"Korsnaebsvej",
    "iso:country":"DK",
    "sg:address":"Korsn\u00e6bsvej 61",
    "sg:city":"R\u00f8dvig Stevns",
    "sg:orig_category":"Maskinstationer",
    "sg:phone":"+45 56 50 60 33",
    "sg:postcode":"4673",
    "sg:province":"Danmark",
    "wof:name":"Nielsen, Jens \u00c5ge",
    "wof:placetype":"venue"
},
  "geometry": {"coordinates":[12.4090147018,55.2659721375],"type":"Point"}
}