{
  "type": "Feature",
  "properties": {
    "addr:full":"N\u00e6stvedvej 70 Vordingborg Danmark 4760",
    "addr:housenumber":"70",
    "addr:postcode":"4760",
    "addr:street":"Naestvedvej",
    "iso:country":"DK",
    "sg:address":"N\u00e6stvedvej 70",
    "sg:city":"Vordingborg",
    "sg:orig_category":"Autoforhandlere",
    "sg:phone":"+45 55 37 26 42",
    "sg:postcode":"4760",
    "sg:province":"Danmark",
    "wof:name":"Pedersen A/S, Leif",
    "wof:placetype":"venue"
},
  "geometry": {"coordinates":[11.8854932785,55.0259857178],"type":"Point"}
}