{
  "type": "Feature",
  "properties": {
    "addr:full":"\u00d8rholm Stationsvej 11 Kongens Lyngby Danmark 2800",
    "addr:housenumber":"11",
    "addr:postcode":"2800",
    "addr:street":"Stationsvej",
    "iso:country":"DK",
    "sg:address":"\u00d8rholm Stationsvej 11",
    "sg:city":"Kongens Lyngby",
    "sg:orig_category":"Arkitekter",
    "sg:phone":"+45 45 88 67 17",
    "sg:postcode":"2800",
    "sg:province":"Danmark",
    "wof:name":"Andersen, John",
    "wof:placetype":"venue"
},
  "geometry": {"coordinates":[12.5083799362,55.7996292114],"type":"Point"}
}