{
  "type": "Feature",
  "properties": {
    "addr:full":"N\u00f8rrek\u00e6r 1 R\u00f8dovre Danmark 2610",
    "addr:housenumber":"1",
    "addr:postcode":"2610",
    "addr:street":"Norrekaer",
    "iso:country":"DK",
    "sg:address":"N\u00f8rrek\u00e6r 1",
    "sg:city":"R\u00f8dovre",
    "sg:orig_category":"Grillbarer",
    "sg:phone":"+45 36 48 20 30",
    "sg:postcode":"2610",
    "sg:province":"Danmark",
    "wof:name":"P\u00f8lsegrill og pizza",
    "wof:placetype":"venue"
},
  "geometry": {"coordinates":[10.6992139816,61.1027755737],"type":"Point"}
}