{
  "type": "Feature",
  "properties": {
    "iso:country":"DK",
    "sg:address":"Hillerupvej 35 ",
    "sg:city":"Ribe",
    "sg:classifiers":[
        {
            "category":"Real Estate",
            "subcategory":"Surveying",
            "type":"Services"
        }
    ],
    "sg:phone":"+45 76 88 16 00",
    "sg:postcode":"6760",
    "sg:province":"Danmark",
    "sg:tags":[
        "equipment",
        "material",
        "good",
        "-",
        "handling"
    ],
    "wof:name":"LOGITRANS A/S",
    "wof:placetype":"venue"
},
  "geometry": {"coordinates":[8.7346086502,55.3605232239],"type":"Point"}
}