{
  "type": "Feature",
  "properties": {
    "addr:full":"Godth\u00e5bsvej 150, st Frederiksberg Danmark 2000",
    "addr:housenumber":"150",
    "addr:postcode":"2000",
    "addr:street":"Godthaabsvej;St",
    "iso:country":"DK",
    "sg:address":"Godth\u00e5bsvej 150, st",
    "sg:city":"Frederiksberg",
    "sg:orig_category":"Forlag",
    "sg:phone":"+45 38 71 01 87",
    "sg:postcode":"2000",
    "sg:province":"Danmark",
    "wof:name":"Orion, Bogforlaget",
    "wof:placetype":"venue"
},
  "geometry": {"coordinates":[12.5299301147,55.6787872314],"type":"Point"}
}