{
  "type": "Feature",
  "properties": {
    "addr:full":"Fmd.: Hanne Saugbjerg, Thomas Kingos Vej 20 Haderslev Danmark 6100",
    "addr:housenumber":"20",
    "addr:postcode":"6100",
    "addr:street":"Thomas Kingos Vej",
    "iso:country":"DK",
    "sg:address":"Fmd.: Hanne Saugbjerg, Thomas Kingos Vej 20",
    "sg:city":"Haderslev",
    "sg:orig_category":"Musik og sang",
    "sg:phone":"+45 74 53 29 12",
    "sg:postcode":"6100",
    "sg:province":"Danmark",
    "wof:name":"Haderslev Tambourkorps",
    "wof:placetype":"venue"
},
  "geometry": {"coordinates":[9.5100498199,55.2599105835],"type":"Point"}
}