{
  "type": "Feature",
  "properties": {
    "addr:full":"Strandvejen 2 Middelfart Danmark 5500",
    "addr:housenumber":"2",
    "addr:postcode":"5500",
    "addr:street":"Strandvejen",
    "iso:country":"DK",
    "sg:address":"Strandvejen 2",
    "sg:city":"Middelfart",
    "sg:orig_category":"Skilte",
    "sg:phone":"+45 64 41 87 77",
    "sg:postcode":"5500",
    "sg:province":"Danmark",
    "wof:name":"Jack Design",
    "wof:placetype":"venue"
},
  "geometry": {"coordinates":[9.751209259,55.5059013367],"type":"Point"}
}