{
  "type": "Feature",
  "properties": {
    "iso:country":"DK",
    "sg:address":"Adelgade 14",
    "sg:city":"Kolding",
    "sg:classifiers":[
        {
            "category":"Banks & Credit Unions",
            "subcategory":"Bank",
            "type":"Services"
        }
    ],
    "sg:phone":"+45 76 33 65 65",
    "sg:postcode":"6000",
    "sg:province":"Danmark",
    "sg:tags":[
        "banker"
    ],
    "wof:name":"Handelsbanken",
    "wof:placetype":"venue"
},
  "geometry": {"coordinates":[9.4722080231,55.4913024902],"type":"Point"}
}