{
  "type": "Feature",
  "properties": {
    "addr:full":"Thorsgade 4 B Randers Danmark 8900",
    "addr:housenumber":"4 b",
    "addr:postcode":"8900",
    "addr:street":"Thorsgade",
    "iso:country":"DK",
    "sg:address":"Thorsgade 4 B",
    "sg:city":"Randers",
    "sg:orig_category":"Konfekture",
    "sg:phone":"+45 86 42 16 56",
    "sg:postcode":"8900",
    "sg:province":"Danmark",
    "wof:name":"Heimdal Chokolade",
    "wof:placetype":"venue"
},
  "geometry": {"coordinates":[10.039812088,56.4618835449],"type":"Point"}
}