{
  "type": "Feature",
  "properties": {
    "iso:country":"DK",
    "sg:address":"Skanderborgvej 1",
    "sg:city":"Ry",
    "sg:classifiers":[
        {
            "category":"Home & Garden",
            "subcategory":"Home Furnishings",
            "type":"Retail Goods"
        }
    ],
    "sg:phone":"+45 86 89 15 80",
    "sg:postcode":"8680",
    "sg:province":"Danmark",
    "sg:tags":[
        "gardiner"
    ],
    "wof:name":"H\u00f8jgaard Gardiner",
    "wof:placetype":"venue"
},
  "geometry": {"coordinates":[9.7586946487,56.0923042297],"type":"Point"}
}