{
  "type": "Feature",
  "properties": {
    "addr:full":"Kl\u00f8vervej 1 Frederikshavn Danmark 9900",
    "addr:housenumber":"1",
    "addr:postcode":"9900",
    "addr:street":"Klovervej",
    "iso:country":"DK",
    "sg:address":"Kl\u00f8vervej 1",
    "sg:city":"Frederikshavn",
    "sg:orig_category":"Automater",
    "sg:phone":"+45 98 42 26 41",
    "sg:postcode":"9900",
    "sg:province":"Danmark",
    "wof:name":"Vendsyssel Automat A/S",
    "wof:placetype":"venue"
},
  "geometry": {"coordinates":[10.5389976501,57.4480285645],"type":"Point"}
}