{
  "type": "Feature",
  "properties": {
    "addr:full":"Tordenskjoldsgade 32 \u00c5rhus N Danmark 8200",
    "addr:housenumber":"32",
    "addr:postcode":"8200",
    "addr:street":"Tordenskjoldsgade",
    "iso:country":"DK",
    "sg:address":"Tordenskjoldsgade 32",
    "sg:city":"\u00c5rhus N",
    "sg:classifiers":[
        {
            "category":"Home & Garden",
            "subcategory":"Home Furnishings",
            "type":"Retail Goods"
        }
    ],
    "sg:phone":"+45 86 16 84 00",
    "sg:postcode":"8200",
    "sg:province":"Danmark",
    "sg:tags":[
        "gardiner"
    ],
    "sg:website":"www.gottlieb-gardiner.dk",
    "wof:name":"Gottlieb Gardiner",
    "wof:placetype":"venue"
},
  "geometry": {"coordinates":[10.2163696289,56.1709938049],"type":"Point"}
}