{
  "type": "Feature",
  "properties": {
    "addr:full":"Nakskovvej 77 Valby Danmark 2500",
    "addr:housenumber":"77",
    "addr:postcode":"2500",
    "addr:street":"Nakskovvej",
    "iso:country":"DK",
    "sg:address":"Nakskovvej 77",
    "sg:city":"Valby",
    "sg:orig_category":"Snedkermestre",
    "sg:phone":"+45 36 16 60 14",
    "sg:postcode":"2500",
    "sg:province":"Danmark",
    "wof:name":"Rasmussen, Niels F.",
    "wof:placetype":"venue"
},
  "geometry": {"coordinates":[12.4916324615,55.6657562256],"type":"Point"}
}