{
  "type": "Feature",
  "properties": {
    "addr:full":"Vesterg\u00e5rdsvej 18 Glostrup Danmark 2600",
    "addr:housenumber":"18",
    "addr:postcode":"2600",
    "addr:street":"Vestergaardsvej",
    "iso:country":"DK",
    "sg:address":"Vesterg\u00e5rdsvej 18",
    "sg:city":"Glostrup",
    "sg:orig_category":"Skolefritidsordninger",
    "sg:phone":"+45 43 96 66 65",
    "sg:postcode":"2600",
    "sg:province":"Danmark",
    "wof:name":"Vesterg\u00e5rden, SFO",
    "wof:placetype":"venue"
},
  "geometry": {"coordinates":[12.3780136108,55.6655845642],"type":"Point"}
}