{
  "type": "Feature",
  "properties": {
    "iso:country":"DK",
    "sg:address":"Toftagervej 2, \u00d8ster Alling",
    "sg:city":"Auning",
    "sg:orig_category":"Malermestre",
    "sg:phone":"+45 86 49 29 77",
    "sg:postcode":"8963",
    "sg:province":"Danmark",
    "wof:name":"Petersen, Oluf",
    "wof:placetype":"venue"
},
  "geometry": {"coordinates":[10.3770084381,56.430065155],"type":"Point"}
}