{
  "type": "Feature",
  "properties": {
    "addr:full":"Kirsten Piils Vej 40 Vejle Danmark 7100",
    "addr:housenumber":"40",
    "addr:postcode":"7100",
    "addr:street":"Kirsten Piils Vej",
    "iso:country":"DK",
    "sg:address":"Kirsten Piils Vej 40",
    "sg:city":"Vejle",
    "sg:orig_category":"Ejendomshandel",
    "sg:phone":"+45 75 82 03 34",
    "sg:postcode":"7100",
    "sg:province":"Danmark",
    "wof:name":"Fenger, H.B.",
    "wof:placetype":"venue"
},
  "geometry": {"coordinates":[9.5517787933,55.68592453],"type":"Point"}
}