{
  "type": "Feature",
  "properties": {
    "addr:full":"Lundh\u00f8jvej 15 Ry Danmark 8680",
    "addr:housenumber":"15",
    "addr:postcode":"8680",
    "addr:street":"Lundhojvej",
    "iso:country":"DK",
    "sg:address":"Lundh\u00f8jvej 15",
    "sg:city":"Ry",
    "sg:orig_category":"Planteskoler",
    "sg:phone":"+45 86 89 11 83",
    "sg:postcode":"8680",
    "sg:province":"Danmark",
    "wof:name":"Siim Planteskole",
    "wof:placetype":"venue"
},
  "geometry": {"coordinates":[9.7593002319,56.0920562744],"type":"Point"}
}