{
  "type": "Feature",
  "properties": {
    "addr:full":"Gammel Brovej 25 Karreb\u00e6ksminde Danmark 4736",
    "addr:housenumber":"25",
    "addr:postcode":"4736",
    "addr:street":"Gammel Brovej",
    "iso:country":"DK",
    "sg:address":"Gammel Brovej 25",
    "sg:city":"Karreb\u00e6ksminde",
    "sg:orig_category":"Gaveartikler",
    "sg:phone":"+45 40 15 52 91",
    "sg:postcode":"4736",
    "sg:province":"Danmark",
    "sg:website":"www.home19.inet.tele.dk/sloppen",
    "wof:name":"Slopkisten",
    "wof:placetype":"venue"
},
  "geometry": {"coordinates":[12.2043600082,48.5182304382],"type":"Point"}
}