{
  "type": "Feature",
  "properties": {
    "addr:full":"Torve Alle 10 Tranbjerg Danmark 8310",
    "addr:housenumber":"10",
    "addr:postcode":"8310",
    "addr:street":"Torve Alle",
    "iso:country":"DK",
    "sg:address":"Torve Alle 10",
    "sg:city":"Tranbjerg",
    "sg:orig_category":"Kirker",
    "sg:postcode":"8310",
    "sg:province":"Danmark",
    "wof:name":"Tranbjerg Kirke",
    "wof:placetype":"venue"
},
  "geometry": {"coordinates":[10.1378421783,56.0921936035],"type":"Point"}
}