{
  "type": "Feature",
  "properties": {
    "iso:country":"DK",
    "sg:address":"Frederikssundsvej 110",
    "sg:city":"K\u00f8benhavn NV",
    "sg:orig_category":"Blomsterhandlere",
    "sg:phone":"+45 38 81 05 18",
    "sg:postcode":"2400",
    "sg:province":"Danmark",
    "wof:name":"Heidis Blomster",
    "wof:placetype":"venue"
},
  "geometry": {"coordinates":[-117.02272033689999,38.5024604797],"type":"Point"}
}