{
  "type": "Feature",
  "properties": {
    "addr:full":"Vesterbrogade 185 Frederiksberg Danmark 1800",
    "addr:housenumber":"185;1800",
    "addr:street":"Vesterbrogade",
    "iso:country":"DK",
    "sg:address":"Vesterbrogade 185",
    "sg:city":"Frederiksberg",
    "sg:orig_category":"Kasseapparater",
    "sg:phone":"+45 33 21 23 27",
    "sg:postcode":"1800",
    "sg:province":"Danmark",
    "wof:name":"Papirg\u00e5rden A/S",
    "wof:placetype":"venue"
},
  "geometry": {"coordinates":[12.5320997238,55.6706695557],"type":"Point"}
}