{
  "type": "Feature",
  "properties": {
    "addr:full":"Vesterled 1 Ranum Danmark 9681",
    "addr:housenumber":"1",
    "addr:postcode":"9681",
    "addr:street":"Vesterled",
    "iso:country":"DK",
    "sg:address":"Vesterled 1",
    "sg:city":"Ranum",
    "sg:orig_category":"Varmeforsyning",
    "sg:phone":"+45 98 67 60 61",
    "sg:postcode":"9681",
    "sg:province":"Danmark",
    "wof:name":"Ranum Fjernvarmev\u00e6rk A.m.b.A.",
    "wof:placetype":"venue"
},
  "geometry": {"coordinates":[9.2285633087,56.8984031677],"type":"Point"}
}