{
  "type": "Feature",
  "properties": {
    "addr:full":"Amsterdamvej 1 K\u00f8benhavn S Danmark 2300",
    "addr:housenumber":"1",
    "addr:postcode":"2300",
    "addr:street":"Amsterdamvej;S Danmark",
    "iso:country":"DK",
    "sg:address":"Amsterdamvej 1",
    "sg:city":"K\u00f8benhavn S",
    "sg:orig_category":"Hundetrimning",
    "sg:phone":"+45 32 55 18 06",
    "sg:postcode":"2300",
    "sg:province":"Danmark",
    "wof:name":"Amager Hundesalon",
    "wof:placetype":"venue"
},
  "geometry": {"coordinates":[12.6137895584,55.6484603882],"type":"Point"}
}