{
  "type": "Feature",
  "properties": {
    "addr:full":"v/ H\u00f8jmark Brugs, Adelvej 15 Lem Danmark 6940",
    "addr:housenumber":"15",
    "addr:postcode":"6940",
    "addr:street":"Adelvej",
    "iso:country":"DK",
    "sg:address":"v/ H\u00f8jmark Brugs, Adelvej 15",
    "sg:city":"Lem",
    "sg:orig_category":"Apoteker og -udsalg",
    "sg:phone":"+45 97 34 30 09",
    "sg:postcode":"6940",
    "sg:province":"Danmark",
    "wof:name":"H\u00e5ndk\u00f8bsudsalget",
    "wof:placetype":"venue"
},
  "geometry": {"coordinates":[8.3932304382,56.0546112061],"type":"Point"}
}