{
  "type": "Feature",
  "properties": {
    "addr:full":"Nairobi Alle 43 Kastrup Danmark 2770",
    "addr:housenumber":"43",
    "addr:postcode":"2770",
    "addr:street":"Nairobi Alle",
    "iso:country":"DK",
    "sg:address":"Nairobi Alle 43",
    "sg:city":"Kastrup",
    "sg:orig_category":"Skilte",
    "sg:phone":"+45 32 94 22 09",
    "sg:postcode":"2770",
    "sg:province":"Danmark",
    "wof:name":"Riposta",
    "wof:placetype":"venue"
},
  "geometry": {"coordinates":[12.5770587921,55.5992469788],"type":"Point"}
}