{
  "type": "Feature",
  "properties": {
    "addr:full":"Kalkv\u00e6rksvej 9 F Frederikshavn Danmark 9900",
    "addr:housenumber":"9 f",
    "addr:postcode":"9900",
    "addr:street":"Kalkvaerksvej",
    "iso:country":"DK",
    "sg:address":"Kalkv\u00e6rksvej 9 F",
    "sg:city":"Frederikshavn",
    "sg:classifiers":[
        {
            "category":"Personal",
            "subcategory":"Massage",
            "type":"Services"
        }
    ],
    "sg:phone":"+45 98 43 17 51",
    "sg:postcode":"9900",
    "sg:province":"Danmark",
    "wof:name":"Fysiurgisk Kropsmassage",
    "wof:placetype":"venue"
},
  "geometry": {"coordinates":[10.5362997055,57.4396400452],"type":"Point"}
}