{
  "type": "Feature",
  "properties": {
    "iso:country":"DK",
    "sg:address":"Klintevej 6, Knudlund",
    "sg:city":"Them",
    "sg:orig_category":"Lakering",
    "sg:phone":"+45 86 84 81 44",
    "sg:postcode":"8653",
    "sg:province":"Danmark",
    "sg:website":"www.indulak.dk",
    "wof:name":"indu-lak A/S",
    "wof:placetype":"venue"
},
  "geometry": {"coordinates":[9.5489425659,56.0950088501],"type":"Point"}
}