{
  "type": "Feature",
  "properties": {
    "addr:full":"Gammel K\u00f8ge Landevej 174 Valby Danmark 2500",
    "addr:housenumber":"174",
    "addr:postcode":"2500",
    "addr:street":"Gammel Koge Landevej",
    "iso:country":"DK",
    "sg:address":"Gammel K\u00f8ge Landevej 174",
    "sg:city":"Valby",
    "sg:orig_category":"Autoforhandlere",
    "sg:phone":"+45 36 46 25 00",
    "sg:postcode":"2500",
    "sg:province":"Danmark",
    "wof:name":"Nykilde Automobiler I/S",
    "wof:placetype":"venue"
},
  "geometry": {"coordinates":[12.5034427643,55.6456794739],"type":"Point"}
}