{
  "type": "Feature",
  "properties": {
    "addr:full":"Rosenlundvej 10 Lynge Danmark 3540",
    "addr:housenumber":"10",
    "addr:postcode":"3540",
    "addr:street":"Rosenlundvej",
    "iso:country":"DK",
    "sg:address":"Rosenlundvej 10",
    "sg:city":"Lynge",
    "sg:orig_category":"Tekstiltrykkerier",
    "sg:phone":"+45 21 28 50 43",
    "sg:postcode":"3540",
    "sg:province":"Danmark",
    "sg:website":"www.trykpaatoej.dk",
    "wof:name":"Tryk P\u00e5 T\u00f8j",
    "wof:placetype":"venue"
},
  "geometry": {"coordinates":[12.2552404404,55.8271331787],"type":"Point"}
}