{
  "type": "Feature",
  "properties": {
    "iso:country":"DK",
    "sg:address":"Sankt Mari\u00e6 Kirke, Jens Jessens Vej 5",
    "sg:city":"Frederiksberg",
    "sg:orig_category":"Kirkelige foreninger",
    "sg:phone":"+45 38 71 53 35",
    "sg:postcode":"2000",
    "sg:province":"Danmark",
    "wof:name":"Sankt Mari\u00e6 Unge Katolikker",
    "wof:placetype":"venue"
},
  "geometry": {"coordinates":[12.5299301147,55.6787872314],"type":"Point"}
}