{
  "type": "Feature",
  "properties": {
    "iso:country":"DK",
    "sg:address":"Trank\u00e6r Hole 5, Ydby",
    "sg:city":"Hurup",
    "sg:orig_category":"Spejderkorps",
    "sg:phone":"+45 97 95 64 01",
    "sg:postcode":"7760",
    "sg:province":"Danmark",
    "wof:name":"FDF Spejderhytten Kn\u00f8sen",
    "wof:placetype":"venue"
},
  "geometry": {"coordinates":[8.4233045578,56.7485847473],"type":"Point"}
}