{
  "type": "Feature",
  "properties": {
    "addr:full":"\u00d8stergade 27 K\u00f8benhavn Danmark 1100",
    "addr:housenumber":"27;1100",
    "addr:street":"Ostergade",
    "iso:country":"DK",
    "sg:address":"\u00d8stergade 27",
    "sg:city":"K\u00f8benhavn",
    "sg:orig_category":"Detektivbureauer",
    "sg:phone":"+45 33 15 72 72",
    "sg:postcode":"1100",
    "sg:province":"Danmark",
    "sg:website":"www.adasis.dk",
    "wof:name":"Adasis International",
    "wof:placetype":"venue"
},
  "geometry": {"coordinates":[76.3070983887,14.277130127],"type":"Point"}
}