{
  "type": "Feature",
  "properties": {
    "iso:country":"DK",
    "sg:address":"Aaparken 4",
    "sg:city":"Odder",
    "sg:orig_category":"Boligselskaber",
    "sg:phone":"+45 86 54 13 04",
    "sg:postcode":"8300",
    "sg:province":"Danmark",
    "wof:name":"Aaparken A/S",
    "wof:placetype":"venue"
},
  "geometry": {"coordinates":[10.1556663513,55.9771385193],"type":"Point"}
}