{
  "type": "Feature",
  "properties": {
    "iso:country":"DK",
    "sg:address":"Fmd.: Finn Juhler Jensen, L\u00e6rkevej 12, Thorsminde",
    "sg:city":"Ulfborg",
    "sg:orig_category":"Borger- og beboerforeninger",
    "sg:phone":"+45 97 49 70 06",
    "sg:postcode":"6990",
    "sg:province":"Danmark",
    "wof:name":"Thorsminde Borgerforening",
    "wof:placetype":"venue"
},
  "geometry": {"coordinates":[8.3210029602,56.2727661133],"type":"Point"}
}