{
  "type": "Feature",
  "properties": {
    "addr:full":"Byvej 3, Ballum Bredebro Danmark 6261",
    "addr:housenumber":"3",
    "addr:postcode":"6261",
    "addr:street":"Byvej",
    "iso:country":"DK",
    "sg:address":"Byvej 3, Ballum",
    "sg:city":"Bredebro",
    "sg:orig_category":"Autoreparation og -service",
    "sg:phone":"+45 74 71 61 56",
    "sg:postcode":"6261",
    "sg:province":"Danmark",
    "wof:name":"Ballum Autoservice",
    "wof:placetype":"venue"
},
  "geometry": {"coordinates":[8.8284835815,55.0566978455],"type":"Point"}
}