{
  "type": "Feature",
  "properties": {
    "iso:country":"DK",
    "sg:address":"\u00c5lholmvej 15",
    "sg:city":"Valby",
    "sg:orig_category":"Kiosker",
    "sg:phone":"+45 36 16 20 50",
    "sg:postcode":"2500",
    "sg:province":"Danmark",
    "wof:name":"Vin & Tobak",
    "wof:placetype":"venue"
},
  "geometry": {"coordinates":[12.4885520935,55.6717414856],"type":"Point"}
}