{
  "type": "Feature",
  "properties": {
    "addr:full":"Enghavevej 47 Nyk\u00f8bing Danmark 7900",
    "addr:housenumber":"47",
    "addr:postcode":"7900",
    "addr:street":"Enghavevej",
    "iso:country":"DK",
    "sg:address":"Enghavevej 47",
    "sg:city":"Nyk\u00f8bing",
    "sg:orig_category":"Handicap-daginstitutioner",
    "sg:phone":"+45 97 72 58 31",
    "sg:postcode":"7900",
    "sg:province":"Danmark",
    "wof:name":"Aktivitetscentret",
    "wof:placetype":"venue"
},
  "geometry": {"coordinates":[8.8630752563,56.7945251465],"type":"Point"}
}