{
  "type": "Feature",
  "properties": {
    "addr:full":"Bakkevej 5, Farre Give Danmark 7323",
    "addr:housenumber":"5",
    "addr:postcode":"7323",
    "addr:street":"Bakkevej;Farre",
    "iso:country":"DK",
    "sg:address":"Bakkevej 5, Farre",
    "sg:city":"Give",
    "sg:orig_category":"Malermestre",
    "sg:phone":"+45 75 73 31 28",
    "sg:postcode":"7323",
    "sg:province":"Danmark",
    "wof:name":"Poulsen, J\u00f8rgen",
    "wof:placetype":"venue"
},
  "geometry": {"coordinates":[9.2362060547,55.845413208],"type":"Point"}
}