{
  "type": "Feature",
  "properties": {
    "addr:full":"Horsholmstr\u00e6de 7 Albertslund Danmark 2620",
    "addr:housenumber":"7",
    "addr:postcode":"2620",
    "addr:street":"Horsholmstraede",
    "iso:country":"DK",
    "sg:address":"Horsholmstr\u00e6de 7",
    "sg:city":"Albertslund",
    "sg:orig_category":"Arkitekter",
    "sg:phone":"+45 43 64 94 14",
    "sg:postcode":"2620",
    "sg:province":"Danmark",
    "wof:name":"Dahl, Torben og Annette",
    "wof:placetype":"venue"
},
  "geometry": {"coordinates":[12.3517179489,55.6568450928],"type":"Point"}
}