{
  "type": "Feature",
  "properties": {
    "addr:full":"Helsing\u00f8rsvej 1, Postboks 62 Fredensborg Danmark 3480",
    "addr:housenumber":"1;62",
    "addr:postcode":"3480",
    "addr:street":"Helsingorsvej",
    "iso:country":"DK",
    "sg:address":"Helsing\u00f8rsvej 1, Postboks 62",
    "sg:city":"Fredensborg",
    "sg:orig_category":"Lederudvikling",
    "sg:phone":"+45 48 48 51 16",
    "sg:postcode":"3480",
    "sg:province":"Danmark",
    "wof:name":"Freelance Danmark",
    "wof:placetype":"venue"
},
  "geometry": {"coordinates":[12.4020547867,55.9782943726],"type":"Point"}
}