{
  "type": "Feature",
  "properties": {
    "addr:full":"Smedeskovvej 40 Galten Danmark 8464",
    "addr:housenumber":"40",
    "addr:postcode":"8464",
    "addr:street":"Smedeskovvej",
    "iso:country":"DK",
    "sg:address":"Smedeskovvej 40",
    "sg:city":"Galten",
    "sg:orig_category":"Maskinfabrikker",
    "sg:phone":"+45 86 94 35 00",
    "sg:postcode":"8464",
    "sg:province":"Danmark",
    "sg:website":"www.avkvalves.com",
    "wof:name":"AVK International A/S",
    "wof:placetype":"venue"
},
  "geometry": {"coordinates":[9.9171848297,56.1593513489],"type":"Point"}
}