{
  "type": "Feature",
  "properties": {
    "iso:country":"DK",
    "sg:address":"Ungdomsskoleinsp.: Jens E. Jensen, Sundvej 34, Hvalpsund",
    "sg:city":"Fars\u00f8",
    "sg:orig_category":"Kommunale ungdomsskoler",
    "sg:phone":"+45 98 63 86 15",
    "sg:postcode":"9640",
    "sg:province":"Danmark",
    "wof:name":"Fars\u00f8 kommunale Ungdomsskole",
    "wof:placetype":"venue"
},
  "geometry": {"coordinates":[9.1937885284,56.6945037842],"type":"Point"}
}