{
  "type": "Feature",
  "properties": {
    "addr:full":"v/ Frank Henriksen, Bolsbjergvej 15 Mariager Danmark 9550",
    "addr:housenumber":"15",
    "addr:postcode":"9550",
    "addr:street":"Bolsbjergvej",
    "iso:country":"DK",
    "sg:address":"v/ Frank Henriksen, Bolsbjergvej 15",
    "sg:city":"Mariager",
    "sg:orig_category":"Forsamlingshuse",
    "sg:phone":"+45 86 47 84 74",
    "sg:postcode":"9550",
    "sg:province":"Danmark",
    "wof:name":"V. T\u00f8rslev Forsamlingshus",
    "wof:placetype":"venue"
},
  "geometry": {"coordinates":[10.0618648529,56.676902771],"type":"Point"}
}