{
  "type": "Feature",
  "properties": {
    "addr:full":"Tagensvej 90 K\u00f8benhavn N Danmark 2200",
    "addr:housenumber":"90",
    "addr:postcode":"2200",
    "addr:street":"Tagensvej;Kobenhavn N Danmark",
    "iso:country":"DK",
    "sg:address":"Tagensvej 90",
    "sg:city":"K\u00f8benhavn N",
    "sg:orig_category":"Benzinstationer",
    "sg:phone":"+45 35 81 18 21",
    "sg:postcode":"2200",
    "sg:province":"Danmark",
    "wof:name":"Q8",
    "wof:placetype":"venue"
},
  "geometry": {"coordinates":[-76.41683999999999,37.452419],"type":"Point"}
}