{
  "type": "Feature",
  "properties": {
    "addr:full":"Maltvej 86, Askov Vejen Danmark 6600",
    "addr:housenumber":"86",
    "addr:postcode":"6600",
    "addr:street":"Maltvej",
    "iso:country":"DK",
    "sg:address":"Maltvej 86, Askov",
    "sg:city":"Vejen",
    "sg:orig_category":"Kommunale folkeskoler",
    "sg:phone":"+45 75 36 09 68",
    "sg:postcode":"6600",
    "sg:province":"Danmark",
    "wof:name":"Askov-Malt Skole",
    "wof:placetype":"venue"
},
  "geometry": {"coordinates":[9.1396121979,55.4778175354],"type":"Point"}
}