{
  "type": "Feature",
  "properties": {
    "addr:full":"Str\u00f8byvej 23 Hvidovre Danmark 2650",
    "addr:housenumber":"23",
    "addr:postcode":"2650",
    "addr:street":"Strobyvej",
    "iso:country":"DK",
    "sg:address":"Str\u00f8byvej 23",
    "sg:city":"Hvidovre",
    "sg:orig_category":"Malermestre",
    "sg:phone":"+45 40 16 54 33",
    "sg:postcode":"2650",
    "sg:province":"Danmark",
    "wof:name":"Hansen, Benny",
    "wof:placetype":"venue"
},
  "geometry": {"coordinates":[12.483669281,55.6405601501],"type":"Point"}
}