{
  "type": "Feature",
  "properties": {
    "addr:full":"Ager\u00f8vej 33, Ager\u00f8 Karby Danmark 7960",
    "addr:housenumber":"33",
    "addr:postcode":"7960",
    "addr:street":"Agerovej",
    "iso:country":"DK",
    "sg:address":"Ager\u00f8vej 33, Ager\u00f8",
    "sg:city":"Karby",
    "sg:orig_category":"Kirker",
    "sg:postcode":"7960",
    "sg:province":"Danmark",
    "wof:name":"Ager\u00f8 Kirke",
    "wof:placetype":"venue"
},
  "geometry": {"coordinates":[8.5592756271,56.7536697388],"type":"Point"}
}