{
  "type": "Feature",
  "properties": {
    "addr:full":"Bredholtvej 28 Sulsted Danmark 9381",
    "addr:housenumber":"28",
    "addr:postcode":"9381",
    "addr:street":"Bredholtvej",
    "iso:country":"DK",
    "sg:address":"Bredholtvej 28",
    "sg:city":"Sulsted",
    "sg:classifiers":[
        {
            "category":"Food & Beverages",
            "subcategory":"Bakery",
            "type":"Retail Goods"
        }
    ],
    "sg:phone":"+45 98 26 10 18",
    "sg:postcode":"9381",
    "sg:province":"Danmark",
    "sg:tags":[
        "biscuit"
    ],
    "wof:name":"K. E. Biscuits",
    "wof:placetype":"venue"
},
  "geometry": {"coordinates":[9.983258,57.177307],"type":"Point"}
}