{
  "type": "Feature",
  "properties": {
    "iso:country":"DK",
    "sg:address":"Londongade 4",
    "sg:city":"Odense C",
    "sg:orig_category":"Spedition",
    "sg:phone":"+45 66 11 24 05",
    "sg:postcode":"5000",
    "sg:province":"Danmark",
    "wof:name":"Leman",
    "wof:placetype":"venue"
},
  "geometry": {"coordinates":[10.3831386566,55.4061965942],"type":"Point"}
}