{
  "type": "Feature",
  "properties": {
    "iso:country":"DK",
    "sg:address":"Ormh\u00f8jg\u00e5rdvej 1, Postboks 27",
    "sg:city":"Horsens",
    "sg:orig_category":"Biografer",
    "sg:phone":"+45 75 64 67 88",
    "sg:postcode":"8700",
    "sg:province":"Danmark",
    "wof:name":"ABC Biograferne",
    "wof:placetype":"venue"
},
  "geometry": {"coordinates":[9.843245,55.862106],"type":"Point"}
}