{
  "type": "Feature",
  "properties": {
    "addr:full":"Sognepr\u00e6st: Gert Nicolajsen (K/B), Aadalsvej 2 A, Vorgod Videb\u00e6k Danmark 6920",
    "addr:housenumber":"2 a",
    "addr:postcode":"6920",
    "addr:street":"Aadalsvej;Vorgod Videbaek Danmark",
    "iso:country":"DK",
    "sg:address":"Sognepr\u00e6st: Gert Nicolajsen (K/B), Aadalsvej 2 A, Vorgod",
    "sg:city":"Videb\u00e6k",
    "sg:orig_category":"Kirkesogne",
    "sg:phone":"+45 97 17 53 02",
    "sg:postcode":"6920",
    "sg:province":"Danmark",
    "sg:website":"www.folkekirken.dk/sogn/vorgod",
    "wof:name":"Vorgod Sogn",
    "wof:placetype":"venue"
},
  "geometry": {"coordinates":[8.7436800003,55.9904136658],"type":"Point"}
}