{
  "type": "Feature",
  "properties": {
    "addr:full":"Jernbanegade 24 Thors\u00f8 Danmark 8881",
    "addr:housenumber":"24",
    "addr:postcode":"8881",
    "addr:street":"Jernbanegade",
    "iso:country":"DK",
    "sg:address":"Jernbanegade 24",
    "sg:city":"Thors\u00f8",
    "sg:orig_category":"Forsamlingshuse",
    "sg:phone":"+45 86 96 71 52",
    "sg:postcode":"8881",
    "sg:province":"Danmark",
    "wof:name":"Thors\u00f8 Hotel",
    "wof:placetype":"venue"
},
  "geometry": {"coordinates":[9.7914276123,56.2974052429],"type":"Point"}
}