{
  "type": "Feature",
  "properties": {
    "iso:country":"DK",
    "sg:address":"Byrum Hovedgade 49, Byrum",
    "sg:city":"L\u00e6s\u00f8",
    "sg:classifiers":[
        {
            "category":"Manufacturing",
            "subcategory":"Tobacco Products",
            "type":"Manufacturing & Wholesale Goods"
        }
    ],
    "sg:phone":"+45 98 49 10 06",
    "sg:postcode":"9940",
    "sg:province":"Danmark",
    "sg:tags":[
        "manufacturer"
    ],
    "wof:name":"Heintzelmanns Eftf.",
    "wof:placetype":"venue"
},
  "geometry": {"coordinates":[10.9232254028,57.2928199768],"type":"Point"}
}