{
  "type": "Feature",
  "properties": {
    "iso:country":"DK",
    "sg:address":"Falkevej 12",
    "sg:city":"Ribe",
    "sg:orig_category":"Sengeudstyr",
    "sg:phone":"+45 75 41 10 48",
    "sg:postcode":"6760",
    "sg:province":"Danmark",
    "wof:name":"Sterns Sengemilj\u00f8",
    "wof:placetype":"venue"
},
  "geometry": {"coordinates":[8.781541,55.34045],"type":"Point"}
}