{
  "type": "Feature",
  "properties": {
    "iso:country":"DK",
    "sg:address":"Fmd.: Bjarne Kj\u00e6rgaard, Danmarksgade 10",
    "sg:city":"Skjern",
    "sg:orig_category":"Spejderkorps",
    "sg:phone":"+45 97 35 18 46",
    "sg:postcode":"6900",
    "sg:province":"Danmark",
    "wof:name":"FDF, Skjern",
    "wof:placetype":"venue"
},
  "geometry": {"coordinates":[8.492972374,55.9485740662],"type":"Point"}
}