{
  "type": "Feature",
  "properties": {
    "addr:full":"Kirketorvet 16 Vordingborg Danmark 4760",
    "addr:housenumber":"16",
    "addr:postcode":"4760",
    "addr:street":"Kirketorvet",
    "iso:country":"DK",
    "sg:address":"Kirketorvet 16",
    "sg:city":"Vordingborg",
    "sg:orig_category":"Dommerkontorer",
    "sg:phone":"+45 55 36 17 00",
    "sg:postcode":"4760",
    "sg:province":"Danmark",
    "wof:name":"Dommerkontoret",
    "wof:placetype":"venue"
},
  "geometry": {"coordinates":[11.9068336487,55.0087242126],"type":"Point"}
}