{
  "type": "Feature",
  "properties": {
    "addr:full":"Fmd.: Henning Juhl, Parkall\u00e9 45 Tarm Danmark 6880",
    "addr:housenumber":"45",
    "addr:postcode":"6880",
    "addr:street":"Juhl Parkalle\u0301",
    "iso:country":"DK",
    "sg:address":"Fmd.: Henning Juhl, Parkall\u00e9 45",
    "sg:city":"Tarm",
    "sg:orig_category":"Kirkelige foreninger",
    "sg:phone":"+45 97 37 24 85",
    "sg:postcode":"6880",
    "sg:province":"Danmark",
    "wof:name":"Luthersk Missionsforening Tarm",
    "wof:placetype":"venue"
},
  "geometry": {"coordinates":[8.5200052261,55.9060554504],"type":"Point"}
}