{
  "type": "Feature",
  "properties": {
    "iso:country":"DK",
    "sg:address":"Rolighed 12",
    "sg:city":"Sor\u00f8",
    "sg:classifiers":[
        {
            "category":"Personal",
            "subcategory":"Massage",
            "type":"Services"
        }
    ],
    "sg:phone":"+45 57 82 11 78",
    "sg:postcode":"4180",
    "sg:province":"Danmark",
    "wof:name":"Klinik for Krop & Sj\u00e6l",
    "wof:placetype":"venue"
},
  "geometry": {"coordinates":[-102.94467926030001,45.4534721375],"type":"Point"}
}