{
  "type": "Feature",
  "properties": {
    "addr:full":"Fmd.: Hans Thomsen, Dalgasvej 3 Viuf Danmark 6052",
    "addr:housenumber":"3",
    "addr:postcode":"6052",
    "addr:street":"Dalgasvej",
    "iso:country":"DK",
    "sg:address":"Fmd.: Hans Thomsen, Dalgasvej 3",
    "sg:city":"Viuf",
    "sg:orig_category":"Antenneforeninger",
    "sg:phone":"+45 75 56 17 90",
    "sg:postcode":"6052",
    "sg:province":"Danmark",
    "wof:name":"Viuf Antenneforening",
    "wof:placetype":"venue"
},
  "geometry": {"coordinates":[9.4936685562,55.5897674561],"type":"Point"}
}