{
  "type": "Feature",
  "properties": {
    "addr:full":"Naurbjergvej 62 B Havdrup Danmark 4622",
    "addr:housenumber":"62 b",
    "addr:postcode":"4622",
    "addr:street":"Naurbjergvej",
    "iso:country":"DK",
    "sg:address":"Naurbjergvej 62 B",
    "sg:city":"Havdrup",
    "sg:classifiers":[
        {
            "category":"Personal",
            "subcategory":"Psychics & Astrologers",
            "type":"Services"
        }
    ],
    "sg:phone":"+45 46 18 03 83",
    "sg:postcode":"4622",
    "sg:province":"Danmark",
    "sg:tags":[
        "clairvoyance"
    ],
    "wof:name":"Fairy, Jeanne",
    "wof:placetype":"venue"
},
  "geometry": {"coordinates":[12.1159238815,55.5303535461],"type":"Point"}
}