{
  "type": "Feature",
  "properties": {
    "addr:full":"Vestergade 67 A N\u00f8rresundby Danmark 9400",
    "addr:housenumber":"67 a",
    "addr:postcode":"9400",
    "addr:street":"Vestergade",
    "iso:country":"DK",
    "sg:address":"Vestergade 67 A",
    "sg:city":"N\u00f8rresundby",
    "sg:orig_category":"Diners transportables",
    "sg:phone":"+45 98 19 40 50",
    "sg:postcode":"9400",
    "sg:province":"Danmark",
    "wof:name":"Maxwell Diner Transportable",
    "wof:placetype":"venue"
},
  "geometry": {"coordinates":[9.5455904007,56.1682090759],"type":"Point"}
}