{
  "type": "Feature",
  "properties": {
    "addr:full":"Fmd.: Viktor Hedegaard, Vibevej 32, Borbjerg Holstebro Danmark 7500",
    "addr:housenumber":"32",
    "addr:postcode":"7500",
    "addr:street":"Vibevej",
    "iso:country":"DK",
    "sg:address":"Fmd.: Viktor Hedegaard, Vibevej 32, Borbjerg",
    "sg:city":"Holstebro",
    "sg:orig_category":"Kulturelle foreninger",
    "sg:phone":"+45 97 46 10 03",
    "sg:postcode":"7500",
    "sg:province":"Danmark",
    "wof:name":"Holstebro Museumsforening",
    "wof:placetype":"venue"
},
  "geometry": {"coordinates":[8.6202583313,56.3625221252],"type":"Point"}
}