{
  "type": "Feature",
  "properties": {
    "addr:full":"Fmd.: Stig Erskov, Fyrrev\u00e6nget 4, Radsted Saksk\u00f8bing Danmark 4990",
    "addr:housenumber":"4",
    "addr:postcode":"4990",
    "addr:street":"Fmd. Stig Erskov Fyrrevaenget",
    "iso:country":"DK",
    "sg:address":"Fmd.: Stig Erskov, Fyrrev\u00e6nget 4, Radsted",
    "sg:city":"Saksk\u00f8bing",
    "sg:orig_category":"Kulturelle foreninger",
    "sg:phone":"+45 54 70 68 25",
    "sg:postcode":"4990",
    "sg:province":"Danmark",
    "wof:name":"\u00d8stofte Stubm\u00f8lles M\u00f8llelaug",
    "wof:placetype":"venue"
},
  "geometry": {"coordinates":[11.6875448227,54.7894821167],"type":"Point"}
}