{
  "type": "Feature",
  "properties": {
    "addr:full":"Fmd.: Jens Poulsen, Margueritvej 2 Sindal Danmark 9870",
    "addr:housenumber":"2",
    "addr:postcode":"9870",
    "addr:street":"Margueritvej",
    "iso:country":"DK",
    "sg:address":"Fmd.: Jens Poulsen, Margueritvej 2",
    "sg:city":"Sindal",
    "sg:orig_category":"Spejderkorps",
    "sg:phone":"+45 98 93 62 34",
    "sg:postcode":"9870",
    "sg:province":"Danmark",
    "wof:name":"Spejderkorps - 1. Sindal gruppe, Det Danske",
    "wof:placetype":"venue"
},
  "geometry": {"coordinates":[10.2032299042,57.470916748],"type":"Point"}
}