{
  "type": "Feature",
  "properties": {
    "addr:full":"Ellehammersvej 17 Vadum Danmark 9430",
    "addr:housenumber":"17",
    "addr:postcode":"9430",
    "addr:street":"Ellehammersvej",
    "iso:country":"DK",
    "sg:address":"Ellehammersvej 17",
    "sg:city":"Vadum",
    "sg:classifiers":[
        {
            "category":"Communications",
            "type":"Services"
        }
    ],
    "sg:phone":"+45 98 27 17 49",
    "sg:postcode":"9430",
    "sg:province":"Danmark",
    "sg:tags":[
        "og",
        "tv",
        "radio"
    ],
    "sg:website":"www.peradio@pc.dk",
    "wof:name":"Poul Erik's Radio",
    "wof:placetype":"venue"
},
  "geometry": {"coordinates":[9.8577842712,57.1131668091],"type":"Point"}
}