{
  "type": "Feature",
  "properties": {
    "addr:full":"v/Michael Dyhm, Odensegade 20 K\u00f8benhavn \u00d8 Danmark 2100",
    "addr:housenumber":"20",
    "addr:postcode":"2100",
    "addr:street":"Odensegade;O",
    "iso:country":"DK",
    "sg:address":"v/Michael Dyhm, Odensegade 20",
    "sg:city":"K\u00f8benhavn \u00d8",
    "sg:orig_category":"Gulvbehandling",
    "sg:phone":"+45 35 38 49 14",
    "sg:postcode":"2100",
    "sg:province":"Danmark",
    "wof:name":"M.D. Gulvservice",
    "wof:placetype":"venue"
},
  "geometry": {"coordinates":[-90.62181854249999,39.24477005],"type":"Point"}
}