{
  "type": "Feature",
  "properties": {
    "iso:country":"DK",
    "sg:address":"Vibevej 14",
    "sg:city":"Terndrup",
    "sg:orig_category":"Haveservice",
    "sg:phone":"+45 98 33 59 39",
    "sg:postcode":"9575",
    "sg:province":"Danmark",
    "wof:name":"Terndrup Hus- og haveservice",
    "wof:placetype":"venue"
},
  "geometry": {"coordinates":[10.0641479492,56.8143959045],"type":"Point"}
}