{
  "type": "Feature",
  "properties": {
    "addr:full":"Holme M\u00f8llevej 14 Viby Danmark 8260",
    "addr:housenumber":"14",
    "addr:postcode":"8260",
    "addr:street":"Mollevej",
    "iso:country":"DK",
    "sg:address":"Holme M\u00f8llevej 14",
    "sg:city":"Viby",
    "sg:orig_category":"Malermestre",
    "sg:phone":"+45 86 11 81 66",
    "sg:postcode":"8260",
    "sg:province":"Danmark",
    "wof:name":"Elgaard Malerfirma, Bent",
    "wof:placetype":"venue"
},
  "geometry": {"coordinates":[10.1717090607,56.1237068176],"type":"Point"}
}