{
  "type": "Feature",
  "properties": {
    "addr:full":"Hundige Storcenter 2 B, 1. Greve Danmark 2670",
    "addr:housenumber":"2 b 1",
    "addr:postcode":"2670",
    "addr:street":"Storcenter",
    "iso:country":"DK",
    "sg:address":"Hundige Storcenter 2 B, 1.",
    "sg:city":"Greve",
    "sg:orig_category":"Psykologer, praktiserende",
    "sg:phone":"+45 20 74 21 28",
    "sg:postcode":"2670",
    "sg:province":"Danmark",
    "wof:name":"St\u00f8vring, Erik Cand. psych.",
    "wof:placetype":"venue"
},
  "geometry": {"coordinates":[12.3270778656,55.5990715027],"type":"Point"}
}