{
  "type": "Feature",
  "properties": {
    "addr:full":"Hjulsporet 4 Maribo Danmark 4930",
    "addr:housenumber":"4",
    "addr:postcode":"4930",
    "addr:street":"Hjulsporet",
    "iso:country":"DK",
    "sg:address":"Hjulsporet 4",
    "sg:city":"Maribo",
    "sg:orig_category":"Autoreparation og -service",
    "sg:phone":"+45 54 78 25 84",
    "sg:postcode":"4930",
    "sg:province":"Danmark",
    "wof:name":"Jan's Autoservice",
    "wof:placetype":"venue"
},
  "geometry": {"coordinates":[11.5113353729,54.7768745422],"type":"Point"}
}