{
  "type": "Feature",
  "properties": {
    "addr:full":"Gavn\u00f8vej 2 B, Tj\u00f8rring Herning Danmark 7400",
    "addr:housenumber":"2 b",
    "addr:postcode":"7400",
    "addr:street":"Gavnovej;Tjorring",
    "iso:country":"DK",
    "sg:address":"Gavn\u00f8vej 2 B, Tj\u00f8rring",
    "sg:city":"Herning",
    "sg:orig_category":"EDB - udstyr",
    "sg:phone":"+45 97 26 99 88",
    "sg:postcode":"7400",
    "sg:province":"Danmark",
    "wof:name":"Concept Data",
    "wof:placetype":"venue"
},
  "geometry": {"coordinates":[8.9768896103,56.1374168396],"type":"Point"}
}