{
  "type": "Feature",
  "properties": {
    "addr:full":"v/ Ninna Lerager, Tjele Skovvej 3, Tjele Tjele Danmark 8830",
    "addr:housenumber":"3",
    "addr:postcode":"8830",
    "addr:street":"Lerager Tjele Skovvej",
    "iso:country":"DK",
    "sg:address":"v/ Ninna Lerager, Tjele Skovvej 3, Tjele",
    "sg:city":"Tjele",
    "sg:orig_category":"Forsamlingshuse",
    "sg:phone":"+45 86 65 31 38",
    "sg:postcode":"8830",
    "sg:province":"Danmark",
    "wof:name":"\u00d8rum Forsamlingshus",
    "wof:placetype":"venue"
},
  "geometry": {"coordinates":[9.6264801025,56.4818611145],"type":"Point"}
}