{
  "type": "Feature",
  "properties": {
    "addr:full":"Centrumpladsen 18 - 19 Svendborg Danmark 5700",
    "addr:housenumber":"18 19",
    "addr:postcode":"5700",
    "addr:street":"Centrumpladsen",
    "iso:country":"DK",
    "sg:address":"Centrumpladsen 18 - 19",
    "sg:city":"Svendborg",
    "sg:orig_category":"Sparekasser",
    "sg:phone":"+45 62 21 33 22",
    "sg:postcode":"5700",
    "sg:province":"Danmark",
    "wof:name":"Svendborg Sparekasse",
    "wof:placetype":"venue"
},
  "geometry": {"coordinates":[10.6068305969,55.0596160889],"type":"Point"}
}