{
  "type": "Feature",
  "properties": {
    "iso:country":"DK",
    "sg:address":"Alsgade 70",
    "sg:city":"S\u00f8nderborg",
    "sg:orig_category":"Autoreparation og -service",
    "sg:phone":"+45 74 42 47 31",
    "sg:postcode":"6400",
    "sg:province":"Danmark",
    "wof:name":"Christensen, N.P.",
    "wof:placetype":"venue"
},
  "geometry": {"coordinates":[9.8065252304,54.9186515808],"type":"Point"}
}