{
  "type": "Feature",
  "properties": {
    "iso:country":"DK",
    "sg:address":"Hammervej 2",
    "sg:city":"Ulstrup",
    "sg:orig_category":"Levnedsmidler",
    "sg:phone":"+45 86 46 37 00",
    "sg:postcode":"8860",
    "sg:province":"Danmark",
    "wof:name":"Domus Aromatica ApS",
    "wof:placetype":"venue"
},
  "geometry": {"coordinates":[9.7742061615,56.3723335266],"type":"Point"}
}