{
  "type": "Feature",
  "properties": {
    "addr:full":"B\u00f8gekildevej 18 Hasselager Danmark 8361",
    "addr:housenumber":"18",
    "addr:postcode":"8361",
    "addr:street":"Bogekildevej",
    "iso:country":"DK",
    "sg:address":"B\u00f8gekildevej 18",
    "sg:city":"Hasselager",
    "sg:orig_category":"Campingudstyr",
    "sg:phone":"+45 86 28 39 33",
    "sg:postcode":"8361",
    "sg:province":"Danmark",
    "sg:website":"www.ostjysk-caravan.dk",
    "wof:name":"\u00d8stjysk Caravan",
    "wof:placetype":"venue"
},
  "geometry": {"coordinates":[10.0892629623,56.1034469604],"type":"Point"}
}