{
  "type": "Feature",
  "properties": {
    "addr:full":"Meldahlsgade 2 K\u00f8benhavn Danmark 1613",
    "addr:housenumber":"2",
    "addr:postcode":"1613",
    "addr:street":"Meldahlsgade",
    "iso:country":"DK",
    "sg:address":"Meldahlsgade 2",
    "sg:city":"K\u00f8benhavn",
    "sg:orig_category":"Fodterapeuter",
    "sg:phone":"+45 33 15 34 07",
    "sg:postcode":"1613",
    "sg:province":"Danmark",
    "wof:name":"Klinik for Fodterapi Buen",
    "wof:placetype":"venue"
},
  "geometry": {"coordinates":[12.5614004135,55.6745300293],"type":"Point"}
}