{
  "type": "Feature",
  "properties": {
    "addr:full":"Hulsigvej 2, Hulsig Skagen Danmark 9990",
    "addr:housenumber":"2",
    "addr:postcode":"9990",
    "addr:street":"Hulsigvej",
    "iso:country":"DK",
    "sg:address":"Hulsigvej 2, Hulsig",
    "sg:city":"Skagen",
    "sg:orig_category":"Kirker",
    "sg:postcode":"9990",
    "sg:province":"Danmark",
    "wof:name":"Hulsig Kirke",
    "wof:placetype":"venue"
},
  "geometry": {"coordinates":[10.5958003998,57.7247200012],"type":"Point"}
}