{
  "type": "Feature",
  "properties": {
    "iso:country":"DK",
    "sg:address":"N\u00f8rregade 10",
    "sg:city":"Hirtshals",
    "sg:orig_category":"Blomsterhandlere",
    "sg:phone":"+45 98 94 60 33",
    "sg:postcode":"9850",
    "sg:province":"Danmark",
    "wof:name":"N\u00f8rregades Blomster",
    "wof:placetype":"venue"
},
  "geometry": {"coordinates":[9.9574298859,57.589881897],"type":"Point"}
}