{
  "type": "Feature",
  "properties": {
    "addr:full":"Skoleleder: Karen Lindberg, Vestergade 1, 1.tv. Helsinge Danmark 3200",
    "addr:housenumber":"1",
    "addr:postcode":"1.tv;3200",
    "addr:street":"Vestergade",
    "iso:country":"DK",
    "sg:address":"Skoleleder: Karen Lindberg, Vestergade 1, 1.tv.",
    "sg:city":"Helsinge",
    "sg:orig_category":"Oplysningsforbund",
    "sg:phone":"+45 48 79 71 75",
    "sg:postcode":"3200",
    "sg:province":"Danmark",
    "sg:website":"www.fof-helsinge.dk",
    "wof:name":"FOF Folkeligt Oplysnings Forbund",
    "wof:placetype":"venue"
},
  "geometry": {"coordinates":[12.196846962,56.0224456787],"type":"Point"}
}