{
  "type": "Feature",
  "properties": {
    "iso:country":"DK",
    "sg:address":"N\u00f8rreskiftevej 9, Brundby",
    "sg:city":"Sams\u00f8",
    "sg:orig_category":"Dag- og distriktsblade",
    "sg:phone":"+45 86 59 07 26",
    "sg:postcode":"8305",
    "sg:province":"Danmark",
    "wof:name":"\u00c5rhus Stiftstidende",
    "wof:placetype":"venue"
},
  "geometry": {"coordinates":[10.5885000229,55.8320198059],"type":"Point"}
}