{
  "type": "Feature",
  "properties": {
    "iso:country":"DK",
    "sg:address":"Fmd.: Ruth Wolf, Hornsh\u00f8jvej 43, Klokkerholm",
    "sg:city":"Hjallerup",
    "sg:orig_category":"Kirkelige foreninger",
    "sg:phone":"+45 98 28 42 48",
    "sg:postcode":"9320",
    "sg:province":"Danmark",
    "wof:name":"Indre Missions Samfund i Hjallerup",
    "wof:placetype":"venue"
},
  "geometry": {"coordinates":[10.1444702148,57.1677742004],"type":"Point"}
}