{
  "type": "Feature",
  "properties": {
    "addr:full":"Fmd.: Carl Olesen, M\u00e5gevej 1 Jyderup Danmark 4450",
    "addr:housenumber":"1",
    "addr:postcode":"4450",
    "addr:street":"Carl Olesen Maagevej",
    "iso:country":"DK",
    "sg:address":"Fmd.: Carl Olesen, M\u00e5gevej 1",
    "sg:city":"Jyderup",
    "sg:orig_category":"Hobbybetonede foreninger",
    "sg:phone":"+45 59 27 66 88",
    "sg:postcode":"4450",
    "sg:province":"Danmark",
    "wof:name":"St\u00f8tteforeningen Jyderup Fodbold",
    "wof:placetype":"venue"
},
  "geometry": {"coordinates":[11.4029512405,55.6602401733],"type":"Point"}
}