{
  "type": "Feature",
  "properties": {
    "addr:full":"Aalborgvej 1 Terndrup Danmark 9575",
    "addr:housenumber":"1",
    "addr:postcode":"9575",
    "addr:street":"Aalborgvej;Danmark",
    "iso:country":"DK",
    "sg:address":"Aalborgvej 1",
    "sg:city":"Terndrup",
    "sg:orig_category":"Apoteker og -udsalg",
    "sg:phone":"+45 98 33 50 04",
    "sg:postcode":"9575",
    "sg:province":"Danmark",
    "wof:name":"Apoteksudsalget i Terndrup",
    "wof:placetype":"venue"
},
  "geometry": {"coordinates":[10.0581827164,56.8157844543],"type":"Point"}
}