{
  "type": "Feature",
  "properties": {
    "iso:country":"DK",
    "sg:address":"R\u00e5dhustorvet 1",
    "sg:city":"Farum",
    "sg:classifiers":[
        {
            "category":"Banks & Credit Unions",
            "subcategory":"Bank",
            "type":"Services"
        }
    ],
    "sg:phone":"+45 44 34 05 50",
    "sg:postcode":"3520",
    "sg:province":"Danmark",
    "sg:tags":[
        "banker"
    ],
    "wof:name":"BG Bank A/S",
    "wof:placetype":"venue"
},
  "geometry": {"coordinates":[12.376458,55.814976],"type":"Point"}
}