{
  "type": "Feature",
  "properties": {
    "addr:full":"Lagonis Minde 20 Faaborg Danmark 5600",
    "addr:housenumber":"20",
    "addr:postcode":"5600",
    "addr:street":"Lagonis Minde",
    "iso:country":"DK",
    "sg:address":"Lagonis Minde 20",
    "sg:city":"Faaborg",
    "sg:orig_category":"Fabrikker",
    "sg:phone":"+45 62 61 16 56",
    "sg:postcode":"5600",
    "sg:province":"Danmark",
    "wof:name":"Fiona",
    "wof:placetype":"venue"
},
  "geometry": {"coordinates":[10.2408685684,55.0990715027],"type":"Point"}
}