{
  "type": "Feature",
  "properties": {
    "addr:full":"Snorresgade 18-20 K\u00f8benhavn S Danmark 2300",
    "addr:housenumber":"18-20",
    "addr:postcode":"2300",
    "addr:street":"Snorresgade;Kobenhavn S Danmark",
    "iso:country":"DK",
    "sg:address":"Snorresgade 18-20",
    "sg:city":"K\u00f8benhavn S",
    "sg:orig_category":"Rederier",
    "sg:phone":"+45 32 66 81 00",
    "sg:postcode":"2300",
    "sg:province":"Danmark",
    "wof:name":"Scan-Shipping A/S",
    "wof:placetype":"venue"
},
  "geometry": {"coordinates":[-82.57545471189999,38.4224014282],"type":"Point"}
}