{
  "type": "Feature",
  "properties": {
    "addr:full":"Flegborg 2 A Vejle Danmark 7100",
    "addr:housenumber":"2 a",
    "addr:postcode":"7100",
    "addr:street":"Flegborg",
    "iso:country":"DK",
    "sg:address":"Flegborg 2 A",
    "sg:city":"Vejle",
    "sg:orig_category":"Vikarbureauer",
    "sg:phone":"+45 75 72 72 37",
    "sg:postcode":"7100",
    "sg:province":"Danmark",
    "wof:name":"Trekantens Vikar Service ApS",
    "wof:placetype":"venue"
},
  "geometry": {"coordinates":[9.5331277847,55.7099723816],"type":"Point"}
}