{
  "type": "Feature",
  "properties": {
    "iso:country":"DK",
    "sg:address":"Fmd.: Kaj D. Nielsen, Chr. Andersens Vej 23",
    "sg:city":"Gram",
    "sg:orig_category":"Kirkelige foreninger",
    "sg:phone":"+45 74 82 30 77",
    "sg:postcode":"6510",
    "sg:province":"Danmark",
    "wof:name":"Indre Mission i Gram",
    "wof:placetype":"venue"
},
  "geometry": {"coordinates":[9.048166275,55.2940940857],"type":"Point"}
}