{
  "type": "Feature",
  "properties": {
    "iso:country":"DK",
    "sg:address":"Fuglehavevej 1",
    "sg:city":"Ballerup",
    "sg:orig_category":"Arkitekter",
    "sg:phone":"+45 44 97 80 17",
    "sg:postcode":"2750",
    "sg:province":"Danmark",
    "wof:name":"Gram, Erik",
    "wof:placetype":"venue"
},
  "geometry": {"coordinates":[12.3528699875,55.7527618408],"type":"Point"}
}