{
  "type": "Feature",
  "properties": {
    "addr:full":"Industrivej 16 Gram Danmark 6510",
    "addr:housenumber":"16",
    "addr:postcode":"6510",
    "addr:street":"Industrivej",
    "iso:country":"DK",
    "sg:address":"Industrivej 16",
    "sg:city":"Gram",
    "sg:orig_category":"Autoophug",
    "sg:phone":"+45 74 82 17 17",
    "sg:postcode":"6510",
    "sg:province":"Danmark",
    "wof:name":"Citroen Ophug",
    "wof:placetype":"venue"
},
  "geometry": {"coordinates":[9.0424947739,55.2814559937],"type":"Point"}
}