{
  "type": "Feature",
  "properties": {
    "addr:full":"Industrivej 5  Skjern Danmark 6900",
    "addr:housenumber":"5",
    "addr:postcode":"6900",
    "addr:street":"Industrivej",
    "iso:country":"DK",
    "sg:address":"Industrivej 5 ",
    "sg:city":"Skjern",
    "sg:classifiers":[
        {
            "category":"Parking",
            "subcategory":"Lot",
            "type":"Transportation"
        }
    ],
    "sg:phone":"+45 97 35 05 88",
    "sg:postcode":"6900",
    "sg:province":"Danmark",
    "sg:tags":[
        "transport",
        "road"
    ],
    "wof:name":"J M JENSEN SKJERN APS",
    "wof:placetype":"venue"
},
  "geometry": {"coordinates":[8.4909305573,55.9567985535],"type":"Point"}
}