{
  "type": "Feature",
  "properties": {
    "addr:full":"Absalonsgade 1 Sor\u00f8 Danmark 4180",
    "addr:housenumber":"1",
    "addr:postcode":"4180",
    "addr:street":"Absalonsgade",
    "iso:country":"DK",
    "sg:address":"Absalonsgade 1",
    "sg:city":"Sor\u00f8",
    "sg:orig_category":"Dag- og distriktsblade",
    "sg:phone":"+45 57 83 15 60",
    "sg:postcode":"4180",
    "sg:province":"Danmark",
    "wof:name":"Dagbladet Sor\u00f8",
    "wof:placetype":"venue"
},
  "geometry": {"coordinates":[11.5579576492,55.4347457886],"type":"Point"}
}