{
  "type": "Feature",
  "properties": {
    "iso:country":"DK",
    "sg:address":"Svendborgvej 49, Ollerup",
    "sg:city":"Vester Skerninge",
    "sg:orig_category":"Engros handel",
    "sg:phone":"+45 63 24 60 00",
    "sg:postcode":"5762",
    "sg:province":"Danmark",
    "wof:name":"K\u00fchne Scandinavia A/S",
    "wof:placetype":"venue"
},
  "geometry": {"coordinates":[10.5008449554,55.070400238],"type":"Point"}
}