{
  "type": "Feature",
  "properties": {
    "addr:full":"Fmd.: A. Hagdrup, Randtofte S\u00f8vej 14 Greve Danmark 2670",
    "addr:housenumber":"14",
    "addr:postcode":"2670",
    "addr:street":"Sovej",
    "iso:country":"DK",
    "sg:address":"Fmd.: A. Hagdrup, Randtofte S\u00f8vej 14",
    "sg:city":"Greve",
    "sg:orig_category":"Grundejerforeninger",
    "sg:phone":"+45 43 90 41 62",
    "sg:postcode":"2670",
    "sg:province":"Danmark",
    "wof:name":"Randtofte Strand- og Vejlaug",
    "wof:placetype":"venue"
},
  "geometry": {"coordinates":[12.2941808701,55.5844078064],"type":"Point"}
}