{
  "type": "Feature",
  "properties": {
    "addr:full":"Udlejning: Kjeld Mathiasen, Klapskovvej 12, Tinning Hinnerup Danmark 8382",
    "addr:housenumber":"12",
    "addr:postcode":"8382",
    "addr:street":"Klapskovvej;Tinning",
    "iso:country":"DK",
    "sg:address":"Udlejning: Kjeld Mathiasen, Klapskovvej 12, Tinning",
    "sg:city":"Hinnerup",
    "sg:orig_category":"Forsamlingshuse",
    "sg:phone":"+45 86 98 61 39",
    "sg:postcode":"8382",
    "sg:province":"Danmark",
    "wof:name":"Tinning Forsamlingshus",
    "wof:placetype":"venue"
},
  "geometry": {"coordinates":[10.0614156723,56.2650604248],"type":"Point"}
}