{
  "type": "Feature",
  "properties": {
    "addr:full":"Vibensholmsvej 9, Fredtofte Kokkedal Danmark 2980",
    "addr:housenumber":"9",
    "addr:postcode":"2980",
    "addr:street":"Vibensholmsvej;Fredtofte",
    "iso:country":"DK",
    "sg:address":"Vibensholmsvej 9, Fredtofte",
    "sg:city":"Kokkedal",
    "sg:orig_category":"Planteskoler",
    "sg:phone":"+45 48 28 02 76",
    "sg:postcode":"2980",
    "sg:province":"Danmark",
    "wof:name":"Cassias' Planteskole",
    "wof:placetype":"venue"
},
  "geometry": {"coordinates":[12.4769096375,55.9091339111],"type":"Point"}
}