{
  "type": "Feature",
  "properties": {
    "addr:full":"Ravnsbjergvej 6 Esbjerg V Danmark 6710",
    "addr:housenumber":"6",
    "addr:postcode":"6710",
    "addr:street":"Ravnsbjergvej",
    "iso:country":"DK",
    "sg:address":"Ravnsbjergvej 6",
    "sg:city":"Esbjerg V",
    "sg:orig_category":"Kirker",
    "sg:phone":"+45 75 16 77 61",
    "sg:postcode":"6710",
    "sg:province":"Danmark",
    "wof:name":"Baptistkirken",
    "wof:placetype":"venue"
},
  "geometry": {"coordinates":[8.4350786209,55.5261001587],"type":"Point"}
}