{
  "type": "Feature",
  "properties": {
    "addr:full":"R\u00f8nnesholm 2 Slagelse Danmark 4200",
    "addr:housenumber":"2",
    "addr:postcode":"4200",
    "addr:street":"Ronnesholm",
    "iso:country":"DK",
    "sg:address":"R\u00f8nnesholm 2",
    "sg:city":"Slagelse",
    "sg:orig_category":"Fotografer",
    "sg:phone":"+45 58 26 71 33",
    "sg:postcode":"4200",
    "sg:province":"Danmark",
    "wof:name":"C.H.M. Foto",
    "wof:placetype":"venue"
},
  "geometry": {"coordinates":[11.3732833862,55.4606742859],"type":"Point"}
}