{
  "type": "Feature",
  "properties": {
    "iso:country":"DK",
    "sg:address":"Nygade 28",
    "sg:city":"Silkeborg",
    "sg:orig_category":"Helseprodukter",
    "sg:phone":"+45 86 81 22 66",
    "sg:postcode":"8600",
    "sg:province":"Danmark",
    "wof:name":"Heksekosten",
    "wof:placetype":"venue"
},
  "geometry": {"coordinates":[9.5463933945,56.1671714783],"type":"Point"}
}