{
  "type": "Feature",
  "properties": {
    "addr:full":"Horsensvej 66 Vodskov Danmark 9310",
    "addr:housenumber":"66",
    "addr:postcode":"9310",
    "addr:street":"Horsensvej",
    "iso:country":"DK",
    "sg:address":"Horsensvej 66",
    "sg:city":"Vodskov",
    "sg:orig_category":"Maskinstationer",
    "sg:phone":"+45 98 25 64 88",
    "sg:postcode":"9310",
    "sg:province":"Danmark",
    "wof:name":"Langholt Maskinstation",
    "wof:placetype":"venue"
},
  "geometry": {"coordinates":[10.0674591064,57.094455719],"type":"Point"}
}