{
  "type": "Feature",
  "properties": {
    "addr:full":"Bjerreg\u00e5rdsvej 16 Valby Danmark 2500",
    "addr:housenumber":"16",
    "addr:postcode":"2500",
    "addr:street":"Bjerregaardsvej",
    "iso:country":"DK",
    "sg:address":"Bjerreg\u00e5rdsvej 16",
    "sg:city":"Valby",
    "sg:orig_category":"Foreninger og organisationer",
    "sg:phone":"+45 36 17 23 00",
    "sg:postcode":"2500",
    "sg:province":"Danmark",
    "sg:website":"www.bkd.dk",
    "wof:name":"Bager & Konditormestre i Danmark",
    "wof:placetype":"venue"
},
  "geometry": {"coordinates":[12.5277051926,55.6643028259],"type":"Point"}
}