{
  "type": "Feature",
  "properties": {
    "addr:full":"Niels Ebbesens Vej 25 Frederiksberg Danmark 1911",
    "addr:housenumber":"25",
    "addr:postcode":"1911",
    "addr:street":"Niels Ebbesens Vej",
    "iso:country":"DK",
    "sg:address":"Niels Ebbesens Vej 25",
    "sg:city":"Frederiksberg",
    "sg:orig_category":"Psykoterapi",
    "sg:phone":"+45 33 25 05 63",
    "sg:postcode":"1911",
    "sg:province":"Danmark",
    "sg:website":"www.lyngbye.net",
    "wof:name":"Lyngbye, Paul",
    "wof:placetype":"venue"
},
  "geometry": {"coordinates":[12.5491313934,55.6783485413],"type":"Point"}
}