{
  "type": "Feature",
  "properties": {
    "addr:full":"Kontaktpers.: Gurli Hamann M\u00f8lgaard, Viborgvej 348, Bjergby Vinderup Danmark 7830",
    "addr:housenumber":"348",
    "addr:postcode":"7830",
    "addr:street":"Viborgvej;Bjergby",
    "iso:country":"DK",
    "sg:address":"Kontaktpers.: Gurli Hamann M\u00f8lgaard, Viborgvej 348, Bjergby",
    "sg:city":"Vinderup",
    "sg:orig_category":"Borger- og beboerforeninger",
    "sg:phone":"+45 97 45 23 30",
    "sg:postcode":"7830",
    "sg:province":"Danmark",
    "wof:name":"Bjergby og Omegns Borgerforening",
    "wof:placetype":"venue"
},
  "geometry": {"coordinates":[8.7796897888,56.482635498],"type":"Point"}
}