{
  "type": "Feature",
  "properties": {
    "addr:full":"Vestergade 9 Vildbjerg Danmark 7480",
    "addr:housenumber":"9",
    "addr:postcode":"7480",
    "addr:street":"Vestergade",
    "iso:country":"DK",
    "sg:address":"Vestergade 9",
    "sg:city":"Vildbjerg",
    "sg:orig_category":"Netcafeer",
    "sg:phone":"+45 97 13 11 45",
    "sg:postcode":"7480",
    "sg:province":"Danmark",
    "wof:name":"SID Internetcafe",
    "wof:placetype":"venue"
},
  "geometry": {"coordinates":[8.7652111053,56.1986312866],"type":"Point"}
}