{
  "type": "Feature",
  "properties": {
    "addr:full":"Gr\u00f8nsundsvej 318, Horbelev Horbelev Danmark 4871",
    "addr:housenumber":"318",
    "addr:postcode":"4871",
    "addr:street":"Gronsundsvej",
    "iso:country":"DK",
    "sg:address":"Gr\u00f8nsundsvej 318, Horbelev",
    "sg:city":"Horbelev",
    "sg:orig_category":"Plejehjem",
    "sg:phone":"+45 54 49 44 22",
    "sg:postcode":"4871",
    "sg:province":"Danmark",
    "wof:name":"Horbelev Plejehjem",
    "wof:placetype":"venue"
},
  "geometry": {"coordinates":[12.0557804108,54.8232345581],"type":"Point"}
}