{
  "type": "Feature",
  "properties": {
    "addr:full":"R\u00e5dhuscentret 11 Vojens Danmark 6500",
    "addr:housenumber":"11",
    "addr:postcode":"6500",
    "addr:street":"Raadhuscentret",
    "iso:country":"DK",
    "sg:address":"R\u00e5dhuscentret 11",
    "sg:city":"Vojens",
    "sg:orig_category":"Brugsforeninger",
    "sg:phone":"+45 74 54 11 36",
    "sg:postcode":"6500",
    "sg:province":"Danmark",
    "wof:name":"Kvickly",
    "wof:placetype":"venue"
},
  "geometry": {"coordinates":[9.2921257019,55.2462501526],"type":"Point"}
}