{
  "type": "Feature",
  "properties": {
    "iso:country":"DK",
    "sg:address":"Jernbanegade 31",
    "sg:city":"N\u00e6stved",
    "sg:orig_category":"Bodegaer",
    "sg:phone":"+45 55 77 44 06",
    "sg:postcode":"4700",
    "sg:province":"Danmark",
    "wof:name":"Tower Pub",
    "wof:placetype":"venue"
},
  "geometry": {"coordinates":[11.7655515671,55.2310829163],"type":"Point"}
}