{
  "type": "Feature",
  "properties": {
    "addr:full":"Nordre Industrivej 2 R\u00f8dding Danmark 6630",
    "addr:housenumber":"2",
    "addr:postcode":"6630",
    "addr:street":"Nordre Industrivej",
    "iso:country":"DK",
    "sg:address":"Nordre Industrivej 2",
    "sg:city":"R\u00f8dding",
    "sg:orig_category":"Fliser",
    "sg:phone":"+45 74 84 17 84",
    "sg:postcode":"6630",
    "sg:province":"Danmark",
    "wof:name":"Fliseimport\u00f8ren",
    "wof:placetype":"venue"
},
  "geometry": {"coordinates":[12.035369873,60.8038711548],"type":"Point"}
}