{
  "type": "Feature",
  "properties": {
    "addr:full":"S\u00f8ndergade 19 Kjellerup Danmark 8620",
    "addr:housenumber":"19",
    "addr:postcode":"8620",
    "addr:street":"Sondergade",
    "iso:country":"DK",
    "sg:address":"S\u00f8ndergade 19",
    "sg:city":"Kjellerup",
    "sg:orig_category":"Cafeterier",
    "sg:phone":"+45 86 88 29 44",
    "sg:postcode":"8620",
    "sg:province":"Danmark",
    "wof:name":"Torvecaf\u00e9en",
    "wof:placetype":"venue"
},
  "geometry": {"coordinates":[9.4310474396,56.2880973816],"type":"Point"}
}