{
  "type": "Feature",
  "properties": {
    "addr:full":"\u00c6blehaven 9 Egtved Danmark 6040",
    "addr:housenumber":"9",
    "addr:postcode":"6040",
    "addr:street":"Aeblehaven",
    "iso:country":"DK",
    "sg:address":"\u00c6blehaven 9",
    "sg:city":"Egtved",
    "sg:orig_category":"Fodplejere",
    "sg:phone":"+45 75 55 25 59",
    "sg:postcode":"6040",
    "sg:province":"Danmark",
    "wof:name":"Mariannes Fodklinik",
    "wof:placetype":"venue"
},
  "geometry": {"coordinates":[9.3181762695,55.6106910706],"type":"Point"}
}