{
  "type": "Feature",
  "properties": {
    "addr:full":"Fmd.: J\u00f8rgen Gammelgaard, Borup Tv\u00e6rvej 63, Borup Vr\u00e5 Danmark 9760",
    "addr:housenumber":"63",
    "addr:postcode":"9760",
    "addr:street":"Gammelgaard;Tvaervej",
    "iso:country":"DK",
    "sg:address":"Fmd.: J\u00f8rgen Gammelgaard, Borup Tv\u00e6rvej 63, Borup",
    "sg:city":"Vr\u00e5",
    "sg:orig_category":"Kulturelle foreninger",
    "sg:phone":"+45 98 98 22 39",
    "sg:postcode":"9760",
    "sg:province":"Danmark",
    "wof:name":"Flygtninge-venskabsforeningen",
    "wof:placetype":"venue"
},
  "geometry": {"coordinates":[-96.50723266599999,47.1803092957],"type":"Point"}
}