{
  "type": "Feature",
  "properties": {
    "addr:full":"Kongensgade 2 Kongerslev Danmark 9293",
    "addr:housenumber":"2",
    "addr:postcode":"9293",
    "addr:street":"Kongensgade",
    "iso:country":"DK",
    "sg:address":"Kongensgade 2",
    "sg:city":"Kongerslev",
    "sg:orig_category":"Skolefritidsordninger",
    "sg:phone":"+45 98 33 21 45",
    "sg:postcode":"9293",
    "sg:province":"Danmark",
    "wof:name":"Kongerslev skolefritidsordning",
    "wof:placetype":"venue"
},
  "geometry": {"coordinates":[10.1196107864,56.8895111084],"type":"Point"}
}