{
  "type": "Feature",
  "properties": {
    "iso:country":"DK",
    "sg:address":"Hovedgaden 16",
    "sg:city":"Svinninge",
    "sg:orig_category":"Kiosker",
    "sg:phone":"+45 59 26 50 83",
    "sg:postcode":"4520",
    "sg:province":"Danmark",
    "wof:name":"Skansen",
    "wof:placetype":"venue"
},
  "geometry": {"coordinates":[11.46737957,55.7230873108],"type":"Point"}
}