{
  "type": "Feature",
  "properties": {
    "addr:full":"Brandts Passage 29 Odense C Danmark 5000",
    "addr:housenumber":"29",
    "addr:postcode":"5000",
    "addr:street":"Brandts Passage",
    "iso:country":"DK",
    "sg:address":"Brandts Passage 29",
    "sg:city":"Odense C",
    "sg:orig_category":"Museer",
    "sg:phone":"+45 65 91 19 42",
    "sg:postcode":"5000",
    "sg:province":"Danmark",
    "sg:website":"www.tidenssamling.dk",
    "wof:name":"Tidens Samling",
    "wof:placetype":"venue"
},
  "geometry": {"coordinates":[10.3814601898,55.3954086304],"type":"Point"}
}