{
  "type": "Feature",
  "properties": {
    "addr:full":"Willumsens Alle 21 Karlslunde Danmark 2690",
    "addr:housenumber":"21",
    "addr:postcode":"2690",
    "addr:street":"Willumsens Alle",
    "iso:country":"DK",
    "sg:address":"Willumsens Alle 21",
    "sg:city":"Karlslunde",
    "sg:orig_category":"Konsulentvirksomheder",
    "sg:phone":"+45 46 15 30 43",
    "sg:postcode":"2690",
    "sg:province":"Danmark",
    "wof:name":"Stanley Brask, import-eksport",
    "wof:placetype":"venue"
},
  "geometry": {"coordinates":[12.2600278854,55.5689620972],"type":"Point"}
}