{
  "type": "Feature",
  "properties": {
    "addr:full":"Havnegade 30 Thybor\u00f8n Danmark 7680",
    "addr:housenumber":"30",
    "addr:postcode":"7680",
    "addr:street":"Havnegade",
    "iso:country":"DK",
    "sg:address":"Havnegade 30",
    "sg:city":"Thybor\u00f8n",
    "sg:orig_category":"Fiskeauktioner",
    "sg:phone":"+45 97 83 14 11",
    "sg:postcode":"7680",
    "sg:province":"Danmark",
    "wof:name":"Thybor\u00f8n Fiskeauktion A/S",
    "wof:placetype":"venue"
},
  "geometry": {"coordinates":[-94.46161651609999,47.8553733826],"type":"Point"}
}