{
  "type": "Feature",
  "properties": {
    "addr:full":"Risb\u00f8gevej 9 Brabrand Danmark 8220",
    "addr:housenumber":"9",
    "addr:postcode":"8220",
    "addr:street":"Risbogevej",
    "iso:country":"DK",
    "sg:address":"Risb\u00f8gevej 9",
    "sg:city":"Brabrand",
    "sg:orig_category":"Vinduespolering",
    "sg:phone":"+45 86 26 26 79",
    "sg:postcode":"8220",
    "sg:province":"Danmark",
    "wof:name":"Madsen, Henrik",
    "wof:placetype":"venue"
},
  "geometry": {"coordinates":[10.1146869659,56.1522216797],"type":"Point"}
}