{
  "type": "Feature",
  "properties": {
    "iso:country":"DK",
    "sg:address":"Hammersh\u00f8j 3, \u00d8land",
    "sg:city":"Brovst",
    "sg:orig_category":"Kommunale folkeskoler",
    "sg:phone":"+45 98 23 60 93",
    "sg:postcode":"9460",
    "sg:province":"Danmark",
    "wof:name":"Langeslund/\u00d8land Skole",
    "wof:placetype":"venue"
},
  "geometry": {"coordinates":[9.5220241547,57.097366333],"type":"Point"}
}