{
  "type": "Feature",
  "properties": {
    "addr:full":"Letland Alle 3  Taastrup Danmark 2630",
    "addr:housenumber":"3",
    "addr:postcode":"2630",
    "addr:street":"Letland Alle",
    "iso:country":"DK",
    "sg:address":"Letland Alle 3 ",
    "sg:city":"Taastrup",
    "sg:classifiers":[
        {
            "category":"Parking",
            "subcategory":"Lot",
            "type":"Transportation"
        }
    ],
    "sg:phone":"+45 43 58 77 77",
    "sg:postcode":"2630",
    "sg:province":"Danmark",
    "sg:tags":[
        "transport",
        "road"
    ],
    "wof:name":"DFN - DANSKE FRAGTM\u00c6NDS N\u00c6RDISTRIBUTION A/S",
    "wof:placetype":"venue"
},
  "geometry": {"coordinates":[12.2537622452,55.6372489929],"type":"Point"}
}