{
  "type": "Feature",
  "properties": {
    "addr:full":"Fmd.: Per M\u00f8ller, Ringdams Kobbel 28 Vejle Danmark 7100",
    "addr:housenumber":"28",
    "addr:postcode":"7100",
    "addr:street":"Ringdams Kobbel",
    "iso:country":"DK",
    "sg:address":"Fmd.: Per M\u00f8ller, Ringdams Kobbel 28",
    "sg:city":"Vejle",
    "sg:orig_category":"Kirkelige foreninger",
    "sg:phone":"+45 74 85 05 73",
    "sg:postcode":"7100",
    "sg:province":"Danmark",
    "wof:name":"Indre Mission i Vejle",
    "wof:placetype":"venue"
},
  "geometry": {"coordinates":[9.5525445938,55.7275924683],"type":"Point"}
}