{
  "type": "Feature",
  "properties": {
    "iso:country":"DK",
    "sg:address":"N\u00e6rumgade 16",
    "sg:city":"K\u00f8benhavn N",
    "sg:orig_category":"Alternativ behandling",
    "sg:phone":"+45 35 82 88 81",
    "sg:postcode":"2200",
    "sg:province":"Danmark",
    "sg:website":"www.africanhealing.com",
    "wof:name":"African Healingscenter",
    "wof:placetype":"venue"
},
  "geometry": {"coordinates":[-93.21099853520001,43.4552688599],"type":"Point"}
}