{
  "type": "Feature",
  "properties": {
    "addr:full":"Mejerivej 2, Bred Vissenbjerg Danmark 5492",
    "addr:housenumber":"2",
    "addr:postcode":"5492",
    "addr:street":"Mejerivej;Bred",
    "iso:country":"DK",
    "sg:address":"Mejerivej 2, Bred",
    "sg:city":"Vissenbjerg",
    "sg:orig_category":"Autoreparation og -service",
    "sg:phone":"+45 64 47 15 16",
    "sg:postcode":"5492",
    "sg:province":"Danmark",
    "wof:name":"P.J. Auto",
    "wof:placetype":"venue"
},
  "geometry": {"coordinates":[10.1324472427,55.386051178],"type":"Point"}
}