{
  "type": "Feature",
  "properties": {
    "addr:full":"Industrivej 11 D Padborg Danmark 6330",
    "addr:housenumber":"11 d",
    "addr:postcode":"6330",
    "addr:street":"Industrivej",
    "iso:country":"DK",
    "sg:address":"Industrivej 11 D",
    "sg:city":"Padborg",
    "sg:orig_category":"Grillbarer",
    "sg:phone":"+45 74 67 33 38",
    "sg:postcode":"6330",
    "sg:province":"Danmark",
    "wof:name":"Industrivejens Grillbar",
    "wof:placetype":"venue"
},
  "geometry": {"coordinates":[9.3504858017,54.8318443298],"type":"Point"}
}