{
  "type": "Feature",
  "properties": {
    "addr:full":"Danmarksgade 53 Esbjerg Danmark 6700",
    "addr:housenumber":"53",
    "addr:postcode":"6700",
    "addr:street":"Danmarksgade",
    "iso:country":"DK",
    "sg:address":"Danmarksgade 53",
    "sg:city":"Esbjerg",
    "sg:orig_category":"Kommunale folkeskoler",
    "sg:phone":"+45 79 15 73 00",
    "sg:postcode":"6700",
    "sg:province":"Danmark",
    "sg:website":"www.danmarksgade.esbjergskole.dk",
    "wof:name":"Danmarksgades Skole",
    "wof:placetype":"venue"
},
  "geometry": {"coordinates":[8.4505701065,55.4679679871],"type":"Point"}
}