{
  "type": "Feature",
  "properties": {
    "addr:full":"Fmd.: Lone Rosen\u00f8rn Jakobsen, Kasted Byvej 5, Kasted \u00c5rhus N Danmark 8200",
    "addr:housenumber":"5",
    "addr:postcode":"8200",
    "addr:street":"Rosenorn;Kasted Byvej;Kasted",
    "iso:country":"DK",
    "sg:address":"Fmd.: Lone Rosen\u00f8rn Jakobsen, Kasted Byvej 5, Kasted",
    "sg:city":"\u00c5rhus N",
    "sg:orig_category":"Borger- og beboerforeninger",
    "sg:phone":"+45 86 24 72 61",
    "sg:postcode":"8200",
    "sg:province":"Danmark",
    "wof:name":"Kasted og Omegns Beboerforening",
    "wof:placetype":"venue"
},
  "geometry": {"coordinates":[10.129070282,56.2068710327],"type":"Point"}
}