{
  "type": "Feature",
  "properties": {
    "iso:country":"DK",
    "sg:address":"Overholmvej 40",
    "sg:city":"Hedensted",
    "sg:orig_category":"Blomster og planter, kunstige",
    "sg:phone":"+45 75 89 22 66",
    "sg:postcode":"8722",
    "sg:province":"Danmark",
    "sg:website":"www.silkeplant.dk",
    "wof:name":"Silkeplant Danmark A/S",
    "wof:placetype":"venue"
},
  "geometry": {"coordinates":[9.69766,55.762039],"type":"Point"}
}