{
  "type": "Feature",
  "properties": {
    "addr:full":"Houmvej 2 Hemmet Danmark 6893",
    "addr:housenumber":"2",
    "addr:postcode":"6893",
    "addr:street":"Houmvej",
    "iso:country":"DK",
    "sg:address":"Houmvej 2",
    "sg:city":"Hemmet",
    "sg:orig_category":"Vinduespolering",
    "sg:phone":"+45 97 37 51 77",
    "sg:postcode":"6893",
    "sg:province":"Danmark",
    "wof:name":"Simmelsgaard, Peter Hartvig",
    "wof:placetype":"venue"
},
  "geometry": {"coordinates":[8.3495998383,55.8533706665],"type":"Point"}
}