{
  "type": "Feature",
  "properties": {
    "addr:full":"Ved Kildepladsen 4 Borup Danmark 4140",
    "addr:housenumber":"4",
    "addr:postcode":"4140",
    "addr:street":"Ved Kildepladsen",
    "iso:country":"DK",
    "sg:address":"Ved Kildepladsen 4",
    "sg:city":"Borup",
    "sg:orig_category":"Non-Classified Establishments",
    "sg:phone":"+45 57 52 66 05",
    "sg:postcode":"4140",
    "sg:province":"Danmark",
    "wof:name":"Malerklemmen - Tehandel",
    "wof:placetype":"venue"
},
  "geometry": {"coordinates":[11.9403858185,55.4686203003],"type":"Point"}
}