{
  "type": "Feature",
  "properties": {
    "addr:full":"v/ Ungdomsskolen, Holbergsvej 42, Postboks 23 Dianalund Danmark 4293",
    "addr:housenumber":"42;23",
    "addr:postcode":"4293",
    "addr:street":"Holbergsvej",
    "iso:country":"DK",
    "sg:address":"v/ Ungdomsskolen, Holbergsvej 42, Postboks 23",
    "sg:city":"Dianalund",
    "sg:orig_category":"Ungdomsklubber",
    "sg:phone":"+45 58 26 53 08",
    "sg:postcode":"4293",
    "sg:province":"Danmark",
    "wof:name":"Dianalund Ungdomsskoleklub",
    "wof:placetype":"venue"
},
  "geometry": {"coordinates":[11.4945745468,55.5332489014],"type":"Point"}
}