{
  "type": "Feature",
  "properties": {
    "iso:country":"DK",
    "sg:address":"Bredgade 15",
    "sg:city":"Lang\u00e5",
    "sg:orig_category":"Advokater",
    "sg:phone":"+45 86 46 18 99",
    "sg:postcode":"8870",
    "sg:province":"Danmark",
    "wof:name":"Engelbrechtsen, Carl Erik",
    "wof:placetype":"venue"
},
  "geometry": {"coordinates":[9.8950338364,56.3910980225],"type":"Point"}
}