{
  "type": "Feature",
  "properties": {
    "addr:full":"Belgiensvej 4 Nyk\u00f8bing Danmark 4800",
    "addr:housenumber":"4",
    "addr:postcode":"4800",
    "addr:street":"Belgiensvej",
    "iso:country":"DK",
    "sg:address":"Belgiensvej 4",
    "sg:city":"Nyk\u00f8bing",
    "sg:classifiers":[
        {
            "category":"Professional",
            "subcategory":"Art Services",
            "type":"Services"
        }
    ],
    "sg:phone":"+45 54 85 24 26",
    "sg:postcode":"4800",
    "sg:province":"Danmark",
    "sg:tags":[
        "foreninger"
    ],
    "wof:name":"Vimpel & Reklametryk",
    "wof:placetype":"venue"
},
  "geometry": {"coordinates":[-114.0768203735,46.4432411194],"type":"Point"}
}