{
  "type": "Feature",
  "properties": {
    "addr:full":"Tingvej 91 Vodskov Danmark 9310",
    "addr:housenumber":"91",
    "addr:postcode":"9310",
    "addr:street":"Tingvej",
    "iso:country":"DK",
    "sg:address":"Tingvej 91",
    "sg:city":"Vodskov",
    "sg:orig_category":"Havneservice",
    "sg:phone":"+45 98 29 63 93",
    "sg:postcode":"9310",
    "sg:province":"Danmark",
    "wof:name":"Cebulla, J.",
    "wof:placetype":"venue"
},
  "geometry": {"coordinates":[10.0008029938,57.1176300049],"type":"Point"}
}