{
  "type": "Feature",
  "properties": {
    "addr:full":"Lynge Byvej 11 Sor\u00f8 Danmark 4180",
    "addr:housenumber":"11",
    "addr:postcode":"4180",
    "addr:street":"Lynge Byvej",
    "iso:country":"DK",
    "sg:address":"Lynge Byvej 11",
    "sg:city":"Sor\u00f8",
    "sg:orig_category":"Diamantboring",
    "sg:phone":"+45 57 82 11 45",
    "sg:postcode":"4180",
    "sg:province":"Danmark",
    "wof:name":"Herbst, Karen",
    "wof:placetype":"venue"
},
  "geometry": {"coordinates":[11.5655918121,55.4006233215],"type":"Point"}
}