{
  "type": "Feature",
  "properties": {
    "addr:full":"\u00c5boulevarden 20 \u00c5rhus C Danmark 8000",
    "addr:housenumber":"20",
    "addr:postcode":"8000",
    "addr:street":"Aaboulevarden",
    "iso:country":"DK",
    "sg:address":"\u00c5boulevarden 20",
    "sg:city":"\u00c5rhus C",
    "sg:orig_category":"Reklamebureauer",
    "sg:phone":"+45 86 19 90 11",
    "sg:postcode":"8000",
    "sg:province":"Danmark",
    "wof:name":"Kullberg Kommunikation",
    "wof:placetype":"venue"
},
  "geometry": {"coordinates":[4.717400074,49.7588005066],"type":"Point"}
}