{
  "type": "Feature",
  "properties": {
    "addr:full":"Leder: Annine Kristensen, Vejlevej 20, Hodde Tistrup Danmark 6862",
    "addr:housenumber":"20",
    "addr:postcode":"6862",
    "addr:street":"Vejlevej",
    "iso:country":"DK",
    "sg:address":"Leder: Annine Kristensen, Vejlevej 20, Hodde",
    "sg:city":"Tistrup",
    "sg:orig_category":"Ungdomsklubber",
    "sg:phone":"+45 75 29 96 51",
    "sg:postcode":"6862",
    "sg:province":"Danmark",
    "wof:name":"Tistrup Ungdomsklub",
    "wof:placetype":"venue"
},
  "geometry": {"coordinates":[8.6105747223,55.7163848877],"type":"Point"}
}