{
  "type": "Feature",
  "properties": {
    "addr:full":"Spigerborgade 2, 2. Varde Danmark 6800",
    "addr:housenumber":"2 2",
    "addr:postcode":"6800",
    "addr:street":"Spigerborgade",
    "iso:country":"DK",
    "sg:address":"Spigerborgade 2, 2.",
    "sg:city":"Varde",
    "sg:classifiers":[
        {
            "category":"Professional",
            "subcategory":"Advertising",
            "type":"Services"
        }
    ],
    "sg:phone":"+45 75 22 43 88",
    "sg:postcode":"6800",
    "sg:province":"Danmark",
    "sg:tags":[
        "marketing"
    ],
    "wof:name":"Bach Marketing",
    "wof:placetype":"venue"
},
  "geometry": {"coordinates":[8.4817876816,55.6226615906],"type":"Point"}
}