{
  "type": "Feature",
  "properties": {
    "addr:full":"Hastrupskolen, Langelandsvej 70 K\u00f8ge Danmark 4600",
    "addr:housenumber":"70",
    "addr:postcode":"4600",
    "addr:street":"Langelandsvej",
    "iso:country":"DK",
    "sg:address":"Hastrupskolen, Langelandsvej 70",
    "sg:city":"K\u00f8ge",
    "sg:orig_category":"Ungdomsklubber",
    "sg:phone":"+45 56 65 44 87",
    "sg:postcode":"4600",
    "sg:province":"Danmark",
    "wof:name":"Skuffen Hastrupklubben",
    "wof:placetype":"venue"
},
  "geometry": {"coordinates":[12.1526346207,55.4365997314],"type":"Point"}
}