{
  "type": "Feature",
  "properties": {
    "addr:full":"Ahornvej 11 Ry Danmark 8680",
    "addr:housenumber":"11",
    "addr:postcode":"8680",
    "addr:street":"Ahornvej",
    "iso:country":"DK",
    "sg:address":"Ahornvej 11",
    "sg:city":"Ry",
    "sg:orig_category":"Antenneforeninger",
    "sg:phone":"+45 40 87 21 11",
    "sg:postcode":"8680",
    "sg:province":"Danmark",
    "wof:name":"Ry Antenneforening",
    "wof:placetype":"venue"
},
  "geometry": {"coordinates":[9.7768411636,56.0845146179],"type":"Point"}
}