{
  "type": "Feature",
  "properties": {
    "addr:full":"S\u00f8ndre Centervej 2 K\u00f8ge Danmark 4600",
    "addr:housenumber":"2",
    "addr:postcode":"4600",
    "addr:street":"Sondre Centervej",
    "iso:country":"DK",
    "sg:address":"S\u00f8ndre Centervej 2",
    "sg:city":"K\u00f8ge",
    "sg:orig_category":"Integrerede institutioner",
    "sg:phone":"+45 56 65 08 41",
    "sg:postcode":"4600",
    "sg:province":"Danmark",
    "wof:name":"Spiren",
    "wof:placetype":"venue"
},
  "geometry": {"coordinates":[12.1753787994,55.4797592163],"type":"Point"}
}