{
  "type": "Feature",
  "properties": {
    "addr:full":"V\u00e5g\u00f8vej 22  Horsens Danmark 8700",
    "addr:housenumber":"22",
    "addr:postcode":"8700",
    "addr:street":"Vaagovej",
    "iso:country":"DK",
    "sg:address":"V\u00e5g\u00f8vej 22 ",
    "sg:city":"Horsens",
    "sg:classifiers":[
        {
            "category":"Autos & Motor Vehicles",
            "subcategory":"Boat Sales",
            "type":"Retail Goods"
        }
    ],
    "sg:phone":"+45 75 62 03 00",
    "sg:postcode":"8700",
    "sg:province":"Danmark",
    "wof:name":"SEJLSNEDKEREN",
    "wof:placetype":"venue"
},
  "geometry": {"coordinates":[9.8074684143,55.8575592041],"type":"Point"}
}