{
  "type": "Feature",
  "properties": {
    "iso:country":"DK",
    "sg:address":"v/ Else Kristensen, Hvalpsundvej 12, Holmager",
    "sg:city":"Nibe",
    "sg:orig_category":"Spejderkorps",
    "sg:phone":"+45 98 35 70 69",
    "sg:postcode":"9240",
    "sg:province":"Danmark",
    "wof:name":"FDF, Bislev",
    "wof:placetype":"venue"
},
  "geometry": {"coordinates":[9.6393280029,56.982421875],"type":"Point"}
}