{
  "type": "Feature",
  "properties": {
    "addr:full":"Havnen 3 Horsens Danmark 8700",
    "addr:housenumber":"3",
    "addr:postcode":"8700",
    "addr:street":"Havnen",
    "iso:country":"DK",
    "sg:address":"Havnen 3",
    "sg:city":"Horsens",
    "sg:orig_category":"Spedition",
    "sg:phone":"+45 75 61 67 66",
    "sg:postcode":"8700",
    "sg:province":"Danmark",
    "wof:name":"E. P. Spedition",
    "wof:placetype":"venue"
},
  "geometry": {"coordinates":[9.8598184586,55.8582687378],"type":"Point"}
}