{
  "type": "Feature",
  "properties": {
    "addr:full":"Fmd.: Henrik Bertelsen, Stavnsbjergvej 19 Vejen Danmark 6600",
    "addr:housenumber":"19",
    "addr:postcode":"6600",
    "addr:street":"Henrik Bertelsen Stavnsbjergvej",
    "iso:country":"DK",
    "sg:address":"Fmd.: Henrik Bertelsen, Stavnsbjergvej 19",
    "sg:city":"Vejen",
    "sg:orig_category":"Faglige organisationer og foreninger",
    "sg:phone":"+45 75 36 46 35",
    "sg:postcode":"6600",
    "sg:province":"Danmark",
    "wof:name":"Br\u00f8rupegnens Familielandbrug",
    "wof:placetype":"venue"
},
  "geometry": {"coordinates":[9.1396121979,55.4778175354],"type":"Point"}
}