{
  "type": "Feature",
  "properties": {
    "iso:country":"DK",
    "sg:address":"Gl. Landevej 155",
    "sg:city":"Herning",
    "sg:orig_category":"Kiosker",
    "sg:phone":"+45 97 22 52 62",
    "sg:postcode":"7400",
    "sg:province":"Danmark",
    "wof:name":"Superkiosken",
    "wof:placetype":"venue"
},
  "geometry": {"coordinates":[8.9593515396,56.1400146484],"type":"Point"}
}