{
  "type": "Feature",
  "properties": {
    "addr:full":"Vester Hedensvej 5 Gandrup Danmark 9362",
    "addr:housenumber":"5",
    "addr:postcode":"9362",
    "addr:street":"Vester Hedensvej",
    "iso:country":"DK",
    "sg:address":"Vester Hedensvej 5",
    "sg:city":"Gandrup",
    "sg:orig_category":"Dyrefoder",
    "sg:phone":"+45 98 25 94 74",
    "sg:postcode":"9362",
    "sg:province":"Danmark",
    "wof:name":"M. B. Hobby & Dyrefoder",
    "wof:placetype":"venue"
},
  "geometry": {"coordinates":[10.1838264465,57.0521087646],"type":"Point"}
}