{
  "type": "Feature",
  "properties": {
    "addr:full":"Maglekildevej 7 Roskilde Danmark 4000",
    "addr:housenumber":"7",
    "addr:postcode":"4000",
    "addr:street":"Maglekildevej",
    "iso:country":"DK",
    "sg:address":"Maglekildevej 7",
    "sg:city":"Roskilde",
    "sg:orig_category":"Arkitekter",
    "sg:phone":"+45 46 36 85 50",
    "sg:postcode":"4000",
    "sg:province":"Danmark",
    "wof:name":"Johansen & Partnere",
    "wof:placetype":"venue"
},
  "geometry": {"coordinates":[12.0766067505,55.643787384],"type":"Point"}
}