{
  "type": "Feature",
  "properties": {
    "addr:full":"Tv\u00e6rvej 3 Billund Danmark 7190",
    "addr:housenumber":"3",
    "addr:postcode":"7190",
    "addr:street":"Tvaervej",
    "iso:country":"DK",
    "sg:address":"Tv\u00e6rvej 3",
    "sg:city":"Billund",
    "sg:orig_category":"Boligselskaber",
    "sg:phone":"+45 75 33 12 60",
    "sg:postcode":"7190",
    "sg:province":"Danmark",
    "wof:name":"Billund Boligforening",
    "wof:placetype":"venue"
},
  "geometry": {"coordinates":[9.1128463745,55.7332344055],"type":"Point"}
}