{
  "type": "Feature",
  "properties": {
    "addr:full":"Kongensgade 12 Slangerup Danmark 3550",
    "addr:housenumber":"12",
    "addr:postcode":"3550",
    "addr:street":"Kongensgade",
    "iso:country":"DK",
    "sg:address":"Kongensgade 12",
    "sg:city":"Slangerup",
    "sg:orig_category":"Briller",
    "sg:phone":"+45 47 33 42 11",
    "sg:postcode":"3550",
    "sg:province":"Danmark",
    "sg:website":"www.ditsyn.dk",
    "wof:name":"Dit Syn Slangerup",
    "wof:placetype":"venue"
},
  "geometry": {"coordinates":[12.1720523834,55.8458518982],"type":"Point"}
}