{
  "type": "Feature",
  "properties": {
    "addr:full":"Randersvej 20 Lang\u00e5 Danmark 8870",
    "addr:housenumber":"20",
    "addr:postcode":"8870",
    "addr:street":"Randersvej",
    "iso:country":"DK",
    "sg:address":"Randersvej 20",
    "sg:city":"Lang\u00e5",
    "sg:orig_category":"Autoreparation og -service",
    "sg:phone":"+45 86 46 12 22",
    "sg:postcode":"8870",
    "sg:province":"Danmark",
    "sg:website":"www.kalstrupsauto.dk",
    "wof:name":"Kalstrups Autov\u00e6rksted ApS",
    "wof:placetype":"venue"
},
  "geometry": {"coordinates":[9.8978347778,56.393661499],"type":"Point"}
}