{
  "type": "Feature",
  "properties": {
    "iso:country":"DK",
    "sg:address":"Teknikerbyen 21",
    "sg:city":"Virum",
    "sg:classifiers":[
        {
            "category":"Banks & Credit Unions",
            "subcategory":"Financial Services",
            "type":"Services"
        }
    ],
    "sg:phone":"+45 45 98 50 00",
    "sg:postcode":"2830",
    "sg:province":"Danmark",
    "sg:tags":[
        "banking",
        "finance",
        "insurance"
    ],
    "wof:name":"NORDISK FACTORING A/S",
    "wof:placetype":"venue"
},
  "geometry": {"coordinates":[12.4974689484,55.8007087708],"type":"Point"}
}