{
  "type": "Feature",
  "properties": {
    "addr:full":"Fmd.: Ole Sandersen, Byrstedvej 12, Bradsted Suldrup Danmark 9541",
    "addr:housenumber":"12",
    "addr:postcode":"9541",
    "addr:street":"Byrstedvej",
    "iso:country":"DK",
    "sg:address":"Fmd.: Ole Sandersen, Byrstedvej 12, Bradsted",
    "sg:city":"Suldrup",
    "sg:orig_category":"Borger- og beboerforeninger",
    "sg:phone":"+45 98 38 73 36",
    "sg:postcode":"9541",
    "sg:province":"Danmark",
    "wof:name":"Byrsted Borgerforening",
    "wof:placetype":"venue"
},
  "geometry": {"coordinates":[9.701379776,56.8489303589],"type":"Point"}
}