{
  "type": "Feature",
  "properties": {
    "iso:country":"DK",
    "sg:address":"Odensevej 21",
    "sg:city":"Ringe",
    "sg:classifiers":[
        {
            "category":"Communications",
            "subcategory":"Film & Video Production",
            "type":"Services"
        }
    ],
    "sg:phone":"+45 62 62 15 30",
    "sg:postcode":"5750",
    "sg:province":"Danmark",
    "sg:tags":[
        "radio-",
        "og",
        "tv-service"
    ],
    "wof:name":"Stolberg, Sam",
    "wof:placetype":"venue"
},
  "geometry": {"coordinates":[10.4775571823,55.2419052124],"type":"Point"}
}