{
  "type": "Feature",
  "properties": {
    "addr:full":"Vester Kirkestr\u00e6de 14 Randers Danmark 8900",
    "addr:housenumber":"14",
    "addr:postcode":"8900",
    "iso:country":"DK",
    "sg:address":"Vester Kirkestr\u00e6de 14",
    "sg:city":"Randers",
    "sg:classifiers":[
        {
            "category":"Arts & Performance",
            "subcategory":"Arts Center",
            "type":"Entertainment"
        }
    ],
    "sg:phone":"+45 86 42 98 40",
    "sg:postcode":"8900",
    "sg:province":"Danmark",
    "sg:tags":[
        "patchwork"
    ],
    "wof:name":"Pedari Patchwork",
    "wof:placetype":"venue"
},
  "geometry": {"coordinates":[10.0341873169,56.4598922729],"type":"Point"}
}