{
  "type": "Feature",
  "properties": {
    "addr:full":"St. Sct. Mikkels Gade 14 Viborg Danmark 8800",
    "addr:housenumber":"14",
    "addr:postcode":"8800",
    "addr:street":"Sct. Mikkels Gade",
    "iso:country":"DK",
    "sg:address":"St. Sct. Mikkels Gade 14",
    "sg:city":"Viborg",
    "sg:orig_category":"Vikarbureauer",
    "sg:phone":"+45 87 26 22 44",
    "sg:postcode":"8800",
    "sg:province":"Danmark",
    "wof:name":"Temp-Team",
    "wof:placetype":"venue"
},
  "geometry": {"coordinates":[9.4099807739,56.4496765137],"type":"Point"}
}