{
  "type": "Feature",
  "properties": {
    "addr:full":"Fmd.: Per Endrup, Kirkevej 13, Bakkendrup G\u00f8rlev Danmark 4281",
    "addr:housenumber":"13",
    "addr:postcode":"4281",
    "addr:street":"Kirkevej",
    "iso:country":"DK",
    "sg:address":"Fmd.: Per Endrup, Kirkevej 13, Bakkendrup",
    "sg:city":"G\u00f8rlev",
    "sg:orig_category":"Kulturelle foreninger",
    "sg:phone":"+45 58 85 59 53",
    "sg:postcode":"4281",
    "sg:province":"Danmark",
    "wof:name":"Mellemfolkeligt Samvirke, Slagelse lokalgruppe",
    "wof:placetype":"venue"
},
  "geometry": {"coordinates":[11.1143903732,55.5207710266],"type":"Point"}
}