{
  "type": "Feature",
  "properties": {
    "addr:full":"Skolebakken 7, \u00d8. T\u00f8rslev Gjerlev Danmark 8983",
    "addr:housenumber":"7 o.",
    "addr:postcode":"8983",
    "addr:street":"Skolebakken;Torslev Gjerlev Danmark",
    "iso:country":"DK",
    "sg:address":"Skolebakken 7, \u00d8. T\u00f8rslev",
    "sg:city":"Gjerlev",
    "sg:orig_category":"Skolefritidsordninger",
    "sg:phone":"+45 86 47 61 92",
    "sg:postcode":"8983",
    "sg:province":"Danmark",
    "wof:name":"Gr\u00f8nh\u00f8jskolens Fritidsordning",
    "wof:placetype":"venue"
},
  "geometry": {"coordinates":[10.1887750626,56.5788421631],"type":"Point"}
}