{
  "type": "Feature",
  "properties": {
    "iso:country":"DK",
    "sg:address":"Storegade 38, 1",
    "sg:city":"Bramming",
    "sg:orig_category":"Eksport",
    "sg:phone":"+45 75 10 22 40",
    "sg:postcode":"6740",
    "sg:province":"Danmark",
    "sg:website":"www.mirekexport.dk",
    "wof:name":"Mirek Export ApS",
    "wof:placetype":"venue"
},
  "geometry": {"coordinates":[8.6981496811,55.4655570984],"type":"Point"}
}