{
  "type": "Feature",
  "properties": {
    "addr:full":"Fmd.: Hanne Larsen, Laugsh\u00f8jvej 3, Nyrup Mark H\u00f8jby Danmark 4573",
    "addr:housenumber":"3",
    "addr:postcode":"4573",
    "addr:street":"Laugshojvej;Mark;Danmark",
    "iso:country":"DK",
    "sg:address":"Fmd.: Hanne Larsen, Laugsh\u00f8jvej 3, Nyrup Mark",
    "sg:city":"H\u00f8jby",
    "sg:orig_category":"Husflidsforeninger",
    "sg:phone":"+45 59 30 26 73",
    "sg:postcode":"4573",
    "sg:province":"Danmark",
    "wof:name":"H\u00f8jby Husholdningsforening",
    "wof:placetype":"venue"
},
  "geometry": {"coordinates":[115.1525192261,35.9290504456],"type":"Point"}
}