{
  "type": "Feature",
  "properties": {
    "addr:full":"Ejnar Nielsens Vej 4 Gjern Danmark 8883",
    "addr:housenumber":"4",
    "addr:postcode":"8883",
    "addr:street":"Ejnar Nielsens Vej",
    "iso:country":"DK",
    "sg:address":"Ejnar Nielsens Vej 4",
    "sg:city":"Gjern",
    "sg:orig_category":"Begravelsesforretninger",
    "sg:phone":"+45 86 87 51 15",
    "sg:postcode":"8883",
    "sg:province":"Danmark",
    "wof:name":"Gjern Begravelsesforretning",
    "wof:placetype":"venue"
},
  "geometry": {"coordinates":[9.7394037247,56.2305335999],"type":"Point"}
}