{
  "type": "Feature",
  "properties": {
    "addr:full":"Industrivej 6 Langeskov Danmark 5550",
    "addr:housenumber":"6",
    "addr:postcode":"5550",
    "addr:street":"Industrivej",
    "iso:country":"DK",
    "sg:address":"Industrivej 6",
    "sg:city":"Langeskov",
    "sg:classifiers":[
        {
            "category":"Wholesale",
            "subcategory":"Chemicals & Plastics",
            "type":"Manufacturing & Wholesale Goods"
        }
    ],
    "sg:phone":"+45 63 38 10 00",
    "sg:postcode":"5550",
    "sg:province":"Danmark",
    "wof:name":"Rexam Closures and Containers A/S",
    "wof:placetype":"venue"
},
  "geometry": {"coordinates":[10.5773143768,55.3535499573],"type":"Point"}
}