{
  "type": "Feature",
  "properties": {
    "addr:full":"Kirkebakken 5 Hundested Danmark 3390",
    "addr:housenumber":"5",
    "addr:postcode":"3390",
    "addr:street":"Kirkebakken",
    "iso:country":"DK",
    "sg:address":"Kirkebakken 5",
    "sg:city":"Hundested",
    "sg:orig_category":"Kirker",
    "sg:postcode":"3390",
    "sg:province":"Danmark",
    "wof:name":"Lyn\u00e6s Kirke",
    "wof:placetype":"venue"
},
  "geometry": {"coordinates":[11.8593034744,55.950958252],"type":"Point"}
}