{
  "type": "Feature",
  "properties": {
    "addr:full":"Hermodsgade 8 K\u00f8benhavn N Danmark 2200",
    "addr:housenumber":"8",
    "addr:postcode":"2200",
    "addr:street":"Hermodsgade;N Danmark",
    "iso:country":"DK",
    "sg:address":"Hermodsgade 8",
    "sg:city":"K\u00f8benhavn N",
    "sg:classifiers":[
        {
            "category":"Museum",
            "type":"Entertainment"
        }
    ],
    "sg:phone":"+45 35 87 73 00",
    "sg:postcode":"2200",
    "sg:province":"Danmark",
    "sg:tags":[
        "og",
        "skat",
        "told"
    ],
    "wof:name":"Told- og Skatteregion K\u00f8benhavn 2 (Nord).",
    "wof:placetype":"venue"
},
  "geometry": {"coordinates":[-74.0000457764,43.6337890625],"type":"Point"}
}