{
  "type": "Feature",
  "properties": {
    "iso:country":"DK",
    "sg:address":"Vedelsgade 14",
    "sg:city":"Sor\u00f8",
    "sg:classifiers":[
        {
            "category":"Communications",
            "type":"Services"
        }
    ],
    "sg:phone":"+45 57 82 12 06",
    "sg:postcode":"4180",
    "sg:province":"Danmark",
    "sg:tags":[
        "radio-",
        "og",
        "tv-stationer"
    ],
    "wof:name":"SNR - Sor\u00f8 N\u00e6r Radio",
    "wof:placetype":"venue"
},
  "geometry": {"coordinates":[-102.94467926030001,45.4534721375],"type":"Point"}
}