{
  "type": "Feature",
  "properties": {
    "addr:full":"Fabjergstad 31, Fabjerg Lemvig Danmark 7620",
    "addr:housenumber":"31",
    "addr:postcode":"7620",
    "addr:street":"Fabjergstad",
    "iso:country":"DK",
    "sg:address":"Fabjergstad 31, Fabjerg",
    "sg:city":"Lemvig",
    "sg:orig_category":"Socialpsykiatriske bosteder",
    "sg:phone":"+45 97 89 31 13",
    "sg:postcode":"7620",
    "sg:province":"Danmark",
    "wof:name":"Psykiatrien i Ringkj\u00f8bing Amt, K\u00e6r-Huset",
    "wof:placetype":"venue"
},
  "geometry": {"coordinates":[8.3073654175,56.5505104065],"type":"Point"}
}