{
  "type": "Feature",
  "properties": {
    "addr:full":"Fmd.: Steen Dall, Skipperkobbel 22 Gram Danmark 6510",
    "addr:housenumber":"22",
    "addr:postcode":"6510",
    "addr:street":"Skipperkobbel",
    "iso:country":"DK",
    "sg:address":"Fmd.: Steen Dall, Skipperkobbel 22",
    "sg:city":"Gram",
    "sg:orig_category":"Antenneforeninger",
    "sg:phone":"+45 74 82 26 07",
    "sg:postcode":"6510",
    "sg:province":"Danmark",
    "wof:name":"Gram Antenneforening",
    "wof:placetype":"venue"
},
  "geometry": {"coordinates":[9.0392875671,55.2878417969],"type":"Point"}
}