{
  "type": "Feature",
  "properties": {
    "addr:full":"Baunevej 150 Taastrup Danmark 2630",
    "addr:housenumber":"150",
    "addr:postcode":"2630",
    "addr:street":"Baunevej",
    "iso:country":"DK",
    "sg:address":"Baunevej 150",
    "sg:city":"Taastrup",
    "sg:orig_category":"Vagtbureauer",
    "sg:phone":"+45 43 99 68 20",
    "sg:postcode":"2630",
    "sg:province":"Danmark",
    "wof:name":"Kontrolgruppen",
    "wof:placetype":"venue"
},
  "geometry": {"coordinates":[12.298948288,55.6382522583],"type":"Point"}
}