{
  "type": "Feature",
  "properties": {
    "addr:full":"Torvet 4 Nibe Danmark 9240",
    "addr:housenumber":"4",
    "addr:postcode":"9240",
    "addr:street":"Torvet",
    "iso:country":"DK",
    "sg:address":"Torvet 4",
    "sg:city":"Nibe",
    "sg:orig_category":"Reklamegaver",
    "sg:phone":"+45 98 35 22 70",
    "sg:postcode":"9240",
    "sg:province":"Danmark",
    "wof:name":"Butler Design & Profilgaver",
    "wof:placetype":"venue"
},
  "geometry": {"coordinates":[9.6393489838,56.9826545715],"type":"Point"}
}