{
  "type": "Feature",
  "properties": {
    "addr:full":"Havnevej 17 Vordingborg Danmark 4760",
    "addr:housenumber":"17",
    "addr:postcode":"4760",
    "addr:street":"Havnevej",
    "iso:country":"DK",
    "sg:address":"Havnevej 17",
    "sg:city":"Vordingborg",
    "sg:orig_category":"Kiosker",
    "sg:phone":"+45 55 34 12 55",
    "sg:postcode":"4760",
    "sg:province":"Danmark",
    "wof:name":"Nordhavnskiosken",
    "wof:placetype":"venue"
},
  "geometry": {"coordinates":[11.9113016129,55.0050201416],"type":"Point"}
}