{
  "type": "Feature",
  "properties": {
    "iso:country":"DK",
    "sg:address":"Fmd.: Kirsten Birkholm, Trekanten 2, Asserballe",
    "sg:city":"Augustenborg",
    "sg:orig_category":"Kulturelle foreninger",
    "sg:phone":"+45 74 47 34 30",
    "sg:postcode":"6440",
    "sg:province":"Danmark",
    "sg:website":"www.lof-alssund.dk",
    "wof:name":"LOF (Liberalt Oplysnings Forbund)",
    "wof:placetype":"venue"
},
  "geometry": {"coordinates":[9.8727750778,54.9459037781],"type":"Point"}
}