{
  "type": "Feature",
  "properties": {
    "addr:full":"Buskh\u00f8jvej 19 Padborg Danmark 6330",
    "addr:housenumber":"19",
    "addr:postcode":"6330",
    "addr:street":"Buskhojvej",
    "iso:country":"DK",
    "sg:address":"Buskh\u00f8jvej 19",
    "sg:city":"Padborg",
    "sg:orig_category":"Malermestre",
    "sg:phone":"+45 74 67 33 48",
    "sg:postcode":"6330",
    "sg:province":"Danmark",
    "wof:name":"Pedersen, Erik",
    "wof:placetype":"venue"
},
  "geometry": {"coordinates":[9.352104187,54.822933197],"type":"Point"}
}