{
  "type": "Feature",
  "properties": {
    "iso:country":"DK",
    "sg:address":"Kr\u00e6mmergade 20",
    "sg:city":"Nibe",
    "sg:orig_category":"Handicapboliger",
    "sg:phone":"+45 98 35 38 70",
    "sg:postcode":"9240",
    "sg:province":"Danmark",
    "wof:name":"Boenheden",
    "wof:placetype":"venue"
},
  "geometry": {"coordinates":[9.6399822235,56.9872245789],"type":"Point"}
}