{
  "type": "Feature",
  "properties": {
    "addr:full":"Odinsvej 22 Ringsted Danmark 4100",
    "addr:housenumber":"22",
    "addr:postcode":"4100",
    "addr:street":"Odinsvej",
    "iso:country":"DK",
    "sg:address":"Odinsvej 22",
    "sg:city":"Ringsted",
    "sg:orig_category":"Autoforhandlere",
    "sg:phone":"+45 57 67 42 48",
    "sg:postcode":"4100",
    "sg:province":"Danmark",
    "wof:name":"Henrik Olsen Automobiler",
    "wof:placetype":"venue"
},
  "geometry": {"coordinates":[11.7982702255,55.4332199097],"type":"Point"}
}