{
  "type": "Feature",
  "properties": {
    "iso:country":"DK",
    "sg:address":"Myntevej 11 A",
    "sg:city":"Risskov",
    "sg:orig_category":"Glas- og glasvareindustri",
    "sg:phone":"+45 86 17 00 50",
    "sg:postcode":"8240",
    "sg:province":"Danmark",
    "sg:website":"www.iso-mec.dk",
    "wof:name":"ISO-MEC",
    "wof:placetype":"venue"
},
  "geometry": {"coordinates":[10.2529144287,56.1997756958],"type":"Point"}
}