{
  "type": "Feature",
  "properties": {
    "addr:full":"Carlsh\u00f8jvej 47 Kongens Lyngby Danmark 2800",
    "addr:housenumber":"47",
    "addr:postcode":"2800",
    "addr:street":"Carlshojvej",
    "iso:country":"DK",
    "sg:address":"Carlsh\u00f8jvej 47",
    "sg:city":"Kongens Lyngby",
    "sg:orig_category":"Videobutikker og -klubber",
    "sg:phone":"+45 45 87 48 70",
    "sg:postcode":"2800",
    "sg:province":"Danmark",
    "wof:name":"Lehmann, K\u00f8bmand",
    "wof:placetype":"venue"
},
  "geometry": {"coordinates":[12.5368299484,55.7949905396],"type":"Point"}
}