{
  "type": "Feature",
  "properties": {
    "addr:full":"Vestermarksvej 19 Aabenraa Danmark 6200",
    "addr:housenumber":"19",
    "addr:postcode":"6200",
    "addr:street":"Vestermarksvej",
    "iso:country":"DK",
    "sg:address":"Vestermarksvej 19",
    "sg:city":"Aabenraa",
    "sg:orig_category":"Babyudstyr",
    "sg:phone":"+45 74 62 78 80",
    "sg:postcode":"6200",
    "sg:province":"Danmark",
    "wof:name":"Baby-Vest",
    "wof:placetype":"venue"
},
  "geometry": {"coordinates":[9.397296,55.047768],"type":"Point"}
}