{
  "type": "Feature",
  "properties": {
    "iso:country":"DK",
    "sg:address":"Fmd.: Hans Petersen, Houmannsgade 20, 2",
    "sg:city":"Horsens",
    "sg:orig_category":"Kolonihaveforeninger",
    "sg:phone":"+45 75 62 09 73",
    "sg:postcode":"8700",
    "sg:province":"Danmark",
    "wof:name":"Kolonihaveforbundet, Horsens kreds",
    "wof:placetype":"venue"
},
  "geometry": {"coordinates":[9.8432445526,55.8621063232],"type":"Point"}
}