{
  "type": "Feature",
  "properties": {
    "addr:full":"Greve Bygade 13 Greve Danmark 2670",
    "addr:housenumber":"13",
    "addr:postcode":"2670",
    "addr:street":"Greve Bygade",
    "iso:country":"DK",
    "sg:address":"Greve Bygade 13",
    "sg:city":"Greve",
    "sg:orig_category":"Kontormaskiner",
    "sg:phone":"+45 43 40 43 01",
    "sg:postcode":"2670",
    "sg:province":"Danmark",
    "wof:name":"Umates A/S",
    "wof:placetype":"venue"
},
  "geometry": {"coordinates":[12.2969064713,55.5873222351],"type":"Point"}
}