{
  "type": "Feature",
  "properties": {
    "addr:full":"Risvej 28 Skanderborg Danmark 8660",
    "addr:housenumber":"28",
    "addr:postcode":"8660",
    "addr:street":"Risvej",
    "iso:country":"DK",
    "sg:address":"Risvej 28",
    "sg:city":"Skanderborg",
    "sg:orig_category":"Skolefritidsordninger",
    "sg:phone":"+45 86 53 85 05",
    "sg:postcode":"8660",
    "sg:province":"Danmark",
    "wof:name":"Baunehaven SFO, Jupiter",
    "wof:placetype":"venue"
},
  "geometry": {"coordinates":[9.8625869751,55.975566864],"type":"Point"}
}