{
  "type": "Feature",
  "properties": {
    "iso:country":"DK",
    "sg:address":"\u00d8rstedsvej 7",
    "sg:city":"Silkeborg",
    "sg:classifiers":[
        {
            "category":"Airport",
            "type":"Transportation"
        }
    ],
    "sg:phone":"+45 70 23 08 08",
    "sg:postcode":"8600",
    "sg:province":"Danmark",
    "sg:tags":[
        "automation"
    ],
    "sg:website":"www.sinus-automation.dk",
    "wof:name":"Sinus Automation ApS",
    "wof:placetype":"venue"
},
  "geometry": {"coordinates":[9.5711736679,56.1983375549],"type":"Point"}
}