{
  "type": "Feature",
  "properties": {
    "addr:full":"Urbansgade 19 Aalborg Danmark 9000",
    "addr:housenumber":"19",
    "addr:postcode":"9000",
    "addr:street":"Urbansgade",
    "iso:country":"DK",
    "sg:address":"Urbansgade 19",
    "sg:city":"Aalborg",
    "sg:orig_category":"Musikinstrumenter",
    "sg:phone":"+45 98 13 24 33",
    "sg:postcode":"9000",
    "sg:province":"Danmark",
    "wof:name":"Christensen, Alfred",
    "wof:placetype":"venue"
},
  "geometry": {"coordinates":[9.9160327911,57.0493545532],"type":"Point"}
}