{
  "type": "Feature",
  "properties": {
    "iso:country":"DK",
    "sg:address":"Eriksmindevej 20",
    "sg:city":"Greve",
    "sg:orig_category":"Kirker",
    "sg:postcode":"2670",
    "sg:province":"Danmark",
    "wof:name":"Hundige Kirke",
    "wof:placetype":"venue"
},
  "geometry": {"coordinates":[12.3181829453,55.5942153931],"type":"Point"}
}