{
  "type": "Feature",
  "properties": {
    "addr:full":"St. Voldgade 5 Randers Danmark 8900",
    "addr:housenumber":"5",
    "addr:postcode":"8900",
    "addr:street":"Voldgade",
    "iso:country":"DK",
    "sg:address":"St. Voldgade 5",
    "sg:city":"Randers",
    "sg:classifiers":[
        {
            "category":"Home & Garden",
            "subcategory":"Home Furnishings",
            "type":"Retail Goods"
        }
    ],
    "sg:phone":"+45 86 41 23 00",
    "sg:postcode":"8900",
    "sg:province":"Danmark",
    "sg:tags":[
        "gardiner"
    ],
    "wof:name":"AM-Gardiner Randers ApS",
    "wof:placetype":"venue"
},
  "geometry": {"coordinates":[10.0335683823,56.4602355957],"type":"Point"}
}