{
  "type": "Feature",
  "properties": {
    "addr:full":"M\u00f8llesvinget 38, Moltrup Haderslev Danmark 6100",
    "addr:housenumber":"38",
    "addr:postcode":"6100",
    "addr:street":"Mollesvinget;Moltrup",
    "iso:country":"DK",
    "sg:address":"M\u00f8llesvinget 38, Moltrup",
    "sg:city":"Haderslev",
    "sg:orig_category":"Kommunale folkeskoler",
    "sg:phone":"+45 74 53 27 93",
    "sg:postcode":"6100",
    "sg:province":"Danmark",
    "wof:name":"Moltrup Skole, Haderslev Kommunale Skolev\u00e6sens Heldagsskole",
    "wof:placetype":"venue"
},
  "geometry": {"coordinates":[9.4879703522,55.2505493164],"type":"Point"}
}