{
  "type": "Feature",
  "properties": {
    "addr:full":"Gl. F\u00e6rgevej 4 Esbjerg Danmark 6700",
    "addr:housenumber":"4",
    "addr:postcode":"6700",
    "addr:street":"Faergevej",
    "iso:country":"DK",
    "sg:address":"Gl. F\u00e6rgevej 4",
    "sg:city":"Esbjerg",
    "sg:orig_category":"Transport",
    "sg:phone":"+45 75 13 61 11",
    "sg:postcode":"6700",
    "sg:province":"Danmark",
    "wof:name":"Danzas ASG Eurocargo A/S",
    "wof:placetype":"venue"
},
  "geometry": {"coordinates":[8.456905365,55.465221405],"type":"Point"}
}