{
  "type": "Feature",
  "properties": {
    "addr:full":"Bibliotekvej 56 Hvidovre Danmark 2650",
    "addr:housenumber":"56",
    "addr:postcode":"2650",
    "addr:street":"Bibliotekvej",
    "iso:country":"DK",
    "sg:address":"Bibliotekvej 56",
    "sg:city":"Hvidovre",
    "sg:orig_category":"Benzinstationer",
    "sg:phone":"+45 36 78 63 75",
    "sg:postcode":"2650",
    "sg:province":"Danmark",
    "wof:name":"Hydro Texaco",
    "wof:placetype":"venue"
},
  "geometry": {"coordinates":[12.4692487717,55.6411247253],"type":"Point"}
}