{
  "type": "Feature",
  "properties": {
    "iso:country":"DK",
    "sg:address":"C. J. Frandsens Vej 2",
    "sg:city":"K\u00f8benhavn NV",
    "sg:classifiers":[
        {
            "category":"Professional",
            "subcategory":"Business Services",
            "type":"Services"
        }
    ],
    "sg:phone":"+45 39 69 39 24",
    "sg:postcode":"2400",
    "sg:province":"Danmark",
    "sg:tags":[
        "import",
        "vin"
    ],
    "wof:name":"Ege Vin",
    "wof:placetype":"venue"
},
  "geometry": {"coordinates":[-117.02272033689999,38.5024604797],"type":"Point"}
}