{
  "type": "Feature",
  "properties": {
    "addr:full":"Nyvej 4 Jyderup Danmark 4450",
    "addr:housenumber":"4",
    "addr:postcode":"4450",
    "addr:street":"Nyvej",
    "iso:country":"DK",
    "sg:address":"Nyvej 4",
    "sg:city":"Jyderup",
    "sg:orig_category":"Farve og tapet",
    "sg:phone":"+45 59 27 70 76",
    "sg:postcode":"4450",
    "sg:province":"Danmark",
    "wof:name":"Farve & Rammecenter",
    "wof:placetype":"venue"
},
  "geometry": {"coordinates":[11.3965797424,55.6602058411],"type":"Point"}
}