{
  "type": "Feature",
  "properties": {
    "addr:full":"R\u00f8dbyvej 78, Hillested Maribo Danmark 4930",
    "addr:housenumber":"78",
    "addr:postcode":"4930",
    "addr:street":"Rodbyvej",
    "iso:country":"DK",
    "sg:address":"R\u00f8dbyvej 78, Hillested",
    "sg:city":"Maribo",
    "sg:orig_category":"Autoreparation og -service",
    "sg:phone":"+45 54 78 18 21",
    "sg:postcode":"4930",
    "sg:province":"Danmark",
    "wof:name":"Hardenberg Biler",
    "wof:placetype":"venue"
},
  "geometry": {"coordinates":[11.502035141,54.7743835449],"type":"Point"}
}