{
  "type": "Feature",
  "properties": {
    "addr:full":"Industriv\u00e6nget 20 Havdrup Danmark 4622",
    "addr:housenumber":"20",
    "addr:postcode":"4622",
    "addr:street":"Industrivaenget",
    "iso:country":"DK",
    "sg:address":"Industriv\u00e6nget 20",
    "sg:city":"Havdrup",
    "sg:orig_category":"Smedemestre",
    "sg:phone":"+45 46 18 60 22",
    "sg:postcode":"4622",
    "sg:province":"Danmark",
    "sg:website":"www.havdrup-pladeindustri.dk",
    "wof:name":"Havdrup Pladeindustri ApS",
    "wof:placetype":"venue"
},
  "geometry": {"coordinates":[12.1263952255,55.5499420166],"type":"Point"}
}