{
  "type": "Feature",
  "properties": {
    "addr:full":"Fmd.: Per Kristiansen, Byvej 31 Bryrup Danmark 8654",
    "addr:housenumber":"31",
    "addr:postcode":"8654",
    "addr:street":"Byvej",
    "iso:country":"DK",
    "sg:address":"Fmd.: Per Kristiansen, Byvej 31",
    "sg:city":"Bryrup",
    "sg:orig_category":"Turistforeninger",
    "sg:phone":"+45 75 75 65 83",
    "sg:postcode":"8654",
    "sg:province":"Danmark",
    "sg:website":"www.turist-them.dk",
    "wof:name":"Bryrup-Them Turistforening",
    "wof:placetype":"venue"
},
  "geometry": {"coordinates":[9.5107898712,56.0237388611],"type":"Point"}
}