{
  "type": "Feature",
  "properties": {
    "addr:full":"Ramsherred 7 Broager Danmark 6310",
    "addr:housenumber":"7",
    "addr:postcode":"6310",
    "addr:street":"Ramsherred",
    "iso:country":"DK",
    "sg:address":"Ramsherred 7",
    "sg:city":"Broager",
    "sg:classifiers":[
        {
            "category":"Taxi",
            "type":"Transportation"
        }
    ],
    "sg:phone":"+45 74 44 21 41",
    "sg:postcode":"6310",
    "sg:province":"Danmark",
    "wof:name":"Johnny's Taxi",
    "wof:placetype":"venue"
},
  "geometry": {"coordinates":[9.6673240662,54.8893623352],"type":"Point"}
}