{
  "type": "Feature",
  "properties": {
    "addr:full":"Skomagertorvet 6 Nibe Danmark 9240",
    "addr:housenumber":"6",
    "addr:postcode":"9240",
    "addr:street":"Skomagertorvet",
    "iso:country":"DK",
    "sg:address":"Skomagertorvet 6",
    "sg:city":"Nibe",
    "sg:orig_category":"Pizzeriaer",
    "sg:phone":"+45 98 35 20 81",
    "sg:postcode":"9240",
    "sg:province":"Danmark",
    "wof:name":"Kebab House",
    "wof:placetype":"venue"
},
  "geometry": {"coordinates":[9.6370954514,56.9815979004],"type":"Point"}
}