{
  "type": "Feature",
  "properties": {
    "addr:full":"Byst\u00e6vneparken 4 Br\u00f8nsh\u00f8j Danmark 2700",
    "addr:housenumber":"4",
    "addr:postcode":"2700",
    "addr:street":"Bystaevneparken",
    "iso:country":"DK",
    "sg:address":"Byst\u00e6vneparken 4",
    "sg:city":"Br\u00f8nsh\u00f8j",
    "sg:orig_category":"Integrerede institutioner",
    "sg:phone":"+45 38 60 00 68",
    "sg:postcode":"2700",
    "sg:province":"Danmark",
    "wof:name":"B\u00f8rnehuset i Byst\u00e6vneparken",
    "wof:placetype":"venue"
},
  "geometry": {"coordinates":[-65.6866531372,-23.1981296539],"type":"Point"}
}