{
  "type": "Feature",
  "properties": {
    "addr:full":"Drejet 7, Tor\u00f8 Huse Assens Danmark 5610",
    "addr:housenumber":"7",
    "addr:postcode":"5610",
    "addr:street":"Drejet;Toro Huse",
    "iso:country":"DK",
    "sg:address":"Drejet 7, Tor\u00f8 Huse",
    "sg:city":"Assens",
    "sg:orig_category":"Forsamlingshuse",
    "sg:phone":"+45 64 71 10 60",
    "sg:postcode":"5610",
    "sg:province":"Danmark",
    "wof:name":"Thor\u00f8huse Forsamlingshus",
    "wof:placetype":"venue"
},
  "geometry": {"coordinates":[9.8998937607,55.2702522278],"type":"Point"}
}