{
  "type": "Feature",
  "properties": {
    "addr:full":"Fmd.: Poul Lentge, Annasvej 25 Karlslunde Danmark 2690",
    "addr:housenumber":"25",
    "addr:postcode":"2690",
    "addr:street":"Poul Lentge Annasvej",
    "iso:country":"DK",
    "sg:address":"Fmd.: Poul Lentge, Annasvej 25",
    "sg:city":"Karlslunde",
    "sg:orig_category":"Grundejerforeninger",
    "sg:phone":"+45 46 15 40 23",
    "sg:postcode":"2690",
    "sg:province":"Danmark",
    "wof:name":"Annasvejs Grundejerforening",
    "wof:placetype":"venue"
},
  "geometry": {"coordinates":[12.2294149399,55.5701599121],"type":"Point"}
}