{
  "type": "Feature",
  "properties": {
    "addr:full":"Fruerlund 9 N\u00e6rum Danmark 2850",
    "addr:housenumber":"9",
    "addr:postcode":"2850",
    "addr:street":"Fruerlund",
    "iso:country":"DK",
    "sg:address":"Fruerlund 9",
    "sg:city":"N\u00e6rum",
    "sg:orig_category":"Tandklinikker, Kommunale",
    "sg:phone":"+45 45 80 13 07",
    "sg:postcode":"2850",
    "sg:province":"Danmark",
    "wof:name":"N\u00e6rum Skoles Tandklinik",
    "wof:placetype":"venue"
},
  "geometry": {"coordinates":[12.5385198593,55.8138389587],"type":"Point"}
}