{
  "type": "Feature",
  "properties": {
    "addr:full":"Pilevej 16 Risskov Danmark 8240",
    "addr:housenumber":"16",
    "addr:postcode":"8240",
    "addr:street":"Pilevej",
    "iso:country":"DK",
    "sg:address":"Pilevej 16",
    "sg:city":"Risskov",
    "sg:orig_category":"Psykologer, praktiserende",
    "sg:phone":"+45 86 17 14 17",
    "sg:postcode":"8240",
    "sg:province":"Danmark",
    "wof:name":"Abel, Karin",
    "wof:placetype":"venue"
},
  "geometry": {"coordinates":[10.247086525,56.1924743652],"type":"Point"}
}