{
  "type": "Feature",
  "properties": {
    "iso:country":"DK",
    "sg:address":"Stenhuggervej 20",
    "sg:city":"Esbjerg V",
    "sg:orig_category":"Snedkermestre",
    "sg:phone":"+45 75 15 72 51",
    "sg:postcode":"6710",
    "sg:province":"Danmark",
    "wof:name":"Jensen & Jensen ApS, T\u00f8mrer & Snedkerfirmaet",
    "wof:placetype":"venue"
},
  "geometry": {"coordinates":[8.4132957458,55.5096626282],"type":"Point"}
}