{
  "type": "Feature",
  "properties": {
    "addr:full":"Fmd.: Hans Madsen, Lundg\u00e5rdsvej 6, Rostrup Arden Danmark 9510",
    "addr:housenumber":"6",
    "addr:postcode":"9510",
    "addr:street":"Lundgaardsvej",
    "iso:country":"DK",
    "sg:address":"Fmd.: Hans Madsen, Lundg\u00e5rdsvej 6, Rostrup",
    "sg:city":"Arden",
    "sg:orig_category":"Hobbybetonede foreninger",
    "sg:phone":"+45 96 40 82 06",
    "sg:postcode":"9510",
    "sg:province":"Danmark",
    "wof:name":"Hobro Filatelistklub",
    "wof:placetype":"venue"
},
  "geometry": {"coordinates":[9.8580989838,56.7683296204],"type":"Point"}
}