{
  "type": "Feature",
  "properties": {
    "addr:full":"Rungsted Plads 21 K\u00f8benhavn N Danmark 2200",
    "addr:housenumber":"21",
    "addr:postcode":"2200",
    "addr:street":"Rungsted Plads;N Danmark",
    "iso:country":"DK",
    "sg:address":"Rungsted Plads 21",
    "sg:city":"K\u00f8benhavn N",
    "sg:orig_category":"Kiosker",
    "sg:phone":"+45 35 85 33 62",
    "sg:postcode":"2200",
    "sg:province":"Danmark",
    "wof:name":"Minimarked",
    "wof:placetype":"venue"
},
  "geometry": {"coordinates":[12.5326404572,55.8842201233],"type":"Point"}
}