{
  "type": "Feature",
  "properties": {
    "addr:full":"Hostrupsgade 34 Silkeborg Danmark 8600",
    "addr:housenumber":"34",
    "addr:postcode":"8600",
    "addr:street":"Hostrupsgade",
    "iso:country":"DK",
    "sg:address":"Hostrupsgade 34",
    "sg:city":"Silkeborg",
    "sg:orig_category":"Pizzeriaer",
    "sg:phone":"+45 86 80 08 61",
    "sg:postcode":"8600",
    "sg:province":"Danmark",
    "wof:name":"Hawaii",
    "wof:placetype":"venue"
},
  "geometry": {"coordinates":[9.5449810028,56.1668281555],"type":"Point"}
}