{
  "type": "Feature",
  "properties": {
    "addr:full":"Hulg\u00e5rdsvej 1 K\u00f8benhavn NV Danmark 2400",
    "addr:housenumber":"1",
    "addr:postcode":"2400",
    "addr:street":"Hulgaardsvej",
    "iso:country":"DK",
    "sg:address":"Hulg\u00e5rdsvej 1",
    "sg:city":"K\u00f8benhavn NV",
    "sg:orig_category":"Rammer",
    "sg:phone":"+45 38 86 11 46",
    "sg:postcode":"2400",
    "sg:province":"Danmark",
    "wof:name":"Plakathuset",
    "wof:placetype":"venue"
},
  "geometry": {"coordinates":[-117.02272033689999,38.5024604797],"type":"Point"}
}