{
  "type": "Feature",
  "properties": {
    "addr:full":"Fmd.: Sv. E. Hjorth, I Bakkerne 29, Aarsdale Svaneke Danmark 3740",
    "addr:housenumber":"29",
    "addr:postcode":"3740",
    "addr:street":"Bakkerne",
    "iso:country":"DK",
    "sg:address":"Fmd.: Sv. E. Hjorth, I Bakkerne 29, Aarsdale",
    "sg:city":"Svaneke",
    "sg:orig_category":"Grundejerforeninger",
    "sg:phone":"+45 56 49 65 17",
    "sg:postcode":"3740",
    "sg:province":"Danmark",
    "wof:name":"Grundejerforeningen Strandvangen og Strandparken",
    "wof:placetype":"venue"
},
  "geometry": {"coordinates":[15.1410236359,55.1078643799],"type":"Point"}
}