{
  "type": "Feature",
  "properties": {
    "addr:full":"\u00d8stergade 110  Broby Danmark 5672",
    "addr:housenumber":"110",
    "addr:postcode":"5672",
    "addr:street":"Ostergade",
    "iso:country":"DK",
    "sg:address":"\u00d8stergade 110 ",
    "sg:city":"Broby",
    "sg:classifiers":[
        {
            "category":"Manufacturing",
            "subcategory":"Lumber",
            "type":"Manufacturing & Wholesale Goods"
        }
    ],
    "sg:phone":"+45 62 69 14 22",
    "sg:postcode":"5672",
    "sg:province":"Danmark",
    "sg:tags":[
        "wood"
    ],
    "wof:name":"FYNS FACONSP\u00c6ND A/S",
    "wof:placetype":"venue"
},
  "geometry": {"coordinates":[10.3407239914,55.2657814026],"type":"Point"}
}