{
  "type": "Feature",
  "properties": {
    "addr:full":"Vallensved Bygade 51, Vallensved N\u00e6stved Danmark 4700",
    "addr:housenumber":"51",
    "addr:postcode":"4700",
    "addr:street":"Vallensved Bygade",
    "iso:country":"DK",
    "sg:address":"Vallensved Bygade 51, Vallensved",
    "sg:city":"N\u00e6stved",
    "sg:orig_category":"Autoreparation og -service",
    "sg:phone":"+45 55 44 70 90",
    "sg:postcode":"4700",
    "sg:province":"Danmark",
    "wof:name":"MN Auto",
    "wof:placetype":"venue"
},
  "geometry": {"coordinates":[11.7542486191,55.2315444946],"type":"Point"}
}