{
  "type": "Feature",
  "properties": {
    "iso:country":"DK",
    "sg:address":"Klostervej 28",
    "sg:city":"Ry",
    "sg:orig_category":"Gallerier",
    "sg:phone":"+45 86 89 30 12",
    "sg:postcode":"8680",
    "sg:province":"Danmark",
    "wof:name":"Guden\u00e5, Galleri",
    "wof:placetype":"venue"
},
  "geometry": {"coordinates":[9.7597265244,56.0890350342],"type":"Point"}
}