{
  "type": "Feature",
  "properties": {
    "addr:full":"R\u00f8rmosen 81 Roskilde Danmark 4000",
    "addr:housenumber":"81",
    "addr:postcode":"4000",
    "addr:street":"Rormosen",
    "iso:country":"DK",
    "sg:address":"R\u00f8rmosen 81",
    "sg:city":"Roskilde",
    "sg:classifiers":[
        {
            "category":"Communications",
            "subcategory":"Film & Video Production",
            "type":"Services"
        }
    ],
    "sg:phone":"+45 46 32 61 71",
    "sg:postcode":"4000",
    "sg:province":"Danmark",
    "sg:tags":[
        "radio-",
        "og",
        "tv-service"
    ],
    "wof:name":"Melgaard, Carsten",
    "wof:placetype":"venue"
},
  "geometry": {"coordinates":[12.0909376144,55.6404838562],"type":"Point"}
}