{
  "type": "Feature",
  "properties": {
    "iso:country":"DK",
    "sg:address":"Solv\u00e6nget 2, Str\u00f8by Egede",
    "sg:city":"K\u00f8ge",
    "sg:orig_category":"Zoneterapeuter",
    "sg:phone":"+45 56 26 60 74",
    "sg:postcode":"4600",
    "sg:province":"Danmark",
    "wof:name":"Kosiara, Ena",
    "wof:placetype":"venue"
},
  "geometry": {"coordinates":[6.4543700218,52.4404983521],"type":"Point"}
}