{
  "type": "Feature",
  "properties": {
    "addr:full":"Sdr. Landevej 198, Pedersker Aakirkeby Danmark 3720",
    "addr:housenumber":"198",
    "addr:postcode":"3720",
    "addr:street":"Sdr. Landevej;Pedersker",
    "iso:country":"DK",
    "sg:address":"Sdr. Landevej 198, Pedersker",
    "sg:city":"Aakirkeby",
    "sg:orig_category":"Autoforhandlere",
    "sg:phone":"+45 56 97 79 00",
    "sg:postcode":"3720",
    "sg:province":"Danmark",
    "wof:name":"N. B. Biler",
    "wof:placetype":"venue"
},
  "geometry": {"coordinates":[14.9202880859,55.070110321],"type":"Point"}
}