{
  "type": "Feature",
  "properties": {
    "addr:full":"Christian Pejtersen, Tofteg\u00e5rdsv\u00e6nget 143 Fredensborg Danmark 3480",
    "addr:housenumber":"143",
    "addr:postcode":"3480",
    "iso:country":"DK",
    "sg:address":"Christian Pejtersen, Tofteg\u00e5rdsv\u00e6nget 143",
    "sg:city":"Fredensborg",
    "sg:orig_category":"\u00c3\u2020ldreorganisationer og klubber",
    "sg:phone":"+45 48 48 25 51",
    "sg:postcode":"3480",
    "sg:province":"Danmark",
    "wof:name":"SIDs Efterl\u00f8ns- og Pensionistklub",
    "wof:placetype":"venue"
},
  "geometry": {"coordinates":[12.4020547867,55.9782943726],"type":"Point"}
}