{
  "type": "Feature",
  "properties": {
    "addr:full":"Fredrik Bajers Vej 7 A/B Aalborg \u00d8 Danmark 9220",
    "addr:housenumber":"7 a / b",
    "addr:postcode":"9220",
    "addr:street":"Fredrik Bajers Vej;Danmark",
    "iso:country":"DK",
    "sg:address":"Fredrik Bajers Vej 7 A/B",
    "sg:city":"Aalborg \u00d8",
    "sg:orig_category":"Hobbybetonede foreninger",
    "sg:postcode":"9220",
    "sg:province":"Danmark",
    "sg:website":"www.bridge.dk/ubk",
    "wof:name":"UBK - Universitetets Bridgeklub",
    "wof:placetype":"venue"
},
  "geometry": {"coordinates":[10.0031700134,57.0515899658],"type":"Point"}
}