{
  "type": "Feature",
  "properties": {
    "iso:country":"DK",
    "sg:address":"Gr\u00f8nnevej 15",
    "sg:city":"Tinglev",
    "sg:orig_category":"Blomsterhandlere",
    "sg:phone":"+45 74 64 47 15",
    "sg:postcode":"6360",
    "sg:province":"Danmark",
    "wof:name":"Blomsterhj\u00f8rnet",
    "wof:placetype":"venue"
},
  "geometry": {"coordinates":[9.2544593811,54.9347839355],"type":"Point"}
}