{
  "type": "Feature",
  "properties": {
    "addr:full":"Vestergade 19 Odense C Danmark 5000",
    "addr:housenumber":"19",
    "addr:postcode":"5000",
    "addr:street":"Vestergade",
    "iso:country":"DK",
    "sg:address":"Vestergade 19",
    "sg:city":"Odense C",
    "sg:orig_category":"Advokater",
    "sg:phone":"+45 66 13 65 33",
    "sg:postcode":"5000",
    "sg:province":"Danmark",
    "wof:name":"Halskov, Erling",
    "wof:placetype":"venue"
},
  "geometry": {"coordinates":[10.3874397278,55.3961868286],"type":"Point"}
}