{
  "type": "Feature",
  "properties": {
    "addr:full":"Aborrev\u00e6nget 6 Vordingborg Danmark 4760",
    "addr:housenumber":"6",
    "addr:postcode":"4760",
    "addr:street":"Aborrevaenget",
    "iso:country":"DK",
    "sg:address":"Aborrev\u00e6nget 6",
    "sg:city":"Vordingborg",
    "sg:orig_category":"Snedkermestre",
    "sg:phone":"+45 40 36 09 19",
    "sg:postcode":"4760",
    "sg:province":"Danmark",
    "sg:website":"www.ks-totalservice.dk",
    "wof:name":"KS Totalservice",
    "wof:placetype":"venue"
},
  "geometry": {"coordinates":[11.9124183655,55.0085449219],"type":"Point"}
}