{
  "type": "Feature",
  "properties": {
    "addr:full":"Kordilgade 36 Kalundborg Danmark 4400",
    "addr:housenumber":"36",
    "addr:postcode":"4400",
    "addr:street":"Kordilgade",
    "iso:country":"DK",
    "sg:address":"Kordilgade 36",
    "sg:city":"Kalundborg",
    "sg:orig_category":"Cykler",
    "sg:phone":"+45 59 51 04 57",
    "sg:postcode":"4400",
    "sg:province":"Danmark",
    "wof:name":"Mosquito Cykel Center",
    "wof:placetype":"venue"
},
  "geometry": {"coordinates":[11.0917644501,55.6797523499],"type":"Point"}
}