{
  "type": "Feature",
  "properties": {
    "addr:full":"Torvegade 2 A Ringk\u00f8bing Danmark 6950",
    "addr:housenumber":"2 a",
    "addr:postcode":"6950",
    "addr:street":"Torvegade",
    "iso:country":"DK",
    "sg:address":"Torvegade 2 A",
    "sg:city":"Ringk\u00f8bing",
    "sg:orig_category":"Ejendomshandel",
    "sg:phone":"+45 97 32 43 44",
    "sg:postcode":"6950",
    "sg:province":"Danmark",
    "sg:website":"www.nybolig.dk",
    "wof:name":"Nybolig Ringk\u00f8bing",
    "wof:placetype":"venue"
},
  "geometry": {"coordinates":[8.2429771423,56.0906677246],"type":"Point"}
}