{
  "type": "Feature",
  "properties": {
    "iso:country":"DK",
    "sg:address":"S\u00f8ndermarken 6, Fjellerup",
    "sg:city":"Glesborg",
    "sg:orig_category":"Kirkesogne",
    "sg:phone":"+45 87 79 09 08",
    "sg:postcode":"8585",
    "sg:province":"Danmark",
    "wof:name":"Fjellerup Valgmenighed",
    "wof:placetype":"venue"
},
  "geometry": {"coordinates":[10.5884723663,56.5124320984],"type":"Point"}
}