{
  "type": "Feature",
  "properties": {
    "addr:full":"Frederiksborgvej 1A K\u00f8benhavn NV Danmark 2400",
    "addr:housenumber":"1a",
    "addr:postcode":"2400",
    "addr:street":"Frederiksborgvej",
    "iso:country":"DK",
    "sg:address":"Frederiksborgvej 1A",
    "sg:city":"K\u00f8benhavn NV",
    "sg:orig_category":"Videobutikker og -klubber",
    "sg:phone":"+45 38 19 02 91",
    "sg:postcode":"2400",
    "sg:province":"Danmark",
    "sg:website":"www.blockbuster.dk",
    "wof:name":"Blockbuster Video Danmark A/S",
    "wof:placetype":"venue"
},
  "geometry": {"coordinates":[-117.02272033689999,38.5024604797],"type":"Point"}
}