{
  "type": "Feature",
  "properties": {
    "iso:country":"DK",
    "sg:address":"Gr\u00f8nlandsgade 3 1.",
    "sg:city":"Kerteminde",
    "sg:orig_category":"Advokater",
    "sg:phone":"+45 65 32 47 44",
    "sg:postcode":"5300",
    "sg:province":"Danmark",
    "wof:name":"Advokatfirmaet Kielberg",
    "wof:placetype":"venue"
},
  "geometry": {"coordinates":[10.6620788574,55.4516563416],"type":"Point"}
}