{
  "type": "Feature",
  "properties": {
    "addr:full":"Pr\u00e6stev\u00e6nget 1 Hjallerup Danmark 9320",
    "addr:housenumber":"1",
    "addr:postcode":"9320",
    "addr:street":"Praestevaenget",
    "iso:country":"DK",
    "sg:address":"Pr\u00e6stev\u00e6nget 1",
    "sg:city":"Hjallerup",
    "sg:orig_category":"Fritidshjem",
    "sg:phone":"+45 98 28 23 17",
    "sg:postcode":"9320",
    "sg:province":"Danmark",
    "wof:name":"Regnbuen, Fritidshjemmet",
    "wof:placetype":"venue"
},
  "geometry": {"coordinates":[10.1444702148,57.1677742004],"type":"Point"}
}