{
  "type": "Feature",
  "properties": {
    "addr:full":"Skibet Bakkevej 8 Vejle Danmark 7100",
    "addr:housenumber":"8",
    "addr:postcode":"7100",
    "addr:street":"Skibet Bakkevej",
    "iso:country":"DK",
    "sg:address":"Skibet Bakkevej 8",
    "sg:city":"Vejle",
    "sg:orig_category":"Frugtplantager",
    "sg:phone":"+45 75 88 15 14",
    "sg:postcode":"7100",
    "sg:province":"Danmark",
    "wof:name":"Skibet Frugtplantage",
    "wof:placetype":"venue"
},
  "geometry": {"coordinates":[9.4598093033,55.693687439],"type":"Point"}
}