{
  "type": "Feature",
  "properties": {
    "addr:full":"Dalgasgade 24 - 26 Silkeborg Danmark 8600",
    "addr:housenumber":"24 26",
    "addr:postcode":"8600",
    "addr:street":"Dalgasgade",
    "iso:country":"DK",
    "sg:address":"Dalgasgade 24 - 26",
    "sg:city":"Silkeborg",
    "sg:orig_category":"Faglige organisationer og foreninger",
    "sg:phone":"+45 86 82 13 11",
    "sg:postcode":"8600",
    "sg:province":"Danmark",
    "wof:name":"Forbundet af Offentligt Ansatte",
    "wof:placetype":"venue"
},
  "geometry": {"coordinates":[9.5322723389,56.1631622314],"type":"Point"}
}