{
  "type": "Feature",
  "properties": {
    "addr:full":"Kvislemarkvej Sandved Danmark 4262",
    "addr:postcode":"4262",
    "addr:street":"Kvislemarkvej",
    "iso:country":"DK",
    "sg:address":"Kvislemarkvej",
    "sg:city":"Sandved",
    "sg:orig_category":"Kirker",
    "sg:postcode":"4262",
    "sg:province":"Danmark",
    "wof:name":"Kvislemark Kirke",
    "wof:placetype":"venue"
},
  "geometry": {"coordinates":[11.5656576157,55.2550506592],"type":"Point"}
}