{
  "type": "Feature",
  "properties": {
    "addr:full":"Valdemarsgade 27 K\u00f8benhavn Danmark 1665",
    "addr:housenumber":"27",
    "addr:postcode":"1665",
    "addr:street":"Valdemarsgade",
    "iso:country":"DK",
    "sg:address":"Valdemarsgade 27",
    "sg:city":"K\u00f8benhavn",
    "sg:orig_category":"Vuggestuer",
    "sg:phone":"+45 33 22 11 81",
    "sg:postcode":"1665",
    "sg:province":"Danmark",
    "wof:name":"Sct. Matth\u00e6us Sogns Menighedsvuggestue",
    "wof:placetype":"venue"
},
  "geometry": {"coordinates":[12.548740387,55.671081543],"type":"Point"}
}