{
  "type": "Feature",
  "properties": {
    "addr:full":"H\u00e5ndv\u00e6rksvej 5, St. Darum Bramming Danmark 6740",
    "addr:housenumber":"5",
    "addr:postcode":"6740",
    "addr:street":"Haandvaerksvej",
    "iso:country":"DK",
    "sg:address":"H\u00e5ndv\u00e6rksvej 5, St. Darum",
    "sg:city":"Bramming",
    "sg:orig_category":"Autoreparation og -service",
    "sg:phone":"+45 75 17 91 15",
    "sg:postcode":"6740",
    "sg:province":"Danmark",
    "wof:name":"Lindberg's Auto, Erik",
    "wof:placetype":"venue"
},
  "geometry": {"coordinates":[8.6974096298,55.4655303955],"type":"Point"}
}