{
  "type": "Feature",
  "properties": {
    "addr:full":"\u00d8strigsgade 51 4 tv K\u00f8benhavn S Danmark 2300",
    "addr:housenumber":"51 4 tv",
    "addr:postcode":"2300",
    "addr:street":"Ostrigsgade;Kobenhavn S Danmark",
    "iso:country":"DK",
    "sg:address":"\u00d8strigsgade 51 4 tv",
    "sg:city":"K\u00f8benhavn S",
    "sg:orig_category":"Konsulentvirksomheder",
    "sg:phone":"+45 32 55 71 10",
    "sg:postcode":"2300",
    "sg:province":"Danmark",
    "wof:name":"Vision Technology",
    "wof:placetype":"venue"
},
  "geometry": {"coordinates":[-90.0232543945,34.9927711487],"type":"Point"}
}