{
  "type": "Feature",
  "properties": {
    "addr:full":"Skolevej 3, S\u00f8ften Hinnerup Danmark 8382",
    "addr:housenumber":"3",
    "addr:postcode":"8382",
    "addr:street":"Skolevej;Soften",
    "iso:country":"DK",
    "sg:address":"Skolevej 3, S\u00f8ften",
    "sg:city":"Hinnerup",
    "sg:orig_category":"Fritidscentre",
    "sg:phone":"+45 86 98 50 08",
    "sg:postcode":"8382",
    "sg:province":"Danmark",
    "wof:name":"S\u00f8ften Fritidscenter",
    "wof:placetype":"venue"
},
  "geometry": {"coordinates":[10.0614156723,56.2650604248],"type":"Point"}
}