{
  "type": "Feature",
  "properties": {
    "addr:full":"Gammel Kongevej 15 K\u00f8benhavn Danmark 1610",
    "addr:housenumber":"15;1610",
    "addr:street":"Gammel Kongevej",
    "iso:country":"DK",
    "sg:address":"Gammel Kongevej 15",
    "sg:city":"K\u00f8benhavn",
    "sg:orig_category":"Revisorer",
    "sg:phone":"+45 33 26 70 00",
    "sg:postcode":"1610",
    "sg:province":"Danmark",
    "wof:name":"Nicolaisen, Andreas",
    "wof:placetype":"venue"
},
  "geometry": {"coordinates":[12.543299675,55.6758003235],"type":"Point"}
}