{
  "type": "Feature",
  "properties": {
    "addr:full":"N\u00f8debovej 26, N\u00f8debo Fredensborg Danmark 3480",
    "addr:housenumber":"26",
    "addr:postcode":"3480",
    "addr:street":"Nodebovej",
    "iso:country":"DK",
    "sg:address":"N\u00f8debovej 26, N\u00f8debo",
    "sg:city":"Fredensborg",
    "sg:orig_category":"Forsamlingshuse",
    "sg:phone":"+45 48 48 07 46",
    "sg:postcode":"3480",
    "sg:province":"Danmark",
    "wof:name":"N\u00f8debo Kro, Forsamlingshuset",
    "wof:placetype":"venue"
},
  "geometry": {"coordinates":[12.4020547867,55.9782943726],"type":"Point"}
}