{
  "type": "Feature",
  "properties": {
    "addr:full":"Jyllandsvej 11 Brande Danmark 7330",
    "addr:housenumber":"11",
    "addr:postcode":"7330",
    "addr:street":"Jyllandsvej",
    "iso:country":"DK",
    "sg:address":"Jyllandsvej 11",
    "sg:city":"Brande",
    "sg:orig_category":"Autosadelmagere",
    "sg:phone":"+45 97 18 07 47",
    "sg:postcode":"7330",
    "sg:province":"Danmark",
    "wof:name":"Brande Autosadelmageri I/S",
    "wof:placetype":"venue"
},
  "geometry": {"coordinates":[9.1456098557,55.9327583313],"type":"Point"}
}