{
  "type": "Feature",
  "properties": {
    "addr:full":"S\u00f8ndergade 37 A Frederikshavn Danmark 9900",
    "addr:housenumber":"37 a",
    "addr:postcode":"9900",
    "addr:street":"Sondergade",
    "iso:country":"DK",
    "sg:address":"S\u00f8ndergade 37 A",
    "sg:city":"Frederikshavn",
    "sg:orig_category":"Fodplejere",
    "sg:phone":"+45 98 43 01 48",
    "sg:postcode":"9900",
    "sg:province":"Danmark",
    "wof:name":"Fodklinikken",
    "wof:placetype":"venue"
},
  "geometry": {"coordinates":[10.5314416885,57.4347229004],"type":"Point"}
}