{
  "type": "Feature",
  "properties": {
    "addr:full":"Langgade 59 Gedser Danmark 4874",
    "addr:housenumber":"59",
    "addr:postcode":"4874",
    "addr:street":"Langgade",
    "iso:country":"DK",
    "sg:address":"Langgade 59",
    "sg:city":"Gedser",
    "sg:classifiers":[
        {
            "category":"Restaurant",
            "type":"Food & Drink"
        }
    ],
    "sg:phone":"+45 54 17 17 08",
    "sg:postcode":"4874",
    "sg:province":"Danmark",
    "wof:name":"Gedser, Hotel",
    "wof:placetype":"venue"
},
  "geometry": {"coordinates":[11.9295969009,54.5760116577],"type":"Point"}
}