{
  "type": "Feature",
  "properties": {
    "addr:full":"Blonds Alle 43 Fredericia Danmark 7000",
    "addr:housenumber":"43",
    "addr:postcode":"7000",
    "addr:street":"Blonds Alle",
    "iso:country":"DK",
    "sg:address":"Blonds Alle 43",
    "sg:city":"Fredericia",
    "sg:orig_category":"Danseundervisning",
    "sg:phone":"+45 75 91 50 96",
    "sg:postcode":"7000",
    "sg:province":"Danmark",
    "wof:name":"L. B. Dans",
    "wof:placetype":"venue"
},
  "geometry": {"coordinates":[9.7637672424,55.5848274231],"type":"Point"}
}