{
  "type": "Feature",
  "properties": {
    "addr:full":"Bredgade 36 Lang\u00e5 Danmark 8870",
    "addr:housenumber":"36",
    "addr:postcode":"8870",
    "addr:street":"Bredgade",
    "iso:country":"DK",
    "sg:address":"Bredgade 36",
    "sg:city":"Lang\u00e5",
    "sg:orig_category":"Optikere",
    "sg:phone":"+45 86 46 10 34",
    "sg:postcode":"8870",
    "sg:province":"Danmark",
    "wof:name":"Andersen, Aksel A.",
    "wof:placetype":"venue"
},
  "geometry": {"coordinates":[9.8958835602,56.3891181946],"type":"Point"}
}