{
  "type": "Feature",
  "properties": {
    "addr:full":"Provst Bjarne Christensen, Hammelev Bygade 7 Vojens Danmark 6500",
    "addr:housenumber":"7",
    "addr:postcode":"6500",
    "addr:street":"Provst;Hammelev Bygade",
    "iso:country":"DK",
    "sg:address":"Provst Bjarne Christensen, Hammelev Bygade 7",
    "sg:city":"Vojens",
    "sg:orig_category":"Kirkesogne",
    "sg:phone":"+45 74 50 71 12",
    "sg:postcode":"6500",
    "sg:province":"Danmark",
    "wof:name":"Hammelev Sogn",
    "wof:placetype":"venue"
},
  "geometry": {"coordinates":[9.2987146378,55.2457237244],"type":"Point"}
}