{
  "type": "Feature",
  "properties": {
    "addr:full":"Hvidovrevej 78 R\u00f8dovre Danmark 2610",
    "addr:housenumber":"78",
    "addr:postcode":"2610",
    "addr:street":"Hvidovrevej",
    "iso:country":"DK",
    "sg:address":"Hvidovrevej 78",
    "sg:city":"R\u00f8dovre",
    "sg:classifiers":[
        {
            "category":"Communications",
            "type":"Services"
        }
    ],
    "sg:phone":"+45 36 41 50 00",
    "sg:postcode":"2610",
    "sg:province":"Danmark",
    "sg:tags":[
        "og",
        "tv",
        "radio"
    ],
    "wof:name":"Kim's Corner - 2tal",
    "wof:placetype":"venue"
},
  "geometry": {"coordinates":[10.6992139816,61.1027755737],"type":"Point"}
}