{
  "type": "Feature",
  "properties": {
    "addr:full":"J\u00e6gersborg All\u00e9 139 Gentofte Danmark 2820",
    "addr:housenumber":"139",
    "addr:postcode":"2820",
    "addr:street":"Jaegersborg Alle\u0301",
    "iso:country":"DK",
    "sg:address":"J\u00e6gersborg All\u00e9 139",
    "sg:city":"Gentofte",
    "sg:orig_category":"Statslige direktorater og styrelser",
    "sg:phone":"+45 39 76 35 05",
    "sg:postcode":"2820",
    "sg:province":"Danmark",
    "sg:website":"www.alkoholviden.dk",
    "wof:name":"Videncenter om Alkohol",
    "wof:placetype":"venue"
},
  "geometry": {"coordinates":[12.5409173965,55.7482719421],"type":"Point"}
}