{
  "type": "Feature",
  "properties": {
    "addr:full":"Jegstrupvej 6 A Viborg Danmark 8800",
    "addr:housenumber":"6 a",
    "addr:postcode":"8800",
    "addr:street":"Jegstrupvej",
    "iso:country":"DK",
    "sg:address":"Jegstrupvej 6 A",
    "sg:city":"Viborg",
    "sg:orig_category":"Cykler",
    "sg:phone":"+45 86 62 80 60",
    "sg:postcode":"8800",
    "sg:province":"Danmark",
    "wof:name":"K. V. J. Cykler",
    "wof:placetype":"venue"
},
  "geometry": {"coordinates":[9.3952636719,56.4543075562],"type":"Point"}
}