{
  "type": "Feature",
  "properties": {
    "addr:full":"Fan\u00f8vej 5 A Viborg Danmark 8800",
    "addr:housenumber":"5 a",
    "addr:postcode":"8800",
    "addr:street":"Fanovej",
    "iso:country":"DK",
    "sg:address":"Fan\u00f8vej 5 A",
    "sg:city":"Viborg",
    "sg:orig_category":"Boligudlejning",
    "sg:phone":"+45 86 61 24 00",
    "sg:postcode":"8800",
    "sg:province":"Danmark",
    "wof:name":"Gl - Ejendomme",
    "wof:placetype":"venue"
},
  "geometry": {"coordinates":[9.3729562759,56.4502906799],"type":"Point"}
}