{
  "type": "Feature",
  "properties": {
    "addr:full":"Kastetvej 29 Aalborg Danmark 9000",
    "addr:housenumber":"29",
    "addr:postcode":"9000",
    "addr:street":"Kastetvej",
    "iso:country":"DK",
    "sg:address":"Kastetvej 29",
    "sg:city":"Aalborg",
    "sg:orig_category":"Pizzeriaer",
    "sg:phone":"+45 98 16 18 66",
    "sg:postcode":"9000",
    "sg:province":"Danmark",
    "wof:name":"Mexico City",
    "wof:placetype":"venue"
},
  "geometry": {"coordinates":[9.9061594009,57.0530548096],"type":"Point"}
}