{
  "type": "Feature",
  "properties": {
    "addr:full":"V\u00e6rkstedsvej 1 Fredericia Danmark 7000",
    "addr:housenumber":"1",
    "addr:postcode":"7000",
    "addr:street":"Vaerkstedsvej",
    "iso:country":"DK",
    "sg:address":"V\u00e6rkstedsvej 1",
    "sg:city":"Fredericia",
    "sg:orig_category":"Isolering",
    "sg:phone":"+45 75 92 90 00",
    "sg:postcode":"7000",
    "sg:province":"Danmark",
    "sg:website":"www.norisol.com",
    "wof:name":"Norisol A/S",
    "wof:placetype":"venue"
},
  "geometry": {"coordinates":[9.7596530914,55.5893936157],"type":"Point"}
}