{
  "type": "Feature",
  "properties": {
    "addr:full":"R\u00f8rg\u00e5rdsvej 23, Smollerup Stoholm Danmark 7850",
    "addr:housenumber":"23",
    "addr:postcode":"7850",
    "addr:street":"Rorgaardsvej;Stoholm",
    "iso:country":"DK",
    "sg:address":"R\u00f8rg\u00e5rdsvej 23, Smollerup",
    "sg:city":"Stoholm",
    "sg:orig_category":"Produkthandlere",
    "sg:phone":"+45 97 54 12 36",
    "sg:postcode":"7850",
    "sg:province":"Danmark",
    "wof:name":"Bruno's Produkt",
    "wof:placetype":"venue"
},
  "geometry": {"coordinates":[9.148730278,56.4856910706],"type":"Point"}
}