{
  "type": "Feature",
  "properties": {
    "addr:full":"M\u00f8llergade 31 Svendborg Danmark 5700",
    "addr:housenumber":"31",
    "addr:postcode":"5700",
    "addr:street":"Mollergade",
    "iso:country":"DK",
    "sg:address":"M\u00f8llergade 31",
    "sg:city":"Svendborg",
    "sg:orig_category":"Skomagere",
    "sg:phone":"+45 62 21 05 90",
    "sg:postcode":"5700",
    "sg:province":"Danmark",
    "wof:name":"Saacks Eftf. Tr\u00e6skoforretningen",
    "wof:placetype":"venue"
},
  "geometry": {"coordinates":[10.6100120544,55.060798645],"type":"Point"}
}