{
  "type": "Feature",
  "properties": {
    "addr:full":"N\u00e6sh\u00f8jvej 22 Harlev Danmark 8462",
    "addr:housenumber":"22",
    "addr:postcode":"8462",
    "addr:street":"Naeshojvej",
    "iso:country":"DK",
    "sg:address":"N\u00e6sh\u00f8jvej 22",
    "sg:city":"Harlev",
    "sg:orig_category":"Integrerede institutioner",
    "sg:phone":"+45 86 94 24 04",
    "sg:postcode":"8462",
    "sg:province":"Danmark",
    "wof:name":"N\u00e6sh\u00f8jvej, Integreret Inst.",
    "wof:placetype":"venue"
},
  "geometry": {"coordinates":[10.0093507767,56.1557807922],"type":"Point"}
}