{
  "type": "Feature",
  "properties": {
    "addr:full":"Baunevej 25, \u00c5gerup Roskilde Danmark 4000",
    "addr:housenumber":"25",
    "addr:postcode":"4000",
    "addr:street":"Baunevej",
    "iso:country":"DK",
    "sg:address":"Baunevej 25, \u00c5gerup",
    "sg:city":"Roskilde",
    "sg:orig_category":"Malermestre",
    "sg:phone":"+45 46 78 72 66",
    "sg:postcode":"4000",
    "sg:province":"Danmark",
    "wof:name":"J\u00f8rgensen, Svend Humle",
    "wof:placetype":"venue"
},
  "geometry": {"coordinates":[12.0909376144,55.6404838562],"type":"Point"}
}