{
  "type": "Feature",
  "properties": {
    "addr:full":"Fiskehuskajen 13 Skagen Danmark 9990",
    "addr:housenumber":"13",
    "addr:postcode":"9990",
    "addr:street":"Fiskehuskajen",
    "iso:country":"DK",
    "sg:address":"Fiskehuskajen 13",
    "sg:city":"Skagen",
    "sg:classifiers":[
        {
            "category":"Restaurant",
            "type":"Food & Drink"
        }
    ],
    "sg:phone":"+45 98 44 35 44",
    "sg:postcode":"9990",
    "sg:province":"Danmark",
    "wof:name":"Skagen Fiskerestaurant",
    "wof:placetype":"venue"
},
  "geometry": {"coordinates":[10.5889320374,57.7192993164],"type":"Point"}
}