{
  "type": "Feature",
  "properties": {
    "iso:country":"DK",
    "sg:address":"Odensevej 18 G, Hjallese",
    "sg:city":"Odense S",
    "sg:orig_category":"Non-Classified Establishments",
    "sg:phone":"+45 66 15 24 10",
    "sg:postcode":"5260",
    "sg:province":"Danmark",
    "wof:name":"JOB JOKER Erhvervbekl\u00e6dning",
    "wof:placetype":"venue"
},
  "geometry": {"coordinates":[10.3157806396,55.3122825623],"type":"Point"}
}