{
  "type": "Feature",
  "properties": {
    "iso:country":"DK",
    "sg:address":"Borgerg\u00e5rden, Vimmelskaftet 2",
    "sg:city":"Give",
    "sg:orig_category":"Biblioteker",
    "sg:phone":"+45 75 73 14 55",
    "sg:postcode":"7323",
    "sg:province":"Danmark",
    "sg:website":"www.givebib.dk",
    "wof:name":"Give Bibliotek",
    "wof:placetype":"venue"
},
  "geometry": {"coordinates":[9.237116,55.843773],"type":"Point"}
}