{
  "type": "Feature",
  "properties": {
    "addr:full":"Rosenlunds Alle 6 Vanl\u00f8se Danmark 2720",
    "addr:housenumber":"6",
    "addr:postcode":"2720",
    "addr:street":"Rosenlunds Alle",
    "iso:country":"DK",
    "sg:address":"Rosenlunds Alle 6",
    "sg:city":"Vanl\u00f8se",
    "sg:orig_category":"Autoreparation og -service",
    "sg:phone":"+45 38 79 09 09",
    "sg:postcode":"2720",
    "sg:province":"Danmark",
    "wof:name":"Went Auto",
    "wof:placetype":"venue"
},
  "geometry": {"coordinates":[13.346449852,57.5253982544],"type":"Point"}
}