{
  "type": "Feature",
  "properties": {
    "iso:country":"DK",
    "sg:address":"Dankwart Dreyers Vej 20 B",
    "sg:city":"Assens",
    "sg:orig_category":"Supermarkeder",
    "sg:phone":"+45 64 71 17 59",
    "sg:postcode":"5610",
    "sg:province":"Danmark",
    "wof:name":"Kisa - Marked",
    "wof:placetype":"venue"
},
  "geometry": {"coordinates":[9.894903183,55.2741394043],"type":"Point"}
}