{
  "type": "Feature",
  "properties": {
    "addr:full":"v/ Gerhart Larsen, Gr\u00e6sted V\u00e6nge 16 Gr\u00e6sted Danmark 3230",
    "addr:housenumber":"16",
    "addr:postcode":"3230",
    "addr:street":"Vaenge",
    "iso:country":"DK",
    "sg:address":"v/ Gerhart Larsen, Gr\u00e6sted V\u00e6nge 16",
    "sg:city":"Gr\u00e6sted",
    "sg:orig_category":"Grundejerforeninger",
    "sg:phone":"+45 48 39 18 62",
    "sg:postcode":"3230",
    "sg:province":"Danmark",
    "wof:name":"Grundejerforeningen Gr\u00e6sted V\u00e6nge",
    "wof:placetype":"venue"
},
  "geometry": {"coordinates":[-88.6614227295,44.1987304688],"type":"Point"}
}