{
  "type": "Feature",
  "properties": {
    "addr:full":"Gl. Kirkevej 33 Herning Danmark 7400",
    "addr:housenumber":"33",
    "addr:postcode":"7400",
    "addr:street":"Gl. Kirkevej",
    "iso:country":"DK",
    "sg:address":"Gl. Kirkevej 33",
    "sg:city":"Herning",
    "sg:orig_category":"Kirkesogne",
    "sg:phone":"+45 97 12 66 48",
    "sg:postcode":"7400",
    "sg:province":"Danmark",
    "wof:name":"Hedeager Sogns Kirkekontor",
    "wof:placetype":"venue"
},
  "geometry": {"coordinates":[8.953245163,56.1440048218],"type":"Point"}
}