{
  "type": "Feature",
  "properties": {
    "iso:country":"DK",
    "sg:address":"Gammelbyvej 55, Gammelby",
    "sg:city":"Vejen",
    "sg:orig_category":"Malermestre",
    "sg:phone":"+45 75 38 29 24",
    "sg:postcode":"6600",
    "sg:province":"Danmark",
    "sg:website":"www.arenkiel.dk",
    "wof:name":"Arenkiel, Hans",
    "wof:placetype":"venue"
},
  "geometry": {"coordinates":[9.1396121979,55.4778175354],"type":"Point"}
}