{
  "type": "Feature",
  "properties": {
    "addr:full":"v/ Ole Larsen, Morb\u00e6rv\u00e6nget 63 Frederikssund Danmark 3600",
    "addr:housenumber":"63",
    "addr:postcode":"3600",
    "iso:country":"DK",
    "sg:address":"v/ Ole Larsen, Morb\u00e6rv\u00e6nget 63",
    "sg:city":"Frederikssund",
    "sg:orig_category":"Hobbybetonede foreninger",
    "sg:phone":"+45 47 31 74 79",
    "sg:postcode":"3600",
    "sg:province":"Danmark",
    "wof:name":"St. R\u00f8rb\u00e6k Fiskeklub",
    "wof:placetype":"venue"
},
  "geometry": {"coordinates":[12.0661621094,55.8370323181],"type":"Point"}
}