{
  "type": "Feature",
  "properties": {
    "addr:full":"Byskovcentret, Pantholm 45 Slagelse Danmark 4200",
    "addr:housenumber":"45",
    "addr:postcode":"4200",
    "addr:street":"Pantholm",
    "iso:country":"DK",
    "sg:address":"Byskovcentret, Pantholm 45",
    "sg:city":"Slagelse",
    "sg:orig_category":"Solcentre",
    "sg:phone":"+45 58 50 36 00",
    "sg:postcode":"4200",
    "sg:province":"Danmark",
    "wof:name":"\u00d8stbyens Solcenter",
    "wof:placetype":"venue"
},
  "geometry": {"coordinates":[11.3569850922,55.4050865173],"type":"Point"}
}