{
  "type": "Feature",
  "properties": {
    "iso:country":"DK",
    "sg:address":"B\u00fclowsvej 3",
    "sg:city":"Fredericia",
    "sg:orig_category":"Solcentre",
    "sg:phone":"+45 21 49 95 01",
    "sg:postcode":"7000",
    "sg:province":"Danmark",
    "wof:name":"Fremtidens Solcenter",
    "wof:placetype":"venue"
},
  "geometry": {"coordinates":[9.7591047287,55.566368103],"type":"Point"}
}