{
  "type": "Feature",
  "properties": {
    "addr:full":"Gl. Hadsundvej 4 Mariager Danmark 9550",
    "addr:housenumber":"4",
    "addr:postcode":"9550",
    "addr:street":"Gl. Hadsundvej",
    "iso:country":"DK",
    "sg:address":"Gl. Hadsundvej 4",
    "sg:city":"Mariager",
    "sg:orig_category":"Gartnerier",
    "sg:phone":"+45 98 58 38 97",
    "sg:postcode":"9550",
    "sg:province":"Danmark",
    "wof:name":"Rosenly",
    "wof:placetype":"venue"
},
  "geometry": {"coordinates":[10.0753002167,56.6762161255],"type":"Point"}
}