{
  "type": "Feature",
  "properties": {
    "iso:country":"DK",
    "sg:address":"Fmd.: Egon Madsen, Ingstrupvej 43, R\u00f8dding",
    "sg:city":"Tjele",
    "sg:orig_category":"\u00c3\u2020ldreorganisationer og klubber",
    "sg:phone":"+45 86 65 11 76",
    "sg:postcode":"8830",
    "sg:province":"Danmark",
    "wof:name":"R\u00f8dding Pensionistforening",
    "wof:placetype":"venue"
},
  "geometry": {"coordinates":[9.6264801025,56.4818611145],"type":"Point"}
}