{
  "type": "Feature",
  "properties": {
    "addr:full":"\u00d8sterdalen 18 Gr\u00e6sted Danmark 3230",
    "addr:housenumber":"18",
    "addr:postcode":"3230",
    "addr:street":"Osterdalen",
    "iso:country":"DK",
    "sg:address":"\u00d8sterdalen 18",
    "sg:city":"Gr\u00e6sted",
    "sg:orig_category":"Murermestre",
    "sg:phone":"+45 48 39 25 84",
    "sg:postcode":"3230",
    "sg:province":"Danmark",
    "wof:name":"Johansen, Finn",
    "wof:placetype":"venue"
},
  "geometry": {"coordinates":[-78.6975326538,35.0151481628],"type":"Point"}
}