{
  "type": "Feature",
  "properties": {
    "addr:full":"N\u00f8rregade 58, 2. Holstebro Danmark 7500",
    "addr:housenumber":"58 2",
    "addr:postcode":"7500",
    "addr:street":"Norregade",
    "iso:country":"DK",
    "sg:address":"N\u00f8rregade 58, 2.",
    "sg:city":"Holstebro",
    "sg:orig_category":"Advokater",
    "sg:phone":"+45 97 42 37 33",
    "sg:postcode":"7500",
    "sg:province":"Danmark",
    "wof:name":"M\u00f8ller, Allan B. og Asger Toft",
    "wof:placetype":"venue"
},
  "geometry": {"coordinates":[8.6193523407,56.3623542786],"type":"Point"}
}