{
  "type": "Feature",
  "properties": {
    "addr:full":"Granbakken 5 Glesborg Danmark 8585",
    "addr:housenumber":"5",
    "addr:postcode":"8585",
    "addr:street":"Granbakken",
    "iso:country":"DK",
    "sg:address":"Granbakken 5",
    "sg:city":"Glesborg",
    "sg:orig_category":"Faglige organisationer og -foreninger",
    "sg:phone":"+45 86 38 72 16",
    "sg:postcode":"8585",
    "sg:province":"Danmark",
    "wof:name":"Skibs- og Baadebyggere i Danmark, Foreningen af",
    "wof:placetype":"venue"
},
  "geometry": {"coordinates":[10.7162303925,56.4801025391],"type":"Point"}
}