{
  "type": "Feature",
  "properties": {
    "addr:full":"Bakkevej 2 Bramming Danmark 6740",
    "addr:housenumber":"2",
    "addr:postcode":"6740",
    "addr:street":"Bakkevej",
    "iso:country":"DK",
    "sg:address":"Bakkevej 2",
    "sg:city":"Bramming",
    "sg:orig_category":"Kommunale folkeskoler",
    "sg:phone":"+45 75 17 30 22",
    "sg:postcode":"6740",
    "sg:province":"Danmark",
    "wof:name":"Bakkevejens Skole",
    "wof:placetype":"venue"
},
  "geometry": {"coordinates":[8.7005462646,55.4711303711],"type":"Point"}
}