{
  "type": "Feature",
  "properties": {
    "iso:country":"DK",
    "sg:address":"Fmd.: Elisabeth S\u00f8rensen, Lillemarken 8",
    "sg:city":"Harpelunde",
    "sg:orig_category":"Legestuer",
    "sg:postcode":"4912",
    "sg:province":"Danmark",
    "wof:name":"H\u00f8jreby legestue",
    "wof:placetype":"venue"
},
  "geometry": {"coordinates":[11.0865898132,54.8770065308],"type":"Point"}
}