{
  "type": "Feature",
  "properties": {
    "addr:full":"Frilandsvej 8 Vr\u00e5 Danmark 9760",
    "addr:housenumber":"8",
    "addr:postcode":"9760",
    "addr:street":"Frilandsvej",
    "iso:country":"DK",
    "sg:address":"Frilandsvej 8",
    "sg:city":"Vr\u00e5",
    "sg:orig_category":"Vaskerier",
    "sg:phone":"+45 99 67 21 00",
    "sg:postcode":"9760",
    "sg:province":"Danmark",
    "sg:website":"www.vdv.dk",
    "wof:name":"Vraa Dampvaskeri A/S",
    "wof:placetype":"venue"
},
  "geometry": {"coordinates":[9.9557209015,57.3569564819],"type":"Point"}
}