{
  "type": "Feature",
  "properties": {
    "addr:full":"V\u00e6vergangen 30 Karlslunde Danmark 2690",
    "addr:housenumber":"30",
    "addr:postcode":"2690",
    "addr:street":"Vaevergangen",
    "iso:country":"DK",
    "sg:address":"V\u00e6vergangen 30",
    "sg:city":"Karlslunde",
    "sg:orig_category":"Gearmotorer",
    "sg:phone":"+45 46 15 45 00",
    "sg:postcode":"2690",
    "sg:province":"Danmark",
    "wof:name":"Brevini Danmark A/S",
    "wof:placetype":"venue"
},
  "geometry": {"coordinates":[12.2383127213,55.5699501038],"type":"Point"}
}