{
  "type": "Feature",
  "properties": {
    "addr:full":"Algade 59 Ringe Danmark 5750",
    "addr:housenumber":"59",
    "addr:postcode":"5750",
    "addr:street":"Algade",
    "iso:country":"DK",
    "sg:address":"Algade 59",
    "sg:city":"Ringe",
    "sg:orig_category":"Dag- og distriktsblade",
    "sg:phone":"+45 62 62 12 60",
    "sg:postcode":"5750",
    "sg:province":"Danmark",
    "wof:name":"Fyns Amts Avis",
    "wof:placetype":"venue"
},
  "geometry": {"coordinates":[10.4783201218,55.2394676208],"type":"Point"}
}