{
  "type": "Feature",
  "properties": {
    "addr:full":"Kolonivej 7, 1. sal, Filadelfia Dianalund Danmark 4293",
    "addr:housenumber":"7 1 sal",
    "addr:postcode":"4293",
    "addr:street":"Kolonivej;Filadelfia",
    "iso:country":"DK",
    "sg:address":"Kolonivej 7, 1. sal, Filadelfia",
    "sg:city":"Dianalund",
    "sg:orig_category":"Jordemodercentre",
    "sg:phone":"+45 58 26 46 46",
    "sg:postcode":"4293",
    "sg:province":"Danmark",
    "wof:name":"Jordemoderkonsultationen",
    "wof:placetype":"venue"
},
  "geometry": {"coordinates":[11.4945745468,55.5332489014],"type":"Point"}
}