{
  "type": "Feature",
  "properties": {
    "iso:country":"DK",
    "sg:address":"Estrupvej 6 A",
    "sg:city":"Esbjerg",
    "sg:orig_category":"Betonvarefabrikker",
    "sg:phone":"+45 75 45 10 11",
    "sg:postcode":"6700",
    "sg:province":"Danmark",
    "sg:website":"www.grindsted-betonvarefabrik.dk",
    "wof:name":"Grindsted Betonvarefabrik A/S",
    "wof:placetype":"venue"
},
  "geometry": {"coordinates":[8.455653,55.462063],"type":"Point"}
}