{
  "type": "Feature",
  "properties": {
    "addr:full":"Bygaden 15, Lejre Lejre Danmark 4320",
    "addr:housenumber":"15",
    "addr:postcode":"4320",
    "addr:street":"Bygaden",
    "iso:country":"DK",
    "sg:address":"Bygaden 15, Lejre",
    "sg:city":"Lejre",
    "sg:orig_category":"INGENI\u00c3\u02dcRER",
    "sg:phone":"+45 46 48 20 60",
    "sg:postcode":"4320",
    "sg:province":"Danmark",
    "wof:name":"Pro-Consult A/S",
    "wof:placetype":"venue"
},
  "geometry": {"coordinates":[11.9678316116,55.6005630493],"type":"Point"}
}