{
  "type": "Feature",
  "properties": {
    "addr:full":"Ballerup Byvej 115 Ballerup Danmark 2750",
    "addr:housenumber":"115",
    "addr:postcode":"2750",
    "addr:street":"Ballerup Byvej",
    "iso:country":"DK",
    "sg:address":"Ballerup Byvej 115",
    "sg:city":"Ballerup",
    "sg:orig_category":"Benzinstationer",
    "sg:phone":"+45 44 97 02 21",
    "sg:postcode":"2750",
    "sg:province":"Danmark",
    "wof:name":"Statoil Servicenter",
    "wof:placetype":"venue"
},
  "geometry": {"coordinates":[12.3840284348,55.728969574],"type":"Point"}
}