{
  "type": "Feature",
  "properties": {
    "addr:full":"Parallelvej 11 Frederikshavn Danmark 9900",
    "addr:housenumber":"11",
    "addr:postcode":"9900",
    "addr:street":"Parallelvej",
    "iso:country":"DK",
    "sg:address":"Parallelvej 11",
    "sg:city":"Frederikshavn",
    "sg:orig_category":"Ejendomshandel",
    "sg:phone":"+45 98 43 43 00",
    "sg:postcode":"9900",
    "sg:province":"Danmark",
    "sg:website":"www.calundan.dk",
    "wof:name":"Calundan, Ejendomsm\u00e6glerfirmaet",
    "wof:placetype":"venue"
},
  "geometry": {"coordinates":[10.5340442657,57.4394645691],"type":"Point"}
}