{
  "type": "Feature",
  "properties": {
    "iso:country":"DK",
    "sg:address":"Sognepr\u00e6st: Bjarne Hougaard (K/B), Hvamvej 95, Hvam",
    "sg:city":"Aalestrup",
    "sg:orig_category":"Kirkesogne",
    "sg:phone":"+45 98 64 80 11",
    "sg:postcode":"9620",
    "sg:province":"Danmark",
    "wof:name":"Hvam og Hvilsom Sogne",
    "wof:placetype":"venue"
},
  "geometry": {"coordinates":[9.4901504517,56.6938285828],"type":"Point"}
}