{
  "type": "Feature",
  "properties": {
    "addr:full":"Bjergbanksvej 6 Middelfart Danmark 5500",
    "addr:housenumber":"6",
    "addr:postcode":"5500",
    "addr:street":"Bjergbanksvej",
    "iso:country":"DK",
    "sg:address":"Bjergbanksvej 6",
    "sg:city":"Middelfart",
    "sg:orig_category":"Fritidsklubber",
    "sg:phone":"+45 64 41 26 48",
    "sg:postcode":"5500",
    "sg:province":"Danmark",
    "wof:name":"Fritidscentret Bjergbanken",
    "wof:placetype":"venue"
},
  "geometry": {"coordinates":[9.7339916229,55.5010566711],"type":"Point"}
}