{
  "type": "Feature",
  "properties": {
    "addr:full":"Industriparken 12, Skrydstrup Vojens Danmark 6500",
    "addr:housenumber":"12",
    "addr:postcode":"6500",
    "addr:street":"Industriparken;Skrydstrup",
    "iso:country":"DK",
    "sg:address":"Industriparken 12, Skrydstrup",
    "sg:city":"Vojens",
    "sg:orig_category":"Glas- og glasvareindustri",
    "sg:phone":"+45 74 54 25 55",
    "sg:postcode":"6500",
    "sg:province":"Danmark",
    "sg:website":"www.mirit.dk",
    "wof:name":"Mirit-Glas",
    "wof:placetype":"venue"
},
  "geometry": {"coordinates":[9.2987146378,55.2457237244],"type":"Point"}
}