{
  "type": "Feature",
  "properties": {
    "iso:country":"DK",
    "sg:address":"Storegade 50",
    "sg:city":"Brande",
    "sg:orig_category":"Boghandlere",
    "sg:phone":"+45 97 18 05 00",
    "sg:postcode":"7330",
    "sg:province":"Danmark",
    "wof:name":"B\u00f8ger og Papir",
    "wof:placetype":"venue"
},
  "geometry": {"coordinates":[9.128329277,55.9423675537],"type":"Point"}
}