{
  "type": "Feature",
  "properties": {
    "addr:full":"Havnevej 45 Roskilde Danmark 4000",
    "addr:housenumber":"45",
    "addr:postcode":"4000",
    "addr:street":"Havnevej",
    "iso:country":"DK",
    "sg:address":"Havnevej 45",
    "sg:city":"Roskilde",
    "sg:orig_category":"Skibsproviantering",
    "sg:phone":"+45 46 35 09 24",
    "sg:postcode":"4000",
    "sg:province":"Danmark",
    "wof:name":"Skibsprovianten ApS",
    "wof:placetype":"venue"
},
  "geometry": {"coordinates":[12.0764427185,55.6499443054],"type":"Point"}
}