{
  "type": "Feature",
  "properties": {
    "addr:full":"Strandg\u00e5rdsh\u00f8j 48 Ebeltoft Danmark 8400",
    "addr:housenumber":"48",
    "addr:postcode":"8400",
    "addr:street":"Strandgaardshoj",
    "iso:country":"DK",
    "sg:address":"Strandg\u00e5rdsh\u00f8j 48",
    "sg:city":"Ebeltoft",
    "sg:orig_category":"Lokalpsykiatri",
    "sg:phone":"+45 86 34 28 53",
    "sg:postcode":"8400",
    "sg:province":"Danmark",
    "wof:name":"Bost\u00f8tten og V\u00e6restedet, Lokalpsykiatrien Ebeltoft Kommune",
    "wof:placetype":"venue"
},
  "geometry": {"coordinates":[10.6778745651,56.199798584],"type":"Point"}
}