{
  "type": "Feature",
  "properties": {
    "iso:country":"DK",
    "sg:address":"Englandsv. 11 ",
    "sg:city":"Vejle",
    "sg:classifiers":[
        {
            "category":"Banks & Credit Unions",
            "subcategory":"Bank",
            "type":"Services"
        }
    ],
    "sg:phone":"+45 75 72 37 55",
    "sg:postcode":"7100",
    "sg:province":"Danmark",
    "sg:tags":[
        "banking",
        "institution"
    ],
    "wof:name":"HEVICO A/S",
    "wof:placetype":"venue"
},
  "geometry": {"coordinates":[9.551196,55.731815],"type":"Point"}
}