{
  "type": "Feature",
  "properties": {
    "iso:country":"DK",
    "sg:address":"Sm\u00e5k\u00e6rvej 64, Hejsager",
    "sg:city":"Haderslev",
    "sg:orig_category":"Alternativ behandling",
    "sg:phone":"+45 74 57 14 11",
    "sg:postcode":"6100",
    "sg:province":"Danmark",
    "wof:name":"Olling, Tove",
    "wof:placetype":"venue"
},
  "geometry": {"coordinates":[9.4879703522,55.2505493164],"type":"Point"}
}