{
  "type": "Feature",
  "properties": {
    "addr:full":"Korsh\u00f8j 4 Frederikssund Danmark 3600",
    "addr:housenumber":"4",
    "addr:postcode":"3600",
    "addr:street":"Korshoj",
    "iso:country":"DK",
    "sg:address":"Korsh\u00f8j 4",
    "sg:city":"Frederikssund",
    "sg:orig_category":"Autoforhandlere",
    "sg:phone":"+45 47 31 05 10",
    "sg:postcode":"3600",
    "sg:province":"Danmark",
    "wof:name":"AASBERG BIL A/S",
    "wof:placetype":"venue"
},
  "geometry": {"coordinates":[12.0661621094,55.8370323181],"type":"Point"}
}