{
  "type": "Feature",
  "properties": {
    "addr:full":"Skanderborgvej 230 Viby Danmark 8260",
    "addr:housenumber":"230",
    "addr:postcode":"8260",
    "addr:street":"Skanderborgvej",
    "iso:country":"DK",
    "sg:address":"Skanderborgvej 230",
    "sg:city":"Viby",
    "sg:orig_category":"Gallerier",
    "sg:phone":"+45 86 28 91 86",
    "sg:postcode":"8260",
    "sg:province":"Danmark",
    "sg:website":"www.ravnsbjerghus.dk",
    "wof:name":"Ravnsbjerghus",
    "wof:placetype":"venue"
},
  "geometry": {"coordinates":[10.1432914734,56.11951828],"type":"Point"}
}