{
  "type": "Feature",
  "properties": {
    "iso:country":"DK",
    "sg:address":"Ryvangs All\u00e9 87",
    "sg:city":"Hellerup",
    "sg:orig_category":"Grillbarer",
    "sg:phone":"+45 39 62 73 16",
    "sg:postcode":"2900",
    "sg:province":"Danmark",
    "wof:name":"Big inn Grill",
    "wof:placetype":"venue"
},
  "geometry": {"coordinates":[12.5680599213,55.7315483093],"type":"Point"}
}