{
  "type": "Feature",
  "properties": {
    "iso:country":"DK",
    "sg:address":"Vestergade 9 C",
    "sg:city":"Helsinge",
    "sg:orig_category":"Diners transportables",
    "sg:phone":"+45 20 49 10 81",
    "sg:postcode":"3200",
    "sg:province":"Danmark",
    "wof:name":"Helsinge Dinner",
    "wof:placetype":"venue"
},
  "geometry": {"coordinates":[12.1969099045,56.0220947266],"type":"Point"}
}