{
  "type": "Feature",
  "properties": {
    "addr:full":"Staldg\u00e5rdsgade 12 Randers Danmark 8900",
    "addr:housenumber":"12",
    "addr:postcode":"8900",
    "addr:street":"Staldgaardsgade",
    "iso:country":"DK",
    "sg:address":"Staldg\u00e5rdsgade 12",
    "sg:city":"Randers",
    "sg:orig_category":"Antikvariater",
    "sg:phone":"+45 86 41 43 11",
    "sg:postcode":"8900",
    "sg:province":"Danmark",
    "wof:name":"O. R. B\u00f8ger & Video",
    "wof:placetype":"venue"
},
  "geometry": {"coordinates":[10.0311899185,56.4612007141],"type":"Point"}
}