{
  "type": "Feature",
  "properties": {
    "addr:full":"Havnegade 5 A Frederikssund Danmark 3600",
    "addr:housenumber":"5 a",
    "addr:postcode":"3600",
    "addr:street":"Havnegade",
    "iso:country":"DK",
    "sg:address":"Havnegade 5 A",
    "sg:city":"Frederikssund",
    "sg:orig_category":"Forsikringer",
    "sg:phone":"+45 47 36 03 50",
    "sg:postcode":"3600",
    "sg:province":"Danmark",
    "wof:name":"Codan Forsikring",
    "wof:placetype":"venue"
},
  "geometry": {"coordinates":[12.0569238663,55.837146759],"type":"Point"}
}