{
  "type": "Feature",
  "properties": {
    "addr:full":"v/ Tj\u00f8rneg\u00e5rdsskolen, Holb\u00e6kvej 65 Roskilde Danmark 4000",
    "addr:housenumber":"65",
    "addr:postcode":"4000",
    "addr:street":"Holbaekvej",
    "iso:country":"DK",
    "sg:address":"v/ Tj\u00f8rneg\u00e5rdsskolen, Holb\u00e6kvej 65",
    "sg:city":"Roskilde",
    "sg:orig_category":"Kulturcentre",
    "sg:phone":"+45 46 33 25 19",
    "sg:postcode":"4000",
    "sg:province":"Danmark",
    "wof:name":"Tj\u00f8rneg\u00e5rdsskolens Kulturcenter",
    "wof:placetype":"venue"
},
  "geometry": {"coordinates":[12.0909376144,55.6404838562],"type":"Point"}
}