{
  "type": "Feature",
  "properties": {
    "iso:country":"DK",
    "sg:address":"Ambolten 13",
    "sg:city":"Kolding",
    "sg:classifiers":[
        {
            "category":"Taxi",
            "type":"Transportation"
        }
    ],
    "sg:phone":"+45 75 52 15 00",
    "sg:postcode":"6000",
    "sg:province":"Danmark",
    "wof:name":"Kolding Taxa",
    "wof:placetype":"venue"
},
  "geometry": {"coordinates":[9.4753656387,55.465637207],"type":"Point"}
}