{
  "type": "Feature",
  "properties": {
    "addr:full":"Langebjergv\u00e6nget 12 Roskilde Danmark 4000",
    "addr:housenumber":"12",
    "addr:postcode":"4000",
    "addr:street":"Langebjergvaenget",
    "iso:country":"DK",
    "sg:address":"Langebjergv\u00e6nget 12",
    "sg:city":"Roskilde",
    "sg:orig_category":"\u00c3\u02dcl- og mineralvandsdepoter",
    "sg:phone":"+45 46 75 70 54",
    "sg:postcode":"4000",
    "sg:province":"Danmark",
    "wof:name":"Faxe Ceres Thor,Roskilde Depot",
    "wof:placetype":"venue"
},
  "geometry": {"coordinates":[12.1425247192,55.6468238831],"type":"Point"}
}