{
  "type": "Feature",
  "properties": {
    "addr:full":"Kyperstien 1, Hesselballe Uldum Danmark 7171",
    "addr:housenumber":"1",
    "addr:postcode":"7171",
    "addr:street":"Kyperstien",
    "iso:country":"DK",
    "sg:address":"Kyperstien 1, Hesselballe",
    "sg:city":"Uldum",
    "sg:orig_category":"Skorstensfejere",
    "sg:phone":"+45 75 67 86 48",
    "sg:postcode":"7171",
    "sg:province":"Danmark",
    "wof:name":"Pedersen, Chr. H\u00f8gild",
    "wof:placetype":"venue"
},
  "geometry": {"coordinates":[9.5898447037,55.8469467163],"type":"Point"}
}