{
  "type": "Feature",
  "properties": {
    "addr:full":"Birkholmvej 2, Osted Roskilde Danmark 4000",
    "addr:housenumber":"2",
    "addr:postcode":"4000",
    "addr:street":"Birkholmvej;Osted",
    "iso:country":"DK",
    "sg:address":"Birkholmvej 2, Osted",
    "sg:city":"Roskilde",
    "sg:orig_category":"Gravemaskiner",
    "sg:phone":"+45 46 49 75 75",
    "sg:postcode":"4000",
    "sg:province":"Danmark",
    "wof:name":"Hydrema A/S",
    "wof:placetype":"venue"
},
  "geometry": {"coordinates":[12.0909376144,55.6404838562],"type":"Point"}
}