{
  "type": "Feature",
  "properties": {
    "addr:full":"Ringvej 24, Glyng\u00f8re Roslev Danmark 7870",
    "addr:housenumber":"24",
    "addr:postcode":"7870",
    "addr:street":"Ringvej;Glyngore",
    "iso:country":"DK",
    "sg:address":"Ringvej 24, Glyng\u00f8re",
    "sg:city":"Roslev",
    "sg:orig_category":"Diskoteker",
    "sg:phone":"+45 97 73 17 66",
    "sg:postcode":"7870",
    "sg:province":"Danmark",
    "wof:name":"Downstairs, Diskotek",
    "wof:placetype":"venue"
},
  "geometry": {"coordinates":[8.8715353012,56.7570304871],"type":"Point"}
}