{
  "type": "Feature",
  "properties": {
    "addr:full":"Nordhavnsvej 5 A Haderslev Danmark 6100",
    "addr:housenumber":"5 a",
    "addr:postcode":"6100",
    "addr:street":"Nordhavnsvej",
    "iso:country":"DK",
    "sg:address":"Nordhavnsvej 5 A",
    "sg:city":"Haderslev",
    "sg:orig_category":"El-motorer",
    "sg:phone":"+45 74 53 19 38",
    "sg:postcode":"6100",
    "sg:province":"Danmark",
    "wof:name":"Elektrog\u00e5rden",
    "wof:placetype":"venue"
},
  "geometry": {"coordinates":[9.498632431,55.2517700195],"type":"Point"}
}