{
  "type": "Feature",
  "properties": {
    "addr:full":"Gammel Jernbanevej 7 Kongens Lyngby Danmark 2800",
    "addr:housenumber":"7",
    "addr:postcode":"2800",
    "addr:street":"Gammel Jernbanevej",
    "iso:country":"DK",
    "sg:address":"Gammel Jernbanevej 7",
    "sg:city":"Kongens Lyngby",
    "sg:orig_category":"Garn",
    "sg:phone":"+45 45 88 10 88",
    "sg:postcode":"2800",
    "sg:province":"Danmark",
    "sg:website":"www.uldstedet.dk",
    "wof:name":"Uldstedet",
    "wof:placetype":"venue"
},
  "geometry": {"coordinates":[12.5049123764,55.7690544128],"type":"Point"}
}