{
  "type": "Feature",
  "properties": {
    "addr:full":"Fmd.: Grethe Dyrby, Egevang 4 Skanderborg Danmark 8660",
    "addr:housenumber":"4",
    "addr:postcode":"8660",
    "addr:street":"Egevang",
    "iso:country":"DK",
    "sg:address":"Fmd.: Grethe Dyrby, Egevang 4",
    "sg:city":"Skanderborg",
    "sg:orig_category":"Kulturelle foreninger",
    "sg:phone":"+45 86 52 30 09",
    "sg:postcode":"8660",
    "sg:province":"Danmark",
    "wof:name":"Skanderborg Teaterforening, B\u00f8rneteatret",
    "wof:placetype":"venue"
},
  "geometry": {"coordinates":[9.929974556,56.0380249023],"type":"Point"}
}