{
  "type": "Feature",
  "properties": {
    "addr:full":"Lygten 47-49 K\u00f8benhavn NV Danmark 2400",
    "addr:housenumber":"47-49",
    "addr:postcode":"2400",
    "addr:street":"Lygten",
    "iso:country":"DK",
    "sg:address":"Lygten 47-49",
    "sg:city":"K\u00f8benhavn NV",
    "sg:orig_category":"Filmproduktion",
    "sg:phone":"+45 35 81 17 00",
    "sg:postcode":"2400",
    "sg:province":"Danmark",
    "sg:website":"www.johan-ankerstjerne.dk",
    "wof:name":"Ankerstjerne, Johan",
    "wof:placetype":"venue"
},
  "geometry": {"coordinates":[-117.02272033689999,38.5024604797],"type":"Point"}
}