{
  "type": "Feature",
  "properties": {
    "iso:country":"DK",
    "sg:address":"Marselis Boulevard 36, 2.",
    "sg:city":"\u00c5rhus C",
    "sg:orig_category":"Indretningsarkitekter",
    "sg:phone":"+45 86 76 01 90",
    "sg:postcode":"8000",
    "sg:province":"Danmark",
    "wof:name":"Schmidt, Lone",
    "wof:placetype":"venue"
},
  "geometry": {"coordinates":[-116.27327728269999,32.6635398865],"type":"Point"}
}