{
  "type": "Feature",
  "properties": {
    "addr:full":"Frederiksgade 48 B, st. \u00c5rhus C Danmark 8000",
    "addr:housenumber":"48",
    "addr:postcode":"8000",
    "addr:street":"Frederiksgade;B St.",
    "iso:country":"DK",
    "sg:address":"Frederiksgade 48 B, st.",
    "sg:city":"\u00c5rhus C",
    "sg:orig_category":"Grillbarer",
    "sg:phone":"+45 86 12 81 22",
    "sg:postcode":"8000",
    "sg:province":"Danmark",
    "wof:name":"Alt i 1",
    "wof:placetype":"venue"
},
  "geometry": {"coordinates":[12.5930995941,55.6829986572],"type":"Point"}
}