{
  "type": "Feature",
  "properties": {
    "addr:full":"Fr\u00f8g\u00e5rd All\u00e9 8, H\u00f8je Taastrup Taastrup Danmark 2630",
    "addr:housenumber":"8",
    "addr:postcode":"2630",
    "addr:street":"Frogaard Alle\u0301",
    "iso:country":"DK",
    "sg:address":"Fr\u00f8g\u00e5rd All\u00e9 8, H\u00f8je Taastrup",
    "sg:city":"Taastrup",
    "sg:orig_category":"Private skoler",
    "sg:phone":"+45 43 52 19 59",
    "sg:postcode":"2630",
    "sg:province":"Danmark",
    "sg:website":"www.sanktpaulsskole.dk",
    "wof:name":"Skt. Pauls Skole",
    "wof:placetype":"venue"
},
  "geometry": {"coordinates":[12.3020896912,55.6506767273],"type":"Point"}
}