{
  "type": "Feature",
  "properties": {
    "addr:full":"Gr\u00e6nsevej 3, Foldingbro Lintrup Danmark 6660",
    "addr:housenumber":"3",
    "addr:postcode":"6660",
    "addr:street":"Graensevej",
    "iso:country":"DK",
    "sg:address":"Gr\u00e6nsevej 3, Foldingbro",
    "sg:city":"Lintrup",
    "sg:orig_category":"Trailere",
    "sg:phone":"+45 74 85 54 98",
    "sg:postcode":"6660",
    "sg:province":"Danmark",
    "wof:name":"Foldingbro Trailercenter",
    "wof:placetype":"venue"
},
  "geometry": {"coordinates":[8.9733600616,55.408870697],"type":"Point"}
}