{
  "type": "Feature",
  "properties": {
    "addr:full":"Posthustorvet 2 Skive Danmark 7800",
    "addr:housenumber":"2",
    "addr:postcode":"7800",
    "addr:street":"Posthustorvet",
    "iso:country":"DK",
    "sg:address":"Posthustorvet 2",
    "sg:city":"Skive",
    "sg:orig_category":"Forsikringer",
    "sg:phone":"+45 96 14 06 60",
    "sg:postcode":"7800",
    "sg:province":"Danmark",
    "wof:name":"Tryg-Baltica",
    "wof:placetype":"venue"
},
  "geometry": {"coordinates":[9.0255708694,56.5653419495],"type":"Point"}
}