{
  "type": "Feature",
  "properties": {
    "addr:full":"Skovg\u00e5rdsvej 2 Ribe Danmark 6760",
    "addr:housenumber":"2",
    "addr:postcode":"6760",
    "addr:street":"Skovgaardsvej",
    "iso:country":"DK",
    "sg:address":"Skovg\u00e5rdsvej 2",
    "sg:city":"Ribe",
    "sg:orig_category":"Rideskoler",
    "sg:phone":"+45 75 42 18 47",
    "sg:postcode":"6760",
    "sg:province":"Danmark",
    "wof:name":"Ribe Ride Center",
    "wof:placetype":"venue"
},
  "geometry": {"coordinates":[8.7692670822,55.3425598145],"type":"Point"}
}