{
  "type": "Feature",
  "properties": {
    "addr:full":"Hovvejen 5, Skjoldelev Sabro Danmark 8471",
    "addr:housenumber":"5",
    "addr:postcode":"8471",
    "addr:street":"Hovvejen",
    "iso:country":"DK",
    "sg:address":"Hovvejen 5, Skjoldelev",
    "sg:city":"Sabro",
    "sg:orig_category":"Diners transportables",
    "sg:phone":"+45 86 94 95 29",
    "sg:postcode":"8471",
    "sg:province":"Danmark",
    "wof:name":"Oplandets Mobile K\u00f8kken",
    "wof:placetype":"venue"
},
  "geometry": {"coordinates":[10.0375204086,56.2109718323],"type":"Point"}
}