{
  "type": "Feature",
  "properties": {
    "addr:full":"Langgade 45 Gadbjerg Danmark 7321",
    "addr:housenumber":"45",
    "addr:postcode":"7321",
    "addr:street":"Langgade",
    "iso:country":"DK",
    "sg:address":"Langgade 45",
    "sg:city":"Gadbjerg",
    "sg:orig_category":"Apoteker og -udsalg",
    "sg:phone":"+45 75 87 60 34",
    "sg:postcode":"7321",
    "sg:province":"Danmark",
    "wof:name":"H\u00e5ndk\u00f8bsudsalg",
    "wof:placetype":"venue"
},
  "geometry": {"coordinates":[9.3245782852,55.7726020813],"type":"Point"}
}