{
  "type": "Feature",
  "properties": {
    "addr:full":"Jomfrustien 3 Haderslev Danmark 6100",
    "addr:housenumber":"3",
    "addr:postcode":"6100",
    "addr:street":"Jomfrustien",
    "iso:country":"DK",
    "sg:address":"Jomfrustien 3",
    "sg:city":"Haderslev",
    "sg:classifiers":[
        {
            "category":"Restaurant",
            "type":"Food & Drink"
        }
    ],
    "sg:phone":"+45 74 53 01 20",
    "sg:postcode":"6100",
    "sg:province":"Danmark",
    "wof:name":"China Barbecue",
    "wof:placetype":"venue"
},
  "geometry": {"coordinates":[9.488951683,55.2511253357],"type":"Point"}
}