{
  "type": "Feature",
  "properties": {
    "iso:country":"DK",
    "sg:address":"Drastrup Skovvej 33 A",
    "sg:city":"Aalborg SV",
    "sg:orig_category":"Isolering",
    "sg:phone":"+45 98 18 85 55",
    "sg:postcode":"9200",
    "sg:province":"Danmark",
    "wof:name":"Jensen Isolering A/S, J\u00f8rgen",
    "wof:placetype":"venue"
},
  "geometry": {"coordinates":[9.8663339615,57.0029602051],"type":"Point"}
}