{
  "type": "Feature",
  "properties": {
    "addr:full":"Industrivej 34 Vamdrup Danmark 6580",
    "addr:housenumber":"34",
    "addr:postcode":"6580",
    "addr:street":"Industrivej",
    "iso:country":"DK",
    "sg:address":"Industrivej 34",
    "sg:city":"Vamdrup",
    "sg:orig_category":"Maskinfabrikker",
    "sg:phone":"+45 75 58 18 55",
    "sg:postcode":"6580",
    "sg:province":"Danmark",
    "wof:name":"H\u00f8rlyck og Kongsted Maskinfabrik A/S",
    "wof:placetype":"venue"
},
  "geometry": {"coordinates":[9.2995185852,55.4344673157],"type":"Point"}
}