{
  "type": "Feature",
  "properties": {
    "addr:full":"Sct. Laurentii Vej 28 Skagen Danmark 9990",
    "addr:housenumber":"28",
    "addr:postcode":"9990",
    "addr:street":"Sct. Laurentii Vej",
    "iso:country":"DK",
    "sg:address":"Sct. Laurentii Vej 28",
    "sg:city":"Skagen",
    "sg:orig_category":"Slagter og viktualie",
    "sg:phone":"+45 98 44 17 00",
    "sg:postcode":"9990",
    "sg:province":"Danmark",
    "wof:name":"Super Brugsen",
    "wof:placetype":"venue"
},
  "geometry": {"coordinates":[10.5908346176,57.7229957581],"type":"Point"}
}