{
  "type": "Feature",
  "properties": {
    "addr:full":"Fmd.: S\u00f8ren Kiersgaard, Klintevej 14, Postboks 154 Faaborg Danmark 5600",
    "addr:housenumber":"14;154",
    "addr:postcode":"5600",
    "addr:street":"Klintevej",
    "iso:country":"DK",
    "sg:address":"Fmd.: S\u00f8ren Kiersgaard, Klintevej 14, Postboks 154",
    "sg:city":"Faaborg",
    "sg:orig_category":"Kulturelle foreninger",
    "sg:phone":"+45 62 61 26 00",
    "sg:postcode":"5600",
    "sg:province":"Danmark",
    "wof:name":"Tr\u00e6skibspladsen",
    "wof:placetype":"venue"
},
  "geometry": {"coordinates":[10.2400531769,55.0950622559],"type":"Point"}
}