{
  "type": "Feature",
  "properties": {
    "addr:full":"Vestervang 7 Skanderborg Danmark 8660",
    "addr:housenumber":"7",
    "addr:postcode":"8660",
    "addr:street":"Vestervang",
    "iso:country":"DK",
    "sg:address":"Vestervang 7",
    "sg:city":"Skanderborg",
    "sg:orig_category":"Slagter og viktualie",
    "sg:phone":"+45 86 51 28 24",
    "sg:postcode":"8660",
    "sg:province":"Danmark",
    "sg:website":"www.home1.stofanet.dk/oko",
    "wof:name":"Mors\u00f8, Slagter",
    "wof:placetype":"venue"
},
  "geometry": {"coordinates":[9.922375679,56.0350379944],"type":"Point"}
}