{
  "type": "Feature",
  "properties": {
    "addr:full":"Ruten 6 K Br\u00f8nsh\u00f8j Danmark 2700",
    "addr:housenumber":"6 k",
    "addr:postcode":"2700",
    "addr:street":"Ruten;Bronshoj Danmark",
    "iso:country":"DK",
    "sg:address":"Ruten 6 K",
    "sg:city":"Br\u00f8nsh\u00f8j",
    "sg:orig_category":"Grillbarer",
    "sg:phone":"+45 38 80 87 86",
    "sg:postcode":"2700",
    "sg:province":"Danmark",
    "wof:name":"Gonzales Cantina",
    "wof:placetype":"venue"
},
  "geometry": {"coordinates":[7.481180191,52.5436515808],"type":"Point"}
}