{
  "type": "Feature",
  "properties": {
    "addr:full":"Klosterbakken 2 Odense C Danmark 5000",
    "addr:housenumber":"2",
    "addr:postcode":"5000",
    "addr:street":"Klosterbakken",
    "iso:country":"DK",
    "sg:address":"Klosterbakken 2",
    "sg:city":"Odense C",
    "sg:orig_category":"Kirker",
    "sg:phone":"+45 66 12 03 92",
    "sg:postcode":"5000",
    "sg:province":"Danmark",
    "wof:name":"Odense Domkirke - Sct. Knuds Kirke",
    "wof:placetype":"venue"
},
  "geometry": {"coordinates":[10.3882007599,55.3936462402],"type":"Point"}
}