{
  "type": "Feature",
  "properties": {
    "addr:full":"Fmd.: Poul Pedersen, Gr\u00f8nneled 18 Albertslund Danmark 2620",
    "addr:housenumber":"18",
    "addr:postcode":"2620",
    "addr:street":"Poul;Gronneled",
    "iso:country":"DK",
    "sg:address":"Fmd.: Poul Pedersen, Gr\u00f8nneled 18",
    "sg:city":"Albertslund",
    "sg:orig_category":"\u00c3\u2020ldreorganisationer og klubber",
    "sg:phone":"+45 43 64 96 05",
    "sg:postcode":"2620",
    "sg:province":"Danmark",
    "wof:name":"Solhusene/Gr\u00f8nneled Pensionistklub",
    "wof:placetype":"venue"
},
  "geometry": {"coordinates":[12.3517179489,55.6568450928],"type":"Point"}
}