{
  "type": "Feature",
  "properties": {
    "addr:full":"Pr\u00e6stevangen 8 Dannemare Danmark 4983",
    "addr:housenumber":"8",
    "addr:postcode":"4983",
    "addr:street":"Praestevangen",
    "iso:country":"DK",
    "sg:address":"Pr\u00e6stevangen 8",
    "sg:city":"Dannemare",
    "sg:orig_category":"Revisorer",
    "sg:phone":"+45 54 94 46 64",
    "sg:postcode":"4983",
    "sg:province":"Danmark",
    "wof:name":"Mortensen, Bent",
    "wof:placetype":"venue"
},
  "geometry": {"coordinates":[11.1857805252,54.7613449097],"type":"Point"}
}