{
  "type": "Feature",
  "properties": {
    "addr:full":"M\u00f8lbjergg\u00e5rdvej 7, G\u00f8tterup Toftlund Danmark 6520",
    "addr:housenumber":"7",
    "addr:postcode":"6520",
    "addr:street":"Molbjerggaardvej;Gotterup",
    "iso:country":"DK",
    "sg:address":"M\u00f8lbjergg\u00e5rdvej 7, G\u00f8tterup",
    "sg:city":"Toftlund",
    "sg:orig_category":"Maskinstationer",
    "sg:phone":"+45 20 13 36 63",
    "sg:postcode":"6520",
    "sg:province":"Danmark",
    "wof:name":"CB Kartoffelservice",
    "wof:placetype":"venue"
},
  "geometry": {"coordinates":[9.0629367828,55.1926651001],"type":"Point"}
}