{
  "type": "Feature",
  "properties": {
    "addr:full":"Blegdamsvej 30 K\u00f8benhavn N Danmark 2200",
    "addr:housenumber":"30",
    "addr:postcode":"2200",
    "addr:street":"Blegdamsvej;N Danmark",
    "iso:country":"DK",
    "sg:address":"Blegdamsvej 30",
    "sg:city":"K\u00f8benhavn N",
    "sg:orig_category":"Psykologer, praktiserende",
    "sg:phone":"+45 35 37 38 81",
    "sg:postcode":"2200",
    "sg:province":"Danmark",
    "wof:name":"Javas Psykolog Praksis",
    "wof:placetype":"venue"
},
  "geometry": {"coordinates":[-94.46161651609999,47.8553733826],"type":"Point"}
}