{
  "type": "Feature",
  "properties": {
    "iso:country":"DK",
    "sg:address":"Birk Centerpark 15",
    "sg:city":"Herning",
    "sg:orig_category":"Boghandlere",
    "sg:phone":"+45 97 21 66 12",
    "sg:postcode":"7400",
    "sg:province":"Danmark",
    "sg:website":"www.hih.dk",
    "wof:name":"Birk Studieboghandel",
    "wof:placetype":"venue"
},
  "geometry": {"coordinates":[9.0272855759,56.1284103394],"type":"Point"}
}