{
  "type": "Feature",
  "properties": {
    "iso:country":"DK",
    "sg:address":"Flensborgvej 185 ",
    "sg:city":"Aabenraa",
    "sg:classifiers":[
        {
            "category":"Utilities",
            "subcategory":"Electric",
            "type":"Services"
        }
    ],
    "sg:phone":"+45 74 31 41 41",
    "sg:postcode":"6200",
    "sg:province":"Danmark",
    "sg:tags":[
        "electricity"
    ],
    "wof:name":"ELSAM A/S ENSTEDV\u00c6RKET",
    "wof:placetype":"venue"
},
  "geometry": {"coordinates":[9.4341201782,55.0205192566],"type":"Point"}
}