{
  "type": "Feature",
  "properties": {
    "iso:country":"DK",
    "sg:address":"Skr\u00e6nten 23, Hosby",
    "sg:city":"Juelsminde",
    "sg:classifiers":[
        {
            "category":"Taxi",
            "type":"Transportation"
        }
    ],
    "sg:phone":"+45 70 26 00 27",
    "sg:postcode":"7130",
    "sg:province":"Danmark",
    "wof:name":"Juelsminde Bilen",
    "wof:placetype":"venue"
},
  "geometry": {"coordinates":[10.0143985748,55.7135848999],"type":"Point"}
}