{
  "type": "Feature",
  "properties": {
    "addr:full":"Howitzvej 32 Frederiksberg Danmark 2000",
    "addr:housenumber":"32",
    "addr:postcode":"2000",
    "addr:street":"Howitzvej",
    "iso:country":"DK",
    "sg:address":"Howitzvej 32",
    "sg:city":"Frederiksberg",
    "sg:orig_category":"Dommerkontorer",
    "sg:phone":"+45 38 14 54 00",
    "sg:postcode":"2000",
    "sg:province":"Danmark",
    "wof:name":"Retten p\u00e5 Frederiksberg",
    "wof:placetype":"venue"
},
  "geometry": {"coordinates":[12.5290899277,55.6798477173],"type":"Point"}
}