{
  "type": "Feature",
  "properties": {
    "addr:full":"Sct. Mathias Gade 29 Viborg Danmark 8800",
    "addr:housenumber":"29",
    "addr:postcode":"8800",
    "addr:street":"Sct. Mathias Gade",
    "iso:country":"DK",
    "sg:address":"Sct. Mathias Gade 29",
    "sg:city":"Viborg",
    "sg:orig_category":"Boghandlere",
    "sg:phone":"+45 86 61 39 00",
    "sg:postcode":"8800",
    "sg:province":"Danmark",
    "wof:name":"Kj\u00e6rs Boghandel",
    "wof:placetype":"venue"
},
  "geometry": {"coordinates":[9.4068536758,56.4493255615],"type":"Point"}
}