{
  "type": "Feature",
  "properties": {
    "iso:country":"DK",
    "sg:address":"Rugvang 36 - 38, Tarup",
    "sg:city":"Odense NV",
    "sg:classifiers":[
        {
            "category":"Banks & Credit Unions",
            "subcategory":"Bank",
            "type":"Services"
        }
    ],
    "sg:phone":"+45 63 16 71 00",
    "sg:postcode":"5210",
    "sg:province":"Danmark",
    "sg:tags":[
        "banker"
    ],
    "wof:name":"BG Bank",
    "wof:placetype":"venue"
},
  "geometry": {"coordinates":[10.274764,55.430332],"type":"Point"}
}