{
  "type": "Feature",
  "properties": {
    "iso:country":"DK",
    "sg:address":"Ved Kirken 8",
    "sg:city":"Frederikssund",
    "sg:orig_category":"Kirkesogne",
    "sg:phone":"+45 47 31 30 25",
    "sg:postcode":"3600",
    "sg:province":"Danmark",
    "wof:name":"Frederikssund Sogns Kirkekontor",
    "wof:placetype":"venue"
},
  "geometry": {"coordinates":[12.0680570602,55.8391838074],"type":"Point"}
}