{
  "type": "Feature",
  "properties": {
    "addr:full":"Pr\u00e6steg\u00e5rdsvej 4 Vojens Danmark 6500",
    "addr:housenumber":"4",
    "addr:postcode":"6500",
    "addr:street":"Praestegaardsvej",
    "iso:country":"DK",
    "sg:address":"Pr\u00e6steg\u00e5rdsvej 4",
    "sg:city":"Vojens",
    "sg:orig_category":"Legestuer",
    "sg:phone":"+45 74 54 01 33",
    "sg:postcode":"6500",
    "sg:province":"Danmark",
    "wof:name":"Vojens Legestue",
    "wof:placetype":"venue"
},
  "geometry": {"coordinates":[9.2987146378,55.2457237244],"type":"Point"}
}