{
  "type": "Feature",
  "properties": {
    "addr:full":"Kalundborgvej 24 Snertinge Danmark 4460",
    "addr:housenumber":"24",
    "addr:postcode":"4460",
    "addr:street":"Kalundborgvej",
    "iso:country":"DK",
    "sg:address":"Kalundborgvej 24",
    "sg:city":"Snertinge",
    "sg:orig_category":"Posthuse",
    "sg:phone":"+45 59 26 80 23",
    "sg:postcode":"4460",
    "sg:province":"Danmark",
    "wof:name":"Post Danmark, Snertinge Posthus",
    "wof:placetype":"venue"
},
  "geometry": {"coordinates":[11.3827447891,55.7115936279],"type":"Point"}
}