{
  "type": "Feature",
  "properties": {
    "addr:full":"Bannestrupparken 57, Tvis Holstebro Danmark 7500",
    "addr:housenumber":"57",
    "addr:postcode":"7500",
    "addr:street":"Bannestrupparken",
    "iso:country":"DK",
    "sg:address":"Bannestrupparken 57, Tvis",
    "sg:city":"Holstebro",
    "sg:orig_category":"Forlag",
    "sg:phone":"+45 97 43 54 88",
    "sg:postcode":"7500",
    "sg:province":"Danmark",
    "wof:name":"Ventus, Forlaget",
    "wof:placetype":"venue"
},
  "geometry": {"coordinates":[8.6202583313,56.3625221252],"type":"Point"}
}