{
  "type": "Feature",
  "properties": {
    "addr:full":"Ringvej 16 Ry Danmark 8680",
    "addr:housenumber":"16",
    "addr:postcode":"8680",
    "addr:street":"Ringvej",
    "iso:country":"DK",
    "sg:address":"Ringvej 16",
    "sg:city":"Ry",
    "sg:orig_category":"Kirker",
    "sg:postcode":"8680",
    "sg:province":"Danmark",
    "wof:name":"Alling Kirke",
    "wof:placetype":"venue"
},
  "geometry": {"coordinates":[9.7293510437,56.112827301],"type":"Point"}
}