{
  "type": "Feature",
  "properties": {
    "addr:full":"Bakkegaardsvej 1, Sn\u00e6rild Odder Danmark 8300",
    "addr:housenumber":"1",
    "addr:postcode":"8300",
    "addr:street":"Bakkegaardsvej;Snaerild",
    "iso:country":"DK",
    "sg:address":"Bakkegaardsvej 1, Sn\u00e6rild",
    "sg:city":"Odder",
    "sg:orig_category":"Dykkere",
    "sg:phone":"+45 86 54 08 00",
    "sg:postcode":"8300",
    "sg:province":"Danmark",
    "wof:name":"PM Diving A/S",
    "wof:placetype":"venue"
},
  "geometry": {"coordinates":[10.1497612,55.9733161926],"type":"Point"}
}