{
  "type": "Feature",
  "properties": {
    "addr:full":"Borupvang 2 Ballerup Danmark 2750",
    "addr:housenumber":"2",
    "addr:postcode":"2750",
    "addr:street":"Borupvang",
    "iso:country":"DK",
    "sg:address":"Borupvang 2",
    "sg:city":"Ballerup",
    "sg:orig_category":"Posthuse",
    "sg:phone":"+45 39 54 27 50",
    "sg:postcode":"2750",
    "sg:province":"Danmark",
    "wof:name":"Post Danmark, Lautrup Posthus",
    "wof:placetype":"venue"
},
  "geometry": {"coordinates":[12.386516571,55.7330627441],"type":"Point"}
}