{
  "type": "Feature",
  "properties": {
    "iso:country":"DK",
    "sg:address":"Vestervang 25, Kolby K\u00e5s",
    "sg:city":"Sams\u00f8",
    "sg:orig_category":"Revisorer",
    "sg:phone":"+45 86 59 11 30",
    "sg:postcode":"8305",
    "sg:province":"Danmark",
    "sg:website":"www.lokalrevisor.dk",
    "wof:name":"Nielsen, John Drjer",
    "wof:placetype":"venue"
},
  "geometry": {"coordinates":[-86.09934997560001,31.2234687805],"type":"Point"}
}