{
  "type": "Feature",
  "properties": {
    "addr:full":"Vejlevej 62, Givskud Give Danmark 7323",
    "addr:housenumber":"62",
    "addr:postcode":"7323",
    "addr:street":"Vejlevej",
    "iso:country":"DK",
    "sg:address":"Vejlevej 62, Givskud",
    "sg:city":"Give",
    "sg:orig_category":"Akupunktur",
    "sg:phone":"+45 75 73 03 44",
    "sg:postcode":"7323",
    "sg:province":"Danmark",
    "wof:name":"M/K Akupunktur, Zone- og Kiroterapi",
    "wof:placetype":"venue"
},
  "geometry": {"coordinates":[9.2362060547,55.845413208],"type":"Point"}
}