{
  "type": "Feature",
  "properties": {
    "addr:full":"Vestre Havneplads 13 Kalundborg Danmark 4400",
    "addr:housenumber":"13",
    "addr:postcode":"4400",
    "addr:street":"Vestre Havneplads",
    "iso:country":"DK",
    "sg:address":"Vestre Havneplads 13",
    "sg:city":"Kalundborg",
    "sg:orig_category":"Tandteknikere, Kliniske",
    "sg:phone":"+45 59 51 07 70",
    "sg:postcode":"4400",
    "sg:province":"Danmark",
    "wof:name":"Ghasemi, Nick",
    "wof:placetype":"venue"
},
  "geometry": {"coordinates":[11.1029930115,55.674785614],"type":"Point"}
}