{
  "type": "Feature",
  "properties": {
    "iso:country":"DK",
    "sg:address":"Stevnsh\u00f8jvej 99",
    "sg:city":"Store Heddinge",
    "sg:orig_category":"Dagcentre",
    "sg:phone":"+45 56 50 24 88",
    "sg:postcode":"4660",
    "sg:province":"Danmark",
    "wof:name":"Dagcenter",
    "wof:placetype":"venue"
},
  "geometry": {"coordinates":[12.3895797729,55.3113174438],"type":"Point"}
}