{
  "type": "Feature",
  "properties": {
    "addr:full":"K\u00f8benhavnsvej 205 Roskilde Danmark 4000",
    "addr:housenumber":"205",
    "addr:postcode":"4000",
    "addr:street":"Kobenhavnsvej",
    "iso:country":"DK",
    "sg:address":"K\u00f8benhavnsvej 205",
    "sg:city":"Roskilde",
    "sg:orig_category":"Autoforhandlere",
    "sg:phone":"+45 46 75 40 04",
    "sg:postcode":"4000",
    "sg:province":"Danmark",
    "wof:name":"Bilteam Roskilde",
    "wof:placetype":"venue"
},
  "geometry": {"coordinates":[12.1240301132,55.6432189941],"type":"Point"}
}