{
  "type": "Feature",
  "properties": {
    "addr:full":"Hovedvejen 196 Glostrup Danmark 2600",
    "addr:housenumber":"196",
    "addr:postcode":"2600",
    "addr:street":"Hovedvejen",
    "iso:country":"DK",
    "sg:address":"Hovedvejen 196",
    "sg:city":"Glostrup",
    "sg:orig_category":"Autoforhandlere",
    "sg:phone":"+45 43 27 07 20",
    "sg:postcode":"2600",
    "sg:province":"Danmark",
    "wof:name":"Andersen & Martini A/S",
    "wof:placetype":"venue"
},
  "geometry": {"coordinates":[12.3858785629,55.6652297974],"type":"Point"}
}