{
  "type": "Feature",
  "properties": {
    "addr:full":"H\u00f8jene 5 Hejnsvig Danmark 7250",
    "addr:housenumber":"5",
    "addr:postcode":"7250",
    "addr:street":"Hojene",
    "iso:country":"DK",
    "sg:address":"H\u00f8jene 5",
    "sg:city":"Hejnsvig",
    "sg:orig_category":"Fritidsklubber",
    "sg:phone":"+45 75 33 54 95",
    "sg:postcode":"7250",
    "sg:province":"Danmark",
    "wof:name":"KFUM-spejderne Hejnsvig",
    "wof:placetype":"venue"
},
  "geometry": {"coordinates":[8.9913749695,55.6938171387],"type":"Point"}
}