{
  "type": "Feature",
  "properties": {
    "addr:full":"Hareskovvej 15 Kalundborg Danmark 4400",
    "addr:housenumber":"15",
    "addr:postcode":"4400",
    "addr:street":"Hareskovvej",
    "iso:country":"DK",
    "sg:address":"Hareskovvej 15",
    "sg:city":"Kalundborg",
    "sg:orig_category":"Dyrefoder",
    "sg:phone":"+45 59 56 18 90",
    "sg:postcode":"4400",
    "sg:province":"Danmark",
    "wof:name":"Holm's Foderbutik",
    "wof:placetype":"venue"
},
  "geometry": {"coordinates":[11.1157827377,55.6656761169],"type":"Point"}
}