{
  "type": "Feature",
  "properties": {
    "addr:full":"Markvej 121 A Skagen Danmark 9990",
    "addr:housenumber":"121 a",
    "addr:postcode":"9990",
    "addr:street":"Markvej",
    "iso:country":"DK",
    "sg:address":"Markvej 121 A",
    "sg:city":"Skagen",
    "sg:orig_category":"Forsamlingshuse",
    "sg:phone":"+45 98 44 24 97",
    "sg:postcode":"9990",
    "sg:province":"Danmark",
    "wof:name":"Klitrosen",
    "wof:placetype":"venue"
},
  "geometry": {"coordinates":[10.5765943527,57.7256507874],"type":"Point"}
}