{
  "type": "Feature",
  "properties": {
    "addr:full":"Lundbergsvej 2 Ebeltoft Danmark 8400",
    "addr:housenumber":"2",
    "addr:postcode":"8400",
    "addr:street":"Lundbergsvej",
    "iso:country":"DK",
    "sg:address":"Lundbergsvej 2",
    "sg:city":"Ebeltoft",
    "sg:orig_category":"Central pladsanvisning",
    "sg:phone":"+45 89 52 13 19",
    "sg:postcode":"8400",
    "sg:province":"Danmark",
    "wof:name":"B\u00f8rnehaver i Ebeltoft Kommune",
    "wof:placetype":"venue"
},
  "geometry": {"coordinates":[10.6754837036,56.1795806885],"type":"Point"}
}