{
  "type": "Feature",
  "properties": {
    "addr:full":"Kirkevej 16, Stryn\u00f8 Rudk\u00f8bing Danmark 5900",
    "addr:housenumber":"16",
    "addr:postcode":"5900",
    "addr:street":"Kirkevej",
    "iso:country":"DK",
    "sg:address":"Kirkevej 16, Stryn\u00f8",
    "sg:city":"Rudk\u00f8bing",
    "sg:orig_category":"Kirker",
    "sg:postcode":"5900",
    "sg:province":"Danmark",
    "wof:name":"Stryn\u00f8 Kirke",
    "wof:placetype":"venue"
},
  "geometry": {"coordinates":[-69.88223266599999,45.0590782166],"type":"Point"}
}