{
  "type": "Feature",
  "properties": {
    "addr:full":"Kirkelundvej 18A, Bellinge Odense SV Danmark 5250",
    "addr:housenumber":"18a",
    "addr:postcode":"5250",
    "addr:street":"Kirkelundvej",
    "iso:country":"DK",
    "sg:address":"Kirkelundvej 18A, Bellinge",
    "sg:city":"Odense SV",
    "sg:orig_category":"Kirker",
    "sg:postcode":"5250",
    "sg:province":"Danmark",
    "wof:name":"Bellinge Kirke",
    "wof:placetype":"venue"
},
  "geometry": {"coordinates":[10.3153953552,55.3362998962],"type":"Point"}
}