{
  "type": "Feature",
  "properties": {
    "addr:full":"Skallerup Skolevej 4 Hj\u00f8rring Danmark 9800",
    "addr:housenumber":"4",
    "addr:postcode":"9800",
    "addr:street":"Skallerup Skolevej",
    "iso:country":"DK",
    "sg:address":"Skallerup Skolevej 4",
    "sg:city":"Hj\u00f8rring",
    "sg:orig_category":"Ungdomsklubber",
    "sg:phone":"+45 98 96 84 41",
    "sg:postcode":"9800",
    "sg:province":"Danmark",
    "wof:name":"Skallerup Ungdomsklub",
    "wof:placetype":"venue"
},
  "geometry": {"coordinates":[9.8696298599,57.4598884583],"type":"Point"}
}