{
  "type": "Feature",
  "properties": {
    "addr:full":"Frederiksv\u00e6rkvej 119, Raml\u00f8se Helsinge Danmark 3200",
    "addr:housenumber":"119",
    "addr:postcode":"3200",
    "addr:street":"Frederiksvaerkvej;Ramlose",
    "iso:country":"DK",
    "sg:address":"Frederiksv\u00e6rkvej 119, Raml\u00f8se",
    "sg:city":"Helsinge",
    "sg:orig_category":"Murermestre",
    "sg:phone":"+45 48 71 21 02",
    "sg:postcode":"3200",
    "sg:province":"Danmark",
    "wof:name":"Andersen, Henning",
    "wof:placetype":"venue"
},
  "geometry": {"coordinates":[12.196846962,56.0224456787],"type":"Point"}
}