{
  "type": "Feature",
  "properties": {
    "addr:full":"Skovv\u00e6nget 13, Arrild Toftlund Danmark 6520",
    "addr:housenumber":"13",
    "addr:postcode":"6520",
    "addr:street":"Skovvaenget;Arrild",
    "iso:country":"DK",
    "sg:address":"Skovv\u00e6nget 13, Arrild",
    "sg:city":"Toftlund",
    "sg:orig_category":"Murermestre",
    "sg:phone":"+45 74 83 42 65",
    "sg:postcode":"6520",
    "sg:province":"Danmark",
    "sg:website":"www.stenger.dk",
    "wof:name":"Stenger Bygge- og Entrepren\u00f8rforr. I/S, Brdr.",
    "wof:placetype":"venue"
},
  "geometry": {"coordinates":[9.0629367828,55.1926651001],"type":"Point"}
}