{
  "type": "Feature",
  "properties": {
    "addr:full":"Havnen 1 Horsens Danmark 8700",
    "addr:housenumber":"1",
    "addr:postcode":"8700",
    "addr:street":"Havnen",
    "iso:country":"DK",
    "sg:address":"Havnen 1",
    "sg:city":"Horsens",
    "sg:orig_category":"Erhvervsskoler",
    "sg:phone":"+45 76 25 50 00",
    "sg:postcode":"8700",
    "sg:province":"Danmark",
    "sg:website":"www.vitusbering.dk",
    "wof:name":"Vitus Bering Center for Videreg\u00e5ende Uddannelse",
    "wof:placetype":"venue"
},
  "geometry": {"coordinates":[9.8591651917,55.8590354919],"type":"Point"}
}