{
  "type": "Feature",
  "properties": {
    "iso:country":"DK",
    "sg:address":"Ved Stadsgraven 11",
    "sg:city":"K\u00f8benhavn S",
    "sg:orig_category":"Vuggestuer",
    "sg:phone":"+45 32 95 33 56",
    "sg:postcode":"2300",
    "sg:province":"Danmark",
    "wof:name":"K\u00f8benhavns Kommunes Vuggestue",
    "wof:placetype":"venue"
},
  "geometry": {"coordinates":[12.6124000549,55.6774101257],"type":"Point"}
}