{
  "type": "Feature",
  "properties": {
    "addr:full":"Ketteg\u00e5rd Alle 16 Hvidovre Danmark 2650",
    "addr:housenumber":"16",
    "addr:postcode":"2650",
    "addr:street":"Kettegaard Alle",
    "iso:country":"DK",
    "sg:address":"Ketteg\u00e5rd Alle 16",
    "sg:city":"Hvidovre",
    "sg:orig_category":"Vuggestuer",
    "sg:phone":"+45 36 75 32 19",
    "sg:postcode":"2650",
    "sg:province":"Danmark",
    "wof:name":"Rosenh\u00f8j Vuggestue",
    "wof:placetype":"venue"
},
  "geometry": {"coordinates":[12.4724473953,55.6481361389],"type":"Point"}
}