{
  "type": "Feature",
  "properties": {
    "addr:full":"Bagsv\u00e6rdvej 138 A-B Kongens Lyngby Danmark 2800",
    "addr:housenumber":"138 a-b",
    "addr:postcode":"2800",
    "addr:street":"Bagsvaerdvej",
    "iso:country":"DK",
    "sg:address":"Bagsv\u00e6rdvej 138 A-B",
    "sg:city":"Kongens Lyngby",
    "sg:orig_category":"Handicapboliger",
    "sg:phone":"+45 45 93 31 38",
    "sg:postcode":"2800",
    "sg:province":"Danmark",
    "wof:name":"Bof\u00e6llesskab for udv.h\u00e6mmede",
    "wof:placetype":"venue"
},
  "geometry": {"coordinates":[12.5368299484,55.7949905396],"type":"Point"}
}