{
  "type": "Feature",
  "properties": {
    "addr:full":"Enghaven 2 Holstebro Danmark 7500",
    "addr:housenumber":"2",
    "addr:postcode":"7500",
    "addr:street":"Enghaven",
    "iso:country":"DK",
    "sg:address":"Enghaven 2",
    "sg:city":"Holstebro",
    "sg:orig_category":"Kiosker",
    "sg:phone":"+45 97 42 01 60",
    "sg:postcode":"7500",
    "sg:province":"Danmark",
    "wof:name":"City Papirhandel",
    "wof:placetype":"venue"
},
  "geometry": {"coordinates":[8.7039852142,56.3207130432],"type":"Point"}
}