{
  "type": "Feature",
  "properties": {
    "iso:country":"DK",
    "sg:address":"Frederikssundsvej 77",
    "sg:city":"K\u00f8benhavn NV",
    "sg:orig_category":"Kommunale folkeskoler",
    "sg:phone":"+45 38 10 45 65",
    "sg:postcode":"2400",
    "sg:province":"Danmark",
    "wof:name":"Frederikssundsvejens Skole",
    "wof:placetype":"venue"
},
  "geometry": {"coordinates":[-117.02272033689999,38.5024604797],"type":"Point"}
}