{
  "type": "Feature",
  "properties": {
    "addr:full":"Fmd.: Christina Jensen, Askelunden 9 Snertinge Danmark 4460",
    "addr:housenumber":"9",
    "addr:postcode":"4460",
    "addr:street":"Askelunden",
    "iso:country":"DK",
    "sg:address":"Fmd.: Christina Jensen, Askelunden 9",
    "sg:city":"Snertinge",
    "sg:orig_category":"Grundejerforeninger",
    "sg:phone":"+45 59 26 85 24",
    "sg:postcode":"4460",
    "sg:province":"Danmark",
    "wof:name":"Lunden",
    "wof:placetype":"venue"
},
  "geometry": {"coordinates":[11.3833780289,55.7136611938],"type":"Point"}
}