{
  "type": "Feature",
  "properties": {
    "addr:full":"Pr\u00e6stemosen 50 Hvidovre Danmark 2650",
    "addr:housenumber":"50",
    "addr:postcode":"2650",
    "addr:street":"Praestemosen",
    "iso:country":"DK",
    "sg:address":"Pr\u00e6stemosen 50",
    "sg:city":"Hvidovre",
    "sg:orig_category":"Revisorer",
    "sg:phone":"+45 36 75 91 78",
    "sg:postcode":"2650",
    "sg:province":"Danmark",
    "wof:name":"M\u00f8ller, Wolmer",
    "wof:placetype":"venue"
},
  "geometry": {"coordinates":[12.4620428085,55.6564903259],"type":"Point"}
}