{
  "type": "Feature",
  "properties": {
    "addr:full":"Hovedgaden 59 Svinninge Danmark 4520",
    "addr:housenumber":"59",
    "addr:postcode":"4520",
    "addr:street":"Hovedgaden",
    "iso:country":"DK",
    "sg:address":"Hovedgaden 59",
    "sg:city":"Svinninge",
    "sg:orig_category":"Grillbarer",
    "sg:phone":"+45 59 26 18 60",
    "sg:postcode":"4520",
    "sg:province":"Danmark",
    "wof:name":"Markedspladsens P\u00f8lsevogn",
    "wof:placetype":"venue"
},
  "geometry": {"coordinates":[11.4617586136,55.7218971252],"type":"Point"}
}