{
  "type": "Feature",
  "properties": {
    "addr:full":"S\u00f8ndre Alle 26 Valby Danmark 2500",
    "addr:housenumber":"26",
    "addr:postcode":"2500",
    "addr:street":"Sondre Alle",
    "iso:country":"DK",
    "sg:address":"S\u00f8ndre Alle 26",
    "sg:city":"Valby",
    "sg:orig_category":"Designere",
    "sg:phone":"+45 36 44 00 75",
    "sg:postcode":"2500",
    "sg:province":"Danmark",
    "wof:name":"Christensen Design, Dan",
    "wof:placetype":"venue"
},
  "geometry": {"coordinates":[12.4946622849,55.6660766602],"type":"Point"}
}