{
  "type": "Feature",
  "properties": {
    "addr:full":"Posthustorvet 4 Skive Danmark 7800",
    "addr:housenumber":"4",
    "addr:postcode":"7800",
    "addr:street":"Posthustorvet",
    "iso:country":"DK",
    "sg:address":"Posthustorvet 4",
    "sg:city":"Skive",
    "sg:orig_category":"Fotohandlere",
    "sg:phone":"+45 97 52 64 61",
    "sg:postcode":"7800",
    "sg:province":"Danmark",
    "wof:name":"Posthustorvet's Foto",
    "wof:placetype":"venue"
},
  "geometry": {"coordinates":[9.0256299973,56.5650100708],"type":"Point"}
}