{
  "type": "Feature",
  "properties": {
    "addr:full":"Fmd.: Gretha Baumann, B\u00f8gevangen 9 Dronninglund Danmark 9330",
    "addr:housenumber":"9",
    "addr:postcode":"9330",
    "addr:street":"Bogevangen",
    "iso:country":"DK",
    "sg:address":"Fmd.: Gretha Baumann, B\u00f8gevangen 9",
    "sg:city":"Dronninglund",
    "sg:orig_category":"Husflidsforeninger",
    "sg:phone":"+45 98 84 12 88",
    "sg:postcode":"9330",
    "sg:province":"Danmark",
    "wof:name":"Dronninglund Husmoderforening",
    "wof:placetype":"venue"
},
  "geometry": {"coordinates":[10.2918195724,57.1594543457],"type":"Point"}
}