{
  "type": "Feature",
  "properties": {
    "iso:country":"DK",
    "sg:address":"Nymarksvej 34",
    "sg:city":"Fredericia",
    "sg:orig_category":"Brugsforeninger",
    "sg:phone":"+45 75 92 92 22",
    "sg:postcode":"7000",
    "sg:province":"Danmark",
    "wof:name":"Super Brugsen",
    "wof:placetype":"venue"
},
  "geometry": {"coordinates":[9.7609348297,55.5744361877],"type":"Point"}
}