{
  "type": "Feature",
  "properties": {
    "addr:full":"Tingvej 10 K\u00f8benhavn S Danmark 2300",
    "addr:housenumber":"10",
    "addr:postcode":"2300",
    "addr:street":"Tingvej;S Danmark",
    "iso:country":"DK",
    "sg:address":"Tingvej 10",
    "sg:city":"K\u00f8benhavn S",
    "sg:orig_category":"Cykler",
    "sg:phone":"+45 32 58 70 48",
    "sg:postcode":"2300",
    "sg:province":"Danmark",
    "wof:name":"Gold Star",
    "wof:placetype":"venue"
},
  "geometry": {"coordinates":[-82.57898712159999,38.4234962463],"type":"Point"}
}