{
  "type": "Feature",
  "properties": {
    "iso:country":"DK",
    "sg:address":"Fasanvej 4",
    "sg:city":"Ans",
    "sg:orig_category":"Revisorer",
    "sg:phone":"+45 86 87 02 27",
    "sg:postcode":"8643",
    "sg:province":"Danmark",
    "wof:name":"Ans Bogf\u00f8ringscentral",
    "wof:placetype":"venue"
},
  "geometry": {"coordinates":[9.5914907455,56.3061180115],"type":"Point"}
}