{
  "type": "Feature",
  "properties": {
    "iso:country":"DK",
    "sg:address":"Gammel Stationsvej 7 ",
    "sg:city":"Randers",
    "sg:classifiers":[
        {
            "category":"Professional",
            "subcategory":"Advertising",
            "type":"Services"
        }
    ],
    "sg:phone":"+45 86 42 57 11",
    "sg:postcode":"8900",
    "sg:province":"Danmark",
    "sg:tags":[
        "communication",
        "medium"
    ],
    "wof:name":"PROINFO A/S",
    "wof:placetype":"venue"
},
  "geometry": {"coordinates":[10.0402240753,56.4535675049],"type":"Point"}
}