{
  "type": "Feature",
  "properties": {
    "addr:full":"Leder: Uffe Hansen, Vibevej 21 Dalmose Danmark 4261",
    "addr:housenumber":"21",
    "addr:postcode":"4261",
    "addr:street":"Vibevej",
    "iso:country":"DK",
    "sg:address":"Leder: Uffe Hansen, Vibevej 21",
    "sg:city":"Dalmose",
    "sg:orig_category":"\u00c3\u02dcvrig fritidsundervisning",
    "sg:phone":"+45 58 18 80 84",
    "sg:postcode":"4261",
    "sg:province":"Danmark",
    "wof:name":"Hash\u00f8j Aftenskole",
    "wof:placetype":"venue"
},
  "geometry": {"coordinates":[11.423330307,55.2912635803],"type":"Point"}
}