{
  "type": "Feature",
  "properties": {
    "addr:full":"Hornemansgade 36 A K\u00f8benhavn \u00d8 Danmark 2100",
    "addr:housenumber":"36 a",
    "addr:postcode":"2100",
    "addr:street":"Hornemansgade;Kobenhavn O Danmark",
    "iso:country":"DK",
    "sg:address":"Hornemansgade 36 A",
    "sg:city":"K\u00f8benhavn \u00d8",
    "sg:orig_category":"Malermestre",
    "sg:phone":"+45 39 27 50 81",
    "sg:postcode":"2100",
    "sg:province":"Danmark",
    "wof:name":"Henrik Jespersen ApS",
    "wof:placetype":"venue"
},
  "geometry": {"coordinates":[11.6836299896,60.2548065186],"type":"Point"}
}