{
  "type": "Feature",
  "properties": {
    "addr:full":"Smallegade 6 Frederiksberg Danmark 2000",
    "addr:housenumber":"6",
    "addr:postcode":"2000",
    "addr:street":"Smallegade",
    "iso:country":"DK",
    "sg:address":"Smallegade 6",
    "sg:city":"Frederiksberg",
    "sg:orig_category":"Posthuse",
    "sg:phone":"+45 38 87 63 03",
    "sg:postcode":"2000",
    "sg:province":"Danmark",
    "wof:name":"Post Danmark, Postkontoret",
    "wof:placetype":"venue"
},
  "geometry": {"coordinates":[12.5323209763,55.6786308289],"type":"Point"}
}