{
  "type": "Feature",
  "properties": {
    "addr:full":"Storgade 13 Sor\u00f8 Danmark 4180",
    "addr:housenumber":"13",
    "addr:postcode":"4180",
    "addr:street":"Storgade",
    "iso:country":"DK",
    "sg:address":"Storgade 13",
    "sg:city":"Sor\u00f8",
    "sg:orig_category":"Ejendomshandel",
    "sg:phone":"+45 57 86 11 00",
    "sg:postcode":"4180",
    "sg:province":"Danmark",
    "sg:website":"www.edc.dk",
    "wof:name":"EDC M\u00e6glerne - Sor\u00f8 Ejendomshandel",
    "wof:placetype":"venue"
},
  "geometry": {"coordinates":[-102.94467926030001,45.4534721375],"type":"Point"}
}