{
  "type": "Feature",
  "properties": {
    "addr:full":"v/ Jan J\u00f8rgensen, Egernvej 6 Esbjerg N Danmark 6715",
    "addr:housenumber":"6",
    "addr:postcode":"6715",
    "addr:street":"Egernvej",
    "iso:country":"DK",
    "sg:address":"v/ Jan J\u00f8rgensen, Egernvej 6",
    "sg:city":"Esbjerg N",
    "sg:orig_category":"Kirkelige foreninger",
    "sg:phone":"+45 75 45 45 48",
    "sg:postcode":"6715",
    "sg:province":"Danmark",
    "wof:name":"Indre Missions Unge",
    "wof:placetype":"venue"
},
  "geometry": {"coordinates":[8.4780550003,55.535610199],"type":"Point"}
}