{
  "type": "Feature",
  "properties": {
    "addr:full":"Volden 12 Kalundborg Danmark 4400",
    "addr:housenumber":"12",
    "addr:postcode":"4400",
    "addr:street":"Volden",
    "iso:country":"DK",
    "sg:address":"Volden 12",
    "sg:city":"Kalundborg",
    "sg:orig_category":"Turistbureau og -information",
    "sg:phone":"+45 59 51 09 15",
    "sg:postcode":"4400",
    "sg:province":"Danmark",
    "sg:website":"www.kalundborg-turistbureau.dk",
    "wof:name":"Kalundborg Turistbureau",
    "wof:placetype":"venue"
},
  "geometry": {"coordinates":[11.085436821,55.6806640625],"type":"Point"}
}