{
  "type": "Feature",
  "properties": {
    "iso:country":"DK",
    "sg:address":"Vestergade 4",
    "sg:city":"Viborg",
    "sg:orig_category":"Sko",
    "sg:phone":"+45 86 62 19 99",
    "sg:postcode":"8800",
    "sg:province":"Danmark",
    "wof:name":"Bianco Footwear",
    "wof:placetype":"venue"
},
  "geometry": {"coordinates":[9.4068279266,56.4505195618],"type":"Point"}
}