{
  "type": "Feature",
  "properties": {
    "iso:country":"DK",
    "sg:address":"Solr\u00f8d Strandvej 109",
    "sg:city":"Solr\u00f8d Strand",
    "sg:classifiers":[
        {
            "category":"Home & Garden",
            "subcategory":"Home Furnishings",
            "type":"Retail Goods"
        }
    ],
    "sg:phone":"+45 56 14 05 66",
    "sg:postcode":"2680",
    "sg:province":"Danmark",
    "sg:tags":[
        "gardiner"
    ],
    "sg:website":"www.moltzen.dk",
    "wof:name":"Moltzen Gardiner",
    "wof:placetype":"venue"
},
  "geometry": {"coordinates":[-122.35903167719999,48.9091377258],"type":"Point"}
}