{
  "type": "Feature",
  "properties": {
    "addr:full":"Algade 24 B Vordingborg Danmark 4760",
    "addr:housenumber":"24 b",
    "addr:postcode":"4760",
    "addr:street":"Algade",
    "iso:country":"DK",
    "sg:address":"Algade 24 B",
    "sg:city":"Vordingborg",
    "sg:orig_category":"Glarmestre og glarmagere",
    "sg:phone":"+45 55 37 60 90",
    "sg:postcode":"4760",
    "sg:province":"Danmark",
    "wof:name":"HD-Glas",
    "wof:placetype":"venue"
},
  "geometry": {"coordinates":[11.9034690857,55.011592865],"type":"Point"}
}