{
  "type": "Feature",
  "properties": {
    "addr:full":"M\u00e5ensvej 15, Sulb\u00e6k Frederikshavn Danmark 9900",
    "addr:housenumber":"15",
    "addr:postcode":"9900",
    "addr:street":"Maaensvej",
    "iso:country":"DK",
    "sg:address":"M\u00e5ensvej 15, Sulb\u00e6k",
    "sg:city":"Frederikshavn",
    "sg:orig_category":"Flytteforretninger",
    "sg:phone":"+45 98 46 52 72",
    "sg:postcode":"9900",
    "sg:province":"Danmark",
    "wof:name":"M\u00f8llers Flytteservice / Tage Johansen",
    "wof:placetype":"venue"
},
  "geometry": {"coordinates":[10.5362997055,57.4396400452],"type":"Point"}
}