{
  "type": "Feature",
  "properties": {
    "addr:full":"Farvergade 15 N\u00e6stved Danmark 4700",
    "addr:housenumber":"15",
    "addr:postcode":"4700",
    "addr:street":"Farvergade",
    "iso:country":"DK",
    "sg:address":"Farvergade 15",
    "sg:city":"N\u00e6stved",
    "sg:orig_category":"Realkreditinstitutter",
    "sg:phone":"+45 33 12 53 00",
    "sg:postcode":"4700",
    "sg:province":"Danmark",
    "sg:website":"www.rd.dk",
    "wof:name":"Realkredit Danmark",
    "wof:placetype":"venue"
},
  "geometry": {"coordinates":[11.7548942566,55.2301979065],"type":"Point"}
}