{
  "type": "Feature",
  "properties": {
    "addr:full":"Amagerf\u00e6lledvej 11 K\u00f8benhavn S Danmark 2300",
    "addr:housenumber":"11",
    "addr:postcode":"2300",
    "addr:street":"Amagerfaelledvej;S Danmark",
    "iso:country":"DK",
    "sg:address":"Amagerf\u00e6lledvej 11",
    "sg:city":"K\u00f8benhavn S",
    "sg:orig_category":"Arkitekter",
    "sg:phone":"+45 32 95 18 93",
    "sg:postcode":"2300",
    "sg:province":"Danmark",
    "wof:name":"Ekeberg, Tove",
    "wof:placetype":"venue"
},
  "geometry": {"coordinates":[-78.1299133301,36.7267417908],"type":"Point"}
}