{
  "type": "Feature",
  "properties": {
    "addr:full":"Hobrovej 62 Randers Danmark 8900",
    "addr:housenumber":"62",
    "addr:postcode":"8900",
    "addr:street":"Hobrovej",
    "iso:country":"DK",
    "sg:address":"Hobrovej 62",
    "sg:city":"Randers",
    "sg:orig_category":"Fodplejere",
    "sg:phone":"+45 86 40 52 30",
    "sg:postcode":"8900",
    "sg:province":"Danmark",
    "wof:name":"Clinic Clemens",
    "wof:placetype":"venue"
},
  "geometry": {"coordinates":[10.0220117569,56.4671592712],"type":"Point"}
}