{
  "type": "Feature",
  "properties": {
    "addr:full":"Skovridervej 27 Esbjerg N Danmark 6715",
    "addr:housenumber":"27",
    "addr:postcode":"6715",
    "addr:street":"Skovridervej",
    "iso:country":"DK",
    "sg:address":"Skovridervej 27",
    "sg:city":"Esbjerg N",
    "sg:orig_category":"Planteskoler",
    "sg:phone":"+45 75 16 72 99",
    "sg:postcode":"6715",
    "sg:province":"Danmark",
    "wof:name":"Skovriderg\u00e5rdens Havecenter",
    "wof:placetype":"venue"
},
  "geometry": {"coordinates":[8.4470529556,55.5359306335],"type":"Point"}
}