{
  "type": "Feature",
  "properties": {
    "addr:full":"Caspersvej 7 Frederikshavn Danmark 9900",
    "addr:housenumber":"7",
    "addr:postcode":"9900",
    "addr:street":"Caspersvej",
    "iso:country":"DK",
    "sg:address":"Caspersvej 7",
    "sg:city":"Frederikshavn",
    "sg:orig_category":"Plejehjem",
    "sg:phone":"+45 98 42 43 55",
    "sg:postcode":"9900",
    "sg:province":"Danmark",
    "wof:name":"Gigtplejehjemmet",
    "wof:placetype":"venue"
},
  "geometry": {"coordinates":[10.535656929,57.4455795288],"type":"Point"}
}