{
  "type": "Feature",
  "properties": {
    "addr:full":"Vindingsvej 13 Horsens Danmark 8700",
    "addr:housenumber":"13",
    "addr:postcode":"8700",
    "addr:street":"Vindingsvej",
    "iso:country":"DK",
    "sg:address":"Vindingsvej 13",
    "sg:city":"Horsens",
    "sg:orig_category":"Murermestre",
    "sg:phone":"+45 75 65 83 21",
    "sg:postcode":"8700",
    "sg:province":"Danmark",
    "wof:name":"Stenbjerg Totalbyg ApS",
    "wof:placetype":"venue"
},
  "geometry": {"coordinates":[9.9174852371,55.8783950806],"type":"Point"}
}