{
  "type": "Feature",
  "properties": {
    "addr:full":"St\u00e6remosen 14 Gilleleje Danmark 3250",
    "addr:housenumber":"14",
    "addr:postcode":"3250",
    "addr:street":"Staeremosen",
    "iso:country":"DK",
    "sg:address":"St\u00e6remosen 14",
    "sg:city":"Gilleleje",
    "sg:orig_category":"Fotografer",
    "sg:phone":"+45 48 30 22 11",
    "sg:postcode":"3250",
    "sg:province":"Danmark",
    "wof:name":"DK Foto ApS",
    "wof:placetype":"venue"
},
  "geometry": {"coordinates":[12.3200597763,56.1123695374],"type":"Point"}
}