{
  "type": "Feature",
  "properties": {
    "iso:country":"DK",
    "sg:address":"Fynshovedvej 604",
    "sg:city":"Martofte",
    "sg:orig_category":"Diamantboring",
    "sg:phone":"+45 65 34 22 29",
    "sg:postcode":"5390",
    "sg:province":"Danmark",
    "wof:name":"J\u00f8rgensen, Lars Bo",
    "wof:placetype":"venue"
},
  "geometry": {"coordinates":[10.6503810883,55.5640869141],"type":"Point"}
}