{
  "type": "Feature",
  "properties": {
    "iso:country":"DK",
    "sg:address":"Magleg\u00e5rds Alle 110",
    "sg:city":"S\u00f8borg",
    "sg:orig_category":"INGENI\u00c3\u02dcRER",
    "sg:phone":"+45 39 66 03 77",
    "sg:postcode":"2860",
    "sg:province":"Danmark",
    "wof:name":"Pedersen, Peter Alsted",
    "wof:placetype":"venue"
},
  "geometry": {"coordinates":[-101.39041900629999,35.6679611206],"type":"Point"}
}