{
  "type": "Feature",
  "properties": {
    "addr:full":"Hollandsvej 25, 1. th. Kongens Lyngby Danmark 2800",
    "addr:housenumber":"25 1 th.",
    "addr:postcode":"2800",
    "addr:street":"Hollandsvej",
    "iso:country":"DK",
    "sg:address":"Hollandsvej 25, 1. th.",
    "sg:city":"Kongens Lyngby",
    "sg:orig_category":"Arkitekter",
    "sg:phone":"+45 45 93 88 89",
    "sg:postcode":"2800",
    "sg:province":"Danmark",
    "wof:name":"Mose, Karina",
    "wof:placetype":"venue"
},
  "geometry": {"coordinates":[12.5368299484,55.7949905396],"type":"Point"}
}