{
  "type": "Feature",
  "properties": {
    "addr:full":"\u00d8stergade 11 Skjern Danmark 6900",
    "addr:housenumber":"11",
    "addr:postcode":"6900",
    "addr:street":"Ostergade",
    "iso:country":"DK",
    "sg:address":"\u00d8stergade 11",
    "sg:city":"Skjern",
    "sg:classifiers":[
        {
            "category":"Restaurant",
            "type":"Food & Drink"
        }
    ],
    "sg:phone":"+45 97 35 43 04",
    "sg:postcode":"6900",
    "sg:province":"Danmark",
    "wof:name":"Buffalo",
    "wof:placetype":"venue"
},
  "geometry": {"coordinates":[8.4934587479,55.9488105774],"type":"Point"}
}