{
  "type": "Feature",
  "properties": {
    "addr:full":"Bybjergvej 5 Skovlunde Danmark 2740",
    "addr:housenumber":"5",
    "addr:postcode":"2740",
    "addr:street":"Bybjergvej",
    "iso:country":"DK",
    "sg:address":"Bybjergvej 5",
    "sg:city":"Skovlunde",
    "sg:orig_category":"Vuggestuer",
    "sg:phone":"+45 44 77 16 04",
    "sg:postcode":"2740",
    "sg:province":"Danmark",
    "wof:name":"Ellekilde, Vuggestuen",
    "wof:placetype":"venue"
},
  "geometry": {"coordinates":[12.4023809433,55.7188529968],"type":"Point"}
}