{
  "type": "Feature",
  "properties": {
    "addr:full":"\u00c5rhusgade 119 A K\u00f8benhavn \u00d8 Danmark 2100",
    "addr:housenumber":"119 a",
    "addr:postcode":"2100",
    "addr:street":"Aarhusgade;Kobenhavn O Danmark",
    "iso:country":"DK",
    "sg:address":"\u00c5rhusgade 119 A",
    "sg:city":"K\u00f8benhavn \u00d8",
    "sg:orig_category":"Posthuse",
    "sg:phone":"+45 35 28 91 08",
    "sg:postcode":"2100",
    "sg:province":"Danmark",
    "wof:name":"Post Danmark, Frihavnens Posthus",
    "wof:placetype":"venue"
},
  "geometry": {"coordinates":[11.6836299896,60.2548065186],"type":"Point"}
}