{
  "type": "Feature",
  "properties": {
    "addr:full":"v/ Henrik Wellejus, Sauntev\u00e6nget 14 B Hornb\u00e6k Danmark 3100",
    "addr:housenumber":"14 b",
    "addr:postcode":"3100",
    "addr:street":"Sauntevaenget",
    "iso:country":"DK",
    "sg:address":"v/ Henrik Wellejus, Sauntev\u00e6nget 14 B",
    "sg:city":"Hornb\u00e6k",
    "sg:classifiers":[
        {
            "category":"Communications",
            "type":"Services"
        }
    ],
    "sg:phone":"+45 49 70 01 90",
    "sg:postcode":"3100",
    "sg:province":"Danmark",
    "sg:tags":[
        "radio-",
        "og",
        "tv-stationer"
    ],
    "wof:name":"Radiophelia 92,8 Mhz",
    "wof:placetype":"venue"
},
  "geometry": {"coordinates":[77.2480392456,14.1354398727],"type":"Point"}
}