{
  "type": "Feature",
  "properties": {
    "iso:country":"DK",
    "sg:address":"Alleen 2, Radsted",
    "sg:city":"Saksk\u00f8bing",
    "sg:orig_category":"Konsulentvirksomheder",
    "sg:phone":"+45 54 70 67 99",
    "sg:postcode":"4990",
    "sg:province":"Danmark",
    "sg:website":"www.bp-v.dk",
    "wof:name":"Konsulentfirmaet bp-u",
    "wof:placetype":"venue"
},
  "geometry": {"coordinates":[11.6875448227,54.7894821167],"type":"Point"}
}