{
  "type": "Feature",
  "properties": {
    "iso:country":"DK",
    "sg:address":"Kirkepladsen 12 A",
    "sg:city":"Haslev",
    "sg:orig_category":"Begravelsesforretninger",
    "sg:phone":"+45 56 31 27 35",
    "sg:postcode":"4690",
    "sg:province":"Danmark",
    "sg:website":"www.wilhh.dk/begravelsesforretning",
    "wof:name":"Bedemandsfirmaet a 1894, Wilh. Hansen",
    "wof:placetype":"venue"
},
  "geometry": {"coordinates":[11.963523,55.323315],"type":"Point"}
}