{
  "type": "Feature",
  "properties": {
    "iso:country":"DK",
    "sg:address":"R\u00e5dmands Boulevard 45",
    "sg:city":"Randers",
    "sg:orig_category":"El-automatik",
    "sg:phone":"+45 86 43 30 00",
    "sg:postcode":"8900",
    "sg:province":"Danmark",
    "wof:name":"Semco Automation",
    "wof:placetype":"venue"
},
  "geometry": {"coordinates":[10.0213279724,56.4677352905],"type":"Point"}
}