{
  "type": "Feature",
  "properties": {
    "addr:full":"Kontaktpers.: Inge Andersen, Havnevej 23 Strandby Danmark 9970",
    "addr:housenumber":"23",
    "addr:postcode":"9970",
    "addr:street":"Havnevej",
    "iso:country":"DK",
    "sg:address":"Kontaktpers.: Inge Andersen, Havnevej 23",
    "sg:city":"Strandby",
    "sg:orig_category":"Spejderkorps",
    "sg:phone":"+45 98 48 28 38",
    "sg:postcode":"9970",
    "sg:province":"Danmark",
    "wof:name":"FDF Piger, Strandby",
    "wof:placetype":"venue"
},
  "geometry": {"coordinates":[10.4970350266,57.4932899475],"type":"Point"}
}