{
  "type": "Feature",
  "properties": {
    "iso:country":"DK",
    "sg:address":"\u00d8ster Hurupvej 3, Als",
    "sg:city":"Hadsund",
    "sg:orig_category":"Sparekasser",
    "sg:phone":"+45 98 58 13 88",
    "sg:postcode":"9560",
    "sg:province":"Danmark",
    "wof:name":"Sparekassen Himmerland",
    "wof:placetype":"venue"
},
  "geometry": {"coordinates":[10.115904808,56.7150764465],"type":"Point"}
}