{
  "type": "Feature",
  "properties": {
    "iso:country":"DK",
    "sg:address":"Sandtoften 3 - 7",
    "sg:city":"Gentofte",
    "sg:orig_category":"Handicap-daginstitutioner",
    "sg:phone":"+45 45 88 63 33",
    "sg:postcode":"2820",
    "sg:province":"Danmark",
    "wof:name":"Sandtoften V\u00e6rkstedscentret",
    "wof:placetype":"venue"
},
  "geometry": {"coordinates":[12.5034456253,55.7578849792],"type":"Point"}
}