{
  "type": "Feature",
  "properties": {
    "addr:full":"S\u00f8ndergade 1 Nibe Danmark 9240",
    "addr:housenumber":"1",
    "addr:postcode":"9240",
    "addr:street":"Sondergade",
    "iso:country":"DK",
    "sg:address":"S\u00f8ndergade 1",
    "sg:city":"Nibe",
    "sg:orig_category":"Boghandlere",
    "sg:phone":"+45 98 35 35 93",
    "sg:postcode":"9240",
    "sg:province":"Danmark",
    "wof:name":"Nibe Boghandel",
    "wof:placetype":"venue"
},
  "geometry": {"coordinates":[9.6356086731,56.9819641113],"type":"Point"}
}