{
  "type": "Feature",
  "properties": {
    "addr:full":"Fmd.: Steen Hansen, Ternevej 11 Viby Sj\u00e6lland Danmark 4130",
    "addr:housenumber":"11",
    "addr:postcode":"4130",
    "addr:street":"Ternevej",
    "iso:country":"DK",
    "sg:address":"Fmd.: Steen Hansen, Ternevej 11",
    "sg:city":"Viby Sj\u00e6lland",
    "sg:orig_category":"Grundejerforeninger",
    "sg:phone":"+45 46 19 32 15",
    "sg:postcode":"4130",
    "sg:province":"Danmark",
    "wof:name":"Birkager, Grundejerforeningen",
    "wof:placetype":"venue"
},
  "geometry": {"coordinates":[12.024274826,55.5473709106],"type":"Point"}
}