{
  "type": "Feature",
  "properties": {
    "addr:full":"Bredgade 9 Roskilde Danmark 4000",
    "addr:housenumber":"9",
    "addr:postcode":"4000",
    "addr:street":"Bredgade",
    "iso:country":"DK",
    "sg:address":"Bredgade 9",
    "sg:city":"Roskilde",
    "sg:orig_category":"Teatre",
    "sg:phone":"+45 46 35 32 94",
    "sg:postcode":"4000",
    "sg:province":"Danmark",
    "wof:name":"Teatret i Det Bl\u00e5 Hus",
    "wof:placetype":"venue"
},
  "geometry": {"coordinates":[12.0795192719,55.6393585205],"type":"Point"}
}