{
  "type": "Feature",
  "properties": {
    "addr:full":"Bredgade 17 Bording Danmark 7441",
    "addr:housenumber":"17",
    "addr:postcode":"7441",
    "addr:street":"Bredgade",
    "iso:country":"DK",
    "sg:address":"Bredgade 17",
    "sg:city":"Bording",
    "sg:orig_category":"Jordemodercentre",
    "sg:phone":"+45 86 86 18 52",
    "sg:postcode":"7441",
    "sg:province":"Danmark",
    "wof:name":"Jordemoderkonsultationen",
    "wof:placetype":"venue"
},
  "geometry": {"coordinates":[9.2788906097,56.1454238892],"type":"Point"}
}