{
  "type": "Feature",
  "properties": {
    "addr:full":"Skolegade 23 Holsted Danmark 6670",
    "addr:housenumber":"23",
    "addr:postcode":"6670",
    "addr:street":"Skolegade",
    "iso:country":"DK",
    "sg:address":"Skolegade 23",
    "sg:city":"Holsted",
    "sg:orig_category":"Kinesiologi",
    "sg:phone":"+45 75 39 21 86",
    "sg:postcode":"6670",
    "sg:province":"Danmark",
    "wof:name":"Klinikken",
    "wof:placetype":"venue"
},
  "geometry": {"coordinates":[8.9133958817,55.5134506226],"type":"Point"}
}