{
  "type": "Feature",
  "properties": {
    "addr:full":"Elmegade 5 K\u00f8benhavn N Danmark 2200",
    "addr:housenumber":"5",
    "addr:postcode":"2200",
    "addr:street":"Elmegade;N Danmark",
    "iso:country":"DK",
    "sg:address":"Elmegade 5",
    "sg:city":"K\u00f8benhavn N",
    "sg:classifiers":[
        {
            "category":"Professional",
            "subcategory":"Advertising",
            "type":"Services"
        }
    ],
    "sg:phone":"+45 35 36 14 35",
    "sg:postcode":"2200",
    "sg:province":"Danmark",
    "sg:tags":[
        "marketing"
    ],
    "wof:name":"Marosi Markedsunders\u00f8gelser",
    "wof:placetype":"venue"
},
  "geometry": {"coordinates":[-76.4168395996,37.452419281],"type":"Point"}
}