{
  "type": "Feature",
  "properties": {
    "addr:full":"Falkoner Alle 54 Frederiksberg Danmark 2000",
    "addr:housenumber":"54",
    "addr:postcode":"2000",
    "addr:street":"Falkoner Alle",
    "iso:country":"DK",
    "sg:address":"Falkoner Alle 54",
    "sg:city":"Frederiksberg",
    "sg:orig_category":"INGENI\u00c3\u02dcRER",
    "sg:phone":"+45 35 36 45 00",
    "sg:postcode":"2000",
    "sg:province":"Danmark",
    "sg:website":"www.falkon.dk",
    "wof:name":"Falkon A/S R\u00e5dgivende Ingeni\u00f8rer",
    "wof:placetype":"venue"
},
  "geometry": {"coordinates":[12.5369138718,55.6836280823],"type":"Point"}
}