{
  "type": "Feature",
  "properties": {
    "iso:country":"DK",
    "sg:address":"Naffet 2",
    "sg:city":"Haderslev",
    "sg:orig_category":"Boligselskaber",
    "sg:phone":"+45 74 53 12 15",
    "sg:postcode":"6100",
    "sg:province":"Danmark",
    "sg:website":"www.danskboligselskab.dk",
    "wof:name":"Boligselskabet R\u00f8dekro v/Dansk Boligselskab s.m.b.a.",
    "wof:placetype":"venue"
},
  "geometry": {"coordinates":[9.490363121,55.2490081787],"type":"Point"}
}