{
  "type": "Feature",
  "properties": {
    "addr:full":"Fmd.: Leif Kayer\u00f8d, Gustav Johannsens Vej 38 Frederiksberg Danmark 2000",
    "addr:housenumber":"38",
    "addr:postcode":"2000",
    "addr:street":"Gustav Johannsens Vej",
    "iso:country":"DK",
    "sg:address":"Fmd.: Leif Kayer\u00f8d, Gustav Johannsens Vej 38",
    "sg:city":"Frederiksberg",
    "sg:orig_category":"Kulturelle foreninger",
    "sg:phone":"+45 38 71 43 26",
    "sg:postcode":"2000",
    "sg:province":"Danmark",
    "wof:name":"Glostrup Teaterforening og B\u00f8rneteaterklub",
    "wof:placetype":"venue"
},
  "geometry": {"coordinates":[12.5012350082,55.6809196472],"type":"Point"}
}