{
  "type": "Feature",
  "properties": {
    "iso:country":"DK",
    "sg:address":"M\u00e5strupvej 100",
    "sg:city":"Sindal",
    "sg:orig_category":"Kurerservice",
    "sg:phone":"+45 98 93 07 28",
    "sg:postcode":"9870",
    "sg:province":"Danmark",
    "wof:name":"Andersen, Ren\u00e9",
    "wof:placetype":"venue"
},
  "geometry": {"coordinates":[10.2752819061,57.5178260803],"type":"Point"}
}