{
  "type": "Feature",
  "properties": {
    "addr:full":"Industriparken 15, Lind Herning Danmark 7400",
    "addr:housenumber":"15",
    "addr:postcode":"7400",
    "addr:street":"Industriparken",
    "iso:country":"DK",
    "sg:address":"Industriparken 15, Lind",
    "sg:city":"Herning",
    "sg:orig_category":"Autolakering",
    "sg:phone":"+45 97 12 81 85",
    "sg:postcode":"7400",
    "sg:province":"Danmark",
    "wof:name":"Lind Autolakering",
    "wof:placetype":"venue"
},
  "geometry": {"coordinates":[8.9768896103,56.1374168396],"type":"Point"}
}