{
  "type": "Feature",
  "properties": {
    "iso:country":"DK",
    "sg:address":"Ris\u00f8 Huse 37",
    "sg:city":"Roskilde",
    "sg:orig_category":"Diskoteker",
    "sg:phone":"+45 22 20 04 22",
    "sg:postcode":"4000",
    "sg:province":"Danmark",
    "wof:name":"Roeds Mobildiscotek",
    "wof:placetype":"venue"
},
  "geometry": {"coordinates":[12.1073999405,55.691619873],"type":"Point"}
}