{
  "type": "Feature",
  "properties": {
    "addr:full":"Caroline Amalie Vej 31 Kongens Lyngby Danmark 2800",
    "addr:housenumber":"31",
    "addr:postcode":"2800",
    "addr:street":"Caroline Amalie Vej",
    "iso:country":"DK",
    "sg:address":"Caroline Amalie Vej 31",
    "sg:city":"Kongens Lyngby",
    "sg:orig_category":"Arkitekter",
    "sg:postcode":"2800",
    "sg:province":"Danmark",
    "wof:name":"Tegnestuen Caroline Amalievej",
    "wof:placetype":"venue"
},
  "geometry": {"coordinates":[12.5024290085,55.7829627991],"type":"Point"}
}