{
  "type": "Feature",
  "properties": {
    "addr:full":"Fmd.: Ingrid Berggreen, Egeparken 3 Ikast Danmark 7430",
    "addr:housenumber":"3",
    "addr:postcode":"7430",
    "addr:street":"Egeparken",
    "iso:country":"DK",
    "sg:address":"Fmd.: Ingrid Berggreen, Egeparken 3",
    "sg:city":"Ikast",
    "sg:orig_category":"Kirkelige foreninger",
    "sg:phone":"+45 97 15 44 24",
    "sg:postcode":"7430",
    "sg:province":"Danmark",
    "wof:name":"Unge Hjem",
    "wof:placetype":"venue"
},
  "geometry": {"coordinates":[9.1559419632,56.1394767761],"type":"Point"}
}