{
  "type": "Feature",
  "properties": {
    "addr:full":"Rugmarken 5 Farum Danmark 3520",
    "addr:housenumber":"5",
    "addr:postcode":"3520",
    "addr:street":"Rugmarken",
    "iso:country":"DK",
    "sg:address":"Rugmarken 5",
    "sg:city":"Farum",
    "sg:classifiers":[
        {
            "category":"Wholesale",
            "subcategory":"Chemicals & Plastics",
            "type":"Manufacturing & Wholesale Goods"
        }
    ],
    "sg:phone":"+45 44 95 39 08",
    "sg:postcode":"3520",
    "sg:province":"Danmark",
    "wof:name":"Leta Plastic ApS",
    "wof:placetype":"venue"
},
  "geometry": {"coordinates":[12.3741035461,55.8165435791],"type":"Point"}
}