{
  "type": "Feature",
  "properties": {
    "addr:full":"Gr\u00f8nningen 30 Haderslev Danmark 6100",
    "addr:housenumber":"30",
    "addr:postcode":"6100",
    "addr:street":"Gronningen",
    "iso:country":"DK",
    "sg:address":"Gr\u00f8nningen 30",
    "sg:city":"Haderslev",
    "sg:orig_category":"Bagere",
    "sg:phone":"+45 74 52 47 30",
    "sg:postcode":"6100",
    "sg:province":"Danmark",
    "wof:name":"Guldbageren Gr\u00f8nningen",
    "wof:placetype":"venue"
},
  "geometry": {"coordinates":[9.4879703522,55.2505493164],"type":"Point"}
}