{
  "type": "Feature",
  "properties": {
    "addr:full":"Sognepr\u00e6st: Mogens P. C. Svendsen (K/B), Pr\u00e6stev\u00e6nget 5, K\u00f8lk\u00e6r Herning Danmark 7400",
    "addr:housenumber":"k / b;5",
    "addr:postcode":"7400",
    "addr:street":"Mogens P. C. Svendsen;Praestevaenget;Kolkaer",
    "iso:country":"DK",
    "sg:address":"Sognepr\u00e6st: Mogens P. C. Svendsen (K/B), Pr\u00e6stev\u00e6nget 5, K\u00f8lk\u00e6r",
    "sg:city":"Herning",
    "sg:orig_category":"Kirkesogne",
    "sg:phone":"+45 97 14 70 52",
    "sg:postcode":"7400",
    "sg:province":"Danmark",
    "wof:name":"K\u00f8lkj\u00e6r-Kollund Sogne",
    "wof:placetype":"venue"
},
  "geometry": {"coordinates":[8.9768896103,56.1374168396],"type":"Point"}
}