{
  "type": "Feature",
  "properties": {
    "addr:full":"Adelgade 21 Hobro Danmark 9500",
    "addr:housenumber":"21",
    "addr:postcode":"9500",
    "addr:street":"Adelgade",
    "iso:country":"DK",
    "sg:address":"Adelgade 21",
    "sg:city":"Hobro",
    "sg:orig_category":"Designere",
    "sg:phone":"+45 96 57 00 84",
    "sg:postcode":"9500",
    "sg:province":"Danmark",
    "wof:name":"Joy Design, Greg",
    "wof:placetype":"venue"
},
  "geometry": {"coordinates":[9.7938022614,56.6389884949],"type":"Point"}
}