{
  "type": "Feature",
  "properties": {
    "addr:full":"Dalgas Boulevard 91 Frederiksberg Danmark 2000",
    "addr:housenumber":"91",
    "addr:postcode":"2000",
    "addr:street":"Dalgas Boulevard",
    "iso:country":"DK",
    "sg:address":"Dalgas Boulevard 91",
    "sg:city":"Frederiksberg",
    "sg:orig_category":"Apoteker og -udsalg",
    "sg:phone":"+45 38 86 43 43",
    "sg:postcode":"2000",
    "sg:province":"Danmark",
    "wof:name":"Dalgas Boulevard Apotek",
    "wof:placetype":"venue"
},
  "geometry": {"coordinates":[12.5105810165,55.6816902161],"type":"Point"}
}