{
  "type": "Feature",
  "properties": {
    "addr:full":"Strandvejen 80 Hellerup Danmark 2900",
    "addr:housenumber":"80",
    "addr:postcode":"2900",
    "addr:street":"Strandvejen",
    "iso:country":"DK",
    "sg:address":"Strandvejen 80",
    "sg:city":"Hellerup",
    "sg:classifiers":[
        {
            "category":"Banks & Credit Unions",
            "subcategory":"Bank",
            "type":"Services"
        }
    ],
    "sg:phone":"+45 39 45 80 80",
    "sg:postcode":"2900",
    "sg:province":"Danmark",
    "sg:tags":[
        "banker"
    ],
    "sg:website":"www.danskebank.dk",
    "wof:name":"Danske Bank",
    "wof:placetype":"venue"
},
  "geometry": {"coordinates":[12.5765781403,55.7301940918],"type":"Point"}
}