{
  "type": "Feature",
  "properties": {
    "addr:full":"Landpolitiassistent: Per Toustrup, Bakkevej 22, Nr. Broby Broby Danmark 5672",
    "addr:housenumber":"22",
    "addr:postcode":"5672",
    "addr:street":"Bakkevej",
    "iso:country":"DK",
    "sg:address":"Landpolitiassistent: Per Toustrup, Bakkevej 22, Nr. Broby",
    "sg:city":"Broby",
    "sg:orig_category":"Politi",
    "sg:phone":"+45 62 63 20 48",
    "sg:postcode":"5672",
    "sg:province":"Danmark",
    "wof:name":"Landpolitiet i Broby",
    "wof:placetype":"venue"
},
  "geometry": {"coordinates":[10.3131303787,55.2695846558],"type":"Point"}
}