{
  "type": "Feature",
  "properties": {
    "addr:full":"Vonsildvej 32, Vonsild Kolding Danmark 6000",
    "addr:housenumber":"32",
    "addr:postcode":"6000",
    "addr:street":"Vonsildvej;Vonsild",
    "iso:country":"DK",
    "sg:address":"Vonsildvej 32, Vonsild",
    "sg:city":"Kolding",
    "sg:orig_category":"Benzinstationer",
    "sg:phone":"+45 75 56 61 03",
    "sg:postcode":"6000",
    "sg:province":"Danmark",
    "wof:name":"Texaco Vonsild",
    "wof:placetype":"venue"
},
  "geometry": {"coordinates":[9.473395,55.486359],"type":"Point"}
}