{
  "type": "Feature",
  "properties": {
    "addr:full":"Jagtvej 155 D K\u00f8benhavn N Danmark 2200",
    "addr:housenumber":"155 d",
    "addr:postcode":"2200",
    "addr:street":"Jagtvej;Kobenhavn N Danmark",
    "iso:country":"DK",
    "sg:address":"Jagtvej 155 D",
    "sg:city":"K\u00f8benhavn N",
    "sg:orig_category":"Fagforbund og -foreninger",
    "sg:phone":"+45 35 82 63 63",
    "sg:postcode":"2200",
    "sg:province":"Danmark",
    "wof:name":"IFF K\u00f8benhavn",
    "wof:placetype":"venue"
},
  "geometry": {"coordinates":[-112.4642486572,36.7487220764],"type":"Point"}
}