{
  "type": "Feature",
  "properties": {
    "addr:full":"Vestergade 25 Vejle Danmark 7100",
    "addr:housenumber":"25",
    "addr:postcode":"7100",
    "addr:street":"Vestergade",
    "iso:country":"DK",
    "sg:address":"Vestergade 25",
    "sg:city":"Vejle",
    "sg:orig_category":"Indramning",
    "sg:phone":"+45 75 82 12 30",
    "sg:postcode":"7100",
    "sg:province":"Danmark",
    "wof:name":"Avanti",
    "wof:placetype":"venue"
},
  "geometry": {"coordinates":[9.5361785889,55.7121658325],"type":"Point"}
}