{
  "type": "Feature",
  "properties": {
    "addr:full":"Thisted Kystvej 4 Thisted Danmark 7700",
    "addr:housenumber":"4",
    "addr:postcode":"7700",
    "addr:street":"Thisted Kystvej",
    "iso:country":"DK",
    "sg:address":"Thisted Kystvej 4",
    "sg:city":"Thisted",
    "sg:classifiers":[
        {
            "category":"Museum",
            "type":"Entertainment"
        }
    ],
    "sg:phone":"+45 99 17 73 00",
    "sg:postcode":"7700",
    "sg:province":"Danmark",
    "sg:tags":[
        "og",
        "skat",
        "told"
    ],
    "wof:name":"Skyldr\u00e5det for Viborg Amt Ndr. Skyldkreds",
    "wof:placetype":"venue"
},
  "geometry": {"coordinates":[8.6908779144,56.9516143799],"type":"Point"}
}