{
  "type": "Feature",
  "properties": {
    "addr:full":"Fmd.: Kirsten Penther, Hallenslevvej 20, Hallenslev G\u00f8rlev Danmark 4281",
    "addr:housenumber":"20",
    "addr:postcode":"4281",
    "addr:street":"Hallenslevvej",
    "iso:country":"DK",
    "sg:address":"Fmd.: Kirsten Penther, Hallenslevvej 20, Hallenslev",
    "sg:city":"G\u00f8rlev",
    "sg:orig_category":"Kulturelle foreninger",
    "sg:phone":"+45 58 85 37 53",
    "sg:postcode":"4281",
    "sg:province":"Danmark",
    "wof:name":"T\u00f8mmerup Sogns Lokalhistoriske Forening",
    "wof:placetype":"venue"
},
  "geometry": {"coordinates":[11.1143903732,55.5207710266],"type":"Point"}
}