{
  "type": "Feature",
  "properties": {
    "addr:full":"Fmd.: Keld J\u00f8rgensen, Vestervej 11 Ringsted Danmark 4100",
    "addr:housenumber":"11",
    "addr:postcode":"4100",
    "addr:street":"Vestervej",
    "iso:country":"DK",
    "sg:address":"Fmd.: Keld J\u00f8rgensen, Vestervej 11",
    "sg:city":"Ringsted",
    "sg:orig_category":"Kolonihaveforeninger",
    "sg:phone":"+45 57 61 70 08",
    "sg:postcode":"4100",
    "sg:province":"Danmark",
    "wof:name":"Kolonihaveforbundet",
    "wof:placetype":"venue"
},
  "geometry": {"coordinates":[11.7875862122,55.4458961487],"type":"Point"}
}