{
  "type": "Feature",
  "properties": {
    "addr:full":"Vodskovvej 136 Vodskov Danmark 9310",
    "addr:housenumber":"136",
    "addr:postcode":"9310",
    "addr:street":"Vodskovvej",
    "iso:country":"DK",
    "sg:address":"Vodskovvej 136",
    "sg:city":"Vodskov",
    "sg:orig_category":"Kiropraktorer",
    "sg:phone":"+45 98 28 64 11",
    "sg:postcode":"9310",
    "sg:province":"Danmark",
    "wof:name":"Kiropraktisk Klinik",
    "wof:placetype":"venue"
},
  "geometry": {"coordinates":[10.0681066513,57.1256256104],"type":"Point"}
}