{
  "type": "Feature",
  "properties": {
    "addr:full":"Vestergade 2 Jelling Danmark 7300",
    "addr:housenumber":"2",
    "addr:postcode":"7300",
    "addr:street":"Vestergade",
    "iso:country":"DK",
    "sg:address":"Vestergade 2",
    "sg:city":"Jelling",
    "sg:orig_category":"Boligselskaber",
    "sg:phone":"+45 75 87 11 26",
    "sg:postcode":"7300",
    "sg:province":"Danmark",
    "wof:name":"Jelling Boligselskab",
    "wof:placetype":"venue"
},
  "geometry": {"coordinates":[9.4178333282,55.7567901611],"type":"Point"}
}