{
  "type": "Feature",
  "properties": {
    "addr:full":"Dalgas Avenue 46 \u00c5rhus C Danmark 8000",
    "addr:housenumber":"46",
    "addr:postcode":"8000",
    "addr:street":"Dalgas Avenue",
    "iso:country":"DK",
    "sg:address":"Dalgas Avenue 46",
    "sg:city":"\u00c5rhus C",
    "sg:orig_category":"Statslige direktorater og styrelser",
    "sg:phone":"+45 86 14 51 00",
    "sg:postcode":"8000",
    "sg:province":"Danmark",
    "wof:name":"\u00c5rhus Stift",
    "wof:placetype":"venue"
},
  "geometry": {"coordinates":[-66.94068145750001,-27.6476192474],"type":"Point"}
}