{
  "type": "Feature",
  "properties": {
    "iso:country":"DK",
    "sg:address":"Fmd.: Tulle Zehngraff, J\u00e6gersborgvej 2, Sjolte",
    "sg:city":"Tappern\u00f8je",
    "sg:orig_category":"Kulturelle foreninger",
    "sg:phone":"+45 55 96 52 74",
    "sg:postcode":"4733",
    "sg:province":"Danmark",
    "wof:name":"Everdrup Kor- og Musikforening",
    "wof:placetype":"venue"
},
  "geometry": {"coordinates":[11.9756202698,55.1781692505],"type":"Point"}
}