{
  "type": "Feature",
  "properties": {
    "addr:full":"Meinungsgade 4 KLD. K\u00f8benhavn N Danmark 2200",
    "addr:housenumber":"4 kld. kobenhavn",
    "addr:postcode":"2200",
    "addr:street":"Meinungsgade;N Danmark",
    "iso:country":"DK",
    "sg:address":"Meinungsgade 4 KLD.",
    "sg:city":"K\u00f8benhavn N",
    "sg:orig_category":"Blikkenslagere",
    "sg:phone":"+45 35 36 31 19",
    "sg:postcode":"2200",
    "sg:province":"Danmark",
    "wof:name":"Frederiksen ApS, Blikkenslagerfirmaet S\u00f8ren",
    "wof:placetype":"venue"
},
  "geometry": {"coordinates":[-76.41683999999999,37.452419],"type":"Point"}
}