{
  "type": "Feature",
  "properties": {
    "addr:full":"Thorvaldsensgade 29 \u00c5rhus C Danmark 8000",
    "addr:housenumber":"29",
    "addr:postcode":"8000",
    "addr:street":"Thorvaldsensgade",
    "iso:country":"DK",
    "sg:address":"Thorvaldsensgade 29",
    "sg:city":"\u00c5rhus C",
    "sg:orig_category":"Cykler",
    "sg:phone":"+45 86 13 34 36",
    "sg:postcode":"8000",
    "sg:province":"Danmark",
    "wof:name":"Fri Cykler",
    "wof:placetype":"venue"
},
  "geometry": {"coordinates":[4.717400074,49.7588005066],"type":"Point"}
}