{
  "type": "Feature",
  "properties": {
    "addr:full":"Skovalle 16 Lang\u00e5 Danmark 8870",
    "addr:housenumber":"16",
    "addr:postcode":"8870",
    "addr:street":"Skovalle",
    "iso:country":"DK",
    "sg:address":"Skovalle 16",
    "sg:city":"Lang\u00e5",
    "sg:orig_category":"Campingpladser",
    "sg:phone":"+45 86 46 13 02",
    "sg:postcode":"8870",
    "sg:province":"Danmark",
    "wof:name":"Lang\u00e5 Campingplads",
    "wof:placetype":"venue"
},
  "geometry": {"coordinates":[9.9061393738,56.3874168396],"type":"Point"}
}