{
  "type": "Feature",
  "properties": {
    "addr:full":"N\u00f8rre Frankel 2, Havneby R\u00f8m\u00f8 Danmark 6792",
    "addr:housenumber":"2",
    "addr:postcode":"6792",
    "addr:street":"Frankel",
    "iso:country":"DK",
    "sg:address":"N\u00f8rre Frankel 2, Havneby",
    "sg:city":"R\u00f8m\u00f8",
    "sg:orig_category":"Skilte",
    "sg:phone":"+45 74 75 57 42",
    "sg:postcode":"6792",
    "sg:province":"Danmark",
    "wof:name":"Stjerne Sign",
    "wof:placetype":"venue"
},
  "geometry": {"coordinates":[8.5544652939,55.0871963501],"type":"Point"}
}