{
  "type": "Feature",
  "properties": {
    "addr:full":"D\u00f8esvej 56 Holstebro Danmark 7500",
    "addr:housenumber":"56",
    "addr:postcode":"7500",
    "addr:street":"Doesvej",
    "iso:country":"DK",
    "sg:address":"D\u00f8esvej 56",
    "sg:city":"Holstebro",
    "sg:orig_category":"Fritidsklubber",
    "sg:phone":"+45 96 11 61 90",
    "sg:postcode":"7500",
    "sg:province":"Danmark",
    "wof:name":"Klub Trekanten D\u00f8esvej",
    "wof:placetype":"venue"
},
  "geometry": {"coordinates":[8.6054334641,56.3690109253],"type":"Point"}
}