{
  "type": "Feature",
  "properties": {
    "addr:full":"Nytorv 13 B, o.g., 1. tv. Aalborg Danmark 9000",
    "addr:housenumber":"13 b;1",
    "addr:postcode":"9000",
    "addr:street":"Nytorv;O.G.;Tv.",
    "iso:country":"DK",
    "sg:address":"Nytorv 13 B, o.g., 1. tv.",
    "sg:city":"Aalborg",
    "sg:orig_category":"Kulturcentre",
    "sg:phone":"+45 98 12 95 40",
    "sg:postcode":"9000",
    "sg:province":"Danmark",
    "wof:name":"Kulturcenteret Aalborg",
    "wof:placetype":"venue"
},
  "geometry": {"coordinates":[9.9162902832,57.0493545532],"type":"Point"}
}