{
  "type": "Feature",
  "properties": {
    "addr:full":"Barfredsvej 82 - 84 Frederikshavn Danmark 9900",
    "addr:housenumber":"82 84",
    "addr:postcode":"9900",
    "addr:street":"Barfredsvej",
    "iso:country":"DK",
    "sg:address":"Barfredsvej 82 - 84",
    "sg:city":"Frederikshavn",
    "sg:orig_category":"Autoforhandlere",
    "sg:phone":"+45 98 42 11 44",
    "sg:postcode":"9900",
    "sg:province":"Danmark",
    "wof:name":"Carlsen & S\u00f8n, G. S.",
    "wof:placetype":"venue"
},
  "geometry": {"coordinates":[10.5322704315,57.4450798035],"type":"Point"}
}