{
  "type": "Feature",
  "properties": {
    "addr:full":"\u00d8stergade 50 Assens Danmark 5610",
    "addr:housenumber":"50",
    "addr:postcode":"5610",
    "addr:street":"Ostergade",
    "iso:country":"DK",
    "sg:address":"\u00d8stergade 50",
    "sg:city":"Assens",
    "sg:classifiers":[
        {
            "category":"Communications",
            "type":"Services"
        }
    ],
    "sg:phone":"+45 64 71 12 56",
    "sg:postcode":"5610",
    "sg:province":"Danmark",
    "sg:tags":[
        "og",
        "tv",
        "radio"
    ],
    "wof:name":"2tal Jensby",
    "wof:placetype":"venue"
},
  "geometry": {"coordinates":[9.8982038498,55.2699661255],"type":"Point"}
}