{
  "type": "Feature",
  "properties": {
    "addr:full":"Artillerivej 150 K\u00f8benhavn S Danmark 2300",
    "addr:housenumber":"150",
    "addr:postcode":"2300",
    "addr:street":"Artillerivej;Kobenhavn S Danmark",
    "iso:country":"DK",
    "sg:address":"Artillerivej 150",
    "sg:city":"K\u00f8benhavn S",
    "sg:orig_category":"Grillbarer",
    "sg:phone":"+45 32 95 27 06",
    "sg:postcode":"2300",
    "sg:province":"Danmark",
    "wof:name":"Bryggen's Grill",
    "wof:placetype":"venue"
},
  "geometry": {"coordinates":[-78.1299133301,36.7267417908],"type":"Point"}
}