{
  "type": "Feature",
  "properties": {
    "addr:full":"Gotfred Rodes Vej 9 Charlottenlund Danmark 2920",
    "addr:housenumber":"9",
    "addr:postcode":"2920",
    "addr:street":"Gotfred Rodes Vej",
    "iso:country":"DK",
    "sg:address":"Gotfred Rodes Vej 9",
    "sg:city":"Charlottenlund",
    "sg:orig_category":"Import-eksport",
    "sg:phone":"+45 39 90 08 18",
    "sg:postcode":"2920",
    "sg:province":"Danmark",
    "wof:name":"Natuco",
    "wof:placetype":"venue"
},
  "geometry": {"coordinates":[12.5663928986,55.7677764893],"type":"Point"}
}