{
  "type": "Feature",
  "properties": {
    "addr:full":"Sognepr\u00e6st: J\u00f8rgen Mose Laursen, Besser Hovedgade 1 Sams\u00f8 Danmark 8305",
    "addr:housenumber":"1",
    "addr:postcode":"8305",
    "addr:street":"Jorgen Mose Laursen Besser Hovedgade",
    "iso:country":"DK",
    "sg:address":"Sognepr\u00e6st: J\u00f8rgen Mose Laursen, Besser Hovedgade 1",
    "sg:city":"Sams\u00f8",
    "sg:orig_category":"Kirkesogne",
    "sg:phone":"+45 86 59 00 83",
    "sg:postcode":"8305",
    "sg:province":"Danmark",
    "wof:name":"Besser Sogn",
    "wof:placetype":"venue"
},
  "geometry": {"coordinates":[-86.164932251,31.0499763489],"type":"Point"}
}