{
  "type": "Feature",
  "properties": {
    "addr:full":"S\u00f8nderg\u00e5rdsvej 5, Hvolb\u00e6k Skanderborg Danmark 8660",
    "addr:housenumber":"5",
    "addr:postcode":"8660",
    "addr:street":"Sondergaardsvej",
    "iso:country":"DK",
    "sg:address":"S\u00f8nderg\u00e5rdsvej 5, Hvolb\u00e6k",
    "sg:city":"Skanderborg",
    "sg:classifiers":[
        {
            "category":"Arts & Performance",
            "subcategory":"Dance",
            "type":"Entertainment"
        }
    ],
    "sg:phone":"+45 86 53 13 66",
    "sg:postcode":"8660",
    "sg:province":"Danmark",
    "sg:tags":[
        "montage"
    ],
    "wof:name":"LJ Montage",
    "wof:placetype":"venue"
},
  "geometry": {"coordinates":[9.929974556,56.0380249023],"type":"Point"}
}