{
  "type": "Feature",
  "properties": {
    "addr:full":"Gl. Landevej 1 Vejle Danmark 7100",
    "addr:housenumber":"1",
    "addr:postcode":"7100",
    "addr:street":"Gl. Landevej",
    "iso:country":"DK",
    "sg:address":"Gl. Landevej 1",
    "sg:city":"Vejle",
    "sg:orig_category":"Farve og tapet",
    "sg:phone":"+45 75 85 12 11",
    "sg:postcode":"7100",
    "sg:province":"Danmark",
    "wof:name":"Bekan",
    "wof:placetype":"venue"
},
  "geometry": {"coordinates":[9.5470199585,55.692615509],"type":"Point"}
}