{
  "type": "Feature",
  "properties": {
    "addr:full":"Lynge Stationsvej 16 Lynge Danmark 3540",
    "addr:housenumber":"16",
    "addr:postcode":"3540",
    "addr:street":"Lynge Stationsvej",
    "iso:country":"DK",
    "sg:address":"Lynge Stationsvej 16",
    "sg:city":"Lynge",
    "sg:orig_category":"Ungdomsklubber",
    "sg:phone":"+45 48 18 82 37",
    "sg:postcode":"3540",
    "sg:province":"Danmark",
    "wof:name":"Hobitten B\u00f8rne- og Ungdomshus",
    "wof:placetype":"venue"
},
  "geometry": {"coordinates":[12.2691783905,55.8359222412],"type":"Point"}
}