{
  "type": "Feature",
  "properties": {
    "iso:country":"DK",
    "sg:address":"Hedevolden 3",
    "sg:city":"Hedehusene",
    "sg:orig_category":"Spejderkorps",
    "sg:phone":"+45 46 56 19 58",
    "sg:postcode":"2640",
    "sg:province":"Danmark",
    "sg:website":"www.fdf.dk/home/hedehusene",
    "wof:name":"FDF, Hedehusene",
    "wof:placetype":"venue"
},
  "geometry": {"coordinates":[12.2024774551,55.6495094299],"type":"Point"}
}