{
  "type": "Feature",
  "properties": {
    "addr:full":"Tofteledet 19 Herlev Danmark 2730",
    "addr:housenumber":"19",
    "addr:postcode":"2730",
    "addr:street":"Tofteledet",
    "iso:country":"DK",
    "sg:address":"Tofteledet 19",
    "sg:city":"Herlev",
    "sg:orig_category":"Arkitekter",
    "sg:phone":"+45 44 94 50 14",
    "sg:postcode":"2730",
    "sg:province":"Danmark",
    "wof:name":"Bygningsr\u00e5dgiverne",
    "wof:placetype":"venue"
},
  "geometry": {"coordinates":[12.4129104614,55.739025116],"type":"Point"}
}