{
  "type": "Feature",
  "properties": {
    "addr:full":"Kontaktperson: Susanne Lange, J\u00f8rgensg\u00e5rd 5 B Aabenraa Danmark 6200",
    "addr:housenumber":"5 b",
    "addr:postcode":"6200",
    "addr:street":"Jorgensgaard",
    "iso:country":"DK",
    "sg:address":"Kontaktperson: Susanne Lange, J\u00f8rgensg\u00e5rd 5 B",
    "sg:city":"Aabenraa",
    "sg:orig_category":"Loger",
    "sg:phone":"+45 74 62 92 27",
    "sg:postcode":"6200",
    "sg:province":"Danmark",
    "wof:name":"Sct. Georgsgilderne 2. Aabenraa",
    "wof:placetype":"venue"
},
  "geometry": {"coordinates":[9.4213867188,55.0449562073],"type":"Point"}
}