{
  "type": "Feature",
  "properties": {
    "iso:country":"DK",
    "sg:address":"Herningvej 48",
    "sg:city":"Aalborg \u00d8",
    "sg:orig_category":"Billard",
    "sg:phone":"+45 98 15 76 03",
    "sg:postcode":"9220",
    "sg:province":"Danmark",
    "wof:name":"Aalborg Billardmontering",
    "wof:placetype":"venue"
},
  "geometry": {"coordinates":[9.982559,57.026096],"type":"Point"}
}