{
  "type": "Feature",
  "properties": {
    "iso:country":"DK",
    "sg:address":"Elektronvej 3",
    "sg:city":"Greve",
    "sg:orig_category":"Smedemestre",
    "sg:phone":"+45 43 90 23 11",
    "sg:postcode":"2670",
    "sg:province":"Danmark",
    "wof:name":"Reflex Danmark ApS",
    "wof:placetype":"venue"
},
  "geometry": {"coordinates":[12.3002576828,55.6063957214],"type":"Point"}
}