{
  "type": "Feature",
  "properties": {
    "iso:country":"DK",
    "sg:address":"Fmd.: Ole Kaas Andersen, Nygade 84",
    "sg:city":"Ikast",
    "sg:orig_category":"Hobbybetonede foreninger",
    "sg:phone":"+45 97 15 64 71",
    "sg:postcode":"7430",
    "sg:province":"Danmark",
    "wof:name":"Danmarks Civile Hundef\u00f8rerforening, Ikast afdeling",
    "wof:placetype":"venue"
},
  "geometry": {"coordinates":[9.1559419632,56.1394767761],"type":"Point"}
}