{
  "type": "Feature",
  "properties": {
    "addr:full":"Tjelevej 5, \u00d8rum Tjele Danmark 8830",
    "addr:housenumber":"5",
    "addr:postcode":"8830",
    "addr:street":"Tjelevej;Orum",
    "iso:country":"DK",
    "sg:address":"Tjelevej 5, \u00d8rum",
    "sg:city":"Tjele",
    "sg:orig_category":"Foder",
    "sg:phone":"+45 86 65 26 55",
    "sg:postcode":"8830",
    "sg:province":"Danmark",
    "wof:name":"A-One Feed Supplements LTD.",
    "wof:placetype":"venue"
},
  "geometry": {"coordinates":[9.6264801025,56.4818611145],"type":"Point"}
}