{
  "type": "Feature",
  "properties": {
    "addr:full":"Odensevej 95 Faaborg Danmark 5600",
    "addr:housenumber":"95",
    "addr:postcode":"5600",
    "addr:street":"Odensevej",
    "iso:country":"DK",
    "sg:address":"Odensevej 95",
    "sg:city":"Faaborg",
    "sg:orig_category":"Reklamegaver",
    "sg:phone":"+45 62 61 82 82",
    "sg:postcode":"5600",
    "sg:province":"Danmark",
    "sg:website":"www.kaaredesign.dk",
    "wof:name":"Kaare Design ApS, L.",
    "wof:placetype":"venue"
},
  "geometry": {"coordinates":[10.2400655746,55.1084823608],"type":"Point"}
}