{
  "type": "Feature",
  "properties": {
    "addr:full":"Nymindegabvej 247 Outrup Danmark 6855",
    "addr:housenumber":"247",
    "addr:postcode":"6855",
    "addr:street":"Nymindegabvej",
    "iso:country":"DK",
    "sg:address":"Nymindegabvej 247",
    "sg:city":"Outrup",
    "sg:orig_category":"Diners transportables",
    "sg:phone":"+45 75 25 17 29",
    "sg:postcode":"6855",
    "sg:province":"Danmark",
    "sg:website":"www.hjortshoejs.dk",
    "wof:name":"Hjortsh\u00f8j's Party Grill Diner Transportable",
    "wof:placetype":"venue"
},
  "geometry": {"coordinates":[8.3378772736,55.7291107178],"type":"Point"}
}