{
  "type": "Feature",
  "properties": {
    "addr:full":"Poulsgade 2-4 Herning Danmark 7400",
    "addr:housenumber":"2-4",
    "addr:postcode":"7400",
    "addr:street":"Poulsgade",
    "iso:country":"DK",
    "sg:address":"Poulsgade 2-4",
    "sg:city":"Herning",
    "sg:orig_category":"Autoudlejning",
    "sg:phone":"+45 97 22 64 99",
    "sg:postcode":"7400",
    "sg:province":"Danmark",
    "wof:name":"Avis biludlejning i Herning",
    "wof:placetype":"venue"
},
  "geometry": {"coordinates":[8.9840717316,56.1325492859],"type":"Point"}
}