{
  "type": "Feature",
  "properties": {
    "addr:full":"Holte Stationsvej 36 Holte Danmark 2840",
    "addr:housenumber":"36",
    "addr:postcode":"2840",
    "addr:street":"Holte Stationsvej",
    "iso:country":"DK",
    "sg:address":"Holte Stationsvej 36",
    "sg:city":"Holte",
    "sg:orig_category":"Jernbaner",
    "sg:phone":"+45 45 42 01 61",
    "sg:postcode":"2840",
    "sg:province":"Danmark",
    "wof:name":"DSB, Holte Station",
    "wof:placetype":"venue"
},
  "geometry": {"coordinates":[12.469045639,55.8084373474],"type":"Point"}
}