{
  "type": "Feature",
  "properties": {
    "addr:full":"Korreborgvej 23 Bjerringbro Danmark 8850",
    "addr:housenumber":"23",
    "addr:postcode":"8850",
    "addr:street":"Korreborgvej",
    "iso:country":"DK",
    "sg:address":"Korreborgvej 23",
    "sg:city":"Bjerringbro",
    "sg:orig_category":"Murermestre",
    "sg:phone":"+45 86 68 52 28",
    "sg:postcode":"8850",
    "sg:province":"Danmark",
    "wof:name":"Jensen, Finn",
    "wof:placetype":"venue"
},
  "geometry": {"coordinates":[9.6059980392,56.4255714417],"type":"Point"}
}