{
  "type": "Feature",
  "properties": {
    "iso:country":"DK",
    "sg:address":"Vesl\u00f8s Stationsvej 27",
    "sg:city":"Vesl\u00f8s",
    "sg:classifiers":[
        {
            "category":"Banks & Credit Unions",
            "subcategory":"Bank",
            "type":"Services"
        }
    ],
    "sg:phone":"+45 97 99 35 00",
    "sg:postcode":"7742",
    "sg:province":"Danmark",
    "sg:tags":[
        "banker"
    ],
    "sg:website":"www.ehh.dk",
    "wof:name":"Egnsbank Han Herred",
    "wof:placetype":"venue"
},
  "geometry": {"coordinates":[-80.725227,26.676359],"type":"Point"}
}