{
  "type": "Feature",
  "properties": {
    "addr:full":"Skivevej 68 Sunds Danmark 7451",
    "addr:housenumber":"68",
    "addr:postcode":"7451",
    "addr:street":"Skivevej",
    "iso:country":"DK",
    "sg:address":"Skivevej 68",
    "sg:city":"Sunds",
    "sg:orig_category":"Blomsterhandlere",
    "sg:phone":"+45 97 14 10 50",
    "sg:postcode":"7451",
    "sg:province":"Danmark",
    "wof:name":"Svendsen, Lene",
    "wof:placetype":"venue"
},
  "geometry": {"coordinates":[9.0080680847,56.2371292114],"type":"Point"}
}