{
  "type": "Feature",
  "properties": {
    "addr:full":"Skovglimt 11 Krus\u00e5 Danmark 6340",
    "addr:housenumber":"11",
    "addr:postcode":"6340",
    "addr:street":"Skovglimt",
    "iso:country":"DK",
    "sg:address":"Skovglimt 11",
    "sg:city":"Krus\u00e5",
    "sg:orig_category":"Genbrugsbutikker",
    "sg:phone":"+45 73 67 31 31",
    "sg:postcode":"6340",
    "sg:province":"Danmark",
    "wof:name":"Dansk R\u00f8de Kors Genbrugsbutik",
    "wof:placetype":"venue"
},
  "geometry": {"coordinates":[9.3994226456,54.8487319946],"type":"Point"}
}