{
  "type": "Feature",
  "properties": {
    "addr:full":"Leder: Henny Jensenius, M\u00e5gebakken Odense SV Danmark 5250",
    "addr:postcode":"5250",
    "addr:street":"Maagebakken",
    "iso:country":"DK",
    "sg:address":"Leder: Henny Jensenius, M\u00e5gebakken",
    "sg:city":"Odense SV",
    "sg:orig_category":"Lokalarkiver",
    "sg:postcode":"5250",
    "sg:province":"Danmark",
    "wof:name":"Sanderum Sogns Lokalhistoriske Arkiv",
    "wof:placetype":"venue"
},
  "geometry": {"coordinates":[10.3153953552,55.3362998962],"type":"Point"}
}