{
  "type": "Feature",
  "properties": {
    "iso:country":"DK",
    "sg:address":"Fmd.: Helge Hvid, \u00d8sterh\u00f8j Bygade 149",
    "sg:city":"Ballerup",
    "sg:orig_category":"Grundejerforeninger",
    "sg:phone":"+45 44 68 56 80",
    "sg:postcode":"2750",
    "sg:province":"Danmark",
    "wof:name":"Grundejerforeningen, Bopladsen",
    "wof:placetype":"venue"
},
  "geometry": {"coordinates":[12.361000061,55.7301216125],"type":"Point"}
}