{
  "type": "Feature",
  "properties": {
    "addr:full":"Industriparken 18 Jyderup Danmark 4450",
    "addr:housenumber":"18",
    "addr:postcode":"4450",
    "addr:street":"Industriparken",
    "iso:country":"DK",
    "sg:address":"Industriparken 18",
    "sg:city":"Jyderup",
    "sg:orig_category":"Vaskerier",
    "sg:phone":"+45 59 27 76 74",
    "sg:postcode":"4450",
    "sg:province":"Danmark",
    "wof:name":"Erhvervsvaskeriet",
    "wof:placetype":"venue"
},
  "geometry": {"coordinates":[11.4127721786,55.6594772339],"type":"Point"}
}