{
  "type": "Feature",
  "properties": {
    "addr:full":"Fmd.: Kim Bertelsen, Humlehaven 4, Postboks 263 Hedensted Danmark 8722",
    "addr:housenumber":"4;263",
    "addr:postcode":"8722",
    "addr:street":"Humlehaven",
    "iso:country":"DK",
    "sg:address":"Fmd.: Kim Bertelsen, Humlehaven 4, Postboks 263",
    "sg:city":"Hedensted",
    "sg:orig_category":"Loger",
    "sg:phone":"+45 75 89 06 88",
    "sg:postcode":"8722",
    "sg:province":"Danmark",
    "sg:website":"www.jcvejk.dk",
    "wof:name":"Junior Chamber Vejle",
    "wof:placetype":"venue"
},
  "geometry": {"coordinates":[9.6973247528,55.7688903809],"type":"Point"}
}