{
  "type": "Feature",
  "properties": {
    "addr:full":"Skovbakken 70 Farum Danmark 3520",
    "addr:housenumber":"70",
    "addr:postcode":"3520",
    "addr:street":"Skovbakken",
    "iso:country":"DK",
    "sg:address":"Skovbakken 70",
    "sg:city":"Farum",
    "sg:orig_category":"INGENI\u00c3\u02dcRER",
    "sg:phone":"+45 44 95 35 08",
    "sg:postcode":"3520",
    "sg:province":"Danmark",
    "sg:website":"www.anderschristensen.dk",
    "wof:name":"Christensen, Anders",
    "wof:placetype":"venue"
},
  "geometry": {"coordinates":[12.3993339539,55.8093986511],"type":"Point"}
}