{
  "type": "Feature",
  "properties": {
    "iso:country":"DK",
    "sg:address":"Hersnap Bygade 14, Hersnap",
    "sg:city":"Dalby",
    "sg:orig_category":"Kontorservice",
    "sg:phone":"+45 65 34 19 97",
    "sg:postcode":"5380",
    "sg:province":"Danmark",
    "wof:name":"RS Kontorservice",
    "wof:placetype":"venue"
},
  "geometry": {"coordinates":[10.6553220749,55.5158843994],"type":"Point"}
}