{
  "type": "Feature",
  "properties": {
    "addr:full":"\u00d8rslevklostervej 140, Hald H\u00f8jslev Danmark 7840",
    "addr:housenumber":"140",
    "addr:postcode":"7840",
    "addr:street":"Orslevklostervej",
    "iso:country":"DK",
    "sg:address":"\u00d8rslevklostervej 140, Hald",
    "sg:city":"H\u00f8jslev",
    "sg:orig_category":"Forsamlingshuse",
    "sg:postcode":"7840",
    "sg:province":"Danmark",
    "wof:name":"Hald forsamlingshus",
    "wof:placetype":"venue"
},
  "geometry": {"coordinates":[9.110039711,56.5504264832],"type":"Point"}
}