{
  "type": "Feature",
  "properties": {
    "iso:country":"DK",
    "sg:address":"Himmerlandsgade 46",
    "sg:city":"Aars",
    "sg:orig_category":"Slagter og viktualie",
    "sg:phone":"+45 98 62 40 74",
    "sg:postcode":"9600",
    "sg:province":"Danmark",
    "wof:name":"Klemmen",
    "wof:placetype":"venue"
},
  "geometry": {"coordinates":[9.5199356079,56.8035163879],"type":"Point"}
}