{
  "type": "Feature",
  "properties": {
    "addr:full":"\u00d8rrev\u00e6nget 5, Sinding Herning Danmark 7400",
    "addr:housenumber":"5",
    "addr:postcode":"7400",
    "addr:street":"Orrevaenget;Sinding",
    "iso:country":"DK",
    "sg:address":"\u00d8rrev\u00e6nget 5, Sinding",
    "sg:city":"Herning",
    "sg:orig_category":"Forsamlingshuse",
    "sg:phone":"+45 97 13 62 66",
    "sg:postcode":"7400",
    "sg:province":"Danmark",
    "wof:name":"Sinding Forsamlingshus",
    "wof:placetype":"venue"
},
  "geometry": {"coordinates":[8.9768896103,56.1374168396],"type":"Point"}
}