{
  "type": "Feature",
  "properties": {
    "addr:full":"Byrum Hovedgade 87, Byrum L\u00e6s\u00f8 Danmark 9940",
    "addr:housenumber":"87",
    "addr:postcode":"9940",
    "addr:street":"Byrum Hovedgade",
    "iso:country":"DK",
    "sg:address":"Byrum Hovedgade 87, Byrum",
    "sg:city":"L\u00e6s\u00f8",
    "sg:orig_category":"Kiosker",
    "sg:phone":"+45 98 49 14 54",
    "sg:postcode":"9940",
    "sg:province":"Danmark",
    "wof:name":"Centrum D\u00f8gnkiosken",
    "wof:placetype":"venue"
},
  "geometry": {"coordinates":[10.9232254028,57.2928199768],"type":"Point"}
}