{
  "type": "Feature",
  "properties": {
    "iso:country":"DK",
    "sg:address":"Engblommevej 7, Bellinge",
    "sg:city":"Odense SV",
    "sg:orig_category":"Solcentre",
    "sg:phone":"+45 65 96 08 25",
    "sg:postcode":"5250",
    "sg:province":"Danmark",
    "wof:name":"Andersen, Henning Nykj\u00e6r",
    "wof:placetype":"venue"
},
  "geometry": {"coordinates":[10.3153953552,55.3362998962],"type":"Point"}
}