{
  "type": "Feature",
  "properties": {
    "addr:full":"R\u00f8n Alle 2 - 4 Haslev Danmark 4690",
    "addr:housenumber":"2 4",
    "addr:postcode":"4690",
    "addr:street":"Ron Alle",
    "iso:country":"DK",
    "sg:address":"R\u00f8n Alle 2 - 4",
    "sg:city":"Haslev",
    "sg:orig_category":"Billard",
    "sg:phone":"+45 56 31 22 23",
    "sg:postcode":"4690",
    "sg:province":"Danmark",
    "sg:website":"www.haslev-billardfabrik.dk",
    "wof:name":"Haslev Billardfabrik",
    "wof:placetype":"venue"
},
  "geometry": {"coordinates":[11.980436,55.321037],"type":"Point"}
}