{
  "type": "Feature",
  "properties": {
    "addr:full":"Tranh\u00f8j 13, Tranum Brovst Danmark 9460",
    "addr:housenumber":"13",
    "addr:postcode":"9460",
    "addr:street":"Tranhoj;Tranum",
    "iso:country":"DK",
    "sg:address":"Tranh\u00f8j 13, Tranum",
    "sg:city":"Brovst",
    "sg:orig_category":"Forsamlingshuse",
    "sg:phone":"+45 98 23 52 66",
    "sg:postcode":"9460",
    "sg:province":"Danmark",
    "wof:name":"Tranum Forsamingshus",
    "wof:placetype":"venue"
},
  "geometry": {"coordinates":[9.5220241547,57.097366333],"type":"Point"}
}