{
  "type": "Feature",
  "properties": {
    "addr:full":"Ramtenvej 14 Nimtofte Danmark 8581",
    "addr:housenumber":"14",
    "addr:postcode":"8581",
    "addr:street":"Ramtenvej",
    "iso:country":"DK",
    "sg:address":"Ramtenvej 14",
    "sg:city":"Nimtofte",
    "sg:orig_category":"Kommunale folkeskoler",
    "sg:phone":"+45 86 39 81 37",
    "sg:postcode":"8581",
    "sg:province":"Danmark",
    "wof:name":"Bauneskolen",
    "wof:placetype":"venue"
},
  "geometry": {"coordinates":[10.5704011917,56.4093132019],"type":"Point"}
}