{
  "type": "Feature",
  "properties": {
    "addr:full":"Fars\u00f8vej 22, Strandby Fars\u00f8 Danmark 9640",
    "addr:housenumber":"22",
    "addr:postcode":"9640",
    "addr:street":"Farsovej",
    "iso:country":"DK",
    "sg:address":"Fars\u00f8vej 22, Strandby",
    "sg:city":"Fars\u00f8",
    "sg:orig_category":"Murermestre",
    "sg:phone":"+45 98 63 63 06",
    "sg:postcode":"9640",
    "sg:province":"Danmark",
    "wof:name":"M\u00f8ller, Erik",
    "wof:placetype":"venue"
},
  "geometry": {"coordinates":[9.1937885284,56.6945037842],"type":"Point"}
}