{
  "type": "Feature",
  "properties": {
    "iso:country":"DK",
    "sg:address":"Vester Alle 6",
    "sg:city":"\u00c5rhus C",
    "sg:orig_category":"Alternativ behandling",
    "sg:phone":"+45 86 19 06 00",
    "sg:postcode":"8000",
    "sg:province":"Danmark",
    "sg:website":"www.klinikkenaarhus.dk",
    "wof:name":"Laserklinikken",
    "wof:placetype":"venue"
},
  "geometry": {"coordinates":[-85.2299499512,37.1363105774],"type":"Point"}
}