{
  "type": "Feature",
  "properties": {
    "addr:full":"Baltorpvej 20 A Ballerup Danmark 2750",
    "addr:housenumber":"20 a",
    "addr:postcode":"2750",
    "addr:street":"Baltorpvej",
    "iso:country":"DK",
    "sg:address":"Baltorpvej 20 A",
    "sg:city":"Ballerup",
    "sg:orig_category":"Erhvervsskoler",
    "sg:phone":"+45 44 20 02 00",
    "sg:postcode":"2750",
    "sg:province":"Danmark",
    "sg:website":"www.hib.dk",
    "wof:name":"Handelsskolen i Ballerup",
    "wof:placetype":"venue"
},
  "geometry": {"coordinates":[12.3520078659,55.7302856445],"type":"Point"}
}