{
  "type": "Feature",
  "properties": {
    "addr:full":"Lyngby Hovedgade 48, 1. Kongens Lyngby Danmark 2800",
    "addr:housenumber":"48 1",
    "addr:postcode":"2800",
    "addr:street":"Lyngby Hovedgade",
    "iso:country":"DK",
    "sg:address":"Lyngby Hovedgade 48, 1.",
    "sg:city":"Kongens Lyngby",
    "sg:orig_category":"Musik- og sangundervisning",
    "sg:phone":"+45 45 93 23 16",
    "sg:postcode":"2800",
    "sg:province":"Danmark",
    "wof:name":"Nielsen, Birgitte Friis",
    "wof:placetype":"venue"
},
  "geometry": {"coordinates":[12.5014419556,55.7718544006],"type":"Point"}
}