{
  "type": "Feature",
  "properties": {
    "addr:full":"Bredgade 20 st K\u00f8benhavn Danmark 1260",
    "addr:housenumber":"20",
    "addr:postcode":"1260",
    "addr:street":"Bredgade",
    "iso:country":"DK",
    "sg:address":"Bredgade 20 st",
    "sg:city":"K\u00f8benhavn",
    "sg:orig_category":"Cafeer",
    "sg:phone":"+45 33 15 40 45",
    "sg:postcode":"1260",
    "sg:province":"Danmark",
    "wof:name":"Caf\u00e9 Asb\u00e6k",
    "wof:placetype":"venue"
},
  "geometry": {"coordinates":[12.5931997299,55.6845016479],"type":"Point"}
}