{
  "type": "Feature",
  "properties": {
    "iso:country":"DK",
    "sg:address":"Pannerupvej 7",
    "sg:city":"Trige",
    "sg:orig_category":"Vuggestuer",
    "sg:phone":"+45 86 23 17 30",
    "sg:postcode":"8380",
    "sg:province":"Danmark",
    "wof:name":"Lindeg\u00e5rden, Vuggestue",
    "wof:placetype":"venue"
},
  "geometry": {"coordinates":[10.1552419662,56.256061554],"type":"Point"}
}