{
  "type": "Feature",
  "properties": {
    "addr:full":"Rydeng 2 A Egtved Danmark 6040",
    "addr:housenumber":"2 a",
    "addr:postcode":"6040",
    "addr:street":"Rydeng",
    "iso:country":"DK",
    "sg:address":"Rydeng 2 A",
    "sg:city":"Egtved",
    "sg:orig_category":"Gigtsygdomme Reumatologi",
    "sg:phone":"+45 75 55 17 77",
    "sg:postcode":"6040",
    "sg:province":"Danmark",
    "wof:name":"Dalsgaard, J\u00f8rgen",
    "wof:placetype":"venue"
},
  "geometry": {"coordinates":[9.3043527603,55.6153793335],"type":"Point"}
}