{
  "type": "Feature",
  "properties": {
    "addr:full":"Toftlundvej 146, Spandet Ribe Danmark 6760",
    "addr:housenumber":"146",
    "addr:postcode":"6760",
    "addr:street":"Toftlundvej;Spandet",
    "iso:country":"DK",
    "sg:address":"Toftlundvej 146, Spandet",
    "sg:city":"Ribe",
    "sg:orig_category":"Murermestre",
    "sg:phone":"+45 74 86 74 60",
    "sg:postcode":"6760",
    "sg:province":"Danmark",
    "wof:name":"Spandet Murerforretning",
    "wof:placetype":"venue"
},
  "geometry": {"coordinates":[8.7656240463,55.3297042847],"type":"Point"}
}