{
  "type": "Feature",
  "properties": {
    "addr:full":"Fjordvej 9 Hundested Danmark 3390",
    "addr:housenumber":"9",
    "addr:postcode":"3390",
    "addr:street":"Fjordvej",
    "iso:country":"DK",
    "sg:address":"Fjordvej 9",
    "sg:city":"Hundested",
    "sg:orig_category":"Solcentre",
    "sg:phone":"+45 47 93 86 27",
    "sg:postcode":"3390",
    "sg:province":"Danmark",
    "wof:name":"Midnight Sun",
    "wof:placetype":"venue"
},
  "geometry": {"coordinates":[11.8560113907,55.9589347839],"type":"Point"}
}