{
  "type": "Feature",
  "properties": {
    "addr:full":"Soldalen 8 Vildbjerg Danmark 7480",
    "addr:housenumber":"8",
    "addr:postcode":"7480",
    "addr:street":"Soldalen",
    "iso:country":"DK",
    "sg:address":"Soldalen 8",
    "sg:city":"Vildbjerg",
    "sg:orig_category":"Skolefritidsordninger",
    "sg:phone":"+45 97 13 28 28",
    "sg:postcode":"7480",
    "sg:province":"Danmark",
    "wof:name":"Kildebakkeskolens Fritidsordning",
    "wof:placetype":"venue"
},
  "geometry": {"coordinates":[8.7770166397,56.1949577332],"type":"Point"}
}