{
  "type": "Feature",
  "properties": {
    "addr:full":"Sognepr\u00e6st: S\u00f8ren R. Willesen, Bygaden 34, Kundby Svinninge Danmark 4520",
    "addr:housenumber":"34",
    "addr:postcode":"4520",
    "addr:street":"Bygaden",
    "iso:country":"DK",
    "sg:address":"Sognepr\u00e6st: S\u00f8ren R. Willesen, Bygaden 34, Kundby",
    "sg:city":"Svinninge",
    "sg:orig_category":"Kirkesogne",
    "sg:phone":"+45 59 26 40 88",
    "sg:postcode":"4520",
    "sg:province":"Danmark",
    "sg:website":"www.folkekirken.dk/sogn/kundby",
    "wof:name":"Kundby Sogn",
    "wof:placetype":"venue"
},
  "geometry": {"coordinates":[11.4649095535,55.7226104736],"type":"Point"}
}