{
  "type": "Feature",
  "properties": {
    "addr:full":"Vejlevej 26 Fredericia Danmark 7000",
    "addr:housenumber":"26",
    "addr:postcode":"7000",
    "addr:street":"Vejlevej",
    "iso:country":"DK",
    "sg:address":"Vejlevej 26",
    "sg:city":"Fredericia",
    "sg:orig_category":"Servicestationer",
    "sg:phone":"+45 75 93 42 44",
    "sg:postcode":"7000",
    "sg:province":"Danmark",
    "wof:name":"Shell Service",
    "wof:placetype":"venue"
},
  "geometry": {"coordinates":[9.7238950729,55.569480896],"type":"Point"}
}