{
  "type": "Feature",
  "properties": {
    "addr:full":"Fmd.: K. S. Laursen, \u00d8rumvej 26 Hvidovre Danmark 2650",
    "addr:housenumber":"26",
    "addr:postcode":"2650",
    "addr:street":"Orumvej",
    "iso:country":"DK",
    "sg:address":"Fmd.: K. S. Laursen, \u00d8rumvej 26",
    "sg:city":"Hvidovre",
    "sg:orig_category":"Grundejerforeninger",
    "sg:phone":"+45 36 49 07 85",
    "sg:postcode":"2650",
    "sg:province":"Danmark",
    "wof:name":"Aved\u00f8re Grundejerforening",
    "wof:placetype":"venue"
},
  "geometry": {"coordinates":[12.474360466,55.6366386414],"type":"Point"}
}