{
  "type": "Feature",
  "properties": {
    "iso:country":"DK",
    "sg:address":"Bethaniavej 8",
    "sg:city":"Jelling",
    "sg:orig_category":"Cykler",
    "sg:phone":"+45 75 87 10 44",
    "sg:postcode":"7300",
    "sg:province":"Danmark",
    "wof:name":"Imgro",
    "wof:placetype":"venue"
},
  "geometry": {"coordinates":[9.4166707993,55.7551803589],"type":"Point"}
}