{
  "type": "Feature",
  "properties": {
    "addr:full":"v/ Harry Lyngs\u00f8, Brakkervej 8 Egtved Danmark 6040",
    "addr:housenumber":"8",
    "addr:postcode":"6040",
    "addr:street":"Brakkervej",
    "iso:country":"DK",
    "sg:address":"v/ Harry Lyngs\u00f8, Brakkervej 8",
    "sg:city":"Egtved",
    "sg:orig_category":"\u00c3\u2020ldreorganisationer og klubber",
    "sg:phone":"+45 75 55 32 26",
    "sg:postcode":"6040",
    "sg:province":"Danmark",
    "wof:name":"\u00d8. Starup/\u00c5g\u00e5rd Efterl\u00f8n- og Pensionistforening",
    "wof:placetype":"venue"
},
  "geometry": {"coordinates":[9.3087482452,55.6161613464],"type":"Point"}
}