{
  "type": "Feature",
  "properties": {
    "addr:full":"Gr\u00f8nnegade 43 Faaborg Danmark 5600",
    "addr:housenumber":"43",
    "addr:postcode":"5600",
    "addr:street":"Gronnegade",
    "iso:country":"DK",
    "sg:address":"Gr\u00f8nnegade 43",
    "sg:city":"Faaborg",
    "sg:orig_category":"Dyrehandlere",
    "sg:phone":"+45 62 61 35 82",
    "sg:postcode":"5600",
    "sg:province":"Danmark",
    "wof:name":"Gr\u00f8nnegades Dyrehandel",
    "wof:placetype":"venue"
},
  "geometry": {"coordinates":[10.2446546555,55.0957832336],"type":"Point"}
}