{
  "type": "Feature",
  "properties": {
    "addr:full":"Storegade 27, \u00d8. Doense Hobro Danmark 9500",
    "addr:housenumber":"27 o.",
    "addr:postcode":"9500",
    "addr:street":"Storegade;Doense",
    "iso:country":"DK",
    "sg:address":"Storegade 27, \u00d8. Doense",
    "sg:city":"Hobro",
    "sg:orig_category":"Brugsforeninger",
    "sg:phone":"+45 98 55 40 16",
    "sg:postcode":"9500",
    "sg:province":"Danmark",
    "wof:name":"Lokal Brugsen",
    "wof:placetype":"venue"
},
  "geometry": {"coordinates":[9.7946596146,56.6382789612],"type":"Point"}
}