{
  "type": "Feature",
  "properties": {
    "addr:full":"\u00d8rnsbjergvej 10, Tr\u00f8llund Hejnsvig Danmark 7250",
    "addr:housenumber":"10",
    "addr:postcode":"7250",
    "addr:street":"Ornsbjergvej",
    "iso:country":"DK",
    "sg:address":"\u00d8rnsbjergvej 10, Tr\u00f8llund",
    "sg:city":"Hejnsvig",
    "sg:orig_category":"Erhvervslokaler, Udlejning af",
    "sg:phone":"+45 75 33 54 60",
    "sg:postcode":"7250",
    "sg:province":"Danmark",
    "wof:name":"Larsen, Gerd Johannes",
    "wof:placetype":"venue"
},
  "geometry": {"coordinates":[8.9966459274,55.6951141357],"type":"Point"}
}