{
  "type": "Feature",
  "properties": {
    "addr:full":"Ravnsborggade 22 K\u00f8benhavn N Danmark 2200",
    "addr:housenumber":"22",
    "addr:postcode":"2200",
    "addr:street":"Ravnsborggade;N Danmark",
    "iso:country":"DK",
    "sg:address":"Ravnsborggade 22",
    "sg:city":"K\u00f8benhavn N",
    "sg:orig_category":"Antikviteter",
    "sg:phone":"+45 35 37 88 89",
    "sg:postcode":"2200",
    "sg:province":"Danmark",
    "wof:name":"Ingerslev Antik",
    "wof:placetype":"venue"
},
  "geometry": {"coordinates":[-112.1497955322,36.4110908508],"type":"Point"}
}