{
  "type": "Feature",
  "properties": {
    "addr:full":"Bj\u00f8rnb\u00e6kvej 33  Hjallerup Danmark 9320",
    "addr:housenumber":"33",
    "addr:postcode":"9320",
    "addr:street":"Bjornbaekvej",
    "iso:country":"DK",
    "sg:address":"Bj\u00f8rnb\u00e6kvej 33 ",
    "sg:city":"Hjallerup",
    "sg:classifiers":[
        {
            "category":"Food & Beverages",
            "subcategory":"Dairy",
            "type":"Retail Goods"
        }
    ],
    "sg:phone":"+45 98 28 12 00",
    "sg:postcode":"9320",
    "sg:province":"Danmark",
    "sg:tags":[
        "product"
    ],
    "wof:name":"MEJERI \u00d8RUM",
    "wof:placetype":"venue"
},
  "geometry": {"coordinates":[10.1444702148,57.1677742004],"type":"Point"}
}