{
  "type": "Feature",
  "properties": {
    "addr:full":"Lindskovvej 9, Hadsund Syd Hadsund Danmark 9560",
    "addr:housenumber":"9",
    "addr:postcode":"9560",
    "addr:street":"Lindskovvej;Syd",
    "iso:country":"DK",
    "sg:address":"Lindskovvej 9, Hadsund Syd",
    "sg:city":"Hadsund",
    "sg:orig_category":"Ejendomshandel",
    "sg:phone":"+45 98 57 21 17",
    "sg:postcode":"9560",
    "sg:province":"Danmark",
    "wof:name":"Westergaards Ejendomsm\u00e6glerfirma",
    "wof:placetype":"venue"
},
  "geometry": {"coordinates":[10.115904808,56.7150764465],"type":"Point"}
}