{
  "type": "Feature",
  "properties": {
    "addr:full":"Amagerbrogade 32 K\u00f8benhavn S Danmark 2300",
    "addr:housenumber":"32",
    "addr:postcode":"2300",
    "addr:street":"Amagerbrogade;Kobenhavn S Danmark",
    "iso:country":"DK",
    "sg:address":"Amagerbrogade 32",
    "sg:city":"K\u00f8benhavn S",
    "sg:classifiers":[
        {
            "category":"Restaurant",
            "type":"Food & Drink"
        }
    ],
    "sg:phone":"+45 32 95 22 15",
    "sg:postcode":"2300",
    "sg:province":"Danmark",
    "wof:name":"Pasta House",
    "wof:placetype":"venue"
},
  "geometry": {"coordinates":[-78.1299133301,36.7267417908],"type":"Point"}
}