{
  "type": "Feature",
  "properties": {
    "iso:country":"DK",
    "sg:address":"Hulskovvej 33, Sdr. Vilstrup",
    "sg:city":"Kolding",
    "sg:orig_category":"Kirker",
    "sg:postcode":"6000",
    "sg:province":"Danmark",
    "wof:name":"Sdr. Vilstrup Kirke",
    "wof:placetype":"venue"
},
  "geometry": {"coordinates":[9.4733953476,55.4863586426],"type":"Point"}
}