{
  "type": "Feature",
  "properties": {
    "addr:full":"v/ Ellen E. Christensen, Surreroj 15, Bylderup Bylderup-Bov Danmark 6372",
    "addr:housenumber":"15",
    "addr:postcode":"6372",
    "addr:street":"Surreroj;Bylderup",
    "iso:country":"DK",
    "sg:address":"v/ Ellen E. Christensen, Surreroj 15, Bylderup",
    "sg:city":"Bylderup-Bov",
    "sg:orig_category":"\u00c3\u02dcvrig fritidsundervisning",
    "sg:phone":"+45 74 76 28 33",
    "sg:postcode":"6372",
    "sg:province":"Danmark",
    "wof:name":"AB-skolen",
    "wof:placetype":"venue"
},
  "geometry": {"coordinates":[9.0861902237,54.941783905],"type":"Point"}
}