{
  "type": "Feature",
  "properties": {
    "iso:country":"DK",
    "sg:address":"Engdraget 2",
    "sg:city":"Svendborg",
    "sg:orig_category":"Integrerede institutioner",
    "sg:phone":"+45 62 22 98 44",
    "sg:postcode":"5700",
    "sg:province":"Danmark",
    "wof:name":"Kildeb\u00e6kken, B\u00f8rnehave",
    "wof:placetype":"venue"
},
  "geometry": {"coordinates":[10.578125,55.0479850769],"type":"Point"}
}