{
  "type": "Feature",
  "properties": {
    "addr:full":"v/ Anne-Grethe Falk, Smedel\u00f8kken 70, Tejn Allinge Danmark 3770",
    "addr:housenumber":"70",
    "addr:postcode":"3770",
    "addr:street":"Tejn",
    "iso:country":"DK",
    "sg:address":"v/ Anne-Grethe Falk, Smedel\u00f8kken 70, Tejn",
    "sg:city":"Allinge",
    "sg:orig_category":"Spejderkorps",
    "sg:phone":"+45 56 48 19 31",
    "sg:postcode":"3770",
    "sg:province":"Danmark",
    "wof:name":"Adventistsamfundets Spejderkorps",
    "wof:placetype":"venue"
},
  "geometry": {"coordinates":[14.7998552322,55.2743835449],"type":"Point"}
}