{
  "type": "Feature",
  "properties": {
    "addr:full":"Floravej 23 Ringe Danmark 5750",
    "addr:housenumber":"23",
    "addr:postcode":"5750",
    "addr:street":"Floravej",
    "iso:country":"DK",
    "sg:address":"Floravej 23",
    "sg:city":"Ringe",
    "sg:orig_category":"\u00c3\u02dcvrige institutioner",
    "sg:phone":"+45 62 62 45 00",
    "sg:postcode":"5750",
    "sg:province":"Danmark",
    "wof:name":"Bof\u00e6llesskabet Floravej",
    "wof:placetype":"venue"
},
  "geometry": {"coordinates":[10.4754238129,55.2411117554],"type":"Point"}
}