{
  "type": "Feature",
  "properties": {
    "iso:country":"DK",
    "sg:address":"Sct. Nilsvej 4",
    "sg:city":"Slangerup",
    "sg:orig_category":"Isolering",
    "sg:phone":"+45 47 33 50 56",
    "sg:postcode":"3550",
    "sg:province":"Danmark",
    "wof:name":"Vimo Isolation",
    "wof:placetype":"venue"
},
  "geometry": {"coordinates":[12.1745872498,55.840007782],"type":"Point"}
}