{
  "type": "Feature",
  "properties": {
    "addr:full":"Sct. J\u00f8rgensgade 1 Gudhjem Danmark 3760",
    "addr:housenumber":"1",
    "addr:postcode":"3760",
    "addr:street":"Jorgensgade",
    "iso:country":"DK",
    "sg:address":"Sct. J\u00f8rgensgade 1",
    "sg:city":"Gudhjem",
    "sg:orig_category":"Malermestre",
    "sg:phone":"+45 56 48 50 16",
    "sg:postcode":"3760",
    "sg:province":"Danmark",
    "wof:name":"Tranberg, Hans",
    "wof:placetype":"venue"
},
  "geometry": {"coordinates":[15.1870470047,55.3205566406],"type":"Point"}
}