{
  "type": "Feature",
  "properties": {
    "addr:full":"Str\u00f8bjergvej 29, Sigerslev\u00f8ster Frederikssund Danmark 3600",
    "addr:housenumber":"29",
    "addr:postcode":"3600",
    "addr:street":"Strobjergvej",
    "iso:country":"DK",
    "sg:address":"Str\u00f8bjergvej 29, Sigerslev\u00f8ster",
    "sg:city":"Frederikssund",
    "sg:orig_category":"Maskinfabrikker",
    "sg:phone":"+45 48 21 84 11",
    "sg:postcode":"3600",
    "sg:province":"Danmark",
    "wof:name":"Labotek A/S",
    "wof:placetype":"venue"
},
  "geometry": {"coordinates":[12.0661621094,55.8370323181],"type":"Point"}
}