{
  "type": "Feature",
  "properties": {
    "iso:country":"DK",
    "sg:address":"Vardevej 36",
    "sg:city":"Vejle",
    "sg:orig_category":"Slagter og viktualie",
    "sg:phone":"+45 75 82 09 70",
    "sg:postcode":"7100",
    "sg:province":"Danmark",
    "wof:name":"N\u00f8rskov, E.",
    "wof:placetype":"venue"
},
  "geometry": {"coordinates":[9.5235042572,55.7159843445],"type":"Point"}
}