{
  "type": "Feature",
  "properties": {
    "addr:full":"Fribr\u00f8ndsvej 7 Sejer\u00f8 Danmark 4592",
    "addr:housenumber":"7",
    "addr:postcode":"4592",
    "addr:street":"Fribrondsvej",
    "iso:country":"DK",
    "sg:address":"Fribr\u00f8ndsvej 7",
    "sg:city":"Sejer\u00f8",
    "sg:classifiers":[
        {
            "category":"Restaurant",
            "type":"Food & Drink"
        }
    ],
    "sg:phone":"+45 59 59 00 07",
    "sg:postcode":"4592",
    "sg:province":"Danmark",
    "wof:name":"Sp\u00e6tten, Caf\u00e9",
    "wof:placetype":"venue"
},
  "geometry": {"coordinates":[11.1474161148,55.8862762451],"type":"Point"}
}