{
  "type": "Feature",
  "properties": {
    "iso:country":"DK",
    "sg:address":"Vestergade 28 D",
    "sg:city":"Vejle",
    "sg:orig_category":"Konsulentvirksomheder",
    "sg:phone":"+45 75 72 33 30",
    "sg:postcode":"7100",
    "sg:province":"Danmark",
    "wof:name":"Axco Risikostyring",
    "wof:placetype":"venue"
},
  "geometry": {"coordinates":[9.5369787216,55.7132606506],"type":"Point"}
}