{
  "type": "Feature",
  "properties": {
    "addr:full":"Madevej 13 Aabenraa Danmark 6200",
    "addr:housenumber":"13",
    "addr:postcode":"6200",
    "addr:street":"Madevej",
    "iso:country":"DK",
    "sg:address":"Madevej 13",
    "sg:city":"Aabenraa",
    "sg:orig_category":"INGENI\u00c3\u02dcRER",
    "sg:phone":"+45 74 62 69 70",
    "sg:postcode":"6200",
    "sg:province":"Danmark",
    "wof:name":"Bro A/S, Carl",
    "wof:placetype":"venue"
},
  "geometry": {"coordinates":[9.4203796387,55.0439567566],"type":"Point"}
}