{
  "type": "Feature",
  "properties": {
    "addr:full":"Jernbanegade 5 Kolding Danmark 6000",
    "addr:housenumber":"5",
    "addr:postcode":"6000",
    "addr:street":"Jernbanegade",
    "iso:country":"DK",
    "sg:address":"Jernbanegade 5",
    "sg:city":"Kolding",
    "sg:classifiers":[
        {
            "category":"Banks & Credit Unions",
            "subcategory":"Bank",
            "type":"Services"
        }
    ],
    "sg:phone":"+45 76 34 18 00",
    "sg:postcode":"6000",
    "sg:province":"Danmark",
    "sg:tags":[
        "banker"
    ],
    "sg:website":"www.jyskebank.dk",
    "wof:name":"Jyske Bank",
    "wof:placetype":"venue"
},
  "geometry": {"coordinates":[9.475233078,55.4902572632],"type":"Point"}
}