{
  "type": "Feature",
  "properties": {
    "addr:full":"Vejlegadebro 1 - 5 Nakskov Danmark 4900",
    "addr:housenumber":"1 5",
    "addr:postcode":"4900",
    "addr:street":"Vejlegadebro",
    "iso:country":"DK",
    "sg:address":"Vejlegadebro 1 - 5",
    "sg:city":"Nakskov",
    "sg:orig_category":"Autoophug",
    "sg:phone":"+45 54 92 15 30",
    "sg:postcode":"4900",
    "sg:province":"Danmark",
    "wof:name":"Johnnie's Autodele",
    "wof:placetype":"venue"
},
  "geometry": {"coordinates":[11.1312141418,54.83335495],"type":"Point"}
}