{
  "type": "Feature",
  "properties": {
    "addr:full":"Nordre Strandvej 357 Hornb\u00e6k Danmark 3100",
    "addr:housenumber":"357",
    "addr:postcode":"3100",
    "addr:street":"Nordre Strandvej",
    "iso:country":"DK",
    "sg:address":"Nordre Strandvej 357",
    "sg:city":"Hornb\u00e6k",
    "sg:orig_category":"Pizzeriaer",
    "sg:phone":"+45 49 70 37 57",
    "sg:postcode":"3100",
    "sg:province":"Danmark",
    "wof:name":"Jims Pizza og Shawarmasted",
    "wof:placetype":"venue"
},
  "geometry": {"coordinates":[12.035369873,60.8038711548],"type":"Point"}
}