{
  "type": "Feature",
  "properties": {
    "addr:full":"Peblinge Dossering 20 K\u00f8benhavn N Danmark 2200",
    "addr:housenumber":"20",
    "addr:postcode":"2200",
    "addr:street":"Peblinge Dossering;N Danmark",
    "iso:country":"DK",
    "sg:address":"Peblinge Dossering 20",
    "sg:city":"K\u00f8benhavn N",
    "sg:orig_category":"Diskoteker, Mobile",
    "sg:phone":"+45 22 20 04 22",
    "sg:postcode":"2200",
    "sg:province":"Danmark",
    "sg:website":"www.rdg.dk",
    "wof:name":"R.D Light & Sound I/S",
    "wof:placetype":"venue"
},
  "geometry": {"coordinates":[-94.49351501460001,47.8772392273],"type":"Point"}
}