{
  "type": "Feature",
  "properties": {
    "addr:full":"Ny Kongensgade 13 K\u00f8benhavn Danmark 1472",
    "addr:housenumber":"13",
    "addr:postcode":"1472",
    "addr:street":"Kongensgade",
    "iso:country":"DK",
    "sg:address":"Ny Kongensgade 13",
    "sg:city":"K\u00f8benhavn",
    "sg:orig_category":"Statslige direktorater og styrelser",
    "sg:phone":"+45 33 91 11 99",
    "sg:postcode":"1472",
    "sg:province":"Danmark",
    "sg:website":"www.symfonien.dk",
    "wof:name":"Sj\u00e6llands Symfoniorkester",
    "wof:placetype":"venue"
},
  "geometry": {"coordinates":[12.5766000748,55.6721000671],"type":"Point"}
}