{
  "type": "Feature",
  "properties": {
    "addr:full":"Mosevej 3 Kirke Hyllinge Danmark 4070",
    "addr:housenumber":"3",
    "addr:postcode":"4070",
    "addr:street":"Mosevej",
    "iso:country":"DK",
    "sg:address":"Mosevej 3",
    "sg:city":"Kirke Hyllinge",
    "sg:orig_category":"Elektroindustri",
    "sg:phone":"+45 46 40 44 05",
    "sg:postcode":"4070",
    "sg:province":"Danmark",
    "wof:name":"Larsen & Brusgaard",
    "wof:placetype":"venue"
},
  "geometry": {"coordinates":[11.8962593079,55.70570755],"type":"Point"}
}