{
  "type": "Feature",
  "properties": {
    "iso:country":"DK",
    "sg:address":"Falkoner Alle 17",
    "sg:city":"Frederiksberg",
    "sg:classifiers":[
        {
            "category":"Restaurant",
            "type":"Food & Drink"
        }
    ],
    "sg:phone":"+45 38 11 93 33",
    "sg:postcode":"2000",
    "sg:province":"Danmark",
    "wof:name":"Vagabondos Cantina",
    "wof:placetype":"venue"
},
  "geometry": {"coordinates":[12.5339269638,55.6807403564],"type":"Point"}
}