{
  "type": "Feature",
  "properties": {
    "addr:full":"N\u00f8rregade 144, Gl. Ejby Ejby Danmark 5592",
    "addr:housenumber":"144",
    "addr:postcode":"5592",
    "addr:street":"Norregade;Gl. Ejby",
    "iso:country":"DK",
    "sg:address":"N\u00f8rregade 144, Gl. Ejby",
    "sg:city":"Ejby",
    "sg:orig_category":"Autoforhandlere",
    "sg:phone":"+45 64 46 12 27",
    "sg:postcode":"5592",
    "sg:province":"Danmark",
    "wof:name":"Madsen A/S, E. Hindsgaul",
    "wof:placetype":"venue"
},
  "geometry": {"coordinates":[9.9277296066,55.4288444519],"type":"Point"}
}