{
  "type": "Feature",
  "properties": {
    "iso:country":"DK",
    "sg:address":"St. Sct. Peder Str\u00e6de 4",
    "sg:city":"Viborg",
    "sg:classifiers":[
        {
            "category":"Banks & Credit Unions",
            "subcategory":"Bank",
            "type":"Services"
        }
    ],
    "sg:phone":"+45 86 60 27 00",
    "sg:postcode":"8800",
    "sg:province":"Danmark",
    "sg:tags":[
        "banker"
    ],
    "sg:website":"www.vestjyskbank.dk",
    "wof:name":"Vestjysk Bank A/S",
    "wof:placetype":"venue"
},
  "geometry": {"coordinates":[9.40715,56.452671],"type":"Point"}
}