{
  "type": "Feature",
  "properties": {
    "addr:full":"Thorsgade 2 Randers Danmark 8900",
    "addr:housenumber":"2",
    "addr:postcode":"8900",
    "addr:street":"Thorsgade",
    "iso:country":"DK",
    "sg:address":"Thorsgade 2",
    "sg:city":"Randers",
    "sg:orig_category":"Reklamebureauer",
    "sg:phone":"+45 87 10 07 00",
    "sg:postcode":"8900",
    "sg:province":"Danmark",
    "sg:website":"www.genialtnavn.dk",
    "wof:name":"Munch & Munch ApS",
    "wof:placetype":"venue"
},
  "geometry": {"coordinates":[10.0399122238,56.4614830017],"type":"Point"}
}