{
  "type": "Feature",
  "properties": {
    "addr:full":"Brandstationen, Vestergade 131 Skanderborg Danmark 8660",
    "addr:housenumber":"131",
    "addr:postcode":"8660",
    "addr:street":"Vestergade",
    "iso:country":"DK",
    "sg:address":"Brandstationen, Vestergade 131",
    "sg:city":"Skanderborg",
    "sg:orig_category":"Redningsberedskab",
    "sg:phone":"+45 86 52 21 88",
    "sg:postcode":"8660",
    "sg:province":"Danmark",
    "wof:name":"Brand & Redning, Skanderborg",
    "wof:placetype":"venue"
},
  "geometry": {"coordinates":[9.929974556,56.0380249023],"type":"Point"}
}