{
  "type": "Feature",
  "properties": {
    "addr:full":"Ll. Karlsmindevej 45 Hundested Danmark 3390",
    "addr:housenumber":"45",
    "addr:postcode":"3390",
    "addr:street":"Ll. Karlsmindevej",
    "iso:country":"DK",
    "sg:address":"Ll. Karlsmindevej 45",
    "sg:city":"Hundested",
    "sg:orig_category":"Fugning",
    "sg:phone":"+45 47 93 88 58",
    "sg:postcode":"3390",
    "sg:province":"Danmark",
    "wof:name":"R. M. Fugeservice",
    "wof:placetype":"venue"
},
  "geometry": {"coordinates":[11.861281395,55.9681816101],"type":"Point"}
}