{
  "type": "Feature",
  "properties": {
    "addr:full":"M\u00f8llem\u00e6rsk 24 Aabenraa Danmark 6200",
    "addr:housenumber":"24",
    "addr:postcode":"6200",
    "addr:street":"Mollemaersk",
    "iso:country":"DK",
    "sg:address":"M\u00f8llem\u00e6rsk 24",
    "sg:city":"Aabenraa",
    "sg:orig_category":"Skomagere",
    "sg:phone":"+45 74 42 28 88",
    "sg:postcode":"6200",
    "sg:province":"Danmark",
    "wof:name":"Sahva H\u00e5ndskomageren",
    "wof:placetype":"venue"
},
  "geometry": {"coordinates":[9.4213867188,55.0449562073],"type":"Point"}
}