{
  "type": "Feature",
  "properties": {
    "addr:full":"Fmd.: Tim Larsen Ambus, Bakkelyg\u00e5rdsvej 21 Melby Danmark 3370",
    "addr:housenumber":"21",
    "addr:postcode":"3370",
    "addr:street":"Bakkelygaardsvej",
    "iso:country":"DK",
    "sg:address":"Fmd.: Tim Larsen Ambus, Bakkelyg\u00e5rdsvej 21",
    "sg:city":"Melby",
    "sg:orig_category":"Hobbybetonede foreninger",
    "sg:phone":"+45 47 98 85 11",
    "sg:postcode":"3370",
    "sg:province":"Danmark",
    "wof:name":"Sch\u00e6ferhundeklubben for Danmark, Kreds 39, Arres\u00f8",
    "wof:placetype":"venue"
},
  "geometry": {"coordinates":[11.9925775528,55.9966087341],"type":"Point"}
}