{
  "type": "Feature",
  "properties": {
    "addr:full":"Vestre Ringgade 33 B \u00c5rhus C Danmark 8000",
    "addr:housenumber":"33 b",
    "addr:postcode":"8000",
    "addr:street":"Vestre Ringgade",
    "iso:country":"DK",
    "sg:address":"Vestre Ringgade 33 B",
    "sg:city":"\u00c5rhus C",
    "sg:orig_category":"Blikkenslagere",
    "sg:phone":"+45 87 44 88 00",
    "sg:postcode":"8000",
    "sg:province":"Danmark",
    "sg:website":"www.nmvvs.dk",
    "wof:name":"M\u00f8lgaard A/S, Niels",
    "wof:placetype":"venue"
},
  "geometry": {"coordinates":[6.87629,62.460281],"type":"Point"}
}