{
  "type": "Feature",
  "properties": {
    "addr:full":"Kontkatpers.: Knud Roager, Egev\u00e6nget 5, Jejsing T\u00f8nder Danmark 6270",
    "addr:housenumber":"5",
    "addr:postcode":"6270",
    "addr:street":"Knud Roager Egevaenget",
    "iso:country":"DK",
    "sg:address":"Kontkatpers.: Knud Roager, Egev\u00e6nget 5, Jejsing",
    "sg:city":"T\u00f8nder",
    "sg:orig_category":"Kirkelige foreninger",
    "sg:phone":"+45 74 73 46 41",
    "sg:postcode":"6270",
    "sg:province":"Danmark",
    "sg:website":"www.dlm.dk",
    "wof:name":"T\u00f8nder Kreds Luthersk Mission",
    "wof:placetype":"venue"
},
  "geometry": {"coordinates":[8.9661502838,54.9350318909],"type":"Point"}
}