{
  "type": "Feature",
  "properties": {
    "iso:country":"DK",
    "sg:address":"Hogvej 5, Smouen",
    "sg:city":"R\u00f8nde",
    "sg:orig_category":"Brudekjoler",
    "sg:phone":"+45 86 37 18 33",
    "sg:postcode":"8410",
    "sg:province":"Danmark",
    "sg:website":"www.brudesalonen.dk",
    "wof:name":"Brudesalonen",
    "wof:placetype":"venue"
},
  "geometry": {"coordinates":[10.4288892746,56.295917511],"type":"Point"}
}