{
  "type": "Feature",
  "properties": {
    "addr:full":"Skolegade 8 Frederikshavn Danmark 9900",
    "addr:housenumber":"8",
    "addr:postcode":"9900",
    "addr:street":"Skolegade",
    "iso:country":"DK",
    "sg:address":"Skolegade 8",
    "sg:city":"Frederikshavn",
    "sg:orig_category":"Musikskoler, Kommunale",
    "sg:phone":"+45 96 22 56 21",
    "sg:postcode":"9900",
    "sg:province":"Danmark",
    "wof:name":"Frederikshavn Kommunale Musikskole",
    "wof:placetype":"venue"
},
  "geometry": {"coordinates":[10.5357265472,57.4421463013],"type":"Point"}
}