{
  "type": "Feature",
  "properties": {
    "addr:full":"Gl. Skivevej 85 Viborg Danmark 8800",
    "addr:housenumber":"85",
    "addr:postcode":"8800",
    "addr:street":"Gl. Skivevej",
    "iso:country":"DK",
    "sg:address":"Gl. Skivevej 85",
    "sg:city":"Viborg",
    "sg:orig_category":"Blomsterhandlere",
    "sg:phone":"+45 86 62 04 99",
    "sg:postcode":"8800",
    "sg:province":"Danmark",
    "wof:name":"Palmehaven",
    "wof:placetype":"venue"
},
  "geometry": {"coordinates":[9.4008378983,56.4655952454],"type":"Point"}
}