{
  "type": "Feature",
  "properties": {
    "iso:country":"DK",
    "sg:address":"v/ Jytte Frithiof, Christians\u00f8 0",
    "sg:city":"Svaneke",
    "sg:orig_category":"Spejderkorps",
    "sg:phone":"+45 56 46 20 54",
    "sg:postcode":"3740",
    "sg:province":"Danmark",
    "wof:name":"Det Danske Spejderkorps, Christians\u00f8",
    "wof:placetype":"venue"
},
  "geometry": {"coordinates":[15.140504837,55.1364555359],"type":"Point"}
}