{
  "type": "Feature",
  "properties": {
    "addr:full":"D\u00e6mningen 15 - 17 Vejle Danmark 7100",
    "addr:housenumber":"15 17",
    "addr:postcode":"7100",
    "addr:street":"Daemningen",
    "iso:country":"DK",
    "sg:address":"D\u00e6mningen 15 - 17",
    "sg:city":"Vejle",
    "sg:orig_category":"Faglige organisationer og foreninger",
    "sg:phone":"+45 75 72 22 55",
    "sg:postcode":"7100",
    "sg:province":"Danmark",
    "sg:website":"www.krifa.dk",
    "wof:name":"Kristelige Fagbev\u00e6gelse, Den",
    "wof:placetype":"venue"
},
  "geometry": {"coordinates":[9.5355138779,55.7080497742],"type":"Point"}
}