{
  "type": "Feature",
  "properties": {
    "addr:full":"Birkevangen 2, Birkelse Aabybro Danmark 9440",
    "addr:housenumber":"2",
    "addr:postcode":"9440",
    "addr:street":"Birkevangen",
    "iso:country":"DK",
    "sg:address":"Birkevangen 2, Birkelse",
    "sg:city":"Aabybro",
    "sg:orig_category":"Filialbiblioteker",
    "sg:phone":"+45 98 24 33 41",
    "sg:postcode":"9440",
    "sg:province":"Danmark",
    "wof:name":"Vedsted Bibliotek",
    "wof:placetype":"venue"
},
  "geometry": {"coordinates":[9.7341356277,57.1588287354],"type":"Point"}
}