{
  "type": "Feature",
  "properties": {
    "addr:full":"S\u00f8ndre Thorstedvej 1 Thisted Danmark 7700",
    "addr:housenumber":"1",
    "addr:postcode":"7700",
    "addr:street":"Sondre Thorstedvej",
    "iso:country":"DK",
    "sg:address":"S\u00f8ndre Thorstedvej 1",
    "sg:city":"Thisted",
    "sg:orig_category":"Maskinfabrikker",
    "sg:phone":"+45 97 97 12 00",
    "sg:postcode":"7700",
    "sg:province":"Danmark",
    "sg:website":"www.thy-staalbyg.dk",
    "wof:name":"Thy St\u00e5l-Byg A/S",
    "wof:placetype":"venue"
},
  "geometry": {"coordinates":[8.6057128906,56.9725456238],"type":"Point"}
}