{
  "type": "Feature",
  "properties": {
    "addr:full":"H\u00e5ndv\u00e6rkerv\u00e6nget 11, Ramme Lemvig Danmark 7620",
    "addr:housenumber":"11",
    "addr:postcode":"7620",
    "addr:street":"Haandvaerkervaenget",
    "iso:country":"DK",
    "sg:address":"H\u00e5ndv\u00e6rkerv\u00e6nget 11, Ramme",
    "sg:city":"Lemvig",
    "sg:orig_category":"Fabrikker",
    "sg:phone":"+45 97 88 98 00",
    "sg:postcode":"7620",
    "sg:province":"Danmark",
    "wof:name":"Kota A/S",
    "wof:placetype":"venue"
},
  "geometry": {"coordinates":[8.3073654175,56.5505104065],"type":"Point"}
}