{
  "type": "Feature",
  "properties": {
    "addr:full":"Valdemarsgade 13 Svendborg Danmark 5700",
    "addr:housenumber":"13",
    "addr:postcode":"5700",
    "addr:street":"Valdemarsgade",
    "iso:country":"DK",
    "sg:address":"Valdemarsgade 13",
    "sg:city":"Svendborg",
    "sg:orig_category":"Teatre",
    "sg:phone":"+45 62 21 14 17",
    "sg:postcode":"5700",
    "sg:province":"Danmark",
    "wof:name":"Svendborg FritidsTeater",
    "wof:placetype":"venue"
},
  "geometry": {"coordinates":[10.611328125,55.0553627014],"type":"Point"}
}