{
  "type": "Feature",
  "properties": {
    "addr:full":"Blegdamsvej 28 F K\u00f8benhavn N Danmark 2200",
    "addr:housenumber":"28 f",
    "addr:postcode":"2200",
    "addr:street":"Blegdamsvej;Kobenhavn N Danmark",
    "iso:country":"DK",
    "sg:address":"Blegdamsvej 28 F",
    "sg:city":"K\u00f8benhavn N",
    "sg:orig_category":"Fotografer",
    "sg:phone":"+45 35 36 15 50",
    "sg:postcode":"2200",
    "sg:province":"Danmark",
    "wof:name":"Hansen, Bjarne",
    "wof:placetype":"venue"
},
  "geometry": {"coordinates":[-73.9864273071,43.6976699829],"type":"Point"}
}