{
  "type": "Feature",
  "properties": {
    "addr:full":"Hjortkj\u00e6rsvej 28 Aars Danmark 9600",
    "addr:housenumber":"28",
    "addr:postcode":"9600",
    "addr:street":"Hjortkjaersvej",
    "iso:country":"DK",
    "sg:address":"Hjortkj\u00e6rsvej 28",
    "sg:city":"Aars",
    "sg:orig_category":"Maskinfabrikker",
    "sg:phone":"+45 98 62 15 32",
    "sg:postcode":"9600",
    "sg:province":"Danmark",
    "wof:name":"Vestdansk Maskinfabrik A/S",
    "wof:placetype":"venue"
},
  "geometry": {"coordinates":[9.495390892,56.8061065674],"type":"Point"}
}