{
  "type": "Feature",
  "properties": {
    "addr:full":"v/ Vagn Karstad, B\u00f8geparken 264,st.tv. Odense N\u00d8 Danmark 5240",
    "addr:housenumber":"264",
    "addr:postcode":"5240",
    "addr:street":"Bogeparken;St.Tv.",
    "iso:country":"DK",
    "sg:address":"v/ Vagn Karstad, B\u00f8geparken 264,st.tv.",
    "sg:city":"Odense N\u00d8",
    "sg:orig_category":"Hobbybetonede foreninger",
    "sg:phone":"+45 66 10 44 45",
    "sg:postcode":"5240",
    "sg:province":"Danmark",
    "wof:name":"Fritidsforeningen B\u00f8gen",
    "wof:placetype":"venue"
},
  "geometry": {"coordinates":[10.444185257,55.4261131287],"type":"Point"}
}