{
  "type": "Feature",
  "properties": {
    "addr:full":"Fmd.: Erhardt Tonnesen, Maribovej 12 Holeby Danmark 4960",
    "addr:housenumber":"12",
    "addr:postcode":"4960",
    "addr:street":"Maribovej",
    "iso:country":"DK",
    "sg:address":"Fmd.: Erhardt Tonnesen, Maribovej 12",
    "sg:city":"Holeby",
    "sg:orig_category":"Faglige organisationer og foreninger",
    "sg:phone":"+45 54 60 68 02",
    "sg:postcode":"4960",
    "sg:province":"Danmark",
    "sg:website":"www.lederne.dk",
    "wof:name":"Ledernes Hovedorganisation, Maribo",
    "wof:placetype":"venue"
},
  "geometry": {"coordinates":[11.4715652466,54.7092895508],"type":"Point"}
}