{
  "type": "Feature",
  "properties": {
    "addr:full":"Sortemosevej 1 C Herlev Danmark 2730",
    "addr:housenumber":"1 c",
    "addr:postcode":"2730",
    "addr:street":"Sortemosevej",
    "iso:country":"DK",
    "sg:address":"Sortemosevej 1 C",
    "sg:city":"Herlev",
    "sg:orig_category":"Integrerede institutioner",
    "sg:phone":"+45 44 52 59 49",
    "sg:postcode":"2730",
    "sg:province":"Danmark",
    "wof:name":"Troldebo B\u00f8rneinstitution",
    "wof:placetype":"venue"
},
  "geometry": {"coordinates":[12.3976888657,55.7502593994],"type":"Point"}
}