{
  "type": "Feature",
  "properties": {
    "iso:country":"DK",
    "sg:address":"Vesterbrogade 161",
    "sg:city":"Frederiksberg",
    "sg:orig_category":"Bodegaer",
    "sg:phone":"+45 33 31 51 39",
    "sg:postcode":"1800",
    "sg:province":"Danmark",
    "wof:name":"Robert, Hos",
    "wof:placetype":"venue"
},
  "geometry": {"coordinates":[12.5370473862,55.6703300476],"type":"Point"}
}