{
  "type": "Feature",
  "properties": {
    "addr:full":"Skriverhusene 10 Albertslund Danmark 2620",
    "addr:housenumber":"10",
    "addr:postcode":"2620",
    "addr:street":"Skriverhusene",
    "iso:country":"DK",
    "sg:address":"Skriverhusene 10",
    "sg:city":"Albertslund",
    "sg:orig_category":"Sikkerhedsudstyr",
    "sg:phone":"+45 43 45 59 77",
    "sg:postcode":"2620",
    "sg:province":"Danmark",
    "wof:name":"Tope, Konsulentfirmaet",
    "wof:placetype":"venue"
},
  "geometry": {"coordinates":[12.3612117767,55.6714096069],"type":"Point"}
}