{
  "type": "Feature",
  "properties": {
    "iso:country":"DK",
    "sg:address":"Gilleleje Hovedgade 1",
    "sg:city":"Gilleleje",
    "sg:orig_category":"Bagere",
    "sg:phone":"+45 48 30 02 76",
    "sg:postcode":"3250",
    "sg:province":"Danmark",
    "wof:name":"\u00c5bageriet ApS",
    "wof:placetype":"venue"
},
  "geometry": {"coordinates":[12.3079118729,56.1246986389],"type":"Point"}
}