{
  "type": "Feature",
  "properties": {
    "addr:full":"Hovedgaden 2 Kirke Hvals\u00f8 Danmark 4330",
    "addr:housenumber":"2",
    "addr:postcode":"4330",
    "addr:street":"Hovedgaden",
    "iso:country":"DK",
    "sg:address":"Hovedgaden 2",
    "sg:city":"Kirke Hvals\u00f8",
    "sg:classifiers":[
        {
            "category":"Communications",
            "type":"Services"
        }
    ],
    "sg:phone":"+45 46 40 99 29",
    "sg:postcode":"4330",
    "sg:province":"Danmark",
    "sg:tags":[
        "og",
        "tv",
        "radio"
    ],
    "sg:website":"www.hvradio.dk",
    "wof:name":"Hvals\u00f8 Radio",
    "wof:placetype":"venue"
},
  "geometry": {"coordinates":[9.2555503845,54.9375686646],"type":"Point"}
}