{
  "type": "Feature",
  "properties": {
    "addr:full":"N\u00f8rremarksvej 16, \u00d8land Brovst Danmark 9460",
    "addr:housenumber":"16",
    "addr:postcode":"9460",
    "addr:street":"Norremarksvej;Oland",
    "iso:country":"DK",
    "sg:address":"N\u00f8rremarksvej 16, \u00d8land",
    "sg:city":"Brovst",
    "sg:orig_category":"Alternativ behandling",
    "sg:phone":"+45 98 23 63 53",
    "sg:postcode":"9460",
    "sg:province":"Danmark",
    "wof:name":"Graversen, Nanna Tops\u00f8e",
    "wof:placetype":"venue"
},
  "geometry": {"coordinates":[9.5220241547,57.097366333],"type":"Point"}
}