{
  "type": "Feature",
  "properties": {
    "addr:full":"Industrivej 2 - 4 Spentrup Danmark 8981",
    "addr:housenumber":"2 4",
    "addr:postcode":"8981",
    "addr:street":"Industrivej",
    "iso:country":"DK",
    "sg:address":"Industrivej 2 - 4",
    "sg:city":"Spentrup",
    "sg:orig_category":"Trykluft",
    "sg:phone":"+45 87 82 83 00",
    "sg:postcode":"8981",
    "sg:province":"Danmark",
    "sg:website":"www.flak.dk",
    "wof:name":"Flak Industritrykluft",
    "wof:placetype":"venue"
},
  "geometry": {"coordinates":[10.030049324,56.5443458557],"type":"Point"}
}