{
  "type": "Feature",
  "properties": {
    "addr:full":"Banegraven 26 Slangerup Danmark 3550",
    "addr:housenumber":"26",
    "addr:postcode":"3550",
    "addr:street":"Banegraven",
    "iso:country":"DK",
    "sg:address":"Banegraven 26",
    "sg:city":"Slangerup",
    "sg:orig_category":"Trykkerier",
    "sg:phone":"+45 47 38 00 94",
    "sg:postcode":"3550",
    "sg:province":"Danmark",
    "wof:name":"Nordsj\u00e6llands Trykcenter ApS",
    "wof:placetype":"venue"
},
  "geometry": {"coordinates":[12.1847696304,55.8456382751],"type":"Point"}
}