{
  "type": "Feature",
  "properties": {
    "addr:full":"Katedralvej 22 Stege Danmark 4780",
    "addr:housenumber":"22",
    "addr:postcode":"4780",
    "addr:street":"Katedralvej",
    "iso:country":"DK",
    "sg:address":"Katedralvej 22",
    "sg:city":"Stege",
    "sg:orig_category":"Maskinfabrikker",
    "sg:phone":"+45 55 81 18 88",
    "sg:postcode":"4780",
    "sg:province":"Danmark",
    "wof:name":"M\u00f8n Maskinbyg ApS",
    "wof:placetype":"venue"
},
  "geometry": {"coordinates":[12.2898273468,54.9920654297],"type":"Point"}
}