{
  "type": "Feature",
  "properties": {
    "addr:full":"Pr\u00e6stetoften 6, \u00d8. Egesborg Mern Danmark 4735",
    "addr:housenumber":"6 o.",
    "addr:postcode":"4735",
    "addr:street":"Praestetoften",
    "iso:country":"DK",
    "sg:address":"Pr\u00e6stetoften 6, \u00d8. Egesborg",
    "sg:city":"Mern",
    "sg:orig_category":"Private skoler",
    "sg:phone":"+45 55 99 77 20",
    "sg:postcode":"4735",
    "sg:province":"Danmark",
    "wof:name":"Friskolen \u00d8ster Egesborg",
    "wof:placetype":"venue"
},
  "geometry": {"coordinates":[12.0578746796,55.049079895],"type":"Point"}
}