{
  "type": "Feature",
  "properties": {
    "addr:full":"Fiskebrogade 20 Esbjerg Danmark 6700",
    "addr:housenumber":"20",
    "addr:postcode":"6700",
    "addr:street":"Fiskebrogade",
    "iso:country":"DK",
    "sg:address":"Fiskebrogade 20",
    "sg:city":"Esbjerg",
    "sg:orig_category":"Fiskeriudstyr",
    "sg:phone":"+45 75 12 10 36",
    "sg:postcode":"6700",
    "sg:province":"Danmark",
    "wof:name":"Andersen & S\u00f8nner",
    "wof:placetype":"venue"
},
  "geometry": {"coordinates":[8.4292201996,55.4741897583],"type":"Point"}
}