{
  "type": "Feature",
  "properties": {
    "addr:full":"Lufthavnsvej 10 Hanstholm Danmark 7730",
    "addr:housenumber":"10",
    "addr:postcode":"7730",
    "addr:street":"Lufthavnsvej",
    "iso:country":"DK",
    "sg:address":"Lufthavnsvej 10",
    "sg:city":"Hanstholm",
    "sg:orig_category":"Elektronik",
    "sg:phone":"+45 97 96 51 78",
    "sg:postcode":"7730",
    "sg:province":"Danmark",
    "wof:name":"Thomsen Electronic",
    "wof:placetype":"venue"
},
  "geometry": {"coordinates":[8.6923246384,57.0718803406],"type":"Point"}
}