{
  "type": "Feature",
  "properties": {
    "iso:country":"DK",
    "sg:address":"Hjulmagervej 34",
    "sg:city":"Aalborg",
    "sg:orig_category":"Maskinudlejning",
    "sg:phone":"+45 98 10 38 44",
    "sg:postcode":"9000",
    "sg:province":"Danmark",
    "sg:website":"www.dne-udlejning.dk",
    "wof:name":"DNE Materieludlejning A/S",
    "wof:placetype":"venue"
},
  "geometry": {"coordinates":[9.9237670898,57.0398330688],"type":"Point"}
}