{
  "type": "Feature",
  "properties": {
    "addr:full":"\u00d8stergade 2 Frederikssund Danmark 3600",
    "addr:housenumber":"2",
    "addr:postcode":"3600",
    "addr:street":"Ostergade",
    "iso:country":"DK",
    "sg:address":"\u00d8stergade 2",
    "sg:city":"Frederikssund",
    "sg:orig_category":"Chokolade",
    "sg:phone":"+45 47 31 07 70",
    "sg:postcode":"3600",
    "sg:province":"Danmark",
    "wof:name":"Mona-Lisa Chokolade",
    "wof:placetype":"venue"
},
  "geometry": {"coordinates":[12.0586061478,55.839302063],"type":"Point"}
}