{
  "type": "Feature",
  "properties": {
    "addr:full":"Olfert Fischers Gade 4, 3 tv K\u00f8benhavn Danmark 1311",
    "addr:housenumber":"4 3 tv;1311",
    "addr:street":"Olfert Fischers Gade",
    "iso:country":"DK",
    "sg:address":"Olfert Fischers Gade 4, 3 tv",
    "sg:city":"K\u00f8benhavn",
    "sg:orig_category":"Engros handel",
    "sg:phone":"+45 33 91 11 91",
    "sg:postcode":"1311",
    "sg:province":"Danmark",
    "wof:name":"S\u00f8ndergaard, Hans",
    "wof:placetype":"venue"
},
  "geometry": {"coordinates":[12.5869998932,55.6869010925],"type":"Point"}
}