{
  "type": "Feature",
  "properties": {
    "addr:full":"\u00d8stre Stationsvej 27 Odense C Danmark 5000",
    "addr:housenumber":"27",
    "addr:postcode":"5000",
    "addr:street":"Ostre Stationsvej",
    "iso:country":"DK",
    "sg:address":"\u00d8stre Stationsvej 27",
    "sg:city":"Odense C",
    "sg:orig_category":"Videobutikker og -klubber",
    "sg:phone":"+45 66 12 07 38",
    "sg:postcode":"5000",
    "sg:province":"Danmark",
    "sg:website":"www.blockbuster.dk",
    "wof:name":"Blockbuster",
    "wof:placetype":"venue"
},
  "geometry": {"coordinates":[10.383769989,55.4007835388],"type":"Point"}
}