{
  "type": "Feature",
  "properties": {
    "addr:full":"Ellemosevej 15, Ugerl\u00f8se Kalundborg Danmark 4400",
    "addr:housenumber":"15",
    "addr:postcode":"4400",
    "addr:street":"Ellemosevej;Ugerlose",
    "iso:country":"DK",
    "sg:address":"Ellemosevej 15, Ugerl\u00f8se",
    "sg:city":"Kalundborg",
    "sg:orig_category":"Isolering",
    "sg:phone":"+45 59 50 40 83",
    "sg:postcode":"4400",
    "sg:province":"Danmark",
    "wof:name":"Pedersen, Kai",
    "wof:placetype":"venue"
},
  "geometry": {"coordinates":[11.0934085846,55.6797485352],"type":"Point"}
}