{
  "type": "Feature",
  "properties": {
    "iso:country":"DK",
    "sg:address":"Biblioteket, Dannebrogsgade 43, 1.",
    "sg:city":"Aalborg",
    "sg:orig_category":"Legestuer",
    "sg:phone":"+45 99 31 52 90",
    "sg:postcode":"9000",
    "sg:province":"Danmark",
    "wof:name":"Legestuen Vestbyens K\u00e6led\u00e6gger",
    "wof:placetype":"venue"
},
  "geometry": {"coordinates":[9.9044532776,57.0530700684],"type":"Point"}
}