{
  "type": "Feature",
  "properties": {
    "addr:full":"v/ Mehmet Yildirim, Nordengen 49 Kokkedal Danmark 2980",
    "addr:housenumber":"49",
    "addr:postcode":"2980",
    "addr:street":"Nordengen",
    "iso:country":"DK",
    "sg:address":"v/ Mehmet Yildirim, Nordengen 49",
    "sg:city":"Kokkedal",
    "sg:orig_category":"Kulturelle foreninger",
    "sg:phone":"+45 49 14 21 64",
    "sg:postcode":"2980",
    "sg:province":"Danmark",
    "wof:name":"Karlebo Komm. Venskabsforening for Danskere og Indvandrere",
    "wof:placetype":"venue"
},
  "geometry": {"coordinates":[12.4769096375,55.9091339111],"type":"Point"}
}