{
  "type": "Feature",
  "properties": {
    "addr:full":"Bjerreg\u00e5rdsvej 8 Valby Danmark 2500",
    "addr:housenumber":"8",
    "addr:postcode":"2500",
    "addr:street":"Bjerregaardsvej",
    "iso:country":"DK",
    "sg:address":"Bjerreg\u00e5rdsvej 8",
    "sg:city":"Valby",
    "sg:orig_category":"Kursusudbydere",
    "sg:phone":"+45 36 46 46 38",
    "sg:postcode":"2500",
    "sg:province":"Danmark",
    "wof:name":"Samconsult",
    "wof:placetype":"venue"
},
  "geometry": {"coordinates":[12.5268716812,55.6660385132],"type":"Point"}
}