{
  "type": "Feature",
  "properties": {
    "addr:full":"\u00d8stre Alle 97 Nyk\u00f8bing Danmark 4800",
    "addr:housenumber":"97",
    "addr:postcode":"4800",
    "addr:street":"Ostre Alle",
    "iso:country":"DK",
    "sg:address":"\u00d8stre Alle 97",
    "sg:city":"Nyk\u00f8bing",
    "sg:orig_category":"Dyreparker",
    "sg:phone":"+45 54 85 20 26",
    "sg:postcode":"4800",
    "sg:province":"Danmark",
    "wof:name":"Folkeparken (Zoo)",
    "wof:placetype":"venue"
},
  "geometry": {"coordinates":[-114.0768203735,46.4432411194],"type":"Point"}
}