{
  "type": "Feature",
  "properties": {
    "addr:full":"Vestergade 126 Grindsted Danmark 7200",
    "addr:housenumber":"126",
    "addr:postcode":"7200",
    "addr:street":"Vestergade",
    "iso:country":"DK",
    "sg:address":"Vestergade 126",
    "sg:city":"Grindsted",
    "sg:orig_category":"Rejsebureauer",
    "sg:phone":"+45 75 32 03 48",
    "sg:postcode":"7200",
    "sg:province":"Danmark",
    "wof:name":"Alfa Rejseformidling",
    "wof:placetype":"venue"
},
  "geometry": {"coordinates":[8.9068078995,55.7613639832],"type":"Point"}
}