{
  "type": "Feature",
  "properties": {
    "iso:country":"DK",
    "sg:address":"Bogensevej 48, N\u00e6sby",
    "sg:city":"Odense N",
    "sg:orig_category":"Bagere",
    "sg:phone":"+45 66 18 15 49",
    "sg:postcode":"5270",
    "sg:province":"Danmark",
    "wof:name":"N\u00e6sby Bageren",
    "wof:placetype":"venue"
},
  "geometry": {"coordinates":[10.33068,55.471142],"type":"Point"}
}