{
  "type": "Feature",
  "properties": {
    "addr:full":"Mariagervej 66, Skellerup Hobro Danmark 9500",
    "addr:housenumber":"66",
    "addr:postcode":"9500",
    "addr:street":"Mariagervej",
    "iso:country":"DK",
    "sg:address":"Mariagervej 66, Skellerup",
    "sg:city":"Hobro",
    "sg:orig_category":"Efterskoler",
    "sg:phone":"+45 98 55 52 55",
    "sg:postcode":"9500",
    "sg:province":"Danmark",
    "sg:website":"www.hobroefterskole.dk",
    "wof:name":"Hobro Efterskole",
    "wof:placetype":"venue"
},
  "geometry": {"coordinates":[9.7946596146,56.6382789612],"type":"Point"}
}