{
  "type": "Feature",
  "properties": {
    "addr:full":"Vestergade 22 Stubbek\u00f8bing Danmark 4850",
    "addr:housenumber":"22",
    "addr:postcode":"4850",
    "addr:street":"Vestergade",
    "iso:country":"DK",
    "sg:address":"Vestergade 22",
    "sg:city":"Stubbek\u00f8bing",
    "sg:classifiers":[
        {
            "category":"Communications",
            "type":"Services"
        }
    ],
    "sg:phone":"+45 54 44 11 81",
    "sg:postcode":"4850",
    "sg:province":"Danmark",
    "sg:tags":[
        "og",
        "tv",
        "radio"
    ],
    "sg:website":"www.radius.dk",
    "wof:name":"2Tal Stubbek\u00f8bing",
    "wof:placetype":"venue"
},
  "geometry": {"coordinates":[-114.0767440796,46.4432487488],"type":"Point"}
}