{
  "type": "Feature",
  "properties": {
    "iso:country":"DK",
    "sg:address":"Olaviusvej 2 A",
    "sg:city":"Skagen",
    "sg:orig_category":"Boligselskaber",
    "sg:phone":"+45 98 44 59 33",
    "sg:postcode":"9990",
    "sg:province":"Danmark",
    "wof:name":"Boligforeningen af 1952",
    "wof:placetype":"venue"
},
  "geometry": {"coordinates":[10.572977066,57.7231178284],"type":"Point"}
}