{
  "type": "Feature",
  "properties": {
    "addr:full":"Fabriksvej 13 Tim Danmark 6980",
    "addr:housenumber":"13",
    "addr:postcode":"6980",
    "addr:street":"Fabriksvej",
    "iso:country":"DK",
    "sg:address":"Fabriksvej 13",
    "sg:city":"Tim",
    "sg:orig_category":"Maskinfabrikker",
    "sg:phone":"+45 97 33 35 44",
    "sg:postcode":"6980",
    "sg:province":"Danmark",
    "sg:website":"www.tim2000.com",
    "wof:name":"Tim 2000 P/S",
    "wof:placetype":"venue"
},
  "geometry": {"coordinates":[8.3085346222,56.1939849854],"type":"Point"}
}