{
  "type": "Feature",
  "properties": {
    "addr:full":"Fmd.: Gurli Mose Pedersen, Poststr\u00e6det 13, Skovsgaard Brovst Danmark 9460",
    "addr:housenumber":"13",
    "addr:postcode":"9460",
    "addr:street":"Gurli Mose;Poststraedet;Skovsgaard",
    "iso:country":"DK",
    "sg:address":"Fmd.: Gurli Mose Pedersen, Poststr\u00e6det 13, Skovsgaard",
    "sg:city":"Brovst",
    "sg:orig_category":"Musik og sang",
    "sg:phone":"+45 98 23 36 20",
    "sg:postcode":"9460",
    "sg:province":"Danmark",
    "wof:name":"Hanbokoret",
    "wof:placetype":"venue"
},
  "geometry": {"coordinates":[9.5220241547,57.097366333],"type":"Point"}
}