{
  "type": "Feature",
  "properties": {
    "addr:full":"Stendamsgade 12 Nyborg Danmark 5800",
    "addr:housenumber":"12",
    "addr:postcode":"5800",
    "addr:street":"Stendamsgade",
    "iso:country":"DK",
    "sg:address":"Stendamsgade 12",
    "sg:city":"Nyborg",
    "sg:orig_category":"Politi",
    "sg:phone":"+45 65 31 14 48",
    "sg:postcode":"5800",
    "sg:province":"Danmark",
    "wof:name":"Politikontoret i Nyborg.",
    "wof:placetype":"venue"
},
  "geometry": {"coordinates":[10.7884616852,55.3140411377],"type":"Point"}
}