{
  "type": "Feature",
  "properties": {
    "iso:country":"DK",
    "sg:address":"Lundvej 20",
    "sg:city":"Viborg",
    "sg:orig_category":"Revisorer",
    "sg:phone":"+45 86 60 35 50",
    "sg:postcode":"8800",
    "sg:province":"Danmark",
    "sg:website":"www.revision-lo.dk",
    "wof:name":"Olsen A/S Registreret Revisionsaktieselskab, Revisionsfirmaet Lars",
    "wof:placetype":"venue"
},
  "geometry": {"coordinates":[9.3750400543,56.4628791809],"type":"Point"}
}