{
  "type": "Feature",
  "properties": {
    "addr:full":"Alsikevej 12 Randers Danmark 8900",
    "addr:housenumber":"12",
    "addr:postcode":"8900",
    "addr:street":"Alsikevej",
    "iso:country":"DK",
    "sg:address":"Alsikevej 12",
    "sg:city":"Randers",
    "sg:orig_category":"Internet, udbydere",
    "sg:phone":"+45 86 40 80 55",
    "sg:postcode":"8900",
    "sg:province":"Danmark",
    "sg:website":"www.wwi.dk",
    "wof:name":"WorldWeb Interactive ApS",
    "wof:placetype":"venue"
},
  "geometry": {"coordinates":[10.0218458176,56.4877929688],"type":"Point"}
}