{
  "type": "Feature",
  "properties": {
    "addr:full":"Generatorvej 15 Herlev Danmark 2730",
    "addr:housenumber":"15",
    "addr:postcode":"2730",
    "addr:street":"Generatorvej",
    "iso:country":"DK",
    "sg:address":"Generatorvej 15",
    "sg:city":"Herlev",
    "sg:orig_category":"EDB - udstyr",
    "sg:phone":"+45 44 84 51 44",
    "sg:postcode":"2730",
    "sg:province":"Danmark",
    "wof:name":"Focus Computer A/S",
    "wof:placetype":"venue"
},
  "geometry": {"coordinates":[12.4662733078,55.7300682068],"type":"Point"}
}