{
  "type": "Feature",
  "properties": {
    "addr:full":"Tampenkaj 1 Esbjerg Danmark 6700",
    "addr:housenumber":"1",
    "addr:postcode":"6700",
    "addr:street":"Tampenkaj",
    "iso:country":"DK",
    "sg:address":"Tampenkaj 1",
    "sg:city":"Esbjerg",
    "sg:orig_category":"Fiskeindustri",
    "sg:phone":"+45 76 11 56 66",
    "sg:postcode":"6700",
    "sg:province":"Danmark",
    "sg:website":"www.essi.dk",
    "wof:name":"Essi Konsumfisk A.M.B.A.",
    "wof:placetype":"venue"
},
  "geometry": {"coordinates":[8.4182100296,55.4755859375],"type":"Point"}
}