{
  "type": "Feature",
  "properties": {
    "iso:country":"DK",
    "sg:address":"Egedevej 83",
    "sg:city":"Fakse",
    "sg:classifiers":[
        {
            "category":"Taxi",
            "type":"Transportation"
        }
    ],
    "sg:phone":"+45 56 71 44 55",
    "sg:postcode":"4640",
    "sg:province":"Danmark",
    "wof:name":"Faksebilerne",
    "wof:placetype":"venue"
},
  "geometry": {"coordinates":[12.1065998077,55.2679901123],"type":"Point"}
}