{
  "type": "Feature",
  "properties": {
    "addr:full":"Lindholm Stationsvej 2, Lindholm Slangerup Danmark 3550",
    "addr:housenumber":"2",
    "addr:postcode":"3550",
    "addr:street":"Lindholm Stationsvej",
    "iso:country":"DK",
    "sg:address":"Lindholm Stationsvej 2, Lindholm",
    "sg:city":"Slangerup",
    "sg:orig_category":"Spejderkorps",
    "sg:phone":"+45 47 33 47 73",
    "sg:postcode":"3550",
    "sg:province":"Danmark",
    "wof:name":"Lindholmhytten",
    "wof:placetype":"venue"
},
  "geometry": {"coordinates":[12.1717596054,55.8460769653],"type":"Point"}
}