{
  "type": "Feature",
  "properties": {
    "addr:full":"Willemoesvej 3 Slagelse Danmark 4200",
    "addr:housenumber":"3",
    "addr:postcode":"4200",
    "addr:street":"Willemoesvej",
    "iso:country":"DK",
    "sg:address":"Willemoesvej 3",
    "sg:city":"Slagelse",
    "sg:orig_category":"Mobiltelefoner",
    "sg:phone":"+45 58 50 00 66",
    "sg:postcode":"4200",
    "sg:province":"Danmark",
    "wof:name":"PROF-COM",
    "wof:placetype":"venue"
},
  "geometry": {"coordinates":[11.3374500275,55.4006271362],"type":"Point"}
}