{
  "type": "Feature",
  "properties": {
    "addr:full":"Fmd.: Inger Rahbek Andersen, Hofmansvej 3, Roost Branderup Danmark 6535",
    "addr:housenumber":"3",
    "addr:postcode":"6535",
    "addr:street":"Hofmansvej",
    "iso:country":"DK",
    "sg:address":"Fmd.: Inger Rahbek Andersen, Hofmansvej 3, Roost",
    "sg:city":"Branderup",
    "sg:orig_category":"Kulturelle foreninger",
    "sg:phone":"+45 74 83 43 84",
    "sg:postcode":"6535",
    "sg:province":"Danmark",
    "wof:name":"Lokalhistorisk Forening for Arrild Sogn",
    "wof:placetype":"venue"
},
  "geometry": {"coordinates":[9.0691099167,55.1218643188],"type":"Point"}
}