{
  "type": "Feature",
  "properties": {
    "addr:full":"Finsensgade 51, 1. tv. \u00c5rhus N Danmark 8200",
    "addr:housenumber":"51 1 tv.",
    "addr:postcode":"8200",
    "addr:street":"Finsensgade",
    "iso:country":"DK",
    "sg:address":"Finsensgade 51, 1. tv.",
    "sg:city":"\u00c5rhus N",
    "sg:orig_category":"Psykologer, praktiserende",
    "sg:phone":"+45 86 10 34 97",
    "sg:postcode":"8200",
    "sg:province":"Danmark",
    "wof:name":"Christensen, Torben \u00d8stergaard",
    "wof:placetype":"venue"
},
  "geometry": {"coordinates":[4.9393601418,49.7092018127],"type":"Point"}
}