{
  "type": "Feature",
  "properties": {
    "addr:full":"Chr. Jacobsens Vej 2, Arentsminde Brovst Danmark 9460",
    "addr:housenumber":"2",
    "addr:postcode":"9460",
    "addr:street":"Chr. Jacobsens Vej",
    "iso:country":"DK",
    "sg:address":"Chr. Jacobsens Vej 2, Arentsminde",
    "sg:city":"Brovst",
    "sg:orig_category":"Sparekasser",
    "sg:phone":"+45 98 23 81 81",
    "sg:postcode":"9460",
    "sg:province":"Danmark",
    "wof:name":"Arentsminde Sparekasse",
    "wof:placetype":"venue"
},
  "geometry": {"coordinates":[9.5220241547,57.097366333],"type":"Point"}
}