{
  "type": "Feature",
  "properties": {
    "addr:full":"Fredensgade 40 \u00c5rhus C Danmark 8000",
    "addr:housenumber":"40",
    "addr:postcode":"8000",
    "addr:street":"Fredensgade",
    "iso:country":"DK",
    "sg:address":"Fredensgade 40",
    "sg:city":"\u00c5rhus C",
    "sg:orig_category":"Rejsebureauer",
    "sg:phone":"+45 70 15 40 15",
    "sg:postcode":"8000",
    "sg:province":"Danmark",
    "sg:website":"www.kilroytravels.dk",
    "wof:name":"KILROY travels",
    "wof:placetype":"venue"
},
  "geometry": {"coordinates":[4.717400074,49.7588005066],"type":"Point"}
}