{
  "type": "Feature",
  "properties": {
    "addr:full":"Torvet 5 N\u00f8rresundby Danmark 9400",
    "addr:housenumber":"5",
    "addr:postcode":"9400",
    "addr:street":"Torvet",
    "iso:country":"DK",
    "sg:address":"Torvet 5",
    "sg:city":"N\u00f8rresundby",
    "sg:orig_category":"Posthuse",
    "sg:phone":"+45 96 32 84 00",
    "sg:postcode":"9400",
    "sg:province":"Danmark",
    "wof:name":"Post Danmark, Posthuset i N\u00f8rresundby",
    "wof:placetype":"venue"
},
  "geometry": {"coordinates":[10.6905498505,59.8094596863],"type":"Point"}
}