{
  "type": "Feature",
  "properties": {
    "addr:full":"Rudolph Berghs Gade 1 K\u00f8benhavn \u00d8 Danmark 2100",
    "addr:housenumber":"1",
    "addr:postcode":"2100",
    "addr:street":"Rudolph Berghs Gade;O",
    "iso:country":"DK",
    "sg:address":"Rudolph Berghs Gade 1",
    "sg:city":"K\u00f8benhavn \u00d8",
    "sg:orig_category":"Pizzeriaer",
    "sg:phone":"+45 39 29 59 29",
    "sg:postcode":"2100",
    "sg:province":"Danmark",
    "wof:name":"Sicilia Pizzaria",
    "wof:placetype":"venue"
},
  "geometry": {"coordinates":[-83.6696090698,41.2972297668],"type":"Point"}
}