{
  "type": "Feature",
  "properties": {
    "addr:full":"Godth\u00e5bsvej 64 Frederiksberg Danmark 2000",
    "addr:housenumber":"64",
    "addr:postcode":"2000",
    "addr:street":"Godthaabsvej",
    "iso:country":"DK",
    "sg:address":"Godth\u00e5bsvej 64",
    "sg:city":"Frederiksberg",
    "sg:orig_category":"Model- og statistbureauer",
    "sg:phone":"+45 38 86 90 84",
    "sg:postcode":"2000",
    "sg:province":"Danmark",
    "wof:name":"3xStjerne-Booking",
    "wof:placetype":"venue"
},
  "geometry": {"coordinates":[12.5286340714,55.6877670288],"type":"Point"}
}