{
  "type": "Feature",
  "properties": {
    "addr:full":"Jernbanegade 9 Agerb\u00e6k Danmark 6753",
    "addr:housenumber":"9",
    "addr:postcode":"6753",
    "addr:street":"Jernbanegade",
    "iso:country":"DK",
    "sg:address":"Jernbanegade 9",
    "sg:city":"Agerb\u00e6k",
    "sg:orig_category":"Posthuse",
    "sg:phone":"+45 79 12 12 12",
    "sg:postcode":"6753",
    "sg:province":"Danmark",
    "wof:name":"Post Danmark, Agerb\u00e6k Posthus",
    "wof:placetype":"venue"
},
  "geometry": {"coordinates":[8.8042154312,55.600856781],"type":"Point"}
}