{
  "type": "Feature",
  "properties": {
    "addr:full":"Alleen 4 S\u00f8by Danmark 5985",
    "addr:housenumber":"4",
    "addr:postcode":"5985",
    "addr:street":"Alleen",
    "iso:country":"DK",
    "sg:address":"Alleen 4",
    "sg:city":"S\u00f8by",
    "sg:orig_category":"Rederier",
    "sg:phone":"+45 62 58 13 44",
    "sg:postcode":"5985",
    "sg:province":"Danmark",
    "wof:name":"Christensen, J\u00f8rgen",
    "wof:placetype":"venue"
},
  "geometry": {"coordinates":[-78.0637512207,43.0498466492],"type":"Point"}
}