{
  "type": "Feature",
  "properties": {
    "addr:full":"Jernbanegade 11, 1 Padborg Danmark 6330",
    "addr:housenumber":"11 1",
    "addr:postcode":"6330",
    "addr:street":"Jernbanegade",
    "iso:country":"DK",
    "sg:address":"Jernbanegade 11, 1",
    "sg:city":"Padborg",
    "sg:orig_category":"Kiropraktorer",
    "sg:phone":"+45 74 67 10 11",
    "sg:postcode":"6330",
    "sg:province":"Danmark",
    "wof:name":"Kiropraktisk Klinik",
    "wof:placetype":"venue"
},
  "geometry": {"coordinates":[9.3594274521,54.8241157532],"type":"Point"}
}