{
  "type": "Feature",
  "properties": {
    "addr:full":"Abildvej 5 E Svendborg Danmark 5700",
    "addr:housenumber":"5 e",
    "addr:postcode":"5700",
    "addr:street":"Abildvej",
    "iso:country":"DK",
    "sg:address":"Abildvej 5 E",
    "sg:city":"Svendborg",
    "sg:orig_category":"Video- og TV-produktion",
    "sg:phone":"+45 40 16 15 51",
    "sg:postcode":"5700",
    "sg:province":"Danmark",
    "wof:name":"Frame Factory I/S",
    "wof:placetype":"venue"
},
  "geometry": {"coordinates":[10.6065101624,55.0595970154],"type":"Point"}
}