{
  "type": "Feature",
  "properties": {
    "addr:full":"R\u00f8nneb\u00e6rvej 49 Holte Danmark 2840",
    "addr:housenumber":"49",
    "addr:postcode":"2840",
    "addr:street":"Ronnebaervej",
    "iso:country":"DK",
    "sg:address":"R\u00f8nneb\u00e6rvej 49",
    "sg:city":"Holte",
    "sg:orig_category":"Psykoanalyse",
    "sg:phone":"+45 45 42 35 30",
    "sg:postcode":"2840",
    "sg:province":"Danmark",
    "sg:website":"www.sensetik.dk",
    "wof:name":"Sensetik Instituttet",
    "wof:placetype":"venue"
},
  "geometry": {"coordinates":[12.4706554413,55.8122367859],"type":"Point"}
}