{
  "type": "Feature",
  "properties": {
    "addr:full":"Ristingevej 2 Humble Danmark 5932",
    "addr:housenumber":"2",
    "addr:postcode":"5932",
    "addr:street":"Ristingevej",
    "iso:country":"DK",
    "sg:address":"Ristingevej 2",
    "sg:city":"Humble",
    "sg:orig_category":"HOTELS: OG MOTELLER",
    "sg:phone":"+45 62 57 11 34",
    "sg:postcode":"5932",
    "sg:province":"Danmark",
    "sg:website":"www.humblekro.dk",
    "wof:name":"Humble Kro",
    "wof:placetype":"venue"
},
  "geometry": {"coordinates":[10.6978521347,54.8262901306],"type":"Point"}
}