{
  "type": "Feature",
  "properties": {
    "addr:full":"Daltoften 20 Grindsted Danmark 7200",
    "addr:housenumber":"20",
    "addr:postcode":"7200",
    "addr:street":"Daltoften",
    "iso:country":"DK",
    "sg:address":"Daltoften 20",
    "sg:city":"Grindsted",
    "sg:orig_category":"Fritidshjem",
    "sg:postcode":"7200",
    "sg:province":"Danmark",
    "wof:name":"\u00d8stbyen Klub",
    "wof:placetype":"venue"
},
  "geometry": {"coordinates":[8.9517717361,55.7583732605],"type":"Point"}
}