{
  "type": "Feature",
  "properties": {
    "iso:country":"DK",
    "sg:address":"Vinkelvej 8",
    "sg:city":"Gredstedbro",
    "sg:orig_category":"Naturgas install. og -service",
    "sg:phone":"+45 75 43 16 52",
    "sg:postcode":"6771",
    "sg:province":"Danmark",
    "sg:website":"www.gredstedbro-vvs.dk",
    "wof:name":"Gredstedbro VVS ApS",
    "wof:placetype":"venue"
},
  "geometry": {"coordinates":[8.7426309586,55.3998260498],"type":"Point"}
}