{
  "type": "Feature",
  "properties": {
    "addr:full":"L\u00e6rkevej 24, Allerup Holb\u00e6k Danmark 4300",
    "addr:housenumber":"24",
    "addr:postcode":"4300",
    "addr:street":"Laerkevej",
    "iso:country":"DK",
    "sg:address":"L\u00e6rkevej 24, Allerup",
    "sg:city":"Holb\u00e6k",
    "sg:orig_category":"Vinduespolering",
    "sg:phone":"+45 26 16 84 21",
    "sg:postcode":"4300",
    "sg:province":"Danmark",
    "sg:website":"www.nc-vinduespolering.dk",
    "wof:name":"N. C. Vinduespolering",
    "wof:placetype":"venue"
},
  "geometry": {"coordinates":[11.7100753784,55.717956543],"type":"Point"}
}