{
  "type": "Feature",
  "properties": {
    "addr:full":"Fmd.: Arne B. Aksgl\u00e6de, \u00c5byvej 38, Hundstrup Vester Skerninge Danmark 5762",
    "addr:housenumber":"38",
    "addr:postcode":"5762",
    "addr:street":"Arne;Aabyvej",
    "iso:country":"DK",
    "sg:address":"Fmd.: Arne B. Aksgl\u00e6de, \u00c5byvej 38, Hundstrup",
    "sg:city":"Vester Skerninge",
    "sg:orig_category":"Faglige organisationer og foreninger",
    "sg:phone":"+45 62 24 37 79",
    "sg:postcode":"5762",
    "sg:province":"Danmark",
    "wof:name":"Familielandbruget Egebjerg",
    "wof:placetype":"venue"
},
  "geometry": {"coordinates":[10.5008449554,55.070400238],"type":"Point"}
}