{
  "type": "Feature",
  "properties": {
    "addr:full":"Leder: Per Kattrup, Kielsh\u00f8j 82 Farum Danmark 3520",
    "addr:housenumber":"82",
    "addr:postcode":"3520",
    "addr:street":"Kielshoj",
    "iso:country":"DK",
    "sg:address":"Leder: Per Kattrup, Kielsh\u00f8j 82",
    "sg:city":"Farum",
    "sg:orig_category":"Oplysningsforbund",
    "sg:postcode":"3520",
    "sg:province":"Danmark",
    "wof:name":"Frit Oplysningsforbund",
    "wof:placetype":"venue"
},
  "geometry": {"coordinates":[12.3755493164,55.8150291443],"type":"Point"}
}