{
  "type": "Feature",
  "properties": {
    "addr:full":"Amagerbrogade 72 K\u00f8benhavn S Danmark 2300",
    "addr:housenumber":"72",
    "addr:postcode":"2300",
    "addr:street":"Amagerbrogade;Kobenhavn S Danmark",
    "iso:country":"DK",
    "sg:address":"Amagerbrogade 72",
    "sg:city":"K\u00f8benhavn S",
    "sg:orig_category":"Gulvbehandling",
    "sg:phone":"+45 32 96 30 96",
    "sg:postcode":"2300",
    "sg:province":"Danmark",
    "wof:name":"Ideal Gulve",
    "wof:placetype":"venue"
},
  "geometry": {"coordinates":[-82.59252166749999,38.4454154968],"type":"Point"}
}