{
  "type": "Feature",
  "properties": {
    "addr:full":"Fladbrovej 3 A Randers Danmark 8900",
    "addr:housenumber":"3 a",
    "addr:postcode":"8900",
    "addr:street":"Fladbrovej",
    "iso:country":"DK",
    "sg:address":"Fladbrovej 3 A",
    "sg:city":"Randers",
    "sg:classifiers":[
        {
            "category":"Banks & Credit Unions",
            "subcategory":"Financial Services",
            "type":"Services"
        }
    ],
    "sg:phone":"+45 86 41 50 66",
    "sg:postcode":"8900",
    "sg:province":"Danmark",
    "sg:tags":[
        "banking",
        "finance",
        "insurance"
    ],
    "wof:name":"HOLME INVEST A/S",
    "wof:placetype":"venue"
},
  "geometry": {"coordinates":[9.9908161163,56.4661865234],"type":"Point"}
}