{
  "type": "Feature",
  "properties": {
    "addr:full":"R\u00f8de Sig 10, Moseby Pandrup Danmark 9490",
    "addr:housenumber":"10",
    "addr:postcode":"9490",
    "addr:street":"Rode Sig;Moseby",
    "iso:country":"DK",
    "sg:address":"R\u00f8de Sig 10, Moseby",
    "sg:city":"Pandrup",
    "sg:orig_category":"Konfekture",
    "sg:phone":"+45 98 24 51 56",
    "sg:postcode":"9490",
    "sg:province":"Danmark",
    "wof:name":"Candyman Slik En Gros",
    "wof:placetype":"venue"
},
  "geometry": {"coordinates":[9.6769151688,57.223815918],"type":"Point"}
}