{
  "type": "Feature",
  "properties": {
    "addr:full":"Hovmosevej 16, Gadevang Hiller\u00f8d Danmark 3400",
    "addr:housenumber":"16",
    "addr:postcode":"3400",
    "addr:street":"Hovmosevej",
    "iso:country":"DK",
    "sg:address":"Hovmosevej 16, Gadevang",
    "sg:city":"Hiller\u00f8d",
    "sg:orig_category":"Psykologer, praktiserende",
    "sg:phone":"+45 48 24 21 04",
    "sg:postcode":"3400",
    "sg:province":"Danmark",
    "wof:name":"Boysen, Karl",
    "wof:placetype":"venue"
},
  "geometry": {"coordinates":[12.3056097031,55.9288215637],"type":"Point"}
}