{
  "type": "Feature",
  "properties": {
    "iso:country":"DK",
    "sg:address":"Ejstrupvej 18 B",
    "sg:city":"Skals",
    "sg:orig_category":"Distriktsbiblioteker",
    "sg:phone":"+45 86 69 49 45",
    "sg:postcode":"8832",
    "sg:province":"Danmark",
    "wof:name":"Skals Bibliotek",
    "wof:placetype":"venue"
},
  "geometry": {"coordinates":[9.4074344635,56.5581703186],"type":"Point"}
}