{
  "type": "Feature",
  "properties": {
    "addr:full":"Bispensgade 32 Aalborg Danmark 9000",
    "addr:housenumber":"32",
    "addr:postcode":"9000",
    "addr:street":"Bispensgade",
    "iso:country":"DK",
    "sg:address":"Bispensgade 32",
    "sg:city":"Aalborg",
    "sg:orig_category":"Optikere",
    "sg:phone":"+45 98 12 82 16",
    "sg:postcode":"9000",
    "sg:province":"Danmark",
    "wof:name":"V\u00e6rum Optik",
    "wof:placetype":"venue"
},
  "geometry": {"coordinates":[9.9168205261,57.0496139526],"type":"Point"}
}