{
  "type": "Feature",
  "properties": {
    "addr:full":"Bjergbygade 114 Slagelse Danmark 4200",
    "addr:housenumber":"114",
    "addr:postcode":"4200",
    "addr:street":"Bjergbygade",
    "iso:country":"DK",
    "sg:address":"Bjergbygade 114",
    "sg:city":"Slagelse",
    "sg:orig_category":"Autoreparation og -service",
    "sg:phone":"+45 58 52 12 82",
    "sg:postcode":"4200",
    "sg:province":"Danmark",
    "wof:name":"Denis Autov\u00e6rksted",
    "wof:placetype":"venue"
},
  "geometry": {"coordinates":[11.3433036804,55.3910636902],"type":"Point"}
}