{
  "type": "Feature",
  "properties": {
    "addr:full":"Bredgade 59 N\u00f8rre Nebel Danmark 6830",
    "addr:housenumber":"59",
    "addr:postcode":"6830",
    "addr:street":"Bredgade",
    "iso:country":"DK",
    "sg:address":"Bredgade 59",
    "sg:city":"N\u00f8rre Nebel",
    "sg:orig_category":"Boghandlere",
    "sg:phone":"+45 75 28 80 19",
    "sg:postcode":"6830",
    "sg:province":"Danmark",
    "wof:name":"N\u00f8rre Nebel Boghandel",
    "wof:placetype":"venue"
},
  "geometry": {"coordinates":[8.2920293808,55.7789306641],"type":"Point"}
}