{
  "type": "Feature",
  "properties": {
    "addr:full":"Bavneh\u00f8jvej 19 Silkeborg Danmark 8600",
    "addr:housenumber":"19",
    "addr:postcode":"8600",
    "addr:street":"Bavnehojvej",
    "iso:country":"DK",
    "sg:address":"Bavneh\u00f8jvej 19",
    "sg:city":"Silkeborg",
    "sg:orig_category":"Rutebiler",
    "sg:postcode":"8600",
    "sg:province":"Danmark",
    "wof:name":"Arriva",
    "wof:placetype":"venue"
},
  "geometry": {"coordinates":[9.5805826187,56.1855888367],"type":"Point"}
}