{
  "type": "Feature",
  "properties": {
    "addr:full":"Torsvej 141, N\u00f8rlem Lemvig Danmark 7620",
    "addr:housenumber":"141",
    "addr:postcode":"7620",
    "addr:street":"Torsvej",
    "iso:country":"DK",
    "sg:address":"Torsvej 141, N\u00f8rlem",
    "sg:city":"Lemvig",
    "sg:orig_category":"Helseprodukter",
    "sg:phone":"+45 97 82 01 73",
    "sg:postcode":"7620",
    "sg:province":"Danmark",
    "wof:name":"Skovgaard/Dana Form",
    "wof:placetype":"venue"
},
  "geometry": {"coordinates":[8.3073654175,56.5505104065],"type":"Point"}
}