{
  "type": "Feature",
  "properties": {
    "iso:country":"DK",
    "sg:address":"Hundige Strandvej 111",
    "sg:city":"Greve",
    "sg:orig_category":"Gaveartikler",
    "sg:phone":"+45 43 90 03 11",
    "sg:postcode":"2670",
    "sg:province":"Danmark",
    "wof:name":"Brigitte Blomster & Design",
    "wof:placetype":"venue"
},
  "geometry": {"coordinates":[12.3437595367,55.5945091248],"type":"Point"}
}