{
  "type": "Feature",
  "properties": {
    "addr:full":"Pr\u00e6stegaardsvej 1 A Christiansfeld Danmark 6070",
    "addr:housenumber":"1 a",
    "addr:postcode":"6070",
    "addr:street":"Praestegaardsvej",
    "iso:country":"DK",
    "sg:address":"Pr\u00e6stegaardsvej 1 A",
    "sg:city":"Christiansfeld",
    "sg:orig_category":"Pizzeriaer",
    "sg:phone":"+45 74 56 10 70",
    "sg:postcode":"6070",
    "sg:province":"Danmark",
    "wof:name":"Hyggehj\u00f8rnet",
    "wof:placetype":"venue"
},
  "geometry": {"coordinates":[9.4830732346,55.3537483215],"type":"Point"}
}