{
  "type": "Feature",
  "properties": {
    "addr:full":"B\u00e5rdes\u00f8vej 59, B\u00e5rdes\u00f8 Otterup Danmark 5450",
    "addr:housenumber":"59",
    "addr:postcode":"5450",
    "addr:street":"Baardesovej;Baardeso",
    "iso:country":"DK",
    "sg:address":"B\u00e5rdes\u00f8vej 59, B\u00e5rdes\u00f8",
    "sg:city":"Otterup",
    "sg:orig_category":"Forsamlingshuse",
    "sg:phone":"+45 64 87 14 56",
    "sg:postcode":"5450",
    "sg:province":"Danmark",
    "wof:name":"B\u00e5rdes\u00f8 Forsamlingshus",
    "wof:placetype":"venue"
},
  "geometry": {"coordinates":[10.4545049667,55.5641746521],"type":"Point"}
}