{
  "type": "Feature",
  "properties": {
    "addr:full":"Kirkevej 3 Grenaa Danmark 8500",
    "addr:housenumber":"3",
    "addr:postcode":"8500",
    "addr:street":"Kirkevej",
    "iso:country":"DK",
    "sg:address":"Kirkevej 3",
    "sg:city":"Grenaa",
    "sg:orig_category":"Kirker",
    "sg:postcode":"8500",
    "sg:province":"Danmark",
    "wof:name":"Enslev Kirke",
    "wof:placetype":"venue"
},
  "geometry": {"coordinates":[10.811164856,56.3632202148],"type":"Point"}
}