{
  "type": "Feature",
  "properties": {
    "addr:full":"Ullerslevvej 33 Nakskov Danmark 4900",
    "addr:housenumber":"33",
    "addr:postcode":"4900",
    "addr:street":"Ullerslevvej",
    "iso:country":"DK",
    "sg:address":"Ullerslevvej 33",
    "sg:city":"Nakskov",
    "sg:orig_category":"Malermestre",
    "sg:phone":"+45 54 93 96 91",
    "sg:postcode":"4900",
    "sg:province":"Danmark",
    "wof:name":"S\u00f8rensen, Bjarne",
    "wof:placetype":"venue"
},
  "geometry": {"coordinates":[11.2103834152,54.823551178],"type":"Point"}
}