{
  "type": "Feature",
  "properties": {
    "addr:full":"Gr\u00f8nager 7 Greve Danmark 2670",
    "addr:housenumber":"7",
    "addr:postcode":"2670",
    "addr:street":"Gronager",
    "iso:country":"DK",
    "sg:address":"Gr\u00f8nager 7",
    "sg:city":"Greve",
    "sg:orig_category":"Engros handel",
    "sg:phone":"+45 43 90 17 11",
    "sg:postcode":"2670",
    "sg:province":"Danmark",
    "wof:name":"Hupfer Danmark",
    "wof:placetype":"venue"
},
  "geometry": {"coordinates":[12.2844676971,55.5896644592],"type":"Point"}
}