{
  "type": "Feature",
  "properties": {
    "addr:full":"Mosegade 34 A Hedensted Danmark 8722",
    "addr:housenumber":"34 a",
    "addr:postcode":"8722",
    "addr:street":"Mosegade",
    "iso:country":"DK",
    "sg:address":"Mosegade 34 A",
    "sg:city":"Hedensted",
    "sg:orig_category":"Blomsterhandlere",
    "sg:phone":"+45 75 89 10 21",
    "sg:postcode":"8722",
    "sg:province":"Danmark",
    "wof:name":"Drivhuset",
    "wof:placetype":"venue"
},
  "geometry": {"coordinates":[9.6986188889,55.7744903564],"type":"Point"}
}