{
  "type": "Feature",
  "properties": {
    "addr:full":"Sor\u00f8vej 31 Stenlille Danmark 4295",
    "addr:housenumber":"31",
    "addr:postcode":"4295",
    "addr:street":"Sorovej",
    "iso:country":"DK",
    "sg:address":"Sor\u00f8vej 31",
    "sg:city":"Stenlille",
    "sg:orig_category":"Forsamlingshuse",
    "sg:phone":"+45 57 80 40 46",
    "sg:postcode":"4295",
    "sg:province":"Danmark",
    "wof:name":"Stenmagle og Omegns Forsamlingshus",
    "wof:placetype":"venue"
},
  "geometry": {"coordinates":[11.6185188293,55.5519371033],"type":"Point"}
}