{
  "type": "Feature",
  "properties": {
    "addr:full":"Parallelvej 15 Kongens Lyngby Danmark 2800",
    "addr:housenumber":"15",
    "addr:postcode":"2800",
    "addr:street":"Parallelvej",
    "iso:country":"DK",
    "sg:address":"Parallelvej 15",
    "sg:city":"Kongens Lyngby",
    "sg:orig_category":"INGENI\u00c3\u02dcRER",
    "sg:phone":"+45 45 97 22 11",
    "sg:postcode":"2800",
    "sg:province":"Danmark",
    "wof:name":"COWI R\u00e5dgivende Ingeni\u00f8rer AS",
    "wof:placetype":"venue"
},
  "geometry": {"coordinates":[12.5062637329,55.7661018372],"type":"Point"}
}