{
  "type": "Feature",
  "properties": {
    "iso:country":"DK",
    "sg:address":"Bagergade 28 - 30",
    "sg:city":"Svendborg",
    "sg:orig_category":"Vuggestuer",
    "sg:phone":"+45 62 21 33 62",
    "sg:postcode":"5700",
    "sg:province":"Danmark",
    "wof:name":"B\u00f8rnely Vuggestue",
    "wof:placetype":"venue"
},
  "geometry": {"coordinates":[10.6082038879,55.0617446899],"type":"Point"}
}