{
  "type": "Feature",
  "properties": {
    "iso:country":"DK",
    "sg:address":"D\u00e6rupvej 5",
    "sg:city":"Glamsbjerg",
    "sg:orig_category":"Socialpsykiatriske bosteder",
    "sg:phone":"+45 64 72 16 52",
    "sg:postcode":"5620",
    "sg:province":"Danmark",
    "wof:name":"Drivhuset Glamsbjerg",
    "wof:placetype":"venue"
},
  "geometry": {"coordinates":[10.1004276276,55.2809715271],"type":"Point"}
}