{
  "type": "Feature",
  "properties": {
    "iso:country":"DK",
    "sg:address":"Bondovej 6, Sanderum",
    "sg:city":"Odense SV",
    "sg:classifiers":[
        {
            "category":"Home & Garden",
            "subcategory":"Home Furnishings",
            "type":"Retail Goods"
        }
    ],
    "sg:phone":"+45 66 17 28 00",
    "sg:postcode":"5250",
    "sg:province":"Danmark",
    "sg:tags":[
        "gardiner"
    ],
    "wof:name":"Gardin Mont\u00f8ren Odense ApS",
    "wof:placetype":"venue"
},
  "geometry": {"coordinates":[10.3153953552,55.3362998962],"type":"Point"}
}