{
  "type": "Feature",
  "properties": {
    "addr:full":"Havrevej 8 Aulum Danmark 7490",
    "addr:housenumber":"8",
    "addr:postcode":"7490",
    "addr:street":"Havrevej",
    "iso:country":"DK",
    "sg:address":"Havrevej 8",
    "sg:city":"Aulum",
    "sg:orig_category":"Fotografer",
    "sg:phone":"+45 97 47 27 73",
    "sg:postcode":"7490",
    "sg:province":"Danmark",
    "wof:name":"Olesen, Ester",
    "wof:placetype":"venue"
},
  "geometry": {"coordinates":[8.7954826355,56.2710151672],"type":"Point"}
}