{
  "type": "Feature",
  "properties": {
    "addr:full":"Fmd.: Stig Ladefoged, Ivar Huitfeldts Gade 47 \u00c5rhus N Danmark 8200",
    "addr:housenumber":"47",
    "addr:postcode":"8200",
    "addr:street":"Fmd. Stig Ladefoged Ivar Huitfeldts Gade",
    "iso:country":"DK",
    "sg:address":"Fmd.: Stig Ladefoged, Ivar Huitfeldts Gade 47",
    "sg:city":"\u00c5rhus N",
    "sg:orig_category":"Grundejerforeninger",
    "sg:phone":"+45 86 16 60 74",
    "sg:postcode":"8200",
    "sg:province":"Danmark",
    "wof:name":"Grundejerforeningen Tingh\u00f8jg\u00e5rd",
    "wof:placetype":"venue"
},
  "geometry": {"coordinates":[99.92501068120001,34.2430114746],"type":"Point"}
}