{
  "type": "Feature",
  "properties": {
    "addr:full":"Banevolden 12 Malling Danmark 8340",
    "addr:housenumber":"12",
    "addr:postcode":"8340",
    "addr:street":"Banevolden",
    "iso:country":"DK",
    "sg:address":"Banevolden 12",
    "sg:city":"Malling",
    "sg:orig_category":"Gulvafslibning",
    "sg:phone":"+45 86 93 35 66",
    "sg:postcode":"8340",
    "sg:province":"Danmark",
    "wof:name":"A. O. Gulvafslibning",
    "wof:placetype":"venue"
},
  "geometry": {"coordinates":[10.1884355545,56.0312080383],"type":"Point"}
}