{
  "type": "Feature",
  "properties": {
    "addr:full":"S\u00f8ndergade 10, City 1 - Biledgaard Centret Horsens Danmark 8700",
    "addr:housenumber":"10",
    "addr:postcode":"8700",
    "addr:street":"Sondergade;Centret",
    "iso:country":"DK",
    "sg:address":"S\u00f8ndergade 10, City 1 - Biledgaard Centret",
    "sg:city":"Horsens",
    "sg:orig_category":"Telebutikker",
    "sg:phone":"+45 76 25 05 66",
    "sg:postcode":"8700",
    "sg:province":"Danmark",
    "wof:name":"Sonofon Partner",
    "wof:placetype":"venue"
},
  "geometry": {"coordinates":[9.8432445526,55.8621063232],"type":"Point"}
}