{
  "type": "Feature",
  "properties": {
    "iso:country":"DK",
    "sg:address":"v/ Knud Erik Verner, Vadstedvej 185, Svenstrup",
    "sg:city":"Hammel",
    "sg:orig_category":"Hobbybetonede foreninger",
    "sg:phone":"+45 86 96 15 82",
    "sg:postcode":"8450",
    "sg:province":"Danmark",
    "wof:name":"Hammel Bridgeklub",
    "wof:placetype":"venue"
},
  "geometry": {"coordinates":[9.8615541458,56.2554588318],"type":"Point"}
}