{
  "type": "Feature",
  "properties": {
    "addr:full":"Holstebrovej 23 Skive Danmark 7800",
    "addr:housenumber":"23",
    "addr:postcode":"7800",
    "addr:street":"Holstebrovej",
    "iso:country":"DK",
    "sg:address":"Holstebrovej 23",
    "sg:city":"Skive",
    "sg:orig_category":"Gallerier",
    "sg:phone":"+45 97 51 30 30",
    "sg:postcode":"7800",
    "sg:province":"Danmark",
    "wof:name":"No 23, Galleri",
    "wof:placetype":"venue"
},
  "geometry": {"coordinates":[9.0164785385,56.5681381226],"type":"Point"}
}