{
  "type": "Feature",
  "properties": {
    "addr:full":"Brogade 7 K\u00f8ge Danmark 4600",
    "addr:housenumber":"7",
    "addr:postcode":"4600",
    "addr:street":"Brogade",
    "iso:country":"DK",
    "sg:address":"Brogade 7",
    "sg:city":"K\u00f8ge",
    "sg:orig_category":"Dagplejeformidling",
    "sg:phone":"+45 56 67 67 67",
    "sg:postcode":"4600",
    "sg:province":"Danmark",
    "wof:name":"Dagplejeformidlingen",
    "wof:placetype":"venue"
},
  "geometry": {"coordinates":[12.1823301315,55.4556388855],"type":"Point"}
}