{
  "type": "Feature",
  "properties": {
    "addr:full":"Mejlbyvej 3 Lintrup Danmark 6660",
    "addr:housenumber":"3",
    "addr:postcode":"6660",
    "addr:street":"Mejlbyvej",
    "iso:country":"DK",
    "sg:address":"Mejlbyvej 3",
    "sg:city":"Lintrup",
    "sg:orig_category":"Epoxybehandling",
    "sg:phone":"+45 74 85 51 27",
    "sg:postcode":"6660",
    "sg:province":"Danmark",
    "wof:name":"Erbou Special-Service",
    "wof:placetype":"venue"
},
  "geometry": {"coordinates":[8.9542322159,55.4004936218],"type":"Point"}
}