{
  "type": "Feature",
  "properties": {
    "iso:country":"DK",
    "sg:address":"Bernstorffsgade 4",
    "sg:city":"K\u00f8benhavn",
    "sg:orig_category":"HOTELS: OG MOTELLER",
    "sg:phone":"+45 33 14 92 62",
    "sg:postcode":"1577",
    "sg:province":"Danmark",
    "sg:website":"www.accorhotel.dk",
    "wof:name":"Sofitel Copenhagen",
    "wof:placetype":"venue"
},
  "geometry": {"coordinates":[12.5688199997,55.6709785461],"type":"Point"}
}