{
  "type": "Feature",
  "properties": {
    "iso:country":"DK",
    "sg:address":"Nygade 12",
    "sg:city":"Kalundborg",
    "sg:orig_category":"Teatre",
    "sg:phone":"+45 59 51 24 21",
    "sg:postcode":"4400",
    "sg:province":"Danmark",
    "wof:name":"Kalundborg Amat\u00f8r Teater",
    "wof:placetype":"venue"
},
  "geometry": {"coordinates":[11.0943031311,55.6786117554],"type":"Point"}
}