{
  "type": "Feature",
  "properties": {
    "addr:full":"Danmarksgade 34 Frederikshavn Danmark 9900",
    "addr:housenumber":"34",
    "addr:postcode":"9900",
    "addr:street":"Danmarksgade",
    "iso:country":"DK",
    "sg:address":"Danmarksgade 34",
    "sg:city":"Frederikshavn",
    "sg:orig_category":"Fotografer",
    "sg:phone":"+45 98 42 80 66",
    "sg:postcode":"9900",
    "sg:province":"Danmark",
    "wof:name":"Foto 34",
    "wof:placetype":"venue"
},
  "geometry": {"coordinates":[10.5374116898,57.4423866272],"type":"Point"}
}