{
  "type": "Feature",
  "properties": {
    "iso:country":"DK",
    "sg:address":"Storegade 7 ",
    "sg:city":"Randers",
    "sg:classifiers":[
        {
            "category":"Shopping",
            "subcategory":"Clothing, Apparel, & Fashions",
            "type":"Retail Goods"
        }
    ],
    "sg:phone":"+45 86 42 35 86",
    "sg:postcode":"8900",
    "sg:province":"Danmark",
    "sg:tags":[
        "clothes"
    ],
    "wof:name":"N K ELGAARD APS",
    "wof:placetype":"venue"
},
  "geometry": {"coordinates":[10.0381584167,56.4582481384],"type":"Point"}
}