{
  "type": "Feature",
  "properties": {
    "addr:full":"S\u00f8ndergade 30, Nordenbro Humble Danmark 5932",
    "addr:housenumber":"30",
    "addr:postcode":"5932",
    "addr:street":"Sondergade;Nordenbro",
    "iso:country":"DK",
    "sg:address":"S\u00f8ndergade 30, Nordenbro",
    "sg:city":"Humble",
    "sg:orig_category":"Murermestre",
    "sg:phone":"+45 62 56 12 58",
    "sg:postcode":"5932",
    "sg:province":"Danmark",
    "wof:name":"Jacobsen, Arne",
    "wof:placetype":"venue"
},
  "geometry": {"coordinates":[10.6990814209,54.8273429871],"type":"Point"}
}