{
  "type": "Feature",
  "properties": {
    "iso:country":"DK",
    "sg:address":"Holmegade 18",
    "sg:city":"Ulfborg",
    "sg:classifiers":[
        {
            "category":"Banks & Credit Unions",
            "subcategory":"Bank",
            "type":"Services"
        }
    ],
    "sg:phone":"+45 97 49 19 00",
    "sg:postcode":"6990",
    "sg:province":"Danmark",
    "sg:tags":[
        "banker"
    ],
    "wof:name":"Nordea",
    "wof:placetype":"venue"
},
  "geometry": {"coordinates":[8.322052002,56.2737197876],"type":"Point"}
}