{
  "type": "Feature",
  "properties": {
    "iso:country":"DK",
    "sg:address":"Hj\u00f8rringvej 112, H\u00f8rby",
    "sg:city":"S\u00e6by",
    "sg:orig_category":"Bagere",
    "sg:phone":"+45 98 46 60 06",
    "sg:postcode":"9300",
    "sg:province":"Danmark",
    "wof:name":"H\u00f8rby Bageri",
    "wof:placetype":"venue"
},
  "geometry": {"coordinates":[-78.063751,43.049847],"type":"Point"}
}