{
  "type": "Feature",
  "properties": {
    "iso:country":"DK",
    "sg:address":"\u00d8rb\u00e6kvej 11",
    "sg:city":"Svendborg",
    "sg:orig_category":"Supermarkeder",
    "sg:phone":"+45 62 21 03 14",
    "sg:postcode":"5700",
    "sg:province":"Danmark",
    "wof:name":"Aktiv Super I/S",
    "wof:placetype":"venue"
},
  "geometry": {"coordinates":[10.6065101624,55.0595970154],"type":"Point"}
}