{
  "type": "Feature",
  "properties": {
    "iso:country":"DK",
    "sg:address":"Torvet 11",
    "sg:city":"Haderslev",
    "sg:orig_category":"Stoffer",
    "sg:phone":"+45 74 53 13 35",
    "sg:postcode":"6100",
    "sg:province":"Danmark",
    "wof:name":"Magdalene",
    "wof:placetype":"venue"
},
  "geometry": {"coordinates":[9.4881305695,55.249004364],"type":"Point"}
}