{
  "type": "Feature",
  "properties": {
    "addr:full":"Egev\u00e6nget 51, Askov Vejen Danmark 6600",
    "addr:housenumber":"51",
    "addr:postcode":"6600",
    "addr:street":"Egevaenget",
    "iso:country":"DK",
    "sg:address":"Egev\u00e6nget 51, Askov",
    "sg:city":"Vejen",
    "sg:orig_category":"Ure og urmagere",
    "sg:phone":"+45 75 36 23 74",
    "sg:postcode":"6600",
    "sg:province":"Danmark",
    "wof:name":"KJ - Ure",
    "wof:placetype":"venue"
},
  "geometry": {"coordinates":[9.1396121979,55.4778175354],"type":"Point"}
}