{
  "type": "Feature",
  "properties": {
    "iso:country":"DK",
    "sg:address":"Bredgade 26",
    "sg:city":"Hedensted",
    "sg:orig_category":"Blomsterhandlere",
    "sg:phone":"+45 75 89 09 17",
    "sg:postcode":"8722",
    "sg:province":"Danmark",
    "wof:name":"Bl\u00e5 Valmue, Den",
    "wof:placetype":"venue"
},
  "geometry": {"coordinates":[9.6965761185,55.7695388794],"type":"Point"}
}