{
  "type": "Feature",
  "properties": {
    "iso:country":"DK",
    "sg:address":"Vestergade 24",
    "sg:city":"Thisted",
    "sg:orig_category":"Advokater",
    "sg:phone":"+45 97 92 00 66",
    "sg:postcode":"7700",
    "sg:province":"Danmark",
    "wof:name":"Haumann - \u00d8stergaard - Fastrup",
    "wof:placetype":"venue"
},
  "geometry": {"coordinates":[8.6872253418,56.9549026489],"type":"Point"}
}