{
  "type": "Feature",
  "properties": {
    "addr:full":"Guldborgvej 270 Guldborg Danmark 4862",
    "addr:housenumber":"270",
    "addr:postcode":"4862",
    "addr:street":"Guldborgvej",
    "iso:country":"DK",
    "sg:address":"Guldborgvej 270",
    "sg:city":"Guldborg",
    "sg:orig_category":"Autoforhandlere",
    "sg:phone":"+45 54 77 06 06",
    "sg:postcode":"4862",
    "sg:province":"Danmark",
    "wof:name":"Auto-Frank Guldborg ApS",
    "wof:placetype":"venue"
},
  "geometry": {"coordinates":[11.7380428314,54.8659172058],"type":"Point"}
}