{
  "type": "Feature",
  "properties": {
    "addr:full":"Rug\u00e5rdsvej 644, Slukefter Odense NV Danmark 5210",
    "addr:housenumber":"644",
    "addr:postcode":"5210",
    "addr:street":"Rugaardsvej;Slukefter",
    "iso:country":"DK",
    "sg:address":"Rug\u00e5rdsvej 644, Slukefter",
    "sg:city":"Odense NV",
    "sg:orig_category":"Autoreparation og -service",
    "sg:postcode":"5210",
    "sg:province":"Danmark",
    "wof:name":"Slukefter Smede- og Autoreparation I/S",
    "wof:placetype":"venue"
},
  "geometry": {"coordinates":[10.274764061,55.4303321838],"type":"Point"}
}