{
  "type": "Feature",
  "properties": {
    "addr:full":"Vesterbro 5 Havndal Danmark 8970",
    "addr:housenumber":"5",
    "addr:postcode":"8970",
    "addr:street":"Vesterbro",
    "iso:country":"DK",
    "sg:address":"Vesterbro 5",
    "sg:city":"Havndal",
    "sg:orig_category":"Skomagere",
    "sg:phone":"+45 86 47 00 27",
    "sg:postcode":"8970",
    "sg:province":"Danmark",
    "wof:name":"Jensen, L. P.",
    "wof:placetype":"venue"
},
  "geometry": {"coordinates":[10.1913671494,56.653427124],"type":"Point"}
}