{
  "type": "Feature",
  "properties": {
    "iso:country":"DK",
    "sg:address":"Dorphs Alle 22",
    "sg:city":"Taastrup",
    "sg:orig_category":"Malermestre",
    "sg:phone":"+45 43 71 79 81",
    "sg:postcode":"2630",
    "sg:province":"Danmark",
    "wof:name":"Hansen, J\u00f8rgen",
    "wof:placetype":"venue"
},
  "geometry": {"coordinates":[12.3067493439,55.6492996216],"type":"Point"}
}