{
  "type": "Feature",
  "properties": {
    "addr:full":"Vindingevej 10 Roskilde Danmark 4000",
    "addr:housenumber":"10",
    "addr:postcode":"4000",
    "addr:street":"Vindingevej",
    "iso:country":"DK",
    "sg:address":"Vindingevej 10",
    "sg:city":"Roskilde",
    "sg:orig_category":"Motionscentre",
    "sg:phone":"+45 46 32 33 49",
    "sg:postcode":"4000",
    "sg:province":"Danmark",
    "wof:name":"Studie One",
    "wof:placetype":"venue"
},
  "geometry": {"coordinates":[12.0960407257,55.6393127441],"type":"Point"}
}