{
  "type": "Feature",
  "properties": {
    "iso:country":"DK",
    "sg:address":"S\u00f8nderbrogade 16",
    "sg:city":"Vejle",
    "sg:orig_category":"Renserier",
    "sg:phone":"+45 78 82 52 51",
    "sg:postcode":"7100",
    "sg:province":"Danmark",
    "wof:name":"S\u00f8nderbro Renseri",
    "wof:placetype":"venue"
},
  "geometry": {"coordinates":[9.5318632126,55.7046051025],"type":"Point"}
}