{
  "type": "Feature",
  "properties": {
    "iso:country":"DK",
    "sg:address":"Byst\u00e6vnet 2, Stenl\u00f8se",
    "sg:city":"Odense S",
    "sg:orig_category":"INGENI\u00c3\u02dcRER",
    "sg:phone":"+45 66 15 19 62",
    "sg:postcode":"5260",
    "sg:province":"Danmark",
    "wof:name":"Sick, Palle",
    "wof:placetype":"venue"
},
  "geometry": {"coordinates":[10.3157806396,55.3122825623],"type":"Point"}
}