{
  "type": "Feature",
  "properties": {
    "addr:full":"Holte Midtpunkt 23 Holte Danmark 2840",
    "addr:housenumber":"23",
    "addr:postcode":"2840",
    "addr:street":"Holte Midtpunkt",
    "iso:country":"DK",
    "sg:address":"Holte Midtpunkt 23",
    "sg:city":"Holte",
    "sg:classifiers":[
        {
            "category":"Restaurant",
            "type":"Food & Drink"
        }
    ],
    "sg:phone":"+45 45 41 22 40",
    "sg:postcode":"2840",
    "sg:province":"Danmark",
    "wof:name":"Caf\u00e9 Emil",
    "wof:placetype":"venue"
},
  "geometry": {"coordinates":[12.4706125259,55.811164856],"type":"Point"}
}