{
  "type": "Feature",
  "properties": {
    "iso:country":"DK",
    "sg:address":"Gruppeleder: Benny Clemmensen, Agerskovvej 47 B, Hammerum",
    "sg:city":"Herning",
    "sg:orig_category":"Spejderkorps",
    "sg:phone":"+45 97 11 96 24",
    "sg:postcode":"7400",
    "sg:province":"Danmark",
    "wof:name":"KFUM-spejderne - Hammerum",
    "wof:placetype":"venue"
},
  "geometry": {"coordinates":[8.9768896103,56.1374168396],"type":"Point"}
}