{
  "type": "Feature",
  "properties": {
    "addr:full":"Strandholtvej 6, Stige Odense N Danmark 5270",
    "addr:housenumber":"6",
    "addr:postcode":"5270",
    "addr:street":"Strandholtvej;Stige",
    "iso:country":"DK",
    "sg:address":"Strandholtvej 6, Stige",
    "sg:city":"Odense N",
    "sg:orig_category":"Psykologer, praktiserende",
    "sg:phone":"+45 66 18 64 67",
    "sg:postcode":"5270",
    "sg:province":"Danmark",
    "wof:name":"Nielsen, Kurt",
    "wof:placetype":"venue"
},
  "geometry": {"coordinates":[10.3306798935,55.4711418152],"type":"Point"}
}