{
  "type": "Feature",
  "properties": {
    "iso:country":"DK",
    "sg:address":"Munkebjergv\u00e6nget 2 - 14",
    "sg:city":"Odense M",
    "sg:orig_category":"Kollegier",
    "sg:phone":"+45 63 95 11 00",
    "sg:postcode":"5230",
    "sg:province":"Danmark",
    "wof:name":"Thomas B Thriges Kollegium",
    "wof:placetype":"venue"
},
  "geometry": {"coordinates":[10.4090681076,55.3723640442],"type":"Point"}
}