{
  "type": "Feature",
  "properties": {
    "iso:country":"DK",
    "sg:address":"Vestergade 13",
    "sg:city":"Arden",
    "sg:orig_category":"Bagere",
    "sg:phone":"+45 98 56 10 80",
    "sg:postcode":"9510",
    "sg:province":"Danmark",
    "wof:name":"Arden Bageri",
    "wof:placetype":"venue"
},
  "geometry": {"coordinates":[9.858262,56.76897],"type":"Point"}
}