{
  "type": "Feature",
  "properties": {
    "iso:country":"DK",
    "sg:address":"M\u00f8llegade 3",
    "sg:city":"Gilleleje",
    "sg:classifiers":[
        {
            "category":"Restaurant",
            "type":"Food & Drink"
        }
    ],
    "sg:phone":"+45 48 30 16 66",
    "sg:postcode":"3250",
    "sg:province":"Danmark",
    "wof:name":"Kok & Kone",
    "wof:placetype":"venue"
},
  "geometry": {"coordinates":[12.3032236099,56.1254730225],"type":"Point"}
}