{
  "type": "Feature",
  "properties": {
    "addr:full":"Jagtvej 147 K\u00f8benhavn N Danmark 2200",
    "addr:housenumber":"147",
    "addr:postcode":"2200",
    "addr:street":"Jagtvej;N Danmark",
    "iso:country":"DK",
    "sg:address":"Jagtvej 147",
    "sg:city":"K\u00f8benhavn N",
    "sg:classifiers":[
        {
            "category":"Restaurant",
            "type":"Food & Drink"
        }
    ],
    "sg:phone":"+45 35 83 72 13",
    "sg:postcode":"2200",
    "sg:province":"Danmark",
    "wof:name":"Tagensborg",
    "wof:placetype":"venue"
},
  "geometry": {"coordinates":[-112.4202804565,36.7173728943],"type":"Point"}
}