{
  "type": "Feature",
  "properties": {
    "addr:full":"Ralvej 65 Aalborg Danmark 9000",
    "addr:housenumber":"65",
    "addr:postcode":"9000",
    "addr:street":"Ralvej",
    "iso:country":"DK",
    "sg:address":"Ralvej 65",
    "sg:city":"Aalborg",
    "sg:orig_category":"Faglige organisationer og foreninger",
    "sg:phone":"+45 98 16 97 35",
    "sg:postcode":"9000",
    "sg:province":"Danmark",
    "wof:name":"Aalborg Ny Fiskeriforening",
    "wof:placetype":"venue"
},
  "geometry": {"coordinates":[9.8892841339,57.0580253601],"type":"Point"}
}