{
  "type": "Feature",
  "properties": {
    "iso:country":"DK",
    "sg:address":"Nederdammen 35",
    "sg:city":"Ribe",
    "sg:orig_category":"Brugskunst",
    "sg:phone":"+45 75 42 43 50",
    "sg:postcode":"6760",
    "sg:province":"Danmark",
    "wof:name":"Carisma",
    "wof:placetype":"venue"
},
  "geometry": {"coordinates":[8.7659168243,55.3299026489],"type":"Point"}
}