{
  "type": "Feature",
  "properties": {
    "addr:full":"L\u00f8kkeled 6, Vilstrup Haderslev Danmark 6100",
    "addr:housenumber":"6",
    "addr:postcode":"6100",
    "addr:street":"Lokkeled;Vilstrup",
    "iso:country":"DK",
    "sg:address":"L\u00f8kkeled 6, Vilstrup",
    "sg:city":"Haderslev",
    "sg:orig_category":"Helsekost",
    "sg:phone":"+45 74 58 28 68",
    "sg:postcode":"6100",
    "sg:province":"Danmark",
    "wof:name":"Brink-Vilsen, Dorte",
    "wof:placetype":"venue"
},
  "geometry": {"coordinates":[9.4879703522,55.2505493164],"type":"Point"}
}