{
  "type": "Feature",
  "properties": {
    "addr:full":"Danmarksgade 45 Esbjerg Danmark 6700",
    "addr:housenumber":"45",
    "addr:postcode":"6700",
    "addr:street":"Danmarksgade",
    "iso:country":"DK",
    "sg:address":"Danmarksgade 45",
    "sg:city":"Esbjerg",
    "sg:orig_category":"Karate og selvforsvar",
    "sg:phone":"+45 75 12 43 53",
    "sg:postcode":"6700",
    "sg:province":"Danmark",
    "wof:name":"Esbjerg Karate Klub",
    "wof:placetype":"venue"
},
  "geometry": {"coordinates":[8.4514980316,55.4678611755],"type":"Point"}
}