{
  "type": "Feature",
  "properties": {
    "addr:full":"Hovedgaden 13 Ulstrup Danmark 8860",
    "addr:housenumber":"13",
    "addr:postcode":"8860",
    "addr:street":"Hovedgaden",
    "iso:country":"DK",
    "sg:address":"Hovedgaden 13",
    "sg:city":"Ulstrup",
    "sg:orig_category":"Kiosker",
    "sg:phone":"+45 86 46 33 81",
    "sg:postcode":"8860",
    "sg:province":"Danmark",
    "wof:name":"Kiosk 13",
    "wof:placetype":"venue"
},
  "geometry": {"coordinates":[9.7943086624,56.3919067383],"type":"Point"}
}