{
  "type": "Feature",
  "properties": {
    "addr:full":"Agner Fmd.: S\u00f8rensen, Oddevej 44, Klim Fjerritslev Danmark 9690",
    "addr:housenumber":"44",
    "addr:postcode":"9690",
    "addr:street":"Sorensen Oddevej",
    "iso:country":"DK",
    "sg:address":"Agner Fmd.: S\u00f8rensen, Oddevej 44, Klim",
    "sg:city":"Fjerritslev",
    "sg:orig_category":"Kirkelige foreninger",
    "sg:phone":"+45 98 22 52 65",
    "sg:postcode":"9690",
    "sg:province":"Danmark",
    "wof:name":"Indre Missions Samfund i Klim",
    "wof:placetype":"venue"
},
  "geometry": {"coordinates":[9.2667350769,57.0882301331],"type":"Point"}
}