{
  "type": "Feature",
  "properties": {
    "addr:full":"Glyng\u00f8revej 62, V. Lyby Skive Danmark 7800",
    "addr:housenumber":"62",
    "addr:postcode":"7800",
    "addr:street":"Glyngorevej;Lyby",
    "iso:country":"DK",
    "sg:address":"Glyng\u00f8revej 62, V. Lyby",
    "sg:city":"Skive",
    "sg:orig_category":"Dyrefoder",
    "sg:phone":"+45 25 36 49 50",
    "sg:postcode":"7800",
    "sg:province":"Danmark",
    "wof:name":"Dyrenes Paradis",
    "wof:placetype":"venue"
},
  "geometry": {"coordinates":[9.0320358276,56.5666427612],"type":"Point"}
}