{
  "type": "Feature",
  "properties": {
    "addr:full":"Sindalsvej 40 Risskov Danmark 8240",
    "addr:housenumber":"40",
    "addr:postcode":"8240",
    "addr:street":"Sindalsvej",
    "iso:country":"DK",
    "sg:address":"Sindalsvej 40",
    "sg:city":"Risskov",
    "sg:orig_category":"Autolakering",
    "sg:phone":"+45 86 21 18 55",
    "sg:postcode":"8240",
    "sg:province":"Danmark",
    "sg:website":"www.ic-autolakering.dk",
    "wof:name":"I. C. Autolakering ApS",
    "wof:placetype":"venue"
},
  "geometry": {"coordinates":[10.2132911682,56.2100334167],"type":"Point"}
}