{
  "type": "Feature",
  "properties": {
    "iso:country":"DK",
    "sg:address":"Farum Gydevej 85",
    "sg:city":"Farum",
    "sg:orig_category":"Revisorer",
    "sg:phone":"+45 44 95 06 41",
    "sg:postcode":"3520",
    "sg:province":"Danmark",
    "sg:website":"www.gdahlfelt.dk",
    "wof:name":"Dahlfelt Farum, G.",
    "wof:placetype":"venue"
},
  "geometry": {"coordinates":[12.3615913391,55.8211746216],"type":"Point"}
}