{
  "type": "Feature",
  "properties": {
    "addr:full":"Gryde Torv 24 Thisted Danmark 7700",
    "addr:housenumber":"24",
    "addr:postcode":"7700",
    "addr:street":"Gryde Torv",
    "iso:country":"DK",
    "sg:address":"Gryde Torv 24",
    "sg:city":"Thisted",
    "sg:orig_category":"Fodterapeuter",
    "sg:phone":"+45 97 92 26 50",
    "sg:postcode":"7700",
    "sg:province":"Danmark",
    "wof:name":"Klinik for Fodterapi",
    "wof:placetype":"venue"
},
  "geometry": {"coordinates":[8.6930885315,56.9542999268],"type":"Point"}
}