{
  "type": "Feature",
  "properties": {
    "addr:full":"Toftevej 60 Outrup Danmark 6855",
    "addr:housenumber":"60",
    "addr:postcode":"6855",
    "addr:street":"Toftevej",
    "iso:country":"DK",
    "sg:address":"Toftevej 60",
    "sg:city":"Outrup",
    "sg:orig_category":"Maskinstationer",
    "sg:phone":"+45 75 25 12 13",
    "sg:postcode":"6855",
    "sg:province":"Danmark",
    "wof:name":"Madsen Maskinstation, Egon",
    "wof:placetype":"venue"
},
  "geometry": {"coordinates":[8.3488464355,55.7102775574],"type":"Point"}
}