{
  "type": "Feature",
  "properties": {
    "addr:full":"v/ Connie M\u00f8ller, Sandkn\u00f8sen 45, Sanderum Odense SV Danmark 5250",
    "addr:housenumber":"45",
    "addr:postcode":"5250",
    "addr:street":"Sanderum",
    "iso:country":"DK",
    "sg:address":"v/ Connie M\u00f8ller, Sandkn\u00f8sen 45, Sanderum",
    "sg:city":"Odense SV",
    "sg:orig_category":"Hobbybetonede foreninger",
    "sg:phone":"+45 66 17 07 26",
    "sg:postcode":"5250",
    "sg:province":"Danmark",
    "sg:website":"www.dacf.dk",
    "wof:name":"Dansk AutoCamper Forening",
    "wof:placetype":"venue"
},
  "geometry": {"coordinates":[10.3153953552,55.3362998962],"type":"Point"}
}