{
  "type": "Feature",
  "properties": {
    "addr:full":"Strandvejen 12 Ebeltoft Danmark 8400",
    "addr:housenumber":"12",
    "addr:postcode":"8400",
    "addr:street":"Strandvejen",
    "iso:country":"DK",
    "sg:address":"Strandvejen 12",
    "sg:city":"Ebeltoft",
    "sg:orig_category":"Sportsartikler",
    "sg:phone":"+45 86 34 45 55",
    "sg:postcode":"8400",
    "sg:province":"Danmark",
    "sg:website":"www.steffen-fritid.dk",
    "wof:name":"Steffen Fritid",
    "wof:placetype":"venue"
},
  "geometry": {"coordinates":[10.6730880737,56.1953125],"type":"Point"}
}