{
  "type": "Feature",
  "properties": {
    "addr:full":"Lufthavnsvej 3  Billund Danmark 7190",
    "addr:housenumber":"3",
    "addr:postcode":"7190",
    "addr:street":"Lufthavnsvej",
    "iso:country":"DK",
    "sg:address":"Lufthavnsvej 3 ",
    "sg:city":"Billund",
    "sg:classifiers":[
        {
            "category":"Airport",
            "subcategory":"General Aviation",
            "type":"Transportation"
        }
    ],
    "sg:phone":"+45 76 50 50 50",
    "sg:postcode":"7190",
    "sg:province":"Danmark",
    "sg:tags":[
        "transport",
        "air"
    ],
    "wof:name":"BILLUND LUFTHAVN AMBA",
    "wof:placetype":"venue"
},
  "geometry": {"coordinates":[9.1361255646,55.7485198975],"type":"Point"}
}