{
  "type": "Feature",
  "properties": {
    "addr:full":"(Fmd. Jens Kristian Pedersen), Amagerbrogade 187 K\u00f8benhavn S Danmark 2300",
    "addr:housenumber":"187",
    "addr:postcode":"2300",
    "addr:street":"Amagerbrogade;Kobenhavn S Danmark",
    "iso:country":"DK",
    "sg:address":"(Fmd. Jens Kristian Pedersen), Amagerbrogade 187",
    "sg:city":"K\u00f8benhavn S",
    "sg:orig_category":"Foreninger og organisationer",
    "sg:phone":"+45 32 58 92 77",
    "sg:postcode":"2300",
    "sg:province":"Danmark",
    "sg:website":"www.socialdemokratiet.dk",
    "wof:name":"Socialdemokratiet Sundby 4-kreds",
    "wof:placetype":"venue"
},
  "geometry": {"coordinates":[-78.1299133301,36.7267417908],"type":"Point"}
}