{
  "type": "Feature",
  "properties": {
    "addr:full":"Krabbesbrovej 23, Ulsted Hals Danmark 9370",
    "addr:housenumber":"23",
    "addr:postcode":"9370",
    "addr:street":"Krabbesbrovej;Ulsted",
    "iso:country":"DK",
    "sg:address":"Krabbesbrovej 23, Ulsted",
    "sg:city":"Hals",
    "sg:orig_category":"Stearinlys",
    "sg:phone":"+45 98 25 44 00",
    "sg:postcode":"9370",
    "sg:province":"Danmark",
    "wof:name":"Ulve - Lys",
    "wof:placetype":"venue"
},
  "geometry": {"coordinates":[10.3669347763,57.0597991943],"type":"Point"}
}