{
  "type": "Feature",
  "properties": {
    "addr:full":"Haderslevvej 45 Ribe Danmark 6760",
    "addr:housenumber":"45",
    "addr:postcode":"6760",
    "addr:street":"Haderslevvej",
    "iso:country":"DK",
    "sg:address":"Haderslevvej 45",
    "sg:city":"Ribe",
    "sg:orig_category":"Blikkenslagere",
    "sg:phone":"+45 75 42 18 32",
    "sg:postcode":"6760",
    "sg:province":"Danmark",
    "wof:name":"Nissen, Egon",
    "wof:placetype":"venue"
},
  "geometry": {"coordinates":[8.7740316391,55.3177604675],"type":"Point"}
}