{
  "type": "Feature",
  "properties": {
    "addr:full":"Vestergade 9 Struer Danmark 7600",
    "addr:housenumber":"9",
    "addr:postcode":"7600",
    "addr:street":"Vestergade",
    "iso:country":"DK",
    "sg:address":"Vestergade 9",
    "sg:city":"Struer",
    "sg:orig_category":"Materialister",
    "sg:phone":"+45 97 85 05 52",
    "sg:postcode":"7600",
    "sg:province":"Danmark",
    "wof:name":"Struer Materialhandel",
    "wof:placetype":"venue"
},
  "geometry": {"coordinates":[8.5907506943,56.4917373657],"type":"Point"}
}