{
  "type": "Feature",
  "properties": {
    "addr:full":"Hjortsvangen 15 Give Danmark 7323",
    "addr:housenumber":"15",
    "addr:postcode":"7323",
    "addr:street":"Hjortsvangen",
    "iso:country":"DK",
    "sg:address":"Hjortsvangen 15",
    "sg:city":"Give",
    "sg:orig_category":"Fabrikker",
    "sg:phone":"+45 75 73 18 44",
    "sg:postcode":"7323",
    "sg:province":"Danmark",
    "wof:name":"Dan Cake A/S",
    "wof:placetype":"venue"
},
  "geometry": {"coordinates":[9.2494564056,55.8598709106],"type":"Point"}
}