{
  "type": "Feature",
  "properties": {
    "addr:full":"Skolegade 11 Grindsted Danmark 7200",
    "addr:housenumber":"11",
    "addr:postcode":"7200",
    "addr:street":"Skolegade",
    "iso:country":"DK",
    "sg:address":"Skolegade 11",
    "sg:city":"Grindsted",
    "sg:orig_category":"Arkitekter",
    "sg:phone":"+45 75 32 31 24",
    "sg:postcode":"7200",
    "sg:province":"Danmark",
    "wof:name":"Madsen, Erik Kousgaard",
    "wof:placetype":"venue"
},
  "geometry": {"coordinates":[8.9288921356,55.7582321167],"type":"Point"}
}