{
  "type": "Feature",
  "properties": {
    "iso:country":"DK",
    "sg:address":"Limfjordsgade 9, Koldby",
    "sg:city":"Snedsted",
    "sg:orig_category":"Skolefritidsordninger",
    "sg:phone":"+45 97 93 68 32",
    "sg:postcode":"7752",
    "sg:province":"Danmark",
    "wof:name":"Marieh\u00f8nen, Koldby Skoles SFO",
    "wof:placetype":"venue"
},
  "geometry": {"coordinates":[8.5276002884,56.8460388184],"type":"Point"}
}