{
  "type": "Feature",
  "properties": {
    "addr:full":"S\u00f8ndergade 1 Kjellerup Danmark 8620",
    "addr:housenumber":"1",
    "addr:postcode":"8620",
    "addr:street":"Sondergade",
    "iso:country":"DK",
    "sg:address":"S\u00f8ndergade 1",
    "sg:city":"Kjellerup",
    "sg:classifiers":[
        {
            "category":"Banks & Credit Unions",
            "subcategory":"Bank",
            "type":"Services"
        }
    ],
    "sg:phone":"+45 87 70 01 11",
    "sg:postcode":"8620",
    "sg:province":"Danmark",
    "sg:tags":[
        "banker"
    ],
    "wof:name":"Jyske Bank",
    "wof:placetype":"venue"
},
  "geometry": {"coordinates":[9.4309110641,56.2832870483],"type":"Point"}
}