{
  "type": "Feature",
  "properties": {
    "addr:full":"Fmd.: Johanne Jensen, H. I. Bies Plads 251 Hobro Danmark 9500",
    "addr:housenumber":"251",
    "addr:postcode":"9500",
    "addr:street":"H. I. Bies Plads",
    "iso:country":"DK",
    "sg:address":"Fmd.: Johanne Jensen, H. I. Bies Plads 251",
    "sg:city":"Hobro",
    "sg:orig_category":"\u00c3\u2020ldreorganisationer og klubber",
    "sg:phone":"+45 98 52 28 31",
    "sg:postcode":"9500",
    "sg:province":"Danmark",
    "wof:name":"Den Kommunale Pensionistklub",
    "wof:placetype":"venue"
},
  "geometry": {"coordinates":[9.7969417572,56.6381263733],"type":"Point"}
}