{
  "type": "Feature",
  "properties": {
    "addr:full":"Lange-M\u00fcllers Vej 10 Herning Danmark 7400",
    "addr:housenumber":"10",
    "addr:postcode":"7400",
    "addr:street":"Lange-Muellers Vej",
    "iso:country":"DK",
    "sg:address":"Lange-M\u00fcllers Vej 10",
    "sg:city":"Herning",
    "sg:orig_category":"Psykologer, praktiserende",
    "sg:phone":"+45 97 12 08 91",
    "sg:postcode":"7400",
    "sg:province":"Danmark",
    "wof:name":"Odgaard, Jens",
    "wof:placetype":"venue"
},
  "geometry": {"coordinates":[8.9768896103,56.1374168396],"type":"Point"}
}