{
  "type": "Feature",
  "properties": {
    "addr:full":"Fmd.: Harry M\u00f8ller, Hyldeg\u00e5rdsvej 26 Ringsted Danmark 4100",
    "addr:housenumber":"26",
    "addr:postcode":"4100",
    "addr:street":"Hyldegaardsvej",
    "iso:country":"DK",
    "sg:address":"Fmd.: Harry M\u00f8ller, Hyldeg\u00e5rdsvej 26",
    "sg:city":"Ringsted",
    "sg:orig_category":"\u00c3\u2020ldreorganisationer og klubber",
    "sg:phone":"+45 57 61 56 30",
    "sg:postcode":"4100",
    "sg:province":"Danmark",
    "wof:name":"Ringsted Pensionistforening",
    "wof:placetype":"venue"
},
  "geometry": {"coordinates":[11.7875862122,55.4458961487],"type":"Point"}
}