{
  "type": "Feature",
  "properties": {
    "addr:full":"Falkoner Alle 54 Frederiksberg Danmark 2000",
    "addr:housenumber":"54",
    "addr:postcode":"2000",
    "addr:street":"Falkoner Alle",
    "iso:country":"DK",
    "sg:address":"Falkoner Alle 54",
    "sg:city":"Frederiksberg",
    "sg:orig_category":"Antikviteter",
    "sg:phone":"+45 35 37 49 68",
    "sg:postcode":"2000",
    "sg:province":"Danmark",
    "wof:name":"Dewajtis Antik, Richard P\u00fcrkhardt",
    "wof:placetype":"venue"
},
  "geometry": {"coordinates":[12.5369138718,55.6836280823],"type":"Point"}
}