{
  "type": "Feature",
  "properties": {
    "addr:full":"D\u00e6mningen 66 Vejle Danmark 7100",
    "addr:housenumber":"66",
    "addr:postcode":"7100",
    "addr:street":"Daemningen",
    "iso:country":"DK",
    "sg:address":"D\u00e6mningen 66",
    "sg:city":"Vejle",
    "sg:orig_category":"Revisorer",
    "sg:phone":"+45 75 82 58 33",
    "sg:postcode":"7100",
    "sg:province":"Danmark",
    "wof:name":"Revisionsfirmaet Spallou",
    "wof:placetype":"venue"
},
  "geometry": {"coordinates":[9.5363683701,55.7102966309],"type":"Point"}
}