{
  "type": "Feature",
  "properties": {
    "addr:full":"Kass.: Bjarne Schobius, Skovstjernen 20 Holstebro Danmark 7500",
    "addr:housenumber":"20",
    "addr:postcode":"7500",
    "addr:street":"Skovstjernen",
    "iso:country":"DK",
    "sg:address":"Kass.: Bjarne Schobius, Skovstjernen 20",
    "sg:city":"Holstebro",
    "sg:orig_category":"Musik og sang",
    "sg:phone":"+45 97 41 16 62",
    "sg:postcode":"7500",
    "sg:province":"Danmark",
    "wof:name":"Industri- og H\u00e5ndv\u00e6rkerforen. Mandskor",
    "wof:placetype":"venue"
},
  "geometry": {"coordinates":[8.6202583313,56.3625221252],"type":"Point"}
}