{
  "type": "Feature",
  "properties": {
    "addr:full":"Lokesvej 5 Thors\u00f8 Danmark 8881",
    "addr:housenumber":"5",
    "addr:postcode":"8881",
    "addr:street":"Lokesvej",
    "iso:country":"DK",
    "sg:address":"Lokesvej 5",
    "sg:city":"Thors\u00f8",
    "sg:orig_category":"Oliefyr og service",
    "sg:phone":"+45 86 96 66 12",
    "sg:postcode":"8881",
    "sg:province":"Danmark",
    "wof:name":"Kristensen, J\u00f8rn",
    "wof:placetype":"venue"
},
  "geometry": {"coordinates":[9.7899580002,56.2992591858],"type":"Point"}
}