{
  "type": "Feature",
  "properties": {
    "addr:full":"K\u00e6debyvej 1 Humble Danmark 5932",
    "addr:housenumber":"1",
    "addr:postcode":"5932",
    "addr:street":"Kaedebyvej",
    "iso:country":"DK",
    "sg:address":"K\u00e6debyvej 1",
    "sg:city":"Humble",
    "sg:orig_category":"Landbrugsmaskiner",
    "sg:phone":"+45 62 57 12 55",
    "sg:postcode":"5932",
    "sg:province":"Danmark",
    "sg:website":"www.kaedeby.dk",
    "wof:name":"K\u00e6deby Maskinforretning A/S",
    "wof:placetype":"venue"
},
  "geometry": {"coordinates":[10.7046308517,54.8404388428],"type":"Point"}
}