{
  "type": "Feature",
  "properties": {
    "addr:full":"v/ Carl Chr. Rosenberg, Jernbanegade 31 Aabenraa Danmark 6200",
    "addr:housenumber":"31",
    "addr:postcode":"6200",
    "addr:street":"Chr.;Jernbanegade",
    "iso:country":"DK",
    "sg:address":"v/ Carl Chr. Rosenberg, Jernbanegade 31",
    "sg:city":"Aabenraa",
    "sg:orig_category":"Kolonihaveforeninger",
    "sg:phone":"+45 74 62 69 68",
    "sg:postcode":"6200",
    "sg:province":"Danmark",
    "wof:name":"Haveforeningen Virkelyst",
    "wof:placetype":"venue"
},
  "geometry": {"coordinates":[9.4213867188,55.0449562073],"type":"Point"}
}