{
  "type": "Feature",
  "properties": {
    "addr:full":"\u00c5gade 1 Lemvig Danmark 7620",
    "addr:housenumber":"1",
    "addr:postcode":"7620",
    "addr:street":"Aagade",
    "iso:country":"DK",
    "sg:address":"\u00c5gade 1",
    "sg:city":"Lemvig",
    "sg:orig_category":"Garn",
    "sg:phone":"+45 97 82 09 80",
    "sg:postcode":"7620",
    "sg:province":"Danmark",
    "wof:name":"Strikkeboden",
    "wof:placetype":"venue"
},
  "geometry": {"coordinates":[8.3097248077,56.5505599976],"type":"Point"}
}