{
  "type": "Feature",
  "properties": {
    "addr:full":"Vester S\u00f8gade 78 K\u00f8benhavn Danmark 1601",
    "addr:housenumber":"78;1601",
    "addr:street":"Sogade",
    "iso:country":"DK",
    "sg:address":"Vester S\u00f8gade 78",
    "sg:city":"K\u00f8benhavn",
    "sg:orig_category":"Psykologer, praktiserende",
    "sg:phone":"+45 33 12 13 60",
    "sg:postcode":"1601",
    "sg:province":"Danmark",
    "wof:name":"Glud, Emmy",
    "wof:placetype":"venue"
},
  "geometry": {"coordinates":[-85.2299499512,37.1363105774],"type":"Point"}
}