{
  "type": "Feature",
  "properties": {
    "addr:full":"M\u00f8llegade 71 Ikast Danmark 7430",
    "addr:housenumber":"71",
    "addr:postcode":"7430",
    "addr:street":"Mollegade",
    "iso:country":"DK",
    "sg:address":"M\u00f8llegade 71",
    "sg:city":"Ikast",
    "sg:orig_category":"Zoneterapeuter",
    "sg:phone":"+45 97 15 60 74",
    "sg:postcode":"7430",
    "sg:province":"Danmark",
    "wof:name":"Lund, Inge",
    "wof:placetype":"venue"
},
  "geometry": {"coordinates":[9.1624250412,56.1340827942],"type":"Point"}
}