{
  "type": "Feature",
  "properties": {
    "addr:full":"Virumgade 11 D Virum Danmark 2830",
    "addr:housenumber":"11 d",
    "addr:postcode":"2830",
    "addr:street":"Virumgade",
    "iso:country":"DK",
    "sg:address":"Virumgade 11 D",
    "sg:city":"Virum",
    "sg:orig_category":"Arkitekter",
    "sg:phone":"+45 45 85 33 33",
    "sg:postcode":"2830",
    "sg:province":"Danmark",
    "wof:name":"Paludan & Ramsager",
    "wof:placetype":"venue"
},
  "geometry": {"coordinates":[12.4737586975,55.789516449],"type":"Point"}
}