{
  "type": "Feature",
  "properties": {
    "addr:full":"Fmd.: Jens Sillesen, Tagensvej 47, 2. K\u00f8benhavn N Danmark 2200",
    "addr:housenumber":"47 2",
    "addr:postcode":"2200",
    "addr:street":"Tagensvej;Kobenhavn N Danmark",
    "iso:country":"DK",
    "sg:address":"Fmd.: Jens Sillesen, Tagensvej 47, 2.",
    "sg:city":"K\u00f8benhavn N",
    "sg:orig_category":"Politiske foreninger, \u00c3\u02dcvrige",
    "sg:phone":"+45 35 84 03 58",
    "sg:postcode":"2200",
    "sg:province":"Danmark",
    "wof:name":"Centrum-Demokraternes Ungdom",
    "wof:placetype":"venue"
},
  "geometry": {"coordinates":[-76.4168395996,37.452419281],"type":"Point"}
}