{
  "type": "Feature",
  "properties": {
    "addr:full":"Algade 4, 2.sal Nyk\u00f8bing Danmark 7900",
    "addr:housenumber":"4",
    "addr:postcode":"7900",
    "addr:street":"Algade;Nykobing",
    "iso:country":"DK",
    "sg:address":"Algade 4, 2.sal",
    "sg:city":"Nyk\u00f8bing",
    "sg:orig_category":"Faglige organisationer og foreninger",
    "sg:phone":"+45 97 72 22 91",
    "sg:postcode":"7900",
    "sg:province":"Danmark",
    "wof:name":"HK, Skive/Nyk\u00f8bing M. Afd.",
    "wof:placetype":"venue"
},
  "geometry": {"coordinates":[-114.0768203735,46.4432411194],"type":"Point"}
}