{
  "type": "Feature",
  "properties": {
    "addr:full":"Brandbjergvej 12  Jelling Danmark 7300",
    "addr:housenumber":"12",
    "addr:postcode":"7300",
    "addr:street":"Brandbjergvej",
    "iso:country":"DK",
    "sg:address":"Brandbjergvej 12 ",
    "sg:city":"Jelling",
    "sg:classifiers":[
        {
            "category":"Professional",
            "subcategory":"Business Services",
            "type":"Services"
        }
    ],
    "sg:phone":"+45 75 87 15 00",
    "sg:postcode":"7300",
    "sg:province":"Danmark",
    "sg:tags":[
        "advice"
    ],
    "wof:name":"BRANDBJERG H\u00d8JSKOLE",
    "wof:placetype":"venue"
},
  "geometry": {"coordinates":[9.4753360748,55.7718315125],"type":"Point"}
}