{
  "type": "Feature",
  "properties": {
    "addr:full":"Lucernevej 79 Randers Danmark 8900",
    "addr:housenumber":"79",
    "addr:postcode":"8900",
    "addr:street":"Lucernevej",
    "iso:country":"DK",
    "sg:address":"Lucernevej 79",
    "sg:city":"Randers",
    "sg:orig_category":"Murermestre",
    "sg:phone":"+45 87 10 09 77",
    "sg:postcode":"8900",
    "sg:province":"Danmark",
    "wof:name":"Hedebo A/S",
    "wof:placetype":"venue"
},
  "geometry": {"coordinates":[10.0244436264,56.4835357666],"type":"Point"}
}