{
  "type": "Feature",
  "properties": {
    "iso:country":"DK",
    "sg:address":"v/ Tom Jensen, Karmstensvej 27",
    "sg:city":"\u00d8lstykke",
    "sg:orig_category":"Kulturelle foreninger",
    "sg:phone":"+45 47 17 72 49",
    "sg:postcode":"3650",
    "sg:province":"Danmark",
    "wof:name":"\u00d8lstykke Amat\u00f8rscene",
    "wof:placetype":"venue"
},
  "geometry": {"coordinates":[-109.33489990229999,40.3696899414],"type":"Point"}
}