{
  "type": "Feature",
  "properties": {
    "iso:country":"DK",
    "sg:address":"Vestergade 44",
    "sg:city":"K\u00f8ge",
    "sg:orig_category":"Glarmestre og glarmagere",
    "sg:phone":"+45 56 66 00 58",
    "sg:postcode":"4600",
    "sg:province":"Danmark",
    "wof:name":"K\u00f8ges Glarmester",
    "wof:placetype":"venue"
},
  "geometry": {"coordinates":[9.5455904007,56.1682090759],"type":"Point"}
}