{
  "type": "Feature",
  "properties": {
    "addr:full":"Badehusvej 16 Aalborg Danmark 9000",
    "addr:housenumber":"16",
    "addr:postcode":"9000",
    "addr:street":"Badehusvej",
    "iso:country":"DK",
    "sg:address":"Badehusvej 16",
    "sg:city":"Aalborg",
    "sg:orig_category":"Advokater",
    "sg:phone":"+45 70 15 10 00",
    "sg:postcode":"9000",
    "sg:province":"Danmark",
    "wof:name":"Hjulmand & Kaptain, Advokatfirma",
    "wof:placetype":"venue"
},
  "geometry": {"coordinates":[9.9135150909,57.0527076721],"type":"Point"}
}