{
  "type": "Feature",
  "properties": {
    "addr:full":"\u00c5lholm Parkvej 17 Nysted Danmark 4880",
    "addr:housenumber":"17",
    "addr:postcode":"4880",
    "addr:street":"Aalholm Parkvej",
    "iso:country":"DK",
    "sg:address":"\u00c5lholm Parkvej 17",
    "sg:city":"Nysted",
    "sg:orig_category":"Museer",
    "sg:phone":"+45 54 87 19 11",
    "sg:postcode":"4880",
    "sg:province":"Danmark",
    "wof:name":"Aalholm Automobil Museum",
    "wof:placetype":"venue"
},
  "geometry": {"coordinates":[11.7067317963,54.6677474976],"type":"Point"}
}