{
  "type": "Feature",
  "properties": {
    "iso:country":"DK",
    "sg:address":"Skovbakken 41",
    "sg:city":"Esbjerg N",
    "sg:orig_category":"Non-Classified Establishments",
    "sg:phone":"+45 75 12 86 73",
    "sg:postcode":"6715",
    "sg:province":"Danmark",
    "wof:name":"Westoil A/S",
    "wof:placetype":"venue"
},
  "geometry": {"coordinates":[8.4462013245,55.5038032532],"type":"Point"}
}