{
  "type": "Feature",
  "properties": {
    "addr:full":"S\u00f8nderbakken 9, Glud Horsens Danmark 8700",
    "addr:housenumber":"9",
    "addr:postcode":"8700",
    "addr:street":"Sonderbakken;Glud",
    "iso:country":"DK",
    "sg:address":"S\u00f8nderbakken 9, Glud",
    "sg:city":"Horsens",
    "sg:orig_category":"Slagterier",
    "sg:phone":"+45 75 68 74 95",
    "sg:postcode":"8700",
    "sg:province":"Danmark",
    "wof:name":"Glud Slagtehus",
    "wof:placetype":"venue"
},
  "geometry": {"coordinates":[9.8432445526,55.8621063232],"type":"Point"}
}