{
  "type": "Feature",
  "properties": {
    "addr:full":"Trunderup Dongsvej 21 Kv\u00e6rndrup Danmark 5772",
    "addr:housenumber":"21",
    "addr:postcode":"5772",
    "addr:street":"Trunderup Dongsvej",
    "iso:country":"DK",
    "sg:address":"Trunderup Dongsvej 21",
    "sg:city":"Kv\u00e6rndrup",
    "sg:orig_category":"Murermestre",
    "sg:phone":"+45 62 29 20 57",
    "sg:postcode":"5772",
    "sg:province":"Danmark",
    "wof:name":"Trunderup Murer Forretning",
    "wof:placetype":"venue"
},
  "geometry": {"coordinates":[10.5854816437,55.1817588806],"type":"Point"}
}