{
  "type": "Feature",
  "properties": {
    "iso:country":"DK",
    "sg:address":"Skomagergade 9",
    "sg:city":"Roskilde",
    "sg:orig_category":"Konfekture",
    "sg:phone":"+45 46 35 24 93",
    "sg:postcode":"4000",
    "sg:province":"Danmark",
    "wof:name":"Frellsen, I. M.",
    "wof:placetype":"venue"
},
  "geometry": {"coordinates":[12.0788421631,55.6407623291],"type":"Point"}
}