{
  "type": "Feature",
  "properties": {
    "addr:full":"Skovbrynet 6, Sahl Vinderup Danmark 7830",
    "addr:housenumber":"6",
    "addr:postcode":"7830",
    "addr:street":"Skovbrynet;Sahl",
    "iso:country":"DK",
    "sg:address":"Skovbrynet 6, Sahl",
    "sg:city":"Vinderup",
    "sg:orig_category":"Plejehjem",
    "sg:phone":"+45 97 44 14 46",
    "sg:postcode":"7830",
    "sg:province":"Danmark",
    "wof:name":"Sahl Hvilehjem",
    "wof:placetype":"venue"
},
  "geometry": {"coordinates":[8.7796897888,56.482635498],"type":"Point"}
}