{
  "type": "Feature",
  "properties": {
    "iso:country":"DK",
    "sg:address":"Cypresvej 2",
    "sg:city":"Herning",
    "sg:orig_category":"Autoelektro",
    "sg:phone":"+45 97 22 44 99",
    "sg:postcode":"7400",
    "sg:province":"Danmark",
    "wof:name":"TJ Auto-El I/S",
    "wof:placetype":"venue"
},
  "geometry": {"coordinates":[8.9328918457,56.133190155],"type":"Point"}
}