{
  "type": "Feature",
  "properties": {
    "addr:full":"Fmd.: Stig Carlsen, Klaptoftvej 1, Velling Ringk\u00f8bing Danmark 6950",
    "addr:housenumber":"1",
    "addr:postcode":"6950",
    "addr:street":"Fmd. Stig Carlsen Klaptoftvej",
    "iso:country":"DK",
    "sg:address":"Fmd.: Stig Carlsen, Klaptoftvej 1, Velling",
    "sg:city":"Ringk\u00f8bing",
    "sg:orig_category":"Hobbybetonede foreninger",
    "sg:phone":"+45 97 32 37 66",
    "sg:postcode":"6950",
    "sg:province":"Danmark",
    "wof:name":"Ringk\u00f8bing og Omegns Fugleforening",
    "wof:placetype":"venue"
},
  "geometry": {"coordinates":[8.2507953644,56.0878334045],"type":"Point"}
}