{
  "type": "Feature",
  "properties": {
    "addr:full":"Odensevej 12, Gelsted Gelsted Danmark 5591",
    "addr:housenumber":"12",
    "addr:postcode":"5591",
    "addr:street":"Odensevej",
    "iso:country":"DK",
    "sg:address":"Odensevej 12, Gelsted",
    "sg:city":"Gelsted",
    "sg:orig_category":"Autoreparation og -service",
    "sg:phone":"+45 64 49 13 40",
    "sg:postcode":"5591",
    "sg:province":"Danmark",
    "wof:name":"Q8 Gelsted Motorkompagni",
    "wof:placetype":"venue"
},
  "geometry": {"coordinates":[9.9734048843,55.3995094299],"type":"Point"}
}