{
  "type": "Feature",
  "properties": {
    "addr:full":"Fmd.: Svend Hansen, Gedser Landevej 67 Gedser Danmark 4874",
    "addr:housenumber":"67",
    "addr:postcode":"4874",
    "addr:street":"Gedser Landevej",
    "iso:country":"DK",
    "sg:address":"Fmd.: Svend Hansen, Gedser Landevej 67",
    "sg:city":"Gedser",
    "sg:orig_category":"Hobbybetonede foreninger",
    "sg:phone":"+45 54 17 97 13",
    "sg:postcode":"4874",
    "sg:province":"Danmark",
    "wof:name":"Sydfalster Frim\u00e6rkeklub",
    "wof:placetype":"venue"
},
  "geometry": {"coordinates":[11.9617109299,54.600353241],"type":"Point"}
}