{
  "type": "Feature",
  "properties": {
    "iso:country":"DK",
    "sg:address":"Skovhavevej 9 A, Sdr. H\u00f8jrup",
    "sg:city":"Ringe",
    "sg:orig_category":"Kirker",
    "sg:postcode":"5750",
    "sg:province":"Danmark",
    "wof:name":"Sdr. H\u00f8jrup Kirke",
    "wof:placetype":"venue"
},
  "geometry": {"coordinates":[10.4781074524,55.2356643677],"type":"Point"}
}