{
  "type": "Feature",
  "properties": {
    "addr:full":"Frederikssundsvej 27 K\u00f8benhavn NV Danmark 2400",
    "addr:housenumber":"27",
    "addr:postcode":"2400",
    "addr:street":"Frederikssundsvej",
    "iso:country":"DK",
    "sg:address":"Frederikssundsvej 27",
    "sg:city":"K\u00f8benhavn NV",
    "sg:orig_category":"Glarmestre og glarmagere",
    "sg:phone":"+45 38 19 45 10",
    "sg:postcode":"2400",
    "sg:province":"Danmark",
    "wof:name":"Nord-Vest Glarmesteren",
    "wof:placetype":"venue"
},
  "geometry": {"coordinates":[-117.02272033689999,38.5024604797],"type":"Point"}
}