{
  "type": "Feature",
  "properties": {
    "addr:full":"Store Torvegade 9 R\u00f8nne Danmark 3700",
    "addr:housenumber":"9",
    "addr:postcode":"3700",
    "addr:street":"Store Torvegade",
    "iso:country":"DK",
    "sg:address":"Store Torvegade 9",
    "sg:city":"R\u00f8nne",
    "sg:orig_category":"Sko",
    "sg:phone":"+45 56 95 08 38",
    "sg:postcode":"3700",
    "sg:province":"Danmark",
    "wof:name":"Skoringen",
    "wof:placetype":"venue"
},
  "geometry": {"coordinates":[14.6975498199,55.0993003845],"type":"Point"}
}