{
  "type": "Feature",
  "properties": {
    "addr:full":"Sortedam Dossering 7 C K\u00f8benhavn N Danmark 2200",
    "addr:housenumber":"7 c",
    "addr:postcode":"2200",
    "addr:street":"Sortedam Dossering;Kobenhavn N Danmark",
    "iso:country":"DK",
    "sg:address":"Sortedam Dossering 7 C",
    "sg:city":"K\u00f8benhavn N",
    "sg:orig_category":"Antikviteter",
    "sg:phone":"+45 35 35 04 20",
    "sg:postcode":"2200",
    "sg:province":"Danmark",
    "wof:name":"Antikhallen",
    "wof:placetype":"venue"
},
  "geometry": {"coordinates":[-76.4168395996,37.452419281],"type":"Point"}
}