{
  "type": "Feature",
  "properties": {
    "addr:full":"Sundbyvej 30, Biersted Aabybro Danmark 9440",
    "addr:housenumber":"30",
    "addr:postcode":"9440",
    "addr:street":"Sundbyvej;Biersted",
    "iso:country":"DK",
    "sg:address":"Sundbyvej 30, Biersted",
    "sg:city":"Aabybro",
    "sg:orig_category":"Ungdomsklubber",
    "sg:postcode":"9440",
    "sg:province":"Danmark",
    "wof:name":"Biersted Ungdomsklub",
    "wof:placetype":"venue"
},
  "geometry": {"coordinates":[9.7341356277,57.1588287354],"type":"Point"}
}