{
  "type": "Feature",
  "properties": {
    "addr:full":"Vestergade 59 Odense C Danmark 5000",
    "addr:housenumber":"59",
    "addr:postcode":"5000",
    "addr:street":"Vestergade",
    "iso:country":"DK",
    "sg:address":"Vestergade 59",
    "sg:city":"Odense C",
    "sg:orig_category":"Boghandlere",
    "sg:phone":"+45 66 11 40 33",
    "sg:postcode":"5000",
    "sg:province":"Danmark",
    "wof:name":"Bog & ide",
    "wof:placetype":"venue"
},
  "geometry": {"coordinates":[10.3835468292,55.3949813843],"type":"Point"}
}