{
  "type": "Feature",
  "properties": {
    "iso:country":"DK",
    "sg:address":"Overgaden Neden Vandet 43",
    "sg:city":"K\u00f8benhavn",
    "sg:classifiers":[
        {
            "category":"Restaurant",
            "type":"Food & Drink"
        }
    ],
    "sg:phone":"+45 32 57 86 20",
    "sg:postcode":"1414",
    "sg:province":"Danmark",
    "wof:name":"St\u00e6rkodder, Restaurant",
    "wof:placetype":"venue"
},
  "geometry": {"coordinates":[12.5897798538,55.6723518372],"type":"Point"}
}