{
  "type": "Feature",
  "properties": {
    "iso:country":"DK",
    "sg:address":"Brog\u00e5rdsvej 90, Fangel",
    "sg:city":"Odense S",
    "sg:classifiers":[
        {
            "category":"Restaurant",
            "type":"Food & Drink"
        }
    ],
    "sg:phone":"+45 65 96 12 60",
    "sg:postcode":"5260",
    "sg:province":"Danmark",
    "wof:name":"Ny Kratholm, Det",
    "wof:placetype":"venue"
},
  "geometry": {"coordinates":[10.3157806396,55.3122825623],"type":"Point"}
}