{
  "type": "Feature",
  "properties": {
    "addr:full":"S\u00f8ndergade 27 Kolding Danmark 6000",
    "addr:housenumber":"27",
    "addr:postcode":"6000",
    "addr:street":"Sondergade",
    "iso:country":"DK",
    "sg:address":"S\u00f8ndergade 27",
    "sg:city":"Kolding",
    "sg:orig_category":"Cykler",
    "sg:phone":"+45 75 52 08 67",
    "sg:postcode":"6000",
    "sg:province":"Danmark",
    "wof:name":"St\u00e6chmann",
    "wof:placetype":"venue"
},
  "geometry": {"coordinates":[9.4728250504,55.4869728088],"type":"Point"}
}