{
  "type": "Feature",
  "properties": {
    "iso:country":"DK",
    "sg:address":"Vestervej 3",
    "sg:city":"Grenaa",
    "sg:orig_category":"Voksenuddannelsescentre",
    "sg:phone":"+45 87 58 21 00",
    "sg:postcode":"8500",
    "sg:province":"Danmark",
    "sg:website":"www.grenaa-vuc.dk",
    "wof:name":"VUC Grenaa",
    "wof:placetype":"venue"
},
  "geometry": {"coordinates":[10.8691959381,56.4143409729],"type":"Point"}
}