{
  "type": "Feature",
  "properties": {
    "addr:full":"Storegade 45 Haderslev Danmark 6100",
    "addr:housenumber":"45",
    "addr:postcode":"6100",
    "addr:street":"Storegade",
    "iso:country":"DK",
    "sg:address":"Storegade 45",
    "sg:city":"Haderslev",
    "sg:orig_category":"Pizzeriaer",
    "sg:phone":"+45 74 53 30 39",
    "sg:postcode":"6100",
    "sg:province":"Danmark",
    "wof:name":"Mama - Mia, Pizzeria",
    "wof:placetype":"venue"
},
  "geometry": {"coordinates":[9.4814538956,55.252204895],"type":"Point"}
}