{
  "type": "Feature",
  "properties": {
    "iso:country":"DK",
    "sg:address":"Vestre Havnevej 16",
    "sg:city":"Kalundborg",
    "sg:orig_category":"Alternativ behandling",
    "sg:phone":"+45 59 51 22 89",
    "sg:postcode":"4400",
    "sg:province":"Danmark",
    "wof:name":"Dannenberg, Lis",
    "wof:placetype":"venue"
},
  "geometry": {"coordinates":[11.0812969208,55.6786727905],"type":"Point"}
}