{
  "type": "Feature",
  "properties": {
    "iso:country":"DK",
    "sg:address":"Vestre Lindeskov 167",
    "sg:city":"Glostrup",
    "sg:orig_category":"Skadeservice",
    "sg:phone":"+45 20 71 60 71",
    "sg:postcode":"2600",
    "sg:province":"Danmark",
    "wof:name":"H. R. H.",
    "wof:placetype":"venue"
},
  "geometry": {"coordinates":[12.414730072,55.6826782227],"type":"Point"}
}