{
  "type": "Feature",
  "properties": {
    "addr:full":"H\u00f8jen 7, Ravnsh\u00f8j Frederikshavn Danmark 9900",
    "addr:housenumber":"7",
    "addr:postcode":"9900",
    "addr:street":"Hojen",
    "iso:country":"DK",
    "sg:address":"H\u00f8jen 7, Ravnsh\u00f8j",
    "sg:city":"Frederikshavn",
    "sg:orig_category":"Murermestre",
    "sg:phone":"+45 98 48 41 74",
    "sg:postcode":"9900",
    "sg:province":"Danmark",
    "sg:website":"www.carsten-nielsen.dk",
    "wof:name":"Nielsen, Byggefirma Carsten",
    "wof:placetype":"venue"
},
  "geometry": {"coordinates":[10.5362997055,57.4396400452],"type":"Point"}
}