{
  "type": "Feature",
  "properties": {
    "addr:full":"Leder: Norma Nielsen, Vaarstvej 329 Gistrup Danmark 9260",
    "addr:housenumber":"329",
    "addr:postcode":"9260",
    "addr:street":"Nielsen Vaarstvej",
    "iso:country":"DK",
    "sg:address":"Leder: Norma Nielsen, Vaarstvej 329",
    "sg:city":"Gistrup",
    "sg:orig_category":"Lokalarkiver",
    "sg:phone":"+45 98 33 33 89",
    "sg:postcode":"9260",
    "sg:province":"Danmark",
    "wof:name":"Gunderup Sogns Lokalhistoriske Arkiv",
    "wof:placetype":"venue"
},
  "geometry": {"coordinates":[9.9942445755,56.9978294373],"type":"Point"}
}