{
  "type": "Feature",
  "properties": {
    "addr:full":"Resenvej 26 Skive Danmark 7800",
    "addr:housenumber":"26",
    "addr:postcode":"7800",
    "addr:street":"Resenvej",
    "iso:country":"DK",
    "sg:address":"Resenvej 26",
    "sg:city":"Skive",
    "sg:orig_category":"Autoreparation og -service",
    "sg:phone":"+45 97 52 02 99",
    "sg:postcode":"7800",
    "sg:province":"Danmark",
    "wof:name":"Johnsens Autoservice I/S",
    "wof:placetype":"venue"
},
  "geometry": {"coordinates":[9.0306100845,56.5722999573],"type":"Point"}
}