{
  "type": "Feature",
  "properties": {
    "iso:country":"DK",
    "sg:address":"Lerchenfeldvej 34",
    "sg:city":"Kalundborg",
    "sg:orig_category":"Handicapboliger",
    "sg:phone":"+45 59 55 56 00",
    "sg:postcode":"4400",
    "sg:province":"Danmark",
    "wof:name":"Trekl\u00f8veret",
    "wof:placetype":"venue"
},
  "geometry": {"coordinates":[11.110367775,55.6678543091],"type":"Point"}
}