{
  "type": "Feature",
  "properties": {
    "addr:full":"\u00d8stergade 10 Toftlund Danmark 6520",
    "addr:housenumber":"10",
    "addr:postcode":"6520",
    "addr:street":"Ostergade",
    "iso:country":"DK",
    "sg:address":"\u00d8stergade 10",
    "sg:city":"Toftlund",
    "sg:orig_category":"Pizzeriaer",
    "sg:phone":"+45 74 83 02 54",
    "sg:postcode":"6520",
    "sg:province":"Danmark",
    "wof:name":"Caf\u00e9 Aladdin",
    "wof:placetype":"venue"
},
  "geometry": {"coordinates":[9.0652418137,55.1923751831],"type":"Point"}
}