{
  "type": "Feature",
  "properties": {
    "addr:full":"Herlev Torv 8 Herlev Danmark 2730",
    "addr:housenumber":"8",
    "addr:postcode":"2730",
    "addr:street":"Herlev Torv",
    "iso:country":"DK",
    "sg:address":"Herlev Torv 8",
    "sg:city":"Herlev",
    "sg:orig_category":"Konfekture",
    "sg:phone":"+45 44 84 00 53",
    "sg:postcode":"2730",
    "sg:province":"Danmark",
    "wof:name":"Chokoland",
    "wof:placetype":"venue"
},
  "geometry": {"coordinates":[12.4394168854,55.7237854004],"type":"Point"}
}