{
  "type": "Feature",
  "properties": {
    "addr:full":"v/ Lillian Larsen, Vendbjerg 17, Nors Thisted Danmark 7700",
    "addr:housenumber":"17",
    "addr:postcode":"7700",
    "addr:street":"Vendbjerg;Nors",
    "iso:country":"DK",
    "sg:address":"v/ Lillian Larsen, Vendbjerg 17, Nors",
    "sg:city":"Thisted",
    "sg:orig_category":"Hobbybetonede foreninger",
    "sg:phone":"+45 97 98 16 26",
    "sg:postcode":"7700",
    "sg:province":"Danmark",
    "wof:name":"Hjemmenes Aften",
    "wof:placetype":"venue"
},
  "geometry": {"coordinates":[8.6919784546,56.9556121826],"type":"Point"}
}