{
  "type": "Feature",
  "properties": {
    "addr:full":"Kirkecenteret, Ellehammersvej 14 Vadum Danmark 9430",
    "addr:housenumber":"14",
    "addr:postcode":"9430",
    "addr:street":"Ellehammersvej",
    "iso:country":"DK",
    "sg:address":"Kirkecenteret, Ellehammersvej 14",
    "sg:city":"Vadum",
    "sg:orig_category":"Legestuer",
    "sg:phone":"+45 99 31 52 90",
    "sg:postcode":"9430",
    "sg:province":"Danmark",
    "wof:name":"Vadum Legestue",
    "wof:placetype":"venue"
},
  "geometry": {"coordinates":[9.8614330292,57.1187477112],"type":"Point"}
}