{
  "type": "Feature",
  "properties": {
    "addr:full":"Viby Ringvej 17, 2. Viby Danmark 8260",
    "addr:housenumber":"17 2",
    "addr:postcode":"8260",
    "addr:street":"Viby Ringvej",
    "iso:country":"DK",
    "sg:address":"Viby Ringvej 17, 2.",
    "sg:city":"Viby",
    "sg:orig_category":"Solcentre",
    "sg:phone":"+45 86 11 46 88",
    "sg:postcode":"8260",
    "sg:province":"Danmark",
    "wof:name":"Solsikke Sun",
    "wof:placetype":"venue"
},
  "geometry": {"coordinates":[10.1608419418,56.1292877197],"type":"Point"}
}