{
  "type": "Feature",
  "properties": {
    "iso:country":"DK",
    "sg:address":"Fmd.: Erik Villumsen, Arnborgvej 15, B\u00f8lling",
    "sg:city":"Skjern",
    "sg:orig_category":"Kirkelige foreninger",
    "sg:phone":"+45 97 36 88 08",
    "sg:postcode":"6900",
    "sg:province":"Danmark",
    "wof:name":"Indre Missions Samfund, B\u00f8lling",
    "wof:placetype":"venue"
},
  "geometry": {"coordinates":[8.492972374,55.9485740662],"type":"Point"}
}