{
  "type": "Feature",
  "properties": {
    "addr:full":"Skivevej 54 Holstebro Danmark 7500",
    "addr:housenumber":"54",
    "addr:postcode":"7500",
    "addr:street":"Skivevej",
    "iso:country":"DK",
    "sg:address":"Skivevej 54",
    "sg:city":"Holstebro",
    "sg:orig_category":"Solcentre",
    "sg:phone":"+45 97 40 64 65",
    "sg:postcode":"7500",
    "sg:province":"Danmark",
    "wof:name":"Sun-Tan",
    "wof:placetype":"venue"
},
  "geometry": {"coordinates":[8.6280050278,56.3682899475],"type":"Point"}
}