{
  "type": "Feature",
  "properties": {
    "addr:full":"Vestergade 44 Ranum Danmark 9681",
    "addr:housenumber":"44",
    "addr:postcode":"9681",
    "addr:street":"Vestergade",
    "iso:country":"DK",
    "sg:address":"Vestergade 44",
    "sg:city":"Ranum",
    "sg:orig_category":"\u00c3\u02dcvrige skoler",
    "sg:phone":"+45 98 67 69 67",
    "sg:postcode":"9681",
    "sg:province":"Danmark",
    "sg:website":"www.kunstskole.dk",
    "wof:name":"Ranum Kunstskole",
    "wof:placetype":"venue"
},
  "geometry": {"coordinates":[9.2280731201,56.8972816467],"type":"Point"}
}