{
  "type": "Feature",
  "properties": {
    "addr:full":"Industrivej 4 Struer Danmark 7600",
    "addr:housenumber":"4",
    "addr:postcode":"7600",
    "addr:street":"Industrivej",
    "iso:country":"DK",
    "sg:address":"Industrivej 4",
    "sg:city":"Struer",
    "sg:orig_category":"Metalvarefabrikker",
    "sg:phone":"+45 97 85 06 22",
    "sg:postcode":"7600",
    "sg:province":"Danmark",
    "wof:name":"Metalvarefabrikken Struer ApS",
    "wof:placetype":"venue"
},
  "geometry": {"coordinates":[8.5819997787,56.4872703552],"type":"Point"}
}