{
  "type": "Feature",
  "properties": {
    "addr:full":"Norgeskajen 2 Hirtshals Danmark 9850",
    "addr:housenumber":"2",
    "addr:postcode":"9850",
    "addr:street":"Norgeskajen",
    "iso:country":"DK",
    "sg:address":"Norgeskajen 2",
    "sg:city":"Hirtshals",
    "sg:classifiers":[
        {
            "category":"Museum",
            "type":"Entertainment"
        }
    ],
    "sg:phone":"+45 98 94 17 88",
    "sg:postcode":"9850",
    "sg:province":"Danmark",
    "sg:tags":[
        "og",
        "skat",
        "told"
    ],
    "wof:name":"Toldkontrollen i Hirtshals.",
    "wof:placetype":"venue"
},
  "geometry": {"coordinates":[9.9599866867,57.5884933472],"type":"Point"}
}