{
  "type": "Feature",
  "properties": {
    "addr:full":"Fmd.: Claus Holm S\u00f8rensen, Hadsundvej 1 C Aalborg Danmark 9000",
    "addr:housenumber":"1 c",
    "addr:postcode":"9000",
    "addr:street":"Hadsundvej",
    "iso:country":"DK",
    "sg:address":"Fmd.: Claus Holm S\u00f8rensen, Hadsundvej 1 C",
    "sg:city":"Aalborg",
    "sg:orig_category":"Hobbybetonede foreninger",
    "sg:phone":"+45 20 26 61 19",
    "sg:postcode":"9000",
    "sg:province":"Danmark",
    "wof:name":"Aalborg Akvarieforening",
    "wof:placetype":"venue"
},
  "geometry": {"coordinates":[9.9162902832,57.0493545532],"type":"Point"}
}