{
  "type": "Feature",
  "properties": {
    "addr:full":"Vestcentret, Venusvej 10 Fredericia Danmark 7000",
    "addr:housenumber":"10",
    "addr:postcode":"7000",
    "addr:street":"Venusvej",
    "iso:country":"DK",
    "sg:address":"Vestcentret, Venusvej 10",
    "sg:city":"Fredericia",
    "sg:orig_category":"Posthuse",
    "sg:phone":"+45 79 43 50 00",
    "sg:postcode":"7000",
    "sg:province":"Danmark",
    "wof:name":"Post Danmark, Posthuset i Vestcentret",
    "wof:placetype":"venue"
},
  "geometry": {"coordinates":[9.7591047287,55.566368103],"type":"Point"}
}