{
  "type": "Feature",
  "properties": {
    "addr:full":"\u00d8stervangsvej 3 Randers Danmark 8900",
    "addr:housenumber":"3",
    "addr:postcode":"8900",
    "addr:street":"Ostervangsvej",
    "iso:country":"DK",
    "sg:address":"\u00d8stervangsvej 3",
    "sg:city":"Randers",
    "sg:orig_category":"Rejsebureauer",
    "sg:phone":"+45 86 40 77 36",
    "sg:postcode":"8900",
    "sg:province":"Danmark",
    "sg:website":"www.france-vacances.dk",
    "wof:name":"France Vacances",
    "wof:placetype":"venue"
},
  "geometry": {"coordinates":[10.0473146439,56.4671134949],"type":"Point"}
}