{
  "type": "Feature",
  "properties": {
    "addr:full":"Danmarksgade 66, o.g. Frederikshavn Danmark 9900",
    "addr:housenumber":"66",
    "addr:postcode":"o.g.;9900",
    "addr:street":"Danmarksgade",
    "iso:country":"DK",
    "sg:address":"Danmarksgade 66, o.g.",
    "sg:city":"Frederikshavn",
    "sg:orig_category":"Optikere",
    "sg:phone":"+45 98 42 32 44",
    "sg:postcode":"9900",
    "sg:province":"Danmark",
    "wof:name":"Brilleexperten - Otto J\u00f8rgensen",
    "wof:placetype":"venue"
},
  "geometry": {"coordinates":[10.5362997055,57.4396400452],"type":"Point"}
}