{
  "type": "Feature",
  "properties": {
    "addr:full":"Fruerhusvej 21, Solbjerg B\u00e6lum Danmark 9574",
    "addr:housenumber":"21",
    "addr:postcode":"9574",
    "addr:street":"Fruerhusvej",
    "iso:country":"DK",
    "sg:address":"Fruerhusvej 21, Solbjerg",
    "sg:city":"B\u00e6lum",
    "sg:orig_category":"Aktivitetscentre",
    "sg:phone":"+45 99 82 85 30",
    "sg:postcode":"9574",
    "sg:province":"Danmark",
    "wof:name":"Servicecenter Solbjerg",
    "wof:placetype":"venue"
},
  "geometry": {"coordinates":[10.140458107,56.8097114563],"type":"Point"}
}