{
  "type": "Feature",
  "properties": {
    "addr:full":"Pr\u00e6stbrovej 82 Erslev Danmark 7950",
    "addr:housenumber":"82",
    "addr:postcode":"7950",
    "addr:street":"Praestbrovej",
    "iso:country":"DK",
    "sg:address":"Pr\u00e6stbrovej 82",
    "sg:city":"Erslev",
    "sg:orig_category":"Fodplejere",
    "sg:phone":"+45 97 74 12 32",
    "sg:postcode":"7950",
    "sg:province":"Danmark",
    "wof:name":"St\u00f8vlb\u00e6k, Lise",
    "wof:placetype":"venue"
},
  "geometry": {"coordinates":[8.7604703903,56.8275146484],"type":"Point"}
}