{
  "type": "Feature",
  "properties": {
    "iso:country":"DK",
    "sg:address":"Div.chef: Mogens Gerstr\u00f8m, Nyp\u00f8lsgade 12, Nyp\u00f8l",
    "sg:city":"Sydals",
    "sg:orig_category":"Spejderkorps",
    "sg:phone":"+45 74 40 41 45",
    "sg:postcode":"6470",
    "sg:province":"Danmark",
    "wof:name":"KFUM-spejderne, Als Division",
    "wof:placetype":"venue"
},
  "geometry": {"coordinates":[9.8924627304,54.9105377197],"type":"Point"}
}