{
  "type": "Feature",
  "properties": {
    "addr:full":"R\u00f8nnevej 58, Bodilsker Nex\u00f8 Danmark 3730",
    "addr:housenumber":"58",
    "addr:postcode":"3730",
    "addr:street":"Ronnevej",
    "iso:country":"DK",
    "sg:address":"R\u00f8nnevej 58, Bodilsker",
    "sg:city":"Nex\u00f8",
    "sg:orig_category":"Sten og grus",
    "sg:phone":"+45 56 48 84 16",
    "sg:postcode":"3730",
    "sg:province":"Danmark",
    "wof:name":"Bornholms Sandstensbrud",
    "wof:placetype":"venue"
},
  "geometry": {"coordinates":[15.1096076965,55.0267219543],"type":"Point"}
}