{
  "type": "Feature",
  "properties": {
    "addr:full":"Marinus B\u00f8dkers Vej 17 Frederikshavn Danmark 9900",
    "addr:housenumber":"17",
    "addr:postcode":"9900",
    "addr:street":"Bodkers Vej",
    "iso:country":"DK",
    "sg:address":"Marinus B\u00f8dkers Vej 17",
    "sg:city":"Frederikshavn",
    "sg:orig_category":"Murermestre",
    "sg:phone":"+45 98 43 00 90",
    "sg:postcode":"9900",
    "sg:province":"Danmark",
    "sg:website":"www.damgaard-olesen.dk",
    "wof:name":"Svend Damgaard Olesen A/S",
    "wof:placetype":"venue"
},
  "geometry": {"coordinates":[10.526599884,57.4167442322],"type":"Point"}
}