{
  "type": "Feature",
  "properties": {
    "addr:full":"\u00d8stergade 9B Hadsten Danmark 8370",
    "addr:housenumber":"9b",
    "addr:postcode":"8370",
    "addr:street":"Ostergade",
    "iso:country":"DK",
    "sg:address":"\u00d8stergade 9B",
    "sg:city":"Hadsten",
    "sg:orig_category":"Politi",
    "sg:phone":"+45 86 98 25 50",
    "sg:postcode":"8370",
    "sg:province":"Danmark",
    "wof:name":"Politikontoret i Hadsten",
    "wof:placetype":"venue"
},
  "geometry": {"coordinates":[10.0474405289,56.3277130127],"type":"Point"}
}