{
  "type": "Feature",
  "properties": {
    "addr:full":"Storskovvej 32 Dronninglund Danmark 9330",
    "addr:housenumber":"32",
    "addr:postcode":"9330",
    "addr:street":"Storskovvej",
    "iso:country":"DK",
    "sg:address":"Storskovvej 32",
    "sg:city":"Dronninglund",
    "sg:orig_category":"Murermestre",
    "sg:phone":"+45 98 86 16 37",
    "sg:postcode":"9330",
    "sg:province":"Danmark",
    "wof:name":"Jensen A/S, Ove J.",
    "wof:placetype":"venue"
},
  "geometry": {"coordinates":[10.2782526016,57.2053642273],"type":"Point"}
}