{
  "type": "Feature",
  "properties": {
    "addr:full":"Gl. \u00c5lbovej 30, Stenderup S\u00f8nder Stenderup Danmark 6092",
    "addr:housenumber":"30",
    "addr:postcode":"6092",
    "addr:street":"Aalbovej",
    "iso:country":"DK",
    "sg:address":"Gl. \u00c5lbovej 30, Stenderup",
    "sg:city":"S\u00f8nder Stenderup",
    "sg:orig_category":"Campingpladser",
    "sg:phone":"+45 75 57 11 16",
    "sg:postcode":"6092",
    "sg:province":"Danmark",
    "wof:name":"Gl. \u00c5lbo Camping",
    "wof:placetype":"venue"
},
  "geometry": {"coordinates":[9.6103696823,55.4608459473],"type":"Point"}
}