{
  "type": "Feature",
  "properties": {
    "iso:country":"DK",
    "sg:address":"Kirkebjerg Alle 154",
    "sg:city":"Br\u00f8ndby",
    "sg:orig_category":"Konservatorer",
    "sg:phone":"+45 43 96 82 09",
    "sg:postcode":"2605",
    "sg:province":"Danmark",
    "wof:name":"Buch, N. O. Funder",
    "wof:placetype":"venue"
},
  "geometry": {"coordinates":[12.4045686722,55.6468238831],"type":"Point"}
}