{
  "type": "Feature",
  "properties": {
    "addr:full":"v/ Ole Larsen, Kirkestien 7, Gl. Kalvehave Kalvehave Danmark 4771",
    "addr:housenumber":"7",
    "addr:postcode":"4771",
    "addr:street":"Kirkestien;Gl. Kalvehave",
    "iso:country":"DK",
    "sg:address":"v/ Ole Larsen, Kirkestien 7, Gl. Kalvehave",
    "sg:city":"Kalvehave",
    "sg:orig_category":"Havne",
    "sg:phone":"+45 55 38 88 07",
    "sg:postcode":"4771",
    "sg:province":"Danmark",
    "wof:name":"Gl. Kalvehave Havn",
    "wof:placetype":"venue"
},
  "geometry": {"coordinates":[12.1613817215,54.9965782166],"type":"Point"}
}