{
  "type": "Feature",
  "properties": {
    "addr:full":"Strandvej 13, Glyng\u00f8re Roslev Danmark 7870",
    "addr:housenumber":"13",
    "addr:postcode":"7870",
    "addr:street":"Strandvej;Glyngore",
    "iso:country":"DK",
    "sg:address":"Strandvej 13, Glyng\u00f8re",
    "sg:city":"Roslev",
    "sg:orig_category":"Distriktsbiblioteker",
    "sg:phone":"+45 99 76 31 87",
    "sg:postcode":"7870",
    "sg:province":"Danmark",
    "wof:name":"Glyng\u00f8re Bibliotek",
    "wof:placetype":"venue"
},
  "geometry": {"coordinates":[8.8715353012,56.7570304871],"type":"Point"}
}