{
  "type": "Feature",
  "properties": {
    "addr:full":"Vangevej 9 Lemvig Danmark 7620",
    "addr:housenumber":"9",
    "addr:postcode":"7620",
    "addr:street":"Vangevej",
    "iso:country":"DK",
    "sg:address":"Vangevej 9",
    "sg:city":"Lemvig",
    "sg:orig_category":"Slagterier",
    "sg:phone":"+45 97 82 17 18",
    "sg:postcode":"7620",
    "sg:province":"Danmark",
    "wof:name":"Lemvig Kreaturslagteri",
    "wof:placetype":"venue"
},
  "geometry": {"coordinates":[8.2954397202,56.546169281],"type":"Point"}
}