{
  "type": "Feature",
  "properties": {
    "addr:full":"Fmd.: Peder Tovgaard, R\u00e6veh\u00f8jen 6 Viborg Danmark 8800",
    "addr:housenumber":"6",
    "addr:postcode":"8800",
    "addr:street":"Raevehojen",
    "iso:country":"DK",
    "sg:address":"Fmd.: Peder Tovgaard, R\u00e6veh\u00f8jen 6",
    "sg:city":"Viborg",
    "sg:orig_category":"Soldaterforeninger",
    "sg:phone":"+45 86 67 27 00",
    "sg:postcode":"8800",
    "sg:province":"Danmark",
    "wof:name":"Garderforeningen for Viborg og Omegn",
    "wof:placetype":"venue"
},
  "geometry": {"coordinates":[9.4071502686,56.452671051],"type":"Point"}
}