{
  "type": "Feature",
  "properties": {
    "addr:full":"H. P. \u00d8rums Gade 7 K\u00f8benhavn \u00d8 Danmark 2100",
    "addr:housenumber":"7",
    "addr:postcode":"2100",
    "addr:street":"H.;Orums Gade;O",
    "iso:country":"DK",
    "sg:address":"H. P. \u00d8rums Gade 7",
    "sg:city":"K\u00f8benhavn \u00d8",
    "sg:orig_category":"Blomsterhandlere",
    "sg:phone":"+45 40 41 94 84",
    "sg:postcode":"2100",
    "sg:province":"Danmark",
    "wof:name":"Fru Hansens K\u00e6lder I/S",
    "wof:placetype":"venue"
},
  "geometry": {"coordinates":[-80.0050125122,35.9546585083],"type":"Point"}
}