{
  "type": "Feature",
  "properties": {
    "iso:country":"DK",
    "sg:address":"Priorgade 5",
    "sg:city":"Nibe",
    "sg:orig_category":"Malermestre",
    "sg:phone":"+45 98 35 37 01",
    "sg:postcode":"9240",
    "sg:province":"Danmark",
    "wof:name":"Nibe Malerforretning",
    "wof:placetype":"venue"
},
  "geometry": {"coordinates":[9.6340017319,56.9824829102],"type":"Point"}
}