{
  "type": "Feature",
  "properties": {
    "iso:country":"DK",
    "sg:address":"K\u00e6rlundsvej 25",
    "sg:city":"Aalborg",
    "sg:orig_category":"Revisorer",
    "sg:phone":"+45 98 16 45 00",
    "sg:postcode":"9000",
    "sg:province":"Danmark",
    "wof:name":"Norddan, Revisorgruppen",
    "wof:placetype":"venue"
},
  "geometry": {"coordinates":[9.9127464294,57.0387191772],"type":"Point"}
}