{
  "type": "Feature",
  "properties": {
    "addr:full":"Birthevej 7, M\u00f8rdrup, Postboks 43 Esperg\u00e6rde Danmark 3060",
    "addr:housenumber":"7;43",
    "addr:postcode":"3060",
    "addr:street":"Birthevej;Postboks",
    "iso:country":"DK",
    "sg:address":"Birthevej 7, M\u00f8rdrup, Postboks 43",
    "sg:city":"Esperg\u00e6rde",
    "sg:classifiers":[
        {
            "category":"Professional",
            "subcategory":"Business Services",
            "type":"Services"
        }
    ],
    "sg:phone":"+45 49 13 42 11",
    "sg:postcode":"3060",
    "sg:province":"Danmark",
    "sg:tags":[
        "import",
        "vin"
    ],
    "sg:website":"www.nwi.dk",
    "wof:name":"Noble Wine International ApS",
    "wof:placetype":"venue"
},
  "geometry": {"coordinates":[11.6512403488,47.8390617371],"type":"Point"}
}