{
  "type": "Feature",
  "properties": {
    "addr:full":"D\u00e6mningen 2, Nustrup Vojens Danmark 6500",
    "addr:housenumber":"2",
    "addr:postcode":"6500",
    "addr:street":"Daemningen;Nustrup",
    "iso:country":"DK",
    "sg:address":"D\u00e6mningen 2, Nustrup",
    "sg:city":"Vojens",
    "sg:orig_category":"Apoteker og -udsalg",
    "sg:phone":"+45 74 87 11 07",
    "sg:postcode":"6500",
    "sg:province":"Danmark",
    "wof:name":"H\u00e5ndk\u00f8bsudsalg - Gram Apotek",
    "wof:placetype":"venue"
},
  "geometry": {"coordinates":[9.2987146378,55.2457237244],"type":"Point"}
}