{
  "type": "Feature",
  "properties": {
    "addr:full":"\u00d8rslevvej 18 Vordingborg Danmark 4760",
    "addr:housenumber":"18",
    "addr:postcode":"4760",
    "addr:street":"Orslevvej",
    "iso:country":"DK",
    "sg:address":"\u00d8rslevvej 18",
    "sg:city":"Vordingborg",
    "sg:orig_category":"Hudpleje",
    "sg:phone":"+45 55 98 59 08",
    "sg:postcode":"4760",
    "sg:province":"Danmark",
    "wof:name":"Beaty for all Seasons",
    "wof:placetype":"venue"
},
  "geometry": {"coordinates":[11.9888210297,55.0421409607],"type":"Point"}
}