{
  "type": "Feature",
  "properties": {
    "iso:country":"DK",
    "sg:address":"Svanetorvet 1",
    "sg:city":"Nyk\u00f8bing",
    "sg:orig_category":"Blikkenslagere",
    "sg:phone":"+45 59 93 17 81",
    "sg:postcode":"4500",
    "sg:province":"Danmark",
    "wof:name":"Smedeg\u00e5rden Nyk\u00f8bing Sj\u00e6lland ApS",
    "wof:placetype":"venue"
},
  "geometry": {"coordinates":[16.09696,78.31598700000001],"type":"Point"}
}