{
  "type": "Feature",
  "properties": {
    "addr:full":"v/ Arne Jensen, Skovv\u00e6nget 14 Karise Danmark 4653",
    "addr:housenumber":"14",
    "addr:postcode":"4653",
    "iso:country":"DK",
    "sg:address":"v/ Arne Jensen, Skovv\u00e6nget 14",
    "sg:city":"Karise",
    "sg:orig_category":"Grundejerforeninger",
    "sg:phone":"+45 56 78 86 03",
    "sg:postcode":"4653",
    "sg:province":"Danmark",
    "wof:name":"Skovv\u00e6nget Grundejerforening",
    "wof:placetype":"venue"
},
  "geometry": {"coordinates":[12.1990203857,55.3030395508],"type":"Point"}
}