{
  "type": "Feature",
  "properties": {
    "addr:full":"Baunev\u00e6nget 20, N\u00f8debo Fredensborg Danmark 3480",
    "addr:housenumber":"20",
    "addr:postcode":"3480",
    "addr:street":"Baunevaenget",
    "iso:country":"DK",
    "sg:address":"Baunev\u00e6nget 20, N\u00f8debo",
    "sg:city":"Fredensborg",
    "sg:orig_category":"Revisorer",
    "sg:phone":"+45 48 48 18 44",
    "sg:postcode":"3480",
    "sg:province":"Danmark",
    "wof:name":"EC Regnskab & R\u00e5dgivning",
    "wof:placetype":"venue"
},
  "geometry": {"coordinates":[12.4020547867,55.9782943726],"type":"Point"}
}