{
  "type": "Feature",
  "properties": {
    "addr:full":"Fuglesangsalle 16 Vejen Danmark 6600",
    "addr:housenumber":"16",
    "addr:postcode":"6600",
    "addr:street":"Fuglesangsalle",
    "iso:country":"DK",
    "sg:address":"Fuglesangsalle 16",
    "sg:city":"Vejen",
    "sg:orig_category":"Vejmateriel",
    "sg:phone":"+45 79 96 23 23",
    "sg:postcode":"6600",
    "sg:province":"Danmark",
    "sg:website":"www.asfalt.dk",
    "wof:name":"NCC Danmark A/S, Asfalt",
    "wof:placetype":"venue"
},
  "geometry": {"coordinates":[9.1351976395,55.4625854492],"type":"Point"}
}