{
  "type": "Feature",
  "properties": {
    "addr:full":"Syrenvej 3, Bedsted L\u00f8gumkloster Danmark 6240",
    "addr:housenumber":"3",
    "addr:postcode":"6240",
    "addr:street":"Syrenvej",
    "iso:country":"DK",
    "sg:address":"Syrenvej 3, Bedsted",
    "sg:city":"L\u00f8gumkloster",
    "sg:orig_category":"Skolefritidsordninger",
    "sg:phone":"+45 73 77 78 77",
    "sg:postcode":"6240",
    "sg:province":"Danmark",
    "wof:name":"Skolefritidsordningen ved Bedsted Skole",
    "wof:placetype":"venue"
},
  "geometry": {"coordinates":[8.9515838623,55.058506012],"type":"Point"}
}