{
  "type": "Feature",
  "properties": {
    "addr:full":"v/ Cathrine Petersen, Engtoften 12, Tofterup Grindsted Danmark 7200",
    "addr:housenumber":"12",
    "addr:postcode":"7200",
    "addr:street":"Engtoften;Tofterup",
    "iso:country":"DK",
    "sg:address":"v/ Cathrine Petersen, Engtoften 12, Tofterup",
    "sg:city":"Grindsted",
    "sg:orig_category":"\u00c3\u2020ldreorganisationer og klubber",
    "sg:phone":"+45 75 33 71 39",
    "sg:postcode":"7200",
    "sg:province":"Danmark",
    "wof:name":"Starup Pensionistforening",
    "wof:placetype":"venue"
},
  "geometry": {"coordinates":[8.9288702011,55.7560272217],"type":"Point"}
}