{
  "type": "Feature",
  "properties": {
    "addr:full":"Strandvejen 203 Hellerup Danmark 2900",
    "addr:housenumber":"203",
    "addr:postcode":"2900",
    "addr:street":"Strandvejen",
    "iso:country":"DK",
    "sg:address":"Strandvejen 203",
    "sg:city":"Hellerup",
    "sg:classifiers":[
        {
            "category":"Restaurant",
            "type":"Food & Drink"
        }
    ],
    "sg:phone":"+45 39 62 27 67",
    "sg:postcode":"2900",
    "sg:province":"Danmark",
    "wof:name":"Via Appia",
    "wof:placetype":"venue"
},
  "geometry": {"coordinates":[12.5754089355,55.7375946045],"type":"Point"}
}