{
  "type": "Feature",
  "properties": {
    "addr:full":"Tingvejen 30 N, Skrydstrup Vojens Danmark 6500",
    "addr:housenumber":"30",
    "addr:postcode":"6500",
    "addr:street":"Tingvejen;N Skrydstrup",
    "iso:country":"DK",
    "sg:address":"Tingvejen 30 N, Skrydstrup",
    "sg:city":"Vojens",
    "sg:orig_category":"Etiketter",
    "sg:phone":"+45 74 54 09 33",
    "sg:postcode":"6500",
    "sg:province":"Danmark",
    "wof:name":"H & M Maskiner A/S",
    "wof:placetype":"venue"
},
  "geometry": {"coordinates":[9.2987146378,55.2457237244],"type":"Point"}
}