{
  "type": "Feature",
  "properties": {
    "addr:full":"v/Ole Kristensen, Jernbanegade 4 - 6 Frederikshavn Danmark 9900",
    "addr:housenumber":"4 6",
    "addr:postcode":"9900",
    "addr:street":"Jernbanegade",
    "iso:country":"DK",
    "sg:address":"v/Ole Kristensen, Jernbanegade 4 - 6",
    "sg:city":"Frederikshavn",
    "sg:orig_category":"Ambassader og konsulater",
    "sg:phone":"+45 99 21 22 23",
    "sg:postcode":"9900",
    "sg:province":"Danmark",
    "wof:name":"Konsulat for Finland",
    "wof:placetype":"venue"
},
  "geometry": {"coordinates":[10.5362997055,57.4396400452],"type":"Point"}
}