{
  "type": "Feature",
  "properties": {
    "iso:country":"DK",
    "sg:address":"Fmd.: Thorkild Jensen, Vorup\u00f8rvej 161",
    "sg:city":"Thisted",
    "sg:orig_category":"Borger- og beboerforeninger",
    "sg:phone":"+45 97 93 73 37",
    "sg:postcode":"7700",
    "sg:province":"Danmark",
    "sg:website":"www.hundborg-net.dk",
    "wof:name":"Hundborg og Omegns Borgerforening",
    "wof:placetype":"venue"
},
  "geometry": {"coordinates":[8.6919784546,56.9556121826],"type":"Point"}
}