{
  "type": "Feature",
  "properties": {
    "iso:country":"DK",
    "sg:address":"Sj\u00f8lund Gade 1",
    "sg:city":"Sj\u00f8lund",
    "sg:orig_category":"Brugsforeninger",
    "sg:phone":"+45 75 57 41 44",
    "sg:postcode":"6093",
    "sg:province":"Danmark",
    "wof:name":"Dagli' Brugsen Vejstrup",
    "wof:placetype":"venue"
},
  "geometry": {"coordinates":[-115.0078277588,38.8556137085],"type":"Point"}
}