{
  "type": "Feature",
  "properties": {
    "addr:full":"Estrupsgade 6 Silkeborg Danmark 8600",
    "addr:housenumber":"6",
    "addr:postcode":"8600",
    "addr:street":"Estrupsgade",
    "iso:country":"DK",
    "sg:address":"Estrupsgade 6",
    "sg:city":"Silkeborg",
    "sg:classifiers":[
        {
            "category":"Restaurant",
            "type":"Food & Drink"
        }
    ],
    "sg:phone":"+45 86 81 67 99",
    "sg:postcode":"8600",
    "sg:province":"Danmark",
    "wof:name":"Bosporus",
    "wof:placetype":"venue"
},
  "geometry": {"coordinates":[9.5447368622,56.1662597656],"type":"Point"}
}