{
  "type": "Feature",
  "properties": {
    "addr:full":"Vonsildvej 47, Vonsild Kolding Danmark 6000",
    "addr:housenumber":"47",
    "addr:postcode":"6000",
    "addr:street":"Vonsildvej;Vonsild",
    "iso:country":"DK",
    "sg:address":"Vonsildvej 47, Vonsild",
    "sg:city":"Kolding",
    "sg:orig_category":"Kirker",
    "sg:postcode":"6000",
    "sg:province":"Danmark",
    "wof:name":"Vonsild Kirke",
    "wof:placetype":"venue"
},
  "geometry": {"coordinates":[9.4733953476,55.4863586426],"type":"Point"}
}