{
  "type": "Feature",
  "properties": {
    "addr:full":"Sandagervej 40 Herning Danmark 7400",
    "addr:housenumber":"40",
    "addr:postcode":"7400",
    "addr:street":"Sandagervej",
    "iso:country":"DK",
    "sg:address":"Sandagervej 40",
    "sg:city":"Herning",
    "sg:orig_category":"Dagrenovation",
    "sg:phone":"+45 97 32 53 00",
    "sg:postcode":"7400",
    "sg:province":"Danmark",
    "sg:website":"www.mariuspedersen.dk",
    "wof:name":"Pedersen A/S, Marius",
    "wof:placetype":"venue"
},
  "geometry": {"coordinates":[8.9362077713,56.1236076355],"type":"Point"}
}