{
  "type": "Feature",
  "properties": {
    "addr:full":"Fmd.: Louis Rovs Hansen, Godth\u00e5bsvej 3 Frederikshavn Danmark 9900",
    "addr:housenumber":"3",
    "addr:postcode":"9900",
    "addr:street":"Godthaabsvej",
    "iso:country":"DK",
    "sg:address":"Fmd.: Louis Rovs Hansen, Godth\u00e5bsvej 3",
    "sg:city":"Frederikshavn",
    "sg:orig_category":"Hobbybetonede foreninger",
    "sg:phone":"+45 98 42 15 99",
    "sg:postcode":"9900",
    "sg:province":"Danmark",
    "wof:name":"S\u00e6by Flyveklub",
    "wof:placetype":"venue"
},
  "geometry": {"coordinates":[10.5362997055,57.4396400452],"type":"Point"}
}