{
  "type": "Feature",
  "properties": {
    "addr:full":"Ramsherred 4 Aabenraa Danmark 6200",
    "addr:housenumber":"4",
    "addr:postcode":"6200",
    "addr:street":"Ramsherred",
    "iso:country":"DK",
    "sg:address":"Ramsherred 4",
    "sg:city":"Aabenraa",
    "sg:classifiers":[
        {
            "category":"Food & Beverages",
            "subcategory":"Liquor & Beverages",
            "type":"Retail Goods"
        }
    ],
    "sg:phone":"+45 74 62 25 21",
    "sg:postcode":"6200",
    "sg:province":"Danmark",
    "sg:tags":[
        "vin"
    ],
    "wof:name":"Carstensen Vine",
    "wof:placetype":"venue"
},
  "geometry": {"coordinates":[9.4181251526,55.0474395752],"type":"Point"}
}