{
  "type": "Feature",
  "properties": {
    "addr:full":"Egebakken 24, Gjess\u00f8 Silkeborg Danmark 8600",
    "addr:housenumber":"24",
    "addr:postcode":"8600",
    "addr:street":"Egebakken;Gjesso",
    "iso:country":"DK",
    "sg:address":"Egebakken 24, Gjess\u00f8",
    "sg:city":"Silkeborg",
    "sg:classifiers":[
        {
            "category":"Food & Beverages",
            "subcategory":"Candy",
            "type":"Retail Goods"
        }
    ],
    "sg:phone":"+45 86 84 79 44",
    "sg:postcode":"8600",
    "sg:province":"Danmark",
    "sg:tags":[
        "finer"
    ],
    "wof:name":"Schj\u00f8dt's Fin\u00e9rhandel A/S",
    "wof:placetype":"venue"
},
  "geometry": {"coordinates":[9.5524425507,56.1693305969],"type":"Point"}
}