{
  "type": "Feature",
  "properties": {
    "addr:full":"Fmd.: Arne Korsgaard, Okslundvej 30, Lindknud Br\u00f8rup Danmark 6650",
    "addr:housenumber":"30",
    "addr:postcode":"6650",
    "addr:street":"Arne;Okslundvej",
    "iso:country":"DK",
    "sg:address":"Fmd.: Arne Korsgaard, Okslundvej 30, Lindknud",
    "sg:city":"Br\u00f8rup",
    "sg:orig_category":"Antenneforeninger",
    "sg:phone":"+45 75 38 82 54",
    "sg:postcode":"6650",
    "sg:province":"Danmark",
    "wof:name":"Lindknud Antenneforening",
    "wof:placetype":"venue"
},
  "geometry": {"coordinates":[9.0038452148,55.4421157837],"type":"Point"}
}