{
  "type": "Feature",
  "properties": {
    "iso:country":"DK",
    "sg:address":"Kollund Byvej 17",
    "sg:city":"Herning",
    "sg:orig_category":"Systuer",
    "sg:phone":"+45 97 22 22 61",
    "sg:postcode":"7400",
    "sg:province":"Danmark",
    "wof:name":"Kollund L\u00f8nsy",
    "wof:placetype":"venue"
},
  "geometry": {"coordinates":[9.0276098251,56.092880249],"type":"Point"}
}