{
  "type": "Feature",
  "properties": {
    "addr:full":"Lindholm \u00d8 13 Kalvehave Danmark 4771",
    "addr:housenumber":"13",
    "addr:postcode":"4771",
    "addr:street":"Lindholm O",
    "iso:country":"DK",
    "sg:address":"Lindholm \u00d8 13",
    "sg:city":"Kalvehave",
    "sg:orig_category":"Statslige direktorater og styrelser",
    "sg:phone":"+45 55 86 02 00",
    "sg:postcode":"4771",
    "sg:province":"Danmark",
    "sg:website":"www.vetvirus.dk",
    "wof:name":"Statens Veterin\u00e6re Institut for Virusforskning",
    "wof:placetype":"venue"
},
  "geometry": {"coordinates":[12.1613817215,54.9965782166],"type":"Point"}
}