{
  "type": "Feature",
  "properties": {
    "addr:full":"Fmd.: Svend Christiansen, Butterupvej 90 Regstrup Danmark 4420",
    "addr:housenumber":"90",
    "addr:postcode":"4420",
    "addr:street":"Butterupvej",
    "iso:country":"DK",
    "sg:address":"Fmd.: Svend Christiansen, Butterupvej 90",
    "sg:city":"Regstrup",
    "sg:orig_category":"Hobbybetonede foreninger",
    "sg:phone":"+45 59 47 14 65",
    "sg:postcode":"4420",
    "sg:province":"Danmark",
    "wof:name":"Dianalund-M\u00f8rk\u00f8v Brevdueforening",
    "wof:placetype":"venue"
},
  "geometry": {"coordinates":[11.6131772995,55.6769638062],"type":"Point"}
}