{
  "type": "Feature",
  "properties": {
    "addr:full":"Jernbanegade 10 Store Heddinge Danmark 4660",
    "addr:housenumber":"10",
    "addr:postcode":"4660",
    "addr:street":"Jernbanegade",
    "iso:country":"DK",
    "sg:address":"Jernbanegade 10",
    "sg:city":"Store Heddinge",
    "sg:orig_category":"Jernbaner",
    "sg:phone":"+45 56 56 04 04",
    "sg:postcode":"4660",
    "sg:province":"Danmark",
    "wof:name":"\u00d8stbanen, Store-Heddinge Station",
    "wof:placetype":"venue"
},
  "geometry": {"coordinates":[12.3869695663,55.3099212646],"type":"Point"}
}