{
  "type": "Feature",
  "properties": {
    "addr:full":"Skovl\u00f8kkevej 17 Kolding Danmark 6000",
    "addr:housenumber":"17",
    "addr:postcode":"6000",
    "addr:street":"Skovlokkevej",
    "iso:country":"DK",
    "sg:address":"Skovl\u00f8kkevej 17",
    "sg:city":"Kolding",
    "sg:orig_category":"Malermestre",
    "sg:phone":"+45 75 53 18 55",
    "sg:postcode":"6000",
    "sg:province":"Danmark",
    "wof:name":"Kolding Malerg\u00e5rd",
    "wof:placetype":"venue"
},
  "geometry": {"coordinates":[9.4615650177,55.4922142029],"type":"Point"}
}