{
  "type": "Feature",
  "properties": {
    "addr:full":"Tingvej 2 Haslev Danmark 4690",
    "addr:housenumber":"2",
    "addr:postcode":"4690",
    "addr:street":"Tingvej",
    "iso:country":"DK",
    "sg:address":"Tingvej 2",
    "sg:city":"Haslev",
    "sg:orig_category":"Politi",
    "sg:phone":"+45 56 31 14 48",
    "sg:postcode":"4690",
    "sg:province":"Danmark",
    "wof:name":"Haslev Politistation",
    "wof:placetype":"venue"
},
  "geometry": {"coordinates":[11.9580545425,55.3280944824],"type":"Point"}
}