{
  "type": "Feature",
  "properties": {
    "addr:full":"T\u00f8nnesgade 14 Vejle Danmark 7100",
    "addr:housenumber":"14",
    "addr:postcode":"7100",
    "addr:street":"Tonnesgade",
    "iso:country":"DK",
    "sg:address":"T\u00f8nnesgade 14",
    "sg:city":"Vejle",
    "sg:orig_category":"Trossamfund uden for folkekirken",
    "sg:postcode":"7100",
    "sg:province":"Danmark",
    "wof:name":"Katolsk-Apostolisk Kirke",
    "wof:placetype":"venue"
},
  "geometry": {"coordinates":[9.5344762802,55.711933136],"type":"Point"}
}