{
  "type": "Feature",
  "properties": {
    "addr:full":"Brogade 8 Varde Danmark 6800",
    "addr:housenumber":"8",
    "addr:postcode":"6800",
    "addr:street":"Brogade",
    "iso:country":"DK",
    "sg:address":"Brogade 8",
    "sg:city":"Varde",
    "sg:orig_category":"Blomsterhandlere",
    "sg:phone":"+45 75 22 01 24",
    "sg:postcode":"6800",
    "sg:province":"Danmark",
    "wof:name":"Larsen's Blomster",
    "wof:placetype":"venue"
},
  "geometry": {"coordinates":[8.48229599,55.6194267273],"type":"Point"}
}