{
  "type": "Feature",
  "properties": {
    "iso:country":"DK",
    "sg:address":"Tv\u00e6rgade 17",
    "sg:city":"Gesten",
    "sg:orig_category":"Havebrugsmaskiner",
    "sg:phone":"+45 75 55 76 97",
    "sg:postcode":"6621",
    "sg:province":"Danmark",
    "wof:name":"S. H. Maskinservice",
    "wof:placetype":"venue"
},
  "geometry": {"coordinates":[9.2036886215,55.5264511108],"type":"Point"}
}