{
  "type": "Feature",
  "properties": {
    "addr:full":"Nytorv 15 Frederikshavn Danmark 9900",
    "addr:housenumber":"15",
    "addr:postcode":"9900",
    "addr:street":"Nytorv",
    "iso:country":"DK",
    "sg:address":"Nytorv 15",
    "sg:city":"Frederikshavn",
    "sg:orig_category":"Fotokopiering",
    "sg:phone":"+45 98 42 23 24",
    "sg:postcode":"9900",
    "sg:province":"Danmark",
    "wof:name":"Frederikshavn Lyskopiering & Farvekopicenter",
    "wof:placetype":"venue"
},
  "geometry": {"coordinates":[10.5404558182,57.4457168579],"type":"Point"}
}