{
  "type": "Feature",
  "properties": {
    "iso:country":"DK",
    "sg:address":"Rosenkildevej 53",
    "sg:city":"Slagelse",
    "sg:orig_category":"Behandlingshjem",
    "sg:phone":"+45 58 50 68 31",
    "sg:postcode":"4200",
    "sg:province":"Danmark",
    "sg:website":"www.handicap.net/skovbrynet",
    "wof:name":"Skovbrynet Bo- og Servicetilbud",
    "wof:placetype":"venue"
},
  "geometry": {"coordinates":[11.3644895554,55.4202003479],"type":"Point"}
}