{
  "type": "Feature",
  "properties": {
    "addr:full":"Gemsevej 11 Skive Danmark 7800",
    "addr:housenumber":"11",
    "addr:postcode":"7800",
    "addr:street":"Gemsevej",
    "iso:country":"DK",
    "sg:address":"Gemsevej 11",
    "sg:city":"Skive",
    "sg:orig_category":"Motionscentre, Art. for",
    "sg:phone":"+45 97 52 81 88",
    "sg:postcode":"7800",
    "sg:province":"Danmark",
    "sg:website":"www.danasport.dk",
    "wof:name":"Danasport ApS",
    "wof:placetype":"venue"
},
  "geometry": {"coordinates":[9.0340023041,56.5377082825],"type":"Point"}
}