{
  "type": "Feature",
  "properties": {
    "addr:full":"\u00d8stergade 6 Frederikssund Danmark 3600",
    "addr:housenumber":"6",
    "addr:postcode":"3600",
    "addr:street":"Ostergade",
    "iso:country":"DK",
    "sg:address":"\u00d8stergade 6",
    "sg:city":"Frederikssund",
    "sg:classifiers":[
        {
            "category":"Professional",
            "subcategory":"Computer Services",
            "type":"Services"
        }
    ],
    "sg:phone":"+45 47 38 44 84",
    "sg:postcode":"3600",
    "sg:province":"Danmark",
    "sg:tags":[
        "edb",
        "-",
        "software"
    ],
    "sg:website":"www.revisorinformatik.dk",
    "wof:name":"Revisor Informatik ApS",
    "wof:placetype":"venue"
},
  "geometry": {"coordinates":[12.0590000153,55.8393478394],"type":"Point"}
}