{
  "type": "Feature",
  "properties": {
    "addr:full":"Stormgade 65 Esbjerg Danmark 6700",
    "addr:housenumber":"65",
    "addr:postcode":"6700",
    "addr:street":"Stormgade",
    "iso:country":"DK",
    "sg:address":"Stormgade 65",
    "sg:city":"Esbjerg",
    "sg:orig_category":"INGENI\u00c3\u02dcRER",
    "sg:phone":"+45 76 10 97 97",
    "sg:postcode":"6700",
    "sg:province":"Danmark",
    "sg:website":"www.birch-krogboe.dk",
    "wof:name":"Birch & Krogboe A/S",
    "wof:placetype":"venue"
},
  "geometry": {"coordinates":[8.4456653595,55.4725418091],"type":"Point"}
}