{
  "type": "Feature",
  "properties": {
    "iso:country":"DK",
    "sg:address":"J\u00f8rgensg\u00e5rd Skovvej 101-107, Aab\u00e6k",
    "sg:city":"Aabenraa",
    "sg:orig_category":"Efterskoler",
    "sg:phone":"+45 74 62 50 63",
    "sg:postcode":"6200",
    "sg:province":"Danmark",
    "wof:name":"Aab\u00e6k Efterskole",
    "wof:placetype":"venue"
},
  "geometry": {"coordinates":[9.4213867188,55.0449562073],"type":"Point"}
}