{
  "type": "Feature",
  "properties": {
    "addr:full":"v/ Gerda Madsen, Sportsvej 3 Jyllinge Danmark 4040",
    "addr:housenumber":"3",
    "addr:postcode":"4040",
    "addr:street":"Sportsvej",
    "iso:country":"DK",
    "sg:address":"v/ Gerda Madsen, Sportsvej 3",
    "sg:city":"Jyllinge",
    "sg:orig_category":"Aftenskoler",
    "sg:phone":"+45 46 78 97 78",
    "sg:postcode":"4040",
    "sg:province":"Danmark",
    "wof:name":"APA, Afsp\u00e6ndings P\u00e6dagogisk Aftenskole",
    "wof:placetype":"venue"
},
  "geometry": {"coordinates":[12.1163625717,55.7643737793],"type":"Point"}
}