{
  "type": "Feature",
  "properties": {
    "addr:full":"R\u00f8nningevej 1 Langeskov Danmark 5550",
    "addr:housenumber":"1",
    "addr:postcode":"5550",
    "addr:street":"Ronningevej",
    "iso:country":"DK",
    "sg:address":"R\u00f8nningevej 1",
    "sg:city":"Langeskov",
    "sg:orig_category":"Bagere",
    "sg:phone":"+45 65 38 11 45",
    "sg:postcode":"5550",
    "sg:province":"Danmark",
    "wof:name":"Stub's Bageri",
    "wof:placetype":"venue"
},
  "geometry": {"coordinates":[10.591015,55.358788],"type":"Point"}
}