{
  "type": "Feature",
  "properties": {
    "addr:full":"Meterbuen 15 Skovlunde Danmark 2740",
    "addr:housenumber":"15",
    "addr:postcode":"2740",
    "addr:street":"Meterbuen",
    "iso:country":"DK",
    "sg:address":"Meterbuen 15",
    "sg:city":"Skovlunde",
    "sg:orig_category":"Transport",
    "sg:phone":"+45 44 92 92 00",
    "sg:postcode":"2740",
    "sg:province":"Danmark",
    "sg:website":"www.sendebudet.dk",
    "wof:name":"Sendebudet",
    "wof:placetype":"venue"
},
  "geometry": {"coordinates":[12.4165086746,55.7168197632],"type":"Point"}
}