{
  "type": "Feature",
  "properties": {
    "addr:full":"Vilstrupvej 55 Haderslev Danmark 6100",
    "addr:housenumber":"55",
    "addr:postcode":"6100",
    "addr:street":"Vilstrupvej",
    "iso:country":"DK",
    "sg:address":"Vilstrupvej 55",
    "sg:city":"Haderslev",
    "sg:orig_category":"Redningsberedskab",
    "sg:phone":"+45 74 52 42 37",
    "sg:postcode":"6100",
    "sg:province":"Danmark",
    "wof:name":"Beredskabsstyrelsen Sydjylland",
    "wof:placetype":"venue"
},
  "geometry": {"coordinates":[9.4961338043,55.2275352478],"type":"Point"}
}