{
  "type": "Feature",
  "properties": {
    "addr:full":"Rosevej 5, Ballen Vester Skerninge Danmark 5762",
    "addr:housenumber":"5",
    "addr:postcode":"5762",
    "addr:street":"Rosevej;Ballen",
    "iso:country":"DK",
    "sg:address":"Rosevej 5, Ballen",
    "sg:city":"Vester Skerninge",
    "sg:orig_category":"Zoneterapeuter",
    "sg:phone":"+45 62 24 20 91",
    "sg:postcode":"5762",
    "sg:province":"Danmark",
    "wof:name":"Solar Plexus",
    "wof:placetype":"venue"
},
  "geometry": {"coordinates":[10.5008449554,55.070400238],"type":"Point"}
}