{
  "type": "Feature",
  "properties": {
    "addr:full":"Diplomvej 373 Kgs. Lyngby 2800",
    "addr:housenumber":"373",
    "addr:postcode":"2800",
    "addr:street":"Diplomvej",
    "iso:country":"DK",
    "sg:address":"Diplomvej 373",
    "sg:city":"Kgs. Lyngby",
    "sg:classifiers":[
        {
            "category":"Professional",
            "subcategory":"Computer Services",
            "type":"Services"
        }
    ],
    "sg:postcode":"2800",
    "sg:tags":[
        "finance",
        "investing",
        "saas",
        "copenhagen",
        "on-demand-software",
        "stocks",
        "stock-markets"
    ],
    "sg:website":"http://upsido.com",
    "wof:name":"UPSIDO.com",
    "wof:placetype":"venue"
},
  "geometry": {"coordinates":[12.512689,55.782052],"type":"Point"}
}