{
  "type": "Feature",
  "properties": {
    "addr:full":"Norgesgade 2 Esbjerg Danmark 6700",
    "addr:housenumber":"2",
    "addr:postcode":"6700",
    "addr:street":"Norgesgade",
    "iso:country":"DK",
    "sg:address":"Norgesgade 2",
    "sg:city":"Esbjerg",
    "sg:orig_category":"Faglige organisationer og foreninger",
    "sg:phone":"+45 75 13 39 44",
    "sg:postcode":"6700",
    "sg:province":"Danmark",
    "wof:name":"Blik & R\u00f8r Esbjerg Afdeling",
    "wof:placetype":"venue"
},
  "geometry": {"coordinates":[8.4573354721,55.4677848816],"type":"Point"}
}