{
  "type": "Feature",
  "properties": {
    "iso:country":"DK",
    "sg:address":"Fmd.: Svend B\u00f8gsted, Tingstedvej 9 C, Reerslev",
    "sg:city":"Hedehusene",
    "sg:orig_category":"Spejderkorps",
    "sg:phone":"+45 46 56 36 86",
    "sg:postcode":"2640",
    "sg:province":"Danmark",
    "wof:name":"DDS, Balder Hedehusene Gruppe",
    "wof:placetype":"venue"
},
  "geometry": {"coordinates":[12.1993551254,55.6496009827],"type":"Point"}
}