{
  "type": "Feature",
  "properties": {
    "addr:full":"\u00c5lholm Parkvej 5 Nysted Danmark 4880",
    "addr:housenumber":"5",
    "addr:postcode":"4880",
    "addr:street":"Aalholm Parkvej",
    "iso:country":"DK",
    "sg:address":"\u00c5lholm Parkvej 5",
    "sg:city":"Nysted",
    "sg:orig_category":"Video- og TV-produktion",
    "sg:phone":"+45 54 87 19 04",
    "sg:postcode":"4880",
    "sg:province":"Danmark",
    "wof:name":"H.L. Sound & Videocenter",
    "wof:placetype":"venue"
},
  "geometry": {"coordinates":[11.7209844589,54.6647071838],"type":"Point"}
}