{
  "type": "Feature",
  "properties": {
    "addr:full":"H\u00f8jholtvej 19 Ryslinge Danmark 5856",
    "addr:housenumber":"19",
    "addr:postcode":"5856",
    "addr:street":"Hojholtvej",
    "iso:country":"DK",
    "sg:address":"H\u00f8jholtvej 19",
    "sg:city":"Ryslinge",
    "sg:orig_category":"Zoneterapeuter",
    "sg:phone":"+45 62 67 15 70",
    "sg:postcode":"5856",
    "sg:province":"Danmark",
    "wof:name":"Fjellerup Zoneterapi",
    "wof:placetype":"venue"
},
  "geometry": {"coordinates":[10.5612268448,55.2376976013],"type":"Point"}
}