{
  "type": "Feature",
  "properties": {
    "addr:full":"Steng\u00e5rdsvej 4 Lynge Danmark 3540",
    "addr:housenumber":"4",
    "addr:postcode":"3540",
    "addr:street":"Stengaardsvej",
    "iso:country":"DK",
    "sg:address":"Steng\u00e5rdsvej 4",
    "sg:city":"Lynge",
    "sg:orig_category":"Snedkermestre",
    "sg:phone":"+45 48 18 74 87",
    "sg:postcode":"3540",
    "sg:province":"Danmark",
    "wof:name":"Andersen, Erik Ferslev",
    "wof:placetype":"venue"
},
  "geometry": {"coordinates":[12.2707662582,55.8206253052],"type":"Point"}
}