{
  "type": "Feature",
  "properties": {
    "addr:full":"Kongensgade 27, 3 Odense C Danmark 5000",
    "addr:housenumber":"27 3",
    "addr:postcode":"5000",
    "addr:street":"Kongensgade",
    "iso:country":"DK",
    "sg:address":"Kongensgade 27, 3",
    "sg:city":"Odense C",
    "sg:orig_category":"Revisorer",
    "sg:phone":"+45 66 12 75 24",
    "sg:postcode":"5000",
    "sg:province":"Danmark",
    "wof:name":"Nielsen, Revisionsfirmaet Leif",
    "wof:placetype":"venue"
},
  "geometry": {"coordinates":[10.3820323944,55.396282196],"type":"Point"}
}