{
  "type": "Feature",
  "properties": {
    "addr:full":"Bredgade 21 B Skjern Danmark 6900",
    "addr:housenumber":"21 b",
    "addr:postcode":"6900",
    "addr:street":"Bredgade",
    "iso:country":"DK",
    "sg:address":"Bredgade 21 B",
    "sg:city":"Skjern",
    "sg:orig_category":"Rutebiler",
    "sg:phone":"+45 97 35 06 77",
    "sg:postcode":"6900",
    "sg:province":"Danmark",
    "wof:name":"Rutebilstationen",
    "wof:placetype":"venue"
},
  "geometry": {"coordinates":[8.4949502945,55.9456062317],"type":"Point"}
}