{
  "type": "Feature",
  "properties": {
    "addr:full":"B\u00e6la 1 Hasle Danmark 3790",
    "addr:housenumber":"1",
    "addr:postcode":"3790",
    "addr:street":"Baela",
    "iso:country":"DK",
    "sg:address":"B\u00e6la 1",
    "sg:city":"Hasle",
    "sg:orig_category":"Markiser",
    "sg:phone":"+45 56 96 47 11",
    "sg:postcode":"3790",
    "sg:province":"Danmark",
    "sg:website":"www.haslenord.dk",
    "wof:name":"Hasle Nord v/Kennet Hansen",
    "wof:placetype":"venue"
},
  "geometry": {"coordinates":[14.7092161179,55.1995201111],"type":"Point"}
}