{
  "type": "Feature",
  "properties": {
    "addr:full":"Gludstedvej 2, Godrum Hampen Danmark 7362",
    "addr:housenumber":"2",
    "addr:postcode":"7362",
    "addr:street":"Gludstedvej",
    "iso:country":"DK",
    "sg:address":"Gludstedvej 2, Godrum",
    "sg:city":"Hampen",
    "sg:orig_category":"Botilbud",
    "sg:phone":"+45 86 86 92 33",
    "sg:postcode":"7362",
    "sg:province":"Danmark",
    "wof:name":"Godrum Arbejde Adlers Forsorgshjem",
    "wof:placetype":"venue"
},
  "geometry": {"coordinates":[9.3543596268,56.0194015503],"type":"Point"}
}