{
  "type": "Feature",
  "properties": {
    "iso:country":"DK",
    "sg:address":"Fmd.: Lisbeth Domino, Hobrovej 12, Rold",
    "sg:city":"Arden",
    "sg:orig_category":"Borger- og beboerforeninger",
    "sg:phone":"+45 98 56 22 40",
    "sg:postcode":"9510",
    "sg:province":"Danmark",
    "wof:name":"Rold Bylaug",
    "wof:placetype":"venue"
},
  "geometry": {"coordinates":[9.8580989838,56.7683296204],"type":"Point"}
}