{
  "type": "Feature",
  "properties": {
    "addr:full":"Sundparken 1 Frederikssund Danmark 3600",
    "addr:housenumber":"1",
    "addr:postcode":"3600",
    "addr:street":"Sundparken",
    "iso:country":"DK",
    "sg:address":"Sundparken 1",
    "sg:city":"Frederikssund",
    "sg:orig_category":"Boligselskaber",
    "sg:phone":"+45 47 31 31 97",
    "sg:postcode":"3600",
    "sg:province":"Danmark",
    "wof:name":"Oppe-Sundby Boligselskab",
    "wof:placetype":"venue"
},
  "geometry": {"coordinates":[12.079460144,55.8311653137],"type":"Point"}
}