{
  "type": "Feature",
  "properties": {
    "addr:full":"Rungstedvej 79 Rungsted Kyst Danmark 2960",
    "addr:housenumber":"79",
    "addr:postcode":"2960",
    "addr:street":"Rungstedvej",
    "iso:country":"DK",
    "sg:address":"Rungstedvej 79",
    "sg:city":"Rungsted Kyst",
    "sg:classifiers":[
        {
            "category":"Banks & Credit Unions",
            "subcategory":"Bank",
            "type":"Services"
        }
    ],
    "sg:phone":"+45 45 16 21 50",
    "sg:postcode":"2960",
    "sg:province":"Danmark",
    "sg:tags":[
        "banker"
    ],
    "sg:website":"www.danskebank.dk",
    "wof:name":"Danske Bank",
    "wof:placetype":"venue"
},
  "geometry": {"coordinates":[12.5290021896,55.8837966919],"type":"Point"}
}