{
  "type": "Feature",
  "properties": {
    "addr:full":"Hjallesegade 11, Hjallese Odense S Danmark 5260",
    "addr:housenumber":"11",
    "addr:postcode":"5260",
    "addr:street":"Hjallesegade;Hjallese",
    "iso:country":"DK",
    "sg:address":"Hjallesegade 11, Hjallese",
    "sg:city":"Odense S",
    "sg:orig_category":"Kollegier",
    "sg:phone":"+45 66 15 06 96",
    "sg:postcode":"5260",
    "sg:province":"Danmark",
    "wof:name":"Kaj Munk Kollegiet",
    "wof:placetype":"venue"
},
  "geometry": {"coordinates":[10.3157806396,55.3122825623],"type":"Point"}
}