{
  "type": "Feature",
  "properties": {
    "addr:full":"Bygade 109 Vonge Danmark 7173",
    "addr:housenumber":"109",
    "addr:postcode":"7173",
    "addr:street":"Bygade",
    "iso:country":"DK",
    "sg:address":"Bygade 109",
    "sg:city":"Vonge",
    "sg:orig_category":"Kirker",
    "sg:postcode":"7173",
    "sg:province":"Danmark",
    "wof:name":"Vonge Kirke",
    "wof:placetype":"venue"
},
  "geometry": {"coordinates":[9.4274673462,55.8562583923],"type":"Point"}
}