{
  "type": "Feature",
  "properties": {
    "iso:country":"DK",
    "sg:address":"Tofteg\u00e5rdsvej 1",
    "sg:city":"Frederikshavn",
    "sg:classifiers":[
        {
            "category":"Communications",
            "type":"Services"
        }
    ],
    "sg:phone":"+45 98 42 62 11",
    "sg:postcode":"9900",
    "sg:province":"Danmark",
    "sg:tags":[
        "og",
        "tv",
        "radio"
    ],
    "sg:website":"www.mariendal.dk",
    "wof:name":"Mariendal Gruppen",
    "wof:placetype":"venue"
},
  "geometry": {"coordinates":[10.5013160706,57.445350647],"type":"Point"}
}