{
  "type": "Feature",
  "properties": {
    "addr:full":"Fmd.: Nils Gjerl\u00f8v Hansen, Kr. Zahrtmanns Plads 76 Frederiksberg Danmark 2000",
    "addr:housenumber":"76",
    "addr:postcode":"2000",
    "addr:street":"Kr. Zahrtmanns Plads",
    "iso:country":"DK",
    "sg:address":"Fmd.: Nils Gjerl\u00f8v Hansen, Kr. Zahrtmanns Plads 76",
    "sg:city":"Frederiksberg",
    "sg:orig_category":"Borger- og beboerforeninger",
    "sg:phone":"+45 38 34 62 06",
    "sg:postcode":"2000",
    "sg:province":"Danmark",
    "sg:website":"www.ffn.dk",
    "wof:name":"Frederiksberg For\u00e6ldren\u00e6vn",
    "wof:placetype":"venue"
},
  "geometry": {"coordinates":[12.5299301147,55.6787872314],"type":"Point"}
}