{
  "type": "Feature",
  "properties": {
    "iso:country":"DK",
    "sg:address":"Hovmarken 2",
    "sg:city":"Lystrup",
    "sg:orig_category":"Varmeforsyning",
    "sg:phone":"+45 86 22 16 99",
    "sg:postcode":"8520",
    "sg:province":"Danmark",
    "wof:name":"Lystrup Fjernvarmev\u00e6rk",
    "wof:placetype":"venue"
},
  "geometry": {"coordinates":[10.2410068512,56.2343025208],"type":"Point"}
}