{
  "type": "Feature",
  "properties": {
    "addr:full":"Lumringsbrovej 1 Greve Danmark 2670",
    "addr:housenumber":"1",
    "addr:postcode":"2670",
    "addr:street":"Lumringsbrovej",
    "iso:country":"DK",
    "sg:address":"Lumringsbrovej 1",
    "sg:city":"Greve",
    "sg:orig_category":"Kolonihaveforeninger",
    "sg:phone":"+45 43 90 54 75",
    "sg:postcode":"2670",
    "sg:province":"Danmark",
    "wof:name":"Hundige Haveforening",
    "wof:placetype":"venue"
},
  "geometry": {"coordinates":[12.350440979,55.6020050049],"type":"Point"}
}