{
  "type": "Feature",
  "properties": {
    "addr:full":"Pederstrupvej 9 D, Slukefter Odense NV Danmark 5210",
    "addr:housenumber":"9 d",
    "addr:postcode":"5210",
    "addr:street":"Pederstrupvej;Slukefter",
    "iso:country":"DK",
    "sg:address":"Pederstrupvej 9 D, Slukefter",
    "sg:city":"Odense NV",
    "sg:orig_category":"Malerforretninger",
    "sg:phone":"+45 40 37 06 80",
    "sg:postcode":"5210",
    "sg:province":"Danmark",
    "wof:name":"Christensen, Kenneth Knud",
    "wof:placetype":"venue"
},
  "geometry": {"coordinates":[10.274764061,55.4303321838],"type":"Point"}
}