{
  "type": "Feature",
  "properties": {
    "addr:full":"Prinsessegade 72 Fredericia Danmark 7000",
    "addr:housenumber":"72",
    "addr:postcode":"7000",
    "addr:street":"Prinsessegade",
    "iso:country":"DK",
    "sg:address":"Prinsessegade 72",
    "sg:city":"Fredericia",
    "sg:orig_category":"Faglige organisationer og foreninger",
    "sg:phone":"+45 75 92 46 88",
    "sg:postcode":"7000",
    "sg:province":"Danmark",
    "wof:name":"Dansk El-Forbund",
    "wof:placetype":"venue"
},
  "geometry": {"coordinates":[9.7576246262,55.5636863708],"type":"Point"}
}