{
  "type": "Feature",
  "properties": {
    "addr:full":"v/ Erling Smed, \u00d8stervang 88 Maribo Danmark 4930",
    "addr:housenumber":"88",
    "addr:postcode":"4930",
    "iso:country":"DK",
    "sg:address":"v/ Erling Smed, \u00d8stervang 88",
    "sg:city":"Maribo",
    "sg:orig_category":"Grundejerforeninger",
    "sg:phone":"+45 54 78 10 28",
    "sg:postcode":"4930",
    "sg:province":"Danmark",
    "wof:name":"Maribo Grundejerforening",
    "wof:placetype":"venue"
},
  "geometry": {"coordinates":[11.502035141,54.7743835449],"type":"Point"}
}