{
  "type": "Feature",
  "properties": {
    "addr:full":"V\u00e6rket, Mariagervej 6 Randers Danmark 8900",
    "addr:housenumber":"6",
    "addr:postcode":"8900",
    "addr:street":"Mariagervej",
    "iso:country":"DK",
    "sg:address":"V\u00e6rket, Mariagervej 6",
    "sg:city":"Randers",
    "sg:orig_category":"Musik og sang",
    "sg:phone":"+45 86 41 28 33",
    "sg:postcode":"8900",
    "sg:province":"Danmark",
    "wof:name":"Randers Kammerorkester",
    "wof:placetype":"venue"
},
  "geometry": {"coordinates":[10.0323352814,56.4647865295],"type":"Point"}
}