{
  "type": "Feature",
  "properties": {
    "addr:full":"Frejasvej 12 Ringsted Danmark 4100",
    "addr:housenumber":"12",
    "addr:postcode":"4100",
    "addr:street":"Frejasvej",
    "iso:country":"DK",
    "sg:address":"Frejasvej 12",
    "sg:city":"Ringsted",
    "sg:orig_category":"Autoforhandlere",
    "sg:phone":"+45 57 68 40 00",
    "sg:postcode":"4100",
    "sg:province":"Danmark",
    "wof:name":"Fiat-Alfa-Lancia, Max Due A/S",
    "wof:placetype":"venue"
},
  "geometry": {"coordinates":[11.8010120392,55.4315948486],"type":"Point"}
}