{
  "type": "Feature",
  "properties": {
    "addr:full":"R\u00f8jlevej 22 B, Nr. S\u00f8by \u00c5rslev Danmark 5792",
    "addr:housenumber":"22 b nr.",
    "addr:postcode":"5792",
    "addr:street":"Rojlevej;Soby Aarslev Danmark",
    "iso:country":"DK",
    "sg:address":"R\u00f8jlevej 22 B, Nr. S\u00f8by",
    "sg:city":"\u00c5rslev",
    "sg:orig_category":"Integrerede institutioner",
    "sg:phone":"+45 63 90 47 30",
    "sg:postcode":"5792",
    "sg:province":"Danmark",
    "wof:name":"B\u00f8rnehuset Regnbuen",
    "wof:placetype":"venue"
},
  "geometry": {"coordinates":[166.9221496582,-0.5282999873],"type":"Point"}
}