{
  "type": "Feature",
  "properties": {
    "iso:country":"DK",
    "sg:address":"M\u00f8llevej 1",
    "sg:city":"Tisvildeleje",
    "sg:orig_category":"Investering",
    "sg:phone":"+45 26 20 93 90",
    "sg:postcode":"3220",
    "sg:province":"Danmark",
    "wof:name":"B\u00f8jsen-M\u00f8ller, Svend",
    "wof:placetype":"venue"
},
  "geometry": {"coordinates":[12.0764846802,56.0589904785],"type":"Point"}
}