{
  "type": "Feature",
  "properties": {
    "addr:full":"S\u00e6rslevvej 11 B Stubbek\u00f8bing Danmark 4850",
    "addr:housenumber":"11 b",
    "addr:postcode":"4850",
    "addr:street":"Saerslevvej",
    "iso:country":"DK",
    "sg:address":"S\u00e6rslevvej 11 B",
    "sg:city":"Stubbek\u00f8bing",
    "sg:orig_category":"Sten og grus",
    "sg:phone":"+45 54 44 51 56",
    "sg:postcode":"4850",
    "sg:province":"Danmark",
    "wof:name":"Nr. Taastrup Grusgrav",
    "wof:placetype":"venue"
},
  "geometry": {"coordinates":[-114.0767440796,46.4432487488],"type":"Point"}
}