{
  "type": "Feature",
  "properties": {
    "addr:full":"Skovshoved Havn 12  Charlottenlund Danmark 2920",
    "addr:housenumber":"12",
    "addr:postcode":"2920",
    "addr:street":"Skovshoved Havn",
    "iso:country":"DK",
    "sg:address":"Skovshoved Havn 12 ",
    "sg:city":"Charlottenlund",
    "sg:classifiers":[
        {
            "category":"Autos & Motor Vehicles",
            "subcategory":"Boat Sales",
            "type":"Retail Goods"
        }
    ],
    "sg:phone":"+45 39 63 22 10",
    "sg:postcode":"2920",
    "sg:province":"Danmark",
    "wof:name":"EURO SAILS A/S",
    "wof:placetype":"venue"
},
  "geometry": {"coordinates":[12.5918369293,55.7584342957],"type":"Point"}
}