{
  "type": "Feature",
  "properties": {
    "addr:full":"Frederikssundsvej 60 C 2.sal K\u00f8benhavn NV Danmark 2400",
    "addr:housenumber":"60 c 2.sal",
    "addr:postcode":"2400",
    "addr:street":"Frederikssundsvej",
    "iso:country":"DK",
    "sg:address":"Frederikssundsvej 60 C 2.sal",
    "sg:city":"K\u00f8benhavn NV",
    "sg:orig_category":"Ejendomsservice",
    "sg:phone":"+45 70 26 80 30",
    "sg:postcode":"2400",
    "sg:province":"Danmark",
    "sg:website":"www.kbh-ren.dk",
    "wof:name":"K\u00f8benhavns Reng\u00f8ring",
    "wof:placetype":"venue"
},
  "geometry": {"coordinates":[-117.02272033689999,38.5024604797],"type":"Point"}
}