{
  "type": "Feature",
  "properties": {
    "addr:full":"Slotsgade 20 Haderslev Danmark 6100",
    "addr:housenumber":"20",
    "addr:postcode":"6100",
    "addr:street":"Slotsgade",
    "iso:country":"DK",
    "sg:address":"Slotsgade 20",
    "sg:city":"Haderslev",
    "sg:orig_category":"Museer",
    "sg:phone":"+45 74 53 08 58",
    "sg:postcode":"6100",
    "sg:province":"Danmark",
    "wof:name":"Ehlers Samlingen",
    "wof:placetype":"venue"
},
  "geometry": {"coordinates":[9.4903831482,55.2497520447],"type":"Point"}
}