{
  "type": "Feature",
  "properties": {
    "addr:full":"Torvet 3 Hals Danmark 9370",
    "addr:housenumber":"3",
    "addr:postcode":"9370",
    "addr:street":"Torvet",
    "iso:country":"DK",
    "sg:address":"Torvet 3",
    "sg:city":"Hals",
    "sg:classifiers":[
        {
            "category":"Restaurant",
            "type":"Food & Drink"
        }
    ],
    "sg:phone":"+45 98 25 14 00",
    "sg:postcode":"9370",
    "sg:province":"Danmark",
    "wof:name":"Torvekroen",
    "wof:placetype":"venue"
},
  "geometry": {"coordinates":[10.3075456619,56.9942741394],"type":"Point"}
}