{
  "type": "Feature",
  "properties": {
    "addr:full":"Lykkemosevej 18 Fredensborg Danmark 3480",
    "addr:housenumber":"18",
    "addr:postcode":"3480",
    "addr:street":"Lykkemosevej",
    "iso:country":"DK",
    "sg:address":"Lykkemosevej 18",
    "sg:city":"Fredensborg",
    "sg:orig_category":"Blomsterhandlere",
    "sg:phone":"+45 26 83 14 51",
    "sg:postcode":"3480",
    "sg:province":"Danmark",
    "wof:name":"Kirstens Blomsterv\u00e6rksted",
    "wof:placetype":"venue"
},
  "geometry": {"coordinates":[12.4139699936,55.9751167297],"type":"Point"}
}