{
  "type": "Feature",
  "properties": {
    "addr:full":"L\u00f8vevej 46 Bryrup Danmark 8654",
    "addr:housenumber":"46",
    "addr:postcode":"8654",
    "addr:street":"Lovevej",
    "iso:country":"DK",
    "sg:address":"L\u00f8vevej 46",
    "sg:city":"Bryrup",
    "sg:orig_category":"Maskinstationer",
    "sg:phone":"+45 75 75 73 23",
    "sg:postcode":"8654",
    "sg:province":"Danmark",
    "wof:name":"L\u00f8ve Maskinstation",
    "wof:placetype":"venue"
},
  "geometry": {"coordinates":[9.4863605499,56.0124130249],"type":"Point"}
}