{
  "type": "Feature",
  "properties": {
    "addr:full":"M\u00f8llevej 5 Stensved Danmark 4773",
    "addr:housenumber":"5",
    "addr:postcode":"4773",
    "addr:street":"Mollevej",
    "iso:country":"DK",
    "sg:address":"M\u00f8llevej 5",
    "sg:city":"Stensved",
    "sg:orig_category":"Automater",
    "sg:phone":"+45 55 38 61 41",
    "sg:postcode":"4773",
    "sg:province":"Danmark",
    "wof:name":"Stensved Automatudlejning ApS",
    "wof:placetype":"venue"
},
  "geometry": {"coordinates":[12.0342769623,54.9960670471],"type":"Point"}
}