{
  "type": "Feature",
  "properties": {
    "addr:full":"M. Bechs Alle 122 Hvidovre Danmark 2650",
    "addr:housenumber":"122",
    "addr:postcode":"2650",
    "addr:street":"M. Bechs Alle",
    "iso:country":"DK",
    "sg:address":"M. Bechs Alle 122",
    "sg:city":"Hvidovre",
    "sg:orig_category":"Fritidshjem",
    "sg:phone":"+45 36 47 02 35",
    "sg:postcode":"2650",
    "sg:province":"Danmark",
    "wof:name":"Pr\u00e6stemosen Fritidshjem",
    "wof:placetype":"venue"
},
  "geometry": {"coordinates":[12.4674348831,55.65417099],"type":"Point"}
}