{
  "type": "Feature",
  "properties": {
    "addr:full":"Jegstrupvej 44 Hasselager Danmark 8361",
    "addr:housenumber":"44",
    "addr:postcode":"8361",
    "addr:street":"Jegstrupvej",
    "iso:country":"DK",
    "sg:address":"Jegstrupvej 44",
    "sg:city":"Hasselager",
    "sg:orig_category":"Fisk og vildt",
    "sg:phone":"+45 86 28 85 00",
    "sg:postcode":"8361",
    "sg:province":"Danmark",
    "wof:name":"Tims",
    "wof:placetype":"venue"
},
  "geometry": {"coordinates":[10.1070480347,56.1054916382],"type":"Point"}
}