{
  "type": "Feature",
  "properties": {
    "addr:full":"M\u00f8llergade 71 Svendborg Danmark 5700",
    "addr:housenumber":"71",
    "addr:postcode":"5700",
    "addr:street":"Mollergade",
    "iso:country":"DK",
    "sg:address":"M\u00f8llergade 71",
    "sg:city":"Svendborg",
    "sg:orig_category":"Forsikringer",
    "sg:phone":"+45 62 21 70 03",
    "sg:postcode":"5700",
    "sg:province":"Danmark",
    "wof:name":"Povinsforsikring",
    "wof:placetype":"venue"
},
  "geometry": {"coordinates":[10.6117534637,55.0630607605],"type":"Point"}
}