{
  "type": "Feature",
  "properties": {
    "addr:full":"Rosensgade 35 Odder Danmark 8300",
    "addr:housenumber":"35",
    "addr:postcode":"8300",
    "addr:street":"Rosensgade",
    "iso:country":"DK",
    "sg:address":"Rosensgade 35",
    "sg:city":"Odder",
    "sg:orig_category":"Hobbyartikler",
    "sg:phone":"+45 86 54 35 11",
    "sg:postcode":"8300",
    "sg:province":"Danmark",
    "wof:name":"Id\u00e9 Butikken",
    "wof:placetype":"venue"
},
  "geometry": {"coordinates":[10.145606041,55.9722251892],"type":"Point"}
}