{
  "type": "Feature",
  "properties": {
    "addr:full":"Dalumvej 4-6, Dalum Odense SV Danmark 5250",
    "addr:housenumber":"4-6",
    "addr:postcode":"5250",
    "addr:street":"Dalumvej;Dalum",
    "iso:country":"DK",
    "sg:address":"Dalumvej 4-6, Dalum",
    "sg:city":"Odense SV",
    "sg:orig_category":"Cykler",
    "sg:phone":"+45 66 13 46 50",
    "sg:postcode":"5250",
    "sg:province":"Danmark",
    "wof:name":"Oddershede Cykler ApS",
    "wof:placetype":"venue"
},
  "geometry": {"coordinates":[10.3153953552,55.3362998962],"type":"Point"}
}