{
  "type": "Feature",
  "properties": {
    "addr:full":"Fmd.: Ole M\u00f8ller, Br\u00f8demosevej 65, Asserbo Frederiksv\u00e6rk Danmark 3300",
    "addr:housenumber":"65",
    "addr:postcode":"3300",
    "addr:street":"Ole;Brodemosevej",
    "iso:country":"DK",
    "sg:address":"Fmd.: Ole M\u00f8ller, Br\u00f8demosevej 65, Asserbo",
    "sg:city":"Frederiksv\u00e6rk",
    "sg:orig_category":"Grundejerforeninger",
    "sg:phone":"+45 47 74 51 06",
    "sg:postcode":"3300",
    "sg:province":"Danmark",
    "wof:name":"Frederiksv\u00e6rk Grundejerforening",
    "wof:placetype":"venue"
},
  "geometry": {"coordinates":[12.0195035934,55.9789772034],"type":"Point"}
}