{
  "type": "Feature",
  "properties": {
    "addr:full":"Leb\u00f8lvej 23, Leb\u00f8l Sydals Danmark 6470",
    "addr:housenumber":"23",
    "addr:postcode":"6470",
    "addr:street":"Lebolvej;Lebol",
    "iso:country":"DK",
    "sg:address":"Leb\u00f8lvej 23, Leb\u00f8l",
    "sg:city":"Sydals",
    "sg:orig_category":"Autoreparation og -service",
    "sg:phone":"+45 74 40 76 12",
    "sg:postcode":"6470",
    "sg:province":"Danmark",
    "wof:name":"Leb\u00f8l Auto",
    "wof:placetype":"venue"
},
  "geometry": {"coordinates":[9.8924627304,54.9105377197],"type":"Point"}
}