{
  "type": "Feature",
  "properties": {
    "addr:full":"Vestre Alle 13 Aalborg Danmark 9000",
    "addr:housenumber":"13",
    "addr:postcode":"9000",
    "addr:street":"Vestre Alle",
    "iso:country":"DK",
    "sg:address":"Vestre Alle 13",
    "sg:city":"Aalborg",
    "sg:orig_category":"Supermarkeder",
    "sg:phone":"+45 96 30 50 70",
    "sg:postcode":"9000",
    "sg:province":"Danmark",
    "wof:name":"Super Brugsen",
    "wof:placetype":"venue"
},
  "geometry": {"coordinates":[9.9071149826,57.0339431763],"type":"Point"}
}