{
  "type": "Feature",
  "properties": {
    "iso:country":"DK",
    "sg:address":"Strandstien 2, Listed",
    "sg:city":"Svaneke",
    "sg:orig_category":"Cafeer",
    "sg:phone":"+45 56 49 90 42",
    "sg:postcode":"3740",
    "sg:province":"Danmark",
    "wof:name":"Engberg's Caf\u00e9",
    "wof:placetype":"venue"
},
  "geometry": {"coordinates":[15.140504837,55.1364555359],"type":"Point"}
}