{
  "type": "Feature",
  "properties": {
    "iso:country":"DK",
    "sg:address":"Enghavevej 20",
    "sg:city":"K\u00f8benhavn",
    "sg:orig_category":"Begravelsesforretninger",
    "sg:phone":"+45 33 23 07 85",
    "sg:postcode":"1674",
    "sg:province":"Danmark",
    "sg:website":"www.begravelse-bisp.dk",
    "wof:name":"Enghave Bedemandsforretning",
    "wof:placetype":"venue"
},
  "geometry": {"coordinates":[12.54541,55.669659],"type":"Point"}
}