{
  "type": "Feature",
  "properties": {
    "iso:country":"DK",
    "sg:address":"Fmd.: Morten Topholm Rud, Primulavej 61, 3. tv.",
    "sg:city":"Odense C",
    "sg:orig_category":"Hobbybetonede foreninger",
    "sg:phone":"+45 66 11 64 92",
    "sg:postcode":"5000",
    "sg:province":"Danmark",
    "sg:website":"home6.inet.tele.dk/if-skak",
    "wof:name":"Skakklub, L\u00e6seforeningens",
    "wof:placetype":"venue"
},
  "geometry": {"coordinates":[10.390794754,55.3961715698],"type":"Point"}
}