{
  "type": "Feature",
  "properties": {
    "addr:full":"Korsvejen 39 Skanderborg Danmark 8660",
    "addr:housenumber":"39",
    "addr:postcode":"8660",
    "addr:street":"Korsvejen",
    "iso:country":"DK",
    "sg:address":"Korsvejen 39",
    "sg:city":"Skanderborg",
    "sg:orig_category":"Kommunale ungdomsskoler",
    "sg:phone":"+45 86 52 54 03",
    "sg:postcode":"8660",
    "sg:province":"Danmark",
    "wof:name":"Skanderborg Ungdomsskole Heltidsundervisningen",
    "wof:placetype":"venue"
},
  "geometry": {"coordinates":[9.9027013779,56.0417976379],"type":"Point"}
}