{
  "type": "Feature",
  "properties": {
    "addr:full":"Anagervej 2 Munke Bjergby Danmark 4190",
    "addr:housenumber":"2",
    "addr:postcode":"4190",
    "addr:street":"Anagervej",
    "iso:country":"DK",
    "sg:address":"Anagervej 2",
    "sg:city":"Munke Bjergby",
    "sg:orig_category":"Vinduespolering",
    "sg:phone":"+45 57 80 68 48",
    "sg:postcode":"4190",
    "sg:province":"Danmark",
    "wof:name":"Herbst, Tommy",
    "wof:placetype":"venue"
},
  "geometry": {"coordinates":[11.5126180649,55.488899231],"type":"Point"}
}