{
  "type": "Feature",
  "properties": {
    "addr:full":"Fmd.: Lise Hansen, \u00c5havevej 32, Voersaa S\u00e6by Danmark 9300",
    "addr:housenumber":"32",
    "addr:postcode":"9300",
    "addr:street":"Aahavevej",
    "iso:country":"DK",
    "sg:address":"Fmd.: Lise Hansen, \u00c5havevej 32, Voersaa",
    "sg:city":"S\u00e6by",
    "sg:orig_category":"Musik og sang",
    "sg:phone":"+45 98 46 01 26",
    "sg:postcode":"9300",
    "sg:province":"Danmark",
    "wof:name":"Visens Venner I Aalborg",
    "wof:placetype":"venue"
},
  "geometry": {"coordinates":[10.5322313309,57.2625923157],"type":"Point"}
}