{
  "type": "Feature",
  "properties": {
    "addr:full":"Mors\u00f8gade 2 Aalborg Danmark 9000",
    "addr:housenumber":"2",
    "addr:postcode":"9000",
    "addr:street":"Morsogade",
    "iso:country":"DK",
    "sg:address":"Mors\u00f8gade 2",
    "sg:city":"Aalborg",
    "sg:classifiers":[
        {
            "category":"Communications",
            "type":"Services"
        }
    ],
    "sg:phone":"+45 98 11 79 44",
    "sg:postcode":"9000",
    "sg:province":"Danmark",
    "sg:tags":[
        "og",
        "tv",
        "radio"
    ],
    "sg:website":"www.acedanmark.dk",
    "wof:name":"ACE Danmark ApS",
    "wof:placetype":"venue"
},
  "geometry": {"coordinates":[9.9345111847,57.0415115356],"type":"Point"}
}