{
  "type": "Feature",
  "properties": {
    "addr:full":"N\u00e6ssundvej 437 - 439 Karby Danmark 7960",
    "addr:housenumber":"437",
    "addr:postcode":"439;7960",
    "addr:street":"Naessundvej",
    "iso:country":"DK",
    "sg:address":"N\u00e6ssundvej 437 - 439",
    "sg:city":"Karby",
    "sg:orig_category":"EDB - udstyr",
    "sg:phone":"+45 97 76 11 93",
    "sg:postcode":"7960",
    "sg:province":"Danmark",
    "wof:name":"IM Teknik",
    "wof:placetype":"venue"
},
  "geometry": {"coordinates":[8.5615940094,56.7530403137],"type":"Point"}
}