{
  "type": "Feature",
  "properties": {
    "addr:full":"Lumby-T\u00e5rup-Vej 73, Lumby-Torp Odense N Danmark 5270",
    "addr:housenumber":"73",
    "addr:postcode":"5270",
    "addr:street":"Lumby-Taarup-Vej;Lumby-Torp",
    "iso:country":"DK",
    "sg:address":"Lumby-T\u00e5rup-Vej 73, Lumby-Torp",
    "sg:city":"Odense N",
    "sg:orig_category":"Tegnere og tegnestuer",
    "sg:phone":"+45 65 95 49 50",
    "sg:postcode":"5270",
    "sg:province":"Danmark",
    "wof:name":"Tegnestuen Lumbyg",
    "wof:placetype":"venue"
},
  "geometry": {"coordinates":[10.3306798935,55.4711418152],"type":"Point"}
}