{
  "type": "Feature",
  "properties": {
    "addr:full":"Nordre Fasanvej 173 Frederiksberg Danmark 2000",
    "addr:housenumber":"173",
    "addr:postcode":"2000",
    "addr:street":"Nordre Fasanvej",
    "iso:country":"DK",
    "sg:address":"Nordre Fasanvej 173",
    "sg:city":"Frederiksberg",
    "sg:orig_category":"Elektro",
    "sg:phone":"+45 38 11 39 80",
    "sg:postcode":"2000",
    "sg:province":"Danmark",
    "wof:name":"JH Automation & Supply ApS",
    "wof:placetype":"venue"
},
  "geometry": {"coordinates":[12.5324964523,55.6933708191],"type":"Point"}
}