{
  "type": "Feature",
  "properties": {
    "addr:full":"R\u00e5dhustorvet 1 Farum Danmark 3520",
    "addr:housenumber":"1",
    "addr:postcode":"3520",
    "addr:street":"Raadhustorvet",
    "iso:country":"DK",
    "sg:address":"R\u00e5dhustorvet 1",
    "sg:city":"Farum",
    "sg:orig_category":"Ejendomshandel",
    "sg:phone":"+45 44 95 95 45",
    "sg:postcode":"3520",
    "sg:province":"Danmark",
    "sg:website":"www.nybolig.dk",
    "wof:name":"Nybolig, Michael Rasmussen",
    "wof:placetype":"venue"
},
  "geometry": {"coordinates":[12.376458168,55.8149757385],"type":"Point"}
}