{
  "type": "Feature",
  "properties": {
    "addr:full":"Rugv\u00e6nget 14 Vejle Danmark 7100",
    "addr:housenumber":"14",
    "addr:postcode":"7100",
    "addr:street":"Rugvaenget",
    "iso:country":"DK",
    "sg:address":"Rugv\u00e6nget 14",
    "sg:city":"Vejle",
    "sg:orig_category":"Personaleudvikling",
    "sg:phone":"+45 75 72 58 55",
    "sg:postcode":"7100",
    "sg:province":"Danmark",
    "wof:name":"IPU",
    "wof:placetype":"venue"
},
  "geometry": {"coordinates":[9.5368051529,55.7113952637],"type":"Point"}
}