{
  "type": "Feature",
  "properties": {
    "iso:country":"DK",
    "sg:address":"Toldbodvej 8",
    "sg:city":"Vejle",
    "sg:orig_category":"Slagterier",
    "sg:phone":"+45 75 82 00 99",
    "sg:postcode":"7100",
    "sg:province":"Danmark",
    "wof:name":"Vejle Eksportslagteri A/S",
    "wof:placetype":"venue"
},
  "geometry": {"coordinates":[9.5428495407,55.7053413391],"type":"Point"}
}