{
  "type": "Feature",
  "properties": {
    "addr:full":"Fj\u00e6llebrosvejen 80 Faaborg Danmark 5600",
    "addr:housenumber":"80",
    "addr:postcode":"5600",
    "addr:street":"Fjaellebrosvejen",
    "iso:country":"DK",
    "sg:address":"Fj\u00e6llebrosvejen 80",
    "sg:city":"Faaborg",
    "sg:orig_category":"Zoneterapeuter",
    "sg:phone":"+45 62 61 60 85",
    "sg:postcode":"5600",
    "sg:province":"Danmark",
    "wof:name":"Lassen, Conny",
    "wof:placetype":"venue"
},
  "geometry": {"coordinates":[10.3816165924,55.0603942871],"type":"Point"}
}