{
  "type": "Feature",
  "properties": {
    "addr:full":"R\u00f8sn\u00e6svej 187 A Kalundborg Danmark 4400",
    "addr:housenumber":"187 a",
    "addr:postcode":"4400",
    "addr:street":"Rosnaesvej",
    "iso:country":"DK",
    "sg:address":"R\u00f8sn\u00e6svej 187 A",
    "sg:city":"Kalundborg",
    "sg:orig_category":"Arkitekter",
    "sg:phone":"+45 59 50 85 96",
    "sg:postcode":"4400",
    "sg:province":"Danmark",
    "wof:name":"Birkeland, Thor",
    "wof:placetype":"venue"
},
  "geometry": {"coordinates":[11.0934085846,55.6797485352],"type":"Point"}
}