{
  "type": "Feature",
  "properties": {
    "iso:country":"DK",
    "sg:address":"N\u00f8rregade 10",
    "sg:city":"Galten",
    "sg:orig_category":"Kiosker",
    "sg:phone":"+45 86 94 42 63",
    "sg:postcode":"8464",
    "sg:province":"Danmark",
    "wof:name":"Galten Kiosk",
    "wof:placetype":"venue"
},
  "geometry": {"coordinates":[9.903719902,56.1558189392],"type":"Point"}
}