{
  "type": "Feature",
  "properties": {
    "addr:full":"Ramsherred 29 Aabenraa Danmark 6200",
    "addr:housenumber":"29",
    "addr:postcode":"6200",
    "addr:street":"Ramsherred",
    "iso:country":"DK",
    "sg:address":"Ramsherred 29",
    "sg:city":"Aabenraa",
    "sg:orig_category":"Garn",
    "sg:phone":"+45 74 62 23 62",
    "sg:postcode":"6200",
    "sg:province":"Danmark",
    "wof:name":"Ret og Vrang",
    "wof:placetype":"venue"
},
  "geometry": {"coordinates":[9.4184656143,55.0460891724],"type":"Point"}
}