{
  "type": "Feature",
  "properties": {
    "addr:full":"Stenskovvej 70, Stj\u00e6r Galten Danmark 8464",
    "addr:housenumber":"70",
    "addr:postcode":"8464",
    "addr:street":"Stenskovvej;Stjaer",
    "iso:country":"DK",
    "sg:address":"Stenskovvej 70, Stj\u00e6r",
    "sg:city":"Galten",
    "sg:orig_category":"Arkitekter",
    "sg:phone":"+45 86 95 07 11",
    "sg:postcode":"8464",
    "sg:province":"Danmark",
    "wof:name":"Stenskoven, Tegnestuen i",
    "wof:placetype":"venue"
},
  "geometry": {"coordinates":[9.9034748077,56.1558837891],"type":"Point"}
}