{
  "type": "Feature",
  "properties": {
    "iso:country":"DK",
    "sg:address":"Lunikvej 26 K",
    "sg:city":"Greve",
    "sg:orig_category":"Bogbinderier",
    "sg:phone":"+45 43 69 16 14",
    "sg:postcode":"2670",
    "sg:province":"Danmark",
    "wof:name":"Bogbinderen",
    "wof:placetype":"venue"
},
  "geometry": {"coordinates":[12.2941808701,55.5844078064],"type":"Point"}
}