{
  "type": "Feature",
  "properties": {
    "addr:full":"\u00d8stergade 5 Toftlund Danmark 6520",
    "addr:housenumber":"5",
    "addr:postcode":"6520",
    "addr:street":"Ostergade",
    "iso:country":"DK",
    "sg:address":"\u00d8stergade 5",
    "sg:city":"Toftlund",
    "sg:orig_category":"Web- og Internetdesign",
    "sg:phone":"+45 73 90 90 09",
    "sg:postcode":"6520",
    "sg:province":"Danmark",
    "sg:website":"www.ebit.dk",
    "wof:name":"E-Bit",
    "wof:placetype":"venue"
},
  "geometry": {"coordinates":[9.0647850037,55.1926498413],"type":"Point"}
}