{
  "type": "Feature",
  "properties": {
    "iso:country":"DK",
    "sg:address":"Gennem Bakkerne 8",
    "sg:city":"Vodskov",
    "sg:orig_category":"Handicapboliger",
    "sg:phone":"+45 98 29 34 24",
    "sg:postcode":"9310",
    "sg:province":"Danmark",
    "wof:name":"Hjemmet i Hammer Bakkker",
    "wof:placetype":"venue"
},
  "geometry": {"coordinates":[10.0265169144,57.1146430969],"type":"Point"}
}