{
  "type": "Feature",
  "properties": {
    "addr:full":"Kl\u00f8servejen 2  Bjerringbro Danmark 8850",
    "addr:housenumber":"2",
    "addr:postcode":"8850",
    "addr:street":"Kloservejen",
    "iso:country":"DK",
    "sg:address":"Kl\u00f8servejen 2 ",
    "sg:city":"Bjerringbro",
    "sg:classifiers":[
        {
            "category":"Farming",
            "subcategory":"Livestock Farm",
            "type":"Manufacturing & Wholesale Goods"
        }
    ],
    "sg:phone":"+45 86 68 16 55",
    "sg:postcode":"8850",
    "sg:province":"Danmark",
    "sg:tags":[
        "agriculture"
    ],
    "wof:name":"MASKINFABRIKKEN JE-MA A/S",
    "wof:placetype":"venue"
},
  "geometry": {"coordinates":[9.6371879578,56.3362236023],"type":"Point"}
}