{
  "type": "Feature",
  "properties": {
    "addr:full":"v/ Jakob R\u00f8lmer, Markledet 34 Ringk\u00f8bing Danmark 6950",
    "addr:housenumber":"34",
    "addr:postcode":"6950",
    "addr:street":"Markledet",
    "iso:country":"DK",
    "sg:address":"v/ Jakob R\u00f8lmer, Markledet 34",
    "sg:city":"Ringk\u00f8bing",
    "sg:orig_category":"Grundejerforeninger",
    "sg:phone":"+45 97 32 13 58",
    "sg:postcode":"6950",
    "sg:province":"Danmark",
    "wof:name":"Grundejerforeningen Bymarken",
    "wof:placetype":"venue"
},
  "geometry": {"coordinates":[-114.0767440796,46.4432487488],"type":"Point"}
}