{
  "type": "Feature",
  "properties": {
    "addr:full":"v/ Niels P. Bundgaard, \u00d8sterbakken 16, H\u00f8ruphav Sydals Danmark 6470",
    "addr:housenumber":"16",
    "addr:postcode":"6470",
    "addr:street":"Osterbakken;Horuphav",
    "iso:country":"DK",
    "sg:address":"v/ Niels P. Bundgaard, \u00d8sterbakken 16, H\u00f8ruphav",
    "sg:city":"Sydals",
    "sg:orig_category":"Grundejerforeninger",
    "sg:phone":"+45 74 41 58 71",
    "sg:postcode":"6470",
    "sg:province":"Danmark",
    "wof:name":"Grundejerforeningen, \u00d8sterbakken",
    "wof:placetype":"venue"
},
  "geometry": {"coordinates":[9.8924627304,54.9105377197],"type":"Point"}
}