{
  "type": "Feature",
  "properties": {
    "addr:full":"Dansbrovej 11 Sor\u00f8 Danmark 4180",
    "addr:housenumber":"11",
    "addr:postcode":"4180",
    "addr:street":"Dansbrovej",
    "iso:country":"DK",
    "sg:address":"Dansbrovej 11",
    "sg:city":"Sor\u00f8",
    "sg:orig_category":"Musikforlag",
    "sg:phone":"+45 57 84 48 41",
    "sg:postcode":"4180",
    "sg:province":"Danmark",
    "wof:name":"JL's Musikbureau",
    "wof:placetype":"venue"
},
  "geometry": {"coordinates":[-102.94467926030001,45.4534721375],"type":"Point"}
}