{
  "type": "Feature",
  "properties": {
    "addr:full":"N\u00f8rregade 14 Aalborg Danmark 9000",
    "addr:housenumber":"14",
    "addr:postcode":"9000",
    "addr:street":"Norregade",
    "iso:country":"DK",
    "sg:address":"N\u00f8rregade 14",
    "sg:city":"Aalborg",
    "sg:orig_category":"Iskiosker",
    "sg:phone":"+45 98 16 52 88",
    "sg:postcode":"9000",
    "sg:province":"Danmark",
    "wof:name":"Vaffelhuset",
    "wof:placetype":"venue"
},
  "geometry": {"coordinates":[9.9267454147,57.0465087891],"type":"Point"}
}