{
  "type": "Feature",
  "properties": {
    "addr:full":"Fmd.: Axel Kristoffersen, Vall\u00f8by Bygade 6, Vall\u00f8by K\u00f8ge Danmark 4600",
    "addr:housenumber":"6",
    "addr:postcode":"4600",
    "addr:street":"Bygade",
    "iso:country":"DK",
    "sg:address":"Fmd.: Axel Kristoffersen, Vall\u00f8by Bygade 6, Vall\u00f8by",
    "sg:city":"K\u00f8ge",
    "sg:orig_category":"Borger- og beboerforeninger",
    "sg:phone":"+45 56 26 64 20",
    "sg:postcode":"4600",
    "sg:province":"Danmark",
    "wof:name":"Vall\u00f8by Borgerforening",
    "wof:placetype":"venue"
},
  "geometry": {"coordinates":[-107.8339996338,40.0480003357],"type":"Point"}
}