{
  "type": "Feature",
  "properties": {
    "addr:full":"R\u00e5dhuset, Niels Espes Vej 8 Hedensted Danmark 8722",
    "addr:housenumber":"8",
    "addr:postcode":"8722",
    "addr:street":"Niels Espes Vej",
    "iso:country":"DK",
    "sg:address":"R\u00e5dhuset, Niels Espes Vej 8",
    "sg:city":"Hedensted",
    "sg:orig_category":"Kommunen",
    "sg:phone":"+45 79 74 11 11",
    "sg:postcode":"8722",
    "sg:province":"Danmark",
    "wof:name":"Hedensted Kommune",
    "wof:placetype":"venue"
},
  "geometry": {"coordinates":[9.697769165,55.7677726746],"type":"Point"}
}