{
  "type": "Feature",
  "properties": {
    "iso:country":"DK",
    "sg:address":"Storegade 12",
    "sg:city":"Broager",
    "sg:classifiers":[
        {
            "category":"Banks & Credit Unions",
            "subcategory":"Bank",
            "type":"Services"
        }
    ],
    "sg:phone":"+45 74 44 12 04",
    "sg:postcode":"6310",
    "sg:province":"Danmark",
    "sg:tags":[
        "banker"
    ],
    "wof:name":"Sydbank",
    "wof:placetype":"venue"
},
  "geometry": {"coordinates":[9.6742191315,54.8891525269],"type":"Point"}
}