{
  "type": "Feature",
  "properties": {
    "addr:full":"Sejlstrupvej 8, Hundelev L\u00f8kken Danmark 9480",
    "addr:housenumber":"8",
    "addr:postcode":"9480",
    "addr:street":"Sejlstrupvej;Lokken",
    "iso:country":"DK",
    "sg:address":"Sejlstrupvej 8, Hundelev",
    "sg:city":"L\u00f8kken",
    "sg:orig_category":"Integrerede institutioner",
    "sg:phone":"+45 99 67 14 50",
    "sg:postcode":"9480",
    "sg:province":"Danmark",
    "wof:name":"Regnbuen B\u00f8rneinstitution",
    "wof:placetype":"venue"
},
  "geometry": {"coordinates":[9.715880394,57.3703308105],"type":"Point"}
}