{
  "type": "Feature",
  "properties": {
    "iso:country":"DK",
    "sg:address":"Bredgade 26",
    "sg:city":"Videb\u00e6k",
    "sg:orig_category":"Dag- og distriktsblade",
    "sg:phone":"+45 97 17 20 46",
    "sg:postcode":"6920",
    "sg:province":"Danmark",
    "sg:website":"www.herningfolkeblad.dk",
    "wof:name":"Herning Folkeblad",
    "wof:placetype":"venue"
},
  "geometry": {"coordinates":[8.6312484741,56.0913848877],"type":"Point"}
}