{
  "type": "Feature",
  "properties": {
    "addr:full":"Tv\u00e6rgade 20 Kjellerup Danmark 8620",
    "addr:housenumber":"20",
    "addr:postcode":"8620",
    "addr:street":"Tvaergade",
    "iso:country":"DK",
    "sg:address":"Tv\u00e6rgade 20",
    "sg:city":"Kjellerup",
    "sg:orig_category":"Forsikringer",
    "sg:phone":"+45 86 88 11 75",
    "sg:postcode":"8620",
    "sg:province":"Danmark",
    "wof:name":"N\u00e6r-Brand",
    "wof:placetype":"venue"
},
  "geometry": {"coordinates":[9.4273424149,56.2904853821],"type":"Point"}
}