{
  "type": "Feature",
  "properties": {
    "addr:full":"Ving\u00e5rdsgade 10 Aalborg Danmark 9000",
    "addr:housenumber":"10",
    "addr:postcode":"9000",
    "addr:street":"Vingaardsgade",
    "iso:country":"DK",
    "sg:address":"Ving\u00e5rdsgade 10",
    "sg:city":"Aalborg",
    "sg:orig_category":"Supermarkeder",
    "sg:phone":"+45 98 13 61 00",
    "sg:postcode":"9000",
    "sg:province":"Danmark",
    "wof:name":"Super Brugsen",
    "wof:placetype":"venue"
},
  "geometry": {"coordinates":[9.9185476303,57.0471725464],"type":"Point"}
}