{
  "type": "Feature",
  "properties": {
    "addr:full":"Dalvej 9 Gentofte Danmark 2820",
    "addr:housenumber":"9",
    "addr:postcode":"2820",
    "addr:street":"Dalvej",
    "iso:country":"DK",
    "sg:address":"Dalvej 9",
    "sg:city":"Gentofte",
    "sg:orig_category":"Projekter",
    "sg:phone":"+45 39 63 29 29",
    "sg:postcode":"2820",
    "sg:province":"Danmark",
    "wof:name":"Innocon",
    "wof:placetype":"venue"
},
  "geometry": {"coordinates":[12.5503368378,55.761932373],"type":"Point"}
}