{
  "type": "Feature",
  "properties": {
    "addr:full":"Ndr. Ringvej 3, Rindum Ringk\u00f8bing Danmark 6950",
    "addr:housenumber":"3",
    "addr:postcode":"6950",
    "addr:street":"Ndr. Ringvej",
    "iso:country":"DK",
    "sg:address":"Ndr. Ringvej 3, Rindum",
    "sg:city":"Ringk\u00f8bing",
    "sg:orig_category":"Stenhuggere",
    "sg:phone":"+45 97 32 24 18",
    "sg:postcode":"6950",
    "sg:province":"Danmark",
    "wof:name":"Stenhuggerg\u00e5rden ApS",
    "wof:placetype":"venue"
},
  "geometry": {"coordinates":[-114.0767440796,46.4432487488],"type":"Point"}
}