{
  "type": "Feature",
  "properties": {
    "addr:full":"Jernbanegade 10 Fredericia Danmark 7000",
    "addr:housenumber":"10",
    "addr:postcode":"7000",
    "addr:street":"Jernbanegade",
    "iso:country":"DK",
    "sg:address":"Jernbanegade 10",
    "sg:city":"Fredericia",
    "sg:orig_category":"Museer",
    "sg:phone":"+45 72 10 69 80",
    "sg:postcode":"7000",
    "sg:province":"Danmark",
    "wof:name":"Bymuseet",
    "wof:placetype":"venue"
},
  "geometry": {"coordinates":[9.7459802628,55.5643730164],"type":"Point"}
}