{
  "type": "Feature",
  "properties": {
    "addr:full":"Frederiksborggade 22 K\u00f8benhavn Danmark 1360",
    "addr:housenumber":"22;1360",
    "addr:street":"Frederiksborggade",
    "iso:country":"DK",
    "sg:address":"Frederiksborggade 22",
    "sg:city":"K\u00f8benhavn",
    "sg:orig_category":"Videobutikker og -klubber",
    "sg:phone":"+45 33 91 09 03",
    "sg:postcode":"1360",
    "sg:province":"Danmark",
    "wof:name":"Christianshavn Video",
    "wof:placetype":"venue"
},
  "geometry": {"coordinates":[12.5662698746,55.6857414246],"type":"Point"}
}