{
  "type": "Feature",
  "properties": {
    "addr:full":"Lille Bl\u00f8devej 2 - 4 Frederikssund Danmark 3600",
    "addr:housenumber":"2 4",
    "addr:postcode":"3600",
    "addr:street":"Blodevej",
    "iso:country":"DK",
    "sg:address":"Lille Bl\u00f8devej 2 - 4",
    "sg:city":"Frederikssund",
    "sg:orig_category":"Trykkerier",
    "sg:phone":"+45 47 31 01 65",
    "sg:postcode":"3600",
    "sg:province":"Danmark",
    "wof:name":"Hugin Tryk",
    "wof:placetype":"venue"
},
  "geometry": {"coordinates":[12.0602607727,55.8353233337],"type":"Point"}
}