{
  "type": "Feature",
  "properties": {
    "addr:full":"Gevn\u00f8 Gade 17, Gevn\u00f8 Store Heddinge Danmark 4660",
    "addr:housenumber":"17",
    "addr:postcode":"4660",
    "addr:street":"Gevno Gade",
    "iso:country":"DK",
    "sg:address":"Gevn\u00f8 Gade 17, Gevn\u00f8",
    "sg:city":"Store Heddinge",
    "sg:orig_category":"Forsamlingshuse",
    "sg:phone":"+45 56 50 82 07",
    "sg:postcode":"4660",
    "sg:province":"Danmark",
    "wof:name":"Sydstevns Forsamlingshus",
    "wof:placetype":"venue"
},
  "geometry": {"coordinates":[12.3895797729,55.3113174438],"type":"Point"}
}