{
  "type": "Feature",
  "properties": {
    "iso:country":"DK",
    "sg:address":"Resenvej 46 A",
    "sg:city":"Skive",
    "sg:orig_category":"Kiosker",
    "sg:phone":"+45 97 52 25 25",
    "sg:postcode":"7800",
    "sg:province":"Danmark",
    "wof:name":"Resenvejs Kiosk",
    "wof:placetype":"venue"
},
  "geometry": {"coordinates":[9.0304422379,56.5753059387],"type":"Point"}
}