{
  "type": "Feature",
  "properties": {
    "addr:full":"Bytorvet 21 B Hedensted Danmark 8722",
    "addr:housenumber":"21 b",
    "addr:postcode":"8722",
    "addr:street":"Bytorvet",
    "iso:country":"DK",
    "sg:address":"Bytorvet 21 B",
    "sg:city":"Hedensted",
    "sg:orig_category":"Apoteker og -udsalg",
    "sg:phone":"+45 75 89 10 66",
    "sg:postcode":"8722",
    "sg:province":"Danmark",
    "wof:name":"Hedensted Apotek",
    "wof:placetype":"venue"
},
  "geometry": {"coordinates":[9.7005882263,55.7688407898],"type":"Point"}
}