{
  "type": "Feature",
  "properties": {
    "addr:full":"Ringstedgade 21 Roskilde Danmark 4000",
    "addr:housenumber":"21",
    "addr:postcode":"4000",
    "addr:street":"Ringstedgade",
    "iso:country":"DK",
    "sg:address":"Ringstedgade 21",
    "sg:city":"Roskilde",
    "sg:orig_category":"Autoreparation og -service",
    "sg:phone":"+45 46 36 93 64",
    "sg:postcode":"4000",
    "sg:province":"Danmark",
    "wof:name":"Kofod Auto, Frank",
    "wof:placetype":"venue"
},
  "geometry": {"coordinates":[12.0763950348,55.6386451721],"type":"Point"}
}