{
  "type": "Feature",
  "properties": {
    "addr:full":"Odensevej 22 Langeskov Danmark 5550",
    "addr:housenumber":"22",
    "addr:postcode":"5550",
    "addr:street":"Odensevej",
    "iso:country":"DK",
    "sg:address":"Odensevej 22",
    "sg:city":"Langeskov",
    "sg:orig_category":"Servicestationer",
    "sg:phone":"+45 65 38 10 22",
    "sg:postcode":"5550",
    "sg:province":"Danmark",
    "wof:name":"DK Benzin",
    "wof:placetype":"venue"
},
  "geometry": {"coordinates":[10.588526,55.362774],"type":"Point"}
}