{
  "type": "Feature",
  "properties": {
    "addr:full":"H\u00f8jkolvej 21, Hasle \u00c5rhus V Danmark 8210",
    "addr:housenumber":"21",
    "addr:postcode":"8210",
    "addr:street":"Hojkolvej",
    "iso:country":"DK",
    "sg:address":"H\u00f8jkolvej 21, Hasle",
    "sg:city":"\u00c5rhus V",
    "sg:classifiers":[
        {
            "category":"Restaurant",
            "type":"Food & Drink"
        }
    ],
    "sg:phone":"+45 86 15 48 18",
    "sg:postcode":"8210",
    "sg:province":"Danmark",
    "wof:name":"Johansen, Henning",
    "wof:placetype":"venue"
},
  "geometry": {"coordinates":[14.7065896988,55.1830787659],"type":"Point"}
}