{
  "type": "Feature",
  "properties": {
    "iso:country":"DK",
    "sg:address":"Jagtvej 139, 2 tv.",
    "sg:city":"K\u00f8benhavn N",
    "sg:orig_category":"Advokater",
    "sg:phone":"+45 35 81 88 10",
    "sg:postcode":"2200",
    "sg:province":"Danmark",
    "wof:name":"Guldbrandsen, Jesper N.",
    "wof:placetype":"venue"
},
  "geometry": {"coordinates":[-112.4224624634,36.7228736877],"type":"Point"}
}