{
  "type": "Feature",
  "properties": {
    "addr:full":"Helgavej 22 Odense M Danmark 5230",
    "addr:housenumber":"22",
    "addr:postcode":"5230",
    "addr:street":"Helgavej",
    "iso:country":"DK",
    "sg:address":"Helgavej 22",
    "sg:city":"Odense M",
    "sg:orig_category":"Faglige organisationer og foreninger",
    "sg:phone":"+45 66 12 52 05",
    "sg:postcode":"5230",
    "sg:province":"Danmark",
    "wof:name":"Dansk El-Forbund, Kreds 6 & Afd. 8",
    "wof:placetype":"venue"
},
  "geometry": {"coordinates":[10.3919487,55.3847465515],"type":"Point"}
}