{
  "type": "Feature",
  "properties": {
    "addr:full":"Fmd.: Finn Larsen, Sidingevej 15 A, Ulstrup Vig Danmark 4560",
    "addr:housenumber":"15 a",
    "addr:postcode":"4560",
    "addr:street":"Sidingevej",
    "iso:country":"DK",
    "sg:address":"Fmd.: Finn Larsen, Sidingevej 15 A, Ulstrup",
    "sg:city":"Vig",
    "sg:orig_category":"Hobbybetonede foreninger",
    "sg:phone":"+45 59 31 60 71",
    "sg:postcode":"4560",
    "sg:province":"Danmark",
    "wof:name":"Trundholm Walkie Klub, TW",
    "wof:placetype":"venue"
},
  "geometry": {"coordinates":[-82.79159545900001,39.2505378723],"type":"Point"}
}