{
  "type": "Feature",
  "properties": {
    "iso:country":"DK",
    "sg:address":"v/ Arne Larsen, Pr\u00e6st\u00f8vej 2",
    "sg:city":"Kalvehave",
    "sg:orig_category":"Hobbybetonede foreninger",
    "sg:phone":"+45 55 38 01 21",
    "sg:postcode":"4771",
    "sg:province":"Danmark",
    "wof:name":"Harmonikaspillerne Sydsj\u00e6lland",
    "wof:placetype":"venue"
},
  "geometry": {"coordinates":[12.1613817215,54.9965782166],"type":"Point"}
}