{
  "type": "Feature",
  "properties": {
    "addr:full":"Skovl\u00f8kken 10, Tarup Odense NV Danmark 5210",
    "addr:housenumber":"10",
    "addr:postcode":"5210",
    "addr:street":"Skovlokken",
    "iso:country":"DK",
    "sg:address":"Skovl\u00f8kken 10, Tarup",
    "sg:city":"Odense NV",
    "sg:classifiers":[
        {
            "category":"Professional",
            "subcategory":"Computer Services",
            "type":"Services"
        }
    ],
    "sg:phone":"+45 63 16 60 65",
    "sg:postcode":"5210",
    "sg:province":"Danmark",
    "sg:tags":[
        "edb",
        "-",
        "software"
    ],
    "wof:name":"Computing Solutions",
    "wof:placetype":"venue"
},
  "geometry": {"coordinates":[10.274764061,55.4303321838],"type":"Point"}
}