{
  "type": "Feature",
  "properties": {
    "addr:full":"Esperg\u00e6rde Centeret, Vester Torv 5, Esperg\u00e6rde Centret Esperg\u00e6rde Danmark 3060",
    "addr:housenumber":"5",
    "addr:postcode":"3060",
    "addr:street":"Vester Torv",
    "iso:country":"DK",
    "sg:address":"Esperg\u00e6rde Centeret, Vester Torv 5, Esperg\u00e6rde Centret",
    "sg:city":"Esperg\u00e6rde",
    "sg:orig_category":"Genbrugsbutikker",
    "sg:phone":"+45 49 13 52 22",
    "sg:postcode":"3060",
    "sg:province":"Danmark",
    "wof:name":"Kirkens Genbrug",
    "wof:placetype":"venue"
},
  "geometry": {"coordinates":[11.6512403488,47.8390617371],"type":"Point"}
}