{
  "type": "Feature",
  "properties": {
    "iso:country":"DK",
    "sg:address":"Hovedgaden 4 C",
    "sg:city":"Alling\u00e5bro",
    "sg:orig_category":"Dag- og distriktsblade",
    "sg:phone":"+45 86 48 15 55",
    "sg:postcode":"8961",
    "sg:province":"Danmark",
    "sg:website":"www.lokalavisen.dk",
    "wof:name":"Lokalavisen Rougs\u00f8-S\u00f8nderhald",
    "wof:placetype":"venue"
},
  "geometry": {"coordinates":[-73.92324829099999,40.8257446289],"type":"Point"}
}