{
  "type": "Feature",
  "properties": {
    "addr:full":"Maglestenen 25, Arnakke Vipper\u00f8d Danmark 4390",
    "addr:housenumber":"25",
    "addr:postcode":"4390",
    "addr:street":"Maglestenen",
    "iso:country":"DK",
    "sg:address":"Maglestenen 25, Arnakke",
    "sg:city":"Vipper\u00f8d",
    "sg:classifiers":[
        {
            "category":"Food & Beverages",
            "subcategory":"Liquor & Beverages",
            "type":"Retail Goods"
        }
    ],
    "sg:phone":"+45 59 18 25 25",
    "sg:postcode":"4390",
    "sg:province":"Danmark",
    "sg:tags":[
        "vin"
    ],
    "sg:website":"www.arnakkevinimport.dk",
    "wof:name":"Arnakke Vinimport",
    "wof:placetype":"venue"
},
  "geometry": {"coordinates":[11.770031929,55.6723098755],"type":"Point"}
}