{
  "type": "Feature",
  "properties": {
    "addr:full":"Fr\u00f8slev Bygade 8, Fr\u00f8slev Store Heddinge Danmark 4660",
    "addr:housenumber":"8",
    "addr:postcode":"4660",
    "addr:street":"Froslev Bygade",
    "iso:country":"DK",
    "sg:address":"Fr\u00f8slev Bygade 8, Fr\u00f8slev",
    "sg:city":"Store Heddinge",
    "sg:orig_category":"Forsamlingshuse",
    "sg:phone":"+45 56 50 82 67",
    "sg:postcode":"4660",
    "sg:province":"Danmark",
    "wof:name":"Fr\u00f8slev Forsamlingshus",
    "wof:placetype":"venue"
},
  "geometry": {"coordinates":[12.3895797729,55.3113174438],"type":"Point"}
}