{
  "type": "Feature",
  "properties": {
    "addr:full":"Vestergade 71 Odense C Danmark 5000",
    "addr:housenumber":"71",
    "addr:postcode":"5000",
    "addr:street":"Vestergade",
    "iso:country":"DK",
    "sg:address":"Vestergade 71",
    "sg:city":"Odense C",
    "sg:orig_category":"Sportsartikler",
    "sg:phone":"+45 66 13 02 22",
    "sg:postcode":"5000",
    "sg:province":"Danmark",
    "wof:name":"Larsen Sport ApS, Kurt",
    "wof:placetype":"venue"
},
  "geometry": {"coordinates":[10.3822278976,55.3946609497],"type":"Point"}
}