{
  "type": "Feature",
  "properties": {
    "iso:country":"DK",
    "sg:address":"Himmerlandsgade 106",
    "sg:city":"Aars",
    "sg:orig_category":"Bodegaer",
    "sg:phone":"+45 98 62 50 50",
    "sg:postcode":"9600",
    "sg:province":"Danmark",
    "wof:name":"Johannes V, Visev\u00e6rtshuset",
    "wof:placetype":"venue"
},
  "geometry": {"coordinates":[9.5130281448,56.8035316467],"type":"Point"}
}