{
  "type": "Feature",
  "properties": {
    "addr:full":"Turbinevej 1 Herlev Danmark 2730",
    "addr:housenumber":"1",
    "addr:postcode":"2730",
    "addr:street":"Turbinevej",
    "iso:country":"DK",
    "sg:address":"Turbinevej 1",
    "sg:city":"Herlev",
    "sg:orig_category":"Elektro",
    "sg:phone":"+45 44 92 91 70",
    "sg:postcode":"2730",
    "sg:province":"Danmark",
    "wof:name":"P.M. Elektro",
    "wof:placetype":"venue"
},
  "geometry": {"coordinates":[12.459774971,55.7327613831],"type":"Point"}
}