{
  "type": "Feature",
  "properties": {
    "iso:country":"DK",
    "sg:address":"Baneg\u00e5rdspladsen 4",
    "sg:city":"Nyk\u00f8bing",
    "sg:classifiers":[
        {
            "category":"Banks & Credit Unions",
            "subcategory":"Bank",
            "type":"Services"
        }
    ],
    "sg:phone":"+45 54 84 03 30",
    "sg:postcode":"4800",
    "sg:province":"Danmark",
    "sg:tags":[
        "banker"
    ],
    "wof:name":"BG Bank A/S",
    "wof:placetype":"venue"
},
  "geometry": {"coordinates":[-114.07682,46.443241],"type":"Point"}
}