{
  "type": "Feature",
  "properties": {
    "addr:full":"Skolevej 7 Ebeltoft Danmark 8400",
    "addr:housenumber":"7",
    "addr:postcode":"8400",
    "addr:street":"Skolevej",
    "iso:country":"DK",
    "sg:address":"Skolevej 7",
    "sg:city":"Ebeltoft",
    "sg:orig_category":"Kommunale ungdomsskoler",
    "sg:phone":"+45 86 34 12 74",
    "sg:postcode":"8400",
    "sg:province":"Danmark",
    "wof:name":"Ebeltoft Ungdomsskole",
    "wof:placetype":"venue"
},
  "geometry": {"coordinates":[10.6845369339,56.1965065002],"type":"Point"}
}