{
  "type": "Feature",
  "properties": {
    "addr:full":"S\u00f8ndergade 11 Kjellerup Danmark 8620",
    "addr:housenumber":"11",
    "addr:postcode":"8620",
    "addr:street":"Sondergade",
    "iso:country":"DK",
    "sg:address":"S\u00f8ndergade 11",
    "sg:city":"Kjellerup",
    "sg:orig_category":"Fotografer",
    "sg:phone":"+45 86 88 28 00",
    "sg:postcode":"8620",
    "sg:province":"Danmark",
    "wof:name":"Winther Foto",
    "wof:placetype":"venue"
},
  "geometry": {"coordinates":[9.4307203293,56.2887153625],"type":"Point"}
}