{
  "type": "Feature",
  "properties": {
    "addr:full":"Sj\u00f8rupvej 0 Viborg Danmark 8800",
    "addr:housenumber":"0",
    "addr:postcode":"8800",
    "addr:street":"Sjorupvej",
    "iso:country":"DK",
    "sg:address":"Sj\u00f8rupvej 0",
    "sg:city":"Viborg",
    "sg:orig_category":"Kirker",
    "sg:postcode":"8800",
    "sg:province":"Danmark",
    "wof:name":"Lysgaard Kirke",
    "wof:placetype":"venue"
},
  "geometry": {"coordinates":[9.4071502686,56.452671051],"type":"Point"}
}