{
  "type": "Feature",
  "properties": {
    "iso:country":"DK",
    "sg:address":"v/ Ellen Hyllested, Kannesh\u00f8jvej 6, Fjellerup",
    "sg:city":"Glesborg",
    "sg:orig_category":"Husflidsforeninger",
    "sg:postcode":"8585",
    "sg:province":"Danmark",
    "wof:name":"Fjellerup Husmoderforening",
    "wof:placetype":"venue"
},
  "geometry": {"coordinates":[10.5884723663,56.5124320984],"type":"Point"}
}