{
  "type": "Feature",
  "properties": {
    "addr:full":"L\u00f8gtvedvej 17, L\u00f8gtved Jyderup Danmark 4450",
    "addr:housenumber":"17",
    "addr:postcode":"4450",
    "addr:street":"Logtvedvej;Logtved",
    "iso:country":"DK",
    "sg:address":"L\u00f8gtvedvej 17, L\u00f8gtved",
    "sg:city":"Jyderup",
    "sg:orig_category":"Sommerhustilsyn",
    "sg:phone":"+45 58 25 00 23",
    "sg:postcode":"4450",
    "sg:province":"Danmark",
    "wof:name":"J.P. Ejendomsservice",
    "wof:placetype":"venue"
},
  "geometry": {"coordinates":[11.4029512405,55.6602401733],"type":"Point"}
}