{
  "type": "Feature",
  "properties": {
    "addr:full":"Algade 26 Ringe Danmark 5750",
    "addr:housenumber":"26",
    "addr:postcode":"5750",
    "addr:street":"Algade",
    "iso:country":"DK",
    "sg:address":"Algade 26",
    "sg:city":"Ringe",
    "sg:orig_category":"Benzinstationer",
    "sg:phone":"+45 62 62 22 67",
    "sg:postcode":"5750",
    "sg:province":"Danmark",
    "wof:name":"Statoil Servicenter",
    "wof:placetype":"venue"
},
  "geometry": {"coordinates":[10.4784555435,55.2362632751],"type":"Point"}
}