{
  "type": "Feature",
  "properties": {
    "iso:country":"DK",
    "sg:address":"Vejlevej 102 ",
    "sg:city":"Horsens",
    "sg:classifiers":[
        {
            "category":"Home & Garden",
            "subcategory":"Home Furnishings",
            "type":"Retail Goods"
        }
    ],
    "sg:phone":"+45 75 63 09 00",
    "sg:postcode":"8700",
    "sg:province":"Danmark",
    "sg:tags":[
        "household"
    ],
    "wof:name":"ENGELL M\u00d8BLER A/S",
    "wof:placetype":"venue"
},
  "geometry": {"coordinates":[9.8061361313,55.832824707],"type":"Point"}
}