{
  "type": "Feature",
  "properties": {
    "addr:full":"Industridalen 8, Johannesberg Lang\u00e5 Danmark 8870",
    "addr:housenumber":"8",
    "addr:postcode":"8870",
    "addr:street":"Industridalen",
    "iso:country":"DK",
    "sg:address":"Industridalen 8, Johannesberg",
    "sg:city":"Lang\u00e5",
    "sg:orig_category":"Maskinfabrikker",
    "sg:phone":"+45 86 46 21 00",
    "sg:postcode":"8870",
    "sg:province":"Danmark",
    "wof:name":"Dan-List A/S",
    "wof:placetype":"venue"
},
  "geometry": {"coordinates":[9.8955049515,56.3900756836],"type":"Point"}
}