{
  "type": "Feature",
  "properties": {
    "addr:full":"Brundlund Slot 1 Aabenraa Danmark 6200",
    "addr:housenumber":"1",
    "addr:postcode":"6200",
    "addr:street":"Brundlund Slot",
    "iso:country":"DK",
    "sg:address":"Brundlund Slot 1",
    "sg:city":"Aabenraa",
    "sg:orig_category":"Museer",
    "sg:phone":"+45 74 63 36 49",
    "sg:postcode":"6200",
    "sg:province":"Danmark",
    "wof:name":"Kunstmuseet",
    "wof:placetype":"venue"
},
  "geometry": {"coordinates":[9.4141139984,55.0396347046],"type":"Point"}
}