{
  "type": "Feature",
  "properties": {
    "iso:country":"DK",
    "sg:address":"Fmd.: Lissy Cramer, R\u00f8dtj\u00f8rnvej 33 B",
    "sg:city":"Herning",
    "sg:orig_category":"Husflidsforeninger",
    "sg:phone":"+45 97 21 15 06",
    "sg:postcode":"7400",
    "sg:province":"Danmark",
    "wof:name":"Herning Husmoderforening",
    "wof:placetype":"venue"
},
  "geometry": {"coordinates":[8.9768896103,56.1374168396],"type":"Point"}
}