{
  "type": "Feature",
  "properties": {
    "addr:full":"Valg\u00e5rdsvej 4 Valby Danmark 2500",
    "addr:housenumber":"4",
    "addr:postcode":"2500",
    "addr:street":"Valgaardsvej",
    "iso:country":"DK",
    "sg:address":"Valg\u00e5rdsvej 4",
    "sg:city":"Valby",
    "sg:orig_category":"\u00c3\u02dcvrige foreninger",
    "sg:phone":"+45 36 16 11 55",
    "sg:postcode":"2500",
    "sg:province":"Danmark",
    "wof:name":"Valby Netv\u00e6rksprojekt",
    "wof:placetype":"venue"
},
  "geometry": {"coordinates":[12.5184211731,55.6610984802],"type":"Point"}
}