{
  "type": "Feature",
  "properties": {
    "iso:country":"DK",
    "sg:address":"Blomsterv\u00e6nget 49 - 55, Rindum",
    "sg:city":"Ringk\u00f8bing",
    "sg:orig_category":"Handicapboliger",
    "sg:phone":"+45 97 32 31 44",
    "sg:postcode":"6950",
    "sg:province":"Danmark",
    "wof:name":"Blomsterv\u00e6nget Pensionat",
    "wof:placetype":"venue"
},
  "geometry": {"coordinates":[-114.0767440796,46.4432487488],"type":"Point"}
}