{
  "type": "Feature",
  "properties": {
    "addr:full":"Bomose Alle 9 Helsinge Danmark 3200",
    "addr:housenumber":"9",
    "addr:postcode":"3200",
    "addr:street":"Bomose Alle",
    "iso:country":"DK",
    "sg:address":"Bomose Alle 9",
    "sg:city":"Helsinge",
    "sg:orig_category":"Mobiltelefoner",
    "sg:phone":"+45 48 79 90 11",
    "sg:postcode":"3200",
    "sg:province":"Danmark",
    "wof:name":"Vic Helsinge",
    "wof:placetype":"venue"
},
  "geometry": {"coordinates":[12.1742696762,56.0205459595],"type":"Point"}
}