{
  "type": "Feature",
  "properties": {
    "addr:full":"Bl\u00e5g\u00e5rdsgade 16 A K\u00f8benhavn N Danmark 2200",
    "addr:housenumber":"16 a",
    "addr:postcode":"2200",
    "addr:street":"Blaagaardsgade;Kobenhavn N Danmark",
    "iso:country":"DK",
    "sg:address":"Bl\u00e5g\u00e5rdsgade 16 A",
    "sg:city":"K\u00f8benhavn N",
    "sg:orig_category":"Integrerede institutioner",
    "sg:phone":"+45 35 39 65 41",
    "sg:postcode":"2200",
    "sg:province":"Danmark",
    "wof:name":"Kvindecentrets pasningsordning",
    "wof:placetype":"venue"
},
  "geometry": {"coordinates":[-94.2525939941,47.9151039124],"type":"Point"}
}