{
  "type": "Feature",
  "properties": {
    "addr:full":"R\u00f8nshovedvej 12 Vejle Danmark 7100",
    "addr:housenumber":"12",
    "addr:postcode":"7100",
    "addr:street":"Ronshovedvej",
    "iso:country":"DK",
    "sg:address":"R\u00f8nshovedvej 12",
    "sg:city":"Vejle",
    "sg:orig_category":"Kemisk industri",
    "sg:phone":"+45 75 82 66 33",
    "sg:postcode":"7100",
    "sg:province":"Danmark",
    "wof:name":"Perskemi A/S",
    "wof:placetype":"venue"
},
  "geometry": {"coordinates":[9.5509719849,55.6953468323],"type":"Point"}
}