{
  "type": "Feature",
  "properties": {
    "iso:country":"DK",
    "sg:address":"Attemosevej 93, S\u00f8ller\u00f8d",
    "sg:city":"Holte",
    "sg:orig_category":"Hestepensioner",
    "sg:phone":"+45 45 56 55 99",
    "sg:postcode":"2840",
    "sg:province":"Danmark",
    "wof:name":"Attemoseg\u00e5rd Hestepension",
    "wof:placetype":"venue"
},
  "geometry": {"coordinates":[12.4706554413,55.8122367859],"type":"Point"}
}