{
  "type": "Feature",
  "properties": {
    "addr:full":"Kjellerupsgade 12 B, 1. Aalborg Danmark 9000",
    "addr:housenumber":"12 b 1",
    "addr:postcode":"9000",
    "addr:street":"Kjellerupsgade",
    "iso:country":"DK",
    "sg:address":"Kjellerupsgade 12 B, 1.",
    "sg:city":"Aalborg",
    "sg:orig_category":"Faglige organisationer og foreninger",
    "sg:phone":"+45 70 15 04 10",
    "sg:postcode":"9000",
    "sg:province":"Danmark",
    "wof:name":"Ejendomsfunktion\u00e6rernes Fagforening, Nordjylland",
    "wof:placetype":"venue"
},
  "geometry": {"coordinates":[9.9305076599,57.0451087952],"type":"Point"}
}