{
  "type": "Feature",
  "properties": {
    "addr:full":"Kattegatvej 16 Skagen Danmark 9990",
    "addr:housenumber":"16",
    "addr:postcode":"9990",
    "addr:street":"Kattegatvej",
    "iso:country":"DK",
    "sg:address":"Kattegatvej 16",
    "sg:city":"Skagen",
    "sg:orig_category":"Autoforhandlere",
    "sg:phone":"+45 98 44 23 66",
    "sg:postcode":"9990",
    "sg:province":"Danmark",
    "sg:website":"www.toyota-skagen.dk",
    "wof:name":"Toyota Skagen Autohj\u00f8rnet I/S",
    "wof:placetype":"venue"
},
  "geometry": {"coordinates":[10.5684108734,57.7266082764],"type":"Point"}
}