{
  "type": "Feature",
  "properties": {
    "addr:full":"Islevvangen 31 R\u00f8dovre Danmark 2610",
    "addr:housenumber":"31",
    "addr:postcode":"2610",
    "addr:street":"Islevvangen",
    "iso:country":"DK",
    "sg:address":"Islevvangen 31",
    "sg:city":"R\u00f8dovre",
    "sg:orig_category":"Kopiering",
    "sg:phone":"+45 44 53 43 02",
    "sg:postcode":"2610",
    "sg:province":"Danmark",
    "wof:name":"Streg & Tekst",
    "wof:placetype":"venue"
},
  "geometry": {"coordinates":[10.6992139816,61.1027755737],"type":"Point"}
}