{
  "type": "Feature",
  "properties": {
    "addr:full":"v/ Lotte A. Wissing, Kornager 401, Br\u00f8nsholm Kokkedal Danmark 2980",
    "addr:housenumber":"401",
    "addr:postcode":"2980",
    "addr:street":"Kornager;Bronsholm",
    "iso:country":"DK",
    "sg:address":"v/ Lotte A. Wissing, Kornager 401, Br\u00f8nsholm",
    "sg:city":"Kokkedal",
    "sg:orig_category":"Hobbybetonede foreninger",
    "sg:phone":"+45 49 18 05 52",
    "sg:postcode":"2980",
    "sg:province":"Danmark",
    "sg:website":"www.schaeferhund.dk/kreds82",
    "wof:name":"Sch\u00e6ferhundeklubben kreds 82",
    "wof:placetype":"venue"
},
  "geometry": {"coordinates":[12.4769096375,55.9091339111],"type":"Point"}
}