{
  "type": "Feature",
  "properties": {
    "addr:full":"Tinghusvej 4 Ry Danmark 8680",
    "addr:housenumber":"4",
    "addr:postcode":"8680",
    "addr:street":"Tinghusvej",
    "iso:country":"DK",
    "sg:address":"Tinghusvej 4",
    "sg:city":"Ry",
    "sg:orig_category":"Planteskoler",
    "sg:phone":"+45 86 89 16 22",
    "sg:postcode":"8680",
    "sg:province":"Danmark",
    "wof:name":"Rye N\u00f8rskov Skovdistrikt & Planteskole",
    "wof:placetype":"venue"
},
  "geometry": {"coordinates":[9.7016658783,56.0877838135],"type":"Point"}
}