{
  "type": "Feature",
  "properties": {
    "addr:full":"v/ Olav Christensen, Gyvelvej 19 N\u00f8rresundby Danmark 9400",
    "addr:housenumber":"19",
    "addr:postcode":"9400",
    "addr:street":"Gyvelvej",
    "iso:country":"DK",
    "sg:address":"v/ Olav Christensen, Gyvelvej 19",
    "sg:city":"N\u00f8rresundby",
    "sg:orig_category":"Grundejerforeninger",
    "sg:phone":"+45 98 17 38 74",
    "sg:postcode":"9400",
    "sg:province":"Danmark",
    "wof:name":"N\u00f8rre Uttrup Grundejerforening",
    "wof:placetype":"venue"
},
  "geometry": {"coordinates":[-120.56749725340001,41.2807998657],"type":"Point"}
}