{
  "type": "Feature",
  "properties": {
    "addr:full":"Kl\u00f8vmosevej 9 Ryslinge Danmark 5856",
    "addr:housenumber":"9",
    "addr:postcode":"5856",
    "addr:street":"Klovmosevej",
    "iso:country":"DK",
    "sg:address":"Kl\u00f8vmosevej 9",
    "sg:city":"Ryslinge",
    "sg:orig_category":"Cykler",
    "sg:phone":"+45 62 67 17 56",
    "sg:postcode":"5856",
    "sg:province":"Danmark",
    "sg:website":"www.mosquito-ryslinge.dk",
    "wof:name":"Fjellerup Cykel- & Knallertforretning",
    "wof:placetype":"venue"
},
  "geometry": {"coordinates":[10.5637578964,55.2349624634],"type":"Point"}
}