{
  "type": "Feature",
  "properties": {
    "addr:full":"Strandvejen 427 Henne Danmark 6854",
    "addr:housenumber":"427",
    "addr:postcode":"6854",
    "addr:street":"Strandvejen",
    "iso:country":"DK",
    "sg:address":"Strandvejen 427",
    "sg:city":"Henne",
    "sg:orig_category":"Brugskunst",
    "sg:phone":"+45 76 52 43 32",
    "sg:postcode":"6854",
    "sg:province":"Danmark",
    "wof:name":"Shop In",
    "wof:placetype":"venue"
},
  "geometry": {"coordinates":[8.178609848,55.7400894165],"type":"Point"}
}