{
  "type": "Feature",
  "properties": {
    "iso:country":"DK",
    "sg:address":"Vesterbyvej 12, \u00d8sterild",
    "sg:city":"Thisted",
    "sg:orig_category":"Tagmalere",
    "sg:phone":"+45 97 99 71 30",
    "sg:postcode":"7700",
    "sg:province":"Danmark",
    "wof:name":"Nielsen, Kim",
    "wof:placetype":"venue"
},
  "geometry": {"coordinates":[8.6919784546,56.9556121826],"type":"Point"}
}