{
  "type": "Feature",
  "properties": {
    "iso:country":"DK",
    "sg:address":"Gr\u00f8nnegade 51",
    "sg:city":"Stubbek\u00f8bing",
    "sg:orig_category":"Blikkenslagere",
    "sg:phone":"+45 54 44 18 78",
    "sg:postcode":"4850",
    "sg:province":"Danmark",
    "wof:name":"Madsen, Mogens",
    "wof:placetype":"venue"
},
  "geometry": {"coordinates":[-114.07674400000001,46.443249],"type":"Point"}
}