{
  "type": "Feature",
  "properties": {
    "addr:full":"Bredgade 15 Karup Danmark 7470",
    "addr:housenumber":"15",
    "addr:postcode":"7470",
    "addr:street":"Bredgade",
    "iso:country":"DK",
    "sg:address":"Bredgade 15",
    "sg:city":"Karup",
    "sg:orig_category":"Forsamlingshuse",
    "sg:phone":"+45 97 10 10 49",
    "sg:postcode":"7470",
    "sg:province":"Danmark",
    "wof:name":"Karup Forsamlingshus",
    "wof:placetype":"venue"
},
  "geometry": {"coordinates":[9.16522789,56.3076477051],"type":"Point"}
}