{
  "type": "Feature",
  "properties": {
    "addr:full":"v/ Counsellor Hans-Aage Steenberg, Daleg\u00e5rdsvej 12, Olsker Allinge Danmark 3770",
    "addr:housenumber":"12",
    "addr:postcode":"3770",
    "addr:street":"Steenberg Dalegaardsvej;Olsker",
    "iso:country":"DK",
    "sg:address":"v/ Counsellor Hans-Aage Steenberg, Daleg\u00e5rdsvej 12, Olsker",
    "sg:city":"Allinge",
    "sg:orig_category":"Loger",
    "sg:phone":"+45 56 48 05 27",
    "sg:postcode":"3770",
    "sg:province":"Danmark",
    "wof:name":"Hasle Rotary Klub",
    "wof:placetype":"venue"
},
  "geometry": {"coordinates":[14.7998552322,55.2743835449],"type":"Point"}
}