{
  "type": "Feature",
  "properties": {
    "addr:full":"v/ Ib Pedersen, Godsparken 98 Greve Danmark 2670",
    "addr:housenumber":"98",
    "addr:postcode":"2670",
    "addr:street":"Godsparken",
    "iso:country":"DK",
    "sg:address":"v/ Ib Pedersen, Godsparken 98",
    "sg:city":"Greve",
    "sg:orig_category":"Hobbybetonede foreninger",
    "sg:phone":"+45 43 90 38 02",
    "sg:postcode":"2670",
    "sg:province":"Danmark",
    "wof:name":"Hundeklubben i Albertslund",
    "wof:placetype":"venue"
},
  "geometry": {"coordinates":[12.2941808701,55.5844078064],"type":"Point"}
}