{
  "type": "Feature",
  "properties": {
    "addr:full":"Nordre Fasanvej 25 Frederiksberg Danmark 2000",
    "addr:housenumber":"25",
    "addr:postcode":"2000",
    "addr:street":"Nordre Fasanvej",
    "iso:country":"DK",
    "sg:address":"Nordre Fasanvej 25",
    "sg:city":"Frederiksberg",
    "sg:orig_category":"Supermarkeder",
    "sg:phone":"+45 38 86 98 00",
    "sg:postcode":"2000",
    "sg:province":"Danmark",
    "wof:name":"F\u00f8tex",
    "wof:placetype":"venue"
},
  "geometry": {"coordinates":[12.5226173401,55.6820106506],"type":"Point"}
}