{
  "type": "Feature",
  "properties": {
    "addr:full":"Drejervej 21, 3., Postboks 681 K\u00f8benhavn NV Danmark 2400",
    "addr:housenumber":"21 3;681",
    "addr:postcode":"2400",
    "addr:street":"Drejervej;Postboks",
    "iso:country":"DK",
    "sg:address":"Drejervej 21, 3., Postboks 681",
    "sg:city":"K\u00f8benhavn NV",
    "sg:classifiers":[
        {
            "category":"Communications",
            "type":"Services"
        }
    ],
    "sg:phone":"+45 70 20 40 01",
    "sg:postcode":"2400",
    "sg:province":"Danmark",
    "sg:tags":[
        "radio-",
        "og",
        "tv-stationer"
    ],
    "wof:name":"U-Lands TV",
    "wof:placetype":"venue"
},
  "geometry": {"coordinates":[-117.02272033689999,38.5024604797],"type":"Point"}
}