{
  "type": "Feature",
  "properties": {
    "addr:full":"Hovedgaden 30 Stenlille Danmark 4295",
    "addr:housenumber":"30",
    "addr:postcode":"4295",
    "addr:street":"Hovedgaden",
    "iso:country":"DK",
    "sg:address":"Hovedgaden 30",
    "sg:city":"Stenlille",
    "sg:orig_category":"Bagere",
    "sg:phone":"+45 57 80 40 97",
    "sg:postcode":"4295",
    "sg:province":"Danmark",
    "wof:name":"Stenlille Bageren",
    "wof:placetype":"venue"
},
  "geometry": {"coordinates":[11.587939,55.53756],"type":"Point"}
}