{
  "type": "Feature",
  "properties": {
    "addr:full":"Kass.: Anders Kr\u00f8ldrup, Kystvej 3 Frederikshavn Danmark 9900",
    "addr:housenumber":"3",
    "addr:postcode":"9900",
    "addr:street":"Kroldrup Kystvej",
    "iso:country":"DK",
    "sg:address":"Kass.: Anders Kr\u00f8ldrup, Kystvej 3",
    "sg:city":"Frederikshavn",
    "sg:orig_category":"Faglige organisationer og foreninger",
    "sg:phone":"+45 98 42 37 65",
    "sg:postcode":"9900",
    "sg:province":"Danmark",
    "wof:name":"Dansk Musiker Forbund, Frederikshavn Afdeling",
    "wof:placetype":"venue"
},
  "geometry": {"coordinates":[10.5362997055,57.4396400452],"type":"Point"}
}