{
  "type": "Feature",
  "properties": {
    "iso:country":"DK",
    "sg:address":"S\u00f8ndergade 20",
    "sg:city":"Galten",
    "sg:orig_category":"Sparekasser",
    "sg:phone":"+45 86 94 38 99",
    "sg:postcode":"8464",
    "sg:province":"Danmark",
    "wof:name":"Galten Sparekasse",
    "wof:placetype":"venue"
},
  "geometry": {"coordinates":[9.9028072357,56.1527442932],"type":"Point"}
}