{
  "type": "Feature",
  "properties": {
    "addr:full":"Vesterbro 1 Nyk\u00f8bing Danmark 4500",
    "addr:housenumber":"1",
    "addr:postcode":"4500",
    "addr:street":"Vesterbro",
    "iso:country":"DK",
    "sg:address":"Vesterbro 1",
    "sg:city":"Nyk\u00f8bing",
    "sg:orig_category":"Bogtrykkerier",
    "sg:phone":"+45 59 91 45 15",
    "sg:postcode":"4500",
    "sg:province":"Danmark",
    "wof:name":"Trykkerg\u00e5rden",
    "wof:placetype":"venue"
},
  "geometry": {"coordinates":[11.6107749939,55.938621521],"type":"Point"}
}