{
  "type": "Feature",
  "properties": {
    "addr:full":"Skibbrogade 1 Kalundborg Danmark 4400",
    "addr:housenumber":"1",
    "addr:postcode":"4400",
    "addr:street":"Skibbrogade",
    "iso:country":"DK",
    "sg:address":"Skibbrogade 1",
    "sg:city":"Kalundborg",
    "sg:orig_category":"Revisorer",
    "sg:phone":"+45 59 51 35 40",
    "sg:postcode":"4400",
    "sg:province":"Danmark",
    "wof:name":"PricewaterhouseCoopers",
    "wof:placetype":"venue"
},
  "geometry": {"coordinates":[11.0852594376,55.6780891418],"type":"Point"}
}