{
  "type": "Feature",
  "properties": {
    "iso:country":"DK",
    "sg:address":"Bernstorffsvej 127",
    "sg:city":"Hellerup",
    "sg:orig_category":"Sportsartikler",
    "sg:phone":"+45 39 62 95 14",
    "sg:postcode":"2900",
    "sg:province":"Danmark",
    "sg:website":"www.zogmatch.dk",
    "wof:name":"Z & Match",
    "wof:placetype":"venue"
},
  "geometry": {"coordinates":[12.5566596985,55.7421302795],"type":"Point"}
}