{
  "type": "Feature",
  "properties": {
    "addr:full":"Himmelbjergvej 20 Ry Danmark 8680",
    "addr:housenumber":"20",
    "addr:postcode":"8680",
    "addr:street":"Himmelbjergvej",
    "iso:country":"DK",
    "sg:address":"Himmelbjergvej 20",
    "sg:city":"Ry",
    "sg:orig_category":"HOTELS: OG MOTELLER",
    "sg:phone":"+45 86 89 80 45",
    "sg:postcode":"8680",
    "sg:province":"Danmark",
    "wof:name":"Himmelbjerget, Hotel",
    "wof:placetype":"venue"
},
  "geometry": {"coordinates":[9.6854534149,56.1015701294],"type":"Point"}
}