{
  "type": "Feature",
  "properties": {
    "iso:country":"DK",
    "sg:address":"R\u00f8rdalsvej 31",
    "sg:city":"Aalborg \u00d8",
    "sg:orig_category":"Non-Classified Establishments",
    "sg:phone":"+45 80 20 88 88",
    "sg:postcode":"9220",
    "sg:province":"Danmark",
    "wof:name":"Kuwait Petroleum Danmark A/S",
    "wof:placetype":"venue"
},
  "geometry": {"coordinates":[9.9675178528,57.0586471558],"type":"Point"}
}