{
  "type": "Feature",
  "properties": {
    "addr:full":"Sejet Bygade 39 Horsens Danmark 8700",
    "addr:housenumber":"39",
    "addr:postcode":"8700",
    "addr:street":"Sejet Bygade",
    "iso:country":"DK",
    "sg:address":"Sejet Bygade 39",
    "sg:city":"Horsens",
    "sg:orig_category":"Fodplejere",
    "sg:phone":"+45 75 68 22 29",
    "sg:postcode":"8700",
    "sg:province":"Danmark",
    "wof:name":"Sejet Fod- og hudklinik",
    "wof:placetype":"venue"
},
  "geometry": {"coordinates":[9.9280452728,55.8179512024],"type":"Point"}
}