{
  "type": "Feature",
  "properties": {
    "iso:country":"DK",
    "sg:address":"Adgangsvejen 9",
    "sg:city":"Esbjerg",
    "sg:orig_category":"Isolering",
    "sg:phone":"+45 75 13 83 33",
    "sg:postcode":"6700",
    "sg:province":"Danmark",
    "wof:name":"Nytech Isolering A/S",
    "wof:placetype":"venue"
},
  "geometry": {"coordinates":[8.4381790161,55.4670982361],"type":"Point"}
}