{
  "type": "Feature",
  "properties": {
    "addr:full":"Birkebakken 22 Odense S Danmark 5260",
    "addr:housenumber":"22",
    "addr:postcode":"5260",
    "addr:street":"Birkebakken",
    "iso:country":"DK",
    "sg:address":"Birkebakken 22",
    "sg:city":"Odense S",
    "sg:orig_category":"Metalvarefabrikker",
    "sg:phone":"+45 66 15 29 38",
    "sg:postcode":"5260",
    "sg:province":"Danmark",
    "wof:name":"Bellinge Drivhusservice",
    "wof:placetype":"venue"
},
  "geometry": {"coordinates":[10.3556947708,55.3450469971],"type":"Point"}
}