{
  "type": "Feature",
  "properties": {
    "addr:full":"Daug\u00e5rdvej 32 Hedensted Danmark 8722",
    "addr:housenumber":"32",
    "addr:postcode":"8722",
    "addr:street":"Daugaardvej",
    "iso:country":"DK",
    "sg:address":"Daug\u00e5rdvej 32",
    "sg:city":"Hedensted",
    "sg:orig_category":"Murermestre",
    "sg:phone":"+45 75 89 01 09",
    "sg:postcode":"8722",
    "sg:province":"Danmark",
    "wof:name":"Medio-Byg Aps",
    "wof:placetype":"venue"
},
  "geometry": {"coordinates":[9.700261116,55.7532844543],"type":"Point"}
}