{
  "type": "Feature",
  "properties": {
    "addr:full":"Fmd.: Laurids Mortensen, Trombakken 6 Snedsted Danmark 7752",
    "addr:housenumber":"6",
    "addr:postcode":"7752",
    "addr:street":"Laurids Mortensen Trombakken",
    "iso:country":"DK",
    "sg:address":"Fmd.: Laurids Mortensen, Trombakken 6",
    "sg:city":"Snedsted",
    "sg:orig_category":"Musik og sang",
    "sg:phone":"+45 97 93 49 49",
    "sg:postcode":"7752",
    "sg:province":"Danmark",
    "sg:website":"www.teutoner.dk",
    "wof:name":"Teutonernes Rejse",
    "wof:placetype":"venue"
},
  "geometry": {"coordinates":[8.5276002884,56.8460388184],"type":"Point"}
}