{
  "type": "Feature",
  "properties": {
    "addr:full":"\u00d8stergade 15 Frederikssund Danmark 3600",
    "addr:housenumber":"15",
    "addr:postcode":"3600",
    "addr:street":"Ostergade",
    "iso:country":"DK",
    "sg:address":"\u00d8stergade 15",
    "sg:city":"Frederikssund",
    "sg:classifiers":[
        {
            "category":"Banks & Credit Unions",
            "subcategory":"Bank",
            "type":"Services"
        }
    ],
    "sg:phone":"+45 47 36 06 06",
    "sg:postcode":"3600",
    "sg:province":"Danmark",
    "sg:tags":[
        "banker"
    ],
    "wof:name":"Jyske Bank",
    "wof:placetype":"venue"
},
  "geometry": {"coordinates":[12.0617904663,55.8396072388],"type":"Point"}
}