{
  "type": "Feature",
  "properties": {
    "addr:full":"Blegbanken 3, 2. Vejle Danmark 7100",
    "addr:housenumber":"3 2",
    "addr:postcode":"7100",
    "addr:street":"Blegbanken",
    "iso:country":"DK",
    "sg:address":"Blegbanken 3, 2.",
    "sg:city":"Vejle",
    "sg:classifiers":[
        {
            "category":"Social Services",
            "subcategory":"Child Care",
            "type":"Services"
        }
    ],
    "sg:phone":"+45 76 40 53 53",
    "sg:postcode":"7100",
    "sg:province":"Danmark",
    "sg:tags":[
        "hospice"
    ],
    "wof:name":"Sct. Maria Hospice Center",
    "wof:placetype":"venue"
},
  "geometry": {"coordinates":[9.5307245255,55.7077217102],"type":"Point"}
}