{
  "type": "Feature",
  "properties": {
    "addr:full":"A. S. \u00d8rsteds Vej 37 Viborg Danmark 8800",
    "addr:housenumber":"37",
    "addr:postcode":"8800",
    "addr:street":"A.;Orsteds Vej",
    "iso:country":"DK",
    "sg:address":"A. S. \u00d8rsteds Vej 37",
    "sg:city":"Viborg",
    "sg:orig_category":"Revisorer",
    "sg:phone":"+45 86 60 29 66",
    "sg:postcode":"8800",
    "sg:province":"Danmark",
    "sg:website":"www.deconorth.dk",
    "wof:name":"B\u00f8gelund, Verner",
    "wof:placetype":"venue"
},
  "geometry": {"coordinates":[9.395113945,56.451965332],"type":"Point"}
}