{
  "type": "Feature",
  "properties": {
    "addr:full":"Jomfru Ane Gade 3 Aalborg Danmark 9000",
    "addr:housenumber":"3",
    "addr:postcode":"9000",
    "addr:street":"Jomfru Ane Gade",
    "iso:country":"DK",
    "sg:address":"Jomfru Ane Gade 3",
    "sg:city":"Aalborg",
    "sg:orig_category":"Diskoteker",
    "sg:phone":"+45 98 16 37 08",
    "sg:postcode":"9000",
    "sg:province":"Danmark",
    "wof:name":"Jomfru Ane's Dansebar",
    "wof:placetype":"venue"
},
  "geometry": {"coordinates":[9.9183721542,57.0496368408],"type":"Point"}
}