{
  "type": "Feature",
  "properties": {
    "addr:full":"Bredgade 102 Bording Danmark 7441",
    "addr:housenumber":"102",
    "addr:postcode":"7441",
    "addr:street":"Bredgade",
    "iso:country":"DK",
    "sg:address":"Bredgade 102",
    "sg:city":"Bording",
    "sg:orig_category":"Servicestationer",
    "sg:phone":"+45 86 86 11 99",
    "sg:postcode":"7441",
    "sg:province":"Danmark",
    "wof:name":"Statoil Servicenter",
    "wof:placetype":"venue"
},
  "geometry": {"coordinates":[9.2849760056,56.1402854919],"type":"Point"}
}