{
  "type": "Feature",
  "properties": {
    "iso:country":"DK",
    "sg:address":"Bredgade 102",
    "sg:city":"Bording",
    "sg:orig_category":"Servicestationer",
    "sg:phone":"+45 86 86 11 99",
    "sg:postcode":"7441",
    "sg:province":"Danmark",
    "wof:name":"Statoil Servicenter",
    "wof:placetype":"venue"
},
  "geometry": {"coordinates":[9.2849760056,56.1402854919],"type":"Point"}
}