{
  "type": "Feature",
  "properties": {
    "iso:country":"DK",
    "sg:address":"Snedkervej 17",
    "sg:city":"Esbjerg V",
    "sg:orig_category":"Serigrafi",
    "sg:phone":"+45 75 15 66 66",
    "sg:postcode":"6710",
    "sg:province":"Danmark",
    "sg:website":"www.ehserigrafi.dk",
    "wof:name":"EH Serigrafi ApS",
    "wof:placetype":"venue"
},
  "geometry": {"coordinates":[8.41424,55.504528],"type":"Point"}
}