{
  "type": "Feature",
  "properties": {
    "addr:full":"Buldreg\u00e5rdsvej 6, Nyker R\u00f8nne Danmark 3700",
    "addr:housenumber":"6",
    "addr:postcode":"3700",
    "addr:street":"Buldregaardsvej",
    "iso:country":"DK",
    "sg:address":"Buldreg\u00e5rdsvej 6, Nyker",
    "sg:city":"R\u00f8nne",
    "sg:classifiers":[
        {
            "category":"Communications",
            "type":"Services"
        }
    ],
    "sg:phone":"+45 56 96 32 17",
    "sg:postcode":"3700",
    "sg:province":"Danmark",
    "sg:tags":[
        "og",
        "tv",
        "radio"
    ],
    "wof:name":"Bimo Elektronik",
    "wof:placetype":"venue"
},
  "geometry": {"coordinates":[14.6975498199,55.0993003845],"type":"Point"}
}