{
  "type": "Feature",
  "properties": {
    "iso:country":"DK",
    "sg:address":"Fredericiavej 2 B",
    "sg:city":"Vejle",
    "sg:classifiers":[
        {
            "category":"Personal",
            "subcategory":"Massage",
            "type":"Services"
        }
    ],
    "sg:phone":"+45 75 83 22 99",
    "sg:postcode":"7100",
    "sg:province":"Danmark",
    "wof:name":"Hummel, Inge",
    "wof:placetype":"venue"
},
  "geometry": {"coordinates":[9.5361404419,55.6993217468],"type":"Point"}
}