{
  "type": "Feature",
  "properties": {
    "addr:full":"M\u00f8ntmestervej 31 K\u00f8benhavn NV Danmark 2400",
    "addr:housenumber":"31",
    "addr:postcode":"2400",
    "addr:street":"Montmestervej",
    "iso:country":"DK",
    "sg:address":"M\u00f8ntmestervej 31",
    "sg:city":"K\u00f8benhavn NV",
    "sg:orig_category":"Facadebehandling",
    "sg:phone":"+45 38 17 17 17",
    "sg:postcode":"2400",
    "sg:province":"Danmark",
    "sg:website":"www.iss.dk",
    "wof:name":"ISS Reng\u00f8ring",
    "wof:placetype":"venue"
},
  "geometry": {"coordinates":[-117.02272033689999,38.5024604797],"type":"Point"}
}