{
  "type": "Feature",
  "properties": {
    "addr:full":"Ivigtutvej 70 Esbjerg N Danmark 6715",
    "addr:housenumber":"70",
    "addr:postcode":"6715",
    "addr:street":"Ivigtutvej",
    "iso:country":"DK",
    "sg:address":"Ivigtutvej 70",
    "sg:city":"Esbjerg N",
    "sg:orig_category":"Fodplejere",
    "sg:phone":"+45 75 15 58 77",
    "sg:postcode":"6715",
    "sg:province":"Danmark",
    "wof:name":"Danielsen, Oddv\u00f8r",
    "wof:placetype":"venue"
},
  "geometry": {"coordinates":[8.452296257,55.5120925903],"type":"Point"}
}