{
  "type": "Feature",
  "properties": {
    "addr:full":"R\u00f8rmosen 5 Roskilde Danmark 4000",
    "addr:housenumber":"5",
    "addr:postcode":"4000",
    "addr:street":"Rormosen",
    "iso:country":"DK",
    "sg:address":"R\u00f8rmosen 5",
    "sg:city":"Roskilde",
    "sg:orig_category":"Integrerede institutioner",
    "sg:phone":"+45 46 36 48 42",
    "sg:postcode":"4000",
    "sg:province":"Danmark",
    "wof:name":"B\u00f8rnehuset R\u00f8rmosen",
    "wof:placetype":"venue"
},
  "geometry": {"coordinates":[12.0909376144,55.6404838562],"type":"Point"}
}