{
  "type": "Feature",
  "properties": {
    "iso:country":"DK",
    "sg:address":"Industrivej 14, Postboks 230",
    "sg:city":"Roskilde",
    "sg:orig_category":"Kaffe og the",
    "sg:phone":"+45 46 75 53 00",
    "sg:postcode":"4000",
    "sg:province":"Danmark",
    "wof:name":"I. M. Frellsen K/S",
    "wof:placetype":"venue"
},
  "geometry": {"coordinates":[12.0909376144,55.6404838562],"type":"Point"}
}