{
  "type": "Feature",
  "properties": {
    "addr:full":"Ramsherred 38 Aabenraa Danmark 6200",
    "addr:housenumber":"38",
    "addr:postcode":"6200",
    "addr:street":"Ramsherred",
    "iso:country":"DK",
    "sg:address":"Ramsherred 38",
    "sg:city":"Aabenraa",
    "sg:orig_category":"Chokolade",
    "sg:phone":"+45 74 62 70 98",
    "sg:postcode":"6200",
    "sg:province":"Danmark",
    "wof:name":"Oles Chokolade",
    "wof:placetype":"venue"
},
  "geometry": {"coordinates":[9.4183740616,55.0453643799],"type":"Point"}
}