{
  "type": "Feature",
  "properties": {
    "addr:full":"R\u00f8deledsvej 73 Svendborg Danmark 5700",
    "addr:housenumber":"73",
    "addr:postcode":"5700",
    "addr:street":"Rodeledsvej",
    "iso:country":"DK",
    "sg:address":"R\u00f8deledsvej 73",
    "sg:city":"Svendborg",
    "sg:orig_category":"Kirker og trossamfund u. f. folkekirken",
    "sg:phone":"+45 62 22 84 92",
    "sg:postcode":"5700",
    "sg:province":"Danmark",
    "wof:name":"Jehovas Vidner",
    "wof:placetype":"venue"
},
  "geometry": {"coordinates":[10.5992298126,55.0720214844],"type":"Point"}
}