{
  "type": "Feature",
  "properties": {
    "addr:full":"Greve Center 6 D Greve Danmark 2670",
    "addr:housenumber":"6",
    "addr:postcode":"2670",
    "addr:street":"D",
    "iso:country":"DK",
    "sg:address":"Greve Center 6 D",
    "sg:city":"Greve",
    "sg:orig_category":"Gymnastik- og motionsredskaber",
    "sg:phone":"+45 43 90 00 33",
    "sg:postcode":"2670",
    "sg:province":"Danmark",
    "wof:name":"Sport X-tra",
    "wof:placetype":"venue"
},
  "geometry": {"coordinates":[12.2755298615,55.595451355],"type":"Point"}
}