{
  "type": "Feature",
  "properties": {
    "addr:full":"Rosenhavestr\u00e6de 2 B Roskilde Danmark 4000",
    "addr:housenumber":"2 b",
    "addr:postcode":"4000",
    "addr:street":"Rosenhavestraede",
    "iso:country":"DK",
    "sg:address":"Rosenhavestr\u00e6de 2 B",
    "sg:city":"Roskilde",
    "sg:classifiers":[
        {
            "category":"Restaurant",
            "type":"Food & Drink"
        }
    ],
    "sg:phone":"+45 46 35 03 15",
    "sg:postcode":"4000",
    "sg:province":"Danmark",
    "wof:name":"Satchmo, Cafe",
    "wof:placetype":"venue"
},
  "geometry": {"coordinates":[12.0909376144,55.6404838562],"type":"Point"}
}