{
  "type": "Feature",
  "properties": {
    "addr:full":"Sydvestkajen 4  Hirtshals Danmark 9850",
    "addr:housenumber":"4",
    "addr:postcode":"9850",
    "addr:street":"Sydvestkajen",
    "iso:country":"DK",
    "sg:address":"Sydvestkajen 4 ",
    "sg:city":"Hirtshals",
    "sg:classifiers":[
        {
            "category":"Autos & Motor Vehicles",
            "subcategory":"Boat Sales",
            "type":"Retail Goods"
        }
    ],
    "sg:phone":"+45 98 94 44 55",
    "sg:postcode":"9850",
    "sg:province":"Danmark",
    "wof:name":"KARLSSON BEDDING APS",
    "wof:placetype":"venue"
},
  "geometry": {"coordinates":[9.9576597214,57.5922393799],"type":"Point"}
}