{
  "type": "Feature",
  "properties": {
    "addr:full":"Klintevej 22, Klinte Bogense Danmark 5400",
    "addr:housenumber":"22",
    "addr:postcode":"5400",
    "addr:street":"Klintevej",
    "iso:country":"DK",
    "sg:address":"Klintevej 22, Klinte",
    "sg:city":"Bogense",
    "sg:orig_category":"Kirker",
    "sg:postcode":"5400",
    "sg:province":"Danmark",
    "wof:name":"Klinte Kirke",
    "wof:placetype":"venue"
},
  "geometry": {"coordinates":[10.0943098068,55.5637893677],"type":"Point"}
}