{
  "type": "Feature",
  "properties": {
    "addr:full":"Heldumvej 4 Lemvig Danmark 7620",
    "addr:housenumber":"4",
    "addr:postcode":"7620",
    "addr:street":"Heldumvej",
    "iso:country":"DK",
    "sg:address":"Heldumvej 4",
    "sg:city":"Lemvig",
    "sg:orig_category":"Kiosker",
    "sg:phone":"+45 97 82 08 21",
    "sg:postcode":"7620",
    "sg:province":"Danmark",
    "wof:name":"Heldumvejs Kiosk",
    "wof:placetype":"venue"
},
  "geometry": {"coordinates":[8.2959594727,56.5482673645],"type":"Point"}
}