{
  "type": "Feature",
  "properties": {
    "addr:full":"Fmd.: N. Feilberg J\u00f8rgensen, Odense Domhus, Albanigade 28 Odense C Danmark 5000",
    "addr:housenumber":"28",
    "addr:postcode":"5000",
    "addr:street":"Jorgensen;Albanigade",
    "iso:country":"DK",
    "sg:address":"Fmd.: N. Feilberg J\u00f8rgensen, Odense Domhus, Albanigade 28",
    "sg:city":"Odense C",
    "sg:orig_category":"Faglige organisationer og foreninger",
    "sg:phone":"+45 66 11 47 12",
    "sg:postcode":"5000",
    "sg:province":"Danmark",
    "wof:name":"Juridisk Forening for Fyn",
    "wof:placetype":"venue"
},
  "geometry": {"coordinates":[10.390794754,55.3961715698],"type":"Point"}
}