{
  "type": "Feature",
  "properties": {
    "addr:full":"Langk\u00e6rvej 35 Brande Danmark 7330",
    "addr:housenumber":"35",
    "addr:postcode":"7330",
    "addr:street":"Langkaervej",
    "iso:country":"DK",
    "sg:address":"Langk\u00e6rvej 35",
    "sg:city":"Brande",
    "sg:orig_category":"Autoreparation og -service",
    "sg:phone":"+45 96 42 02 22",
    "sg:postcode":"7330",
    "sg:province":"Danmark",
    "wof:name":"Last og Bus Brande",
    "wof:placetype":"venue"
},
  "geometry": {"coordinates":[9.1366691589,55.9177894592],"type":"Point"}
}