{
  "type": "Feature",
  "properties": {
    "addr:full":"Vesterm\u00f8llevej 22, Fruering Skanderborg Danmark 8660",
    "addr:housenumber":"22",
    "addr:postcode":"8660",
    "addr:street":"Vestermollevej;Fruering",
    "iso:country":"DK",
    "sg:address":"Vesterm\u00f8llevej 22, Fruering",
    "sg:city":"Skanderborg",
    "sg:orig_category":"Forsamlingshuse",
    "sg:phone":"+45 86 52 07 60",
    "sg:postcode":"8660",
    "sg:province":"Danmark",
    "wof:name":"Fruering Forsamlingshus",
    "wof:placetype":"venue"
},
  "geometry": {"coordinates":[9.929974556,56.0380249023],"type":"Point"}
}