{
  "type": "Feature",
  "properties": {
    "addr:full":"K\u00e6r M\u00f8llevej 19, Aller Christiansfeld Danmark 6070",
    "addr:housenumber":"19",
    "addr:postcode":"6070",
    "addr:street":"Mollevej",
    "iso:country":"DK",
    "sg:address":"K\u00e6r M\u00f8llevej 19, Aller",
    "sg:city":"Christiansfeld",
    "sg:orig_category":"Private- og friskoler",
    "sg:phone":"+45 74 56 16 92",
    "sg:postcode":"6070",
    "sg:province":"Danmark",
    "wof:name":"Aller Friskole",
    "wof:placetype":"venue"
},
  "geometry": {"coordinates":[9.4834346771,55.3550567627],"type":"Point"}
}