{
  "type": "Feature",
  "properties": {
    "addr:full":"Langbyg\u00e5rdsvej 14 Glamsbjerg Danmark 5620",
    "addr:housenumber":"14",
    "addr:postcode":"5620",
    "addr:street":"Langbygaardsvej",
    "iso:country":"DK",
    "sg:address":"Langbyg\u00e5rdsvej 14",
    "sg:city":"Glamsbjerg",
    "sg:orig_category":"Efterskoler",
    "sg:phone":"+45 64 72 39 05",
    "sg:postcode":"5620",
    "sg:province":"Danmark",
    "wof:name":"Sydvestfyns Efterskole",
    "wof:placetype":"venue"
},
  "geometry": {"coordinates":[10.1146087646,55.2715873718],"type":"Point"}
}