{
  "type": "Feature",
  "properties": {
    "addr:full":"Lyngby Hovedgade 28 Kongens Lyngby Danmark 2800",
    "addr:housenumber":"28",
    "addr:postcode":"2800",
    "addr:street":"Lyngby Hovedgade",
    "iso:country":"DK",
    "sg:address":"Lyngby Hovedgade 28",
    "sg:city":"Kongens Lyngby",
    "sg:orig_category":"Biblioteker",
    "sg:phone":"+45 45 97 37 00",
    "sg:postcode":"2800",
    "sg:province":"Danmark",
    "wof:name":"Stadsbiblioteket i Lyngby",
    "wof:placetype":"venue"
},
  "geometry": {"coordinates":[12.499589,55.773193],"type":"Point"}
}