{
  "type": "Feature",
  "properties": {
    "addr:full":"Hellerupvej 5 Hellerup Danmark 2900",
    "addr:housenumber":"5",
    "addr:postcode":"2900",
    "addr:street":"Hellerupvej",
    "iso:country":"DK",
    "sg:address":"Hellerupvej 5",
    "sg:city":"Hellerup",
    "sg:orig_category":"Tandklinikker, Kommunale",
    "sg:phone":"+45 39 62 35 66",
    "sg:postcode":"2900",
    "sg:province":"Danmark",
    "wof:name":"Centraltandklinikken",
    "wof:placetype":"venue"
},
  "geometry": {"coordinates":[12.5744533539,55.7314376831],"type":"Point"}
}