{
  "type": "Feature",
  "properties": {
    "addr:full":"v/ K\u00f8bmand Th\u00f8fner, Kalvehavevej 2 B Mern Danmark 4735",
    "addr:housenumber":"2 b",
    "addr:postcode":"4735",
    "addr:street":"Kalvehavevej",
    "iso:country":"DK",
    "sg:address":"v/ K\u00f8bmand Th\u00f8fner, Kalvehavevej 2 B",
    "sg:city":"Mern",
    "sg:orig_category":"Posthuse",
    "sg:phone":"+45 55 93 08 09",
    "sg:postcode":"4735",
    "sg:province":"Danmark",
    "wof:name":"Post Danmark, Samdriftsposthus Mern",
    "wof:placetype":"venue"
},
  "geometry": {"coordinates":[12.0578746796,55.049079895],"type":"Point"}
}