{
  "type": "Feature",
  "properties": {
    "addr:full":"Fmd.: Bent J\u00f8rgensen, \u00c5havevej 6 Silkeborg Danmark 8600",
    "addr:housenumber":"6",
    "addr:postcode":"8600",
    "addr:street":"Aahavevej",
    "iso:country":"DK",
    "sg:address":"Fmd.: Bent J\u00f8rgensen, \u00c5havevej 6",
    "sg:city":"Silkeborg",
    "sg:orig_category":"Faglige organisationer og foreninger",
    "sg:phone":"+45 86 82 98 62",
    "sg:postcode":"8600",
    "sg:province":"Danmark",
    "wof:name":"Ledernes Hovedorganisation Silkeborg Afdeling",
    "wof:placetype":"venue"
},
  "geometry": {"coordinates":[9.5524425507,56.1693305969],"type":"Point"}
}