{
  "type": "Feature",
  "properties": {
    "iso:country":"DK",
    "sg:address":"Oddevej 1, K\u00f8belev",
    "sg:city":"Nakskov",
    "sg:orig_category":"Malermestre",
    "sg:phone":"+45 54 90 30 70",
    "sg:postcode":"4900",
    "sg:province":"Danmark",
    "wof:name":"Rasmussen, Malerfirmaet Frank",
    "wof:placetype":"venue"
},
  "geometry": {"coordinates":[11.1359500885,54.8330116272],"type":"Point"}
}