{
  "type": "Feature",
  "properties": {
    "addr:full":"Fmd.: Jens N\u00f8rg\u00e5rd, S\u00f8ndermarken 63 Hjallerup Danmark 9320",
    "addr:housenumber":"63",
    "addr:postcode":"9320",
    "addr:street":"Sondermarken",
    "iso:country":"DK",
    "sg:address":"Fmd.: Jens N\u00f8rg\u00e5rd, S\u00f8ndermarken 63",
    "sg:city":"Hjallerup",
    "sg:orig_category":"Kulturelle foreninger",
    "sg:phone":"+45 98 28 18 48",
    "sg:postcode":"9320",
    "sg:province":"Danmark",
    "wof:name":"Hjallerup-Thorup Kristelige Lytterforening",
    "wof:placetype":"venue"
},
  "geometry": {"coordinates":[10.1444702148,57.1677742004],"type":"Point"}
}