{
  "type": "Feature",
  "properties": {
    "addr:full":"Neptunvej 12 Ikast Danmark 7430",
    "addr:housenumber":"12",
    "addr:postcode":"7430",
    "addr:street":"Neptunvej",
    "iso:country":"DK",
    "sg:address":"Neptunvej 12",
    "sg:city":"Ikast",
    "sg:orig_category":"EDB - udstyr",
    "sg:phone":"+45 70 20 20 24",
    "sg:postcode":"7430",
    "sg:province":"Danmark",
    "sg:website":"www.edbbutikken.dk",
    "wof:name":"EDB Butikken",
    "wof:placetype":"venue"
},
  "geometry": {"coordinates":[9.1415195465,56.1380691528],"type":"Point"}
}