{
  "type": "Feature",
  "properties": {
    "addr:full":"Jernbanegade 44 S\u00f8nderborg Danmark 6400",
    "addr:housenumber":"44",
    "addr:postcode":"6400",
    "addr:street":"Jernbanegade",
    "iso:country":"DK",
    "sg:address":"Jernbanegade 44",
    "sg:city":"S\u00f8nderborg",
    "sg:orig_category":"Pizzeriaer",
    "sg:phone":"+45 74 43 17 27",
    "sg:postcode":"6400",
    "sg:province":"Danmark",
    "wof:name":"Pizza Expressen",
    "wof:placetype":"venue"
},
  "geometry": {"coordinates":[9.7890348434,54.9111709595],"type":"Point"}
}