{
  "type": "Feature",
  "properties": {
    "iso:country":"DK",
    "sg:address":"Ringstedgade 24, st. th.",
    "sg:city":"Roskilde",
    "sg:orig_category":"Boligtekstil",
    "sg:phone":"+45 46 35 00 51",
    "sg:postcode":"4000",
    "sg:province":"Danmark",
    "wof:name":"Interi\u00f8r & Boligindretning",
    "wof:placetype":"venue"
},
  "geometry": {"coordinates":[12.0909376144,55.6404838562],"type":"Point"}
}