{
  "type": "Feature",
  "properties": {
    "addr:full":"Gammel H\u00f8jmevej 60, H\u00f8jme Odense SV Danmark 5250",
    "addr:housenumber":"60",
    "addr:postcode":"5250",
    "addr:street":"Gammel Hojmevej;Hojme",
    "iso:country":"DK",
    "sg:address":"Gammel H\u00f8jmevej 60, H\u00f8jme",
    "sg:city":"Odense SV",
    "sg:orig_category":"Malermestre",
    "sg:phone":"+45 66 17 02 61",
    "sg:postcode":"5250",
    "sg:province":"Danmark",
    "wof:name":"Jespersen, Vagn Egeskov",
    "wof:placetype":"venue"
},
  "geometry": {"coordinates":[10.3153953552,55.3362998962],"type":"Point"}
}