{
  "type": "Feature",
  "properties": {
    "iso:country":"DK",
    "sg:address":"Torvegade 4",
    "sg:city":"Varde",
    "sg:orig_category":"Dentallaboratorier",
    "sg:phone":"+45 75 21 22 20",
    "sg:postcode":"6800",
    "sg:province":"Danmark",
    "wof:name":"GS Dentallaboratorium",
    "wof:placetype":"venue"
},
  "geometry": {"coordinates":[8.4806404114,55.619884491],"type":"Point"}
}