{
  "type": "Feature",
  "properties": {
    "addr:full":"Torvet 1 Grenaa Danmark 8500",
    "addr:housenumber":"1",
    "addr:postcode":"8500",
    "addr:street":"Torvet",
    "iso:country":"DK",
    "sg:address":"Torvet 1",
    "sg:city":"Grenaa",
    "sg:orig_category":"Turistbureau og -information",
    "sg:phone":"+45 87 58 12 00",
    "sg:postcode":"8500",
    "sg:province":"Danmark",
    "sg:website":"www.grenaa-turistbureau.dk",
    "wof:name":"Grenaa Turistbureau",
    "wof:placetype":"venue"
},
  "geometry": {"coordinates":[10.8758192062,56.4138031006],"type":"Point"}
}