{
  "type": "Feature",
  "properties": {
    "addr:full":"Fabriksvej 30 Struer Danmark 7600",
    "addr:housenumber":"30",
    "addr:postcode":"7600",
    "addr:street":"Fabriksvej",
    "iso:country":"DK",
    "sg:address":"Fabriksvej 30",
    "sg:city":"Struer",
    "sg:orig_category":"Fabrikker",
    "sg:phone":"+45 97 85 00 88",
    "sg:postcode":"7600",
    "sg:province":"Danmark",
    "wof:name":"\u00d8rum ApS, Th.",
    "wof:placetype":"venue"
},
  "geometry": {"coordinates":[8.577129364,56.4830932617],"type":"Point"}
}