{
  "type": "Feature",
  "properties": {
    "addr:full":"Kanalgaden 3 Albertslund Danmark 2620",
    "addr:housenumber":"3",
    "addr:postcode":"2620",
    "addr:street":"Kanalgaden",
    "iso:country":"DK",
    "sg:address":"Kanalgaden 3",
    "sg:city":"Albertslund",
    "sg:orig_category":"Mobiltelefoner",
    "sg:phone":"+45 43 66 92 99",
    "sg:postcode":"2620",
    "sg:province":"Danmark",
    "sg:website":"www.tele-ringen.dk",
    "wof:name":"TeleRingen Albertslund",
    "wof:placetype":"venue"
},
  "geometry": {"coordinates":[12.3533792496,55.6549377441],"type":"Point"}
}