{
  "type": "Feature",
  "properties": {
    "addr:full":"S\u00e6rk\u00e6rparken 78 Holstebro Danmark 7500",
    "addr:housenumber":"78",
    "addr:postcode":"7500",
    "addr:street":"Saerkaerparken",
    "iso:country":"DK",
    "sg:address":"S\u00e6rk\u00e6rparken 78",
    "sg:city":"Holstebro",
    "sg:orig_category":"Skilte",
    "sg:phone":"+45 97 42 24 25",
    "sg:postcode":"7500",
    "sg:province":"Danmark",
    "wof:name":"Broberg Reklame",
    "wof:placetype":"venue"
},
  "geometry": {"coordinates":[8.6202583313,56.3625221252],"type":"Point"}
}