{
  "type": "Feature",
  "properties": {
    "addr:full":"Tjelevej 22, Tj\u00f8rring Herning Danmark 7400",
    "addr:housenumber":"22",
    "addr:postcode":"7400",
    "addr:street":"Tjelevej;Tjorring",
    "iso:country":"DK",
    "sg:address":"Tjelevej 22, Tj\u00f8rring",
    "sg:city":"Herning",
    "sg:orig_category":"Autoforhandlere",
    "sg:phone":"+45 97 26 89 22",
    "sg:postcode":"7400",
    "sg:province":"Danmark",
    "sg:website":"www.ib-pedersen-automobiler.dk",
    "wof:name":"Pedersen Automobiler, Ib",
    "wof:placetype":"venue"
},
  "geometry": {"coordinates":[8.9768896103,56.1374168396],"type":"Point"}
}