{
  "type": "Feature",
  "properties": {
    "iso:country":"DK",
    "sg:address":"\u00d8stergade 63 A",
    "sg:city":"Vamdrup",
    "sg:orig_category":"Hundepsykologer",
    "sg:phone":"+45 70 27 11 72",
    "sg:postcode":"6580",
    "sg:province":"Danmark",
    "wof:name":"Familiehunden",
    "wof:placetype":"venue"
},
  "geometry": {"coordinates":[9.291431427,55.423625946],"type":"Point"}
}