{
  "type": "Feature",
  "properties": {
    "addr:full":"L\u00f8jtertoft 34 A Nordborg Danmark 6430",
    "addr:housenumber":"34 a",
    "addr:postcode":"6430",
    "addr:street":"Lojtertoft",
    "iso:country":"DK",
    "sg:address":"L\u00f8jtertoft 34 A",
    "sg:city":"Nordborg",
    "sg:orig_category":"Psykologer, praktiserende",
    "sg:phone":"+45 74 49 09 28",
    "sg:postcode":"6430",
    "sg:province":"Danmark",
    "wof:name":"Dahlstrup, Britta",
    "wof:placetype":"venue"
},
  "geometry": {"coordinates":[9.7483615875,55.0551147461],"type":"Point"}
}