{
  "type": "Feature",
  "properties": {
    "addr:full":"Godth\u00e5bsvej 49 Svenstrup Danmark 9230",
    "addr:housenumber":"49",
    "addr:postcode":"9230",
    "addr:street":"Godthaabsvej",
    "iso:country":"DK",
    "sg:address":"Godth\u00e5bsvej 49",
    "sg:city":"Svenstrup",
    "sg:orig_category":"Servicestationer",
    "sg:phone":"+45 98 38 17 20",
    "sg:postcode":"9230",
    "sg:province":"Danmark",
    "wof:name":"Q8",
    "wof:placetype":"venue"
},
  "geometry": {"coordinates":[9.8440418243,56.9725379944],"type":"Point"}
}