{
  "type": "Feature",
  "properties": {
    "iso:country":"DK",
    "sg:address":"M. Bechs Alle 10",
    "sg:city":"Hvidovre",
    "sg:orig_category":"\u00c3\u02dcvrige foreninger",
    "sg:phone":"+45 36 75 06 70",
    "sg:postcode":"2650",
    "sg:province":"Danmark",
    "wof:name":"For\u00e6ldrer\u00e5det Baunevangens Fritidshjem",
    "wof:placetype":"venue"
},
  "geometry": {"coordinates":[12.4715957642,55.6546821594],"type":"Point"}
}