{
  "type": "Feature",
  "properties": {
    "iso:country":"DK",
    "sg:address":"Bellah\u00f8jvej 20",
    "sg:city":"Br\u00f8nsh\u00f8j",
    "sg:orig_category":"Selskabslokaler",
    "sg:phone":"+45 38 28 90 00",
    "sg:postcode":"2700",
    "sg:province":"Danmark",
    "wof:name":"Restaurant Bellah\u00f8j",
    "wof:placetype":"venue"
},
  "geometry": {"coordinates":[-65.686653,-23.19813],"type":"Point"}
}