{
  "type": "Feature",
  "properties": {
    "addr:full":"Egedalvej 3, Grimstrup \u00c5rre Danmark 6818",
    "addr:housenumber":"3",
    "addr:postcode":"6818",
    "addr:street":"Egedalvej",
    "iso:country":"DK",
    "sg:address":"Egedalvej 3, Grimstrup",
    "sg:city":"\u00c5rre",
    "sg:orig_category":"Kirker",
    "sg:postcode":"6818",
    "sg:province":"Danmark",
    "wof:name":"Grimstrup Kirke",
    "wof:placetype":"venue"
},
  "geometry": {"coordinates":[8.6546201706,55.5267105103],"type":"Point"}
}