{
  "type": "Feature",
  "properties": {
    "addr:full":"City Centret 7 St\u00f8vring Danmark 9530",
    "addr:housenumber":"7",
    "addr:postcode":"9530",
    "addr:street":"City Centret",
    "iso:country":"DK",
    "sg:address":"City Centret 7",
    "sg:city":"St\u00f8vring",
    "sg:orig_category":"Spedition",
    "sg:phone":"+45 96 86 12 12",
    "sg:postcode":"9530",
    "sg:province":"Danmark",
    "sg:website":"www.lundsoe.dk",
    "wof:name":"Lunds\u00f8e Transport og Spedition ApS",
    "wof:placetype":"venue"
},
  "geometry": {"coordinates":[-103.3810424805,34.3614616394],"type":"Point"}
}