{
  "type": "Feature",
  "properties": {
    "addr:full":"Smidsbjergvej 4 Grevinge Danmark 4571",
    "addr:housenumber":"4",
    "addr:postcode":"4571",
    "addr:street":"Smidsbjergvej",
    "iso:country":"DK",
    "sg:address":"Smidsbjergvej 4",
    "sg:city":"Grevinge",
    "sg:orig_category":"Rideskoler",
    "sg:phone":"+45 59 65 98 46",
    "sg:postcode":"4571",
    "sg:province":"Danmark",
    "wof:name":"Mandals Hestepension",
    "wof:placetype":"venue"
},
  "geometry": {"coordinates":[11.5796403885,55.8059158325],"type":"Point"}
}