{
  "type": "Feature",
  "properties": {
    "addr:full":"J\u00e6ttevej 54 Ringsted Danmark 4100",
    "addr:housenumber":"54",
    "addr:postcode":"4100",
    "addr:street":"Jaettevej",
    "iso:country":"DK",
    "sg:address":"J\u00e6ttevej 54",
    "sg:city":"Ringsted",
    "sg:orig_category":"Gaffeltrucks",
    "sg:phone":"+45 57 61 80 90",
    "sg:postcode":"4100",
    "sg:province":"Danmark",
    "wof:name":"Heden Gaffeltruck A/S",
    "wof:placetype":"venue"
},
  "geometry": {"coordinates":[11.8086223602,55.4319000244],"type":"Point"}
}