{
  "type": "Feature",
  "properties": {
    "addr:full":"Vesterbro 70 Odense C Danmark 5000",
    "addr:housenumber":"70",
    "addr:postcode":"5000",
    "addr:street":"Vesterbro",
    "iso:country":"DK",
    "sg:address":"Vesterbro 70",
    "sg:city":"Odense C",
    "sg:orig_category":"Pizzeriaer",
    "sg:phone":"+45 66 11 44 68",
    "sg:postcode":"5000",
    "sg:province":"Danmark",
    "wof:name":"Pizza Aspendos",
    "wof:placetype":"venue"
},
  "geometry": {"coordinates":[10.3749542236,55.3939476013],"type":"Point"}
}