{
  "type": "Feature",
  "properties": {
    "addr:full":"Akseltorv 4 A Kolding Danmark 6000",
    "addr:housenumber":"4 a",
    "addr:postcode":"6000",
    "addr:street":"Akseltorv",
    "iso:country":"DK",
    "sg:address":"Akseltorv 4 A",
    "sg:city":"Kolding",
    "sg:classifiers":[
        {
            "category":"Banks & Credit Unions",
            "subcategory":"Bank",
            "type":"Services"
        }
    ],
    "sg:phone":"+45 76 33 24 00",
    "sg:postcode":"6000",
    "sg:province":"Danmark",
    "sg:tags":[
        "banker"
    ],
    "sg:website":"www.danskebank.dk",
    "wof:name":"Danske Bank",
    "wof:placetype":"venue"
},
  "geometry": {"coordinates":[9.47359,55.490162],"type":"Point"}
}