{
  "type": "Feature",
  "properties": {
    "addr:full":"\u00d8stre Havnevej 23 Svendborg Danmark 5700",
    "addr:housenumber":"23",
    "addr:postcode":"5700",
    "addr:street":"Ostre Havnevej",
    "iso:country":"DK",
    "sg:address":"\u00d8stre Havnevej 23",
    "sg:city":"Svendborg",
    "sg:orig_category":"Non-Classified Establishments",
    "sg:phone":"+45 62 80 01 56",
    "sg:postcode":"5700",
    "sg:province":"Danmark",
    "wof:name":"ConvideEDB",
    "wof:placetype":"venue"
},
  "geometry": {"coordinates":[10.6218709946,55.0612182617],"type":"Point"}
}