{
  "type": "Feature",
  "properties": {
    "addr:full":"Randersvej 94 Ry Danmark 8680",
    "addr:housenumber":"94",
    "addr:postcode":"8680",
    "addr:street":"Randersvej",
    "iso:country":"DK",
    "sg:address":"Randersvej 94",
    "sg:city":"Ry",
    "sg:classifiers":[
        {
            "category":"Building & Trades",
            "subcategory":"Construction",
            "type":"Services"
        }
    ],
    "sg:phone":"+45 20 46 14 89",
    "sg:postcode":"8680",
    "sg:province":"Danmark",
    "sg:tags":[
        "ventilation"
    ],
    "wof:name":"KM Montage",
    "wof:placetype":"venue"
},
  "geometry": {"coordinates":[9.7850780487,56.1096687317],"type":"Point"}
}