{
  "type": "Feature",
  "properties": {
    "addr:full":"Bavnebjergvej 4 Ry Danmark 8680",
    "addr:housenumber":"4",
    "addr:postcode":"8680",
    "addr:street":"Bavnebjergvej",
    "iso:country":"DK",
    "sg:address":"Bavnebjergvej 4",
    "sg:city":"Ry",
    "sg:orig_category":"Autoreparation og -service",
    "sg:phone":"+45 86 57 70 38",
    "sg:postcode":"8680",
    "sg:province":"Danmark",
    "wof:name":"Dover",
    "wof:placetype":"venue"
},
  "geometry": {"coordinates":[9.8297176361,56.0809516907],"type":"Point"}
}