{
  "type": "Feature",
  "properties": {
    "addr:full":"Fosdalvej 69, Lerup Brovst Danmark 9460",
    "addr:housenumber":"69",
    "addr:postcode":"9460",
    "addr:street":"Fosdalvej;Lerup",
    "iso:country":"DK",
    "sg:address":"Fosdalvej 69, Lerup",
    "sg:city":"Brovst",
    "sg:orig_category":"\u00c3\u02dcvrige skoler",
    "sg:phone":"+45 98 23 50 44",
    "sg:postcode":"9460",
    "sg:province":"Danmark",
    "sg:website":"www.naturcenterfosdalen.dk",
    "wof:name":"Naturcenter Fosdalen",
    "wof:placetype":"venue"
},
  "geometry": {"coordinates":[9.5220241547,57.097366333],"type":"Point"}
}