{
  "type": "Feature",
  "properties": {
    "iso:country":"DK",
    "sg:address":"Bjarkesvej 9",
    "sg:city":"Slagelse",
    "sg:orig_category":"Kontorservice",
    "sg:phone":"+45 58 52 00 01",
    "sg:postcode":"4200",
    "sg:province":"Danmark",
    "sg:website":"www.ha-erhvervsservice.dk",
    "wof:name":"HA Erhvervsservice",
    "wof:placetype":"venue"
},
  "geometry": {"coordinates":[11.343413353,55.388130188],"type":"Point"}
}