{
  "type": "Feature",
  "properties": {
    "addr:full":"Herlev Hovedgade 137 Herlev Danmark 2730",
    "addr:housenumber":"137",
    "addr:postcode":"2730",
    "addr:street":"Herlev Hovedgade",
    "iso:country":"DK",
    "sg:address":"Herlev Hovedgade 137",
    "sg:city":"Herlev",
    "sg:orig_category":"Teatre, Artikler for",
    "sg:phone":"+45 44 84 78 95",
    "sg:postcode":"2730",
    "sg:province":"Danmark",
    "wof:name":"Victory Producing Co.",
    "wof:placetype":"venue"
},
  "geometry": {"coordinates":[12.4375038147,55.7230148315],"type":"Point"}
}