{
  "type": "Feature",
  "properties": {
    "addr:full":"Vermehrensvej 14 Odense M Danmark 5230",
    "addr:housenumber":"14",
    "addr:postcode":"5230",
    "addr:street":"Vermehrensvej",
    "iso:country":"DK",
    "sg:address":"Vermehrensvej 14",
    "sg:city":"Odense M",
    "sg:orig_category":"INGENI\u00c3\u02dcRER",
    "sg:phone":"+45 66 11 14 05",
    "sg:postcode":"5230",
    "sg:province":"Danmark",
    "wof:name":"Bro A/S, Carl",
    "wof:placetype":"venue"
},
  "geometry": {"coordinates":[10.4177560806,55.3917694092],"type":"Point"}
}