{
  "type": "Feature",
  "properties": {
    "addr:full":"B\u00f8gebakken 1 Aalborg S\u00d8 Danmark 9210",
    "addr:housenumber":"1",
    "addr:postcode":"9210",
    "addr:street":"Bogebakken",
    "iso:country":"DK",
    "sg:address":"B\u00f8gebakken 1",
    "sg:city":"Aalborg S\u00d8",
    "sg:orig_category":"Konsulentvirksomheder",
    "sg:phone":"+45 98 12 33 45",
    "sg:postcode":"9210",
    "sg:province":"Danmark",
    "wof:name":"TN Data",
    "wof:placetype":"venue"
},
  "geometry": {"coordinates":[9.9425764084,57.0150032043],"type":"Point"}
}