{
  "type": "Feature",
  "properties": {
    "iso:country":"DK",
    "sg:address":"Falkoner Alle 16",
    "sg:city":"Frederiksberg",
    "sg:orig_category":"Begravelsesforretninger",
    "sg:phone":"+45 38 34 65 11",
    "sg:postcode":"2000",
    "sg:province":"Danmark",
    "wof:name":"Begravelsesforretningen Danmark A/S",
    "wof:placetype":"venue"
},
  "geometry": {"coordinates":[12.53394,55.679707],"type":"Point"}
}