{
  "type": "Feature",
  "properties": {
    "addr:full":"\u00c5lb\u00e6kvej 18, Lihme Sp\u00f8ttrup Danmark 7860",
    "addr:housenumber":"18",
    "addr:postcode":"7860",
    "addr:street":"Aalbaekvej",
    "iso:country":"DK",
    "sg:address":"\u00c5lb\u00e6kvej 18, Lihme",
    "sg:city":"Sp\u00f8ttrup",
    "sg:orig_category":"Lokalarkiver",
    "sg:phone":"+45 97 56 01 38",
    "sg:postcode":"7860",
    "sg:province":"Danmark",
    "wof:name":"Sp\u00f8ttrup Lokalhistoriske Arkiv",
    "wof:placetype":"venue"
},
  "geometry": {"coordinates":[8.7428588867,56.5733261108],"type":"Point"}
}