{
  "type": "Feature",
  "properties": {
    "iso:country":"DK",
    "sg:address":"Tapdrupvej 82",
    "sg:city":"Viborg",
    "sg:orig_category":"Belysning",
    "sg:phone":"+45 86 60 00 23",
    "sg:postcode":"8800",
    "sg:province":"Danmark",
    "wof:name":"Day-Lite",
    "wof:placetype":"venue"
},
  "geometry": {"coordinates":[9.48,56.44054],"type":"Point"}
}