{
  "type": "Feature",
  "properties": {
    "addr:full":"Fmd.: Orla Tonnesen, S\u00f8nderk\u00e6r 504 Billund Danmark 7190",
    "addr:housenumber":"504",
    "addr:postcode":"7190",
    "iso:country":"DK",
    "sg:address":"Fmd.: Orla Tonnesen, S\u00f8nderk\u00e6r 504",
    "sg:city":"Billund",
    "sg:orig_category":"Musik og sang",
    "sg:phone":"+45 75 33 87 17",
    "sg:postcode":"7190",
    "sg:province":"Danmark",
    "wof:name":"Billund Harmonikaklub",
    "wof:placetype":"venue"
},
  "geometry": {"coordinates":[9.1138372421,55.7316017151],"type":"Point"}
}