{
  "type": "Feature",
  "properties": {
    "addr:full":"Strandvejen 168 Snekkersten Danmark 3070",
    "addr:housenumber":"168",
    "addr:postcode":"3070",
    "addr:street":"Strandvejen",
    "iso:country":"DK",
    "sg:address":"Strandvejen 168",
    "sg:city":"Snekkersten",
    "sg:orig_category":"Psykologer, praktiserende",
    "sg:phone":"+45 49 22 38 80",
    "sg:postcode":"3070",
    "sg:province":"Danmark",
    "wof:name":"Holmgren, Anette Kofod",
    "wof:placetype":"venue"
},
  "geometry": {"coordinates":[12.5901756287,56.0096473694],"type":"Point"}
}