{
  "type": "Feature",
  "properties": {
    "addr:full":"Hersegade 7 C Roskilde Danmark 4000",
    "addr:housenumber":"7 c",
    "addr:postcode":"4000",
    "addr:street":"Hersegade",
    "iso:country":"DK",
    "sg:address":"Hersegade 7 C",
    "sg:city":"Roskilde",
    "sg:orig_category":"Musikinstrumenter",
    "sg:phone":"+45 46 32 42 02",
    "sg:postcode":"4000",
    "sg:province":"Danmark",
    "wof:name":"Musik-Butikken A/S",
    "wof:placetype":"venue"
},
  "geometry": {"coordinates":[12.0848484039,55.6398353577],"type":"Point"}
}