{
  "type": "Feature",
  "properties": {
    "iso:country":"DK",
    "sg:address":"Haderslevvej 75 D",
    "sg:city":"Kolding",
    "sg:orig_category":"Revisorer",
    "sg:phone":"+45 75 52 11 02",
    "sg:postcode":"6000",
    "sg:province":"Danmark",
    "wof:name":"Kolding Revision-Institut",
    "wof:placetype":"venue"
},
  "geometry": {"coordinates":[9.4690952301,55.4817008972],"type":"Point"}
}