{
  "type": "Feature",
  "properties": {
    "addr:full":"Gammel Kongevej 78 Frederiksberg Danmark 1850",
    "addr:housenumber":"78",
    "addr:postcode":"1850",
    "addr:street":"Gammel Kongevej",
    "iso:country":"DK",
    "sg:address":"Gammel Kongevej 78",
    "sg:city":"Frederiksberg",
    "sg:orig_category":"Psykologer, praktiserende",
    "sg:phone":"+45 33 24 38 44",
    "sg:postcode":"1850",
    "sg:province":"Danmark",
    "wof:name":"Skovgaard, Birgitte",
    "wof:placetype":"venue"
},
  "geometry": {"coordinates":[12.5507736206,55.6744918823],"type":"Point"}
}