{
  "type": "Feature",
  "properties": {
    "addr:full":"Haraldsvej 66 Randers Danmark 8900",
    "addr:housenumber":"66",
    "addr:postcode":"8900",
    "addr:street":"Haraldsvej",
    "iso:country":"DK",
    "sg:address":"Haraldsvej 66",
    "sg:city":"Randers",
    "sg:orig_category":"Plastemballage",
    "sg:phone":"+45 86 41 29 55",
    "sg:postcode":"8900",
    "sg:province":"Danmark",
    "wof:name":"Dan-Plast A/S",
    "wof:placetype":"venue"
},
  "geometry": {"coordinates":[10.0539703369,56.4379806519],"type":"Point"}
}