{
  "type": "Feature",
  "properties": {
    "iso:country":"DK",
    "sg:address":"N\u00f8rregade 49",
    "sg:city":"Fars\u00f8",
    "sg:classifiers":[
        {
            "category":"Taxi",
            "type":"Transportation"
        }
    ],
    "sg:phone":"+45 98 63 12 22",
    "sg:postcode":"9640",
    "sg:province":"Danmark",
    "wof:name":"Bo's Taxi",
    "wof:placetype":"venue"
},
  "geometry": {"coordinates":[-109.44831848139999,42.1062355042],"type":"Point"}
}