{
  "type": "Feature",
  "properties": {
    "addr:full":"Marielyst Strandvej 57 V\u00e6ggerl\u00f8se Danmark 4873",
    "addr:housenumber":"57",
    "addr:postcode":"4873",
    "addr:street":"Marielyst Strandvej",
    "iso:country":"DK",
    "sg:address":"Marielyst Strandvej 57",
    "sg:city":"V\u00e6ggerl\u00f8se",
    "sg:orig_category":"Diners transportables",
    "sg:phone":"+45 54 13 21 70",
    "sg:postcode":"4873",
    "sg:province":"Danmark",
    "wof:name":"Larsen's Plads, Restaurant",
    "wof:placetype":"venue"
},
  "geometry": {"coordinates":[11.9238767624,54.7119483948],"type":"Point"}
}