{
  "type": "Feature",
  "properties": {
    "addr:full":"Alsvej 15 Middelfart Danmark 5500",
    "addr:housenumber":"15",
    "addr:postcode":"5500",
    "addr:street":"Alsvej",
    "iso:country":"DK",
    "sg:address":"Alsvej 15",
    "sg:city":"Middelfart",
    "sg:orig_category":"\u00c3\u02dcl- og mineralvandsdepoter",
    "sg:phone":"+45 64 41 44 14",
    "sg:postcode":"5500",
    "sg:province":"Danmark",
    "wof:name":"Albani Depotet",
    "wof:placetype":"venue"
},
  "geometry": {"coordinates":[9.7623605728,55.5003662109],"type":"Point"}
}