{
  "type": "Feature",
  "properties": {
    "addr:full":"Bogtrykkervej 24 K\u00f8benhavn NV Danmark 2400",
    "addr:housenumber":"24",
    "addr:postcode":"2400",
    "addr:street":"Bogtrykkervej",
    "iso:country":"DK",
    "sg:address":"Bogtrykkervej 24",
    "sg:city":"K\u00f8benhavn NV",
    "sg:orig_category":"Fritidshjem",
    "sg:phone":"+45 35 81 42 20",
    "sg:postcode":"2400",
    "sg:province":"Danmark",
    "wof:name":"Dommerparkens Fritidshjem",
    "wof:placetype":"venue"
},
  "geometry": {"coordinates":[-117.02272033689999,38.5024604797],"type":"Point"}
}