{
  "type": "Feature",
  "properties": {
    "addr:full":"v/ Ruth S\u00f8rensen, M\u00f8llerjorden 51, H\u00f8jby Lejre Danmark 4320",
    "addr:housenumber":"51",
    "addr:postcode":"4320",
    "addr:street":"Hojby",
    "iso:country":"DK",
    "sg:address":"v/ Ruth S\u00f8rensen, M\u00f8llerjorden 51, H\u00f8jby",
    "sg:city":"Lejre",
    "sg:orig_category":"Loger",
    "sg:phone":"+45 46 48 08 74",
    "sg:postcode":"4320",
    "sg:province":"Danmark",
    "wof:name":"Sct. Georgs Gilderne",
    "wof:placetype":"venue"
},
  "geometry": {"coordinates":[11.9678316116,55.6005630493],"type":"Point"}
}