{
  "type": "Feature",
  "properties": {
    "addr:full":"Paladspassagen 8  Vejle Danmark 7100",
    "addr:housenumber":"8",
    "addr:postcode":"7100",
    "addr:street":"Paladspassagen",
    "iso:country":"DK",
    "sg:address":"Paladspassagen 8 ",
    "sg:city":"Vejle",
    "sg:classifiers":[
        {
            "category":"Farming",
            "subcategory":"Livestock Farm",
            "type":"Manufacturing & Wholesale Goods"
        }
    ],
    "sg:phone":"+45 75 83 73 35",
    "sg:postcode":"7100",
    "sg:province":"Danmark",
    "sg:tags":[
        "agriculture"
    ],
    "wof:name":"FRUGT OG BLOMSTERLAND",
    "wof:placetype":"venue"
},
  "geometry": {"coordinates":[9.5341053009,55.7112617493],"type":"Point"}
}