{
  "type": "Feature",
  "properties": {
    "addr:full":"Ahorngade 62 Vejen Danmark 6600",
    "addr:housenumber":"62",
    "addr:postcode":"6600",
    "addr:street":"Ahorngade",
    "iso:country":"DK",
    "sg:address":"Ahorngade 62",
    "sg:city":"Vejen",
    "sg:orig_category":"Handicapboliger",
    "sg:phone":"+45 75 36 48 07",
    "sg:postcode":"6600",
    "sg:province":"Danmark",
    "wof:name":"Bof\u00e6llesskabet",
    "wof:placetype":"venue"
},
  "geometry": {"coordinates":[9.1422433853,55.4750137329],"type":"Point"}
}