{
  "type": "Feature",
  "properties": {
    "iso:country":"DK",
    "sg:address":"Engelholm All\u00e9 1 ",
    "sg:city":"Taastrup",
    "sg:classifiers":[
        {
            "category":"Banks & Credit Unions",
            "subcategory":"Financial Services",
            "type":"Services"
        }
    ],
    "sg:phone":"+45 43 55 80 00",
    "sg:postcode":"2630",
    "sg:province":"Danmark",
    "sg:tags":[
        "banking",
        "finance",
        "insurance"
    ],
    "wof:name":"NORDEUROPA A/S, ALKA",
    "wof:placetype":"venue"
},
  "geometry": {"coordinates":[12.268686,55.644531],"type":"Point"}
}