{
  "type": "Feature",
  "properties": {
    "addr:full":"Boulevarden 27 Aalborg Danmark 9000",
    "addr:housenumber":"27",
    "addr:postcode":"9000",
    "addr:street":"Boulevarden",
    "iso:country":"DK",
    "sg:address":"Boulevarden 27",
    "sg:city":"Aalborg",
    "sg:orig_category":"Renserier",
    "sg:phone":"+45 98 12 89 88",
    "sg:postcode":"9000",
    "sg:province":"Danmark",
    "wof:name":"Rens-O-Mat",
    "wof:placetype":"venue"
},
  "geometry": {"coordinates":[9.9185066223,57.0446243286],"type":"Point"}
}