{
  "type": "Feature",
  "properties": {
    "iso:country":"DK",
    "sg:address":"Forchhammersvej 18",
    "sg:city":"Frederiksberg",
    "sg:orig_category":"Stofmisbruger-institutioner",
    "sg:phone":"+45 35 36 22 85",
    "sg:postcode":"1920",
    "sg:province":"Danmark",
    "wof:name":"Behandlingsinstitutionen Forchammersvej",
    "wof:placetype":"venue"
},
  "geometry": {"coordinates":[12.5511732101,55.6802024841],"type":"Point"}
}