{
  "type": "Feature",
  "properties": {
    "iso:country":"DK",
    "sg:address":"\u00c5gade 2",
    "sg:city":"Skive",
    "sg:orig_category":"Supermarkeder",
    "sg:phone":"+45 96 14 42 00",
    "sg:postcode":"7800",
    "sg:province":"Danmark",
    "wof:name":"Kvickly",
    "wof:placetype":"venue"
},
  "geometry": {"coordinates":[9.0314216614,56.5654373169],"type":"Point"}
}