{
  "type": "Feature",
  "properties": {
    "iso:country":"DK",
    "sg:address":"Ilbjerg Alle 108",
    "sg:city":"Herlev",
    "sg:orig_category":"Snedkermestre",
    "sg:phone":"+45 44 92 90 83",
    "sg:postcode":"2730",
    "sg:province":"Danmark",
    "wof:name":"R\u00f8rh\u00f8j, Ren\u00e9",
    "wof:placetype":"venue"
},
  "geometry": {"coordinates":[12.4690828323,55.7286224365],"type":"Point"}
}