{
  "type": "Feature",
  "properties": {
    "addr:full":"Hovedgaden 42 H\u00f8ng Danmark 4270",
    "addr:housenumber":"42",
    "addr:postcode":"4270",
    "addr:street":"Hovedgaden;Hong Danmark",
    "iso:country":"DK",
    "sg:address":"Hovedgaden 42",
    "sg:city":"H\u00f8ng",
    "sg:orig_category":"Fodplejere",
    "sg:phone":"+45 58 85 43 00",
    "sg:postcode":"4270",
    "sg:province":"Danmark",
    "wof:name":"Klinik For Fodterapi",
    "wof:placetype":"venue"
},
  "geometry": {"coordinates":[9.2555503845,54.9375686646],"type":"Point"}
}