{
  "type": "Feature",
  "properties": {
    "addr:full":"Fmd.: Kurt Bertelsen, Strandetvej 1, Lund H\u00f8jslev Danmark 7840",
    "addr:housenumber":"1",
    "addr:postcode":"7840",
    "addr:street":"Strandetvej",
    "iso:country":"DK",
    "sg:address":"Fmd.: Kurt Bertelsen, Strandetvej 1, Lund",
    "sg:city":"H\u00f8jslev",
    "sg:orig_category":"Forsamlingshuse",
    "sg:phone":"+45 97 53 95 53",
    "sg:postcode":"7840",
    "sg:province":"Danmark",
    "wof:name":"Lund forsamlingshus",
    "wof:placetype":"venue"
},
  "geometry": {"coordinates":[9.110039711,56.5504264832],"type":"Point"}
}