{
  "type": "Feature",
  "properties": {
    "addr:full":"Sydtoftevej 20 S\u00f8borg Danmark 2860",
    "addr:housenumber":"20",
    "addr:postcode":"2860",
    "addr:street":"Sydtoftevej",
    "iso:country":"DK",
    "sg:address":"Sydtoftevej 20",
    "sg:city":"S\u00f8borg",
    "sg:orig_category":"Web- og Internetdesign",
    "sg:phone":"+45 39 66 66 92",
    "sg:postcode":"2860",
    "sg:province":"Danmark",
    "sg:website":"www.Click-a-site.dk",
    "wof:name":"Click-a-site ApS",
    "wof:placetype":"venue"
},
  "geometry": {"coordinates":[-101.2610626221,35.6759033203],"type":"Point"}
}