{
  "type": "Feature",
  "properties": {
    "addr:full":"Petersmindevej 3 Vejen Danmark 6600",
    "addr:housenumber":"3",
    "addr:postcode":"6600",
    "addr:street":"Petersmindevej",
    "iso:country":"DK",
    "sg:address":"Petersmindevej 3",
    "sg:city":"Vejen",
    "sg:orig_category":"Gymnasier og HF-kurser",
    "sg:phone":"+45 75 36 32 77",
    "sg:postcode":"6600",
    "sg:province":"Danmark",
    "wof:name":"Vejen Gymnasium og HF",
    "wof:placetype":"venue"
},
  "geometry": {"coordinates":[9.1206932068,55.474811554],"type":"Point"}
}