{
  "type": "Feature",
  "properties": {
    "iso:country":"DK",
    "sg:address":"v/ Povl Benneballe M\u00f8ller, Ferskes\u00f8str\u00e6de 28",
    "sg:city":"Nex\u00f8",
    "sg:orig_category":"Teatre",
    "sg:phone":"+45 56 49 27 25",
    "sg:postcode":"3730",
    "sg:province":"Danmark",
    "wof:name":"Scene 2",
    "wof:placetype":"venue"
},
  "geometry": {"coordinates":[15.1096076965,55.0267219543],"type":"Point"}
}