{
  "type": "Feature",
  "properties": {
    "addr:full":"Fmd.: Arne Andersen, Violvej 2, Faarup Nyk\u00f8bing Danmark 7900",
    "addr:housenumber":"2",
    "addr:postcode":"7900",
    "addr:street":"Arne;Violvej",
    "iso:country":"DK",
    "sg:address":"Fmd.: Arne Andersen, Violvej 2, Faarup",
    "sg:city":"Nyk\u00f8bing",
    "sg:orig_category":"Faglige organisationer og foreninger",
    "sg:phone":"+45 97 72 42 01",
    "sg:postcode":"7900",
    "sg:province":"Danmark",
    "wof:name":"Ledernes Hovedorganisation",
    "wof:placetype":"venue"
},
  "geometry": {"coordinates":[8.8630752563,56.7945251465],"type":"Point"}
}