{
  "type": "Feature",
  "properties": {
    "addr:full":"Askj\u00e6rvej 21, Fugdal Hejnsvig Danmark 7250",
    "addr:housenumber":"21",
    "addr:postcode":"7250",
    "addr:street":"Askjaervej",
    "iso:country":"DK",
    "sg:address":"Askj\u00e6rvej 21, Fugdal",
    "sg:city":"Hejnsvig",
    "sg:orig_category":"Landbrugsmaskiner",
    "sg:phone":"+45 75 33 54 30",
    "sg:postcode":"7250",
    "sg:province":"Danmark",
    "wof:name":"Landbrug",
    "wof:placetype":"venue"
},
  "geometry": {"coordinates":[8.9966459274,55.6951141357],"type":"Point"}
}