{
  "type": "Feature",
  "properties": {
    "addr:full":"Danalien 7-13 Aalborg Danmark 9000",
    "addr:housenumber":"7-13",
    "addr:postcode":"9000",
    "addr:street":"Danalien",
    "iso:country":"DK",
    "sg:address":"Danalien 7-13",
    "sg:city":"Aalborg",
    "sg:orig_category":"Plejehjemsboliger",
    "sg:phone":"+45 98 14 92 18",
    "sg:postcode":"9000",
    "sg:province":"Danmark",
    "wof:name":"Danah\u00f8j",
    "wof:placetype":"venue"
},
  "geometry": {"coordinates":[9.9416856766,57.0294265747],"type":"Point"}
}