{
  "type": "Feature",
  "properties": {
    "addr:full":"Godth\u00e5bsvej 174 Frederiksberg Danmark 2000",
    "addr:housenumber":"174",
    "addr:postcode":"2000",
    "addr:street":"Godthaabsvej",
    "iso:country":"DK",
    "sg:address":"Godth\u00e5bsvej 174",
    "sg:city":"Frederiksberg",
    "sg:orig_category":"Renserier",
    "sg:phone":"+45 38 87 02 49",
    "sg:postcode":"2000",
    "sg:province":"Danmark",
    "wof:name":"Rekord Rens",
    "wof:placetype":"venue"
},
  "geometry": {"coordinates":[12.5170431137,55.6903991699],"type":"Point"}
}