{
  "type": "Feature",
  "properties": {
    "iso:country":"DK",
    "sg:address":"Industriholmen 11",
    "sg:city":"Hvidovre",
    "sg:orig_category":"Skilte",
    "sg:phone":"+45 36 49 70 00",
    "sg:postcode":"2650",
    "sg:province":"Danmark",
    "sg:website":"www.neoplastic.com",
    "wof:name":"Neoplastic A/S",
    "wof:placetype":"venue"
},
  "geometry": {"coordinates":[12.4779491425,55.6112556458],"type":"Point"}
}