{
  "type": "Feature",
  "properties": {
    "iso:country":"DK",
    "sg:address":"Holtskovg\u00e5rdsvej 21, Fruering",
    "sg:city":"Skanderborg",
    "sg:orig_category":"Transport",
    "sg:phone":"+45 86 52 31 22",
    "sg:postcode":"8660",
    "sg:province":"Danmark",
    "wof:name":"Lund & S\u00f8nner ApS, Erik",
    "wof:placetype":"venue"
},
  "geometry": {"coordinates":[9.929974556,56.0380249023],"type":"Point"}
}