{
  "type": "Feature",
  "properties": {
    "addr:full":"Kobberupvej 8, Mejrup Holstebro Danmark 7500",
    "addr:housenumber":"8",
    "addr:postcode":"7500",
    "addr:street":"Kobberupvej;Mejrup",
    "iso:country":"DK",
    "sg:address":"Kobberupvej 8, Mejrup",
    "sg:city":"Holstebro",
    "sg:orig_category":"Investering",
    "sg:phone":"+45 97 42 78 98",
    "sg:postcode":"7500",
    "sg:province":"Danmark",
    "wof:name":"Difko",
    "wof:placetype":"venue"
},
  "geometry": {"coordinates":[8.6202583313,56.3625221252],"type":"Point"}
}