{
  "type": "Feature",
  "properties": {
    "addr:full":"Ellebakken 2 Hellerup Danmark 2900",
    "addr:housenumber":"2",
    "addr:postcode":"2900",
    "addr:street":"Ellebakken",
    "iso:country":"DK",
    "sg:address":"Ellebakken 2",
    "sg:city":"Hellerup",
    "sg:orig_category":"Musikere",
    "sg:phone":"+45 39 62 49 04",
    "sg:postcode":"2900",
    "sg:province":"Danmark",
    "wof:name":"Guillaume, Edith",
    "wof:placetype":"venue"
},
  "geometry": {"coordinates":[12.5512266159,55.7264060974],"type":"Point"}
}