{
  "type": "Feature",
  "properties": {
    "iso:country":"DK",
    "sg:address":"Haarlev Mark 1 A ",
    "sg:city":"H\u00e5rlev",
    "sg:classifiers":[
        {
            "category":"Sports & Exercise",
            "subcategory":"Playing Field",
            "type":"Entertainment"
        }
    ],
    "sg:phone":"+45 56 28 80 00",
    "sg:postcode":"4652",
    "sg:province":"Danmark",
    "sg:tags":[
        "game"
    ],
    "wof:name":"H\u00d8JAGER BELYSNING A/S",
    "wof:placetype":"venue"
},
  "geometry": {"coordinates":[12.2353239059,55.3440475464],"type":"Point"}
}