{
  "type": "Feature",
  "properties": {
    "addr:full":"Gammel Jernbanevej 27 Valby Danmark 2500",
    "addr:housenumber":"27",
    "addr:postcode":"2500",
    "addr:street":"Gammel Jernbanevej",
    "iso:country":"DK",
    "sg:address":"Gammel Jernbanevej 27",
    "sg:city":"Valby",
    "sg:orig_category":"HOTELS: OG MOTELLER",
    "sg:phone":"+45 36 45 45 72",
    "sg:postcode":"2500",
    "sg:province":"Danmark",
    "sg:website":"www.nordiskhotelgruppe.dk",
    "wof:name":"Rossini, Hotel",
    "wof:placetype":"venue"
},
  "geometry": {"coordinates":[12.5186080933,55.6642341614],"type":"Point"}
}