{
  "type": "Feature",
  "properties": {
    "iso:country":"DK",
    "sg:address":"Kappelagervej 46",
    "sg:city":"Vejle",
    "sg:orig_category":"Servicestationer",
    "sg:phone":"+45 75 86 05 00",
    "sg:postcode":"7100",
    "sg:province":"Danmark",
    "wof:name":"Shell Service",
    "wof:placetype":"venue"
},
  "geometry": {"coordinates":[9.563741684,55.641002655],"type":"Point"}
}