{
  "type": "Feature",
  "properties": {
    "iso:country":"DK",
    "sg:address":"Mariagervej 139 - 141",
    "sg:city":"Randers",
    "sg:orig_category":"Bowlingcentre",
    "sg:phone":"+45 86 40 87 77",
    "sg:postcode":"8900",
    "sg:province":"Danmark",
    "sg:website":"www.master-bowl.dk",
    "wof:name":"Master Bowl A/S",
    "wof:placetype":"venue"
},
  "geometry": {"coordinates":[10.0310564041,56.4694595337],"type":"Point"}
}