{
  "type": "Feature",
  "properties": {
    "addr:full":"Morten Bo Petersen, Milanovej 7 a 4 tv K\u00f8benhavn S Danmark 2300",
    "addr:housenumber":"7 a 4 tv",
    "addr:postcode":"2300",
    "addr:street":"Morten;Milanovej;Kobenhavn S Danmark",
    "iso:country":"DK",
    "sg:address":"Morten Bo Petersen, Milanovej 7 a 4 tv",
    "sg:city":"K\u00f8benhavn S",
    "sg:orig_category":"Reklamebureauer",
    "sg:phone":"+45 28 12 57 26",
    "sg:postcode":"2300",
    "sg:province":"Danmark",
    "wof:name":"Online Commercial",
    "wof:placetype":"venue"
},
  "geometry": {"coordinates":[11.5408401489,44.5157089233],"type":"Point"}
}