{
  "type": "Feature",
  "properties": {
    "addr:full":"Skjoldsgade 41 Esbjerg Danmark 6700",
    "addr:housenumber":"41",
    "addr:postcode":"6700",
    "addr:street":"Skjoldsgade",
    "iso:country":"DK",
    "sg:address":"Skjoldsgade 41",
    "sg:city":"Esbjerg",
    "sg:orig_category":"Botilbud",
    "sg:phone":"+45 75 12 84 01",
    "sg:postcode":"6700",
    "sg:province":"Danmark",
    "wof:name":"Skjoldbo, beskyttet pensionat",
    "wof:placetype":"venue"
},
  "geometry": {"coordinates":[8.4504652023,55.4715614319],"type":"Point"}
}