{
  "type": "Feature",
  "properties": {
    "addr:full":"Sk\u00e6rg\u00e5rdvej 16 Herning Danmark 7400",
    "addr:housenumber":"16",
    "addr:postcode":"7400",
    "addr:street":"Skaergaardvej",
    "iso:country":"DK",
    "sg:address":"Sk\u00e6rg\u00e5rdvej 16",
    "sg:city":"Herning",
    "sg:orig_category":"Musikere",
    "sg:phone":"+45 97 12 60 03",
    "sg:postcode":"7400",
    "sg:province":"Danmark",
    "wof:name":"Br\u00f8nholt, Niels",
    "wof:placetype":"venue"
},
  "geometry": {"coordinates":[8.9768896103,56.1374168396],"type":"Point"}
}