{
  "type": "Feature",
  "properties": {
    "addr:full":"Svinget 11 Varde Danmark 6800",
    "addr:housenumber":"11",
    "addr:postcode":"6800",
    "addr:street":"Svinget",
    "iso:country":"DK",
    "sg:address":"Svinget 11",
    "sg:city":"Varde",
    "sg:orig_category":"Fragtcentraler",
    "sg:phone":"+45 76 95 21 09",
    "sg:postcode":"6800",
    "sg:province":"Danmark",
    "wof:name":"Varde Fragtcentral",
    "wof:placetype":"venue"
},
  "geometry": {"coordinates":[8.4761390686,55.6242446899],"type":"Point"}
}