{
  "type": "Feature",
  "properties": {
    "addr:full":"Nibe Nibe Danmark 9240",
    "addr:postcode":"9240",
    "addr:street":"Nibe",
    "iso:country":"DK",
    "sg:address":"Nibe",
    "sg:city":"Nibe",
    "sg:orig_category":"HOTELS: OG MOTELLER",
    "sg:phone":"+45 98 35 16 77",
    "sg:postcode":"9240",
    "sg:province":"Danmark",
    "wof:name":"Ph\u00f8nix Nibe, Hotel",
    "wof:placetype":"venue"
},
  "geometry": {"coordinates":[9.7121305466,56.9580764771],"type":"Point"}
}