{
  "type": "Feature",
  "properties": {
    "addr:full":"Thistedvej 465, V. Thorup Fjerritslev Danmark 9690",
    "addr:housenumber":"465 v.",
    "addr:postcode":"9690",
    "addr:street":"Thistedvej;Thorup",
    "iso:country":"DK",
    "sg:address":"Thistedvej 465, V. Thorup",
    "sg:city":"Fjerritslev",
    "sg:orig_category":"Brugsforeninger",
    "sg:phone":"+45 98 22 51 00",
    "sg:postcode":"9690",
    "sg:province":"Danmark",
    "wof:name":"LokalBrugsen V. Thorup",
    "wof:placetype":"venue"
},
  "geometry": {"coordinates":[9.2667350769,57.0882301331],"type":"Point"}
}