{
  "type": "Feature",
  "properties": {
    "iso:country":"DK",
    "sg:address":"Frederikssundsvej 278",
    "sg:city":"Br\u00f8nsh\u00f8j",
    "sg:orig_category":"Glarmestre og glarmagere",
    "sg:phone":"+45 38 28 16 02",
    "sg:postcode":"2700",
    "sg:province":"Danmark",
    "wof:name":"Juhl, K.",
    "wof:placetype":"venue"
},
  "geometry": {"coordinates":[-99.2046127319,19.4762001038],"type":"Point"}
}