{
  "type": "Feature",
  "properties": {
    "addr:full":"Ellebjergvej 2 Risskov Danmark 8240",
    "addr:housenumber":"2",
    "addr:postcode":"8240",
    "addr:street":"Ellebjergvej",
    "iso:country":"DK",
    "sg:address":"Ellebjergvej 2",
    "sg:city":"Risskov",
    "sg:orig_category":"Slagter og viktualie",
    "sg:phone":"+45 86 17 66 38",
    "sg:postcode":"8240",
    "sg:province":"Danmark",
    "wof:name":"Forteparkens K\u00f8dforsyning",
    "wof:placetype":"venue"
},
  "geometry": {"coordinates":[10.2343254089,56.194355011],"type":"Point"}
}