{
  "type": "Feature",
  "properties": {
    "addr:full":"Herlufsholm Alle 20 N\u00e6stved Danmark 4700",
    "addr:housenumber":"20",
    "addr:postcode":"4700",
    "addr:street":"Herlufsholm Alle",
    "iso:country":"DK",
    "sg:address":"Herlufsholm Alle 20",
    "sg:city":"N\u00e6stved",
    "sg:orig_category":"Plejehjem",
    "sg:phone":"+45 55 78 59 50",
    "sg:postcode":"4700",
    "sg:province":"Danmark",
    "wof:name":"Herlufsholmhjemmet",
    "wof:placetype":"venue"
},
  "geometry": {"coordinates":[11.7474727631,55.2355117798],"type":"Point"}
}