{
  "type": "Feature",
  "properties": {
    "addr:full":"R\u00e5bhuivej 17 Gandrup Danmark 9362",
    "addr:housenumber":"17",
    "addr:postcode":"9362",
    "addr:street":"Raabhuivej",
    "iso:country":"DK",
    "sg:address":"R\u00e5bhuivej 17",
    "sg:city":"Gandrup",
    "sg:orig_category":"Snedkermestre",
    "sg:phone":"+45 98 25 94 76",
    "sg:postcode":"9362",
    "sg:province":"Danmark",
    "wof:name":"Andersen, Poul",
    "wof:placetype":"venue"
},
  "geometry": {"coordinates":[10.1908025742,57.0381202698],"type":"Point"}
}