{
  "type": "Feature",
  "properties": {
    "iso:country":"DK",
    "sg:address":"Tranehusene 75",
    "sg:city":"Albertslund",
    "sg:orig_category":"Sammensatte institutioner",
    "sg:phone":"+45 43 62 11 20",
    "sg:postcode":"2620",
    "sg:province":"Danmark",
    "wof:name":"K\u00e6rmosen B\u00f8rnehus",
    "wof:placetype":"venue"
},
  "geometry": {"coordinates":[12.3506097794,55.6745529175],"type":"Point"}
}