{
  "type": "Feature",
  "properties": {
    "addr:full":"v/ Hans J\u00f8rgen H\u00f8y, B\u00f8geskovvej 16, Rasborg, Postboks 36 Solbjerg Danmark 8355",
    "addr:housenumber":"16;36",
    "addr:postcode":"8355",
    "addr:street":"Bogeskovvej;Postboks",
    "iso:country":"DK",
    "sg:address":"v/ Hans J\u00f8rgen H\u00f8y, B\u00f8geskovvej 16, Rasborg, Postboks 36",
    "sg:city":"Solbjerg",
    "sg:orig_category":"Hobbybetonede foreninger",
    "sg:postcode":"8355",
    "sg:province":"Danmark",
    "wof:name":"\u00c5rhus Frim\u00e6rke Klub (APK)",
    "wof:placetype":"venue"
},
  "geometry": {"coordinates":[10.0810050964,56.0374946594],"type":"Point"}
}