{
  "type": "Feature",
  "properties": {
    "iso:country":"DK",
    "sg:address":"Hastrupvej 1",
    "sg:city":"Spentrup",
    "sg:orig_category":"Kirker",
    "sg:postcode":"8981",
    "sg:province":"Danmark",
    "wof:name":"Spentrup Kirke",
    "wof:placetype":"venue"
},
  "geometry": {"coordinates":[10.0296201706,56.539390564],"type":"Point"}
}