{
  "type": "Feature",
  "properties": {
    "addr:full":"Vestre Gade 18, Br\u00f8ndby\u00f8ster Br\u00f8ndby Danmark 2605",
    "addr:housenumber":"18",
    "addr:postcode":"2605",
    "addr:street":"Vestre Gade",
    "iso:country":"DK",
    "sg:address":"Vestre Gade 18, Br\u00f8ndby\u00f8ster",
    "sg:city":"Br\u00f8ndby",
    "sg:orig_category":"Telekommunikation",
    "sg:phone":"+45 77 30 30 30",
    "sg:postcode":"2605",
    "sg:province":"Danmark",
    "wof:name":"Zone Systems A/S",
    "wof:placetype":"venue"
},
  "geometry": {"coordinates":[6.8762898445,62.4602813721],"type":"Point"}
}