{
  "type": "Feature",
  "properties": {
    "addr:full":"Industrivej 14 Fjerritslev Danmark 9690",
    "addr:housenumber":"14",
    "addr:postcode":"9690",
    "addr:street":"Industrivej",
    "iso:country":"DK",
    "sg:address":"Industrivej 14",
    "sg:city":"Fjerritslev",
    "sg:orig_category":"Autoreparation og -service",
    "sg:phone":"+45 98 21 17 27",
    "sg:postcode":"9690",
    "sg:province":"Danmark",
    "wof:name":"Holst, H.J.",
    "wof:placetype":"venue"
},
  "geometry": {"coordinates":[9.2514095306,57.0879631042],"type":"Point"}
}