{
  "type": "Feature",
  "properties": {
    "addr:full":"Resenvej 89 Skive Danmark 7800",
    "addr:housenumber":"89",
    "addr:postcode":"7800",
    "addr:street":"Resenvej",
    "iso:country":"DK",
    "sg:address":"Resenvej 89",
    "sg:city":"Skive",
    "sg:orig_category":"Faglige organisationer og foreninger",
    "sg:phone":"+45 97 52 06 77",
    "sg:postcode":"7800",
    "sg:province":"Danmark",
    "sg:website":"webhotel.sid.dk/skive_a",
    "wof:name":"SID - Skive afd. A",
    "wof:placetype":"venue"
},
  "geometry": {"coordinates":[9.0287647247,56.5799331665],"type":"Point"}
}