{
  "type": "Feature",
  "properties": {
    "addr:full":"Fmd.: Finn L. Falkersby, Svinget 17, st. K\u00f8benhavn S Danmark 2300",
    "addr:housenumber":"17",
    "addr:postcode":"2300",
    "addr:street":"Finn;Svinget;Danmark",
    "iso:country":"DK",
    "sg:address":"Fmd.: Finn L. Falkersby, Svinget 17, st.",
    "sg:city":"K\u00f8benhavn S",
    "sg:orig_category":"Kulturelle foreninger",
    "sg:phone":"+45 32 54 61 82",
    "sg:postcode":"2300",
    "sg:province":"Danmark",
    "wof:name":"Amager Kunstforening",
    "wof:placetype":"venue"
},
  "geometry": {"coordinates":[12.5980396271,55.6666603088],"type":"Point"}
}