{
  "type": "Feature",
  "properties": {
    "addr:full":"H. C. \u00d8rsteds Vej 4 Haderslev Danmark 6100",
    "addr:housenumber":"4",
    "addr:postcode":"6100",
    "addr:street":"H. C. Orsteds Vej",
    "iso:country":"DK",
    "sg:address":"H. C. \u00d8rsteds Vej 4",
    "sg:city":"Haderslev",
    "sg:orig_category":"Fabrikker",
    "sg:phone":"+45 74 52 63 63",
    "sg:postcode":"6100",
    "sg:province":"Danmark",
    "wof:name":"Nitodan A/S",
    "wof:placetype":"venue"
},
  "geometry": {"coordinates":[9.4941854477,55.2591514587],"type":"Point"}
}