{
  "type": "Feature",
  "properties": {
    "addr:full":"Oustrupvej 42 Aars Danmark 9600",
    "addr:housenumber":"42",
    "addr:postcode":"9600",
    "addr:street":"Oustrupvej",
    "iso:country":"DK",
    "sg:address":"Oustrupvej 42",
    "sg:city":"Aars",
    "sg:orig_category":"Fagforbund og fagforeninger",
    "sg:postcode":"9600",
    "sg:province":"Danmark",
    "wof:name":"LO i Aalestrup",
    "wof:placetype":"venue"
},
  "geometry": {"coordinates":[9.5280046463,56.8125801086],"type":"Point"}
}