{
  "type": "Feature",
  "properties": {
    "addr:full":"Vestergade 10 Vorbasse Danmark 6623",
    "addr:housenumber":"10",
    "addr:postcode":"6623",
    "addr:street":"Vestergade",
    "iso:country":"DK",
    "sg:address":"Vestergade 10",
    "sg:city":"Vorbasse",
    "sg:orig_category":"Sparekasser",
    "sg:phone":"+45 75 33 37 88",
    "sg:postcode":"6623",
    "sg:province":"Danmark",
    "wof:name":"Vorbasse - Hejnsvig Sparekasse",
    "wof:placetype":"venue"
},
  "geometry": {"coordinates":[9.0800714493,55.6303329468],"type":"Point"}
}