{
  "type": "Feature",
  "properties": {
    "addr:full":"Idr\u00e6tsvej 5 Esperg\u00e6rde Danmark 3060",
    "addr:housenumber":"5",
    "addr:postcode":"3060",
    "addr:street":"Idraetsvej",
    "iso:country":"DK",
    "sg:address":"Idr\u00e6tsvej 5",
    "sg:city":"Esperg\u00e6rde",
    "sg:orig_category":"Cafeterier",
    "sg:phone":"+45 49 13 51 59",
    "sg:postcode":"3060",
    "sg:province":"Danmark",
    "wof:name":"Cafeteriet Idr\u00e6tshallen",
    "wof:placetype":"venue"
},
  "geometry": {"coordinates":[11.6512403488,47.8390617371],"type":"Point"}
}