{
  "type": "Feature",
  "properties": {
    "addr:full":"Storegade 53 Hadsund Danmark 9560",
    "addr:housenumber":"53",
    "addr:postcode":"9560",
    "addr:street":"Storegade",
    "iso:country":"DK",
    "sg:address":"Storegade 53",
    "sg:city":"Hadsund",
    "sg:orig_category":"Cafeterier",
    "sg:phone":"+45 98 57 20 11",
    "sg:postcode":"9560",
    "sg:province":"Danmark",
    "wof:name":"Center Caf\u00e9en",
    "wof:placetype":"venue"
},
  "geometry": {"coordinates":[10.1148862839,56.7185401917],"type":"Point"}
}