{
  "type": "Feature",
  "properties": {
    "iso:country":"DK",
    "sg:address":"v/ Peter L. Nielsen, H\u00f8rbyg\u00e5rdvej 3, \u00d8ls",
    "sg:city":"Hobro",
    "sg:orig_category":"Soldaterforeninger",
    "sg:phone":"+45 98 52 54 48",
    "sg:postcode":"9500",
    "sg:province":"Danmark",
    "sg:website":"www.garderforeningerne.dk",
    "wof:name":"Garderforeningen for Randers by og Omegn",
    "wof:placetype":"venue"
},
  "geometry": {"coordinates":[9.7946596146,56.6382789612],"type":"Point"}
}