{
  "type": "Feature",
  "properties": {
    "iso:country":"DK",
    "sg:address":"Struervej 78",
    "sg:city":"Holstebro",
    "sg:orig_category":"Benzinstationer",
    "sg:phone":"+45 99 33 33 88",
    "sg:postcode":"7500",
    "sg:province":"Danmark",
    "wof:name":"Metax Benzin",
    "wof:placetype":"venue"
},
  "geometry": {"coordinates":[8.616623,56.371578],"type":"Point"}
}