{
  "type": "Feature",
  "properties": {
    "addr:full":"Langgade 16 - 18 Nyk\u00f8bing Danmark 4800",
    "addr:housenumber":"16 18",
    "addr:postcode":"4800",
    "addr:street":"Langgade",
    "iso:country":"DK",
    "sg:address":"Langgade 16 - 18",
    "sg:city":"Nyk\u00f8bing",
    "sg:orig_category":"Korn og foderstoffer",
    "sg:phone":"+45 54 85 27 22",
    "sg:postcode":"4800",
    "sg:province":"Danmark",
    "wof:name":"Aktieselskabet Korn- og Foderstof Kompagniet",
    "wof:placetype":"venue"
},
  "geometry": {"coordinates":[-114.0768203735,46.4432411194],"type":"Point"}
}