{
  "type": "Feature",
  "properties": {
    "addr:full":"Jernbanegade 13 K\u00f8ge Danmark 4600",
    "addr:housenumber":"13",
    "addr:postcode":"4600",
    "addr:street":"Jernbanegade",
    "iso:country":"DK",
    "sg:address":"Jernbanegade 13",
    "sg:city":"K\u00f8ge",
    "sg:orig_category":"Farve og tapet",
    "sg:phone":"+45 56 65 22 01",
    "sg:postcode":"4600",
    "sg:province":"Danmark",
    "wof:name":"S\u00f8ndergaards Farver",
    "wof:placetype":"venue"
},
  "geometry": {"coordinates":[12.2430353165,55.4170417786],"type":"Point"}
}