{
  "type": "Feature",
  "properties": {
    "addr:full":"Hovedgaden 8 Humble Danmark 5932",
    "addr:housenumber":"8",
    "addr:postcode":"5932",
    "addr:street":"Hovedgaden",
    "iso:country":"DK",
    "sg:address":"Hovedgaden 8",
    "sg:city":"Humble",
    "sg:orig_category":"Boghandlere",
    "sg:phone":"+45 62 57 10 04",
    "sg:postcode":"5932",
    "sg:province":"Danmark",
    "sg:website":"www.bogguide.dk/7303",
    "wof:name":"St\u00fcrup's Boghandel",
    "wof:placetype":"venue"
},
  "geometry": {"coordinates":[10.6991329193,54.8269615173],"type":"Point"}
}