{
  "type": "Feature",
  "properties": {
    "addr:full":"Niels Ebbesens Vej 21 Frederiksberg Danmark 1911",
    "addr:housenumber":"21",
    "addr:postcode":"1911",
    "addr:street":"Niels Ebbesens Vej",
    "iso:country":"DK",
    "sg:address":"Niels Ebbesens Vej 21",
    "sg:city":"Frederiksberg",
    "sg:orig_category":"Vuggestuer",
    "sg:phone":"+45 38 21 15 00",
    "sg:postcode":"1911",
    "sg:province":"Danmark",
    "wof:name":"Hobbitten, Frederiksberg Kommunes Vuggestue",
    "wof:placetype":"venue"
},
  "geometry": {"coordinates":[12.550151825,55.6781311035],"type":"Point"}
}