{
  "type": "Feature",
  "properties": {
    "iso:country":"DK",
    "sg:address":"Lundvej 4",
    "sg:city":"Viborg",
    "sg:orig_category":"Snedkermestre",
    "sg:phone":"+45 86 61 41 06",
    "sg:postcode":"8800",
    "sg:province":"Danmark",
    "wof:name":"J\u00f8rgensen, Morten",
    "wof:placetype":"venue"
},
  "geometry": {"coordinates":[9.3760976791,56.4633255005],"type":"Point"}
}