{
  "type": "Feature",
  "properties": {
    "addr:full":"Thrigesvej 16 Silkeborg Danmark 8600",
    "addr:housenumber":"16",
    "addr:postcode":"8600",
    "addr:street":"Thrigesvej",
    "iso:country":"DK",
    "sg:address":"Thrigesvej 16",
    "sg:city":"Silkeborg",
    "sg:orig_category":"Malermestre",
    "sg:phone":"+45 86 80 15 66",
    "sg:postcode":"8600",
    "sg:province":"Danmark",
    "wof:name":"Nielsen & S\u00f8n, Malerfirmaet",
    "wof:placetype":"venue"
},
  "geometry": {"coordinates":[9.563794136,56.1968154907],"type":"Point"}
}