{
  "type": "Feature",
  "properties": {
    "addr:full":"S\u00f8lystvej 2 Aalborg \u00d8 Danmark 9220",
    "addr:housenumber":"2",
    "addr:postcode":"9220",
    "addr:street":"Solystvej;Danmark",
    "iso:country":"DK",
    "sg:address":"S\u00f8lystvej 2",
    "sg:city":"Aalborg \u00d8",
    "sg:orig_category":"Kirker",
    "sg:postcode":"9220",
    "sg:province":"Danmark",
    "wof:name":"R\u00f8rdal Kirke",
    "wof:placetype":"venue"
},
  "geometry": {"coordinates":[9.9667215347,57.0562744141],"type":"Point"}
}