{
  "type": "Feature",
  "properties": {
    "addr:full":"Herlev Hovedgade 82 Herlev Danmark 2730",
    "addr:housenumber":"82",
    "addr:postcode":"2730",
    "addr:street":"Herlev Hovedgade",
    "iso:country":"DK",
    "sg:address":"Herlev Hovedgade 82",
    "sg:city":"Herlev",
    "sg:orig_category":"Autoudlejning",
    "sg:phone":"+45 44 94 66 67",
    "sg:postcode":"2730",
    "sg:province":"Danmark",
    "sg:website":"www.europcar.dk",
    "wof:name":"Europcar",
    "wof:placetype":"venue"
},
  "geometry": {"coordinates":[12.4487743378,55.7203712463],"type":"Point"}
}