{
  "type": "Feature",
  "properties": {
    "addr:full":"Strandbyvej 41 Aalborg \u00d8 Danmark 9220",
    "addr:housenumber":"41",
    "addr:postcode":"9220",
    "addr:street":"Strandbyvej;Danmark",
    "iso:country":"DK",
    "sg:address":"Strandbyvej 41",
    "sg:city":"Aalborg \u00d8",
    "sg:orig_category":"Murermestre",
    "sg:phone":"+45 98 15 77 03",
    "sg:postcode":"9220",
    "sg:province":"Danmark",
    "wof:name":"Bach, Br\u00f8drene",
    "wof:placetype":"venue"
},
  "geometry": {"coordinates":[10.0165262222,57.0369682312],"type":"Point"}
}