{
  "type": "Feature",
  "properties": {
    "addr:full":"Rytterhaven 12 Svendborg Danmark 5700",
    "addr:housenumber":"12",
    "addr:postcode":"5700",
    "addr:street":"Rytterhaven",
    "iso:country":"DK",
    "sg:address":"Rytterhaven 12",
    "sg:city":"Svendborg",
    "sg:orig_category":"Naturgas",
    "sg:phone":"+45 62 21 10 83",
    "sg:postcode":"5700",
    "sg:province":"Danmark",
    "wof:name":"Rasmussen VVS, Bent",
    "wof:placetype":"venue"
},
  "geometry": {"coordinates":[10.5693368912,55.0687599182],"type":"Point"}
}