{
  "type": "Feature",
  "properties": {
    "addr:full":"Havnevagtvej 4  Skagen Danmark 9990",
    "addr:housenumber":"4",
    "addr:postcode":"9990",
    "addr:street":"Havnevagtvej",
    "iso:country":"DK",
    "sg:address":"Havnevagtvej 4 ",
    "sg:city":"Skagen",
    "sg:classifiers":[
        {
            "category":"Farming",
            "subcategory":"Livestock Farm",
            "type":"Manufacturing & Wholesale Goods"
        }
    ],
    "sg:phone":"+45 98 44 18 33",
    "sg:postcode":"9990",
    "sg:province":"Danmark",
    "sg:tags":[
        "agriculture"
    ],
    "wof:name":"HAVFISK SKAGEN A/S",
    "wof:placetype":"venue"
},
  "geometry": {"coordinates":[10.5963029861,57.7215805054],"type":"Point"}
}