{
  "type": "Feature",
  "properties": {
    "addr:full":"Alkj\u00e6rh\u00f8j 13 Ringk\u00f8bing Danmark 6950",
    "addr:housenumber":"13",
    "addr:postcode":"6950",
    "addr:street":"Alkjaerhoj",
    "iso:country":"DK",
    "sg:address":"Alkj\u00e6rh\u00f8j 13",
    "sg:city":"Ringk\u00f8bing",
    "sg:orig_category":"Musik- og solistbureauer",
    "sg:phone":"+45 97 32 39 30",
    "sg:postcode":"6950",
    "sg:province":"Danmark",
    "wof:name":"Star Music",
    "wof:placetype":"venue"
},
  "geometry": {"coordinates":[-114.0767440796,46.4432487488],"type":"Point"}
}