{
  "type": "Feature",
  "properties": {
    "addr:full":"Vestergade 8, Herrestrup Grevinge Danmark 4571",
    "addr:housenumber":"8",
    "addr:postcode":"4571",
    "addr:street":"Vestergade",
    "iso:country":"DK",
    "sg:address":"Vestergade 8, Herrestrup",
    "sg:city":"Grevinge",
    "sg:orig_category":"Skolefritidsordninger",
    "sg:phone":"+45 59 65 85 53",
    "sg:postcode":"4571",
    "sg:province":"Danmark",
    "wof:name":"SFO Grevinge Centralskole",
    "wof:placetype":"venue"
},
  "geometry": {"coordinates":[11.5593652725,55.7873153687],"type":"Point"}
}