{
  "type": "Feature",
  "properties": {
    "addr:full":"Vangled 17, Nordby Fan\u00f8 Danmark 6720",
    "addr:housenumber":"17",
    "addr:postcode":"6720",
    "addr:street":"Vangled",
    "iso:country":"DK",
    "sg:address":"Vangled 17, Nordby",
    "sg:city":"Fan\u00f8",
    "sg:orig_category":"Fotografer",
    "sg:phone":"+45 75 16 20 42",
    "sg:postcode":"6720",
    "sg:province":"Danmark",
    "wof:name":"Jacobsen, Ann Birgitte Ulrich",
    "wof:placetype":"venue"
},
  "geometry": {"coordinates":[8.4069461823,55.4484786987],"type":"Point"}
}