{
  "type": "Feature",
  "properties": {
    "addr:full":"Bredsten Ldv. 131, Karlskov Give Danmark 7323",
    "addr:housenumber":"131",
    "addr:postcode":"7323",
    "addr:street":"Karlskov",
    "iso:country":"DK",
    "sg:address":"Bredsten Ldv. 131, Karlskov",
    "sg:city":"Give",
    "sg:orig_category":"Skolefritidsordninger",
    "sg:phone":"+45 75 73 80 44",
    "sg:postcode":"7323",
    "sg:province":"Danmark",
    "wof:name":"SFO i Karlskov",
    "wof:placetype":"venue"
},
  "geometry": {"coordinates":[9.2362060547,55.845413208],"type":"Point"}
}