{
  "type": "Feature",
  "properties": {
    "addr:full":"R\u00f8nnevej 5, Kildekrog Hornb\u00e6k Danmark 3100",
    "addr:housenumber":"5",
    "addr:postcode":"3100",
    "addr:street":"Ronnevej",
    "iso:country":"DK",
    "sg:address":"R\u00f8nnevej 5, Kildekrog",
    "sg:city":"Hornb\u00e6k",
    "sg:orig_category":"Ejendomshandel",
    "sg:phone":"+45 40 28 06 57",
    "sg:postcode":"3100",
    "sg:province":"Danmark",
    "sg:website":"www.jhc.dk",
    "wof:name":"J.H.C Bolig",
    "wof:placetype":"venue"
},
  "geometry": {"coordinates":[12.4300451279,56.0916366577],"type":"Point"}
}