{
  "type": "Feature",
  "properties": {
    "addr:full":"Dals\u00f8 Park 118, Kr. V\u00e6rl\u00f8se V\u00e6rl\u00f8se Danmark 3500",
    "addr:housenumber":"118",
    "addr:postcode":"3500",
    "addr:street":"Kr. Vaerlose Vaerlose Danmark",
    "iso:country":"DK",
    "sg:address":"Dals\u00f8 Park 118, Kr. V\u00e6rl\u00f8se",
    "sg:city":"V\u00e6rl\u00f8se",
    "sg:orig_category":"EDB - udstyr",
    "sg:phone":"+45 44 48 46 18",
    "sg:postcode":"3500",
    "sg:province":"Danmark",
    "wof:name":"S L Consult",
    "wof:placetype":"venue"
},
  "geometry": {"coordinates":[127.8501663208,36.4481506348],"type":"Point"}
}