{
  "type": "Feature",
  "properties": {
    "addr:full":"Skolegade 16 Nyk\u00f8bing Danmark 4800",
    "addr:housenumber":"16",
    "addr:postcode":"4800",
    "addr:street":"Skolegade",
    "iso:country":"DK",
    "sg:address":"Skolegade 16",
    "sg:city":"Nyk\u00f8bing",
    "sg:orig_category":"Teatre",
    "sg:phone":"+45 54 88 99 66",
    "sg:postcode":"4800",
    "sg:province":"Danmark",
    "wof:name":"Masken Egnsteater",
    "wof:placetype":"venue"
},
  "geometry": {"coordinates":[-114.0768203735,46.4432411194],"type":"Point"}
}