{
  "type": "Feature",
  "properties": {
    "addr:full":"Kaslundvej 36, \u00d8rsbjerg Aarup Danmark 5560",
    "addr:housenumber":"36",
    "addr:postcode":"5560",
    "addr:street":"Kaslundvej",
    "iso:country":"DK",
    "sg:address":"Kaslundvej 36, \u00d8rsbjerg",
    "sg:city":"Aarup",
    "sg:orig_category":"Rideskoler",
    "sg:phone":"+45 64 43 16 19",
    "sg:postcode":"5560",
    "sg:province":"Danmark",
    "wof:name":"V\u00e6ngeg\u00e5rdens Rideskole",
    "wof:placetype":"venue"
},
  "geometry": {"coordinates":[10.0490245819,55.3808059692],"type":"Point"}
}