{
  "type": "Feature",
  "properties": {
    "addr:full":"Vigsn\u00e6s Byvej 34 Guldborg Danmark 4862",
    "addr:housenumber":"34",
    "addr:postcode":"4862",
    "addr:street":"Vigsnaes Byvej",
    "iso:country":"DK",
    "sg:address":"Vigsn\u00e6s Byvej 34",
    "sg:city":"Guldborg",
    "sg:orig_category":"Transport",
    "sg:phone":"+45 40 88 55 51",
    "sg:postcode":"4862",
    "sg:province":"Danmark",
    "wof:name":"Tempo Transport",
    "wof:placetype":"venue"
},
  "geometry": {"coordinates":[11.7405948639,54.8682060242],"type":"Point"}
}