{
  "type": "Feature",
  "properties": {
    "addr:full":"Bakkevej 6 H\u00f8ng Danmark 4270",
    "addr:housenumber":"6",
    "addr:postcode":"4270",
    "addr:street":"Bakkevej;Hong Danmark",
    "iso:country":"DK",
    "sg:address":"Bakkevej 6",
    "sg:city":"H\u00f8ng",
    "sg:orig_category":"Malermestre",
    "sg:phone":"+45 58 85 25 90",
    "sg:postcode":"4270",
    "sg:province":"Danmark",
    "wof:name":"Christensen, Jan",
    "wof:placetype":"venue"
},
  "geometry": {"coordinates":[11.2921628952,55.5112075806],"type":"Point"}
}