{
  "type": "Feature",
  "properties": {
    "addr:full":"Elmegade 21 Vojens Danmark 6500",
    "addr:housenumber":"21",
    "addr:postcode":"6500",
    "addr:street":"Elmegade",
    "iso:country":"DK",
    "sg:address":"Elmegade 21",
    "sg:city":"Vojens",
    "sg:orig_category":"Cykler",
    "sg:phone":"+45 74 54 32 31",
    "sg:postcode":"6500",
    "sg:province":"Danmark",
    "wof:name":"Fri Cykler, Ludvig Cykler & Knallerter",
    "wof:placetype":"venue"
},
  "geometry": {"coordinates":[9.3003616333,55.2448043823],"type":"Point"}
}