{
  "type": "Feature",
  "properties": {
    "iso:country":"DK",
    "sg:address":"Overbys Alle 24",
    "sg:city":"Valby",
    "sg:orig_category":"Autoforhandlere",
    "sg:phone":"+45 36 16 17 18",
    "sg:postcode":"2500",
    "sg:province":"Danmark",
    "wof:name":"Autoforetningen",
    "wof:placetype":"venue"
},
  "geometry": {"coordinates":[12.500658989,55.665512085],"type":"Point"}
}