{
  "type": "Feature",
  "properties": {
    "addr:full":"Fmd.: Ingrid Bergman, Orevej 105, Ore Stubbek\u00f8bing Danmark 4850",
    "addr:housenumber":"105",
    "addr:postcode":"4850",
    "addr:street":"Orevej",
    "iso:country":"DK",
    "sg:address":"Fmd.: Ingrid Bergman, Orevej 105, Ore",
    "sg:city":"Stubbek\u00f8bing",
    "sg:orig_category":"Borger- og beboerforeninger",
    "sg:phone":"+45 54 44 16 79",
    "sg:postcode":"4850",
    "sg:province":"Danmark",
    "wof:name":"Aastrup sogns Beboerforening af 1983",
    "wof:placetype":"venue"
},
  "geometry": {"coordinates":[12.0587949753,54.8847007751],"type":"Point"}
}