{
  "type": "Feature",
  "properties": {
    "addr:full":"Broholmvej 42 Ikast Danmark 7430",
    "addr:housenumber":"42",
    "addr:postcode":"7430",
    "addr:street":"Broholmvej",
    "iso:country":"DK",
    "sg:address":"Broholmvej 42",
    "sg:city":"Ikast",
    "sg:orig_category":"Tagrenovering",
    "sg:phone":"+45 97 15 50 86",
    "sg:postcode":"7430",
    "sg:province":"Danmark",
    "wof:name":"Jydsk Tagrens",
    "wof:placetype":"venue"
},
  "geometry": {"coordinates":[9.1523447037,56.1570854187],"type":"Point"}
}