{
  "type": "Feature",
  "properties": {
    "addr:full":"Klanleder: Frank S\u00f8rensen, Vellingvej 29, Smidstrup Fredericia Danmark 7000",
    "addr:housenumber":"29",
    "addr:postcode":"7000",
    "addr:street":"Vellingvej",
    "iso:country":"DK",
    "sg:address":"Klanleder: Frank S\u00f8rensen, Vellingvej 29, Smidstrup",
    "sg:city":"Fredericia",
    "sg:orig_category":"Spejderkorps",
    "sg:phone":"+45 75 86 00 24",
    "sg:postcode":"7000",
    "sg:province":"Danmark",
    "wof:name":"KFUM/K-spejderne i Smidstrup-Sk\u00e6rup",
    "wof:placetype":"venue"
},
  "geometry": {"coordinates":[9.7591047287,55.566368103],"type":"Point"}
}