{
  "type": "Feature",
  "properties": {
    "addr:full":"\u00d8stervinge 24 Esbjerg Danmark 6700",
    "addr:housenumber":"24",
    "addr:postcode":"6700",
    "addr:street":"Ostervinge",
    "iso:country":"DK",
    "sg:address":"\u00d8stervinge 24",
    "sg:city":"Esbjerg",
    "sg:orig_category":"Pelsdyrartikler",
    "sg:phone":"+45 75 13 13 77",
    "sg:postcode":"6700",
    "sg:province":"Danmark",
    "wof:name":"Esbjerg Taner ApS",
    "wof:placetype":"venue"
},
  "geometry": {"coordinates":[8.4450073242,55.478931427],"type":"Point"}
}