{
  "type": "Feature",
  "properties": {
    "iso:country":"DK",
    "sg:address":"Menelaos Boulevard 71",
    "sg:city":"Hvidovre",
    "sg:orig_category":"Ejendomshandel",
    "sg:phone":"+45 36 78 22 74",
    "sg:postcode":"2650",
    "sg:province":"Danmark",
    "wof:name":"Andersen, Charles",
    "wof:placetype":"venue"
},
  "geometry": {"coordinates":[12.4678916931,55.6349105835],"type":"Point"}
}