{
  "type": "Feature",
  "properties": {
    "addr:full":"v/ Maren B. Lauridsen, Trekl\u00f8vervej 1, No Ringk\u00f8bing Danmark 6950",
    "addr:housenumber":"1",
    "addr:postcode":"6950",
    "addr:street":"Treklovervej;No Ringkobing Danmark",
    "iso:country":"DK",
    "sg:address":"v/ Maren B. Lauridsen, Trekl\u00f8vervej 1, No",
    "sg:city":"Ringk\u00f8bing",
    "sg:orig_category":"\u00c3\u02dcvrig fritidsundervisning",
    "sg:phone":"+45 97 33 52 00",
    "sg:postcode":"6950",
    "sg:province":"Danmark",
    "wof:name":"Ringk\u00f8bingegnens Husflidskreds",
    "wof:placetype":"venue"
},
  "geometry": {"coordinates":[8.2507953644,56.0878334045],"type":"Point"}
}