{
  "type": "Feature",
  "properties": {
    "iso:country":"DK",
    "sg:address":"Industriparken 2, Skodborg",
    "sg:city":"R\u00f8dding",
    "sg:orig_category":"Undervognsbehandling",
    "sg:phone":"+45 74 84 88 90",
    "sg:postcode":"6630",
    "sg:province":"Danmark",
    "sg:website":"www.pavamanden.dk",
    "wof:name":"Pava Undervognscenter",
    "wof:placetype":"venue"
},
  "geometry": {"coordinates":[9.2022953033,55.3564414978],"type":"Point"}
}