{
  "type": "Feature",
  "properties": {
    "addr:full":"Korsl\u00f8kkevej 1 M Odense S\u00d8 Danmark 5220",
    "addr:housenumber":"1",
    "addr:postcode":"5220",
    "addr:street":"Korslokkevej;M Odense",
    "iso:country":"DK",
    "sg:address":"Korsl\u00f8kkevej 1 M",
    "sg:city":"Odense S\u00d8",
    "sg:orig_category":"Boligselskaber",
    "sg:phone":"+45 66 15 66 76",
    "sg:postcode":"5220",
    "sg:province":"Danmark",
    "wof:name":"Fyns Almennyttige Boligselskab",
    "wof:placetype":"venue"
},
  "geometry": {"coordinates":[10.4583454132,55.3316917419],"type":"Point"}
}