{
  "type": "Feature",
  "properties": {
    "addr:full":"Svend Erik Willendrup, Slotsalle 8 B Augustenborg Danmark 6440",
    "addr:housenumber":"8 b",
    "addr:postcode":"6440",
    "addr:street":"Svend;Slotsalle",
    "iso:country":"DK",
    "sg:address":"Svend Erik Willendrup, Slotsalle 8 B",
    "sg:city":"Augustenborg",
    "sg:orig_category":"Hobbybetonede foreninger",
    "sg:phone":"+45 74 47 25 55",
    "sg:postcode":"6440",
    "sg:province":"Danmark",
    "sg:website":"www.dmkf.dk",
    "wof:name":"Dansk Milit\u00e6rhistorisk K\u00f8ret\u00f8js-Forening",
    "wof:placetype":"venue"
},
  "geometry": {"coordinates":[9.8727750778,54.9459037781],"type":"Point"}
}