{
  "type": "Feature",
  "properties": {
    "addr:full":"Bygaden 5, Venslev Skibby Danmark 4050",
    "addr:housenumber":"5",
    "addr:postcode":"4050",
    "addr:street":"Bygaden;Venslev",
    "iso:country":"DK",
    "sg:address":"Bygaden 5, Venslev",
    "sg:city":"Skibby",
    "sg:classifiers":[
        {
            "category":"Taxi",
            "type":"Transportation"
        }
    ],
    "sg:phone":"+45 47 52 91 39",
    "sg:postcode":"4050",
    "sg:province":"Danmark",
    "wof:name":"Venslev Taxi & Minibus",
    "wof:placetype":"venue"
},
  "geometry": {"coordinates":[11.9594116211,55.7502975464],"type":"Point"}
}