{
  "type": "Feature",
  "properties": {
    "addr:full":"Kvinderupvej 11 B, Kvinderup Slangerup Danmark 3550",
    "addr:housenumber":"11 b",
    "addr:postcode":"3550",
    "addr:street":"Kvinderupvej;Kvinderup",
    "iso:country":"DK",
    "sg:address":"Kvinderupvej 11 B, Kvinderup",
    "sg:city":"Slangerup",
    "sg:orig_category":"Landbrugsmaskiner",
    "sg:phone":"+45 48 27 86 16",
    "sg:postcode":"3550",
    "sg:province":"Danmark",
    "wof:name":"B\u00f8ttcher, Werner",
    "wof:placetype":"venue"
},
  "geometry": {"coordinates":[12.1717596054,55.8460769653],"type":"Point"}
}