{
  "type": "Feature",
  "properties": {
    "addr:full":"Humleb\u00e6kvej 32, Langstrup Fredensborg Danmark 3480",
    "addr:housenumber":"32",
    "addr:postcode":"3480",
    "addr:street":"Humlebaekvej",
    "iso:country":"DK",
    "sg:address":"Humleb\u00e6kvej 32, Langstrup",
    "sg:city":"Fredensborg",
    "sg:orig_category":"Engros handel",
    "sg:phone":"+45 48 48 29 00",
    "sg:postcode":"3480",
    "sg:province":"Danmark",
    "wof:name":"Reinhold Andersen",
    "wof:placetype":"venue"
},
  "geometry": {"coordinates":[12.4020547867,55.9782943726],"type":"Point"}
}