{
  "type": "Feature",
  "properties": {
    "addr:full":"Fmd.: J\u00f8rgen Holst, Bellisvej 12 Hj\u00f8rring Danmark 9800",
    "addr:housenumber":"12",
    "addr:postcode":"9800",
    "addr:street":"Bellisvej",
    "iso:country":"DK",
    "sg:address":"Fmd.: J\u00f8rgen Holst, Bellisvej 12",
    "sg:city":"Hj\u00f8rring",
    "sg:orig_category":"Hobbybetonede foreninger",
    "sg:phone":"+45 98 92 46 71",
    "sg:postcode":"9800",
    "sg:province":"Danmark",
    "wof:name":"Vendsyssel Motorcykelklub Genbrug",
    "wof:placetype":"venue"
},
  "geometry": {"coordinates":[-95.3725967407,47.6348991394],"type":"Point"}
}