{
  "type": "Feature",
  "properties": {
    "iso:country":"DK",
    "sg:address":"Siriusvej 1",
    "sg:city":"Ikast",
    "sg:orig_category":"Belysning",
    "sg:phone":"+45 97 15 77 25",
    "sg:postcode":"7430",
    "sg:province":"Danmark",
    "wof:name":"Elk\u00f8b Ikast",
    "wof:placetype":"venue"
},
  "geometry": {"coordinates":[9.142198,56.137985],"type":"Point"}
}