{
  "type": "Feature",
  "properties": {
    "addr:full":"Kettingvej 1 Augustenborg Danmark 6440",
    "addr:housenumber":"1",
    "addr:postcode":"6440",
    "addr:street":"Kettingvej",
    "iso:country":"DK",
    "sg:address":"Kettingvej 1",
    "sg:city":"Augustenborg",
    "sg:orig_category":"Skolefritidsordninger",
    "sg:phone":"+45 74 47 26 15",
    "sg:postcode":"6440",
    "sg:province":"Danmark",
    "wof:name":"Augustenborg Skole Skolefritidsordning",
    "wof:placetype":"venue"
},
  "geometry": {"coordinates":[9.8726673126,54.946559906],"type":"Point"}
}