{
  "type": "Feature",
  "properties": {
    "addr:full":"Trekanten 1, G\u00f8rslev Ringsted Danmark 4100",
    "addr:housenumber":"1",
    "addr:postcode":"4100",
    "addr:street":"Trekanten;Gorslev",
    "iso:country":"DK",
    "sg:address":"Trekanten 1, G\u00f8rslev",
    "sg:city":"Ringsted",
    "sg:orig_category":"Kirker",
    "sg:postcode":"4100",
    "sg:province":"Danmark",
    "wof:name":"G\u00f8rslev Kirke",
    "wof:placetype":"venue"
},
  "geometry": {"coordinates":[11.7875862122,55.4458961487],"type":"Point"}
}