{
  "type": "Feature",
  "properties": {
    "iso:country":"DK",
    "sg:address":"Ved Vesterport 4",
    "sg:city":"K\u00f8benhavn",
    "sg:orig_category":"Rejsebureauer",
    "sg:phone":"+45 70 13 33 00",
    "sg:postcode":"1612",
    "sg:province":"Danmark",
    "wof:name":"Simon's Charter",
    "wof:placetype":"venue"
},
  "geometry": {"coordinates":[12.5642995834,55.6741981506],"type":"Point"}
}