{
  "type": "Feature",
  "properties": {
    "addr:full":"M\u00f8llegade 9 - 13 \u00c5rhus C Danmark 8000",
    "addr:housenumber":"9 13",
    "addr:postcode":"8000",
    "addr:street":"Mollegade",
    "iso:country":"DK",
    "sg:address":"M\u00f8llegade 9 - 13",
    "sg:city":"\u00c5rhus C",
    "sg:orig_category":"Arkitekter",
    "sg:phone":"+45 70 11 70 11",
    "sg:postcode":"8000",
    "sg:province":"Danmark",
    "sg:website":"www.arkitektgruppen.dk",
    "wof:name":"Arkitektgruppen Aarhus",
    "wof:placetype":"venue"
},
  "geometry": {"coordinates":[4.717400074,49.7588005066],"type":"Point"}
}