{
  "type": "Feature",
  "properties": {
    "addr:full":"Leder: Bent Nielsen, Klempeg\u00e5rdsvej 117, Nr. Dalby Borup Danmark 4140",
    "addr:housenumber":"117",
    "addr:postcode":"4140",
    "addr:street":"Klempegaardsvej;Nr. Dalby",
    "iso:country":"DK",
    "sg:address":"Leder: Bent Nielsen, Klempeg\u00e5rdsvej 117, Nr. Dalby",
    "sg:city":"Borup",
    "sg:orig_category":"Musik og sang",
    "sg:phone":"+45 57 52 67 11",
    "sg:postcode":"4140",
    "sg:province":"Danmark",
    "wof:name":"Skovbo Seniorkor",
    "wof:placetype":"venue"
},
  "geometry": {"coordinates":[11.9749145508,55.4920845032],"type":"Point"}
}