{
  "type": "Feature",
  "properties": {
    "addr:full":"Assensvej 196 Stenstrup Danmark 5771",
    "addr:housenumber":"196",
    "addr:postcode":"5771",
    "addr:street":"Assensvej",
    "iso:country":"DK",
    "sg:address":"Assensvej 196",
    "sg:city":"Stenstrup",
    "sg:orig_category":"Murermestre",
    "sg:phone":"+45 62 26 24 24",
    "sg:postcode":"5771",
    "sg:province":"Danmark",
    "wof:name":"Christensen, Erik",
    "wof:placetype":"venue"
},
  "geometry": {"coordinates":[10.5017786026,55.1282844543],"type":"Point"}
}