{
  "type": "Feature",
  "properties": {
    "addr:full":"S\u00f8ndergade 21 H\u00f8jer Danmark 6280",
    "addr:housenumber":"21",
    "addr:postcode":"6280",
    "addr:street":"Sondergade",
    "iso:country":"DK",
    "sg:address":"S\u00f8ndergade 21",
    "sg:city":"H\u00f8jer",
    "sg:orig_category":"\u00c3\u02dcvrige skoler",
    "sg:phone":"+45 74 78 27 33",
    "sg:postcode":"6280",
    "sg:province":"Danmark",
    "sg:website":"www.designsem.dk",
    "wof:name":"Design Seminariet",
    "wof:placetype":"venue"
},
  "geometry": {"coordinates":[-2.1972899437,49.2049789429],"type":"Point"}
}