{
  "type": "Feature",
  "properties": {
    "addr:full":"Gruppeleder: Per Andersen, Pilevang 3 Haslev Danmark 4690",
    "addr:housenumber":"3",
    "addr:postcode":"4690",
    "addr:street":"Pilevang",
    "iso:country":"DK",
    "sg:address":"Gruppeleder: Per Andersen, Pilevang 3",
    "sg:city":"Haslev",
    "sg:orig_category":"Spejderkorps",
    "sg:phone":"+45 56 31 63 75",
    "sg:postcode":"4690",
    "sg:province":"Danmark",
    "wof:name":"KFUM-spejderne Peder Oxe Gruppe",
    "wof:placetype":"venue"
},
  "geometry": {"coordinates":[11.9678049088,55.3230895996],"type":"Point"}
}