{
  "type": "Feature",
  "properties": {
    "iso:country":"DK",
    "sg:address":"\u00d8stre Havnevej 2, Havnebyen",
    "sg:city":"Sj\u00e6llands Odde",
    "sg:classifiers":[
        {
            "category":"Banks & Credit Unions",
            "subcategory":"Bank",
            "type":"Services"
        }
    ],
    "sg:phone":"+45 59 36 34 20",
    "sg:postcode":"4583",
    "sg:province":"Danmark",
    "sg:tags":[
        "banker"
    ],
    "sg:website":"www.danskebank.dk",
    "wof:name":"Danske Bank",
    "wof:placetype":"venue"
},
  "geometry": {"coordinates":[11.319868,55.979973],"type":"Point"}
}