{
  "type": "Feature",
  "properties": {
    "addr:full":"Nimbusvej 7-11 Greve Danmark 2670",
    "addr:housenumber":"7-11",
    "addr:postcode":"2670",
    "addr:street":"Nimbusvej",
    "iso:country":"DK",
    "sg:address":"Nimbusvej 7-11",
    "sg:city":"Greve",
    "sg:orig_category":"Hydraulik",
    "sg:phone":"+45 43 97 05 00",
    "sg:postcode":"2670",
    "sg:province":"Danmark",
    "sg:website":"www.hydra.dk",
    "wof:name":"Hydra Grene A/S",
    "wof:placetype":"venue"
},
  "geometry": {"coordinates":[12.3031415939,55.6072425842],"type":"Point"}
}