{
  "type": "Feature",
  "properties": {
    "iso:country":"DK",
    "sg:address":"\u00d8stervej 1, Kolby",
    "sg:city":"Sams\u00f8",
    "sg:orig_category":"Begravelsesforretninger",
    "sg:phone":"+45 86 59 05 65",
    "sg:postcode":"8305",
    "sg:province":"Danmark",
    "wof:name":"Sams\u00f8 Begravelsesforretning",
    "wof:placetype":"venue"
},
  "geometry": {"coordinates":[10.5885,55.83202],"type":"Point"}
}