{
  "type": "Feature",
  "properties": {
    "addr:full":"Ulvevej 21 Havdrup Danmark 4622",
    "addr:housenumber":"21",
    "addr:postcode":"4622",
    "addr:street":"Ulvevej",
    "iso:country":"DK",
    "sg:address":"Ulvevej 21",
    "sg:city":"Havdrup",
    "sg:orig_category":"Flasker",
    "sg:phone":"+45 46 18 54 80",
    "sg:postcode":"4622",
    "sg:province":"Danmark",
    "sg:website":"www.flaskegenbrug.dk",
    "wof:name":"Kroghs Flaskegenbrug A/S",
    "wof:placetype":"venue"
},
  "geometry": {"coordinates":[12.1223106384,55.5492477417],"type":"Point"}
}