{
  "type": "Feature",
  "properties": {
    "iso:country":"DK",
    "sg:address":"Fruedalsvej 10",
    "sg:city":"Tureby",
    "sg:classifiers":[
        {
            "category":"Professional",
            "subcategory":"Art Services",
            "type":"Services"
        }
    ],
    "sg:phone":"+45 56 28 34 15",
    "sg:postcode":"4682",
    "sg:province":"Danmark",
    "sg:tags":[
        "blomster"
    ],
    "wof:name":"Pr\u00e6strud & Kjeldsmark",
    "wof:placetype":"venue"
},
  "geometry": {"coordinates":[12.085395,55.389927],"type":"Point"}
}