{
  "type": "Feature",
  "properties": {
    "addr:full":"Forstander: Inger Kragh-Schwarz, Nordkrogen 24, Jelling Jelling Danmark 7300",
    "addr:housenumber":"24",
    "addr:postcode":"7300",
    "addr:street":"Nordkrogen",
    "iso:country":"DK",
    "sg:address":"Forstander: Inger Kragh-Schwarz, Nordkrogen 24, Jelling",
    "sg:city":"Jelling",
    "sg:orig_category":"\u00c3\u2020ldreorganisationer og klubber",
    "sg:phone":"+45 75 87 24 11",
    "sg:postcode":"7300",
    "sg:province":"Danmark",
    "wof:name":"\u00c6ldre p\u00e5 H\u00f8jskole i Udlandet",
    "wof:placetype":"venue"
},
  "geometry": {"coordinates":[9.4184103012,55.7558555603],"type":"Point"}
}