{
  "type": "Feature",
  "properties": {
    "addr:full":"v/ Bent Esbensen, Gl. Vardevej 213 Esbjerg N Danmark 6715",
    "addr:housenumber":"213",
    "addr:postcode":"6715",
    "addr:street":"Gl. Vardevej",
    "iso:country":"DK",
    "sg:address":"v/ Bent Esbensen, Gl. Vardevej 213",
    "sg:city":"Esbjerg N",
    "sg:orig_category":"Hobbybetonede foreninger",
    "sg:phone":"+45 75 12 48 98",
    "sg:postcode":"6715",
    "sg:province":"Danmark",
    "wof:name":"Vestjysk Flyveklub",
    "wof:placetype":"venue"
},
  "geometry": {"coordinates":[8.4780550003,55.535610199],"type":"Point"}
}