{
  "type": "Feature",
  "properties": {
    "addr:full":"Kalundborgvej 59 A Slagelse Danmark 4200",
    "addr:housenumber":"59 a",
    "addr:postcode":"4200",
    "addr:street":"Kalundborgvej",
    "iso:country":"DK",
    "sg:address":"Kalundborgvej 59 A",
    "sg:city":"Slagelse",
    "sg:orig_category":"Plejecentre",
    "sg:phone":"+45 58 53 33 55",
    "sg:postcode":"4200",
    "sg:province":"Danmark",
    "wof:name":"Plejecentret Elmelunden",
    "wof:placetype":"venue"
},
  "geometry": {"coordinates":[11.3363752365,55.4134254456],"type":"Point"}
}