{
  "type": "Feature",
  "properties": {
    "addr:full":"Rug\u00e5rdsvej 727 Morud Danmark 5462",
    "addr:housenumber":"727",
    "addr:postcode":"5462",
    "addr:street":"Rugaardsvej",
    "iso:country":"DK",
    "sg:address":"Rug\u00e5rdsvej 727",
    "sg:city":"Morud",
    "sg:orig_category":"Tandklinikker, Kommunale",
    "sg:phone":"+45 65 96 44 30",
    "sg:postcode":"5462",
    "sg:province":"Danmark",
    "wof:name":"Havrehedskolens komm. tandklinik",
    "wof:placetype":"venue"
},
  "geometry": {"coordinates":[10.1953392029,55.443572998],"type":"Point"}
}