{
  "type": "Feature",
  "properties": {
    "iso:country":"DK",
    "sg:address":"Albuen 3",
    "sg:city":"Kolding",
    "sg:orig_category":"Babyudstyr",
    "sg:phone":"+45 75 50 71 88",
    "sg:postcode":"6000",
    "sg:province":"Danmark",
    "wof:name":"Alt til Mor & Barn ApS",
    "wof:placetype":"venue"
},
  "geometry": {"coordinates":[9.456125,55.516651],"type":"Point"}
}