{
  "type": "Feature",
  "properties": {
    "addr:full":"Herlev Hovedgade 123 Herlev Danmark 2730",
    "addr:housenumber":"123",
    "addr:postcode":"2730",
    "addr:street":"Herlev Hovedgade",
    "iso:country":"DK",
    "sg:address":"Herlev Hovedgade 123",
    "sg:city":"Herlev",
    "sg:orig_category":"Pizzeriaer",
    "sg:phone":"+45 44 84 05 08",
    "sg:postcode":"2730",
    "sg:province":"Danmark",
    "wof:name":"Sorrentos Pizzeria & Cafe",
    "wof:placetype":"venue"
},
  "geometry": {"coordinates":[12.439915657,55.7227592468],"type":"Point"}
}