{
  "type": "Feature",
  "properties": {
    "iso:country":"DK",
    "sg:address":"Rustrupvej 18",
    "sg:city":"Them",
    "sg:orig_category":"Korn og foderstoffer",
    "sg:phone":"+45 86 84 70 99",
    "sg:postcode":"8653",
    "sg:province":"Danmark",
    "wof:name":"Aarhusegnens Andel A.m.b.A.",
    "wof:placetype":"venue"
},
  "geometry": {"coordinates":[9.5425462723,56.0959854126],"type":"Point"}
}