{
  "type": "Feature",
  "properties": {
    "addr:full":"Hostrupsgade 41 A Silkeborg Danmark 8600",
    "addr:housenumber":"41 a",
    "addr:postcode":"8600",
    "addr:street":"Hostrupsgade",
    "iso:country":"DK",
    "sg:address":"Hostrupsgade 41 A",
    "sg:city":"Silkeborg",
    "sg:orig_category":"Lokalarkiver",
    "sg:phone":"+45 87 22 19 24",
    "sg:postcode":"8600",
    "sg:province":"Danmark",
    "sg:website":"www.silkeborg-bibliotek.dk",
    "wof:name":"Lokalhistorisk Arkiv",
    "wof:placetype":"venue"
},
  "geometry": {"coordinates":[9.5462150574,56.1658096313],"type":"Point"}
}