{
  "type": "Feature",
  "properties": {
    "addr:full":"Brogade 33 Svendborg Danmark 5700",
    "addr:housenumber":"33",
    "addr:postcode":"5700",
    "addr:street":"Brogade",
    "iso:country":"DK",
    "sg:address":"Brogade 33",
    "sg:city":"Svendborg",
    "sg:orig_category":"RESTAURANTS: CAFEER",
    "sg:phone":"+45 62 20 21 95",
    "sg:postcode":"5700",
    "sg:province":"Danmark",
    "wof:name":"Citronen, Caf\u00e9",
    "wof:placetype":"venue"
},
  "geometry": {"coordinates":[10.6109275818,55.0584373474],"type":"Point"}
}