{
  "type": "Feature",
  "properties": {
    "addr:full":"Kredsl.: Thomas Dalsgaard, Gr\u00f8nlykkeparken 21 D Greve Danmark 2670",
    "addr:housenumber":"21 d",
    "addr:postcode":"2670",
    "addr:street":"Gronlykkeparken",
    "iso:country":"DK",
    "sg:address":"Kredsl.: Thomas Dalsgaard, Gr\u00f8nlykkeparken 21 D",
    "sg:city":"Greve",
    "sg:orig_category":"Spejderkorps",
    "sg:phone":"+45 43 97 76 97",
    "sg:postcode":"2670",
    "sg:province":"Danmark",
    "sg:website":"www.fdf.dk/hundige",
    "wof:name":"FDF Hundige Kreds",
    "wof:placetype":"venue"
},
  "geometry": {"coordinates":[12.2941808701,55.5844078064],"type":"Point"}
}