{
  "type": "Feature",
  "properties": {
    "iso:country":"DK",
    "sg:address":"Elvej 1",
    "sg:city":"Agerskov",
    "sg:orig_category":"Bodegaer",
    "sg:phone":"+45 74 83 39 33",
    "sg:postcode":"6534",
    "sg:province":"Danmark",
    "wof:name":"\u00c6 Baneg\u00e5rd",
    "wof:placetype":"venue"
},
  "geometry": {"coordinates":[9.1272974014,55.1308631897],"type":"Point"}
}