{
  "type": "Feature",
  "properties": {
    "addr:full":"Nissumvej 34, N\u00f8rlem Lemvig Danmark 7620",
    "addr:housenumber":"34",
    "addr:postcode":"7620",
    "addr:street":"Nissumvej",
    "iso:country":"DK",
    "sg:address":"Nissumvej 34, N\u00f8rlem",
    "sg:city":"Lemvig",
    "sg:orig_category":"Integrerede institutioner",
    "sg:phone":"+45 97 82 09 93",
    "sg:postcode":"7620",
    "sg:province":"Danmark",
    "wof:name":"N\u00f8rlem B\u00f8rnehave og Fritidshjem",
    "wof:placetype":"venue"
},
  "geometry": {"coordinates":[8.3073654175,56.5505104065],"type":"Point"}
}