{
  "type": "Feature",
  "properties": {
    "addr:full":"Langen\u00e6sparken, \u00c5benr\u00e5gade 0 \u00c5rhus C Danmark 8000",
    "addr:housenumber":"0",
    "addr:postcode":"8000",
    "addr:street":"Langenaesparken Aabenraagade",
    "iso:country":"DK",
    "sg:address":"Langen\u00e6sparken, \u00c5benr\u00e5gade 0",
    "sg:city":"\u00c5rhus C",
    "sg:orig_category":"Legesteder",
    "sg:phone":"+45 86 11 52 58",
    "sg:postcode":"8000",
    "sg:province":"Danmark",
    "wof:name":"Legepladsen Langen\u00e6s",
    "wof:placetype":"venue"
},
  "geometry": {"coordinates":[99.92501068120001,34.2430114746],"type":"Point"}
}