{
  "type": "Feature",
  "properties": {
    "iso:country":"DK",
    "sg:address":"Falkoner Alle 120",
    "sg:city":"Frederiksberg",
    "sg:orig_category":"Blomsterhandlere",
    "sg:phone":"+45 35 39 08 42",
    "sg:postcode":"2000",
    "sg:province":"Danmark",
    "wof:name":"Flora, Fr\u00f8ken",
    "wof:placetype":"venue"
},
  "geometry": {"coordinates":[12.541015625,55.6873283386],"type":"Point"}
}