{
  "type": "Feature",
  "properties": {
    "addr:full":"Fiskerhusene 26 Albertslund Danmark 2620",
    "addr:housenumber":"26",
    "addr:postcode":"2620",
    "addr:street":"Fiskerhusene",
    "iso:country":"DK",
    "sg:address":"Fiskerhusene 26",
    "sg:city":"Albertslund",
    "sg:orig_category":"Revisorer",
    "sg:phone":"+45 43 64 95 43",
    "sg:postcode":"2620",
    "sg:province":"Danmark",
    "wof:name":"AR Revision",
    "wof:placetype":"venue"
},
  "geometry": {"coordinates":[12.3587598801,55.6711883545],"type":"Point"}
}