{
  "type": "Feature",
  "properties": {
    "addr:full":"Bredgade 146 Hurup Danmark 7760",
    "addr:housenumber":"146",
    "addr:postcode":"7760",
    "addr:street":"Bredgade",
    "iso:country":"DK",
    "sg:address":"Bredgade 146",
    "sg:city":"Hurup",
    "sg:orig_category":"Kiropraktorer",
    "sg:phone":"+45 97 95 11 15",
    "sg:postcode":"7760",
    "sg:province":"Danmark",
    "wof:name":"Kiropraktorerne i Thy",
    "wof:placetype":"venue"
},
  "geometry": {"coordinates":[8.4183635712,56.7502822876],"type":"Point"}
}