{
  "type": "Feature",
  "properties": {
    "addr:full":"Amagerf\u00e6lledvej 22, 3 th K\u00f8benhavn S Danmark 2300",
    "addr:housenumber":"22 3 th",
    "addr:postcode":"2300",
    "addr:street":"Amagerfaelledvej;Kobenhavn S Danmark",
    "iso:country":"DK",
    "sg:address":"Amagerf\u00e6lledvej 22, 3 th",
    "sg:city":"K\u00f8benhavn S",
    "sg:orig_category":"Konsulentvirksomheder",
    "sg:phone":"+45 32 54 80 36",
    "sg:postcode":"2300",
    "sg:province":"Danmark",
    "sg:website":"www.webhuset.dk/erhvervsfilosof.dk",
    "wof:name":"Filosofisk Konsulent Mag. Art",
    "wof:placetype":"venue"
},
  "geometry": {"coordinates":[-78.1299133301,36.7267417908],"type":"Point"}
}