{
  "type": "Feature",
  "properties": {
    "iso:country":"DK",
    "sg:address":"Sm\u00f8rmosevej 7, Thur\u00f8",
    "sg:city":"Svendborg",
    "sg:orig_category":"Campingpladser",
    "sg:phone":"+45 62 20 52 54",
    "sg:postcode":"5700",
    "sg:province":"Danmark",
    "sg:website":"www.fdm.dk",
    "wof:name":"FDM's Campingplads",
    "wof:placetype":"venue"
},
  "geometry": {"coordinates":[10.6065101624,55.0595970154],"type":"Point"}
}