{
  "type": "Feature",
  "properties": {
    "addr:full":"Frankrigsgade 70, 2. K\u00f8benhavn S Danmark 2300",
    "addr:housenumber":"70 2",
    "addr:postcode":"2300",
    "addr:street":"Frankrigsgade;Kobenhavn S Danmark",
    "iso:country":"DK",
    "sg:address":"Frankrigsgade 70, 2.",
    "sg:city":"K\u00f8benhavn S",
    "sg:orig_category":"Psykoanalyse",
    "sg:phone":"+45 32 58 80 01",
    "sg:postcode":"2300",
    "sg:province":"Danmark",
    "wof:name":"Reymert, Carsten E.",
    "wof:placetype":"venue"
},
  "geometry": {"coordinates":[-82.5942764282,38.4557495117],"type":"Point"}
}