{
  "type": "Feature",
  "properties": {
    "iso:country":"DK",
    "sg:address":"Randersvej 4, Gammel Estrup",
    "sg:city":"Auning",
    "sg:orig_category":"Kulturelle organisationer og -foreninger",
    "sg:phone":"+45 86 48 30 01",
    "sg:postcode":"8963",
    "sg:province":"Danmark",
    "wof:name":"Landbohistorisk Selskab",
    "wof:placetype":"venue"
},
  "geometry": {"coordinates":[10.3770084381,56.430065155],"type":"Point"}
}