{
  "type": "Feature",
  "properties": {
    "addr:full":"\u00d8stre Kanalvej 10 Odense C Danmark 5000",
    "addr:housenumber":"10",
    "addr:postcode":"5000",
    "addr:street":"Ostre Kanalvej",
    "iso:country":"DK",
    "sg:address":"\u00d8stre Kanalvej 10",
    "sg:city":"Odense C",
    "sg:orig_category":"Havne",
    "sg:postcode":"5000",
    "sg:province":"Danmark",
    "wof:name":"Lystb\u00e5dehavnen Stige \u00d8",
    "wof:placetype":"venue"
},
  "geometry": {"coordinates":[10.4271812439,55.4514694214],"type":"Point"}
}