{
  "type": "Feature",
  "properties": {
    "iso:country":"DK",
    "sg:address":"Studevej 15, Stude",
    "sg:city":"Vemmelev",
    "sg:orig_category":"Trykluft",
    "sg:phone":"+45 58 38 40 35",
    "sg:postcode":"4241",
    "sg:province":"Danmark",
    "wof:name":"KL-Support",
    "wof:placetype":"venue"
},
  "geometry": {"coordinates":[11.2580623627,55.363407135],"type":"Point"}
}