{
  "type": "Feature",
  "properties": {
    "addr:full":"Randersvej 162 \u00c5rhus N Danmark 8200",
    "addr:housenumber":"162",
    "addr:postcode":"8200",
    "addr:street":"Randersvej",
    "iso:country":"DK",
    "sg:address":"Randersvej 162",
    "sg:city":"\u00c5rhus N",
    "sg:orig_category":"Autoreparation og -service",
    "sg:phone":"+45 86 16 55 16",
    "sg:postcode":"8200",
    "sg:province":"Danmark",
    "sg:website":"www.q8.dk",
    "wof:name":"Q8-Servicecenter",
    "wof:placetype":"venue"
},
  "geometry": {"coordinates":[4.9393601418,49.7092018127],"type":"Point"}
}