{
  "type": "Feature",
  "properties": {
    "addr:full":"Industrivej 30 Vamdrup Danmark 6580",
    "addr:housenumber":"30",
    "addr:postcode":"6580",
    "addr:street":"Industrivej",
    "iso:country":"DK",
    "sg:address":"Industrivej 30",
    "sg:city":"Vamdrup",
    "sg:orig_category":"Autoreparation og -service",
    "sg:phone":"+45 75 58 16 46",
    "sg:postcode":"6580",
    "sg:province":"Danmark",
    "wof:name":"Karsten Juul Automobiler A/S",
    "wof:placetype":"venue"
},
  "geometry": {"coordinates":[9.2986726761,55.4338493347],"type":"Point"}
}