{
  "type": "Feature",
  "properties": {
    "iso:country":"DK",
    "sg:address":"M\u00f8llehaven 15",
    "sg:city":"Jyllinge",
    "sg:orig_category":"Reklame",
    "sg:phone":"+45 46 78 99 01",
    "sg:postcode":"4040",
    "sg:province":"Danmark",
    "sg:website":"www.dsd-textiltryk.dk",
    "wof:name":"Dansk Serigrafi Design",
    "wof:placetype":"venue"
},
  "geometry": {"coordinates":[12.1298885345,55.7586021423],"type":"Point"}
}