{
  "type": "Feature",
  "properties": {
    "addr:full":"R\u00e5dhuset, Karlebo R\u00e5dhus, Egevangen 3 B Kokkedal Danmark 2980",
    "addr:housenumber":"3 b",
    "addr:postcode":"2980",
    "addr:street":"Egevangen",
    "iso:country":"DK",
    "sg:address":"R\u00e5dhuset, Karlebo R\u00e5dhus, Egevangen 3 B",
    "sg:city":"Kokkedal",
    "sg:orig_category":"Dagplejeformidling",
    "sg:phone":"+45 45 17 50 00",
    "sg:postcode":"2980",
    "sg:province":"Danmark",
    "wof:name":"Den Kommunale Dagpleje",
    "wof:placetype":"venue"
},
  "geometry": {"coordinates":[12.4769096375,55.9091339111],"type":"Point"}
}