{
  "type": "Feature",
  "properties": {
    "addr:full":"Torvet 9 Lemvig Danmark 7620",
    "addr:housenumber":"9",
    "addr:postcode":"7620",
    "addr:street":"Torvet",
    "iso:country":"DK",
    "sg:address":"Torvet 9",
    "sg:city":"Lemvig",
    "sg:orig_category":"Fotohandlere",
    "sg:phone":"+45 97 82 03 01",
    "sg:postcode":"7620",
    "sg:province":"Danmark",
    "wof:name":"LS Foto",
    "wof:placetype":"venue"
},
  "geometry": {"coordinates":[8.3073654175,56.5505104065],"type":"Point"}
}