{
  "type": "Feature",
  "properties": {
    "addr:full":"Paradis\u00e5sen 6, \u00d8ver\u00f8d Holte Danmark 2840",
    "addr:housenumber":"6",
    "addr:postcode":"2840",
    "addr:street":"Paradisaasen",
    "iso:country":"DK",
    "sg:address":"Paradis\u00e5sen 6, \u00d8ver\u00f8d",
    "sg:city":"Holte",
    "sg:orig_category":"Bogtrykkerier",
    "sg:phone":"+45 45 41 14 07",
    "sg:postcode":"2840",
    "sg:province":"Danmark",
    "wof:name":"Idon Tryk - Offset",
    "wof:placetype":"venue"
},
  "geometry": {"coordinates":[12.4706554413,55.8122367859],"type":"Point"}
}