{
  "type": "Feature",
  "properties": {
    "addr:full":"Wilders Plads 15 C K\u00f8benhavn Danmark 1403",
    "addr:housenumber":"15 c;1403",
    "addr:street":"Wilders Plads",
    "iso:country":"DK",
    "sg:address":"Wilders Plads 15 C",
    "sg:city":"K\u00f8benhavn",
    "sg:orig_category":"Reklamebureauer",
    "sg:phone":"+45 32 96 06 12",
    "sg:postcode":"1403",
    "sg:province":"Danmark",
    "wof:name":"Musikbranchens Reklamebureau",
    "wof:placetype":"venue"
},
  "geometry": {"coordinates":[12.5941696167,55.6755905151],"type":"Point"}
}