{
  "type": "Feature",
  "properties": {
    "iso:country":"DK",
    "sg:address":"\u00c5stvej 75, Lindeballe",
    "sg:city":"Gadbjerg",
    "sg:orig_category":"Kirker",
    "sg:postcode":"7321",
    "sg:province":"Danmark",
    "wof:name":"Lindeballe Kirke",
    "wof:placetype":"venue"
},
  "geometry": {"coordinates":[9.3234148026,55.7708015442],"type":"Point"}
}