{
  "type": "Feature",
  "properties": {
    "iso:country":"DK",
    "sg:address":"Glostrup Torv 6",
    "sg:city":"Glostrup",
    "sg:orig_category":"Dag- og distriktsblade",
    "sg:phone":"+45 43 96 00 31",
    "sg:postcode":"2600",
    "sg:province":"Danmark",
    "sg:website":"www.folkebladet.dk",
    "wof:name":"Folkebladet for Glostrup og Vestegnen A/S",
    "wof:placetype":"venue"
},
  "geometry": {"coordinates":[12.3974895477,55.6651268005],"type":"Point"}
}