{
  "type": "Feature",
  "properties": {
    "addr:full":"Cikorievej 5 Odense S\u00d8 Danmark 5220",
    "addr:housenumber":"5",
    "addr:postcode":"5220",
    "addr:street":"Cikorievej",
    "iso:country":"DK",
    "sg:address":"Cikorievej 5",
    "sg:city":"Odense S\u00d8",
    "sg:orig_category":"Murermestre",
    "sg:phone":"+45 66 12 08 10",
    "sg:postcode":"5220",
    "sg:province":"Danmark",
    "wof:name":"Hansson & Knudsen A/S",
    "wof:placetype":"venue"
},
  "geometry": {"coordinates":[10.4400568008,55.3932533264],"type":"Point"}
}