{
  "type": "Feature",
  "properties": {
    "addr:full":"Helgavej 23 Odense M Danmark 5230",
    "addr:housenumber":"23",
    "addr:postcode":"5230",
    "addr:street":"Helgavej",
    "iso:country":"DK",
    "sg:address":"Helgavej 23",
    "sg:city":"Odense M",
    "sg:orig_category":"Elektroindustri",
    "sg:phone":"+45 63 12 29 60",
    "sg:postcode":"5230",
    "sg:province":"Danmark",
    "wof:name":"HG-Elektronik",
    "wof:placetype":"venue"
},
  "geometry": {"coordinates":[10.3927106857,55.3850021362],"type":"Point"}
}