{
  "type": "Feature",
  "properties": {
    "addr:full":"R\u00f8dovre Parkvej 130 R\u00f8dovre Danmark 2610",
    "addr:housenumber":"130",
    "addr:postcode":"2610",
    "addr:street":"Parkvej",
    "iso:country":"DK",
    "sg:address":"R\u00f8dovre Parkvej 130",
    "sg:city":"R\u00f8dovre",
    "sg:orig_category":"Lokalradio",
    "sg:phone":"+45 36 70 66 00",
    "sg:postcode":"2610",
    "sg:province":"Danmark",
    "wof:name":"Radio R\u00f8dovre",
    "wof:placetype":"venue"
},
  "geometry": {"coordinates":[10.6992139816,61.1027755737],"type":"Point"}
}