{
  "type": "Feature",
  "properties": {
    "addr:full":"Kirketorvet 9 Vordingborg Danmark 4760",
    "addr:housenumber":"9",
    "addr:postcode":"4760",
    "addr:street":"Kirketorvet",
    "iso:country":"DK",
    "sg:address":"Kirketorvet 9",
    "sg:city":"Vordingborg",
    "sg:orig_category":"Faglige organisationer og foreninger",
    "sg:phone":"+45 55 37 47 22",
    "sg:postcode":"4760",
    "sg:province":"Danmark",
    "sg:website":"www.lo-storstroem.dk",
    "wof:name":"LO Storstr\u00f8ms Amt",
    "wof:placetype":"venue"
},
  "geometry": {"coordinates":[11.9070663452,55.0089569092],"type":"Point"}
}