{
  "type": "Feature",
  "properties": {
    "addr:full":"v/ Niels Buhl, Holgersdalvej 3, As Juelsminde Danmark 7130",
    "addr:housenumber":"3",
    "addr:postcode":"7130",
    "addr:street":"Holgersdalvej",
    "iso:country":"DK",
    "sg:address":"v/ Niels Buhl, Holgersdalvej 3, As",
    "sg:city":"Juelsminde",
    "sg:orig_category":"Borger- og beboerforeninger",
    "sg:phone":"+45 75 69 04 17",
    "sg:postcode":"7130",
    "sg:province":"Danmark",
    "wof:name":"As Sogns Beboerforening",
    "wof:placetype":"venue"
},
  "geometry": {"coordinates":[10.0143985748,55.7135848999],"type":"Point"}
}