{
  "type": "Feature",
  "properties": {
    "addr:full":"Vestergade 8 R\u00f8dby Danmark 4970",
    "addr:housenumber":"8",
    "addr:postcode":"4970",
    "addr:street":"Vestergade",
    "iso:country":"DK",
    "sg:address":"Vestergade 8",
    "sg:city":"R\u00f8dby",
    "sg:orig_category":"Handicapboliger",
    "sg:phone":"+45 54 60 18 50",
    "sg:postcode":"4970",
    "sg:province":"Danmark",
    "wof:name":"Skomager Hus V\u00e6rested",
    "wof:placetype":"venue"
},
  "geometry": {"coordinates":[9.5455904007,56.1682090759],"type":"Point"}
}