{
  "type": "Feature",
  "properties": {
    "addr:full":"N\u00f8rregade 17 Agerskov Danmark 6534",
    "addr:housenumber":"17",
    "addr:postcode":"6534",
    "addr:street":"Norregade",
    "iso:country":"DK",
    "sg:address":"N\u00f8rregade 17",
    "sg:city":"Agerskov",
    "sg:orig_category":"Tandklinikker, Kommunale",
    "sg:phone":"+45 73 21 24 48",
    "sg:postcode":"6534",
    "sg:province":"Danmark",
    "wof:name":"Skoletandklinikken",
    "wof:placetype":"venue"
},
  "geometry": {"coordinates":[9.1322822571,55.1311073303],"type":"Point"}
}