{
  "type": "Feature",
  "properties": {
    "addr:full":"Stationen 1 A Svinninge Danmark 4520",
    "addr:housenumber":"1 a",
    "addr:postcode":"4520",
    "addr:street":"Stationen",
    "iso:country":"DK",
    "sg:address":"Stationen 1 A",
    "sg:city":"Svinninge",
    "sg:orig_category":"Posthuse",
    "sg:phone":"+45 59 26 50 18",
    "sg:postcode":"4520",
    "sg:province":"Danmark",
    "wof:name":"Post Danmark, Svinninge distributionscenter",
    "wof:placetype":"venue"
},
  "geometry": {"coordinates":[11.4668264389,55.723072052],"type":"Point"}
}