{
  "type": "Feature",
  "properties": {
    "iso:country":"DK",
    "sg:address":"Gr\u00f8nnemosen 9, Postboks 166",
    "sg:city":"S\u00f8borg",
    "sg:orig_category":"Asfalt",
    "sg:phone":"+45 39 69 79 13",
    "sg:postcode":"2860",
    "sg:province":"Danmark",
    "sg:website":"www.nyfalt.dk",
    "wof:name":"NYFALT A/S",
    "wof:placetype":"venue"
},
  "geometry": {"coordinates":[-101.39041900629999,35.6679611206],"type":"Point"}
}