{
  "type": "Feature",
  "properties": {
    "addr:full":"Vilhelmsborgvej 161, Flynder Lemvig Danmark 7620",
    "addr:housenumber":"161",
    "addr:postcode":"7620",
    "addr:street":"Vilhelmsborgvej",
    "iso:country":"DK",
    "sg:address":"Vilhelmsborgvej 161, Flynder",
    "sg:city":"Lemvig",
    "sg:orig_category":"Murermestre",
    "sg:phone":"+45 97 88 98 85",
    "sg:postcode":"7620",
    "sg:province":"Danmark",
    "wof:name":"Kvisgaard, Svend Erland",
    "wof:placetype":"venue"
},
  "geometry": {"coordinates":[8.3073654175,56.5505104065],"type":"Point"}
}