{
  "type": "Feature",
  "properties": {
    "addr:full":"Thorstedvej 152 Thisted Danmark 7700",
    "addr:housenumber":"152",
    "addr:postcode":"7700",
    "addr:street":"Thorstedvej",
    "iso:country":"DK",
    "sg:address":"Thorstedvej 152",
    "sg:city":"Thisted",
    "sg:orig_category":"Private- og friskoler",
    "sg:phone":"+45 97 97 13 05",
    "sg:postcode":"7700",
    "sg:province":"Danmark",
    "wof:name":"Thorsted Friskole",
    "wof:placetype":"venue"
},
  "geometry": {"coordinates":[8.6238517761,56.9693717957],"type":"Point"}
}