{
  "type": "Feature",
  "properties": {
    "addr:full":"Falkoner Alle 58 Frederiksberg Danmark 2000",
    "addr:housenumber":"58",
    "addr:postcode":"2000",
    "addr:street":"Falkoner Alle",
    "iso:country":"DK",
    "sg:address":"Falkoner Alle 58",
    "sg:city":"Frederiksberg",
    "sg:orig_category":"Farve og tapet",
    "sg:phone":"+45 35 35 63 74",
    "sg:postcode":"2000",
    "sg:province":"Danmark",
    "wof:name":"Sies Farve & Tapetmagasin",
    "wof:placetype":"venue"
},
  "geometry": {"coordinates":[12.5371675491,55.6837806702],"type":"Point"}
}