{
  "type": "Feature",
  "properties": {
    "addr:full":"Vesterbro 61 A Aalborg Danmark 9000",
    "addr:housenumber":"61 a",
    "addr:postcode":"9000",
    "addr:street":"Vesterbro",
    "iso:country":"DK",
    "sg:address":"Vesterbro 61 A",
    "sg:city":"Aalborg",
    "sg:orig_category":"Begravelsesforretninger",
    "sg:phone":"+45 98 38 13 22",
    "sg:postcode":"9000",
    "sg:province":"Danmark",
    "wof:name":"Svenstrup og Omegns Begravelsesforretning",
    "wof:placetype":"venue"
},
  "geometry": {"coordinates":[9.91458,57.047291],"type":"Point"}
}