{
  "type": "Feature",
  "properties": {
    "addr:full":"Klarup Skolevej 21 Klarup Danmark 9270",
    "addr:housenumber":"21",
    "addr:postcode":"9270",
    "addr:street":"Klarup Skolevej",
    "iso:country":"DK",
    "sg:address":"Klarup Skolevej 21",
    "sg:city":"Klarup",
    "sg:orig_category":"Lokalarkiver",
    "sg:phone":"+45 98 32 62 08",
    "sg:postcode":"9270",
    "sg:province":"Danmark",
    "wof:name":"Lokalhistorisk Arkiv For Romdrup-Klarup",
    "wof:placetype":"venue"
},
  "geometry": {"coordinates":[10.0489301682,57.0084152222],"type":"Point"}
}