{
  "type": "Feature",
  "properties": {
    "addr:full":"Roseng\u00e5rds Alle 104 A Vejle Danmark 7100",
    "addr:housenumber":"104 a",
    "addr:postcode":"7100",
    "addr:street":"Rosengaards Alle",
    "iso:country":"DK",
    "sg:address":"Roseng\u00e5rds Alle 104 A",
    "sg:city":"Vejle",
    "sg:orig_category":"Integrerede institutioner",
    "sg:phone":"+45 75 72 20 22",
    "sg:postcode":"7100",
    "sg:province":"Danmark",
    "wof:name":"Asebo",
    "wof:placetype":"venue"
},
  "geometry": {"coordinates":[9.5497722626,55.6825256348],"type":"Point"}
}