{
  "type": "Feature",
  "properties": {
    "addr:full":"Rugtoften 13, Skodborg R\u00f8dding Danmark 6630",
    "addr:housenumber":"13",
    "addr:postcode":"6630",
    "addr:street":"Rugtoften",
    "iso:country":"DK",
    "sg:address":"Rugtoften 13, Skodborg",
    "sg:city":"R\u00f8dding",
    "sg:orig_category":"Blomsterhandlere",
    "sg:phone":"+45 74 84 88 98",
    "sg:postcode":"6630",
    "sg:province":"Danmark",
    "wof:name":"Blomsterv\u00e6rkstedet",
    "wof:placetype":"venue"
},
  "geometry": {"coordinates":[9.2022953033,55.3564414978],"type":"Point"}
}