{
  "type": "Feature",
  "properties": {
    "iso:country":"DK",
    "sg:address":"Tingstedet 27",
    "sg:city":"Billund",
    "sg:orig_category":"Skilte",
    "sg:phone":"+45 75 33 28 22",
    "sg:postcode":"7190",
    "sg:province":"Danmark",
    "sg:website":"www.lani.dk",
    "wof:name":"Lani Design",
    "wof:placetype":"venue"
},
  "geometry": {"coordinates":[9.1109323502,55.7141799927],"type":"Point"}
}