{
  "type": "Feature",
  "properties": {
    "addr:full":"N\u00f8rregade 17 Nyborg Danmark 5800",
    "addr:housenumber":"17",
    "addr:postcode":"5800",
    "addr:street":"Norregade",
    "iso:country":"DK",
    "sg:address":"N\u00f8rregade 17",
    "sg:city":"Nyborg",
    "sg:orig_category":"Blomsterhandlere",
    "sg:phone":"+45 65 30 19 66",
    "sg:postcode":"5800",
    "sg:province":"Danmark",
    "wof:name":"Blomsterv\u00e6rkstedet Tine P.",
    "wof:placetype":"venue"
},
  "geometry": {"coordinates":[10.7927036285,55.3123893738],"type":"Point"}
}