{
  "type": "Feature",
  "properties": {
    "addr:full":"Halsvej 290 Vodskov Danmark 9310",
    "addr:housenumber":"290",
    "addr:postcode":"9310",
    "addr:street":"Halsvej",
    "iso:country":"DK",
    "sg:address":"Halsvej 290",
    "sg:city":"Vodskov",
    "sg:orig_category":"Forsikringer",
    "sg:phone":"+45 98 25 55 66",
    "sg:postcode":"9310",
    "sg:province":"Danmark",
    "wof:name":"Kaj Frilev",
    "wof:placetype":"venue"
},
  "geometry": {"coordinates":[10.1361207962,57.0639266968],"type":"Point"}
}