{
  "type": "Feature",
  "properties": {
    "iso:country":"DK",
    "sg:address":"Fmd.: Leif Johannessen, M\u00f8llevej 7",
    "sg:city":"Knebel",
    "sg:orig_category":"Borger- og beboerforeninger",
    "sg:phone":"+45 86 35 22 26",
    "sg:postcode":"8420",
    "sg:province":"Danmark",
    "wof:name":"Borgerforeningen Mols",
    "wof:placetype":"venue"
},
  "geometry": {"coordinates":[10.3770122528,56.1816596985],"type":"Point"}
}