{
  "type": "Feature",
  "properties": {
    "addr:full":"J. Petersens Vej 9 Nibe Danmark 9240",
    "addr:housenumber":"9",
    "addr:postcode":"9240",
    "addr:street":"J. Petersens Vej",
    "iso:country":"DK",
    "sg:address":"J. Petersens Vej 9",
    "sg:city":"Nibe",
    "sg:orig_category":"Fabrikker",
    "sg:phone":"+45 98 35 15 00",
    "sg:postcode":"9240",
    "sg:province":"Danmark",
    "wof:name":"Petersens Beslagfabrik Nibe, A/S J.",
    "wof:placetype":"venue"
},
  "geometry": {"coordinates":[9.647482872,56.9882049561],"type":"Point"}
}