{
  "type": "Feature",
  "properties": {
    "addr:full":"L\u00f8vevej 32 Bryrup Danmark 8654",
    "addr:housenumber":"32",
    "addr:postcode":"8654",
    "addr:street":"Lovevej",
    "iso:country":"DK",
    "sg:address":"L\u00f8vevej 32",
    "sg:city":"Bryrup",
    "sg:orig_category":"Autoreparation og -service",
    "sg:phone":"+45 75 75 79 25",
    "sg:postcode":"8654",
    "sg:province":"Danmark",
    "wof:name":"Larsen, Bent Skov",
    "wof:placetype":"venue"
},
  "geometry": {"coordinates":[9.4738540649,56.0185241699],"type":"Point"}
}