{
  "type": "Feature",
  "properties": {
    "addr:full":"Binderupvej 4, Binderup Nibe Danmark 9240",
    "addr:housenumber":"4",
    "addr:postcode":"9240",
    "addr:street":"Binderupvej;Binderup",
    "iso:country":"DK",
    "sg:address":"Binderupvej 4, Binderup",
    "sg:city":"Nibe",
    "sg:orig_category":"Murermestre",
    "sg:phone":"+45 98 35 15 88",
    "sg:postcode":"9240",
    "sg:province":"Danmark",
    "wof:name":"Strauss, Jens Richard",
    "wof:placetype":"venue"
},
  "geometry": {"coordinates":[9.6393280029,56.982421875],"type":"Point"}
}