{
  "type": "Feature",
  "properties": {
    "addr:full":"S\u00f8nderskovvej 234, G\u00e5ser Gandrup Danmark 9362",
    "addr:housenumber":"234",
    "addr:postcode":"9362",
    "addr:street":"Sonderskovvej;Gaaser",
    "iso:country":"DK",
    "sg:address":"S\u00f8nderskovvej 234, G\u00e5ser",
    "sg:city":"Gandrup",
    "sg:orig_category":"Kirker",
    "sg:postcode":"9362",
    "sg:province":"Danmark",
    "wof:name":"G\u00e5ser Kirke",
    "wof:placetype":"venue"
},
  "geometry": {"coordinates":[10.1787033081,57.0536804199],"type":"Point"}
}