{
  "type": "Feature",
  "properties": {
    "addr:full":"Guden\u00e5vej 20 Esbjerg V Danmark 6710",
    "addr:housenumber":"20",
    "addr:postcode":"6710",
    "addr:street":"Gudenaavej",
    "iso:country":"DK",
    "sg:address":"Guden\u00e5vej 20",
    "sg:city":"Esbjerg V",
    "sg:orig_category":"Campingpladser",
    "sg:phone":"+45 75 15 88 22",
    "sg:postcode":"6710",
    "sg:province":"Danmark",
    "sg:website":"home5.inet.tele.dk/adalcamp/",
    "wof:name":"\u00c5dalens Camping",
    "wof:placetype":"venue"
},
  "geometry": {"coordinates":[8.3863229752,55.5063285828],"type":"Point"}
}