{
  "type": "Feature",
  "properties": {
    "iso:country":"DK",
    "sg:address":"Carl Baggers All\u00e9 26",
    "sg:city":"Charlottenlund",
    "sg:orig_category":"INGENI\u00c3\u02dcRER",
    "sg:phone":"+45 39 63 10 66",
    "sg:postcode":"2920",
    "sg:province":"Danmark",
    "wof:name":"Klinkby, P.H.",
    "wof:placetype":"venue"
},
  "geometry": {"coordinates":[12.5648975372,55.7512054443],"type":"Point"}
}