{
  "type": "Feature",
  "properties": {
    "iso:country":"DK",
    "sg:address":"Klaus Berntsens Vej 155, H\u00f8jby",
    "sg:city":"Odense S",
    "sg:classifiers":[
        {
            "category":"Professional",
            "subcategory":"Computer Services",
            "type":"Services"
        }
    ],
    "sg:phone":"+45 65 95 86 72",
    "sg:postcode":"5260",
    "sg:province":"Danmark",
    "sg:tags":[
        "edb",
        "-",
        "software"
    ],
    "wof:name":"Fyns Teleteknik",
    "wof:placetype":"venue"
},
  "geometry": {"coordinates":[10.3157806396,55.3122825623],"type":"Point"}
}