{
  "type": "Feature",
  "properties": {
    "iso:country":"DK",
    "sg:address":"Vester Alle 11, Hammerum",
    "sg:city":"Herning",
    "sg:orig_category":"Teatre",
    "sg:phone":"+45 97 11 81 91",
    "sg:postcode":"7400",
    "sg:province":"Danmark",
    "wof:name":"Teatertruppen Replikken",
    "wof:placetype":"venue"
},
  "geometry": {"coordinates":[8.9768896103,56.1374168396],"type":"Point"}
}