{
  "type": "Feature",
  "properties": {
    "addr:full":"Stadagervej 64 Herlev Danmark 2730",
    "addr:housenumber":"64",
    "addr:postcode":"2730",
    "addr:street":"Stadagervej",
    "iso:country":"DK",
    "sg:address":"Stadagervej 64",
    "sg:city":"Herlev",
    "sg:orig_category":"Fabrikker",
    "sg:phone":"+45 44 85 20 01",
    "sg:postcode":"2730",
    "sg:province":"Danmark",
    "wof:name":"Jensen, Ole",
    "wof:placetype":"venue"
},
  "geometry": {"coordinates":[12.4233045578,55.7501029968],"type":"Point"}
}