{
  "type": "Feature",
  "properties": {
    "addr:full":"Indre Ringvej 2 Viborg Danmark 8800",
    "addr:housenumber":"2",
    "addr:postcode":"8800",
    "addr:street":"Indre Ringvej",
    "iso:country":"DK",
    "sg:address":"Indre Ringvej 2",
    "sg:city":"Viborg",
    "sg:orig_category":"Servicestationer",
    "sg:phone":"+45 86 62 16 16",
    "sg:postcode":"8800",
    "sg:province":"Danmark",
    "wof:name":"Statoil Servicenter",
    "wof:placetype":"venue"
},
  "geometry": {"coordinates":[9.4368953705,56.3980751038],"type":"Point"}
}