{
  "type": "Feature",
  "properties": {
    "addr:full":"Fredensgade 12 A Hinnerup Danmark 8382",
    "addr:housenumber":"12 a",
    "addr:postcode":"8382",
    "addr:street":"Fredensgade",
    "iso:country":"DK",
    "sg:address":"Fredensgade 12 A",
    "sg:city":"Hinnerup",
    "sg:orig_category":"Taksatorer",
    "sg:phone":"+45 86 91 14 00",
    "sg:postcode":"8382",
    "sg:province":"Danmark",
    "sg:website":"www.oktaksation.dk",
    "wof:name":"OK Taksation & Vurdering",
    "wof:placetype":"venue"
},
  "geometry": {"coordinates":[10.0645666122,56.2645492554],"type":"Point"}
}