{
  "type": "Feature",
  "properties": {
    "addr:full":"Bredgade 64 N\u00f8rre Nebel Danmark 6830",
    "addr:housenumber":"64",
    "addr:postcode":"6830",
    "addr:street":"Bredgade",
    "iso:country":"DK",
    "sg:address":"Bredgade 64",
    "sg:city":"N\u00f8rre Nebel",
    "sg:orig_category":"Antikviteter",
    "sg:phone":"+45 75 28 81 38",
    "sg:postcode":"6830",
    "sg:province":"Danmark",
    "wof:name":"Farmors Tid, Fra",
    "wof:placetype":"venue"
},
  "geometry": {"coordinates":[8.294131279,55.7783050537],"type":"Point"}
}