{
  "type": "Feature",
  "properties": {
    "iso:country":"DK",
    "sg:address":"Fredrik Bajers Gade 16",
    "sg:city":"Horsens",
    "sg:orig_category":"Boligselskaber",
    "sg:phone":"+45 75 61 10 66",
    "sg:postcode":"8700",
    "sg:province":"Danmark",
    "wof:name":"\u00d8stjysk Boligselskab af 1976",
    "wof:placetype":"venue"
},
  "geometry": {"coordinates":[9.837389946,55.8584365845],"type":"Point"}
}