{
  "type": "Feature",
  "properties": {
    "addr:full":"Ansvej 114 Silkeborg Danmark 8600",
    "addr:housenumber":"114",
    "addr:postcode":"8600",
    "addr:street":"Ansvej",
    "iso:country":"DK",
    "sg:address":"Ansvej 114",
    "sg:city":"Silkeborg",
    "sg:orig_category":"Cafeterier",
    "sg:phone":"+45 86 82 48 07",
    "sg:postcode":"8600",
    "sg:province":"Danmark",
    "wof:name":"Silkeborg Hallernes Cafeteria",
    "wof:placetype":"venue"
},
  "geometry": {"coordinates":[9.5726699829,56.1834907532],"type":"Point"}
}