{
  "type": "Feature",
  "properties": {
    "addr:full":"Kontaktprs.: Ingrid H\u00f8y Hansen, Diget 8 Sor\u00f8 Danmark 4180",
    "addr:housenumber":"8",
    "addr:postcode":"4180",
    "addr:street":"Diget",
    "iso:country":"DK",
    "sg:address":"Kontaktprs.: Ingrid H\u00f8y Hansen, Diget 8",
    "sg:city":"Sor\u00f8",
    "sg:orig_category":"Musik og sang",
    "sg:phone":"+45 57 83 11 44",
    "sg:postcode":"4180",
    "sg:province":"Danmark",
    "wof:name":"Pro Cantu",
    "wof:placetype":"venue"
},
  "geometry": {"coordinates":[11.556344986,55.432800293],"type":"Point"}
}