{
  "type": "Feature",
  "properties": {
    "addr:full":"Sognepr\u00e6st: Knud Ove Mandrup (K/B), Gr\u00f8nb\u00e6k pr\u00e6steg\u00e5rd, Pr\u00e6stevangen 39, Gr\u00f8nb\u00e6k Ans Danmark 8643",
    "addr:housenumber":"39",
    "addr:postcode":"8643",
    "addr:street":"Knud Ove;Praestevangen",
    "iso:country":"DK",
    "sg:address":"Sognepr\u00e6st: Knud Ove Mandrup (K/B), Gr\u00f8nb\u00e6k pr\u00e6steg\u00e5rd, Pr\u00e6stevangen 39, Gr\u00f8nb\u00e6k",
    "sg:city":"Ans",
    "sg:orig_category":"Kirkesogne",
    "sg:phone":"+45 86 87 01 05",
    "sg:postcode":"8643",
    "sg:province":"Danmark",
    "wof:name":"Gr\u00f8nb\u00e6k Sogn",
    "wof:placetype":"venue"
},
  "geometry": {"coordinates":[9.5927238464,56.3078765869],"type":"Point"}
}