{
  "type": "Feature",
  "properties": {
    "iso:country":"DK",
    "sg:address":"M\u00f8llevej 15",
    "sg:city":"Borup",
    "sg:orig_category":"Landboorganisationer",
    "sg:phone":"+45 57 56 17 00",
    "sg:postcode":"4140",
    "sg:province":"Danmark",
    "wof:name":"Landbo Centrum",
    "wof:placetype":"venue"
},
  "geometry": {"coordinates":[11.9860429764,55.4994354248],"type":"Point"}
}