{
  "type": "Feature",
  "properties": {
    "addr:full":"Kobbervej 8 Herlev Danmark 2730",
    "addr:housenumber":"8",
    "addr:postcode":"2730",
    "addr:street":"Kobbervej",
    "iso:country":"DK",
    "sg:address":"Kobbervej 8",
    "sg:city":"Herlev",
    "sg:orig_category":"Ejendomshandel",
    "sg:phone":"+45 44 57 03 30",
    "sg:postcode":"2730",
    "sg:province":"Danmark",
    "wof:name":"Bech, Poul Erik",
    "wof:placetype":"venue"
},
  "geometry": {"coordinates":[12.4411420822,55.7251205444],"type":"Point"}
}