{
  "type": "Feature",
  "properties": {
    "addr:full":"Vantorevej 105 B Nysted Danmark 4880",
    "addr:housenumber":"105 b",
    "addr:postcode":"4880",
    "addr:street":"Vantorevej",
    "iso:country":"DK",
    "sg:address":"Vantorevej 105 B",
    "sg:city":"Nysted",
    "sg:orig_category":"Kirker",
    "sg:postcode":"4880",
    "sg:province":"Danmark",
    "wof:name":"Vantore Kirke",
    "wof:placetype":"venue"
},
  "geometry": {"coordinates":[11.7945861816,54.6612854004],"type":"Point"}
}