{
  "type": "Feature",
  "properties": {
    "addr:full":"Aalborgvej 251 Aabybro Danmark 9440",
    "addr:housenumber":"251",
    "addr:postcode":"9440",
    "addr:street":"Aalborgvej",
    "iso:country":"DK",
    "sg:address":"Aalborgvej 251",
    "sg:city":"Aabybro",
    "sg:orig_category":"Autoforhandlere",
    "sg:phone":"+45 98 26 96 02",
    "sg:postcode":"9440",
    "sg:province":"Danmark",
    "wof:name":"\u00c5lborgvejens Autohandel",
    "wof:placetype":"venue"
},
  "geometry": {"coordinates":[9.7928619385,57.1290245056],"type":"Point"}
}