{
  "type": "Feature",
  "properties": {
    "addr:full":"S\u00e6dding Ringvej 3 Esbjerg V Danmark 6710",
    "addr:housenumber":"3",
    "addr:postcode":"6710",
    "addr:street":"Saedding Ringvej",
    "iso:country":"DK",
    "sg:address":"S\u00e6dding Ringvej 3",
    "sg:city":"Esbjerg V",
    "sg:orig_category":"Campingvogne",
    "sg:phone":"+45 75 15 99 66",
    "sg:postcode":"6710",
    "sg:province":"Danmark",
    "wof:name":"Camping & fritid",
    "wof:placetype":"venue"
},
  "geometry": {"coordinates":[8.406750679,55.5032234192],"type":"Point"}
}