{
  "type": "Feature",
  "properties": {
    "addr:full":"R\u00e5dhusvej 4 Fakse Danmark 4640",
    "addr:housenumber":"4",
    "addr:postcode":"4640",
    "addr:street":"Raadhusvej",
    "iso:country":"DK",
    "sg:address":"R\u00e5dhusvej 4",
    "sg:city":"Fakse",
    "sg:orig_category":"Lokalarkiver",
    "sg:phone":"+45 56 71 40 72",
    "sg:postcode":"4640",
    "sg:province":"Danmark",
    "wof:name":"Faxe-R\u00f8nnede Lokalhistoriske Arkiv",
    "wof:placetype":"venue"
},
  "geometry": {"coordinates":[12.1205911636,55.250453949],"type":"Point"}
}