{
  "type": "Feature",
  "properties": {
    "iso:country":"DK",
    "sg:address":"Palle Fl\u00f8es Vej 11, Hammerum",
    "sg:city":"Herning",
    "sg:orig_category":"Kunstmalere",
    "sg:phone":"+45 97 11 80 98",
    "sg:postcode":"7400",
    "sg:province":"Danmark",
    "wof:name":"Nyholm, Leif",
    "wof:placetype":"venue"
},
  "geometry": {"coordinates":[8.9768896103,56.1374168396],"type":"Point"}
}