{
  "type": "Feature",
  "properties": {
    "addr:full":"Jyllandsgade 41 Esbjerg Danmark 6700",
    "addr:housenumber":"41",
    "addr:postcode":"6700",
    "addr:street":"Jyllandsgade",
    "iso:country":"DK",
    "sg:address":"Jyllandsgade 41",
    "sg:city":"Esbjerg",
    "sg:classifiers":[
        {
            "category":"Restaurant",
            "type":"Food & Drink"
        }
    ],
    "sg:phone":"+45 75 13 89 45",
    "sg:postcode":"6700",
    "sg:province":"Danmark",
    "wof:name":"Troubaduren Restaurant og Bodega",
    "wof:placetype":"venue"
},
  "geometry": {"coordinates":[8.4477643967,55.4680404663],"type":"Point"}
}