{
  "type": "Feature",
  "properties": {
    "addr:full":"Hjertingvej 21-23 Esbjerg Danmark 6700",
    "addr:postcode":"21-23;6700",
    "addr:street":"Hjertingvej",
    "iso:country":"DK",
    "sg:address":"Hjertingvej 21-23",
    "sg:city":"Esbjerg",
    "sg:orig_category":"Symaskiner",
    "sg:phone":"+45 75 13 75 39",
    "sg:postcode":"6700",
    "sg:province":"Danmark",
    "wof:name":"Dethe Stoffer",
    "wof:placetype":"venue"
},
  "geometry": {"coordinates":[8.4293193817,55.4796485901],"type":"Point"}
}