{
  "type": "Feature",
  "properties": {
    "addr:full":"Skovshovedvej 4. kld. th. Charlottenlund Danmark 2920",
    "addr:housenumber":"4 kld. th.",
    "addr:postcode":"2920",
    "addr:street":"Skovshovedvej",
    "iso:country":"DK",
    "sg:address":"Skovshovedvej 4. kld. th.",
    "sg:city":"Charlottenlund",
    "sg:orig_category":"Arkitekter",
    "sg:phone":"+45 39 63 49 59",
    "sg:postcode":"2920",
    "sg:province":"Danmark",
    "wof:name":"J. D. A. Design",
    "wof:placetype":"venue"
},
  "geometry": {"coordinates":[12.5721197128,55.7532615662],"type":"Point"}
}