{
  "type": "Feature",
  "properties": {
    "addr:full":"K\u00f8bmagergade 3B K\u00f8benhavn Danmark 1150",
    "addr:housenumber":"3b",
    "addr:postcode":"1150",
    "addr:street":"Kobmagergade",
    "iso:country":"DK",
    "sg:address":"K\u00f8bmagergade 3B",
    "sg:city":"K\u00f8benhavn",
    "sg:classifiers":[
        {
            "category":"Professional",
            "subcategory":"Advertising",
            "type":"Services"
        }
    ],
    "sg:phone":"+45 33 32 48 32",
    "sg:postcode":"1150",
    "sg:province":"Danmark",
    "sg:tags":[
        "marketing"
    ],
    "wof:name":"Markeds R\u00e5dgivning, Luna",
    "wof:placetype":"venue"
},
  "geometry": {"coordinates":[76.3070983887,14.277130127],"type":"Point"}
}