{
  "type": "Feature",
  "properties": {
    "addr:full":"v/ Merko, S\u00f8ndervang 1 Balle Danmark 8444",
    "addr:housenumber":"1",
    "addr:postcode":"8444",
    "addr:street":"Sondervang",
    "iso:country":"DK",
    "sg:address":"v/ Merko, S\u00f8ndervang 1",
    "sg:city":"Balle",
    "sg:orig_category":"Apoteker og -udsalg",
    "sg:phone":"+45 86 33 70 09",
    "sg:postcode":"8444",
    "sg:province":"Danmark",
    "wof:name":"H\u00e5ndk\u00f8bsudsalget",
    "wof:placetype":"venue"
},
  "geometry": {"coordinates":[10.8090896606,56.31640625],"type":"Point"}
}