{
  "type": "Feature",
  "properties": {
    "addr:full":"\u00d8dis Byvej 1 Vamdrup Danmark 6580",
    "addr:housenumber":"1",
    "addr:postcode":"6580",
    "addr:street":"Odis Byvej",
    "iso:country":"DK",
    "sg:address":"\u00d8dis Byvej 1",
    "sg:city":"Vamdrup",
    "sg:orig_category":"Kirker",
    "sg:postcode":"6580",
    "sg:province":"Danmark",
    "wof:name":"\u00d8dis Kirke",
    "wof:placetype":"venue"
},
  "geometry": {"coordinates":[9.2839107513,55.4266548157],"type":"Point"}
}