{
  "type": "Feature",
  "properties": {
    "iso:country":"DK",
    "sg:address":"Sundbyvej 106, Sundby",
    "sg:city":"Erslev",
    "sg:orig_category":"Zoneterapeuter",
    "sg:phone":"+45 97 74 63 28",
    "sg:postcode":"7950",
    "sg:province":"Danmark",
    "wof:name":"Gr\u00f8n, Gunver",
    "wof:placetype":"venue"
},
  "geometry": {"coordinates":[8.7200698853,56.8354682922],"type":"Point"}
}