{
  "type": "Feature",
  "properties": {
    "addr:full":"K\u00e6rvej 309 Billund Danmark 7190",
    "addr:housenumber":"309",
    "addr:postcode":"7190",
    "addr:street":"Kaervej",
    "iso:country":"DK",
    "sg:address":"K\u00e6rvej 309",
    "sg:city":"Billund",
    "sg:orig_category":"Elektronik",
    "sg:phone":"+45 75 33 17 42",
    "sg:postcode":"7190",
    "sg:province":"Danmark",
    "sg:website":"www.era-elec.dk",
    "wof:name":"Era Electronics",
    "wof:placetype":"venue"
},
  "geometry": {"coordinates":[9.1085338593,55.7241401672],"type":"Point"}
}