{
  "type": "Feature",
  "properties": {
    "addr:full":"Trong\u00e5rdsparken 36 Kongens Lyngby Danmark 2800",
    "addr:housenumber":"36",
    "addr:postcode":"2800",
    "addr:street":"Trongaardsparken",
    "iso:country":"DK",
    "sg:address":"Trong\u00e5rdsparken 36",
    "sg:city":"Kongens Lyngby",
    "sg:classifiers":[
        {
            "category":"Professional",
            "subcategory":"Computer Services",
            "type":"Services"
        }
    ],
    "sg:phone":"+45 45 93 00 28",
    "sg:postcode":"2800",
    "sg:province":"Danmark",
    "sg:tags":[
        "edb",
        "-",
        "software"
    ],
    "sg:website":"www.f-data.dk",
    "wof:name":"F-Data",
    "wof:placetype":"venue"
},
  "geometry": {"coordinates":[12.5328531265,55.775352478],"type":"Point"}
}