{
  "type": "Feature",
  "properties": {
    "iso:country":"DK",
    "sg:address":"Jernbanegade 1 G",
    "sg:city":"Kolding",
    "sg:orig_category":"Advokater",
    "sg:phone":"+45 75 54 24 55",
    "sg:postcode":"6000",
    "sg:province":"Danmark",
    "wof:name":"Knudsen, Jan Kj\u00e6r",
    "wof:placetype":"venue"
},
  "geometry": {"coordinates":[9.4733953476,55.4863586426],"type":"Point"}
}