{
  "type": "Feature",
  "properties": {
    "addr:full":"Lundeparken 1, 1. tv. Frederikssund Danmark 3600",
    "addr:housenumber":"1 1 tv.",
    "addr:postcode":"3600",
    "addr:street":"Lundeparken",
    "iso:country":"DK",
    "sg:address":"Lundeparken 1, 1. tv.",
    "sg:city":"Frederikssund",
    "sg:orig_category":"Konsulentvirksomheder",
    "sg:phone":"+45 21 94 16 11",
    "sg:postcode":"3600",
    "sg:province":"Danmark",
    "wof:name":"ADT Consulting",
    "wof:placetype":"venue"
},
  "geometry": {"coordinates":[12.0661621094,55.8370323181],"type":"Point"}
}