{
  "type": "Feature",
  "properties": {
    "addr:full":"Sverrigsvej 2 Skive Danmark 7800",
    "addr:housenumber":"2",
    "addr:postcode":"7800",
    "addr:street":"Sverrigsvej",
    "iso:country":"DK",
    "sg:address":"Sverrigsvej 2",
    "sg:city":"Skive",
    "sg:orig_category":"Lastvogne",
    "sg:phone":"+45 70 10 11 66",
    "sg:postcode":"7800",
    "sg:province":"Danmark",
    "wof:name":"Viking Lastbil A/S",
    "wof:placetype":"venue"
},
  "geometry": {"coordinates":[9.0413970947,56.5633468628],"type":"Point"}
}