{
  "type": "Feature",
  "properties": {
    "iso:country":"DK",
    "sg:address":"Fortunfortvej 3 B",
    "sg:city":"Kongens Lyngby",
    "sg:orig_category":"Hobbybetonede foreninger",
    "sg:phone":"+45 45 87 61 87",
    "sg:postcode":"2800",
    "sg:province":"Danmark",
    "wof:name":"Bug Club Herbie 4-ever",
    "wof:placetype":"venue"
},
  "geometry": {"coordinates":[12.5430641174,55.7812652588],"type":"Point"}
}