{
  "type": "Feature",
  "properties": {
    "iso:country":"DK",
    "sg:address":"Gislumvej 27 A",
    "sg:city":"Aars",
    "sg:classifiers":[
        {
            "category":"Utilities",
            "subcategory":"Refuse",
            "type":"Services"
        }
    ],
    "sg:postcode":"9600",
    "sg:province":"Danmark",
    "sg:tags":[
        "catering"
    ],
    "wof:name":"K\u00f8kkensnedkeren",
    "wof:placetype":"venue"
},
  "geometry": {"coordinates":[9.5133018494,56.8002204895],"type":"Point"}
}