{
  "type": "Feature",
  "properties": {
    "addr:full":"Poppelg\u00e5rdvej 9 B S\u00f8borg Danmark 2860",
    "addr:housenumber":"9 b",
    "addr:postcode":"2860",
    "addr:street":"Poppelgaardvej",
    "iso:country":"DK",
    "sg:address":"Poppelg\u00e5rdvej 9 B",
    "sg:city":"S\u00f8borg",
    "sg:classifiers":[
        {
            "category":"Airport",
            "type":"Transportation"
        }
    ],
    "sg:phone":"+45 39 66 08 09",
    "sg:postcode":"2860",
    "sg:province":"Danmark",
    "sg:tags":[
        "automation"
    ],
    "wof:name":"JLI Vision A/S",
    "wof:placetype":"venue"
},
  "geometry": {"coordinates":[-101.3893203735,35.6754798889],"type":"Point"}
}