{
  "type": "Feature",
  "properties": {
    "addr:full":"Fmd.: Ivar C. H. Castenschiold, Ny Kirstinebergvej 23, Kraghave Nyk\u00f8bing Danmark 4800",
    "addr:housenumber":"23",
    "addr:postcode":"4800",
    "addr:street":"Ivar;Ny Kirstinebergvej",
    "iso:country":"DK",
    "sg:address":"Fmd.: Ivar C. H. Castenschiold, Ny Kirstinebergvej 23, Kraghave",
    "sg:city":"Nyk\u00f8bing",
    "sg:orig_category":"Soldaterforeninger",
    "sg:phone":"+45 54 43 94 11",
    "sg:postcode":"4800",
    "sg:province":"Danmark",
    "wof:name":"Falster og \u00d8stlollands Garderforening",
    "wof:placetype":"venue"
},
  "geometry": {"coordinates":[-76.50189208979999,42.8563194275],"type":"Point"}
}