{
  "type": "Feature",
  "properties": {
    "addr:full":"Gildemester: Margit Fohlmann, Dronningeholmen 5 Taastrup Danmark 2630",
    "addr:housenumber":"5",
    "addr:postcode":"2630",
    "addr:street":"Dronningeholmen",
    "iso:country":"DK",
    "sg:address":"Gildemester: Margit Fohlmann, Dronningeholmen 5",
    "sg:city":"Taastrup",
    "sg:orig_category":"Loger",
    "sg:phone":"+45 43 99 12 18",
    "sg:postcode":"2630",
    "sg:province":"Danmark",
    "wof:name":"1. Sct. Georgs-gilde",
    "wof:placetype":"venue"
},
  "geometry": {"coordinates":[12.3020896912,55.6506767273],"type":"Point"}
}