{
  "type": "Feature",
  "properties": {
    "addr:full":"Sankelmarksgade 1 A Aalborg Danmark 9000",
    "addr:housenumber":"1 a",
    "addr:postcode":"9000",
    "addr:street":"Sankelmarksgade",
    "iso:country":"DK",
    "sg:address":"Sankelmarksgade 1 A",
    "sg:city":"Aalborg",
    "sg:classifiers":[
        {
            "category":"Restaurant",
            "type":"Food & Drink"
        }
    ],
    "sg:phone":"+45 98 11 44 08",
    "sg:postcode":"9000",
    "sg:province":"Danmark",
    "wof:name":"Akropolis",
    "wof:placetype":"venue"
},
  "geometry": {"coordinates":[9.918381691,57.0461425781],"type":"Point"}
}