{
  "type": "Feature",
  "properties": {
    "addr:full":"Bjolderupvej 5 Bolderslev Danmark 6392",
    "addr:housenumber":"5",
    "addr:postcode":"6392",
    "addr:street":"Bjolderupvej",
    "iso:country":"DK",
    "sg:address":"Bjolderupvej 5",
    "sg:city":"Bolderslev",
    "sg:orig_category":"Maskinstationer",
    "sg:phone":"+45 74 64 62 47",
    "sg:postcode":"6392",
    "sg:province":"Danmark",
    "wof:name":"Bolderslev & Hjordk\u00e6r Maskinstation A/S",
    "wof:placetype":"venue"
},
  "geometry": {"coordinates":[9.2689838409,54.9921722412],"type":"Point"}
}