{
  "type": "Feature",
  "properties": {
    "iso:country":"DK",
    "sg:address":"Steen Blichers Vej 3",
    "sg:city":"Holstebro",
    "sg:classifiers":[
        {
            "category":"Building & Trades",
            "subcategory":"Construction",
            "type":"Services"
        }
    ],
    "sg:phone":"+45 97 41 42 33",
    "sg:postcode":"7500",
    "sg:province":"Danmark",
    "sg:tags":[
        "renovation"
    ],
    "wof:name":"Kirk, J\u00f8rgen",
    "wof:placetype":"venue"
},
  "geometry": {"coordinates":[8.6290225983,56.3529663086],"type":"Point"}
}