{
  "type": "Feature",
  "properties": {
    "addr:full":"Julianehedevej 2 Bording Danmark 7441",
    "addr:housenumber":"2",
    "addr:postcode":"7441",
    "addr:street":"Julianehedevej",
    "iso:country":"DK",
    "sg:address":"Julianehedevej 2",
    "sg:city":"Bording",
    "sg:orig_category":"Landbrugsmaskiner",
    "sg:phone":"+45 86 86 20 93",
    "sg:postcode":"7441",
    "sg:province":"Danmark",
    "wof:name":"Ivan's Maskinservice",
    "wof:placetype":"venue"
},
  "geometry": {"coordinates":[9.2957420349,56.165813446],"type":"Point"}
}