{
  "type": "Feature",
  "properties": {
    "iso:country":"DK",
    "sg:address":"Bavneh\u00f8jvej 19",
    "sg:city":"Silkeborg",
    "sg:orig_category":"Handicaplifte",
    "sg:phone":"+45 87 20 18 88",
    "sg:postcode":"8600",
    "sg:province":"Danmark",
    "sg:website":"www.rolko.dk",
    "wof:name":"Rolko Scandinavia ApS",
    "wof:placetype":"venue"
},
  "geometry": {"coordinates":[9.5805826187,56.1855888367],"type":"Point"}
}