{
  "type": "Feature",
  "properties": {
    "iso:country":"DK",
    "sg:address":"Baneg\u00e5rdspladsen 4",
    "sg:city":"Vordingborg",
    "sg:orig_category":"Jernbaner",
    "sg:phone":"+45 70 13 14 15",
    "sg:postcode":"4760",
    "sg:province":"Danmark",
    "wof:name":"DSB, Vordingborg Station",
    "wof:placetype":"venue"
},
  "geometry": {"coordinates":[11.9000310898,55.0122070312],"type":"Point"}
}