{
  "type": "Feature",
  "properties": {
    "iso:country":"DK",
    "sg:address":"Fmd.: Jane Pasgaard, Ringgade 47, Lomborg",
    "sg:city":"Lemvig",
    "sg:orig_category":"Kirkelige foreninger",
    "sg:phone":"+45 97 88 89 96",
    "sg:postcode":"7620",
    "sg:province":"Danmark",
    "wof:name":"Indre Missions Ungdom i Lemvig",
    "wof:placetype":"venue"
},
  "geometry": {"coordinates":[8.3073654175,56.5505104065],"type":"Point"}
}