{
  "type": "Feature",
  "properties": {
    "addr:full":"R\u00f8nnevej 90, Nylars Aakirkeby Danmark 3720",
    "addr:housenumber":"90",
    "addr:postcode":"3720",
    "addr:street":"Ronnevej",
    "iso:country":"DK",
    "sg:address":"R\u00f8nnevej 90, Nylars",
    "sg:city":"Aakirkeby",
    "sg:orig_category":"Landbrugsmaskiner",
    "sg:phone":"+45 56 94 74 50",
    "sg:postcode":"3720",
    "sg:province":"Danmark",
    "sg:website":"www.ap-hellisen.dk",
    "wof:name":"Hellisen A/S, A.P.",
    "wof:placetype":"venue"
},
  "geometry": {"coordinates":[14.9202880859,55.070110321],"type":"Point"}
}