{
  "type": "Feature",
  "properties": {
    "addr:full":"Dalinsvej 74 Randers Danmark 8900",
    "addr:housenumber":"74",
    "addr:postcode":"8900",
    "addr:street":"Dalinsvej",
    "iso:country":"DK",
    "sg:address":"Dalinsvej 74",
    "sg:city":"Randers",
    "sg:orig_category":"Databehandling",
    "sg:phone":"+45 40 93 30 69",
    "sg:postcode":"8900",
    "sg:province":"Danmark",
    "wof:name":"Amok Media",
    "wof:placetype":"venue"
},
  "geometry": {"coordinates":[9.9720687866,56.4602508545],"type":"Point"}
}