{
  "type": "Feature",
  "properties": {
    "addr:full":"Skovh\u00f8j 16 Kolding Danmark 6000",
    "addr:housenumber":"16",
    "addr:postcode":"6000",
    "addr:street":"Skovhoj",
    "iso:country":"DK",
    "sg:address":"Skovh\u00f8j 16",
    "sg:city":"Kolding",
    "sg:orig_category":"Solcentre",
    "sg:phone":"+45 20 22 12 22",
    "sg:postcode":"6000",
    "sg:province":"Danmark",
    "wof:name":"Ultra Sun",
    "wof:placetype":"venue"
},
  "geometry": {"coordinates":[9.4714012146,55.4819984436],"type":"Point"}
}