{
  "type": "Feature",
  "properties": {
    "addr:full":"Thistedvej 43 - 45, Halvrimmen Brovst Danmark 9460",
    "addr:housenumber":"43 45",
    "addr:postcode":"9460",
    "addr:street":"Thistedvej;Halvrimmen",
    "iso:country":"DK",
    "sg:address":"Thistedvej 43 - 45, Halvrimmen",
    "sg:city":"Brovst",
    "sg:orig_category":"Autoreparation og -service",
    "sg:phone":"+45 98 23 88 13",
    "sg:postcode":"9460",
    "sg:province":"Danmark",
    "wof:name":"Anthons Automobil-Service",
    "wof:placetype":"venue"
},
  "geometry": {"coordinates":[9.5220241547,57.097366333],"type":"Point"}
}