{
  "type": "Feature",
  "properties": {
    "addr:full":"Greveager 3, 1 tv. Greve Danmark 2670",
    "addr:housenumber":"3 1 tv.",
    "addr:postcode":"2670",
    "addr:street":"Greveager",
    "iso:country":"DK",
    "sg:address":"Greveager 3, 1 tv.",
    "sg:city":"Greve",
    "sg:orig_category":"Gartnerier",
    "sg:phone":"+45 40 51 42 72",
    "sg:postcode":"2670",
    "sg:province":"Danmark",
    "wof:name":"Gr\u00e6sr\u00f8dderne I/S",
    "wof:placetype":"venue"
},
  "geometry": {"coordinates":[12.2941808701,55.5844078064],"type":"Point"}
}