{
  "type": "Feature",
  "properties": {
    "addr:full":"Ravsted Hovedgade 55 Bylderup-Bov Danmark 6372",
    "addr:housenumber":"55",
    "addr:postcode":"6372",
    "addr:street":"Ravsted Hovedgade",
    "iso:country":"DK",
    "sg:address":"Ravsted Hovedgade 55",
    "sg:city":"Bylderup-Bov",
    "sg:orig_category":"Autoreparation og -service",
    "sg:phone":"+45 74 64 73 23",
    "sg:postcode":"6372",
    "sg:province":"Danmark",
    "wof:name":"Schr\u00f8der Autov\u00e6rksted, P. C.",
    "wof:placetype":"venue"
},
  "geometry": {"coordinates":[9.1277303696,55.0044593811],"type":"Point"}
}