{
  "type": "Feature",
  "properties": {
    "addr:full":"Thistedvej 335, Klim Fjerritslev Danmark 9690",
    "addr:housenumber":"335",
    "addr:postcode":"9690",
    "addr:street":"Thistedvej;Klim",
    "iso:country":"DK",
    "sg:address":"Thistedvej 335, Klim",
    "sg:city":"Fjerritslev",
    "sg:orig_category":"Hundetrimning",
    "sg:phone":"+45 98 22 55 28",
    "sg:postcode":"9690",
    "sg:province":"Danmark",
    "wof:name":"Ruth's Hundesalon",
    "wof:placetype":"venue"
},
  "geometry": {"coordinates":[9.2667350769,57.0882301331],"type":"Point"}
}