{
  "type": "Feature",
  "properties": {
    "addr:full":"Dumpen 18 Viborg Danmark 8800",
    "addr:housenumber":"18",
    "addr:postcode":"8800",
    "addr:street":"Dumpen",
    "iso:country":"DK",
    "sg:address":"Dumpen 18",
    "sg:city":"Viborg",
    "sg:orig_category":"Pizzeriaer",
    "sg:phone":"+45 86 62 26 22",
    "sg:postcode":"8800",
    "sg:province":"Danmark",
    "wof:name":"Pizza Expressen",
    "wof:placetype":"venue"
},
  "geometry": {"coordinates":[9.4040250778,56.449131012],"type":"Point"}
}