{
  "type": "Feature",
  "properties": {
    "addr:full":"H\u00f8dyssevej 9, Gunds\u00f8magle Roskilde Danmark 4000",
    "addr:housenumber":"9",
    "addr:postcode":"4000",
    "addr:street":"Hodyssevej",
    "iso:country":"DK",
    "sg:address":"H\u00f8dyssevej 9, Gunds\u00f8magle",
    "sg:city":"Roskilde",
    "sg:orig_category":"Kogekoner",
    "sg:phone":"+45 46 78 87 49",
    "sg:postcode":"4000",
    "sg:province":"Danmark",
    "wof:name":"Irenes Mad Service",
    "wof:placetype":"venue"
},
  "geometry": {"coordinates":[12.0909376144,55.6404838562],"type":"Point"}
}