{
  "type": "Feature",
  "properties": {
    "addr:full":"Industrivej 6 Slagelse Danmark 4200",
    "addr:housenumber":"6",
    "addr:postcode":"4200",
    "addr:street":"Industrivej",
    "iso:country":"DK",
    "sg:address":"Industrivej 6",
    "sg:city":"Slagelse",
    "sg:orig_category":"Maskinfabrikker",
    "sg:phone":"+45 58 55 52 00",
    "sg:postcode":"4200",
    "sg:province":"Danmark",
    "sg:website":"www.wolfking.com",
    "wof:name":"Wolfking A/S",
    "wof:placetype":"venue"
},
  "geometry": {"coordinates":[11.3870897293,55.4127960205],"type":"Point"}
}