{
  "type": "Feature",
  "properties": {
    "addr:full":"Torvegade 23 Padborg Danmark 6330",
    "addr:housenumber":"23",
    "addr:postcode":"6330",
    "addr:street":"Torvegade",
    "iso:country":"DK",
    "sg:address":"Torvegade 23",
    "sg:city":"Padborg",
    "sg:orig_category":"Guldsmede",
    "sg:phone":"+45 74 67 32 74",
    "sg:postcode":"6330",
    "sg:province":"Danmark",
    "wof:name":"Jensen, Jan",
    "wof:placetype":"venue"
},
  "geometry": {"coordinates":[9.3600759506,54.8254776001],"type":"Point"}
}