{
  "type": "Feature",
  "properties": {
    "iso:country":"DK",
    "sg:address":"\u00d8stervej 5",
    "sg:city":"Holeby",
    "sg:orig_category":"Sparekasser",
    "sg:phone":"+45 54 60 60 16",
    "sg:postcode":"4960",
    "sg:province":"Danmark",
    "sg:website":"www.sparlolland.dk",
    "wof:name":"Sparekassen Lolland",
    "wof:placetype":"venue"
},
  "geometry": {"coordinates":[11.4752225876,54.7087745667],"type":"Point"}
}