{
  "type": "Feature",
  "properties": {
    "addr:full":"Herlev Bygade 40, 1. Herlev Danmark 2730",
    "addr:housenumber":"40 1",
    "addr:postcode":"2730",
    "addr:street":"Herlev Bygade",
    "iso:country":"DK",
    "sg:address":"Herlev Bygade 40, 1.",
    "sg:city":"Herlev",
    "sg:orig_category":"Alternativ behandling",
    "sg:phone":"+45 44 92 79 88",
    "sg:postcode":"2730",
    "sg:province":"Danmark",
    "wof:name":"Akupunktur Klinik i Herlev",
    "wof:placetype":"venue"
},
  "geometry": {"coordinates":[12.4383592606,55.7251396179],"type":"Point"}
}