{
  "type": "Feature",
  "properties": {
    "addr:full":"Nymarksvej 1, Thyregod Give Danmark 7323",
    "addr:housenumber":"1",
    "addr:postcode":"7323",
    "addr:street":"Nymarksvej;Thyregod",
    "iso:country":"DK",
    "sg:address":"Nymarksvej 1, Thyregod",
    "sg:city":"Give",
    "sg:classifiers":[
        {
            "category":"Taxi",
            "type":"Transportation"
        }
    ],
    "sg:phone":"+45 75 73 40 86",
    "sg:postcode":"7323",
    "sg:province":"Danmark",
    "wof:name":"Thyregod Taxi",
    "wof:placetype":"venue"
},
  "geometry": {"coordinates":[9.2362060547,55.845413208],"type":"Point"}
}