{
  "type": "Feature",
  "properties": {
    "addr:full":"Lynge Bygade 18 A Lynge Danmark 3540",
    "addr:housenumber":"18 a",
    "addr:postcode":"3540",
    "addr:street":"Lynge Bygade",
    "iso:country":"DK",
    "sg:address":"Lynge Bygade 18 A",
    "sg:city":"Lynge",
    "sg:orig_category":"Musikere",
    "sg:phone":"+45 48 18 71 33",
    "sg:postcode":"3540",
    "sg:province":"Danmark",
    "wof:name":"Peters, Ole",
    "wof:placetype":"venue"
},
  "geometry": {"coordinates":[12.2806854248,55.8430671692],"type":"Point"}
}