{
  "type": "Feature",
  "properties": {
    "addr:full":"Motelvej 2, Karlstrup Karlslunde Danmark 2690",
    "addr:housenumber":"2",
    "addr:postcode":"2690",
    "addr:street":"Motelvej;Karlstrup",
    "iso:country":"DK",
    "sg:address":"Motelvej 2, Karlstrup",
    "sg:city":"Karlslunde",
    "sg:classifiers":[
        {
            "category":"Restaurant",
            "type":"Food & Drink"
        }
    ],
    "sg:phone":"+45 56 14 70 17",
    "sg:postcode":"2690",
    "sg:province":"Danmark",
    "wof:name":"McDonalds",
    "wof:placetype":"venue"
},
  "geometry": {"coordinates":[12.2294149399,55.5701599121],"type":"Point"}
}