{
  "type": "Feature",
  "properties": {
    "iso:country":"DK",
    "sg:address":"Lokesalle 69",
    "sg:city":"Horsens",
    "sg:orig_category":"Spedition",
    "sg:phone":"+45 75 64 23 00",
    "sg:postcode":"8700",
    "sg:province":"Danmark",
    "wof:name":"Transland Horsens A/S Spedition",
    "wof:placetype":"venue"
},
  "geometry": {"coordinates":[9.8207817078,55.8514709473],"type":"Point"}
}