{
  "type": "Feature",
  "properties": {
    "addr:full":"Verningevej 10, Nr. Broby Broby Danmark 5672",
    "addr:housenumber":"10",
    "addr:postcode":"5672",
    "addr:street":"Verningevej",
    "iso:country":"DK",
    "sg:address":"Verningevej 10, Nr. Broby",
    "sg:city":"Broby",
    "sg:orig_category":"Malermestre",
    "sg:phone":"+45 62 63 21 72",
    "sg:postcode":"5672",
    "sg:province":"Danmark",
    "wof:name":"Jakobsen ApS, Malerfirmaet Holger",
    "wof:placetype":"venue"
},
  "geometry": {"coordinates":[10.3131303787,55.2695846558],"type":"Point"}
}