{
  "type": "Feature",
  "properties": {
    "addr:full":"Frichsvej 18 Silkeborg Danmark 8600",
    "addr:housenumber":"18",
    "addr:postcode":"8600",
    "addr:street":"Frichsvej",
    "iso:country":"DK",
    "sg:address":"Frichsvej 18",
    "sg:city":"Silkeborg",
    "sg:orig_category":"Databehandling",
    "sg:phone":"+45 89 22 43 00",
    "sg:postcode":"8600",
    "sg:province":"Danmark",
    "wof:name":"Silkeborg Datacentral A/S",
    "wof:placetype":"venue"
},
  "geometry": {"coordinates":[9.5653800964,56.1949157715],"type":"Point"}
}