{
  "type": "Feature",
  "properties": {
    "iso:country":"DK",
    "sg:address":"Ullerslev-Centret 23-24",
    "sg:city":"Ullerslev",
    "sg:classifiers":[
        {
            "category":"Banks & Credit Unions",
            "subcategory":"Bank",
            "type":"Services"
        }
    ],
    "sg:phone":"+45 63 35 60 00",
    "sg:postcode":"5540",
    "sg:province":"Danmark",
    "sg:tags":[
        "banker"
    ],
    "wof:name":"BG Bank",
    "wof:placetype":"venue"
},
  "geometry": {"coordinates":[10.665449,55.359928],"type":"Point"}
}