{
  "type": "Feature",
  "properties": {
    "addr:full":"Sm\u00f8gen 5, Thorup Knebel Danmark 8420",
    "addr:housenumber":"5",
    "addr:postcode":"8420",
    "addr:street":"Smogen;Thorup",
    "iso:country":"DK",
    "sg:address":"Sm\u00f8gen 5, Thorup",
    "sg:city":"Knebel",
    "sg:orig_category":"Murermestre",
    "sg:phone":"+45 86 35 10 87",
    "sg:postcode":"8420",
    "sg:province":"Danmark",
    "wof:name":"St\u00f8ve, Bent",
    "wof:placetype":"venue"
},
  "geometry": {"coordinates":[10.3770122528,56.1816596985],"type":"Point"}
}