{
  "type": "Feature",
  "properties": {
    "addr:full":"Dagli' Brugsen, Agersb\u00f8lvej 5, Lindved Vejle Danmark 7100",
    "addr:housenumber":"5",
    "addr:postcode":"7100",
    "addr:street":"Agersbolvej",
    "iso:country":"DK",
    "sg:address":"Dagli' Brugsen, Agersb\u00f8lvej 5, Lindved",
    "sg:city":"Vejle",
    "sg:orig_category":"Posthuse",
    "sg:phone":"+45 75 85 11 44",
    "sg:postcode":"7100",
    "sg:province":"Danmark",
    "wof:name":"Post Danmark, Lindved Posthus",
    "wof:placetype":"venue"
},
  "geometry": {"coordinates":[9.6454601288,55.7950935364],"type":"Point"}
}