{
  "type": "Feature",
  "properties": {
    "addr:full":"Aldrupvej 226, Aldrup Fjerritslev Danmark 9690",
    "addr:housenumber":"226",
    "addr:postcode":"9690",
    "addr:street":"Aldrupvej;Aldrup",
    "iso:country":"DK",
    "sg:address":"Aldrupvej 226, Aldrup",
    "sg:city":"Fjerritslev",
    "sg:orig_category":"Vinduespolering",
    "sg:phone":"+45 98 21 28 82",
    "sg:postcode":"9690",
    "sg:province":"Danmark",
    "wof:name":"Himmerlands Vinduespolering",
    "wof:placetype":"venue"
},
  "geometry": {"coordinates":[9.2667350769,57.0882301331],"type":"Point"}
}