{
  "type": "Feature",
  "properties": {
    "addr:full":"Strengevej 2 Ribe Danmark 6760",
    "addr:housenumber":"2",
    "addr:postcode":"6760",
    "addr:street":"Strengevej",
    "iso:country":"DK",
    "sg:address":"Strengevej 2",
    "sg:city":"Ribe",
    "sg:classifiers":[
        {
            "category":"Home & Garden",
            "subcategory":"Home Furnishings",
            "type":"Retail Goods"
        }
    ],
    "sg:phone":"+45 75 41 00 37",
    "sg:postcode":"6760",
    "sg:province":"Danmark",
    "sg:tags":[
        "gardiner"
    ],
    "wof:name":"GardinNyt",
    "wof:placetype":"venue"
},
  "geometry": {"coordinates":[8.7743930817,55.3173179626],"type":"Point"}
}