{
  "type": "Feature",
  "properties": {
    "addr:full":"v/Vr\u00e5 Hovedbibliotek, Sdr. Vr\u00e5vej 1 Vr\u00e5 Danmark 9760",
    "addr:housenumber":"1",
    "addr:postcode":"9760",
    "addr:street":"Vraavej",
    "iso:country":"DK",
    "sg:address":"v/Vr\u00e5 Hovedbibliotek, Sdr. Vr\u00e5vej 1",
    "sg:city":"Vr\u00e5",
    "sg:orig_category":"Turistbureau og -information",
    "sg:phone":"+45 99 67 12 60",
    "sg:postcode":"9760",
    "sg:province":"Danmark",
    "wof:name":"Vr\u00e5 Turistinformation",
    "wof:placetype":"venue"
},
  "geometry": {"coordinates":[9.9477567673,57.3534927368],"type":"Point"}
}