{
  "type": "Feature",
  "properties": {
    "addr:full":"Sverigesgade 2 Odense C Danmark 5000",
    "addr:housenumber":"2",
    "addr:postcode":"5000",
    "addr:street":"Sverigesgade",
    "iso:country":"DK",
    "sg:address":"Sverigesgade 2",
    "sg:city":"Odense C",
    "sg:orig_category":"Laboratorier",
    "sg:phone":"+45 66 12 11 50",
    "sg:postcode":"5000",
    "sg:province":"Danmark",
    "wof:name":"DLG Centrallaboratorium",
    "wof:placetype":"venue"
},
  "geometry": {"coordinates":[10.3825502396,55.4105491638],"type":"Point"}
}