{
  "type": "Feature",
  "properties": {
    "addr:full":"Kraftv\u00e6rksvej 25 K\u00f8benhavn S Danmark 2300",
    "addr:housenumber":"25",
    "addr:postcode":"2300",
    "addr:street":"Kraftvaerksvej;S Danmark",
    "iso:country":"DK",
    "sg:address":"Kraftv\u00e6rksvej 25",
    "sg:city":"K\u00f8benhavn S",
    "sg:classifiers":[
        {
            "category":"Building & Trades",
            "subcategory":"Construction",
            "type":"Services"
        }
    ],
    "sg:phone":"+45 32 66 18 98",
    "sg:postcode":"2300",
    "sg:province":"Danmark",
    "sg:tags":[
        "renovation"
    ],
    "sg:website":"www.r98.dk",
    "wof:name":"R98",
    "wof:placetype":"venue"
},
  "geometry": {"coordinates":[-82.5005874634,38.414390564],"type":"Point"}
}