{
  "type": "Feature",
  "properties": {
    "addr:full":"Lottrups G\u00e5rd 9 Odense C Danmark 5000",
    "addr:housenumber":"9",
    "addr:postcode":"5000",
    "addr:street":"Lottrups Gaard",
    "iso:country":"DK",
    "sg:address":"Lottrups G\u00e5rd 9",
    "sg:city":"Odense C",
    "sg:orig_category":"Tegnere og tegnestuer",
    "sg:phone":"+45 66 13 62 00",
    "sg:postcode":"5000",
    "sg:province":"Danmark",
    "wof:name":"Gr\u00e5br\u00f8drene M.A.A., Arkitektfirmaet",
    "wof:placetype":"venue"
},
  "geometry": {"coordinates":[10.3832578659,55.3939285278],"type":"Point"}
}