{
  "type": "Feature",
  "properties": {
    "addr:full":"K\u00e6rsangervej 2 Lang\u00e5 Danmark 8870",
    "addr:housenumber":"2",
    "addr:postcode":"8870",
    "addr:street":"Kaersangervej",
    "iso:country":"DK",
    "sg:address":"K\u00e6rsangervej 2",
    "sg:city":"Lang\u00e5",
    "sg:orig_category":"Maskinfabrikker",
    "sg:phone":"+45 86 46 11 23",
    "sg:postcode":"8870",
    "sg:province":"Danmark",
    "wof:name":"Elbima",
    "wof:placetype":"venue"
},
  "geometry": {"coordinates":[9.8994455338,56.3949317932],"type":"Point"}
}