{
  "type": "Feature",
  "properties": {
    "addr:full":"Fmd.: Per Skytte Madsen, Kovangen 623 Fredensborg Danmark 3480",
    "addr:housenumber":"623",
    "addr:postcode":"3480",
    "addr:street":"Kovangen",
    "iso:country":"DK",
    "sg:address":"Fmd.: Per Skytte Madsen, Kovangen 623",
    "sg:city":"Fredensborg",
    "sg:orig_category":"Hobbybetonede foreninger",
    "sg:phone":"+45 48 48 44 72",
    "sg:postcode":"3480",
    "sg:province":"Danmark",
    "wof:name":"Fredensborg Modeljernbaneklub Lille Nord",
    "wof:placetype":"venue"
},
  "geometry": {"coordinates":[12.4020547867,55.9782943726],"type":"Point"}
}