{
  "type": "Feature",
  "properties": {
    "addr:full":"Frydsvej 21 Kolding Danmark 6000",
    "addr:housenumber":"21",
    "addr:postcode":"6000",
    "addr:street":"Frydsvej",
    "iso:country":"DK",
    "sg:address":"Frydsvej 21",
    "sg:city":"Kolding",
    "sg:orig_category":"Dykkerudstyr",
    "sg:phone":"+45 75 53 52 91",
    "sg:postcode":"6000",
    "sg:province":"Danmark",
    "sg:website":"www.kolding-dc.dk",
    "wof:name":"Kolding Dykker Center",
    "wof:placetype":"venue"
},
  "geometry": {"coordinates":[9.473985672,55.4966163635],"type":"Point"}
}