{
  "type": "Feature",
  "properties": {
    "addr:full":"Transformervej 29 Herlev Danmark 2730",
    "addr:housenumber":"29",
    "addr:postcode":"2730",
    "addr:street":"Transformervej",
    "iso:country":"DK",
    "sg:address":"Transformervej 29",
    "sg:city":"Herlev",
    "sg:orig_category":"Reproanstalter",
    "sg:phone":"+45 44 84 51 00",
    "sg:postcode":"2730",
    "sg:province":"Danmark",
    "wof:name":"Graulund & J\u00f8rgensen A/S",
    "wof:placetype":"venue"
},
  "geometry": {"coordinates":[12.4690723419,55.7312431335],"type":"Point"}
}