{
  "type": "Feature",
  "properties": {
    "addr:full":"D\u00e5sbjergvej 24, Vridsted Skive Danmark 7800",
    "addr:housenumber":"24",
    "addr:postcode":"7800",
    "addr:street":"Daasbjergvej;Vridsted",
    "iso:country":"DK",
    "sg:address":"D\u00e5sbjergvej 24, Vridsted",
    "sg:city":"Skive",
    "sg:classifiers":[
        {
            "category":"Communications",
            "type":"Services"
        }
    ],
    "sg:phone":"+45 97 54 73 05",
    "sg:postcode":"7800",
    "sg:province":"Danmark",
    "sg:tags":[
        "og",
        "tv",
        "radio"
    ],
    "wof:name":"Sj\u00f8rup-Vridsted Radio & TV",
    "wof:placetype":"venue"
},
  "geometry": {"coordinates":[9.0320358276,56.5666427612],"type":"Point"}
}