{
  "type": "Feature",
  "properties": {
    "addr:full":"T\u00f8mmerbyvej 186 Vesl\u00f8s Danmark 7742",
    "addr:housenumber":"186",
    "addr:postcode":"7742",
    "addr:street":"Tommerbyvej",
    "iso:country":"DK",
    "sg:address":"T\u00f8mmerbyvej 186",
    "sg:city":"Vesl\u00f8s",
    "sg:orig_category":"Malermestre",
    "sg:phone":"+45 97 99 38 55",
    "sg:postcode":"7742",
    "sg:province":"Danmark",
    "wof:name":"Inger's Malerforretning",
    "wof:placetype":"venue"
},
  "geometry": {"coordinates":[-78.1299133301,36.7267417908],"type":"Point"}
}