{
  "type": "Feature",
  "properties": {
    "iso:country":"DK",
    "sg:address":"Fmd.: K\u00e5re Andresen, Vestergade 32",
    "sg:city":"Idestrup",
    "sg:orig_category":"Grundejerforeninger",
    "sg:phone":"+45 54 14 86 07",
    "sg:postcode":"4872",
    "sg:province":"Danmark",
    "wof:name":"Idestrup og Omegns Grundejerforening",
    "wof:placetype":"venue"
},
  "geometry": {"coordinates":[11.957859993,54.7407112122],"type":"Point"}
}