{
  "type": "Feature",
  "properties": {
    "addr:full":"Lyngh\u00f8jvej 6 B Lynge Danmark 3540",
    "addr:housenumber":"6 b",
    "addr:postcode":"3540",
    "addr:street":"Lynghojvej",
    "iso:country":"DK",
    "sg:address":"Lyngh\u00f8jvej 6 B",
    "sg:city":"Lynge",
    "sg:orig_category":"Bagere",
    "sg:phone":"+45 48 16 06 00",
    "sg:postcode":"3540",
    "sg:province":"Danmark",
    "wof:name":"Krummen, Bagerforretningen",
    "wof:placetype":"venue"
},
  "geometry": {"coordinates":[12.277308,55.840843],"type":"Point"}
}