{
  "type": "Feature",
  "properties": {
    "addr:full":"Fmd.: Jesper Grande, Baunev\u00e6nget 42, N\u00f8debo Fredensborg Danmark 3480",
    "addr:housenumber":"42",
    "addr:postcode":"3480",
    "addr:street":"Jesper;Nodebo",
    "iso:country":"DK",
    "sg:address":"Fmd.: Jesper Grande, Baunev\u00e6nget 42, N\u00f8debo",
    "sg:city":"Fredensborg",
    "sg:orig_category":"Grundejerforeninger",
    "sg:phone":"+45 48 47 60 78",
    "sg:postcode":"3480",
    "sg:province":"Danmark",
    "wof:name":"Grundejerforeningen Baunebjergg\u00e5rd",
    "wof:placetype":"venue"
},
  "geometry": {"coordinates":[12.4020547867,55.9782943726],"type":"Point"}
}