{
  "type": "Feature",
  "properties": {
    "iso:country":"DK",
    "sg:address":"Korsvangen 11",
    "sg:city":"Ringe",
    "sg:orig_category":"Legeredskaber",
    "sg:phone":"+45 63 62 10 11",
    "sg:postcode":"5750",
    "sg:province":"Danmark",
    "sg:website":"www.kompan.com",
    "wof:name":"KOMPAN A/S - Nordic Division",
    "wof:placetype":"venue"
},
  "geometry": {"coordinates":[10.4818267822,55.2471199036],"type":"Point"}
}