{
  "type": "Feature",
  "properties": {
    "addr:full":"\u00d8stergade 60-62 Sk\u00e5rup Danmark 5881",
    "addr:housenumber":"60-62",
    "addr:postcode":"5881",
    "addr:street":"Ostergade",
    "iso:country":"DK",
    "sg:address":"\u00d8stergade 60-62",
    "sg:city":"Sk\u00e5rup",
    "sg:orig_category":"Autoreparation og -service",
    "sg:phone":"+45 62 23 19 91",
    "sg:postcode":"5881",
    "sg:province":"Danmark",
    "sg:website":"www.auto-centrum.dk",
    "wof:name":"Auto Centrum Sk\u00e5rup",
    "wof:placetype":"venue"
},
  "geometry": {"coordinates":[10.6887655258,55.0955543518],"type":"Point"}
}