{
  "type": "Feature",
  "properties": {
    "addr:full":"Violvej 3 A Vordingborg Danmark 4760",
    "addr:housenumber":"3 a",
    "addr:postcode":"4760",
    "addr:street":"Violvej",
    "iso:country":"DK",
    "sg:address":"Violvej 3 A",
    "sg:city":"Vordingborg",
    "sg:orig_category":"\u00c3\u02dcvrige skoler",
    "sg:phone":"+45 55 36 06 36",
    "sg:postcode":"4760",
    "sg:province":"Danmark",
    "sg:website":"www.vhh.dk",
    "wof:name":"Vordingborg Husholdnings- og H\u00e5ndarbejdsskole",
    "wof:placetype":"venue"
},
  "geometry": {"coordinates":[11.9066743851,55.0059890747],"type":"Point"}
}