{
  "type": "Feature",
  "properties": {
    "addr:full":"Leder: Gustav Byskov Nielsen, Birkildvej 13, Asp Struer Danmark 7600",
    "addr:housenumber":"13",
    "addr:postcode":"7600",
    "addr:street":"Birkildvej;Asp",
    "iso:country":"DK",
    "sg:address":"Leder: Gustav Byskov Nielsen, Birkildvej 13, Asp",
    "sg:city":"Struer",
    "sg:orig_category":"Ungdomsklubber",
    "sg:phone":"+45 97 48 72 52",
    "sg:postcode":"7600",
    "sg:province":"Danmark",
    "wof:name":"Ungt Forum Ungdomsklub",
    "wof:placetype":"venue"
},
  "geometry": {"coordinates":[8.5946903229,56.491191864],"type":"Point"}
}