{
  "type": "Feature",
  "properties": {
    "iso:country":"DK",
    "sg:address":"Skovsbjergvej 5, Stenderup",
    "sg:city":"Toftlund",
    "sg:orig_category":"Rejsebureauer",
    "sg:phone":"+45 74 83 14 77",
    "sg:postcode":"6520",
    "sg:province":"Danmark",
    "wof:name":"Madsen, Carsten Juelsg\u00e5rd",
    "wof:placetype":"venue"
},
  "geometry": {"coordinates":[9.0629367828,55.1926651001],"type":"Point"}
}