{
  "type": "Feature",
  "properties": {
    "addr:full":"Kornv\u00e6nget 68 Ballerup Danmark 2750",
    "addr:housenumber":"68",
    "addr:postcode":"2750",
    "addr:street":"Kornvaenget",
    "iso:country":"DK",
    "sg:address":"Kornv\u00e6nget 68",
    "sg:city":"Ballerup",
    "sg:orig_category":"Kiosker",
    "sg:phone":"+45 44 65 22 10",
    "sg:postcode":"2750",
    "sg:province":"Danmark",
    "wof:name":"Elitekiosken",
    "wof:placetype":"venue"
},
  "geometry": {"coordinates":[12.361000061,55.7301216125],"type":"Point"}
}