{
  "type": "Feature",
  "properties": {
    "addr:full":"\u00d8stre Alle 28 Slagelse Danmark 4200",
    "addr:housenumber":"28",
    "addr:postcode":"4200",
    "addr:street":"Ostre Alle",
    "iso:country":"DK",
    "sg:address":"\u00d8stre Alle 28",
    "sg:city":"Slagelse",
    "sg:orig_category":"Autoforhandlere",
    "sg:phone":"+45 58 52 18 50",
    "sg:postcode":"4200",
    "sg:province":"Danmark",
    "sg:website":"www.aut-forhandler.dk/thomas-schultz/",
    "wof:name":"Th. Schultz Automobiler ApS",
    "wof:placetype":"venue"
},
  "geometry": {"coordinates":[11.3671560287,55.4096488953],"type":"Point"}
}