{
  "type": "Feature",
  "properties": {
    "addr:full":"\u00d8strigsgade 23 2.th. K\u00f8benhavn S Danmark 2300",
    "addr:housenumber":"23 2.th",
    "addr:postcode":"2300",
    "addr:street":"Ostrigsgade;Kobenhavn S Danmark",
    "iso:country":"DK",
    "sg:address":"\u00d8strigsgade 23 2.th.",
    "sg:city":"K\u00f8benhavn S",
    "sg:orig_category":"Kasinoer",
    "sg:phone":"+45 28 70 29 49",
    "sg:postcode":"2300",
    "sg:province":"Danmark",
    "sg:website":"www.jokerswild.dk",
    "wof:name":"Joker's Wild FunCasino",
    "wof:placetype":"venue"
},
  "geometry": {"coordinates":[-78.1299133301,36.7267417908],"type":"Point"}
}