{
  "type": "Feature",
  "properties": {
    "addr:full":"Degnekrogen 4, Arnborg Herning Danmark 7400",
    "addr:housenumber":"4",
    "addr:postcode":"7400",
    "addr:street":"Degnekrogen;Arnborg",
    "iso:country":"DK",
    "sg:address":"Degnekrogen 4, Arnborg",
    "sg:city":"Herning",
    "sg:orig_category":"Integrerede institutioner",
    "sg:phone":"+45 96 28 92 11",
    "sg:postcode":"7400",
    "sg:province":"Danmark",
    "wof:name":"Arnborg B\u00f8rnecenter",
    "wof:placetype":"venue"
},
  "geometry": {"coordinates":[8.9768896103,56.1374168396],"type":"Point"}
}