{
  "type": "Feature",
  "properties": {
    "addr:full":"Sj\u00e6llandsgade 86 Herning Danmark 7400",
    "addr:housenumber":"86",
    "addr:postcode":"7400",
    "addr:street":"Sjaellandsgade",
    "iso:country":"DK",
    "sg:address":"Sj\u00e6llandsgade 86",
    "sg:city":"Herning",
    "sg:orig_category":"Tandklinikker, Kommunale",
    "sg:phone":"+45 97 22 57 56",
    "sg:postcode":"7400",
    "sg:province":"Danmark",
    "wof:name":"Herningsholmskolens Tandklinik",
    "wof:placetype":"venue"
},
  "geometry": {"coordinates":[8.9924030304,56.1408157349],"type":"Point"}
}