{
  "type": "Feature",
  "properties": {
    "addr:full":"Gr.leder: Gert J\u00f8rgensen, Almstokvej 29 Vorbasse Danmark 6623",
    "addr:housenumber":"29",
    "addr:postcode":"6623",
    "addr:street":"Almstokvej",
    "iso:country":"DK",
    "sg:address":"Gr.leder: Gert J\u00f8rgensen, Almstokvej 29",
    "sg:city":"Vorbasse",
    "sg:orig_category":"Spejderkorps",
    "sg:phone":"+45 75 33 46 18",
    "sg:postcode":"6623",
    "sg:province":"Danmark",
    "wof:name":"KFUM-Spejderne, Hejnsvig",
    "wof:placetype":"venue"
},
  "geometry": {"coordinates":[9.0800552368,55.6312217712],"type":"Point"}
}