{
  "type": "Feature",
  "properties": {
    "addr:full":"R\u00f8nnevej 14 Nex\u00f8 Danmark 3730",
    "addr:housenumber":"14",
    "addr:postcode":"3730",
    "addr:street":"Ronnevej",
    "iso:country":"DK",
    "sg:address":"R\u00f8nnevej 14",
    "sg:city":"Nex\u00f8",
    "sg:orig_category":"Forlystelser",
    "sg:phone":"+45 56 49 25 75",
    "sg:postcode":"3730",
    "sg:province":"Danmark",
    "wof:name":"Bornholms Sommerfuglepark Tropeland",
    "wof:placetype":"venue"
},
  "geometry": {"coordinates":[15.1096076965,55.0267219543],"type":"Point"}
}