{
  "type": "Feature",
  "properties": {
    "addr:full":"Ebstrupvej 60 Silkeborg Danmark 8600",
    "addr:housenumber":"60",
    "addr:postcode":"8600",
    "addr:street":"Ebstrupvej",
    "iso:country":"DK",
    "sg:address":"Ebstrupvej 60",
    "sg:city":"Silkeborg",
    "sg:orig_category":"Korn og foderstoffer",
    "sg:phone":"+45 86 85 91 22",
    "sg:postcode":"8600",
    "sg:province":"Danmark",
    "wof:name":"Aarhusegnens Andel",
    "wof:placetype":"venue"
},
  "geometry": {"coordinates":[9.5610208511,56.2200737],"type":"Point"}
}