{
  "type": "Feature",
  "properties": {
    "iso:country":"DK",
    "sg:address":"S\u00f8ndergade 22",
    "sg:city":"Odense C",
    "sg:orig_category":"Sportsartikler",
    "sg:phone":"+45 65 90 66 90",
    "sg:postcode":"5000",
    "sg:province":"Danmark",
    "wof:name":"KetShop",
    "wof:placetype":"venue"
},
  "geometry": {"coordinates":[10.3796482086,55.3928871155],"type":"Point"}
}