{
  "type": "Feature",
  "properties": {
    "addr:full":"Havnebryggen 5 Svaneke Danmark 3740",
    "addr:housenumber":"5",
    "addr:postcode":"3740",
    "addr:street":"Havnebryggen",
    "iso:country":"DK",
    "sg:address":"Havnebryggen 5",
    "sg:city":"Svaneke",
    "sg:orig_category":"HOTELS: OG MOTELLER",
    "sg:phone":"+45 56 49 60 20",
    "sg:postcode":"3740",
    "sg:province":"Danmark",
    "wof:name":"\u00d8sters\u00f8en, Hotel",
    "wof:placetype":"venue"
},
  "geometry": {"coordinates":[15.1437540054,55.1356887817],"type":"Point"}
}