{
  "type": "Feature",
  "properties": {
    "addr:full":"Fmd.: Susanne Hede Jensen, Hjelmensgade 12 \u00c5rhus C Danmark 8000",
    "addr:housenumber":"12",
    "addr:postcode":"8000",
    "addr:street":"Hjelmensgade",
    "iso:country":"DK",
    "sg:address":"Fmd.: Susanne Hede Jensen, Hjelmensgade 12",
    "sg:city":"\u00c5rhus C",
    "sg:orig_category":"Private skoler",
    "sg:phone":"+45 86 12 31 51",
    "sg:postcode":"8000",
    "sg:province":"Danmark",
    "sg:website":"www.laureal.dk",
    "wof:name":"Laursens Realskole",
    "wof:placetype":"venue"
},
  "geometry": {"coordinates":[13.5130796432,62.4200592041],"type":"Point"}
}