{
  "type": "Feature",
  "properties": {
    "iso:country":"DK",
    "sg:address":"B\u00f8ssemagervej 4",
    "sg:city":"Viborg",
    "sg:orig_category":"Skilte",
    "sg:phone":"+45 86 61 05 22",
    "sg:postcode":"8800",
    "sg:province":"Danmark",
    "wof:name":"Skilte-Centret",
    "wof:placetype":"venue"
},
  "geometry": {"coordinates":[9.4051742554,56.4684791565],"type":"Point"}
}