{
  "type": "Feature",
  "properties": {
    "iso:country":"DK",
    "sg:address":"Knullen 2, H\u00f8jby",
    "sg:city":"Odense S",
    "sg:orig_category":"Maskinfabrikker",
    "sg:phone":"+45 63 95 55 55",
    "sg:postcode":"5260",
    "sg:province":"Danmark",
    "sg:website":"www.texas.dk",
    "wof:name":"TEXAS Andreas Petersen A/S",
    "wof:placetype":"venue"
},
  "geometry": {"coordinates":[10.3157806396,55.3122825623],"type":"Point"}
}