{
  "type": "Feature",
  "properties": {
    "addr:full":"Dr\u00e5by S\u00f8vej 2 A Ebeltoft Danmark 8400",
    "addr:housenumber":"2 a",
    "addr:postcode":"8400",
    "addr:street":"Sovej",
    "iso:country":"DK",
    "sg:address":"Dr\u00e5by S\u00f8vej 2 A",
    "sg:city":"Ebeltoft",
    "sg:orig_category":"Kirker",
    "sg:postcode":"8400",
    "sg:province":"Danmark",
    "wof:name":"Dr\u00e5by Kirke",
    "wof:placetype":"venue"
},
  "geometry": {"coordinates":[10.70358181,56.223072052],"type":"Point"}
}