{
  "type": "Feature",
  "properties": {
    "addr:full":"Londongade 1 Odense C Danmark 5000",
    "addr:housenumber":"1",
    "addr:postcode":"5000",
    "addr:street":"Londongade",
    "iso:country":"DK",
    "sg:address":"Londongade 1",
    "sg:city":"Odense C",
    "sg:orig_category":"Havne",
    "sg:phone":"+45 66 12 07 92",
    "sg:postcode":"5000",
    "sg:province":"Danmark",
    "wof:name":"Odense Havn",
    "wof:placetype":"venue"
},
  "geometry": {"coordinates":[10.3838014603,55.4064102173],"type":"Point"}
}