{
  "type": "Feature",
  "properties": {
    "addr:full":"Vodroffsvej 11 Frederiksberg Danmark 1900",
    "addr:housenumber":"11",
    "addr:postcode":"1900",
    "addr:street":"Vodroffsvej",
    "iso:country":"DK",
    "sg:address":"Vodroffsvej 11",
    "sg:city":"Frederiksberg",
    "sg:orig_category":"Arkitekter",
    "sg:phone":"+45 33 24 07 65",
    "sg:postcode":"1900",
    "sg:province":"Danmark",
    "wof:name":"Sauer, Nis",
    "wof:placetype":"venue"
},
  "geometry": {"coordinates":[12.554523468,55.674747467],"type":"Point"}
}