{
  "type": "Feature",
  "properties": {
    "addr:full":"Gammel Bagsv\u00e6rdvej 34 Kongens Lyngby Danmark 2800",
    "addr:housenumber":"34",
    "addr:postcode":"2800",
    "addr:street":"Gammel Bagsvaerdvej",
    "iso:country":"DK",
    "sg:address":"Gammel Bagsv\u00e6rdvej 34",
    "sg:city":"Kongens Lyngby",
    "sg:orig_category":"Skolefritidsordninger",
    "sg:phone":"+45 45 87 86 04",
    "sg:postcode":"2800",
    "sg:province":"Danmark",
    "wof:name":"Engelsborgskolens Skolefritidsordning",
    "wof:placetype":"venue"
},
  "geometry": {"coordinates":[12.4913167953,55.7675209045],"type":"Point"}
}