{
  "type": "Feature",
  "properties": {
    "addr:full":"Tr\u00e6lundvej 1 Herning Danmark 7400",
    "addr:housenumber":"1",
    "addr:postcode":"7400",
    "addr:street":"Traelundvej",
    "iso:country":"DK",
    "sg:address":"Tr\u00e6lundvej 1",
    "sg:city":"Herning",
    "sg:orig_category":"Integrerede institutioner",
    "sg:phone":"+45 97 21 50 88",
    "sg:postcode":"7400",
    "sg:province":"Danmark",
    "wof:name":"Daginstitutionen Meldg\u00e5rd",
    "wof:placetype":"venue"
},
  "geometry": {"coordinates":[8.9713850021,56.1678314209],"type":"Point"}
}