{
  "type": "Feature",
  "properties": {
    "addr:full":"Lunden 10  Agedrup Danmark 5320",
    "addr:housenumber":"10",
    "addr:postcode":"5320",
    "addr:street":"Lunden",
    "iso:country":"DK",
    "sg:address":"Lunden 10 ",
    "sg:city":"Agedrup",
    "sg:classifiers":[
        {
            "category":"Wholesale",
            "subcategory":"Machinery & Supplies",
            "type":"Manufacturing & Wholesale Goods"
        }
    ],
    "sg:phone":"+45 66 10 92 00",
    "sg:postcode":"5320",
    "sg:province":"Danmark",
    "sg:tags":[
        "-",
        "agriculture",
        "equipment"
    ],
    "wof:name":"MASKINHANDLER SC, SVEND CARLSEN, \u00c5SUM A/S",
    "wof:placetype":"venue"
},
  "geometry": {"coordinates":[10.4672412872,55.417514801],"type":"Point"}
}