{
  "type": "Feature",
  "properties": {
    "addr:full":"N\u00f8rregade 81, st. Esbjerg Danmark 6700",
    "addr:housenumber":"81",
    "addr:postcode":"6700",
    "addr:street":"Norregade;St.",
    "iso:country":"DK",
    "sg:address":"N\u00f8rregade 81, st.",
    "sg:city":"Esbjerg",
    "sg:orig_category":"Ejendomsadministration",
    "sg:phone":"+45 75 13 26 13",
    "sg:postcode":"6700",
    "sg:province":"Danmark",
    "wof:name":"Myrup, Aase",
    "wof:placetype":"venue"
},
  "geometry": {"coordinates":[8.456905365,55.465221405],"type":"Point"}
}