{
  "type": "Feature",
  "properties": {
    "iso:country":"DK",
    "sg:address":"Bakkeg\u00e5rdsvej 1, Vivild",
    "sg:city":"Alling\u00e5bro",
    "sg:orig_category":"Hestepensioner",
    "sg:phone":"+45 86 48 69 19",
    "sg:postcode":"8961",
    "sg:province":"Danmark",
    "wof:name":"Vivild Ridecenter",
    "wof:placetype":"venue"
},
  "geometry": {"coordinates":[10.3230552673,56.4639511108],"type":"Point"}
}