{
  "type": "Feature",
  "properties": {
    "addr:full":"Svaleg\u00e5rdsvej 43 B Aalborg Danmark 9000",
    "addr:housenumber":"43 b",
    "addr:postcode":"9000",
    "addr:street":"Svalegaardsvej",
    "iso:country":"DK",
    "sg:address":"Svaleg\u00e5rdsvej 43 B",
    "sg:city":"Aalborg",
    "sg:orig_category":"Psykologer, praktiserende",
    "sg:phone":"+45 98 18 71 00",
    "sg:postcode":"9000",
    "sg:province":"Danmark",
    "wof:name":"Rasmussen, Ida",
    "wof:placetype":"venue"
},
  "geometry": {"coordinates":[9.8761196136,57.040019989],"type":"Point"}
}