{
  "type": "Feature",
  "properties": {
    "addr:full":"Odensevej 100, Herrested \u00d8rb\u00e6k Danmark 5853",
    "addr:housenumber":"100",
    "addr:postcode":"5853",
    "addr:street":"Odensevej",
    "iso:country":"DK",
    "sg:address":"Odensevej 100, Herrested",
    "sg:city":"\u00d8rb\u00e6k",
    "sg:orig_category":"Forsamlingshuse",
    "sg:phone":"+45 65 98 10 93",
    "sg:postcode":"5853",
    "sg:province":"Danmark",
    "wof:name":"Herrested Forsamlingshus",
    "wof:placetype":"venue"
},
  "geometry": {"coordinates":[10.6713848114,55.2553749084],"type":"Point"}
}