{
  "type": "Feature",
  "properties": {
    "addr:full":"Nyropsgade 25 K\u00f8benhavn Danmark 1602",
    "addr:housenumber":"25;1602",
    "addr:street":"Nyropsgade",
    "iso:country":"DK",
    "sg:address":"Nyropsgade 25",
    "sg:city":"K\u00f8benhavn",
    "sg:orig_category":"Fagforbund og -foreninger",
    "sg:phone":"+45 33 68 28 26",
    "sg:postcode":"1602",
    "sg:province":"Danmark",
    "wof:name":"K\u00d8BENHAVN, afd. 13, METAL",
    "wof:placetype":"venue"
},
  "geometry": {"coordinates":[12.5633001328,55.6786003113],"type":"Point"}
}