{
  "type": "Feature",
  "properties": {
    "addr:full":"Vestensborg All\u00e8 28 Nyk\u00f8bing Danmark 4800",
    "addr:housenumber":"28",
    "addr:postcode":"4800",
    "addr:street":"Vestensborg Alle\u0300",
    "iso:country":"DK",
    "sg:address":"Vestensborg All\u00e8 28",
    "sg:city":"Nyk\u00f8bing",
    "sg:orig_category":"Erhvervs- og brancheforeninger",
    "sg:phone":"+45 54 85 19 77",
    "sg:postcode":"4800",
    "sg:province":"Danmark",
    "wof:name":"Forenede Danske Motorejere",
    "wof:placetype":"venue"
},
  "geometry": {"coordinates":[-114.0768203735,46.4432411194],"type":"Point"}
}