{
  "type": "Feature",
  "properties": {
    "iso:country":"DK",
    "sg:address":"Jernbanegade 33",
    "sg:city":"Hirtshals",
    "sg:orig_category":"Boligselskaber",
    "sg:phone":"+45 98 94 18 56",
    "sg:postcode":"9850",
    "sg:province":"Danmark",
    "wof:name":"Hirtshals Boligforening",
    "wof:placetype":"venue"
},
  "geometry": {"coordinates":[9.9618940353,57.590637207],"type":"Point"}
}