{
  "type": "Feature",
  "properties": {
    "addr:full":"S\u00f8nder Tranders Vej 24 Aalborg S\u00d8 Danmark 9210",
    "addr:housenumber":"24",
    "addr:postcode":"9210",
    "addr:street":"Sonder Tranders Vej",
    "iso:country":"DK",
    "sg:address":"S\u00f8nder Tranders Vej 24",
    "sg:city":"Aalborg S\u00d8",
    "sg:orig_category":"Undervognsbehandling",
    "sg:phone":"+45 98 14 30 03",
    "sg:postcode":"9210",
    "sg:province":"Danmark",
    "wof:name":"Gug Anti - Rustcenter",
    "wof:placetype":"venue"
},
  "geometry": {"coordinates":[9.9313783646,57.0044555664],"type":"Point"}
}