{
  "type": "Feature",
  "properties": {
    "iso:country":"DK",
    "sg:address":"Dyrehavsbakken 41",
    "sg:city":"Klampenborg",
    "sg:classifiers":[
        {
            "category":"Restaurant",
            "type":"Food & Drink"
        }
    ],
    "sg:phone":"+45 39 64 31 64",
    "sg:postcode":"2930",
    "sg:province":"Danmark",
    "wof:name":"Bakkens Perle",
    "wof:placetype":"venue"
},
  "geometry": {"coordinates":[12.5786800385,55.7748908997],"type":"Point"}
}