{
  "type": "Feature",
  "properties": {
    "addr:full":"Kamhusene 22 Valby Danmark 2500",
    "addr:housenumber":"22",
    "addr:postcode":"2500",
    "addr:street":"Kamhusene",
    "iso:country":"DK",
    "sg:address":"Kamhusene 22",
    "sg:city":"Valby",
    "sg:orig_category":"Boligselskaber",
    "sg:phone":"+45 36 30 75 76",
    "sg:postcode":"2500",
    "sg:province":"Danmark",
    "wof:name":"Lejerbo, Boligselskabet Kamhusene",
    "wof:placetype":"venue"
},
  "geometry": {"coordinates":[12.4799728394,55.6632766724],"type":"Point"}
}