{
  "type": "Feature",
  "properties": {
    "addr:full":"Bredgade 25 Aarup Danmark 5560",
    "addr:housenumber":"25",
    "addr:postcode":"5560",
    "addr:street":"Bredgade",
    "iso:country":"DK",
    "sg:address":"Bredgade 25",
    "sg:city":"Aarup",
    "sg:orig_category":"Apoteker og -udsalg",
    "sg:phone":"+45 64 43 10 27",
    "sg:postcode":"5560",
    "sg:province":"Danmark",
    "wof:name":"Aarup Apotek",
    "wof:placetype":"venue"
},
  "geometry": {"coordinates":[10.0496921539,55.3812637329],"type":"Point"}
}