{
  "type": "Feature",
  "properties": {
    "iso:country":"DK",
    "sg:address":"Kulsviervej 76",
    "sg:city":"Kongens Lyngby",
    "sg:orig_category":"Blomsterhandlere",
    "sg:phone":"+45 45 87 93 14",
    "sg:postcode":"2800",
    "sg:province":"Danmark",
    "wof:name":"Eriks Blomster",
    "wof:placetype":"venue"
},
  "geometry": {"coordinates":[12.5128946304,55.7933082581],"type":"Point"}
}