{
  "type": "Feature",
  "properties": {
    "addr:full":"Vestre Ringvej 11 Bjerringbro Danmark 8850",
    "addr:housenumber":"11",
    "addr:postcode":"8850",
    "addr:street":"Vestre Ringvej",
    "iso:country":"DK",
    "sg:address":"Vestre Ringvej 11",
    "sg:city":"Bjerringbro",
    "sg:orig_category":"Musikskoler, Kommunale",
    "sg:phone":"+45 86 68 33 33",
    "sg:postcode":"8850",
    "sg:province":"Danmark",
    "wof:name":"Den F\u00e6lleskommunale Musikskole for Bjerringbro, Hvorslev og Kjellerup kommuner",
    "wof:placetype":"venue"
},
  "geometry": {"coordinates":[9.6389789581,56.3767166138],"type":"Point"}
}