{
  "type": "Feature",
  "properties": {
    "addr:full":"Dyndetvej 9 Borup Danmark 4140",
    "addr:housenumber":"9",
    "addr:postcode":"4140",
    "addr:street":"Dyndetvej",
    "iso:country":"DK",
    "sg:address":"Dyndetvej 9",
    "sg:city":"Borup",
    "sg:orig_category":"Boligudlejning",
    "sg:phone":"+45 57 52 21 80",
    "sg:postcode":"4140",
    "sg:province":"Danmark",
    "wof:name":"Borup Boligudlejning",
    "wof:placetype":"venue"
},
  "geometry": {"coordinates":[11.9532766342,55.4754829407],"type":"Point"}
}