{
  "type": "Feature",
  "properties": {
    "addr:full":"Kirkeb\u00e6kvej 136 Viborg Danmark 8800",
    "addr:housenumber":"136",
    "addr:postcode":"8800",
    "addr:street":"Kirkebaekvej",
    "iso:country":"DK",
    "sg:address":"Kirkeb\u00e6kvej 136",
    "sg:city":"Viborg",
    "sg:orig_category":"Genbrugspladser",
    "sg:phone":"+45 86 61 39 55",
    "sg:postcode":"8800",
    "sg:province":"Danmark",
    "sg:website":"www.revas.dk",
    "wof:name":"Revas, I/S",
    "wof:placetype":"venue"
},
  "geometry": {"coordinates":[9.3593845367,56.4750518799],"type":"Point"}
}