{
  "type": "Feature",
  "properties": {
    "addr:full":"S\u00f8ndergade 26 Hinnerup Danmark 8382",
    "addr:housenumber":"26",
    "addr:postcode":"8382",
    "addr:street":"Sondergade",
    "iso:country":"DK",
    "sg:address":"S\u00f8ndergade 26",
    "sg:city":"Hinnerup",
    "sg:orig_category":"Lokalarkiver",
    "sg:phone":"+45 86 98 54 44",
    "sg:postcode":"8382",
    "sg:province":"Danmark",
    "wof:name":"Hinnerup Egnsarkiv (Brog\u00e5rden)",
    "wof:placetype":"venue"
},
  "geometry": {"coordinates":[10.0594186783,56.2612991333],"type":"Point"}
}