{
  "type": "Feature",
  "properties": {
    "addr:full":"Bygaden 25, N\u00f8rhalne Vadum Danmark 9430",
    "addr:housenumber":"25",
    "addr:postcode":"9430",
    "addr:street":"Bygaden",
    "iso:country":"DK",
    "sg:address":"Bygaden 25, N\u00f8rhalne",
    "sg:city":"Vadum",
    "sg:orig_category":"Forsamlingshuse",
    "sg:phone":"+45 98 26 87 96",
    "sg:postcode":"9430",
    "sg:province":"Danmark",
    "wof:name":"N\u00f8rhalne Forsamlingshus",
    "wof:placetype":"venue"
},
  "geometry": {"coordinates":[9.8614330292,57.1187477112],"type":"Point"}
}