{
  "type": "Feature",
  "properties": {
    "addr:full":"Gladsaxe M\u00f8llevej 93 S\u00f8borg Danmark 2860",
    "addr:housenumber":"93",
    "addr:postcode":"2860",
    "addr:street":"Mollevej",
    "iso:country":"DK",
    "sg:address":"Gladsaxe M\u00f8llevej 93",
    "sg:city":"S\u00f8borg",
    "sg:orig_category":"Alternativ behandling",
    "sg:phone":"+45 39 56 01 43",
    "sg:postcode":"2860",
    "sg:province":"Danmark",
    "wof:name":"Kate Matalon",
    "wof:placetype":"venue"
},
  "geometry": {"coordinates":[12.4719963074,55.7422676086],"type":"Point"}
}