{
  "type": "Feature",
  "properties": {
    "iso:country":"DK",
    "sg:address":"Gr\u00f8nsgade 1",
    "sg:city":"Holstebro",
    "sg:orig_category":"Advokater",
    "sg:phone":"+45 97 41 21 00",
    "sg:postcode":"7500",
    "sg:province":"Danmark",
    "wof:name":"Laursen, Tom Uldall Hansen & Ib Ren\u00e9",
    "wof:placetype":"venue"
},
  "geometry": {"coordinates":[8.6259326935,56.3564605713],"type":"Point"}
}