{
  "type": "Feature",
  "properties": {
    "addr:full":"Liv\u00f8vej 13  Viborg Danmark 8800",
    "addr:housenumber":"13",
    "addr:postcode":"8800",
    "addr:street":"Livovej",
    "iso:country":"DK",
    "sg:address":"Liv\u00f8vej 13 ",
    "sg:city":"Viborg",
    "sg:classifiers":[
        {
            "category":"Home & Garden",
            "subcategory":"Home Furnishings",
            "type":"Retail Goods"
        }
    ],
    "sg:phone":"+45 86 62 72 00",
    "sg:postcode":"8800",
    "sg:province":"Danmark",
    "sg:tags":[
        "household"
    ],
    "wof:name":"SELTA M\u00d8BLER VIBORG A/S",
    "wof:placetype":"venue"
},
  "geometry": {"coordinates":[9.3652868271,56.4487075806],"type":"Point"}
}