{
  "type": "Feature",
  "properties": {
    "addr:full":"Algade 42 Roskilde Danmark 4000",
    "addr:housenumber":"42",
    "addr:postcode":"4000",
    "addr:street":"Algade",
    "iso:country":"DK",
    "sg:address":"Algade 42",
    "sg:city":"Roskilde",
    "sg:orig_category":"Sko",
    "sg:phone":"+45 46 32 57 41",
    "sg:postcode":"4000",
    "sg:province":"Danmark",
    "wof:name":"Bianco Footwear",
    "wof:placetype":"venue"
},
  "geometry": {"coordinates":[12.087138176,55.6407623291],"type":"Point"}
}