{
  "type": "Feature",
  "properties": {
    "addr:full":"S\u00f8markevej 2, Magleby Borre Danmark 4791",
    "addr:housenumber":"2",
    "addr:postcode":"4791",
    "addr:street":"Somarkevej",
    "iso:country":"DK",
    "sg:address":"S\u00f8markevej 2, Magleby",
    "sg:city":"Borre",
    "sg:orig_category":"Keramik",
    "sg:phone":"+45 55 81 20 61",
    "sg:postcode":"4791",
    "sg:province":"Danmark",
    "wof:name":"Bodil Keramik",
    "wof:placetype":"venue"
},
  "geometry": {"coordinates":[12.4392347336,54.9952545166],"type":"Point"}
}