{
  "type": "Feature",
  "properties": {
    "iso:country":"DK",
    "sg:address":"Lotte Laursen, R\u00e5gelejevej 37",
    "sg:city":"Vejby",
    "sg:orig_category":"Campingpladser",
    "sg:phone":"+45 48 70 67 88",
    "sg:postcode":"3210",
    "sg:province":"Danmark",
    "wof:name":"Vejby Strand Camping",
    "wof:placetype":"venue"
},
  "geometry": {"coordinates":[12.1534852982,56.0930938721],"type":"Point"}
}