{
  "type": "Feature",
  "properties": {
    "addr:full":"Fmd.: Morten E. J\u00f8rgensen, Bredgade 54 A, Bred Vissenbjerg Danmark 5492",
    "addr:housenumber":"54 a",
    "addr:postcode":"5492",
    "addr:street":"Morten;Bredgade;Bred",
    "iso:country":"DK",
    "sg:address":"Fmd.: Morten E. J\u00f8rgensen, Bredgade 54 A, Bred",
    "sg:city":"Vissenbjerg",
    "sg:orig_category":"Kulturelle foreninger",
    "sg:phone":"+45 64 47 28 94",
    "sg:postcode":"5492",
    "sg:province":"Danmark",
    "wof:name":"Vissenbjerg Sogn's R\u00f8verband",
    "wof:placetype":"venue"
},
  "geometry": {"coordinates":[10.1324472427,55.386051178],"type":"Point"}
}