{
  "type": "Feature",
  "properties": {
    "addr:full":"Englandsvej 3 Hammel Danmark 8450",
    "addr:housenumber":"3",
    "addr:postcode":"8450",
    "addr:street":"Englandsvej",
    "iso:country":"DK",
    "sg:address":"Englandsvej 3",
    "sg:city":"Hammel",
    "sg:orig_category":"Karrosserifabrikker",
    "sg:phone":"+45 86 96 96 44",
    "sg:postcode":"8450",
    "sg:province":"Danmark",
    "wof:name":"Voka Industri A/S",
    "wof:placetype":"venue"
},
  "geometry": {"coordinates":[9.8576107025,56.2365760803],"type":"Point"}
}