{
  "type": "Feature",
  "properties": {
    "addr:full":"T\u00f8strupvej 36, Aadum Tarm Danmark 6880",
    "addr:housenumber":"36",
    "addr:postcode":"6880",
    "addr:street":"Tostrupvej;Aadum",
    "iso:country":"DK",
    "sg:address":"T\u00f8strupvej 36, Aadum",
    "sg:city":"Tarm",
    "sg:orig_category":"Autoophug",
    "sg:phone":"+45 97 37 61 66",
    "sg:postcode":"6880",
    "sg:province":"Danmark",
    "wof:name":"Aadum Autoophug A/S",
    "wof:placetype":"venue"
},
  "geometry": {"coordinates":[8.5200052261,55.9060554504],"type":"Point"}
}