{
  "type": "Feature",
  "properties": {
    "iso:country":"DK",
    "sg:address":"Algade 41 - 51, 2.",
    "sg:city":"Aalborg",
    "sg:classifiers":[
        {
            "category":"Banks & Credit Unions",
            "subcategory":"Bank",
            "type":"Services"
        }
    ],
    "sg:phone":"+45 99 33 21 00",
    "sg:postcode":"9000",
    "sg:province":"Danmark",
    "sg:tags":[
        "banker"
    ],
    "wof:name":"Nordea Erhvervs afdeling",
    "wof:placetype":"venue"
},
  "geometry": {"coordinates":[9.91629,57.049355],"type":"Point"}
}