{
  "type": "Feature",
  "properties": {
    "addr:full":"Torvegade 18 Fakse Danmark 4640",
    "addr:housenumber":"18",
    "addr:postcode":"4640",
    "addr:street":"Torvegade",
    "iso:country":"DK",
    "sg:address":"Torvegade 18",
    "sg:city":"Fakse",
    "sg:orig_category":"Materialister",
    "sg:phone":"+45 56 71 48 26",
    "sg:postcode":"4640",
    "sg:province":"Danmark",
    "wof:name":"Matas - Materialisten",
    "wof:placetype":"venue"
},
  "geometry": {"coordinates":[12.1199102402,55.2580490112],"type":"Point"}
}