{
  "type": "Feature",
  "properties": {
    "addr:full":"Vestergade 13 Ranum Danmark 9681",
    "addr:housenumber":"13",
    "addr:postcode":"9681",
    "addr:street":"Vestergade",
    "iso:country":"DK",
    "sg:address":"Vestergade 13",
    "sg:city":"Ranum",
    "sg:classifiers":[
        {
            "category":"Restaurant",
            "type":"Food & Drink"
        }
    ],
    "sg:phone":"+45 98 67 61 16",
    "sg:postcode":"9681",
    "sg:province":"Danmark",
    "wof:name":"Postkassen, Restaurant",
    "wof:placetype":"venue"
},
  "geometry": {"coordinates":[9.2297458649,56.8992958069],"type":"Point"}
}