{
  "type": "Feature",
  "properties": {
    "addr:full":"Jyllandsgade 10, 1. Herning Danmark 7400",
    "addr:housenumber":"10 1",
    "addr:postcode":"7400",
    "addr:street":"Jyllandsgade",
    "iso:country":"DK",
    "sg:address":"Jyllandsgade 10, 1.",
    "sg:city":"Herning",
    "sg:orig_category":"Fodplejere",
    "sg:phone":"+45 97 22 29 64",
    "sg:postcode":"7400",
    "sg:province":"Danmark",
    "wof:name":"Madsen Fodpleje & Zoneterapi, Birthe",
    "wof:placetype":"venue"
},
  "geometry": {"coordinates":[8.9690847397,56.1350784302],"type":"Point"}
}