{
  "type": "Feature",
  "properties": {
    "iso:country":"DK",
    "sg:address":"Sj\u00e6llandsvej 4",
    "sg:city":"Kongens Lyngby",
    "sg:orig_category":"Ejendomshandel",
    "sg:phone":"+45 45 87 83 80",
    "sg:postcode":"2800",
    "sg:province":"Danmark",
    "wof:name":"Cronstad, N.",
    "wof:placetype":"venue"
},
  "geometry": {"coordinates":[12.5091333389,55.7972602844],"type":"Point"}
}