{
  "type": "Feature",
  "properties": {
    "addr:full":"Frederiksborggade 42 K\u00f8benhavn Danmark 1360",
    "addr:housenumber":"42;1360",
    "addr:street":"Frederiksborggade",
    "iso:country":"DK",
    "sg:address":"Frederiksborggade 42",
    "sg:city":"K\u00f8benhavn",
    "sg:orig_category":"Elektronik",
    "sg:phone":"+45 33 11 15 70",
    "sg:postcode":"1360",
    "sg:province":"Danmark",
    "sg:website":"www.brinck.dk",
    "wof:name":"Brinck Elektronik og Handel ApS",
    "wof:placetype":"venue"
},
  "geometry": {"coordinates":[12.5662698746,55.6857414246],"type":"Point"}
}