{
  "type": "Feature",
  "properties": {
    "addr:full":"Fmd.: John Schmidt, Led\u00f8jevej 30 Albertslund Danmark 2620",
    "addr:housenumber":"30",
    "addr:postcode":"2620",
    "addr:street":"Ledojevej",
    "iso:country":"DK",
    "sg:address":"Fmd.: John Schmidt, Led\u00f8jevej 30",
    "sg:city":"Albertslund",
    "sg:orig_category":"Grundejerforeninger",
    "sg:phone":"+45 43 62 27 50",
    "sg:postcode":"2620",
    "sg:province":"Danmark",
    "sg:website":"www.risby.dk",
    "wof:name":"Risby Grundejerforening",
    "wof:placetype":"venue"
},
  "geometry": {"coordinates":[12.3517179489,55.6568450928],"type":"Point"}
}