{
  "type": "Feature",
  "properties": {
    "addr:full":"Hersegade 5 Roskilde Danmark 4000",
    "addr:housenumber":"5",
    "addr:postcode":"4000",
    "addr:street":"Hersegade",
    "iso:country":"DK",
    "sg:address":"Hersegade 5",
    "sg:city":"Roskilde",
    "sg:orig_category":"\u00c3\u02dcvrige institutioner",
    "sg:phone":"+45 46 36 93 38",
    "sg:postcode":"4000",
    "sg:province":"Danmark",
    "wof:name":"St\u00f8ttecentret for fysisk/ psykisk udviklingsh\u00e6mmede",
    "wof:placetype":"venue"
},
  "geometry": {"coordinates":[12.0847873688,55.6400108337],"type":"Point"}
}