{
  "type": "Feature",
  "properties": {
    "addr:full":"S\u00f8ndersti 3 Stege Danmark 4780",
    "addr:housenumber":"3",
    "addr:postcode":"4780",
    "addr:street":"Sondersti",
    "iso:country":"DK",
    "sg:address":"S\u00f8ndersti 3",
    "sg:city":"Stege",
    "sg:orig_category":"Diskoteker",
    "sg:phone":"+45 55 81 81 32",
    "sg:postcode":"4780",
    "sg:province":"Danmark",
    "wof:name":"Diskotek Pakhuset",
    "wof:placetype":"venue"
},
  "geometry": {"coordinates":[12.2850761414,54.9830322266],"type":"Point"}
}