{
  "type": "Feature",
  "properties": {
    "iso:country":"DK",
    "sg:address":"Gildemester: Emilie Beck-Lauritzen, Voldgade 47, 2.tv.",
    "sg:city":"Struer",
    "sg:orig_category":"Loger",
    "sg:phone":"+45 97 84 03 96",
    "sg:postcode":"7600",
    "sg:province":"Danmark",
    "wof:name":"1. Sct. Georgs Gilde, Struer",
    "wof:placetype":"venue"
},
  "geometry": {"coordinates":[8.5946903229,56.491191864],"type":"Point"}
}