{
  "type": "Feature",
  "properties": {
    "iso:country":"DK",
    "sg:address":"Kirkebakkevej 28",
    "sg:city":"Munke Bjergby",
    "sg:classifiers":[
        {
            "category":"Banks & Credit Unions",
            "subcategory":"Bank",
            "type":"Services"
        }
    ],
    "sg:phone":"+45 57 89 29 71",
    "sg:postcode":"4190",
    "sg:province":"Danmark",
    "sg:tags":[
        "banker"
    ],
    "wof:name":"Slagelse Sparekasse",
    "wof:placetype":"venue"
},
  "geometry": {"coordinates":[11.5210027695,55.505821228],"type":"Point"}
}