{
  "type": "Feature",
  "properties": {
    "addr:full":"Ravmarken 2 Strandby Danmark 9970",
    "addr:housenumber":"2",
    "addr:postcode":"9970",
    "addr:street":"Ravmarken",
    "iso:country":"DK",
    "sg:address":"Ravmarken 2",
    "sg:city":"Strandby",
    "sg:orig_category":"Bogtrykkerier",
    "sg:phone":"+45 98 48 16 00",
    "sg:postcode":"9970",
    "sg:province":"Danmark",
    "wof:name":"Nordjysk Formulartryk A/S",
    "wof:placetype":"venue"
},
  "geometry": {"coordinates":[10.4856624603,57.4867630005],"type":"Point"}
}