{
  "type": "Feature",
  "properties": {
    "addr:full":"Skoleholmen 9 Greve Danmark 2670",
    "addr:housenumber":"9",
    "addr:postcode":"2670",
    "addr:street":"Skoleholmen",
    "iso:country":"DK",
    "sg:address":"Skoleholmen 9",
    "sg:city":"Greve",
    "sg:orig_category":"Kirkesogne",
    "sg:phone":"+45 43 90 68 91",
    "sg:postcode":"2670",
    "sg:province":"Danmark",
    "wof:name":"Greve Kirkes og Johanneskirkens Kordegenekontor",
    "wof:placetype":"venue"
},
  "geometry": {"coordinates":[12.2982416153,55.5817108154],"type":"Point"}
}