{
  "type": "Feature",
  "properties": {
    "addr:full":"J. E. Ohlsens Gade 7 K\u00f8benhavn \u00d8 Danmark 2100",
    "addr:housenumber":"7",
    "addr:postcode":"2100",
    "addr:street":"J.;Ohlsens Gade;O",
    "iso:country":"DK",
    "sg:address":"J. E. Ohlsens Gade 7",
    "sg:city":"K\u00f8benhavn \u00d8",
    "sg:orig_category":"Revisorer",
    "sg:phone":"+45 35 42 46 99",
    "sg:postcode":"2100",
    "sg:province":"Danmark",
    "wof:name":"Perch, Nils M\u00f8ller",
    "wof:placetype":"venue"
},
  "geometry": {"coordinates":[99.92501068120001,34.2430114746],"type":"Point"}
}