{
  "type": "Feature",
  "properties": {
    "addr:full":"Mejlbyvej 682, Mejlby Hjortsh\u00f8j Danmark 8530",
    "addr:housenumber":"682",
    "addr:postcode":"8530",
    "addr:street":"Mejlbyvej;Mejlby Hjortshoj Danmark",
    "iso:country":"DK",
    "sg:address":"Mejlbyvej 682, Mejlby",
    "sg:city":"Hjortsh\u00f8j",
    "sg:orig_category":"Kirker",
    "sg:postcode":"8530",
    "sg:province":"Danmark",
    "wof:name":"Mejlby Kirke",
    "wof:placetype":"venue"
},
  "geometry": {"coordinates":[10.1459388733,56.2984962463],"type":"Point"}
}