{
  "type": "Feature",
  "properties": {
    "addr:full":"Galgebakken S\u00f8nder 9-2 A Albertslund Danmark 2620",
    "addr:housenumber":"9-2 a",
    "addr:postcode":"2620",
    "addr:street":"Galgebakken Sonder",
    "iso:country":"DK",
    "sg:address":"Galgebakken S\u00f8nder 9-2 A",
    "sg:city":"Albertslund",
    "sg:orig_category":"Psykologer, praktiserende",
    "sg:phone":"+45 43 62 16 67",
    "sg:postcode":"2620",
    "sg:province":"Danmark",
    "wof:name":"Andersen, Kirsten Thordal",
    "wof:placetype":"venue"
},
  "geometry": {"coordinates":[12.3499403,55.6761474609],"type":"Point"}
}