{
  "type": "Feature",
  "properties": {
    "iso:country":"DK",
    "sg:address":"Byst\u00e6vnet 1",
    "sg:city":"Lystrup",
    "sg:orig_category":"Kiosker",
    "sg:phone":"+45 86 22 14 05",
    "sg:postcode":"8520",
    "sg:province":"Danmark",
    "wof:name":"Kiosken Handelscentret",
    "wof:placetype":"venue"
},
  "geometry": {"coordinates":[10.2296104431,56.2340431213],"type":"Point"}
}