{
  "type": "Feature",
  "properties": {
    "addr:full":"Esbern Snaresvej 55 Kalundborg Danmark 4400",
    "addr:housenumber":"55",
    "addr:postcode":"4400",
    "addr:street":"Esbern Snaresvej",
    "iso:country":"DK",
    "sg:address":"Esbern Snaresvej 55",
    "sg:city":"Kalundborg",
    "sg:orig_category":"Dagcentre",
    "sg:phone":"+45 59 51 68 00",
    "sg:postcode":"4400",
    "sg:province":"Danmark",
    "wof:name":"Kalundborg Kommunes Dagcenter",
    "wof:placetype":"venue"
},
  "geometry": {"coordinates":[11.0814247131,55.6855201721],"type":"Point"}
}