{
  "type": "Feature",
  "properties": {
    "addr:full":"Blangstedg\u00e5rdsvej 27 Odense S\u00d8 Danmark 5220",
    "addr:housenumber":"27",
    "addr:postcode":"5220",
    "addr:street":"Blangstedgaardsvej",
    "iso:country":"DK",
    "sg:address":"Blangstedg\u00e5rdsvej 27",
    "sg:city":"Odense S\u00d8",
    "sg:orig_category":"Malermestre",
    "sg:phone":"+45 66 15 53 00",
    "sg:postcode":"5220",
    "sg:province":"Danmark",
    "wof:name":"Christensen Odense A/S, Boris",
    "wof:placetype":"venue"
},
  "geometry": {"coordinates":[10.4403162003,55.3858833313],"type":"Point"}
}