{
  "type": "Feature",
  "properties": {
    "addr:full":"Industrivej 3 Vejle \u00d8 Danmark 7120",
    "addr:housenumber":"3",
    "addr:postcode":"7120",
    "addr:street":"Industrivej",
    "iso:country":"DK",
    "sg:address":"Industrivej 3",
    "sg:city":"Vejle \u00d8",
    "sg:orig_category":"Etiketter",
    "sg:phone":"+45 75 81 43 11",
    "sg:postcode":"7120",
    "sg:province":"Danmark",
    "wof:name":"Dan Labels A/S",
    "wof:placetype":"venue"
},
  "geometry": {"coordinates":[9.6020708084,55.7273292542],"type":"Point"}
}