{
  "type": "Feature",
  "properties": {
    "addr:full":"Kontaktpers.: Knud Reinhardt, Greve, Postboks 1215 Roskilde Danmark 4000",
    "addr:postcode":"1215;4000",
    "addr:street":"Knud Reinhardt;Postboks",
    "iso:country":"DK",
    "sg:address":"Kontaktpers.: Knud Reinhardt, Greve, Postboks 1215",
    "sg:city":"Roskilde",
    "sg:orig_category":"Antenneforeninger",
    "sg:phone":"+45 46 13 63 43",
    "sg:postcode":"4000",
    "sg:province":"Danmark",
    "sg:website":"www.kabelnet.dk",
    "wof:name":"Tune Kabelnet",
    "wof:placetype":"venue"
},
  "geometry": {"coordinates":[12.0909376144,55.6404838562],"type":"Point"}
}