{
  "type": "Feature",
  "properties": {
    "iso:country":"DK",
    "sg:address":"Alstrupvej 32, Vester Hjermitslev",
    "sg:city":"Br\u00f8nderslev",
    "sg:orig_category":"Landbrugsmaskiner",
    "sg:phone":"+45 98 88 70 29",
    "sg:postcode":"9700",
    "sg:province":"Danmark",
    "wof:name":"K. N. Maskinservice",
    "wof:placetype":"venue"
},
  "geometry": {"coordinates":[9.7584476471,57.2860298157],"type":"Point"}
}