{
  "type": "Feature",
  "properties": {
    "addr:full":"\u00d8stergade 12 Ejstrupholm Danmark 7361",
    "addr:housenumber":"12",
    "addr:postcode":"7361",
    "addr:street":"Ostergade",
    "iso:country":"DK",
    "sg:address":"\u00d8stergade 12",
    "sg:city":"Ejstrupholm",
    "sg:orig_category":"Revisorer",
    "sg:phone":"+45 76 87 11 00",
    "sg:postcode":"7361",
    "sg:province":"Danmark",
    "sg:website":"www.bdo.dk",
    "wof:name":"BDO ScanRevision",
    "wof:placetype":"venue"
},
  "geometry": {"coordinates":[9.2912454605,55.9836273193],"type":"Point"}
}