{
  "type": "Feature",
  "properties": {
    "addr:full":"Fmd.: Johannes Karlsen, Tonr\u00e5 37 Gedved Danmark 8751",
    "addr:housenumber":"37",
    "addr:postcode":"8751",
    "addr:street":"Tonraa",
    "iso:country":"DK",
    "sg:address":"Fmd.: Johannes Karlsen, Tonr\u00e5 37",
    "sg:city":"Gedved",
    "sg:orig_category":"Boligselskaber",
    "sg:phone":"+45 75 66 51 81",
    "sg:postcode":"8751",
    "sg:province":"Danmark",
    "wof:name":"Andelsboligforeningen Tonr\u00e5",
    "wof:placetype":"venue"
},
  "geometry": {"coordinates":[9.8441801071,55.9348068237],"type":"Point"}
}