{
  "type": "Feature",
  "properties": {
    "addr:full":"K\u00e6mpesvej 2 Frederikssund Danmark 3600",
    "addr:housenumber":"2",
    "addr:postcode":"3600",
    "addr:street":"Kaempesvej",
    "iso:country":"DK",
    "sg:address":"K\u00e6mpesvej 2",
    "sg:city":"Frederikssund",
    "sg:orig_category":"Malermestre",
    "sg:phone":"+45 47 31 47 10",
    "sg:postcode":"3600",
    "sg:province":"Danmark",
    "wof:name":"Frederiksen, John",
    "wof:placetype":"venue"
},
  "geometry": {"coordinates":[12.0783987045,55.8301811218],"type":"Point"}
}