{
  "type": "Feature",
  "properties": {
    "addr:full":"Buen 18 Frederiksberg Danmark 2000",
    "addr:housenumber":"18",
    "addr:postcode":"2000",
    "addr:street":"Buen",
    "iso:country":"DK",
    "sg:address":"Buen 18",
    "sg:city":"Frederiksberg",
    "sg:orig_category":"Psykologer, praktiserende",
    "sg:phone":"+45 38 71 50 31",
    "sg:postcode":"2000",
    "sg:province":"Danmark",
    "wof:name":"Kempf, Jan",
    "wof:placetype":"venue"
},
  "geometry": {"coordinates":[12.4977626801,55.6838722229],"type":"Point"}
}