{
  "type": "Feature",
  "properties": {
    "iso:country":"DK",
    "sg:address":"Amtsvejen 34, Filskov",
    "sg:city":"Grindsted",
    "sg:orig_category":"Kursussteder",
    "sg:phone":"+45 75 34 81 11",
    "sg:postcode":"7200",
    "sg:province":"Danmark",
    "sg:website":"www.filskovkro.dk",
    "wof:name":"Filskov Kro",
    "wof:placetype":"venue"
},
  "geometry": {"coordinates":[8.9288702011,55.7560272217],"type":"Point"}
}