{
  "type": "Feature",
  "properties": {
    "iso:country":"DK",
    "sg:address":"Gravsholtvej 92 ",
    "sg:city":"Vodskov",
    "sg:classifiers":[
        {
            "category":"Farming",
            "subcategory":"Livestock Farm",
            "type":"Manufacturing & Wholesale Goods"
        }
    ],
    "sg:phone":"+45 96 38 94 20",
    "sg:postcode":"9310",
    "sg:province":"Danmark",
    "sg:tags":[
        "agriculture"
    ],
    "wof:name":"AKV LANGHOLT AMBA",
    "wof:placetype":"venue"
},
  "geometry": {"coordinates":[10.0983667374,57.1290779114],"type":"Point"}
}