{
  "type": "Feature",
  "properties": {
    "addr:full":"Leder: Annelise Lassesen, Raskvej 5, Aale T\u00f8rring Danmark 7160",
    "addr:housenumber":"5",
    "addr:postcode":"7160",
    "addr:street":"Raskvej",
    "iso:country":"DK",
    "sg:address":"Leder: Annelise Lassesen, Raskvej 5, Aale",
    "sg:city":"T\u00f8rring",
    "sg:orig_category":"\u00c3\u02dcvrig fritidsundervisning",
    "sg:phone":"+45 75 67 60 54",
    "sg:postcode":"7160",
    "sg:province":"Danmark",
    "wof:name":"\u00c5le Aftenskole",
    "wof:placetype":"venue"
},
  "geometry": {"coordinates":[9.4808645248,55.8502807617],"type":"Point"}
}