{
  "type": "Feature",
  "properties": {
    "addr:full":"Sct. Mathias Gade 58 Viborg Danmark 8800",
    "addr:housenumber":"58",
    "addr:postcode":"8800",
    "addr:street":"Sct. Mathias Gade",
    "iso:country":"DK",
    "sg:address":"Sct. Mathias Gade 58",
    "sg:city":"Viborg",
    "sg:orig_category":"Farve og tapet",
    "sg:phone":"+45 86 62 03 61",
    "sg:postcode":"8800",
    "sg:province":"Danmark",
    "wof:name":"Thuesens Farvehandel",
    "wof:placetype":"venue"
},
  "geometry": {"coordinates":[9.4076423645,56.4492607117],"type":"Point"}
}