{
  "type": "Feature",
  "properties": {
    "iso:country":"DK",
    "sg:address":"Vesterbrogade 92",
    "sg:city":"Holstebro",
    "sg:orig_category":"Servicestationer",
    "sg:phone":"+45 97 42 22 76",
    "sg:postcode":"7500",
    "sg:province":"Danmark",
    "wof:name":"DK-Benzin",
    "wof:placetype":"venue"
},
  "geometry": {"coordinates":[8.606004,56.353188],"type":"Point"}
}