{
  "type": "Feature",
  "properties": {
    "iso:country":"DK",
    "sg:address":"Stryn\u00f8vej 38",
    "sg:city":"Esbjerg V",
    "sg:classifiers":[
        {
            "category":"Personal",
            "subcategory":"Massage",
            "type":"Services"
        }
    ],
    "sg:phone":"+45 75 15 25 27",
    "sg:postcode":"6710",
    "sg:province":"Danmark",
    "wof:name":"Pedersen, Ingeborg \u00d8stergaard",
    "wof:placetype":"venue"
},
  "geometry": {"coordinates":[8.4186954498,55.5015830994],"type":"Point"}
}