{
  "type": "Feature",
  "properties": {
    "iso:country":"DK",
    "sg:address":"N\u00e6stvedvej 230",
    "sg:city":"Ringsted",
    "sg:orig_category":"Brugsforeninger",
    "sg:phone":"+45 57 61 00 93",
    "sg:postcode":"4100",
    "sg:province":"Danmark",
    "wof:name":"Dagli' Brugsen H\u00f8m",
    "wof:placetype":"venue"
},
  "geometry": {"coordinates":[11.7875862122,55.4458961487],"type":"Point"}
}