{
  "type": "Feature",
  "properties": {
    "addr:full":"Havnegade 18 Hirtshals Danmark 9850",
    "addr:housenumber":"18",
    "addr:postcode":"9850",
    "addr:street":"Havnegade",
    "iso:country":"DK",
    "sg:address":"Havnegade 18",
    "sg:city":"Hirtshals",
    "sg:orig_category":"Advokater",
    "sg:phone":"+45 98 94 18 00",
    "sg:postcode":"9850",
    "sg:province":"Danmark",
    "wof:name":"Baltsersen, Advokatfirmaet Allan Mose",
    "wof:placetype":"venue"
},
  "geometry": {"coordinates":[9.9629049301,57.5919380188],"type":"Point"}
}