{
  "type": "Feature",
  "properties": {
    "addr:full":"Sankt Nicolai Gade 11, 1. Svendborg Danmark 5700",
    "addr:housenumber":"11 1",
    "addr:postcode":"5700",
    "addr:street":"Nicolai Gade",
    "iso:country":"DK",
    "sg:address":"Sankt Nicolai Gade 11, 1.",
    "sg:city":"Svendborg",
    "sg:orig_category":"Psykologer, praktiserende",
    "sg:phone":"+45 62 21 00 54",
    "sg:postcode":"5700",
    "sg:province":"Danmark",
    "wof:name":"Christmas, Lone",
    "wof:placetype":"venue"
},
  "geometry": {"coordinates":[10.6077194214,55.0577125549],"type":"Point"}
}