{
  "type": "Feature",
  "properties": {
    "iso:country":"DK",
    "sg:address":"Baldersbuen 15 F",
    "sg:city":"Hedehusene",
    "sg:orig_category":"Ergonomi",
    "sg:phone":"+45 46 59 70 84",
    "sg:postcode":"2640",
    "sg:province":"Danmark",
    "sg:website":"www.ergoteam.dk",
    "wof:name":"ErgoTeam A/S",
    "wof:placetype":"venue"
},
  "geometry": {"coordinates":[12.1993551254,55.6496009827],"type":"Point"}
}