{
  "type": "Feature",
  "properties": {
    "addr:full":"Holstensvej 7 Fredericia Danmark 7000",
    "addr:housenumber":"7",
    "addr:postcode":"7000",
    "addr:street":"Holstensvej",
    "iso:country":"DK",
    "sg:address":"Holstensvej 7",
    "sg:city":"Fredericia",
    "sg:orig_category":"Transportmateriel",
    "sg:phone":"+45 75 91 40 00",
    "sg:postcode":"7000",
    "sg:province":"Danmark",
    "wof:name":"Harbo A/S, Peter",
    "wof:placetype":"venue"
},
  "geometry": {"coordinates":[9.7442569733,55.5616645813],"type":"Point"}
}