{
  "type": "Feature",
  "properties": {
    "addr:full":"Odensevej 3, Glamsdalen Glamsbjerg Danmark 5620",
    "addr:housenumber":"3",
    "addr:postcode":"5620",
    "addr:street":"Odensevej;Glamsdalen",
    "iso:country":"DK",
    "sg:address":"Odensevej 3, Glamsdalen",
    "sg:city":"Glamsbjerg",
    "sg:orig_category":"Blikkenslagere",
    "sg:phone":"+45 64 72 13 22",
    "sg:postcode":"5620",
    "sg:province":"Danmark",
    "wof:name":"Glamsbjerg Blikkenslagerforretning",
    "wof:placetype":"venue"
},
  "geometry": {"coordinates":[10.10525,55.278332],"type":"Point"}
}