{
  "type": "Feature",
  "properties": {
    "addr:full":"v/ Tom Pedersen, Hvidager 39 Albertslund Danmark 2620",
    "addr:housenumber":"39",
    "addr:postcode":"2620",
    "addr:street":"Hvidager",
    "iso:country":"DK",
    "sg:address":"v/ Tom Pedersen, Hvidager 39",
    "sg:city":"Albertslund",
    "sg:orig_category":"Loger",
    "sg:phone":"+45 43 64 85 35",
    "sg:postcode":"2620",
    "sg:province":"Danmark",
    "wof:name":"Lions Club",
    "wof:placetype":"venue"
},
  "geometry": {"coordinates":[12.3517179489,55.6568450928],"type":"Point"}
}