{
  "type": "Feature",
  "properties": {
    "addr:full":"\u00d8sterled 40 Aakirkeby Danmark 3720",
    "addr:housenumber":"40",
    "addr:postcode":"3720",
    "addr:street":"Osterled",
    "iso:country":"DK",
    "sg:address":"\u00d8sterled 40",
    "sg:city":"Aakirkeby",
    "sg:orig_category":"Malermestre",
    "sg:phone":"+45 56 97 54 24",
    "sg:postcode":"3720",
    "sg:province":"Danmark",
    "wof:name":"Kofod, Malerfirma Brian",
    "wof:placetype":"venue"
},
  "geometry": {"coordinates":[14.9286146164,55.0691146851],"type":"Point"}
}