{
  "type": "Feature",
  "properties": {
    "addr:full":"Gr\u00f8nsundsvej 353, Horbelev Horbelev Danmark 4871",
    "addr:housenumber":"353",
    "addr:postcode":"4871",
    "addr:street":"Gronsundsvej",
    "iso:country":"DK",
    "sg:address":"Gr\u00f8nsundsvej 353, Horbelev",
    "sg:city":"Horbelev",
    "sg:orig_category":"Supermarkeder",
    "sg:phone":"+45 54 44 50 37",
    "sg:postcode":"4871",
    "sg:province":"Danmark",
    "wof:name":"Merko Horbelev",
    "wof:placetype":"venue"
},
  "geometry": {"coordinates":[12.0557804108,54.8232345581],"type":"Point"}
}