{
  "type": "Feature",
  "properties": {
    "addr:full":"Sognepr\u00e6st: Anders Bonde (K/B), Lyng\u00e5vej 85, Lyng\u00e5 Hadsten Danmark 8370",
    "addr:housenumber":"85",
    "addr:postcode":"8370",
    "addr:street":"Lyngaavej",
    "iso:country":"DK",
    "sg:address":"Sognepr\u00e6st: Anders Bonde (K/B), Lyng\u00e5vej 85, Lyng\u00e5",
    "sg:city":"Hadsten",
    "sg:orig_category":"Kirkesogne",
    "sg:phone":"+45 86 98 12 24",
    "sg:postcode":"8370",
    "sg:province":"Danmark",
    "wof:name":"Lerbjerg og Lyng\u00e5 Sogne",
    "wof:placetype":"venue"
},
  "geometry": {"coordinates":[10.047659874,56.3287239075],"type":"Point"}
}