{
  "type": "Feature",
  "properties": {
    "iso:country":"DK",
    "sg:address":"Vangede Bygade 128",
    "sg:city":"Gentofte",
    "sg:orig_category":"Dyreklinikker og -hospitaler",
    "sg:phone":"+45 39 76 00 77",
    "sg:postcode":"2820",
    "sg:province":"Danmark",
    "wof:name":"Ny Mose Dyreklinik",
    "wof:placetype":"venue"
},
  "geometry": {"coordinates":[12.5204696655,55.7474975586],"type":"Point"}
}