{
  "type": "Feature",
  "properties": {
    "addr:full":"Rousth\u00f8js Alle 51 Juelsminde Danmark 7130",
    "addr:housenumber":"51",
    "addr:postcode":"7130",
    "addr:street":"Rousthojs Alle",
    "iso:country":"DK",
    "sg:address":"Rousth\u00f8js Alle 51",
    "sg:city":"Juelsminde",
    "sg:orig_category":"Apoteker og -udsalg",
    "sg:phone":"+45 75 69 43 61",
    "sg:postcode":"7130",
    "sg:province":"Danmark",
    "wof:name":"Apoteksudsalget",
    "wof:placetype":"venue"
},
  "geometry": {"coordinates":[10.010011673,55.7094230652],"type":"Point"}
}