{
  "type": "Feature",
  "properties": {
    "iso:country":"DK",
    "sg:address":"Fmd.: Viggo Nielsen, Rosenv\u00e6nget 5",
    "sg:city":"Bedsted",
    "sg:orig_category":"\u00c3\u2020ldreorganisationer og klubber",
    "sg:phone":"+45 97 94 52 20",
    "sg:postcode":"7755",
    "sg:province":"Danmark",
    "wof:name":"Bedsted-Grurup Pensionistforening",
    "wof:placetype":"venue"
},
  "geometry": {"coordinates":[8.4905691147,56.8179664612],"type":"Point"}
}