{
  "type": "Feature",
  "properties": {
    "iso:country":"DK",
    "sg:address":"Jernbanevej 4",
    "sg:city":"Pr\u00e6st\u00f8",
    "sg:orig_category":"Servicestationer",
    "sg:phone":"+45 55 99 11 80",
    "sg:postcode":"4720",
    "sg:province":"Danmark",
    "wof:name":"Hydro - Texaco",
    "wof:placetype":"venue"
},
  "geometry": {"coordinates":[12.0376024246,55.1222724915],"type":"Point"}
}