{
  "type": "Feature",
  "properties": {
    "addr:full":"v/ Erik Holm Nielsen, Ulvk\u00e6rvej 4, Jegind\u00f8 Thyholm Danmark 7790",
    "addr:housenumber":"4",
    "addr:postcode":"7790",
    "addr:street":"Holm;Ulvkaervej",
    "iso:country":"DK",
    "sg:address":"v/ Erik Holm Nielsen, Ulvk\u00e6rvej 4, Jegind\u00f8",
    "sg:city":"Thyholm",
    "sg:orig_category":"Kulturelle foreninger",
    "sg:phone":"+45 97 87 91 40",
    "sg:postcode":"7790",
    "sg:province":"Danmark",
    "wof:name":"Jens Glob Samvirket",
    "wof:placetype":"venue"
},
  "geometry": {"coordinates":[8.525765419,56.6507072449],"type":"Point"}
}