{
  "type": "Feature",
  "properties": {
    "iso:country":"DK",
    "sg:address":"Vestergade ",
    "sg:classifiers":[
        {
            "category":"Banks & Credit Unions",
            "subcategory":"Bank",
            "type":"Services"
        }
    ],
    "sg:phone":"+45 98 64 15 00",
    "sg:postcode":"12",
    "wof:name":"Unibank A/S",
    "wof:placetype":"venue"
},
  "geometry": {"coordinates":[9.54559,56.168209],"type":"Point"}
}