{
  "type": "Feature",
  "properties": {
    "iso:country":"DK",
    "sg:address":"Mullesg\u00e5rdvej 3, Houe",
    "sg:city":"Lemvig",
    "sg:orig_category":"Jagt- og fiskeudstyr",
    "sg:phone":"+45 97 88 94 65",
    "sg:postcode":"7620",
    "sg:province":"Danmark",
    "wof:name":"Jagt- & Sportsskytteudstyr",
    "wof:placetype":"venue"
},
  "geometry": {"coordinates":[8.3073654175,56.5505104065],"type":"Point"}
}