{
  "type": "Feature",
  "properties": {
    "iso:country":"DK",
    "sg:address":"Kongstrupvej 38",
    "sg:city":"Sejer\u00f8",
    "sg:orig_category":"Ejendomshandel",
    "sg:phone":"+45 59 59 11 11",
    "sg:postcode":"4592",
    "sg:province":"Danmark",
    "wof:name":"Weimann, Jens",
    "wof:placetype":"venue"
},
  "geometry": {"coordinates":[11.1737890244,55.874420166],"type":"Point"}
}