{
  "type": "Feature",
  "properties": {
    "addr:full":"v/ Lars Lykke Hansen, Skerningeg\u00e5rdsvej 12 Vester Skerninge Danmark 5762",
    "addr:housenumber":"12",
    "addr:postcode":"5762",
    "addr:street":"Skerningegaardsvej",
    "iso:country":"DK",
    "sg:address":"v/ Lars Lykke Hansen, Skerningeg\u00e5rdsvej 12",
    "sg:city":"Vester Skerninge",
    "sg:orig_category":"Hobbybetonede foreninger",
    "sg:phone":"+45 62 24 22 08",
    "sg:postcode":"5762",
    "sg:province":"Danmark",
    "wof:name":"Sydfyns M\u00f8ntklub",
    "wof:placetype":"venue"
},
  "geometry": {"coordinates":[10.5008449554,55.070400238],"type":"Point"}
}