{
  "type": "Feature",
  "properties": {
    "addr:full":"Fmd.: Rikke U. Christensen, Elsborgvej 9, Sj\u00f8rslev Kjellerup Danmark 8620",
    "addr:housenumber":"9",
    "addr:postcode":"8620",
    "addr:street":"Fmd.;Elsborgvej",
    "iso:country":"DK",
    "sg:address":"Fmd.: Rikke U. Christensen, Elsborgvej 9, Sj\u00f8rslev",
    "sg:city":"Kjellerup",
    "sg:orig_category":"Borger- og beboerforeninger",
    "sg:phone":"+45 86 66 80 50",
    "sg:postcode":"8620",
    "sg:province":"Danmark",
    "wof:name":"Sj\u00f8rslev-Demstrup Borgerforening",
    "wof:placetype":"venue"
},
  "geometry": {"coordinates":[9.430934906,56.2877655029],"type":"Point"}
}