{
  "type": "Feature",
  "properties": {
    "iso:country":"DK",
    "sg:address":"Klokkervej 1 B, Hasle",
    "sg:city":"\u00c5rhus V",
    "sg:classifiers":[
        {
            "category":"Professional",
            "subcategory":"Computer Services",
            "type":"Services"
        }
    ],
    "sg:phone":"+45 86 15 32 53",
    "sg:postcode":"8210",
    "sg:province":"Danmark",
    "sg:tags":[
        "edb",
        "-",
        "software"
    ],
    "wof:name":"Persona",
    "wof:placetype":"venue"
},
  "geometry": {"coordinates":[14.7065896988,55.1830787659],"type":"Point"}
}