{
  "type": "Feature",
  "properties": {
    "addr:full":"Fmd.: Else Jensen, Syv Holmevej 10 Viby Sj\u00e6lland Danmark 4130",
    "addr:housenumber":"10",
    "addr:postcode":"4130",
    "addr:street":"Syv Holmevej",
    "iso:country":"DK",
    "sg:address":"Fmd.: Else Jensen, Syv Holmevej 10",
    "sg:city":"Viby Sj\u00e6lland",
    "sg:orig_category":"Husflidsforeninger",
    "sg:phone":"+45 46 19 39 16",
    "sg:postcode":"4130",
    "sg:province":"Danmark",
    "wof:name":"Rams\u00f8 Familiebrugs Husholdningsudvalg",
    "wof:placetype":"venue"
},
  "geometry": {"coordinates":[12.0485076904,55.5666732788],"type":"Point"}
}