{
  "type": "Feature",
  "properties": {
    "iso:country":"DK",
    "sg:address":"Storegade 8",
    "sg:city":"Varde",
    "sg:orig_category":"Genbrugsbutikker",
    "sg:phone":"+45 75 22 53 06",
    "sg:postcode":"6800",
    "sg:province":"Danmark",
    "wof:name":"Sudan Genbrugsbutik",
    "wof:placetype":"venue"
},
  "geometry": {"coordinates":[8.4838008881,55.6193389893],"type":"Point"}
}