{
  "type": "Feature",
  "properties": {
    "addr:full":"Frichsvej 11 Silkeborg Danmark 8600",
    "addr:housenumber":"11",
    "addr:postcode":"8600",
    "addr:street":"Frichsvej",
    "iso:country":"DK",
    "sg:address":"Frichsvej 11",
    "sg:city":"Silkeborg",
    "sg:orig_category":"Hydraulik",
    "sg:phone":"+45 86 81 39 88",
    "sg:postcode":"8600",
    "sg:province":"Danmark",
    "wof:name":"Nordhydraulic",
    "wof:placetype":"venue"
},
  "geometry": {"coordinates":[9.5649957657,56.1951675415],"type":"Point"}
}