{
  "type": "Feature",
  "properties": {
    "addr:full":"Sognepr\u00e6st: Kim Tesdorph Vinberg (K/B), Karisevej 52, Dalby Haslev Danmark 4690",
    "addr:housenumber":"52",
    "addr:postcode":"4690",
    "addr:street":"Karisevej",
    "iso:country":"DK",
    "sg:address":"Sognepr\u00e6st: Kim Tesdorph Vinberg (K/B), Karisevej 52, Dalby",
    "sg:city":"Haslev",
    "sg:orig_category":"Kirkesogne",
    "sg:phone":"+45 56 39 80 17",
    "sg:postcode":"4690",
    "sg:province":"Danmark",
    "wof:name":"S\u00f8nder Dalby og Tureby sogne",
    "wof:placetype":"venue"
},
  "geometry": {"coordinates":[11.9678049088,55.3230895996],"type":"Point"}
}