{
  "type": "Feature",
  "properties": {
    "addr:full":"Hestk\u00e6rvej 32, Krogager Mark Grindsted Danmark 7200",
    "addr:housenumber":"32",
    "addr:postcode":"7200",
    "addr:street":"Hestkaervej;Krogager Mark",
    "iso:country":"DK",
    "sg:address":"Hestk\u00e6rvej 32, Krogager Mark",
    "sg:city":"Grindsted",
    "sg:orig_category":"Autoreparation og -service",
    "sg:phone":"+45 75 33 92 31",
    "sg:postcode":"7200",
    "sg:province":"Danmark",
    "wof:name":"JK Biler",
    "wof:placetype":"venue"
},
  "geometry": {"coordinates":[8.9288702011,55.7560272217],"type":"Point"}
}