{
  "type": "Feature",
  "properties": {
    "addr:full":"Viborgvej 156, Hasle \u00c5rhus V Danmark 8210",
    "addr:housenumber":"156",
    "addr:postcode":"8210",
    "addr:street":"Viborgvej",
    "iso:country":"DK",
    "sg:address":"Viborgvej 156, Hasle",
    "sg:city":"\u00c5rhus V",
    "sg:orig_category":"Skolefritidsordninger",
    "sg:phone":"+45 86 15 39 50",
    "sg:postcode":"8210",
    "sg:province":"Danmark",
    "wof:name":"Hasle Skoles Skolefritidsordning",
    "wof:placetype":"venue"
},
  "geometry": {"coordinates":[14.7065896988,55.1830787659],"type":"Point"}
}