{
  "type": "Feature",
  "properties": {
    "addr:full":"Vorreg\u00e5rds Alle 56 - 60 \u00c5rhus N Danmark 8200",
    "addr:housenumber":"56 60",
    "addr:postcode":"8200",
    "addr:street":"Vorregaards Alle",
    "iso:country":"DK",
    "sg:address":"Vorreg\u00e5rds Alle 56 - 60",
    "sg:city":"\u00c5rhus N",
    "sg:orig_category":"Fritidshjem",
    "sg:phone":"+45 86 16 66 25",
    "sg:postcode":"8200",
    "sg:province":"Danmark",
    "wof:name":"Regineh\u00f8j, Fritidshjem",
    "wof:placetype":"venue"
},
  "geometry": {"coordinates":[4.9393601418,49.7092018127],"type":"Point"}
}