{
  "type": "Feature",
  "properties": {
    "addr:full":"Hjortsvangen 88 Give Danmark 7323",
    "addr:housenumber":"88",
    "addr:postcode":"7323",
    "addr:street":"Hjortsvangen",
    "iso:country":"DK",
    "sg:address":"Hjortsvangen 88",
    "sg:city":"Give",
    "sg:classifiers":[
        {
            "category":"Manufacturing",
            "subcategory":"Tobacco Products",
            "type":"Manufacturing & Wholesale Goods"
        }
    ],
    "sg:phone":"+45 75 73 25 40",
    "sg:postcode":"7323",
    "sg:province":"Danmark",
    "sg:tags":[
        "manufacturer"
    ],
    "wof:name":"Give T\u00f8jcenter",
    "wof:placetype":"venue"
},
  "geometry": {"coordinates":[9.2434625626,55.85389328],"type":"Point"}
}