{
  "type": "Feature",
  "properties": {
    "iso:country":"DK",
    "sg:address":"Vesterbrogade 9",
    "sg:city":"Viborg",
    "sg:orig_category":"Bagere",
    "sg:phone":"+45 86 62 36 95",
    "sg:postcode":"8800",
    "sg:province":"Danmark",
    "wof:name":"Varme Br\u00f8d, Det",
    "wof:placetype":"venue"
},
  "geometry": {"coordinates":[9.400378,56.449722],"type":"Point"}
}