{
  "type": "Feature",
  "properties": {
    "addr:full":"Bakkeh\u00e6ldet 49  K\u00f8ge Danmark 4600",
    "addr:housenumber":"49",
    "addr:postcode":"4600",
    "addr:street":"Bakkehaeldet",
    "iso:country":"DK",
    "sg:address":"Bakkeh\u00e6ldet 49 ",
    "sg:city":"K\u00f8ge",
    "sg:classifiers":[
        {
            "category":"Professional",
            "subcategory":"Advertising",
            "type":"Services"
        }
    ],
    "sg:phone":"+45 56 26 65 12",
    "sg:postcode":"4600",
    "sg:province":"Danmark",
    "sg:tags":[
        "communication",
        "medium"
    ],
    "wof:name":"MOVIESOUND V/PREBEN MORTENSEN",
    "wof:placetype":"venue"
},
  "geometry": {"coordinates":[12.2395334244,55.3983383179],"type":"Point"}
}