{
  "type": "Feature",
  "properties": {
    "addr:full":"\u00c5landsvej 3 - 5 Viborg Danmark 8800",
    "addr:housenumber":"3 5",
    "addr:postcode":"8800",
    "addr:street":"Aalandsvej",
    "iso:country":"DK",
    "sg:address":"\u00c5landsvej 3 - 5",
    "sg:city":"Viborg",
    "sg:orig_category":"Autoopretning",
    "sg:phone":"+45 86 62 80 88",
    "sg:postcode":"8800",
    "sg:province":"Danmark",
    "wof:name":"Viborg Autoopretning",
    "wof:placetype":"venue"
},
  "geometry": {"coordinates":[9.368976593,56.4564781189],"type":"Point"}
}