{
  "type": "Feature",
  "properties": {
    "addr:full":"K\u00e6rtoften 10, Hasle \u00c5rhus V Danmark 8210",
    "addr:housenumber":"10",
    "addr:postcode":"8210",
    "addr:street":"Kaertoften",
    "iso:country":"DK",
    "sg:address":"K\u00e6rtoften 10, Hasle",
    "sg:city":"\u00c5rhus V",
    "sg:classifiers":[
        {
            "category":"Restaurant",
            "type":"Food & Drink"
        }
    ],
    "sg:phone":"+45 86 15 37 88",
    "sg:postcode":"8210",
    "sg:province":"Danmark",
    "wof:name":"La Marharita Pizzaria",
    "wof:placetype":"venue"
},
  "geometry": {"coordinates":[14.7065896988,55.1830787659],"type":"Point"}
}