{
  "type": "Feature",
  "properties": {
    "addr:full":"M\u00f8lleh\u00f8jvej 8, K\u00e6rby Kalundborg Danmark 4400",
    "addr:housenumber":"8",
    "addr:postcode":"4400",
    "addr:street":"Mollehojvej;Kaerby",
    "iso:country":"DK",
    "sg:address":"M\u00f8lleh\u00f8jvej 8, K\u00e6rby",
    "sg:city":"Kalundborg",
    "sg:orig_category":"Hospitalsudstyr",
    "sg:phone":"+45 59 50 02 25",
    "sg:postcode":"4400",
    "sg:province":"Danmark",
    "wof:name":"H.H. Hospilab ApS",
    "wof:placetype":"venue"
},
  "geometry": {"coordinates":[11.0934085846,55.6797485352],"type":"Point"}
}