{
  "type": "Feature",
  "properties": {
    "addr:full":"Svanekevej 2 Herning Danmark 7400",
    "addr:housenumber":"2",
    "addr:postcode":"7400",
    "addr:street":"Svanekevej",
    "iso:country":"DK",
    "sg:address":"Svanekevej 2",
    "sg:city":"Herning",
    "sg:orig_category":"Revisorer",
    "sg:phone":"+45 97 12 52 44",
    "sg:postcode":"7400",
    "sg:province":"Danmark",
    "wof:name":"Vistisen & Lunde Nielsen A/S",
    "wof:placetype":"venue"
},
  "geometry": {"coordinates":[8.9834403992,56.1536636353],"type":"Point"}
}