{
  "type": "Feature",
  "properties": {
    "addr:full":"Torvegade 18 Skive Danmark 7800",
    "addr:housenumber":"18",
    "addr:postcode":"7800",
    "addr:street":"Torvegade",
    "iso:country":"DK",
    "sg:address":"Torvegade 18",
    "sg:city":"Skive",
    "sg:orig_category":"Farve og tapet",
    "sg:phone":"+45 97 52 01 12",
    "sg:postcode":"7800",
    "sg:province":"Danmark",
    "wof:name":"Mortensen, M. J.",
    "wof:placetype":"venue"
},
  "geometry": {"coordinates":[9.0293636322,56.5679244995],"type":"Point"}
}