{
  "type": "Feature",
  "properties": {
    "addr:full":"Blommevangen 2, Sm\u00f8rumnedre Sm\u00f8rum Danmark 2765",
    "addr:housenumber":"2",
    "addr:postcode":"2765",
    "addr:street":"Blommevangen",
    "iso:country":"DK",
    "sg:address":"Blommevangen 2, Sm\u00f8rumnedre",
    "sg:city":"Sm\u00f8rum",
    "sg:orig_category":"Reklamebureauer",
    "sg:phone":"+45 44 65 75 44",
    "sg:postcode":"2765",
    "sg:province":"Danmark",
    "wof:name":"Schneider Reklame & Marketing I/S",
    "wof:placetype":"venue"
},
  "geometry": {"coordinates":[-89.9975738525,38.1341552734],"type":"Point"}
}