{
  "type": "Feature",
  "properties": {
    "addr:full":"Daltoften 80, Agedrup Agedrup Danmark 5320",
    "addr:housenumber":"80",
    "addr:postcode":"5320",
    "addr:street":"Daltoften",
    "iso:country":"DK",
    "sg:address":"Daltoften 80, Agedrup",
    "sg:city":"Agedrup",
    "sg:orig_category":"INGENI\u00c3\u02dcRER",
    "sg:phone":"+45 66 10 75 80",
    "sg:postcode":"5320",
    "sg:province":"Danmark",
    "wof:name":"KB Maskinkonstruktion",
    "wof:placetype":"venue"
},
  "geometry": {"coordinates":[10.4700860977,55.4257240295],"type":"Point"}
}