{
  "type": "Feature",
  "properties": {
    "addr:full":"Fmd.: Michael Poulsen, S\u00f8ndergade 29 Bording Danmark 7441",
    "addr:housenumber":"29",
    "addr:postcode":"7441",
    "addr:street":"Sondergade",
    "iso:country":"DK",
    "sg:address":"Fmd.: Michael Poulsen, S\u00f8ndergade 29",
    "sg:city":"Bording",
    "sg:orig_category":"Hobbybetonede foreninger",
    "sg:phone":"+45 86 86 29 95",
    "sg:postcode":"7441",
    "sg:province":"Danmark",
    "wof:name":"Them sogns Jagtforening",
    "wof:placetype":"venue"
},
  "geometry": {"coordinates":[9.2792396545,56.1449508667],"type":"Point"}
}