{
  "type": "Feature",
  "properties": {
    "iso:country":"DK",
    "sg:address":"Ulstedvej 7",
    "sg:city":"K\u00f8ge",
    "sg:orig_category":"Malermestre",
    "sg:phone":"+45 56 65 52 35",
    "sg:postcode":"4600",
    "sg:province":"Danmark",
    "wof:name":"Andreasen K\u00f8ge A/S, Leif",
    "wof:placetype":"venue"
},
  "geometry": {"coordinates":[12.1614980698,55.4708518982],"type":"Point"}
}