{
  "type": "Feature",
  "properties": {
    "addr:full":"Fmd.: Inger Breindahl, Borgerv\u00e6nget 34 Esbjerg V Danmark 6710",
    "addr:housenumber":"34",
    "addr:postcode":"6710",
    "addr:street":"Borgervaenget",
    "iso:country":"DK",
    "sg:address":"Fmd.: Inger Breindahl, Borgerv\u00e6nget 34",
    "sg:city":"Esbjerg V",
    "sg:orig_category":"\u00c3\u2020ldreorganisationer og klubber",
    "sg:phone":"+45 75 15 28 42",
    "sg:postcode":"6710",
    "sg:province":"Danmark",
    "wof:name":"M\u00f8destedets Centerklub",
    "wof:placetype":"venue"
},
  "geometry": {"coordinates":[8.4009799957,55.5313110352],"type":"Point"}
}