{
  "type": "Feature",
  "properties": {
    "addr:full":"Bytoften 10 Langeskov Danmark 5550",
    "addr:housenumber":"10",
    "addr:postcode":"5550",
    "addr:street":"Bytoften",
    "iso:country":"DK",
    "sg:address":"Bytoften 10",
    "sg:city":"Langeskov",
    "sg:orig_category":"Maskinfabrikker",
    "sg:phone":"+45 65 38 12 88",
    "sg:postcode":"5550",
    "sg:province":"Danmark",
    "sg:website":"www.egelykke.dk",
    "wof:name":"Egelykke Jensens Maskinfabrik A/S",
    "wof:placetype":"venue"
},
  "geometry": {"coordinates":[10.5797624588,55.3492927551],"type":"Point"}
}