{
  "type": "Feature",
  "properties": {
    "addr:full":"Fmd.: Holger Jensen, H\u00e5strupvej 36, Smidstrup Fredericia Danmark 7000",
    "addr:housenumber":"36",
    "addr:postcode":"7000",
    "addr:street":"Haastrupvej",
    "iso:country":"DK",
    "sg:address":"Fmd.: Holger Jensen, H\u00e5strupvej 36, Smidstrup",
    "sg:city":"Fredericia",
    "sg:orig_category":"Loger",
    "sg:postcode":"7000",
    "sg:province":"Danmark",
    "wof:name":"Y's mens club, Trekanten",
    "wof:placetype":"venue"
},
  "geometry": {"coordinates":[9.7591047287,55.566368103],"type":"Point"}
}