{
  "type": "Feature",
  "properties": {
    "addr:full":"Bybjergvej 5 Esperg\u00e6rde Danmark 3060",
    "addr:housenumber":"5",
    "addr:postcode":"3060",
    "addr:street":"Bybjergvej",
    "iso:country":"DK",
    "sg:address":"Bybjergvej 5",
    "sg:city":"Esperg\u00e6rde",
    "sg:orig_category":"Import-eksport",
    "sg:phone":"+45 49 17 60 60",
    "sg:postcode":"3060",
    "sg:province":"Danmark",
    "sg:website":"www.satex.dk",
    "wof:name":"Special Auto Trading A/S",
    "wof:placetype":"venue"
},
  "geometry": {"coordinates":[11.6512403488,47.8390617371],"type":"Point"}
}