{
  "type": "Feature",
  "properties": {
    "addr:full":"Gammelbyvej 24, Gammelby Vejen Danmark 6600",
    "addr:housenumber":"24",
    "addr:postcode":"6600",
    "addr:street":"Gammelbyvej",
    "iso:country":"DK",
    "sg:address":"Gammelbyvej 24, Gammelby",
    "sg:city":"Vejen",
    "sg:orig_category":"Antikviteter",
    "sg:phone":"+45 75 36 80 10",
    "sg:postcode":"6600",
    "sg:province":"Danmark",
    "wof:name":"Unik Antik",
    "wof:placetype":"venue"
},
  "geometry": {"coordinates":[9.1396121979,55.4778175354],"type":"Point"}
}