{
  "type": "Feature",
  "properties": {
    "addr:full":"M\u00f8llestr\u00e6de 1 A, 3. Kalundborg Danmark 4400",
    "addr:housenumber":"1 a 3",
    "addr:postcode":"4400",
    "addr:street":"Mollestraede",
    "iso:country":"DK",
    "sg:address":"M\u00f8llestr\u00e6de 1 A, 3.",
    "sg:city":"Kalundborg",
    "sg:orig_category":"Forsikringer",
    "sg:phone":"+45 59 51 60 16",
    "sg:postcode":"4400",
    "sg:province":"Danmark",
    "wof:name":"hf-forsikring g/s",
    "wof:placetype":"venue"
},
  "geometry": {"coordinates":[11.0934085846,55.6797485352],"type":"Point"}
}