{
  "type": "Feature",
  "properties": {
    "iso:country":"DK",
    "sg:address":"H\u00e5ndv\u00e6rkervangen 9",
    "sg:city":"Slangerup",
    "sg:orig_category":"Beslagsmede",
    "sg:phone":"+45 47 33 59 55",
    "sg:postcode":"3550",
    "sg:province":"Danmark",
    "wof:name":"Kj\u00e6rs Beslagsmedie ApS",
    "wof:placetype":"venue"
},
  "geometry": {"coordinates":[12.17176,55.846077],"type":"Point"}
}