{
  "type": "Feature",
  "properties": {
    "addr:full":"Havnegade 101 R\u00f8dby Danmark 4970",
    "addr:housenumber":"101",
    "addr:postcode":"4970",
    "addr:street":"Havnegade",
    "iso:country":"DK",
    "sg:address":"Havnegade 101",
    "sg:city":"R\u00f8dby",
    "sg:orig_category":"Skoler",
    "sg:phone":"+45 54 60 50 89",
    "sg:postcode":"4970",
    "sg:province":"Danmark",
    "wof:name":"Havneskolen",
    "wof:placetype":"venue"
},
  "geometry": {"coordinates":[11.3621282578,54.6666526794],"type":"Point"}
}