{
  "type": "Feature",
  "properties": {
    "iso:country":"DK",
    "sg:address":"Snerlevej 1, No",
    "sg:city":"Ringk\u00f8bing",
    "sg:orig_category":"Tegnere og tegnestuer",
    "sg:phone":"+45 97 33 03 82",
    "sg:postcode":"6950",
    "sg:province":"Danmark",
    "wof:name":"Prima Design",
    "wof:placetype":"venue"
},
  "geometry": {"coordinates":[8.2507953644,56.0878334045],"type":"Point"}
}