{
  "type": "Feature",
  "properties": {
    "addr:full":"Fmd.: Mogens Backe, Mortenstrupvej 36 H\u00f8rsholm Danmark 2970",
    "addr:housenumber":"36",
    "addr:postcode":"2970",
    "addr:street":"Mogens Backe Mortenstrupvej",
    "iso:country":"DK",
    "sg:address":"Fmd.: Mogens Backe, Mortenstrupvej 36",
    "sg:city":"H\u00f8rsholm",
    "sg:orig_category":"Hobbybetonede foreninger",
    "sg:phone":"+45 45 86 80 29",
    "sg:postcode":"2970",
    "sg:province":"Danmark",
    "wof:name":"Rungsted Salonskytteforening",
    "wof:placetype":"venue"
},
  "geometry": {"coordinates":[16.5499992371,63.4333000183],"type":"Point"}
}