{
  "type": "Feature",
  "properties": {
    "addr:full":"Brejningg\u00e5rdsvej 12 Spjald Danmark 6971",
    "addr:housenumber":"12",
    "addr:postcode":"6971",
    "addr:street":"Brejninggaardsvej",
    "iso:country":"DK",
    "sg:address":"Brejningg\u00e5rdsvej 12",
    "sg:city":"Spjald",
    "sg:orig_category":"Efterskoler",
    "sg:phone":"+45 97 38 16 44",
    "sg:postcode":"6971",
    "sg:province":"Danmark",
    "sg:website":"www.brejninggaard.dk",
    "wof:name":"Brejninggaard Efterskole",
    "wof:placetype":"venue"
},
  "geometry": {"coordinates":[8.5120706558,56.1161689758],"type":"Point"}
}