{
  "type": "Feature",
  "properties": {
    "iso:country":"DK",
    "sg:address":"Fmd.: Annamarie Bertelsen, S\u00f8ndermarken 5, Jels",
    "sg:city":"R\u00f8dding",
    "sg:orig_category":"Husflidsforeninger",
    "sg:phone":"+45 74 55 21 76",
    "sg:postcode":"6630",
    "sg:province":"Danmark",
    "wof:name":"Jels Husholdningsforening",
    "wof:placetype":"venue"
},
  "geometry": {"coordinates":[9.2022953033,55.3564414978],"type":"Point"}
}