{
  "type": "Feature",
  "properties": {
    "addr:full":"Chr. Husteds Vej 2 Ringk\u00f8bing Danmark 6950",
    "addr:housenumber":"2",
    "addr:postcode":"6950",
    "addr:street":"Chr. Husteds Vej",
    "iso:country":"DK",
    "sg:address":"Chr. Husteds Vej 2",
    "sg:city":"Ringk\u00f8bing",
    "sg:orig_category":"Grillbarer",
    "sg:phone":"+45 97 32 29 70",
    "sg:postcode":"6950",
    "sg:province":"Danmark",
    "wof:name":"Delikatessen",
    "wof:placetype":"venue"
},
  "geometry": {"coordinates":[-102.0896530151,42.0193557739],"type":"Point"}
}