{
  "type": "Feature",
  "properties": {
    "iso:country":"DK",
    "sg:address":"Vemmetoftevej 4 A, St. Spjellerup",
    "sg:city":"Fakse",
    "sg:orig_category":"Konservatorer",
    "sg:phone":"+45 56 71 03 69",
    "sg:postcode":"4640",
    "sg:province":"Danmark",
    "wof:name":"Kristensen, Birgitte",
    "wof:placetype":"venue"
},
  "geometry": {"coordinates":[12.1203422546,55.2574195862],"type":"Point"}
}