{
  "type": "Feature",
  "properties": {
    "addr:full":"Tvedvangen 295 Herlev Danmark 2730",
    "addr:housenumber":"295",
    "addr:postcode":"2730",
    "addr:street":"Tvedvangen",
    "iso:country":"DK",
    "sg:address":"Tvedvangen 295",
    "sg:city":"Herlev",
    "sg:orig_category":"Autoreparation og -service",
    "sg:phone":"+45 44 91 05 70",
    "sg:postcode":"2730",
    "sg:province":"Danmark",
    "wof:name":"H.J. Auto ApS (v/E. Jespersen)",
    "wof:placetype":"venue"
},
  "geometry": {"coordinates":[12.4133787155,55.7418251038],"type":"Point"}
}