{
  "type": "Feature",
  "properties": {
    "iso:country":"DK",
    "sg:address":"M\u00f8llevej 100, Over Draaby",
    "sg:city":"J\u00e6gerspris",
    "sg:orig_category":"Kommunale folkeskoler",
    "sg:phone":"+45 47 53 12 24",
    "sg:postcode":"3630",
    "sg:province":"Danmark",
    "wof:name":"Sogneskolen",
    "wof:placetype":"venue"
},
  "geometry": {"coordinates":[11.9136800766,55.9269866943],"type":"Point"}
}