{
  "type": "Feature",
  "properties": {
    "addr:full":"Jernbanegade 10 Lem Danmark 6940",
    "addr:housenumber":"10",
    "addr:postcode":"6940",
    "addr:street":"Jernbanegade",
    "iso:country":"DK",
    "sg:address":"Jernbanegade 10",
    "sg:city":"Lem",
    "sg:classifiers":[
        {
            "category":"Taxi",
            "type":"Transportation"
        }
    ],
    "sg:phone":"+45 97 34 24 24",
    "sg:postcode":"6940",
    "sg:province":"Danmark",
    "wof:name":"Lem Taxi",
    "wof:placetype":"venue"
},
  "geometry": {"coordinates":[8.3851461411,56.0251274109],"type":"Point"}
}