{
  "type": "Feature",
  "properties": {
    "addr:full":"Mattrupvej 6, Mattrup Klovborg Danmark 8765",
    "addr:housenumber":"6",
    "addr:postcode":"8765",
    "addr:street":"Mattrupvej",
    "iso:country":"DK",
    "sg:address":"Mattrupvej 6, Mattrup",
    "sg:city":"Klovborg",
    "sg:orig_category":"Rejsebureauer",
    "sg:phone":"+45 75 76 12 45",
    "sg:postcode":"8765",
    "sg:province":"Danmark",
    "wof:name":"Andersen's Marketing og Kurser, Eigil",
    "wof:placetype":"venue"
},
  "geometry": {"coordinates":[9.4899053574,55.9317016602],"type":"Point"}
}