{
  "type": "Feature",
  "properties": {
    "iso:country":"DK",
    "sg:address":"Niels Bohrs All\u00e9 181",
    "sg:city":"Odense S\u00d8",
    "sg:orig_category":"Isenkram en gros",
    "sg:phone":"+45 66 15 77 00",
    "sg:postcode":"5220",
    "sg:province":"Danmark",
    "wof:name":"R\u00f8r- og Armaturimport A/S",
    "wof:placetype":"venue"
},
  "geometry": {"coordinates":[10.4422969818,55.3764915466],"type":"Point"}
}