{
  "type": "Feature",
  "properties": {
    "addr:full":"Thrigesvej 37 Ikast Danmark 7430",
    "addr:housenumber":"37",
    "addr:postcode":"7430",
    "addr:street":"Thrigesvej",
    "iso:country":"DK",
    "sg:address":"Thrigesvej 37",
    "sg:city":"Ikast",
    "sg:orig_category":"Dataservice",
    "sg:phone":"+45 97 25 22 88",
    "sg:postcode":"7430",
    "sg:province":"Danmark",
    "wof:name":"Unicom",
    "wof:placetype":"venue"
},
  "geometry": {"coordinates":[9.1409320831,56.1203155518],"type":"Point"}
}