{
  "type": "Feature",
  "properties": {
    "iso:country":"DK",
    "sg:address":"Cort Adelers Gade 2",
    "sg:city":"K\u00f8benhavn",
    "sg:classifiers":[
        {
            "category":"Restaurant",
            "type":"Food & Drink"
        }
    ],
    "sg:phone":"+45 33 12 66 14",
    "sg:postcode":"1053",
    "sg:province":"Danmark",
    "wof:name":"Caf\u00e9-Restaurant Amsterdam",
    "wof:placetype":"venue"
},
  "geometry": {"coordinates":[12.5907297134,55.6780586243],"type":"Point"}
}