{
  "type": "Feature",
  "properties": {
    "addr:full":"Krogvejen 4, \u00c5gerup Vipper\u00f8d Danmark 4390",
    "addr:housenumber":"4",
    "addr:postcode":"4390",
    "addr:street":"Krogvejen",
    "iso:country":"DK",
    "sg:address":"Krogvejen 4, \u00c5gerup",
    "sg:city":"Vipper\u00f8d",
    "sg:orig_category":"Kommunale folkeskoler",
    "sg:phone":"+45 59 11 06 00",
    "sg:postcode":"4390",
    "sg:province":"Danmark",
    "wof:name":"\u00c5gerup skole",
    "wof:placetype":"venue"
},
  "geometry": {"coordinates":[11.770031929,55.6723098755],"type":"Point"}
}