{
  "type": "Feature",
  "properties": {
    "addr:full":"Bredgade 52 Karise Danmark 4653",
    "addr:housenumber":"52",
    "addr:postcode":"4653",
    "addr:street":"Bredgade",
    "iso:country":"DK",
    "sg:address":"Bredgade 52",
    "sg:city":"Karise",
    "sg:orig_category":"Antikviteter",
    "sg:phone":"+45 56 78 93 06",
    "sg:postcode":"4653",
    "sg:province":"Danmark",
    "sg:website":"www.splatter.dk",
    "wof:name":"Marskandiseren i Karise",
    "wof:placetype":"venue"
},
  "geometry": {"coordinates":[12.2060823441,55.3064651489],"type":"Point"}
}