{
  "type": "Feature",
  "properties": {
    "addr:full":"Frederiksholms Kanal 20 K\u00f8benhavn Danmark 1220",
    "addr:housenumber":"20",
    "addr:postcode":"1220",
    "addr:street":"Frederiksholms Kanal",
    "iso:country":"DK",
    "sg:address":"Frederiksholms Kanal 20",
    "sg:city":"K\u00f8benhavn",
    "sg:orig_category":"Fotografer",
    "sg:phone":"+45 33 14 50 18",
    "sg:postcode":"1220",
    "sg:province":"Danmark",
    "wof:name":"Bader Fotografi",
    "wof:placetype":"venue"
},
  "geometry": {"coordinates":[12.5790996552,55.6731987],"type":"Point"}
}