{
  "type": "Feature",
  "properties": {
    "iso:country":"DK",
    "sg:address":"Smedebjergevej 61, Vejerslev",
    "sg:city":"Vils",
    "sg:orig_category":"Kommunale folkeskoler",
    "sg:phone":"+45 97 76 70 99",
    "sg:postcode":"7980",
    "sg:province":"Danmark",
    "wof:name":"Vejerslev Skole",
    "wof:placetype":"venue"
},
  "geometry": {"coordinates":[8.7282047272,56.7638053894],"type":"Point"}
}