{
  "type": "Feature",
  "properties": {
    "addr:full":"Gyrstinge Bygade 47, Gyrstinge Ringsted Danmark 4100",
    "addr:housenumber":"47",
    "addr:postcode":"4100",
    "addr:street":"Gyrstinge Bygade;Gyrstinge",
    "iso:country":"DK",
    "sg:address":"Gyrstinge Bygade 47, Gyrstinge",
    "sg:city":"Ringsted",
    "sg:orig_category":"Zoneterapeuter",
    "sg:phone":"+45 57 84 53 27",
    "sg:postcode":"4100",
    "sg:province":"Danmark",
    "wof:name":"Klinik for Zoneterapi",
    "wof:placetype":"venue"
},
  "geometry": {"coordinates":[11.7875862122,55.4458961487],"type":"Point"}
}