{
  "type": "Feature",
  "properties": {
    "addr:full":"Fmd.: Anton Thorskov, S\u00f8ren Andreasens Vej 8 F\u00e5revejle Danmark 4540",
    "addr:housenumber":"8",
    "addr:postcode":"4540",
    "addr:street":"Andreasens Vej",
    "iso:country":"DK",
    "sg:address":"Fmd.: Anton Thorskov, S\u00f8ren Andreasens Vej 8",
    "sg:city":"F\u00e5revejle",
    "sg:orig_category":"Kirkelige foreninger",
    "sg:phone":"+45 59 65 56 26",
    "sg:postcode":"4540",
    "sg:province":"Danmark",
    "wof:name":"Indre Mision, F\u00e5revejle",
    "wof:placetype":"venue"
},
  "geometry": {"coordinates":[-102.1564025879,33.8074111938],"type":"Point"}
}