{
  "type": "Feature",
  "properties": {
    "addr:full":"A. W. Holms Vej 1 B Gilleleje Danmark 3250",
    "addr:housenumber":"1 b",
    "addr:postcode":"3250",
    "addr:street":"A. W. Holms Vej",
    "iso:country":"DK",
    "sg:address":"A. W. Holms Vej 1 B",
    "sg:city":"Gilleleje",
    "sg:orig_category":"Glarmestre og glarmagere",
    "sg:phone":"+45 48 30 00 63",
    "sg:postcode":"3250",
    "sg:province":"Danmark",
    "wof:name":"Gilleleje Vinduer",
    "wof:placetype":"venue"
},
  "geometry": {"coordinates":[12.2995014191,56.1264343262],"type":"Point"}
}