{
  "type": "Feature",
  "properties": {
    "addr:full":"Rendbjergvej 12 Egernsund Danmark 6320",
    "addr:housenumber":"12",
    "addr:postcode":"6320",
    "addr:street":"Rendbjergvej",
    "iso:country":"DK",
    "sg:address":"Rendbjergvej 12",
    "sg:city":"Egernsund",
    "sg:orig_category":"Feriekolonier",
    "sg:phone":"+45 74 44 23 20",
    "sg:postcode":"6320",
    "sg:province":"Danmark",
    "wof:name":"Rendbjerg Feriekoloni",
    "wof:placetype":"venue"
},
  "geometry": {"coordinates":[9.6052465439,54.9049377441],"type":"Point"}
}