{
  "type": "Feature",
  "properties": {
    "addr:full":"Artillerivej 149 K\u00f8benhavn S Danmark 2300",
    "addr:housenumber":"149",
    "addr:postcode":"2300",
    "addr:street":"Artillerivej;S Danmark",
    "iso:country":"DK",
    "sg:address":"Artillerivej 149",
    "sg:city":"K\u00f8benhavn S",
    "sg:orig_category":"Autoreparation og -service",
    "sg:phone":"+45 32 96 68 68",
    "sg:postcode":"2300",
    "sg:province":"Danmark",
    "wof:name":"J B Auto- og Pladev\u00e6rksted",
    "wof:placetype":"venue"
},
  "geometry": {"coordinates":[-78.1299133301,36.7267417908],"type":"Point"}
}