{
  "type": "Feature",
  "properties": {
    "addr:full":"Kultur- og socialforvaltningen, Kirkevej 5 Gedved Danmark 8751",
    "addr:housenumber":"5",
    "addr:postcode":"8751",
    "addr:street":"Kirkevej",
    "iso:country":"DK",
    "sg:address":"Kultur- og socialforvaltningen, Kirkevej 5",
    "sg:city":"Gedved",
    "sg:orig_category":"Dagplejeformidling",
    "sg:phone":"+45 79 69 69 69",
    "sg:postcode":"8751",
    "sg:province":"Danmark",
    "wof:name":"Dagplejeformidlingen",
    "wof:placetype":"venue"
},
  "geometry": {"coordinates":[9.8441801071,55.9348068237],"type":"Point"}
}