{
  "type": "Feature",
  "properties": {
    "addr:full":"\u00c5havevej 86 Silkeborg Danmark 8600",
    "addr:housenumber":"86",
    "addr:postcode":"8600",
    "addr:street":"Aahavevej",
    "iso:country":"DK",
    "sg:address":"\u00c5havevej 86",
    "sg:city":"Silkeborg",
    "sg:orig_category":"Malermestre",
    "sg:phone":"+45 86 81 41 31",
    "sg:postcode":"8600",
    "sg:province":"Danmark",
    "wof:name":"Pedersen, Steen",
    "wof:placetype":"venue"
},
  "geometry": {"coordinates":[9.5555114746,56.1624984741],"type":"Point"}
}