{
  "type": "Feature",
  "properties": {
    "addr:full":"N\u00f8rregade 56 - 58 Vejen Danmark 6600",
    "addr:housenumber":"56 58",
    "addr:postcode":"6600",
    "addr:street":"Norregade",
    "iso:country":"DK",
    "sg:address":"N\u00f8rregade 56 - 58",
    "sg:city":"Vejen",
    "sg:orig_category":"Faglige organisationer og foreninger",
    "sg:phone":"+45 75 36 78 88",
    "sg:postcode":"6600",
    "sg:province":"Danmark",
    "wof:name":"HK, Vejen afdeling",
    "wof:placetype":"venue"
},
  "geometry": {"coordinates":[9.1394119263,55.4790611267],"type":"Point"}
}