{
  "type": "Feature",
  "properties": {
    "addr:full":"\u00d8stre Alle 58 Gilleleje Danmark 3250",
    "addr:housenumber":"58",
    "addr:postcode":"3250",
    "addr:street":"Ostre Alle",
    "iso:country":"DK",
    "sg:address":"\u00d8stre Alle 58",
    "sg:city":"Gilleleje",
    "sg:orig_category":"Transport",
    "sg:phone":"+45 40 41 38 67",
    "sg:postcode":"3250",
    "sg:province":"Danmark",
    "wof:name":"T.E. Transport",
    "wof:placetype":"venue"
},
  "geometry": {"coordinates":[12.3290157318,56.1197853088],"type":"Point"}
}