{
  "type": "Feature",
  "properties": {
    "addr:full":"Fredens Torv 2 \u00c5rhus C Danmark 8000",
    "addr:housenumber":"2",
    "addr:postcode":"8000",
    "addr:street":"Fredens Torv",
    "iso:country":"DK",
    "sg:address":"Fredens Torv 2",
    "sg:city":"\u00c5rhus C",
    "sg:orig_category":"Filmproduktion",
    "sg:phone":"+45 86 12 40 22",
    "sg:postcode":"8000",
    "sg:province":"Danmark",
    "wof:name":"Retrospect Film & TV Produktion",
    "wof:placetype":"venue"
},
  "geometry": {"coordinates":[4.717400074,49.7588005066],"type":"Point"}
}