{
  "type": "Feature",
  "properties": {
    "iso:country":"DK",
    "sg:address":"Klostervej 10",
    "sg:city":"Ry",
    "sg:orig_category":"Blomsterhandlere",
    "sg:phone":"+45 86 89 37 15",
    "sg:postcode":"8680",
    "sg:province":"Danmark",
    "wof:name":"Flora",
    "wof:placetype":"venue"
},
  "geometry": {"coordinates":[9.7575473785,56.0918045044],"type":"Point"}
}