{
  "type": "Feature",
  "properties": {
    "iso:country":"DK",
    "sg:address":"Konsulentkontoret, Lille S\u00f8gade 10",
    "sg:city":"Silkeborg",
    "sg:orig_category":"\u00c3\u02dcvrige skoler",
    "sg:phone":"+45 86 81 19 44",
    "sg:postcode":"8600",
    "sg:province":"Danmark",
    "wof:name":"Erhvervspraktik, Ungdomsvejledning",
    "wof:placetype":"venue"
},
  "geometry": {"coordinates":[9.5524425507,56.1693305969],"type":"Point"}
}