{
  "type": "Feature",
  "properties": {
    "addr:full":"Saturnvej 8, Uglev Thyholm Danmark 7790",
    "addr:housenumber":"8",
    "addr:postcode":"7790",
    "addr:street":"Saturnvej;Uglev",
    "iso:country":"DK",
    "sg:address":"Saturnvej 8, Uglev",
    "sg:city":"Thyholm",
    "sg:classifiers":[
        {
            "category":"Manufacturing",
            "subcategory":"Tobacco Products",
            "type":"Manufacturing & Wholesale Goods"
        }
    ],
    "sg:phone":"+45 97 87 50 26",
    "sg:postcode":"7790",
    "sg:province":"Danmark",
    "sg:tags":[
        "manufacturer"
    ],
    "wof:name":"Lauritsen, I. P.",
    "wof:placetype":"venue"
},
  "geometry": {"coordinates":[8.525765419,56.6507072449],"type":"Point"}
}