{
  "type": "Feature",
  "properties": {
    "addr:full":"Fmd.: Sigurd Kj\u00e6rgaard, Nybovej 17 Aalborg Danmark 9000",
    "addr:housenumber":"17",
    "addr:postcode":"9000",
    "addr:street":"Nybovej",
    "iso:country":"DK",
    "sg:address":"Fmd.: Sigurd Kj\u00e6rgaard, Nybovej 17",
    "sg:city":"Aalborg",
    "sg:orig_category":"Hobbybetonede foreninger",
    "sg:phone":"+45 98 12 09 97",
    "sg:postcode":"9000",
    "sg:province":"Danmark",
    "wof:name":"Brevdueforeningen DAN 023 Aalborg",
    "wof:placetype":"venue"
},
  "geometry": {"coordinates":[9.9162902832,57.0493545532],"type":"Point"}
}