{
  "type": "Feature",
  "properties": {
    "addr:full":"Kirke Alle 9 S\u00f8nderborg Danmark 6400",
    "addr:housenumber":"9",
    "addr:postcode":"6400",
    "addr:street":"Kirke Alle",
    "iso:country":"DK",
    "sg:address":"Kirke Alle 9",
    "sg:city":"S\u00f8nderborg",
    "sg:orig_category":"Dagcentre",
    "sg:phone":"+45 74 42 81 66",
    "sg:postcode":"6400",
    "sg:province":"Danmark",
    "wof:name":"Dagcentret Alleen",
    "wof:placetype":"venue"
},
  "geometry": {"coordinates":[11.1919002533,62.5022697449],"type":"Point"}
}