{
  "type": "Feature",
  "properties": {
    "iso:country":"DK",
    "sg:address":"Vejlevej 114, Stouby",
    "sg:city":"Stouby",
    "sg:orig_category":"Landbrugsmaskiner",
    "sg:phone":"+45 75 89 77 82",
    "sg:postcode":"7140",
    "sg:province":"Danmark",
    "wof:name":"Traktorg\u00e5rden",
    "wof:placetype":"venue"
},
  "geometry": {"coordinates":[9.7896795273,55.7045059204],"type":"Point"}
}