{
  "type": "Feature",
  "properties": {
    "iso:country":"DK",
    "sg:address":"S\u00f8ndergade 3",
    "sg:city":"Br\u00f8rup",
    "sg:orig_category":"Optikere",
    "sg:phone":"+45 75 38 46 47",
    "sg:postcode":"6650",
    "sg:province":"Danmark",
    "wof:name":"Br\u00f8rup Optik",
    "wof:placetype":"venue"
},
  "geometry": {"coordinates":[-93.1630935669,32.8507347107],"type":"Point"}
}