{
  "type": "Feature",
  "properties": {
    "addr:full":"Platanvej 12 Frederiksberg Danmark 1810",
    "addr:housenumber":"12;1810",
    "addr:street":"Platanvej",
    "iso:country":"DK",
    "sg:address":"Platanvej 12",
    "sg:city":"Frederiksberg",
    "sg:orig_category":"Forsikringer",
    "sg:phone":"+45 33 21 83 11",
    "sg:postcode":"1810",
    "sg:province":"Danmark",
    "wof:name":"Ulykkesforsikringsforbundet for dansk Fiskeri",
    "wof:placetype":"venue"
},
  "geometry": {"coordinates":[12.5393857956,55.6703414917],"type":"Point"}
}