{
  "type": "Feature",
  "properties": {
    "addr:full":"\u00d8stre Gjesingvej 19 Esbjerg N Danmark 6715",
    "addr:housenumber":"19",
    "addr:postcode":"6715",
    "addr:street":"Ostre Gjesingvej",
    "iso:country":"DK",
    "sg:address":"\u00d8stre Gjesingvej 19",
    "sg:city":"Esbjerg N",
    "sg:orig_category":"Blikkenslagere",
    "sg:phone":"+45 75 12 96 22",
    "sg:postcode":"6715",
    "sg:province":"Danmark",
    "wof:name":"Nilsen & S\u00f8n, I. C.",
    "wof:placetype":"venue"
},
  "geometry": {"coordinates":[8.4564428329,55.5065727234],"type":"Point"}
}