{
  "type": "Feature",
  "properties": {
    "iso:country":"DK",
    "sg:address":"N\u00f8rregade 9",
    "sg:city":"Grindsted",
    "sg:orig_category":"Boligtekstil",
    "sg:phone":"+45 75 31 00 00",
    "sg:postcode":"7200",
    "sg:province":"Danmark",
    "wof:name":"BO-NYT",
    "wof:placetype":"venue"
},
  "geometry": {"coordinates":[8.9273004532,55.7584075928],"type":"Point"}
}