{
  "type": "Feature",
  "properties": {
    "addr:full":"Vestenskovvej 10 Nakskov Danmark 4900",
    "addr:housenumber":"10",
    "addr:postcode":"4900",
    "addr:street":"Vestenskovvej",
    "iso:country":"DK",
    "sg:address":"Vestenskovvej 10",
    "sg:city":"Nakskov",
    "sg:orig_category":"Forsamlingshuse",
    "sg:phone":"+45 54 94 86 82",
    "sg:postcode":"4900",
    "sg:province":"Danmark",
    "wof:name":"Vestenskovs Forsamlingshus",
    "wof:placetype":"venue"
},
  "geometry": {"coordinates":[11.085814476,54.7812843323],"type":"Point"}
}