{
  "type": "Feature",
  "properties": {
    "addr:full":"K\u00e6rrimmervej 2 Vildbjerg Danmark 7480",
    "addr:housenumber":"2",
    "addr:postcode":"7480",
    "addr:street":"Kaerrimmervej",
    "iso:country":"DK",
    "sg:address":"K\u00e6rrimmervej 2",
    "sg:city":"Vildbjerg",
    "sg:orig_category":"Autoreparation og -service",
    "sg:phone":"+45 97 13 21 21",
    "sg:postcode":"7480",
    "sg:province":"Danmark",
    "wof:name":"Vesterkilde Auto",
    "wof:placetype":"venue"
},
  "geometry": {"coordinates":[8.7193403244,56.1604423523],"type":"Point"}
}