{
  "type": "Feature",
  "properties": {
    "addr:full":"Rytterg\u00e5rdsvej 135 Farum Danmark 3520",
    "addr:housenumber":"135",
    "addr:postcode":"3520",
    "addr:street":"Ryttergaardsvej",
    "iso:country":"DK",
    "sg:address":"Rytterg\u00e5rdsvej 135",
    "sg:city":"Farum",
    "sg:orig_category":"Fritidsklubber",
    "sg:phone":"+45 44 95 97 55",
    "sg:postcode":"3520",
    "sg:province":"Danmark",
    "wof:name":"Idr\u00e6tten",
    "wof:placetype":"venue"
},
  "geometry": {"coordinates":[12.3565397263,55.8152351379],"type":"Point"}
}