{
  "type": "Feature",
  "properties": {
    "iso:country":"DK",
    "sg:address":"Hylkevej 96",
    "sg:city":"Skanderborg",
    "sg:orig_category":"Bagere",
    "sg:phone":"+45 86 53 80 12",
    "sg:postcode":"8660",
    "sg:province":"Danmark",
    "wof:name":"Hylke Bageri",
    "wof:placetype":"venue"
},
  "geometry": {"coordinates":[9.93344,55.993561],"type":"Point"}
}