{
  "type": "Feature",
  "properties": {
    "addr:full":"N\u00f8rregade 1, 1. Horsens Danmark 8700",
    "addr:housenumber":"1 1",
    "addr:postcode":"8700",
    "addr:street":"Norregade",
    "iso:country":"DK",
    "sg:address":"N\u00f8rregade 1, 1.",
    "sg:city":"Horsens",
    "sg:orig_category":"Kirurgi",
    "sg:phone":"+45 75 61 57 77",
    "sg:postcode":"8700",
    "sg:province":"Danmark",
    "wof:name":"Hansen, Carsten",
    "wof:placetype":"venue"
},
  "geometry": {"coordinates":[9.8508443832,55.8628044128],"type":"Point"}
}