{
  "type": "Feature",
  "properties": {
    "iso:country":"DK",
    "sg:address":"Cikorievej 1",
    "sg:city":"Holb\u00e6k",
    "sg:orig_category":"Kursusudbydere",
    "sg:phone":"+45 59 44 19 08",
    "sg:postcode":"4300",
    "sg:province":"Danmark",
    "sg:website":"www.mckursus.dk",
    "wof:name":"MC Kursus ApS",
    "wof:placetype":"venue"
},
  "geometry": {"coordinates":[76.3070983887,14.277130127],"type":"Point"}
}