{
  "type": "Feature",
  "properties": {
    "addr:full":"M\u00f8ltrupvej 70 Vildbjerg Danmark 7480",
    "addr:housenumber":"70",
    "addr:postcode":"7480",
    "addr:street":"Moltrupvej",
    "iso:country":"DK",
    "sg:address":"M\u00f8ltrupvej 70",
    "sg:city":"Vildbjerg",
    "sg:orig_category":"Statslige direktorater og styrelser",
    "sg:phone":"+45 97 13 18 00",
    "sg:postcode":"7480",
    "sg:province":"Danmark",
    "wof:name":"M\u00f8ltrup optagelseshjem",
    "wof:placetype":"venue"
},
  "geometry": {"coordinates":[8.7566404343,56.1766815186],"type":"Point"}
}