{
  "type": "Feature",
  "properties": {
    "addr:full":"Griffenfeldsgade 41 K\u00f8benhavn N Danmark 2200",
    "addr:housenumber":"41",
    "addr:postcode":"2200",
    "addr:street":"Griffenfeldsgade;Kobenhavn N Danmark",
    "iso:country":"DK",
    "sg:address":"Griffenfeldsgade 41",
    "sg:city":"K\u00f8benhavn N",
    "sg:orig_category":"Foreninger og organisationer",
    "sg:phone":"+45 35 35 06 08",
    "sg:postcode":"2200",
    "sg:province":"Danmark",
    "wof:name":"Venstresocialisterne Landsorganisation",
    "wof:placetype":"venue"
},
  "geometry": {"coordinates":[-76.4168395996,37.452419281],"type":"Point"}
}