{
  "type": "Feature",
  "properties": {
    "addr:full":"B\u00f8rupvej 211 A Tranbjerg Danmark 8310",
    "addr:housenumber":"211 a",
    "addr:postcode":"8310",
    "addr:street":"Borupvej",
    "iso:country":"DK",
    "sg:address":"B\u00f8rupvej 211 A",
    "sg:city":"Tranbjerg",
    "sg:orig_category":"Forlag",
    "sg:phone":"+45 86 29 67 97",
    "sg:postcode":"8310",
    "sg:province":"Danmark",
    "wof:name":"Benja, Forlaget",
    "wof:placetype":"venue"
},
  "geometry": {"coordinates":[10.1249141693,56.0984420776],"type":"Point"}
}