{
  "type": "Feature",
  "properties": {
    "addr:full":"Thyregodsvej 14 Valby Danmark 2500",
    "addr:housenumber":"14",
    "addr:postcode":"2500",
    "addr:street":"Thyregodsvej",
    "iso:country":"DK",
    "sg:address":"Thyregodsvej 14",
    "sg:city":"Valby",
    "sg:orig_category":"Integrerede institutioner",
    "sg:phone":"+45 36 30 23 79",
    "sg:postcode":"2500",
    "sg:province":"Danmark",
    "wof:name":"Dag- og skoleinstitutionen Valbyh\u00f8j",
    "wof:placetype":"venue"
},
  "geometry": {"coordinates":[12.5116453171,55.6625785828],"type":"Point"}
}