{
  "type": "Feature",
  "properties": {
    "addr:full":"Vestermarksvej 4 Vejen Danmark 6600",
    "addr:housenumber":"4",
    "addr:postcode":"6600",
    "addr:street":"Vestermarksvej",
    "iso:country":"DK",
    "sg:address":"Vestermarksvej 4",
    "sg:city":"Vejen",
    "sg:classifiers":[
        {
            "category":"Restaurant",
            "type":"Food & Drink"
        }
    ],
    "sg:phone":"+45 75 36 64 64",
    "sg:postcode":"6600",
    "sg:province":"Danmark",
    "wof:name":"McDonald's",
    "wof:placetype":"venue"
},
  "geometry": {"coordinates":[9.1275501251,55.4935836792],"type":"Point"}
}