{
  "type": "Feature",
  "properties": {
    "iso:country":"DK",
    "sg:address":"Falkoner Alle 8",
    "sg:city":"Frederiksberg",
    "sg:classifiers":[
        {
            "category":"Banks & Credit Unions",
            "subcategory":"Bank",
            "type":"Services"
        }
    ],
    "sg:phone":"+45 33 86 23 80",
    "sg:postcode":"2000",
    "sg:province":"Danmark",
    "sg:tags":[
        "banker"
    ],
    "sg:website":"www.danskebank.dk",
    "wof:name":"Danske Bank",
    "wof:placetype":"venue"
},
  "geometry": {"coordinates":[12.533723,55.678963],"type":"Point"}
}