{
  "type": "Feature",
  "properties": {
    "addr:full":"Syrenvej 39 A Vojens Danmark 6500",
    "addr:housenumber":"39 a",
    "addr:postcode":"6500",
    "addr:street":"Syrenvej",
    "iso:country":"DK",
    "sg:address":"Syrenvej 39 A",
    "sg:city":"Vojens",
    "sg:orig_category":"Supermarkeder",
    "sg:phone":"+45 74 54 14 48",
    "sg:postcode":"6500",
    "sg:province":"Danmark",
    "wof:name":"GB - Superland",
    "wof:placetype":"venue"
},
  "geometry": {"coordinates":[9.3135547638,55.2442245483],"type":"Point"}
}