{
  "type": "Feature",
  "properties": {
    "addr:full":"Emil M\u00f8llers Gade 105 Horsens Danmark 8700",
    "addr:housenumber":"105",
    "addr:postcode":"8700",
    "addr:street":"Emil Mollers Gade",
    "iso:country":"DK",
    "sg:address":"Emil M\u00f8llers Gade 105",
    "sg:city":"Horsens",
    "sg:classifiers":[
        {
            "category":"Restaurant",
            "type":"Food & Drink"
        }
    ],
    "sg:phone":"+45 75 62 74 34",
    "sg:postcode":"8700",
    "sg:province":"Danmark",
    "wof:name":"Pusterummet",
    "wof:placetype":"venue"
},
  "geometry": {"coordinates":[9.8342628479,55.8693733215],"type":"Point"}
}