{
  "type": "Feature",
  "properties": {
    "addr:full":"Ryesgade 23, 3. \u00c5rhus C Danmark 8000",
    "addr:housenumber":"23 3",
    "addr:postcode":"8000",
    "addr:street":"Ryesgade",
    "iso:country":"DK",
    "sg:address":"Ryesgade 23, 3.",
    "sg:city":"\u00c5rhus C",
    "sg:orig_category":"Finansiering",
    "sg:phone":"+45 86 18 26 00",
    "sg:postcode":"8000",
    "sg:province":"Danmark",
    "wof:name":"Dansk Investering \u00c5rhus A/S",
    "wof:placetype":"venue"
},
  "geometry": {"coordinates":[4.717400074,49.7588005066],"type":"Point"}
}