{
  "type": "Feature",
  "properties": {
    "iso:country":"DK",
    "sg:address":"Skolegade 36",
    "sg:city":"Holstebro",
    "sg:orig_category":"Slagter og viktualie",
    "sg:phone":"+45 97 42 03 09",
    "sg:postcode":"7500",
    "sg:province":"Danmark",
    "wof:name":"Lange, Slagtermester",
    "wof:placetype":"venue"
},
  "geometry": {"coordinates":[8.6113042831,56.3614997864],"type":"Point"}
}