{
  "type": "Feature",
  "properties": {
    "addr:full":"N\u00f8vlingvej 178 Gistrup Danmark 9260",
    "addr:housenumber":"178",
    "addr:postcode":"9260",
    "addr:street":"Novlingvej",
    "iso:country":"DK",
    "sg:address":"N\u00f8vlingvej 178",
    "sg:city":"Gistrup",
    "sg:orig_category":"Autoreparation og -service",
    "sg:phone":"+45 98 31 49 48",
    "sg:postcode":"9260",
    "sg:province":"Danmark",
    "sg:website":"www.auto85.dk",
    "wof:name":"Auto 85",
    "wof:placetype":"venue"
},
  "geometry": {"coordinates":[9.9600343704,56.9701385498],"type":"Point"}
}