{
  "type": "Feature",
  "properties": {
    "iso:country":"DK",
    "sg:address":"Vesterbrogade 186",
    "sg:city":"Frederiksberg",
    "sg:orig_category":"Garn",
    "sg:phone":"+45 33 24 19 46",
    "sg:postcode":"1800",
    "sg:province":"Danmark",
    "sg:website":"www.axc-strik.homepage.dk",
    "wof:name":"A. C. Strik",
    "wof:placetype":"venue"
},
  "geometry": {"coordinates":[12.5350761414,55.6706352234],"type":"Point"}
}