{
  "type": "Feature",
  "properties": {
    "addr:full":"Parkv\u00e6nget 10 Tranbjerg Danmark 8310",
    "addr:housenumber":"10",
    "addr:postcode":"8310",
    "addr:street":"Parkvaenget",
    "iso:country":"DK",
    "sg:address":"Parkv\u00e6nget 10",
    "sg:city":"Tranbjerg",
    "sg:orig_category":"Oplysningsforbund",
    "sg:phone":"+45 86 29 05 28",
    "sg:postcode":"8310",
    "sg:province":"Danmark",
    "wof:name":"Oplysningsforbundet af 1980",
    "wof:placetype":"venue"
},
  "geometry": {"coordinates":[10.1377973557,56.0914382935],"type":"Point"}
}