{
  "type": "Feature",
  "properties": {
    "iso:country":"DK",
    "sg:address":"Havnegade 1",
    "sg:city":"Svendborg",
    "sg:orig_category":"Kirker",
    "sg:postcode":"5700",
    "sg:province":"Danmark",
    "wof:name":"Katolsk Sct. Knuds Kirke",
    "wof:placetype":"venue"
},
  "geometry": {"coordinates":[10.6128330231,55.0627746582],"type":"Point"}
}