{
  "type": "Feature",
  "properties": {
    "addr:full":"Gammel \u00d8sterg\u00e5rdsvej 5 Malling Danmark 8340",
    "addr:housenumber":"5",
    "addr:postcode":"8340",
    "addr:street":"Gammel Ostergaardsvej",
    "iso:country":"DK",
    "sg:address":"Gammel \u00d8sterg\u00e5rdsvej 5",
    "sg:city":"Malling",
    "sg:orig_category":"Solvarme",
    "sg:phone":"+45 86 93 33 22",
    "sg:postcode":"8340",
    "sg:province":"Danmark",
    "wof:name":"Lykkegaard VVS & Energiteknik",
    "wof:placetype":"venue"
},
  "geometry": {"coordinates":[10.1924476624,56.0387992859],"type":"Point"}
}