{
  "type": "Feature",
  "properties": {
    "addr:full":"Fmd.: Nick Hansen, Engdiget 12, Hvam Aalestrup Danmark 9620",
    "addr:housenumber":"12",
    "addr:postcode":"9620",
    "addr:street":"Engdiget",
    "iso:country":"DK",
    "sg:address":"Fmd.: Nick Hansen, Engdiget 12, Hvam",
    "sg:city":"Aalestrup",
    "sg:orig_category":"Andelsboligforeninger",
    "sg:phone":"+45 98 64 29 50",
    "sg:postcode":"9620",
    "sg:province":"Danmark",
    "wof:name":"Engdiget, Andelsboligforeningen",
    "wof:placetype":"venue"
},
  "geometry": {"coordinates":[9.4901504517,56.6938285828],"type":"Point"}
}