{
  "type": "Feature",
  "properties": {
    "addr:full":"Pr\u00e6stemarksvej 8 Roskilde Danmark 4000",
    "addr:housenumber":"8",
    "addr:postcode":"4000",
    "addr:street":"Praestemarksvej",
    "iso:country":"DK",
    "sg:address":"Pr\u00e6stemarksvej 8",
    "sg:city":"Roskilde",
    "sg:orig_category":"El-artikler",
    "sg:phone":"+45 46 75 63 22",
    "sg:postcode":"4000",
    "sg:province":"Danmark",
    "wof:name":"J\u00f8rgensen & Co. A/S",
    "wof:placetype":"venue"
},
  "geometry": {"coordinates":[12.1109857559,55.6429100037],"type":"Point"}
}