{
  "type": "Feature",
  "properties": {
    "addr:full":"Busgadehuset, Frederiksgade 25 \u00c5rhus C Danmark 8000",
    "addr:housenumber":"25",
    "addr:postcode":"8000",
    "addr:street":"Frederiksgade",
    "iso:country":"DK",
    "sg:address":"Busgadehuset, Frederiksgade 25",
    "sg:city":"\u00c5rhus C",
    "sg:classifiers":[
        {
            "category":"Restaurant",
            "type":"Food & Drink"
        }
    ],
    "sg:phone":"+45 86 13 04 79",
    "sg:postcode":"8000",
    "sg:province":"Danmark",
    "wof:name":"Anders, Hos",
    "wof:placetype":"venue"
},
  "geometry": {"coordinates":[12.5930995941,55.6829986572],"type":"Point"}
}