{
  "type": "Feature",
  "properties": {
    "iso:country":"DK",
    "sg:address":"v/ J\u00f8rgen Skott, Dragsmurvej 11, Begtrup",
    "sg:city":"Knebel",
    "sg:orig_category":"Spejderkorps",
    "sg:phone":"+45 86 35 18 17",
    "sg:postcode":"8420",
    "sg:province":"Danmark",
    "wof:name":"Sct. Georgsgildet",
    "wof:placetype":"venue"
},
  "geometry": {"coordinates":[10.3770122528,56.1816596985],"type":"Point"}
}