{
  "type": "Feature",
  "properties": {
    "addr:full":"Gyvelvej 14 Vejle Danmark 7100",
    "addr:housenumber":"14",
    "addr:postcode":"7100",
    "addr:street":"Gyvelvej",
    "iso:country":"DK",
    "sg:address":"Gyvelvej 14",
    "sg:city":"Vejle",
    "sg:orig_category":"Motorcykler",
    "sg:phone":"+45 75 72 73 96",
    "sg:postcode":"7100",
    "sg:province":"Danmark",
    "wof:name":"Ulrik's MC Import Ducati",
    "wof:placetype":"venue"
},
  "geometry": {"coordinates":[9.5199394226,55.6916732788],"type":"Point"}
}