{
  "type": "Feature",
  "properties": {
    "iso:country":"DK",
    "sg:address":"v/ Birgit Larsen, Knudskovparken 75 B",
    "sg:city":"Holb\u00e6k",
    "sg:orig_category":"Spejderkorps",
    "sg:phone":"+45 59 44 37 30",
    "sg:postcode":"4300",
    "sg:province":"Danmark",
    "wof:name":"FDF Holb\u00e6k",
    "wof:placetype":"venue"
},
  "geometry": {"coordinates":[77.2480392456,14.1354398727],"type":"Point"}
}