{
  "type": "Feature",
  "properties": {
    "addr:full":"Parkvej 3 Faaborg Danmark 5600",
    "addr:housenumber":"3",
    "addr:postcode":"5600",
    "addr:street":"Parkvej",
    "iso:country":"DK",
    "sg:address":"Parkvej 3",
    "sg:city":"Faaborg",
    "sg:orig_category":"Farve og tapet",
    "sg:phone":"+45 62 61 05 65",
    "sg:postcode":"5600",
    "sg:province":"Danmark",
    "wof:name":"Malernes Lagersalg",
    "wof:placetype":"venue"
},
  "geometry": {"coordinates":[10.255645752,55.0901260376],"type":"Point"}
}