{
  "type": "Feature",
  "properties": {
    "addr:full":"Fredensgade 28 Kolding Danmark 6000",
    "addr:housenumber":"28",
    "addr:postcode":"6000",
    "addr:street":"Fredensgade",
    "iso:country":"DK",
    "sg:address":"Fredensgade 28",
    "sg:city":"Kolding",
    "sg:classifiers":[
        {
            "category":"Restaurant",
            "type":"Food & Drink"
        }
    ],
    "sg:phone":"+45 75 53 53 83",
    "sg:postcode":"6000",
    "sg:province":"Danmark",
    "wof:name":"Munke - K\u00e6lderen",
    "wof:placetype":"venue"
},
  "geometry": {"coordinates":[9.476313591,55.4859466553],"type":"Point"}
}