{
  "type": "Feature",
  "properties": {
    "addr:full":"Fmd.: Tove Kamp Hansen, T\u00f8ndborgvej 29, T\u00f8ndborg Kjellerup Danmark 8620",
    "addr:housenumber":"29",
    "addr:postcode":"8620",
    "addr:street":"Tove Kamp;Tondborgvej;Tondborg",
    "iso:country":"DK",
    "sg:address":"Fmd.: Tove Kamp Hansen, T\u00f8ndborgvej 29, T\u00f8ndborg",
    "sg:city":"Kjellerup",
    "sg:orig_category":"Musik og sang",
    "sg:phone":"+45 86 88 89 06",
    "sg:postcode":"8620",
    "sg:province":"Danmark",
    "wof:name":"Silkeborg Koret",
    "wof:placetype":"venue"
},
  "geometry": {"coordinates":[9.430934906,56.2877655029],"type":"Point"}
}