{
  "type": "Feature",
  "properties": {
    "addr:full":"\u00d8stervang 3 Varde Danmark 6800",
    "addr:housenumber":"3",
    "addr:postcode":"6800",
    "addr:street":"Ostervang",
    "iso:country":"DK",
    "sg:address":"\u00d8stervang 3",
    "sg:city":"Varde",
    "sg:orig_category":"Handicapboliger",
    "sg:phone":"+45 75 21 16 58",
    "sg:postcode":"6800",
    "sg:province":"Danmark",
    "wof:name":"Bo-\u00d8stervang",
    "wof:placetype":"venue"
},
  "geometry": {"coordinates":[8.4832010269,55.6214141846],"type":"Point"}
}