{
  "type": "Feature",
  "properties": {
    "addr:full":"Skolevej 2-4 Ullerslev Danmark 5540",
    "addr:housenumber":"2-4",
    "addr:postcode":"5540",
    "addr:street":"Skolevej",
    "iso:country":"DK",
    "sg:address":"Skolevej 2-4",
    "sg:city":"Ullerslev",
    "sg:orig_category":"Fritidsklubber",
    "sg:phone":"+45 63 35 12 26",
    "sg:postcode":"5540",
    "sg:province":"Danmark",
    "wof:name":"Juniorklubben",
    "wof:placetype":"venue"
},
  "geometry": {"coordinates":[10.6711616516,55.3588981628],"type":"Point"}
}