{
  "type": "Feature",
  "properties": {
    "addr:full":"Industrivej 5 Spentrup Danmark 8981",
    "addr:housenumber":"5",
    "addr:postcode":"8981",
    "addr:street":"Industrivej",
    "iso:country":"DK",
    "sg:address":"Industrivej 5",
    "sg:city":"Spentrup",
    "sg:orig_category":"INGENI\u00c3\u02dcRER",
    "sg:phone":"+45 86 47 70 99",
    "sg:postcode":"8981",
    "sg:province":"Danmark",
    "wof:name":"S\u00f8rensen Ingeni\u00f8rfirma A/S, S\u00f8ren",
    "wof:placetype":"venue"
},
  "geometry": {"coordinates":[10.0297222137,56.5454559326],"type":"Point"}
}