{
  "type": "Feature",
  "properties": {
    "addr:full":"Chr. Hansensvej 5 Frederiksv\u00e6rk Danmark 3300",
    "addr:housenumber":"5",
    "addr:postcode":"3300",
    "addr:street":"Chr. Hansensvej",
    "iso:country":"DK",
    "sg:address":"Chr. Hansensvej 5",
    "sg:city":"Frederiksv\u00e6rk",
    "sg:orig_category":"Arkitekter",
    "sg:phone":"+45 47 72 02 25",
    "sg:postcode":"3300",
    "sg:province":"Danmark",
    "wof:name":"Poulsen Arkitekt MAA., Kai O.",
    "wof:placetype":"venue"
},
  "geometry": {"coordinates":[1.7223600149,46.8559417725],"type":"Point"}
}