{
  "type": "Feature",
  "properties": {
    "addr:full":"Birkevej 27, Hornum Aars Danmark 9600",
    "addr:housenumber":"27",
    "addr:postcode":"9600",
    "addr:street":"Birkevej",
    "iso:country":"DK",
    "sg:address":"Birkevej 27, Hornum",
    "sg:city":"Aars",
    "sg:orig_category":"Maskinstationer",
    "sg:phone":"+45 98 66 11 10",
    "sg:postcode":"9600",
    "sg:province":"Danmark",
    "wof:name":"Gundersen, Knud Erik",
    "wof:placetype":"venue"
},
  "geometry": {"coordinates":[9.5170412064,56.8031692505],"type":"Point"}
}