{
  "type": "Feature",
  "properties": {
    "addr:full":"Schandorffstr\u00e6de 13, 2. \u00c5rhus C Danmark 8000",
    "addr:housenumber":"13 2",
    "addr:postcode":"8000",
    "addr:street":"Schandorffstraede",
    "iso:country":"DK",
    "sg:address":"Schandorffstr\u00e6de 13, 2.",
    "sg:city":"\u00c5rhus C",
    "sg:orig_category":"Faglige organisationer og foreninger",
    "sg:phone":"+45 86 13 20 77",
    "sg:postcode":"8000",
    "sg:province":"Danmark",
    "wof:name":"PMF, P\u00e6dagogisk Medhj\u00e6lper Forbund",
    "wof:placetype":"venue"
},
  "geometry": {"coordinates":[4.717400074,49.7588005066],"type":"Point"}
}