{
  "type": "Feature",
  "properties": {
    "addr:full":"Fmd.: Otto Husmann, Neesvej 55, Nees Vemb Danmark 7570",
    "addr:housenumber":"55",
    "addr:postcode":"7570",
    "addr:street":"Neesvej",
    "iso:country":"DK",
    "sg:address":"Fmd.: Otto Husmann, Neesvej 55, Nees",
    "sg:city":"Vemb",
    "sg:orig_category":"Borger- og beboerforeninger",
    "sg:phone":"+45 97 88 41 33",
    "sg:postcode":"7570",
    "sg:province":"Danmark",
    "wof:name":"Nees-Skalstrup Sogneforening",
    "wof:placetype":"venue"
},
  "geometry": {"coordinates":[8.343793869,56.343082428],"type":"Point"}
}