{
  "type": "Feature",
  "properties": {
    "iso:country":"DK",
    "sg:address":"Bagsv\u00e6rdvej 144 A",
    "sg:city":"Kongens Lyngby",
    "sg:orig_category":"Ungdomsklubber",
    "sg:phone":"+45 45 88 36 91",
    "sg:postcode":"2800",
    "sg:province":"Danmark",
    "wof:name":"Klub 144",
    "wof:placetype":"venue"
},
  "geometry": {"coordinates":[12.5368299484,55.7949905396],"type":"Point"}
}