{
  "type": "Feature",
  "properties": {
    "addr:full":"Jernbanegade 3 Brovst Danmark 9460",
    "addr:housenumber":"3",
    "addr:postcode":"9460",
    "addr:street":"Jernbanegade",
    "iso:country":"DK",
    "sg:address":"Jernbanegade 3",
    "sg:city":"Brovst",
    "sg:orig_category":"Fodplejere",
    "sg:phone":"+45 98 23 37 37",
    "sg:postcode":"9460",
    "sg:province":"Danmark",
    "wof:name":"Brovst Fod- og Hudplejeklinik",
    "wof:placetype":"venue"
},
  "geometry": {"coordinates":[9.5224790573,57.0976409912],"type":"Point"}
}