{
  "type": "Feature",
  "properties": {
    "addr:full":"Egemosevej 6 Vejstrup Danmark 5882",
    "addr:housenumber":"6",
    "addr:postcode":"5882",
    "addr:street":"Egemosevej",
    "iso:country":"DK",
    "sg:address":"Egemosevej 6",
    "sg:city":"Vejstrup",
    "sg:orig_category":"Kirker",
    "sg:postcode":"5882",
    "sg:province":"Danmark",
    "wof:name":"Vejstrup Kirke",
    "wof:placetype":"venue"
},
  "geometry": {"coordinates":[10.7097921371,55.1043777466],"type":"Point"}
}