{
  "type": "Feature",
  "properties": {
    "addr:full":"Messingvej 42 D Randers Danmark 8900",
    "addr:housenumber":"42 d",
    "addr:postcode":"8900",
    "addr:street":"Messingvej",
    "iso:country":"DK",
    "sg:address":"Messingvej 42 D",
    "sg:city":"Randers",
    "sg:orig_category":"Elektroindustri",
    "sg:phone":"+45 86 44 74 55",
    "sg:postcode":"8900",
    "sg:province":"Danmark",
    "wof:name":"Iso Matic ApS",
    "wof:placetype":"venue"
},
  "geometry": {"coordinates":[10.0498714447,56.4320259094],"type":"Point"}
}