{
  "type": "Feature",
  "properties": {
    "addr:full":"S\u00f8ndergade 3 Toftlund Danmark 6520",
    "addr:housenumber":"3",
    "addr:postcode":"6520",
    "addr:street":"Sondergade",
    "iso:country":"DK",
    "sg:address":"S\u00f8ndergade 3",
    "sg:city":"Toftlund",
    "sg:classifiers":[
        {
            "category":"Banks & Credit Unions",
            "subcategory":"Bank",
            "type":"Services"
        }
    ],
    "sg:phone":"+45 73 83 25 20",
    "sg:postcode":"6520",
    "sg:province":"Danmark",
    "sg:tags":[
        "banker"
    ],
    "sg:website":"www.danskebank.dk",
    "wof:name":"Danske Bank",
    "wof:placetype":"venue"
},
  "geometry": {"coordinates":[9.0641937256,55.1922683716],"type":"Point"}
}