{
  "type": "Feature",
  "properties": {
    "addr:full":"Gl. Hadsundvej 22 Randers Danmark 8900",
    "addr:housenumber":"22",
    "addr:postcode":"8900",
    "addr:street":"Gl. Hadsundvej",
    "iso:country":"DK",
    "sg:address":"Gl. Hadsundvej 22",
    "sg:city":"Randers",
    "sg:orig_category":"Renserier",
    "sg:phone":"+45 86 42 33 19",
    "sg:postcode":"8900",
    "sg:province":"Danmark",
    "wof:name":"Eton Rens",
    "wof:placetype":"venue"
},
  "geometry": {"coordinates":[10.0422477722,56.4671401978],"type":"Point"}
}