{
  "type": "Feature",
  "properties": {
    "addr:full":"Middelfartvej 29, Baaring Asperup Danmark 5466",
    "addr:housenumber":"29",
    "addr:postcode":"5466",
    "addr:street":"Middelfartvej",
    "iso:country":"DK",
    "sg:address":"Middelfartvej 29, Baaring",
    "sg:city":"Asperup",
    "sg:orig_category":"Autoreparation og -service",
    "sg:phone":"+45 64 48 10 02",
    "sg:postcode":"5466",
    "sg:province":"Danmark",
    "wof:name":"B\u00e5ring Auto",
    "wof:placetype":"venue"
},
  "geometry": {"coordinates":[9.9057912827,55.4908866882],"type":"Point"}
}