{
  "type": "Feature",
  "properties": {
    "addr:full":"Bagerstr\u00e6de 4 Fredensborg Danmark 3480",
    "addr:housenumber":"4",
    "addr:postcode":"3480",
    "addr:street":"Bagerstraede",
    "iso:country":"DK",
    "sg:address":"Bagerstr\u00e6de 4",
    "sg:city":"Fredensborg",
    "sg:orig_category":"Belysning",
    "sg:phone":"+45 48 48 07 45",
    "sg:postcode":"3480",
    "sg:province":"Danmark",
    "wof:name":"Id\u00e9-Lys",
    "wof:placetype":"venue"
},
  "geometry": {"coordinates":[12.4020547867,55.9782943726],"type":"Point"}
}