{
  "type": "Feature",
  "properties": {
    "addr:full":"Hasselager Stationsvej 10 Hasselager Danmark 8361",
    "addr:housenumber":"10",
    "addr:postcode":"8361",
    "addr:street":"Hasselager Stationsvej",
    "iso:country":"DK",
    "sg:address":"Hasselager Stationsvej 10",
    "sg:city":"Hasselager",
    "sg:orig_category":"Malermestre",
    "sg:phone":"+45 86 28 31 42",
    "sg:postcode":"8361",
    "sg:province":"Danmark",
    "wof:name":"Knudsen, K. & E. Ravnkilde",
    "wof:placetype":"venue"
},
  "geometry": {"coordinates":[10.100728035,56.1050834656],"type":"Point"}
}