{
  "type": "Feature",
  "properties": {
    "addr:full":"Skovagervej 2 Risskov Danmark 8240",
    "addr:housenumber":"2",
    "addr:postcode":"8240",
    "addr:street":"Skovagervej",
    "iso:country":"DK",
    "sg:address":"Skovagervej 2",
    "sg:city":"Risskov",
    "sg:orig_category":"Offentlige sygehuse",
    "sg:phone":"+45 77 89 20 00",
    "sg:postcode":"8240",
    "sg:province":"Danmark",
    "wof:name":"Psykiatrisk Hospital i \u00c5rhus",
    "wof:placetype":"venue"
},
  "geometry": {"coordinates":[10.2290678024,56.1861305237],"type":"Point"}
}