{
  "type": "Feature",
  "properties": {
    "iso:country":"DK",
    "sg:address":"Industrivej 3 ",
    "sg:city":"Bredebro",
    "sg:classifiers":[
        {
            "category":"Autos & Motor Vehicles",
            "subcategory":"Automobile Sales",
            "type":"Retail Goods"
        }
    ],
    "sg:phone":"+45 74 71 12 24",
    "sg:postcode":"6261",
    "sg:province":"Danmark",
    "sg:tags":[
        "industrial"
    ],
    "wof:name":"BREDEBRO AUTO-SERVICE A/S",
    "wof:placetype":"venue"
},
  "geometry": {"coordinates":[8.8259277344,55.0592308044],"type":"Point"}
}