{
  "type": "Feature",
  "properties": {
    "addr:full":"Fmd.: Jens K. Bach-Mose, Hovedvejen 54, Flovlev Thyholm Danmark 7790",
    "addr:housenumber":"54",
    "addr:postcode":"7790",
    "addr:street":"Hovedvejen",
    "iso:country":"DK",
    "sg:address":"Fmd.: Jens K. Bach-Mose, Hovedvejen 54, Flovlev",
    "sg:city":"Thyholm",
    "sg:orig_category":"Soldaterforeninger",
    "sg:phone":"+45 97 87 11 65",
    "sg:postcode":"7790",
    "sg:province":"Danmark",
    "wof:name":"Thyholm Soldatervennerkreds",
    "wof:placetype":"venue"
},
  "geometry": {"coordinates":[8.525765419,56.6507072449],"type":"Point"}
}