{
  "type": "Feature",
  "properties": {
    "iso:country":"DK",
    "sg:address":"Gl. Frijsenborgvej 2",
    "sg:city":"Hammel",
    "sg:orig_category":"Grillbarer",
    "sg:phone":"+45 86 96 33 23",
    "sg:postcode":"8450",
    "sg:province":"Danmark",
    "wof:name":"Grilhuset ApS",
    "wof:placetype":"venue"
},
  "geometry": {"coordinates":[9.8696146011,56.2575111389],"type":"Point"}
}