{
  "type": "Feature",
  "properties": {
    "addr:full":"Vestre Strandvej 18 Skagen Danmark 9990",
    "addr:housenumber":"18",
    "addr:postcode":"9990",
    "addr:street":"Vestre Strandvej",
    "iso:country":"DK",
    "sg:address":"Vestre Strandvej 18",
    "sg:city":"Skagen",
    "sg:orig_category":"Sejlmagere",
    "sg:phone":"+45 98 44 20 62",
    "sg:postcode":"9990",
    "sg:province":"Danmark",
    "wof:name":"Havnens Rigger- og Sejlmagerv\u00e6rksted",
    "wof:placetype":"venue"
},
  "geometry": {"coordinates":[10.5842056274,57.7184448242],"type":"Point"}
}