{
  "type": "Feature",
  "properties": {
    "iso:country":"DK",
    "sg:address":"Stationsholmen 5",
    "sg:city":"Greve",
    "sg:orig_category":"Grillbarer",
    "sg:phone":"+45 43 90 74 99",
    "sg:postcode":"2670",
    "sg:province":"Danmark",
    "wof:name":"DSB Minibar",
    "wof:placetype":"venue"
},
  "geometry": {"coordinates":[12.2959461212,55.5818595886],"type":"Point"}
}