{
  "type": "Feature",
  "properties": {
    "addr:full":"Kolloparken 27 Aalborg SV Danmark 9200",
    "addr:housenumber":"27",
    "addr:postcode":"9200",
    "addr:street":"Kolloparken",
    "iso:country":"DK",
    "sg:address":"Kolloparken 27",
    "sg:city":"Aalborg SV",
    "sg:orig_category":"Varme- og ventilation, Art.for",
    "sg:phone":"+45 98 34 35 40",
    "sg:postcode":"9200",
    "sg:province":"Danmark",
    "wof:name":"Nordjysk Energiteknik",
    "wof:placetype":"venue"
},
  "geometry": {"coordinates":[9.8189220428,56.9994010925],"type":"Point"}
}