{
  "type": "Feature",
  "properties": {
    "addr:full":"Fiskergade 28 \u00c5rhus C Danmark 8000",
    "addr:housenumber":"28",
    "addr:postcode":"8000",
    "addr:street":"Fiskergade",
    "iso:country":"DK",
    "sg:address":"Fiskergade 28",
    "sg:city":"\u00c5rhus C",
    "sg:classifiers":[
        {
            "category":"Restaurant",
            "type":"Food & Drink"
        }
    ],
    "sg:phone":"+45 86 19 46 11",
    "sg:postcode":"8000",
    "sg:province":"Danmark",
    "wof:name":"Albufeto",
    "wof:placetype":"venue"
},
  "geometry": {"coordinates":[4.717400074,49.7588005066],"type":"Point"}
}