{
  "type": "Feature",
  "properties": {
    "addr:full":"Stockflethsvej 4 Frederiksberg Danmark 2000",
    "addr:housenumber":"4",
    "addr:postcode":"2000",
    "addr:street":"Stockflethsvej",
    "iso:country":"DK",
    "sg:address":"Stockflethsvej 4",
    "sg:city":"Frederiksberg",
    "sg:orig_category":"Plejehjem",
    "sg:phone":"+45 38 21 35 90",
    "sg:postcode":"2000",
    "sg:province":"Danmark",
    "wof:name":"Vestervang, Frederiksberg Kommunes Plejehjem",
    "wof:placetype":"venue"
},
  "geometry": {"coordinates":[12.5193214417,55.6860389709],"type":"Point"}
}