{
  "type": "Feature",
  "properties": {
    "addr:full":"Plantagevej 49 Gentofte Danmark 2820",
    "addr:housenumber":"49",
    "addr:postcode":"2820",
    "addr:street":"Plantagevej",
    "iso:country":"DK",
    "sg:address":"Plantagevej 49",
    "sg:city":"Gentofte",
    "sg:classifiers":[
        {
            "category":"Professional",
            "subcategory":"Computer Services",
            "type":"Services"
        }
    ],
    "sg:phone":"+45 39 76 32 42",
    "sg:postcode":"2820",
    "sg:province":"Danmark",
    "sg:tags":[
        "edb",
        "-",
        "software"
    ],
    "wof:name":"Redhouse Data",
    "wof:placetype":"venue"
},
  "geometry": {"coordinates":[12.5246515274,55.7418746948],"type":"Point"}
}