{
  "type": "Feature",
  "properties": {
    "iso:country":"DK",
    "sg:address":"Kildevej 208",
    "sg:city":"Vejby",
    "sg:orig_category":"Malermestre",
    "sg:phone":"+45 24 82 43 11",
    "sg:postcode":"3210",
    "sg:province":"Danmark",
    "wof:name":"Malerdesign.dk",
    "wof:placetype":"venue"
},
  "geometry": {"coordinates":[12.1191520691,56.0607757568],"type":"Point"}
}