{
  "type": "Feature",
  "properties": {
    "addr:full":"Vesterlunden 1 Snertinge Danmark 4460",
    "addr:housenumber":"1",
    "addr:postcode":"4460",
    "addr:street":"Vesterlunden",
    "iso:country":"DK",
    "sg:address":"Vesterlunden 1",
    "sg:city":"Snertinge",
    "sg:orig_category":"\u00c3\u2020ldrecentre",
    "sg:phone":"+45 59 26 26 14",
    "sg:postcode":"4460",
    "sg:province":"Danmark",
    "wof:name":"\u00c6ldrecentret Vesterlunden",
    "wof:placetype":"venue"
},
  "geometry": {"coordinates":[11.3816003799,55.7144851685],"type":"Point"}
}