{
  "type": "Feature",
  "properties": {
    "addr:full":"Kronprinsensgade 13, 4 K\u00f8benhavn Danmark 1114",
    "addr:housenumber":"13 4;1114",
    "addr:street":"Kronprinsensgade",
    "iso:country":"DK",
    "sg:address":"Kronprinsensgade 13, 4",
    "sg:city":"K\u00f8benhavn",
    "sg:classifiers":[
        {
            "category":"Internet Cafe",
            "subcategory":"None",
            "type":"Food & Drink"
        }
    ],
    "sg:phone":"+45 33 14 08 96",
    "sg:postcode":"1114",
    "sg:province":"Danmark",
    "sg:website":"www.inform-service.dk",
    "wof:name":"Inform Service ApS",
    "wof:placetype":"venue"
},
  "geometry": {"coordinates":[12.5811004639,55.6797981262],"type":"Point"}
}