{
  "type": "Feature",
  "properties": {
    "addr:full":"Tingvejen 282, Starup Grindsted Danmark 7200",
    "addr:housenumber":"282",
    "addr:postcode":"7200",
    "addr:street":"Tingvejen;Starup",
    "iso:country":"DK",
    "sg:address":"Tingvejen 282, Starup",
    "sg:city":"Grindsted",
    "sg:orig_category":"Autoreparation og -service",
    "sg:phone":"+45 75 33 70 79",
    "sg:postcode":"7200",
    "sg:province":"Danmark",
    "wof:name":"Starup Autoservice",
    "wof:placetype":"venue"
},
  "geometry": {"coordinates":[8.9288702011,55.7560272217],"type":"Point"}
}