{
  "type": "Feature",
  "properties": {
    "iso:country":"DK",
    "sg:address":"Reerslevvej 52",
    "sg:city":"Hedehusene",
    "sg:orig_category":"Revisorer",
    "sg:phone":"+45 46 56 11 28",
    "sg:postcode":"2640",
    "sg:province":"Danmark",
    "wof:name":"Rusbjerg Revision",
    "wof:placetype":"venue"
},
  "geometry": {"coordinates":[12.1949138641,55.6451301575],"type":"Point"}
}