{
  "type": "Feature",
  "properties": {
    "addr:full":"Fmd.: Finn Wohlert, Teaterstien 6, 2., th. Haderslev Danmark 6100",
    "addr:housenumber":"6 2 th.",
    "addr:postcode":"6100",
    "addr:street":"Teaterstien",
    "iso:country":"DK",
    "sg:address":"Fmd.: Finn Wohlert, Teaterstien 6, 2., th.",
    "sg:city":"Haderslev",
    "sg:orig_category":"Kulturelle foreninger",
    "sg:phone":"+45 74 52 72 29",
    "sg:postcode":"6100",
    "sg:province":"Danmark",
    "wof:name":"Haderslev Skydeselskab af 1857",
    "wof:placetype":"venue"
},
  "geometry": {"coordinates":[9.4879703522,55.2505493164],"type":"Point"}
}