{
  "type": "Feature",
  "properties": {
    "addr:full":"Thinggade 18 A Skive Danmark 7800",
    "addr:housenumber":"18 a",
    "addr:postcode":"7800",
    "addr:street":"Thinggade",
    "iso:country":"DK",
    "sg:address":"Thinggade 18 A",
    "sg:city":"Skive",
    "sg:orig_category":"Rejsebureauer",
    "sg:phone":"+45 97 52 50 66",
    "sg:postcode":"7800",
    "sg:province":"Danmark",
    "sg:website":"www.fdm-travek.dk",
    "wof:name":"FDM Travel",
    "wof:placetype":"venue"
},
  "geometry": {"coordinates":[9.0287094116,56.5656776428],"type":"Point"}
}