{
  "type": "Feature",
  "properties": {
    "iso:country":"DK",
    "sg:address":"\u00d8stergade 6",
    "sg:city":"Middelfart",
    "sg:orig_category":"Blomsterhandlere",
    "sg:phone":"+45 64 41 73 73",
    "sg:postcode":"5500",
    "sg:province":"Danmark",
    "wof:name":"Acacia Blomster",
    "wof:placetype":"venue"
},
  "geometry": {"coordinates":[9.7324590683,55.4963722229],"type":"Point"}
}