{
  "type": "Feature",
  "properties": {
    "iso:country":"DK",
    "sg:address":"H\u00f8jbyvej 49 A, H\u00f8jby",
    "sg:city":"Lejre",
    "sg:orig_category":"Gartnerier",
    "sg:phone":"+45 46 48 10 98",
    "sg:postcode":"4320",
    "sg:province":"Danmark",
    "wof:name":"H\u00f8jbyvangen ApS, Gartneriet",
    "wof:placetype":"venue"
},
  "geometry": {"coordinates":[11.9678316116,55.6005630493],"type":"Point"}
}