{
  "type": "Feature",
  "properties": {
    "addr:full":"Dusg\u00e5rdvej 1, Ammitsb\u00f8l Vejle Danmark 7100",
    "addr:housenumber":"1",
    "addr:postcode":"7100",
    "addr:street":"Dusgaardvej",
    "iso:country":"DK",
    "sg:address":"Dusg\u00e5rdvej 1, Ammitsb\u00f8l",
    "sg:city":"Vejle",
    "sg:orig_category":"Havebrugsmaskiner",
    "sg:phone":"+45 75 86 47 77",
    "sg:postcode":"7100",
    "sg:province":"Danmark",
    "wof:name":"JR Maskincenter",
    "wof:placetype":"venue"
},
  "geometry": {"coordinates":[9.5368051529,55.7113952637],"type":"Point"}
}