{
  "type": "Feature",
  "properties": {
    "addr:full":"Vesterhavsvej 59 Blokhus Danmark 9492",
    "addr:housenumber":"59",
    "addr:postcode":"9492",
    "addr:street":"Vesterhavsvej",
    "iso:country":"DK",
    "sg:address":"Vesterhavsvej 59",
    "sg:city":"Blokhus",
    "sg:orig_category":"HOTELS: OG MOTELLER",
    "sg:phone":"+45 98 20 83 55",
    "sg:postcode":"9492",
    "sg:province":"Danmark",
    "sg:website":"www.hune.dk",
    "wof:name":"Hune, Motel",
    "wof:placetype":"venue"
},
  "geometry": {"coordinates":[9.6268978119,57.2476921082],"type":"Point"}
}