{
  "type": "Feature",
  "properties": {
    "addr:full":"Nyk\u00f8bingvej 45 Saksk\u00f8bing Danmark 4990",
    "addr:housenumber":"45",
    "addr:postcode":"4990",
    "addr:street":"Nykobingvej",
    "iso:country":"DK",
    "sg:address":"Nyk\u00f8bingvej 45",
    "sg:city":"Saksk\u00f8bing",
    "sg:orig_category":"Autoreparation og -service",
    "sg:phone":"+45 54 70 48 28",
    "sg:postcode":"4990",
    "sg:province":"Danmark",
    "wof:name":"Q8 Service",
    "wof:placetype":"venue"
},
  "geometry": {"coordinates":[-114.0767440796,46.4432487488],"type":"Point"}
}