{
  "type": "Feature",
  "properties": {
    "addr:full":"Stationspladsen 5 Varde Danmark 6800",
    "addr:housenumber":"5",
    "addr:postcode":"6800",
    "addr:street":"Stationspladsen",
    "iso:country":"DK",
    "sg:address":"Stationspladsen 5",
    "sg:city":"Varde",
    "sg:orig_category":"Posthuse",
    "sg:phone":"+45 79 12 12 12",
    "sg:postcode":"6800",
    "sg:province":"Danmark",
    "wof:name":"Post Danmark, Varde postkontor",
    "wof:placetype":"venue"
},
  "geometry": {"coordinates":[8.4835567474,55.6159286499],"type":"Point"}
}