{
  "type": "Feature",
  "properties": {
    "addr:full":"Stokkildhovedvej 3, Kollund Herning Danmark 7400",
    "addr:housenumber":"3",
    "addr:postcode":"7400",
    "addr:street":"Stokkildhovedvej;Kollund",
    "iso:country":"DK",
    "sg:address":"Stokkildhovedvej 3, Kollund",
    "sg:city":"Herning",
    "sg:orig_category":"Forsamlingshuse",
    "sg:phone":"+45 97 12 90 06",
    "sg:postcode":"7400",
    "sg:province":"Danmark",
    "wof:name":"Kollund Forsamlingshus",
    "wof:placetype":"venue"
},
  "geometry": {"coordinates":[8.9768896103,56.1374168396],"type":"Point"}
}