{
  "type": "Feature",
  "properties": {
    "addr:full":"Fmd.: Lilly Holtet, R\u00f8dovrevej 236, F, 1.2. R\u00f8dovre Danmark 2610",
    "addr:housenumber":"236 f 1.2",
    "addr:postcode":"2610",
    "addr:street":"Rodovrevej",
    "iso:country":"DK",
    "sg:address":"Fmd.: Lilly Holtet, R\u00f8dovrevej 236, F, 1.2.",
    "sg:city":"R\u00f8dovre",
    "sg:orig_category":"Musik og sang",
    "sg:phone":"+45 36 41 53 25",
    "sg:postcode":"2610",
    "sg:province":"Danmark",
    "wof:name":"Visens Venner i Glostrup",
    "wof:placetype":"venue"
},
  "geometry": {"coordinates":[10.6992139816,61.1027755737],"type":"Point"}
}