{
  "type": "Feature",
  "properties": {
    "addr:full":"Nystedvej 9 Valby Danmark 2500",
    "addr:housenumber":"9",
    "addr:postcode":"2500",
    "addr:street":"Nystedvej",
    "iso:country":"DK",
    "sg:address":"Nystedvej 9",
    "sg:city":"Valby",
    "sg:orig_category":"Psykologer, praktiserende",
    "sg:phone":"+45 36 45 00 80",
    "sg:postcode":"2500",
    "sg:province":"Danmark",
    "wof:name":"Debes, Frode",
    "wof:placetype":"venue"
},
  "geometry": {"coordinates":[12.4916143417,55.6684303284],"type":"Point"}
}