{
  "type": "Feature",
  "properties": {
    "addr:full":"Kornv\u00e6nget 32 Ballerup Danmark 2750",
    "addr:housenumber":"32",
    "addr:postcode":"2750",
    "addr:street":"Kornvaenget",
    "iso:country":"DK",
    "sg:address":"Kornv\u00e6nget 32",
    "sg:city":"Ballerup",
    "sg:orig_category":"Vuggestuer",
    "sg:phone":"+45 44 77 16 12",
    "sg:postcode":"2750",
    "sg:province":"Danmark",
    "wof:name":"Vuggestuen",
    "wof:placetype":"venue"
},
  "geometry": {"coordinates":[12.361000061,55.7301216125],"type":"Point"}
}