{
  "type": "Feature",
  "properties": {
    "addr:full":"Magleh\u00f8jvej 44 Frederikssund Danmark 3600",
    "addr:housenumber":"44",
    "addr:postcode":"3600",
    "addr:street":"Maglehojvej",
    "iso:country":"DK",
    "sg:address":"Magleh\u00f8jvej 44",
    "sg:city":"Frederikssund",
    "sg:orig_category":"Psykoterapi",
    "sg:phone":"+45 47 38 46 10",
    "sg:postcode":"3600",
    "sg:province":"Danmark",
    "wof:name":"Klinikken",
    "wof:placetype":"venue"
},
  "geometry": {"coordinates":[12.081735611,55.8318748474],"type":"Point"}
}