{
  "type": "Feature",
  "properties": {
    "addr:full":"Nederdammen 25 C Ribe Danmark 6760",
    "addr:housenumber":"25 c",
    "addr:postcode":"6760",
    "addr:street":"Nederdammen",
    "iso:country":"DK",
    "sg:address":"Nederdammen 25 C",
    "sg:city":"Ribe",
    "sg:orig_category":"Papirvarer",
    "sg:phone":"+45 75 42 49 59",
    "sg:postcode":"6760",
    "sg:province":"Danmark",
    "wof:name":"PapirHuset",
    "wof:placetype":"venue"
},
  "geometry": {"coordinates":[8.7651863098,55.3297691345],"type":"Point"}
}