{
  "type": "Feature",
  "properties": {
    "addr:full":"Store Torv 3, Postboks 630 8100",
    "addr:housenumber":"3;630",
    "addr:postcode":"8100",
    "addr:street":"Store Torv",
    "iso:country":"DK",
    "sg:address":"Store Torv 3, Postboks 630",
    "sg:classifiers":[
        {
            "category":"Banks & Credit Unions",
            "subcategory":"Bank",
            "type":"Services"
        }
    ],
    "sg:phone":"+45 87 30 70 00",
    "sg:postcode":"8100",
    "sg:tags":[
        "banker"
    ],
    "wof:name":"BG Bank A/S",
    "wof:placetype":"venue"
},
  "geometry": {"coordinates":[2.07783,49.143101],"type":"Point"}
}