{
  "type": "Feature",
  "properties": {
    "addr:full":"Rytterk\u00e6r 21, Herringl\u00f8se Veks\u00f8 Sj\u00e6lland Danmark 3670",
    "addr:housenumber":"21",
    "addr:postcode":"3670",
    "addr:street":"Rytterkaer",
    "iso:country":"DK",
    "sg:address":"Rytterk\u00e6r 21, Herringl\u00f8se",
    "sg:city":"Veks\u00f8 Sj\u00e6lland",
    "sg:orig_category":"Trykkerier",
    "sg:phone":"+45 46 76 94 88",
    "sg:postcode":"3670",
    "sg:province":"Danmark",
    "wof:name":"Simoffset ApS",
    "wof:placetype":"venue"
},
  "geometry": {"coordinates":[-76.0886383057,38.7291030884],"type":"Point"}
}