{
  "type": "Feature",
  "properties": {
    "iso:country":"DK",
    "sg:address":"Marselisborg Alle 11",
    "sg:city":"\u00c5rhus C",
    "sg:orig_category":"Bagere",
    "sg:phone":"+45 86 13 04 01",
    "sg:postcode":"8000",
    "sg:province":"Danmark",
    "wof:name":"Andersen, Jens Christian",
    "wof:placetype":"venue"
},
  "geometry": {"coordinates":[4.7174,49.758801],"type":"Point"}
}