{
  "type": "Feature",
  "properties": {
    "addr:full":"Amtsvejen 13, St. Lyngby \u00d8lsted Danmark 3310",
    "addr:housenumber":"13",
    "addr:postcode":"3310",
    "addr:street":"Amtsvejen",
    "iso:country":"DK",
    "sg:address":"Amtsvejen 13, St. Lyngby",
    "sg:city":"\u00d8lsted",
    "sg:orig_category":"Begravelsesforretninger",
    "sg:phone":"+45 47 74 99 00",
    "sg:postcode":"3310",
    "sg:province":"Danmark",
    "sg:website":"www.bedemand.dk",
    "wof:name":"Arres\u00f8 Begravelsesforretning",
    "wof:placetype":"venue"
},
  "geometry": {"coordinates":[12.0502872467,55.9014205933],"type":"Point"}
}