{
  "type": "Feature",
  "properties": {
    "addr:full":"Frederiksgade 2 D Skive Danmark 7800",
    "addr:housenumber":"2 d",
    "addr:postcode":"7800",
    "addr:street":"Frederiksgade",
    "iso:country":"DK",
    "sg:address":"Frederiksgade 2 D",
    "sg:city":"Skive",
    "sg:orig_category":"Antikvariater",
    "sg:phone":"+45 40 76 47 76",
    "sg:postcode":"7800",
    "sg:province":"Danmark",
    "wof:name":"Bogcentralen",
    "wof:placetype":"venue"
},
  "geometry": {"coordinates":[9.0257349014,56.5674858093],"type":"Point"}
}