{
  "type": "Feature",
  "properties": {
    "addr:full":"Fmd.: Helmer Andersen, Kildevej 6, Vistoft Knebel Danmark 8420",
    "addr:housenumber":"6",
    "addr:postcode":"8420",
    "addr:street":"Kildevej",
    "iso:country":"DK",
    "sg:address":"Fmd.: Helmer Andersen, Kildevej 6, Vistoft",
    "sg:city":"Knebel",
    "sg:orig_category":"Kulturelle foreninger",
    "sg:phone":"+45 86 35 12 83",
    "sg:postcode":"8420",
    "sg:province":"Danmark",
    "wof:name":"Gr\u00e6nseforeningen for Ebeltoft Og Omegn",
    "wof:placetype":"venue"
},
  "geometry": {"coordinates":[10.3770122528,56.1816596985],"type":"Point"}
}