{
  "type": "Feature",
  "properties": {
    "addr:full":"Vaarstvej 200 Gistrup Danmark 9260",
    "addr:housenumber":"200",
    "addr:postcode":"9260",
    "addr:street":"Vaarstvej",
    "iso:country":"DK",
    "sg:address":"Vaarstvej 200",
    "sg:city":"Gistrup",
    "sg:orig_category":"Brugsforeninger",
    "sg:phone":"+45 98 33 31 12",
    "sg:postcode":"9260",
    "sg:province":"Danmark",
    "wof:name":"Lokal Brugsen",
    "wof:placetype":"venue"
},
  "geometry": {"coordinates":[10.0546121597,56.9378814697],"type":"Point"}
}