{
  "type": "Feature",
  "properties": {
    "addr:full":"Fabriksparken 58  Glostrup Danmark 2600",
    "addr:housenumber":"58",
    "addr:postcode":"2600",
    "addr:street":"Fabriksparken",
    "iso:country":"DK",
    "sg:address":"Fabriksparken 58 ",
    "sg:city":"Glostrup",
    "sg:classifiers":[
        {
            "category":"Wholesale",
            "subcategory":"Drugs",
            "type":"Manufacturing & Wholesale Goods"
        }
    ],
    "sg:phone":"+45 43 29 30 00",
    "sg:postcode":"2600",
    "sg:province":"Danmark",
    "sg:tags":[
        "chemical",
        "pharmaceutical"
    ],
    "wof:name":"ACADIA PHARMACEUTICALS A/S",
    "wof:placetype":"venue"
},
  "geometry": {"coordinates":[12.3810739517,55.6844863892],"type":"Point"}
}