{
  "type": "Feature",
  "properties": {
    "iso:country":"DK",
    "sg:address":"Fmd.: Else Fink, Mjels Bygade 13",
    "sg:city":"Svenstrup",
    "sg:orig_category":"Hobbybetonede foreninger",
    "sg:phone":"+45 98 38 45 18",
    "sg:postcode":"9230",
    "sg:province":"Danmark",
    "wof:name":"Jydske Haveselskab Midthimmerlands Havekreds, Det",
    "wof:placetype":"venue"
},
  "geometry": {"coordinates":[9.8525295258,56.9723396301],"type":"Point"}
}