{
  "type": "Feature",
  "properties": {
    "addr:full":"H\u00e6kmosen 3 Herlev Danmark 2730",
    "addr:housenumber":"3",
    "addr:postcode":"2730",
    "addr:street":"Haekmosen",
    "iso:country":"DK",
    "sg:address":"H\u00e6kmosen 3",
    "sg:city":"Herlev",
    "sg:orig_category":"Autoreparation og -service",
    "sg:phone":"+45 44 44 15 20",
    "sg:postcode":"2730",
    "sg:province":"Danmark",
    "wof:name":"Shell Ring 4 Autov\u00e6rksted",
    "wof:placetype":"venue"
},
  "geometry": {"coordinates":[12.4031600952,55.753200531],"type":"Point"}
}