{
  "type": "Feature",
  "properties": {
    "addr:full":"v/ Marie Laursen Worm, Lyngbjergvej 63, Faarup Nyk\u00f8bing Danmark 7900",
    "addr:housenumber":"63",
    "addr:postcode":"7900",
    "addr:street":"Worm Lyngbjergvej",
    "iso:country":"DK",
    "sg:address":"v/ Marie Laursen Worm, Lyngbjergvej 63, Faarup",
    "sg:city":"Nyk\u00f8bing",
    "sg:orig_category":"Kirkelige foreninger",
    "sg:phone":"+45 97 72 00 76",
    "sg:postcode":"7900",
    "sg:province":"Danmark",
    "wof:name":"S\u00f8ndagsskolens Legestue, Nyk\u00f8bing Mors",
    "wof:placetype":"venue"
},
  "geometry": {"coordinates":[8.8630752563,56.7945251465],"type":"Point"}
}