{
  "type": "Feature",
  "properties": {
    "addr:full":"F\u00e5borgvej 96, Gummerup Glamsbjerg Danmark 5620",
    "addr:housenumber":"96",
    "addr:postcode":"5620",
    "addr:street":"Faaborgvej",
    "iso:country":"DK",
    "sg:address":"F\u00e5borgvej 96, Gummerup",
    "sg:city":"Glamsbjerg",
    "sg:orig_category":"Havebrugsmaskiner",
    "sg:phone":"+45 64 72 13 72",
    "sg:postcode":"5620",
    "sg:province":"Danmark",
    "wof:name":"AP-Motorcenter Gummerup",
    "wof:placetype":"venue"
},
  "geometry": {"coordinates":[10.1052503586,55.2783317566],"type":"Point"}
}