{
  "type": "Feature",
  "properties": {
    "addr:full":"Sl\u00e5envej 138, Mejdal Holstebro Danmark 7500",
    "addr:housenumber":"138",
    "addr:postcode":"7500",
    "addr:street":"Slaaenvej;Mejdal",
    "iso:country":"DK",
    "sg:address":"Sl\u00e5envej 138, Mejdal",
    "sg:city":"Holstebro",
    "sg:orig_category":"Psykologer, praktiserende",
    "sg:phone":"+45 97 40 35 83",
    "sg:postcode":"7500",
    "sg:province":"Danmark",
    "wof:name":"Kirk, Henry",
    "wof:placetype":"venue"
},
  "geometry": {"coordinates":[8.6202583313,56.3625221252],"type":"Point"}
}