{
  "type": "Feature",
  "properties": {
    "addr:full":"Man\u00f8gade 3. 3.th. K\u00f8benhavn \u00d8 Danmark 2100",
    "addr:housenumber":"3 3.th",
    "addr:postcode":"2100",
    "addr:street":"Manogade;Kobenhavn O Danmark",
    "iso:country":"DK",
    "sg:address":"Man\u00f8gade 3. 3.th.",
    "sg:city":"K\u00f8benhavn \u00d8",
    "sg:orig_category":"Filmproduktion",
    "sg:phone":"+45 39 20 10 12",
    "sg:postcode":"2100",
    "sg:province":"Danmark",
    "sg:website":"www.planetproduction.dk",
    "wof:name":"Planet Production ApS",
    "wof:placetype":"venue"
},
  "geometry": {"coordinates":[99.92501068120001,34.2430114746],"type":"Point"}
}