{
  "type": "Feature",
  "properties": {
    "iso:country":"DK",
    "sg:address":"Jernbanegade 8",
    "sg:city":"N\u00e6stved",
    "sg:orig_category":"Supermarkeder",
    "sg:phone":"+45 55 72 66 55",
    "sg:postcode":"4700",
    "sg:province":"Danmark",
    "wof:name":"Kvickly",
    "wof:placetype":"venue"
},
  "geometry": {"coordinates":[11.7632703781,55.230556488],"type":"Point"}
}