{
  "type": "Feature",
  "properties": {
    "iso:country":"DK",
    "sg:address":"Gr\u00f8nnegade 7",
    "sg:city":"Vejen",
    "sg:orig_category":"\u00c3\u2020ldreorganisationer og klubber",
    "sg:phone":"+45 74 84 86 30",
    "sg:postcode":"6600",
    "sg:province":"Danmark",
    "wof:name":"R\u00f8dding Folke-, Invalide- og Pensionistforening for Skodborg og Omegn",
    "wof:placetype":"venue"
},
  "geometry": {"coordinates":[9.1373310089,55.4720878601],"type":"Point"}
}