{
  "type": "Feature",
  "properties": {
    "iso:country":"DK",
    "sg:address":"Jernbanegade 2",
    "sg:city":"Slagelse",
    "sg:classifiers":[
        {
            "category":"Banks & Credit Unions",
            "subcategory":"Bank",
            "type":"Services"
        }
    ],
    "sg:phone":"+45 58 52 88 77",
    "sg:postcode":"4200",
    "sg:province":"Danmark",
    "sg:tags":[
        "banker"
    ],
    "wof:name":"Arbejdernes Landsbank",
    "wof:placetype":"venue"
},
  "geometry": {"coordinates":[11.353472,55.405071],"type":"Point"}
}