{
  "type": "Feature",
  "properties": {
    "addr:full":"Fruens Vej 15 - 17, Skovby Rask M\u00f8lle Danmark 8763",
    "addr:housenumber":"15 17",
    "addr:postcode":"8763",
    "addr:street":"Fruens Vej;Skovby Rask",
    "iso:country":"DK",
    "sg:address":"Fruens Vej 15 - 17, Skovby",
    "sg:city":"Rask M\u00f8lle",
    "sg:orig_category":"Malermestre",
    "sg:phone":"+45 75 67 90 60",
    "sg:postcode":"8763",
    "sg:province":"Danmark",
    "wof:name":"Reenberg & S\u00f8n A/S, Malerfirma",
    "wof:placetype":"venue"
},
  "geometry": {"coordinates":[9.6123399734,55.8722496033],"type":"Point"}
}