{
  "type": "Feature",
  "properties": {
    "addr:full":"v/ Finn Reincke, Greisvej 44, st. tv. K\u00f8benhavn S Danmark 2300",
    "addr:housenumber":"44 st. tv.",
    "addr:postcode":"2300",
    "addr:street":"Greisvej;Kobenhavn S Danmark",
    "iso:country":"DK",
    "sg:address":"v/ Finn Reincke, Greisvej 44, st. tv.",
    "sg:city":"K\u00f8benhavn S",
    "sg:orig_category":"Grundejerforeninger",
    "sg:phone":"+45 32 51 58 24",
    "sg:postcode":"2300",
    "sg:province":"Danmark",
    "wof:name":"Ravnsbjerg Grundejerforening",
    "wof:placetype":"venue"
},
  "geometry": {"coordinates":[-78.1299133301,36.7267417908],"type":"Point"}
}