{
  "type": "Feature",
  "properties": {
    "addr:full":"Nym\u00f8llevej 155, K\u00f8lby Nibe Danmark 9240",
    "addr:housenumber":"155",
    "addr:postcode":"9240",
    "addr:street":"Nymollevej;Kolby",
    "iso:country":"DK",
    "sg:address":"Nym\u00f8llevej 155, K\u00f8lby",
    "sg:city":"Nibe",
    "sg:orig_category":"Varmeforsyning",
    "sg:phone":"+45 98 68 60 30",
    "sg:postcode":"9240",
    "sg:province":"Danmark",
    "wof:name":"Farstrup-K\u00f8lby Kraftvarmev\u00e6rk Amba",
    "wof:placetype":"venue"
},
  "geometry": {"coordinates":[9.6393280029,56.982421875],"type":"Point"}
}