{
  "type": "Feature",
  "properties": {
    "addr:full":"B\u00e5dsmandsvej 2 Asaa Danmark 9340",
    "addr:housenumber":"2",
    "addr:postcode":"9340",
    "addr:street":"Baadsmandsvej",
    "iso:country":"DK",
    "sg:address":"B\u00e5dsmandsvej 2",
    "sg:city":"Asaa",
    "sg:orig_category":"Murermestre",
    "sg:phone":"+45 98 85 19 22",
    "sg:postcode":"9340",
    "sg:province":"Danmark",
    "wof:name":"Nielsen, Henning",
    "wof:placetype":"venue"
},
  "geometry": {"coordinates":[10.3964557648,57.1439247131],"type":"Point"}
}