{
  "type": "Feature",
  "properties": {
    "addr:full":"Hylstrupvej 37 Fjenneslev Danmark 4173",
    "addr:housenumber":"37",
    "addr:postcode":"4173",
    "addr:street":"Hylstrupvej",
    "iso:country":"DK",
    "sg:address":"Hylstrupvej 37",
    "sg:city":"Fjenneslev",
    "sg:orig_category":"Vinduespolering",
    "sg:phone":"+45 57 80 94 71",
    "sg:postcode":"4173",
    "sg:province":"Danmark",
    "wof:name":"Ulrich Skarby",
    "wof:placetype":"venue"
},
  "geometry": {"coordinates":[11.6519289017,55.4186019897],"type":"Point"}
}