{
  "type": "Feature",
  "properties": {
    "iso:country":"DK",
    "sg:address":"Lille R\u00f8rb\u00e6kvej 16",
    "sg:city":"Frederikssund",
    "sg:orig_category":"Alternativ behandling",
    "sg:phone":"+45 47 10 02 25",
    "sg:postcode":"3600",
    "sg:province":"Danmark",
    "wof:name":"Christensen, Kurt",
    "wof:placetype":"venue"
},
  "geometry": {"coordinates":[12.1012248993,55.7865791321],"type":"Point"}
}