{
  "type": "Feature",
  "properties": {
    "iso:country":"DK",
    "sg:address":"N\u00f8ddelunden 24",
    "sg:city":"Esbjerg \u00d8",
    "sg:orig_category":"INGENI\u00c3\u02dcRER",
    "sg:phone":"+45 75 14 28 49",
    "sg:postcode":"6705",
    "sg:province":"Danmark",
    "wof:name":"Jensen, Gunnar Uth",
    "wof:placetype":"venue"
},
  "geometry": {"coordinates":[8.4736213684,55.4949760437],"type":"Point"}
}