{
  "type": "Feature",
  "properties": {
    "addr:full":"Industrivej 25 Dalmose Danmark 4261",
    "addr:housenumber":"25",
    "addr:postcode":"4261",
    "addr:street":"Industrivej",
    "iso:country":"DK",
    "sg:address":"Industrivej 25",
    "sg:city":"Dalmose",
    "sg:orig_category":"Landbrugsmaskiner",
    "sg:phone":"+45 58 18 81 00",
    "sg:postcode":"4261",
    "sg:province":"Danmark",
    "wof:name":"S M Maskiner A/S",
    "wof:placetype":"venue"
},
  "geometry": {"coordinates":[11.4226579666,55.2956314087],"type":"Point"}
}