{
  "type": "Feature",
  "properties": {
    "addr:full":"Blenstrupvej 37, Askildrup Sk\u00f8rping Danmark 9520",
    "addr:housenumber":"37",
    "addr:postcode":"9520",
    "addr:street":"Blenstrupvej",
    "iso:country":"DK",
    "sg:address":"Blenstrupvej 37, Askildrup",
    "sg:city":"Sk\u00f8rping",
    "sg:orig_category":"Autoreparation og -service",
    "sg:phone":"+45 98 33 94 74",
    "sg:postcode":"9520",
    "sg:province":"Danmark",
    "wof:name":"JI Biler",
    "wof:placetype":"venue"
},
  "geometry": {"coordinates":[9.8477077484,56.8337860107],"type":"Point"}
}