{
  "type": "Feature",
  "properties": {
    "addr:full":"Troels-Lunds Vej 15 Frederiksberg Danmark 2000",
    "addr:housenumber":"15",
    "addr:postcode":"2000",
    "addr:street":"Troels-Lunds Vej",
    "iso:country":"DK",
    "sg:address":"Troels-Lunds Vej 15",
    "sg:city":"Frederiksberg",
    "sg:orig_category":"Gymnasier og HF-kurser",
    "sg:phone":"+45 38 74 20 66",
    "sg:postcode":"2000",
    "sg:province":"Danmark",
    "sg:website":"www.johannesskolen.dk",
    "wof:name":"Johannesskolen",
    "wof:placetype":"venue"
},
  "geometry": {"coordinates":[12.5018625259,55.675037384],"type":"Point"}
}