{
  "type": "Feature",
  "properties": {
    "iso:country":"DK",
    "sg:address":"Osvej 1",
    "sg:city":"Jyllinge",
    "sg:orig_category":"Begravelsesforretninger",
    "sg:phone":"+45 46 78 99 29",
    "sg:postcode":"4040",
    "sg:province":"Danmark",
    "wof:name":"Bedemands/Begravelsforretning for Jyllinge-Gunds\u00f8 og omegn",
    "wof:placetype":"venue"
},
  "geometry": {"coordinates":[12.113360405,55.7655601501],"type":"Point"}
}