{
  "type": "Feature",
  "properties": {
    "addr:full":"Ravnstrupvej 37 Viborg Danmark 8800",
    "addr:housenumber":"37",
    "addr:postcode":"8800",
    "addr:street":"Ravnstrupvej",
    "iso:country":"DK",
    "sg:address":"Ravnstrupvej 37",
    "sg:city":"Viborg",
    "sg:classifiers":[
        {
            "category":"Restaurant",
            "type":"Food & Drink"
        }
    ],
    "sg:phone":"+45 86 64 75 99",
    "sg:postcode":"8800",
    "sg:province":"Danmark",
    "wof:name":"N\u00f8sset",
    "wof:placetype":"venue"
},
  "geometry": {"coordinates":[9.2855892181,56.4656562805],"type":"Point"}
}