{
  "type": "Feature",
  "properties": {
    "addr:full":"Marienlystvej 6 Silkeborg Danmark 8600",
    "addr:housenumber":"6",
    "addr:postcode":"8600",
    "addr:street":"Marienlystvej",
    "iso:country":"DK",
    "sg:address":"Marienlystvej 6",
    "sg:city":"Silkeborg",
    "sg:orig_category":"Autoforhandlere",
    "sg:phone":"+45 86 83 76 20",
    "sg:postcode":"8600",
    "sg:province":"Danmark",
    "wof:name":"BT Automobiler",
    "wof:placetype":"venue"
},
  "geometry": {"coordinates":[9.5593557358,56.1382369995],"type":"Point"}
}