{
  "type": "Feature",
  "properties": {
    "addr:full":"Gr\u00e6sted V\u00e6nge 48 Gr\u00e6sted Danmark 3230",
    "addr:housenumber":"48",
    "addr:postcode":"3230",
    "addr:street":"Graested Danmark",
    "iso:country":"DK",
    "sg:address":"Gr\u00e6sted V\u00e6nge 48",
    "sg:city":"Gr\u00e6sted",
    "sg:orig_category":"Havecentre",
    "sg:phone":"+45 48 39 29 96",
    "sg:postcode":"3230",
    "sg:province":"Danmark",
    "wof:name":"Gr\u00e6sted Entrepren\u00f8rfirma",
    "wof:placetype":"venue"
},
  "geometry": {"coordinates":[13.5614004135,7.356400013],"type":"Point"}
}