{
  "type": "Feature",
  "properties": {
    "addr:full":"Vestergade 5 Gudme Danmark 5884",
    "addr:housenumber":"5",
    "addr:postcode":"5884",
    "addr:street":"Vestergade",
    "iso:country":"DK",
    "sg:address":"Vestergade 5",
    "sg:city":"Gudme",
    "sg:orig_category":"Fotografer",
    "sg:phone":"+45 62 25 23 20",
    "sg:postcode":"5884",
    "sg:province":"Danmark",
    "sg:website":"www.krystal-foto.dk",
    "wof:name":"Krystal Foto",
    "wof:placetype":"venue"
},
  "geometry": {"coordinates":[10.7037134171,55.1538467407],"type":"Point"}
}