{
  "type": "Feature",
  "properties": {
    "addr:full":"Havnen 5 Gilleleje Danmark 3250",
    "addr:housenumber":"5",
    "addr:postcode":"3250",
    "addr:street":"Havnen",
    "iso:country":"DK",
    "sg:address":"Havnen 5",
    "sg:city":"Gilleleje",
    "sg:orig_category":"Fiskeeksport",
    "sg:phone":"+45 48 30 03 27",
    "sg:postcode":"3250",
    "sg:province":"Danmark",
    "wof:name":"Larsenfisk A/S",
    "wof:placetype":"venue"
},
  "geometry": {"coordinates":[12.3072032928,56.1255531311],"type":"Point"}
}