{
  "type": "Feature",
  "properties": {
    "addr:full":"Tuborg Parkvej 1 Hellerup Danmark 2900",
    "addr:housenumber":"1",
    "addr:postcode":"2900",
    "addr:street":"Tuborg Parkvej",
    "iso:country":"DK",
    "sg:address":"Tuborg Parkvej 1",
    "sg:city":"Hellerup",
    "sg:orig_category":"Servicestationer",
    "sg:phone":"+45 39 40 45 91",
    "sg:postcode":"2900",
    "sg:province":"Danmark",
    "wof:name":"Hydro Texaco",
    "wof:placetype":"venue"
},
  "geometry": {"coordinates":[12.5788946152,55.7284355164],"type":"Point"}
}