{
  "type": "Feature",
  "properties": {
    "iso:country":"DK",
    "sg:address":"Fmd.: Jan Valbak-Andersen, Hyrdeh\u00f8j 16",
    "sg:city":"Faaborg",
    "sg:orig_category":"Musik og sang",
    "sg:phone":"+45 62 61 00 85",
    "sg:postcode":"5600",
    "sg:province":"Danmark",
    "wof:name":"Foreningen Faaborg Musikteater",
    "wof:placetype":"venue"
},
  "geometry": {"coordinates":[10.2400531769,55.0950622559],"type":"Point"}
}