{
  "type": "Feature",
  "properties": {
    "iso:country":"DK",
    "sg:address":"Vestergade 53",
    "sg:city":"Vamdrup",
    "sg:orig_category":"Kirker",
    "sg:postcode":"6580",
    "sg:province":"Danmark",
    "wof:name":"Vamdrup Kirke",
    "wof:placetype":"venue"
},
  "geometry": {"coordinates":[9.2728528976,55.4287338257],"type":"Point"}
}