{
  "type": "Feature",
  "properties": {
    "addr:full":"Skomagergade 26 Roskilde Danmark 4000",
    "addr:housenumber":"26",
    "addr:postcode":"4000",
    "addr:street":"Skomagergade",
    "iso:country":"DK",
    "sg:address":"Skomagergade 26",
    "sg:city":"Roskilde",
    "sg:orig_category":"Materialister",
    "sg:phone":"+45 46 35 80 00",
    "sg:postcode":"4000",
    "sg:province":"Danmark",
    "wof:name":"Materialisten",
    "wof:placetype":"venue"
},
  "geometry": {"coordinates":[12.0780906677,55.6409759521],"type":"Point"}
}