{
  "type": "Feature",
  "properties": {
    "addr:full":"v/Kirstem Piper, Johannevej 21 H\u00f8rsholm Danmark 2970",
    "addr:housenumber":"21",
    "addr:postcode":"2970",
    "addr:street":"Johannevej",
    "iso:country":"DK",
    "sg:address":"v/Kirstem Piper, Johannevej 21",
    "sg:city":"H\u00f8rsholm",
    "sg:orig_category":"Grundejerforeninger",
    "sg:phone":"+45 45 86 04 75",
    "sg:postcode":"2970",
    "sg:province":"Danmark",
    "wof:name":"Jyderup Lyng Grundejerforening",
    "wof:placetype":"venue"
},
  "geometry": {"coordinates":[-94.8623504639,39.1430892944],"type":"Point"}
}