{
  "type": "Feature",
  "properties": {
    "iso:country":"DK",
    "sg:address":"R\u00e5dhusstr\u00e6de 10",
    "sg:city":"K\u00f8benhavn",
    "sg:orig_category":"Dentallaboratorier",
    "sg:phone":"+45 33 32 02 47",
    "sg:postcode":"1466",
    "sg:province":"Danmark",
    "wof:name":"Nordin, Gytte",
    "wof:placetype":"venue"
},
  "geometry": {"coordinates":[76.3070983887,14.277130127],"type":"Point"}
}