{
  "type": "Feature",
  "properties": {
    "addr:full":"v/ Niels Ove Jensen, Viborgvej 51, M\u00f8nsted Viborg Danmark 8800",
    "addr:housenumber":"51",
    "addr:postcode":"8800",
    "addr:street":"Ove;Viborgvej",
    "iso:country":"DK",
    "sg:address":"v/ Niels Ove Jensen, Viborgvej 51, M\u00f8nsted",
    "sg:city":"Viborg",
    "sg:orig_category":"Folkedans",
    "sg:phone":"+45 86 64 51 61",
    "sg:postcode":"8800",
    "sg:province":"Danmark",
    "wof:name":"M\u00f8nsted Folkedanserforening",
    "wof:placetype":"venue"
},
  "geometry": {"coordinates":[9.4071502686,56.452671051],"type":"Point"}
}