{
  "type": "Feature",
  "properties": {
    "addr:full":"Industrivej 7-9 Bramming Danmark 6740",
    "addr:housenumber":"7-9",
    "addr:postcode":"6740",
    "addr:street":"Industrivej",
    "iso:country":"DK",
    "sg:address":"Industrivej 7-9",
    "sg:city":"Bramming",
    "sg:orig_category":"Erhvervsskoler",
    "sg:phone":"+45 79 14 03 22",
    "sg:postcode":"6740",
    "sg:province":"Danmark",
    "wof:name":"AMU-Center Vestjylland",
    "wof:placetype":"venue"
},
  "geometry": {"coordinates":[8.6953611374,55.4644584656],"type":"Point"}
}