{
  "type": "Feature",
  "properties": {
    "addr:full":"Slotsgade 49 Dronninglund Danmark 9330",
    "addr:housenumber":"49",
    "addr:postcode":"9330",
    "addr:street":"Slotsgade",
    "iso:country":"DK",
    "sg:address":"Slotsgade 49",
    "sg:city":"Dronninglund",
    "sg:orig_category":"Materialister",
    "sg:phone":"+45 98 84 10 13",
    "sg:postcode":"9330",
    "sg:province":"Danmark",
    "wof:name":"Matas",
    "wof:placetype":"venue"
},
  "geometry": {"coordinates":[10.2918138504,57.1595916748],"type":"Point"}
}