{
  "type": "Feature",
  "properties": {
    "addr:full":"Kass.: Carsten Lund Nielsen, Firkl\u00f8vervej 52 Horsens Danmark 8700",
    "addr:housenumber":"52",
    "addr:postcode":"8700",
    "addr:street":"Firklovervej",
    "iso:country":"DK",
    "sg:address":"Kass.: Carsten Lund Nielsen, Firkl\u00f8vervej 52",
    "sg:city":"Horsens",
    "sg:orig_category":"Hobbybetonede foreninger",
    "sg:phone":"+45 75 63 03 43",
    "sg:postcode":"8700",
    "sg:province":"Danmark",
    "wof:name":"Bygholm Lystfisker- Og B\u00e5dejerforening",
    "wof:placetype":"venue"
},
  "geometry": {"coordinates":[9.8432445526,55.8621063232],"type":"Point"}
}