{
  "type": "Feature",
  "properties": {
    "addr:full":"Vesterbrogade 10 Viborg Danmark 8800",
    "addr:housenumber":"10",
    "addr:postcode":"8800",
    "addr:street":"Vesterbrogade",
    "iso:country":"DK",
    "sg:address":"Vesterbrogade 10",
    "sg:city":"Viborg",
    "sg:orig_category":"Spillesteder, Rytmiske",
    "sg:phone":"+45 86 62 83 22",
    "sg:postcode":"8800",
    "sg:province":"Danmark",
    "wof:name":"Paletten",
    "wof:placetype":"venue"
},
  "geometry": {"coordinates":[9.4004421234,56.4499893188],"type":"Point"}
}