{
  "type": "Feature",
  "properties": {
    "addr:full":"Ll. Karlsmindevej 27 Hundested Danmark 3390",
    "addr:housenumber":"27",
    "addr:postcode":"3390",
    "addr:street":"Ll. Karlsmindevej",
    "iso:country":"DK",
    "sg:address":"Ll. Karlsmindevej 27",
    "sg:city":"Hundested",
    "sg:orig_category":"Dyreklinikker og -hospitaler",
    "sg:phone":"+45 47 98 34 35",
    "sg:postcode":"3390",
    "sg:province":"Danmark",
    "wof:name":"Dyrl\u00e6geg\u00e5rden",
    "wof:placetype":"venue"
},
  "geometry": {"coordinates":[11.8573722839,55.9681587219],"type":"Point"}
}