{
  "type": "Feature",
  "properties": {
    "addr:full":"Fmd.: Kaj Ove Pedersen, Lindevej 32 Karup Danmark 7470",
    "addr:housenumber":"32",
    "addr:postcode":"7470",
    "addr:street":"Fmd. Kaj Ove;Lindevej",
    "iso:country":"DK",
    "sg:address":"Fmd.: Kaj Ove Pedersen, Lindevej 32",
    "sg:city":"Karup",
    "sg:orig_category":"Hobbybetonede foreninger",
    "sg:phone":"+45 97 10 20 84",
    "sg:postcode":"7470",
    "sg:province":"Danmark",
    "wof:name":"Karup Brevdueforening",
    "wof:placetype":"venue"
},
  "geometry": {"coordinates":[9.2525548935,56.3398017883],"type":"Point"}
}