{
  "type": "Feature",
  "properties": {
    "addr:full":"Ryevej 8, Rye G\u00f8rlev Danmark 4281",
    "addr:housenumber":"8",
    "addr:postcode":"4281",
    "addr:street":"Ryevej",
    "iso:country":"DK",
    "sg:address":"Ryevej 8, Rye",
    "sg:city":"G\u00f8rlev",
    "sg:orig_category":"Ridning",
    "sg:phone":"+45 58 86 07 01",
    "sg:postcode":"4281",
    "sg:province":"Danmark",
    "wof:name":"Rye Ridecenter",
    "wof:placetype":"venue"
},
  "geometry": {"coordinates":[11.1143903732,55.5207710266],"type":"Point"}
}