{
  "type": "Feature",
  "properties": {
    "addr:full":"Bl\u00e5g\u00e5rdsgade 17 K\u00f8benhavn N Danmark 2200",
    "addr:housenumber":"17",
    "addr:postcode":"2200",
    "addr:street":"Blaagaardsgade;N Danmark",
    "iso:country":"DK",
    "sg:address":"Bl\u00e5g\u00e5rdsgade 17",
    "sg:city":"K\u00f8benhavn N",
    "sg:orig_category":"Faglige organisationer og -foreninger",
    "sg:phone":"+45 35 24 55 20",
    "sg:postcode":"2200",
    "sg:province":"Danmark",
    "wof:name":"Daginstitutionernes Lands-Organisation (DLO)",
    "wof:placetype":"venue"
},
  "geometry": {"coordinates":[-87.3646774292,33.4684677124],"type":"Point"}
}