{
  "type": "Feature",
  "properties": {
    "addr:full":"Englandsvej 376 Kastrup Danmark 2770",
    "addr:housenumber":"376",
    "addr:postcode":"2770",
    "addr:street":"Englandsvej",
    "iso:country":"DK",
    "sg:address":"Englandsvej 376",
    "sg:city":"Kastrup",
    "sg:orig_category":"Realkreditinstitutter",
    "sg:phone":"+45 32 46 82 00",
    "sg:postcode":"2770",
    "sg:province":"Danmark",
    "sg:website":"www.nykredit.dk",
    "wof:name":"Nykredit A/S",
    "wof:placetype":"venue"
},
  "geometry": {"coordinates":[12.6042690277,55.6234436035],"type":"Point"}
}