{
  "type": "Feature",
  "properties": {
    "addr:full":"Saltv\u00e6rksvej 68 Kastrup Danmark 2770",
    "addr:housenumber":"68",
    "addr:postcode":"2770",
    "addr:street":"Saltvaerksvej",
    "iso:country":"DK",
    "sg:address":"Saltv\u00e6rksvej 68",
    "sg:city":"Kastrup",
    "sg:orig_category":"Faglige organisationer og foreninger",
    "sg:phone":"+45 32 50 00 18",
    "sg:postcode":"2770",
    "sg:province":"Danmark",
    "wof:name":"Arbejdernes F\u00e6llesorganisation",
    "wof:placetype":"venue"
},
  "geometry": {"coordinates":[12.6376333237,55.6379776001],"type":"Point"}
}