{
  "type": "Feature",
  "properties": {
    "iso:country":"DK",
    "sg:address":"Stenstuegade 3",
    "sg:city":"Slagelse",
    "sg:orig_category":"Biblioteker",
    "sg:phone":"+45 58 55 39 00",
    "sg:postcode":"4200",
    "sg:province":"Danmark",
    "sg:website":"www.slagelsebib.dk",
    "wof:name":"Slagelse Centralbibliotek",
    "wof:placetype":"venue"
},
  "geometry": {"coordinates":[11.352795,55.403133],"type":"Point"}
}