{
  "type": "Feature",
  "properties": {
    "addr:full":"Rugv\u00e6nget 31 Ballerup Danmark 2750",
    "addr:housenumber":"31",
    "addr:postcode":"2750",
    "addr:street":"Rugvaenget",
    "iso:country":"DK",
    "sg:address":"Rugv\u00e6nget 31",
    "sg:city":"Ballerup",
    "sg:orig_category":"Motionscentre",
    "sg:phone":"+45 44 66 32 66",
    "sg:postcode":"2750",
    "sg:province":"Danmark",
    "wof:name":"Ballerup Sol & Motion I/S",
    "wof:placetype":"venue"
},
  "geometry": {"coordinates":[12.361000061,55.7301216125],"type":"Point"}
}