{
  "type": "Feature",
  "properties": {
    "addr:full":"Trige Centervej 10 Trige Danmark 8380",
    "addr:housenumber":"10",
    "addr:postcode":"8380",
    "addr:street":"Trige Centervej",
    "iso:country":"DK",
    "sg:address":"Trige Centervej 10",
    "sg:city":"Trige",
    "sg:orig_category":"Fritidshjem",
    "sg:phone":"+45 86 23 09 50",
    "sg:postcode":"8380",
    "sg:province":"Danmark",
    "wof:name":"Bj\u00f8rnsh\u00f8j, Fritidshjem",
    "wof:placetype":"venue"
},
  "geometry": {"coordinates":[10.1525144577,56.2495117188],"type":"Point"}
}