{
  "type": "Feature",
  "properties": {
    "iso:country":"DK",
    "sg:address":"v/ Dagli' Brugsen, Koldingvej 29, Vester Nebel",
    "sg:city":"Egtved",
    "sg:orig_category":"Apoteker og -udsalg",
    "sg:phone":"+45 75 55 33 09",
    "sg:postcode":"6040",
    "sg:province":"Danmark",
    "wof:name":"Vester Nebel H\u00e5ndk\u00f8bsudsalg",
    "wof:placetype":"venue"
},
  "geometry": {"coordinates":[9.4044952393,55.5653762817],"type":"Point"}
}