{
  "type": "Feature",
  "properties": {
    "addr:full":"Pilekrattet 6 Bjerringbro Danmark 8850",
    "addr:housenumber":"6",
    "addr:postcode":"8850",
    "addr:street":"Pilekrattet",
    "iso:country":"DK",
    "sg:address":"Pilekrattet 6",
    "sg:city":"Bjerringbro",
    "sg:orig_category":"Arkitekter",
    "sg:phone":"+45 86 68 86 80",
    "sg:postcode":"8850",
    "sg:province":"Danmark",
    "wof:name":"Lander, Lone",
    "wof:placetype":"venue"
},
  "geometry": {"coordinates":[9.6587753296,56.3831558228],"type":"Point"}
}