{
  "type": "Feature",
  "properties": {
    "addr:full":"S\u00f8ndergade 52 Hirtshals Danmark 9850",
    "addr:housenumber":"52",
    "addr:postcode":"9850",
    "addr:street":"Sondergade",
    "iso:country":"DK",
    "sg:address":"S\u00f8ndergade 52",
    "sg:city":"Hirtshals",
    "sg:orig_category":"Servicestationer",
    "sg:phone":"+45 98 94 19 10",
    "sg:postcode":"9850",
    "sg:province":"Danmark",
    "wof:name":"Shell Service, A/S",
    "wof:placetype":"venue"
},
  "geometry": {"coordinates":[9.9599866867,57.5884933472],"type":"Point"}
}