{
  "type": "Feature",
  "properties": {
    "addr:full":"Knudevejen 26 Vejen Danmark 6600",
    "addr:housenumber":"26",
    "addr:postcode":"6600",
    "addr:street":"Knudevejen",
    "iso:country":"DK",
    "sg:address":"Knudevejen 26",
    "sg:city":"Vejen",
    "sg:orig_category":"Non-Classified Establishments",
    "sg:phone":"+45 75 36 44 11",
    "sg:postcode":"6600",
    "sg:province":"Danmark",
    "wof:name":"Statoil Center Vejen",
    "wof:placetype":"venue"
},
  "geometry": {"coordinates":[9.14478302,55.4669494629],"type":"Point"}
}