{
  "type": "Feature",
  "properties": {
    "addr:full":"Sognepr\u00e6st: Ole F. Hansen (K/B), Axel Brahesvej 13 Veflinge Danmark 5474",
    "addr:housenumber":"13",
    "addr:postcode":"5474",
    "addr:street":"Axel Brahesvej",
    "iso:country":"DK",
    "sg:address":"Sognepr\u00e6st: Ole F. Hansen (K/B), Axel Brahesvej 13",
    "sg:city":"Veflinge",
    "sg:orig_category":"Kirkesogne",
    "sg:phone":"+45 64 80 10 18",
    "sg:postcode":"5474",
    "sg:province":"Danmark",
    "wof:name":"Veflinge sogn",
    "wof:placetype":"venue"
},
  "geometry": {"coordinates":[10.1596345901,55.4755935669],"type":"Point"}
}