{
  "type": "Feature",
  "properties": {
    "addr:full":"Lyngen 6, Annisse Helsinge Danmark 3200",
    "addr:housenumber":"6",
    "addr:postcode":"3200",
    "addr:street":"Lyngen",
    "iso:country":"DK",
    "sg:address":"Lyngen 6, Annisse",
    "sg:city":"Helsinge",
    "sg:orig_category":"Psykologer, praktiserende",
    "sg:phone":"+45 48 28 72 86",
    "sg:postcode":"3200",
    "sg:province":"Danmark",
    "wof:name":"Bering, Karen Annette",
    "wof:placetype":"venue"
},
  "geometry": {"coordinates":[12.196846962,56.0224456787],"type":"Point"}
}