{
  "type": "Feature",
  "properties": {
    "addr:full":"Tulstrupvej 1 Gr\u00e6sted Danmark 3230",
    "addr:housenumber":"1",
    "addr:postcode":"3230",
    "addr:street":"Tulstrupvej",
    "iso:country":"DK",
    "sg:address":"Tulstrupvej 1",
    "sg:city":"Gr\u00e6sted",
    "sg:orig_category":"Fodterapeuter",
    "sg:phone":"+45 48 39 16 58",
    "sg:postcode":"3230",
    "sg:province":"Danmark",
    "wof:name":"Klinik for Fodterapi",
    "wof:placetype":"venue"
},
  "geometry": {"coordinates":[-78.6975326538,35.0151481628],"type":"Point"}
}