{
  "type": "Feature",
  "properties": {
    "iso:country":"DK",
    "sg:address":"Tosten\u00e6s M\u00f8llevej 1, Tosten\u00e6s",
    "sg:city":"Askeby",
    "sg:orig_category":"Bagere",
    "sg:phone":"+45 55 81 72 16",
    "sg:postcode":"4792",
    "sg:province":"Danmark",
    "wof:name":"Tosten\u00e6s Bageri",
    "wof:placetype":"venue"
},
  "geometry": {"coordinates":[12.145246,54.88385],"type":"Point"}
}