{
  "type": "Feature",
  "properties": {
    "addr:full":"Blaab\u00e6rvej 4 Ans Danmark 8643",
    "addr:housenumber":"4",
    "addr:postcode":"8643",
    "addr:street":"Blaabaervej",
    "iso:country":"DK",
    "sg:address":"Blaab\u00e6rvej 4",
    "sg:city":"Ans",
    "sg:orig_category":"Maskinfabrikker",
    "sg:phone":"+45 86 87 05 82",
    "sg:postcode":"8643",
    "sg:province":"Danmark",
    "wof:name":"Ans Maskinv\u00e6rksted",
    "wof:placetype":"venue"
},
  "geometry": {"coordinates":[9.5850048065,56.3108406067],"type":"Point"}
}