{
  "type": "Feature",
  "properties": {
    "iso:country":"DK",
    "sg:address":"Sct. Laurentii Vej 71",
    "sg:city":"Skagen",
    "sg:classifiers":[
        {
            "category":"Home & Garden",
            "subcategory":"Home Furnishings",
            "type":"Retail Goods"
        }
    ],
    "sg:phone":"+45 98 44 13 98",
    "sg:postcode":"9990",
    "sg:province":"Danmark",
    "sg:tags":[
        "gardiner"
    ],
    "wof:name":"Botex Gardiner & Udstyr",
    "wof:placetype":"venue"
},
  "geometry": {"coordinates":[10.5865077972,57.7213668823],"type":"Point"}
}