{
  "type": "Feature",
  "properties": {
    "addr:full":"Hovedgaden 13 Skibby Danmark 4050",
    "addr:housenumber":"13",
    "addr:postcode":"4050",
    "addr:street":"Hovedgaden",
    "iso:country":"DK",
    "sg:address":"Hovedgaden 13",
    "sg:city":"Skibby",
    "sg:orig_category":"Blomsterhandlere",
    "sg:phone":"+45 47 52 80 83",
    "sg:postcode":"4050",
    "sg:province":"Danmark",
    "sg:website":"www.euroflorist.dk",
    "wof:name":"Skibby Blomster",
    "wof:placetype":"venue"
},
  "geometry": {"coordinates":[11.9596881866,55.7522659302],"type":"Point"}
}