{
  "type": "Feature",
  "properties": {
    "addr:full":"Odensevej 61A, Herrested \u00d8rb\u00e6k Danmark 5853",
    "addr:housenumber":"61a",
    "addr:postcode":"5853",
    "addr:street":"Odensevej",
    "iso:country":"DK",
    "sg:address":"Odensevej 61A, Herrested",
    "sg:city":"\u00d8rb\u00e6k",
    "sg:orig_category":"Kirker",
    "sg:postcode":"5853",
    "sg:province":"Danmark",
    "wof:name":"Herrested kirke",
    "wof:placetype":"venue"
},
  "geometry": {"coordinates":[10.6713848114,55.2553749084],"type":"Point"}
}