{
  "type": "Feature",
  "properties": {
    "addr:full":"Solb\u00e6rvej 7, Hune Blokhus Danmark 9492",
    "addr:housenumber":"7",
    "addr:postcode":"9492",
    "addr:street":"Solbaervej;Hune",
    "iso:country":"DK",
    "sg:address":"Solb\u00e6rvej 7, Hune",
    "sg:city":"Blokhus",
    "sg:orig_category":"Murermestre",
    "sg:phone":"+45 98 20 94 12",
    "sg:postcode":"9492",
    "sg:province":"Danmark",
    "wof:name":"Gj\u00f8l Mureren",
    "wof:placetype":"venue"
},
  "geometry": {"coordinates":[9.5916996002,57.250995636],"type":"Point"}
}