{
  "type": "Feature",
  "properties": {
    "addr:full":"Farmervej 1, Malt Vejen Danmark 6600",
    "addr:housenumber":"1",
    "addr:postcode":"6600",
    "addr:street":"Farmervej",
    "iso:country":"DK",
    "sg:address":"Farmervej 1, Malt",
    "sg:city":"Vejen",
    "sg:orig_category":"Plastvarefabrikker",
    "sg:phone":"+45 75 36 20 22",
    "sg:postcode":"6600",
    "sg:province":"Danmark",
    "wof:name":"Langballe ApS, H.W.",
    "wof:placetype":"venue"
},
  "geometry": {"coordinates":[9.1396121979,55.4778175354],"type":"Point"}
}