{
  "type": "Feature",
  "properties": {
    "addr:full":"Ved Landsoldaten 3, 1 Fredericia Danmark 7000",
    "addr:housenumber":"3 1",
    "addr:postcode":"7000",
    "addr:street":"Ved Landsoldaten",
    "iso:country":"DK",
    "sg:address":"Ved Landsoldaten 3, 1",
    "sg:city":"Fredericia",
    "sg:orig_category":"Plejehjem",
    "sg:phone":"+45 72 10 65 65",
    "sg:postcode":"7000",
    "sg:province":"Danmark",
    "wof:name":"Omr\u00e5de 3 - I.P. Schmidt Omr\u00e5det",
    "wof:placetype":"venue"
},
  "geometry": {"coordinates":[9.7538776398,55.5674972534],"type":"Point"}
}