{
  "type": "Feature",
  "properties": {
    "iso:country":"DK",
    "sg:address":"Kursusleder: Inger Nellemann S\u00f8rensen, Lund\u00f8vej 113, Svenstrup",
    "sg:city":"H\u00f8jslev",
    "sg:orig_category":"\u00c3\u02dcvrig fritidsundervisning",
    "sg:phone":"+45 97 53 70 55",
    "sg:postcode":"7840",
    "sg:province":"Danmark",
    "wof:name":"Dommerby, H\u00f8jslev og Nr. S\u00f8by Aftenskole",
    "wof:placetype":"venue"
},
  "geometry": {"coordinates":[9.110039711,56.5504264832],"type":"Point"}
}