{
  "type": "Feature",
  "properties": {
    "addr:full":"Nyhavn 61 K\u00f8benhavn Danmark 1051",
    "addr:housenumber":"61;1051",
    "addr:street":"Nyhavn",
    "iso:country":"DK",
    "sg:address":"Nyhavn 61",
    "sg:city":"K\u00f8benhavn",
    "sg:classifiers":[
        {
            "category":"Harbor",
            "type":"Transportation"
        }
    ],
    "sg:phone":"+45 33 33 93 55",
    "sg:postcode":"1051",
    "sg:province":"Danmark",
    "sg:tags":[
        "shipping"
    ],
    "sg:website":"www.spar-shipping.dk",
    "wof:name":"Spar Shipping ApS",
    "wof:placetype":"venue"
},
  "geometry": {"coordinates":[12.5919704437,55.679889679],"type":"Point"}
}