{
  "type": "Feature",
  "properties": {
    "addr:full":"Alleen 13 Ry Danmark 8680",
    "addr:housenumber":"13",
    "addr:postcode":"8680",
    "addr:street":"Alleen",
    "iso:country":"DK",
    "sg:address":"Alleen 13",
    "sg:city":"Ry",
    "sg:orig_category":"Psykologer, praktiserende",
    "sg:phone":"+45 86 89 06 05",
    "sg:postcode":"8680",
    "sg:province":"Danmark",
    "wof:name":"Thannel, Bjarne",
    "wof:placetype":"venue"
},
  "geometry": {"coordinates":[9.764134407,56.0951461792],"type":"Point"}
}