{
  "type": "Feature",
  "properties": {
    "addr:full":"Holbergs Have 22 Holb\u00e6k Danmark 4300",
    "addr:housenumber":"22",
    "addr:postcode":"4300",
    "addr:street":"Holbergs Have",
    "iso:country":"DK",
    "sg:address":"Holbergs Have 22",
    "sg:city":"Holb\u00e6k",
    "sg:orig_category":"Arkitekter",
    "sg:phone":"+45 59 43 06 34",
    "sg:postcode":"4300",
    "sg:province":"Danmark",
    "wof:name":"Gettermann, Erik",
    "wof:placetype":"venue"
},
  "geometry": {"coordinates":[11.7483949661,55.7206916809],"type":"Point"}
}