{
  "type": "Feature",
  "properties": {
    "addr:full":"S\u00f8ndergade 22 Hadsten Danmark 8370",
    "addr:housenumber":"22",
    "addr:postcode":"8370",
    "addr:street":"Sondergade",
    "iso:country":"DK",
    "sg:address":"S\u00f8ndergade 22",
    "sg:city":"Hadsten",
    "sg:orig_category":"Bagere",
    "sg:phone":"+45 86 98 02 61",
    "sg:postcode":"8370",
    "sg:province":"Danmark",
    "wof:name":"Lyngaa's Bageri",
    "wof:placetype":"venue"
},
  "geometry": {"coordinates":[10.0440216064,56.3272514343],"type":"Point"}
}