{
  "type": "Feature",
  "properties": {
    "addr:full":"v/ Bodil Hansen, Vestergade 16, Gjerlev Gjerlev Danmark 8983",
    "addr:housenumber":"16",
    "addr:postcode":"8983",
    "addr:street":"Vestergade;Gjerlev Gjerlev Danmark",
    "iso:country":"DK",
    "sg:address":"v/ Bodil Hansen, Vestergade 16, Gjerlev",
    "sg:city":"Gjerlev",
    "sg:orig_category":"Forsamlingshuse",
    "sg:phone":"+45 86 47 47 71",
    "sg:postcode":"8983",
    "sg:province":"Danmark",
    "wof:name":"Gjerlev Forsamlingshus",
    "wof:placetype":"venue"
},
  "geometry": {"coordinates":[10.1887750626,56.5788421631],"type":"Point"}
}