{
  "type": "Feature",
  "properties": {
    "iso:country":"DK",
    "sg:address":"Ellek\u00e6r 1 ",
    "sg:city":"Frederikssund",
    "sg:classifiers":[
        {
            "category":"Food & Beverages",
            "subcategory":"Groceries & Convenience Stores",
            "type":"Retail Goods"
        }
    ],
    "sg:phone":"+45 47 36 52 00",
    "sg:postcode":"3600",
    "sg:province":"Danmark",
    "sg:tags":[
        "drink"
    ],
    "wof:name":"CADISO FOOD A/S",
    "wof:placetype":"venue"
},
  "geometry": {"coordinates":[12.0661621094,55.8370323181],"type":"Point"}
}