{
  "type": "Feature",
  "properties": {
    "addr:full":"Birkevej 87, V. H\u00e6singe Broby Danmark 5672",
    "addr:housenumber":"87",
    "addr:postcode":"5672",
    "addr:street":"Birkevej;Haesinge",
    "iso:country":"DK",
    "sg:address":"Birkevej 87, V. H\u00e6singe",
    "sg:city":"Broby",
    "sg:orig_category":"Medicinalvareindustri",
    "sg:phone":"+45 62 63 36 50",
    "sg:postcode":"5672",
    "sg:province":"Danmark",
    "sg:website":"www.plantemedicin.org",
    "wof:name":"EMPAS - Endelave Medicin A/S",
    "wof:placetype":"venue"
},
  "geometry": {"coordinates":[10.3131303787,55.2695846558],"type":"Point"}
}