{
  "type": "Feature",
  "properties": {
    "addr:full":"S\u00f8vej 27 Borup Danmark 4140",
    "addr:housenumber":"27",
    "addr:postcode":"4140",
    "addr:street":"Sovej",
    "iso:country":"DK",
    "sg:address":"S\u00f8vej 27",
    "sg:city":"Borup",
    "sg:orig_category":"Reparationer",
    "sg:phone":"+45 57 52 72 50",
    "sg:postcode":"4140",
    "sg:province":"Danmark",
    "wof:name":"Multi Tec Service",
    "wof:placetype":"venue"
},
  "geometry": {"coordinates":[11.9749145508,55.4920845032],"type":"Point"}
}