{
  "type": "Feature",
  "properties": {
    "addr:full":"Slagterivej 27 Haslev Danmark 4690",
    "addr:housenumber":"27",
    "addr:postcode":"4690",
    "addr:street":"Slagterivej",
    "iso:country":"DK",
    "sg:address":"Slagterivej 27",
    "sg:city":"Haslev",
    "sg:orig_category":"Varmeforsyning",
    "sg:phone":"+45 56 31 23 33",
    "sg:postcode":"4690",
    "sg:province":"Danmark",
    "wof:name":"Haslev Kraftvarmev\u00e6rk",
    "wof:placetype":"venue"
},
  "geometry": {"coordinates":[11.9624948502,55.3305702209],"type":"Point"}
}