{
  "type": "Feature",
  "properties": {
    "addr:full":"Nedergade 34 A Ebeltoft Danmark 8400",
    "addr:housenumber":"34 a",
    "addr:postcode":"8400",
    "addr:street":"Nedergade",
    "iso:country":"DK",
    "sg:address":"Nedergade 34 A",
    "sg:city":"Ebeltoft",
    "sg:orig_category":"Solcentre",
    "sg:phone":"+45 86 34 48 96",
    "sg:postcode":"8400",
    "sg:province":"Danmark",
    "wof:name":"Ebeltoft M\u00f8ntvask og Sol",
    "wof:placetype":"venue"
},
  "geometry": {"coordinates":[10.6744089127,56.1954193115],"type":"Point"}
}