{
  "type": "Feature",
  "properties": {
    "addr:full":"Knudstrupvej 8, Kongstrup Lang\u00e5 Danmark 8870",
    "addr:housenumber":"8",
    "addr:postcode":"8870",
    "addr:street":"Knudstrupvej",
    "iso:country":"DK",
    "sg:address":"Knudstrupvej 8, Kongstrup",
    "sg:city":"Lang\u00e5",
    "sg:classifiers":[
        {
            "category":"Taxi",
            "type":"Transportation"
        }
    ],
    "sg:phone":"+45 86 46 80 61",
    "sg:postcode":"8870",
    "sg:province":"Danmark",
    "wof:name":"Laurbjerg Lang\u00e5 Taxi",
    "wof:placetype":"venue"
},
  "geometry": {"coordinates":[9.8955049515,56.3900756836],"type":"Point"}
}