{
  "type": "Feature",
  "properties": {
    "addr:full":"Fmd.: Bent Loff-Petersen, Lisevej 6 Stenl\u00f8se Danmark 3660",
    "addr:housenumber":"6",
    "addr:postcode":"3660",
    "addr:street":"Lisevej",
    "iso:country":"DK",
    "sg:address":"Fmd.: Bent Loff-Petersen, Lisevej 6",
    "sg:city":"Stenl\u00f8se",
    "sg:orig_category":"Grundejerforeninger",
    "sg:phone":"+45 47 10 79 74",
    "sg:postcode":"3660",
    "sg:province":"Danmark",
    "wof:name":"Garbog\u00e5rd, Grundejerforeningen",
    "wof:placetype":"venue"
},
  "geometry": {"coordinates":[-105.85247802729999,33.1596488953],"type":"Point"}
}