{
  "type": "Feature",
  "properties": {
    "addr:full":"Kirkebjergvej 4 Jyllinge Danmark 4040",
    "addr:housenumber":"4",
    "addr:postcode":"4040",
    "addr:street":"Kirkebjergvej",
    "iso:country":"DK",
    "sg:address":"Kirkebjergvej 4",
    "sg:city":"Jyllinge",
    "sg:orig_category":"Plejehjem",
    "sg:phone":"+45 46 78 81 51",
    "sg:postcode":"4040",
    "sg:province":"Danmark",
    "wof:name":"Kastanjehaven",
    "wof:placetype":"venue"
},
  "geometry": {"coordinates":[12.1058349609,55.7509498596],"type":"Point"}
}