{
  "type": "Feature",
  "properties": {
    "iso:country":"DK",
    "sg:address":"Fmd.: Jan Hedal, Gr\u00e6sk\u00e6mnervej 20",
    "sg:city":"Svendborg",
    "sg:orig_category":"Kulturelle foreninger",
    "sg:phone":"+45 62 21 44 16",
    "sg:postcode":"5700",
    "sg:province":"Danmark",
    "wof:name":"Bygnings- og Landskabskultur for Sydfyn, Foreningen for",
    "wof:placetype":"venue"
},
  "geometry": {"coordinates":[10.6065101624,55.0595970154],"type":"Point"}
}