{
  "type": "Feature",
  "properties": {
    "addr:full":"S\u00e6byvej 3 Asaa Danmark 9340",
    "addr:housenumber":"3",
    "addr:postcode":"9340",
    "addr:street":"Saebyvej",
    "iso:country":"DK",
    "sg:address":"S\u00e6byvej 3",
    "sg:city":"Asaa",
    "sg:orig_category":"Korn og foderstoffer",
    "sg:phone":"+45 99 96 22 22",
    "sg:postcode":"9340",
    "sg:province":"Danmark",
    "wof:name":"DLG Vendsyssel og Han Herred",
    "wof:placetype":"venue"
},
  "geometry": {"coordinates":[10.4043912888,57.1486625671],"type":"Point"}
}