{
  "type": "Feature",
  "properties": {
    "addr:full":"Sor\u00f8vej 3 Slagelse Danmark 4200",
    "addr:housenumber":"3",
    "addr:postcode":"4200",
    "addr:street":"Sorovej",
    "iso:country":"DK",
    "sg:address":"Sor\u00f8vej 3",
    "sg:city":"Slagelse",
    "sg:orig_category":"Autoelektro",
    "sg:phone":"+45 58 52 35 35",
    "sg:postcode":"4200",
    "sg:province":"Danmark",
    "wof:name":"Autoteknik Bosch Service",
    "wof:placetype":"venue"
},
  "geometry": {"coordinates":[11.3701705933,55.4082984924],"type":"Point"}
}