{
  "type": "Feature",
  "properties": {
    "addr:full":"v/ Anni-Mona Kristensen, Gammel F\u00e6rgevej 25, Sillerslev \u00d8ster Assels Danmark 7990",
    "addr:housenumber":"25",
    "addr:postcode":"7990",
    "addr:street":"Gammel Faergevej;Oster",
    "iso:country":"DK",
    "sg:address":"v/ Anni-Mona Kristensen, Gammel F\u00e6rgevej 25, Sillerslev",
    "sg:city":"\u00d8ster Assels",
    "sg:orig_category":"Forsamlingshuse",
    "sg:phone":"+45 97 76 44 16",
    "sg:postcode":"7990",
    "sg:province":"Danmark",
    "wof:name":"Sillerslev Forsamlingshus",
    "wof:placetype":"venue"
},
  "geometry": {"coordinates":[8.7583551407,56.7187957764],"type":"Point"}
}