{
  "type": "Feature",
  "properties": {
    "addr:full":"Vibensholmsvej 8, Fredtofte Kokkedal Danmark 2980",
    "addr:housenumber":"8",
    "addr:postcode":"2980",
    "addr:street":"Vibensholmsvej;Fredtofte",
    "iso:country":"DK",
    "sg:address":"Vibensholmsvej 8, Fredtofte",
    "sg:city":"Kokkedal",
    "sg:orig_category":"Snedkermestre",
    "sg:phone":"+45 48 28 01 42",
    "sg:postcode":"2980",
    "sg:province":"Danmark",
    "wof:name":"Hoe, Palle",
    "wof:placetype":"venue"
},
  "geometry": {"coordinates":[12.4769096375,55.9091339111],"type":"Point"}
}