{
  "type": "Feature",
  "properties": {
    "addr:full":"N\u00f8rretoften 1, Osted Roskilde Danmark 4000",
    "addr:housenumber":"1",
    "addr:postcode":"4000",
    "addr:street":"Norretoften;Osted",
    "iso:country":"DK",
    "sg:address":"N\u00f8rretoften 1, Osted",
    "sg:city":"Roskilde",
    "sg:orig_category":"Brugsforeninger",
    "sg:phone":"+45 46 49 70 02",
    "sg:postcode":"4000",
    "sg:province":"Danmark",
    "wof:name":"Super Brugsen",
    "wof:placetype":"venue"
},
  "geometry": {"coordinates":[12.0909376144,55.6404838562],"type":"Point"}
}