{
  "type": "Feature",
  "properties": {
    "iso:country":"DK",
    "sg:address":"Bredgade 11",
    "sg:city":"Kolind",
    "sg:orig_category":"Ejendomshandel",
    "sg:phone":"+45 86 39 28 00",
    "sg:postcode":"8560",
    "sg:province":"Danmark",
    "wof:name":"JE Ejendomscenter",
    "wof:placetype":"venue"
},
  "geometry": {"coordinates":[10.5880613327,56.3619728088],"type":"Point"}
}