{
  "type": "Feature",
  "properties": {
    "addr:full":"Agtrupvej 146 Kolding Danmark 6000",
    "addr:housenumber":"146",
    "addr:postcode":"6000",
    "addr:street":"Agtrupvej",
    "iso:country":"DK",
    "sg:address":"Agtrupvej 146",
    "sg:city":"Kolding",
    "sg:orig_category":"Ejendomshandel",
    "sg:phone":"+45 75 54 26 00",
    "sg:postcode":"6000",
    "sg:province":"Danmark",
    "wof:name":"Nybolig - Kolding Syd",
    "wof:placetype":"venue"
},
  "geometry": {"coordinates":[9.4889822006,55.4789924622],"type":"Point"}
}