{
  "type": "Feature",
  "properties": {
    "addr:full":"v/ Jens Chr. Andersen, Toftager 16 Lintrup Danmark 6660",
    "addr:housenumber":"16",
    "addr:postcode":"6660",
    "addr:street":"Toftager",
    "iso:country":"DK",
    "sg:address":"v/ Jens Chr. Andersen, Toftager 16",
    "sg:city":"Lintrup",
    "sg:orig_category":"Borger- og beboerforeninger",
    "sg:phone":"+45 74 85 54 23",
    "sg:postcode":"6660",
    "sg:province":"Danmark",
    "sg:website":"www.lintrup.dk",
    "wof:name":"Lintrup Hjerting Borgerforening",
    "wof:placetype":"venue"
},
  "geometry": {"coordinates":[8.9733600616,55.408870697],"type":"Point"}
}