{
  "type": "Feature",
  "properties": {
    "addr:full":"Bredgade 6 Pandrup Danmark 9490",
    "addr:housenumber":"6",
    "addr:postcode":"9490",
    "addr:street":"Bredgade",
    "iso:country":"DK",
    "sg:address":"Bredgade 6",
    "sg:city":"Pandrup",
    "sg:orig_category":"Dag- og distriktsblade",
    "sg:phone":"+45 98 24 62 22",
    "sg:postcode":"9490",
    "sg:province":"Danmark",
    "wof:name":"Nordjyllands Avisselskab A/S",
    "wof:placetype":"venue"
},
  "geometry": {"coordinates":[9.6767654419,57.2242736816],"type":"Point"}
}