{
  "type": "Feature",
  "properties": {
    "iso:country":"DK",
    "sg:address":"Fiskergade 7 ",
    "sg:city":"Varde",
    "sg:classifiers":[
        {
            "category":"Food & Beverages",
            "subcategory":"Groceries & Convenience Stores",
            "type":"Retail Goods"
        }
    ],
    "sg:phone":"+45 75 22 50 44",
    "sg:postcode":"6800",
    "sg:province":"Danmark",
    "sg:tags":[
        "drink"
    ],
    "wof:name":"FROPEX FOODS AF 1983 A/S",
    "wof:placetype":"venue"
},
  "geometry": {"coordinates":[8.4822015762,55.6201171875],"type":"Point"}
}