{
  "type": "Feature",
  "properties": {
    "addr:full":"Nordh\u00f8jvej 15, St. Tor\u00f8je Fakse Danmark 4640",
    "addr:housenumber":"15",
    "addr:postcode":"4640",
    "addr:street":"Nordhojvej",
    "iso:country":"DK",
    "sg:address":"Nordh\u00f8jvej 15, St. Tor\u00f8je",
    "sg:city":"Fakse",
    "sg:orig_category":"Autoreparation og -service",
    "sg:phone":"+45 56 50 86 48",
    "sg:postcode":"4640",
    "sg:province":"Danmark",
    "wof:name":"Pedersen, Steen Kirkeby",
    "wof:placetype":"venue"
},
  "geometry": {"coordinates":[12.1203422546,55.2574195862],"type":"Point"}
}