{
  "type": "Feature",
  "properties": {
    "addr:full":"Ungdomsskoleinsp: Poul Erik Jensen, Aaparken 31 Aalestrup Danmark 9620",
    "addr:housenumber":"31",
    "addr:postcode":"9620",
    "addr:street":"Poul Erik Jensen Aaparken",
    "iso:country":"DK",
    "sg:address":"Ungdomsskoleinsp: Poul Erik Jensen, Aaparken 31",
    "sg:city":"Aalestrup",
    "sg:orig_category":"Kommunale ungdomsskoler",
    "sg:phone":"+45 98 64 19 62",
    "sg:postcode":"9620",
    "sg:province":"Danmark",
    "wof:name":"Aalestrup kommunale ungdomsskole",
    "wof:placetype":"venue"
},
  "geometry": {"coordinates":[9.4901504517,56.6938285828],"type":"Point"}
}