{
  "type": "Feature",
  "properties": {
    "addr:full":"Vestergade 33  Vemb Danmark 7570",
    "addr:housenumber":"33",
    "addr:postcode":"7570",
    "addr:street":"Vestergade",
    "iso:country":"DK",
    "sg:address":"Vestergade 33 ",
    "sg:city":"Vemb",
    "sg:classifiers":[
        {
            "category":"Home & Garden",
            "subcategory":"Home Furnishings",
            "type":"Retail Goods"
        }
    ],
    "sg:phone":"+45 97 48 13 23",
    "sg:postcode":"7570",
    "sg:province":"Danmark",
    "sg:tags":[
        "household"
    ],
    "wof:name":"P RIMMES M\u00d8BELFABRIK APS",
    "wof:placetype":"venue"
},
  "geometry": {"coordinates":[8.336722374,56.3423233032],"type":"Point"}
}