{
  "type": "Feature",
  "properties": {
    "addr:full":"Fmd.: Orla Nielsen, Kringsv\u00e6nget 28, Bramdrupdam Kolding Danmark 6000",
    "addr:housenumber":"28",
    "addr:postcode":"6000",
    "addr:street":"Bramdrupdam",
    "iso:country":"DK",
    "sg:address":"Fmd.: Orla Nielsen, Kringsv\u00e6nget 28, Bramdrupdam",
    "sg:city":"Kolding",
    "sg:orig_category":"Hobbybetonede foreninger",
    "sg:phone":"+45 75 51 88 94",
    "sg:postcode":"6000",
    "sg:province":"Danmark",
    "wof:name":"Eksperimenterende Danske Radioamat\u00f8rer, Kolding afd.",
    "wof:placetype":"venue"
},
  "geometry": {"coordinates":[9.4733953476,55.4863586426],"type":"Point"}
}