{
  "type": "Feature",
  "properties": {
    "addr:full":"Mimers Alle 15 Esbjerg \u00d8 Danmark 6705",
    "addr:housenumber":"15",
    "addr:postcode":"6705",
    "addr:street":"Mimers Alle;Danmark",
    "iso:country":"DK",
    "sg:address":"Mimers Alle 15",
    "sg:city":"Esbjerg \u00d8",
    "sg:orig_category":"Hobbybetonede foreninger",
    "sg:phone":"+45 75 14 07 68",
    "sg:postcode":"6705",
    "sg:province":"Danmark",
    "wof:name":"P. Hom\u00e5",
    "wof:placetype":"venue"
},
  "geometry": {"coordinates":[8.4742393494,55.4838829041],"type":"Point"}
}