{
  "type": "Feature",
  "properties": {
    "addr:full":"v/ Lillian Mortensen, Roskildevej 13 Kirke Hvals\u00f8 Danmark 4330",
    "addr:housenumber":"13",
    "addr:postcode":"4330",
    "addr:street":"Roskildevej",
    "iso:country":"DK",
    "sg:address":"v/ Lillian Mortensen, Roskildevej 13",
    "sg:city":"Kirke Hvals\u00f8",
    "sg:orig_category":"\u00c3\u2020ldreorganisationer og klubber",
    "sg:phone":"+45 46 40 83 05",
    "sg:postcode":"4330",
    "sg:province":"Danmark",
    "wof:name":"Seniorklubben",
    "wof:placetype":"venue"
},
  "geometry": {"coordinates":[-97.18897247309999,32.5049285889],"type":"Point"}
}