{
  "type": "Feature",
  "properties": {
    "addr:full":"Kass.: Michael Larsen, Siem Byvej 3 Terndrup Danmark 9575",
    "addr:housenumber":"3",
    "addr:postcode":"9575",
    "addr:street":"Siem Byvej;Danmark",
    "iso:country":"DK",
    "sg:address":"Kass.: Michael Larsen, Siem Byvej 3",
    "sg:city":"Terndrup",
    "sg:orig_category":"Borger- og beboerforeninger",
    "sg:phone":"+45 98 33 57 37",
    "sg:postcode":"9575",
    "sg:province":"Danmark",
    "wof:name":"Siem Ejstrup Gadelysforening",
    "wof:placetype":"venue"
},
  "geometry": {"coordinates":[10.058382988,56.8162651062],"type":"Point"}
}