{
  "type": "Feature",
  "properties": {
    "addr:full":"Landsdommervej 35 K\u00f8benhavn NV Danmark 2400",
    "addr:housenumber":"35",
    "addr:postcode":"2400",
    "addr:street":"Landsdommervej",
    "iso:country":"DK",
    "sg:address":"Landsdommervej 35",
    "sg:city":"K\u00f8benhavn NV",
    "sg:orig_category":"Kirkesogne",
    "sg:phone":"+45 35 81 19 77",
    "sg:postcode":"2400",
    "sg:province":"Danmark",
    "wof:name":"Tagensbo sogns kirkekontor",
    "wof:placetype":"venue"
},
  "geometry": {"coordinates":[-117.02272033689999,38.5024604797],"type":"Point"}
}