{
  "type": "Feature",
  "properties": {
    "addr:full":"Islandsgade 3 Ikast Danmark 7430",
    "addr:housenumber":"3",
    "addr:postcode":"7430",
    "addr:street":"Islandsgade",
    "iso:country":"DK",
    "sg:address":"Islandsgade 3",
    "sg:city":"Ikast",
    "sg:orig_category":"Boligselskaber",
    "sg:phone":"+45 97 15 21 55",
    "sg:postcode":"7430",
    "sg:province":"Danmark",
    "wof:name":"Videb\u00e6k Boligforening",
    "wof:placetype":"venue"
},
  "geometry": {"coordinates":[9.1661949158,56.1390075684],"type":"Point"}
}