{
  "type": "Feature",
  "properties": {
    "iso:country":"DK",
    "sg:address":"Djursvang 6",
    "sg:city":"Albertslund",
    "sg:orig_category":"Maskinfabrikker",
    "sg:phone":"+45 43 62 31 82",
    "sg:postcode":"2620",
    "sg:province":"Danmark",
    "wof:name":"Nordisk Kinematograffabrik",
    "wof:placetype":"venue"
},
  "geometry": {"coordinates":[12.3587341309,55.6659393311],"type":"Point"}
}