{
  "type": "Feature",
  "properties": {
    "addr:full":"Kredsleder: Flemming W. Nielsen, Kirkevej 18 Gesten Danmark 6621",
    "addr:housenumber":"18",
    "addr:postcode":"6621",
    "addr:street":"Kredsleder;W. Nielsen Kirkevej",
    "iso:country":"DK",
    "sg:address":"Kredsleder: Flemming W. Nielsen, Kirkevej 18",
    "sg:city":"Gesten",
    "sg:orig_category":"Beredskabsforbund",
    "sg:phone":"+45 75 55 71 49",
    "sg:postcode":"6621",
    "sg:province":"Danmark",
    "wof:name":"Beredskabsforbundet, Vejen Kreds",
    "wof:placetype":"venue"
},
  "geometry": {"coordinates":[9.208596,55.525517],"type":"Point"}
}