{
  "type": "Feature",
  "properties": {
    "addr:full":"Rosenv\u00e6nget 11, Dalum Odense SV Danmark 5250",
    "addr:housenumber":"11",
    "addr:postcode":"5250",
    "addr:street":"Rosenvaenget;Dalum",
    "iso:country":"DK",
    "sg:address":"Rosenv\u00e6nget 11, Dalum",
    "sg:city":"Odense SV",
    "sg:orig_category":"Erhvervslokaler, Udlejning af",
    "sg:phone":"+45 65 91 64 63",
    "sg:postcode":"5250",
    "sg:province":"Danmark",
    "wof:name":"Andersen, Torben P",
    "wof:placetype":"venue"
},
  "geometry": {"coordinates":[10.3153953552,55.3362998962],"type":"Point"}
}