{
  "type": "Feature",
  "properties": {
    "addr:full":"Elme Alle 6, Hareskov V\u00e6rl\u00f8se Danmark 3500",
    "addr:housenumber":"6",
    "addr:postcode":"3500",
    "addr:street":"Elme Alle",
    "iso:country":"DK",
    "sg:address":"Elme Alle 6, Hareskov",
    "sg:city":"V\u00e6rl\u00f8se",
    "sg:orig_category":"Cykler",
    "sg:phone":"+45 44 98 06 03",
    "sg:postcode":"3500",
    "sg:province":"Danmark",
    "wof:name":"Hareskov Cykler",
    "wof:placetype":"venue"
},
  "geometry": {"coordinates":[12.4117698669,55.754650116],"type":"Point"}
}