{
  "type": "Feature",
  "properties": {
    "addr:full":"Andek\u00e6ret 149 Kerteminde Danmark 5300",
    "addr:housenumber":"149",
    "addr:postcode":"5300",
    "iso:country":"DK",
    "sg:address":"Andek\u00e6ret 149",
    "sg:city":"Kerteminde",
    "sg:orig_category":"Integrerede institutioner",
    "sg:phone":"+45 65 32 11 51",
    "sg:postcode":"5300",
    "sg:province":"Danmark",
    "wof:name":"Kerteminde b\u00f8rneg\u00e5rd",
    "wof:placetype":"venue"
},
  "geometry": {"coordinates":[10.6600999832,55.4506492615],"type":"Point"}
}