{
  "type": "Feature",
  "properties": {
    "addr:full":"Vesterbo 97 V\u00e6rl\u00f8se Danmark 3500",
    "addr:housenumber":"97",
    "addr:postcode":"3500",
    "addr:street":"Vesterbo",
    "iso:country":"DK",
    "sg:address":"Vesterbo 97",
    "sg:city":"V\u00e6rl\u00f8se",
    "sg:orig_category":"Murermestre",
    "sg:phone":"+45 44 48 16 76",
    "sg:postcode":"3500",
    "sg:province":"Danmark",
    "wof:name":"Br\u00f8ndsted, Palle",
    "wof:placetype":"venue"
},
  "geometry": {"coordinates":[12.4117698669,55.754650116],"type":"Point"}
}