{
  "type": "Feature",
  "properties": {
    "iso:country":"DK",
    "sg:address":"\u00d8stergaardsvej 5 ",
    "sg:city":"Haarby",
    "sg:classifiers":[
        {
            "category":"Banks & Credit Unions",
            "subcategory":"Bank",
            "type":"Services"
        }
    ],
    "sg:phone":"+45 64 73 17 26",
    "sg:postcode":"5683",
    "sg:province":"Danmark",
    "sg:tags":[
        "banking",
        "institution"
    ],
    "wof:name":"PER BROVN PEDERSEN H\u00c5RBY HOLDING A/S",
    "wof:placetype":"venue"
},
  "geometry": {"coordinates":[10.118504,55.208706],"type":"Point"}
}