{
  "type": "Feature",
  "properties": {
    "addr:full":"Egholm 57 Aalborg Danmark 9000",
    "addr:housenumber":"57",
    "addr:postcode":"9000",
    "addr:street":"Egholm",
    "iso:country":"DK",
    "sg:address":"Egholm 57",
    "sg:city":"Aalborg",
    "sg:orig_category":"Kursussteder",
    "sg:phone":"+45 98 19 40 70",
    "sg:postcode":"9000",
    "sg:province":"Danmark",
    "wof:name":"Egholm Vestergaard",
    "wof:placetype":"venue"
},
  "geometry": {"coordinates":[9.8408155441,57.0651664734],"type":"Point"}
}