{
  "type": "Feature",
  "properties": {
    "addr:full":"Ursinsvej 8 Viborg Danmark 8800",
    "addr:housenumber":"8",
    "addr:postcode":"8800",
    "addr:street":"Ursinsvej",
    "iso:country":"DK",
    "sg:address":"Ursinsvej 8",
    "sg:city":"Viborg",
    "sg:orig_category":"Automater",
    "sg:phone":"+45 86 62 89 89",
    "sg:postcode":"8800",
    "sg:province":"Danmark",
    "wof:name":"A. T. W. Automater ApS.",
    "wof:placetype":"venue"
},
  "geometry": {"coordinates":[9.3965063095,56.4508934021],"type":"Point"}
}