{
  "type": "Feature",
  "properties": {
    "addr:full":"Sognepr\u00e6st: Lars Paludan (K/B), Bodebjergvej 2, K\u00f8ng Glamsbjerg Danmark 5620",
    "addr:housenumber":"2",
    "addr:postcode":"5620",
    "addr:street":"Bodebjergvej;Kong",
    "iso:country":"DK",
    "sg:address":"Sognepr\u00e6st: Lars Paludan (K/B), Bodebjergvej 2, K\u00f8ng",
    "sg:city":"Glamsbjerg",
    "sg:orig_category":"Kirkesogne",
    "sg:phone":"+45 64 72 10 74",
    "sg:postcode":"5620",
    "sg:province":"Danmark",
    "wof:name":"Glamsbjerg og K\u00f8ng sogne",
    "wof:placetype":"venue"
},
  "geometry": {"coordinates":[10.1052503586,55.2783317566],"type":"Point"}
}