{
  "type": "Feature",
  "properties": {
    "addr:full":"M\u00e5gevej 33 K\u00f8benhavn NV Danmark 2400",
    "addr:housenumber":"33",
    "addr:postcode":"2400",
    "addr:street":"Maagevej",
    "iso:country":"DK",
    "sg:address":"M\u00e5gevej 33",
    "sg:city":"K\u00f8benhavn NV",
    "sg:orig_category":"Folkekirken",
    "sg:phone":"+45 38 34 48 36",
    "sg:postcode":"2400",
    "sg:province":"Danmark",
    "wof:name":"Ansgar Kirke",
    "wof:placetype":"venue"
},
  "geometry": {"coordinates":[-117.02272033689999,38.5024604797],"type":"Point"}
}