{
  "type": "Feature",
  "properties": {
    "addr:full":"Br\u00f8ndbyvestervej 24 Glostrup Danmark 2600",
    "addr:housenumber":"24",
    "addr:postcode":"2600",
    "addr:street":"Brondbyvestervej",
    "iso:country":"DK",
    "sg:address":"Br\u00f8ndbyvestervej 24",
    "sg:city":"Glostrup",
    "sg:orig_category":"Plejehjem",
    "sg:phone":"+45 43 96 06 18",
    "sg:postcode":"2600",
    "sg:province":"Danmark",
    "wof:name":"Kirkebrohus Plejehjem",
    "wof:placetype":"venue"
},
  "geometry": {"coordinates":[12.4068870544,55.6590919495],"type":"Point"}
}