{
  "type": "Feature",
  "properties": {
    "iso:country":"DK",
    "sg:address":"Jernbanegade 56",
    "sg:city":"Haslev",
    "sg:classifiers":[
        {
            "category":"Home & Garden",
            "subcategory":"Home Furnishings",
            "type":"Retail Goods"
        }
    ],
    "sg:phone":"+45 56 31 20 49",
    "sg:postcode":"4690",
    "sg:province":"Danmark",
    "sg:tags":[
        "gardiner"
    ],
    "sg:website":"www.profa.dk",
    "wof:name":"Profa Farver",
    "wof:placetype":"venue"
},
  "geometry": {"coordinates":[11.9636278152,55.3246498108],"type":"Point"}
}