{
  "type": "Feature",
  "properties": {
    "iso:country":"DK",
    "sg:address":"Fmd.: Knud-J\u00f8rn Bowmann, Havnevej 89",
    "sg:city":"Grenaa",
    "sg:orig_category":"Borger- og beboerforeninger",
    "sg:phone":"+45 86 32 48 62",
    "sg:postcode":"8500",
    "sg:province":"Danmark",
    "wof:name":"Grenaa Borger- og Arbejderforening",
    "wof:placetype":"venue"
},
  "geometry": {"coordinates":[10.8774929047,56.4126853943],"type":"Point"}
}