{
  "type": "Feature",
  "properties": {
    "iso:country":"DK",
    "sg:address":"Bredgade 48 A",
    "sg:city":"Lang\u00e5",
    "sg:orig_category":"Ejendomshandel",
    "sg:phone":"+45 86 46 28 66",
    "sg:postcode":"8870",
    "sg:province":"Danmark",
    "wof:name":"Bolig-Ringen Lang\u00e5",
    "wof:placetype":"venue"
},
  "geometry": {"coordinates":[9.8963975906,56.3882675171],"type":"Point"}
}