{
  "type": "Feature",
  "properties": {
    "addr:full":"Industrivej Vest 5 Vejen Danmark 6600",
    "addr:housenumber":"5",
    "addr:postcode":"6600",
    "addr:street":"Industrivej Vest",
    "iso:country":"DK",
    "sg:address":"Industrivej Vest 5",
    "sg:city":"Vejen",
    "sg:orig_category":"Autoreparation og -service",
    "sg:phone":"+45 75 36 62 44",
    "sg:postcode":"6600",
    "sg:province":"Danmark",
    "sg:website":"www.automester.dk",
    "wof:name":"Svends V\u00e6rksted",
    "wof:placetype":"venue"
},
  "geometry": {"coordinates":[9.1264829636,55.4894676208],"type":"Point"}
}