{
  "type": "Feature",
  "properties": {
    "iso:country":"DK",
    "sg:address":"Kl\u00f8vervej 6, Klokkerholm",
    "sg:city":"Hjallerup",
    "sg:orig_category":"Maskinfabrikker",
    "sg:phone":"+45 98 28 44 44",
    "sg:postcode":"9320",
    "sg:province":"Danmark",
    "sg:website":"www.klokkerholm.com",
    "wof:name":"Klokkerholm Karosseridele",
    "wof:placetype":"venue"
},
  "geometry": {"coordinates":[10.1444702148,57.1677742004],"type":"Point"}
}