{
  "type": "Feature",
  "properties": {
    "addr:full":"Kirkestien 7, Vejlby Alling\u00e5bro Danmark 8961",
    "addr:housenumber":"7",
    "addr:postcode":"8961",
    "addr:street":"Kirkestien",
    "iso:country":"DK",
    "sg:address":"Kirkestien 7, Vejlby",
    "sg:city":"Alling\u00e5bro",
    "sg:orig_category":"Faglige organisationer og foreninger",
    "sg:phone":"+45 86 48 18 66",
    "sg:postcode":"8961",
    "sg:province":"Danmark",
    "wof:name":"SID Rougs\u00f8-Afd.",
    "wof:placetype":"venue"
},
  "geometry": {"coordinates":[10.3230552673,56.4639511108],"type":"Point"}
}