{
  "type": "Feature",
  "properties": {
    "addr:full":"Aalborgvej 1, Hornum Aars Danmark 9600",
    "addr:housenumber":"1",
    "addr:postcode":"9600",
    "addr:street":"Aalborgvej",
    "iso:country":"DK",
    "sg:address":"Aalborgvej 1, Hornum",
    "sg:city":"Aars",
    "sg:orig_category":"Servicestationer",
    "sg:phone":"+45 98 66 10 92",
    "sg:postcode":"9600",
    "sg:province":"Danmark",
    "wof:name":"Nielsen, Hartvig",
    "wof:placetype":"venue"
},
  "geometry": {"coordinates":[9.5170412064,56.8031692505],"type":"Point"}
}