{
  "type": "Feature",
  "properties": {
    "addr:full":"Bredgade 6 Br\u00f8nderslev Danmark 9700",
    "addr:housenumber":"6",
    "addr:postcode":"9700",
    "addr:street":"Bredgade",
    "iso:country":"DK",
    "sg:address":"Bredgade 6",
    "sg:city":"Br\u00f8nderslev",
    "sg:orig_category":"Cafeterier",
    "sg:phone":"+45 98 82 41 22",
    "sg:postcode":"9700",
    "sg:province":"Danmark",
    "wof:name":"Vaffelhuset",
    "wof:placetype":"venue"
},
  "geometry": {"coordinates":[9.9460144043,57.2695503235],"type":"Point"}
}