{
  "type": "Feature",
  "properties": {
    "addr:full":"v/Jette Haugaard, Helsingevej 7 Helsinge Danmark 3200",
    "addr:housenumber":"7",
    "addr:postcode":"3200",
    "addr:street":"Helsingevej",
    "iso:country":"DK",
    "sg:address":"v/Jette Haugaard, Helsingevej 7",
    "sg:city":"Helsinge",
    "sg:orig_category":"Kulturelle foreninger",
    "sg:phone":"+45 48 28 50 12",
    "sg:postcode":"3200",
    "sg:province":"Danmark",
    "wof:name":"Foreningen for Bygnings- og Landskabskultur i Helsinge Kommune",
    "wof:placetype":"venue"
},
  "geometry": {"coordinates":[12.196846962,56.0224456787],"type":"Point"}
}