{
  "type": "Feature",
  "properties": {
    "addr:full":"Gasv\u00e6rksvej 1 A Haslev Danmark 4690",
    "addr:housenumber":"1 a",
    "addr:postcode":"4690",
    "addr:street":"Gasvaerksvej",
    "iso:country":"DK",
    "sg:address":"Gasv\u00e6rksvej 1 A",
    "sg:city":"Haslev",
    "sg:orig_category":"Hobbyartikler",
    "sg:phone":"+45 56 31 26 31",
    "sg:postcode":"4690",
    "sg:province":"Danmark",
    "sg:website":"www.betema.dk",
    "wof:name":"Betema",
    "wof:placetype":"venue"
},
  "geometry": {"coordinates":[11.9622097015,55.3304405212],"type":"Point"}
}