{
  "type": "Feature",
  "properties": {
    "addr:full":"Wibrandtsvej 83 K\u00f8benhavn S Danmark 2300",
    "addr:housenumber":"83",
    "addr:postcode":"2300",
    "addr:street":"Wibrandtsvej;Kobenhavn S Danmark",
    "iso:country":"DK",
    "sg:address":"Wibrandtsvej 83",
    "sg:city":"K\u00f8benhavn S",
    "sg:orig_category":"Campingvogne",
    "sg:phone":"+45 32 86 11 96",
    "sg:postcode":"2300",
    "sg:province":"Danmark",
    "wof:name":"IS INTERNATIONAL SERVICES",
    "wof:placetype":"venue"
},
  "geometry": {"coordinates":[-78.1299133301,36.7267417908],"type":"Point"}
}