{
  "type": "Feature",
  "properties": {
    "iso:country":"DK",
    "sg:address":"Torpvej 64, Hjallese",
    "sg:city":"Odense S",
    "sg:classifiers":[
        {
            "category":"Retail",
            "subcategory":"Storage",
            "type":"Services"
        }
    ],
    "sg:phone":"+45 65 92 03 88",
    "sg:postcode":"5260",
    "sg:province":"Danmark",
    "sg:tags":[
        "edb",
        "hardware",
        "-"
    ],
    "wof:name":"J.M. R\u00e5dgivning",
    "wof:placetype":"venue"
},
  "geometry": {"coordinates":[10.3157806396,55.3122825623],"type":"Point"}
}