{
  "type": "Feature",
  "properties": {
    "iso:country":"DK",
    "sg:address":"N\u00f8rregade 11",
    "sg:city":"Horsens",
    "sg:orig_category":"Glarmestre og glarmagere",
    "sg:phone":"+45 75 62 52 88",
    "sg:postcode":"8700",
    "sg:province":"Danmark",
    "wof:name":"H\u00f8y, Frantz",
    "wof:placetype":"venue"
},
  "geometry": {"coordinates":[9.8501596451,55.8629112244],"type":"Point"}
}