{
  "type": "Feature",
  "properties": {
    "addr:full":"Ingeborgvej 33 Frederikshavn Danmark 9900",
    "addr:housenumber":"33",
    "addr:postcode":"9900",
    "addr:street":"Ingeborgvej",
    "iso:country":"DK",
    "sg:address":"Ingeborgvej 33",
    "sg:city":"Frederikshavn",
    "sg:orig_category":"Murermestre",
    "sg:phone":"+45 98 42 16 13",
    "sg:postcode":"9900",
    "sg:province":"Danmark",
    "wof:name":"Frederikshavn Fugeservice",
    "wof:placetype":"venue"
},
  "geometry": {"coordinates":[10.5250921249,57.4357681274],"type":"Point"}
}