{
  "type": "Feature",
  "properties": {
    "addr:full":"Fmd.: Christian Pinderup, Vardevej 43 Tarm Danmark 6880",
    "addr:housenumber":"43",
    "addr:postcode":"6880",
    "addr:street":"Vardevej",
    "iso:country":"DK",
    "sg:address":"Fmd.: Christian Pinderup, Vardevej 43",
    "sg:city":"Tarm",
    "sg:orig_category":"Grundejerforeninger",
    "sg:phone":"+45 97 37 18 46",
    "sg:postcode":"6880",
    "sg:province":"Danmark",
    "wof:name":"Blomsterkvarterets Beboer- og Grundejerforening",
    "wof:placetype":"venue"
},
  "geometry": {"coordinates":[8.5200052261,55.9060554504],"type":"Point"}
}