{
  "type": "Feature",
  "properties": {
    "addr:full":"Acaciavej 5 Frederiksberg Danmark 1867",
    "addr:housenumber":"5",
    "addr:postcode":"1867",
    "addr:street":"Acaciavej",
    "iso:country":"DK",
    "sg:address":"Acaciavej 5",
    "sg:city":"Frederiksberg",
    "sg:orig_category":"Forlag",
    "sg:phone":"+45 33 25 99 00",
    "sg:postcode":"1867",
    "sg:province":"Danmark",
    "wof:name":"DSR Forlag",
    "wof:placetype":"venue"
},
  "geometry": {"coordinates":[12.5396909714,55.6785621643],"type":"Point"}
}