{
  "type": "Feature",
  "properties": {
    "addr:full":"Nauerbjergvej 1  Lille Skensved Danmark 4623",
    "addr:housenumber":"1",
    "addr:postcode":"4623",
    "addr:street":"Nauerbjergvej",
    "iso:country":"DK",
    "sg:address":"Nauerbjergvej 1 ",
    "sg:city":"Lille Skensved",
    "sg:classifiers":[
        {
            "category":"Wholesale",
            "subcategory":"Drugs",
            "type":"Manufacturing & Wholesale Goods"
        }
    ],
    "sg:phone":"+45 56 16 90 15",
    "sg:postcode":"4623",
    "sg:province":"Danmark",
    "sg:tags":[
        "chemical",
        "pharmaceutical"
    ],
    "wof:name":"FREDE ANDERSENS FABRIKER A/S",
    "wof:placetype":"venue"
},
  "geometry": {"coordinates":[12.1442775726,55.5142059326],"type":"Point"}
}