{
  "type": "Feature",
  "properties": {
    "addr:full":"Byagervej 5 Fuglebjerg Danmark 4250",
    "addr:housenumber":"5",
    "addr:postcode":"4250",
    "addr:street":"Byagervej",
    "iso:country":"DK",
    "sg:address":"Byagervej 5",
    "sg:city":"Fuglebjerg",
    "sg:classifiers":[
        {
            "category":"Banks & Credit Unions",
            "subcategory":"Bank",
            "type":"Services"
        }
    ],
    "sg:phone":"+45 55 46 04 00",
    "sg:postcode":"4250",
    "sg:province":"Danmark",
    "sg:tags":[
        "banker"
    ],
    "wof:name":"BG Bank A/S",
    "wof:placetype":"venue"
},
  "geometry": {"coordinates":[11.545645,55.302238],"type":"Point"}
}