{
  "type": "Feature",
  "properties": {
    "addr:full":"Storegade 86 Haderslev Danmark 6100",
    "addr:housenumber":"86",
    "addr:postcode":"6100",
    "addr:street":"Storegade",
    "iso:country":"DK",
    "sg:address":"Storegade 86",
    "sg:city":"Haderslev",
    "sg:orig_category":"Faglige organisationer og foreninger",
    "sg:phone":"+45 74 53 08 88",
    "sg:postcode":"6100",
    "sg:province":"Danmark",
    "wof:name":"Kristelige Fagbev\u00e6gelse, Den",
    "wof:placetype":"venue"
},
  "geometry": {"coordinates":[9.4770431519,55.2518234253],"type":"Point"}
}