{
  "type": "Feature",
  "properties": {
    "addr:full":"Fl\u00e6gk\u00e6r 7 Gislinge Danmark 4532",
    "addr:housenumber":"7",
    "addr:postcode":"4532",
    "addr:street":"Flaegkaer",
    "iso:country":"DK",
    "sg:address":"Fl\u00e6gk\u00e6r 7",
    "sg:city":"Gislinge",
    "sg:orig_category":"Autoreparation og -service",
    "sg:phone":"+45 59 46 30 90",
    "sg:postcode":"4532",
    "sg:province":"Danmark",
    "wof:name":"Gislinge Auto- og Pladev\u00e6rksted",
    "wof:placetype":"venue"
},
  "geometry": {"coordinates":[11.5516147614,55.7346343994],"type":"Point"}
}