{
  "type": "Feature",
  "properties": {
    "addr:full":"Vesterbrogade 2, 1. Fredericia Danmark 7000",
    "addr:housenumber":"2 1",
    "addr:postcode":"7000",
    "addr:street":"Vesterbrogade",
    "iso:country":"DK",
    "sg:address":"Vesterbrogade 2, 1.",
    "sg:city":"Fredericia",
    "sg:orig_category":"Forsikringer",
    "sg:phone":"+45 70 11 25 25",
    "sg:postcode":"7000",
    "sg:province":"Danmark",
    "wof:name":"Danica Pension",
    "wof:placetype":"venue"
},
  "geometry": {"coordinates":[9.7489490509,55.5691146851],"type":"Point"}
}