{
  "type": "Feature",
  "properties": {
    "addr:full":"Pr\u00e6stevejen 147 Gr\u00e6sted Danmark 3230",
    "addr:housenumber":"147",
    "addr:postcode":"3230",
    "addr:street":"Graested Danmark",
    "iso:country":"DK",
    "sg:address":"Pr\u00e6stevejen 147",
    "sg:city":"Gr\u00e6sted",
    "sg:orig_category":"Blomsterhandlere",
    "sg:phone":"+45 48 79 00 41",
    "sg:postcode":"3230",
    "sg:province":"Danmark",
    "wof:name":"Blomsterstalden",
    "wof:placetype":"venue"
},
  "geometry": {"coordinates":[-78.6975326538,35.0151481628],"type":"Point"}
}