{
  "type": "Feature",
  "properties": {
    "addr:full":"S\u00f8ndergade 12 A Skive Danmark 7800",
    "addr:housenumber":"12 a",
    "addr:postcode":"7800",
    "addr:street":"Sondergade",
    "iso:country":"DK",
    "sg:address":"S\u00f8ndergade 12 A",
    "sg:city":"Skive",
    "sg:orig_category":"Rutebiler",
    "sg:phone":"+45 97 52 43 00",
    "sg:postcode":"7800",
    "sg:province":"Danmark",
    "wof:name":"Skive Rutebilstation",
    "wof:placetype":"venue"
},
  "geometry": {"coordinates":[9.0258207321,56.5631866455],"type":"Point"}
}