{
  "type": "Feature",
  "properties": {
    "iso:country":"DK",
    "sg:address":"S\u00f8nderg\u00e5rds Alle 4",
    "sg:city":"Otterup",
    "sg:orig_category":"Blikkenslagere",
    "sg:phone":"+45 64 82 51 21",
    "sg:postcode":"5450",
    "sg:province":"Danmark",
    "wof:name":"Christensen Blikkenslager ApS, John",
    "wof:placetype":"venue"
},
  "geometry": {"coordinates":[10.454505,55.564175],"type":"Point"}
}