{
  "type": "Feature",
  "properties": {
    "addr:full":"Slettens Landevej 84, Klinte Holme Bogense Danmark 5400",
    "addr:housenumber":"84",
    "addr:postcode":"5400",
    "addr:street":"Slettens Landevej;Holme",
    "iso:country":"DK",
    "sg:address":"Slettens Landevej 84, Klinte Holme",
    "sg:city":"Bogense",
    "sg:orig_category":"Murermestre",
    "sg:phone":"+45 64 86 13 03",
    "sg:postcode":"5400",
    "sg:province":"Danmark",
    "wof:name":"Hansen, Geert",
    "wof:placetype":"venue"
},
  "geometry": {"coordinates":[10.0943098068,55.5637893677],"type":"Point"}
}