{
  "type": "Feature",
  "properties": {
    "addr:full":"Dybdalsvej 17 Sorring Danmark 8641",
    "addr:housenumber":"17",
    "addr:postcode":"8641",
    "addr:street":"Dybdalsvej",
    "iso:country":"DK",
    "sg:address":"Dybdalsvej 17",
    "sg:city":"Sorring",
    "sg:classifiers":[
        {
            "category":"Taxi",
            "type":"Transportation"
        }
    ],
    "sg:phone":"+45 86 95 74 06",
    "sg:postcode":"8641",
    "sg:province":"Danmark",
    "wof:name":"Heines Taxi og Miniturist",
    "wof:placetype":"venue"
},
  "geometry": {"coordinates":[9.7725429535,56.1754951477],"type":"Point"}
}