{
  "type": "Feature",
  "properties": {
    "iso:country":"DK",
    "sg:address":"\u00d8stermarksvej 17 ",
    "sg:city":"Terndrup",
    "sg:classifiers":[
        {
            "category":"Shopping",
            "subcategory":"Clothing, Apparel, & Fashions",
            "type":"Retail Goods"
        }
    ],
    "sg:phone":"+45 98 33 52 24",
    "sg:postcode":"9575",
    "sg:province":"Danmark",
    "sg:tags":[
        "clothes"
    ],
    "wof:name":"KINELL FASHION A/S",
    "wof:placetype":"venue"
},
  "geometry": {"coordinates":[10.0591917038,56.8121147156],"type":"Point"}
}