{
  "type": "Feature",
  "properties": {
    "iso:country":"DK",
    "sg:address":"Eghovedvej 1",
    "sg:city":"Malling",
    "sg:orig_category":"Integrerede institutioner",
    "sg:phone":"+45 86 93 20 33",
    "sg:postcode":"8340",
    "sg:province":"Danmark",
    "wof:name":"Malling, Integreret Inst.",
    "wof:placetype":"venue"
},
  "geometry": {"coordinates":[10.1968164444,56.0444793701],"type":"Point"}
}