{
  "type": "Feature",
  "properties": {
    "addr:full":"Fiskergade 1 Struer Danmark 7600",
    "addr:housenumber":"1",
    "addr:postcode":"7600",
    "addr:street":"Fiskergade",
    "iso:country":"DK",
    "sg:address":"Fiskergade 1",
    "sg:city":"Struer",
    "sg:orig_category":"Fisk og vildt",
    "sg:phone":"+45 97 85 00 77",
    "sg:postcode":"7600",
    "sg:province":"Danmark",
    "wof:name":"Fiskehallen",
    "wof:placetype":"venue"
},
  "geometry": {"coordinates":[8.595287323,56.4919967651],"type":"Point"}
}