{
  "type": "Feature",
  "properties": {
    "addr:full":"Jernbanegade 2, Sandvig Allinge Danmark 3770",
    "addr:housenumber":"2",
    "addr:postcode":"3770",
    "addr:street":"Jernbanegade;Sandvig",
    "iso:country":"DK",
    "sg:address":"Jernbanegade 2, Sandvig",
    "sg:city":"Allinge",
    "sg:orig_category":"HOTELS: OG MOTELLER",
    "sg:phone":"+45 56 48 05 14",
    "sg:postcode":"3770",
    "sg:province":"Danmark",
    "wof:name":"Turisthotellet",
    "wof:placetype":"venue"
},
  "geometry": {"coordinates":[14.7998552322,55.2743835449],"type":"Point"}
}