{
  "type": "Feature",
  "properties": {
    "addr:full":"Pedersholmparken 3 Frederikssund Danmark 3600",
    "addr:housenumber":"3",
    "addr:postcode":"3600",
    "addr:street":"Pedersholmparken",
    "iso:country":"DK",
    "sg:address":"Pedersholmparken 3",
    "sg:city":"Frederikssund",
    "sg:orig_category":"Autoforhandlere",
    "sg:phone":"+45 47 31 39 07",
    "sg:postcode":"3600",
    "sg:province":"Danmark",
    "wof:name":"Mazda Automobiler, Birthe & Mogens Kloe ApS",
    "wof:placetype":"venue"
},
  "geometry": {"coordinates":[12.0933361053,55.8246650696],"type":"Point"}
}