{
  "type": "Feature",
  "properties": {
    "addr:full":"Kronprinsesse Sofies Vej 12 Frederiksberg Danmark 2000",
    "addr:housenumber":"12",
    "addr:postcode":"2000",
    "addr:street":"Kronprinsesse Sofies Vej",
    "iso:country":"DK",
    "sg:address":"Kronprinsesse Sofies Vej 12",
    "sg:city":"Frederiksberg",
    "sg:orig_category":"Renserier",
    "sg:phone":"+45 38 86 65 65",
    "sg:postcode":"2000",
    "sg:province":"Danmark",
    "wof:name":"ABC Vask & Rens",
    "wof:placetype":"venue"
},
  "geometry": {"coordinates":[12.5331506729,55.6879577637],"type":"Point"}
}