{
  "type": "Feature",
  "properties": {
    "addr:full":"Hjadstrupvej 57, Bladstrup Otterup Danmark 5450",
    "addr:housenumber":"57",
    "addr:postcode":"5450",
    "addr:street":"Hjadstrupvej",
    "iso:country":"DK",
    "sg:address":"Hjadstrupvej 57, Bladstrup",
    "sg:city":"Otterup",
    "sg:orig_category":"Gasfyr og service",
    "sg:phone":"+45 65 95 55 36",
    "sg:postcode":"5450",
    "sg:province":"Danmark",
    "wof:name":"Bladstrupsmeden ApS",
    "wof:placetype":"venue"
},
  "geometry": {"coordinates":[10.4545049667,55.5641746521],"type":"Point"}
}