{
  "type": "Feature",
  "properties": {
    "addr:full":"Spedals\u00f8 Torv 2 Horsens Danmark 8700",
    "addr:housenumber":"2",
    "addr:postcode":"8700",
    "addr:street":"Spedalso Torv",
    "iso:country":"DK",
    "sg:address":"Spedals\u00f8 Torv 2",
    "sg:city":"Horsens",
    "sg:orig_category":"Reklametryk",
    "sg:phone":"+45 75 61 50 30",
    "sg:postcode":"8700",
    "sg:province":"Danmark",
    "wof:name":"Nykopi",
    "wof:placetype":"venue"
},
  "geometry": {"coordinates":[9.8380537033,55.8563041687],"type":"Point"}
}