{
  "type": "Feature",
  "properties": {
    "addr:full":"Borrisvej 16, Borris Skjern Danmark 6900",
    "addr:housenumber":"16",
    "addr:postcode":"6900",
    "addr:street":"Borrisvej;Borris",
    "iso:country":"DK",
    "sg:address":"Borrisvej 16, Borris",
    "sg:city":"Skjern",
    "sg:orig_category":"Autoophug",
    "sg:phone":"+45 97 36 61 79",
    "sg:postcode":"6900",
    "sg:province":"Danmark",
    "wof:name":"Dalager Autohandel og ophug",
    "wof:placetype":"venue"
},
  "geometry": {"coordinates":[8.492972374,55.9485740662],"type":"Point"}
}