{
  "type": "Feature",
  "properties": {
    "iso:country":"DK",
    "sg:address":"Jellingvej 165",
    "sg:city":"Vejle",
    "sg:orig_category":"Integrerede institutioner",
    "sg:phone":"+45 75 82 89 55",
    "sg:postcode":"7100",
    "sg:province":"Danmark",
    "wof:name":"B\u00f8rneg\u00e5rden Hover",
    "wof:placetype":"venue"
},
  "geometry": {"coordinates":[9.5168380737,55.7294540405],"type":"Point"}
}