{
  "type": "Feature",
  "properties": {
    "iso:country":"DK",
    "sg:address":"Stationsholmen 4 A",
    "sg:city":"Greve",
    "sg:orig_category":"Bagere",
    "sg:phone":"+45 43 60 06 42",
    "sg:postcode":"2670",
    "sg:province":"Danmark",
    "wof:name":"Centerbageriet",
    "wof:placetype":"venue"
},
  "geometry": {"coordinates":[12.295509,55.582096],"type":"Point"}
}