{
  "type": "Feature",
  "properties": {
    "iso:country":"DK",
    "sg:address":"Finlandsvej 8 ",
    "sg:city":"Haderslev",
    "sg:classifiers":[
        {
            "category":"Home & Garden",
            "subcategory":"Home Furnishings",
            "type":"Retail Goods"
        }
    ],
    "sg:phone":"+45 73 22 29 00",
    "sg:postcode":"6100",
    "sg:province":"Danmark",
    "sg:tags":[
        "household"
    ],
    "wof:name":"DANSANI A/S",
    "wof:placetype":"venue"
},
  "geometry": {"coordinates":[9.4751033783,55.2644729614],"type":"Point"}
}