{
  "type": "Feature",
  "properties": {
    "addr:full":"B\u00f8rge Jensens Plads 1 Nyborg Danmark 5800",
    "addr:housenumber":"1",
    "addr:postcode":"5800",
    "addr:street":"Borge Jensens Plads",
    "iso:country":"DK",
    "sg:address":"B\u00f8rge Jensens Plads 1",
    "sg:city":"Nyborg",
    "sg:orig_category":"Faglige organisationer og foreninger",
    "sg:phone":"+45 65 31 12 79",
    "sg:postcode":"5800",
    "sg:province":"Danmark",
    "wof:name":"Dansk Metal",
    "wof:placetype":"venue"
},
  "geometry": {"coordinates":[10.7957773209,55.3132133484],"type":"Point"}
}