{
  "type": "Feature",
  "properties": {
    "iso:country":"DK",
    "sg:address":"Stensbyvej 33",
    "sg:city":"Skamby",
    "sg:classifiers":[
        {
            "category":"Communications",
            "type":"Services"
        }
    ],
    "sg:phone":"+45 64 89 24 04",
    "sg:postcode":"5485",
    "sg:province":"Danmark",
    "sg:tags":[
        "og",
        "tv",
        "radio"
    ],
    "wof:name":"Stensby Radio & TV",
    "wof:placetype":"venue"
},
  "geometry": {"coordinates":[10.2746753693,55.5210037231],"type":"Point"}
}