{
  "type": "Feature",
  "properties": {
    "addr:full":"Torvet 3 Maribo Danmark 4930",
    "addr:housenumber":"3",
    "addr:postcode":"4930",
    "addr:street":"Torvet",
    "iso:country":"DK",
    "sg:address":"Torvet 3",
    "sg:city":"Maribo",
    "sg:orig_category":"Korn og foderstoffer",
    "sg:phone":"+45 54 78 11 11",
    "sg:postcode":"4930",
    "sg:province":"Danmark",
    "wof:name":"DLG/Qvade",
    "wof:placetype":"venue"
},
  "geometry": {"coordinates":[11.5014333725,54.7746925354],"type":"Point"}
}