{
  "type": "Feature",
  "properties": {
    "iso:country":"DK",
    "sg:address":"Hallas Alle 1 ",
    "sg:city":"Kalundborg",
    "sg:classifiers":[
        {
            "category":"Wholesale",
            "subcategory":"Drugs",
            "type":"Manufacturing & Wholesale Goods"
        }
    ],
    "sg:phone":"+45 59 51 30 11",
    "sg:postcode":"4400",
    "sg:province":"Danmark",
    "sg:tags":[
        "chemical",
        "pharmaceutical"
    ],
    "wof:name":"NOVO NORDISK A/S",
    "wof:placetype":"venue"
},
  "geometry": {"coordinates":[11.1211977005,55.6711616516],"type":"Point"}
}