{
  "type": "Feature",
  "properties": {
    "addr:full":"Stormgade 4 Hvide Sande Danmark 6960",
    "addr:housenumber":"4",
    "addr:postcode":"6960",
    "addr:street":"Stormgade",
    "iso:country":"DK",
    "sg:address":"Stormgade 4",
    "sg:city":"Hvide Sande",
    "sg:orig_category":"Iskiosker",
    "sg:phone":"+45 97 31 31 31",
    "sg:postcode":"6960",
    "sg:province":"Danmark",
    "wof:name":"Iscaf\u00e9en",
    "wof:placetype":"venue"
},
  "geometry": {"coordinates":[8.1263532639,55.9999198914],"type":"Point"}
}