{
  "type": "Feature",
  "properties": {
    "addr:full":"Stevnsvej 41, Str\u00f8by Egede K\u00f8ge Danmark 4600",
    "addr:housenumber":"41",
    "addr:postcode":"4600",
    "addr:street":"Stevnsvej;Koge",
    "iso:country":"DK",
    "sg:address":"Stevnsvej 41, Str\u00f8by Egede",
    "sg:city":"K\u00f8ge",
    "sg:orig_category":"Dyreklinikker og -hospitaler",
    "sg:phone":"+45 20 29 10 12",
    "sg:postcode":"4600",
    "sg:province":"Danmark",
    "sg:website":"haarlevdyreklinik.dk",
    "wof:name":"B.R. Dyreklinik",
    "wof:placetype":"venue"
},
  "geometry": {"coordinates":[6.4543700218,52.4404983521],"type":"Point"}
}