{
  "type": "Feature",
  "properties": {
    "addr:full":"R\u00f8nneb\u00e6rvej 7 B Vordingborg Danmark 4760",
    "addr:housenumber":"7 b",
    "addr:postcode":"4760",
    "addr:street":"Ronnebaervej",
    "iso:country":"DK",
    "sg:address":"R\u00f8nneb\u00e6rvej 7 B",
    "sg:city":"Vordingborg",
    "sg:orig_category":"Autotransport",
    "sg:phone":"+45 55 37 35 64",
    "sg:postcode":"4760",
    "sg:province":"Danmark",
    "wof:name":"TJ Autotransport ApS",
    "wof:placetype":"venue"
},
  "geometry": {"coordinates":[11.9124183655,55.0085449219],"type":"Point"}
}