{
  "type": "Feature",
  "properties": {
    "iso:country":"DK",
    "sg:address":"Fmd.: Anette V. S\u00f8rensen, Molsvej 97, Gr\u00f8nfeld",
    "sg:city":"Ebeltoft",
    "sg:orig_category":"Borger- og beboerforeninger",
    "sg:phone":"+45 86 36 54 20",
    "sg:postcode":"8400",
    "sg:province":"Danmark",
    "wof:name":"Gr\u00f8nfeld og Omegns Bylaug",
    "wof:placetype":"venue"
},
  "geometry": {"coordinates":[10.6778745651,56.199798584],"type":"Point"}
}