{
  "type": "Feature",
  "properties": {
    "addr:full":"Roskildevej 20 Frederikssund Danmark 3600",
    "addr:housenumber":"20",
    "addr:postcode":"3600",
    "addr:street":"Roskildevej",
    "iso:country":"DK",
    "sg:address":"Roskildevej 20",
    "sg:city":"Frederikssund",
    "sg:orig_category":"Maskinfabrikker",
    "sg:phone":"+45 47 31 03 67",
    "sg:postcode":"3600",
    "sg:province":"Danmark",
    "wof:name":"Str\u00fcwing Maskinfabrik ApS, R.",
    "wof:placetype":"venue"
},
  "geometry": {"coordinates":[12.0697813034,55.8335762024],"type":"Point"}
}