{
  "type": "Feature",
  "properties": {
    "addr:full":"Heimdalsgade 50 Aalborg Danmark 9000",
    "addr:housenumber":"50",
    "addr:postcode":"9000",
    "addr:street":"Heimdalsgade",
    "iso:country":"DK",
    "sg:address":"Heimdalsgade 50",
    "sg:city":"Aalborg",
    "sg:orig_category":"Autoreparation og -service",
    "sg:phone":"+45 98 11 45 11",
    "sg:postcode":"9000",
    "sg:province":"Danmark",
    "wof:name":"H.T. Auto",
    "wof:placetype":"venue"
},
  "geometry": {"coordinates":[9.9540624619,57.0372505188],"type":"Point"}
}