{
  "type": "Feature",
  "properties": {
    "addr:full":"Nordens Huse 2 Aalborg Danmark 9000",
    "addr:housenumber":"2",
    "addr:postcode":"9000",
    "addr:street":"Nordens Huse",
    "iso:country":"DK",
    "sg:address":"Nordens Huse 2",
    "sg:city":"Aalborg",
    "sg:classifiers":[
        {
            "category":"Personal",
            "subcategory":"Massage",
            "type":"Services"
        }
    ],
    "sg:phone":"+45 98 79 02 73",
    "sg:postcode":"9000",
    "sg:province":"Danmark",
    "wof:name":"Hansen, Kirsten",
    "wof:placetype":"venue"
},
  "geometry": {"coordinates":[9.8678283691,57.045375824],"type":"Point"}
}