{
  "type": "Feature",
  "properties": {
    "addr:full":"Grindsted Alle 13 Kastrup Danmark 2770",
    "addr:housenumber":"13",
    "addr:postcode":"2770",
    "addr:street":"Grindsted Alle",
    "iso:country":"DK",
    "sg:address":"Grindsted Alle 13",
    "sg:city":"Kastrup",
    "sg:orig_category":"Akupunktur",
    "sg:phone":"+45 32 51 78 78",
    "sg:postcode":"2770",
    "sg:province":"Danmark",
    "wof:name":"Ashi Akupunktur Klinik",
    "wof:placetype":"venue"
},
  "geometry": {"coordinates":[12.5989151001,55.6200752258],"type":"Point"}
}