{
  "type": "Feature",
  "properties": {
    "addr:full":"Hannerupg\u00e5rdsvej 57 Odense M Danmark 5230",
    "addr:housenumber":"57",
    "addr:postcode":"5230",
    "addr:street":"Hannerupgaardsvej",
    "iso:country":"DK",
    "sg:address":"Hannerupg\u00e5rdsvej 57",
    "sg:city":"Odense M",
    "sg:orig_category":"Tobak",
    "sg:phone":"+45 66 12 46 22",
    "sg:postcode":"5230",
    "sg:province":"Danmark",
    "wof:name":"Bolding Vine",
    "wof:placetype":"venue"
},
  "geometry": {"coordinates":[10.3787193298,55.3852119446],"type":"Point"}
}