{
  "type": "Feature",
  "properties": {
    "iso:country":"DK",
    "sg:address":"Hestehaven 1",
    "sg:city":"Ruds Vedby",
    "sg:orig_category":"Hestetransport",
    "sg:phone":"+45 58 26 18 73",
    "sg:postcode":"4291",
    "sg:province":"Danmark",
    "wof:name":"S\u00f8lvbjerg Stutteri ApS",
    "wof:placetype":"venue"
},
  "geometry": {"coordinates":[11.3982496262,55.5430793762],"type":"Point"}
}