{
  "type": "Feature",
  "properties": {
    "addr:full":"Rennebjergvej 110 Boeslunde Danmark 4242",
    "addr:housenumber":"110",
    "addr:postcode":"4242",
    "addr:street":"Rennebjergvej",
    "iso:country":"DK",
    "sg:address":"Rennebjergvej 110",
    "sg:city":"Boeslunde",
    "sg:orig_category":"Campingpladser",
    "sg:phone":"+45 58 14 02 08",
    "sg:postcode":"4242",
    "sg:province":"Danmark",
    "wof:name":"Campingg\u00e5rden",
    "wof:placetype":"venue"
},
  "geometry": {"coordinates":[11.2685556412,55.2847976685],"type":"Point"}
}