{
  "type": "Feature",
  "properties": {
    "iso:country":"DK",
    "sg:address":"S\u00f8ndermarken 1",
    "sg:city":"Give",
    "sg:orig_category":"Kommunale folkeskoler",
    "sg:phone":"+45 75 73 50 55",
    "sg:postcode":"7323",
    "sg:province":"Danmark",
    "sg:website":"www.soendermarkskolen.dk",
    "wof:name":"S\u00f8ndermarkskolen",
    "wof:placetype":"venue"
},
  "geometry": {"coordinates":[9.2349977493,55.83959198],"type":"Point"}
}