{
  "type": "Feature",
  "properties": {
    "iso:country":"DK",
    "sg:address":"Hvidovre Stationscenter 203, 2",
    "sg:city":"Hvidovre",
    "sg:orig_category":"Kiropraktorer",
    "sg:phone":"+45 36 47 04 47",
    "sg:postcode":"2650",
    "sg:province":"Danmark",
    "wof:name":"Kiropraktisk klinik",
    "wof:placetype":"venue"
},
  "geometry": {"coordinates":[12.4773397446,55.6630897522],"type":"Point"}
}