{
  "type": "Feature",
  "properties": {
    "iso:country":"DK",
    "sg:address":"Algade 34",
    "sg:city":"Roskilde",
    "sg:orig_category":"Brugskunst",
    "sg:phone":"+45 46 32 00 31",
    "sg:postcode":"4000",
    "sg:province":"Danmark",
    "wof:name":"Tiger",
    "wof:placetype":"venue"
},
  "geometry": {"coordinates":[12.0865163803,55.6408538818],"type":"Point"}
}