{
  "type": "Feature",
  "properties": {
    "iso:country":"DK",
    "sg:address":"Houmannsgade 47",
    "sg:city":"Horsens",
    "sg:orig_category":"Boligudlejning",
    "sg:phone":"+45 75 61 49 34",
    "sg:postcode":"8700",
    "sg:province":"Danmark",
    "wof:name":"Pen-Sam, Ejendomskontoret",
    "wof:placetype":"venue"
},
  "geometry": {"coordinates":[9.8428087234,55.8647041321],"type":"Point"}
}