{
  "type": "Feature",
  "properties": {
    "addr:full":"Ribe Landevej 421 Vejle Danmark 7100",
    "addr:housenumber":"421",
    "addr:postcode":"7100",
    "addr:street":"Ribe Landevej",
    "iso:country":"DK",
    "sg:address":"Ribe Landevej 421",
    "sg:city":"Vejle",
    "sg:orig_category":"Autoreparation og -service",
    "sg:phone":"+45 75 82 90 57",
    "sg:postcode":"7100",
    "sg:province":"Danmark",
    "wof:name":"Nr. Vilstrup Autov\u00e6rksted",
    "wof:placetype":"venue"
},
  "geometry": {"coordinates":[9.458483696,55.6870574951],"type":"Point"}
}