{
  "type": "Feature",
  "properties": {
    "addr:full":"Ho Bugt Vej 6 Billum Danmark 6852",
    "addr:housenumber":"6",
    "addr:postcode":"6852",
    "addr:street":"Ho Bugt Vej",
    "iso:country":"DK",
    "sg:address":"Ho Bugt Vej 6",
    "sg:city":"Billum",
    "sg:orig_category":"Pressebureauer",
    "sg:phone":"+45 75 25 89 00",
    "sg:postcode":"6852",
    "sg:province":"Danmark",
    "wof:name":"Askov Press",
    "wof:placetype":"venue"
},
  "geometry": {"coordinates":[8.3223686218,55.5957641602],"type":"Point"}
}