{
  "type": "Feature",
  "properties": {
    "addr:full":"Folehaven 131 Valby Danmark 2500",
    "addr:housenumber":"131",
    "addr:postcode":"2500",
    "addr:street":"Folehaven",
    "iso:country":"DK",
    "sg:address":"Folehaven 131",
    "sg:city":"Valby",
    "sg:classifiers":[
        {
            "category":"Restaurant",
            "type":"Food & Drink"
        }
    ],
    "sg:phone":"+45 36 30 40 70",
    "sg:postcode":"2500",
    "sg:province":"Danmark",
    "wof:name":"Ristorante Folehaven",
    "wof:placetype":"venue"
},
  "geometry": {"coordinates":[12.4918003082,55.6524124146],"type":"Point"}
}