{
  "type": "Feature",
  "properties": {
    "addr:full":"Klingebjergvej 26, Raml\u00f8se Helsinge Danmark 3200",
    "addr:housenumber":"26",
    "addr:postcode":"3200",
    "addr:street":"Klingebjergvej;Ramlose",
    "iso:country":"DK",
    "sg:address":"Klingebjergvej 26, Raml\u00f8se",
    "sg:city":"Helsinge",
    "sg:orig_category":"INGENI\u00c3\u02dcRER",
    "sg:phone":"+45 48 71 28 96",
    "sg:postcode":"3200",
    "sg:province":"Danmark",
    "wof:name":"Projekt Team",
    "wof:placetype":"venue"
},
  "geometry": {"coordinates":[12.196846962,56.0224456787],"type":"Point"}
}