{
  "type": "Feature",
  "properties": {
    "addr:full":"Dyrehavevej 184 Kolding Danmark 6000",
    "addr:housenumber":"184",
    "addr:postcode":"6000",
    "addr:street":"Dyrehavevej",
    "iso:country":"DK",
    "sg:address":"Dyrehavevej 184",
    "sg:city":"Kolding",
    "sg:orig_category":"Slankekonsulenter",
    "sg:phone":"+45 75 50 57 94",
    "sg:postcode":"6000",
    "sg:province":"Danmark",
    "wof:name":"Jensen's Slankekur",
    "wof:placetype":"venue"
},
  "geometry": {"coordinates":[9.4637861252,55.4997596741],"type":"Point"}
}