{
  "type": "Feature",
  "properties": {
    "iso:country":"DK",
    "sg:address":"Holme Ringvej 144",
    "sg:city":"Viby",
    "sg:orig_category":"Begravelsesforretninger",
    "sg:phone":"+45 86 14 50 62",
    "sg:postcode":"8260",
    "sg:province":"Danmark",
    "wof:name":"Viby Begravelsesforretning",
    "wof:placetype":"venue"
},
  "geometry": {"coordinates":[10.161905,56.127419],"type":"Point"}
}