{
  "type": "Feature",
  "properties": {
    "addr:full":"Hanstholmvej 179 Thisted Danmark 7700",
    "addr:housenumber":"179",
    "addr:postcode":"7700",
    "addr:street":"Hanstholmvej",
    "iso:country":"DK",
    "sg:address":"Hanstholmvej 179",
    "sg:city":"Thisted",
    "sg:orig_category":"Kirker",
    "sg:postcode":"7700",
    "sg:province":"Danmark",
    "wof:name":"Tved Kirke",
    "wof:placetype":"venue"
},
  "geometry": {"coordinates":[8.680762291,57.0185241699],"type":"Point"}
}