{
  "type": "Feature",
  "properties": {
    "addr:full":"S\u00f8g\u00e5rdvej 7, Stauning Skjern Danmark 6900",
    "addr:housenumber":"7",
    "addr:postcode":"6900",
    "addr:street":"Sogaardvej",
    "iso:country":"DK",
    "sg:address":"S\u00f8g\u00e5rdvej 7, Stauning",
    "sg:city":"Skjern",
    "sg:orig_category":"Maskinfabrikker",
    "sg:phone":"+45 97 36 92 96",
    "sg:postcode":"6900",
    "sg:province":"Danmark",
    "wof:name":"Knudsen, Evald",
    "wof:placetype":"venue"
},
  "geometry": {"coordinates":[8.492972374,55.9485740662],"type":"Point"}
}