{
  "type": "Feature",
  "properties": {
    "addr:full":"Fmd.: Kaj Munk, Hestehavevej 45 Ryslinge Danmark 5856",
    "addr:housenumber":"45",
    "addr:postcode":"5856",
    "addr:street":"Fmd.;Munk Hestehavevej",
    "iso:country":"DK",
    "sg:address":"Fmd.: Kaj Munk, Hestehavevej 45",
    "sg:city":"Ryslinge",
    "sg:orig_category":"Oplysningsforbund",
    "sg:phone":"+45 62 67 14 57",
    "sg:postcode":"5856",
    "sg:province":"Danmark",
    "wof:name":"L.O.F.",
    "wof:placetype":"venue"
},
  "geometry": {"coordinates":[10.5374507904,55.243019104],"type":"Point"}
}