{
  "type": "Feature",
  "properties": {
    "addr:full":"Jorcks Passage 1 A K\u00f8benhavn Danmark 1162",
    "addr:housenumber":"1 a;1162",
    "addr:street":"Passage",
    "iso:country":"DK",
    "sg:address":"Jorcks Passage 1 A",
    "sg:city":"K\u00f8benhavn",
    "sg:orig_category":"Arkitekter",
    "sg:phone":"+45 33 14 15 68",
    "sg:postcode":"1162",
    "sg:province":"Danmark",
    "wof:name":"Boldsen, J\u00f8rn",
    "wof:placetype":"venue"
},
  "geometry": {"coordinates":[12.5770998001,55.6783981323],"type":"Point"}
}