{
  "type": "Feature",
  "properties": {
    "addr:full":"Hedevej 21 Terndrup Danmark 9575",
    "addr:housenumber":"21",
    "addr:postcode":"9575",
    "addr:street":"Hedevej;Danmark",
    "iso:country":"DK",
    "sg:address":"Hedevej 21",
    "sg:city":"Terndrup",
    "sg:orig_category":"Hobbyartikler",
    "sg:phone":"+45 98 33 63 50",
    "sg:postcode":"9575",
    "sg:province":"Danmark",
    "wof:name":"Hobbyladen",
    "wof:placetype":"venue"
},
  "geometry": {"coordinates":[10.0616025925,56.8127861023],"type":"Point"}
}