{
  "type": "Feature",
  "properties": {
    "addr:full":"Fmd.: Martin Andersen, Havnen 4 Lemvig Danmark 7620",
    "addr:housenumber":"4",
    "addr:postcode":"7620",
    "addr:street":"Havnen",
    "iso:country":"DK",
    "sg:address":"Fmd.: Martin Andersen, Havnen 4",
    "sg:city":"Lemvig",
    "sg:orig_category":"Soldaterforeninger",
    "sg:phone":"+45 97 82 01 72",
    "sg:postcode":"7620",
    "sg:province":"Danmark",
    "wof:name":"Marineforening for Lemvig og Omegn",
    "wof:placetype":"venue"
},
  "geometry": {"coordinates":[8.3073654175,56.5505104065],"type":"Point"}
}