{
  "type": "Feature",
  "properties": {
    "addr:full":"Stenstuegade 12 Slagelse Danmark 4200",
    "addr:housenumber":"12",
    "addr:postcode":"4200",
    "addr:street":"Stenstuegade",
    "iso:country":"DK",
    "sg:address":"Stenstuegade 12",
    "sg:city":"Slagelse",
    "sg:orig_category":"Fagforbund og -foreninger",
    "sg:phone":"+45 58 53 08 63",
    "sg:postcode":"4200",
    "sg:province":"Danmark",
    "wof:name":"Kvindeligt Arbejderforbund",
    "wof:placetype":"venue"
},
  "geometry": {"coordinates":[11.3518705368,55.4032478333],"type":"Point"}
}