{
  "type": "Feature",
  "properties": {
    "addr:full":"Maglebjergvej 4 Kongens Lyngby Danmark 2800",
    "addr:housenumber":"4",
    "addr:postcode":"2800",
    "addr:street":"Maglebjergvej",
    "iso:country":"DK",
    "sg:address":"Maglebjergvej 4",
    "sg:city":"Kongens Lyngby",
    "sg:orig_category":"Firmagaver",
    "sg:phone":"+45 45 88 66 33",
    "sg:postcode":"2800",
    "sg:province":"Danmark",
    "sg:website":"www.rosendahl.dk",
    "wof:name":"Rosendahl A/S",
    "wof:placetype":"venue"
},
  "geometry": {"coordinates":[12.5181798935,55.8004074097],"type":"Point"}
}