{
  "type": "Feature",
  "properties": {
    "addr:full":"v/ J. Brask/Lisberg Management, Slotsmarken 11 H\u00f8rsholm Danmark 2970",
    "addr:housenumber":"11",
    "addr:postcode":"2970",
    "addr:street":"Slotsmarken",
    "iso:country":"DK",
    "sg:address":"v/ J. Brask/Lisberg Management, Slotsmarken 11",
    "sg:city":"H\u00f8rsholm",
    "sg:orig_category":"Grundejerforeninger",
    "sg:phone":"+45 45 86 88 11",
    "sg:postcode":"2970",
    "sg:province":"Danmark",
    "wof:name":"R\u00e5geleje Grundejerlav",
    "wof:placetype":"venue"
},
  "geometry": {"coordinates":[10.7290201187,49.8826408386],"type":"Point"}
}