{
  "type": "Feature",
  "properties": {
    "addr:full":"Lahnsgade 63 Odense C Danmark 5000",
    "addr:housenumber":"63",
    "addr:postcode":"5000",
    "addr:street":"Lahnsgade",
    "iso:country":"DK",
    "sg:address":"Lahnsgade 63",
    "sg:city":"Odense C",
    "sg:orig_category":"Arkitekter",
    "sg:phone":"+45 66 12 23 80",
    "sg:postcode":"5000",
    "sg:province":"Danmark",
    "wof:name":"Petersens Tegnestue, Lehn",
    "wof:placetype":"venue"
},
  "geometry": {"coordinates":[10.3857116699,55.3884925842],"type":"Point"}
}