{
  "type": "Feature",
  "properties": {
    "addr:full":"N\u00e6stvedvej 42 Vordingborg Danmark 4760",
    "addr:housenumber":"42",
    "addr:postcode":"4760",
    "addr:street":"Naestvedvej",
    "iso:country":"DK",
    "sg:address":"N\u00e6stvedvej 42",
    "sg:city":"Vordingborg",
    "sg:classifiers":[
        {
            "category":"Restaurant",
            "type":"Food & Drink"
        }
    ],
    "sg:phone":"+45 55 34 20 95",
    "sg:postcode":"4760",
    "sg:province":"Danmark",
    "wof:name":"VordingBowl's B\u00f8fhus",
    "wof:placetype":"venue"
},
  "geometry": {"coordinates":[11.8966426849,55.0163116455],"type":"Point"}
}