{
  "type": "Feature",
  "properties": {
    "iso:country":"DK",
    "sg:address":"Tonr\u00e5 18",
    "sg:city":"Gedved",
    "sg:orig_category":"Internettjenester",
    "sg:phone":"+45 75 66 40 60",
    "sg:postcode":"8751",
    "sg:province":"Danmark",
    "wof:name":"Pedersen/It",
    "wof:placetype":"venue"
},
  "geometry": {"coordinates":[9.8434400558,55.9268989563],"type":"Point"}
}