{
  "type": "Feature",
  "properties": {
    "addr:full":"v/ S\u00f8ndermarksskolen, Sofus Francks V\u00e6nge 34 Frederiksberg Danmark 2000",
    "addr:housenumber":"34",
    "addr:postcode":"2000",
    "addr:street":"Sofus;Vaenge",
    "iso:country":"DK",
    "sg:address":"v/ S\u00f8ndermarksskolen, Sofus Francks V\u00e6nge 34",
    "sg:city":"Frederiksberg",
    "sg:orig_category":"Skolefritidsordninger",
    "sg:phone":"+45 36 45 40 10",
    "sg:postcode":"2000",
    "sg:province":"Danmark",
    "wof:name":"Sofus Skolefritidsordning",
    "wof:placetype":"venue"
},
  "geometry": {"coordinates":[12.5299301147,55.6787872314],"type":"Point"}
}