{
  "type": "Feature",
  "properties": {
    "addr:full":"Fmd.: Sigrid Laugesen, Lergravvej 22 Aulum Danmark 7490",
    "addr:housenumber":"22",
    "addr:postcode":"7490",
    "addr:street":"Lergravvej",
    "iso:country":"DK",
    "sg:address":"Fmd.: Sigrid Laugesen, Lergravvej 22",
    "sg:city":"Aulum",
    "sg:orig_category":"Musik og sang",
    "sg:phone":"+45 97 47 21 60",
    "sg:postcode":"7490",
    "sg:province":"Danmark",
    "wof:name":"Aulum B\u00f8rne- og Juniorkor",
    "wof:placetype":"venue"
},
  "geometry": {"coordinates":[8.7971401215,56.2653999329],"type":"Point"}
}