{
  "type": "Feature",
  "properties": {
    "addr:full":"Valh\u00f8js Alle 39 R\u00f8dovre Danmark 2610",
    "addr:housenumber":"39",
    "addr:postcode":"2610",
    "addr:street":"Valhojs Alle",
    "iso:country":"DK",
    "sg:address":"Valh\u00f8js Alle 39",
    "sg:city":"R\u00f8dovre",
    "sg:classifiers":[
        {
            "category":"Communications",
            "type":"Services"
        }
    ],
    "sg:phone":"+45 36 41 21 31",
    "sg:postcode":"2610",
    "sg:province":"Danmark",
    "sg:tags":[
        "og",
        "tv",
        "radio"
    ],
    "wof:name":"Seidelin TV",
    "wof:placetype":"venue"
},
  "geometry": {"coordinates":[10.6992139816,61.1027755737],"type":"Point"}
}