{
  "type": "Feature",
  "properties": {
    "addr:full":"Klokkens Kvarter 205, Holluf Pile Odense S\u00d8 Danmark 5220",
    "addr:housenumber":"205",
    "addr:postcode":"5220",
    "addr:street":"Klokkens Kvarter;Pile",
    "iso:country":"DK",
    "sg:address":"Klokkens Kvarter 205, Holluf Pile",
    "sg:city":"Odense S\u00d8",
    "sg:orig_category":"Vinduespolering",
    "sg:phone":"+45 66 15 58 57",
    "sg:postcode":"5220",
    "sg:province":"Danmark",
    "wof:name":"Rasmussen, Torbj\u00f8rn",
    "wof:placetype":"venue"
},
  "geometry": {"coordinates":[10.4583454132,55.3316917419],"type":"Point"}
}