{
  "type": "Feature",
  "properties": {
    "addr:full":"R\u00f8gildvej 41, Arentsminde Brovst Danmark 9460",
    "addr:housenumber":"41",
    "addr:postcode":"9460",
    "addr:street":"Rogildvej",
    "iso:country":"DK",
    "sg:address":"R\u00f8gildvej 41, Arentsminde",
    "sg:city":"Brovst",
    "sg:orig_category":"Servicestationer",
    "sg:phone":"+45 98 23 83 85",
    "sg:postcode":"9460",
    "sg:province":"Danmark",
    "wof:name":"DK-Benzin og N\u00e6rbutik",
    "wof:placetype":"venue"
},
  "geometry": {"coordinates":[9.5220241547,57.097366333],"type":"Point"}
}