{
  "type": "Feature",
  "properties": {
    "addr:full":"Willemoesvej 7, Nordby Fan\u00f8 Danmark 6720",
    "addr:housenumber":"7",
    "addr:postcode":"6720",
    "addr:street":"Willemoesvej",
    "iso:country":"DK",
    "sg:address":"Willemoesvej 7, Nordby",
    "sg:city":"Fan\u00f8",
    "sg:orig_category":"Dag- og distriktsblade",
    "sg:phone":"+45 75 16 20 53",
    "sg:postcode":"6720",
    "sg:province":"Danmark",
    "wof:name":"Fan\u00f8 Ugeblad",
    "wof:placetype":"venue"
},
  "geometry": {"coordinates":[8.4069461823,55.4484786987],"type":"Point"}
}