{
  "type": "Feature",
  "properties": {
    "iso:country":"DK",
    "sg:address":"Hodsagervej 33 A, Simmelk\u00e6r",
    "sg:city":"Sunds",
    "sg:orig_category":"Integrerede institutioner",
    "sg:phone":"+45 97 14 32 83",
    "sg:postcode":"7451",
    "sg:province":"Danmark",
    "wof:name":"Troldhytten",
    "wof:placetype":"venue"
},
  "geometry": {"coordinates":[9.0151100159,56.2057800293],"type":"Point"}
}