{
  "type": "Feature",
  "properties": {
    "addr:full":"Fmd.: Anne-Marie W\u00fcrtz, Sl\u00e5envej 7 A Hornslet Danmark 8543",
    "addr:housenumber":"7 a",
    "addr:postcode":"8543",
    "addr:street":"Slaaenvej",
    "iso:country":"DK",
    "sg:address":"Fmd.: Anne-Marie W\u00fcrtz, Sl\u00e5envej 7 A",
    "sg:city":"Hornslet",
    "sg:orig_category":"\u00c3\u2020ldreorganisationer og klubber",
    "sg:phone":"+45 86 99 51 68",
    "sg:postcode":"8543",
    "sg:province":"Danmark",
    "wof:name":"\u00c6ldre Sagen Rosenholm",
    "wof:placetype":"venue"
},
  "geometry": {"coordinates":[10.3180999756,56.3159866333],"type":"Point"}
}