{
  "type": "Feature",
  "properties": {
    "addr:full":"Borgergade 10 Aalborg Danmark 9000",
    "addr:housenumber":"10",
    "addr:postcode":"9000",
    "addr:street":"Borgergade",
    "iso:country":"DK",
    "sg:address":"Borgergade 10",
    "sg:city":"Aalborg",
    "sg:classifiers":[
        {
            "category":"Restaurant",
            "type":"Food & Drink"
        }
    ],
    "sg:phone":"+45 98 13 74 80",
    "sg:postcode":"9000",
    "sg:province":"Danmark",
    "wof:name":"China Restaurant",
    "wof:placetype":"venue"
},
  "geometry": {"coordinates":[9.9170017242,57.0513153076],"type":"Point"}
}