{
  "type": "Feature",
  "properties": {
    "iso:country":"DK",
    "sg:address":"Hjulmagervej 1",
    "sg:city":"Hjallerup",
    "sg:orig_category":"Lakering",
    "sg:phone":"+45 98 28 13 81",
    "sg:postcode":"9320",
    "sg:province":"Danmark",
    "wof:name":"BT Nord",
    "wof:placetype":"venue"
},
  "geometry": {"coordinates":[10.1616477966,57.1755867004],"type":"Point"}
}