{
  "type": "Feature",
  "properties": {
    "addr:full":"Taastrupg\u00e5rdsvej 24 Taastrup Danmark 2630",
    "addr:housenumber":"24",
    "addr:postcode":"2630",
    "addr:street":"Taastrupgaardsvej",
    "iso:country":"DK",
    "sg:address":"Taastrupg\u00e5rdsvej 24",
    "sg:city":"Taastrup",
    "sg:orig_category":"Fabrikker",
    "sg:phone":"+45 43 55 33 55",
    "sg:postcode":"2630",
    "sg:province":"Danmark",
    "wof:name":"Kohberg Br\u00f8d A/S",
    "wof:placetype":"venue"
},
  "geometry": {"coordinates":[12.2914466858,55.6554298401],"type":"Point"}
}