{
  "type": "Feature",
  "properties": {
    "addr:full":"v/ Frede S. Andersen, Dalbynedervej 5, Udbyover Havndal Danmark 8970",
    "addr:housenumber":"5",
    "addr:postcode":"8970",
    "addr:street":"Dalbynedervej",
    "iso:country":"DK",
    "sg:address":"v/ Frede S. Andersen, Dalbynedervej 5, Udbyover",
    "sg:city":"Havndal",
    "sg:orig_category":"Forsamlingshuse",
    "sg:phone":"+45 86 47 00 68",
    "sg:postcode":"8970",
    "sg:province":"Danmark",
    "wof:name":"Udbyover Forsamlingshus",
    "wof:placetype":"venue"
},
  "geometry": {"coordinates":[10.1937646866,56.6534461975],"type":"Point"}
}