{
  "type": "Feature",
  "properties": {
    "iso:country":"DK",
    "sg:address":"Ellemosen 3 D",
    "sg:city":"Ry",
    "sg:orig_category":"Kopimaskiner",
    "sg:phone":"+45 86 25 23 88",
    "sg:postcode":"8680",
    "sg:province":"Danmark",
    "wof:name":"Lanier Danmark A/S",
    "wof:placetype":"venue"
},
  "geometry": {"coordinates":[9.7838754654,56.090423584],"type":"Point"}
}