{
  "type": "Feature",
  "properties": {
    "iso:country":"DK",
    "sg:address":"Fmd.: Birte Krag S\u00f8rensen, Englerupvej 84, Kr. Sonnerup",
    "sg:city":"Kirke S\u00e5by",
    "sg:orig_category":"\u00c3\u2020ldreorganisationer og klubber",
    "sg:phone":"+45 46 49 28 33",
    "sg:postcode":"4060",
    "sg:province":"Danmark",
    "wof:name":"Bramsn\u00e6s Kommunes \u00c6ldrer\u00e5d",
    "wof:placetype":"venue"
},
  "geometry": {"coordinates":[11.8739786148,55.6341285706],"type":"Point"}
}