{
  "type": "Feature",
  "properties": {
    "addr:full":"Stangk\u00e6r 1, Sm\u00f8rumnedre Sm\u00f8rum Danmark 2765",
    "addr:housenumber":"1",
    "addr:postcode":"2765",
    "addr:street":"Stangkaer",
    "iso:country":"DK",
    "sg:address":"Stangk\u00e6r 1, Sm\u00f8rumnedre",
    "sg:city":"Sm\u00f8rum",
    "sg:orig_category":"Murermestre",
    "sg:phone":"+45 40 68 26 31",
    "sg:postcode":"2765",
    "sg:province":"Danmark",
    "wof:name":"Theisen, E.",
    "wof:placetype":"venue"
},
  "geometry": {"coordinates":[-89.99755859379999,38.1331443787],"type":"Point"}
}