{
  "type": "Feature",
  "properties": {
    "addr:full":"Fmd.: Poul Gade Olesen, Nyg\u00e5rdsvej 100 Skanderborg Danmark 8660",
    "addr:housenumber":"100",
    "addr:postcode":"olesen;8660",
    "addr:street":"Poul Gade;Nygaardsvej",
    "iso:country":"DK",
    "sg:address":"Fmd.: Poul Gade Olesen, Nyg\u00e5rdsvej 100",
    "sg:city":"Skanderborg",
    "sg:orig_category":"Kulturelle foreninger",
    "sg:phone":"+45 86 53 10 37",
    "sg:postcode":"8660",
    "sg:province":"Danmark",
    "wof:name":"Fruering-Vitved Foredragsforening",
    "wof:placetype":"venue"
},
  "geometry": {"coordinates":[9.929974556,56.0380249023],"type":"Point"}
}