{
  "type": "Feature",
  "properties": {
    "addr:full":"Jernbanegade 34 C Fredensborg Danmark 3480",
    "addr:housenumber":"34 c",
    "addr:postcode":"3480",
    "addr:street":"Jernbanegade",
    "iso:country":"DK",
    "sg:address":"Jernbanegade 34 C",
    "sg:city":"Fredensborg",
    "sg:orig_category":"Statistik, bureau",
    "sg:phone":"+45 48 48 41 00",
    "sg:postcode":"3480",
    "sg:province":"Danmark",
    "sg:website":"www.spadille.com",
    "wof:name":"Spadille ApS,Konsulenter i Datamanagement, Statistik og EDB",
    "wof:placetype":"venue"
},
  "geometry": {"coordinates":[12.4031572342,55.9768714905],"type":"Point"}
}