{
  "type": "Feature",
  "properties": {
    "iso:country":"DK",
    "sg:address":"\u00d8stergade 1, 2.",
    "sg:city":"Skjern",
    "sg:orig_category":"Reklamebureauer",
    "sg:phone":"+45 97 35 26 00",
    "sg:postcode":"6900",
    "sg:province":"Danmark",
    "wof:name":"Kj\u00e6rgaard Marketing",
    "wof:placetype":"venue"
},
  "geometry": {"coordinates":[8.4923267365,55.948589325],"type":"Point"}
}