{
  "type": "Feature",
  "properties": {
    "addr:full":"Vesterbro 1 Aalborg Danmark 9000",
    "addr:housenumber":"1",
    "addr:postcode":"9000",
    "addr:street":"Vesterbro",
    "iso:country":"DK",
    "sg:address":"Vesterbro 1",
    "sg:city":"Aalborg",
    "sg:orig_category":"Legestuer",
    "sg:phone":"+45 98 31 52 90",
    "sg:postcode":"9000",
    "sg:province":"Danmark",
    "wof:name":"Legestuen Ansgar Kirken",
    "wof:placetype":"venue"
},
  "geometry": {"coordinates":[9.9108190536,57.0427894592],"type":"Point"}
}