{
  "type": "Feature",
  "properties": {
    "addr:full":"Bredgade 57 Aarup Danmark 5560",
    "addr:housenumber":"57",
    "addr:postcode":"5560",
    "addr:street":"Bredgade",
    "iso:country":"DK",
    "sg:address":"Bredgade 57",
    "sg:city":"Aarup",
    "sg:orig_category":"Slagter og viktualie",
    "sg:phone":"+45 64 43 14 92",
    "sg:postcode":"5560",
    "sg:province":"Danmark",
    "wof:name":"Aarup Slagterforretning",
    "wof:placetype":"venue"
},
  "geometry": {"coordinates":[10.0483503342,55.379573822],"type":"Point"}
}