{
  "type": "Feature",
  "properties": {
    "addr:full":"Enghavevej 17 Silkeborg Danmark 8600",
    "addr:housenumber":"17",
    "addr:postcode":"8600",
    "addr:street":"Enghavevej",
    "iso:country":"DK",
    "sg:address":"Enghavevej 17",
    "sg:city":"Silkeborg",
    "sg:orig_category":"Psykologer, praktiserende",
    "sg:phone":"+45 86 82 12 69",
    "sg:postcode":"8600",
    "sg:province":"Danmark",
    "wof:name":"Jensen, Birgitte Brauner",
    "wof:placetype":"venue"
},
  "geometry": {"coordinates":[9.5573987961,56.1791801453],"type":"Point"}
}