{
  "type": "Feature",
  "properties": {
    "addr:full":"F\u00e5borgvej 110 Vester Skerninge Danmark 5762",
    "addr:housenumber":"110",
    "addr:postcode":"5762",
    "addr:street":"Faaborgvej",
    "iso:country":"DK",
    "sg:address":"F\u00e5borgvej 110",
    "sg:city":"Vester Skerninge",
    "sg:orig_category":"Autoreparation og -service",
    "sg:phone":"+45 62 24 14 19",
    "sg:postcode":"5762",
    "sg:province":"Danmark",
    "wof:name":"Tommy's Auto",
    "wof:placetype":"venue"
},
  "geometry": {"coordinates":[10.4387350082,55.0746803284],"type":"Point"}
}