{
  "type": "Feature",
  "properties": {
    "addr:full":"Hjarn\u00f8vej 13 Fredericia Danmark 7000",
    "addr:housenumber":"13",
    "addr:postcode":"7000",
    "addr:street":"Hjarnovej",
    "iso:country":"DK",
    "sg:address":"Hjarn\u00f8vej 13",
    "sg:city":"Fredericia",
    "sg:orig_category":"Regnskabsassistance",
    "sg:phone":"+45 75 91 22 10",
    "sg:postcode":"7000",
    "sg:province":"Danmark",
    "wof:name":"BMA Bogf\u00f8rings- og Regnskabsservice",
    "wof:placetype":"venue"
},
  "geometry": {"coordinates":[9.7814292908,55.5826301575],"type":"Point"}
}