{
  "type": "Feature",
  "properties": {
    "addr:full":"Hold-An Vej 110 Ballerup Danmark 2750",
    "addr:housenumber":"110",
    "addr:postcode":"2750",
    "addr:street":"Hold-An Vej",
    "iso:country":"DK",
    "sg:address":"Hold-An Vej 110",
    "sg:city":"Ballerup",
    "sg:orig_category":"Telekommunikation",
    "sg:phone":"+45 40 21 99 99",
    "sg:postcode":"2750",
    "sg:province":"Danmark",
    "wof:name":"Linnemann Tele-Erhverv",
    "wof:placetype":"venue"
},
  "geometry": {"coordinates":[12.355670929,55.7239608765],"type":"Point"}
}