{
  "type": "Feature",
  "properties": {
    "iso:country":"DK",
    "sg:address":"Gaun\u00f8vej 11",
    "sg:city":"Br\u00f8nsh\u00f8j",
    "sg:orig_category":"Revisorer",
    "sg:phone":"+45 38 89 89 89",
    "sg:postcode":"2700",
    "sg:province":"Danmark",
    "wof:name":"Danbrit",
    "wof:placetype":"venue"
},
  "geometry": {"coordinates":[12.4721498489,55.7119636536],"type":"Point"}
}