{
  "type": "Feature",
  "properties": {
    "addr:full":"Hjallesevej 126 Odense M Danmark 5230",
    "addr:housenumber":"126",
    "addr:postcode":"5230",
    "addr:street":"Hjallesevej",
    "iso:country":"DK",
    "sg:address":"Hjallesevej 126",
    "sg:city":"Odense M",
    "sg:orig_category":"Posthuse",
    "sg:phone":"+45 66 14 14 08",
    "sg:postcode":"5230",
    "sg:province":"Danmark",
    "wof:name":"Post Danmark, Munkebjerg Posthus",
    "wof:placetype":"venue"
},
  "geometry": {"coordinates":[10.3957796097,55.3807487488],"type":"Point"}
}