{
  "type": "Feature",
  "properties": {
    "addr:full":"H. I. Biesgade 2 Hobro Danmark 9500",
    "addr:housenumber":"2",
    "addr:postcode":"9500",
    "addr:street":"H. I. Biesgade",
    "iso:country":"DK",
    "sg:address":"H. I. Biesgade 2",
    "sg:city":"Hobro",
    "sg:orig_category":"Rutebiler",
    "sg:phone":"+45 98 52 05 99",
    "sg:postcode":"9500",
    "sg:province":"Danmark",
    "wof:name":"Rutebilstationen",
    "wof:placetype":"venue"
},
  "geometry": {"coordinates":[9.7969417572,56.6381263733],"type":"Point"}
}