{
  "type": "Feature",
  "properties": {
    "iso:country":"DK",
    "sg:address":"Hjarupvej 17",
    "sg:city":"Aabenraa",
    "sg:orig_category":"Video- og TV-produktion",
    "sg:phone":"+45 74 62 53 91",
    "sg:postcode":"6200",
    "sg:province":"Danmark",
    "sg:website":"www.freelancefilm.dk",
    "wof:name":"Freelance Film",
    "wof:placetype":"venue"
},
  "geometry": {"coordinates":[9.409620285,55.0536499023],"type":"Point"}
}