{
  "type": "Feature",
  "properties": {
    "addr:full":"T\u00f8rrepladsen 8, Thorning Kjellerup Danmark 8620",
    "addr:housenumber":"8",
    "addr:postcode":"8620",
    "addr:street":"Torrepladsen",
    "iso:country":"DK",
    "sg:address":"T\u00f8rrepladsen 8, Thorning",
    "sg:city":"Kjellerup",
    "sg:orig_category":"Non-Classified Establishments",
    "sg:phone":"+45 86 88 09 09",
    "sg:postcode":"8620",
    "sg:province":"Danmark",
    "wof:name":"Gj\u00f8dvad, Bent",
    "wof:placetype":"venue"
},
  "geometry": {"coordinates":[9.430934906,56.2877655029],"type":"Point"}
}