{
  "type": "Feature",
  "properties": {
    "iso:country":"DK",
    "sg:address":"Bisg\u00e5rdmark 16",
    "sg:city":"Holstebro",
    "sg:orig_category":"\u00c3\u02dcvrig fritidsundervisning",
    "sg:phone":"+45 97 42 46 00",
    "sg:postcode":"7500",
    "sg:province":"Danmark",
    "sg:website":"www.homus.dk",
    "wof:name":"Holstebro Musikskole",
    "wof:placetype":"venue"
},
  "geometry": {"coordinates":[8.5981693268,56.3605957031],"type":"Point"}
}