{
  "type": "Feature",
  "properties": {
    "addr:full":"F\u00e6rchs Torv 1 Nibe Danmark 9240",
    "addr:housenumber":"1",
    "addr:postcode":"9240",
    "addr:street":"Faerchs Torv",
    "iso:country":"DK",
    "sg:address":"F\u00e6rchs Torv 1",
    "sg:city":"Nibe",
    "sg:orig_category":"Ejendomshandel",
    "sg:phone":"+45 98 35 02 66",
    "sg:postcode":"9240",
    "sg:province":"Danmark",
    "wof:name":"Advohus",
    "wof:placetype":"venue"
},
  "geometry": {"coordinates":[9.6393280029,56.982421875],"type":"Point"}
}