{
  "type": "Feature",
  "properties": {
    "addr:full":"Stationsvej 16 Dianalund Danmark 4293",
    "addr:housenumber":"16",
    "addr:postcode":"4293",
    "addr:street":"Stationsvej",
    "iso:country":"DK",
    "sg:address":"Stationsvej 16",
    "sg:city":"Dianalund",
    "sg:orig_category":"Akupunktur",
    "sg:phone":"+45 58 26 00 03",
    "sg:postcode":"4293",
    "sg:province":"Danmark",
    "wof:name":"Christensen, Inger",
    "wof:placetype":"venue"
},
  "geometry": {"coordinates":[11.4953727722,55.5333976746],"type":"Point"}
}