{
  "type": "Feature",
  "properties": {
    "iso:country":"DK",
    "sg:address":"Fmd.: Vagn Mark, \u00c5dalsvej 9",
    "sg:city":"Skals",
    "sg:orig_category":"Hobbybetonede foreninger",
    "sg:phone":"+45 86 69 41 82",
    "sg:postcode":"8832",
    "sg:province":"Danmark",
    "wof:name":"Midtjysk Walkie Union",
    "wof:placetype":"venue"
},
  "geometry": {"coordinates":[9.4030599594,56.5558166504],"type":"Point"}
}