{
  "type": "Feature",
  "properties": {
    "addr:full":"Fmd.: Hans Andresen, Kongevej 227, Tiset Gram Danmark 6510",
    "addr:housenumber":"227",
    "addr:postcode":"6510",
    "addr:street":"Kongevej;Tiset",
    "iso:country":"DK",
    "sg:address":"Fmd.: Hans Andresen, Kongevej 227, Tiset",
    "sg:city":"Gram",
    "sg:orig_category":"Borger- og beboerforeninger",
    "sg:phone":"+45 74 82 01 00",
    "sg:postcode":"6510",
    "sg:province":"Danmark",
    "wof:name":"Tiset Borgerforening",
    "wof:placetype":"venue"
},
  "geometry": {"coordinates":[9.0481977463,55.2877807617],"type":"Point"}
}