{
  "type": "Feature",
  "properties": {
    "iso:country":"DK",
    "sg:address":"Martin Hansens Vej 1 - 3",
    "sg:city":"Ebeltoft",
    "sg:orig_category":"Dyreklinikker og -hospitaler",
    "sg:phone":"+45 86 34 50 69",
    "sg:postcode":"8400",
    "sg:province":"Danmark",
    "wof:name":"Dyrl\u00e6gegruppen",
    "wof:placetype":"venue"
},
  "geometry": {"coordinates":[10.6841497421,56.1880493164],"type":"Point"}
}