{
  "type": "Feature",
  "properties": {
    "addr:full":"Fmd.: Ole Gregersen, Vollerupvej 66 Kalundborg Danmark 4400",
    "addr:housenumber":"66",
    "addr:postcode":"4400",
    "addr:street":"Vollerupvej",
    "iso:country":"DK",
    "sg:address":"Fmd.: Ole Gregersen, Vollerupvej 66",
    "sg:city":"Kalundborg",
    "sg:orig_category":"Loger",
    "sg:phone":"+45 59 50 22 47",
    "sg:postcode":"4400",
    "sg:province":"Danmark",
    "wof:name":"De Danske Forsvarsbr\u00f8dre for Kalundborg og Omegn",
    "wof:placetype":"venue"
},
  "geometry": {"coordinates":[11.0934085846,55.6797485352],"type":"Point"}
}