{
  "type": "Feature",
  "properties": {
    "addr:full":"Vesterlund 9 Vinderup Danmark 7830",
    "addr:housenumber":"9",
    "addr:postcode":"7830",
    "addr:street":"Vesterlund",
    "iso:country":"DK",
    "sg:address":"Vesterlund 9",
    "sg:city":"Vinderup",
    "sg:orig_category":"Glarmestre og glarmagere",
    "sg:phone":"+45 97 44 19 50",
    "sg:postcode":"7830",
    "sg:province":"Danmark",
    "wof:name":"Peters T\u00f8mrer- og Snedkerforretning ApS",
    "wof:placetype":"venue"
},
  "geometry": {"coordinates":[8.7720928192,56.4757614136],"type":"Point"}
}