{
  "type": "Feature",
  "properties": {
    "addr:full":"Sangildvej 10 Karup Danmark 7470",
    "addr:housenumber":"10",
    "addr:postcode":"7470",
    "addr:street":"Sangildvej",
    "iso:country":"DK",
    "sg:address":"Sangildvej 10",
    "sg:city":"Karup",
    "sg:classifiers":[
        {
            "category":"Personal",
            "subcategory":"Massage",
            "type":"Services"
        }
    ],
    "sg:phone":"+45 97 10 20 32",
    "sg:postcode":"7470",
    "sg:province":"Danmark",
    "wof:name":"E. M. Massage",
    "wof:placetype":"venue"
},
  "geometry": {"coordinates":[9.2396821976,56.276927948],"type":"Point"}
}