{
  "type": "Feature",
  "properties": {
    "addr:full":"Nygade 9 Nyk\u00f8bing Danmark 4800",
    "addr:housenumber":"9",
    "addr:postcode":"4800",
    "addr:street":"Nygade",
    "iso:country":"DK",
    "sg:address":"Nygade 9",
    "sg:city":"Nyk\u00f8bing",
    "sg:orig_category":"Cykler",
    "sg:phone":"+45 54 85 13 06",
    "sg:postcode":"4800",
    "sg:province":"Danmark",
    "sg:website":"www.vulkancykler.dk",
    "wof:name":"Vulkan",
    "wof:placetype":"venue"
},
  "geometry": {"coordinates":[11.8678541183,54.769241333],"type":"Point"}
}