{
  "type": "Feature",
  "properties": {
    "addr:full":"N\u00e6stved Landevej 94, Smidstrup Sk\u00e6lsk\u00f8r Danmark 4230",
    "addr:housenumber":"94",
    "addr:postcode":"4230",
    "addr:street":"Naestved Landevej",
    "iso:country":"DK",
    "sg:address":"N\u00e6stved Landevej 94, Smidstrup",
    "sg:city":"Sk\u00e6lsk\u00f8r",
    "sg:orig_category":"Redningsberedskab",
    "sg:phone":"+45 58 16 44 44",
    "sg:postcode":"4230",
    "sg:province":"Danmark",
    "wof:name":"Redningsberedskabet",
    "wof:placetype":"venue"
},
  "geometry": {"coordinates":[11.1915035248,55.2119750977],"type":"Point"}
}