{
  "type": "Feature",
  "properties": {
    "addr:full":"Vestervang 5 Dianalund Danmark 4293",
    "addr:housenumber":"5",
    "addr:postcode":"4293",
    "addr:street":"Vestervang",
    "iso:country":"DK",
    "sg:address":"Vestervang 5",
    "sg:city":"Dianalund",
    "sg:orig_category":"Hobbybetonede foreninger",
    "sg:phone":"+45 58 28 67 89",
    "sg:postcode":"4293",
    "sg:province":"Danmark",
    "wof:name":"Dansk Dahliaselskab",
    "wof:placetype":"venue"
},
  "geometry": {"coordinates":[11.4990968704,55.5282173157],"type":"Point"}
}