{
  "type": "Feature",
  "properties": {
    "addr:full":"Kl\u00f8vervej 24 Billund Danmark 7190",
    "addr:housenumber":"24",
    "addr:postcode":"7190",
    "addr:street":"Klovervej",
    "iso:country":"DK",
    "sg:address":"Kl\u00f8vervej 24",
    "sg:city":"Billund",
    "sg:orig_category":"Helsecentre og -institutter",
    "sg:phone":"+45 75 33 89 81",
    "sg:postcode":"7190",
    "sg:province":"Danmark",
    "wof:name":"Billund Motions- & Helsecenter",
    "wof:placetype":"venue"
},
  "geometry": {"coordinates":[9.1232728958,55.7210121155],"type":"Point"}
}