{
  "type": "Feature",
  "properties": {
    "iso:country":"DK",
    "sg:address":"Vandv\u00e6rksvej 3 D",
    "sg:city":"Hadsund",
    "sg:orig_category":"Revisorer",
    "sg:phone":"+45 98 57 18 14",
    "sg:postcode":"9560",
    "sg:province":"Danmark",
    "wof:name":"Erhvervenes Revisionsanstalt",
    "wof:placetype":"venue"
},
  "geometry": {"coordinates":[10.1131086349,56.7189483643],"type":"Point"}
}