{
  "type": "Feature",
  "properties": {
    "addr:full":"Vendersgade 50 Fredericia Danmark 7000",
    "addr:housenumber":"50",
    "addr:postcode":"7000",
    "addr:street":"Vendersgade",
    "iso:country":"DK",
    "sg:address":"Vendersgade 50",
    "sg:city":"Fredericia",
    "sg:orig_category":"Trossamfund uden for folkekirken",
    "sg:phone":"+45 75 91 17 11",
    "sg:postcode":"7000",
    "sg:province":"Danmark",
    "sg:website":"apokirke-fa.dk",
    "wof:name":"Apostolsk Kirke",
    "wof:placetype":"venue"
},
  "geometry": {"coordinates":[9.7542695999,55.5622901917],"type":"Point"}
}