{
  "type": "Feature",
  "properties": {
    "addr:full":"Skolegade 14 Fars\u00f8 Danmark 9640",
    "addr:housenumber":"14",
    "addr:postcode":"9640",
    "addr:street":"Skolegade",
    "iso:country":"DK",
    "sg:address":"Skolegade 14",
    "sg:city":"Fars\u00f8",
    "sg:orig_category":"Kommunale folkeskoler",
    "sg:phone":"+45 98 63 16 65",
    "sg:postcode":"9640",
    "sg:province":"Danmark",
    "wof:name":"Fars\u00f8 Skole",
    "wof:placetype":"venue"
},
  "geometry": {"coordinates":[-109.44831848139999,42.1062355042],"type":"Point"}
}