{
  "type": "Feature",
  "properties": {
    "iso:country":"DK",
    "sg:address":"Thorsvej 15",
    "sg:city":"Sindal",
    "sg:orig_category":"Arkitekter",
    "sg:phone":"+45 98 93 53 38",
    "sg:postcode":"9870",
    "sg:province":"Danmark",
    "wof:name":"Dan-Plan",
    "wof:placetype":"venue"
},
  "geometry": {"coordinates":[10.1919469833,57.4721031189],"type":"Point"}
}