{
  "type": "Feature",
  "properties": {
    "addr:full":"v/Berit M\u00f8ller Nielsen, B\u00f8dker Balles G\u00e5rd 5 \u00c5rhus C Danmark 8000",
    "addr:housenumber":"5",
    "addr:postcode":"8000",
    "addr:street":"Balles Gaard",
    "iso:country":"DK",
    "sg:address":"v/Berit M\u00f8ller Nielsen, B\u00f8dker Balles G\u00e5rd 5",
    "sg:city":"\u00c5rhus C",
    "sg:orig_category":"Oplysningsforbund",
    "sg:phone":"+45 86 76 09 81",
    "sg:postcode":"8000",
    "sg:province":"Danmark",
    "wof:name":"SFOF, Socialistisk Folkeoplysningsforbund",
    "wof:placetype":"venue"
},
  "geometry": {"coordinates":[-66.94068145750001,-27.6476192474],"type":"Point"}
}