{
  "type": "Feature",
  "properties": {
    "addr:full":"Horsbygvej 20, Rangstrup Agerskov Danmark 6534",
    "addr:housenumber":"20",
    "addr:postcode":"6534",
    "addr:street":"Horsbygvej",
    "iso:country":"DK",
    "sg:address":"Horsbygvej 20, Rangstrup",
    "sg:city":"Agerskov",
    "sg:orig_category":"Flytteforretninger",
    "sg:phone":"+45 26 74 00 81",
    "sg:postcode":"6534",
    "sg:province":"Danmark",
    "wof:name":"B.F. Byens Flytteforretning",
    "wof:placetype":"venue"
},
  "geometry": {"coordinates":[9.1290597916,55.1300849915],"type":"Point"}
}