{
  "type": "Feature",
  "properties": {
    "iso:country":"DK",
    "sg:address":"Godth\u00e5bsvej 5",
    "sg:city":"Svenstrup",
    "sg:orig_category":"Ejendomshandel",
    "sg:phone":"+45 98 38 21 20",
    "sg:postcode":"9230",
    "sg:province":"Danmark",
    "sg:website":"www.kk-bolig.dk",
    "wof:name":"Kold, Karsten v/Vagn \u00d8rtoft",
    "wof:placetype":"venue"
},
  "geometry": {"coordinates":[9.8535194397,56.9720077515],"type":"Point"}
}