{
  "type": "Feature",
  "properties": {
    "iso:country":"DK",
    "sg:address":"Sj\u00e6llandsvej 10",
    "sg:city":"Kolding",
    "sg:orig_category":"Arkitekter",
    "sg:phone":"+45 75 53 87 88",
    "sg:postcode":"6000",
    "sg:province":"Danmark",
    "sg:website":"www.maybom.dk",
    "wof:name":"Maybom, J\u00f8rgen",
    "wof:placetype":"venue"
},
  "geometry": {"coordinates":[9.5001411438,55.5014762878],"type":"Point"}
}