{
  "type": "Feature",
  "properties": {
    "addr:full":"Stokrosevej 8 Beder Danmark 8330",
    "addr:housenumber":"8",
    "addr:postcode":"8330",
    "addr:street":"Stokrosevej",
    "iso:country":"DK",
    "sg:address":"Stokrosevej 8",
    "sg:city":"Beder",
    "sg:classifiers":[
        {
            "category":"Banks & Credit Unions",
            "subcategory":"Investment Brokerage",
            "type":"Services"
        }
    ],
    "sg:phone":"+45 86 93 87 00",
    "sg:postcode":"8330",
    "sg:province":"Danmark",
    "sg:tags":[
        "healing"
    ],
    "wof:name":"Kristensen, Asha",
    "wof:placetype":"venue"
},
  "geometry": {"coordinates":[10.218957901,56.0636253357],"type":"Point"}
}