{
  "type": "Feature",
  "properties": {
    "addr:full":"Tigervej 11 K\u00f8ge Danmark 4600",
    "addr:housenumber":"11",
    "addr:postcode":"4600",
    "addr:street":"Tigervej",
    "iso:country":"DK",
    "sg:address":"Tigervej 11",
    "sg:city":"K\u00f8ge",
    "sg:orig_category":"Fabrikker",
    "sg:phone":"+45 56 65 31 00",
    "sg:postcode":"4600",
    "sg:province":"Danmark",
    "sg:website":"www.primo.dk",
    "wof:name":"Ureflex A/S",
    "wof:placetype":"venue"
},
  "geometry": {"coordinates":[12.1775064468,55.4739341736],"type":"Point"}
}