{
  "type": "Feature",
  "properties": {
    "iso:country":"DK",
    "sg:address":"Tornbyvej 0",
    "sg:city":"Hirtshals",
    "sg:orig_category":"Kirker",
    "sg:postcode":"9850",
    "sg:province":"Danmark",
    "wof:name":"Horne Kirke",
    "wof:placetype":"venue"
},
  "geometry": {"coordinates":[9.9856681824,57.5609436035],"type":"Point"}
}