{
  "type": "Feature",
  "properties": {
    "iso:country":"DK",
    "sg:address":"Strygejernet, Burmeistersgade 24, st.th.",
    "sg:city":"K\u00f8benhavn",
    "sg:orig_category":"Boligselskaber",
    "sg:phone":"+45 32 96 92 02",
    "sg:postcode":"1429",
    "sg:province":"Danmark",
    "wof:name":"Aab, afd. 68",
    "wof:placetype":"venue"
},
  "geometry": {"coordinates":[12.5987997055,55.6754112244],"type":"Point"}
}