{
  "type": "Feature",
  "properties": {
    "addr:full":"V. Marupvej 8, Dejbjerg Skjern Danmark 6900",
    "addr:housenumber":"8",
    "addr:postcode":"6900",
    "addr:street":"V. Marupvej",
    "iso:country":"DK",
    "sg:address":"V. Marupvej 8, Dejbjerg",
    "sg:city":"Skjern",
    "sg:orig_category":"Murermestre",
    "sg:phone":"+45 97 35 28 83",
    "sg:postcode":"6900",
    "sg:province":"Danmark",
    "wof:name":"Kongsholm Murer",
    "wof:placetype":"venue"
},
  "geometry": {"coordinates":[8.492972374,55.9485740662],"type":"Point"}
}