{
  "type": "Feature",
  "properties": {
    "addr:full":"Torvet 3 Blokhus Danmark 9492",
    "addr:housenumber":"3",
    "addr:postcode":"9492",
    "addr:street":"Torvet",
    "iso:country":"DK",
    "sg:address":"Torvet 3",
    "sg:city":"Blokhus",
    "sg:orig_category":"Bowlingcentre",
    "sg:phone":"+45 98 24 88 88",
    "sg:postcode":"9492",
    "sg:province":"Danmark",
    "wof:name":"Beach Bowl",
    "wof:placetype":"venue"
},
  "geometry": {"coordinates":[9.5845441818,57.2517929077],"type":"Point"}
}