{
  "type": "Feature",
  "properties": {
    "addr:full":"Paul Bergs\u00f8es Vej 6 Glostrup Danmark 2600",
    "addr:housenumber":"6",
    "addr:postcode":"2600",
    "addr:street":"Bergsoes Vej",
    "iso:country":"DK",
    "sg:address":"Paul Bergs\u00f8es Vej 6",
    "sg:city":"Glostrup",
    "sg:orig_category":"Faglige organisationer og -foreninger",
    "sg:phone":"+45 77 41 15 44",
    "sg:postcode":"2600",
    "sg:province":"Danmark",
    "wof:name":"Ventilationsfirmaer, Foreningen af",
    "wof:placetype":"venue"
},
  "geometry": {"coordinates":[12.4168787003,55.6684036255],"type":"Point"}
}