{
  "type": "Feature",
  "properties": {
    "addr:full":"Adelvej 23 Lem Danmark 6940",
    "addr:housenumber":"23",
    "addr:postcode":"6940",
    "addr:street":"Adelvej",
    "iso:country":"DK",
    "sg:address":"Adelvej 23",
    "sg:city":"Lem",
    "sg:orig_category":"Korn og foderstoffer",
    "sg:phone":"+45 97 34 33 33",
    "sg:postcode":"6940",
    "sg:province":"Danmark",
    "sg:website":"www.rag.dk",
    "wof:name":"R.A.G.",
    "wof:placetype":"venue"
},
  "geometry": {"coordinates":[8.4001293182,56.0534934998],"type":"Point"}
}