{
  "type": "Feature",
  "properties": {
    "addr:full":"Skovvejen 82 Kolding Danmark 6000",
    "addr:housenumber":"82",
    "addr:postcode":"6000",
    "addr:street":"Skovvejen",
    "iso:country":"DK",
    "sg:address":"Skovvejen 82",
    "sg:city":"Kolding",
    "sg:orig_category":"Integrerede institutioner",
    "sg:phone":"+45 75 50 44 14",
    "sg:postcode":"6000",
    "sg:province":"Danmark",
    "wof:name":"Globus",
    "wof:placetype":"venue"
},
  "geometry": {"coordinates":[9.4734678268,55.5047073364],"type":"Point"}
}