{
  "type": "Feature",
  "properties": {
    "addr:full":"Fmd.: Lars Nielsen, Korsvangen 15, Ugerl\u00f8se Kalundborg Danmark 4400",
    "addr:housenumber":"15",
    "addr:postcode":"4400",
    "addr:street":"Korsvangen;Ugerlose",
    "iso:country":"DK",
    "sg:address":"Fmd.: Lars Nielsen, Korsvangen 15, Ugerl\u00f8se",
    "sg:city":"Kalundborg",
    "sg:orig_category":"Hobbybetonede foreninger",
    "sg:phone":"+45 59 50 45 34",
    "sg:postcode":"4400",
    "sg:province":"Danmark",
    "wof:name":"Hvideb\u00e6k Hundeforening",
    "wof:placetype":"venue"
},
  "geometry": {"coordinates":[11.0934085846,55.6797485352],"type":"Point"}
}