{
  "type": "Feature",
  "properties": {
    "addr:full":"Strandgade 3 Frederiksv\u00e6rk Danmark 3300",
    "addr:housenumber":"3",
    "addr:postcode":"3300",
    "addr:street":"Strandgade",
    "iso:country":"DK",
    "sg:address":"Strandgade 3",
    "sg:city":"Frederiksv\u00e6rk",
    "sg:classifiers":[
        {
            "category":"Restaurant",
            "type":"Food & Drink"
        }
    ],
    "sg:phone":"+45 47 77 06 66",
    "sg:postcode":"3300",
    "sg:province":"Danmark",
    "wof:name":"Strandborg, Hotel",
    "wof:placetype":"venue"
},
  "geometry": {"coordinates":[12.0194816589,55.9724884033],"type":"Point"}
}