{
  "type": "Feature",
  "properties": {
    "addr:full":"v/ Peder Sk\u00e6rlund, Vorup\u00f8rvej 118 Thisted Danmark 7700",
    "addr:housenumber":"118",
    "addr:postcode":"7700",
    "addr:street":"Voruporvej",
    "iso:country":"DK",
    "sg:address":"v/ Peder Sk\u00e6rlund, Vorup\u00f8rvej 118",
    "sg:city":"Thisted",
    "sg:orig_category":"\u00c3\u2020ldreorganisationer og klubber",
    "sg:phone":"+45 97 93 71 08",
    "sg:postcode":"7700",
    "sg:province":"Danmark",
    "wof:name":"Hundborg og omegns pensionistforening",
    "wof:placetype":"venue"
},
  "geometry": {"coordinates":[8.6919784546,56.9556121826],"type":"Point"}
}