{
  "type": "Feature",
  "properties": {
    "addr:full":"Kanalvejen 5 Gilleleje Danmark 3250",
    "addr:housenumber":"5",
    "addr:postcode":"3250",
    "addr:street":"Kanalvejen",
    "iso:country":"DK",
    "sg:address":"Kanalvejen 5",
    "sg:city":"Gilleleje",
    "sg:classifiers":[
        {
            "category":"Restaurant",
            "type":"Food & Drink"
        }
    ],
    "sg:phone":"+45 48 30 16 11",
    "sg:postcode":"3250",
    "sg:province":"Danmark",
    "wof:name":"Chicago Caf\u00e9 og Pizzeria",
    "wof:placetype":"venue"
},
  "geometry": {"coordinates":[12.3059797287,56.1257591248],"type":"Point"}
}