{
  "type": "Feature",
  "properties": {
    "addr:full":"Sagavej 3 Slagelse Danmark 4200",
    "addr:housenumber":"3",
    "addr:postcode":"4200",
    "addr:street":"Sagavej",
    "iso:country":"DK",
    "sg:address":"Sagavej 3",
    "sg:city":"Slagelse",
    "sg:orig_category":"Murermestre",
    "sg:phone":"+45 58 52 72 10",
    "sg:postcode":"4200",
    "sg:province":"Danmark",
    "wof:name":"Hauritz, Robert",
    "wof:placetype":"venue"
},
  "geometry": {"coordinates":[11.3280391693,55.4031143188],"type":"Point"}
}