{
  "type": "Feature",
  "properties": {
    "addr:full":"Kirketorvet 19 Gentofte Danmark 2820",
    "addr:housenumber":"19",
    "addr:postcode":"2820",
    "addr:street":"Kirketorvet",
    "iso:country":"DK",
    "sg:address":"Kirketorvet 19",
    "sg:city":"Gentofte",
    "sg:orig_category":"Begravelsesforretninger",
    "sg:phone":"+45 39 65 75 40",
    "sg:postcode":"2820",
    "sg:province":"Danmark",
    "wof:name":"Dansk Ligbr\u00e6ndingsforening",
    "wof:placetype":"venue"
},
  "geometry": {"coordinates":[12.541085,55.75008],"type":"Point"}
}