{
  "type": "Feature",
  "properties": {
    "iso:country":"DK",
    "sg:address":"Fmd.: Jan Nielsen, Bilds\u00f8vej 74 A, Kr. Stillinge",
    "sg:city":"Slagelse",
    "sg:orig_category":"Hobbybetonede foreninger",
    "sg:phone":"+45 58 54 80 41",
    "sg:postcode":"4200",
    "sg:province":"Danmark",
    "wof:name":"Slagelse Civile Hundef\u00f8rer Forening",
    "wof:placetype":"venue"
},
  "geometry": {"coordinates":[11.3569850922,55.4050865173],"type":"Point"}
}