{
  "type": "Feature",
  "properties": {
    "iso:country":"DK",
    "sg:address":"Lystrupvej 4",
    "sg:city":"Risskov",
    "sg:orig_category":"Kiosker",
    "sg:phone":"+45 86 17 38 33",
    "sg:postcode":"8240",
    "sg:province":"Danmark",
    "wof:name":"Sekskanten, Kiosken",
    "wof:placetype":"venue"
},
  "geometry": {"coordinates":[10.2375431061,56.2005157471],"type":"Point"}
}