{
  "type": "Feature",
  "properties": {
    "iso:country":"DK",
    "sg:address":"Fmd.: Hakon Thomsen, Smedegade 33 st",
    "sg:city":"Horsens",
    "sg:orig_category":"\u00c3\u2020ldreorganisationer og klubber",
    "sg:phone":"+45 75 62 92 62",
    "sg:postcode":"8700",
    "sg:province":"Danmark",
    "wof:name":"Pensionistforeningen af 1948",
    "wof:placetype":"venue"
},
  "geometry": {"coordinates":[9.8432445526,55.8621063232],"type":"Point"}
}