{
  "type": "Feature",
  "properties": {
    "addr:full":"\u00d8ster\u00e5gade 25 Aalborg Danmark 9000",
    "addr:housenumber":"25",
    "addr:postcode":"9000",
    "addr:street":"Osteraagade",
    "iso:country":"DK",
    "sg:address":"\u00d8ster\u00e5gade 25",
    "sg:city":"Aalborg",
    "sg:classifiers":[
        {
            "category":"Restaurant",
            "type":"Food & Drink"
        }
    ],
    "sg:phone":"+45 98 12 06 58",
    "sg:postcode":"9000",
    "sg:province":"Danmark",
    "wof:name":"Marsvin's Vinhus, Ellen",
    "wof:placetype":"venue"
},
  "geometry": {"coordinates":[9.9221143723,57.0498085022],"type":"Point"}
}