{
  "type": "Feature",
  "properties": {
    "addr:full":"Njalsgade 92 K\u00f8benhavn S Danmark 2300",
    "addr:housenumber":"92",
    "addr:postcode":"2300",
    "addr:street":"Njalsgade;Kobenhavn S Danmark",
    "iso:country":"DK",
    "sg:address":"Njalsgade 92",
    "sg:city":"K\u00f8benhavn S",
    "sg:orig_category":"Forlag",
    "sg:phone":"+45 35 32 91 09",
    "sg:postcode":"2300",
    "sg:province":"Danmark",
    "wof:name":"Museum Tusculanums Forlag",
    "wof:placetype":"venue"
},
  "geometry": {"coordinates":[-98.63845825200001,48.075340271],"type":"Point"}
}