{
  "type": "Feature",
  "properties": {
    "addr:full":"Maarupvej 27 Kolind Danmark 8560",
    "addr:housenumber":"27",
    "addr:postcode":"8560",
    "addr:street":"Maarupvej",
    "iso:country":"DK",
    "sg:address":"Maarupvej 27",
    "sg:city":"Kolind",
    "sg:orig_category":"Autoreparation og -service",
    "sg:phone":"+45 86 39 12 11",
    "sg:postcode":"8560",
    "sg:province":"Danmark",
    "wof:name":"Kolind Autov\u00e6rksted",
    "wof:placetype":"venue"
},
  "geometry": {"coordinates":[10.5946264267,56.3560409546],"type":"Point"}
}