{
  "type": "Feature",
  "properties": {
    "addr:full":"Nordre Lyngvej 14 Klemensker Danmark 3782",
    "addr:housenumber":"14",
    "addr:postcode":"3782",
    "addr:street":"Nordre Lyngvej",
    "iso:country":"DK",
    "sg:address":"Nordre Lyngvej 14",
    "sg:city":"Klemensker",
    "sg:orig_category":"Folkedans",
    "sg:phone":"+45 56 96 63 16",
    "sg:postcode":"3782",
    "sg:province":"Danmark",
    "wof:name":"Bornholms Folkedansere",
    "wof:placetype":"venue"
},
  "geometry": {"coordinates":[14.8205862045,55.2106018066],"type":"Point"}
}