{
  "type": "Feature",
  "properties": {
    "addr:full":"Norgesvej 21 Middelfart Danmark 5500",
    "addr:housenumber":"21",
    "addr:postcode":"5500",
    "addr:street":"Norgesvej",
    "iso:country":"DK",
    "sg:address":"Norgesvej 21",
    "sg:city":"Middelfart",
    "sg:orig_category":"Fodplejere",
    "sg:phone":"+45 64 41 14 78",
    "sg:postcode":"5500",
    "sg:province":"Danmark",
    "wof:name":"Rasmussen, Solveig fodterapeut",
    "wof:placetype":"venue"
},
  "geometry": {"coordinates":[9.734295845,55.4988288879],"type":"Point"}
}