{
  "type": "Feature",
  "properties": {
    "addr:full":"Svinget 3 A, Kattinge Roskilde Danmark 4000",
    "addr:housenumber":"3 a",
    "addr:postcode":"4000",
    "addr:street":"Svinget;Kattinge",
    "iso:country":"DK",
    "sg:address":"Svinget 3 A, Kattinge",
    "sg:city":"Roskilde",
    "sg:classifiers":[
        {
            "category":"Personal",
            "subcategory":"Massage",
            "type":"Services"
        }
    ],
    "sg:phone":"+45 46 40 27 82",
    "sg:postcode":"4000",
    "sg:province":"Danmark",
    "sg:website":"www.helsekrogen.dk",
    "wof:name":"Helsekrogen i Kattinge",
    "wof:placetype":"venue"
},
  "geometry": {"coordinates":[12.0909376144,55.6404838562],"type":"Point"}
}