{
  "type": "Feature",
  "properties": {
    "iso:country":"DK",
    "sg:address":"Borgergade 110",
    "sg:city":"Glejbjerg",
    "sg:orig_category":"\u00c3\u2020ldrecentre",
    "sg:phone":"+45 75 19 85 00",
    "sg:postcode":"6752",
    "sg:province":"Danmark",
    "wof:name":"\u00c5struplund \u00c6ldrecenter",
    "wof:placetype":"venue"
},
  "geometry": {"coordinates":[8.8251867294,55.5642929077],"type":"Point"}
}