{
  "type": "Feature",
  "properties": {
    "addr:full":"Strandvejen 157 Hellerup Danmark 2900",
    "addr:housenumber":"157",
    "addr:postcode":"2900",
    "addr:street":"Strandvejen",
    "iso:country":"DK",
    "sg:address":"Strandvejen 157",
    "sg:city":"Hellerup",
    "sg:orig_category":"Investering",
    "sg:phone":"+45 39 61 15 66",
    "sg:postcode":"2900",
    "sg:province":"Danmark",
    "wof:name":"Parts-Invest A/S",
    "wof:placetype":"venue"
},
  "geometry": {"coordinates":[12.5757112503,55.7313423157],"type":"Point"}
}