{
  "type": "Feature",
  "properties": {
    "addr:full":"Oldermand: Mogens Refsgaard, V\u00e6nget 5, Kattinge Roskilde Danmark 4000",
    "addr:housenumber":"5",
    "addr:postcode":"4000",
    "addr:street":"Vaenget;Kattinge",
    "iso:country":"DK",
    "sg:address":"Oldermand: Mogens Refsgaard, V\u00e6nget 5, Kattinge",
    "sg:city":"Roskilde",
    "sg:orig_category":"Borger- og beboerforeninger",
    "sg:phone":"+45 46 40 22 54",
    "sg:postcode":"4000",
    "sg:province":"Danmark",
    "wof:name":"Kattinge Bylaug",
    "wof:placetype":"venue"
},
  "geometry": {"coordinates":[12.0909376144,55.6404838562],"type":"Point"}
}