{
  "type": "Feature",
  "properties": {
    "addr:full":"Kass.: Anders M\u00f8ller, Vorup\u00f8rvej 57 Thisted Danmark 7700",
    "addr:housenumber":"57",
    "addr:postcode":"7700",
    "addr:street":"Voruporvej",
    "iso:country":"DK",
    "sg:address":"Kass.: Anders M\u00f8ller, Vorup\u00f8rvej 57",
    "sg:city":"Thisted",
    "sg:orig_category":"Borger- og beboerforeninger",
    "sg:phone":"+45 97 97 10 51",
    "sg:postcode":"7700",
    "sg:province":"Danmark",
    "wof:name":"Sperring Beboerlaug",
    "wof:placetype":"venue"
},
  "geometry": {"coordinates":[8.6919784546,56.9556121826],"type":"Point"}
}