{
  "type": "Feature",
  "properties": {
    "addr:full":"Hovedgaden 55 Stenlille Danmark 4295",
    "addr:housenumber":"55",
    "addr:postcode":"4295",
    "addr:street":"Hovedgaden",
    "iso:country":"DK",
    "sg:address":"Hovedgaden 55",
    "sg:city":"Stenlille",
    "sg:orig_category":"Garn",
    "sg:phone":"+45 57 80 55 06",
    "sg:postcode":"4295",
    "sg:province":"Danmark",
    "wof:name":"Sabine's Strik - Mode - Garn",
    "wof:placetype":"venue"
},
  "geometry": {"coordinates":[11.5903453827,55.5400161743],"type":"Point"}
}