{
  "type": "Feature",
  "properties": {
    "iso:country":"DK",
    "sg:address":"Herlev Torv 1",
    "sg:city":"Herlev",
    "sg:orig_category":"Renserier",
    "sg:phone":"+45 44 94 04 60",
    "sg:postcode":"2730",
    "sg:province":"Danmark",
    "wof:name":"Herlev Rens",
    "wof:placetype":"venue"
},
  "geometry": {"coordinates":[12.4389677048,55.7234954834],"type":"Point"}
}