{
  "type": "Feature",
  "properties": {
    "iso:country":"DK",
    "sg:address":"Lundebjergg\u00e5rdsvej 16",
    "sg:city":"Skovlunde",
    "sg:orig_category":"Malermestre",
    "sg:phone":"+45 44 91 17 48",
    "sg:postcode":"2740",
    "sg:province":"Danmark",
    "wof:name":"Nielsen, Arne Steen",
    "wof:placetype":"venue"
},
  "geometry": {"coordinates":[12.4048786163,55.7211380005],"type":"Point"}
}