{
  "type": "Feature",
  "properties": {
    "addr:full":"Pillevej 10, Rom Lemvig Danmark 7620",
    "addr:housenumber":"10",
    "addr:postcode":"7620",
    "addr:street":"Pillevej",
    "iso:country":"DK",
    "sg:address":"Pillevej 10, Rom",
    "sg:city":"Lemvig",
    "sg:orig_category":"Genbrugscentre",
    "sg:phone":"+45 97 81 13 83",
    "sg:postcode":"7620",
    "sg:province":"Danmark",
    "wof:name":"Lemvig Kommunes Genbrugsplads for private",
    "wof:placetype":"venue"
},
  "geometry": {"coordinates":[8.3073654175,56.5505104065],"type":"Point"}
}