{
  "type": "Feature",
  "properties": {
    "addr:full":"Vestergade 30 Fjerritslev Danmark 9690",
    "addr:housenumber":"30",
    "addr:postcode":"9690",
    "addr:street":"Vestergade",
    "iso:country":"DK",
    "sg:address":"Vestergade 30",
    "sg:city":"Fjerritslev",
    "sg:orig_category":"Tandteknikere, Kliniske",
    "sg:phone":"+45 98 21 10 38",
    "sg:postcode":"9690",
    "sg:province":"Danmark",
    "wof:name":"Samuel, Karen",
    "wof:placetype":"venue"
},
  "geometry": {"coordinates":[9.25922966,57.0885658264],"type":"Point"}
}