{
  "type": "Feature",
  "properties": {
    "addr:full":"Rengegade 3 Store Heddinge Danmark 4660",
    "addr:housenumber":"3",
    "addr:postcode":"4660",
    "addr:street":"Rengegade",
    "iso:country":"DK",
    "sg:address":"Rengegade 3",
    "sg:city":"Store Heddinge",
    "sg:orig_category":"Begravelsesforretninger",
    "sg:phone":"+45 56 50 29 26",
    "sg:postcode":"4660",
    "sg:province":"Danmark",
    "wof:name":"Stevns Ligkistemagasin",
    "wof:placetype":"venue"
},
  "geometry": {"coordinates":[12.3890733719,55.3086051941],"type":"Point"}
}