{
  "type": "Feature",
  "properties": {
    "addr:full":"Vestergade 21 Aalestrup Danmark 9620",
    "addr:housenumber":"21",
    "addr:postcode":"9620",
    "addr:street":"Vestergade",
    "iso:country":"DK",
    "sg:address":"Vestergade 21",
    "sg:city":"Aalestrup",
    "sg:orig_category":"Ejendomshandel",
    "sg:phone":"+45 98 64 15 70",
    "sg:postcode":"9620",
    "sg:province":"Danmark",
    "sg:website":"www.ejendomsringen.dk",
    "wof:name":"Ejendomsringen Aalestrup",
    "wof:placetype":"venue"
},
  "geometry": {"coordinates":[9.4931221008,56.6938514709],"type":"Point"}
}