{
  "type": "Feature",
  "properties": {
    "addr:full":"Toftev\u00e6nget 16, Vonsild Kolding Danmark 6000",
    "addr:housenumber":"16",
    "addr:postcode":"6000",
    "addr:street":"Toftevaenget;Vonsild",
    "iso:country":"DK",
    "sg:address":"Toftev\u00e6nget 16, Vonsild",
    "sg:city":"Kolding",
    "sg:orig_category":"Autoreparation og -service",
    "sg:phone":"+45 40 14 45 00",
    "sg:postcode":"6000",
    "sg:province":"Danmark",
    "wof:name":"Bork, S\u00f8ren",
    "wof:placetype":"venue"
},
  "geometry": {"coordinates":[9.4733953476,55.4863586426],"type":"Point"}
}