{
  "type": "Feature",
  "properties": {
    "iso:country":"DK",
    "sg:address":"J\u00f8rgen Fibigersgade 10",
    "sg:city":"Hirtshals",
    "sg:orig_category":"Brugskunst",
    "sg:phone":"+45 98 94 36 66",
    "sg:postcode":"9850",
    "sg:province":"Danmark",
    "wof:name":"Alberte, Boutique",
    "wof:placetype":"venue"
},
  "geometry": {"coordinates":[9.9580078125,57.5906257629],"type":"Point"}
}