{
  "type": "Feature",
  "properties": {
    "addr:full":"Markedsgade 30 Randers Danmark 8900",
    "addr:housenumber":"30",
    "addr:postcode":"8900",
    "addr:street":"Markedsgade",
    "iso:country":"DK",
    "sg:address":"Markedsgade 30",
    "sg:city":"Randers",
    "sg:orig_category":"Dyreklinikker og -hospitaler",
    "sg:phone":"+45 86 42 00 07",
    "sg:postcode":"8900",
    "sg:province":"Danmark",
    "wof:name":"Randers Centerklinik",
    "wof:placetype":"venue"
},
  "geometry": {"coordinates":[10.0311727524,56.4639396667],"type":"Point"}
}