{
  "type": "Feature",
  "properties": {
    "addr:full":"Ulrik Birchs Vej 87 Vadum Danmark 9430",
    "addr:housenumber":"87",
    "addr:postcode":"9430",
    "addr:street":"Ulrik Birchs Vej",
    "iso:country":"DK",
    "sg:address":"Ulrik Birchs Vej 87",
    "sg:city":"Vadum",
    "sg:orig_category":"Regnskabsassistance",
    "sg:phone":"+45 98 27 17 07",
    "sg:postcode":"9430",
    "sg:province":"Danmark",
    "wof:name":"MDL Regnskabsservice",
    "wof:placetype":"venue"
},
  "geometry": {"coordinates":[9.8614864349,57.1242523193],"type":"Point"}
}