{
  "type": "Feature",
  "properties": {
    "iso:country":"DK",
    "sg:address":"Buen 11",
    "sg:city":"Kolding",
    "sg:orig_category":"Landbrugsmaskiner",
    "sg:phone":"+45 75 52 04 66",
    "sg:postcode":"6000",
    "sg:province":"Danmark",
    "wof:name":"Kolding/Gravens Maskinforretning A/S",
    "wof:placetype":"venue"
},
  "geometry": {"coordinates":[9.4805965424,55.4881706238],"type":"Point"}
}