{
  "type": "Feature",
  "properties": {
    "addr:full":"Europaplads 2 \u00c5rhus C Danmark 8000",
    "addr:housenumber":"2",
    "addr:postcode":"8000",
    "addr:street":"Europaplads",
    "iso:country":"DK",
    "sg:address":"Europaplads 2",
    "sg:city":"\u00c5rhus C",
    "sg:orig_category":"Rejsebureauer",
    "sg:phone":"+45 87 32 17 00",
    "sg:postcode":"8000",
    "sg:province":"Danmark",
    "sg:website":"www.bennettbti.com",
    "wof:name":"Bennett BTI",
    "wof:placetype":"venue"
},
  "geometry": {"coordinates":[4.717400074,49.7588005066],"type":"Point"}
}