{
  "type": "Feature",
  "properties": {
    "addr:full":"Ingemannsvej 18 Sor\u00f8 Danmark 4180",
    "addr:housenumber":"18",
    "addr:postcode":"4180",
    "addr:street":"Ingemannsvej",
    "iso:country":"DK",
    "sg:address":"Ingemannsvej 18",
    "sg:city":"Sor\u00f8",
    "sg:orig_category":"Momsservice",
    "sg:phone":"+45 57 82 04 48",
    "sg:postcode":"4180",
    "sg:province":"Danmark",
    "wof:name":"KTC",
    "wof:placetype":"venue"
},
  "geometry": {"coordinates":[11.561050415,55.431438446],"type":"Point"}
}