{
  "type": "Feature",
  "properties": {
    "addr:full":"Langebrogade 4 K\u00f8benhavn Danmark 1411",
    "addr:housenumber":"4;1411",
    "addr:street":"Langebrogade",
    "iso:country":"DK",
    "sg:address":"Langebrogade 4",
    "sg:city":"K\u00f8benhavn",
    "sg:orig_category":"Levnedsmidler",
    "sg:phone":"+45 32 66 24 00",
    "sg:postcode":"1411",
    "sg:province":"Danmark",
    "sg:website":"www.distillers.dk",
    "wof:name":"Danske Spritfabrikker, De",
    "wof:placetype":"venue"
},
  "geometry": {"coordinates":[12.5832595825,55.6710395813],"type":"Point"}
}