{
  "type": "Feature",
  "properties": {
    "iso:country":"DK",
    "sg:address":"Vedelsgade 105",
    "sg:city":"Vejle",
    "sg:orig_category":"Revisorer",
    "sg:phone":"+45 75 72 49 50",
    "sg:postcode":"7100",
    "sg:province":"Danmark",
    "wof:name":"Revision 80",
    "wof:placetype":"venue"
},
  "geometry": {"coordinates":[9.5333881378,55.7134895325],"type":"Point"}
}