{
  "type": "Feature",
  "properties": {
    "addr:full":"Korinthvej 25 Aalborg \u00d8 Danmark 9220",
    "addr:housenumber":"25",
    "addr:postcode":"9220",
    "addr:street":"Korinthvej;Danmark",
    "iso:country":"DK",
    "sg:address":"Korinthvej 25",
    "sg:city":"Aalborg \u00d8",
    "sg:orig_category":"Galvanisering",
    "sg:phone":"+45 98 15 12 22",
    "sg:postcode":"9220",
    "sg:province":"Danmark",
    "wof:name":"H.H. El-Galvanisering ApS",
    "wof:placetype":"venue"
},
  "geometry": {"coordinates":[10.0243768692,57.0382728577],"type":"Point"}
}