{
  "type": "Feature",
  "properties": {
    "iso:country":"DK",
    "sg:address":"Lyngby Hovedgade 27 - 29",
    "sg:city":"Kongens Lyngby",
    "sg:orig_category":"Revisorer",
    "sg:phone":"+45 45 88 30 60",
    "sg:postcode":"2800",
    "sg:province":"Danmark",
    "wof:name":"Lyngby Revisionskontor",
    "wof:placetype":"venue"
},
  "geometry": {"coordinates":[12.5024223328,55.7715568542],"type":"Point"}
}