{
  "type": "Feature",
  "properties": {
    "addr:full":"Suensonsvej 7 Silkeborg Danmark 8600",
    "addr:housenumber":"7",
    "addr:postcode":"8600",
    "addr:street":"Suensonsvej",
    "iso:country":"DK",
    "sg:address":"Suensonsvej 7",
    "sg:city":"Silkeborg",
    "sg:classifiers":[
        {
            "category":"Utilities",
            "subcategory":"Refuse",
            "type":"Services"
        }
    ],
    "sg:phone":"+45 86 81 44 86",
    "sg:postcode":"8600",
    "sg:province":"Danmark",
    "sg:tags":[
        "catering"
    ],
    "wof:name":"Risbjerg Catering Toastmaster",
    "wof:placetype":"venue"
},
  "geometry": {"coordinates":[9.575884819,56.2035827637],"type":"Point"}
}