{
  "type": "Feature",
  "properties": {
    "addr:full":"Nyvej 60, Ulb\u00f8lle Vester Skerninge Danmark 5762",
    "addr:housenumber":"60",
    "addr:postcode":"5762",
    "addr:street":"Nyvej",
    "iso:country":"DK",
    "sg:address":"Nyvej 60, Ulb\u00f8lle",
    "sg:city":"Vester Skerninge",
    "sg:orig_category":"Autoreparation og -service",
    "sg:phone":"+45 62 24 19 70",
    "sg:postcode":"5762",
    "sg:province":"Danmark",
    "wof:name":"Ulb\u00f8lle Autov\u00e6rksted",
    "wof:placetype":"venue"
},
  "geometry": {"coordinates":[10.5008449554,55.070400238],"type":"Point"}
}