{
  "type": "Feature",
  "properties": {
    "iso:country":"DK",
    "sg:address":"Agedrupvej 0",
    "sg:city":"Agedrup",
    "sg:orig_category":"Kirker",
    "sg:postcode":"5320",
    "sg:province":"Danmark",
    "wof:name":"Agedrup Kirke",
    "wof:placetype":"venue"
},
  "geometry": {"coordinates":[10.4980964661,55.4251022339],"type":"Point"}
}