{
  "type": "Feature",
  "properties": {
    "addr:full":"Bernstorffsgade 7 K\u00f8benhavn Danmark 1577",
    "addr:housenumber":"7;1577",
    "addr:street":"Bernstorffsgade",
    "iso:country":"DK",
    "sg:address":"Bernstorffsgade 7",
    "sg:city":"K\u00f8benhavn",
    "sg:classifiers":[
        {
            "category":"Restaurant",
            "type":"Food & Drink"
        }
    ],
    "sg:phone":"+45 33 11 06 68",
    "sg:postcode":"1577",
    "sg:province":"Danmark",
    "wof:name":"Bernstorff, Restaurant",
    "wof:placetype":"venue"
},
  "geometry": {"coordinates":[12.5688199997,55.6709785461],"type":"Point"}
}