{
  "type": "Feature",
  "properties": {
    "addr:full":"S\u00f8ndre Boulevard 80B, st. Maribo Danmark 4930",
    "addr:housenumber":"80b",
    "addr:postcode":"4930",
    "addr:street":"Sondre Boulevard;St.",
    "iso:country":"DK",
    "sg:address":"S\u00f8ndre Boulevard 80B, st.",
    "sg:city":"Maribo",
    "sg:orig_category":"Handicapboliger",
    "sg:phone":"+45 54 78 47 82",
    "sg:postcode":"4930",
    "sg:province":"Danmark",
    "sg:website":"www.bnvibo.stam.dk",
    "wof:name":"Bo og Naboskab Vibo",
    "wof:placetype":"venue"
},
  "geometry": {"coordinates":[11.502035141,54.7743835449],"type":"Point"}
}