{
  "type": "Feature",
  "properties": {
    "iso:country":"DK",
    "sg:address":"Revelh\u00f8jvej 29 A, Brendstrup",
    "sg:city":"\u00c5rhus N",
    "sg:orig_category":"Gartnerier",
    "sg:phone":"+45 86 78 65 44",
    "sg:postcode":"8200",
    "sg:province":"Danmark",
    "wof:name":"Ren\u00e9, Gartneriet",
    "wof:placetype":"venue"
},
  "geometry": {"coordinates":[10.1573495865,56.1893997192],"type":"Point"}
}