{
  "type": "Feature",
  "properties": {
    "iso:country":"DK",
    "sg:address":"Silovej 34, Karlstrup",
    "sg:city":"Karlslunde",
    "sg:classifiers":[
        {
            "category":"Taxi",
            "type":"Transportation"
        }
    ],
    "sg:phone":"+45 70 10 66 66",
    "sg:postcode":"2690",
    "sg:province":"Danmark",
    "sg:website":"www.greve-solrodtaxi.dk",
    "wof:name":"Greve-Solr\u00f8d Taxi",
    "wof:placetype":"venue"
},
  "geometry": {"coordinates":[12.2294149399,55.5701599121],"type":"Point"}
}