{
  "type": "Feature",
  "properties": {
    "addr:full":"Jegind\u00f8vej 21 Viborg Danmark 8800",
    "addr:housenumber":"21",
    "addr:postcode":"8800",
    "addr:street":"Jegindovej",
    "iso:country":"DK",
    "sg:address":"Jegind\u00f8vej 21",
    "sg:city":"Viborg",
    "sg:orig_category":"Forlag",
    "sg:phone":"+45 86 60 24 22",
    "sg:postcode":"8800",
    "sg:province":"Danmark",
    "wof:name":"Anna, Forlaget",
    "wof:placetype":"venue"
},
  "geometry": {"coordinates":[9.358001709,56.4513282776],"type":"Point"}
}