{
  "type": "Feature",
  "properties": {
    "addr:full":"Sildevej 8 Skagen Danmark 9990",
    "addr:housenumber":"8",
    "addr:postcode":"9990",
    "addr:street":"Sildevej",
    "iso:country":"DK",
    "sg:address":"Sildevej 8",
    "sg:city":"Skagen",
    "sg:orig_category":"Erhvervs- og brancheforeninger",
    "sg:phone":"+45 98 44 62 11",
    "sg:postcode":"9990",
    "sg:province":"Danmark",
    "wof:name":"Skagen Fiskeriforening",
    "wof:placetype":"venue"
},
  "geometry": {"coordinates":[10.594704628,57.7196884155],"type":"Point"}
}