{
  "type": "Feature",
  "properties": {
    "addr:full":"Havnealle 55 Horsens Danmark 8700",
    "addr:housenumber":"55",
    "addr:postcode":"8700",
    "addr:street":"Havnealle",
    "iso:country":"DK",
    "sg:address":"Havnealle 55",
    "sg:city":"Horsens",
    "sg:classifiers":[
        {
            "category":"Restaurant",
            "type":"Food & Drink"
        }
    ],
    "sg:phone":"+45 75 62 34 81",
    "sg:postcode":"8700",
    "sg:province":"Danmark",
    "wof:name":"Dolly's, Cafe",
    "wof:placetype":"venue"
},
  "geometry": {"coordinates":[9.8577404022,55.8595199585],"type":"Point"}
}