{
  "type": "Feature",
  "properties": {
    "addr:full":"Gammel K\u00f8ge Landevej 501 Hvidovre Danmark 2650",
    "addr:housenumber":"501",
    "addr:postcode":"2650",
    "addr:street":"Gammel Koge Landevej",
    "iso:country":"DK",
    "sg:address":"Gammel K\u00f8ge Landevej 501",
    "sg:city":"Hvidovre",
    "sg:orig_category":"Planteskoler",
    "sg:phone":"+45 36 78 41 97",
    "sg:postcode":"2650",
    "sg:province":"Danmark",
    "wof:name":"K\u00f8gevejens Planteskole I/S",
    "wof:placetype":"venue"
},
  "geometry": {"coordinates":[12.466591835,55.6228599548],"type":"Point"}
}