{
  "type": "Feature",
  "properties": {
    "addr:full":"R\u00e6kke M\u00f8llevej 5, Hanning Skjern Danmark 6900",
    "addr:housenumber":"5",
    "addr:postcode":"6900",
    "addr:street":"Mollevej;Hanning",
    "iso:country":"DK",
    "sg:address":"R\u00e6kke M\u00f8llevej 5, Hanning",
    "sg:city":"Skjern",
    "sg:orig_category":"Forsamlingshuse",
    "sg:phone":"+45 97 36 21 52",
    "sg:postcode":"6900",
    "sg:province":"Danmark",
    "wof:name":"Hanning Forsamlingshus",
    "wof:placetype":"venue"
},
  "geometry": {"coordinates":[8.492972374,55.9485740662],"type":"Point"}
}