{
  "type": "Feature",
  "properties": {
    "addr:full":"Fmd.: J\u00f8rgen Larholm, Kl\u00f8vervej 3 Kirke Hyllinge Danmark 4070",
    "addr:housenumber":"3",
    "addr:postcode":"4070",
    "addr:street":"Klovervej",
    "iso:country":"DK",
    "sg:address":"Fmd.: J\u00f8rgen Larholm, Kl\u00f8vervej 3",
    "sg:city":"Kirke Hyllinge",
    "sg:orig_category":"\u00c3\u2020ldreorganisationer og klubber",
    "sg:phone":"+45 46 40 38 90",
    "sg:postcode":"4070",
    "sg:province":"Danmark",
    "wof:name":"Bramsn\u00e6s Pensionist- og Efterl\u00f8nsforening",
    "wof:placetype":"venue"
},
  "geometry": {"coordinates":[11.9004745483,55.7080039978],"type":"Point"}
}