{
  "type": "Feature",
  "properties": {
    "iso:country":"DK",
    "sg:address":"Sct. Laurentii Vej 129",
    "sg:city":"Skagen",
    "sg:orig_category":"Glarmestre og glarmagere",
    "sg:phone":"+45 98 45 03 31",
    "sg:postcode":"9990",
    "sg:province":"Danmark",
    "wof:name":"Christensen, B\u00f8rge Rye",
    "wof:placetype":"venue"
},
  "geometry": {"coordinates":[10.5776033401,57.7179870605],"type":"Point"}
}