{
  "type": "Feature",
  "properties": {
    "addr:full":"Niels Juels Vej 18 Svendborg Danmark 5700",
    "addr:housenumber":"18",
    "addr:postcode":"5700",
    "addr:street":"Niels Juels Vej",
    "iso:country":"DK",
    "sg:address":"Niels Juels Vej 18",
    "sg:city":"Svendborg",
    "sg:orig_category":"Psykoterapi",
    "sg:phone":"+45 62 22 95 87",
    "sg:postcode":"5700",
    "sg:province":"Danmark",
    "wof:name":"Fenger, Mette",
    "wof:placetype":"venue"
},
  "geometry": {"coordinates":[10.6075935364,55.0538520813],"type":"Point"}
}