{
  "type": "Feature",
  "properties": {
    "addr:full":"Fmd.: Marian Jensen, Bromb\u00e6rvej 17 Slagelse Danmark 4200",
    "addr:housenumber":"17",
    "addr:postcode":"4200",
    "addr:street":"Brombaervej",
    "iso:country":"DK",
    "sg:address":"Fmd.: Marian Jensen, Bromb\u00e6rvej 17",
    "sg:city":"Slagelse",
    "sg:orig_category":"Kulturelle foreninger",
    "sg:phone":"+45 58 52 82 74",
    "sg:postcode":"4200",
    "sg:province":"Danmark",
    "wof:name":"Slagelse Folkedanserforening",
    "wof:placetype":"venue"
},
  "geometry": {"coordinates":[11.3569850922,55.4050865173],"type":"Point"}
}