{
  "type": "Feature",
  "properties": {
    "addr:full":"M\u00f8rupvej 48, M\u00f8rup Herning Danmark 7400",
    "addr:housenumber":"48",
    "addr:postcode":"7400",
    "addr:street":"Morupvej",
    "iso:country":"DK",
    "sg:address":"M\u00f8rupvej 48, M\u00f8rup",
    "sg:city":"Herning",
    "sg:orig_category":"Landbrugsmaskiner",
    "sg:phone":"+45 97 16 84 00",
    "sg:postcode":"7400",
    "sg:province":"Danmark",
    "wof:name":"AB Traktor- og Maskinservice",
    "wof:placetype":"venue"
},
  "geometry": {"coordinates":[8.9768896103,56.1374168396],"type":"Point"}
}