{
  "type": "Feature",
  "properties": {
    "addr:full":"Grusdalsvej 16 Horsens Danmark 8700",
    "addr:housenumber":"16",
    "addr:postcode":"8700",
    "addr:street":"Grusdalsvej",
    "iso:country":"DK",
    "sg:address":"Grusdalsvej 16",
    "sg:city":"Horsens",
    "sg:orig_category":"Ejendomshandel",
    "sg:phone":"+45 75 65 63 35",
    "sg:postcode":"8700",
    "sg:province":"Danmark",
    "wof:name":"Iversen, Jan",
    "wof:placetype":"venue"
},
  "geometry": {"coordinates":[9.8382425308,55.9041824341],"type":"Point"}
}