{
  "type": "Feature",
  "properties": {
    "iso:country":"DK",
    "sg:address":"v/ Thorstein Q. Hemmet, Kettingvej 1 A",
    "sg:city":"Augustenborg",
    "sg:orig_category":"\u00c3\u02dcvrig fritidsundervisning",
    "sg:phone":"+45 74 47 22 66",
    "sg:postcode":"6440",
    "sg:province":"Danmark",
    "wof:name":"Midtals Musikskole",
    "wof:placetype":"venue"
},
  "geometry": {"coordinates":[9.8727750778,54.9459037781],"type":"Point"}
}