{
  "type": "Feature",
  "properties": {
    "addr:full":"Industrivej 40 Aabybro Danmark 9440",
    "addr:housenumber":"40",
    "addr:postcode":"9440",
    "addr:street":"Industrivej",
    "iso:country":"DK",
    "sg:address":"Industrivej 40",
    "sg:city":"Aabybro",
    "sg:orig_category":"Varmeforsyning",
    "sg:phone":"+45 98 24 23 20",
    "sg:postcode":"9440",
    "sg:province":"Danmark",
    "wof:name":"Aabybro Fjernvarmev\u00e6rk A.m.b.A.",
    "wof:placetype":"venue"
},
  "geometry": {"coordinates":[9.744301796,57.155418396],"type":"Point"}
}