{
  "type": "Feature",
  "properties": {
    "addr:full":"Ydunvej 20 Vemmelev Danmark 4241",
    "addr:housenumber":"20",
    "addr:postcode":"4241",
    "addr:street":"Ydunvej",
    "iso:country":"DK",
    "sg:address":"Ydunvej 20",
    "sg:city":"Vemmelev",
    "sg:orig_category":"Forsamlingshuse",
    "sg:phone":"+45 58 38 52 29",
    "sg:postcode":"4241",
    "sg:province":"Danmark",
    "wof:name":"Ydun Forsamlingshus",
    "wof:placetype":"venue"
},
  "geometry": {"coordinates":[11.2296581268,55.3310890198],"type":"Point"}
}