{
  "type": "Feature",
  "properties": {
    "addr:full":"Mosetoften 1 Hedensted Danmark 8722",
    "addr:housenumber":"1",
    "addr:postcode":"8722",
    "addr:street":"Mosetoften",
    "iso:country":"DK",
    "sg:address":"Mosetoften 1",
    "sg:city":"Hedensted",
    "sg:orig_category":"Fabrikker",
    "sg:phone":"+45 75 89 17 01",
    "sg:postcode":"8722",
    "sg:province":"Danmark",
    "wof:name":"X-Pro ApS",
    "wof:placetype":"venue"
},
  "geometry": {"coordinates":[9.6962718964,55.777633667],"type":"Point"}
}