{
  "type": "Feature",
  "properties": {
    "iso:country":"DK",
    "sg:address":"v/ Martin Ulberg, R\u00e5es V\u00e6nge 50",
    "sg:city":"Kalundborg",
    "sg:orig_category":"Spejderkorps",
    "sg:phone":"+45 59 51 00 74",
    "sg:postcode":"4400",
    "sg:province":"Danmark",
    "wof:name":"FDF Kalundborg Kreds",
    "wof:placetype":"venue"
},
  "geometry": {"coordinates":[11.0934085846,55.6797485352],"type":"Point"}
}