{
  "type": "Feature",
  "properties": {
    "addr:full":"L\u00f8gtenvej 25 Hornslet Danmark 8543",
    "addr:housenumber":"25",
    "addr:postcode":"8543",
    "addr:street":"Logtenvej",
    "iso:country":"DK",
    "sg:address":"L\u00f8gtenvej 25",
    "sg:city":"Hornslet",
    "sg:orig_category":"\u00c3\u02dcl- og mineralvandsdepoter",
    "sg:phone":"+45 86 99 50 92",
    "sg:postcode":"8543",
    "sg:province":"Danmark",
    "wof:name":"Bj\u00f8rnkilde Depotet",
    "wof:placetype":"venue"
},
  "geometry": {"coordinates":[10.3186988831,56.3101387024],"type":"Point"}
}