{
  "type": "Feature",
  "properties": {
    "addr:full":"v/ Flemming Bruun, Hannerupg\u00e5rdsvej 22 B Odense M Danmark 5230",
    "addr:housenumber":"22 b",
    "addr:postcode":"5230",
    "addr:street":"Hannerupgaardsvej",
    "iso:country":"DK",
    "sg:address":"v/ Flemming Bruun, Hannerupg\u00e5rdsvej 22 B",
    "sg:city":"Odense M",
    "sg:orig_category":"Spejderkorps",
    "sg:phone":"+45 66 12 12 05",
    "sg:postcode":"5230",
    "sg:province":"Danmark",
    "wof:name":"FDF Odense 14. Thomas Kingo Kreds",
    "wof:placetype":"venue"
},
  "geometry": {"coordinates":[10.3966598511,55.3816184998],"type":"Point"}
}