{
  "type": "Feature",
  "properties": {
    "iso:country":"DK",
    "sg:address":"Gr\u00f8nnegade 1",
    "sg:city":"Stubbek\u00f8bing",
    "sg:classifiers":[
        {
            "category":"Restaurant",
            "type":"Food & Drink"
        }
    ],
    "sg:phone":"+45 54 44 10 09",
    "sg:postcode":"4850",
    "sg:province":"Danmark",
    "wof:name":"Gr\u00f8nsund, Restaurant",
    "wof:placetype":"venue"
},
  "geometry": {"coordinates":[-98.3404388428,35.30727005],"type":"Point"}
}