{
  "type": "Feature",
  "properties": {
    "iso:country":"DK",
    "sg:address":"v/Tyrstrup Skole, Gl. Kongevej 3",
    "sg:city":"Christiansfeld",
    "sg:orig_category":"Jordemodercentre",
    "sg:phone":"+45 74 56 11 42",
    "sg:postcode":"6070",
    "sg:province":"Danmark",
    "wof:name":"Jordemoderkonsultationen i Christiansfeld",
    "wof:placetype":"venue"
},
  "geometry": {"coordinates":[9.4834346771,55.3550567627],"type":"Point"}
}