{
  "type": "Feature",
  "properties": {
    "addr:full":"Fmd.: Hardy Andreasen, Godth\u00e5bsvej 5 Haderslev Danmark 6100",
    "addr:housenumber":"5",
    "addr:postcode":"6100",
    "addr:street":"Godthaabsvej",
    "iso:country":"DK",
    "sg:address":"Fmd.: Hardy Andreasen, Godth\u00e5bsvej 5",
    "sg:city":"Haderslev",
    "sg:orig_category":"Faglige organisationer og foreninger",
    "sg:phone":"+45 74 52 43 11",
    "sg:postcode":"6100",
    "sg:province":"Danmark",
    "wof:name":"Blik- og R\u00f8rarbejderforbund, Haderslev Afdeling",
    "wof:placetype":"venue"
},
  "geometry": {"coordinates":[9.4879703522,55.2505493164],"type":"Point"}
}