{
  "type": "Feature",
  "properties": {
    "iso:country":"DK",
    "sg:address":"Vesterbrogade 61",
    "sg:city":"Gilleleje",
    "sg:orig_category":"Genbrugsbutikker",
    "sg:phone":"+45 48 35 46 16",
    "sg:postcode":"3250",
    "sg:province":"Danmark",
    "wof:name":"Pedersen, Elzbieta",
    "wof:placetype":"venue"
},
  "geometry": {"coordinates":[12.2926607132,56.1239204407],"type":"Point"}
}