{
  "type": "Feature",
  "properties": {
    "addr:full":"Jernbanegade 3 A Slagelse Danmark 4200",
    "addr:housenumber":"3 a",
    "addr:postcode":"4200",
    "addr:street":"Jernbanegade",
    "iso:country":"DK",
    "sg:address":"Jernbanegade 3 A",
    "sg:city":"Slagelse",
    "sg:orig_category":"Murermestre",
    "sg:phone":"+45 58 53 11 16",
    "sg:postcode":"4200",
    "sg:province":"Danmark",
    "wof:name":"Nielsen, Finn Erik",
    "wof:placetype":"venue"
},
  "geometry": {"coordinates":[11.3530378342,55.4052848816],"type":"Point"}
}