{
  "type": "Feature",
  "properties": {
    "addr:full":"v/ Hugo Andersen, Lin\u00e5v\u00e6nget 13 Sunds Danmark 7451",
    "addr:housenumber":"13",
    "addr:postcode":"7451",
    "addr:street":"Linaavaenget",
    "iso:country":"DK",
    "sg:address":"v/ Hugo Andersen, Lin\u00e5v\u00e6nget 13",
    "sg:city":"Sunds",
    "sg:orig_category":"Soldaterforeninger",
    "sg:phone":"+45 97 14 27 30",
    "sg:postcode":"7451",
    "sg:province":"Danmark",
    "wof:name":"Beredskabskorpsets Mandskabsforening",
    "wof:placetype":"venue"
},
  "geometry": {"coordinates":[9.0151100159,56.2057800293],"type":"Point"}
}