{
  "type": "Feature",
  "properties": {
    "addr:full":"Rimmensgade 2 Frederikshavn Danmark 9900",
    "addr:housenumber":"2",
    "addr:postcode":"9900",
    "addr:street":"Rimmensgade",
    "iso:country":"DK",
    "sg:address":"Rimmensgade 2",
    "sg:city":"Frederikshavn",
    "sg:classifiers":[
        {
            "category":"Restaurant",
            "type":"Food & Drink"
        }
    ],
    "sg:phone":"+45 98 42 24 27",
    "sg:postcode":"9900",
    "sg:province":"Danmark",
    "wof:name":"Fladstrand, Restaurant",
    "wof:placetype":"venue"
},
  "geometry": {"coordinates":[10.5344171524,57.4382896423],"type":"Point"}
}