{
  "type": "Feature",
  "properties": {
    "iso:country":"DK",
    "sg:address":"Eriksvej 2",
    "sg:city":"Ringsted",
    "sg:orig_category":"Skolefritidsordninger",
    "sg:phone":"+45 57 67 51 35",
    "sg:postcode":"4100",
    "sg:province":"Danmark",
    "wof:name":"Sdr. Parkskolens SFO II Erikg\u00e5rden",
    "wof:placetype":"venue"
},
  "geometry": {"coordinates":[11.7818489075,55.426574707],"type":"Point"}
}