{
  "type": "Feature",
  "properties": {
    "addr:full":"v/Ole Jensen, Syrenvej 11 Grindsted Danmark 7200",
    "addr:housenumber":"11",
    "addr:postcode":"7200",
    "addr:street":"Syrenvej",
    "iso:country":"DK",
    "sg:address":"v/Ole Jensen, Syrenvej 11",
    "sg:city":"Grindsted",
    "sg:orig_category":"Kirkelige foreninger",
    "sg:phone":"+45 75 32 18 57",
    "sg:postcode":"7200",
    "sg:province":"Danmark",
    "wof:name":"Krisos (Kristne i Social- og Sundhedssektoren), Sydvestjylland",
    "wof:placetype":"venue"
},
  "geometry": {"coordinates":[8.9288702011,55.7560272217],"type":"Point"}
}