{
  "type": "Feature",
  "properties": {
    "addr:full":"Strandvejen 451 Klampenborg Danmark 2930",
    "addr:housenumber":"451",
    "addr:postcode":"2930",
    "addr:street":"Strandvejen",
    "iso:country":"DK",
    "sg:address":"Strandvejen 451",
    "sg:city":"Klampenborg",
    "sg:orig_category":"Teatre",
    "sg:phone":"+45 39 63 49 00",
    "sg:postcode":"2930",
    "sg:province":"Danmark",
    "wof:name":"Bellevue Teatret",
    "wof:placetype":"venue"
},
  "geometry": {"coordinates":[12.5900154114,55.7784767151],"type":"Point"}
}