{
  "type": "Feature",
  "properties": {
    "addr:full":"Pr\u00e6sident: Per Carlsen, Amtstue Alle 6 Ringsted Danmark 4100",
    "addr:housenumber":"6",
    "addr:postcode":"4100",
    "addr:street":"Amtstue Alle",
    "iso:country":"DK",
    "sg:address":"Pr\u00e6sident: Per Carlsen, Amtstue Alle 6",
    "sg:city":"Ringsted",
    "sg:orig_category":"Loger",
    "sg:phone":"+45 57 61 21 67",
    "sg:postcode":"4100",
    "sg:province":"Danmark",
    "wof:name":"Sct. Bendts Rotary",
    "wof:placetype":"venue"
},
  "geometry": {"coordinates":[11.7875862122,55.4458961487],"type":"Point"}
}