{
  "type": "Feature",
  "properties": {
    "iso:country":"DK",
    "sg:address":"Vestergade 3",
    "sg:city":"Stoholm",
    "sg:orig_category":"Sparekasser",
    "sg:phone":"+45 97 54 16 44",
    "sg:postcode":"7850",
    "sg:province":"Danmark",
    "wof:name":"Sparekassen Kronjylland",
    "wof:placetype":"venue"
},
  "geometry": {"coordinates":[9.1504564285,56.4854202271],"type":"Point"}
}