{
  "type": "Feature",
  "properties": {
    "addr:full":"Tinghuset, Vendersgade 30 D Fredericia Danmark 7000",
    "addr:housenumber":"30 d",
    "addr:postcode":"7000",
    "addr:street":"Tinghuset Vendersgade",
    "iso:country":"DK",
    "sg:address":"Tinghuset, Vendersgade 30 D",
    "sg:city":"Fredericia",
    "sg:orig_category":"Dommerkontorer",
    "sg:phone":"+45 76 20 11 99",
    "sg:postcode":"7000",
    "sg:province":"Danmark",
    "wof:name":"Dommerkontor (civil- og fogedret).",
    "wof:placetype":"venue"
},
  "geometry": {"coordinates":[9.7591047287,55.566368103],"type":"Point"}
}