{
  "type": "Feature",
  "properties": {
    "addr:full":"S\u00f8ndergade 4 Vejen Danmark 6600",
    "addr:housenumber":"4",
    "addr:postcode":"6600",
    "addr:street":"Sondergade",
    "iso:country":"DK",
    "sg:address":"S\u00f8ndergade 4",
    "sg:city":"Vejen",
    "sg:orig_category":"Optikere",
    "sg:phone":"+45 75 36 08 77",
    "sg:postcode":"6600",
    "sg:province":"Danmark",
    "sg:website":"www.profiloptik.dk",
    "wof:name":"Profil Optik",
    "wof:placetype":"venue"
},
  "geometry": {"coordinates":[9.1373968124,55.4751625061],"type":"Point"}
}