{
  "type": "Feature",
  "properties": {
    "addr:full":"Auktionsvej 10 Skagen Danmark 9990",
    "addr:housenumber":"10",
    "addr:postcode":"9990",
    "addr:street":"Auktionsvej",
    "iso:country":"DK",
    "sg:address":"Auktionsvej 10",
    "sg:city":"Skagen",
    "sg:orig_category":"Fiskeauktioner",
    "sg:phone":"+45 98 44 12 00",
    "sg:postcode":"9990",
    "sg:province":"Danmark",
    "wof:name":"Skagen Fiskeauktion",
    "wof:placetype":"venue"
},
  "geometry": {"coordinates":[10.5920677185,57.7205505371],"type":"Point"}
}