{
  "type": "Feature",
  "properties": {
    "addr:full":"Kirkegade 20 Mariager Danmark 9550",
    "addr:housenumber":"20",
    "addr:postcode":"9550",
    "addr:street":"Kirkegade",
    "iso:country":"DK",
    "sg:address":"Kirkegade 20",
    "sg:city":"Mariager",
    "sg:orig_category":"Autoreparation og -service",
    "sg:phone":"+45 98 54 19 88",
    "sg:postcode":"9550",
    "sg:province":"Danmark",
    "wof:name":"Svennes Auto",
    "wof:placetype":"venue"
},
  "geometry": {"coordinates":[9.9813804626,56.6491966248],"type":"Point"}
}