{
  "type": "Feature",
  "properties": {
    "addr:full":"Brogade 9 K\u00f8ge Danmark 4600",
    "addr:housenumber":"9",
    "addr:postcode":"4600",
    "addr:street":"Brogade",
    "iso:country":"DK",
    "sg:address":"Brogade 9",
    "sg:city":"K\u00f8ge",
    "sg:orig_category":"Reklamebureauer",
    "sg:phone":"+45 56 64 04 00",
    "sg:postcode":"4600",
    "sg:province":"Danmark",
    "sg:website":"www.aogj.dk",
    "wof:name":"Andersson & Jantzen",
    "wof:placetype":"venue"
},
  "geometry": {"coordinates":[12.182267189,55.4555358887],"type":"Point"}
}