{
  "type": "Feature",
  "properties": {
    "addr:full":"Roskildevej 150 Valby Danmark 2500",
    "addr:housenumber":"150",
    "addr:postcode":"2500",
    "addr:street":"Roskildevej",
    "iso:country":"DK",
    "sg:address":"Roskildevej 150",
    "sg:city":"Valby",
    "sg:orig_category":"Sengeudstyr",
    "sg:phone":"+45 38 71 38 00",
    "sg:postcode":"2500",
    "sg:province":"Danmark",
    "wof:name":"Jysk Senget\u00f8jslager A/S",
    "wof:placetype":"venue"
},
  "geometry": {"coordinates":[12.4881772995,55.6727027893],"type":"Point"}
}