{
  "type": "Feature",
  "properties": {
    "iso:country":"DK",
    "sg:address":"Gasvej 2, Postboks 54",
    "sg:city":"Horsens",
    "sg:orig_category":"Blikkenslagere",
    "sg:phone":"+45 75 62 32 23",
    "sg:postcode":"8700",
    "sg:province":"Danmark",
    "wof:name":"B\u00f8rge Jensen og S\u00f8nner",
    "wof:placetype":"venue"
},
  "geometry": {"coordinates":[9.843245,55.862106],"type":"Point"}
}