{
  "type": "Feature",
  "properties": {
    "addr:full":"Dronning Margrethes Vej 1 \u00d8lstykke Danmark 3650",
    "addr:housenumber":"1",
    "addr:postcode":"3650",
    "addr:street":"Dronning Margrethes Vej",
    "iso:country":"DK",
    "sg:address":"Dronning Margrethes Vej 1",
    "sg:city":"\u00d8lstykke",
    "sg:orig_category":"Integrerede institutioner",
    "sg:phone":"+45 47 16 00 20",
    "sg:postcode":"3650",
    "sg:province":"Danmark",
    "wof:name":"B\u00f8rneinstitution Margrethebakken",
    "wof:placetype":"venue"
},
  "geometry": {"coordinates":[12.1792449951,55.780834198],"type":"Point"}
}