{
  "type": "Feature",
  "properties": {
    "addr:full":"\u00d8stergade 7 A Bagenkop Danmark 5935",
    "addr:housenumber":"7 a",
    "addr:postcode":"5935",
    "addr:street":"Ostergade",
    "iso:country":"DK",
    "sg:address":"\u00d8stergade 7 A",
    "sg:city":"Bagenkop",
    "sg:orig_category":"Farve og tapet",
    "sg:phone":"+45 62 56 11 14",
    "sg:postcode":"5935",
    "sg:province":"Danmark",
    "wof:name":"Karlsens Tapet & Farvehandel",
    "wof:placetype":"venue"
},
  "geometry": {"coordinates":[10.6736545563,54.7497787476],"type":"Point"}
}