{
  "type": "Feature",
  "properties": {
    "addr:full":"v/ Kaj Simonsen, Rugbjerg 44 Greve Danmark 2670",
    "addr:housenumber":"44",
    "addr:postcode":"2670",
    "addr:street":"Rugbjerg",
    "iso:country":"DK",
    "sg:address":"v/ Kaj Simonsen, Rugbjerg 44",
    "sg:city":"Greve",
    "sg:orig_category":"Antenneforeninger",
    "sg:phone":"+45 43 90 99 08",
    "sg:postcode":"2670",
    "sg:province":"Danmark",
    "wof:name":"Hundigegaard Antennelaug",
    "wof:placetype":"venue"
},
  "geometry": {"coordinates":[12.2941808701,55.5844078064],"type":"Point"}
}