{
  "type": "Feature",
  "properties": {
    "addr:full":"Ametystvej 12 Jyllinge Danmark 4040",
    "addr:housenumber":"12",
    "addr:postcode":"4040",
    "addr:street":"Ametystvej",
    "iso:country":"DK",
    "sg:address":"Ametystvej 12",
    "sg:city":"Jyllinge",
    "sg:orig_category":"Databehandling",
    "sg:phone":"+45 46 73 01 15",
    "sg:postcode":"4040",
    "sg:province":"Danmark",
    "sg:website":"www.imagehouse.dk",
    "wof:name":"Gade-Data",
    "wof:placetype":"venue"
},
  "geometry": {"coordinates":[12.1139364243,55.754863739],"type":"Point"}
}