{
  "type": "Feature",
  "properties": {
    "addr:full":"Hoski\u00e6rsvej 17 Nakskov Danmark 4900",
    "addr:housenumber":"17",
    "addr:postcode":"4900",
    "addr:street":"Hoskiaersvej",
    "iso:country":"DK",
    "sg:address":"Hoski\u00e6rsvej 17",
    "sg:city":"Nakskov",
    "sg:orig_category":"Skomagere",
    "sg:phone":"+45 54 92 56 61",
    "sg:postcode":"4900",
    "sg:province":"Danmark",
    "wof:name":"Sahva A/S",
    "wof:placetype":"venue"
},
  "geometry": {"coordinates":[11.1458673477,54.8332901001],"type":"Point"}
}