{
  "type": "Feature",
  "properties": {
    "addr:full":"R\u00e5dhusvej 55 B Fakse Danmark 4640",
    "addr:housenumber":"55 b",
    "addr:postcode":"4640",
    "addr:street":"Raadhusvej",
    "iso:country":"DK",
    "sg:address":"R\u00e5dhusvej 55 B",
    "sg:city":"Fakse",
    "sg:orig_category":"Kiropraktorer",
    "sg:phone":"+45 56 71 30 05",
    "sg:postcode":"4640",
    "sg:province":"Danmark",
    "wof:name":"Kiropraktisk Klinik",
    "wof:placetype":"venue"
},
  "geometry": {"coordinates":[12.1135807037,55.249370575],"type":"Point"}
}