{
  "type": "Feature",
  "properties": {
    "addr:full":"Jernbanevej 2 Farum Danmark 3520",
    "addr:housenumber":"2",
    "addr:postcode":"3520",
    "addr:street":"Jernbanevej",
    "iso:country":"DK",
    "sg:address":"Jernbanevej 2",
    "sg:city":"Farum",
    "sg:orig_category":"Cafeer",
    "sg:phone":"+45 44 95 01 81",
    "sg:postcode":"3520",
    "sg:province":"Danmark",
    "wof:name":"Williams, Caf\u00e9",
    "wof:placetype":"venue"
},
  "geometry": {"coordinates":[12.3729047775,55.8119544983],"type":"Point"}
}