{
  "type": "Feature",
  "properties": {
    "addr:full":"Smedev\u00e6nget 2 Fredericia Danmark 7000",
    "addr:housenumber":"2",
    "addr:postcode":"7000",
    "addr:street":"Smedevaenget",
    "iso:country":"DK",
    "sg:address":"Smedev\u00e6nget 2",
    "sg:city":"Fredericia",
    "sg:orig_category":"Autoreparation og -service",
    "sg:phone":"+45 75 92 55 19",
    "sg:postcode":"7000",
    "sg:province":"Danmark",
    "wof:name":"\u00c5g\u00e5rds Autov\u00e6rksted",
    "wof:placetype":"venue"
},
  "geometry": {"coordinates":[9.7591047287,55.566368103],"type":"Point"}
}