{
  "type": "Feature",
  "properties": {
    "addr:full":"Fmd.: Kaja Hartmann, Rugv\u00e6nget 19, Skalleb\u00f8lle Vissenbjerg Danmark 5492",
    "addr:housenumber":"19",
    "addr:postcode":"5492",
    "addr:street":"Rugvaenget;Skallebolle",
    "iso:country":"DK",
    "sg:address":"Fmd.: Kaja Hartmann, Rugv\u00e6nget 19, Skalleb\u00f8lle",
    "sg:city":"Vissenbjerg",
    "sg:orig_category":"Kulturelle foreninger",
    "sg:phone":"+45 65 96 76 89",
    "sg:postcode":"5492",
    "sg:province":"Danmark",
    "wof:name":"Kulturforeningen N\u00f8jsomhed",
    "wof:placetype":"venue"
},
  "geometry": {"coordinates":[10.1324472427,55.386051178],"type":"Point"}
}