{
  "type": "Feature",
  "properties": {
    "addr:full":"H\u00e5ndv\u00e6rkervej 13 Herlufmagle Danmark 4160",
    "addr:housenumber":"13",
    "addr:postcode":"4160",
    "addr:street":"Haandvaerkervej",
    "iso:country":"DK",
    "sg:address":"H\u00e5ndv\u00e6rkervej 13",
    "sg:city":"Herlufmagle",
    "sg:orig_category":"Keramik",
    "sg:phone":"+45 46 75 79 00",
    "sg:postcode":"4160",
    "sg:province":"Danmark",
    "wof:name":"Dyrholm ApS, J.",
    "wof:placetype":"venue"
},
  "geometry": {"coordinates":[11.7522201538,55.3147735596],"type":"Point"}
}