{
  "type": "Feature",
  "properties": {
    "addr:full":"Blokvej 2 G Ribe Danmark 6760",
    "addr:housenumber":"2 g",
    "addr:postcode":"6760",
    "addr:street":"Blokvej",
    "iso:country":"DK",
    "sg:address":"Blokvej 2 G",
    "sg:city":"Ribe",
    "sg:orig_category":"Andelsboligforeninger",
    "sg:phone":"+45 75 42 40 86",
    "sg:postcode":"6760",
    "sg:province":"Danmark",
    "wof:name":"Boligforeningen Vestenvinden",
    "wof:placetype":"venue"
},
  "geometry": {"coordinates":[8.7656240463,55.3297042847],"type":"Point"}
}