{
  "type": "Feature",
  "properties": {
    "addr:full":"L\u00f8nborgvej 12 Hvidovre Danmark 2650",
    "addr:housenumber":"12",
    "addr:postcode":"2650",
    "addr:street":"Lonborgvej",
    "iso:country":"DK",
    "sg:address":"L\u00f8nborgvej 12",
    "sg:city":"Hvidovre",
    "sg:orig_category":"Gulvafslibning",
    "sg:phone":"+45 36 49 90 20",
    "sg:postcode":"2650",
    "sg:province":"Danmark",
    "wof:name":"Gulvservice",
    "wof:placetype":"venue"
},
  "geometry": {"coordinates":[12.4665908813,55.6325340271],"type":"Point"}
}