{
  "type": "Feature",
  "properties": {
    "addr:full":"Albanivej 15 A, Nr. Lyndelse \u00c5rslev Danmark 5792",
    "addr:housenumber":"15 a nr.",
    "addr:postcode":"5792",
    "addr:street":"Albanivej;Lyndelse Aarslev Danmark",
    "iso:country":"DK",
    "sg:address":"Albanivej 15 A, Nr. Lyndelse",
    "sg:city":"\u00c5rslev",
    "sg:orig_category":"Kirker",
    "sg:postcode":"5792",
    "sg:province":"Danmark",
    "wof:name":"Nr. Lyndelse Kirke",
    "wof:placetype":"venue"
},
  "geometry": {"coordinates":[166.9221496582,-0.5282999873],"type":"Point"}
}