{
  "type": "Feature",
  "properties": {
    "addr:full":"Faaborgvej 19 A, Postboks 16 Gislev Danmark 5854",
    "addr:housenumber":"19 a;16",
    "addr:postcode":"5854",
    "addr:street":"Faaborgvej;Postboks",
    "iso:country":"DK",
    "sg:address":"Faaborgvej 19 A, Postboks 16",
    "sg:city":"Gislev",
    "sg:orig_category":"Fritidsklubber",
    "sg:phone":"+45 62 29 17 98",
    "sg:postcode":"5854",
    "sg:province":"Danmark",
    "wof:name":"Fristedet",
    "wof:placetype":"venue"
},
  "geometry": {"coordinates":[10.5988063812,55.2191352844],"type":"Point"}
}