{
  "type": "Feature",
  "properties": {
    "addr:full":"Br\u00f8dregade 34 Randers Danmark 8900",
    "addr:housenumber":"34",
    "addr:postcode":"8900",
    "addr:street":"Brodregade",
    "iso:country":"DK",
    "sg:address":"Br\u00f8dregade 34",
    "sg:city":"Randers",
    "sg:orig_category":"Parfumerier",
    "sg:phone":"+45 86 40 11 33",
    "sg:postcode":"8900",
    "sg:province":"Danmark",
    "wof:name":"Bodyform",
    "wof:placetype":"venue"
},
  "geometry": {"coordinates":[10.0375680923,56.458896637],"type":"Point"}
}