{
  "type": "Feature",
  "properties": {
    "addr:full":"Jerne Sognehus, M\u00f8llebakken 2 Esbjerg \u00d8 Danmark 6705",
    "addr:housenumber":"2",
    "addr:postcode":"6705",
    "addr:street":"Mollebakken;Danmark",
    "iso:country":"DK",
    "sg:address":"Jerne Sognehus, M\u00f8llebakken 2",
    "sg:city":"Esbjerg \u00d8",
    "sg:orig_category":"Kirkesogne",
    "sg:phone":"+45 76 10 46 30",
    "sg:postcode":"6705",
    "sg:province":"Danmark",
    "wof:name":"Jerne Kirkes Kontor",
    "wof:placetype":"venue"
},
  "geometry": {"coordinates":[8.5338830948,55.5006523132],"type":"Point"}
}