{
  "type": "Feature",
  "properties": {
    "addr:full":"Rymarksvej 23 Hellerup Danmark 2900",
    "addr:housenumber":"23",
    "addr:postcode":"2900",
    "addr:street":"Rymarksvej",
    "iso:country":"DK",
    "sg:address":"Rymarksvej 23",
    "sg:city":"Hellerup",
    "sg:orig_category":"Plejehjem",
    "sg:phone":"+45 39 29 71 22",
    "sg:postcode":"2900",
    "sg:province":"Danmark",
    "wof:name":"Ryholtg\u00e5rd Plejehjem",
    "wof:placetype":"venue"
},
  "geometry": {"coordinates":[12.5628681183,55.7260475159],"type":"Point"}
}