{
  "type": "Feature",
  "properties": {
    "addr:full":"Gl. Agerskovvej 3, Rangstrup Agerskov Danmark 6534",
    "addr:housenumber":"3",
    "addr:postcode":"6534",
    "addr:street":"Gl. Agerskovvej",
    "iso:country":"DK",
    "sg:address":"Gl. Agerskovvej 3, Rangstrup",
    "sg:city":"Agerskov",
    "sg:orig_category":"Maskinstationer",
    "sg:phone":"+45 74 51 91 01",
    "sg:postcode":"6534",
    "sg:province":"Danmark",
    "wof:name":"Rangstrup Maskinstation",
    "wof:placetype":"venue"
},
  "geometry": {"coordinates":[9.1290597916,55.1300849915],"type":"Point"}
}