{
  "type": "Feature",
  "properties": {
    "iso:country":"DK",
    "sg:address":"Duevej 120 B",
    "sg:city":"Frederiksberg",
    "sg:orig_category":"Reklamebureauer",
    "sg:phone":"+45 38 86 03 22",
    "sg:postcode":"2000",
    "sg:province":"Danmark",
    "wof:name":"Layout/Reklame",
    "wof:placetype":"venue"
},
  "geometry": {"coordinates":[12.5313177109,55.6935348511],"type":"Point"}
}