{
  "type": "Feature",
  "properties": {
    "iso:country":"DK",
    "sg:address":"Hj\u00f8rringvej 143",
    "sg:city":"Frederikshavn",
    "sg:orig_category":"Babyudstyr",
    "sg:phone":"+45 98 43 20 77",
    "sg:postcode":"9900",
    "sg:province":"Danmark",
    "wof:name":"BabySam",
    "wof:placetype":"venue"
},
  "geometry": {"coordinates":[10.507711,57.446655],"type":"Point"}
}