{
  "type": "Feature",
  "properties": {
    "addr:full":"Roedsvej 7 Holb\u00e6k Danmark 4300",
    "addr:housenumber":"7",
    "addr:postcode":"4300",
    "addr:street":"Roedsvej",
    "iso:country":"DK",
    "sg:address":"Roedsvej 7",
    "sg:city":"Holb\u00e6k",
    "sg:orig_category":"Psykoterapi",
    "sg:phone":"+45 59 44 37 57",
    "sg:postcode":"4300",
    "sg:province":"Danmark",
    "wof:name":"Dorthe Glamb\u00e6k",
    "wof:placetype":"venue"
},
  "geometry": {"coordinates":[76.3070983887,14.277130127],"type":"Point"}
}