{
  "type": "Feature",
  "properties": {
    "addr:full":"Solh\u00f8jsvej 10 Silkeborg Danmark 8600",
    "addr:housenumber":"10",
    "addr:postcode":"8600",
    "addr:street":"Solhojsvej",
    "iso:country":"DK",
    "sg:address":"Solh\u00f8jsvej 10",
    "sg:city":"Silkeborg",
    "sg:orig_category":"Forsikringer",
    "sg:phone":"+45 86 81 23 33",
    "sg:postcode":"8600",
    "sg:province":"Danmark",
    "wof:name":"Vase, Jens",
    "wof:placetype":"venue"
},
  "geometry": {"coordinates":[9.5351629257,56.1584892273],"type":"Point"}
}