{
  "type": "Feature",
  "properties": {
    "addr:full":"Bogensevej 206, N\u00e6sby Odense N Danmark 5270",
    "addr:housenumber":"206",
    "addr:postcode":"5270",
    "addr:street":"Bogensevej;Naesby",
    "iso:country":"DK",
    "sg:address":"Bogensevej 206, N\u00e6sby",
    "sg:city":"Odense N",
    "sg:orig_category":"Malerforretninger",
    "sg:phone":"+45 23 67 98 13",
    "sg:postcode":"5270",
    "sg:province":"Danmark",
    "wof:name":"Jakobsens Malerforretning",
    "wof:placetype":"venue"
},
  "geometry": {"coordinates":[10.3306798935,55.4711418152],"type":"Point"}
}