{
  "type": "Feature",
  "properties": {
    "addr:full":"C. F. Tietgens Vej 6 Kolding Danmark 6000",
    "addr:housenumber":"6",
    "addr:postcode":"6000",
    "addr:street":"C. F. Tietgens Vej",
    "iso:country":"DK",
    "sg:address":"C. F. Tietgens Vej 6",
    "sg:city":"Kolding",
    "sg:orig_category":"Arbejdsmarkedsuddannelser",
    "sg:phone":"+45 76 37 37 37",
    "sg:postcode":"6000",
    "sg:province":"Danmark",
    "sg:website":"www.amusyd.dk",
    "wof:name":"AMU Syd",
    "wof:placetype":"venue"
},
  "geometry": {"coordinates":[9.4609422684,55.5077667236],"type":"Point"}
}