{
  "type": "Feature",
  "properties": {
    "addr:full":"Skipper Clements Vej 27 Aabybro Danmark 9440",
    "addr:housenumber":"27",
    "addr:postcode":"9440",
    "addr:street":"Skipper Clements Vej",
    "iso:country":"DK",
    "sg:address":"Skipper Clements Vej 27",
    "sg:city":"Aabybro",
    "sg:orig_category":"Handicapboliger",
    "sg:phone":"+45 98 24 43 33",
    "sg:postcode":"9440",
    "sg:province":"Danmark",
    "wof:name":"Boenhed",
    "wof:placetype":"venue"
},
  "geometry": {"coordinates":[9.7366123199,57.1586036682],"type":"Point"}
}