{
  "type": "Feature",
  "properties": {
    "addr:full":"Svalevej 16 Hellerup Danmark 2900",
    "addr:housenumber":"16",
    "addr:postcode":"2900",
    "addr:street":"Svalevej",
    "iso:country":"DK",
    "sg:address":"Svalevej 16",
    "sg:city":"Hellerup",
    "sg:orig_category":"Astrologi",
    "sg:phone":"+45 39 61 07 67",
    "sg:postcode":"2900",
    "sg:province":"Danmark",
    "wof:name":"Balk-M\u00f8ller, Pia",
    "wof:placetype":"venue"
},
  "geometry": {"coordinates":[12.5604200363,55.74584198],"type":"Point"}
}