{
  "type": "Feature",
  "properties": {
    "addr:full":"Krarupsvej 13 - 15 Herning Danmark 7400",
    "addr:housenumber":"13 15",
    "addr:postcode":"7400",
    "addr:street":"Krarupsvej",
    "iso:country":"DK",
    "sg:address":"Krarupsvej 13 - 15",
    "sg:city":"Herning",
    "sg:orig_category":"Forkromning",
    "sg:phone":"+45 97 12 16 55",
    "sg:postcode":"7400",
    "sg:province":"Danmark",
    "wof:name":"Herning Forcromning",
    "wof:placetype":"venue"
},
  "geometry": {"coordinates":[8.9907493591,56.1454734802],"type":"Point"}
}