{
  "type": "Feature",
  "properties": {
    "iso:country":"DK",
    "sg:address":"Kystvej 54",
    "sg:city":"Aabenraa",
    "sg:orig_category":"Servicestationer",
    "sg:phone":"+45 74 62 57 77",
    "sg:postcode":"6200",
    "sg:province":"Danmark",
    "wof:name":"Q8 Service",
    "wof:placetype":"venue"
},
  "geometry": {"coordinates":[9.4210767746,55.0352401733],"type":"Point"}
}