{
  "type": "Feature",
  "properties": {
    "iso:country":"DK",
    "sg:address":"L\u00f8hdesvej 6 B",
    "sg:city":"Engesvang",
    "sg:orig_category":"Broderi",
    "sg:phone":"+45 86 86 40 55",
    "sg:postcode":"7442",
    "sg:province":"Danmark",
    "wof:name":"Camee Broderi A/S",
    "wof:placetype":"venue"
},
  "geometry": {"coordinates":[9.3528785706,56.1611671448],"type":"Point"}
}