{
  "type": "Feature",
  "properties": {
    "addr:full":"Ryesgade 4, Postboks 195 8100",
    "addr:housenumber":"4;195",
    "addr:postcode":"8100",
    "addr:street":"Ryesgade",
    "iso:country":"DK",
    "sg:address":"Ryesgade 4, Postboks 195",
    "sg:classifiers":[
        {
            "category":"Banks & Credit Unions",
            "subcategory":"Bank",
            "type":"Services"
        }
    ],
    "sg:phone":"+45 87 30 11 30",
    "sg:postcode":"8100",
    "sg:tags":[
        "banker"
    ],
    "sg:website":"www.sparbankvest.dk",
    "wof:name":"Sparbank Vest",
    "wof:placetype":"venue"
},
  "geometry": {"coordinates":[2.0778300762,49.1431007385],"type":"Point"}
}