{
  "type": "Feature",
  "properties": {
    "addr:full":"Dannebrogs Alle 7 Kongens Lyngby Danmark 2800",
    "addr:housenumber":"7",
    "addr:postcode":"2800",
    "addr:street":"Dannebrogs Alle",
    "iso:country":"DK",
    "sg:address":"Dannebrogs Alle 7",
    "sg:city":"Kongens Lyngby",
    "sg:classifiers":[
        {
            "category":"Professional",
            "subcategory":"Computer Services",
            "type":"Services"
        }
    ],
    "sg:phone":"+45 45 88 64 59",
    "sg:postcode":"2800",
    "sg:province":"Danmark",
    "sg:tags":[
        "edb",
        "-",
        "software"
    ],
    "wof:name":"In-Data",
    "wof:placetype":"venue"
},
  "geometry": {"coordinates":[12.542974472,55.7930526733],"type":"Point"}
}