{
  "type": "Feature",
  "properties": {
    "addr:full":"Kors\u00f8rvej 4 Fuglebjerg Danmark 4250",
    "addr:housenumber":"4",
    "addr:postcode":"4250",
    "addr:street":"Korsorvej",
    "iso:country":"DK",
    "sg:address":"Kors\u00f8rvej 4",
    "sg:city":"Fuglebjerg",
    "sg:orig_category":"Garn",
    "sg:phone":"+45 55 45 48 38",
    "sg:postcode":"4250",
    "sg:province":"Danmark",
    "sg:website":"www.karen-becker.dk",
    "wof:name":"Becker, Karen",
    "wof:placetype":"venue"
},
  "geometry": {"coordinates":[11.5467453003,55.3060951233],"type":"Point"}
}