{
  "type": "Feature",
  "properties": {
    "addr:full":"Vestergade 25 Helsinge Danmark 3200",
    "addr:housenumber":"25",
    "addr:postcode":"3200",
    "addr:street":"Vestergade",
    "iso:country":"DK",
    "sg:address":"Vestergade 25",
    "sg:city":"Helsinge",
    "sg:orig_category":"Tegnere og tegnestuer",
    "sg:phone":"+45 48 79 77 76",
    "sg:postcode":"3200",
    "sg:province":"Danmark",
    "wof:name":"PC-illustration & reklame ApS",
    "wof:placetype":"venue"
},
  "geometry": {"coordinates":[12.1935367584,56.0223579407],"type":"Point"}
}