{
  "type": "Feature",
  "properties": {
    "addr:full":"Rolighedsvej 23 D Frederiksberg Danmark 1958",
    "addr:housenumber":"23 d;1958",
    "addr:street":"Rolighedsvej",
    "iso:country":"DK",
    "sg:address":"Rolighedsvej 23 D",
    "sg:city":"Frederiksberg",
    "sg:orig_category":"Puljeinstitutioner",
    "sg:phone":"+45 35 36 16 36",
    "sg:postcode":"1958",
    "sg:province":"Danmark",
    "wof:name":"KVL's B\u00f8rnehus",
    "wof:placetype":"venue"
},
  "geometry": {"coordinates":[12.5429925919,55.6844596863],"type":"Point"}
}