{
  "type": "Feature",
  "properties": {
    "addr:full":"Steng\u00e5rds Alle 109 Kongens Lyngby Danmark 2800",
    "addr:housenumber":"109",
    "addr:postcode":"2800",
    "addr:street":"Stengaards Alle",
    "iso:country":"DK",
    "sg:address":"Steng\u00e5rds Alle 109",
    "sg:city":"Kongens Lyngby",
    "sg:orig_category":"Sprogskoler",
    "sg:phone":"+45 44 44 99 62",
    "sg:postcode":"2800",
    "sg:province":"Danmark",
    "sg:website":"www.villarosprog.dk",
    "wof:name":"Villaro Sprog",
    "wof:placetype":"venue"
},
  "geometry": {"coordinates":[12.4835634232,55.755355835],"type":"Point"}
}