{
  "type": "Feature",
  "properties": {
    "addr:full":"Nordskr\u00e6nten 9 Kokkedal Danmark 2980",
    "addr:housenumber":"9",
    "addr:postcode":"2980",
    "addr:street":"Nordskraenten",
    "iso:country":"DK",
    "sg:address":"Nordskr\u00e6nten 9",
    "sg:city":"Kokkedal",
    "sg:orig_category":"Musikere",
    "sg:phone":"+45 45 86 70 16",
    "sg:postcode":"2980",
    "sg:province":"Danmark",
    "wof:name":"Testrup, Alice",
    "wof:placetype":"venue"
},
  "geometry": {"coordinates":[12.4769096375,55.9091339111],"type":"Point"}
}