{
  "type": "Feature",
  "properties": {
    "addr:full":"Frederikssundsvej 128 H Br\u00f8nsh\u00f8j Danmark 2700",
    "addr:housenumber":"128 h",
    "addr:postcode":"2700",
    "addr:street":"Frederikssundsvej;Danmark",
    "iso:country":"DK",
    "sg:address":"Frederikssundsvej 128 H",
    "sg:city":"Br\u00f8nsh\u00f8j",
    "sg:orig_category":"Antikvariater",
    "sg:phone":"+45 38 60 09 92",
    "sg:postcode":"2700",
    "sg:province":"Danmark",
    "wof:name":"Br\u00f8nsh\u00f8j Antikvariat",
    "wof:placetype":"venue"
},
  "geometry": {"coordinates":[-65.6866531372,-23.1981296539],"type":"Point"}
}