{
  "type": "Feature",
  "properties": {
    "addr:full":"Hovedgaden 53 H\u00f8rsholm Danmark 2970",
    "addr:housenumber":"53",
    "addr:postcode":"2970",
    "addr:street":"Hovedgaden",
    "iso:country":"DK",
    "sg:address":"Hovedgaden 53",
    "sg:city":"H\u00f8rsholm",
    "sg:orig_category":"Belysning",
    "sg:phone":"+45 45 76 68 86",
    "sg:postcode":"2970",
    "sg:province":"Danmark",
    "wof:name":"Lysmesteren",
    "wof:placetype":"venue"
},
  "geometry": {"coordinates":[9.25555,54.937569],"type":"Point"}
}