{
  "type": "Feature",
  "properties": {
    "addr:full":"Peter Willemoes Vej 81 Odense S\u00d8 Danmark 5220",
    "addr:housenumber":"81",
    "addr:postcode":"5220",
    "addr:street":"Peter Willemoes Vej",
    "iso:country":"DK",
    "sg:address":"Peter Willemoes Vej 81",
    "sg:city":"Odense S\u00d8",
    "sg:orig_category":"Skovbrug",
    "sg:phone":"+45 20 47 52 27",
    "sg:postcode":"5220",
    "sg:province":"Danmark",
    "wof:name":"Bo's Skovservice",
    "wof:placetype":"venue"
},
  "geometry": {"coordinates":[10.4498443604,55.38697052],"type":"Point"}
}