{
  "type": "Feature",
  "properties": {
    "addr:full":"Gammel Roskildevej 1B \u00d8lstykke Danmark 3650",
    "addr:housenumber":"1b",
    "addr:postcode":"3650",
    "addr:street":"Gammel Roskildevej",
    "iso:country":"DK",
    "sg:address":"Gammel Roskildevej 1B",
    "sg:city":"\u00d8lstykke",
    "sg:orig_category":"Servicestationer",
    "sg:phone":"+45 47 17 81 95",
    "sg:postcode":"3650",
    "sg:province":"Danmark",
    "wof:name":"Shell Service",
    "wof:placetype":"venue"
},
  "geometry": {"coordinates":[12.2043600082,48.5182304382],"type":"Point"}
}