{
  "type": "Feature",
  "properties": {
    "iso:country":"DK",
    "sg:address":"Industrivej Syd 3",
    "sg:city":"Vejen",
    "sg:orig_category":"Bilinspektion",
    "sg:phone":"+45 75 36 36 77",
    "sg:postcode":"6600",
    "sg:province":"Danmark",
    "sg:website":"www.bilsyn.dk",
    "wof:name":"Statens Bilinspektion",
    "wof:placetype":"venue"
},
  "geometry": {"coordinates":[9.15863,55.471817],"type":"Point"}
}