{
  "type": "Feature",
  "properties": {
    "iso:country":"DK",
    "sg:address":"Metalbuen 5",
    "sg:city":"Ballerup",
    "sg:orig_category":"Sengeudstyr",
    "sg:phone":"+45 44 65 99 62",
    "sg:postcode":"2750",
    "sg:province":"Danmark",
    "wof:name":"Jysk Senget\u00f8jslager A/S",
    "wof:placetype":"venue"
},
  "geometry": {"coordinates":[12.387516,55.725891],"type":"Point"}
}