{
  "type": "Feature",
  "properties": {
    "addr:full":"Ingeni\u00f8rv. 10  Sommersted Danmark 6560",
    "addr:housenumber":"10",
    "addr:postcode":"6560",
    "addr:street":"Ingeniorv.",
    "iso:country":"DK",
    "sg:address":"Ingeni\u00f8rv. 10 ",
    "sg:city":"Sommersted",
    "sg:classifiers":[
        {
            "category":"Parking",
            "subcategory":"Lot",
            "type":"Transportation"
        }
    ],
    "sg:phone":"+45 74 50 44 48",
    "sg:postcode":"6560",
    "sg:province":"Danmark",
    "sg:tags":[
        "transport",
        "road"
    ],
    "wof:name":"TORBEN RAFN & CO A/S",
    "wof:placetype":"venue"
},
  "geometry": {"coordinates":[9.2896709442,55.3161659241],"type":"Point"}
}