{
  "type": "Feature",
  "properties": {
    "addr:full":"Overdrevsvejen 114, Lellinge K\u00f8ge Danmark 4600",
    "addr:housenumber":"114",
    "addr:postcode":"4600",
    "addr:street":"Overdrevsvejen;Lellinge Koge Danmark",
    "iso:country":"DK",
    "sg:address":"Overdrevsvejen 114, Lellinge",
    "sg:city":"K\u00f8ge",
    "sg:orig_category":"Foder",
    "sg:phone":"+45 56 86 10 45",
    "sg:postcode":"4600",
    "sg:province":"Danmark",
    "sg:website":"luup-jensen.subnet.dk",
    "wof:name":"Skovlund",
    "wof:placetype":"venue"
},
  "geometry": {"coordinates":[12.2430353165,55.4170417786],"type":"Point"}
}