{
  "type": "Feature",
  "properties": {
    "iso:country":"DK",
    "sg:address":"Byleddet 2",
    "sg:city":"Roskilde",
    "sg:orig_category":"Blikkenslagere",
    "sg:phone":"+45 46 35 10 78",
    "sg:postcode":"4000",
    "sg:province":"Danmark",
    "wof:name":"Blico VVS",
    "wof:placetype":"venue"
},
  "geometry": {"coordinates":[12.108881,55.643482],"type":"Point"}
}