{
  "type": "Feature",
  "properties": {
    "addr:full":"Kirkegade 13 B Lem Danmark 6940",
    "addr:housenumber":"13 b",
    "addr:postcode":"6940",
    "addr:street":"Kirkegade",
    "iso:country":"DK",
    "sg:address":"Kirkegade 13 B",
    "sg:city":"Lem",
    "sg:orig_category":"Kirker",
    "sg:postcode":"6940",
    "sg:province":"Danmark",
    "wof:name":"Lem Sydsogns kirke",
    "wof:placetype":"venue"
},
  "geometry": {"coordinates":[8.3872022629,56.027256012],"type":"Point"}
}