{
  "type": "Feature",
  "properties": {
    "addr:full":"Ryesgade 19 C K\u00f8benhavn N Danmark 2200",
    "addr:housenumber":"19 c",
    "addr:postcode":"2200",
    "addr:street":"Ryesgade;Kobenhavn N Danmark",
    "iso:country":"DK",
    "sg:address":"Ryesgade 19 C",
    "sg:city":"K\u00f8benhavn N",
    "sg:orig_category":"Fotografer",
    "sg:phone":"+45 35 36 38 96",
    "sg:postcode":"2200",
    "sg:province":"Danmark",
    "sg:website":"www.michaeldaugaard.dk",
    "wof:name":"Daugaard, Michael",
    "wof:placetype":"venue"
},
  "geometry": {"coordinates":[-73.825302124,43.7269515991],"type":"Point"}
}