{
  "type": "Feature",
  "properties": {
    "addr:full":"Christian X's Alle 95 Kongens Lyngby Danmark 2800",
    "addr:housenumber":"95",
    "addr:postcode":"2800",
    "addr:street":"Christian X'S Alle",
    "iso:country":"DK",
    "sg:address":"Christian X's Alle 95",
    "sg:city":"Kongens Lyngby",
    "sg:orig_category":"Voksenuddannelsescentre",
    "sg:phone":"+45 70 25 09 09",
    "sg:postcode":"2800",
    "sg:province":"Danmark",
    "sg:website":"www.oresund-vuc.dk",
    "wof:name":"VUC \u00d8resund",
    "wof:placetype":"venue"
},
  "geometry": {"coordinates":[12.5047941208,55.7639045715],"type":"Point"}
}