{
  "type": "Feature",
  "properties": {
    "addr:full":"Ny Munkegade 1 A \u00c5rhus C Danmark 8000",
    "addr:housenumber":"1 a",
    "addr:postcode":"8000",
    "addr:street":"Munkegade",
    "iso:country":"DK",
    "sg:address":"Ny Munkegade 1 A",
    "sg:city":"\u00c5rhus C",
    "sg:orig_category":"Broderi",
    "sg:phone":"+45 86 12 22 44",
    "sg:postcode":"8000",
    "sg:province":"Danmark",
    "wof:name":"Broderi Moderne",
    "wof:placetype":"venue"
},
  "geometry": {"coordinates":[-76.50189208979999,42.8563194275],"type":"Point"}
}