{
  "type": "Feature",
  "properties": {
    "addr:full":"Smakkeg\u00e5rdsvej 78 Gentofte Danmark 2820",
    "addr:housenumber":"78",
    "addr:postcode":"2820",
    "addr:street":"Smakkegaardsvej",
    "iso:country":"DK",
    "sg:address":"Smakkeg\u00e5rdsvej 78",
    "sg:city":"Gentofte",
    "sg:orig_category":"Spedition",
    "sg:phone":"+45 39 65 53 53",
    "sg:postcode":"2820",
    "sg:province":"Danmark",
    "wof:name":"Bagger Spedition ApS, B.",
    "wof:placetype":"venue"
},
  "geometry": {"coordinates":[12.5292472839,55.7595367432],"type":"Point"}
}