{
  "type": "Feature",
  "properties": {
    "iso:country":"DK",
    "sg:address":"Sct. Laurentii Vej 19 A",
    "sg:city":"Skagen",
    "sg:orig_category":"Helsekost",
    "sg:phone":"+45 98 44 30 37",
    "sg:postcode":"9990",
    "sg:province":"Danmark",
    "wof:name":"Helsam",
    "wof:placetype":"venue"
},
  "geometry": {"coordinates":[10.5950117111,57.7242202759],"type":"Point"}
}