{
  "type": "Feature",
  "properties": {
    "iso:country":"DK",
    "sg:address":"v/ Erik Aagaard Jensen, Solv\u00e6nget 12",
    "sg:city":"Kongens Lyngby",
    "sg:orig_category":"Hobbybetonede foreninger",
    "sg:phone":"+45 45 87 21 99",
    "sg:postcode":"2800",
    "sg:province":"Danmark",
    "sg:website":"la.globe.dk",
    "wof:name":"Lyngby Akvarieforening",
    "wof:placetype":"venue"
},
  "geometry": {"coordinates":[12.5368299484,55.7949905396],"type":"Point"}
}