{
  "type": "Feature",
  "properties": {
    "addr:full":"Fmd.: J\u00f8rgen Larsen, Frydsvej 55 Horsens Danmark 8700",
    "addr:housenumber":"55",
    "addr:postcode":"8700",
    "addr:street":"Frydsvej",
    "iso:country":"DK",
    "sg:address":"Fmd.: J\u00f8rgen Larsen, Frydsvej 55",
    "sg:city":"Horsens",
    "sg:orig_category":"Hobbybetonede foreninger",
    "sg:phone":"+45 75 61 61 63",
    "sg:postcode":"8700",
    "sg:province":"Danmark",
    "wof:name":"Skanderborg-Kredsen Kaninavlerforening",
    "wof:placetype":"venue"
},
  "geometry": {"coordinates":[9.8432445526,55.8621063232],"type":"Point"}
}