{
  "type": "Feature",
  "properties": {
    "addr:full":"Tingvej 40 Hornslet Danmark 8543",
    "addr:housenumber":"40",
    "addr:postcode":"8543",
    "addr:street":"Tingvej",
    "iso:country":"DK",
    "sg:address":"Tingvej 40",
    "sg:city":"Hornslet",
    "sg:orig_category":"Arkitekter",
    "sg:phone":"+45 86 97 51 80",
    "sg:postcode":"8543",
    "sg:province":"Danmark",
    "wof:name":"AE Tegnestuen",
    "wof:placetype":"venue"
},
  "geometry": {"coordinates":[10.3124637604,56.3199882507],"type":"Point"}
}