{
  "type": "Feature",
  "properties": {
    "addr:full":"Vesterbro 42 Odense C Danmark 5000",
    "addr:housenumber":"42",
    "addr:postcode":"5000",
    "addr:street":"Vesterbro",
    "iso:country":"DK",
    "sg:address":"Vesterbro 42",
    "sg:city":"Odense C",
    "sg:classifiers":[
        {
            "category":"Home & Garden",
            "subcategory":"Home Furnishings",
            "type":"Retail Goods"
        }
    ],
    "sg:phone":"+45 66 12 59 42",
    "sg:postcode":"5000",
    "sg:province":"Danmark",
    "sg:tags":[
        "gardiner"
    ],
    "wof:name":"Aagaard Gardiner",
    "wof:placetype":"venue"
},
  "geometry": {"coordinates":[10.3769254684,55.3937034607],"type":"Point"}
}