{
  "type": "Feature",
  "properties": {
    "iso:country":"DK",
    "sg:address":"Vestergade 13",
    "sg:city":"Vojens",
    "sg:orig_category":"Bodegaer",
    "sg:phone":"+45 74 54 30 43",
    "sg:postcode":"6500",
    "sg:province":"Danmark",
    "wof:name":"Vojens bodega",
    "wof:placetype":"venue"
},
  "geometry": {"coordinates":[9.2980298996,55.2464866638],"type":"Point"}
}