{
  "type": "Feature",
  "properties": {
    "addr:full":"Halsvej 70 Vodskov Danmark 9310",
    "addr:housenumber":"70",
    "addr:postcode":"9310",
    "addr:street":"Halsvej",
    "iso:country":"DK",
    "sg:address":"Halsvej 70",
    "sg:city":"Vodskov",
    "sg:orig_category":"Lossepladser",
    "sg:phone":"+45 98 29 23 30",
    "sg:postcode":"9310",
    "sg:province":"Danmark",
    "wof:name":"R\u00e6rup Kontrollerede Losseplads",
    "wof:placetype":"venue"
},
  "geometry": {"coordinates":[10.0432395935,57.0888900757],"type":"Point"}
}