{
  "type": "Feature",
  "properties": {
    "addr:full":"Horskildevej 6 Sorring Danmark 8641",
    "addr:housenumber":"6",
    "addr:postcode":"8641",
    "addr:street":"Horskildevej",
    "iso:country":"DK",
    "sg:address":"Horskildevej 6",
    "sg:city":"Sorring",
    "sg:orig_category":"Zoneterapeuter",
    "sg:phone":"+45 86 95 73 12",
    "sg:postcode":"8641",
    "sg:province":"Danmark",
    "wof:name":"Madsen, Tove",
    "wof:placetype":"venue"
},
  "geometry": {"coordinates":[9.8011140823,56.1754379272],"type":"Point"}
}