{
  "type": "Feature",
  "properties": {
    "iso:country":"DK",
    "sg:address":"Industrivej 18 B",
    "sg:city":"Aabybro",
    "sg:orig_category":"Skilte",
    "sg:phone":"+45 98 24 20 51",
    "sg:postcode":"9440",
    "sg:province":"Danmark",
    "sg:website":"www.bbskilte.dk",
    "wof:name":"B. B. Skilte",
    "wof:placetype":"venue"
},
  "geometry": {"coordinates":[9.7447452545,57.1539878845],"type":"Point"}
}