{
  "type": "Feature",
  "properties": {
    "addr:full":"D\u00f8esvej 5 Holstebro Danmark 7500",
    "addr:housenumber":"5",
    "addr:postcode":"7500",
    "addr:street":"Doesvej",
    "iso:country":"DK",
    "sg:address":"D\u00f8esvej 5",
    "sg:city":"Holstebro",
    "sg:orig_category":"Tandklinikker, Kommunale",
    "sg:phone":"+45 96 11 67 09",
    "sg:postcode":"7500",
    "sg:province":"Danmark",
    "wof:name":"Tandklinikken v/ N\u00f8rrelandsskolen",
    "wof:placetype":"venue"
},
  "geometry": {"coordinates":[8.6099338531,56.3645629883],"type":"Point"}
}