{
  "type": "Feature",
  "properties": {
    "addr:full":"Nygade 5 Aabenraa Danmark 6200",
    "addr:housenumber":"5",
    "addr:postcode":"6200",
    "addr:street":"Nygade",
    "iso:country":"DK",
    "sg:address":"Nygade 5",
    "sg:city":"Aabenraa",
    "sg:orig_category":"Sprogcentre",
    "sg:phone":"+45 74 62 62 86",
    "sg:postcode":"6200",
    "sg:province":"Danmark",
    "wof:name":"AOF Sprogcenter Aabenraa/T\u00f8nder",
    "wof:placetype":"venue"
},
  "geometry": {"coordinates":[9.4162225723,55.0415534973],"type":"Point"}
}