{
  "type": "Feature",
  "properties": {
    "addr:full":"Risingsvej 61 Odense C Danmark 5000",
    "addr:housenumber":"61",
    "addr:postcode":"5000",
    "addr:street":"Risingsvej",
    "iso:country":"DK",
    "sg:address":"Risingsvej 61",
    "sg:city":"Odense C",
    "sg:orig_category":"Mobiltelefoner",
    "sg:phone":"+45 72 12 46 00",
    "sg:postcode":"5000",
    "sg:province":"Danmark",
    "wof:name":"Sonofon",
    "wof:placetype":"venue"
},
  "geometry": {"coordinates":[10.4244804382,55.4058418274],"type":"Point"}
}