{
  "type": "Feature",
  "properties": {
    "addr:full":"Dalgas Alle 16 Skive Danmark 7800",
    "addr:housenumber":"16",
    "addr:postcode":"7800",
    "addr:street":"Dalgas Alle",
    "iso:country":"DK",
    "sg:address":"Dalgas Alle 16",
    "sg:city":"Skive",
    "sg:orig_category":"Kiosker",
    "sg:phone":"+45 97 52 34 67",
    "sg:postcode":"7800",
    "sg:province":"Danmark",
    "wof:name":"Dalgas Kiosk",
    "wof:placetype":"venue"
},
  "geometry": {"coordinates":[9.0144166946,56.5545959473],"type":"Point"}
}