{
  "type": "Feature",
  "properties": {
    "addr:full":"N\u00e6stved Landevej 626, Venslev Rude Danmark 4243",
    "addr:housenumber":"626",
    "addr:postcode":"4243",
    "addr:street":"Naestved Landevej;Venslev",
    "iso:country":"DK",
    "sg:address":"N\u00e6stved Landevej 626, Venslev",
    "sg:city":"Rude",
    "sg:orig_category":"Integrerede institutioner",
    "sg:phone":"+45 55 45 96 41",
    "sg:postcode":"4243",
    "sg:province":"Danmark",
    "wof:name":"Kirkeskoven",
    "wof:placetype":"venue"
},
  "geometry": {"coordinates":[11.4970302582,55.2066993713],"type":"Point"}
}