{
  "type": "Feature",
  "properties": {
    "addr:full":"Ivar Lundgaards Vej 6, M\u00e5bjerg Holstebro Danmark 7500",
    "addr:housenumber":"6",
    "addr:postcode":"7500",
    "addr:street":"Ivar Lundgaards Vej",
    "iso:country":"DK",
    "sg:address":"Ivar Lundgaards Vej 6, M\u00e5bjerg",
    "sg:city":"Holstebro",
    "sg:orig_category":"Murermestre",
    "sg:phone":"+45 97 42 87 44",
    "sg:postcode":"7500",
    "sg:province":"Danmark",
    "wof:name":"Degn Holstebro ApS, Entrepren\u00f8rfirmaet Ove",
    "wof:placetype":"venue"
},
  "geometry": {"coordinates":[8.6202583313,56.3625221252],"type":"Point"}
}