{
  "type": "Feature",
  "properties": {
    "iso:country":"DK",
    "sg:address":"Havnen 2",
    "sg:city":"Skive",
    "sg:orig_category":"Korn og foderstoffer",
    "sg:phone":"+45 97 52 44 33",
    "sg:postcode":"7800",
    "sg:province":"Danmark",
    "wof:name":"DLG Dansk Landbrugs Grovvareselskab",
    "wof:placetype":"venue"
},
  "geometry": {"coordinates":[9.0289306641,56.569896698],"type":"Point"}
}