{
  "type": "Feature",
  "properties": {
    "addr:full":"Allegade 23 Frederiksberg Danmark 2000",
    "addr:housenumber":"23",
    "addr:postcode":"2000",
    "addr:street":"Allegade",
    "iso:country":"DK",
    "sg:address":"Allegade 23",
    "sg:city":"Frederiksberg",
    "sg:orig_category":"Bogtrykkerier",
    "sg:phone":"+45 38 33 30 12",
    "sg:postcode":"2000",
    "sg:province":"Danmark",
    "wof:name":"\u00c5-R Reklametryk ApS",
    "wof:placetype":"venue"
},
  "geometry": {"coordinates":[12.5319719315,55.6769943237],"type":"Point"}
}