{
  "type": "Feature",
  "properties": {
    "addr:full":"Ellehammersvej 4 Kolding Danmark 6000",
    "addr:housenumber":"4",
    "addr:postcode":"6000",
    "addr:street":"Ellehammersvej",
    "iso:country":"DK",
    "sg:address":"Ellehammersvej 4",
    "sg:city":"Kolding",
    "sg:orig_category":"Databehandling",
    "sg:phone":"+45 75 54 25 24",
    "sg:postcode":"6000",
    "sg:province":"Danmark",
    "wof:name":"BSF-Consult",
    "wof:placetype":"venue"
},
  "geometry": {"coordinates":[9.4591121674,55.5092506409],"type":"Point"}
}