{
  "type": "Feature",
  "properties": {
    "addr:full":"Lindelyvej 1, Nr. S\u00f8by \u00c5rslev Danmark 5792",
    "addr:housenumber":"1",
    "addr:postcode":"5792",
    "addr:street":"Lindelyvej;Nr. Soby Aarslev Danmark",
    "iso:country":"DK",
    "sg:address":"Lindelyvej 1, Nr. S\u00f8by",
    "sg:city":"\u00c5rslev",
    "sg:orig_category":"Faglige organisationer og -foreninger",
    "sg:phone":"+45 65 90 14 33",
    "sg:postcode":"5792",
    "sg:province":"Danmark",
    "sg:website":"www.el-bolig.dk",
    "wof:name":"Ejendomsm\u00e6glernes Landsorganisation, EL",
    "wof:placetype":"venue"
},
  "geometry": {"coordinates":[166.9221496582,-0.5282999873],"type":"Point"}
}