{
  "type": "Feature",
  "properties": {
    "addr:full":"Egholmsvej 5 D Virum Danmark 2830",
    "addr:housenumber":"5 d",
    "addr:postcode":"2830",
    "addr:street":"Egholmsvej",
    "iso:country":"DK",
    "sg:address":"Egholmsvej 5 D",
    "sg:city":"Virum",
    "sg:orig_category":"Psykoterapi",
    "sg:phone":"+45 45 83 35 83",
    "sg:postcode":"2830",
    "sg:province":"Danmark",
    "wof:name":"B\u00e6rentzen & Schultz I/S",
    "wof:placetype":"venue"
},
  "geometry": {"coordinates":[12.4710159302,55.8010215759],"type":"Point"}
}