{
  "type": "Feature",
  "properties": {
    "addr:full":"Tavlundsvej 66 Mesinge Danmark 5370",
    "addr:housenumber":"66",
    "addr:postcode":"5370",
    "addr:street":"Tavlundsvej",
    "iso:country":"DK",
    "sg:address":"Tavlundsvej 66",
    "sg:city":"Mesinge",
    "sg:orig_category":"Haveservice",
    "sg:phone":"+45 65 34 26 24",
    "sg:postcode":"5370",
    "sg:province":"Danmark",
    "wof:name":"MHS Service",
    "wof:placetype":"venue"
},
  "geometry": {"coordinates":[10.6568136215,55.5020904541],"type":"Point"}
}