{
  "type": "Feature",
  "properties": {
    "addr:full":"Vestbyen 4 Fars\u00f8 Danmark 9640",
    "addr:housenumber":"4",
    "addr:postcode":"9640",
    "addr:street":"Vestbyen",
    "iso:country":"DK",
    "sg:address":"Vestbyen 4",
    "sg:city":"Fars\u00f8",
    "sg:orig_category":"Haveservice",
    "sg:phone":"+45 98 63 20 77",
    "sg:postcode":"9640",
    "sg:province":"Danmark",
    "wof:name":"RCS Service",
    "wof:placetype":"venue"
},
  "geometry": {"coordinates":[-109.3746795654,42.1460418701],"type":"Point"}
}