{
  "type": "Feature",
  "properties": {
    "addr:full":"Amagerbrogade 30 K\u00f8benhavn S Danmark 2300",
    "addr:housenumber":"30",
    "addr:postcode":"2300",
    "addr:street":"Amagerbrogade;S Danmark",
    "iso:country":"DK",
    "sg:address":"Amagerbrogade 30",
    "sg:city":"K\u00f8benhavn S",
    "sg:orig_category":"Mobiltelefoner",
    "sg:phone":"+45 32 57 01 01",
    "sg:postcode":"2300",
    "sg:province":"Danmark",
    "wof:name":"Tele Amager",
    "wof:placetype":"venue"
},
  "geometry": {"coordinates":[-82.4886169434,38.4966163635],"type":"Point"}
}