{
  "type": "Feature",
  "properties": {
    "addr:full":"Sct. Mathias Gade 48 Viborg Danmark 8800",
    "addr:housenumber":"48",
    "addr:postcode":"8800",
    "addr:street":"Sct. Mathias Gade",
    "iso:country":"DK",
    "sg:address":"Sct. Mathias Gade 48",
    "sg:city":"Viborg",
    "sg:classifiers":[
        {
            "category":"Restaurant",
            "type":"Food & Drink"
        }
    ],
    "sg:phone":"+45 86 62 02 73",
    "sg:postcode":"8800",
    "sg:province":"Danmark",
    "wof:name":"Messing Jens",
    "wof:placetype":"venue"
},
  "geometry": {"coordinates":[9.4060325623,56.4490852356],"type":"Point"}
}