{
  "type": "Feature",
  "properties": {
    "addr:full":"Nordskr\u00e6nten 20 Kokkedal Danmark 2980",
    "addr:housenumber":"20",
    "addr:postcode":"2980",
    "addr:street":"Nordskraenten",
    "iso:country":"DK",
    "sg:address":"Nordskr\u00e6nten 20",
    "sg:city":"Kokkedal",
    "sg:orig_category":"Fodplejere",
    "sg:phone":"+45 45 86 25 29",
    "sg:postcode":"2980",
    "sg:province":"Danmark",
    "wof:name":"Schi\u00f8nning, Hulda",
    "wof:placetype":"venue"
},
  "geometry": {"coordinates":[12.4769096375,55.9091339111],"type":"Point"}
}