{
  "type": "Feature",
  "properties": {
    "iso:country":"DK",
    "sg:address":"Padborgvej 99, Smedeby",
    "sg:city":"Krus\u00e5",
    "sg:orig_category":"Hudpleje",
    "sg:phone":"+45 74 67 25 26",
    "sg:postcode":"6340",
    "sg:province":"Danmark",
    "wof:name":"Vollertsen, Jonna",
    "wof:placetype":"venue"
},
  "geometry": {"coordinates":[-122.1739120483,48.0999107361],"type":"Point"}
}