{
  "type": "Feature",
  "properties": {
    "iso:country":"DK",
    "sg:address":"Stratusv. 9 ",
    "sg:city":"Billund",
    "sg:classifiers":[
        {
            "category":"Manufacturing",
            "subcategory":"Aerospace",
            "type":"Manufacturing & Wholesale Goods"
        }
    ],
    "sg:phone":"+45 79 50 80 30",
    "sg:postcode":"7190",
    "sg:province":"Danmark",
    "sg:tags":[
        "aeronautic"
    ],
    "wof:name":"GP & C GLOBAL SUPPORT APS",
    "wof:placetype":"venue"
},
  "geometry": {"coordinates":[9.149805069,55.7352142334],"type":"Point"}
}