{
  "type": "Feature",
  "properties": {
    "addr:full":"Storegade 43 Hadsund Danmark 9560",
    "addr:housenumber":"43",
    "addr:postcode":"9560",
    "addr:street":"Storegade",
    "iso:country":"DK",
    "sg:address":"Storegade 43",
    "sg:city":"Hadsund",
    "sg:orig_category":"Sportsartikler",
    "sg:phone":"+45 98 57 23 22",
    "sg:postcode":"9560",
    "sg:province":"Danmark",
    "wof:name":"Top Sport",
    "wof:placetype":"venue"
},
  "geometry": {"coordinates":[10.115111351,56.7177505493],"type":"Point"}
}