{
  "type": "Feature",
  "properties": {
    "iso:country":"DK",
    "sg:address":"Gl. Tungelundvej 9 C",
    "sg:city":"Thors\u00f8",
    "sg:orig_category":"Badeanstalter",
    "sg:phone":"+45 23 67 97 76",
    "sg:postcode":"8881",
    "sg:province":"Danmark",
    "wof:name":"Tungelund Badet",
    "wof:placetype":"venue"
},
  "geometry": {"coordinates":[-86.715935,32.916103],"type":"Point"}
}