{
  "type": "Feature",
  "properties": {
    "addr:full":"Vejenvej 50, Askov Vejen Danmark 6600",
    "addr:housenumber":"50",
    "addr:postcode":"6600",
    "addr:street":"Vejenvej;Askov",
    "iso:country":"DK",
    "sg:address":"Vejenvej 50, Askov",
    "sg:city":"Vejen",
    "sg:orig_category":"Fejemaskiner",
    "sg:phone":"+45 76 96 22 00",
    "sg:postcode":"6600",
    "sg:province":"Danmark",
    "sg:website":"www.epoke.dk",
    "wof:name":"Epoke A/S",
    "wof:placetype":"venue"
},
  "geometry": {"coordinates":[9.1396121979,55.4778175354],"type":"Point"}
}