{
  "type": "Feature",
  "properties": {
    "iso:country":"DK",
    "sg:address":"Fengersvej 2, 1.",
    "sg:city":"Odense M",
    "sg:orig_category":"Revisorer",
    "sg:phone":"+45 66 11 80 65",
    "sg:postcode":"5230",
    "sg:province":"Danmark",
    "wof:name":"Bruun Bogf\u00f8ring, Lene",
    "wof:placetype":"venue"
},
  "geometry": {"coordinates":[10.3976039886,55.3867073059],"type":"Point"}
}