{
  "type": "Feature",
  "properties": {
    "iso:country":"DK",
    "sg:address":"S\u00f8nder Alle 14 B",
    "sg:city":"\u00c5rhus C",
    "sg:orig_category":"Advokater",
    "sg:phone":"+45 86 12 13 11",
    "sg:postcode":"8000",
    "sg:province":"Danmark",
    "wof:name":"Schouby & Fr\u00f8berg, Advokatfirmaet",
    "wof:placetype":"venue"
},
  "geometry": {"coordinates":[77.2480392456,14.1354398727],"type":"Point"}
}