{
  "type": "Feature",
  "properties": {
    "addr:full":"Gammel K\u00f8ge Landevej 135 Valby Danmark 2500",
    "addr:housenumber":"135",
    "addr:postcode":"2500",
    "addr:street":"Gammel Koge Landevej",
    "iso:country":"DK",
    "sg:address":"Gammel K\u00f8ge Landevej 135",
    "sg:city":"Valby",
    "sg:orig_category":"Musik- og solistbureauer",
    "sg:phone":"+45 70 25 82 00",
    "sg:postcode":"2500",
    "sg:province":"Danmark",
    "sg:website":"www.www.dk",
    "wof:name":"World Wide Management",
    "wof:placetype":"venue"
},
  "geometry": {"coordinates":[12.5032682419,55.6447906494],"type":"Point"}
}