{
  "type": "Feature",
  "properties": {
    "addr:full":"Lavgade 2 Haderslev Danmark 6100",
    "addr:housenumber":"2",
    "addr:postcode":"6100",
    "addr:street":"Lavgade",
    "iso:country":"DK",
    "sg:address":"Lavgade 2",
    "sg:city":"Haderslev",
    "sg:orig_category":"Rejsebureauer",
    "sg:phone":"+45 74 52 62 75",
    "sg:postcode":"6100",
    "sg:province":"Danmark",
    "wof:name":"Euroskan Travel/FDM Partner",
    "wof:placetype":"venue"
},
  "geometry": {"coordinates":[9.487903595,55.2485313416],"type":"Point"}
}