{
  "type": "Feature",
  "properties": {
    "addr:full":"Havnepladsen 5 A Frederikshavn Danmark 9900",
    "addr:housenumber":"5 a",
    "addr:postcode":"9900",
    "addr:street":"Havnepladsen",
    "iso:country":"DK",
    "sg:address":"Havnepladsen 5 A",
    "sg:city":"Frederikshavn",
    "sg:orig_category":"Rejsebureauer",
    "sg:phone":"+45 98 42 78 00",
    "sg:postcode":"9900",
    "sg:province":"Danmark",
    "wof:name":"Samson Travel v/ Hans J. Wellejus",
    "wof:placetype":"venue"
},
  "geometry": {"coordinates":[10.5371828079,57.437625885],"type":"Point"}
}