{
  "type": "Feature",
  "properties": {
    "addr:full":"Slimmingevej 50 Ringsted Danmark 4100",
    "addr:housenumber":"50",
    "addr:postcode":"4100",
    "addr:street":"Slimmingevej",
    "iso:country":"DK",
    "sg:address":"Slimmingevej 50",
    "sg:city":"Ringsted",
    "sg:orig_category":"Flytteforretninger",
    "sg:phone":"+45 20 99 88 81",
    "sg:postcode":"4100",
    "sg:province":"Danmark",
    "wof:name":"K.M.B. Transport & Flyt",
    "wof:placetype":"venue"
},
  "geometry": {"coordinates":[12.0099897385,55.4213790894],"type":"Point"}
}