{
  "type": "Feature",
  "properties": {
    "iso:country":"DK",
    "sg:address":"N\u00f8rremarksvej 32",
    "sg:city":"Klarup",
    "sg:orig_category":"Maskinfabrikker",
    "sg:phone":"+45 98 32 60 66",
    "sg:postcode":"9270",
    "sg:province":"Danmark",
    "wof:name":"Fuglsang A/S, Maskinfabrikken",
    "wof:placetype":"venue"
},
  "geometry": {"coordinates":[10.0522470474,57.0169639587],"type":"Point"}
}