{
  "type": "Feature",
  "properties": {
    "addr:full":"Fmd.: S\u00f8ren Holmberg, Dronning Ingrids Vej 27 \u00d8lstykke Danmark 3650",
    "addr:housenumber":"27",
    "addr:postcode":"3650",
    "addr:street":"Holmberg Dronning Ingrids Vej",
    "iso:country":"DK",
    "sg:address":"Fmd.: S\u00f8ren Holmberg, Dronning Ingrids Vej 27",
    "sg:city":"\u00d8lstykke",
    "sg:orig_category":"Hobbybetonede foreninger",
    "sg:phone":"+45 47 17 48 27",
    "sg:postcode":"3650",
    "sg:province":"Danmark",
    "sg:website":"www.frs-fiskerklub.dk",
    "wof:name":"Frederikssund og Omegns Sportsfiskerforening",
    "wof:placetype":"venue"
},
  "geometry": {"coordinates":[-111.96309661870001,40.6955986023],"type":"Point"}
}