{
  "type": "Feature",
  "properties": {
    "addr:full":"Havnebakken 8, Vester\u00f8 Havn L\u00e6s\u00f8 Danmark 9940",
    "addr:housenumber":"8",
    "addr:postcode":"9940",
    "addr:street":"Havnebakken;Vestero Havn;Danmark",
    "iso:country":"DK",
    "sg:address":"Havnebakken 8, Vester\u00f8 Havn",
    "sg:city":"L\u00e6s\u00f8",
    "sg:orig_category":"HOTELS: OG MOTELLER",
    "sg:phone":"+45 98 49 92 11",
    "sg:postcode":"9940",
    "sg:province":"Danmark",
    "wof:name":"Carlsens Hotel",
    "wof:placetype":"venue"
},
  "geometry": {"coordinates":[-78.1299133301,36.7267417908],"type":"Point"}
}