{
  "type": "Feature",
  "properties": {
    "iso:country":"DK",
    "sg:address":"S\u00f8bredden 27",
    "sg:city":"Gentofte",
    "sg:orig_category":"Korn og foderstoffer",
    "sg:phone":"+45 39 65 18 80",
    "sg:postcode":"2820",
    "sg:province":"Danmark",
    "wof:name":"Brog\u00e5rden Korn & Foderstoffer",
    "wof:placetype":"venue"
},
  "geometry": {"coordinates":[12.526008606,55.7516746521],"type":"Point"}
}