{
  "type": "Feature",
  "properties": {
    "iso:country":"DK",
    "sg:address":"Fjordvangskolen, Regnar Langesvej 1",
    "sg:city":"Kerteminde",
    "sg:orig_category":"Skolefritidsordninger",
    "sg:phone":"+45 65 32 30 52",
    "sg:postcode":"5300",
    "sg:province":"Danmark",
    "wof:name":"Skolefritidsordningen Kompasset",
    "wof:placetype":"venue"
},
  "geometry": {"coordinates":[10.6600999832,55.4506492615],"type":"Point"}
}