{
  "type": "Feature",
  "properties": {
    "addr:full":"Fmd.: Lars Fredslund, Byagervej 20 Br\u00f8rup Danmark 6650",
    "addr:housenumber":"20",
    "addr:postcode":"6650",
    "addr:street":"Byagervej",
    "iso:country":"DK",
    "sg:address":"Fmd.: Lars Fredslund, Byagervej 20",
    "sg:city":"Br\u00f8rup",
    "sg:orig_category":"Loger",
    "sg:phone":"+45 75 38 36 31",
    "sg:postcode":"6650",
    "sg:province":"Danmark",
    "wof:name":"Br\u00f8rup Round Table",
    "wof:placetype":"venue"
},
  "geometry": {"coordinates":[-93.1630935669,32.8507347107],"type":"Point"}
}