{
  "type": "Feature",
  "properties": {
    "addr:full":"\u00d8strigsgade 55 K\u00f8benhavn S Danmark 2300",
    "addr:housenumber":"55",
    "addr:postcode":"2300",
    "addr:street":"Ostrigsgade;Kobenhavn S Danmark",
    "iso:country":"DK",
    "sg:address":"\u00d8strigsgade 55",
    "sg:city":"K\u00f8benhavn S",
    "sg:orig_category":"Chokolade",
    "sg:phone":"+45 32 97 85 94",
    "sg:postcode":"2300",
    "sg:province":"Danmark",
    "wof:name":"Parken Is og Chokolade",
    "wof:placetype":"venue"
},
  "geometry": {"coordinates":[-98.6707077026,48.2092018127],"type":"Point"}
}