{
  "type": "Feature",
  "properties": {
    "iso:country":"DK",
    "sg:address":"Ramsherred 47 B",
    "sg:city":"Aabenraa",
    "sg:orig_category":"Brugskunst",
    "sg:phone":"+45 74 62 23 63",
    "sg:postcode":"6200",
    "sg:province":"Danmark",
    "wof:name":"Gave\u00e6sken",
    "wof:placetype":"venue"
},
  "geometry": {"coordinates":[9.4185323715,55.0453491211],"type":"Point"}
}