{
  "type": "Feature",
  "properties": {
    "iso:country":"DK",
    "sg:address":"Birkevej 15",
    "sg:city":"Engesvang",
    "sg:orig_category":"Integrerede institutioner",
    "sg:phone":"+45 86 86 57 77",
    "sg:postcode":"7442",
    "sg:province":"Danmark",
    "wof:name":"Engesvang Fritidshus",
    "wof:placetype":"venue"
},
  "geometry": {"coordinates":[9.3443632126,56.1721725464],"type":"Point"}
}