{
  "type": "Feature",
  "properties": {
    "addr:full":"B\u00e6kkestr\u00e6de 3, Sandvig Allinge Danmark 3770",
    "addr:housenumber":"3",
    "addr:postcode":"3770",
    "addr:street":"Baekkestraede;Sandvig",
    "iso:country":"DK",
    "sg:address":"B\u00e6kkestr\u00e6de 3, Sandvig",
    "sg:city":"Allinge",
    "sg:orig_category":"Gallerier",
    "sg:phone":"+45 56 48 00 13",
    "sg:postcode":"3770",
    "sg:province":"Danmark",
    "wof:name":"Bl\u00e5 Galleri, Det",
    "wof:placetype":"venue"
},
  "geometry": {"coordinates":[14.7998552322,55.2743835449],"type":"Point"}
}