{
  "type": "Feature",
  "properties": {
    "addr:full":"Katkj\u00e6rvej 2, Lund Skive Danmark 7800",
    "addr:housenumber":"2",
    "addr:postcode":"7800",
    "addr:street":"Katkjaervej",
    "iso:country":"DK",
    "sg:address":"Katkj\u00e6rvej 2, Lund",
    "sg:city":"Skive",
    "sg:orig_category":"Autoforhandlere",
    "sg:phone":"+45 97 51 30 55",
    "sg:postcode":"7800",
    "sg:province":"Danmark",
    "sg:website":"www.skive-autoforum.dk",
    "wof:name":"Skive Autoforum I/S",
    "wof:placetype":"venue"
},
  "geometry": {"coordinates":[9.0320358276,56.5666427612],"type":"Point"}
}