{
  "type": "Feature",
  "properties": {
    "iso:country":"DK",
    "sg:address":"Rolighedsvej 7",
    "sg:city":"Hurup",
    "sg:orig_category":"Revisorer",
    "sg:phone":"+45 97 95 17 11",
    "sg:postcode":"7760",
    "sg:province":"Danmark",
    "wof:name":"ST Revision",
    "wof:placetype":"venue"
},
  "geometry": {"coordinates":[8.4224872589,56.7509803772],"type":"Point"}
}