{
  "type": "Feature",
  "properties": {
    "addr:full":"Baltorpbakken 10 Ballerup Danmark 2750",
    "addr:housenumber":"10",
    "addr:postcode":"2750",
    "addr:street":"Baltorpbakken",
    "iso:country":"DK",
    "sg:address":"Baltorpbakken 10",
    "sg:city":"Ballerup",
    "sg:orig_category":"Autoreservedele",
    "sg:phone":"+45 44 86 68 44",
    "sg:postcode":"2750",
    "sg:province":"Danmark",
    "sg:website":"www.uni-cardan.dk",
    "wof:name":"Dansk Uni-Cardan A/S",
    "wof:placetype":"venue"
},
  "geometry": {"coordinates":[12.3391494751,55.7313804626],"type":"Point"}
}