{
  "type": "Feature",
  "properties": {
    "addr:full":"Vestergade 17 Vissenbjerg Danmark 5492",
    "addr:housenumber":"17",
    "addr:postcode":"5492",
    "addr:street":"Vestergade",
    "iso:country":"DK",
    "sg:address":"Vestergade 17",
    "sg:city":"Vissenbjerg",
    "sg:orig_category":"Zoneterapeuter",
    "sg:phone":"+45 22 12 08 36",
    "sg:postcode":"5492",
    "sg:province":"Danmark",
    "wof:name":"Vissenbjerg Mass\u00f8r/Zoneterapi",
    "wof:placetype":"venue"
},
  "geometry": {"coordinates":[10.1280260086,55.3861427307],"type":"Point"}
}