{
  "type": "Feature",
  "properties": {
    "addr:full":"Fmd.: Keld Dahl, Marievej 9 Aalborg Danmark 9000",
    "addr:housenumber":"9",
    "addr:postcode":"9000",
    "addr:street":"Marievej",
    "iso:country":"DK",
    "sg:address":"Fmd.: Keld Dahl, Marievej 9",
    "sg:city":"Aalborg",
    "sg:orig_category":"Hobbybetonede foreninger",
    "sg:phone":"+45 98 12 23 59",
    "sg:postcode":"9000",
    "sg:province":"Danmark",
    "wof:name":"Nordjysk Radiostyrings Center",
    "wof:placetype":"venue"
},
  "geometry": {"coordinates":[9.9162902832,57.0493545532],"type":"Point"}
}