{
  "type": "Feature",
  "properties": {
    "addr:full":"Kirkeh\u00f8jen 2, Vall\u00f8by K\u00f8ge Danmark 4600",
    "addr:housenumber":"2",
    "addr:postcode":"4600",
    "addr:street":"Kirkehojen",
    "iso:country":"DK",
    "sg:address":"Kirkeh\u00f8jen 2, Vall\u00f8by",
    "sg:city":"K\u00f8ge",
    "sg:orig_category":"Autoreparation og -service",
    "sg:phone":"+45 56 26 61 35",
    "sg:postcode":"4600",
    "sg:province":"Danmark",
    "wof:name":"Ole's Auto",
    "wof:placetype":"venue"
},
  "geometry": {"coordinates":[114.6686172485,37.117401123],"type":"Point"}
}