{
  "type": "Feature",
  "properties": {
    "addr:full":"L\u00e6rkevej 28, Langes\u00f8 Nordborg Danmark 6430",
    "addr:housenumber":"28",
    "addr:postcode":"6430",
    "addr:street":"Laerkevej;Langeso",
    "iso:country":"DK",
    "sg:address":"L\u00e6rkevej 28, Langes\u00f8",
    "sg:city":"Nordborg",
    "sg:orig_category":"Handicapboliger",
    "sg:phone":"+45 74 45 25 41",
    "sg:postcode":"6430",
    "sg:province":"Danmark",
    "wof:name":"Langes\u00f8 Bof\u00e6llesskab",
    "wof:placetype":"venue"
},
  "geometry": {"coordinates":[9.7496232986,55.0542755127],"type":"Point"}
}