{
  "type": "Feature",
  "properties": {
    "addr:full":"Valh\u00f8js Alle 84 B,1.th. R\u00f8dovre Danmark 2610",
    "addr:housenumber":"84 b 1.th",
    "addr:postcode":"2610",
    "addr:street":"Valhojs Alle;Danmark",
    "iso:country":"DK",
    "sg:address":"Valh\u00f8js Alle 84 B,1.th.",
    "sg:city":"R\u00f8dovre",
    "sg:orig_category":"Flytteforretninger",
    "sg:phone":"+45 45 87 71 00",
    "sg:postcode":"2610",
    "sg:province":"Danmark",
    "wof:name":"Prebens Flytteforretning",
    "wof:placetype":"venue"
},
  "geometry": {"coordinates":[10.6992139816,61.1027755737],"type":"Point"}
}