{
  "type": "Feature",
  "properties": {
    "iso:country":"DK",
    "sg:address":"Strandvejen 150, Tranum",
    "sg:city":"Brovst",
    "sg:orig_category":"HOTELS: OG MOTELLER",
    "sg:phone":"+45 70 26 66 56",
    "sg:postcode":"9460",
    "sg:province":"Danmark",
    "wof:name":"FerieHotel Tranum Klit",
    "wof:placetype":"venue"
},
  "geometry": {"coordinates":[9.5220241547,57.097366333],"type":"Point"}
}