{
  "type": "Feature",
  "properties": {
    "addr:full":"Trekanten 1  Vojens Danmark 6500",
    "addr:housenumber":"1",
    "addr:postcode":"6500",
    "addr:street":"Trekanten",
    "iso:country":"DK",
    "sg:address":"Trekanten 1 ",
    "sg:city":"Vojens",
    "sg:classifiers":[
        {
            "category":"Shopping",
            "subcategory":"Computers & Home Electronics",
            "type":"Retail Goods"
        }
    ],
    "sg:phone":"+45 73 24 04 00",
    "sg:postcode":"6500",
    "sg:province":"Danmark",
    "sg:tags":[
        "electronic",
        "electrical",
        "equipment"
    ],
    "wof:name":"SKOUSEN HUSHOLDNINGSMASKINER A/S",
    "wof:placetype":"venue"
},
  "geometry": {"coordinates":[9.3156013489,55.2521362305],"type":"Point"}
}