{
  "type": "Feature",
  "properties": {
    "iso:country":"DK",
    "sg:address":"Per Arnoldi Jensen, Jagtvej 57",
    "sg:city":"K\u00f8benhavn N",
    "sg:orig_category":"Bodegaer",
    "sg:phone":"+45 35 83 62 63",
    "sg:postcode":"2200",
    "sg:province":"Danmark",
    "wof:name":"Juuls Bodega",
    "wof:placetype":"venue"
},
  "geometry": {"coordinates":[-76.4168395996,37.452419281],"type":"Point"}
}