{
  "type": "Feature",
  "properties": {
    "iso:country":"DK",
    "sg:address":"Divisionschef: Marianne Knudsg\u00e5rd, Hollandsvej 13, st. tv.",
    "sg:city":"Kongens Lyngby",
    "sg:orig_category":"Spejderkorps",
    "sg:phone":"+45 45 88 93 72",
    "sg:postcode":"2800",
    "sg:province":"Danmark",
    "wof:name":"KFUK-Spejderne i Danmark, Gentofte Division",
    "wof:placetype":"venue"
},
  "geometry": {"coordinates":[12.5368299484,55.7949905396],"type":"Point"}
}