{
  "type": "Feature",
  "properties": {
    "addr:full":"Herningvej 146 st, tv Ringk\u00f8bing Danmark 6950",
    "addr:housenumber":"146 st",
    "addr:postcode":"6950",
    "addr:street":"Herningvej",
    "iso:country":"DK",
    "sg:address":"Herningvej 146 st, tv",
    "sg:city":"Ringk\u00f8bing",
    "sg:orig_category":"EDB - udstyr",
    "sg:phone":"+45 97 34 35 20",
    "sg:postcode":"6950",
    "sg:province":"Danmark",
    "wof:name":"Vestjysk Medie Engros",
    "wof:placetype":"venue"
},
  "geometry": {"coordinates":[-98.41218566889999,35.2836418152],"type":"Point"}
}