{
  "type": "Feature",
  "properties": {
    "addr:full":"Grupper\u00e5dsfmd.: Lars Rossander S\u00f8rensen, Vestergade 7 Vissenbjerg Danmark 5492",
    "addr:housenumber":"7",
    "addr:postcode":"5492",
    "addr:street":"Vestergade",
    "iso:country":"DK",
    "sg:address":"Grupper\u00e5dsfmd.: Lars Rossander S\u00f8rensen, Vestergade 7",
    "sg:city":"Vissenbjerg",
    "sg:orig_category":"Spejderkorps",
    "sg:phone":"+45 64 47 35 99",
    "sg:postcode":"5492",
    "sg:province":"Danmark",
    "wof:name":"KFUM-spejderne i Vissenbjerg",
    "wof:placetype":"venue"
},
  "geometry": {"coordinates":[10.1324472427,55.386051178],"type":"Point"}
}