{
  "type": "Feature",
  "properties": {
    "addr:full":"Christiansgade 70 Odense C Danmark 5000",
    "addr:housenumber":"70",
    "addr:postcode":"5000",
    "addr:street":"Christiansgade",
    "iso:country":"DK",
    "sg:address":"Christiansgade 70",
    "sg:city":"Odense C",
    "sg:orig_category":"Reklamebureauer",
    "sg:phone":"+45 66 11 27 77",
    "sg:postcode":"5000",
    "sg:province":"Danmark",
    "sg:website":"www.scanad.dk",
    "wof:name":"SCANAD Reklamebureau A/S",
    "wof:placetype":"venue"
},
  "geometry": {"coordinates":[10.4048099518,55.3966674805],"type":"Point"}
}