{
  "type": "Feature",
  "properties": {
    "addr:full":"Backersvej 51 K\u00f8benhavn S Danmark 2300",
    "addr:housenumber":"51",
    "addr:postcode":"2300",
    "addr:street":"Backersvej;Kobenhavn S Danmark",
    "iso:country":"DK",
    "sg:address":"Backersvej 51",
    "sg:city":"K\u00f8benhavn S",
    "sg:classifiers":[
        {
            "category":"Restaurant",
            "type":"Food & Drink"
        }
    ],
    "sg:phone":"+45 32 58 44 26",
    "sg:postcode":"2300",
    "sg:province":"Danmark",
    "wof:name":"Vaaren, Caf\u00e9",
    "wof:placetype":"venue"
},
  "geometry": {"coordinates":[-98.4802474976,36.0598182678],"type":"Point"}
}