{
  "type": "Feature",
  "properties": {
    "addr:full":"Roskildevej 136 Valby Danmark 2500",
    "addr:housenumber":"136",
    "addr:postcode":"2500",
    "addr:street":"Roskildevej",
    "iso:country":"DK",
    "sg:address":"Roskildevej 136",
    "sg:city":"Valby",
    "sg:orig_category":"Kurve",
    "sg:phone":"+45 38 79 30 25",
    "sg:postcode":"2500",
    "sg:province":"Danmark",
    "wof:name":"Kurvehj\u00f8rnet",
    "wof:placetype":"venue"
},
  "geometry": {"coordinates":[12.4911518097,55.6726417542],"type":"Point"}
}