{
  "type": "Feature",
  "properties": {
    "addr:full":"Fmd.: Anne-Mette Vestergaard J\u00f8rgensen, S\u00f8ndergade 38, 1. Nakskov Danmark 4900",
    "addr:housenumber":"38 1",
    "addr:postcode":"4900",
    "addr:street":"Sondergade",
    "iso:country":"DK",
    "sg:address":"Fmd.: Anne-Mette Vestergaard J\u00f8rgensen, S\u00f8ndergade 38, 1.",
    "sg:city":"Nakskov",
    "sg:orig_category":"Kulturelle foreninger",
    "sg:phone":"+45 22 26 52 41",
    "sg:postcode":"4900",
    "sg:province":"Danmark",
    "sg:website":"www.theoffice.net/amvjart",
    "wof:name":"Kunstnergruppen Lukas",
    "wof:placetype":"venue"
},
  "geometry": {"coordinates":[11.1359500885,54.8330116272],"type":"Point"}
}