{
  "type": "Feature",
  "properties": {
    "iso:country":"DK",
    "sg:address":"Fredericiavej 88",
    "sg:city":"Vejle",
    "sg:orig_category":"Revisorer",
    "sg:phone":"+45 75 82 52 11",
    "sg:postcode":"7100",
    "sg:province":"Danmark",
    "sg:website":"www.der-as.dk",
    "wof:name":"Dansk Erhvervs Revision A/S",
    "wof:placetype":"venue"
},
  "geometry": {"coordinates":[9.5487232208,55.6912269592],"type":"Point"}
}