{
  "type": "Feature",
  "properties": {
    "addr:full":"Valby Langgade 127 Valby Danmark 2500",
    "addr:housenumber":"127",
    "addr:postcode":"2500",
    "addr:street":"Valby Langgade",
    "iso:country":"DK",
    "sg:address":"Valby Langgade 127",
    "sg:city":"Valby",
    "sg:classifiers":[
        {
            "category":"Restaurant",
            "type":"Food & Drink"
        }
    ],
    "sg:phone":"+45 36 16 01 60",
    "sg:postcode":"2500",
    "sg:province":"Danmark",
    "wof:name":"Fiorintina Pizza & Grill",
    "wof:placetype":"venue"
},
  "geometry": {"coordinates":[12.5035619736,55.6668167114],"type":"Point"}
}