{
  "type": "Feature",
  "properties": {
    "addr:full":"Bremdalvej 24 Struer Danmark 7600",
    "addr:housenumber":"24",
    "addr:postcode":"7600",
    "addr:street":"Bremdalvej",
    "iso:country":"DK",
    "sg:address":"Bremdalvej 24",
    "sg:city":"Struer",
    "sg:orig_category":"Optikere",
    "sg:phone":"+45 97 85 05 95",
    "sg:postcode":"7600",
    "sg:province":"Danmark",
    "wof:name":"Astrup Optik",
    "wof:placetype":"venue"
},
  "geometry": {"coordinates":[8.582906723,56.5091285706],"type":"Point"}
}