{
  "type": "Feature",
  "properties": {
    "iso:country":"DK",
    "sg:address":"N\u00f8rregade 33",
    "sg:city":"Skive",
    "sg:orig_category":"Bagere",
    "sg:phone":"+45 97 52 12 30",
    "sg:postcode":"7800",
    "sg:province":"Danmark",
    "wof:name":"Hansen Br\u00f8d, Ejdrup",
    "wof:placetype":"venue"
},
  "geometry": {"coordinates":[9.028254,56.57],"type":"Point"}
}