{
  "type": "Feature",
  "properties": {
    "addr:full":"H\u00e5ndv\u00e6rkervej 10 Gislev Danmark 5854",
    "addr:housenumber":"10",
    "addr:postcode":"5854",
    "addr:street":"Haandvaerkervej",
    "iso:country":"DK",
    "sg:address":"H\u00e5ndv\u00e6rkervej 10",
    "sg:city":"Gislev",
    "sg:orig_category":"Servicestationer",
    "sg:phone":"+45 26 96 69 27",
    "sg:postcode":"5854",
    "sg:province":"Danmark",
    "wof:name":"Uno-X",
    "wof:placetype":"venue"
},
  "geometry": {"coordinates":[10.5988063812,55.2191352844],"type":"Point"}
}