{
  "type": "Feature",
  "properties": {
    "iso:country":"DK",
    "sg:address":"Odensevej 50",
    "sg:city":"Ringe",
    "sg:orig_category":"Benzinstationer",
    "sg:phone":"+45 62 62 22 91",
    "sg:postcode":"5750",
    "sg:province":"Danmark",
    "wof:name":"Texaco",
    "wof:placetype":"venue"
},
  "geometry": {"coordinates":[10.476223,55.244701],"type":"Point"}
}