{
  "type": "Feature",
  "properties": {
    "iso:country":"DK",
    "sg:address":"Rugv\u00e6nget 32",
    "sg:city":"Ballerup",
    "sg:orig_category":"Vuggestuer",
    "sg:phone":"+45 44 77 31 91",
    "sg:postcode":"2750",
    "sg:province":"Danmark",
    "wof:name":"Kirstinevang, Vuggestuen",
    "wof:placetype":"venue"
},
  "geometry": {"coordinates":[12.361000061,55.7301216125],"type":"Point"}
}