{
  "type": "Feature",
  "properties": {
    "addr:full":"Dybs\u00f8 Fjordbanke 8 Lundby Danmark 4750",
    "addr:housenumber":"8",
    "addr:postcode":"4750",
    "addr:street":"Dybso Fjordbanke",
    "iso:country":"DK",
    "sg:address":"Dybs\u00f8 Fjordbanke 8",
    "sg:city":"Lundby",
    "sg:orig_category":"Murermestre",
    "sg:phone":"+45 55 76 96 03",
    "sg:postcode":"4750",
    "sg:province":"Danmark",
    "wof:name":"Rasmussen, Hans",
    "wof:placetype":"venue"
},
  "geometry": {"coordinates":[11.8089570999,55.1254806519],"type":"Point"}
}