{
  "type": "Feature",
  "properties": {
    "addr:full":"Birkevej 25, Mejdal Holstebro Danmark 7500",
    "addr:housenumber":"25",
    "addr:postcode":"7500",
    "addr:street":"Birkevej;Mejdal",
    "iso:country":"DK",
    "sg:address":"Birkevej 25, Mejdal",
    "sg:city":"Holstebro",
    "sg:orig_category":"Campingpladser",
    "sg:phone":"+45 97 42 20 68",
    "sg:postcode":"7500",
    "sg:province":"Danmark",
    "wof:name":"DCU Mejdal Camping",
    "wof:placetype":"venue"
},
  "geometry": {"coordinates":[8.6202583313,56.3625221252],"type":"Point"}
}