{
  "type": "Feature",
  "properties": {
    "addr:full":"S\u00f8ndergade 5 Toftlund Danmark 6520",
    "addr:housenumber":"5",
    "addr:postcode":"6520",
    "addr:street":"Sondergade",
    "iso:country":"DK",
    "sg:address":"S\u00f8ndergade 5",
    "sg:city":"Toftlund",
    "sg:orig_category":"Turistbureau og -information",
    "sg:phone":"+45 74 83 11 19",
    "sg:postcode":"6520",
    "sg:province":"Danmark",
    "wof:name":"N\u00f8rre-Rangstrup Turistbureau",
    "wof:placetype":"venue"
},
  "geometry": {"coordinates":[9.0642194748,55.1921272278],"type":"Point"}
}