{
  "type": "Feature",
  "properties": {
    "addr:full":"Havnegade 5 Marstal Danmark 5960",
    "addr:housenumber":"5",
    "addr:postcode":"5960",
    "addr:street":"Havnegade",
    "iso:country":"DK",
    "sg:address":"Havnegade 5",
    "sg:city":"Marstal",
    "sg:orig_category":"Politi",
    "sg:phone":"+45 62 53 14 48",
    "sg:postcode":"5960",
    "sg:province":"Danmark",
    "wof:name":"Marstal Politistation og Politikontor",
    "wof:placetype":"venue"
},
  "geometry": {"coordinates":[10.5203971863,54.8564605713],"type":"Point"}
}