{
  "type": "Feature",
  "properties": {
    "addr:full":"Ostergade  28",
    "addr:housenumber":"28",
    "addr:street":"Ostergade",
    "iso:country":"DK",
    "sg:address":"Ostergade ",
    "sg:classifiers":[
        {
            "category":"Banks & Credit Unions",
            "subcategory":"Bank",
            "type":"Services"
        }
    ],
    "sg:phone":"+45 64 41 20 00",
    "sg:postcode":"28",
    "wof:name":"Unibank A/S",
    "wof:placetype":"venue"
},
  "geometry": {"coordinates":[9.737531,55.503872],"type":"Point"}
}