{
  "type": "Feature",
  "properties": {
    "addr:full":"Byst\u00e6vnevej 30, Ulb\u00f8lle Vester Skerninge Danmark 5762",
    "addr:housenumber":"30",
    "addr:postcode":"5762",
    "addr:street":"Bystaevnevej",
    "iso:country":"DK",
    "sg:address":"Byst\u00e6vnevej 30, Ulb\u00f8lle",
    "sg:city":"Vester Skerninge",
    "sg:orig_category":"Malermestre",
    "sg:phone":"+45 62 24 24 69",
    "sg:postcode":"5762",
    "sg:province":"Danmark",
    "wof:name":"Sydfyns Malerforretning",
    "wof:placetype":"venue"
},
  "geometry": {"coordinates":[10.5008449554,55.070400238],"type":"Point"}
}