{
  "type": "Feature",
  "properties": {
    "addr:full":"H\u00f8jager 92, N\u00e6sby Odense N Danmark 5270",
    "addr:housenumber":"92",
    "addr:postcode":"5270",
    "addr:street":"Hojager;Naesby",
    "iso:country":"DK",
    "sg:address":"H\u00f8jager 92, N\u00e6sby",
    "sg:city":"Odense N",
    "sg:classifiers":[
        {
            "category":"Food & Beverages",
            "subcategory":"Liquor & Beverages",
            "type":"Retail Goods"
        }
    ],
    "sg:phone":"+45 66 18 96 60",
    "sg:postcode":"5270",
    "sg:province":"Danmark",
    "sg:tags":[
        "vin"
    ],
    "wof:name":"Exellent Wine Danmark A/S",
    "wof:placetype":"venue"
},
  "geometry": {"coordinates":[10.3306798935,55.4711418152],"type":"Point"}
}