{
  "type": "Feature",
  "properties": {
    "addr:full":"Vestergade 5 Vamdrup Danmark 6580",
    "addr:housenumber":"5",
    "addr:postcode":"6580",
    "addr:street":"Vestergade",
    "iso:country":"DK",
    "sg:address":"Vestergade 5",
    "sg:city":"Vamdrup",
    "sg:orig_category":"Malermestre",
    "sg:phone":"+45 75 58 22 21",
    "sg:postcode":"6580",
    "sg:province":"Danmark",
    "wof:name":"Schmidt, Bent",
    "wof:placetype":"venue"
},
  "geometry": {"coordinates":[9.281744957,55.42603302],"type":"Point"}
}