{
  "type": "Feature",
  "properties": {
    "addr:full":"Park Alle 18 Struer Danmark 7600",
    "addr:housenumber":"18",
    "addr:postcode":"7600",
    "addr:street":"Park Alle",
    "iso:country":"DK",
    "sg:address":"Park Alle 18",
    "sg:city":"Struer",
    "sg:orig_category":"Kirker",
    "sg:postcode":"7600",
    "sg:province":"Danmark",
    "wof:name":"Voldh\u00f8j Valgmenigheds Kirke",
    "wof:placetype":"venue"
},
  "geometry": {"coordinates":[8.5688667297,56.4816398621],"type":"Point"}
}