{
  "type": "Feature",
  "properties": {
    "iso:country":"DK",
    "sg:address":"Hovedgaden 24",
    "sg:city":"Humble",
    "sg:orig_category":"Supermarkeder",
    "sg:phone":"+45 62 57 11 66",
    "sg:postcode":"5932",
    "sg:province":"Danmark",
    "wof:name":"Aktiv Super",
    "wof:placetype":"venue"
},
  "geometry": {"coordinates":[10.6996860504,54.8280677795],"type":"Point"}
}