{
  "type": "Feature",
  "properties": {
    "addr:full":"Finlandsvej 3, Tved Svendborg Danmark 5700",
    "addr:housenumber":"3",
    "addr:postcode":"5700",
    "addr:street":"Finlandsvej;Tved",
    "iso:country":"DK",
    "sg:address":"Finlandsvej 3, Tved",
    "sg:city":"Svendborg",
    "sg:orig_category":"Glasfiberindustri",
    "sg:phone":"+45 62 21 32 28",
    "sg:postcode":"5700",
    "sg:province":"Danmark",
    "sg:website":"www.siplast.dk",
    "wof:name":"Siplast A/S",
    "wof:placetype":"venue"
},
  "geometry": {"coordinates":[10.6065101624,55.0595970154],"type":"Point"}
}