{
  "type": "Feature",
  "properties": {
    "iso:country":"DK",
    "sg:address":"Leder: Kathe Olsen, F\u00e6rgevej 44, Mjels",
    "sg:city":"Nordborg",
    "sg:orig_category":"\u00c3\u2020ldreorganisationer og klubber",
    "sg:phone":"+45 74 45 11 85",
    "sg:postcode":"6430",
    "sg:province":"Danmark",
    "wof:name":"Havnbjerg/Oksb\u00f8l-Svenstrup Klubben",
    "wof:placetype":"venue"
},
  "geometry": {"coordinates":[9.7496232986,55.0542755127],"type":"Point"}
}