{
  "type": "Feature",
  "properties": {
    "addr:full":"S\u00f8nderborgvej 137, Felsted Aabenraa Danmark 6200",
    "addr:housenumber":"137",
    "addr:postcode":"6200",
    "addr:street":"Sonderborgvej;Felsted",
    "iso:country":"DK",
    "sg:address":"S\u00f8nderborgvej 137, Felsted",
    "sg:city":"Aabenraa",
    "sg:orig_category":"Biblioteker",
    "sg:phone":"+45 74 68 53 20",
    "sg:postcode":"6200",
    "sg:province":"Danmark",
    "sg:website":"www.lundbib.cjb.net",
    "wof:name":"Lundtoft-Felsted Hovedbibliotek",
    "wof:placetype":"venue"
},
  "geometry": {"coordinates":[9.4213867188,55.0449562073],"type":"Point"}
}