{
  "type": "Feature",
  "properties": {
    "iso:country":"DK",
    "sg:address":"Rosenvoldvej 13",
    "sg:city":"Stouby",
    "sg:classifiers":[
        {
            "category":"Taxi",
            "type":"Transportation"
        }
    ],
    "sg:phone":"+45 75 89 75 55",
    "sg:postcode":"7140",
    "sg:province":"Danmark",
    "wof:name":"Rosenvoldvejens Taxi",
    "wof:placetype":"venue"
},
  "geometry": {"coordinates":[9.803896904,55.6897850037],"type":"Point"}
}