{
  "type": "Feature",
  "properties": {
    "addr:full":"v/ Hans Christensen, R\u00f8dager Alle 62 R\u00f8dovre Danmark 2610",
    "addr:housenumber":"62",
    "addr:postcode":"2610",
    "addr:street":"Rodager Alle",
    "iso:country":"DK",
    "sg:address":"v/ Hans Christensen, R\u00f8dager Alle 62",
    "sg:city":"R\u00f8dovre",
    "sg:orig_category":"Grundejerforeninger",
    "sg:phone":"+45 36 70 28 92",
    "sg:postcode":"2610",
    "sg:province":"Danmark",
    "wof:name":"Helse Grundejerforening",
    "wof:placetype":"venue"
},
  "geometry": {"coordinates":[10.6992139816,61.1027755737],"type":"Point"}
}