{
  "type": "Feature",
  "properties": {
    "addr:full":"Englandsgade 32 Esbjerg Danmark 6700",
    "addr:housenumber":"32",
    "addr:postcode":"6700",
    "addr:street":"Englandsgade",
    "iso:country":"DK",
    "sg:address":"Englandsgade 32",
    "sg:city":"Esbjerg",
    "sg:orig_category":"Genbrugsbutikker",
    "sg:phone":"+45 75 45 79 39",
    "sg:postcode":"6700",
    "sg:province":"Danmark",
    "wof:name":"Dansk R\u00f8de Kors genbrugsbutik",
    "wof:placetype":"venue"
},
  "geometry": {"coordinates":[8.4548873901,55.4675445557],"type":"Point"}
}