{
  "type": "Feature",
  "properties": {
    "addr:full":"Klosterplads 2, 1 sal Svendborg Danmark 5700",
    "addr:housenumber":"2 1 sal",
    "addr:postcode":"5700",
    "addr:street":"Klosterplads",
    "iso:country":"DK",
    "sg:address":"Klosterplads 2, 1 sal",
    "sg:city":"Svendborg",
    "sg:orig_category":"Ejendomshandel",
    "sg:phone":"+45 63 21 09 45",
    "sg:postcode":"5700",
    "sg:province":"Danmark",
    "wof:name":"Holm, J\u00f8rgen H.",
    "wof:placetype":"venue"
},
  "geometry": {"coordinates":[10.6065101624,55.0595970154],"type":"Point"}
}