{
  "type": "Feature",
  "properties": {
    "addr:full":"Udklitvej 4, Br\u00f8ndum Fjerritslev Danmark 9690",
    "addr:housenumber":"4",
    "addr:postcode":"9690",
    "addr:street":"Udklitvej",
    "iso:country":"DK",
    "sg:address":"Udklitvej 4, Br\u00f8ndum",
    "sg:city":"Fjerritslev",
    "sg:orig_category":"Hundetrimning",
    "sg:phone":"+45 98 21 38 41",
    "sg:postcode":"9690",
    "sg:province":"Danmark",
    "wof:name":"Muus, Dorthe",
    "wof:placetype":"venue"
},
  "geometry": {"coordinates":[9.2667350769,57.0882301331],"type":"Point"}
}