{
  "type": "Feature",
  "properties": {
    "iso:country":"DK",
    "sg:address":"Stenderup 40",
    "sg:city":"S\u00f8nderborg",
    "sg:orig_category":"Autoreparation og -service",
    "sg:phone":"+45 74 46 90 91",
    "sg:postcode":"6400",
    "sg:province":"Danmark",
    "wof:name":"Stenderup Auto",
    "wof:placetype":"venue"
},
  "geometry": {"coordinates":[9.6913127899,54.930606842],"type":"Point"}
}