{
  "type": "Feature",
  "properties": {
    "addr:full":"Jernbanegade 27-29 Fredericia Danmark 7000",
    "addr:postcode":"27-29;7000",
    "addr:street":"Jernbanegade",
    "iso:country":"DK",
    "sg:address":"Jernbanegade 27-29",
    "sg:city":"Fredericia",
    "sg:orig_category":"Faglige organisationer og foreninger",
    "sg:phone":"+45 75 92 08 39",
    "sg:postcode":"7000",
    "sg:province":"Danmark",
    "wof:name":"Fredericia Transport & Service, SiD afd. T & S",
    "wof:placetype":"venue"
},
  "geometry": {"coordinates":[9.7426424026,55.5667648315],"type":"Point"}
}