{
  "type": "Feature",
  "properties": {
    "addr:full":"Mejerivej 9 Bredsten Danmark 7182",
    "addr:housenumber":"9",
    "addr:postcode":"7182",
    "addr:street":"Mejerivej",
    "iso:country":"DK",
    "sg:address":"Mejerivej 9",
    "sg:city":"Bredsten",
    "sg:orig_category":"Systuer",
    "sg:phone":"+45 75 88 11 19",
    "sg:postcode":"7182",
    "sg:province":"Danmark",
    "wof:name":"Systuen",
    "wof:placetype":"venue"
},
  "geometry": {"coordinates":[9.3844461441,55.7024154663],"type":"Point"}
}