{
  "type": "Feature",
  "properties": {
    "iso:country":"DK",
    "sg:address":"Herning, Postboks 225",
    "sg:city":"Herning",
    "sg:classifiers":[
        {
            "category":"Communications",
            "type":"Services"
        }
    ],
    "sg:phone":"+45 97 21 25 52",
    "sg:postcode":"7400",
    "sg:province":"Danmark",
    "sg:tags":[
        "radio-",
        "og",
        "tv-stationer"
    ],
    "wof:name":"Radio Midtjylland Classic",
    "wof:placetype":"venue"
},
  "geometry": {"coordinates":[8.9768896103,56.1374168396],"type":"Point"}
}