{
  "type": "Feature",
  "properties": {
    "addr:full":"Kredsf\u00f8rer: Lars Frydendal, Holb\u00e6kvej 93 A, Nr. Jernl\u00f8se Regstrup Danmark 4420",
    "addr:housenumber":"93 a nr.",
    "addr:postcode":"4420",
    "addr:street":"Holbaekvej;Jernlose",
    "iso:country":"DK",
    "sg:address":"Kredsf\u00f8rer: Lars Frydendal, Holb\u00e6kvej 93 A, Nr. Jernl\u00f8se",
    "sg:city":"Regstrup",
    "sg:orig_category":"Spejderkorps",
    "sg:phone":"+45 59 18 46 86",
    "sg:postcode":"4420",
    "sg:province":"Danmark",
    "wof:name":"Danske Baptisters Spejderkorps",
    "wof:placetype":"venue"
},
  "geometry": {"coordinates":[11.6131772995,55.6769638062],"type":"Point"}
}