{
  "type": "Feature",
  "properties": {
    "addr:full":"Marselisborg Havnevej 46 D \u00c5rhus C Danmark 8000",
    "addr:housenumber":"46 d",
    "addr:postcode":"8000",
    "addr:street":"Marselisborg Havnevej",
    "iso:country":"DK",
    "sg:address":"Marselisborg Havnevej 46 D",
    "sg:city":"\u00c5rhus C",
    "sg:classifiers":[
        {
            "category":"Restaurant",
            "type":"Food & Drink"
        }
    ],
    "sg:phone":"+45 86 20 20 58",
    "sg:postcode":"8000",
    "sg:province":"Danmark",
    "wof:name":"Navigator, Restaurant",
    "wof:placetype":"venue"
},
  "geometry": {"coordinates":[4.717400074,49.7588005066],"type":"Point"}
}