{
  "type": "Feature",
  "properties": {
    "addr:full":"Sanderumvej 129, Sanderum Odense SV Danmark 5250",
    "addr:housenumber":"129",
    "addr:postcode":"5250",
    "addr:street":"Sanderumvej",
    "iso:country":"DK",
    "sg:address":"Sanderumvej 129, Sanderum",
    "sg:city":"Odense SV",
    "sg:orig_category":"Kirkesogne",
    "sg:phone":"+45 66 17 30 31",
    "sg:postcode":"5250",
    "sg:province":"Danmark",
    "wof:name":"Sanderum Sogns Kirkekontor",
    "wof:placetype":"venue"
},
  "geometry": {"coordinates":[10.3153953552,55.3362998962],"type":"Point"}
}