{
  "type": "Feature",
  "properties": {
    "addr:full":"Kirkealle 2 Arden Danmark 9510",
    "addr:housenumber":"2",
    "addr:postcode":"9510",
    "addr:street":"Kirkealle",
    "iso:country":"DK",
    "sg:address":"Kirkealle 2",
    "sg:city":"Arden",
    "sg:orig_category":"Kirker",
    "sg:postcode":"9510",
    "sg:province":"Danmark",
    "wof:name":"Arden Kirke",
    "wof:placetype":"venue"
},
  "geometry": {"coordinates":[9.9362449646,56.7331352234],"type":"Point"}
}