{
  "type": "Feature",
  "properties": {
    "iso:country":"DK",
    "sg:address":"Bygaden 2, J\u00f8rlunde",
    "sg:city":"Slangerup",
    "sg:orig_category":"INGENI\u00c3\u02dcRER",
    "sg:phone":"+45 40 57 37 87",
    "sg:postcode":"3550",
    "sg:province":"Danmark",
    "sg:website":"www.stageone.dk",
    "wof:name":"Stage One Computing",
    "wof:placetype":"venue"
},
  "geometry": {"coordinates":[12.1717596054,55.8460769653],"type":"Point"}
}