{
  "type": "Feature",
  "properties": {
    "addr:full":"S\u00f8ndergade 20 Kolding Danmark 6000",
    "addr:housenumber":"20",
    "addr:postcode":"6000",
    "addr:street":"Sondergade",
    "iso:country":"DK",
    "sg:address":"S\u00f8ndergade 20",
    "sg:city":"Kolding",
    "sg:orig_category":"Festartikler",
    "sg:phone":"+45 75 52 85 91",
    "sg:postcode":"6000",
    "sg:province":"Danmark",
    "wof:name":"Papirlageret",
    "wof:placetype":"venue"
},
  "geometry": {"coordinates":[9.4724235535,55.487285614],"type":"Point"}
}