{
  "type": "Feature",
  "properties": {
    "addr:full":"v/ Grethe Lund, Kordilgade 60 Kalundborg Danmark 4400",
    "addr:housenumber":"60",
    "addr:postcode":"4400",
    "addr:street":"Kordilgade",
    "iso:country":"DK",
    "sg:address":"v/ Grethe Lund, Kordilgade 60",
    "sg:city":"Kalundborg",
    "sg:orig_category":"Genbrugsbutikker",
    "sg:phone":"+45 59 51 20 86",
    "sg:postcode":"4400",
    "sg:province":"Danmark",
    "wof:name":"Folkekirkens N\u00f8dhj\u00e6lps Genbrugsbutik",
    "wof:placetype":"venue"
},
  "geometry": {"coordinates":[11.0934085846,55.6797485352],"type":"Point"}
}