{
  "type": "Feature",
  "properties": {
    "iso:country":"DK",
    "sg:address":"Vestergade 11",
    "sg:city":"Holsted",
    "sg:orig_category":"Kirker",
    "sg:postcode":"6670",
    "sg:province":"Danmark",
    "wof:name":"Holsted Kirke",
    "wof:placetype":"venue"
},
  "geometry": {"coordinates":[8.9139003754,55.512260437],"type":"Point"}
}