{
  "type": "Feature",
  "properties": {
    "addr:full":"Strandvejen 7 Ebeltoft Danmark 8400",
    "addr:housenumber":"7",
    "addr:postcode":"8400",
    "addr:street":"Strandvejen",
    "iso:country":"DK",
    "sg:address":"Strandvejen 7",
    "sg:city":"Ebeltoft",
    "sg:orig_category":"INGENI\u00c3\u02dcRER",
    "sg:phone":"+45 86 34 24 91",
    "sg:postcode":"8400",
    "sg:province":"Danmark",
    "wof:name":"Vesterskov, Mogens",
    "wof:placetype":"venue"
},
  "geometry": {"coordinates":[10.676440239,56.1990585327],"type":"Point"}
}