{
  "type": "Feature",
  "properties": {
    "addr:full":"Danmarksgade 10 Aulum Danmark 7490",
    "addr:housenumber":"10",
    "addr:postcode":"7490",
    "addr:street":"Danmarksgade",
    "iso:country":"DK",
    "sg:address":"Danmarksgade 10",
    "sg:city":"Aulum",
    "sg:orig_category":"Flytteforretninger",
    "sg:phone":"+45 97 47 15 67",
    "sg:postcode":"7490",
    "sg:province":"Danmark",
    "wof:name":"Aulum Flytteforretning",
    "wof:placetype":"venue"
},
  "geometry": {"coordinates":[8.7961139679,56.266040802],"type":"Point"}
}