{
  "type": "Feature",
  "properties": {
    "addr:full":"Astrupvej 45, Ebdrup Kolind Danmark 8560",
    "addr:housenumber":"45",
    "addr:postcode":"8560",
    "addr:street":"Astrupvej",
    "iso:country":"DK",
    "sg:address":"Astrupvej 45, Ebdrup",
    "sg:city":"Kolind",
    "sg:orig_category":"Forsamlingshuse",
    "sg:phone":"+45 86 39 11 62",
    "sg:postcode":"8560",
    "sg:province":"Danmark",
    "wof:name":"Ebdrup Forsamlingshus, I/S",
    "wof:placetype":"venue"
},
  "geometry": {"coordinates":[10.5873975754,56.3618812561],"type":"Point"}
}