{
  "type": "Feature",
  "properties": {
    "addr:full":"S\u00f8ndervig Landevej 56, S\u00f8ndervig Ringk\u00f8bing Danmark 6950",
    "addr:housenumber":"56",
    "addr:postcode":"6950",
    "addr:street":"Sondervig Landevej",
    "iso:country":"DK",
    "sg:address":"S\u00f8ndervig Landevej 56, S\u00f8ndervig",
    "sg:city":"Ringk\u00f8bing",
    "sg:orig_category":"Glarmestre og glarmagere",
    "sg:phone":"+45 97 33 90 75",
    "sg:postcode":"6950",
    "sg:province":"Danmark",
    "wof:name":"S\u00f8ndervig t\u00f8mrer- og maskinsnedkeri",
    "wof:placetype":"venue"
},
  "geometry": {"coordinates":[-114.0767440796,46.4432487488],"type":"Point"}
}