{
  "type": "Feature",
  "properties": {
    "iso:country":"DK",
    "sg:address":"H\u00f8jv\u00e6nget 225",
    "sg:city":"Odder",
    "sg:orig_category":"Reklamebureauer",
    "sg:phone":"+45 86 54 42 35",
    "sg:postcode":"8300",
    "sg:province":"Danmark",
    "sg:website":"www.olelaasby.dk",
    "wof:name":"Laasby, Ole",
    "wof:placetype":"venue"
},
  "geometry": {"coordinates":[10.1497612,55.9733161926],"type":"Point"}
}