{
  "type": "Feature",
  "properties": {
    "addr:full":"Kontaktpers.: Jens Andersen, Middelfartvej 31, Baaring Asperup Danmark 5466",
    "addr:housenumber":"31",
    "addr:postcode":"5466",
    "addr:street":"Middelfartvej",
    "iso:country":"DK",
    "sg:address":"Kontaktpers.: Jens Andersen, Middelfartvej 31, Baaring",
    "sg:city":"Asperup",
    "sg:orig_category":"Spejderkorps",
    "sg:phone":"+45 64 48 18 00",
    "sg:postcode":"5466",
    "sg:province":"Danmark",
    "wof:name":"KFUM-spejderne",
    "wof:placetype":"venue"
},
  "geometry": {"coordinates":[9.9057912827,55.4908866882],"type":"Point"}
}