{
  "type": "Feature",
  "properties": {
    "iso:country":"DK",
    "sg:address":"Apperupvej 20, Apperup",
    "sg:city":"\u00c5lsg\u00e5rde",
    "sg:orig_category":"Diskoteker, Mobile",
    "sg:phone":"+45 49 70 98 32",
    "sg:postcode":"3140",
    "sg:province":"Danmark",
    "wof:name":"Skru' Ned Mobil Diskotek",
    "wof:placetype":"venue"
},
  "geometry": {"coordinates":[12.5406808853,56.0749893188],"type":"Point"}
}