{
  "type": "Feature",
  "properties": {
    "addr:full":"Vardevej 1 - 3 Aalborg \u00d8 Danmark 9220",
    "addr:housenumber":"1 3",
    "addr:postcode":"9220",
    "addr:street":"Vardevej;Danmark",
    "iso:country":"DK",
    "sg:address":"Vardevej 1 - 3",
    "sg:city":"Aalborg \u00d8",
    "sg:orig_category":"Flytteforretninger",
    "sg:phone":"+45 98 15 47 11",
    "sg:postcode":"9220",
    "sg:province":"Danmark",
    "wof:name":"Expedit Aalborg A/S",
    "wof:placetype":"venue"
},
  "geometry": {"coordinates":[9.9743080139,57.0236091614],"type":"Point"}
}