{
  "type": "Feature",
  "properties": {
    "addr:full":"Adelgade 87E 1. tv. Bogense Danmark 5400",
    "addr:housenumber":"87e 1 tv.",
    "addr:postcode":"5400",
    "addr:street":"Adelgade",
    "iso:country":"DK",
    "sg:address":"Adelgade 87E 1. tv.",
    "sg:city":"Bogense",
    "sg:orig_category":"Zoneterapeuter",
    "sg:phone":"+45 64 81 26 15",
    "sg:postcode":"5400",
    "sg:province":"Danmark",
    "wof:name":"Andersen, Anna L. Madsen",
    "wof:placetype":"venue"
},
  "geometry": {"coordinates":[10.0943098068,55.5637893677],"type":"Point"}
}