{
  "type": "Feature",
  "properties": {
    "addr:full":"Toften 3 Br\u00f8nsh\u00f8j Danmark 2700",
    "addr:housenumber":"3",
    "addr:postcode":"2700",
    "addr:street":"Toften",
    "iso:country":"DK",
    "sg:address":"Toften 3",
    "sg:city":"Br\u00f8nsh\u00f8j",
    "sg:orig_category":"Metaller",
    "sg:phone":"+45 38 60 60 18",
    "sg:postcode":"2700",
    "sg:province":"Danmark",
    "wof:name":"Husum Metalhandel",
    "wof:placetype":"venue"
},
  "geometry": {"coordinates":[-65.6866531372,-23.1981296539],"type":"Point"}
}