{
  "type": "Feature",
  "properties": {
    "addr:full":"Seminarievej 8 Ranum Danmark 9681",
    "addr:housenumber":"8",
    "addr:postcode":"9681",
    "addr:street":"Seminarievej",
    "iso:country":"DK",
    "sg:address":"Seminarievej 8",
    "sg:city":"Ranum",
    "sg:orig_category":"\u00c3\u2020ldreboliger",
    "sg:postcode":"9681",
    "sg:province":"Danmark",
    "wof:name":"\u00c6ldreboliger",
    "wof:placetype":"venue"
},
  "geometry": {"coordinates":[9.2392301559,56.9002189636],"type":"Point"}
}