{
  "type": "Feature",
  "properties": {
    "addr:full":"M\u00f8llealle 5 Nakskov Danmark 4900",
    "addr:housenumber":"5",
    "addr:postcode":"4900",
    "addr:street":"Mollealle",
    "iso:country":"DK",
    "sg:address":"M\u00f8llealle 5",
    "sg:city":"Nakskov",
    "sg:orig_category":"Plejecentre",
    "sg:phone":"+45 54 97 07 00",
    "sg:postcode":"4900",
    "sg:province":"Danmark",
    "sg:website":"www.sundhedsomraadet.dk",
    "wof:name":"Sundhedsomr\u00e5det",
    "wof:placetype":"venue"
},
  "geometry": {"coordinates":[11.1277236938,54.8347663879],"type":"Point"}
}