{
  "type": "Feature",
  "properties": {
    "addr:full":"Kirketorvet 4 Fakse Danmark 4640",
    "addr:housenumber":"4",
    "addr:postcode":"4640",
    "addr:street":"Kirketorvet",
    "iso:country":"DK",
    "sg:address":"Kirketorvet 4",
    "sg:city":"Fakse",
    "sg:orig_category":"Advokater",
    "sg:phone":"+45 56 71 30 25",
    "sg:postcode":"4640",
    "sg:province":"Danmark",
    "wof:name":"Elverdam, Advokatfirmaet Torben",
    "wof:placetype":"venue"
},
  "geometry": {"coordinates":[12.1203422546,55.2574195862],"type":"Point"}
}