{
  "type": "Feature",
  "properties": {
    "addr:full":"Hvarrevej 6 Arden Danmark 9510",
    "addr:housenumber":"6",
    "addr:postcode":"9510",
    "addr:street":"Hvarrevej",
    "iso:country":"DK",
    "sg:address":"Hvarrevej 6",
    "sg:city":"Arden",
    "sg:orig_category":"Cafeterier",
    "sg:phone":"+45 98 56 11 92",
    "sg:postcode":"9510",
    "sg:province":"Danmark",
    "wof:name":"Ardenhallens Cafeteria",
    "wof:placetype":"venue"
},
  "geometry": {"coordinates":[9.8657426834,56.7640304565],"type":"Point"}
}