{
  "type": "Feature",
  "properties": {
    "addr:full":"Bredgade 20, M\u00f8nsted Viborg Danmark 8800",
    "addr:housenumber":"20",
    "addr:postcode":"8800",
    "addr:street":"Bredgade",
    "iso:country":"DK",
    "sg:address":"Bredgade 20, M\u00f8nsted",
    "sg:city":"Viborg",
    "sg:orig_category":"Apoteker og -udsalg",
    "sg:phone":"+45 86 64 61 92",
    "sg:postcode":"8800",
    "sg:province":"Danmark",
    "wof:name":"H\u00e5ndk\u00f8bsudsalg - M\u00f8nsted",
    "wof:placetype":"venue"
},
  "geometry": {"coordinates":[9.4071502686,56.452671051],"type":"Point"}
}