{
  "type": "Feature",
  "properties": {
    "addr:full":"Eriksvej 8 Assens Danmark 5610",
    "addr:housenumber":"8",
    "addr:postcode":"5610",
    "addr:street":"Eriksvej",
    "iso:country":"DK",
    "sg:address":"Eriksvej 8",
    "sg:city":"Assens",
    "sg:orig_category":"Malermestre",
    "sg:phone":"+45 64 71 42 42",
    "sg:postcode":"5610",
    "sg:province":"Danmark",
    "wof:name":"Larsen, Boris",
    "wof:placetype":"venue"
},
  "geometry": {"coordinates":[9.9190359116,55.2780342102],"type":"Point"}
}