{
  "type": "Feature",
  "properties": {
    "addr:full":"Hunderupvej 125 B Odense M Danmark 5230",
    "addr:housenumber":"125 b",
    "addr:postcode":"5230",
    "addr:street":"Hunderupvej",
    "iso:country":"DK",
    "sg:address":"Hunderupvej 125 B",
    "sg:city":"Odense M",
    "sg:orig_category":"Malermestre",
    "sg:phone":"+45 66 14 55 09",
    "sg:postcode":"5230",
    "sg:province":"Danmark",
    "wof:name":"Byskov, Peter J.",
    "wof:placetype":"venue"
},
  "geometry": {"coordinates":[10.3887557983,55.3789672852],"type":"Point"}
}