{
  "type": "Feature",
  "properties": {
    "iso:country":"DK",
    "sg:address":"v/ Erling Clement, K. A. Hasselbalchs Vej 64",
    "sg:city":"Snekkersten",
    "sg:orig_category":"Hobbybetonede foreninger",
    "sg:phone":"+45 49 22 08 65",
    "sg:postcode":"3070",
    "sg:province":"Danmark",
    "wof:name":"Bridgeklubben Pas",
    "wof:placetype":"venue"
},
  "geometry": {"coordinates":[12.5851154327,56.0076637268],"type":"Point"}
}