{
  "type": "Feature",
  "properties": {
    "iso:country":"DK",
    "sg:address":"B\u00f8gevej 2, Kaas",
    "sg:city":"Pandrup",
    "sg:orig_category":"Revisorer",
    "sg:phone":"+45 98 24 53 22",
    "sg:postcode":"9490",
    "sg:province":"Danmark",
    "sg:website":"www.revisiongroen.dk",
    "wof:name":"Gr\u00f8n, Revision",
    "wof:placetype":"venue"
},
  "geometry": {"coordinates":[9.6769151688,57.223815918],"type":"Point"}
}