{
  "type": "Feature",
  "properties": {
    "addr:full":"Snedkerv\u00e6nget 7, Stenstrup N\u00e6stved Danmark 4700",
    "addr:housenumber":"7",
    "addr:postcode":"4700",
    "addr:street":"Snedkervaenget",
    "iso:country":"DK",
    "sg:address":"Snedkerv\u00e6nget 7, Stenstrup",
    "sg:city":"N\u00e6stved",
    "sg:orig_category":"Autoforhandlere",
    "sg:phone":"+45 55 70 08 80",
    "sg:postcode":"4700",
    "sg:province":"Danmark",
    "sg:website":"www.lla-biler.dk",
    "wof:name":"Larsen Automobiler ApS, Leif",
    "wof:placetype":"venue"
},
  "geometry": {"coordinates":[11.7542486191,55.2315444946],"type":"Point"}
}