{
  "type": "Feature",
  "properties": {
    "addr:full":"Frederiksberg Alle 3, 1 K\u00f8benhavn Danmark 1621",
    "addr:housenumber":"3 1",
    "addr:postcode":"1621",
    "addr:street":"Frederiksberg Alle",
    "iso:country":"DK",
    "sg:address":"Frederiksberg Alle 3, 1",
    "sg:city":"K\u00f8benhavn",
    "sg:orig_category":"Fysiurgi og rehabilitering, Gigtsygdomme Reumatologi",
    "sg:phone":"+45 33 31 96 99",
    "sg:postcode":"1621",
    "sg:province":"Danmark",
    "wof:name":"Pedersen, Bo",
    "wof:placetype":"venue"
},
  "geometry": {"coordinates":[12.5494203568,55.672870636],"type":"Point"}
}