{
  "type": "Feature",
  "properties": {
    "addr:full":"Gruppeleder: Brian Andersson, W\u00e6bersvej 8 Roskilde Danmark 4000",
    "addr:housenumber":"8",
    "addr:postcode":"4000",
    "addr:street":"Waebersvej",
    "iso:country":"DK",
    "sg:address":"Gruppeleder: Brian Andersson, W\u00e6bersvej 8",
    "sg:city":"Roskilde",
    "sg:orig_category":"Spejderkorps",
    "sg:phone":"+45 22 43 37 99",
    "sg:postcode":"4000",
    "sg:province":"Danmark",
    "wof:name":"Danske Spejderkorps, Det Bjarke Gruppe",
    "wof:placetype":"venue"
},
  "geometry": {"coordinates":[12.0909376144,55.6404838562],"type":"Point"}
}