{
  "type": "Feature",
  "properties": {
    "addr:full":"Sardinvej 7 Skagen Danmark 9990",
    "addr:housenumber":"7",
    "addr:postcode":"9990",
    "addr:street":"Sardinvej",
    "iso:country":"DK",
    "sg:address":"Sardinvej 7",
    "sg:city":"Skagen",
    "sg:classifiers":[
        {
            "category":"Restaurant",
            "type":"Food & Drink"
        }
    ],
    "sg:phone":"+45 98 44 26 24",
    "sg:postcode":"9990",
    "sg:province":"Danmark",
    "wof:name":"Kabyssen",
    "wof:placetype":"venue"
},
  "geometry": {"coordinates":[10.5844621658,57.7175788879],"type":"Point"}
}