{
  "type": "Feature",
  "properties": {
    "addr:full":"Hovedgaden 42, Skovsgaard Brovst Danmark 9460",
    "addr:housenumber":"42",
    "addr:postcode":"9460",
    "addr:street":"Hovedgaden",
    "iso:country":"DK",
    "sg:address":"Hovedgaden 42, Skovsgaard",
    "sg:city":"Brovst",
    "sg:classifiers":[
        {
            "category":"Communications",
            "type":"Services"
        }
    ],
    "sg:phone":"+45 98 23 00 12",
    "sg:postcode":"9460",
    "sg:province":"Danmark",
    "sg:tags":[
        "og",
        "tv",
        "radio"
    ],
    "sg:website":"www.2tal.dk/skovsgaard",
    "wof:name":"Skovsg\u00e5rd Radio & TV, 2Tal",
    "wof:placetype":"venue"
},
  "geometry": {"coordinates":[9.5220241547,57.097366333],"type":"Point"}
}