{
  "type": "Feature",
  "properties": {
    "addr:full":"K\u00f8gevej 94 Taastrup Danmark 2630",
    "addr:housenumber":"94",
    "addr:postcode":"2630",
    "addr:street":"Kogevej",
    "iso:country":"DK",
    "sg:address":"K\u00f8gevej 94",
    "sg:city":"Taastrup",
    "sg:orig_category":"Fodterapeuter",
    "sg:phone":"+45 43 99 34 00",
    "sg:postcode":"2630",
    "sg:province":"Danmark",
    "wof:name":"Emanuel, Mikael",
    "wof:placetype":"venue"
},
  "geometry": {"coordinates":[12.3020896912,55.6506767273],"type":"Point"}
}