{
  "type": "Feature",
  "properties": {
    "addr:full":"Syrenvej 6 Kongerslev Danmark 9293",
    "addr:housenumber":"6",
    "addr:postcode":"9293",
    "addr:street":"Syrenvej",
    "iso:country":"DK",
    "sg:address":"Syrenvej 6",
    "sg:city":"Kongerslev",
    "sg:orig_category":"Farve og tapet",
    "sg:phone":"+45 98 33 14 22",
    "sg:postcode":"9293",
    "sg:province":"Danmark",
    "wof:name":"Kongerslev Tr\u00e6last og Byggecenter ApS",
    "wof:placetype":"venue"
},
  "geometry": {"coordinates":[10.1174488068,56.8836326599],"type":"Point"}
}