{
  "type": "Feature",
  "properties": {
    "iso:country":"DK",
    "sg:address":"Gr\u00f8nnegade 18",
    "sg:city":"K\u00f8benhavn",
    "sg:orig_category":"Reklamebureauer",
    "sg:phone":"+45 33 91 29 10",
    "sg:postcode":"1107",
    "sg:province":"Danmark",
    "wof:name":"Andkj\u00e6r, Henrik",
    "wof:placetype":"venue"
},
  "geometry": {"coordinates":[76.3070983887,14.277130127],"type":"Point"}
}