{
  "type": "Feature",
  "properties": {
    "iso:country":"DK",
    "sg:address":"Fmd.: Erik Larsen, Hovedgaden 1 A, Viskinge",
    "sg:city":"Sveb\u00f8lle",
    "sg:orig_category":"Borger- og beboerforeninger",
    "sg:phone":"+45 59 29 38 67",
    "sg:postcode":"4470",
    "sg:province":"Danmark",
    "wof:name":"Viskinge Beboerforening",
    "wof:placetype":"venue"
},
  "geometry": {"coordinates":[11.2652997971,55.6623382568],"type":"Point"}
}