{
  "type": "Feature",
  "properties": {
    "addr:full":"Langmosevej 9, Illerhede Ans Danmark 8643",
    "addr:housenumber":"9",
    "addr:postcode":"8643",
    "addr:street":"Langmosevej",
    "iso:country":"DK",
    "sg:address":"Langmosevej 9, Illerhede",
    "sg:city":"Ans",
    "sg:orig_category":"Emballage",
    "sg:phone":"+45 86 87 90 62",
    "sg:postcode":"8643",
    "sg:province":"Danmark",
    "wof:name":"Osbosch",
    "wof:placetype":"venue"
},
  "geometry": {"coordinates":[9.6200656891,56.2750320435],"type":"Point"}
}