{
  "type": "Feature",
  "properties": {
    "addr:full":"Vonsb\u00e6kvej 88 Haderslev Danmark 6100",
    "addr:housenumber":"88",
    "addr:postcode":"6100",
    "addr:street":"Vonsbaekvej",
    "iso:country":"DK",
    "sg:address":"Vonsb\u00e6kvej 88",
    "sg:city":"Haderslev",
    "sg:orig_category":"Kommunale folkeskoler",
    "sg:phone":"+45 74 57 91 82",
    "sg:postcode":"6100",
    "sg:province":"Danmark",
    "wof:name":"Vonsb\u00e6k Skole",
    "wof:placetype":"venue"
},
  "geometry": {"coordinates":[9.6182546616,55.2927742004],"type":"Point"}
}