{
  "type": "Feature",
  "properties": {
    "addr:full":"H\u00f8edvej 63, H\u00f8ed Jystrup Danmark 4174",
    "addr:housenumber":"63",
    "addr:postcode":"4174",
    "addr:street":"Hoedvej",
    "iso:country":"DK",
    "sg:address":"H\u00f8edvej 63, H\u00f8ed",
    "sg:city":"Jystrup",
    "sg:orig_category":"Akupunktur",
    "sg:phone":"+45 57 52 80 62",
    "sg:postcode":"4174",
    "sg:province":"Danmark",
    "wof:name":"Jystrup Akupunktur Klinik",
    "wof:placetype":"venue"
},
  "geometry": {"coordinates":[11.8870201111,55.5071754456],"type":"Point"}
}