{
  "type": "Feature",
  "properties": {
    "addr:full":"Hovedvejen 193 Glostrup Danmark 2600",
    "addr:housenumber":"193",
    "addr:postcode":"2600",
    "addr:street":"Hovedvejen",
    "iso:country":"DK",
    "sg:address":"Hovedvejen 193",
    "sg:city":"Glostrup",
    "sg:orig_category":"Autoforhandlere",
    "sg:phone":"+45 43 96 55 00",
    "sg:postcode":"2600",
    "sg:province":"Danmark",
    "sg:website":"www.autohuset-glostrup.dk",
    "wof:name":"Autohuset Glostrup A/S",
    "wof:placetype":"venue"
},
  "geometry": {"coordinates":[12.3759527206,55.6641998291],"type":"Point"}
}