{
  "type": "Feature",
  "properties": {
    "iso:country":"DK",
    "sg:address":"G\u00f8dvad Bakke 4",
    "sg:city":"Silkeborg",
    "sg:orig_category":"EDB - udstyr",
    "sg:phone":"+45 86 81 26 44",
    "sg:postcode":"8600",
    "sg:province":"Danmark",
    "wof:name":"Lyngs\u00f8e EDB",
    "wof:placetype":"venue"
},
  "geometry": {"coordinates":[9.5837135315,56.1835365295],"type":"Point"}
}