{
  "type": "Feature",
  "properties": {
    "addr:full":"H. C. \u00d8rsteds Vej 38 A Herning Danmark 7400",
    "addr:housenumber":"38 a",
    "addr:postcode":"7400",
    "addr:street":"H. C. Orsteds Vej",
    "iso:country":"DK",
    "sg:address":"H. C. \u00d8rsteds Vej 38 A",
    "sg:city":"Herning",
    "sg:orig_category":"Bogbinderier",
    "sg:phone":"+45 97 22 35 02",
    "sg:postcode":"7400",
    "sg:province":"Danmark",
    "wof:name":"Central-Bogbinderiet",
    "wof:placetype":"venue"
},
  "geometry": {"coordinates":[8.9768896103,56.1374168396],"type":"Point"}
}