{
  "type": "Feature",
  "properties": {
    "addr:full":"Storegade 35 Brande Danmark 7330",
    "addr:housenumber":"35",
    "addr:postcode":"7330",
    "addr:street":"Storegade",
    "iso:country":"DK",
    "sg:address":"Storegade 35",
    "sg:city":"Brande",
    "sg:orig_category":"Diners transportables",
    "sg:phone":"+45 97 18 00 09",
    "sg:postcode":"7330",
    "sg:province":"Danmark",
    "wof:name":"Lorentsen's Madv\u00e6rksted, Slagter",
    "wof:placetype":"venue"
},
  "geometry": {"coordinates":[9.1292562485,55.9421539307],"type":"Point"}
}