{
  "type": "Feature",
  "properties": {
    "addr:full":"Skanderborggade 65 Randers Danmark 8900",
    "addr:housenumber":"65",
    "addr:postcode":"8900",
    "addr:street":"Skanderborggade",
    "iso:country":"DK",
    "sg:address":"Skanderborggade 65",
    "sg:city":"Randers",
    "sg:orig_category":"Skolefritidsordninger",
    "sg:phone":"+45 86 43 05 10",
    "sg:postcode":"8900",
    "sg:province":"Danmark",
    "wof:name":"S\u00f8ndermarkskolens skolefritidsordning",
    "wof:placetype":"venue"
},
  "geometry": {"coordinates":[10.0421657562,56.4378433228],"type":"Point"}
}