{
  "type": "Feature",
  "properties": {
    "addr:full":"Kattesund 1 Horsens Danmark 8700",
    "addr:housenumber":"1",
    "addr:postcode":"8700",
    "addr:street":"Kattesund",
    "iso:country":"DK",
    "sg:address":"Kattesund 1",
    "sg:city":"Horsens",
    "sg:orig_category":"Fotohandlere",
    "sg:phone":"+45 75 62 28 83",
    "sg:postcode":"8700",
    "sg:province":"Danmark",
    "wof:name":"I og W Foto",
    "wof:placetype":"venue"
},
  "geometry": {"coordinates":[9.8525695801,55.8624916077],"type":"Point"}
}