{
  "type": "Feature",
  "properties": {
    "addr:full":"\u00c5gade 13, N\u00e6sby Odense N Danmark 5270",
    "addr:housenumber":"13",
    "addr:postcode":"5270",
    "addr:street":"Aagade;Naesby",
    "iso:country":"DK",
    "sg:address":"\u00c5gade 13, N\u00e6sby",
    "sg:city":"Odense N",
    "sg:orig_category":"Engros handel",
    "sg:phone":"+45 66 18 25 24",
    "sg:postcode":"5270",
    "sg:province":"Danmark",
    "wof:name":"Gladiator Sport",
    "wof:placetype":"venue"
},
  "geometry": {"coordinates":[10.3306798935,55.4711418152],"type":"Point"}
}