{
  "type": "Feature",
  "properties": {
    "addr:full":"Herningvej 9 Nyk\u00f8bing Danmark 4800",
    "addr:housenumber":"9",
    "addr:postcode":"4800",
    "addr:street":"Herningvej",
    "iso:country":"DK",
    "sg:address":"Herningvej 9",
    "sg:city":"Nyk\u00f8bing",
    "sg:classifiers":[
        {
            "category":"Home & Garden",
            "subcategory":"Home Furnishings",
            "type":"Retail Goods"
        }
    ],
    "sg:phone":"+45 54 86 11 11",
    "sg:postcode":"4800",
    "sg:province":"Danmark",
    "sg:tags":[
        "gardiner"
    ],
    "wof:name":"Gardincon ApS",
    "wof:placetype":"venue"
},
  "geometry": {"coordinates":[-114.0768203735,46.4432411194],"type":"Point"}
}