{
  "type": "Feature",
  "properties": {
    "iso:country":"DK",
    "sg:address":"Munkevej 1",
    "sg:city":"Strandby",
    "sg:orig_category":"Bagere",
    "sg:phone":"+45 98 48 11 54",
    "sg:postcode":"9970",
    "sg:province":"Danmark",
    "wof:name":"Strandby Bageri",
    "wof:placetype":"venue"
},
  "geometry": {"coordinates":[10.498552,57.493679],"type":"Point"}
}