{
  "type": "Feature",
  "properties": {
    "iso:country":"DK",
    "sg:address":"Ledetvej 33",
    "sg:city":"Sindal",
    "sg:orig_category":"Betonvarefabrikker",
    "sg:phone":"+45 98 93 57 77",
    "sg:postcode":"9870",
    "sg:province":"Danmark",
    "wof:name":"Sindal Beton",
    "wof:placetype":"venue"
},
  "geometry": {"coordinates":[10.20323,57.470917],"type":"Point"}
}