{
  "type": "Feature",
  "properties": {
    "addr:full":"Frederiksberg Alle 35 Frederiksberg Danmark 1820",
    "addr:housenumber":"35",
    "addr:postcode":"1820",
    "addr:street":"Frederiksberg Alle",
    "iso:country":"DK",
    "sg:address":"Frederiksberg Alle 35",
    "sg:city":"Frederiksberg",
    "sg:orig_category":"Advokater",
    "sg:phone":"+45 33 21 19 88",
    "sg:postcode":"1820",
    "sg:province":"Danmark",
    "wof:name":"Willers, Else",
    "wof:placetype":"venue"
},
  "geometry": {"coordinates":[12.5421209335,55.6735153198],"type":"Point"}
}