{
  "type": "Feature",
  "properties": {
    "addr:full":"Gl. Landevej 15 Albertslund Danmark 2620",
    "addr:housenumber":"15",
    "addr:postcode":"2620",
    "addr:street":"Gl. Landevej",
    "iso:country":"DK",
    "sg:address":"Gl. Landevej 15",
    "sg:city":"Albertslund",
    "sg:orig_category":"Ungdomsklubber",
    "sg:phone":"+45 43 45 40 77",
    "sg:postcode":"2620",
    "sg:province":"Danmark",
    "wof:name":"Storagerg\u00e5rd Familiecenter",
    "wof:placetype":"venue"
},
  "geometry": {"coordinates":[12.3704891205,55.6772079468],"type":"Point"}
}