{
  "type": "Feature",
  "properties": {
    "addr:full":"Havnegade 8 Nyk\u00f8bing Danmark 7900",
    "addr:housenumber":"8",
    "addr:postcode":"7900",
    "addr:street":"Havnegade",
    "iso:country":"DK",
    "sg:address":"Havnegade 8",
    "sg:city":"Nyk\u00f8bing",
    "sg:classifiers":[
        {
            "category":"Restaurant",
            "type":"Food & Drink"
        }
    ],
    "sg:phone":"+45 97 72 00 71",
    "sg:postcode":"7900",
    "sg:province":"Danmark",
    "wof:name":"Mors\u00f8, Restaurant",
    "wof:placetype":"venue"
},
  "geometry": {"coordinates":[8.8630752563,56.7945251465],"type":"Point"}
}