{
  "type": "Feature",
  "properties": {
    "addr:full":"Vester\u00e5gade 36 Kolind Danmark 8560",
    "addr:housenumber":"36",
    "addr:postcode":"8560",
    "addr:street":"Vesteraagade",
    "iso:country":"DK",
    "sg:address":"Vester\u00e5gade 36",
    "sg:city":"Kolind",
    "sg:classifiers":[
        {
            "category":"Taxi",
            "type":"Transportation"
        }
    ],
    "sg:phone":"+45 86 39 22 50",
    "sg:postcode":"8560",
    "sg:province":"Danmark",
    "wof:name":"Kolind Taxi",
    "wof:placetype":"venue"
},
  "geometry": {"coordinates":[10.5843391418,56.3595809937],"type":"Point"}
}