{
  "type": "Feature",
  "properties": {
    "addr:full":"Lillelundvej 36 Herning Danmark 7400",
    "addr:housenumber":"36",
    "addr:postcode":"7400",
    "addr:street":"Lillelundvej",
    "iso:country":"DK",
    "sg:address":"Lillelundvej 36",
    "sg:city":"Herning",
    "sg:orig_category":"Kirker",
    "sg:postcode":"7400",
    "sg:province":"Danmark",
    "wof:name":"Katolsk Kirke Skt. Peter",
    "wof:placetype":"venue"
},
  "geometry": {"coordinates":[8.981803894,56.1534805298],"type":"Point"}
}