{
  "type": "Feature",
  "properties": {
    "addr:full":"Fmd.: Ulla St\u00f8jholm, Vestertorp 78, Gjellerup Herning Danmark 7400",
    "addr:housenumber":"78",
    "addr:postcode":"7400",
    "addr:street":"Vestertorp",
    "iso:country":"DK",
    "sg:address":"Fmd.: Ulla St\u00f8jholm, Vestertorp 78, Gjellerup",
    "sg:city":"Herning",
    "sg:orig_category":"Husflidsforeninger",
    "sg:phone":"+45 97 11 80 30",
    "sg:postcode":"7400",
    "sg:province":"Danmark",
    "wof:name":"DDH Hammerum/Gjellerup. Forening af aktive kvinder",
    "wof:placetype":"venue"
},
  "geometry": {"coordinates":[8.9768896103,56.1374168396],"type":"Point"}
}