{
  "type": "Feature",
  "properties": {
    "addr:full":"Mads Bjerres Vej 3 Holstebro Danmark 7500",
    "addr:housenumber":"3",
    "addr:postcode":"7500",
    "addr:street":"Mads Bjerres Vej",
    "iso:country":"DK",
    "sg:address":"Mads Bjerres Vej 3",
    "sg:city":"Holstebro",
    "sg:orig_category":"Bilinspektion",
    "sg:phone":"+45 97 42 57 11",
    "sg:postcode":"7500",
    "sg:province":"Danmark",
    "sg:website":"www.bilsyn.dk",
    "wof:name":"Statens Bilinspektion",
    "wof:placetype":"venue"
},
  "geometry": {"coordinates":[8.63988,56.366756],"type":"Point"}
}