{
  "type": "Feature",
  "properties": {
    "addr:full":"Fmd.: B\u00f8rge \u00c5gaard, Anne Maries All\u00e9 21, Sanderum Odense SV Danmark 5250",
    "addr:housenumber":"21",
    "addr:postcode":"5250",
    "addr:street":"Anne Maries Alle\u0301;Sanderum",
    "iso:country":"DK",
    "sg:address":"Fmd.: B\u00f8rge \u00c5gaard, Anne Maries All\u00e9 21, Sanderum",
    "sg:city":"Odense SV",
    "sg:orig_category":"\u00c3\u2020ldreorganisationer og klubber",
    "sg:phone":"+45 66 17 22 90",
    "sg:postcode":"5250",
    "sg:province":"Danmark",
    "wof:name":"Hum\u00f8rklubben for pensionister",
    "wof:placetype":"venue"
},
  "geometry": {"coordinates":[10.3153953552,55.3362998962],"type":"Point"}
}