{
  "type": "Feature",
  "properties": {
    "iso:country":"DK",
    "sg:address":"J\u00e6ttevej 14",
    "sg:city":"Ringsted",
    "sg:classifiers":[
        {
            "category":"Building & Trades",
            "subcategory":"Construction",
            "type":"Services"
        }
    ],
    "sg:phone":"+45 57 67 27 67",
    "sg:postcode":"4100",
    "sg:province":"Danmark",
    "sg:tags":[
        "ventilation"
    ],
    "sg:website":"www.kcventilation.dk",
    "wof:name":"KC Ventilation ApS",
    "wof:placetype":"venue"
},
  "geometry": {"coordinates":[11.8086719513,55.433883667],"type":"Point"}
}