{
  "type": "Feature",
  "properties": {
    "iso:country":"DK",
    "sg:address":"Gilleleje Hovedgade 55",
    "sg:city":"Gilleleje",
    "sg:orig_category":"Kirkesogne",
    "sg:phone":"+45 48 30 37 76",
    "sg:postcode":"3250",
    "sg:province":"Danmark",
    "sg:website":"www.folkekirken.dk/sogn/gilleleje",
    "wof:name":"Gilleleje Sogn",
    "wof:placetype":"venue"
},
  "geometry": {"coordinates":[12.3127536774,56.122215271],"type":"Point"}
}