{
  "type": "Feature",
  "properties": {
    "iso:country":"DK",
    "sg:address":"Vestergade 6",
    "sg:city":"Holstebro",
    "sg:classifiers":[
        {
            "category":"Banks & Credit Unions",
            "subcategory":"Bank",
            "type":"Services"
        }
    ],
    "sg:phone":"+45 97 40 66 22",
    "sg:postcode":"7500",
    "sg:province":"Danmark",
    "sg:tags":[
        "banker"
    ],
    "sg:website":"www.sparbankvest.dk",
    "wof:name":"Sparbank Vest",
    "wof:placetype":"venue"
},
  "geometry": {"coordinates":[8.6060647964,56.3543663025],"type":"Point"}
}