{
  "type": "Feature",
  "properties": {
    "iso:country":"DK",
    "sg:address":"Lerp\u00f8tvej 56",
    "sg:city":"Varde",
    "sg:orig_category":"Industri",
    "sg:phone":"+45 75 22 12 66",
    "sg:postcode":"6800",
    "sg:province":"Danmark",
    "wof:name":"Arla Foods A.m.b.A. - Varde Sm\u00f8rmejeri",
    "wof:placetype":"venue"
},
  "geometry": {"coordinates":[8.4749727249,55.6328964233],"type":"Point"}
}