{
  "type": "Feature",
  "properties": {
    "addr:full":"Nordre Fasanvej 230 K\u00f8benhavn N Danmark 2200",
    "addr:housenumber":"230",
    "addr:postcode":"2200",
    "addr:street":"Nordre Fasanvej;Kobenhavn N Danmark",
    "iso:country":"DK",
    "sg:address":"Nordre Fasanvej 230",
    "sg:city":"K\u00f8benhavn N",
    "sg:orig_category":"Fagforbund og -foreninger",
    "sg:phone":"+45 38 33 47 00",
    "sg:postcode":"2200",
    "sg:province":"Danmark",
    "wof:name":"Fagforening for K\u00f8benhavn og Omegn, Bryggeriarbejdernes",
    "wof:placetype":"venue"
},
  "geometry": {"coordinates":[12.035369873,60.8038711548],"type":"Point"}
}