{
  "type": "Feature",
  "properties": {
    "addr:full":"Vesterbrogade 39 A, 1. Gilleleje Danmark 3250",
    "addr:housenumber":"39 a 1",
    "addr:postcode":"3250",
    "addr:street":"Vesterbrogade",
    "iso:country":"DK",
    "sg:address":"Vesterbrogade 39 A, 1.",
    "sg:city":"Gilleleje",
    "sg:orig_category":"Alternativ behandling",
    "sg:phone":"+45 48 30 36 18",
    "sg:postcode":"3250",
    "sg:province":"Danmark",
    "wof:name":"Ikast, Annette",
    "wof:placetype":"venue"
},
  "geometry": {"coordinates":[12.2993917465,56.1259155273],"type":"Point"}
}