{
  "type": "Feature",
  "properties": {
    "addr:full":"Marielundvej 26 Herlev Danmark 2730",
    "addr:housenumber":"26",
    "addr:postcode":"2730",
    "addr:street":"Marielundvej",
    "iso:country":"DK",
    "sg:address":"Marielundvej 26",
    "sg:city":"Herlev",
    "sg:orig_category":"Autolakering",
    "sg:phone":"+45 44 94 68 38",
    "sg:postcode":"2730",
    "sg:province":"Danmark",
    "wof:name":"Gr\u00f8ndahl's Autolakering",
    "wof:placetype":"venue"
},
  "geometry": {"coordinates":[12.4288787842,55.7161941528],"type":"Point"}
}