{
  "type": "Feature",
  "properties": {
    "addr:full":"M\u00f8llergade 92 - 96 Svendborg Danmark 5700",
    "addr:housenumber":"92 96",
    "addr:postcode":"5700",
    "addr:street":"Mollergade",
    "iso:country":"DK",
    "sg:address":"M\u00f8llergade 92 - 96",
    "sg:city":"Svendborg",
    "sg:orig_category":"Varehuse",
    "sg:phone":"+45 63 21 30 00",
    "sg:postcode":"5700",
    "sg:province":"Danmark",
    "wof:name":"F\u00f8tex",
    "wof:placetype":"venue"
},
  "geometry": {"coordinates":[10.6134147644,55.0637321472],"type":"Point"}
}