{
  "type": "Feature",
  "properties": {
    "addr:full":"Islevhusvej 70 Br\u00f8nsh\u00f8j Danmark 2700",
    "addr:housenumber":"70",
    "addr:postcode":"2700",
    "addr:street":"Islevhusvej",
    "iso:country":"DK",
    "sg:address":"Islevhusvej 70",
    "sg:city":"Br\u00f8nsh\u00f8j",
    "sg:orig_category":"Murermestre",
    "sg:phone":"+45 38 28 78 59",
    "sg:postcode":"2700",
    "sg:province":"Danmark",
    "wof:name":"Johansen, Olle V.",
    "wof:placetype":"venue"
},
  "geometry": {"coordinates":[-65.6866531372,-23.1981296539],"type":"Point"}
}