{
  "type": "Feature",
  "properties": {
    "iso:country":"DK",
    "sg:address":"Hadsundvej 8",
    "sg:city":"Terndrup",
    "sg:orig_category":"Bagere",
    "sg:phone":"+45 98 33 50 73",
    "sg:postcode":"9575",
    "sg:province":"Danmark",
    "sg:website":"www.terndrupbageri.dk",
    "wof:name":"Terndrup Bageri ApS",
    "wof:placetype":"venue"
},
  "geometry": {"coordinates":[10.057667,56.81403],"type":"Point"}
}