{
  "type": "Feature",
  "properties": {
    "iso:country":"DK",
    "sg:address":"Sadelmagerporten 2",
    "sg:city":"Hvidovre",
    "sg:orig_category":"Kiosker",
    "sg:phone":"+45 36 49 63 76",
    "sg:postcode":"2650",
    "sg:province":"Danmark",
    "wof:name":"Store Hus Servicekiosk",
    "wof:placetype":"venue"
},
  "geometry": {"coordinates":[12.4555397034,55.6264305115],"type":"Point"}
}