{
  "type": "Feature",
  "properties": {
    "addr:full":"V\u00e6rnedamsvej 15 Frederiksberg Danmark 1819",
    "addr:housenumber":"15;1819",
    "addr:street":"Vaernedamsvej",
    "iso:country":"DK",
    "sg:address":"V\u00e6rnedamsvej 15",
    "sg:city":"Frederiksberg",
    "sg:classifiers":[
        {
            "category":"Food & Beverages",
            "subcategory":"Liquor & Beverages",
            "type":"Retail Goods"
        }
    ],
    "sg:phone":"+45 33 31 13 29",
    "sg:postcode":"1819",
    "sg:province":"Danmark",
    "sg:tags":[
        "vin"
    ],
    "sg:website":"www.juuls.vinhandel.dk",
    "wof:name":"Juul's Vinhandel",
    "wof:placetype":"venue"
},
  "geometry": {"coordinates":[12.5495920181,55.6743278503],"type":"Point"}
}