{
  "type": "Feature",
  "properties": {
    "addr:full":"Fmd.: Mogens Olsen, Lindetoften 59 Taastrup Danmark 2630",
    "addr:housenumber":"59",
    "addr:postcode":"2630",
    "addr:street":"Lindetoften",
    "iso:country":"DK",
    "sg:address":"Fmd.: Mogens Olsen, Lindetoften 59",
    "sg:city":"Taastrup",
    "sg:orig_category":"Musik og sang",
    "sg:phone":"+45 43 99 44 42",
    "sg:postcode":"2630",
    "sg:province":"Danmark",
    "wof:name":"Visens venner i Taastrup",
    "wof:placetype":"venue"
},
  "geometry": {"coordinates":[12.3020896912,55.6506767273],"type":"Point"}
}