{
  "type": "Feature",
  "properties": {
    "addr:full":"Lykkeg\u00e5rdvej 8, Svenstrup Middelfart Danmark 5500",
    "addr:housenumber":"8",
    "addr:postcode":"5500",
    "addr:street":"Lykkegaardvej;Svenstrup",
    "iso:country":"DK",
    "sg:address":"Lykkeg\u00e5rdvej 8, Svenstrup",
    "sg:city":"Middelfart",
    "sg:orig_category":"Slagter og viktualie",
    "sg:phone":"+45 64 40 32 62",
    "sg:postcode":"5500",
    "sg:province":"Danmark",
    "wof:name":"JN. Meat international Aps",
    "wof:placetype":"venue"
},
  "geometry": {"coordinates":[9.7417497635,55.5030250549],"type":"Point"}
}