{
  "type": "Feature",
  "properties": {
    "addr:full":"Vandt\u00e5rnsvej 108 S\u00f8borg Danmark 2860",
    "addr:housenumber":"108",
    "addr:postcode":"2860",
    "addr:street":"Vandtaarnsvej",
    "iso:country":"DK",
    "sg:address":"Vandt\u00e5rnsvej 108",
    "sg:city":"S\u00f8borg",
    "sg:orig_category":"Vinduer",
    "sg:phone":"+45 39 67 22 55",
    "sg:postcode":"2860",
    "sg:province":"Danmark",
    "wof:name":"JNA Trading",
    "wof:placetype":"venue"
},
  "geometry": {"coordinates":[-101.39041900629999,35.6679611206],"type":"Point"}
}