{
  "type": "Feature",
  "properties": {
    "addr:full":"v/ Finn Kokholm, \u00c5dalen 75, Borup Hede Vr\u00e5 Danmark 9760",
    "addr:housenumber":"75",
    "addr:postcode":"9760",
    "addr:street":"Aadalen;Hede;Danmark",
    "iso:country":"DK",
    "sg:address":"v/ Finn Kokholm, \u00c5dalen 75, Borup Hede",
    "sg:city":"Vr\u00e5",
    "sg:orig_category":"\u00c3\u2020ldreorganisationer og klubber",
    "sg:phone":"+45 98 98 17 39",
    "sg:postcode":"9760",
    "sg:province":"Danmark",
    "wof:name":"Vr\u00e5 Pensionistforening",
    "wof:placetype":"venue"
},
  "geometry": {"coordinates":[-96.50723266599999,47.1803092957],"type":"Point"}
}