{
  "type": "Feature",
  "properties": {
    "addr:full":"\u00d8stergade 54 Assens Danmark 5610",
    "addr:housenumber":"54",
    "addr:postcode":"5610",
    "addr:street":"Ostergade",
    "iso:country":"DK",
    "sg:address":"\u00d8stergade 54",
    "sg:city":"Assens",
    "sg:orig_category":"Brugskunst",
    "sg:phone":"+45 64 71 50 03",
    "sg:postcode":"5610",
    "sg:province":"Danmark",
    "wof:name":"Solsikken",
    "wof:placetype":"venue"
},
  "geometry": {"coordinates":[9.8984546661,55.2700004578],"type":"Point"}
}