{
  "type": "Feature",
  "properties": {
    "addr:full":"R\u00f8ntoftevej 34 S\u00f8borg Danmark 2860",
    "addr:housenumber":"34",
    "addr:postcode":"2860",
    "addr:street":"Rontoftevej",
    "iso:country":"DK",
    "sg:address":"R\u00f8ntoftevej 34",
    "sg:city":"S\u00f8borg",
    "sg:orig_category":"Gulvafslibning",
    "sg:phone":"+45 39 66 86 16",
    "sg:postcode":"2860",
    "sg:province":"Danmark",
    "wof:name":"Otterdahls Gulventreprise",
    "wof:placetype":"venue"
},
  "geometry": {"coordinates":[-101.39041900629999,35.6679611206],"type":"Point"}
}