{
  "type": "Feature",
  "properties": {
    "addr:full":"Vindbyholtvej 6 B Fakse Danmark 4640",
    "addr:housenumber":"6 b",
    "addr:postcode":"4640",
    "addr:street":"Vindbyholtvej",
    "iso:country":"DK",
    "sg:address":"Vindbyholtvej 6 B",
    "sg:city":"Fakse",
    "sg:orig_category":"Handicapboliger",
    "sg:phone":"+45 56 72 50 04",
    "sg:postcode":"4640",
    "sg:province":"Danmark",
    "sg:website":"www.marjatta.dk",
    "wof:name":"Voksencenter Vidars Lund",
    "wof:placetype":"venue"
},
  "geometry": {"coordinates":[12.1203422546,55.2574195862],"type":"Point"}
}