{
  "type": "Feature",
  "properties": {
    "addr:full":"Odinsvej 9 K\u00f8ge Danmark 4600",
    "addr:housenumber":"9",
    "addr:postcode":"4600",
    "addr:street":"Odinsvej",
    "iso:country":"DK",
    "sg:address":"Odinsvej 9",
    "sg:city":"K\u00f8ge",
    "sg:orig_category":"Gulvafslibning",
    "sg:phone":"+45 56 65 91 98",
    "sg:postcode":"4600",
    "sg:province":"Danmark",
    "sg:website":"www.jhgulvservice.dk",
    "wof:name":"J.H.Gulvservice",
    "wof:placetype":"venue"
},
  "geometry": {"coordinates":[12.179807663,55.4487380981],"type":"Point"}
}