{
  "type": "Feature",
  "properties": {
    "iso:country":"DK",
    "sg:address":"Sk\u00e6rb\u00e6k Havnegade 43 ",
    "sg:city":"Fredericia",
    "sg:classifiers":[
        {
            "category":"Autos & Motor Vehicles",
            "subcategory":"Boat Sales",
            "type":"Retail Goods"
        }
    ],
    "sg:phone":"+45 75 56 45 22",
    "sg:postcode":"7000",
    "sg:province":"Danmark",
    "wof:name":"FAURBY YACHTS A/S",
    "wof:placetype":"venue"
},
  "geometry": {"coordinates":[9.631403923,55.5135040283],"type":"Point"}
}