{
  "type": "Feature",
  "properties": {
    "addr:full":"Borgervej 3 A, Oue Hobro Danmark 9500",
    "addr:housenumber":"3 a",
    "addr:postcode":"9500",
    "addr:street":"Borgervej;Oue",
    "iso:country":"DK",
    "sg:address":"Borgervej 3 A, Oue",
    "sg:city":"Hobro",
    "sg:orig_category":"Kirker",
    "sg:postcode":"9500",
    "sg:province":"Danmark",
    "wof:name":"Oue Kirke",
    "wof:placetype":"venue"
},
  "geometry": {"coordinates":[9.7946596146,56.6382789612],"type":"Point"}
}