{
  "type": "Feature",
  "properties": {
    "addr:full":"M\u00f8rdrupvej 10 A Esperg\u00e6rde Danmark 3060",
    "addr:housenumber":"10 a",
    "addr:postcode":"3060",
    "addr:street":"Mordrupvej",
    "iso:country":"DK",
    "sg:address":"M\u00f8rdrupvej 10 A",
    "sg:city":"Esperg\u00e6rde",
    "sg:orig_category":"Dentallaboratorier",
    "sg:phone":"+45 49 13 32 60",
    "sg:postcode":"3060",
    "sg:province":"Danmark",
    "wof:name":"Keramisk Laboratorium",
    "wof:placetype":"venue"
},
  "geometry": {"coordinates":[11.6512403488,47.8390617371],"type":"Point"}
}