{
  "type": "Feature",
  "properties": {
    "iso:country":"DK",
    "sg:address":"Kontaktpers. Axel Hansen, Havrev\u00e6nget 19",
    "sg:city":"Haslev",
    "sg:orig_category":"Kirkelige foreninger",
    "sg:phone":"+45 56 31 28 18",
    "sg:postcode":"4690",
    "sg:province":"Danmark",
    "wof:name":"Kirkeligt Samfund og Den grundtvigske H\u00f8jskolekreds for Haslev og Omegn",
    "wof:placetype":"venue"
},
  "geometry": {"coordinates":[11.9678049088,55.3230895996],"type":"Point"}
}