{
  "type": "Feature",
  "properties": {
    "addr:full":"Vester Voldgade 10 K\u00f8benhavn Danmark 1552",
    "addr:housenumber":"10;1552",
    "addr:street":"Vester Voldgade",
    "iso:country":"DK",
    "sg:address":"Vester Voldgade 10",
    "sg:city":"K\u00f8benhavn",
    "sg:orig_category":"Rejsebureauer",
    "sg:phone":"+45 33 11 15 01",
    "sg:postcode":"1552",
    "sg:province":"Danmark",
    "sg:website":"www.skibbyrejser.dk",
    "wof:name":"Skibby Rejser A/S",
    "wof:placetype":"venue"
},
  "geometry": {"coordinates":[12.570400238,55.6759986877],"type":"Point"}
}