{
  "type": "Feature",
  "properties": {
    "addr:full":"Krov\u00e6nget 1 A Borup Danmark 4140",
    "addr:housenumber":"1 a",
    "addr:postcode":"4140",
    "addr:street":"Krovaenget",
    "iso:country":"DK",
    "sg:address":"Krov\u00e6nget 1 A",
    "sg:city":"Borup",
    "sg:orig_category":"Malermestre",
    "sg:phone":"+45 22 35 30 96",
    "sg:postcode":"4140",
    "sg:province":"Danmark",
    "wof:name":"Jensen, Kaj",
    "wof:placetype":"venue"
},
  "geometry": {"coordinates":[11.9749145508,55.4920845032],"type":"Point"}
}