{
  "type": "Feature",
  "properties": {
    "iso:country":"DK",
    "sg:address":"Karlebyvej 104, St. Karleby",
    "sg:city":"Kirke Hyllinge",
    "sg:orig_category":"Snedkermestre",
    "sg:phone":"+45 46 40 41 75",
    "sg:postcode":"4070",
    "sg:province":"Danmark",
    "wof:name":"St. Karleby M\u00f8belsnedkeri",
    "wof:placetype":"venue"
},
  "geometry": {"coordinates":[11.9004745483,55.7080039978],"type":"Point"}
}