{
  "type": "Feature",
  "properties": {
    "addr:full":"Havnegade 2 Holb\u00e6k Danmark 4300",
    "addr:housenumber":"2",
    "addr:postcode":"4300",
    "addr:street":"Havnegade",
    "iso:country":"DK",
    "sg:address":"Havnegade 2",
    "sg:city":"Holb\u00e6k",
    "sg:orig_category":"Realkreditinstitutter",
    "sg:phone":"+45 33 12 53 00",
    "sg:postcode":"4300",
    "sg:province":"Danmark",
    "sg:website":"www.rd.dk",
    "wof:name":"Realkredit Danmark",
    "wof:placetype":"venue"
},
  "geometry": {"coordinates":[11.7080831528,55.7190742493],"type":"Point"}
}