{
  "type": "Feature",
  "properties": {
    "addr:full":"Fmd.: Inger Giver, Vagtelvej 5 Hinnerup Danmark 8382",
    "addr:housenumber":"5",
    "addr:postcode":"8382",
    "addr:street":"Vagtelvej",
    "iso:country":"DK",
    "sg:address":"Fmd.: Inger Giver, Vagtelvej 5",
    "sg:city":"Hinnerup",
    "sg:orig_category":"Hobbybetonede foreninger",
    "sg:phone":"+45 86 91 22 86",
    "sg:postcode":"8382",
    "sg:province":"Danmark",
    "wof:name":"Bridgeklubben i Hinnerup",
    "wof:placetype":"venue"
},
  "geometry": {"coordinates":[10.0614156723,56.2650604248],"type":"Point"}
}