{
  "type": "Feature",
  "properties": {
    "addr:full":"Klovenbjergvej 8, Annisse Helsinge Danmark 3200",
    "addr:housenumber":"8",
    "addr:postcode":"3200",
    "addr:street":"Klovenbjergvej",
    "iso:country":"DK",
    "sg:address":"Klovenbjergvej 8, Annisse",
    "sg:city":"Helsinge",
    "sg:orig_category":"Hospitalsudstyr",
    "sg:phone":"+45 48 28 66 66",
    "sg:postcode":"3200",
    "sg:province":"Danmark",
    "sg:website":"www.mls.dk",
    "wof:name":"MLS - Medical A/S",
    "wof:placetype":"venue"
},
  "geometry": {"coordinates":[12.196846962,56.0224456787],"type":"Point"}
}