{
  "type": "Feature",
  "properties": {
    "addr:full":"Bredgade 11 Roskilde Danmark 4000",
    "addr:housenumber":"11",
    "addr:postcode":"4000",
    "addr:street":"Bredgade",
    "iso:country":"DK",
    "sg:address":"Bredgade 11",
    "sg:city":"Roskilde",
    "sg:orig_category":"Rejsebureauer",
    "sg:phone":"+45 46 35 08 15",
    "sg:postcode":"4000",
    "sg:province":"Danmark",
    "wof:name":"Andersen Bustrafik ApS",
    "wof:placetype":"venue"
},
  "geometry": {"coordinates":[12.0792531967,55.6393585205],"type":"Point"}
}