{
  "type": "Feature",
  "properties": {
    "addr:full":"Vangeboled 9, S\u00f8ller\u00f8d Holte Danmark 2840",
    "addr:housenumber":"9",
    "addr:postcode":"2840",
    "addr:street":"Vangeboled",
    "iso:country":"DK",
    "sg:address":"Vangeboled 9, S\u00f8ller\u00f8d",
    "sg:city":"Holte",
    "sg:orig_category":"Kommunale folkeskoler",
    "sg:phone":"+45 45 80 20 65",
    "sg:postcode":"2840",
    "sg:province":"Danmark",
    "sg:website":"www.vangeboskolen.dk",
    "wof:name":"Vangeboskolen",
    "wof:placetype":"venue"
},
  "geometry": {"coordinates":[12.4706554413,55.8122367859],"type":"Point"}
}