{
  "type": "Feature",
  "properties": {
    "iso:country":"DK",
    "sg:address":"Farum Hovedgade 42",
    "sg:city":"Farum",
    "sg:orig_category":"Bodegaer",
    "sg:phone":"+45 44 95 05 14",
    "sg:postcode":"3520",
    "sg:province":"Danmark",
    "wof:name":"Farum Kro & Cafe",
    "wof:placetype":"venue"
},
  "geometry": {"coordinates":[12.3674058914,55.8112831116],"type":"Point"}
}