{
  "type": "Feature",
  "properties": {
    "addr:full":"Velling Kirkeby 48, Velling Ringk\u00f8bing Danmark 6950",
    "addr:housenumber":"48",
    "addr:postcode":"6950",
    "addr:street":"Velling Kirkeby",
    "iso:country":"DK",
    "sg:address":"Velling Kirkeby 48, Velling",
    "sg:city":"Ringk\u00f8bing",
    "sg:orig_category":"Efterskoler",
    "sg:phone":"+45 97 32 16 88",
    "sg:postcode":"6950",
    "sg:province":"Danmark",
    "sg:website":"www.fjordvangungdomsskole.dk",
    "wof:name":"Fjordvang Ungdomsskole",
    "wof:placetype":"venue"
},
  "geometry": {"coordinates":[8.2507953644,56.0878334045],"type":"Point"}
}