{
  "type": "Feature",
  "properties": {
    "addr:full":"Kirkestr\u00e6de 4  N\u00e6stved Danmark 4700",
    "addr:housenumber":"4",
    "addr:postcode":"4700",
    "addr:street":"Kirkestraede",
    "iso:country":"DK",
    "sg:address":"Kirkestr\u00e6de 4 ",
    "sg:city":"N\u00e6stved",
    "sg:classifiers":[
        {
            "category":"Food & Beverages",
            "subcategory":"Groceries & Convenience Stores",
            "type":"Retail Goods"
        }
    ],
    "sg:phone":"+45 55 72 22 00",
    "sg:postcode":"4700",
    "sg:province":"Danmark",
    "sg:tags":[
        "drink"
    ],
    "wof:name":"LORANGE VINHANDEL A/S",
    "wof:placetype":"venue"
},
  "geometry": {"coordinates":[-73.5173797607,42.0011787415],"type":"Point"}
}