{
  "type": "Feature",
  "properties": {
    "addr:full":"K\u00f8benhavnsvej 150 - 152 Roskilde Danmark 4000",
    "addr:housenumber":"150 152",
    "addr:postcode":"4000",
    "addr:street":"Kobenhavnsvej",
    "iso:country":"DK",
    "sg:address":"K\u00f8benhavnsvej 150 - 152",
    "sg:city":"Roskilde",
    "sg:orig_category":"Autoopretning",
    "sg:phone":"+45 46 75 51 83",
    "sg:postcode":"4000",
    "sg:province":"Danmark",
    "wof:name":"Roskilde Vogn- & Karrosserifabrik I/S",
    "wof:placetype":"venue"
},
  "geometry": {"coordinates":[12.1195573807,55.64270401],"type":"Point"}
}