{
  "type": "Feature",
  "properties": {
    "addr:full":"\u00c5sh\u00f8jvej 46 K\u00f8ge Danmark 4600",
    "addr:housenumber":"46",
    "addr:postcode":"4600",
    "addr:street":"Aashojvej",
    "iso:country":"DK",
    "sg:address":"\u00c5sh\u00f8jvej 46",
    "sg:city":"K\u00f8ge",
    "sg:orig_category":"Psykologer, praktiserende",
    "sg:phone":"+45 56 63 13 63",
    "sg:postcode":"4600",
    "sg:province":"Danmark",
    "wof:name":"Jebro, Lise",
    "wof:placetype":"venue"
},
  "geometry": {"coordinates":[43.3657913208,42.3115196228],"type":"Point"}
}