{
  "type": "Feature",
  "properties": {
    "addr:full":"Sletten 3 Holstebro Danmark 7500",
    "addr:housenumber":"3",
    "addr:postcode":"7500",
    "addr:street":"Sletten",
    "iso:country":"DK",
    "sg:address":"Sletten 3",
    "sg:city":"Holstebro",
    "sg:orig_category":"Autoforhandlere",
    "sg:phone":"+45 97 42 11 55",
    "sg:postcode":"7500",
    "sg:province":"Danmark",
    "sg:website":"www.nissan.dk/holstebro",
    "wof:name":"Henriksen, Ib Biler",
    "wof:placetype":"venue"
},
  "geometry": {"coordinates":[8.6531801224,56.3601799011],"type":"Point"}
}