{
  "type": "Feature",
  "properties": {
    "iso:country":"DK",
    "sg:address":"v/ Erik S. S\u00f8rensen, Vester\u00f8 Havnegade 34, Vester\u00f8 Havn",
    "sg:city":"L\u00e6s\u00f8",
    "sg:orig_category":"Hobbybetonede foreninger",
    "sg:phone":"+45 98 49 92 53",
    "sg:postcode":"9940",
    "sg:province":"Danmark",
    "wof:name":"Biavlerforeningen L\u00e6s\u00f8",
    "wof:placetype":"venue"
},
  "geometry": {"coordinates":[10.9232254028,57.2928199768],"type":"Point"}
}