{
  "type": "Feature",
  "properties": {
    "addr:full":"S\u00f8ndergade 30 Kolding Danmark 6000",
    "addr:housenumber":"30",
    "addr:postcode":"6000",
    "addr:street":"Sondergade",
    "iso:country":"DK",
    "sg:address":"S\u00f8ndergade 30",
    "sg:city":"Kolding",
    "sg:orig_category":"Materialister",
    "sg:phone":"+45 75 53 86 22",
    "sg:postcode":"6000",
    "sg:province":"Danmark",
    "wof:name":"Matas",
    "wof:placetype":"venue"
},
  "geometry": {"coordinates":[9.4723300934,55.4869117737],"type":"Point"}
}