{
  "type": "Feature",
  "properties": {
    "addr:full":"Vestergade 83 \u00c5rhus C Danmark 8000",
    "addr:housenumber":"83",
    "addr:postcode":"8000",
    "addr:street":"Vestergade",
    "iso:country":"DK",
    "sg:address":"Vestergade 83",
    "sg:city":"\u00c5rhus C",
    "sg:orig_category":"Arkitekter",
    "sg:phone":"+45 86 20 92 11",
    "sg:postcode":"8000",
    "sg:province":"Danmark",
    "wof:name":"Eriksen Arkitekter",
    "wof:placetype":"venue"
},
  "geometry": {"coordinates":[9.5455904007,56.1682090759],"type":"Point"}
}