{
  "type": "Feature",
  "properties": {
    "addr:full":"Nyvangvej 11, Toghale T\u00f8nder Danmark 6270",
    "addr:housenumber":"11",
    "addr:postcode":"6270",
    "addr:street":"Nyvangvej",
    "iso:country":"DK",
    "sg:address":"Nyvangvej 11, Toghale",
    "sg:city":"T\u00f8nder",
    "sg:orig_category":"Uldforhandlere",
    "sg:phone":"+45 74 73 85 34",
    "sg:postcode":"6270",
    "sg:province":"Danmark",
    "wof:name":"Uldg\u00e5rden",
    "wof:placetype":"venue"
},
  "geometry": {"coordinates":[8.8009996414,54.9552383423],"type":"Point"}
}