{
  "type": "Feature",
  "properties": {
    "addr:full":"Frederiksberggade 2,1 K\u00f8benhavn Danmark 1459",
    "addr:housenumber":"2,1;1459",
    "addr:street":"Frederiksberggade",
    "iso:country":"DK",
    "sg:address":"Frederiksberggade 2,1",
    "sg:city":"K\u00f8benhavn",
    "sg:orig_category":"Advokater",
    "sg:phone":"+45 33 33 79 13",
    "sg:postcode":"1459",
    "sg:province":"Danmark",
    "wof:name":"Hjort, Vivian",
    "wof:placetype":"venue"
},
  "geometry": {"coordinates":[12.5700597763,55.6768302917],"type":"Point"}
}