{
  "type": "Feature",
  "properties": {
    "addr:full":"Bugattivej 4 Vejle Danmark 7100",
    "addr:housenumber":"4",
    "addr:postcode":"7100",
    "addr:street":"Bugattivej",
    "iso:country":"DK",
    "sg:address":"Bugattivej 4",
    "sg:city":"Vejle",
    "sg:orig_category":"Autoforhandlere",
    "sg:phone":"+45 75 85 78 88",
    "sg:postcode":"7100",
    "sg:province":"Danmark",
    "wof:name":"Haargaard A/S, A.",
    "wof:placetype":"venue"
},
  "geometry": {"coordinates":[9.5368051529,55.7113952637],"type":"Point"}
}