{
  "type": "Feature",
  "properties": {
    "addr:full":"Solvej 7 Ballerup Danmark 2750",
    "addr:housenumber":"7",
    "addr:postcode":"2750",
    "addr:street":"Solvej",
    "iso:country":"DK",
    "sg:address":"Solvej 7",
    "sg:city":"Ballerup",
    "sg:orig_category":"Malermestre",
    "sg:phone":"+45 44 65 61 16",
    "sg:postcode":"2750",
    "sg:province":"Danmark",
    "wof:name":"Schildahl, Svend",
    "wof:placetype":"venue"
},
  "geometry": {"coordinates":[12.3639163971,55.7284584045],"type":"Point"}
}