{
  "type": "Feature",
  "properties": {
    "iso:country":"DK",
    "sg:address":"Bygmestervej 8 ",
    "sg:city":"Hadsund",
    "sg:classifiers":[
        {
            "category":"Building & Trades",
            "subcategory":"Construction",
            "type":"Services"
        }
    ],
    "sg:phone":"+45 98 57 18 55",
    "sg:postcode":"9560",
    "sg:province":"Danmark",
    "sg:tags":[
        "work",
        "public"
    ],
    "wof:name":"NIELS RIISBERG A/S",
    "wof:placetype":"venue"
},
  "geometry": {"coordinates":[10.1075277328,56.7311592102],"type":"Point"}
}