{
  "type": "Feature",
  "properties": {
    "addr:full":"H\u00f8egh Guldbergs Gade 48 Horsens Danmark 8700",
    "addr:housenumber":"48",
    "addr:postcode":"8700",
    "addr:street":"Hoegh Guldbergs Gade",
    "iso:country":"DK",
    "sg:address":"H\u00f8egh Guldbergs Gade 48",
    "sg:city":"Horsens",
    "sg:orig_category":"Autoforhandlere",
    "sg:phone":"+45 75 62 35 11",
    "sg:postcode":"8700",
    "sg:province":"Danmark",
    "wof:name":"Peugeot Horsens",
    "wof:placetype":"venue"
},
  "geometry": {"coordinates":[9.8469820023,55.8506317139],"type":"Point"}
}