{
  "type": "Feature",
  "properties": {
    "addr:full":"Bredgade 5 Br\u00f8nderslev Danmark 9700",
    "addr:housenumber":"5",
    "addr:postcode":"9700",
    "addr:street":"Bredgade",
    "iso:country":"DK",
    "sg:address":"Bredgade 5",
    "sg:city":"Br\u00f8nderslev",
    "sg:orig_category":"Advokater",
    "sg:phone":"+45 98 82 55 44",
    "sg:postcode":"9700",
    "sg:province":"Danmark",
    "wof:name":"Skaarup, Advokatfirmaet Henrik",
    "wof:placetype":"venue"
},
  "geometry": {"coordinates":[9.9458770752,57.2699508667],"type":"Point"}
}