{
  "type": "Feature",
  "properties": {
    "addr:full":"Casinotorvet 4 Slagelse Danmark 4200",
    "addr:housenumber":"4",
    "addr:postcode":"4200",
    "addr:street":"Casinotorvet",
    "iso:country":"DK",
    "sg:address":"Casinotorvet 4",
    "sg:city":"Slagelse",
    "sg:classifiers":[
        {
            "category":"Restaurant",
            "type":"Food & Drink"
        }
    ],
    "sg:phone":"+45 58 53 44 43",
    "sg:postcode":"4200",
    "sg:province":"Danmark",
    "wof:name":"Bella Milano's Cafe & Pizzaria",
    "wof:placetype":"venue"
},
  "geometry": {"coordinates":[11.3540897369,55.4055252075],"type":"Point"}
}