{
  "type": "Feature",
  "properties": {
    "addr:full":"Kirketoften 5 Hobro Danmark 9500",
    "addr:housenumber":"5",
    "addr:postcode":"9500",
    "addr:street":"Kirketoften",
    "iso:country":"DK",
    "sg:address":"Kirketoften 5",
    "sg:city":"Hobro",
    "sg:orig_category":"Arbejdsmarkedsuddannelser",
    "sg:phone":"+45 98 51 23 88",
    "sg:postcode":"9500",
    "sg:province":"Danmark",
    "sg:website":"www.amuaalborg.dk",
    "wof:name":"AMU-Center Hobro",
    "wof:placetype":"venue"
},
  "geometry": {"coordinates":[9.8284320831,56.6315002441],"type":"Point"}
}