{
  "type": "Feature",
  "properties": {
    "addr:full":"Stendyssevej 16 Lynge Danmark 3540",
    "addr:housenumber":"16",
    "addr:postcode":"3540",
    "addr:street":"Stendyssevej",
    "iso:country":"DK",
    "sg:address":"Stendyssevej 16",
    "sg:city":"Lynge",
    "sg:orig_category":"Zoneterapeuter",
    "sg:phone":"+45 20 29 03 12",
    "sg:postcode":"3540",
    "sg:province":"Danmark",
    "wof:name":"Nielsen, Janni",
    "wof:placetype":"venue"
},
  "geometry": {"coordinates":[12.2842817307,55.8411178589],"type":"Point"}
}