{
  "type": "Feature",
  "properties": {
    "addr:full":"Fmd.: Mogens Svane, Sor\u00f8vej 15 Herning Danmark 7400",
    "addr:housenumber":"15",
    "addr:postcode":"7400",
    "addr:street":"Sorovej",
    "iso:country":"DK",
    "sg:address":"Fmd.: Mogens Svane, Sor\u00f8vej 15",
    "sg:city":"Herning",
    "sg:orig_category":"Spejderkorps",
    "sg:phone":"+45 97 21 15 86",
    "sg:postcode":"7400",
    "sg:province":"Danmark",
    "wof:name":"Det Danske Spejderkorps Herningholmgruppe",
    "wof:placetype":"venue"
},
  "geometry": {"coordinates":[8.9768896103,56.1374168396],"type":"Point"}
}