{
  "type": "Feature",
  "properties": {
    "addr:full":"Heln\u00e6svej 9, Agern\u00e6s Ebberup Danmark 5631",
    "addr:housenumber":"9",
    "addr:postcode":"5631",
    "addr:street":"Helnaesvej",
    "iso:country":"DK",
    "sg:address":"Heln\u00e6svej 9, Agern\u00e6s",
    "sg:city":"Ebberup",
    "sg:orig_category":"Kursussteder",
    "sg:phone":"+45 63 73 73 73",
    "sg:postcode":"5631",
    "sg:province":"Danmark",
    "sg:website":"www.gl-avernaes.dk",
    "wof:name":"Gl. Avern\u00e6s",
    "wof:placetype":"venue"
},
  "geometry": {"coordinates":[9.9818639755,55.2415733337],"type":"Point"}
}