{
  "type": "Feature",
  "properties": {
    "addr:full":"Herlev Hovedgade 234 Herlev Danmark 2730",
    "addr:housenumber":"234",
    "addr:postcode":"2730",
    "addr:street":"Herlev Hovedgade",
    "iso:country":"DK",
    "sg:address":"Herlev Hovedgade 234",
    "sg:city":"Herlev",
    "sg:orig_category":"Benzinstationer",
    "sg:phone":"+45 44 84 23 49",
    "sg:postcode":"2730",
    "sg:province":"Danmark",
    "wof:name":"Q8 Service",
    "wof:placetype":"venue"
},
  "geometry": {"coordinates":[12.41686,55.725891],"type":"Point"}
}