{
  "type": "Feature",
  "properties": {
    "addr:full":"Idylvej 5, Postboks 72 Thisted Danmark 7700",
    "addr:housenumber":"5;72",
    "addr:postcode":"7700",
    "addr:street":"Idylvej",
    "iso:country":"DK",
    "sg:address":"Idylvej 5, Postboks 72",
    "sg:city":"Thisted",
    "sg:orig_category":"Arkitekter",
    "sg:phone":"+45 97 92 15 44",
    "sg:postcode":"7700",
    "sg:province":"Danmark",
    "wof:name":"Raaby's Tegnestue, J\u00f8rgen",
    "wof:placetype":"venue"
},
  "geometry": {"coordinates":[8.6919784546,56.9556121826],"type":"Point"}
}