{
  "type": "Feature",
  "properties": {
    "addr:full":"Simmerb\u00f8lle Kirkevej 17, Simmerb\u00f8lle Rudk\u00f8bing Danmark 5900",
    "addr:housenumber":"17",
    "addr:postcode":"5900",
    "addr:street":"Kirkevej",
    "iso:country":"DK",
    "sg:address":"Simmerb\u00f8lle Kirkevej 17, Simmerb\u00f8lle",
    "sg:city":"Rudk\u00f8bing",
    "sg:orig_category":"Boligudlejning",
    "sg:phone":"+45 62 51 53 36",
    "sg:postcode":"5900",
    "sg:province":"Danmark",
    "wof:name":"Eriksen, Henrik Gr\u00e5kj\u00e6r",
    "wof:placetype":"venue"
},
  "geometry": {"coordinates":[-114.0767440796,46.4432487488],"type":"Point"}
}