{
  "type": "Feature",
  "properties": {
    "addr:full":"Strandbakken 64, Veddinge F\u00e5revejle Danmark 4540",
    "addr:housenumber":"64",
    "addr:postcode":"4540",
    "addr:street":"Strandbakken",
    "iso:country":"DK",
    "sg:address":"Strandbakken 64, Veddinge",
    "sg:city":"F\u00e5revejle",
    "sg:orig_category":"Arkitekter",
    "sg:phone":"+45 59 65 43 33",
    "sg:postcode":"4540",
    "sg:province":"Danmark",
    "wof:name":"Gabriel, J\u00f8rgen",
    "wof:placetype":"venue"
},
  "geometry": {"coordinates":[11.4679298401,55.7857704163],"type":"Point"}
}