{
  "type": "Feature",
  "properties": {
    "addr:full":"\u00d8stergade 33 \u00c5rhus C Danmark 8000",
    "addr:housenumber":"33",
    "addr:postcode":"8000",
    "addr:street":"Ostergade",
    "iso:country":"DK",
    "sg:address":"\u00d8stergade 33",
    "sg:city":"\u00c5rhus C",
    "sg:orig_category":"Ejendomshandel",
    "sg:phone":"+45 86 76 03 00",
    "sg:postcode":"8000",
    "sg:province":"Danmark",
    "wof:name":"DanBolig Erhverv",
    "wof:placetype":"venue"
},
  "geometry": {"coordinates":[4.717400074,49.7588005066],"type":"Point"}
}