{
  "type": "Feature",
  "properties": {
    "iso:country":"DK",
    "sg:address":"Vesterhavsgade 111",
    "sg:city":"Esbjerg",
    "sg:orig_category":"Maskinfabrikker",
    "sg:phone":"+45 75 13 64 90",
    "sg:postcode":"6700",
    "sg:province":"Danmark",
    "wof:name":"P H Maskinfabrik",
    "wof:placetype":"venue"
},
  "geometry": {"coordinates":[8.4314527512,55.473575592],"type":"Point"}
}