{
  "type": "Feature",
  "properties": {
    "iso:country":"DK",
    "sg:address":"v/ Otto Nielsen, Kalbyvejen 11",
    "sg:city":"Aakirkeby",
    "sg:orig_category":"\u00c3\u2020ldreorganisationer og klubber",
    "sg:phone":"+45 56 97 42 72",
    "sg:postcode":"3720",
    "sg:province":"Danmark",
    "wof:name":"Aakirkeby Pensionistforening",
    "wof:placetype":"venue"
},
  "geometry": {"coordinates":[14.9202880859,55.070110321],"type":"Point"}
}