{
  "type": "Feature",
  "properties": {
    "addr:full":"Pugdalvej 2 Vildbjerg Danmark 7480",
    "addr:housenumber":"2",
    "addr:postcode":"7480",
    "addr:street":"Pugdalvej",
    "iso:country":"DK",
    "sg:address":"Pugdalvej 2",
    "sg:city":"Vildbjerg",
    "sg:orig_category":"Korn og foderstoffer",
    "sg:phone":"+45 97 13 13 22",
    "sg:postcode":"7480",
    "sg:province":"Danmark",
    "wof:name":"Vildbjerg M\u00f8lle A/S",
    "wof:placetype":"venue"
},
  "geometry": {"coordinates":[8.7725543976,56.201789856],"type":"Point"}
}