{
  "type": "Feature",
  "properties": {
    "iso:country":"DK",
    "sg:address":"Baslund 29",
    "sg:city":"Vejen",
    "sg:orig_category":"Reklamebureauer",
    "sg:phone":"+45 75 36 76 11",
    "sg:postcode":"6600",
    "sg:province":"Danmark",
    "wof:name":"Freelance Reklame",
    "wof:placetype":"venue"
},
  "geometry": {"coordinates":[9.0868368149,55.4723587036],"type":"Point"}
}