{
  "type": "Feature",
  "properties": {
    "addr:full":"M\u00f8llergade 87 1 Svendborg Danmark 5700",
    "addr:housenumber":"87 1",
    "addr:postcode":"5700",
    "addr:street":"Mollergade",
    "iso:country":"DK",
    "sg:address":"M\u00f8llergade 87 1",
    "sg:city":"Svendborg",
    "sg:orig_category":"Teatre",
    "sg:phone":"+45 62 20 21 02",
    "sg:postcode":"5700",
    "sg:province":"Danmark",
    "wof:name":"Svendborg B\u00f8rne- og Ungdomsteater",
    "wof:placetype":"venue"
},
  "geometry": {"coordinates":[10.6130065918,55.0638694763],"type":"Point"}
}