{
  "type": "Feature",
  "properties": {
    "iso:country":"DK",
    "sg:address":"K\u00e6rl\u00f8bervej 11",
    "sg:city":"Klarup",
    "sg:orig_category":"Sengeudstyr",
    "sg:phone":"+45 98 31 99 80",
    "sg:postcode":"9270",
    "sg:province":"Danmark",
    "wof:name":"Magnet Senget\u00f8j",
    "wof:placetype":"venue"
},
  "geometry": {"coordinates":[10.047555,57.013649],"type":"Point"}
}