{
  "type": "Feature",
  "properties": {
    "addr:full":"Hesselbjergvej 38 A, R\u00e5geleje Vejby Danmark 3210",
    "addr:housenumber":"38 a",
    "addr:postcode":"3210",
    "addr:street":"Hesselbjergvej;Raageleje",
    "iso:country":"DK",
    "sg:address":"Hesselbjergvej 38 A, R\u00e5geleje",
    "sg:city":"Vejby",
    "sg:orig_category":"Import-eksport",
    "sg:phone":"+45 48 71 48 18",
    "sg:postcode":"3210",
    "sg:province":"Danmark",
    "wof:name":"Hansen Form International",
    "wof:placetype":"venue"
},
  "geometry": {"coordinates":[12.1534852982,56.0930938721],"type":"Point"}
}