{
  "type": "Feature",
  "properties": {
    "addr:full":"T\u00f8jhushavevej 28 Randers Danmark 8900",
    "addr:housenumber":"28",
    "addr:postcode":"8900",
    "addr:street":"Tojhushavevej",
    "iso:country":"DK",
    "sg:address":"T\u00f8jhushavevej 28",
    "sg:city":"Randers",
    "sg:orig_category":"Private skoler",
    "sg:phone":"+45 86 42 20 10",
    "sg:postcode":"8900",
    "sg:province":"Danmark",
    "wof:name":"Randers Lille Skole",
    "wof:placetype":"venue"
},
  "geometry": {"coordinates":[10.0476379395,56.4633903503],"type":"Point"}
}