{
  "type": "Feature",
  "properties": {
    "iso:country":"DK",
    "sg:address":"Center Boulevard 5",
    "sg:city":"K\u00f8benhavn S",
    "sg:orig_category":"Diners transportables",
    "sg:phone":"+45 32 52 90 00",
    "sg:postcode":"2300",
    "sg:province":"Danmark",
    "wof:name":"Bella Center Restauranter",
    "wof:placetype":"venue"
},
  "geometry": {"coordinates":[12.5774450302,55.6380653381],"type":"Point"}
}