{
  "type": "Feature",
  "properties": {
    "addr:full":"Skolevej 37, Knabstrup M\u00f8rk\u00f8v Danmark 4440",
    "addr:housenumber":"37",
    "addr:postcode":"4440",
    "addr:street":"Skolevej",
    "iso:country":"DK",
    "sg:address":"Skolevej 37, Knabstrup",
    "sg:city":"M\u00f8rk\u00f8v",
    "sg:orig_category":"Skolefritidsordninger",
    "sg:phone":"+45 59 27 32 66",
    "sg:postcode":"4440",
    "sg:province":"Danmark",
    "wof:name":"Kirseb\u00e6rhaven Aldersintegreret B\u00f8rneinstitution",
    "wof:placetype":"venue"
},
  "geometry": {"coordinates":[11.4997396469,55.6530609131],"type":"Point"}
}