{
  "type": "Feature",
  "properties": {
    "addr:full":"Firhuse 1, Vedbys\u00f8nder Slagelse Danmark 4200",
    "addr:housenumber":"1",
    "addr:postcode":"4200",
    "addr:street":"Firhuse;Vedbysonder",
    "iso:country":"DK",
    "sg:address":"Firhuse 1, Vedbys\u00f8nder",
    "sg:city":"Slagelse",
    "sg:orig_category":"INGENI\u00c3\u02dcRER",
    "sg:phone":"+45 58 54 42 32",
    "sg:postcode":"4200",
    "sg:province":"Danmark",
    "wof:name":"Anderberg Engineering ApS",
    "wof:placetype":"venue"
},
  "geometry": {"coordinates":[11.3569850922,55.4050865173],"type":"Point"}
}