{
  "type": "Feature",
  "properties": {
    "addr:full":"Djurslandskajen 1 Grenaa Danmark 8500",
    "addr:housenumber":"1",
    "addr:postcode":"8500",
    "addr:street":"Djurslandskajen",
    "iso:country":"DK",
    "sg:address":"Djurslandskajen 1",
    "sg:city":"Grenaa",
    "sg:orig_category":"Korn og foderstoffer",
    "sg:phone":"+45 86 33 42 22",
    "sg:postcode":"8500",
    "sg:province":"Danmark",
    "sg:website":"www.kfk.dk",
    "wof:name":"Korn- og Foderstof Kompagniet, Aktieselskabet",
    "wof:placetype":"venue"
},
  "geometry": {"coordinates":[10.9224624634,56.4147796631],"type":"Point"}
}