{
  "type": "Feature",
  "properties": {
    "addr:full":"B\u00e6kg\u00e5rdsvej 53 Borup Danmark 4140",
    "addr:housenumber":"53",
    "addr:postcode":"4140",
    "addr:street":"Baekgaardsvej",
    "iso:country":"DK",
    "sg:address":"B\u00e6kg\u00e5rdsvej 53",
    "sg:city":"Borup",
    "sg:orig_category":"Asfaltprodukter",
    "sg:phone":"+45 57 52 63 35",
    "sg:postcode":"4140",
    "sg:province":"Danmark",
    "sg:website":"www.borupkemi.dk",
    "wof:name":"Borup Kemi I/S",
    "wof:placetype":"venue"
},
  "geometry": {"coordinates":[11.9749145508,55.4920845032],"type":"Point"}
}