{
  "type": "Feature",
  "properties": {
    "addr:full":"\u00d8stergade 6, Postboks 141 Middelfart Danmark 5500",
    "addr:housenumber":"6;141",
    "addr:postcode":"5500",
    "addr:street":"Ostergade",
    "iso:country":"DK",
    "sg:address":"\u00d8stergade 6, Postboks 141",
    "sg:city":"Middelfart",
    "sg:orig_category":"INGENI\u00c3\u02dcRER",
    "sg:phone":"+45 63 41 35 55",
    "sg:postcode":"5500",
    "sg:province":"Danmark",
    "wof:name":"Dan Mach Engineering",
    "wof:placetype":"venue"
},
  "geometry": {"coordinates":[9.7417497635,55.5030250549],"type":"Point"}
}