{
  "type": "Feature",
  "properties": {
    "addr:full":"Gammelbyvej 10, F\u00e5rup Jelling Danmark 7300",
    "addr:housenumber":"10",
    "addr:postcode":"7300",
    "addr:street":"Gammelbyvej;Faarup",
    "iso:country":"DK",
    "sg:address":"Gammelbyvej 10, F\u00e5rup",
    "sg:city":"Jelling",
    "sg:orig_category":"Planteskoler",
    "sg:phone":"+45 75 87 11 07",
    "sg:postcode":"7300",
    "sg:province":"Danmark",
    "wof:name":"Bondes Planteskole",
    "wof:placetype":"venue"
},
  "geometry": {"coordinates":[9.4184103012,55.7558555603],"type":"Point"}
}