{
  "type": "Feature",
  "properties": {
    "addr:full":"Svinget 6 Esperg\u00e6rde Danmark 3060",
    "addr:housenumber":"6",
    "addr:postcode":"3060",
    "addr:street":"Svinget",
    "iso:country":"DK",
    "sg:address":"Svinget 6",
    "sg:city":"Esperg\u00e6rde",
    "sg:orig_category":"Revisorer",
    "sg:phone":"+45 49 13 22 69",
    "sg:postcode":"3060",
    "sg:province":"Danmark",
    "wof:name":"J\u00f8rgensen, Henning Bjerregaard",
    "wof:placetype":"venue"
},
  "geometry": {"coordinates":[11.6512403488,47.8390617371],"type":"Point"}
}