{
  "type": "Feature",
  "properties": {
    "iso:country":"DK",
    "sg:address":"v/ Verner Knudsen, Elmevej 12",
    "sg:city":"Glostrup",
    "sg:orig_category":"\u00c3\u2020ldreorganisationer og klubber",
    "sg:phone":"+45 43 45 28 63",
    "sg:postcode":"2600",
    "sg:province":"Danmark",
    "wof:name":"Glostrup Pensionistforening",
    "wof:placetype":"venue"
},
  "geometry": {"coordinates":[12.3957901001,55.6654663086],"type":"Point"}
}