{
  "type": "Feature",
  "properties": {
    "addr:full":"Skomagervej 1 Vejle Danmark 7100",
    "addr:housenumber":"1",
    "addr:postcode":"7100",
    "addr:street":"Skomagervej",
    "iso:country":"DK",
    "sg:address":"Skomagervej 1",
    "sg:city":"Vejle",
    "sg:orig_category":"Kontormaskiner",
    "sg:phone":"+45 70 10 36 66",
    "sg:postcode":"7100",
    "sg:province":"Danmark",
    "wof:name":"Xerox Partner",
    "wof:placetype":"venue"
},
  "geometry": {"coordinates":[9.5368051529,55.7113952637],"type":"Point"}
}