{
  "type": "Feature",
  "properties": {
    "addr:full":"N\u00f8rregade 32 Varde Danmark 6800",
    "addr:housenumber":"32",
    "addr:postcode":"6800",
    "addr:street":"Norregade",
    "iso:country":"DK",
    "sg:address":"N\u00f8rregade 32",
    "sg:city":"Varde",
    "sg:orig_category":"Antikviteter",
    "sg:phone":"+45 75 21 15 00",
    "sg:postcode":"6800",
    "sg:province":"Danmark",
    "sg:website":"www.vestjyskantik.dk",
    "wof:name":"Vestjysk Antik A/S",
    "wof:placetype":"venue"
},
  "geometry": {"coordinates":[8.4801998138,55.6236419678],"type":"Point"}
}