{
  "type": "Feature",
  "properties": {
    "addr:full":"Baltorpvej 22 Ballerup Danmark 2750",
    "addr:housenumber":"22",
    "addr:postcode":"2750",
    "addr:street":"Baltorpvej",
    "iso:country":"DK",
    "sg:address":"Baltorpvej 22",
    "sg:city":"Ballerup",
    "sg:orig_category":"Grillbarer",
    "sg:phone":"+45 44 65 68 35",
    "sg:postcode":"2750",
    "sg:province":"Danmark",
    "wof:name":"Ballerup Kinesisk Grill og Cafeteria",
    "wof:placetype":"venue"
},
  "geometry": {"coordinates":[12.3502902985,55.7299385071],"type":"Point"}
}