{
  "type": "Feature",
  "properties": {
    "addr:full":"Randager 1 Albertslund Danmark 2620",
    "addr:housenumber":"1",
    "addr:postcode":"2620",
    "addr:street":"Randager",
    "iso:country":"DK",
    "sg:address":"Randager 1",
    "sg:city":"Albertslund",
    "sg:orig_category":"Dagplejeformidling",
    "sg:phone":"+45 43 64 25 11",
    "sg:postcode":"2620",
    "sg:province":"Danmark",
    "wof:name":"Dagplejecentret",
    "wof:placetype":"venue"
},
  "geometry": {"coordinates":[12.3386697769,55.668762207],"type":"Point"}
}