{
  "type": "Feature",
  "properties": {
    "addr:full":"Reberbansgade 12 A Aalborg Danmark 9000",
    "addr:housenumber":"12 a",
    "addr:postcode":"9000",
    "addr:street":"Reberbansgade",
    "iso:country":"DK",
    "sg:address":"Reberbansgade 12 A",
    "sg:city":"Aalborg",
    "sg:orig_category":"Blomsterhandlere",
    "sg:phone":"+45 98 11 36 33",
    "sg:postcode":"9000",
    "sg:province":"Danmark",
    "wof:name":"Anettes Blomster",
    "wof:placetype":"venue"
},
  "geometry": {"coordinates":[9.913684845,57.0495300293],"type":"Point"}
}