{
  "type": "Feature",
  "properties": {
    "addr:full":"Haverslevvej 85, Aarestrup Sk\u00f8rping Danmark 9520",
    "addr:housenumber":"85",
    "addr:postcode":"9520",
    "addr:street":"Haverslevvej",
    "iso:country":"DK",
    "sg:address":"Haverslevvej 85, Aarestrup",
    "sg:city":"Sk\u00f8rping",
    "sg:orig_category":"Brugsforeninger",
    "sg:phone":"+45 98 37 50 12",
    "sg:postcode":"9520",
    "sg:province":"Danmark",
    "wof:name":"\u00c5restrup N\u00e6rbutik",
    "wof:placetype":"venue"
},
  "geometry": {"coordinates":[9.8477077484,56.8337860107],"type":"Point"}
}