{
  "type": "Feature",
  "properties": {
    "addr:full":"N\u00f8rregade 9 Haderslev Danmark 6100",
    "addr:housenumber":"9",
    "addr:postcode":"6100",
    "addr:street":"Norregade",
    "iso:country":"DK",
    "sg:address":"N\u00f8rregade 9",
    "sg:city":"Haderslev",
    "sg:orig_category":"Bodegaer",
    "sg:phone":"+45 74 53 09 53",
    "sg:postcode":"6100",
    "sg:province":"Danmark",
    "wof:name":"Buch's Vinstue",
    "wof:placetype":"venue"
},
  "geometry": {"coordinates":[9.4877147675,55.2504043579],"type":"Point"}
}