{
  "type": "Feature",
  "properties": {
    "addr:full":"Meterbuen 25 Skovlunde Danmark 2740",
    "addr:housenumber":"25",
    "addr:postcode":"2740",
    "addr:street":"Meterbuen",
    "iso:country":"DK",
    "sg:address":"Meterbuen 25",
    "sg:city":"Skovlunde",
    "sg:orig_category":"Bogtrykkerier",
    "sg:phone":"+45 44 91 21 11",
    "sg:postcode":"2740",
    "sg:province":"Danmark",
    "wof:name":"Colon Colour Pack A/S",
    "wof:placetype":"venue"
},
  "geometry": {"coordinates":[12.4167299271,55.718585968],"type":"Point"}
}