{
  "type": "Feature",
  "properties": {
    "addr:full":"G\u00f8rtlervej 5 Ringe Danmark 5750",
    "addr:housenumber":"5",
    "addr:postcode":"5750",
    "addr:street":"Gortlervej",
    "iso:country":"DK",
    "sg:address":"G\u00f8rtlervej 5",
    "sg:city":"Ringe",
    "sg:orig_category":"Dyreklinikker og -hospitaler",
    "sg:phone":"+45 62 62 30 01",
    "sg:postcode":"5750",
    "sg:province":"Danmark",
    "sg:website":"www.dyrlaegen.dk",
    "wof:name":"Ringe Dyrehospital",
    "wof:placetype":"venue"
},
  "geometry": {"coordinates":[10.4858722687,55.2367553711],"type":"Point"}
}