{
  "type": "Feature",
  "properties": {
    "addr:full":"Br\u00e5desbakken 1, Tved Knebel Danmark 8420",
    "addr:housenumber":"1",
    "addr:postcode":"8420",
    "addr:street":"Braadesbakken;Tved",
    "iso:country":"DK",
    "sg:address":"Br\u00e5desbakken 1, Tved",
    "sg:city":"Knebel",
    "sg:orig_category":"Autoreparation og -service",
    "sg:phone":"+45 86 35 10 30",
    "sg:postcode":"8420",
    "sg:province":"Danmark",
    "wof:name":"Tved Auto",
    "wof:placetype":"venue"
},
  "geometry": {"coordinates":[10.3770122528,56.1816596985],"type":"Point"}
}