{
  "type": "Feature",
  "properties": {
    "addr:full":"Havneplads 16 Skagen Danmark 9990",
    "addr:housenumber":"16",
    "addr:postcode":"9990",
    "addr:street":"Havneplads",
    "iso:country":"DK",
    "sg:address":"Havneplads 16",
    "sg:city":"Skagen",
    "sg:orig_category":"Supermarkeder",
    "sg:postcode":"9990",
    "sg:province":"Danmark",
    "wof:name":"Skagen Stork\u00f8b",
    "wof:placetype":"venue"
},
  "geometry": {"coordinates":[10.5873632431,57.720035553],"type":"Point"}
}