{
  "type": "Feature",
  "properties": {
    "iso:country":"DK",
    "sg:address":"Skovsvinget 10",
    "sg:city":"Skanderborg",
    "sg:orig_category":"Kursussteder",
    "sg:phone":"+45 89 93 33 33",
    "sg:postcode":"8660",
    "sg:province":"Danmark",
    "wof:name":"Finanssektorens Uddannelsescenter",
    "wof:placetype":"venue"
},
  "geometry": {"coordinates":[9.9551849365,56.0370979309],"type":"Point"}
}