{
  "type": "Feature",
  "properties": {
    "addr:full":"Strandvejen 40 Hellerup Danmark 2900",
    "addr:housenumber":"40",
    "addr:postcode":"2900",
    "addr:street":"Strandvejen",
    "iso:country":"DK",
    "sg:address":"Strandvejen 40",
    "sg:city":"Hellerup",
    "sg:orig_category":"Benzinstationer",
    "sg:phone":"+45 39 29 46 00",
    "sg:postcode":"2900",
    "sg:province":"Danmark",
    "wof:name":"Shell Service",
    "wof:placetype":"venue"
},
  "geometry": {"coordinates":[12.577746,55.722801],"type":"Point"}
}