{
  "type": "Feature",
  "properties": {
    "addr:full":"Industrivej 25 Viborg Danmark 8800",
    "addr:housenumber":"25",
    "addr:postcode":"8800",
    "addr:street":"Industrivej",
    "iso:country":"DK",
    "sg:address":"Industrivej 25",
    "sg:city":"Viborg",
    "sg:orig_category":"Jernhandel",
    "sg:phone":"+45 86 62 25 00",
    "sg:postcode":"8800",
    "sg:province":"Danmark",
    "wof:name":"Reffskier & Selchau A/S",
    "wof:placetype":"venue"
},
  "geometry": {"coordinates":[9.4116134644,56.4701652527],"type":"Point"}
}