{
  "type": "Feature",
  "properties": {
    "iso:country":"DK",
    "sg:address":"Blegdamsvej 40",
    "sg:city":"K\u00f8benhavn N",
    "sg:orig_category":"Blomsterhandlere",
    "sg:phone":"+45 35 36 36 94",
    "sg:postcode":"2200",
    "sg:province":"Danmark",
    "wof:name":"Blomsterbyen",
    "wof:placetype":"venue"
},
  "geometry": {"coordinates":[-97.6880722046,47.8096923828],"type":"Point"}
}