{
  "type": "Feature",
  "properties": {
    "iso:country":"DK",
    "sg:address":"\u00d8sbygade 50",
    "sg:city":"Haderslev",
    "sg:orig_category":"Malermestre",
    "sg:phone":"+45 74 58 40 75",
    "sg:postcode":"6100",
    "sg:province":"Danmark",
    "wof:name":"\u00c6' Maler",
    "wof:placetype":"venue"
},
  "geometry": {"coordinates":[9.4879703522,55.2505493164],"type":"Point"}
}