{
  "type": "Feature",
  "properties": {
    "iso:country":"DK",
    "sg:address":"Viborgvej 111, Mejrup",
    "sg:city":"Holstebro",
    "sg:orig_category":"Brugsforeninger",
    "sg:phone":"+45 97 42 35 07",
    "sg:postcode":"7500",
    "sg:province":"Danmark",
    "sg:website":"www.fdb.dk",
    "wof:name":"Brugsen Mejrup",
    "wof:placetype":"venue"
},
  "geometry": {"coordinates":[8.6202583313,56.3625221252],"type":"Point"}
}