{
  "type": "Feature",
  "properties": {
    "addr:full":"Tv\u00e6rskiftet 5 Beder Danmark 8330",
    "addr:housenumber":"5",
    "addr:postcode":"8330",
    "addr:street":"Tvaerskiftet",
    "iso:country":"DK",
    "sg:address":"Tv\u00e6rskiftet 5",
    "sg:city":"Beder",
    "sg:orig_category":"Snedkermestre",
    "sg:phone":"+45 86 93 80 00",
    "sg:postcode":"8330",
    "sg:province":"Danmark",
    "wof:name":"Beder T\u00f8mrer- og Snedkerforretning",
    "wof:placetype":"venue"
},
  "geometry": {"coordinates":[10.1998882294,56.0550041199],"type":"Point"}
}