{
  "type": "Feature",
  "properties": {
    "addr:full":"Tobaksg\u00e5rden 14 Horsens Danmark 8700",
    "addr:housenumber":"14",
    "addr:postcode":"8700",
    "addr:street":"Tobaksgaarden",
    "iso:country":"DK",
    "sg:address":"Tobaksg\u00e5rden 14",
    "sg:city":"Horsens",
    "sg:orig_category":"\u00c3\u2020ldreorganisationer og klubber",
    "sg:phone":"+45 75 61 21 25",
    "sg:postcode":"8700",
    "sg:province":"Danmark",
    "wof:name":"Horsens Pensionist- & Invalideforening af 1953",
    "wof:placetype":"venue"
},
  "geometry": {"coordinates":[9.8432445526,55.8621063232],"type":"Point"}
}