{
  "type": "Feature",
  "properties": {
    "addr:full":"Storegade 1, Borris Skjern Danmark 6900",
    "addr:housenumber":"1",
    "addr:postcode":"6900",
    "addr:street":"Storegade;Borris",
    "iso:country":"DK",
    "sg:address":"Storegade 1, Borris",
    "sg:city":"Skjern",
    "sg:classifiers":[
        {
            "category":"Banks & Credit Unions",
            "subcategory":"Bank",
            "type":"Services"
        }
    ],
    "sg:phone":"+45 97 36 60 66",
    "sg:postcode":"6900",
    "sg:province":"Danmark",
    "sg:tags":[
        "banker"
    ],
    "sg:website":"www.sda.dk/skjern",
    "wof:name":"Borris, Andelskassen",
    "wof:placetype":"venue"
},
  "geometry": {"coordinates":[8.492972,55.948574],"type":"Point"}
}