{
  "type": "Feature",
  "properties": {
    "iso:country":"DK",
    "sg:address":"Magleparken 18",
    "sg:city":"Ballerup",
    "sg:orig_category":"Legestuer",
    "sg:phone":"+45 44 77 32 84",
    "sg:postcode":"2750",
    "sg:province":"Danmark",
    "wof:name":"Hede-Magleparken Legestue",
    "wof:placetype":"venue"
},
  "geometry": {"coordinates":[12.3621416092,55.7193832397],"type":"Point"}
}