{
  "type": "Feature",
  "properties": {
    "iso:country":"DK",
    "sg:address":"Biblioteket, Universitetsparken 4",
    "sg:city":"K\u00f8benhavn \u00d8",
    "sg:orig_category":"\u00c3\u02dcvrige skoler",
    "sg:phone":"+45 35 36 95 95",
    "sg:postcode":"2100",
    "sg:province":"Danmark",
    "wof:name":"Ergoterapeutskolen i K\u00f8benhavn",
    "wof:placetype":"venue"
},
  "geometry": {"coordinates":[10.2031602859,56.16796875],"type":"Point"}
}