{
  "type": "Feature",
  "properties": {
    "addr:full":"H. C. Andersens Vej 15 Ikast Danmark 7430",
    "addr:housenumber":"15",
    "addr:postcode":"7430",
    "addr:street":"H. C. Andersens Vej",
    "iso:country":"DK",
    "sg:address":"H. C. Andersens Vej 15",
    "sg:city":"Ikast",
    "sg:orig_category":"Engros handel",
    "sg:phone":"+45 97 15 34 01",
    "sg:postcode":"7430",
    "sg:province":"Danmark",
    "sg:website":"www.boelslund.dk",
    "wof:name":"Boelslund Handelsfirma ApS",
    "wof:placetype":"venue"
},
  "geometry": {"coordinates":[9.1636724472,56.1299362183],"type":"Point"}
}