{
  "type": "Feature",
  "properties": {
    "iso:country":"DK",
    "sg:address":"Bag Kirken 6",
    "sg:city":"H\u00f8jby",
    "sg:orig_category":"Kirker",
    "sg:postcode":"4573",
    "sg:province":"Danmark",
    "wof:name":"H\u00f8jby Kirke",
    "wof:placetype":"venue"
},
  "geometry": {"coordinates":[49.7513999939,37.4364013672],"type":"Point"}
}