{
  "type": "Feature",
  "properties": {
    "addr:full":"Kildesvinget 13 Bjerringbro Danmark 8850",
    "addr:housenumber":"13",
    "addr:postcode":"8850",
    "addr:street":"Kildesvinget",
    "iso:country":"DK",
    "sg:address":"Kildesvinget 13",
    "sg:city":"Bjerringbro",
    "sg:orig_category":"Bowlingcentre",
    "sg:phone":"+45 86 68 88 81",
    "sg:postcode":"8850",
    "sg:province":"Danmark",
    "wof:name":"Bjerringbro Bowling Center",
    "wof:placetype":"venue"
},
  "geometry": {"coordinates":[9.6324443817,56.3724327087],"type":"Point"}
}