{
  "type": "Feature",
  "properties": {
    "addr:full":"Porsevej 6 Haderslev Danmark 6100",
    "addr:housenumber":"6",
    "addr:postcode":"6100",
    "addr:street":"Porsevej",
    "iso:country":"DK",
    "sg:address":"Porsevej 6",
    "sg:city":"Haderslev",
    "sg:classifiers":[
        {
            "category":"Communications",
            "type":"Services"
        }
    ],
    "sg:phone":"+45 74 53 01 02",
    "sg:postcode":"6100",
    "sg:province":"Danmark",
    "sg:tags":[
        "radio-",
        "og",
        "tv-stationer"
    ],
    "sg:website":"www.lokalradio-norea.dk",
    "wof:name":"Lokalradioen Norea Radio Haderslev",
    "wof:placetype":"venue"
},
  "geometry": {"coordinates":[9.5010595322,55.2347831726],"type":"Point"}
}