{
  "type": "Feature",
  "properties": {
    "addr:full":"Greve Landevej 87 Greve Danmark 2670",
    "addr:housenumber":"87",
    "addr:postcode":"2670",
    "addr:street":"Greve Landevej",
    "iso:country":"DK",
    "sg:address":"Greve Landevej 87",
    "sg:city":"Greve",
    "sg:orig_category":"Korn og foderstoffer",
    "sg:phone":"+45 43 61 12 88",
    "sg:postcode":"2670",
    "sg:province":"Danmark",
    "wof:name":"Greve M\u00f8lle",
    "wof:placetype":"venue"
},
  "geometry": {"coordinates":[12.2490024567,55.5917701721],"type":"Point"}
}