{
  "type": "Feature",
  "properties": {
    "addr:full":"Kildeg\u00e5rdsvej 183 Odense N\u00d8 Danmark 5240",
    "addr:housenumber":"183",
    "addr:postcode":"5240",
    "addr:street":"Kildegaardsvej",
    "iso:country":"DK",
    "sg:address":"Kildeg\u00e5rdsvej 183",
    "sg:city":"Odense N\u00d8",
    "sg:classifiers":[
        {
            "category":"Arts & Performance",
            "subcategory":"Dance",
            "type":"Entertainment"
        }
    ],
    "sg:phone":"+45 66 10 54 66",
    "sg:postcode":"5240",
    "sg:province":"Danmark",
    "sg:tags":[
        "montage"
    ],
    "wof:name":"L R Montering",
    "wof:placetype":"venue"
},
  "geometry": {"coordinates":[10.4522762299,55.402923584],"type":"Point"}
}