{
  "type": "Feature",
  "properties": {
    "addr:full":"Lars Nielsens Vej 35 Brande Danmark 7330",
    "addr:housenumber":"35",
    "addr:postcode":"7330",
    "addr:street":"Lars Nielsens Vej",
    "iso:country":"DK",
    "sg:address":"Lars Nielsens Vej 35",
    "sg:city":"Brande",
    "sg:orig_category":"Skorstensfejere",
    "sg:phone":"+45 97 18 26 72",
    "sg:postcode":"7330",
    "sg:province":"Danmark",
    "wof:name":"Skj\u00f8dt, Carl R.",
    "wof:placetype":"venue"
},
  "geometry": {"coordinates":[9.1217908859,55.9358291626],"type":"Point"}
}