{
  "type": "Feature",
  "properties": {
    "iso:country":"DK",
    "sg:address":"Kvaglundvej 45",
    "sg:city":"Esbjerg \u00d8",
    "sg:orig_category":"Kiosker",
    "sg:phone":"+45 75 14 01 53",
    "sg:postcode":"6705",
    "sg:province":"Danmark",
    "wof:name":"Tips og Lotto Eksperten",
    "wof:placetype":"venue"
},
  "geometry": {"coordinates":[8.4732809067,55.4851264954],"type":"Point"}
}