{
  "type": "Feature",
  "properties": {
    "iso:country":"DK",
    "sg:address":"N\u00f8rregade 28",
    "sg:city":"Glamsbjerg",
    "sg:orig_category":"Slagter og viktualie",
    "sg:phone":"+45 64 72 32 42",
    "sg:postcode":"5620",
    "sg:province":"Danmark",
    "wof:name":"N\u00f8rregades Slagterforretning",
    "wof:placetype":"venue"
},
  "geometry": {"coordinates":[10.1027240753,55.280254364],"type":"Point"}
}