{
  "type": "Feature",
  "properties": {
    "addr:full":"v/ Mette Petersen, Gr\u00e6ngebjergvej 1, Sneslev Fuglebjerg Danmark 4250",
    "addr:housenumber":"1",
    "addr:postcode":"4250",
    "addr:street":"Graengebjergvej",
    "iso:country":"DK",
    "sg:address":"v/ Mette Petersen, Gr\u00e6ngebjergvej 1, Sneslev",
    "sg:city":"Fuglebjerg",
    "sg:orig_category":"Spejderkorps",
    "sg:phone":"+45 55 45 31 03",
    "sg:postcode":"4250",
    "sg:province":"Danmark",
    "wof:name":"Dalmose FDF",
    "wof:placetype":"venue"
},
  "geometry": {"coordinates":[11.5452251434,55.3061332703],"type":"Point"}
}