{
  "type": "Feature",
  "properties": {
    "addr:full":"Kisserup Krat 8, Kisserup Kirke Hvals\u00f8 Danmark 4330",
    "addr:housenumber":"8",
    "addr:postcode":"4330",
    "addr:street":"Kisserup Krat;Kisserup",
    "iso:country":"DK",
    "sg:address":"Kisserup Krat 8, Kisserup",
    "sg:city":"Kirke Hvals\u00f8",
    "sg:orig_category":"Fotografer",
    "sg:phone":"+45 46 40 95 93",
    "sg:postcode":"4330",
    "sg:province":"Danmark",
    "wof:name":"Thorlacius, Lisbeth",
    "wof:placetype":"venue"
},
  "geometry": {"coordinates":[11.8626852036,55.5937385559],"type":"Point"}
}