{
  "type": "Feature",
  "properties": {
    "addr:full":"Nordtoft 11 Aalborg Danmark 9000",
    "addr:housenumber":"11",
    "addr:postcode":"9000",
    "addr:street":"Nordtoft",
    "iso:country":"DK",
    "sg:address":"Nordtoft 11",
    "sg:city":"Aalborg",
    "sg:orig_category":"Forsikringer",
    "sg:phone":"+45 98 18 97 21",
    "sg:postcode":"9000",
    "sg:province":"Danmark",
    "wof:name":"N\u00f8rrejyll. Gensidige S\u00f8forsikringf.",
    "wof:placetype":"venue"
},
  "geometry": {"coordinates":[9.8865346909,57.0318260193],"type":"Point"}
}