{
  "type": "Feature",
  "properties": {
    "iso:country":"DK",
    "sg:address":"Marselisborg Havn S/I, Marselisborg Havnevej 54",
    "sg:city":"\u00c5rhus C",
    "sg:orig_category":"Havne",
    "sg:phone":"+45 86 19 86 44",
    "sg:postcode":"8000",
    "sg:province":"Danmark",
    "sg:website":"www.marselisborghavn.dk",
    "wof:name":"Lystb\u00e5dehavnen",
    "wof:placetype":"venue"
},
  "geometry": {"coordinates":[-6.7695498466,62.020980835],"type":"Point"}
}