{
  "type": "Feature",
  "properties": {
    "addr:full":"H\u00f8jmosevej 3, Errits\u00f8 Fredericia Danmark 7000",
    "addr:housenumber":"3",
    "addr:postcode":"7000",
    "addr:street":"Hojmosevej",
    "iso:country":"DK",
    "sg:address":"H\u00f8jmosevej 3, Errits\u00f8",
    "sg:city":"Fredericia",
    "sg:orig_category":"Kirker",
    "sg:postcode":"7000",
    "sg:province":"Danmark",
    "wof:name":"Lyng Kirke",
    "wof:placetype":"venue"
},
  "geometry": {"coordinates":[9.7591047287,55.566368103],"type":"Point"}
}