{
  "type": "Feature",
  "properties": {
    "addr:full":"Ramsherred 47 Aabenraa Danmark 6200",
    "addr:housenumber":"47",
    "addr:postcode":"6200",
    "addr:street":"Ramsherred",
    "iso:country":"DK",
    "sg:address":"Ramsherred 47",
    "sg:city":"Aabenraa",
    "sg:orig_category":"Rejsebureauer",
    "sg:phone":"+45 74 62 81 11",
    "sg:postcode":"6200",
    "sg:province":"Danmark",
    "sg:website":"www.toprejser.dk",
    "wof:name":"Top Rejser A/S",
    "wof:placetype":"venue"
},
  "geometry": {"coordinates":[9.4185323715,55.0453491211],"type":"Point"}
}