{
  "type": "Feature",
  "properties": {
    "addr:full":"Ingemannsvej 61 Slagelse Danmark 4200",
    "addr:housenumber":"61",
    "addr:postcode":"4200",
    "addr:street":"Ingemannsvej",
    "iso:country":"DK",
    "sg:address":"Ingemannsvej 61",
    "sg:city":"Slagelse",
    "sg:orig_category":"Advokater",
    "sg:phone":"+45 58 56 74 44",
    "sg:postcode":"4200",
    "sg:province":"Danmark",
    "sg:website":"www.ssllandbo.dk",
    "wof:name":"Advokat Jes L\u00f8kkegaard",
    "wof:placetype":"venue"
},
  "geometry": {"coordinates":[11.3729343414,55.4016647339],"type":"Point"}
}