{
  "type": "Feature",
  "properties": {
    "addr:full":"Thrigesvej 2 Silkeborg Danmark 8600",
    "addr:housenumber":"2",
    "addr:postcode":"8600",
    "addr:street":"Thrigesvej",
    "iso:country":"DK",
    "sg:address":"Thrigesvej 2",
    "sg:city":"Silkeborg",
    "sg:orig_category":"Fabrikker",
    "sg:phone":"+45 86 81 22 44",
    "sg:postcode":"8600",
    "sg:province":"Danmark",
    "wof:name":"Kemp Tr\u00e6 og Fin\u00e9r ApS",
    "wof:placetype":"venue"
},
  "geometry": {"coordinates":[9.5612392426,56.1979217529],"type":"Point"}
}