{
  "type": "Feature",
  "properties": {
    "iso:country":"DK",
    "sg:address":"Slienvej 35",
    "sg:city":"Silkeborg",
    "sg:orig_category":"Tekstforfattere",
    "sg:phone":"+45 86 80 30 56",
    "sg:postcode":"8600",
    "sg:province":"Danmark",
    "wof:name":"Frost, Bo",
    "wof:placetype":"venue"
},
  "geometry": {"coordinates":[9.5183229446,56.1757545471],"type":"Point"}
}