{
  "type": "Feature",
  "properties": {
    "addr:full":"Hjallesevej 25 - 27 Odense C Danmark 5000",
    "addr:housenumber":"25 27",
    "addr:postcode":"5000",
    "addr:street":"Hjallesevej",
    "iso:country":"DK",
    "sg:address":"Hjallesevej 25 - 27",
    "sg:city":"Odense C",
    "sg:orig_category":"Servicestationer",
    "sg:phone":"+45 66 13 04 31",
    "sg:postcode":"5000",
    "sg:province":"Danmark",
    "wof:name":"Shell",
    "wof:placetype":"venue"
},
  "geometry": {"coordinates":[10.396282196,55.3902549744],"type":"Point"}
}