{
  "type": "Feature",
  "properties": {
    "addr:full":"Smedegade 26 Horsens Danmark 8700",
    "addr:housenumber":"26",
    "addr:postcode":"8700",
    "addr:street":"Smedegade",
    "iso:country":"DK",
    "sg:address":"Smedegade 26",
    "sg:city":"Horsens",
    "sg:orig_category":"Dykkerudstyr",
    "sg:phone":"+45 75 60 25 98",
    "sg:postcode":"8700",
    "sg:province":"Danmark",
    "wof:name":"\u00d8stjyllands Dykkercenter",
    "wof:placetype":"venue"
},
  "geometry": {"coordinates":[9.8483839035,55.8642845154],"type":"Point"}
}