{
  "type": "Feature",
  "properties": {
    "addr:full":"Tv\u00e6rgade 1 Padborg Danmark 6330",
    "addr:housenumber":"1",
    "addr:postcode":"6330",
    "addr:street":"Tvaergade",
    "iso:country":"DK",
    "sg:address":"Tv\u00e6rgade 1",
    "sg:city":"Padborg",
    "sg:orig_category":"Farve og tapet",
    "sg:phone":"+45 74 67 32 43",
    "sg:postcode":"6330",
    "sg:province":"Danmark",
    "wof:name":"List-Jensen Farve & Tapet",
    "wof:placetype":"venue"
},
  "geometry": {"coordinates":[9.3570346832,54.820224762],"type":"Point"}
}