{
  "type": "Feature",
  "properties": {
    "addr:full":"Strandvejen 189 Hellerup Danmark 2900",
    "addr:housenumber":"189",
    "addr:postcode":"2900",
    "addr:street":"Strandvejen",
    "iso:country":"DK",
    "sg:address":"Strandvejen 189",
    "sg:city":"Hellerup",
    "sg:orig_category":"Boghandlere",
    "sg:phone":"+45 39 62 04 99",
    "sg:postcode":"2900",
    "sg:province":"Danmark",
    "wof:name":"Strandvejens Boghandel",
    "wof:placetype":"venue"
},
  "geometry": {"coordinates":[12.5746021271,55.7350883484],"type":"Point"}
}