{
  "type": "Feature",
  "properties": {
    "addr:full":"v/Fritz L\u00f8vschall, Bianco Lunos Alle 9 Frederiksberg Danmark 1868",
    "addr:housenumber":"9",
    "addr:postcode":"1868",
    "addr:street":"Lunos Alle",
    "iso:country":"DK",
    "sg:address":"v/Fritz L\u00f8vschall, Bianco Lunos Alle 9",
    "sg:city":"Frederiksberg",
    "sg:orig_category":"Grundejerforeninger",
    "sg:phone":"+45 33 22 57 01",
    "sg:postcode":"1868",
    "sg:province":"Danmark",
    "wof:name":"Tengslemark Ny Grundejerforening",
    "wof:placetype":"venue"
},
  "geometry": {"coordinates":[12.5402030945,55.6774024963],"type":"Point"}
}