{
  "type": "Feature",
  "properties": {
    "iso:country":"DK",
    "sg:address":"Sejr\u00f8gade 4",
    "sg:city":"K\u00f8benhavn \u00d8",
    "sg:orig_category":"Bagere",
    "sg:phone":"+45 39 29 85 17",
    "sg:postcode":"2100",
    "sg:province":"Danmark",
    "wof:name":"Hauge's Bageri",
    "wof:placetype":"venue"
},
  "geometry": {"coordinates":[99.925011,34.243011],"type":"Point"}
}