{
  "type": "Feature",
  "properties": {
    "iso:country":"DK",
    "sg:address":"Jacobsvej 1, Sj\u00f8rring",
    "sg:city":"Thisted",
    "sg:orig_category":"Blikkenslagere",
    "sg:phone":"+45 97 97 10 04",
    "sg:postcode":"7700",
    "sg:province":"Danmark",
    "wof:name":"Sj\u00f8rring Blikkenslagerforretning",
    "wof:placetype":"venue"
},
  "geometry": {"coordinates":[8.691978,56.955612],"type":"Point"}
}