{
  "type": "Feature",
  "properties": {
    "iso:country":"DK",
    "sg:address":"Gormsvej 8",
    "sg:city":"Nyborg",
    "sg:orig_category":"Knallerter",
    "sg:phone":"+45 65 31 08 19",
    "sg:postcode":"5800",
    "sg:province":"Danmark",
    "wof:name":"Billers Cykelforretning",
    "wof:placetype":"venue"
},
  "geometry": {"coordinates":[10.8026103973,55.3078613281],"type":"Point"}
}