{
  "type": "Feature",
  "properties": {
    "iso:country":"DK",
    "sg:address":"Smidstrup Strandvej 53, Smidstrup",
    "sg:city":"Gilleleje",
    "sg:orig_category":"Bagere",
    "sg:phone":"+45 48 31 80 05",
    "sg:postcode":"3250",
    "sg:province":"Danmark",
    "wof:name":"Smidstrup Bageri",
    "wof:placetype":"venue"
},
  "geometry": {"coordinates":[12.308739,56.123463],"type":"Point"}
}