{
  "type": "Feature",
  "properties": {
    "addr:full":"Smedebakken 9 Niv\u00e5 Danmark 2990",
    "addr:housenumber":"9",
    "addr:postcode":"2990",
    "addr:street":"Smedebakken",
    "iso:country":"DK",
    "sg:address":"Smedebakken 9",
    "sg:city":"Niv\u00e5",
    "sg:orig_category":"Integrerede institutioner",
    "sg:phone":"+45 49 14 70 25",
    "sg:postcode":"2990",
    "sg:province":"Danmark",
    "wof:name":"Dysseg\u00e5rdens B\u00f8rnehave",
    "wof:placetype":"venue"
},
  "geometry": {"coordinates":[12.5070781708,55.9311561584],"type":"Point"}
}