{
  "type": "Feature",
  "properties": {
    "addr:full":"Industrivej 1 Aabybro Danmark 9440",
    "addr:housenumber":"1",
    "addr:postcode":"9440",
    "addr:street":"Industrivej",
    "iso:country":"DK",
    "sg:address":"Industrivej 1",
    "sg:city":"Aabybro",
    "sg:orig_category":"Landbrugskonsulenter",
    "sg:phone":"+45 70 13 28 00",
    "sg:postcode":"9440",
    "sg:province":"Danmark",
    "wof:name":"Nord I/S, Landbrugsr\u00e5dgivning",
    "wof:placetype":"venue"
},
  "geometry": {"coordinates":[9.7438430786,57.1528816223],"type":"Point"}
}