{
  "type": "Feature",
  "properties": {
    "iso:country":"DK",
    "sg:address":"Jernbanegade 53",
    "sg:city":"Esbjerg",
    "sg:classifiers":[
        {
            "category":"Restaurant",
            "type":"Food & Drink"
        }
    ],
    "sg:phone":"+45 75 12 06 81",
    "sg:postcode":"6700",
    "sg:province":"Danmark",
    "wof:name":"DSB Cafe",
    "wof:placetype":"venue"
},
  "geometry": {"coordinates":[8.4589586258,55.470199585],"type":"Point"}
}