{
  "type": "Feature",
  "properties": {
    "addr:full":"Mintebjergvej 27, Mintebjerg Sydals Danmark 6470",
    "addr:housenumber":"27",
    "addr:postcode":"6470",
    "addr:street":"Mintebjergvej;Mintebjerg",
    "iso:country":"DK",
    "sg:address":"Mintebjergvej 27, Mintebjerg",
    "sg:city":"Sydals",
    "sg:orig_category":"Landbrugsmaskiner",
    "sg:phone":"+45 74 41 50 12",
    "sg:postcode":"6470",
    "sg:province":"Danmark",
    "wof:name":"Bladt Traktorer, Kurt",
    "wof:placetype":"venue"
},
  "geometry": {"coordinates":[9.8924627304,54.9105377197],"type":"Point"}
}