{
  "type": "Feature",
  "properties": {
    "addr:full":"Enghavevej 3 Viby Danmark 8260",
    "addr:housenumber":"3",
    "addr:postcode":"8260",
    "addr:street":"Enghavevej",
    "iso:country":"DK",
    "sg:address":"Enghavevej 3",
    "sg:city":"Viby",
    "sg:orig_category":"Faglige organisationer og -foreninger",
    "sg:phone":"+45 86 11 87 11",
    "sg:postcode":"8260",
    "sg:province":"Danmark",
    "wof:name":"Undervisningsmidler Brancheforeningen for",
    "wof:placetype":"venue"
},
  "geometry": {"coordinates":[10.1652202606,56.1240615845],"type":"Point"}
}