{
  "type": "Feature",
  "properties": {
    "addr:full":"E. Christensens Vej 13 - 15 Ikast Danmark 7430",
    "addr:housenumber":"13 15",
    "addr:postcode":"7430",
    "addr:street":"E. Christensens Vej",
    "iso:country":"DK",
    "sg:address":"E. Christensens Vej 13 - 15",
    "sg:city":"Ikast",
    "sg:orig_category":"Tekstiltrykkerier",
    "sg:phone":"+45 97 25 24 42",
    "sg:postcode":"7430",
    "sg:province":"Danmark",
    "wof:name":"Ikast Transfertryk",
    "wof:placetype":"venue"
},
  "geometry": {"coordinates":[9.1392021179,56.1387138367],"type":"Point"}
}