{
  "type": "Feature",
  "properties": {
    "addr:full":"Plumsgade 10 2 Odense C Danmark 5000",
    "addr:housenumber":"10 2",
    "addr:postcode":"5000",
    "addr:street":"Plumsgade",
    "iso:country":"DK",
    "sg:address":"Plumsgade 10 2",
    "sg:city":"Odense C",
    "sg:orig_category":"Flytteforretninger",
    "sg:phone":"+45 66 11 01 17",
    "sg:postcode":"5000",
    "sg:province":"Danmark",
    "wof:name":"IC Trans I/S",
    "wof:placetype":"venue"
},
  "geometry": {"coordinates":[10.4013586044,55.4046821594],"type":"Point"}
}