{
  "type": "Feature",
  "properties": {
    "addr:full":"Andaksvej 19 Kalundborg Danmark 4400",
    "addr:housenumber":"19",
    "addr:postcode":"4400",
    "addr:street":"Andaksvej",
    "iso:country":"DK",
    "sg:address":"Andaksvej 19",
    "sg:city":"Kalundborg",
    "sg:orig_category":"Private- og friskoler",
    "sg:phone":"+45 59 50 72 99",
    "sg:postcode":"4400",
    "sg:province":"Danmark",
    "sg:website":"www.tfe.dk",
    "wof:name":"T\u00f8mmerup Fri- og Efterskole",
    "wof:placetype":"venue"
},
  "geometry": {"coordinates":[11.1569499969,55.6910209656],"type":"Point"}
}