{
  "type": "Feature",
  "properties": {
    "iso:country":"DK",
    "sg:address":"Holger Danskes Vej 32 - 34",
    "sg:city":"Frederiksberg",
    "sg:orig_category":"Autoreparation og -service",
    "sg:phone":"+45 38 34 52 00",
    "sg:postcode":"2000",
    "sg:province":"Danmark",
    "wof:name":"Scaniadam",
    "wof:placetype":"venue"
},
  "geometry": {"coordinates":[12.536356926,55.6870803833],"type":"Point"}
}