{
  "type": "Feature",
  "properties": {
    "addr:full":"Emilievej 25 Frederikshavn Danmark 9900",
    "addr:housenumber":"25",
    "addr:postcode":"9900",
    "addr:street":"Emilievej",
    "iso:country":"DK",
    "sg:address":"Emilievej 25",
    "sg:city":"Frederikshavn",
    "sg:orig_category":"Zoneterapeuter",
    "sg:phone":"+45 98 42 11 31",
    "sg:postcode":"9900",
    "sg:province":"Danmark",
    "wof:name":"Jensen, Tove",
    "wof:placetype":"venue"
},
  "geometry": {"coordinates":[10.5276060104,57.4348945618],"type":"Point"}
}