{
  "type": "Feature",
  "properties": {
    "addr:full":"Mejlgade 19 \u00c5rhus C Danmark 8000",
    "addr:housenumber":"19",
    "addr:postcode":"8000",
    "addr:street":"Mejlgade",
    "iso:country":"DK",
    "sg:address":"Mejlgade 19",
    "sg:city":"\u00c5rhus C",
    "sg:orig_category":"Farve og tapet",
    "sg:phone":"+45 86 12 01 45",
    "sg:postcode":"8000",
    "sg:province":"Danmark",
    "wof:name":"Juul's Eftf., J. C.",
    "wof:placetype":"venue"
},
  "geometry": {"coordinates":[4.717400074,49.7588005066],"type":"Point"}
}