{
  "type": "Feature",
  "properties": {
    "addr:full":"Nyh\u00f8jen 105 Munkebo Danmark 5330",
    "addr:housenumber":"105",
    "addr:postcode":"5330",
    "iso:country":"DK",
    "sg:address":"Nyh\u00f8jen 105",
    "sg:city":"Munkebo",
    "sg:orig_category":"Grillbarer",
    "sg:phone":"+45 65 97 65 47",
    "sg:postcode":"5330",
    "sg:province":"Danmark",
    "wof:name":"Burger Banken",
    "wof:placetype":"venue"
},
  "geometry": {"coordinates":[10.5523796082,55.4607658386],"type":"Point"}
}