{
  "type": "Feature",
  "properties": {
    "iso:country":"DK",
    "sg:address":"Fmd.: Jytta Nebel, N\u00f8rskovlundvej 68, Frausing",
    "sg:city":"Ans",
    "sg:orig_category":"Kirkelige foreninger",
    "sg:phone":"+45 86 88 61 98",
    "sg:postcode":"8643",
    "sg:province":"Danmark",
    "wof:name":"KFUM & K i Hinge",
    "wof:placetype":"venue"
},
  "geometry": {"coordinates":[9.6200656891,56.2750320435],"type":"Point"}
}