{
  "type": "Feature",
  "properties": {
    "addr:full":"Frihedslyst Alle 23 Hvidovre Danmark 2650",
    "addr:housenumber":"23",
    "addr:postcode":"2650",
    "addr:street":"Frihedslyst Alle",
    "iso:country":"DK",
    "sg:address":"Frihedslyst Alle 23",
    "sg:city":"Hvidovre",
    "sg:orig_category":"Hushold.apparater, service af",
    "sg:phone":"+45 36 49 98 12",
    "sg:postcode":"2650",
    "sg:province":"Danmark",
    "wof:name":"JA Serviceteknik",
    "wof:placetype":"venue"
},
  "geometry": {"coordinates":[12.4746265411,55.6202049255],"type":"Point"}
}