{
  "type": "Feature",
  "properties": {
    "iso:country":"DK",
    "sg:address":"H\u00f8jbjergvej 3, Kirkeby",
    "sg:city":"Stenstrup",
    "sg:orig_category":"Solvarme",
    "sg:phone":"+45 62 26 16 26",
    "sg:postcode":"5771",
    "sg:province":"Danmark",
    "wof:name":"Sydfyns VVS",
    "wof:placetype":"venue"
},
  "geometry": {"coordinates":[10.5054998398,55.1317520142],"type":"Point"}
}