{
  "type": "Feature",
  "properties": {
    "addr:full":"Dyrehavsbakken 23 Klampenborg Danmark 2930",
    "addr:housenumber":"23",
    "addr:postcode":"2930",
    "addr:street":"Dyrehavsbakken",
    "iso:country":"DK",
    "sg:address":"Dyrehavsbakken 23",
    "sg:city":"Klampenborg",
    "sg:classifiers":[
        {
            "category":"Restaurant",
            "type":"Food & Drink"
        }
    ],
    "sg:phone":"+45 39 64 12 92",
    "sg:postcode":"2930",
    "sg:province":"Danmark",
    "wof:name":"Br\u00e6ddehytten",
    "wof:placetype":"venue"
},
  "geometry": {"coordinates":[12.5787811279,55.7748832703],"type":"Point"}
}