{
  "type": "Feature",
  "properties": {
    "addr:full":"Plantagevej 1 A, F\u00e5rup Jelling Danmark 7300",
    "addr:housenumber":"1 a",
    "addr:postcode":"7300",
    "addr:street":"Plantagevej;Faarup",
    "iso:country":"DK",
    "sg:address":"Plantagevej 1 A, F\u00e5rup",
    "sg:city":"Jelling",
    "sg:orig_category":"Integrerede institutioner",
    "sg:phone":"+45 75 87 00 92",
    "sg:postcode":"7300",
    "sg:province":"Danmark",
    "wof:name":"Jelling B\u00f8rneg\u00e5rd",
    "wof:placetype":"venue"
},
  "geometry": {"coordinates":[9.4184103012,55.7558555603],"type":"Point"}
}