{
  "type": "Feature",
  "properties": {
    "addr:full":"Fmd.: J.O. Korch, H\u00f8jbjergg\u00e5rdsvej 27, \u00d8ver\u00f8d Holte Danmark 2840",
    "addr:housenumber":"27",
    "addr:postcode":"2840",
    "addr:street":"Hojbjerggaardsvej",
    "iso:country":"DK",
    "sg:address":"Fmd.: J.O. Korch, H\u00f8jbjergg\u00e5rdsvej 27, \u00d8ver\u00f8d",
    "sg:city":"Holte",
    "sg:orig_category":"Grundejerforeninger",
    "sg:phone":"+45 45 42 27 43",
    "sg:postcode":"2840",
    "sg:province":"Danmark",
    "wof:name":"H\u00f8jbjergg\u00e5rd Grundejerforening",
    "wof:placetype":"venue"
},
  "geometry": {"coordinates":[12.4706554413,55.8122367859],"type":"Point"}
}