{
  "type": "Feature",
  "properties": {
    "addr:full":"Fmd.: Stig Lund, Strandvangsvej 3 B Esperg\u00e6rde Danmark 3060",
    "addr:housenumber":"3 b",
    "addr:postcode":"3060",
    "addr:street":"Fmd. Stig;Strandvangsvej",
    "iso:country":"DK",
    "sg:address":"Fmd.: Stig Lund, Strandvangsvej 3 B",
    "sg:city":"Esperg\u00e6rde",
    "sg:orig_category":"Grundejerforeninger",
    "sg:phone":"+45 49 13 63 63",
    "sg:postcode":"3060",
    "sg:province":"Danmark",
    "wof:name":"Borger- og Grundejerforeningen for Esperg\u00e6rde og Snekkersten",
    "wof:placetype":"venue"
},
  "geometry": {"coordinates":[11.6512403488,47.8390617371],"type":"Point"}
}