{
  "type": "Feature",
  "properties": {
    "addr:full":"Tinghusvej 6 Fredensborg Danmark 3480",
    "addr:housenumber":"6",
    "addr:postcode":"3480",
    "addr:street":"Tinghusvej",
    "iso:country":"DK",
    "sg:address":"Tinghusvej 6",
    "sg:city":"Fredensborg",
    "sg:orig_category":"Ungdomsklubber",
    "sg:phone":"+45 48 48 16 82",
    "sg:postcode":"3480",
    "sg:province":"Danmark",
    "wof:name":"Den Kommunale Ungdomsskole for Fredensborg-Humleb\u00e6k",
    "wof:placetype":"venue"
},
  "geometry": {"coordinates":[12.4013881683,55.9792823792],"type":"Point"}
}