{
  "type": "Feature",
  "properties": {
    "addr:full":"Amagerbrogade 15 K\u00f8benhavn S Danmark 2300",
    "addr:housenumber":"15",
    "addr:postcode":"2300",
    "addr:street":"Amagerbrogade;S Danmark",
    "iso:country":"DK",
    "sg:address":"Amagerbrogade 15",
    "sg:city":"K\u00f8benhavn S",
    "sg:classifiers":[
        {
            "category":"Restaurant",
            "type":"Food & Drink"
        }
    ],
    "sg:phone":"+45 32 95 44 07",
    "sg:postcode":"2300",
    "sg:province":"Danmark",
    "wof:name":"Restaurant Knossos",
    "wof:placetype":"venue"
},
  "geometry": {"coordinates":[-82.5692062378,38.4656143188],"type":"Point"}
}