{
  "type": "Feature",
  "properties": {
    "addr:full":"Fmd.: T. Westergaard, \u00c5gesdalsvej 11 Ballerup Danmark 2750",
    "addr:housenumber":"11",
    "addr:postcode":"2750",
    "addr:street":"Aagesdalsvej",
    "iso:country":"DK",
    "sg:address":"Fmd.: T. Westergaard, \u00c5gesdalsvej 11",
    "sg:city":"Ballerup",
    "sg:orig_category":"Grundejerforeninger",
    "sg:phone":"+45 44 66 02 94",
    "sg:postcode":"2750",
    "sg:province":"Danmark",
    "wof:name":"Viben Grundejerforening",
    "wof:placetype":"venue"
},
  "geometry": {"coordinates":[12.361000061,55.7301216125],"type":"Point"}
}