{
  "type": "Feature",
  "properties": {
    "addr:full":"Saksk\u00f8bingvej 24, Herritslev Nysted Danmark 4880",
    "addr:housenumber":"24",
    "addr:postcode":"4880",
    "addr:street":"Sakskobingvej",
    "iso:country":"DK",
    "sg:address":"Saksk\u00f8bingvej 24, Herritslev",
    "sg:city":"Nysted",
    "sg:orig_category":"Faglige organisationer og foreninger",
    "sg:phone":"+45 54 86 40 18",
    "sg:postcode":"4880",
    "sg:province":"Danmark",
    "wof:name":"SID",
    "wof:placetype":"venue"
},
  "geometry": {"coordinates":[11.7297554016,54.6671638489],"type":"Point"}
}