{
  "type": "Feature",
  "properties": {
    "addr:full":"Gartnerivej 24 Holstebro Danmark 7500",
    "addr:housenumber":"24",
    "addr:postcode":"7500",
    "addr:street":"Gartnerivej",
    "iso:country":"DK",
    "sg:address":"Gartnerivej 24",
    "sg:city":"Holstebro",
    "sg:orig_category":"Erhvervs- og brancheforeninger",
    "sg:phone":"+45 97 42 61 63",
    "sg:postcode":"7500",
    "sg:province":"Danmark",
    "wof:name":"Holstebro Murermesterforening",
    "wof:placetype":"venue"
},
  "geometry": {"coordinates":[8.6133031845,56.3778266907],"type":"Point"}
}