{
  "type": "Feature",
  "properties": {
    "addr:full":"Tjelevej 25, Tj\u00f8rring Herning Danmark 7400",
    "addr:housenumber":"25",
    "addr:postcode":"7400",
    "addr:street":"Tjelevej;Tjorring",
    "iso:country":"DK",
    "sg:address":"Tjelevej 25, Tj\u00f8rring",
    "sg:city":"Herning",
    "sg:orig_category":"Tandklinikker, Kommunale",
    "sg:phone":"+45 97 26 73 99",
    "sg:postcode":"7400",
    "sg:province":"Danmark",
    "wof:name":"Lundg\u00e5rdskolens Tandklinik",
    "wof:placetype":"venue"
},
  "geometry": {"coordinates":[8.9768896103,56.1374168396],"type":"Point"}
}