{
  "type": "Feature",
  "properties": {
    "iso:country":"DK",
    "sg:address":"Nibevej 139",
    "sg:city":"Fars\u00f8",
    "sg:orig_category":"Autoophug",
    "sg:phone":"+45 98 63 12 80",
    "sg:postcode":"9640",
    "sg:province":"Danmark",
    "wof:name":"Fars\u00f8 Autoophug",
    "wof:placetype":"venue"
},
  "geometry": {"coordinates":[-109.44831848139999,42.1062355042],"type":"Point"}
}