{
  "type": "Feature",
  "properties": {
    "addr:full":"v/ Harald Christensen, Bakkeg\u00e5rdsparken 15 Vejen Danmark 6600",
    "addr:housenumber":"15",
    "addr:postcode":"6600",
    "addr:street":"Bakkegaardsparken",
    "iso:country":"DK",
    "sg:address":"v/ Harald Christensen, Bakkeg\u00e5rdsparken 15",
    "sg:city":"Vejen",
    "sg:orig_category":"\u00c3\u2020ldreorganisationer og klubber",
    "sg:phone":"+45 75 36 03 18",
    "sg:postcode":"6600",
    "sg:province":"Danmark",
    "wof:name":"Vejen Snior Club 1995",
    "wof:placetype":"venue"
},
  "geometry": {"coordinates":[9.1396121979,55.4778175354],"type":"Point"}
}