{
  "type": "Feature",
  "properties": {
    "iso:country":"DK",
    "sg:address":"Str\u00f8get 23",
    "sg:city":"Ikast",
    "sg:orig_category":"Genbrugsbutikker",
    "sg:phone":"+45 97 15 26 20",
    "sg:postcode":"7430",
    "sg:province":"Danmark",
    "wof:name":"Kirkens Korsh\u00e6rs Genbrug",
    "wof:placetype":"venue"
},
  "geometry": {"coordinates":[9.1546030045,56.1408348083],"type":"Point"}
}