{
  "type": "Feature",
  "properties": {
    "addr:full":"Store Kirkestr\u00e6de 11 Assens Danmark 5610",
    "addr:housenumber":"11",
    "addr:postcode":"5610",
    "addr:street":"Kirkestraede",
    "iso:country":"DK",
    "sg:address":"Store Kirkestr\u00e6de 11",
    "sg:city":"Assens",
    "sg:orig_category":"INGENI\u00c3\u02dcRER",
    "sg:phone":"+45 64 71 41 71",
    "sg:postcode":"5610",
    "sg:province":"Danmark",
    "sg:website":"www.bingbang.dk",
    "wof:name":"Bang R\u00e5dgivende Ingeni\u00f8rfirma, J\u00f8rgen",
    "wof:placetype":"venue"
},
  "geometry": {"coordinates":[9.8951311111,55.2695274353],"type":"Point"}
}