{
  "type": "Feature",
  "properties": {
    "iso:country":"DK",
    "sg:address":"Korsgade 10",
    "sg:city":"Svendborg",
    "sg:orig_category":"Kaffe og the",
    "sg:phone":"+45 62 20 32 34",
    "sg:postcode":"5700",
    "sg:province":"Danmark",
    "wof:name":"TeaTime & Aura",
    "wof:placetype":"venue"
},
  "geometry": {"coordinates":[10.6100091934,55.0581245422],"type":"Point"}
}