{
  "type": "Feature",
  "properties": {
    "addr:full":"Nyvej 33 Hobro Danmark 9500",
    "addr:housenumber":"33",
    "addr:postcode":"9500",
    "addr:street":"Nyvej",
    "iso:country":"DK",
    "sg:address":"Nyvej 33",
    "sg:city":"Hobro",
    "sg:orig_category":"Musikere",
    "sg:phone":"+45 98 52 32 34",
    "sg:postcode":"9500",
    "sg:province":"Danmark",
    "wof:name":"Mini",
    "wof:placetype":"venue"
},
  "geometry": {"coordinates":[9.7842664719,56.6418952942],"type":"Point"}
}