{
  "type": "Feature",
  "properties": {
    "addr:full":"Peberhaven 28 Herlev Danmark 2730",
    "addr:housenumber":"28",
    "addr:postcode":"2730",
    "addr:street":"Peberhaven",
    "iso:country":"DK",
    "sg:address":"Peberhaven 28",
    "sg:city":"Herlev",
    "sg:orig_category":"Pizzeriaer",
    "sg:phone":"+45 38 34 24 75",
    "sg:postcode":"2730",
    "sg:province":"Danmark",
    "wof:name":"Munchies Pizza & Pasta",
    "wof:placetype":"venue"
},
  "geometry": {"coordinates":[12.4359922409,55.7425193787],"type":"Point"}
}