{
  "type": "Feature",
  "properties": {
    "addr:full":"Valler\u00f8d Banevej 23 Rungsted Kyst Danmark 2960",
    "addr:housenumber":"23",
    "addr:postcode":"2960",
    "addr:street":"Vallerod Banevej",
    "iso:country":"DK",
    "sg:address":"Valler\u00f8d Banevej 23",
    "sg:city":"Rungsted Kyst",
    "sg:orig_category":"Private skoler",
    "sg:phone":"+45 45 86 32 81",
    "sg:postcode":"2960",
    "sg:province":"Danmark",
    "sg:website":"www.rpr-skole.dk",
    "wof:name":"Rungsted private Realskole",
    "wof:placetype":"venue"
},
  "geometry": {"coordinates":[12.5233001709,55.8893508911],"type":"Point"}
}