{
  "type": "Feature",
  "properties": {
    "addr:full":"Bredgade 68 Lem Danmark 6940",
    "addr:housenumber":"68",
    "addr:postcode":"6940",
    "addr:street":"Bredgade",
    "iso:country":"DK",
    "sg:address":"Bredgade 68",
    "sg:city":"Lem",
    "sg:classifiers":[
        {
            "category":"Banks & Credit Unions",
            "subcategory":"Bank",
            "type":"Services"
        }
    ],
    "sg:phone":"+45 97 34 16 33",
    "sg:postcode":"6940",
    "sg:province":"Danmark",
    "sg:tags":[
        "banker"
    ],
    "wof:name":"Ringkj\u00f8bing Landbobank A/S - Lem afd.",
    "wof:placetype":"venue"
},
  "geometry": {"coordinates":[8.3870382309,56.0261993408],"type":"Point"}
}