{
  "type": "Feature",
  "properties": {
    "addr:full":"Torvegade 32 A Fakse Danmark 4640",
    "addr:housenumber":"32 a",
    "addr:postcode":"4640",
    "addr:street":"Torvegade",
    "iso:country":"DK",
    "sg:address":"Torvegade 32 A",
    "sg:city":"Fakse",
    "sg:orig_category":"Farve og tapet",
    "sg:phone":"+45 56 71 30 56",
    "sg:postcode":"4640",
    "sg:province":"Danmark",
    "sg:website":"www.sadolin.dk",
    "wof:name":"Sadolin-Fakse Farve & Tapet",
    "wof:placetype":"venue"
},
  "geometry": {"coordinates":[12.1195325851,55.2591896057],"type":"Point"}
}