{
  "type": "Feature",
  "properties": {
    "addr:full":"v/ Erik Dreyer, Bernhard Olsens Vej 13 Virum Danmark 2830",
    "addr:housenumber":"13",
    "addr:postcode":"2830",
    "addr:street":"Bernhard Olsens Vej",
    "iso:country":"DK",
    "sg:address":"v/ Erik Dreyer, Bernhard Olsens Vej 13",
    "sg:city":"Virum",
    "sg:orig_category":"Hobbybetonede foreninger",
    "sg:phone":"+45 45 85 48 10",
    "sg:postcode":"2830",
    "sg:province":"Danmark",
    "wof:name":"Lyngby Frim\u00e6rkeklub",
    "wof:placetype":"venue"
},
  "geometry": {"coordinates":[12.4732246399,55.7885513306],"type":"Point"}
}