{
  "type": "Feature",
  "properties": {
    "addr:full":"Firskovvej 22 Kongens Lyngby Danmark 2800",
    "addr:housenumber":"22",
    "addr:postcode":"2800",
    "addr:street":"Firskovvej",
    "iso:country":"DK",
    "sg:address":"Firskovvej 22",
    "sg:city":"Kongens Lyngby",
    "sg:orig_category":"Autoreparation og -service",
    "sg:phone":"+45 45 27 07 90",
    "sg:postcode":"2800",
    "sg:province":"Danmark",
    "wof:name":"FDM Testcenter",
    "wof:placetype":"venue"
},
  "geometry": {"coordinates":[12.5368299484,55.7949905396],"type":"Point"}
}