{
  "type": "Feature",
  "properties": {
    "iso:country":"DK",
    "sg:address":"N\u00f8rregade 5",
    "sg:city":"Hvide Sande",
    "sg:orig_category":"Diskoteker",
    "sg:phone":"+45 97 31 14 55",
    "sg:postcode":"6960",
    "sg:province":"Danmark",
    "wof:name":"Nautico, Diskotek",
    "wof:placetype":"venue"
},
  "geometry": {"coordinates":[8.1297149658,56.0060501099],"type":"Point"}
}