{
  "type": "Feature",
  "properties": {
    "addr:full":"Norgesgade 19, 1. Esbjerg Danmark 6700",
    "addr:housenumber":"19 1",
    "addr:postcode":"6700",
    "addr:street":"Norgesgade",
    "iso:country":"DK",
    "sg:address":"Norgesgade 19, 1.",
    "sg:city":"Esbjerg",
    "sg:orig_category":"Revisorer",
    "sg:phone":"+45 75 13 51 55",
    "sg:postcode":"6700",
    "sg:province":"Danmark",
    "wof:name":"Concept Revision Esbjerg ApS",
    "wof:placetype":"venue"
},
  "geometry": {"coordinates":[8.4549922943,55.4683227539],"type":"Point"}
}