{
  "type": "Feature",
  "properties": {
    "iso:country":"DK",
    "sg:address":"v/ Arne Hansen, Krogen 13, Karlstrup",
    "sg:city":"Karlslunde",
    "sg:orig_category":"\u00c3\u02dcvrige foreninger",
    "sg:postcode":"2690",
    "sg:province":"Danmark",
    "wof:name":"Karlstrup & Omegns Foredragsforening",
    "wof:placetype":"venue"
},
  "geometry": {"coordinates":[12.2294149399,55.5701599121],"type":"Point"}
}