{
  "type": "Feature",
  "properties": {
    "addr:full":"Pilegade 11 Horsens Danmark 8700",
    "addr:housenumber":"11",
    "addr:postcode":"8700",
    "addr:street":"Pilegade",
    "iso:country":"DK",
    "sg:address":"Pilegade 11",
    "sg:city":"Horsens",
    "sg:classifiers":[
        {
            "category":"Personal",
            "subcategory":"Massage",
            "type":"Services"
        }
    ],
    "sg:phone":"+45 75 62 87 62",
    "sg:postcode":"8700",
    "sg:province":"Danmark",
    "wof:name":"Pedersen, Preben Dam",
    "wof:placetype":"venue"
},
  "geometry": {"coordinates":[10.0472831726,55.8215827942],"type":"Point"}
}