{
  "type": "Feature",
  "properties": {
    "addr:full":"Strandvejen 126 Hellerup Danmark 2900",
    "addr:housenumber":"126",
    "addr:postcode":"2900",
    "addr:street":"Strandvejen",
    "iso:country":"DK",
    "sg:address":"Strandvejen 126",
    "sg:city":"Hellerup",
    "sg:orig_category":"Rederier",
    "sg:phone":"+45 39 40 40 11",
    "sg:postcode":"2900",
    "sg:province":"Danmark",
    "wof:name":"Transocean Shipping Agency A/S",
    "wof:placetype":"venue"
},
  "geometry": {"coordinates":[12.5756664276,55.7371368408],"type":"Point"}
}