{
  "type": "Feature",
  "properties": {
    "addr:full":"Hammerum Hovedgade 1 Herning Danmark 7400",
    "addr:housenumber":"1",
    "addr:postcode":"7400",
    "addr:street":"Hammerum Hovedgade",
    "iso:country":"DK",
    "sg:address":"Hammerum Hovedgade 1",
    "sg:city":"Herning",
    "sg:orig_category":"Kommunale folkeskoler",
    "sg:phone":"+45 96 27 00 50",
    "sg:postcode":"7400",
    "sg:province":"Danmark",
    "wof:name":"Hammerum Skole",
    "wof:placetype":"venue"
},
  "geometry": {"coordinates":[9.0725603104,56.1332092285],"type":"Point"}
}