{
  "type": "Feature",
  "properties": {
    "addr:full":"Jernb\u00e6k Alle 44, Raml\u00f8se Helsinge Danmark 3200",
    "addr:housenumber":"44",
    "addr:postcode":"3200",
    "addr:street":"Jernbaek Alle;Ramlose",
    "iso:country":"DK",
    "sg:address":"Jernb\u00e6k Alle 44, Raml\u00f8se",
    "sg:city":"Helsinge",
    "sg:orig_category":"Vikarbureauer",
    "sg:phone":"+45 48 71 10 57",
    "sg:postcode":"3200",
    "sg:province":"Danmark",
    "wof:name":"Lager Vikar",
    "wof:placetype":"venue"
},
  "geometry": {"coordinates":[12.196846962,56.0224456787],"type":"Point"}
}