{
  "type": "Feature",
  "properties": {
    "addr:full":"Bedstedvej 7, Bovlund-Bjerg Branderup Danmark 6535",
    "addr:housenumber":"7",
    "addr:postcode":"6535",
    "addr:street":"Bedstedvej;Branderup Danmark",
    "iso:country":"DK",
    "sg:address":"Bedstedvej 7, Bovlund-Bjerg",
    "sg:city":"Branderup",
    "sg:orig_category":"Oplysningsforbund",
    "sg:phone":"+45 74 59 07 28",
    "sg:postcode":"6535",
    "sg:province":"Danmark",
    "wof:name":"AOF Vojens Dag- og Aftenskole",
    "wof:placetype":"venue"
},
  "geometry": {"coordinates":[9.0691099167,55.1218643188],"type":"Point"}
}