{
  "type": "Feature",
  "properties": {
    "addr:full":"Juelsmindevej 2, Harndrup Harndrup Danmark 5463",
    "addr:housenumber":"2",
    "addr:postcode":"5463",
    "addr:street":"Juelsmindevej",
    "iso:country":"DK",
    "sg:address":"Juelsmindevej 2, Harndrup",
    "sg:city":"Harndrup",
    "sg:orig_category":"Bookingbureauer",
    "sg:phone":"+45 40 55 85 73",
    "sg:postcode":"5463",
    "sg:province":"Danmark",
    "wof:name":"Smedholms Booking Service",
    "wof:placetype":"venue"
},
  "geometry": {"coordinates":[10.0205497742,55.4653778076],"type":"Point"}
}