{
  "type": "Feature",
  "properties": {
    "addr:full":"Over Hadstenvej 48 Hadsten Danmark 8370",
    "addr:housenumber":"48",
    "addr:postcode":"8370",
    "addr:street":"Over Hadstenvej",
    "iso:country":"DK",
    "sg:address":"Over Hadstenvej 48",
    "sg:city":"Hadsten",
    "sg:orig_category":"El-motorer",
    "sg:phone":"+45 86 98 21 11",
    "sg:postcode":"8370",
    "sg:province":"Danmark",
    "sg:website":"www.svendhoyer.dk",
    "wof:name":"Svend H\u00f8yer A/S",
    "wof:placetype":"venue"
},
  "geometry": {"coordinates":[10.0413722992,56.3144989014],"type":"Point"}
}