{
  "type": "Feature",
  "properties": {
    "addr:full":"Herstedvang 10 B Albertslund Danmark 2620",
    "addr:housenumber":"10 b",
    "addr:postcode":"2620",
    "addr:street":"Herstedvang",
    "iso:country":"DK",
    "sg:address":"Herstedvang 10 B",
    "sg:city":"Albertslund",
    "sg:classifiers":[
        {
            "category":"Professional",
            "subcategory":"Computer Services",
            "type":"Services"
        }
    ],
    "sg:phone":"+45 43 24 12 12",
    "sg:postcode":"2620",
    "sg:province":"Danmark",
    "sg:tags":[
        "edb",
        "-",
        "software"
    ],
    "wof:name":"Delta Software A/S",
    "wof:placetype":"venue"
},
  "geometry": {"coordinates":[12.3674592972,55.6676979065],"type":"Point"}
}