{
  "type": "Feature",
  "properties": {
    "iso:country":"DK",
    "sg:address":"Th. Brorsens Vej 56",
    "sg:city":"Nordborg",
    "sg:orig_category":"Bagere",
    "sg:phone":"+45 74 45 47 79",
    "sg:postcode":"6430",
    "sg:province":"Danmark",
    "wof:name":"Nordborg Bageri",
    "wof:placetype":"venue"
},
  "geometry": {"coordinates":[9.754073,55.055264],"type":"Point"}
}