{
  "type": "Feature",
  "properties": {
    "iso:country":"DK",
    "sg:address":"Stadionvej 50 C, Bolbro",
    "sg:city":"Odense V",
    "sg:orig_category":"Hobbybetonede foreninger",
    "sg:phone":"+45 66 14 86 25",
    "sg:postcode":"5200",
    "sg:province":"Danmark",
    "wof:name":"SIKO",
    "wof:placetype":"venue"
},
  "geometry": {"coordinates":[10.2629547119,55.4070854187],"type":"Point"}
}