{
  "type": "Feature",
  "properties": {
    "addr:full":"Eckersbergsvej 6 Odense M Danmark 5230",
    "addr:housenumber":"6",
    "addr:postcode":"5230",
    "addr:street":"Eckersbergsvej",
    "iso:country":"DK",
    "sg:address":"Eckersbergsvej 6",
    "sg:city":"Odense M",
    "sg:orig_category":"Reklamebureauer",
    "sg:phone":"+45 66 14 83 09",
    "sg:postcode":"5230",
    "sg:province":"Danmark",
    "wof:name":"Larsen, Mogens",
    "wof:placetype":"venue"
},
  "geometry": {"coordinates":[10.4137687683,55.3893356323],"type":"Point"}
}