{
  "type": "Feature",
  "properties": {
    "addr:full":"Torvet 1, Hornum Aars Danmark 9600",
    "addr:housenumber":"1",
    "addr:postcode":"9600",
    "addr:street":"Torvet",
    "iso:country":"DK",
    "sg:address":"Torvet 1, Hornum",
    "sg:city":"Aars",
    "sg:classifiers":[
        {
            "category":"Building & Trades",
            "subcategory":"Construction",
            "type":"Services"
        }
    ],
    "sg:phone":"+45 98 66 13 01",
    "sg:postcode":"9600",
    "sg:province":"Danmark",
    "sg:tags":[
        "ventilation"
    ],
    "wof:name":"Hornum Kro",
    "wof:placetype":"venue"
},
  "geometry": {"coordinates":[9.5170412064,56.8031692505],"type":"Point"}
}