{
  "type": "Feature",
  "properties": {
    "addr:full":"Gl. Baneg\u00e5rdsvej 5 Middelfart Danmark 5500",
    "addr:housenumber":"5",
    "addr:postcode":"5500",
    "addr:street":"Gl. Banegaardsvej",
    "iso:country":"DK",
    "sg:address":"Gl. Baneg\u00e5rdsvej 5",
    "sg:city":"Middelfart",
    "sg:orig_category":"Cykler",
    "sg:phone":"+45 64 41 46 26",
    "sg:postcode":"5500",
    "sg:province":"Danmark",
    "wof:name":"Pedalhuset",
    "wof:placetype":"venue"
},
  "geometry": {"coordinates":[9.7412033081,55.5035095215],"type":"Point"}
}