{
  "type": "Feature",
  "properties": {
    "addr:full":"Digevej 4, Lundeh\u00f8je Errindlev Danmark 4895",
    "addr:housenumber":"4",
    "addr:postcode":"4895",
    "addr:street":"Digevej",
    "iso:country":"DK",
    "sg:address":"Digevej 4, Lundeh\u00f8je",
    "sg:city":"Errindlev",
    "sg:orig_category":"Fiskeeksport",
    "sg:phone":"+45 54 60 00 87",
    "sg:postcode":"4895",
    "sg:province":"Danmark",
    "wof:name":"Jensens \u00c5leeksport A/S, Henning",
    "wof:placetype":"venue"
},
  "geometry": {"coordinates":[11.4964237213,54.6684608459],"type":"Point"}
}