{
  "type": "Feature",
  "properties": {
    "addr:full":"Nygade 17 Gr\u00e5sten Danmark 6300",
    "addr:housenumber":"17",
    "addr:postcode":"6300",
    "addr:street":"Nygade",
    "iso:country":"DK",
    "sg:address":"Nygade 17",
    "sg:city":"Gr\u00e5sten",
    "sg:classifiers":[
        {
            "category":"Banks & Credit Unions",
            "subcategory":"Bank",
            "type":"Services"
        }
    ],
    "sg:phone":"+45 73 35 73 73",
    "sg:postcode":"6300",
    "sg:province":"Danmark",
    "sg:tags":[
        "banker"
    ],
    "wof:name":"Sydbank",
    "wof:placetype":"venue"
},
  "geometry": {"coordinates":[9.5957422256,54.9212722778],"type":"Point"}
}