{
  "type": "Feature",
  "properties": {
    "iso:country":"DK",
    "sg:address":"Doktor Abildgaards All\u00e9 2",
    "sg:city":"Frederiksberg",
    "sg:orig_category":"Vaskerier",
    "sg:phone":"+45 35 35 48 18",
    "sg:postcode":"1955",
    "sg:province":"Danmark",
    "wof:name":"Andersens Vaskeri, John",
    "wof:placetype":"venue"
},
  "geometry": {"coordinates":[12.5410003662,55.6843948364],"type":"Point"}
}