{
  "type": "Feature",
  "properties": {
    "addr:full":"Skindergade 34 K\u00f8benhavn Danmark 1159",
    "addr:housenumber":"34;1159",
    "addr:street":"Skindergade",
    "iso:country":"DK",
    "sg:address":"Skindergade 34",
    "sg:city":"K\u00f8benhavn",
    "sg:orig_category":"Antikvariater",
    "sg:phone":"+45 33 15 41 77",
    "sg:postcode":"1159",
    "sg:province":"Danmark",
    "wof:name":"Kaabers Antikvariat",
    "wof:placetype":"venue"
},
  "geometry": {"coordinates":[12.5747699738,55.6798706055],"type":"Point"}
}