{
  "type": "Feature",
  "properties": {
    "addr:full":"Blichersvej 15 A, Thorning Kjellerup Danmark 8620",
    "addr:housenumber":"15 a",
    "addr:postcode":"8620",
    "addr:street":"Blichersvej",
    "iso:country":"DK",
    "sg:address":"Blichersvej 15 A, Thorning",
    "sg:city":"Kjellerup",
    "sg:orig_category":"Cafeer",
    "sg:phone":"+45 86 88 09 56",
    "sg:postcode":"8620",
    "sg:province":"Danmark",
    "wof:name":"Thorning Caf\u00e9",
    "wof:placetype":"venue"
},
  "geometry": {"coordinates":[9.430934906,56.2877655029],"type":"Point"}
}