{
  "type": "Feature",
  "properties": {
    "addr:full":"Kirkebakken 6, Aagaard Egtved Danmark 6040",
    "addr:housenumber":"6",
    "addr:postcode":"6040",
    "addr:street":"Kirkebakken",
    "iso:country":"DK",
    "sg:address":"Kirkebakken 6, Aagaard",
    "sg:city":"Egtved",
    "sg:orig_category":"Valg- og frimenigheder",
    "sg:phone":"+45 75 55 31 22",
    "sg:postcode":"6040",
    "sg:province":"Danmark",
    "wof:name":"\u00c5g\u00e5rd Frimenighed",
    "wof:placetype":"venue"
},
  "geometry": {"coordinates":[9.3087482452,55.6161613464],"type":"Point"}
}