{
  "type": "Feature",
  "properties": {
    "iso:country":"DK",
    "sg:address":"\u00c5kirkebyvej 2",
    "sg:city":"Herning",
    "sg:orig_category":"Dag- og distriktsblade",
    "sg:phone":"+45 97 12 26 55",
    "sg:postcode":"7400",
    "sg:province":"Danmark",
    "wof:name":"Sunds-Gjellerup Avis",
    "wof:placetype":"venue"
},
  "geometry": {"coordinates":[8.979724884,56.1545562744],"type":"Point"}
}