{
  "type": "Feature",
  "properties": {
    "iso:country":"DK",
    "sg:address":"Vestervej 27",
    "sg:city":"Ringsted",
    "sg:orig_category":"Specialskoler for handicappede",
    "sg:phone":"+45 57 67 17 17",
    "sg:postcode":"4100",
    "sg:province":"Danmark",
    "wof:name":"\u00c5dalskolen",
    "wof:placetype":"venue"
},
  "geometry": {"coordinates":[11.7810430527,55.4407463074],"type":"Point"}
}