{
  "type": "Feature",
  "properties": {
    "iso:country":"DK",
    "sg:address":"Sognepr\u00e6st: Karen Brunbjerg (K/B), T\u00f8nagervej 12, Gjerlev",
    "sg:city":"Gjerlev",
    "sg:orig_category":"Kirkesogne",
    "sg:phone":"+45 86 47 46 97",
    "sg:postcode":"8983",
    "sg:province":"Danmark",
    "wof:name":"Gjerlev og Enslev sogne",
    "wof:placetype":"venue"
},
  "geometry": {"coordinates":[10.1887750626,56.5788421631],"type":"Point"}
}