{
  "type": "Feature",
  "properties": {
    "addr:full":"Maig\u00e5rdsvej 2 A Frederikshavn Danmark 9900",
    "addr:housenumber":"2 a",
    "addr:postcode":"9900",
    "addr:street":"Maigaardsvej",
    "iso:country":"DK",
    "sg:address":"Maig\u00e5rdsvej 2 A",
    "sg:city":"Frederikshavn",
    "sg:orig_category":"Farver en gros",
    "sg:phone":"+45 98 43 88 88",
    "sg:postcode":"9900",
    "sg:province":"Danmark",
    "wof:name":"Dyrups Malercenter",
    "wof:placetype":"venue"
},
  "geometry": {"coordinates":[10.501709938,57.4471702576],"type":"Point"}
}