{
  "type": "Feature",
  "properties": {
    "addr:full":"Nyborgvej 674, Aasum Odense S\u00d8 Danmark 5220",
    "addr:housenumber":"674",
    "addr:postcode":"5220",
    "addr:street":"Nyborgvej",
    "iso:country":"DK",
    "sg:address":"Nyborgvej 674, Aasum",
    "sg:city":"Odense S\u00d8",
    "sg:orig_category":"Gartnerier",
    "sg:phone":"+45 65 95 12 03",
    "sg:postcode":"5220",
    "sg:province":"Danmark",
    "wof:name":"Vesterg\u00e5rd Nielsen",
    "wof:placetype":"venue"
},
  "geometry": {"coordinates":[10.4583454132,55.3316917419],"type":"Point"}
}