{
  "type": "Feature",
  "properties": {
    "addr:full":"Fmd.: Helle Ravn Pedersen, Rugstedvej 10, Rugsted Vejle Danmark 7100",
    "addr:housenumber":"10",
    "addr:postcode":"7100",
    "addr:street":"Ravn;Rugstedvej;Rugsted",
    "iso:country":"DK",
    "sg:address":"Fmd.: Helle Ravn Pedersen, Rugstedvej 10, Rugsted",
    "sg:city":"Vejle",
    "sg:orig_category":"Oplysningsforbund",
    "sg:phone":"+45 75 86 54 16",
    "sg:postcode":"7100",
    "sg:province":"Danmark",
    "wof:name":"LOF",
    "wof:placetype":"venue"
},
  "geometry": {"coordinates":[9.5368051529,55.7113952637],"type":"Point"}
}