{
  "type": "Feature",
  "properties": {
    "addr:full":"Robert Svendsens Vej 4 Vadum Danmark 9430",
    "addr:housenumber":"4",
    "addr:postcode":"9430",
    "addr:street":"Robert Svendsens Vej",
    "iso:country":"DK",
    "sg:address":"Robert Svendsens Vej 4",
    "sg:city":"Vadum",
    "sg:orig_category":"Autoreparation og -service",
    "sg:phone":"+45 98 27 20 00",
    "sg:postcode":"9430",
    "sg:province":"Danmark",
    "wof:name":"P. J. Auto",
    "wof:placetype":"venue"
},
  "geometry": {"coordinates":[9.8627386093,57.1187744141],"type":"Point"}
}