{
  "type": "Feature",
  "properties": {
    "addr:full":"VIF's Sekretariat, Hovedgaden 10 H\u00f8rsholm Danmark 2970",
    "addr:housenumber":"10",
    "addr:postcode":"2970",
    "addr:street":"Hovedgaden",
    "iso:country":"DK",
    "sg:address":"VIF's Sekretariat, Hovedgaden 10",
    "sg:city":"H\u00f8rsholm",
    "sg:orig_category":"Faglige organisationer og -foreninger",
    "sg:phone":"+45 45 86 53 91",
    "sg:postcode":"2970",
    "sg:province":"Danmark",
    "sg:website":"www.if-isolering.dk",
    "wof:name":"Fabrikanter af Varmeisoleringsmaterialer, Dansk Forening af",
    "wof:placetype":"venue"
},
  "geometry": {"coordinates":[9.2555503845,54.9375686646],"type":"Point"}
}