{
  "type": "Feature",
  "properties": {
    "addr:full":"Brandsbyvej 35, Emmelev Otterup Danmark 5450",
    "addr:housenumber":"35",
    "addr:postcode":"5450",
    "addr:street":"Brandsbyvej",
    "iso:country":"DK",
    "sg:address":"Brandsbyvej 35, Emmelev",
    "sg:city":"Otterup",
    "sg:orig_category":"Antikviteter",
    "sg:phone":"+45 64 82 33 70",
    "sg:postcode":"5450",
    "sg:province":"Danmark",
    "wof:name":"Otterup Antik",
    "wof:placetype":"venue"
},
  "geometry": {"coordinates":[10.4545049667,55.5641746521],"type":"Point"}
}