{
  "type": "Feature",
  "properties": {
    "addr:full":"Gyldenbjergvej 1, Orehoved N\u00f8rre Alslev Danmark 4840",
    "addr:housenumber":"1",
    "addr:postcode":"4840",
    "addr:street":"Gyldenbjergvej",
    "iso:country":"DK",
    "sg:address":"Gyldenbjergvej 1, Orehoved",
    "sg:city":"N\u00f8rre Alslev",
    "sg:orig_category":"Apoteker og -udsalg",
    "sg:phone":"+45 54 44 60 12",
    "sg:postcode":"4840",
    "sg:province":"Danmark",
    "wof:name":"H\u00e5ndk\u00f8bsudsalget i Orehoved",
    "wof:placetype":"venue"
},
  "geometry": {"coordinates":[11.8542251587,54.9528236389],"type":"Point"}
}