{
  "type": "Feature",
  "properties": {
    "addr:full":"Husager 15 Vejle \u00d8 Danmark 7120",
    "addr:housenumber":"15",
    "addr:postcode":"7120",
    "addr:street":"Husager",
    "iso:country":"DK",
    "sg:address":"Husager 15",
    "sg:city":"Vejle \u00d8",
    "sg:orig_category":"Zoneterapeuter",
    "sg:phone":"+45 75 81 49 16",
    "sg:postcode":"7120",
    "sg:province":"Danmark",
    "wof:name":"Nowack, Britta",
    "wof:placetype":"venue"
},
  "geometry": {"coordinates":[9.6154184341,55.7173652649],"type":"Point"}
}