{
  "type": "Feature",
  "properties": {
    "addr:full":"Torvegade 15 Gram Danmark 6510",
    "addr:housenumber":"15",
    "addr:postcode":"6510",
    "addr:street":"Torvegade",
    "iso:country":"DK",
    "sg:address":"Torvegade 15",
    "sg:city":"Gram",
    "sg:orig_category":"Autoreparation og -service",
    "sg:phone":"+45 74 82 15 45",
    "sg:postcode":"6510",
    "sg:province":"Danmark",
    "wof:name":"Gram Autocentral",
    "wof:placetype":"venue"
},
  "geometry": {"coordinates":[9.0476799011,55.2893753052],"type":"Point"}
}