{
  "type": "Feature",
  "properties": {
    "addr:full":"v/ Dorthe Dahl, Lyngvej 14,2. Kongens Lyngby Danmark 2800",
    "addr:housenumber":"14,2",
    "addr:postcode":"2800",
    "addr:street":"Lyngvej",
    "iso:country":"DK",
    "sg:address":"v/ Dorthe Dahl, Lyngvej 14,2.",
    "sg:city":"Kongens Lyngby",
    "sg:orig_category":"Grundejerforeninger",
    "sg:phone":"+45 45 87 60 90",
    "sg:postcode":"2800",
    "sg:province":"Danmark",
    "wof:name":"Grundejerforeningen Strandg\u00e5rden",
    "wof:placetype":"venue"
},
  "geometry": {"coordinates":[12.5368299484,55.7949905396],"type":"Point"}
}