{
  "type": "Feature",
  "properties": {
    "iso:country":"DK",
    "sg:address":"Frederiksgade 74 A",
    "sg:city":"\u00c5rhus C",
    "sg:orig_category":"Advokater",
    "sg:phone":"+45 86 12 22 11",
    "sg:postcode":"8000",
    "sg:province":"Danmark",
    "wof:name":"Mygind, Anders",
    "wof:placetype":"venue"
},
  "geometry": {"coordinates":[10.203373909,56.1542167664],"type":"Point"}
}