{
  "type": "Feature",
  "properties": {
    "addr:full":"Hyrdevej 18 Esperg\u00e6rde Danmark 3060",
    "addr:housenumber":"18",
    "addr:postcode":"3060",
    "addr:street":"Hyrdevej",
    "iso:country":"DK",
    "sg:address":"Hyrdevej 18",
    "sg:city":"Esperg\u00e6rde",
    "sg:orig_category":"Malermestre",
    "sg:phone":"+45 49 13 24 46",
    "sg:postcode":"3060",
    "sg:province":"Danmark",
    "wof:name":"Jensen & S\u00f8n, Axel",
    "wof:placetype":"venue"
},
  "geometry": {"coordinates":[11.6512403488,47.8390617371],"type":"Point"}
}