{
  "type": "Feature",
  "properties": {
    "addr:full":"Louisevej 6 Brabrand Danmark 8220",
    "addr:housenumber":"6",
    "addr:postcode":"8220",
    "addr:street":"Louisevej",
    "iso:country":"DK",
    "sg:address":"Louisevej 6",
    "sg:city":"Brabrand",
    "sg:orig_category":"Ungdomscentre",
    "sg:phone":"+45 86 25 57 77",
    "sg:postcode":"8220",
    "sg:province":"Danmark",
    "wof:name":"St\u00f8tte p\u00e5 Tv\u00e6rs Vest",
    "wof:placetype":"venue"
},
  "geometry": {"coordinates":[10.1337471008,56.1523094177],"type":"Point"}
}