{
  "type": "Feature",
  "properties": {
    "addr:full":"Villeb\u00f8lvej 5, Villeb\u00f8l Ribe Danmark 6760",
    "addr:housenumber":"5",
    "addr:postcode":"6760",
    "addr:street":"Villebolvej",
    "iso:country":"DK",
    "sg:address":"Villeb\u00f8lvej 5, Villeb\u00f8l",
    "sg:city":"Ribe",
    "sg:orig_category":"Alternativ behandling",
    "sg:phone":"+45 76 88 77 06",
    "sg:postcode":"6760",
    "sg:province":"Danmark",
    "wof:name":"Klinik for Reiki-Healing",
    "wof:placetype":"venue"
},
  "geometry": {"coordinates":[8.7656240463,55.3297042847],"type":"Point"}
}