{
  "type": "Feature",
  "properties": {
    "addr:full":"Solhvervsvej 16 \u00c5rhus N Danmark 8200",
    "addr:housenumber":"16",
    "addr:postcode":"8200",
    "addr:street":"Solhvervsvej",
    "iso:country":"DK",
    "sg:address":"Solhvervsvej 16",
    "sg:city":"\u00c5rhus N",
    "sg:orig_category":"Vagtbureauer",
    "sg:phone":"+45 26 62 09 30",
    "sg:postcode":"8200",
    "sg:province":"Danmark",
    "wof:name":"Universal Security I/S",
    "wof:placetype":"venue"
},
  "geometry": {"coordinates":[4.9393601418,49.7092018127],"type":"Point"}
}