{
  "type": "Feature",
  "properties": {
    "addr:full":"Jyllandsvej 6 Slagelse Danmark 4200",
    "addr:housenumber":"6",
    "addr:postcode":"4200",
    "addr:street":"Jyllandsvej",
    "iso:country":"DK",
    "sg:address":"Jyllandsvej 6",
    "sg:city":"Slagelse",
    "sg:orig_category":"Autoreparation og -service",
    "sg:phone":"+45 58 50 03 24",
    "sg:postcode":"4200",
    "sg:province":"Danmark",
    "wof:name":"Auto Ole",
    "wof:placetype":"venue"
},
  "geometry": {"coordinates":[11.3423376083,55.3972473145],"type":"Point"}
}