{
  "type": "Feature",
  "properties": {
    "addr:full":"Haderslevvej 3 Aabenraa Danmark 6200",
    "addr:housenumber":"3",
    "addr:postcode":"6200",
    "addr:street":"Haderslevvej",
    "iso:country":"DK",
    "sg:address":"Haderslevvej 3",
    "sg:city":"Aabenraa",
    "sg:orig_category":"Biblioteker",
    "sg:phone":"+45 74 62 25 62",
    "sg:postcode":"6200",
    "sg:province":"Danmark",
    "sg:website":"www.dslbibl.dk",
    "wof:name":"Det S\u00f8nderjydske Landsbibliotek",
    "wof:placetype":"venue"
},
  "geometry": {"coordinates":[9.4205093384,55.0494651794],"type":"Point"}
}