{
  "type": "Feature",
  "properties": {
    "addr:full":"\u00d8stbirkvej 36 Horsens Danmark 8700",
    "addr:housenumber":"36",
    "addr:postcode":"8700",
    "addr:street":"Ostbirkvej",
    "iso:country":"DK",
    "sg:address":"\u00d8stbirkvej 36",
    "sg:city":"Horsens",
    "sg:orig_category":"Dyrefoder",
    "sg:phone":"+45 75 65 62 64",
    "sg:postcode":"8700",
    "sg:province":"Danmark",
    "sg:website":"www.foderhuset.dk",
    "wof:name":"Foderhuset",
    "wof:placetype":"venue"
},
  "geometry": {"coordinates":[9.8105926514,55.9234313965],"type":"Point"}
}