{
  "type": "Feature",
  "properties": {
    "addr:full":"Vindingg\u00e5rd Center 27 C Vejle Danmark 7100",
    "addr:housenumber":"27 c",
    "addr:postcode":"7100",
    "iso:country":"DK",
    "sg:address":"Vindingg\u00e5rd Center 27 C",
    "sg:city":"Vejle",
    "sg:orig_category":"Posthuse",
    "sg:phone":"+45 79 43 50 00",
    "sg:postcode":"7100",
    "sg:province":"Danmark",
    "wof:name":"Post Danmark, Vindingg\u00e5rd Center Posthus",
    "wof:placetype":"venue"
},
  "geometry": {"coordinates":[9.5518302917,55.6884346008],"type":"Point"}
}