{
  "type": "Feature",
  "properties": {
    "addr:full":"M. P. Bruuns Gade 39 \u00c5rhus C Danmark 8000",
    "addr:housenumber":"39",
    "addr:postcode":"8000",
    "addr:street":"P. Bruuns Gade",
    "iso:country":"DK",
    "sg:address":"M. P. Bruuns Gade 39",
    "sg:city":"\u00c5rhus C",
    "sg:classifiers":[
        {
            "category":"Food & Beverages",
            "subcategory":"Liquor & Beverages",
            "type":"Retail Goods"
        }
    ],
    "sg:phone":"+45 86 13 31 31",
    "sg:postcode":"8000",
    "sg:province":"Danmark",
    "sg:tags":[
        "vin"
    ],
    "wof:name":"Aarhus Vinhandel",
    "wof:placetype":"venue"
},
  "geometry": {"coordinates":[99.92501068120001,34.2430114746],"type":"Point"}
}