{
  "type": "Feature",
  "properties": {
    "iso:country":"DK",
    "sg:address":"P. G. Ramms Alle 64",
    "sg:city":"Frederiksberg",
    "sg:classifiers":[
        {
            "category":"Home & Garden",
            "subcategory":"Home Furnishings",
            "type":"Retail Goods"
        }
    ],
    "sg:phone":"+45 38 86 30 57",
    "sg:postcode":"2000",
    "sg:province":"Danmark",
    "sg:tags":[
        "gardiner"
    ],
    "wof:name":"A B A Gardiner",
    "wof:placetype":"venue"
},
  "geometry": {"coordinates":[12.5068378448,55.6803321838],"type":"Point"}
}