{
  "type": "Feature",
  "properties": {
    "iso:country":"DK",
    "sg:address":"Trondsvej 16",
    "sg:city":"Skagen",
    "sg:orig_category":"Gallerier",
    "sg:phone":"+45 98 44 44 25",
    "sg:postcode":"9990",
    "sg:province":"Danmark",
    "wof:name":"Galleri Skagen",
    "wof:placetype":"venue"
},
  "geometry": {"coordinates":[10.5864343643,57.7200965881],"type":"Point"}
}