{
  "type": "Feature",
  "properties": {
    "addr:full":"Ingridsvej 14, Ejby Kirke Hyllinge Danmark 4070",
    "addr:housenumber":"14",
    "addr:postcode":"4070",
    "addr:street":"Ingridsvej",
    "iso:country":"DK",
    "sg:address":"Ingridsvej 14, Ejby",
    "sg:city":"Kirke Hyllinge",
    "sg:orig_category":"Murermestre",
    "sg:phone":"+45 46 40 55 18",
    "sg:postcode":"4070",
    "sg:province":"Danmark",
    "wof:name":"Matthisen, Svend S\u00f8ndergaard",
    "wof:placetype":"venue"
},
  "geometry": {"coordinates":[11.9004745483,55.7080039978],"type":"Point"}
}