{
  "type": "Feature",
  "properties": {
    "addr:full":"Troldeh\u00f8j 1 B, Annisse Helsinge Danmark 3200",
    "addr:housenumber":"1 b",
    "addr:postcode":"3200",
    "addr:street":"Troldehoj;Annisse",
    "iso:country":"DK",
    "sg:address":"Troldeh\u00f8j 1 B, Annisse",
    "sg:city":"Helsinge",
    "sg:orig_category":"Revisorer",
    "sg:phone":"+45 48 79 77 71",
    "sg:postcode":"3200",
    "sg:province":"Danmark",
    "wof:name":"M\u00f8ller, Erik",
    "wof:placetype":"venue"
},
  "geometry": {"coordinates":[12.196846962,56.0224456787],"type":"Point"}
}