{
  "type": "Feature",
  "properties": {
    "addr:full":"v/ \u00d8jvind Andreasen, Fabjergvej 53, N\u00f8rlem Lemvig Danmark 7620",
    "addr:housenumber":"53",
    "addr:postcode":"7620",
    "addr:street":"Fabjergvej",
    "iso:country":"DK",
    "sg:address":"v/ \u00d8jvind Andreasen, Fabjergvej 53, N\u00f8rlem",
    "sg:city":"Lemvig",
    "sg:orig_category":"Forbrugerorganisationer",
    "sg:phone":"+45 97 82 23 65",
    "sg:postcode":"7620",
    "sg:province":"Danmark",
    "wof:name":"Socialt Forbrugerr\u00e5d",
    "wof:placetype":"venue"
},
  "geometry": {"coordinates":[8.3073654175,56.5505104065],"type":"Point"}
}