{
  "type": "Feature",
  "properties": {
    "addr:full":"Torvet 6 Ringsted Danmark 4100",
    "addr:housenumber":"6",
    "addr:postcode":"4100",
    "addr:street":"Torvet",
    "iso:country":"DK",
    "sg:address":"Torvet 6",
    "sg:city":"Ringsted",
    "sg:orig_category":"Advokater",
    "sg:phone":"+45 57 61 31 32",
    "sg:postcode":"4100",
    "sg:province":"Danmark",
    "sg:website":"www.advokatfirmaet-svendsen.dk",
    "wof:name":"Advokatfirmaet Svendsen",
    "wof:placetype":"venue"
},
  "geometry": {"coordinates":[11.7886734009,55.445148468],"type":"Point"}
}