{
  "type": "Feature",
  "properties": {
    "addr:full":"Ringstedgade 31 A Roskilde Danmark 4000",
    "addr:housenumber":"31 a",
    "addr:postcode":"4000",
    "addr:street":"Ringstedgade",
    "iso:country":"DK",
    "sg:address":"Ringstedgade 31 A",
    "sg:city":"Roskilde",
    "sg:orig_category":"Solcentre",
    "sg:phone":"+45 46 35 22 10",
    "sg:postcode":"4000",
    "sg:province":"Danmark",
    "wof:name":"Sunshine",
    "wof:placetype":"venue"
},
  "geometry": {"coordinates":[12.0763349533,55.6375923157],"type":"Point"}
}