{
  "type": "Feature",
  "properties": {
    "addr:full":"Brogade 28 Bjerringbro Danmark 8850",
    "addr:housenumber":"28",
    "addr:postcode":"8850",
    "addr:street":"Brogade",
    "iso:country":"DK",
    "sg:address":"Brogade 28",
    "sg:city":"Bjerringbro",
    "sg:orig_category":"Grillbarer",
    "sg:phone":"+45 86 68 49 61",
    "sg:postcode":"8850",
    "sg:province":"Danmark",
    "wof:name":"S\u00f8nderbro P\u00f8lsevogn",
    "wof:placetype":"venue"
},
  "geometry": {"coordinates":[9.6599683762,56.3703460693],"type":"Point"}
}