{
  "type": "Feature",
  "properties": {
    "addr:full":"Havnen 14 Hals Danmark 9370",
    "addr:housenumber":"14",
    "addr:postcode":"9370",
    "addr:street":"Havnen",
    "iso:country":"DK",
    "sg:address":"Havnen 14",
    "sg:city":"Hals",
    "sg:classifiers":[
        {
            "category":"Restaurant",
            "type":"Food & Drink"
        }
    ],
    "sg:phone":"+45 98 25 10 64",
    "sg:postcode":"9370",
    "sg:province":"Danmark",
    "wof:name":"Kommand\u00f8ren",
    "wof:placetype":"venue"
},
  "geometry": {"coordinates":[10.305937767,56.9913444519],"type":"Point"}
}