{
  "type": "Feature",
  "properties": {
    "addr:full":"N\u00f8rrebrogade 52 Randers Danmark 8900",
    "addr:housenumber":"52",
    "addr:postcode":"8900",
    "addr:street":"Norrebrogade",
    "iso:country":"DK",
    "sg:address":"N\u00f8rrebrogade 52",
    "sg:city":"Randers",
    "sg:orig_category":"Slagter og viktualie",
    "sg:phone":"+45 86 42 01 54",
    "sg:postcode":"8900",
    "sg:province":"Danmark",
    "wof:name":"Frandsen, Slagter",
    "wof:placetype":"venue"
},
  "geometry": {"coordinates":[10.036860466,56.4702911377],"type":"Point"}
}