{
  "type": "Feature",
  "properties": {
    "addr:full":"St. Algade 15 Nibe Danmark 9240",
    "addr:housenumber":"15",
    "addr:postcode":"9240",
    "addr:street":"St. Algade",
    "iso:country":"DK",
    "sg:address":"St. Algade 15",
    "sg:city":"Nibe",
    "sg:orig_category":"Materialister",
    "sg:phone":"+45 98 35 22 50",
    "sg:postcode":"9240",
    "sg:province":"Danmark",
    "wof:name":"Matas",
    "wof:placetype":"venue"
},
  "geometry": {"coordinates":[9.6393280029,56.982421875],"type":"Point"}
}