{
  "type": "Feature",
  "properties": {
    "addr:full":"H\u00f8egh Guldbergs Gade 1  Horsens Danmark 8700",
    "addr:housenumber":"1",
    "addr:postcode":"8700",
    "addr:street":"Hoegh Guldbergs Gade",
    "iso:country":"DK",
    "sg:address":"H\u00f8egh Guldbergs Gade 1 ",
    "sg:city":"Horsens",
    "sg:classifiers":[
        {
            "category":"Home & Garden",
            "subcategory":"Home Furnishings",
            "type":"Retail Goods"
        }
    ],
    "sg:phone":"+45 75 62 13 15",
    "sg:postcode":"8700",
    "sg:province":"Danmark",
    "sg:tags":[
        "household"
    ],
    "wof:name":"OLE JENSEN M\u00d8BLER & T\u00c6PPER A/S",
    "wof:placetype":"venue"
},
  "geometry": {"coordinates":[9.8546380997,55.8590087891],"type":"Point"}
}