{
  "type": "Feature",
  "properties": {
    "addr:full":"Hovedgaden 15 Billund Danmark 7190",
    "addr:housenumber":"15",
    "addr:postcode":"7190",
    "addr:street":"Hovedgaden",
    "iso:country":"DK",
    "sg:address":"Hovedgaden 15",
    "sg:city":"Billund",
    "sg:orig_category":"Materialister",
    "sg:phone":"+45 75 33 86 53",
    "sg:postcode":"7190",
    "sg:province":"Danmark",
    "wof:name":"Materialisten i Billund",
    "wof:placetype":"venue"
},
  "geometry": {"coordinates":[9.1136236191,55.7315406799],"type":"Point"}
}