{
  "type": "Feature",
  "properties": {
    "iso:country":"DK",
    "sg:address":"Fmd.: Mona Pedersen, Lindenborgvej 1, Komdrup",
    "sg:city":"Kongerslev",
    "sg:orig_category":"Husflidsforeninger",
    "sg:phone":"+45 98 33 16 80",
    "sg:postcode":"9293",
    "sg:province":"Danmark",
    "wof:name":"Kongerslev Husmoderforening",
    "wof:placetype":"venue"
},
  "geometry": {"coordinates":[10.1150007248,56.8851165771],"type":"Point"}
}