{
  "type": "Feature",
  "properties": {
    "addr:full":"Egeg\u00e5rdsvej 32 34 R\u00f8dovre Danmark 2610",
    "addr:housenumber":"32 34",
    "addr:postcode":"2610",
    "addr:street":"Egegaardsvej",
    "iso:country":"DK",
    "sg:address":"Egeg\u00e5rdsvej 32 34",
    "sg:city":"R\u00f8dovre",
    "sg:orig_category":"Fotosats",
    "sg:phone":"+45 36 41 38 00",
    "sg:postcode":"2610",
    "sg:province":"Danmark",
    "wof:name":"E B Sats",
    "wof:placetype":"venue"
},
  "geometry": {"coordinates":[10.6992139816,61.1027755737],"type":"Point"}
}