{
  "type": "Feature",
  "properties": {
    "addr:full":"Bygaden 101 Dalmose Danmark 4261",
    "addr:housenumber":"101",
    "addr:postcode":"4261",
    "addr:street":"Bygaden",
    "iso:country":"DK",
    "sg:address":"Bygaden 101",
    "sg:city":"Dalmose",
    "sg:orig_category":"Kirker",
    "sg:postcode":"4261",
    "sg:province":"Danmark",
    "wof:name":"H\u00f8ve Kirke",
    "wof:placetype":"venue"
},
  "geometry": {"coordinates":[11.3836603165,55.2824783325],"type":"Point"}
}