{
  "type": "Feature",
  "properties": {
    "addr:full":"H\u00e5rupvej 6 Silkeborg Danmark 8600",
    "addr:housenumber":"6",
    "addr:postcode":"8600",
    "addr:street":"Haarupvej",
    "iso:country":"DK",
    "sg:address":"H\u00e5rupvej 6",
    "sg:city":"Silkeborg",
    "sg:orig_category":"Autoopretning",
    "sg:phone":"+45 86 84 61 59",
    "sg:postcode":"8600",
    "sg:province":"Danmark",
    "wof:name":"Hedelund Auto",
    "wof:placetype":"venue"
},
  "geometry": {"coordinates":[9.6569662094,56.1611213684],"type":"Point"}
}