{
  "type": "Feature",
  "properties": {
    "addr:full":"Glarbjergvej 107 A Randers Danmark 8900",
    "addr:housenumber":"107 a",
    "addr:postcode":"8900",
    "addr:street":"Glarbjergvej",
    "iso:country":"DK",
    "sg:address":"Glarbjergvej 107 A",
    "sg:city":"Randers",
    "sg:orig_category":"Ungdomsklubber",
    "sg:phone":"+45 86 43 10 80",
    "sg:postcode":"8900",
    "sg:province":"Danmark",
    "wof:name":"KFUM's Ungdomsklub",
    "wof:placetype":"venue"
},
  "geometry": {"coordinates":[10.0378875732,56.480266571],"type":"Point"}
}