{
  "type": "Feature",
  "properties": {
    "iso:country":"DK",
    "sg:address":"Vesterbrogade 83",
    "sg:city":"Vejle",
    "sg:orig_category":"Kiosker",
    "sg:phone":"+45 75 82 01 88",
    "sg:postcode":"7100",
    "sg:province":"Danmark",
    "wof:name":"Vestbyens D\u00f8gnkiosk",
    "wof:placetype":"venue"
},
  "geometry": {"coordinates":[9.5285243988,55.7156867981],"type":"Point"}
}