{
  "type": "Feature",
  "properties": {
    "addr:full":"Skovvej 3 Skagen Danmark 9990",
    "addr:housenumber":"3",
    "addr:postcode":"9990",
    "addr:street":"Skovvej",
    "iso:country":"DK",
    "sg:address":"Skovvej 3",
    "sg:city":"Skagen",
    "sg:orig_category":"Revisorer",
    "sg:phone":"+45 98 44 14 00",
    "sg:postcode":"9990",
    "sg:province":"Danmark",
    "wof:name":"Andersen, Revisionsfirmaet Steen",
    "wof:placetype":"venue"
},
  "geometry": {"coordinates":[10.5850963593,57.720916748],"type":"Point"}
}