{
  "type": "Feature",
  "properties": {
    "addr:full":"Sp\u00f8rringvej 42, Mejlby Hjortsh\u00f8j Danmark 8530",
    "addr:housenumber":"42",
    "addr:postcode":"8530",
    "addr:street":"Sporringvej;Mejlby Hjortshoj Danmark",
    "iso:country":"DK",
    "sg:address":"Sp\u00f8rringvej 42, Mejlby",
    "sg:city":"Hjortsh\u00f8j",
    "sg:orig_category":"Musik- og sangundervisning",
    "sg:phone":"+45 86 98 97 55",
    "sg:postcode":"8530",
    "sg:province":"Danmark",
    "wof:name":"Ferenczi, Janos",
    "wof:placetype":"venue"
},
  "geometry": {"coordinates":[10.1459388733,56.2984962463],"type":"Point"}
}