{
  "type": "Feature",
  "properties": {
    "addr:full":"Vindeballegade 39 \u00c6r\u00f8sk\u00f8bing Danmark 5970",
    "addr:housenumber":"39",
    "addr:postcode":"5970",
    "addr:street":"Vindeballegade",
    "iso:country":"DK",
    "sg:address":"Vindeballegade 39",
    "sg:city":"\u00c6r\u00f8sk\u00f8bing",
    "sg:orig_category":"Maskinstationer",
    "sg:phone":"+45 62 52 21 08",
    "sg:postcode":"5970",
    "sg:province":"Danmark",
    "wof:name":"Nymann, J\u00f8rgen S\u00f8rensen",
    "wof:placetype":"venue"
},
  "geometry": {"coordinates":[-114.0767440796,46.4432487488],"type":"Point"}
}