{
  "type": "Feature",
  "properties": {
    "iso:country":"DK",
    "sg:address":"Vestergade 79",
    "sg:city":"Odense C",
    "sg:orig_category":"Broderi",
    "sg:phone":"+45 66 12 02 54",
    "sg:postcode":"5000",
    "sg:province":"Danmark",
    "wof:name":"Kj\u00e6rs Broderi",
    "wof:placetype":"venue"
},
  "geometry": {"coordinates":[10.3812742233,55.3944587708],"type":"Point"}
}