{
  "type": "Feature",
  "properties": {
    "addr:full":"Bugtrupvej 31 Kolind Danmark 8560",
    "addr:housenumber":"31",
    "addr:postcode":"8560",
    "addr:street":"Bugtrupvej",
    "iso:country":"DK",
    "sg:address":"Bugtrupvej 31",
    "sg:city":"Kolind",
    "sg:orig_category":"\u00c3\u2020ldrecentre",
    "sg:postcode":"8560",
    "sg:province":"Danmark",
    "wof:name":"Frejas V\u00e6nge",
    "wof:placetype":"venue"
},
  "geometry": {"coordinates":[10.5774488449,56.361125946],"type":"Point"}
}