{
  "type": "Feature",
  "properties": {
    "iso:country":"DK",
    "sg:address":"Vesterballevej 15 ",
    "sg:city":"Fredericia",
    "sg:classifiers":[
        {
            "category":"Manufacturing",
            "subcategory":"Glass & Minerals",
            "type":"Manufacturing & Wholesale Goods"
        }
    ],
    "sg:phone":"+45 75 94 11 33",
    "sg:postcode":"7000",
    "sg:province":"Danmark",
    "wof:name":"TARPGAARD A/S",
    "wof:placetype":"venue"
},
  "geometry": {"coordinates":[9.7180328369,55.5277175903],"type":"Point"}
}