{
  "type": "Feature",
  "properties": {
    "iso:country":"DK",
    "sg:address":"Aaparken 2",
    "sg:city":"Herning",
    "sg:orig_category":"Boligselskaber",
    "sg:phone":"+45 97 21 43 44",
    "sg:postcode":"7400",
    "sg:province":"Danmark",
    "wof:name":"Boligselskab Frueh\u00f8jgaard",
    "wof:placetype":"venue"
},
  "geometry": {"coordinates":[9.004034996,56.1367912292],"type":"Point"}
}