{
  "type": "Feature",
  "properties": {
    "addr:full":"Lundevangsvej 4 Hellerup Danmark 2900",
    "addr:housenumber":"4",
    "addr:postcode":"2900",
    "addr:street":"Lundevangsvej",
    "iso:country":"DK",
    "sg:address":"Lundevangsvej 4",
    "sg:city":"Hellerup",
    "sg:orig_category":"Konsulater",
    "sg:phone":"+45 39 62 62 88",
    "sg:postcode":"2900",
    "sg:province":"Danmark",
    "wof:name":"Israels Ambassade",
    "wof:placetype":"venue"
},
  "geometry": {"coordinates":[12.5788497925,55.7413787842],"type":"Point"}
}