{
  "type": "Feature",
  "properties": {
    "addr:full":"Odinsvej 174 Vojens Danmark 6500",
    "addr:housenumber":"174",
    "addr:postcode":"6500",
    "addr:street":"Odinsvej",
    "iso:country":"DK",
    "sg:address":"Odinsvej 174",
    "sg:city":"Vojens",
    "sg:orig_category":"Farve- og stilanalyse",
    "sg:phone":"+45 74 54 24 91",
    "sg:postcode":"6500",
    "sg:province":"Danmark",
    "wof:name":"Fuglsang, Inga",
    "wof:placetype":"venue"
},
  "geometry": {"coordinates":[9.2932348251,55.2519607544],"type":"Point"}
}