{
  "type": "Feature",
  "properties": {
    "addr:full":"Bredgade 28, Glyng\u00f8re Roslev Danmark 7870",
    "addr:housenumber":"28",
    "addr:postcode":"7870",
    "addr:street":"Bredgade;Glyngore",
    "iso:country":"DK",
    "sg:address":"Bredgade 28, Glyng\u00f8re",
    "sg:city":"Roslev",
    "sg:orig_category":"Advokater",
    "sg:phone":"+45 97 52 27 22",
    "sg:postcode":"7870",
    "sg:province":"Danmark",
    "wof:name":"Advokathuset A/S",
    "wof:placetype":"venue"
},
  "geometry": {"coordinates":[8.8715353012,56.7570304871],"type":"Point"}
}