{
  "type": "Feature",
  "properties": {
    "addr:full":"Amaliev\u00e6nget 3 Nakskov Danmark 4900",
    "addr:housenumber":"3",
    "addr:postcode":"4900",
    "addr:street":"Amalievaenget",
    "iso:country":"DK",
    "sg:address":"Amaliev\u00e6nget 3",
    "sg:city":"Nakskov",
    "sg:orig_category":"Oliefyr og service",
    "sg:phone":"+45 54 95 11 30",
    "sg:postcode":"4900",
    "sg:province":"Danmark",
    "wof:name":"Christensen ApS, Ole",
    "wof:placetype":"venue"
},
  "geometry": {"coordinates":[11.1359500885,54.8330116272],"type":"Point"}
}