{
  "type": "Feature",
  "properties": {
    "addr:full":"Saltgade 24 Ribe Danmark 6760",
    "addr:housenumber":"24",
    "addr:postcode":"6760",
    "addr:street":"Saltgade",
    "iso:country":"DK",
    "sg:address":"Saltgade 24",
    "sg:city":"Ribe",
    "sg:orig_category":"Cykler",
    "sg:phone":"+45 75 42 41 10",
    "sg:postcode":"6760",
    "sg:province":"Danmark",
    "wof:name":"Saltgades Cykler",
    "wof:placetype":"venue"
},
  "geometry": {"coordinates":[8.7674360275,55.331237793],"type":"Point"}
}