{
  "type": "Feature",
  "properties": {
    "iso:country":"DK",
    "sg:address":"Egehovedvej 4",
    "sg:city":"Marstal",
    "sg:orig_category":"HOTELS: OG MOTELLER",
    "sg:phone":"+45 62 53 33 20",
    "sg:postcode":"5960",
    "sg:province":"Danmark",
    "wof:name":"Hotel \u00c6r\u00f8 Strand",
    "wof:placetype":"venue"
},
  "geometry": {"coordinates":[10.5094232559,54.8506507874],"type":"Point"}
}