{
  "type": "Feature",
  "properties": {
    "addr:full":"M\u00f8rdrupvej 3 Esperg\u00e6rde Danmark 3060",
    "addr:housenumber":"3",
    "addr:postcode":"3060",
    "addr:street":"Mordrupvej",
    "iso:country":"DK",
    "sg:address":"M\u00f8rdrupvej 3",
    "sg:city":"Esperg\u00e6rde",
    "sg:orig_category":"Selskabslokaler",
    "sg:phone":"+45 49 13 23 35",
    "sg:postcode":"3060",
    "sg:province":"Danmark",
    "sg:website":"www.restaurant.leport.dk",
    "wof:name":"Le Port",
    "wof:placetype":"venue"
},
  "geometry": {"coordinates":[11.6512403488,47.8390617371],"type":"Point"}
}