{
  "type": "Feature",
  "properties": {
    "addr:full":"Kongelundsvej 297 Kastrup Danmark 2770",
    "addr:housenumber":"297",
    "addr:postcode":"2770",
    "addr:street":"Kongelundsvej",
    "iso:country":"DK",
    "sg:address":"Kongelundsvej 297",
    "sg:city":"Kastrup",
    "sg:orig_category":"Realkreditinstitutter",
    "sg:phone":"+45 32 50 25 25",
    "sg:postcode":"2770",
    "sg:province":"Danmark",
    "sg:website":"www.edc.dk",
    "wof:name":"H\u00f8j EDC M\u00e6glerne, Skytte",
    "wof:placetype":"venue"
},
  "geometry": {"coordinates":[12.5856704712,55.6161994934],"type":"Point"}
}