{
  "type": "Feature",
  "properties": {
    "iso:country":"DK",
    "sg:address":"Ahlefeldtsvej 15",
    "sg:city":"Odense M",
    "sg:orig_category":"Glarmestre og glarmagere",
    "sg:phone":"+45 66 12 60 94",
    "sg:postcode":"5230",
    "sg:province":"Danmark",
    "wof:name":"Alting Glas",
    "wof:placetype":"venue"
},
  "geometry": {"coordinates":[10.4036817551,55.3827362061],"type":"Point"}
}