{
  "type": "Feature",
  "properties": {
    "iso:country":"DK",
    "sg:address":"M\u00f8lleparken 7",
    "sg:city":"Lunderskov",
    "sg:orig_category":"EDB - udstyr",
    "sg:phone":"+45 75 58 66 47",
    "sg:postcode":"6640",
    "sg:province":"Danmark",
    "wof:name":"RT Data",
    "wof:placetype":"venue"
},
  "geometry": {"coordinates":[9.2943649292,55.4867973328],"type":"Point"}
}