{
  "type": "Feature",
  "properties": {
    "addr:full":"Skolevej 6 Ebberup Danmark 5631",
    "addr:housenumber":"6",
    "addr:postcode":"5631",
    "addr:street":"Skolevej",
    "iso:country":"DK",
    "sg:address":"Skolevej 6",
    "sg:city":"Ebberup",
    "sg:orig_category":"Puljeinstitutioner",
    "sg:phone":"+45 64 74 14 40",
    "sg:postcode":"5631",
    "sg:province":"Danmark",
    "wof:name":"B\u00f8rnehuset i Ebberup, Puljeinstitution",
    "wof:placetype":"venue"
},
  "geometry": {"coordinates":[9.9759302139,55.2405357361],"type":"Point"}
}