{
  "type": "Feature",
  "properties": {
    "iso:country":"DK",
    "sg:address":"Torvet 6",
    "sg:city":"Odder",
    "sg:orig_category":"Advokater",
    "sg:phone":"+45 86 54 02 11",
    "sg:postcode":"8300",
    "sg:province":"Danmark",
    "wof:name":"Advokaterne i Centrum",
    "wof:placetype":"venue"
},
  "geometry": {"coordinates":[10.1468048096,55.9720993042],"type":"Point"}
}