{
  "type": "Feature",
  "properties": {
    "addr:full":"N\u00f8rregade 12 B Ringsted Danmark 4100",
    "addr:housenumber":"12 b",
    "addr:postcode":"4100",
    "addr:street":"Norregade",
    "iso:country":"DK",
    "sg:address":"N\u00f8rregade 12 B",
    "sg:city":"Ringsted",
    "sg:orig_category":"Diskoteker",
    "sg:phone":"+45 57 67 66 04",
    "sg:postcode":"4100",
    "sg:province":"Danmark",
    "wof:name":"Apotekergaarden",
    "wof:placetype":"venue"
},
  "geometry": {"coordinates":[11.7892560959,55.4468917847],"type":"Point"}
}