{
  "type": "Feature",
  "properties": {
    "iso:country":"DK",
    "sg:address":"Nyborgvej 183",
    "sg:city":"Odense S\u00d8",
    "sg:classifiers":[
        {
            "category":"Restaurant",
            "type":"Food & Drink"
        }
    ],
    "sg:phone":"+45 66 12 23 73",
    "sg:postcode":"5220",
    "sg:province":"Danmark",
    "wof:name":"Napoli, Pizza",
    "wof:placetype":"venue"
},
  "geometry": {"coordinates":[10.4215335846,55.3929443359],"type":"Point"}
}