{
  "type": "Feature",
  "properties": {
    "addr:full":"Vestergade 5 Egtved Danmark 6040",
    "addr:housenumber":"5",
    "addr:postcode":"6040",
    "addr:street":"Vestergade",
    "iso:country":"DK",
    "sg:address":"Vestergade 5",
    "sg:city":"Egtved",
    "sg:orig_category":"Sko",
    "sg:phone":"+45 75 55 10 67",
    "sg:postcode":"6040",
    "sg:province":"Danmark",
    "wof:name":"Egtved Sko",
    "wof:placetype":"venue"
},
  "geometry": {"coordinates":[9.3064365387,55.6161613464],"type":"Point"}
}