{
  "type": "Feature",
  "properties": {
    "addr:full":"Vestergade 34 Randers Danmark 8900",
    "addr:housenumber":"34",
    "addr:postcode":"8900",
    "addr:street":"Vestergade",
    "iso:country":"DK",
    "sg:address":"Vestergade 34",
    "sg:city":"Randers",
    "sg:orig_category":"\u00c3\u02dcvrige skoler",
    "sg:phone":"+45 86 41 69 00",
    "sg:postcode":"8900",
    "sg:province":"Danmark",
    "wof:name":"Social- og Sundhedsskolen",
    "wof:placetype":"venue"
},
  "geometry": {"coordinates":[10.0287752151,56.4613342285],"type":"Point"}
}