{
  "type": "Feature",
  "properties": {
    "iso:country":"DK",
    "sg:address":"Jernbanegade 50",
    "sg:city":"Haslev",
    "sg:classifiers":[
        {
            "category":"Restaurant",
            "type":"Food & Drink"
        }
    ],
    "sg:phone":"+45 56 31 37 80",
    "sg:postcode":"4690",
    "sg:province":"Danmark",
    "wof:name":"Pedersens K\u00e6lder, Restaurant",
    "wof:placetype":"venue"
},
  "geometry": {"coordinates":[11.9635343552,55.3257408142],"type":"Point"}
}