{
  "type": "Feature",
  "properties": {
    "addr:full":"Havnegade 24, Jegind\u00f8 Thyholm Danmark 7790",
    "addr:housenumber":"24",
    "addr:postcode":"7790",
    "addr:street":"Havnegade",
    "iso:country":"DK",
    "sg:address":"Havnegade 24, Jegind\u00f8",
    "sg:city":"Thyholm",
    "sg:orig_category":"RESTAURANTS: CAFEER",
    "sg:phone":"+45 97 87 93 30",
    "sg:postcode":"7790",
    "sg:province":"Danmark",
    "wof:name":"\u00c6'skipperhus",
    "wof:placetype":"venue"
},
  "geometry": {"coordinates":[8.525765419,56.6507072449],"type":"Point"}
}