{
  "type": "Feature",
  "properties": {
    "addr:full":"Fredensgade 4 Silkeborg Danmark 8600",
    "addr:housenumber":"4",
    "addr:postcode":"8600",
    "addr:street":"Fredensgade",
    "iso:country":"DK",
    "sg:address":"Fredensgade 4",
    "sg:city":"Silkeborg",
    "sg:orig_category":"Pizzeriaer",
    "sg:phone":"+45 86 80 30 02",
    "sg:postcode":"8600",
    "sg:province":"Danmark",
    "wof:name":"US Pizza",
    "wof:placetype":"venue"
},
  "geometry": {"coordinates":[9.551320076,56.1683006287],"type":"Point"}
}