{
  "type": "Feature",
  "properties": {
    "iso:country":"DK",
    "sg:address":"Fmd.: Svend \u00c5. Christiansen, Dejbjergvej 20, Dejbjerg",
    "sg:city":"Skjern",
    "sg:orig_category":"Hobbybetonede foreninger",
    "sg:phone":"+45 97 34 11 67",
    "sg:postcode":"6900",
    "sg:province":"Danmark",
    "wof:name":"Dejbjerg Husflidsforening",
    "wof:placetype":"venue"
},
  "geometry": {"coordinates":[8.492972374,55.9485740662],"type":"Point"}
}