{
  "type": "Feature",
  "properties": {
    "iso:country":"DK",
    "sg:address":"Vardevej 1 G",
    "sg:city":"Vejle",
    "sg:orig_category":"Blomsterhandlere",
    "sg:phone":"+45 75 72 70 68",
    "sg:postcode":"7100",
    "sg:province":"Danmark",
    "sg:website":"www.decoplant.dk",
    "wof:name":"Deco Plant A/S",
    "wof:placetype":"venue"
},
  "geometry": {"coordinates":[9.5368051529,55.7113952637],"type":"Point"}
}