{
  "type": "Feature",
  "properties": {
    "iso:country":"DK",
    "sg:address":"Tagensvej 54",
    "sg:city":"K\u00f8benhavn N",
    "sg:orig_category":"Solcentre",
    "sg:phone":"+45 35 81 15 04",
    "sg:postcode":"2200",
    "sg:province":"Danmark",
    "wof:name":"Sun On",
    "wof:placetype":"venue"
},
  "geometry": {"coordinates":[-76.4168395996,37.452419281],"type":"Point"}
}