{
  "type": "Feature",
  "properties": {
    "addr:full":"Toften 21 Billund Danmark 7190",
    "addr:housenumber":"21",
    "addr:postcode":"7190",
    "addr:street":"Toften",
    "iso:country":"DK",
    "sg:address":"Toften 21",
    "sg:city":"Billund",
    "sg:orig_category":"Murermestre",
    "sg:phone":"+45 75 33 87 50",
    "sg:postcode":"7190",
    "sg:province":"Danmark",
    "wof:name":"Byg-Teknik",
    "wof:placetype":"venue"
},
  "geometry": {"coordinates":[9.1083402634,55.7305717468],"type":"Point"}
}