{
  "type": "Feature",
  "properties": {
    "addr:full":"Folehaven 68 Valby Danmark 2500",
    "addr:housenumber":"68",
    "addr:postcode":"2500",
    "addr:street":"Folehaven",
    "iso:country":"DK",
    "sg:address":"Folehaven 68",
    "sg:city":"Valby",
    "sg:orig_category":"Pengeinstitutter",
    "sg:phone":"+45 36 30 11 11",
    "sg:postcode":"2500",
    "sg:province":"Danmark",
    "sg:website":"www.unibank.dk",
    "wof:name":"Unibank A/S",
    "wof:placetype":"venue"
},
  "geometry": {"coordinates":[12.5023374557,55.6512565613],"type":"Point"}
}