{
  "type": "Feature",
  "properties": {
    "addr:full":"Bregningevej 4 - 6 Eskebjerg Danmark 4593",
    "addr:housenumber":"4 6",
    "addr:postcode":"4593",
    "addr:street":"Bregningevej",
    "iso:country":"DK",
    "sg:address":"Bregningevej 4 - 6",
    "sg:city":"Eskebjerg",
    "sg:orig_category":"Kursussteder",
    "sg:phone":"+45 59 29 15 27",
    "sg:postcode":"4593",
    "sg:province":"Danmark",
    "sg:website":"www.graesrodsgaarden.dk",
    "wof:name":"Gr\u00e6srodsg\u00e5rdens Kursuscenter",
    "wof:placetype":"venue"
},
  "geometry": {"coordinates":[11.3128910065,55.6843910217],"type":"Point"}
}