{
  "type": "Feature",
  "properties": {
    "iso:country":"DK",
    "sg:address":"Charlottevej 30 G",
    "sg:city":"H\u00f8ng",
    "sg:orig_category":"Glarmestre og glarmagere",
    "sg:phone":"+45 58 85 06 36",
    "sg:postcode":"4270",
    "sg:province":"Danmark",
    "sg:website":"www.pcglas.dk",
    "wof:name":"PC Glas",
    "wof:placetype":"venue"
},
  "geometry": {"coordinates":[20.0167007446,50.0666999817],"type":"Point"}
}