{
  "type": "Feature",
  "properties": {
    "addr:full":"Fmd.: Keld Boysen, Guldbergsvej 9 Odense C Danmark 5000",
    "addr:housenumber":"9",
    "addr:postcode":"5000",
    "addr:street":"Guldbergsvej",
    "iso:country":"DK",
    "sg:address":"Fmd.: Keld Boysen, Guldbergsvej 9",
    "sg:city":"Odense C",
    "sg:orig_category":"\u00c3\u2020ldreorganisationer og klubber",
    "sg:phone":"+45 66 13 22 14",
    "sg:postcode":"5000",
    "sg:province":"Danmark",
    "wof:name":"Pensionist-skak",
    "wof:placetype":"venue"
},
  "geometry": {"coordinates":[10.390794754,55.3961715698],"type":"Point"}
}