{
  "type": "Feature",
  "properties": {
    "addr:full":"Thistedgade 10  Taastrup Danmark 2630",
    "addr:housenumber":"10",
    "addr:postcode":"2630",
    "addr:street":"Thistedgade",
    "iso:country":"DK",
    "sg:address":"Thistedgade 10 ",
    "sg:city":"Taastrup",
    "sg:classifiers":[
        {
            "category":"Utilities",
            "subcategory":"Telephone",
            "type":"Services"
        }
    ],
    "sg:phone":"+45 43 34 46 90",
    "sg:postcode":"2630",
    "sg:province":"Danmark",
    "sg:tags":[
        "telecommunication"
    ],
    "wof:name":"TELE DANMARK A/S",
    "wof:placetype":"venue"
},
  "geometry": {"coordinates":[12.2721805573,55.6470413208],"type":"Point"}
}