{
  "type": "Feature",
  "properties": {
    "addr:full":"Alr\u00f8vej 35, Falling Odder Danmark 8300",
    "addr:housenumber":"35",
    "addr:postcode":"8300",
    "addr:street":"Alrovej;Falling",
    "iso:country":"DK",
    "sg:address":"Alr\u00f8vej 35, Falling",
    "sg:city":"Odder",
    "sg:orig_category":"Skolefritidsordninger",
    "sg:phone":"+45 87 80 38 30",
    "sg:postcode":"8300",
    "sg:province":"Danmark",
    "wof:name":"Skolefritidsordningen v/ \u00d8rting Skole",
    "wof:placetype":"venue"
},
  "geometry": {"coordinates":[10.1497612,55.9733161926],"type":"Point"}
}