{
  "type": "Feature",
  "properties": {
    "addr:full":"Krondrevet 11 A Vordingborg Danmark 4760",
    "addr:housenumber":"11 a",
    "addr:postcode":"4760",
    "addr:street":"Krondrevet",
    "iso:country":"DK",
    "sg:address":"Krondrevet 11 A",
    "sg:city":"Vordingborg",
    "sg:orig_category":"Motionscentre",
    "sg:phone":"+45 55 37 06 05",
    "sg:postcode":"4760",
    "sg:province":"Danmark",
    "wof:name":"Body Pit Motionscenter",
    "wof:placetype":"venue"
},
  "geometry": {"coordinates":[11.8968086243,55.0202598572],"type":"Point"}
}