{
  "type": "Feature",
  "properties": {
    "iso:country":"DK",
    "sg:address":"Idr\u00e6ts Alle 10",
    "sg:city":"Bramming",
    "sg:orig_category":"Cafeterier",
    "sg:phone":"+45 75 17 40 83",
    "sg:postcode":"6740",
    "sg:province":"Danmark",
    "wof:name":"Sportscentrets Cafeteria",
    "wof:placetype":"venue"
},
  "geometry": {"coordinates":[8.6986598969,55.4696655273],"type":"Point"}
}