{
  "type": "Feature",
  "properties": {
    "addr:full":"Domkirkepladsen 3 Roskilde Danmark 4000",
    "addr:housenumber":"3",
    "addr:postcode":"4000",
    "addr:street":"Domkirkepladsen",
    "iso:country":"DK",
    "sg:address":"Domkirkepladsen 3",
    "sg:city":"Roskilde",
    "sg:orig_category":"Kirker",
    "sg:phone":"+45 46 35 16 24",
    "sg:postcode":"4000",
    "sg:province":"Danmark",
    "wof:name":"Roskilde Domkirke",
    "wof:placetype":"venue"
},
  "geometry": {"coordinates":[12.0798053741,55.6421661377],"type":"Point"}
}