{
  "type": "Feature",
  "properties": {
    "addr:full":"Langbyg\u00e5rdsvej 86 Glamsbjerg Danmark 5620",
    "addr:housenumber":"86",
    "addr:postcode":"5620",
    "addr:street":"Langbygaardsvej",
    "iso:country":"DK",
    "sg:address":"Langbyg\u00e5rdsvej 86",
    "sg:city":"Glamsbjerg",
    "sg:orig_category":"Efterskoler",
    "sg:phone":"+45 64 72 36 60",
    "sg:postcode":"5620",
    "sg:province":"Danmark",
    "sg:website":"www.glamsdalen.dk",
    "wof:name":"Glamsdalens Idr\u00e6tsefterskole",
    "wof:placetype":"venue"
},
  "geometry": {"coordinates":[10.1156396866,55.2720298767],"type":"Point"}
}