{
  "type": "Feature",
  "properties": {
    "addr:full":"Gasv\u00e6rksvej 5 Hobro Danmark 9500",
    "addr:housenumber":"5",
    "addr:postcode":"9500",
    "addr:street":"Gasvaerksvej",
    "iso:country":"DK",
    "sg:address":"Gasv\u00e6rksvej 5",
    "sg:city":"Hobro",
    "sg:orig_category":"Haveredskaber",
    "sg:phone":"+45 98 52 28 91",
    "sg:postcode":"9500",
    "sg:province":"Danmark",
    "wof:name":"Hobro Motorservice",
    "wof:placetype":"venue"
},
  "geometry": {"coordinates":[9.8051996231,56.6356201172],"type":"Point"}
}