{
  "type": "Feature",
  "properties": {
    "addr:full":"Viborgvej 44 Skive Danmark 7800",
    "addr:housenumber":"44",
    "addr:postcode":"7800",
    "addr:street":"Viborgvej",
    "iso:country":"DK",
    "sg:address":"Viborgvej 44",
    "sg:city":"Skive",
    "sg:orig_category":"Autoruder",
    "sg:phone":"+45 97 52 13 55",
    "sg:postcode":"7800",
    "sg:province":"Danmark",
    "wof:name":"Alsbjerg & S\u00f8n I/S",
    "wof:placetype":"venue"
},
  "geometry": {"coordinates":[9.0484571457,56.5595588684],"type":"Point"}
}