{
  "type": "Feature",
  "properties": {
    "addr:full":"Vestergade 44 A Svendborg Danmark 5700",
    "addr:housenumber":"44 a",
    "addr:postcode":"5700",
    "addr:street":"Vestergade",
    "iso:country":"DK",
    "sg:address":"Vestergade 44 A",
    "sg:city":"Svendborg",
    "sg:orig_category":"RESTAURANTS: CAFEER",
    "sg:phone":"+45 62 22 44 76",
    "sg:postcode":"5700",
    "sg:province":"Danmark",
    "wof:name":"Tre Musketerer & Milady, De",
    "wof:placetype":"venue"
},
  "geometry": {"coordinates":[10.5991010666,55.0619735718],"type":"Point"}
}