{
  "type": "Feature",
  "properties": {
    "addr:full":"Flade Klit 11, Flade Nyk\u00f8bing Danmark 7900",
    "addr:housenumber":"11",
    "addr:postcode":"7900",
    "addr:street":"Flade Klit",
    "iso:country":"DK",
    "sg:address":"Flade Klit 11, Flade",
    "sg:city":"Nyk\u00f8bing",
    "sg:orig_category":"Kursussteder",
    "sg:phone":"+45 97 74 00 61",
    "sg:postcode":"7900",
    "sg:province":"Danmark",
    "sg:website":"www.duegaarden.dk",
    "wof:name":"Dueg\u00e5rden",
    "wof:placetype":"venue"
},
  "geometry": {"coordinates":[-114.0768203735,46.4432411194],"type":"Point"}
}