{
  "type": "Feature",
  "properties": {
    "addr:full":"Strandgade 14 K\u00f8benhavn Danmark 1401",
    "addr:housenumber":"14;1401",
    "addr:street":"Strandgade",
    "iso:country":"DK",
    "sg:address":"Strandgade 14",
    "sg:city":"K\u00f8benhavn",
    "sg:orig_category":"INGENI\u00c3\u02dcRER",
    "sg:phone":"+45 32 96 41 12",
    "sg:postcode":"1401",
    "sg:province":"Danmark",
    "wof:name":"Morelli, Francesco",
    "wof:placetype":"venue"
},
  "geometry": {"coordinates":[12.5947999954,55.6744003296],"type":"Point"}
}