{
  "type": "Feature",
  "properties": {
    "iso:country":"DK",
    "sg:address":"Karl Bjarnhofs Vej 11",
    "sg:city":"Vejle \u00d8",
    "sg:orig_category":"Reklamebureauer",
    "sg:phone":"+45 75 71 20 00",
    "sg:postcode":"7120",
    "sg:province":"Danmark",
    "wof:name":"Adtention",
    "wof:placetype":"venue"
},
  "geometry": {"coordinates":[9.596244812,55.72473526],"type":"Point"}
}