{
  "type": "Feature",
  "properties": {
    "addr:full":"Toftlundvej 125, Spandet Ribe Danmark 6760",
    "addr:housenumber":"125",
    "addr:postcode":"6760",
    "addr:street":"Toftlundvej",
    "iso:country":"DK",
    "sg:address":"Toftlundvej 125, Spandet",
    "sg:city":"Ribe",
    "sg:orig_category":"EDB - udstyr",
    "sg:phone":"+45 74 86 73 97",
    "sg:postcode":"6760",
    "sg:province":"Danmark",
    "wof:name":"Gravesen Edbware",
    "wof:placetype":"venue"
},
  "geometry": {"coordinates":[8.7656240463,55.3297042847],"type":"Point"}
}