{
  "type": "Feature",
  "properties": {
    "addr:full":"Dronningg\u00e5rds Alle 105 Holte Danmark 2840",
    "addr:housenumber":"105",
    "addr:postcode":"2840",
    "addr:street":"Dronninggaards Alle",
    "iso:country":"DK",
    "sg:address":"Dronningg\u00e5rds Alle 105",
    "sg:city":"Holte",
    "sg:classifiers":[
        {
            "category":"Personal",
            "subcategory":"Massage",
            "type":"Services"
        }
    ],
    "sg:phone":"+45 45 41 15 13",
    "sg:postcode":"2840",
    "sg:province":"Danmark",
    "wof:name":"Din Mass\u00f8r",
    "wof:placetype":"venue"
},
  "geometry": {"coordinates":[12.4478940964,55.8074836731],"type":"Point"}
}