{
  "type": "Feature",
  "properties": {
    "iso:country":"DK",
    "sg:address":"N\u00f8rregade 16",
    "sg:city":"Odense C",
    "sg:orig_category":"Intern Medicin, Allergi Medicinsk allergologi",
    "sg:phone":"+45 66 13 50 33",
    "sg:postcode":"5000",
    "sg:province":"Danmark",
    "wof:name":"Hyldebrandt, Niels",
    "wof:placetype":"venue"
},
  "geometry": {"coordinates":[10.3885707855,55.3977546692],"type":"Point"}
}