{
  "type": "Feature",
  "properties": {
    "addr:full":"Vestergade 50 K\u00f8ge Danmark 4600",
    "addr:housenumber":"50",
    "addr:postcode":"4600",
    "addr:street":"Vestergade",
    "iso:country":"DK",
    "sg:address":"Vestergade 50",
    "sg:city":"K\u00f8ge",
    "sg:orig_category":"Snedkermestre",
    "sg:phone":"+45 56 65 05 07",
    "sg:postcode":"4600",
    "sg:province":"Danmark",
    "wof:name":"K\u00f8ge M\u00f8bel-Snedkeri",
    "wof:placetype":"venue"
},
  "geometry": {"coordinates":[9.5455904007,56.1682090759],"type":"Point"}
}