{
  "type": "Feature",
  "properties": {
    "addr:full":"Hestehaven 46 Fredericia Danmark 7000",
    "addr:housenumber":"46",
    "addr:postcode":"7000",
    "addr:street":"Hestehaven",
    "iso:country":"DK",
    "sg:address":"Hestehaven 46",
    "sg:city":"Fredericia",
    "sg:orig_category":"Fotokopiering",
    "sg:phone":"+45 75 92 31 33",
    "sg:postcode":"7000",
    "sg:province":"Danmark",
    "wof:name":"Damgaard - Jensen A/S",
    "wof:placetype":"venue"
},
  "geometry": {"coordinates":[9.7722320557,55.5815658569],"type":"Point"}
}