{
  "type": "Feature",
  "properties": {
    "iso:country":"DK",
    "sg:address":"Dannebrogsgade 1, 1.",
    "sg:city":"Odense C",
    "sg:orig_category":"Behandlingscentre",
    "sg:phone":"+45 66 13 47 80",
    "sg:postcode":"5000",
    "sg:province":"Danmark",
    "wof:name":"Fyns Amts Behandlingscenter, Unge Afdelingen",
    "wof:placetype":"venue"
},
  "geometry": {"coordinates":[10.388079,55.403473],"type":"Point"}
}