{
  "type": "Feature",
  "properties": {
    "addr:full":"Strandstr\u00e6de 3 Fakse Ladeplads Danmark 4654",
    "addr:housenumber":"3",
    "addr:postcode":"4654",
    "addr:street":"Strandstraede",
    "iso:country":"DK",
    "sg:address":"Strandstr\u00e6de 3",
    "sg:city":"Fakse Ladeplads",
    "sg:orig_category":"Efterskoler",
    "sg:phone":"+45 56 71 66 24",
    "sg:postcode":"4654",
    "sg:province":"Danmark",
    "wof:name":"Faxehus Efterskole",
    "wof:placetype":"venue"
},
  "geometry": {"coordinates":[12.1479282379,55.2115707397],"type":"Point"}
}