{
  "type": "Feature",
  "properties": {
    "iso:country":"DK",
    "sg:address":"Godth\u00e5bsvej 28",
    "sg:city":"Frederiksberg",
    "sg:orig_category":"Bagere",
    "sg:phone":"+45 38 34 22 08",
    "sg:postcode":"2000",
    "sg:province":"Danmark",
    "wof:name":"Yrsa Konditoriet",
    "wof:placetype":"venue"
},
  "geometry": {"coordinates":[12.534045,55.686501],"type":"Point"}
}