{
  "type": "Feature",
  "properties": {
    "iso:country":"DK",
    "sg:address":"Njalsgade 15",
    "sg:city":"K\u00f8benhavn S",
    "sg:orig_category":"Distriktsbiblioteker",
    "sg:phone":"+45 33 66 32 20",
    "sg:postcode":"2300",
    "sg:province":"Danmark",
    "sg:website":"www.kkb.bib.dk/bry/",
    "wof:name":"Islands Brygge bibliotek",
    "wof:placetype":"venue"
},
  "geometry": {"coordinates":[-82.5692062378,38.4656143188],"type":"Point"}
}