{
  "type": "Feature",
  "properties": {
    "iso:country":"DK",
    "sg:address":"Leder: Ellen Hansen, V\u00e6devej 21, V\u00e6de",
    "sg:city":"Morud",
    "sg:orig_category":"Husflidsforeninger",
    "sg:phone":"+45 64 83 12 51",
    "sg:postcode":"5462",
    "sg:province":"Danmark",
    "wof:name":"S\u00f8nders\u00f8 og Omegns Familielandbrugs Familieudvalg",
    "wof:placetype":"venue"
},
  "geometry": {"coordinates":[10.1872348785,55.44323349],"type":"Point"}
}