{
  "type": "Feature",
  "properties": {
    "addr:full":"Boller Slotsvej 20 Horsens Danmark 8700",
    "addr:housenumber":"20",
    "addr:postcode":"8700",
    "addr:street":"Boller Slotsvej",
    "iso:country":"DK",
    "sg:address":"Boller Slotsvej 20",
    "sg:city":"Horsens",
    "sg:orig_category":"Plejeboliger",
    "sg:phone":"+45 75 64 40 10",
    "sg:postcode":"8700",
    "sg:province":"Danmark",
    "wof:name":"Boller Slot",
    "wof:placetype":"venue"
},
  "geometry": {"coordinates":[9.8930101395,55.8392028809],"type":"Point"}
}