{
  "type": "Feature",
  "properties": {
    "iso:country":"DK",
    "sg:address":"Ahorn Alle 46",
    "sg:city":"Ringsted",
    "sg:orig_category":"Kirker",
    "sg:phone":"+45 57 61 82 66",
    "sg:postcode":"4100",
    "sg:province":"Danmark",
    "wof:name":"Klostermarkskirken",
    "wof:placetype":"venue"
},
  "geometry": {"coordinates":[11.7824115753,55.4260520935],"type":"Point"}
}