{
  "type": "Feature",
  "properties": {
    "addr:full":"Sandh\u00f8jsvej 4 Gadstrup Danmark 4621",
    "addr:housenumber":"4",
    "addr:postcode":"4621",
    "addr:street":"Sandhojsvej",
    "iso:country":"DK",
    "sg:address":"Sandh\u00f8jsvej 4",
    "sg:city":"Gadstrup",
    "sg:orig_category":"Integrerede institutioner",
    "sg:phone":"+45 46 19 18 16",
    "sg:postcode":"4621",
    "sg:province":"Danmark",
    "wof:name":"L\u00e6rken",
    "wof:placetype":"venue"
},
  "geometry": {"coordinates":[12.0978450775,55.5737800598],"type":"Point"}
}