{
  "type": "Feature",
  "properties": {
    "addr:full":"Pogestr\u00e6de 31 Odense C Danmark 5000",
    "addr:housenumber":"31",
    "addr:postcode":"5000",
    "addr:street":"Pogestraede",
    "iso:country":"DK",
    "sg:address":"Pogestr\u00e6de 31",
    "sg:city":"Odense C",
    "sg:classifiers":[
        {
            "category":"Restaurant",
            "type":"Food & Drink"
        }
    ],
    "sg:phone":"+45 66 12 12 96",
    "sg:postcode":"5000",
    "sg:province":"Danmark",
    "sg:website":"www.le-provence.dk",
    "wof:name":"Le Provence",
    "wof:placetype":"venue"
},
  "geometry": {"coordinates":[10.390794754,55.3961715698],"type":"Point"}
}