{
  "type": "Feature",
  "properties": {
    "addr:full":"Emdrup Engvej 18 K\u00f8benhavn NV Danmark 2400",
    "addr:housenumber":"18",
    "addr:postcode":"2400",
    "addr:street":"Emdrup Engvej",
    "iso:country":"DK",
    "sg:address":"Emdrup Engvej 18",
    "sg:city":"K\u00f8benhavn NV",
    "sg:orig_category":"Astrologi",
    "sg:phone":"+45 39 66 64 04",
    "sg:postcode":"2400",
    "sg:province":"Danmark",
    "wof:name":"Center for Omsorg, Visdom og Kreativitet",
    "wof:placetype":"venue"
},
  "geometry": {"coordinates":[12.5500001907,55.7167015076],"type":"Point"}
}