{
  "type": "Feature",
  "properties": {
    "addr:full":"Brolandvej 13, Agedrup Agedrup Danmark 5320",
    "addr:housenumber":"13",
    "addr:postcode":"5320",
    "addr:street":"Brolandvej",
    "iso:country":"DK",
    "sg:address":"Brolandvej 13, Agedrup",
    "sg:city":"Agedrup",
    "sg:orig_category":"Malervarer",
    "sg:phone":"+45 66 10 70 32",
    "sg:postcode":"5320",
    "sg:province":"Danmark",
    "wof:name":"Agedrup Malerfirma",
    "wof:placetype":"venue"
},
  "geometry": {"coordinates":[10.4700860977,55.4257240295],"type":"Point"}
}