{
  "type": "Feature",
  "properties": {
    "addr:full":"Kongensgade 67 Esbjerg Danmark 6700",
    "addr:housenumber":"67",
    "addr:postcode":"6700",
    "addr:street":"Kongensgade",
    "iso:country":"DK",
    "sg:address":"Kongensgade 67",
    "sg:city":"Esbjerg",
    "sg:orig_category":"Sko",
    "sg:phone":"+45 75 12 00 99",
    "sg:postcode":"6700",
    "sg:province":"Danmark",
    "wof:name":"Skoringen",
    "wof:placetype":"venue"
},
  "geometry": {"coordinates":[8.4470720291,55.4666671753],"type":"Point"}
}