{
  "type": "Feature",
  "properties": {
    "addr:full":"Sverigesvej 2 Skanderborg Danmark 8660",
    "addr:housenumber":"2",
    "addr:postcode":"8660",
    "addr:street":"Sverigesvej",
    "iso:country":"DK",
    "sg:address":"Sverigesvej 2",
    "sg:city":"Skanderborg",
    "sg:orig_category":"Maskinfabrikker",
    "sg:phone":"+45 86 52 00 66",
    "sg:postcode":"8660",
    "sg:province":"Danmark",
    "wof:name":"Steen ApS, Aleks",
    "wof:placetype":"venue"
},
  "geometry": {"coordinates":[9.9482135773,56.0526351929],"type":"Point"}
}