{
  "type": "Feature",
  "properties": {
    "iso:country":"DK",
    "sg:address":"Houdamvej 9, Vandborg",
    "sg:city":"Lemvig",
    "sg:orig_category":"Autoreparation og -service",
    "sg:phone":"+45 97 83 67 66",
    "sg:postcode":"7620",
    "sg:province":"Danmark",
    "wof:name":"PL Biler",
    "wof:placetype":"venue"
},
  "geometry": {"coordinates":[8.3073654175,56.5505104065],"type":"Point"}
}