{
  "type": "Feature",
  "properties": {
    "addr:full":"Reventlowsvej 56 st Odense C Danmark 5000",
    "addr:housenumber":"56",
    "addr:postcode":"5000",
    "addr:street":"Reventlowsvej;St",
    "iso:country":"DK",
    "sg:address":"Reventlowsvej 56 st",
    "sg:city":"Odense C",
    "sg:orig_category":"Fodplejere",
    "sg:phone":"+45 66 13 68 25",
    "sg:postcode":"5000",
    "sg:province":"Danmark",
    "wof:name":"Meretes Fodpleje/Zoneterapi",
    "wof:placetype":"venue"
},
  "geometry": {"coordinates":[10.390794754,55.3961715698],"type":"Point"}
}