{
  "type": "Feature",
  "properties": {
    "iso:country":"DK",
    "sg:address":"V\u00e6rkstedvej 11",
    "sg:city":"Valby",
    "sg:orig_category":"Maskinfabrikker",
    "sg:phone":"+45 36 30 08 88",
    "sg:postcode":"2500",
    "sg:province":"Danmark",
    "wof:name":"Automa",
    "wof:placetype":"venue"
},
  "geometry": {"coordinates":[12.503569603,55.6529045105],"type":"Point"}
}