{
  "type": "Feature",
  "properties": {
    "addr:full":"Hjortev\u00e6nget 414, Uller\u00f8d Kokkedal Danmark 2980",
    "addr:housenumber":"414",
    "addr:postcode":"2980",
    "addr:street":"Ullerod",
    "iso:country":"DK",
    "sg:address":"Hjortev\u00e6nget 414, Uller\u00f8d",
    "sg:city":"Kokkedal",
    "sg:orig_category":"Murermestre",
    "sg:phone":"+45 49 14 93 42",
    "sg:postcode":"2980",
    "sg:province":"Danmark",
    "wof:name":"Pedersen & Langsig ApS",
    "wof:placetype":"venue"
},
  "geometry": {"coordinates":[12.4769096375,55.9091339111],"type":"Point"}
}