{
  "type": "Feature",
  "properties": {
    "addr:full":"Pilehusene 78 Glostrup Danmark 2600",
    "addr:housenumber":"78",
    "addr:postcode":"2600",
    "addr:street":"Pilehusene",
    "iso:country":"DK",
    "sg:address":"Pilehusene 78",
    "sg:city":"Glostrup",
    "sg:orig_category":"Systuer",
    "sg:phone":"+45 43 96 15 10",
    "sg:postcode":"2600",
    "sg:province":"Danmark",
    "wof:name":"IK Design",
    "wof:placetype":"venue"
},
  "geometry": {"coordinates":[12.4245052338,55.6812515259],"type":"Point"}
}