{
  "type": "Feature",
  "properties": {
    "iso:country":"DK",
    "sg:address":"Stadionvej 36",
    "sg:city":"Bolderslev",
    "sg:orig_category":"Cafeterier",
    "sg:phone":"+45 74 64 65 05",
    "sg:postcode":"6392",
    "sg:province":"Danmark",
    "wof:name":"Cafeterie i Bolderslev Fritidscenter",
    "wof:placetype":"venue"
},
  "geometry": {"coordinates":[9.2785768509,54.9892539978],"type":"Point"}
}