{
  "type": "Feature",
  "properties": {
    "addr:full":"Blyt\u00e6kkervej 9 Viborg Danmark 8800",
    "addr:housenumber":"9",
    "addr:postcode":"8800",
    "addr:street":"Blytaekkervej",
    "iso:country":"DK",
    "sg:address":"Blyt\u00e6kkervej 9",
    "sg:city":"Viborg",
    "sg:orig_category":"Maskinfabrikker",
    "sg:phone":"+45 86 61 15 82",
    "sg:postcode":"8800",
    "sg:province":"Danmark",
    "wof:name":"Fig Maskinfabrik, Jan",
    "wof:placetype":"venue"
},
  "geometry": {"coordinates":[9.399189949,56.4690246582],"type":"Point"}
}