{
  "type": "Feature",
  "properties": {
    "addr:full":"Lillegade 23 Grenaa Danmark 8500",
    "addr:housenumber":"23",
    "addr:postcode":"8500",
    "addr:street":"Lillegade",
    "iso:country":"DK",
    "sg:address":"Lillegade 23",
    "sg:city":"Grenaa",
    "sg:orig_category":"Cykler",
    "sg:phone":"+45 86 32 55 15",
    "sg:postcode":"8500",
    "sg:province":"Danmark",
    "wof:name":"Centrum Cykler",
    "wof:placetype":"venue"
},
  "geometry": {"coordinates":[10.8728609085,56.4145355225],"type":"Point"}
}