{
  "type": "Feature",
  "properties": {
    "addr:full":"Fmd.: Solvej Nielsen, Lundergaardsvej 107 Pandrup Danmark 9490",
    "addr:housenumber":"107",
    "addr:postcode":"9490",
    "addr:street":"Solvej;Lundergaardsvej",
    "iso:country":"DK",
    "sg:address":"Fmd.: Solvej Nielsen, Lundergaardsvej 107",
    "sg:city":"Pandrup",
    "sg:orig_category":"Kirkelige foreninger",
    "sg:phone":"+45 98 24 66 14",
    "sg:postcode":"9490",
    "sg:province":"Danmark",
    "wof:name":"Pandrup kirkes kvindekreds",
    "wof:placetype":"venue"
},
  "geometry": {"coordinates":[9.6769151688,57.223815918],"type":"Point"}
}