{
  "type": "Feature",
  "properties": {
    "addr:full":"Toften 3, Ellinge Ullerslev Danmark 5540",
    "addr:housenumber":"3",
    "addr:postcode":"5540",
    "addr:street":"Toften;Ellinge",
    "iso:country":"DK",
    "sg:address":"Toften 3, Ellinge",
    "sg:city":"Ullerslev",
    "sg:orig_category":"Murermestre",
    "sg:phone":"+45 65 98 15 30",
    "sg:postcode":"5540",
    "sg:province":"Danmark",
    "wof:name":"Ellinge Murerforretning",
    "wof:placetype":"venue"
},
  "geometry": {"coordinates":[10.6675348282,55.3605728149],"type":"Point"}
}