{
  "type": "Feature",
  "properties": {
    "addr:full":"Fisketorvet 12 Odense C Danmark 5000",
    "addr:housenumber":"12",
    "addr:postcode":"5000",
    "addr:street":"Fisketorvet",
    "iso:country":"DK",
    "sg:address":"Fisketorvet 12",
    "sg:city":"Odense C",
    "sg:classifiers":[
        {
            "category":"Restaurant",
            "type":"Food & Drink"
        }
    ],
    "sg:phone":"+45 65 91 53 00",
    "sg:postcode":"5000",
    "sg:province":"Danmark",
    "wof:name":"Ryan's",
    "wof:placetype":"venue"
},
  "geometry": {"coordinates":[10.3892602921,55.3969116211],"type":"Point"}
}