{
  "type": "Feature",
  "properties": {
    "addr:full":"Rugager 18 Haderslev Danmark 6100",
    "addr:housenumber":"18",
    "addr:postcode":"6100",
    "addr:street":"Rugager",
    "iso:country":"DK",
    "sg:address":"Rugager 18",
    "sg:city":"Haderslev",
    "sg:orig_category":"Arkitekter",
    "sg:phone":"+45 74 52 46 59",
    "sg:postcode":"6100",
    "sg:province":"Danmark",
    "wof:name":"J\u00fcrgensen, Gisela",
    "wof:placetype":"venue"
},
  "geometry": {"coordinates":[9.5038032532,55.2429542542],"type":"Point"}
}