{
  "type": "Feature",
  "properties": {
    "addr:full":"Strandvejen Sor\u00f8 Danmark 4180",
    "addr:postcode":"4180",
    "addr:street":"Strandvejen Soro Danmark",
    "iso:country":"DK",
    "sg:address":"Strandvejen",
    "sg:city":"Sor\u00f8",
    "sg:orig_category":"Kirker",
    "sg:postcode":"4180",
    "sg:province":"Danmark",
    "wof:name":"Vester-Broby Kirke",
    "wof:placetype":"venue"
},
  "geometry": {"coordinates":[-102.94467926030001,45.4534721375],"type":"Point"}
}