{
  "type": "Feature",
  "properties": {
    "addr:full":"Karl Bjarnhofs Vej 2 Vejle \u00d8 Danmark 7120",
    "addr:housenumber":"2",
    "addr:postcode":"7120",
    "addr:street":"Karl Bjarnhofs Vej",
    "iso:country":"DK",
    "sg:address":"Karl Bjarnhofs Vej 2",
    "sg:city":"Vejle \u00d8",
    "sg:classifiers":[
        {
            "category":"Communications",
            "type":"Services"
        }
    ],
    "sg:phone":"+45 76 41 78 00",
    "sg:postcode":"7120",
    "sg:province":"Danmark",
    "sg:tags":[
        "radio-",
        "og",
        "tv-stationer"
    ],
    "wof:name":"Kanal 94 (Danmarks Radio).",
    "wof:placetype":"venue"
},
  "geometry": {"coordinates":[9.5971050262,55.7254829407],"type":"Point"}
}