{
  "type": "Feature",
  "properties": {
    "addr:full":"Haslevvej 58 Ringsted Danmark 4100",
    "addr:housenumber":"58",
    "addr:postcode":"4100",
    "addr:street":"Haslevvej",
    "iso:country":"DK",
    "sg:address":"Haslevvej 58",
    "sg:city":"Ringsted",
    "sg:orig_category":"Lufthavn",
    "sg:phone":"+45 57 61 21 81",
    "sg:postcode":"4100",
    "sg:province":"Danmark",
    "wof:name":"Ringsted Flyveplads",
    "wof:placetype":"venue"
},
  "geometry": {"coordinates":[11.8113651276,55.4287567139],"type":"Point"}
}