{
  "type": "Feature",
  "properties": {
    "addr:full":"Torvegade 5 Vejle Danmark 7100",
    "addr:housenumber":"5",
    "addr:postcode":"7100",
    "addr:street":"Torvegade",
    "iso:country":"DK",
    "sg:address":"Torvegade 5",
    "sg:city":"Vejle",
    "sg:classifiers":[
        {
            "category":"Banks & Credit Unions",
            "subcategory":"Bank",
            "type":"Services"
        }
    ],
    "sg:phone":"+45 79 41 70 00",
    "sg:postcode":"7100",
    "sg:province":"Danmark",
    "sg:tags":[
        "banker"
    ],
    "sg:website":"www.danskebank.dk",
    "wof:name":"Danske Bank",
    "wof:placetype":"venue"
},
  "geometry": {"coordinates":[9.532708168,55.7085494995],"type":"Point"}
}