{
  "type": "Feature",
  "properties": {
    "addr:full":"Bjergev\u00e6nget 18, Andst Vejen Danmark 6600",
    "addr:housenumber":"18",
    "addr:postcode":"6600",
    "addr:street":"Bjergevaenget;Andst",
    "iso:country":"DK",
    "sg:address":"Bjergev\u00e6nget 18, Andst",
    "sg:city":"Vejen",
    "sg:classifiers":[
        {
            "category":"Taxi",
            "type":"Transportation"
        }
    ],
    "sg:phone":"+45 75 58 81 19",
    "sg:postcode":"6600",
    "sg:province":"Danmark",
    "wof:name":"Andst - Gesten Taxi",
    "wof:placetype":"venue"
},
  "geometry": {"coordinates":[9.1396121979,55.4778175354],"type":"Point"}
}