{
  "type": "Feature",
  "properties": {
    "addr:full":"Vibekevej 8, Dyrup Odense SV Danmark 5250",
    "addr:housenumber":"8",
    "addr:postcode":"5250",
    "addr:street":"Vibekevej;Dyrup",
    "iso:country":"DK",
    "sg:address":"Vibekevej 8, Dyrup",
    "sg:city":"Odense SV",
    "sg:orig_category":"Ejendomshandel",
    "sg:phone":"+45 66 17 52 95",
    "sg:postcode":"5250",
    "sg:province":"Danmark",
    "wof:name":"Dyrup Byggeanpartsselskab",
    "wof:placetype":"venue"
},
  "geometry": {"coordinates":[10.3153953552,55.3362998962],"type":"Point"}
}