{
  "type": "Feature",
  "properties": {
    "addr:full":"Blegbanken 1 B Vejle Danmark 7100",
    "addr:housenumber":"1 b",
    "addr:postcode":"7100",
    "addr:street":"Blegbanken",
    "iso:country":"DK",
    "sg:address":"Blegbanken 1 B",
    "sg:city":"Vejle",
    "sg:orig_category":"Private skoler",
    "sg:phone":"+45 75 83 51 00",
    "sg:postcode":"7100",
    "sg:province":"Danmark",
    "sg:website":"www.sct-norberts-skole.dk",
    "wof:name":"Sct. Norberts Skole",
    "wof:placetype":"venue"
},
  "geometry": {"coordinates":[9.531624794,55.7077102661],"type":"Point"}
}