{
  "type": "Feature",
  "properties": {
    "addr:full":"Andek\u00e6ret 22 Kerteminde Danmark 5300",
    "addr:housenumber":"22",
    "addr:postcode":"5300",
    "addr:street":"Andekaeret",
    "iso:country":"DK",
    "sg:address":"Andek\u00e6ret 22",
    "sg:city":"Kerteminde",
    "sg:orig_category":"Psykologer, praktiserende",
    "sg:phone":"+45 65 32 31 12",
    "sg:postcode":"5300",
    "sg:province":"Danmark",
    "wof:name":"Greve, J\u00f8rgen",
    "wof:placetype":"venue"
},
  "geometry": {"coordinates":[10.6600999832,55.4506492615],"type":"Point"}
}