{
  "type": "Feature",
  "properties": {
    "addr:full":"Victor Kolbyes Vej 9 Maribo Danmark 4930",
    "addr:housenumber":"9",
    "addr:postcode":"4930",
    "addr:street":"Victor Kolbyes Vej",
    "iso:country":"DK",
    "sg:address":"Victor Kolbyes Vej 9",
    "sg:city":"Maribo",
    "sg:orig_category":"Autoreparation og -service",
    "sg:phone":"+45 54 75 76 77",
    "sg:postcode":"4930",
    "sg:province":"Danmark",
    "wof:name":"J\u00f8rns Auto",
    "wof:placetype":"venue"
},
  "geometry": {"coordinates":[11.502035141,54.7743835449],"type":"Point"}
}