{
  "type": "Feature",
  "properties": {
    "addr:full":"Langgade 26 B, Vivild Alling\u00e5bro Danmark 8961",
    "addr:housenumber":"26 b",
    "addr:postcode":"8961",
    "addr:street":"Langgade;Vivild Allingaabro Danmark",
    "iso:country":"DK",
    "sg:address":"Langgade 26 B, Vivild",
    "sg:city":"Alling\u00e5bro",
    "sg:orig_category":"Fodterapeuter",
    "sg:phone":"+45 86 48 78 88",
    "sg:postcode":"8961",
    "sg:province":"Danmark",
    "wof:name":"Klinik for Fodterapi",
    "wof:placetype":"venue"
},
  "geometry": {"coordinates":[10.3230552673,56.4639511108],"type":"Point"}
}