{
  "type": "Feature",
  "properties": {
    "addr:full":"Glaspustervej 1 Hanstholm Danmark 7730",
    "addr:housenumber":"1",
    "addr:postcode":"7730",
    "addr:street":"Glaspustervej",
    "iso:country":"DK",
    "sg:address":"Glaspustervej 1",
    "sg:city":"Hanstholm",
    "sg:orig_category":"Autoreparation og -service",
    "sg:phone":"+45 97 96 14 00",
    "sg:postcode":"7730",
    "sg:province":"Danmark",
    "wof:name":"J. R. Auto & Scooter",
    "wof:placetype":"venue"
},
  "geometry": {"coordinates":[8.6220588684,57.1159324646],"type":"Point"}
}