{
  "type": "Feature",
  "properties": {
    "iso:country":"DK",
    "sg:address":"R\u00e5dhusgade 13",
    "sg:city":"Odder",
    "sg:orig_category":"Sengeudstyr",
    "sg:phone":"+45 86 56 04 66",
    "sg:postcode":"8300",
    "sg:province":"Danmark",
    "wof:name":"Jysk Senget\u00f8jslager",
    "wof:placetype":"venue"
},
  "geometry": {"coordinates":[10.149966,55.975643],"type":"Point"}
}