{
  "type": "Feature",
  "properties": {
    "addr:full":"Nedergade 24 Odense C Danmark 5000",
    "addr:housenumber":"24",
    "addr:postcode":"5000",
    "addr:street":"Nedergade",
    "iso:country":"DK",
    "sg:address":"Nedergade 24",
    "sg:city":"Odense C",
    "sg:orig_category":"Antikviteter",
    "sg:phone":"+45 66 11 45 22",
    "sg:postcode":"5000",
    "sg:province":"Danmark",
    "wof:name":"Kramboden",
    "wof:placetype":"venue"
},
  "geometry": {"coordinates":[10.3937015533,55.3972091675],"type":"Point"}
}