{
  "type": "Feature",
  "properties": {
    "addr:full":"Perlestikkervej 17 5tv K\u00f8benhavn NV Danmark 2400",
    "addr:housenumber":"17 5tv",
    "addr:postcode":"2400",
    "addr:street":"Perlestikkervej",
    "iso:country":"DK",
    "sg:address":"Perlestikkervej 17 5tv",
    "sg:city":"K\u00f8benhavn NV",
    "sg:orig_category":"Psykologer, praktiserende",
    "sg:phone":"+45 35 81 36 17",
    "sg:postcode":"2400",
    "sg:province":"Danmark",
    "wof:name":"Nielsen, Ketty T.",
    "wof:placetype":"venue"
},
  "geometry": {"coordinates":[-117.02272033689999,38.5024604797],"type":"Point"}
}