{
  "type": "Feature",
  "properties": {
    "addr:full":"V. H\u00e6rup Strandvej 30, Lihme Sp\u00f8ttrup Danmark 7860",
    "addr:housenumber":"30",
    "addr:postcode":"7860",
    "addr:street":"Haerup Strandvej",
    "iso:country":"DK",
    "sg:address":"V. H\u00e6rup Strandvej 30, Lihme",
    "sg:city":"Sp\u00f8ttrup",
    "sg:orig_category":"Cafeer",
    "sg:phone":"+45 97 56 01 66",
    "sg:postcode":"7860",
    "sg:province":"Danmark",
    "wof:name":"Gyldendal Havnecafe",
    "wof:placetype":"venue"
},
  "geometry": {"coordinates":[8.7428588867,56.5733261108],"type":"Point"}
}