{
  "type": "Feature",
  "properties": {
    "addr:full":"N\u00f8rregade 58 Hundested Danmark 3390",
    "addr:housenumber":"58",
    "addr:postcode":"3390",
    "addr:street":"Norregade",
    "iso:country":"DK",
    "sg:address":"N\u00f8rregade 58",
    "sg:city":"Hundested",
    "sg:orig_category":"Farvehandlere",
    "sg:phone":"+45 47 93 74 00",
    "sg:postcode":"3390",
    "sg:province":"Danmark",
    "sg:website":"www.gunners-farvehandel.dk",
    "wof:name":"Gunnars Farvehandel",
    "wof:placetype":"venue"
},
  "geometry": {"coordinates":[11.8515949249,55.9614028931],"type":"Point"}
}