{
  "type": "Feature",
  "properties": {
    "addr:full":"Lyngby Hovedgade 8 A Kongens Lyngby Danmark 2800",
    "addr:housenumber":"8 a",
    "addr:postcode":"2800",
    "addr:street":"Lyngby Hovedgade",
    "iso:country":"DK",
    "sg:address":"Lyngby Hovedgade 8 A",
    "sg:city":"Kongens Lyngby",
    "sg:orig_category":"Autoreparation og -service",
    "sg:phone":"+45 45 87 15 16",
    "sg:postcode":"2800",
    "sg:province":"Danmark",
    "wof:name":"Sorgenfri Auto & Maskinhandel ApS",
    "wof:placetype":"venue"
},
  "geometry": {"coordinates":[12.4970722198,55.7753944397],"type":"Point"}
}