{
  "type": "Feature",
  "properties": {
    "addr:full":"Lodsvej 30 Hvidovre Danmark 2650",
    "addr:housenumber":"30",
    "addr:postcode":"2650",
    "addr:street":"Lodsvej",
    "iso:country":"DK",
    "sg:address":"Lodsvej 30",
    "sg:city":"Hvidovre",
    "sg:orig_category":"El-motorer",
    "sg:phone":"+45 36 49 64 55",
    "sg:postcode":"2650",
    "sg:province":"Danmark",
    "wof:name":"B. S. Elektromotor",
    "wof:placetype":"venue"
},
  "geometry": {"coordinates":[12.4913635254,55.6286125183],"type":"Point"}
}