{
  "type": "Feature",
  "properties": {
    "addr:full":"Havnepladsen 2, 1. Vejle Danmark 7100",
    "addr:housenumber":"2 1",
    "addr:postcode":"7100",
    "addr:street":"Havnepladsen",
    "iso:country":"DK",
    "sg:address":"Havnepladsen 2, 1.",
    "sg:city":"Vejle",
    "sg:orig_category":"Advokater",
    "sg:phone":"+45 75 82 99 11",
    "sg:postcode":"7100",
    "sg:province":"Danmark",
    "wof:name":"Juncker & Dahl-Nielsen, Advokatfirmaet",
    "wof:placetype":"venue"
},
  "geometry": {"coordinates":[9.5401315689,55.7064971924],"type":"Point"}
}