{
  "type": "Feature",
  "properties": {
    "iso:country":"DK",
    "sg:address":"v/ Jens Ottar Hansen, Ved Eltham 1, 2.th.",
    "sg:city":"Hellerup",
    "sg:orig_category":"Spejderkorps",
    "sg:phone":"+45 39 29 33 96",
    "sg:postcode":"2900",
    "sg:province":"Danmark",
    "wof:name":"KFUM-spejderne i Danmark, V\u00e6rl\u00f8se Gruppe",
    "wof:placetype":"venue"
},
  "geometry": {"coordinates":[12.5788497925,55.7413787842],"type":"Point"}
}