{
  "type": "Feature",
  "properties": {
    "addr:full":"Kratbjerg 307 B Fredensborg Danmark 3480",
    "addr:housenumber":"307 b",
    "addr:postcode":"3480",
    "addr:street":"Kratbjerg",
    "iso:country":"DK",
    "sg:address":"Kratbjerg 307 B",
    "sg:city":"Fredensborg",
    "sg:orig_category":"Konfekture",
    "sg:phone":"+45 48 48 09 43",
    "sg:postcode":"3480",
    "sg:province":"Danmark",
    "sg:website":"www.the-sode-liv.dk",
    "wof:name":"S\u00f8de Liv, Det",
    "wof:placetype":"venue"
},
  "geometry": {"coordinates":[12.392952919,55.9684257507],"type":"Point"}
}