{
  "type": "Feature",
  "properties": {
    "addr:full":"Fmd.: Michael Jakobsen, Kirkegade 91 Brovst Danmark 9460",
    "addr:housenumber":"91",
    "addr:postcode":"9460",
    "addr:street":"Kirkegade",
    "iso:country":"DK",
    "sg:address":"Fmd.: Michael Jakobsen, Kirkegade 91",
    "sg:city":"Brovst",
    "sg:orig_category":"Politiske foreninger, \u00c3\u02dcvrige",
    "sg:phone":"+45 98 23 01 35",
    "sg:postcode":"9460",
    "sg:province":"Danmark",
    "wof:name":"Venstres Ungdom i Han Herred og Aabybro",
    "wof:placetype":"venue"
},
  "geometry": {"coordinates":[9.5220241547,57.097366333],"type":"Point"}
}