{
  "type": "Feature",
  "properties": {
    "iso:country":"DK",
    "sg:address":"Lykkebovej 21c",
    "sg:city":"Valby",
    "sg:orig_category":"Vagtbureauer",
    "sg:phone":"+45 36 46 07 25",
    "sg:postcode":"2500",
    "sg:province":"Danmark",
    "wof:name":"DANA Hundetjeneste & Vagtservice",
    "wof:placetype":"venue"
},
  "geometry": {"coordinates":[12.4857120514,55.6588439941],"type":"Point"}
}