{
  "type": "Feature",
  "properties": {
    "iso:country":"DK",
    "sg:address":"Vestervej 48",
    "sg:city":"Nibe",
    "sg:orig_category":"Gaveartikler",
    "sg:phone":"+45 98 34 15 59",
    "sg:postcode":"9240",
    "sg:province":"Danmark",
    "wof:name":"Kramboden",
    "wof:placetype":"venue"
},
  "geometry": {"coordinates":[9.7301673889,57.0053482056],"type":"Point"}
}