{
  "type": "Feature",
  "properties": {
    "addr:full":"\u00d8stergade 68 Hadsund Danmark 9560",
    "addr:housenumber":"68",
    "addr:postcode":"9560",
    "addr:street":"Ostergade",
    "iso:country":"DK",
    "sg:address":"\u00d8stergade 68",
    "sg:city":"Hadsund",
    "sg:orig_category":"Autoforhandlere",
    "sg:phone":"+45 98 57 37 55",
    "sg:postcode":"9560",
    "sg:province":"Danmark",
    "wof:name":"Hvilsted Hadsund, Hans",
    "wof:placetype":"venue"
},
  "geometry": {"coordinates":[10.1263017654,56.7239456177],"type":"Point"}
}