{
  "type": "Feature",
  "properties": {
    "addr:full":"Mergeltoften 1 Niv\u00e5 Danmark 2990",
    "addr:housenumber":"1",
    "addr:postcode":"2990",
    "addr:street":"Mergeltoften",
    "iso:country":"DK",
    "sg:address":"Mergeltoften 1",
    "sg:city":"Niv\u00e5",
    "sg:orig_category":"Fritidshjem",
    "sg:phone":"+45 49 14 15 86",
    "sg:postcode":"2990",
    "sg:province":"Danmark",
    "wof:name":"Fritidshjemmet",
    "wof:placetype":"venue"
},
  "geometry": {"coordinates":[12.4979934692,55.9344444275],"type":"Point"}
}