{
  "type": "Feature",
  "properties": {
    "iso:country":"DK",
    "sg:address":"Axeltorv 7",
    "sg:city":"Nakskov",
    "sg:orig_category":"Ejendomshandel",
    "sg:phone":"+45 54 92 39 12",
    "sg:postcode":"4900",
    "sg:province":"Danmark",
    "sg:website":"www.nybolig.dk",
    "wof:name":"Nybolig",
    "wof:placetype":"venue"
},
  "geometry": {"coordinates":[11.1359500885,54.8330116272],"type":"Point"}
}