{
  "type": "Feature",
  "properties": {
    "addr:full":"\u00c5lholmvej 3 Valby Danmark 2500",
    "addr:housenumber":"3",
    "addr:postcode":"2500",
    "addr:street":"Aalholmvej",
    "iso:country":"DK",
    "sg:address":"\u00c5lholmvej 3",
    "sg:city":"Valby",
    "sg:orig_category":"Elektronik",
    "sg:phone":"+45 40 31 00 20",
    "sg:postcode":"2500",
    "sg:province":"Danmark",
    "sg:website":"www.etec.dk",
    "wof:name":"Etec",
    "wof:placetype":"venue"
},
  "geometry": {"coordinates":[12.4897861481,55.6704940796],"type":"Point"}
}