{
  "type": "Feature",
  "properties": {
    "addr:full":"Fmd.: B\u00f8je \u00d8sterlund, H\u00f8jskolevej 7, Snogh\u00f8j Fredericia Danmark 7000",
    "addr:housenumber":"7",
    "addr:postcode":"7000",
    "addr:street":"Hojskolevej",
    "iso:country":"DK",
    "sg:address":"Fmd.: B\u00f8je \u00d8sterlund, H\u00f8jskolevej 7, Snogh\u00f8j",
    "sg:city":"Fredericia",
    "sg:orig_category":"Kulturelle foreninger",
    "sg:phone":"+45 75 94 31 37",
    "sg:postcode":"7000",
    "sg:province":"Danmark",
    "wof:name":"Foreningen Norden",
    "wof:placetype":"venue"
},
  "geometry": {"coordinates":[9.7591047287,55.566368103],"type":"Point"}
}