{
  "type": "Feature",
  "properties": {
    "addr:full":"Nordfrontvej 39 Herlev Danmark 2730",
    "addr:housenumber":"39",
    "addr:postcode":"2730",
    "addr:street":"Nordfrontvej",
    "iso:country":"DK",
    "sg:address":"Nordfrontvej 39",
    "sg:city":"Herlev",
    "sg:orig_category":"Integrerede institutioner",
    "sg:phone":"+45 44 94 40 86",
    "sg:postcode":"2730",
    "sg:province":"Danmark",
    "wof:name":"Ved Fortet",
    "wof:placetype":"venue"
},
  "geometry": {"coordinates":[12.4597883224,55.7377662659],"type":"Point"}
}