{
  "type": "Feature",
  "properties": {
    "addr:full":"Vestergade 33 Vejle Danmark 7100",
    "addr:housenumber":"33",
    "addr:postcode":"7100",
    "addr:street":"Vestergade",
    "iso:country":"DK",
    "sg:address":"Vestergade 33",
    "sg:city":"Vejle",
    "sg:orig_category":"Pizzeriaer",
    "sg:phone":"+45 75 72 64 43",
    "sg:postcode":"7100",
    "sg:province":"Danmark",
    "wof:name":"Alexander's Pizza Kebab Express",
    "wof:placetype":"venue"
},
  "geometry": {"coordinates":[9.5363874435,55.7128715515],"type":"Point"}
}