{
  "type": "Feature",
  "properties": {
    "addr:full":"Banetoften 4 Ballerup Danmark 2750",
    "addr:housenumber":"4",
    "addr:postcode":"2750",
    "addr:street":"Banetoften",
    "iso:country":"DK",
    "sg:address":"Banetoften 4",
    "sg:city":"Ballerup",
    "sg:orig_category":"Optikere",
    "sg:phone":"+45 44 97 05 86",
    "sg:postcode":"2750",
    "sg:province":"Danmark",
    "sg:website":"www.unikoptik.dk",
    "wof:name":"Unik Optik",
    "wof:placetype":"venue"
},
  "geometry": {"coordinates":[12.3562002182,55.7300682068],"type":"Point"}
}