{
  "type": "Feature",
  "properties": {
    "addr:full":"Fmd.: S\u00f8ren Jensen, Br\u00f8nsholmdalsvej 75 Kokkedal Danmark 2980",
    "addr:housenumber":"75",
    "addr:postcode":"2980",
    "addr:street":"Bronsholmdalsvej",
    "iso:country":"DK",
    "sg:address":"Fmd.: S\u00f8ren Jensen, Br\u00f8nsholmdalsvej 75",
    "sg:city":"Kokkedal",
    "sg:orig_category":"Grundejerforeninger",
    "sg:phone":"+45 45 57 27 38",
    "sg:postcode":"2980",
    "sg:province":"Danmark",
    "wof:name":"Enghaven Grundejerforening",
    "wof:placetype":"venue"
},
  "geometry": {"coordinates":[12.4769096375,55.9091339111],"type":"Point"}
}