{
  "type": "Feature",
  "properties": {
    "addr:full":"Stadionvej 5 Bolderslev Danmark 6392",
    "addr:housenumber":"5",
    "addr:postcode":"6392",
    "addr:street":"Stadionvej",
    "iso:country":"DK",
    "sg:address":"Stadionvej 5",
    "sg:city":"Bolderslev",
    "sg:orig_category":"Sparekasser",
    "sg:phone":"+45 74 64 64 11",
    "sg:postcode":"6392",
    "sg:province":"Danmark",
    "wof:name":"Sparekassen Bolderslev",
    "wof:placetype":"venue"
},
  "geometry": {"coordinates":[9.2794303894,54.9918212891],"type":"Point"}
}