{
  "type": "Feature",
  "properties": {
    "addr:full":"Mineralvej 29 Aalborg \u00d8 Danmark 9220",
    "addr:housenumber":"29",
    "addr:postcode":"9220",
    "addr:street":"Mineralvej;Danmark",
    "iso:country":"DK",
    "sg:address":"Mineralvej 29",
    "sg:city":"Aalborg \u00d8",
    "sg:orig_category":"Spedition",
    "sg:phone":"+45 99 37 76 66",
    "sg:postcode":"9220",
    "sg:province":"Danmark",
    "wof:name":"Danzas ASG Eurocargo A/S",
    "wof:placetype":"venue"
},
  "geometry": {"coordinates":[9.9711532593,57.0522918701],"type":"Point"}
}