{
  "type": "Feature",
  "properties": {
    "addr:full":"Munkensvej 4 Frederiksberg Danmark 2000",
    "addr:housenumber":"4",
    "addr:postcode":"2000",
    "addr:street":"Munkensvej",
    "iso:country":"DK",
    "sg:address":"Munkensvej 4",
    "sg:city":"Frederiksberg",
    "sg:orig_category":"Grundejerforeninger",
    "sg:phone":"+45 38 19 56 83",
    "sg:postcode":"2000",
    "sg:province":"Danmark",
    "wof:name":"Ejerforeningen Bispeengen",
    "wof:placetype":"venue"
},
  "geometry": {"coordinates":[12.5344152451,55.6935272217],"type":"Point"}
}