{
  "type": "Feature",
  "properties": {
    "addr:full":"Jernbanegade 2 Hadsund Danmark 9560",
    "addr:housenumber":"2",
    "addr:postcode":"9560",
    "addr:street":"Jernbanegade",
    "iso:country":"DK",
    "sg:address":"Jernbanegade 2",
    "sg:city":"Hadsund",
    "sg:orig_category":"Kiosker",
    "sg:phone":"+45 98 57 12 33",
    "sg:postcode":"9560",
    "sg:province":"Danmark",
    "wof:name":"Rutebilkiosken",
    "wof:placetype":"venue"
},
  "geometry": {"coordinates":[10.1189203262,56.7175216675],"type":"Point"}
}