{
  "type": "Feature",
  "properties": {
    "addr:full":"N\u00f8rregade 18 Vejen Danmark 6600",
    "addr:housenumber":"18",
    "addr:postcode":"6600",
    "addr:street":"Norregade",
    "iso:country":"DK",
    "sg:address":"N\u00f8rregade 18",
    "sg:city":"Vejen",
    "sg:orig_category":"Trykkerier",
    "sg:phone":"+45 70 20 48 02",
    "sg:postcode":"6600",
    "sg:province":"Danmark",
    "wof:name":"Centraltrykkeriet",
    "wof:placetype":"venue"
},
  "geometry": {"coordinates":[9.1384840012,55.4768562317],"type":"Point"}
}