{
  "type": "Feature",
  "properties": {
    "addr:full":"Adelvej 23-25 Lem Danmark 6940",
    "addr:postcode":"23-25;6940",
    "addr:street":"Adelvej",
    "iso:country":"DK",
    "sg:address":"Adelvej 23-25",
    "sg:city":"Lem",
    "sg:orig_category":"Genbrugspladser",
    "sg:postcode":"6940",
    "sg:province":"Danmark",
    "wof:name":"H\u00f8jmark genbrugsplads",
    "wof:placetype":"venue"
},
  "geometry": {"coordinates":[8.4001293182,56.0534934998],"type":"Point"}
}