{
  "type": "Feature",
  "properties": {
    "addr:full":"William Booths Vej 6 Hvidovre Danmark 2650",
    "addr:housenumber":"6",
    "addr:postcode":"2650",
    "addr:street":"Booths Vej",
    "iso:country":"DK",
    "sg:address":"William Booths Vej 6",
    "sg:city":"Hvidovre",
    "sg:orig_category":"Elektro",
    "sg:phone":"+45 36 77 41 77",
    "sg:postcode":"2650",
    "sg:province":"Danmark",
    "wof:name":"Unique Electronic",
    "wof:placetype":"venue"
},
  "geometry": {"coordinates":[12.4884824753,55.6347694397],"type":"Point"}
}