{
  "type": "Feature",
  "properties": {
    "addr:full":"Algade 74 - 76, Fluebjerg Ejby Danmark 5592",
    "addr:housenumber":"74 76",
    "addr:postcode":"5592",
    "addr:street":"Algade",
    "iso:country":"DK",
    "sg:address":"Algade 74 - 76, Fluebjerg",
    "sg:city":"Ejby",
    "sg:orig_category":"Campingudstyr",
    "sg:phone":"+45 64 46 26 46",
    "sg:postcode":"5592",
    "sg:province":"Danmark",
    "wof:name":"Kai's Caravan",
    "wof:placetype":"venue"
},
  "geometry": {"coordinates":[9.9277296066,55.4288444519],"type":"Point"}
}