{
  "type": "Feature",
  "properties": {
    "addr:full":"Jagtvej 213-215 K\u00f8benhavn \u00d8 Danmark 2100",
    "addr:housenumber":"213-215",
    "addr:postcode":"2100",
    "addr:street":"Jagtvej",
    "iso:country":"DK",
    "sg:address":"Jagtvej 213-215",
    "sg:city":"K\u00f8benhavn \u00d8",
    "sg:orig_category":"Autoreparation og -service",
    "sg:phone":"+45 39 29 40 40",
    "sg:postcode":"2100",
    "sg:province":"Danmark",
    "wof:name":"V\u00e6rkstedet",
    "wof:placetype":"venue"
},
  "geometry": {"coordinates":[-99.2048492432,19.5091400146],"type":"Point"}
}