{
  "type": "Feature",
  "properties": {
    "addr:full":"For\u00e5rsbakken 25 Hundested Danmark 3390",
    "addr:housenumber":"25",
    "addr:postcode":"3390",
    "addr:street":"Foraarsbakken",
    "iso:country":"DK",
    "sg:address":"For\u00e5rsbakken 25",
    "sg:city":"Hundested",
    "sg:orig_category":"Vinduespolering",
    "sg:phone":"+45 47 94 01 71",
    "sg:postcode":"3390",
    "sg:province":"Danmark",
    "wof:name":"City Clean 81",
    "wof:placetype":"venue"
},
  "geometry": {"coordinates":[11.8691902161,55.9511413574],"type":"Point"}
}