{
  "type": "Feature",
  "properties": {
    "addr:full":"Fuglemosev\u00e6nge 30 H\u00f8rsholm Danmark 2970",
    "addr:housenumber":"30",
    "addr:postcode":"2970",
    "addr:street":"Fuglemosevaenge",
    "iso:country":"DK",
    "sg:address":"Fuglemosev\u00e6nge 30",
    "sg:city":"H\u00f8rsholm",
    "sg:orig_category":"Advokater",
    "sg:phone":"+45 45 76 10 60",
    "sg:postcode":"2970",
    "sg:province":"Danmark",
    "wof:name":"Hertling, J\u00f8rgen",
    "wof:placetype":"venue"
},
  "geometry": {"coordinates":[12.5034179688,55.8965415955],"type":"Point"}
}