{
  "type": "Feature",
  "properties": {
    "iso:country":"DK",
    "sg:address":"Vingelodden 1",
    "sg:city":"K\u00f8benhavn N",
    "sg:orig_category":"Stilladser",
    "sg:phone":"+45 35 81 16 88",
    "sg:postcode":"2200",
    "sg:province":"Danmark",
    "sg:website":"www.mk-stilladser.dk",
    "wof:name":"MK Stilladser A/S",
    "wof:placetype":"venue"
},
  "geometry": {"coordinates":[12.5448083878,55.7062187195],"type":"Point"}
}