{
  "type": "Feature",
  "properties": {
    "addr:full":"Engvej 12 H\u00f8ng Danmark 4270",
    "addr:housenumber":"12",
    "addr:postcode":"4270",
    "addr:street":"Engvej;Hong Danmark",
    "iso:country":"DK",
    "sg:address":"Engvej 12",
    "sg:city":"H\u00f8ng",
    "sg:orig_category":"Gulvafslibning",
    "sg:phone":"+45 58 85 46 42",
    "sg:postcode":"4270",
    "sg:province":"Danmark",
    "wof:name":"Johan's Gulvafslibning",
    "wof:placetype":"venue"
},
  "geometry": {"coordinates":[5.1988492012,59.2548561096],"type":"Point"}
}