{
  "type": "Feature",
  "properties": {
    "iso:country":"DK",
    "sg:address":"Storegade 9 B",
    "sg:city":"Asn\u00e6s",
    "sg:orig_category":"Alternativ behandling",
    "sg:phone":"+45 59 65 27 28",
    "sg:postcode":"4550",
    "sg:province":"Danmark",
    "wof:name":"Energi-huset",
    "wof:placetype":"venue"
},
  "geometry": {"coordinates":[6.80377388,58.0931854248],"type":"Point"}
}