{
  "type": "Feature",
  "properties": {
    "addr:full":"L\u00f8venholmvej 18, Gjesing Auning Danmark 8963",
    "addr:housenumber":"18",
    "addr:postcode":"8963",
    "addr:street":"Lovenholmvej",
    "iso:country":"DK",
    "sg:address":"L\u00f8venholmvej 18, Gjesing",
    "sg:city":"Auning",
    "sg:orig_category":"Brugskunst",
    "sg:phone":"+45 86 48 43 09",
    "sg:postcode":"8963",
    "sg:province":"Danmark",
    "wof:name":"Afrodite Stuk",
    "wof:placetype":"venue"
},
  "geometry": {"coordinates":[10.3770084381,56.430065155],"type":"Point"}
}