{
  "type": "Feature",
  "properties": {
    "addr:full":"Skodborg Vestergade 34 R\u00f8dding Danmark 6630",
    "addr:housenumber":"34",
    "addr:postcode":"6630",
    "addr:street":"Skodborg Vestergade",
    "iso:country":"DK",
    "sg:address":"Skodborg Vestergade 34",
    "sg:city":"R\u00f8dding",
    "sg:orig_category":"Korn og foderstoffer",
    "sg:phone":"+45 74 84 81 04",
    "sg:postcode":"6630",
    "sg:province":"Danmark",
    "wof:name":"Aktieselskabet Korn- og Foderstofkompagniet",
    "wof:placetype":"venue"
},
  "geometry": {"coordinates":[9.1459226608,55.4214363098],"type":"Point"}
}