{
  "type": "Feature",
  "properties": {
    "addr:full":"Snekkerupvej 4, Vigersted Ringsted Danmark 4100",
    "addr:housenumber":"4",
    "addr:postcode":"4100",
    "addr:street":"Snekkerupvej;Vigersted",
    "iso:country":"DK",
    "sg:address":"Snekkerupvej 4, Vigersted",
    "sg:city":"Ringsted",
    "sg:orig_category":"Kommunale folkeskoler",
    "sg:phone":"+45 57 62 76 00",
    "sg:postcode":"4100",
    "sg:province":"Danmark",
    "sg:website":"www.vigersted-skole.dk",
    "wof:name":"Vigersted Skole",
    "wof:placetype":"venue"
},
  "geometry": {"coordinates":[11.7875862122,55.4458961487],"type":"Point"}
}