{
  "type": "Feature",
  "properties": {
    "addr:full":"v/ Ivan S\u00f8rensen, Gl. Hammelvej 23, Voldby Hammel Danmark 8450",
    "addr:housenumber":"23",
    "addr:postcode":"8450",
    "addr:street":"Sorensen Gl. Hammelvej;Voldby",
    "iso:country":"DK",
    "sg:address":"v/ Ivan S\u00f8rensen, Gl. Hammelvej 23, Voldby",
    "sg:city":"Hammel",
    "sg:orig_category":"Musik og sang",
    "sg:phone":"+45 86 96 16 02",
    "sg:postcode":"8450",
    "sg:province":"Danmark",
    "wof:name":"Hammel Musikforening",
    "wof:placetype":"venue"
},
  "geometry": {"coordinates":[9.8615541458,56.2554588318],"type":"Point"}
}