{
  "type": "Feature",
  "properties": {
    "addr:full":"Christian Winthers Vej 126 N\u00e6stved Danmark 4700",
    "addr:housenumber":"126",
    "addr:postcode":"4700",
    "addr:street":"Christian Winthers Vej",
    "iso:country":"DK",
    "sg:address":"Christian Winthers Vej 126",
    "sg:city":"N\u00e6stved",
    "sg:classifiers":[
        {
            "category":"Communications",
            "subcategory":"Film & Video Production",
            "type":"Services"
        }
    ],
    "sg:phone":"+45 55 73 14 16",
    "sg:postcode":"4700",
    "sg:province":"Danmark",
    "sg:tags":[
        "radio-",
        "og",
        "tv-service"
    ],
    "wof:name":"Sydsj\u00e6llands AV-Service",
    "wof:placetype":"venue"
},
  "geometry": {"coordinates":[11.7542486191,55.2315444946],"type":"Point"}
}