{
  "type": "Feature",
  "properties": {
    "iso:country":"DK",
    "sg:address":"Jernbanegade 29",
    "sg:city":"Frederikssund",
    "sg:orig_category":"Renserier",
    "sg:phone":"+45 47 31 02 98",
    "sg:postcode":"3600",
    "sg:province":"Danmark",
    "wof:name":"Trikohl-Renseri",
    "wof:placetype":"venue"
},
  "geometry": {"coordinates":[12.0649795532,55.83751297],"type":"Point"}
}