{
  "type": "Feature",
  "properties": {
    "addr:full":"H\u00f8jbyvej 32, H\u00f8jby Odense S Danmark 5260",
    "addr:housenumber":"32",
    "addr:postcode":"5260",
    "addr:street":"Hojbyvej;Hojby",
    "iso:country":"DK",
    "sg:address":"H\u00f8jbyvej 32, H\u00f8jby",
    "sg:city":"Odense S",
    "sg:orig_category":"Korn og foderstoffer",
    "sg:phone":"+45 65 95 86 05",
    "sg:postcode":"5260",
    "sg:province":"Danmark",
    "wof:name":"Hwims Dyremad",
    "wof:placetype":"venue"
},
  "geometry": {"coordinates":[10.3157806396,55.3122825623],"type":"Point"}
}