{
  "type": "Feature",
  "properties": {
    "iso:country":"DK",
    "sg:address":"Glashuset, Storegade 11",
    "sg:city":"Stege",
    "sg:orig_category":"Jagt- og fiskeudstyr",
    "sg:phone":"+45 55 81 15 16",
    "sg:postcode":"4780",
    "sg:province":"Danmark",
    "sg:website":"www.jagtnor.dk",
    "wof:name":"Jagt Nor",
    "wof:placetype":"venue"
},
  "geometry": {"coordinates":[12.2875270844,54.9855155945],"type":"Point"}
}