{
  "type": "Feature",
  "properties": {
    "addr:full":"Provstegade 10 Randers Danmark 8900",
    "addr:housenumber":"10",
    "addr:postcode":"8900",
    "addr:street":"Provstegade",
    "iso:country":"DK",
    "sg:address":"Provstegade 10",
    "sg:city":"Randers",
    "sg:orig_category":"Revisorer",
    "sg:phone":"+45 86 43 31 11",
    "sg:postcode":"8900",
    "sg:province":"Danmark",
    "wof:name":"BDO ScanRevision",
    "wof:placetype":"venue"
},
  "geometry": {"coordinates":[10.0362119675,56.4615440369],"type":"Point"}
}