{
  "type": "Feature",
  "properties": {
    "iso:country":"DK",
    "sg:address":"Bytorvet 34",
    "sg:city":"Hanstholm",
    "sg:orig_category":"Revisorer",
    "sg:phone":"+45 97 96 10 55",
    "sg:postcode":"7730",
    "sg:province":"Danmark",
    "sg:website":"www.bsp.dk",
    "wof:name":"Brandt & Sigsten Pedersen",
    "wof:placetype":"venue"
},
  "geometry": {"coordinates":[8.6058998108,57.1136131287],"type":"Point"}
}