{
  "type": "Feature",
  "properties": {
    "iso:country":"DK",
    "sg:address":"v/ Brian Sand, De Conincksvej 17",
    "sg:city":"Holte",
    "sg:orig_category":"Hobbybetonede foreninger",
    "sg:phone":"+45 45 42 27 07",
    "sg:postcode":"2840",
    "sg:province":"Danmark",
    "wof:name":"Dueklubben Dansk Due Klub",
    "wof:placetype":"venue"
},
  "geometry": {"coordinates":[12.4706554413,55.8122367859],"type":"Point"}
}