{
  "type": "Feature",
  "properties": {
    "iso:country":"DK",
    "sg:address":"H\u00f8gdalvej 7",
    "sg:city":"Silkeborg",
    "sg:orig_category":"Sko",
    "sg:phone":"+45 86 85 55 33",
    "sg:postcode":"8600",
    "sg:province":"Danmark",
    "wof:name":"New Shoes",
    "wof:placetype":"venue"
},
  "geometry": {"coordinates":[9.4913702011,56.2258071899],"type":"Point"}
}