{
  "type": "Feature",
  "properties": {
    "iso:country":"DK",
    "sg:address":"Brigvej 2, Nordby",
    "sg:city":"Fan\u00f8",
    "sg:orig_category":"Blomsterhandlere",
    "sg:phone":"+45 75 16 26 56",
    "sg:postcode":"6720",
    "sg:province":"Danmark",
    "wof:name":"Fan\u00f8 Blomster",
    "wof:placetype":"venue"
},
  "geometry": {"coordinates":[8.4069461823,55.4484786987],"type":"Point"}
}