{
  "type": "Feature",
  "properties": {
    "addr:full":"Sj\u00e6llandsgade 40 Aalborg Danmark 9000",
    "addr:housenumber":"40",
    "addr:postcode":"9000",
    "addr:street":"Sjaellandsgade",
    "iso:country":"DK",
    "sg:address":"Sj\u00e6llandsgade 40",
    "sg:city":"Aalborg",
    "sg:orig_category":"Grillbarer",
    "sg:phone":"+45 98 12 32 34",
    "sg:postcode":"9000",
    "sg:province":"Danmark",
    "wof:name":"Nanking Grill",
    "wof:placetype":"venue"
},
  "geometry": {"coordinates":[9.9392137527,57.0413475037],"type":"Point"}
}