{
  "type": "Feature",
  "properties": {
    "iso:country":"DK",
    "sg:address":"Iller Byvej 42, Iller",
    "sg:city":"Ans",
    "sg:orig_category":"Landbrugsmaskiner",
    "sg:phone":"+45 86 87 09 44",
    "sg:postcode":"8643",
    "sg:province":"Danmark",
    "wof:name":"Intho, Maskinfabrikken",
    "wof:placetype":"venue"
},
  "geometry": {"coordinates":[9.6200656891,56.2750320435],"type":"Point"}
}