{
  "type": "Feature",
  "properties": {
    "addr:full":"Fmd.: Provst Leif Arffmann, B\u00f8gevang 15 Vejle Danmark 7100",
    "addr:housenumber":"15",
    "addr:postcode":"7100",
    "addr:street":"Provst;Bogevang",
    "iso:country":"DK",
    "sg:address":"Fmd.: Provst Leif Arffmann, B\u00f8gevang 15",
    "sg:city":"Vejle",
    "sg:orig_category":"Kulturelle organisationer og -foreninger",
    "sg:phone":"+45 75 82 31 39",
    "sg:postcode":"7100",
    "sg:province":"Danmark",
    "wof:name":"Kirkeg\u00e5rds Kultur, Foreningen for",
    "wof:placetype":"venue"
},
  "geometry": {"coordinates":[9.5368051529,55.7113952637],"type":"Point"}
}