{
  "type": "Feature",
  "properties": {
    "addr:full":"Nibevej 337 A Aalborg SV Danmark 9200",
    "addr:housenumber":"337 a",
    "addr:postcode":"9200",
    "addr:street":"Nibevej",
    "iso:country":"DK",
    "sg:address":"Nibevej 337 A",
    "sg:city":"Aalborg SV",
    "sg:orig_category":"Vinduer",
    "sg:phone":"+45 98 34 35 44",
    "sg:postcode":"9200",
    "sg:province":"Danmark",
    "sg:website":"www.frejlev-trae.dk",
    "wof:name":"Frejlev Tr\u00e6",
    "wof:placetype":"venue"
},
  "geometry": {"coordinates":[9.8126440048,57.0053634644],"type":"Point"}
}