{
  "type": "Feature",
  "properties": {
    "addr:full":"F\u00e6lledvej 2 Kongerslev Danmark 9293",
    "addr:housenumber":"2",
    "addr:postcode":"9293",
    "addr:street":"Faelledvej",
    "iso:country":"DK",
    "sg:address":"F\u00e6lledvej 2",
    "sg:city":"Kongerslev",
    "sg:orig_category":"Varmeforsyning",
    "sg:phone":"+45 98 33 14 72",
    "sg:postcode":"9293",
    "sg:province":"Danmark",
    "wof:name":"Kongerslev Fjernvarmev\u00e6rk",
    "wof:placetype":"venue"
},
  "geometry": {"coordinates":[10.1146726608,56.8847122192],"type":"Point"}
}