{
  "type": "Feature",
  "properties": {
    "addr:full":"Haunstrup Hovedgade 27 Herning Danmark 7400",
    "addr:housenumber":"27",
    "addr:postcode":"7400",
    "addr:street":"Haunstrup Hovedgade",
    "iso:country":"DK",
    "sg:address":"Haunstrup Hovedgade 27",
    "sg:city":"Herning",
    "sg:orig_category":"Autoreparation og -service",
    "sg:phone":"+45 97 16 14 57",
    "sg:postcode":"7400",
    "sg:province":"Danmark",
    "wof:name":"Haunstrup Auto- & Maskinforretning",
    "wof:placetype":"venue"
},
  "geometry": {"coordinates":[8.8116502762,56.120929718],"type":"Point"}
}