{
  "type": "Feature",
  "properties": {
    "addr:full":"Vestergade 14 Vojens Danmark 6500",
    "addr:housenumber":"14",
    "addr:postcode":"6500",
    "addr:street":"Vestergade",
    "iso:country":"DK",
    "sg:address":"Vestergade 14",
    "sg:city":"Vojens",
    "sg:orig_category":"Boghandlere",
    "sg:phone":"+45 74 54 02 95",
    "sg:postcode":"6500",
    "sg:province":"Danmark",
    "sg:website":"www.pjschmidt.dk",
    "wof:name":"Schmidt b\u00f8ger og papir",
    "wof:placetype":"venue"
},
  "geometry": {"coordinates":[9.3015117645,55.2462882996],"type":"Point"}
}