{
  "type": "Feature",
  "properties": {
    "iso:country":"DK",
    "sg:address":"B\u00f8gevej 24",
    "sg:city":"Hals",
    "sg:orig_category":"Boligselskaber",
    "sg:phone":"+45 98 25 17 98",
    "sg:postcode":"9370",
    "sg:province":"Danmark",
    "wof:name":"Hals Boligforening",
    "wof:placetype":"venue"
},
  "geometry": {"coordinates":[10.314283371,56.9981651306],"type":"Point"}
}