{
  "type": "Feature",
  "properties": {
    "addr:full":"Ordruph\u00f8jvej 4 Charlottenlund Danmark 2920",
    "addr:housenumber":"4",
    "addr:postcode":"2920",
    "addr:street":"Ordruphojvej",
    "iso:country":"DK",
    "sg:address":"Ordruph\u00f8jvej 4",
    "sg:city":"Charlottenlund",
    "sg:orig_category":"INGENI\u00c3\u02dcRER",
    "sg:phone":"+45 39 63 90 16",
    "sg:postcode":"2920",
    "sg:province":"Danmark",
    "sg:website":"www.phc.dk",
    "wof:name":"PH-Consult ApS",
    "wof:placetype":"venue"
},
  "geometry": {"coordinates":[12.586561203,55.767250061],"type":"Point"}
}