{
  "type": "Feature",
  "properties": {
    "addr:full":"v/ Ebba Boier, Lundemarken 4, Sandby Svinninge Danmark 4520",
    "addr:housenumber":"4",
    "addr:postcode":"4520",
    "addr:street":"Boier Lundemarken;Sandby",
    "iso:country":"DK",
    "sg:address":"v/ Ebba Boier, Lundemarken 4, Sandby",
    "sg:city":"Svinninge",
    "sg:orig_category":"\u00c3\u02dcvrig fritidsundervisning",
    "sg:phone":"+45 59 46 34 54",
    "sg:postcode":"4520",
    "sg:province":"Danmark",
    "wof:name":"Svinninge Aftenskole",
    "wof:placetype":"venue"
},
  "geometry": {"coordinates":[11.4649095535,55.7226104736],"type":"Point"}
}