{
  "type": "Feature",
  "properties": {
    "addr:full":"Gr\u00f8nnevej 8 Virum Danmark 2830",
    "addr:housenumber":"8",
    "addr:postcode":"2830",
    "addr:street":"Gronnevej",
    "iso:country":"DK",
    "sg:address":"Gr\u00f8nnevej 8",
    "sg:city":"Virum",
    "sg:orig_category":"Bijouterier",
    "sg:phone":"+45 45 85 86 06",
    "sg:postcode":"2830",
    "sg:province":"Danmark",
    "wof:name":"Mon Bijoux",
    "wof:placetype":"venue"
},
  "geometry": {"coordinates":[12.469272,55.80019],"type":"Point"}
}