{
  "type": "Feature",
  "properties": {
    "addr:full":"v/ Karsten M\u00f8ller Pedersen, Langgade 33, Donslund Hejnsvig Danmark 7250",
    "addr:housenumber":"33",
    "addr:postcode":"7250",
    "addr:street":"Pedersen Langgade",
    "iso:country":"DK",
    "sg:address":"v/ Karsten M\u00f8ller Pedersen, Langgade 33, Donslund",
    "sg:city":"Hejnsvig",
    "sg:orig_category":"Borger- og beboerforeninger",
    "sg:phone":"+45 75 39 66 01",
    "sg:postcode":"7250",
    "sg:province":"Danmark",
    "wof:name":"Donslund Borgerforening",
    "wof:placetype":"venue"
},
  "geometry": {"coordinates":[8.9966459274,55.6951141357],"type":"Point"}
}