{
  "type": "Feature",
  "properties": {
    "addr:full":"Brudagervej 2 Vejstrup Danmark 5882",
    "addr:housenumber":"2",
    "addr:postcode":"5882",
    "addr:street":"Brudagervej",
    "iso:country":"DK",
    "sg:address":"Brudagervej 2",
    "sg:city":"Vejstrup",
    "sg:orig_category":"Valg- og frimenigheder",
    "sg:postcode":"5882",
    "sg:province":"Danmark",
    "wof:name":"Vejstrup Valgmenighedskirke",
    "wof:placetype":"venue"
},
  "geometry": {"coordinates":[10.7128295898,55.1092529297],"type":"Point"}
}