{
  "type": "Feature",
  "properties": {
    "addr:full":"Elsdyrl\u00f8kken 58, Korup Odense NV Danmark 5210",
    "addr:housenumber":"58",
    "addr:postcode":"5210",
    "addr:street":"Elsdyrlokken",
    "iso:country":"DK",
    "sg:address":"Elsdyrl\u00f8kken 58, Korup",
    "sg:city":"Odense NV",
    "sg:orig_category":"Engros handel",
    "sg:phone":"+45 65 94 10 87",
    "sg:postcode":"5210",
    "sg:province":"Danmark",
    "wof:name":"Pedersen, Ole",
    "wof:placetype":"venue"
},
  "geometry": {"coordinates":[10.274764061,55.4303321838],"type":"Point"}
}