{
  "type": "Feature",
  "properties": {
    "addr:full":"Lindeengen 26 Skovlunde Danmark 2740",
    "addr:housenumber":"26",
    "addr:postcode":"2740",
    "addr:street":"Lindeengen",
    "iso:country":"DK",
    "sg:address":"Lindeengen 26",
    "sg:city":"Skovlunde",
    "sg:orig_category":"Motorcykler",
    "sg:phone":"+45 44 84 10 11",
    "sg:postcode":"2740",
    "sg:province":"Danmark",
    "wof:name":"Maskinimport",
    "wof:placetype":"venue"
},
  "geometry": {"coordinates":[12.3917484283,55.7094421387],"type":"Point"}
}