{
  "type": "Feature",
  "properties": {
    "iso:country":"DK",
    "sg:address":"Jernbanegade 3",
    "sg:city":"Aalestrup",
    "sg:orig_category":"Bagere",
    "sg:phone":"+45 98 64 10 19",
    "sg:postcode":"9620",
    "sg:province":"Danmark",
    "wof:name":"Centrum Bageriet",
    "wof:placetype":"venue"
},
  "geometry": {"coordinates":[9.495021,56.694283],"type":"Point"}
}