{
  "type": "Feature",
  "properties": {
    "addr:full":"Blenstrupvej 21, Blenstrup Gjerlev Danmark 8983",
    "addr:housenumber":"21",
    "addr:postcode":"8983",
    "addr:street":"Blenstrupvej;Blenstrup Gjerlev Danmark",
    "iso:country":"DK",
    "sg:address":"Blenstrupvej 21, Blenstrup",
    "sg:city":"Gjerlev",
    "sg:orig_category":"Planteskoler",
    "sg:phone":"+45 86 47 49 54",
    "sg:postcode":"8983",
    "sg:province":"Danmark",
    "wof:name":"Dantoft, Kim",
    "wof:placetype":"venue"
},
  "geometry": {"coordinates":[10.1887750626,56.5788421631],"type":"Point"}
}