{
  "type": "Feature",
  "properties": {
    "addr:full":"Fmd.: Torben Karlsson, Reersn\u00e6s Kirkevej 316 Bandholm Danmark 4941",
    "addr:housenumber":"316",
    "addr:postcode":"4941",
    "addr:street":"Kirkevej",
    "iso:country":"DK",
    "sg:address":"Fmd.: Torben Karlsson, Reersn\u00e6s Kirkevej 316",
    "sg:city":"Bandholm",
    "sg:orig_category":"Borger- og beboerforeninger",
    "sg:phone":"+45 54 78 83 94",
    "sg:postcode":"4941",
    "sg:province":"Danmark",
    "wof:name":"Bandholm-Reersn\u00e6s og Blans Beboerforening",
    "wof:placetype":"venue"
},
  "geometry": {"coordinates":[11.4857702255,54.8365211487],"type":"Point"}
}