{
  "type": "Feature",
  "properties": {
    "addr:full":"Frieboeshvile, Lyngby Hovedgade 2 Kongens Lyngby Danmark 2800",
    "addr:housenumber":"2",
    "addr:postcode":"2800",
    "addr:street":"Lyngby Hovedgade",
    "iso:country":"DK",
    "sg:address":"Frieboeshvile, Lyngby Hovedgade 2",
    "sg:city":"Kongens Lyngby",
    "sg:orig_category":"Lokalarkiver",
    "sg:phone":"+45 45 88 43 83",
    "sg:postcode":"2800",
    "sg:province":"Danmark",
    "wof:name":"Byhistorisk Samling for Lyngby-Taarb\u00e6k Kommune",
    "wof:placetype":"venue"
},
  "geometry": {"coordinates":[12.5368299484,55.7949905396],"type":"Point"}
}