{
  "type": "Feature",
  "properties": {
    "addr:full":"Hedemarksgade 5 Frederikshavn Danmark 9900",
    "addr:housenumber":"5",
    "addr:postcode":"9900",
    "addr:street":"Hedemarksgade",
    "iso:country":"DK",
    "sg:address":"Hedemarksgade 5",
    "sg:city":"Frederikshavn",
    "sg:orig_category":"Vinduespolering",
    "sg:phone":"+45 98 42 20 22",
    "sg:postcode":"9900",
    "sg:province":"Danmark",
    "wof:name":"S\u00f8rensens Vinduespolering",
    "wof:placetype":"venue"
},
  "geometry": {"coordinates":[10.5323352814,57.4348869324],"type":"Point"}
}