{
  "type": "Feature",
  "properties": {
    "iso:country":"DK",
    "sg:address":"Nordre Frihavnsgade 26",
    "sg:city":"K\u00f8benhavn \u00d8",
    "sg:orig_category":"Reklamegaver",
    "sg:phone":"+45 70 22 22 31",
    "sg:postcode":"2100",
    "sg:province":"Danmark",
    "wof:name":"Absolute Promotion",
    "wof:placetype":"venue"
},
  "geometry": {"coordinates":[12.035369873,60.8038711548],"type":"Point"}
}