{
  "type": "Feature",
  "properties": {
    "addr:full":"Fmd.: Aage Andersen, Birkevej 32 Aalestrup Danmark 9620",
    "addr:housenumber":"32",
    "addr:postcode":"9620",
    "addr:street":"Birkevej",
    "iso:country":"DK",
    "sg:address":"Fmd.: Aage Andersen, Birkevej 32",
    "sg:city":"Aalestrup",
    "sg:orig_category":"\u00c3\u2020ldreorganisationer og klubber",
    "sg:phone":"+45 98 64 14 79",
    "sg:postcode":"9620",
    "sg:province":"Danmark",
    "wof:name":"Aalestrup Pensionistforening",
    "wof:placetype":"venue"
},
  "geometry": {"coordinates":[9.4901504517,56.6938285828],"type":"Point"}
}