{
  "type": "Feature",
  "properties": {
    "addr:full":"Store Torvegade 36 A R\u00f8nne Danmark 3700",
    "addr:housenumber":"36 a",
    "addr:postcode":"3700",
    "addr:street":"Store Torvegade",
    "iso:country":"DK",
    "sg:address":"Store Torvegade 36 A",
    "sg:city":"R\u00f8nne",
    "sg:orig_category":"EDB - udstyr",
    "sg:phone":"+45 70 25 90 20",
    "sg:postcode":"3700",
    "sg:province":"Danmark",
    "sg:website":"www.hsdataservice.dk",
    "wof:name":"HS Data Service",
    "wof:placetype":"venue"
},
  "geometry": {"coordinates":[14.6975498199,55.0993003845],"type":"Point"}
}