{
  "type": "Feature",
  "properties": {
    "addr:full":"Jernbanegade 66 Roskilde Danmark 4000",
    "addr:housenumber":"66",
    "addr:postcode":"4000",
    "addr:street":"Jernbanegade",
    "iso:country":"DK",
    "sg:address":"Jernbanegade 66",
    "sg:city":"Roskilde",
    "sg:orig_category":"Gravstene",
    "sg:phone":"+45 46 35 03 50",
    "sg:postcode":"4000",
    "sg:province":"Danmark",
    "wof:name":"Hansen Glem & S\u00f8n A/S, H. P.",
    "wof:placetype":"venue"
},
  "geometry": {"coordinates":[12.0775299072,55.6379013062],"type":"Point"}
}