{
  "type": "Feature",
  "properties": {
    "iso:country":"DK",
    "sg:address":"Storegade 23",
    "sg:city":"Esbjerg",
    "sg:orig_category":"Begravelsesforretninger",
    "sg:phone":"+45 75 45 70 51",
    "sg:postcode":"6700",
    "sg:province":"Danmark",
    "wof:name":"Jerne Begravelsesforretning",
    "wof:placetype":"venue"
},
  "geometry": {"coordinates":[8.463517,55.471027],"type":"Point"}
}