{
  "type": "Feature",
  "properties": {
    "addr:full":"Storegade 13 Hadsund Danmark 9560",
    "addr:housenumber":"13",
    "addr:postcode":"9560",
    "addr:street":"Storegade",
    "iso:country":"DK",
    "sg:address":"Storegade 13",
    "sg:city":"Hadsund",
    "sg:orig_category":"Zoneterapeuter",
    "sg:phone":"+45 98 57 28 90",
    "sg:postcode":"9560",
    "sg:province":"Danmark",
    "wof:name":"Hadsund Zoneterapi",
    "wof:placetype":"venue"
},
  "geometry": {"coordinates":[10.1133327484,56.7156829834],"type":"Point"}
}