{
  "type": "Feature",
  "properties": {
    "addr:full":"H\u00f8jtoftevej 15 Esbjerg Danmark 6700",
    "addr:housenumber":"15",
    "addr:postcode":"6700",
    "addr:street":"Hojtoftevej",
    "iso:country":"DK",
    "sg:address":"H\u00f8jtoftevej 15",
    "sg:city":"Esbjerg",
    "sg:orig_category":"Psykologer, praktiserende",
    "sg:phone":"+45 75 13 50 09",
    "sg:postcode":"6700",
    "sg:province":"Danmark",
    "wof:name":"Jensen, Thormod H. S.",
    "wof:placetype":"venue"
},
  "geometry": {"coordinates":[8.4525194168,55.4870948792],"type":"Point"}
}