{
  "type": "Feature",
  "properties": {
    "addr:full":"Navervej 19 - 23 Roskilde Danmark 4000",
    "addr:housenumber":"19 23",
    "addr:postcode":"4000",
    "addr:street":"Navervej",
    "iso:country":"DK",
    "sg:address":"Navervej 19 - 23",
    "sg:city":"Roskilde",
    "sg:orig_category":"Jernhandel",
    "sg:phone":"+45 46 75 50 58",
    "sg:postcode":"4000",
    "sg:province":"Danmark",
    "sg:website":"www.roskilde-jernvaerk.dk",
    "wof:name":"Roskilde Jernv\u00e6rk A/S",
    "wof:placetype":"venue"
},
  "geometry": {"coordinates":[12.1199607849,55.6384887695],"type":"Point"}
}