{
  "type": "Feature",
  "properties": {
    "addr:full":"Ved Stranden 14 - 16 Aalborg Danmark 9000",
    "addr:housenumber":"14 16",
    "addr:postcode":"9000",
    "addr:street":"Ved Stranden",
    "iso:country":"DK",
    "sg:address":"Ved Stranden 14 - 16",
    "sg:city":"Aalborg",
    "sg:classifiers":[
        {
            "category":"Restaurant",
            "type":"Food & Drink"
        }
    ],
    "sg:phone":"+45 96 31 27 27",
    "sg:postcode":"9000",
    "sg:province":"Danmark",
    "wof:name":"Pascal, Restaurant",
    "wof:placetype":"venue"
},
  "geometry": {"coordinates":[9.9200048447,57.050743103],"type":"Point"}
}