{
  "type": "Feature",
  "properties": {
    "addr:full":"Jernbanegade 8, st. Nakskov Danmark 4900",
    "addr:housenumber":"8",
    "addr:postcode":"4900",
    "addr:street":"Jernbanegade",
    "iso:country":"DK",
    "sg:address":"Jernbanegade 8, st.",
    "sg:city":"Nakskov",
    "sg:orig_category":"\u00c3\u02dcvrig fritidsundervisning",
    "sg:phone":"+45 54 95 63 04",
    "sg:postcode":"4900",
    "sg:province":"Danmark",
    "wof:name":"Foreningssekretariatet",
    "wof:placetype":"venue"
},
  "geometry": {"coordinates":[11.1359500885,54.8330116272],"type":"Point"}
}