{
  "type": "Feature",
  "properties": {
    "addr:full":"Solvangsalle 5 Odder Danmark 8300",
    "addr:housenumber":"5",
    "addr:postcode":"8300",
    "addr:street":"Solvangsalle",
    "iso:country":"DK",
    "sg:address":"Solvangsalle 5",
    "sg:city":"Odder",
    "sg:orig_category":"Fodterapeuter",
    "sg:phone":"+45 86 56 09 39",
    "sg:postcode":"8300",
    "sg:province":"Danmark",
    "wof:name":"Klinik for Fodterapi",
    "wof:placetype":"venue"
},
  "geometry": {"coordinates":[10.1380805969,55.9725227356],"type":"Point"}
}