{
  "type": "Feature",
  "properties": {
    "addr:full":"Saltv\u00e6rksvej 65 Kastrup Danmark 2770",
    "addr:housenumber":"65",
    "addr:postcode":"2770",
    "addr:street":"Saltvaerksvej",
    "iso:country":"DK",
    "sg:address":"Saltv\u00e6rksvej 65",
    "sg:city":"Kastrup",
    "sg:orig_category":"Skolefritidsordninger",
    "sg:phone":"+45 32 50 83 88",
    "sg:postcode":"2770",
    "sg:province":"Danmark",
    "wof:name":"Skolefritidsordningen ved Skotteg\u00e5rdsskolen",
    "wof:placetype":"venue"
},
  "geometry": {"coordinates":[12.6377773285,55.6377220154],"type":"Point"}
}