{
  "type": "Feature",
  "properties": {
    "addr:full":"Smedemestervej 16 Faaborg Danmark 5600",
    "addr:housenumber":"16",
    "addr:postcode":"5600",
    "addr:street":"Smedemestervej",
    "iso:country":"DK",
    "sg:address":"Smedemestervej 16",
    "sg:city":"Faaborg",
    "sg:orig_category":"Autoforhandlere",
    "sg:phone":"+45 62 61 93 15",
    "sg:postcode":"5600",
    "sg:province":"Danmark",
    "wof:name":"Bild's Biler",
    "wof:placetype":"venue"
},
  "geometry": {"coordinates":[10.2347955704,55.1109809875],"type":"Point"}
}