{
  "type": "Feature",
  "properties": {
    "addr:full":"Tarmvej 12 Aalborg \u00d8 Danmark 9220",
    "addr:housenumber":"12",
    "addr:postcode":"9220",
    "addr:street":"Tarmvej;Danmark",
    "iso:country":"DK",
    "sg:address":"Tarmvej 12",
    "sg:city":"Aalborg \u00d8",
    "sg:orig_category":"Glas en gros",
    "sg:phone":"+45 98 15 45 11",
    "sg:postcode":"9220",
    "sg:province":"Danmark",
    "wof:name":"VG Glas A/S",
    "wof:placetype":"venue"
},
  "geometry": {"coordinates":[9.9729995728,57.0272102356],"type":"Point"}
}