{
  "type": "Feature",
  "properties": {
    "addr:full":"Tjurg\u00e5rden 215 A Greve Danmark 2670",
    "addr:housenumber":"215",
    "addr:postcode":"2670",
    "addr:street":"A Greve Danmark",
    "iso:country":"DK",
    "sg:address":"Tjurg\u00e5rden 215 A",
    "sg:city":"Greve",
    "sg:orig_category":"Fritidsklubber",
    "sg:phone":"+45 43 90 91 47",
    "sg:postcode":"2670",
    "sg:province":"Danmark",
    "wof:name":"Tjurg\u00e5rden Fritidsklub, Greve Fritidscenter GFC",
    "wof:placetype":"venue"
},
  "geometry": {"coordinates":[12.2941808701,55.5844078064],"type":"Point"}
}