{
  "type": "Feature",
  "properties": {
    "iso:country":"DK",
    "sg:address":"Amager Landevej 37",
    "sg:city":"Kastrup",
    "sg:orig_category":"Apoteker og -udsalg",
    "sg:phone":"+45 32 50 06 17",
    "sg:postcode":"2770",
    "sg:province":"Danmark",
    "wof:name":"T\u00e5rnby Apotek",
    "wof:placetype":"venue"
},
  "geometry": {"coordinates":[12.6192274094,55.636516571],"type":"Point"}
}