{
  "type": "Feature",
  "properties": {
    "addr:full":"S\u00f8ren Nordbys Vej 13 Hirtshals Danmark 9850",
    "addr:housenumber":"13",
    "addr:postcode":"9850",
    "addr:street":"Soren Nordbys Vej",
    "iso:country":"DK",
    "sg:address":"S\u00f8ren Nordbys Vej 13",
    "sg:city":"Hirtshals",
    "sg:orig_category":"Fiskeeksport",
    "sg:phone":"+45 98 94 26 99",
    "sg:postcode":"9850",
    "sg:province":"Danmark",
    "wof:name":"KEKA Fisk ApS",
    "wof:placetype":"venue"
},
  "geometry": {"coordinates":[9.9871969223,57.5876464844],"type":"Point"}
}