{
  "type": "Feature",
  "properties": {
    "addr:full":"Damhus Boulevard 51 R\u00f8dovre Danmark 2610",
    "addr:housenumber":"51",
    "addr:postcode":"2610",
    "addr:street":"Damhus Boulevard",
    "iso:country":"DK",
    "sg:address":"Damhus Boulevard 51",
    "sg:city":"R\u00f8dovre",
    "sg:orig_category":"Murermestre",
    "sg:phone":"+45 36 72 10 84",
    "sg:postcode":"2610",
    "sg:province":"Danmark",
    "wof:name":"Rasmussen, Jens",
    "wof:placetype":"venue"
},
  "geometry": {"coordinates":[10.6992139816,61.1027755737],"type":"Point"}
}