{
  "type": "Feature",
  "properties": {
    "addr:full":"Storegade 15 Brande Danmark 7330",
    "addr:housenumber":"15",
    "addr:postcode":"7330",
    "addr:street":"Storegade",
    "iso:country":"DK",
    "sg:address":"Storegade 15",
    "sg:city":"Brande",
    "sg:orig_category":"Optikere",
    "sg:phone":"+45 97 18 08 76",
    "sg:postcode":"7330",
    "sg:province":"Danmark",
    "wof:name":"Nyt Syn - Stensgaard Optik",
    "wof:placetype":"venue"
},
  "geometry": {"coordinates":[9.1268930435,55.9438285828],"type":"Point"}
}