{
  "type": "Feature",
  "properties": {
    "iso:country":"DK",
    "sg:address":"Store Torv 2",
    "sg:city":"Holstebro",
    "sg:orig_category":"Brudekjoler",
    "sg:phone":"+45 97 42 43 80",
    "sg:postcode":"7500",
    "sg:province":"Danmark",
    "wof:name":"Lilly Brudekjoler",
    "wof:placetype":"venue"
},
  "geometry": {"coordinates":[8.6168460846,56.3580589294],"type":"Point"}
}