{
  "type": "Feature",
  "properties": {
    "addr:full":"Rosenlundvej 3 Lynge Danmark 3540",
    "addr:housenumber":"3",
    "addr:postcode":"3540",
    "addr:street":"Rosenlundvej",
    "iso:country":"DK",
    "sg:address":"Rosenlundvej 3",
    "sg:city":"Lynge",
    "sg:orig_category":"Sportsartikler",
    "sg:phone":"+45 48 18 86 36",
    "sg:postcode":"3540",
    "sg:province":"Danmark",
    "wof:name":"M\u00f8lle\u00e5ens ProShop",
    "wof:placetype":"venue"
},
  "geometry": {"coordinates":[12.2698497772,55.8225517273],"type":"Point"}
}