{
  "type": "Feature",
  "properties": {
    "addr:full":"Storegade 25 B Bjerringbro Danmark 8850",
    "addr:housenumber":"25 b",
    "addr:postcode":"8850",
    "addr:street":"Storegade",
    "iso:country":"DK",
    "sg:address":"Storegade 25 B",
    "sg:city":"Bjerringbro",
    "sg:orig_category":"Kiropraktorer",
    "sg:phone":"+45 86 68 47 99",
    "sg:postcode":"8850",
    "sg:province":"Danmark",
    "wof:name":"Kiropraktisk Klinik Bjerringbro",
    "wof:placetype":"venue"
},
  "geometry": {"coordinates":[9.6548242569,56.374130249],"type":"Point"}
}