{
  "type": "Feature",
  "properties": {
    "addr:full":"Skovagervej 6 C Risskov Danmark 8240",
    "addr:housenumber":"6 c",
    "addr:postcode":"8240",
    "addr:street":"Skovagervej",
    "iso:country":"DK",
    "sg:address":"Skovagervej 6 C",
    "sg:city":"Risskov",
    "sg:orig_category":"Pressebureauer",
    "sg:phone":"+45 86 17 04 61",
    "sg:postcode":"8240",
    "sg:province":"Danmark",
    "sg:website":"www.ytr.dk",
    "wof:name":"Kommunikator",
    "wof:placetype":"venue"
},
  "geometry": {"coordinates":[10.227853775,56.1878929138],"type":"Point"}
}