{
  "type": "Feature",
  "properties": {
    "addr:full":"Hedelyparken 51, st.th. Greve Danmark 2670",
    "addr:housenumber":"51",
    "addr:postcode":"2670",
    "addr:street":"Hedelyparken;St.Th.",
    "iso:country":"DK",
    "sg:address":"Hedelyparken 51, st.th.",
    "sg:city":"Greve",
    "sg:orig_category":"Ungdomsboliger og -hybler",
    "sg:phone":"+45 43 90 56 42",
    "sg:postcode":"2670",
    "sg:province":"Danmark",
    "wof:name":"Hyblerne i Greve",
    "wof:placetype":"venue"
},
  "geometry": {"coordinates":[12.2941808701,55.5844078064],"type":"Point"}
}