{
  "type": "Feature",
  "properties": {
    "iso:country":"DK",
    "sg:address":"S\u00e6rk\u00e6rparken 179",
    "sg:city":"Holstebro",
    "sg:orig_category":"Hudpleje",
    "sg:phone":"+45 97 40 60 99",
    "sg:postcode":"7500",
    "sg:province":"Danmark",
    "wof:name":"Hudpleje Klinikken",
    "wof:placetype":"venue"
},
  "geometry": {"coordinates":[8.6202583313,56.3625221252],"type":"Point"}
}