{
  "type": "Feature",
  "properties": {
    "addr:full":"Ramsherred 10 B Aabenraa Danmark 6200",
    "addr:housenumber":"10 b",
    "addr:postcode":"6200",
    "addr:street":"Ramsherred",
    "iso:country":"DK",
    "sg:address":"Ramsherred 10 B",
    "sg:city":"Aabenraa",
    "sg:orig_category":"Hobbyartikler",
    "sg:phone":"+45 74 62 13 01",
    "sg:postcode":"6200",
    "sg:province":"Danmark",
    "wof:name":"Birk's Sy & Hobby",
    "wof:placetype":"venue"
},
  "geometry": {"coordinates":[9.417974472,55.0471801758],"type":"Point"}
}