{
  "type": "Feature",
  "properties": {
    "addr:full":"Nordre K\u00e6rvej 20 Balle Danmark 8444",
    "addr:housenumber":"20",
    "addr:postcode":"8444",
    "addr:street":"Nordre Kaervej",
    "iso:country":"DK",
    "sg:address":"Nordre K\u00e6rvej 20",
    "sg:city":"Balle",
    "sg:orig_category":"Video- og TV-produktion",
    "sg:phone":"+45 86 33 77 99",
    "sg:postcode":"8444",
    "sg:province":"Danmark",
    "wof:name":"Dynamic Produktions I/S",
    "wof:placetype":"venue"
},
  "geometry": {"coordinates":[10.8090896606,56.31640625],"type":"Point"}
}