{
  "type": "Feature",
  "properties": {
    "addr:full":"Hundige Storcenter 26, 2. Greve Danmark 2670",
    "addr:housenumber":"26 2",
    "addr:postcode":"2670",
    "iso:country":"DK",
    "sg:address":"Hundige Storcenter 26, 2.",
    "sg:city":"Greve",
    "sg:orig_category":"Revisorer",
    "sg:phone":"+45 43 60 08 68",
    "sg:postcode":"2670",
    "sg:province":"Danmark",
    "sg:website":"www.danpars.dk",
    "wof:name":"DanPars Revision",
    "wof:placetype":"venue"
},
  "geometry": {"coordinates":[12.3274593353,55.5990333557],"type":"Point"}
}