{
  "type": "Feature",
  "properties": {
    "addr:full":"Plovheldvej 10 Hvidovre Danmark 2650",
    "addr:housenumber":"10",
    "addr:postcode":"2650",
    "addr:street":"Plovheldvej",
    "iso:country":"DK",
    "sg:address":"Plovheldvej 10",
    "sg:city":"Hvidovre",
    "sg:orig_category":"Fritidshjem",
    "sg:phone":"+45 36 47 03 49",
    "sg:postcode":"2650",
    "sg:province":"Danmark",
    "wof:name":"Holmeg\u00e5rden Fritidshjem",
    "wof:placetype":"venue"
},
  "geometry": {"coordinates":[12.4715871811,55.6622390747],"type":"Point"}
}