{
  "type": "Feature",
  "properties": {
    "addr:full":"Fmd.: Martin Hulgaard, Lindev\u00e6nget 12 Hjerm Danmark 7560",
    "addr:housenumber":"12",
    "addr:postcode":"7560",
    "addr:street":"Lindevaenget",
    "iso:country":"DK",
    "sg:address":"Fmd.: Martin Hulgaard, Lindev\u00e6nget 12",
    "sg:city":"Hjerm",
    "sg:orig_category":"Politiske foreninger, \u00c3\u02dcvrige",
    "sg:phone":"+45 97 46 49 32",
    "sg:postcode":"7560",
    "sg:province":"Danmark",
    "wof:name":"Konservativ Ungdom i Struer",
    "wof:placetype":"venue"
},
  "geometry": {"coordinates":[8.6395950317,56.4384765625],"type":"Point"}
}