{
  "type": "Feature",
  "properties": {
    "addr:full":"Kapellanstr\u00e6de 1 Faaborg Danmark 5600",
    "addr:housenumber":"1",
    "addr:postcode":"5600",
    "addr:street":"Kapellanstraede",
    "iso:country":"DK",
    "sg:address":"Kapellanstr\u00e6de 1",
    "sg:city":"Faaborg",
    "sg:orig_category":"Fodterapeuter",
    "sg:phone":"+45 62 61 24 28",
    "sg:postcode":"5600",
    "sg:province":"Danmark",
    "wof:name":"Schaldemose og Therese Davidsen, Kirsten",
    "wof:placetype":"venue"
},
  "geometry": {"coordinates":[10.2452087402,55.0948638916],"type":"Point"}
}