{
  "type": "Feature",
  "properties": {
    "addr:full":"Jerupvej 613, Mosbjerg Sindal Danmark 9870",
    "addr:housenumber":"613",
    "addr:postcode":"9870",
    "addr:street":"Jerupvej",
    "iso:country":"DK",
    "sg:address":"Jerupvej 613, Mosbjerg",
    "sg:city":"Sindal",
    "sg:orig_category":"Museer",
    "sg:phone":"+45 98 93 05 77",
    "sg:postcode":"9870",
    "sg:province":"Danmark",
    "wof:name":"Vendsyssel Historiske Museum",
    "wof:placetype":"venue"
},
  "geometry": {"coordinates":[10.2032299042,57.470916748],"type":"Point"}
}