{
  "type": "Feature",
  "properties": {
    "iso:country":"DK",
    "sg:address":"Simmersted Byvej 14",
    "sg:city":"Vojens",
    "sg:orig_category":"Maskinfabrikker",
    "sg:phone":"+45 74 50 63 74",
    "sg:postcode":"6500",
    "sg:province":"Danmark",
    "wof:name":"J. A. Sp\u00e5ntagning",
    "wof:placetype":"venue"
},
  "geometry": {"coordinates":[9.3747682571,55.3012657166],"type":"Point"}
}