{
  "type": "Feature",
  "properties": {
    "addr:full":"v/ Merian S\u00f8rensen, Onsholtvej 8 Viby Danmark 8260",
    "addr:housenumber":"8",
    "addr:postcode":"8260",
    "addr:street":"Onsholtvej",
    "iso:country":"DK",
    "sg:address":"v/ Merian S\u00f8rensen, Onsholtvej 8",
    "sg:city":"Viby",
    "sg:orig_category":"Spejderkorps",
    "sg:phone":"+45 86 28 00 49",
    "sg:postcode":"8260",
    "sg:province":"Danmark",
    "wof:name":"KFUK-spejderne Langen\u00e6s-Stavtrup Gruppe",
    "wof:placetype":"venue"
},
  "geometry": {"coordinates":[10.1164493561,56.1353530884],"type":"Point"}
}