{
  "type": "Feature",
  "properties": {
    "addr:full":"Fasanvej 9 Dianalund Danmark 4293",
    "addr:housenumber":"9",
    "addr:postcode":"4293",
    "addr:street":"Fasanvej",
    "iso:country":"DK",
    "sg:address":"Fasanvej 9",
    "sg:city":"Dianalund",
    "sg:orig_category":"Revisorer",
    "sg:phone":"+45 58 26 45 02",
    "sg:postcode":"4293",
    "sg:province":"Danmark",
    "wof:name":"Pedersen, Bent Lundberg",
    "wof:placetype":"venue"
},
  "geometry": {"coordinates":[11.4894924164,55.5153999329],"type":"Point"}
}