{
  "type": "Feature",
  "properties": {
    "addr:full":"Gl. Kongevej 34 Tarm Danmark 6880",
    "addr:housenumber":"34",
    "addr:postcode":"6880",
    "addr:street":"Gl. Kongevej",
    "iso:country":"DK",
    "sg:address":"Gl. Kongevej 34",
    "sg:city":"Tarm",
    "sg:orig_category":"Malermestre",
    "sg:phone":"+45 97 37 12 37",
    "sg:postcode":"6880",
    "sg:province":"Danmark",
    "wof:name":"Omer, Mogens",
    "wof:placetype":"venue"
},
  "geometry": {"coordinates":[8.5229492188,55.9127502441],"type":"Point"}
}