{
  "type": "Feature",
  "properties": {
    "addr:full":"Fmd.: J\u00f8rgen Nielsen, Kastanievej 16, Laurbjerg Lang\u00e5 Danmark 8870",
    "addr:housenumber":"16",
    "addr:postcode":"8870",
    "addr:street":"Kastanievej",
    "iso:country":"DK",
    "sg:address":"Fmd.: J\u00f8rgen Nielsen, Kastanievej 16, Laurbjerg",
    "sg:city":"Lang\u00e5",
    "sg:orig_category":"Museer",
    "sg:phone":"+45 86 46 81 58",
    "sg:postcode":"8870",
    "sg:province":"Danmark",
    "wof:name":"Museum i Lang\u00e5",
    "wof:placetype":"venue"
},
  "geometry": {"coordinates":[9.8955049515,56.3900756836],"type":"Point"}
}