{
  "type": "Feature",
  "properties": {
    "addr:full":"Kalorievej 11 Grenaa Danmark 8500",
    "addr:housenumber":"11",
    "addr:postcode":"8500",
    "addr:street":"Kalorievej",
    "iso:country":"DK",
    "sg:address":"Kalorievej 11",
    "sg:city":"Grenaa",
    "sg:orig_category":"El-forsyning",
    "sg:phone":"+45 87 58 62 00",
    "sg:postcode":"8500",
    "sg:province":"Danmark",
    "wof:name":"Grenaa Kraftvarmev\u00e6rk",
    "wof:placetype":"venue"
},
  "geometry": {"coordinates":[10.9065704346,56.4236984253],"type":"Point"}
}