{
  "type": "Feature",
  "properties": {
    "addr:full":"Gammel K\u00f8ge Landevej 87 Valby Danmark 2500",
    "addr:housenumber":"87",
    "addr:postcode":"2500",
    "addr:street":"Gammel Koge Landevej",
    "iso:country":"DK",
    "sg:address":"Gammel K\u00f8ge Landevej 87",
    "sg:city":"Valby",
    "sg:orig_category":"Autoforhandlere",
    "sg:phone":"+45 36 44 10 44",
    "sg:postcode":"2500",
    "sg:province":"Danmark",
    "sg:website":"www.skoda-kbh.dk",
    "wof:name":"J.H. Auto",
    "wof:placetype":"venue"
},
  "geometry": {"coordinates":[12.5096988678,55.6525497437],"type":"Point"}
}