{
  "type": "Feature",
  "properties": {
    "iso:country":"DK",
    "sg:address":"Urbakken 12",
    "sg:city":"Aalborg S\u00d8",
    "sg:orig_category":"Skibscontainere",
    "sg:phone":"+45 98 14 82 88",
    "sg:postcode":"9210",
    "sg:province":"Danmark",
    "wof:name":"Dansk Container Service ApS",
    "wof:placetype":"venue"
},
  "geometry": {"coordinates":[9.927854538,57.0126495361],"type":"Point"}
}