{
  "type": "Feature",
  "properties": {
    "addr:full":"Kanalvej 167 Aabybro Danmark 9440",
    "addr:housenumber":"167",
    "addr:postcode":"9440",
    "addr:street":"Kanalvej",
    "iso:country":"DK",
    "sg:address":"Kanalvej 167",
    "sg:city":"Aabybro",
    "sg:orig_category":"Forsamlingshuse",
    "sg:phone":"+45 98 24 31 75",
    "sg:postcode":"9440",
    "sg:province":"Danmark",
    "wof:name":"S\u00f8engens Forsamlingshus",
    "wof:placetype":"venue"
},
  "geometry": {"coordinates":[9.7393598557,57.12059021],"type":"Point"}
}