{
  "type": "Feature",
  "properties": {
    "addr:full":"R\u00f8dh\u00f8j 52 Asn\u00e6s Danmark 4550",
    "addr:housenumber":"52",
    "addr:postcode":"4550",
    "addr:street":"Rodhoj",
    "iso:country":"DK",
    "sg:address":"R\u00f8dh\u00f8j 52",
    "sg:city":"Asn\u00e6s",
    "sg:orig_category":"Revisorer",
    "sg:phone":"+45 59 65 00 16",
    "sg:postcode":"4550",
    "sg:province":"Danmark",
    "wof:name":"Siemsen, Revisionsfirmaet Henning",
    "wof:placetype":"venue"
},
  "geometry": {"coordinates":[-98.43292236329999,48.1657714844],"type":"Point"}
}