{
  "type": "Feature",
  "properties": {
    "addr:full":"Sj\u00e6llandsgade 3, Rindum Ringk\u00f8bing Danmark 6950",
    "addr:housenumber":"3",
    "addr:postcode":"6950",
    "addr:street":"Sjaellandsgade",
    "iso:country":"DK",
    "sg:address":"Sj\u00e6llandsgade 3, Rindum",
    "sg:city":"Ringk\u00f8bing",
    "sg:orig_category":"Autoforhandlere",
    "sg:phone":"+45 97 32 42 22",
    "sg:postcode":"6950",
    "sg:province":"Danmark",
    "wof:name":"Autoforum Ringk\u00f8bing A/S",
    "wof:placetype":"venue"
},
  "geometry": {"coordinates":[-114.0767440796,46.4432487488],"type":"Point"}
}