{
  "type": "Feature",
  "properties": {
    "iso:country":"DK",
    "sg:address":"Gartnergade 2",
    "sg:city":"Nyborg",
    "sg:classifiers":[
        {
            "category":"Personal",
            "subcategory":"Massage",
            "type":"Services"
        }
    ],
    "sg:phone":"+45 65 30 16 19",
    "sg:postcode":"5800",
    "sg:province":"Danmark",
    "wof:name":"Nyborg Muskelpleje",
    "wof:placetype":"venue"
},
  "geometry": {"coordinates":[10.7996091843,55.3064155579],"type":"Point"}
}