{
  "type": "Feature",
  "properties": {
    "iso:country":"DK",
    "sg:address":"Algade 118",
    "sg:city":"Br\u00f8nderslev",
    "sg:orig_category":"Blomsterhandlere",
    "sg:phone":"+45 98 82 04 89",
    "sg:postcode":"9700",
    "sg:province":"Danmark",
    "wof:name":"Fynbog\u00e5rden",
    "wof:placetype":"venue"
},
  "geometry": {"coordinates":[9.9190502167,57.0478210449],"type":"Point"}
}