{
  "type": "Feature",
  "properties": {
    "addr:full":"Nyh\u00f8jen 702 Munkebo Danmark 5330",
    "addr:housenumber":"702",
    "addr:postcode":"5330",
    "iso:country":"DK",
    "sg:address":"Nyh\u00f8jen 702",
    "sg:city":"Munkebo",
    "sg:orig_category":"Murermestre",
    "sg:phone":"+45 65 97 69 40",
    "sg:postcode":"5330",
    "sg:province":"Danmark",
    "wof:name":"Christensen, Claus H.",
    "wof:placetype":"venue"
},
  "geometry": {"coordinates":[10.5529537201,55.4627342224],"type":"Point"}
}