{
  "type": "Feature",
  "properties": {
    "addr:full":"v/ Viggo Kaasbjerg, Bymosevej 87 Helsinge Danmark 3200",
    "addr:housenumber":"87",
    "addr:postcode":"3200",
    "addr:street":"Bymosevej",
    "iso:country":"DK",
    "sg:address":"v/ Viggo Kaasbjerg, Bymosevej 87",
    "sg:city":"Helsinge",
    "sg:orig_category":"\u00c3\u02dcvrig fritidsundervisning",
    "sg:phone":"+45 48 79 73 46",
    "sg:postcode":"3200",
    "sg:province":"Danmark",
    "wof:name":"Studiekredsen af 91296",
    "wof:placetype":"venue"
},
  "geometry": {"coordinates":[12.196846962,56.0224456787],"type":"Point"}
}