{
  "type": "Feature",
  "properties": {
    "addr:full":"Skoleleddet 1 Slagelse Danmark 4200",
    "addr:housenumber":"1",
    "addr:postcode":"4200",
    "addr:street":"Skoleleddet",
    "iso:country":"DK",
    "sg:address":"Skoleleddet 1",
    "sg:city":"Slagelse",
    "sg:orig_category":"Malermestre",
    "sg:phone":"+45 58 52 62 32",
    "sg:postcode":"4200",
    "sg:province":"Danmark",
    "wof:name":"Christiansens Eftf., Villy",
    "wof:placetype":"venue"
},
  "geometry": {"coordinates":[11.329419136,55.3996238708],"type":"Point"}
}