{
  "type": "Feature",
  "properties": {
    "addr:full":"Fmd.: Ole Hegelund, Storstr\u00f8msvej 13 Guldborg Danmark 4862",
    "addr:housenumber":"13",
    "addr:postcode":"4862",
    "addr:street":"Storstromsvej",
    "iso:country":"DK",
    "sg:address":"Fmd.: Ole Hegelund, Storstr\u00f8msvej 13",
    "sg:city":"Guldborg",
    "sg:orig_category":"Grundejerforeninger",
    "sg:phone":"+45 54 77 06 36",
    "sg:postcode":"4862",
    "sg:province":"Danmark",
    "wof:name":"Guldborg Falster Grundejer- og Lejerforening",
    "wof:placetype":"venue"
},
  "geometry": {"coordinates":[11.7405948639,54.8682060242],"type":"Point"}
}