{
  "type": "Feature",
  "properties": {
    "addr:full":"Fmd.: Bente Henriksen, H\u00f8rv\u00e6nget 17 Haslev Danmark 4690",
    "addr:housenumber":"17",
    "addr:postcode":"4690",
    "addr:street":"Fmd. Bente Henriksen Horvaenget",
    "iso:country":"DK",
    "sg:address":"Fmd.: Bente Henriksen, H\u00f8rv\u00e6nget 17",
    "sg:city":"Haslev",
    "sg:orig_category":"Kulturelle foreninger",
    "sg:phone":"+45 56 31 11 33",
    "sg:postcode":"4690",
    "sg:province":"Danmark",
    "sg:website":"home1.stofanet.dk/hat",
    "wof:name":"Haslev Amat\u00f8r Teater, HAT",
    "wof:placetype":"venue"
},
  "geometry": {"coordinates":[11.9678049088,55.3230895996],"type":"Point"}
}