{
  "type": "Feature",
  "properties": {
    "iso:country":"DK",
    "sg:address":"Storegade 22",
    "sg:city":"Lunderskov",
    "sg:orig_category":"Bodegaer",
    "sg:phone":"+45 75 58 61 21",
    "sg:postcode":"6640",
    "sg:province":"Danmark",
    "wof:name":"Skomageren",
    "wof:placetype":"venue"
},
  "geometry": {"coordinates":[9.3005933762,55.4796638489],"type":"Point"}
}