{
  "type": "Feature",
  "properties": {
    "iso:country":"DK",
    "sg:address":"Havsg\u00e5rdsvej 29",
    "sg:city":"Hellerup",
    "sg:orig_category":"Skibsklassificering",
    "sg:phone":"+45 39 40 00 11",
    "sg:postcode":"2900",
    "sg:province":"Danmark",
    "wof:name":"S.A. Thomasens Eftf.",
    "wof:placetype":"venue"
},
  "geometry": {"coordinates":[12.5511255264,55.7252998352],"type":"Point"}
}