{
  "type": "Feature",
  "properties": {
    "addr:full":"Adelgade 44 Ebeltoft Danmark 8400",
    "addr:housenumber":"44",
    "addr:postcode":"8400",
    "addr:street":"Adelgade",
    "iso:country":"DK",
    "sg:address":"Adelgade 44",
    "sg:city":"Ebeltoft",
    "sg:orig_category":"HOTELS: OG MOTELLER",
    "sg:phone":"+45 86 34 10 90",
    "sg:postcode":"8400",
    "sg:province":"Danmark",
    "wof:name":"Ebeltoft, Hotel",
    "wof:placetype":"venue"
},
  "geometry": {"coordinates":[10.6792430878,56.1998100281],"type":"Point"}
}