{
  "type": "Feature",
  "properties": {
    "addr:full":"Bysmedevej 38, Tilst Tilst Danmark 8381",
    "addr:housenumber":"38",
    "addr:postcode":"8381",
    "addr:street":"Bysmedevej",
    "iso:country":"DK",
    "sg:address":"Bysmedevej 38, Tilst",
    "sg:city":"Tilst",
    "sg:orig_category":"Zoneterapeuter",
    "sg:phone":"+45 86 24 70 60",
    "sg:postcode":"8381",
    "sg:province":"Danmark",
    "wof:name":"Jensen, Maiken",
    "wof:placetype":"venue"
},
  "geometry": {"coordinates":[10.1078147888,56.1882019043],"type":"Point"}
}