{
  "type": "Feature",
  "properties": {
    "addr:full":"Fmd.: Bent Rasmussen, Engdalen 17 Grenaa Danmark 8500",
    "addr:housenumber":"17",
    "addr:postcode":"8500",
    "addr:street":"Engdalen",
    "iso:country":"DK",
    "sg:address":"Fmd.: Bent Rasmussen, Engdalen 17",
    "sg:city":"Grenaa",
    "sg:orig_category":"Hobbybetonede foreninger",
    "sg:phone":"+45 86 32 28 58",
    "sg:postcode":"8500",
    "sg:province":"Danmark",
    "wof:name":"Racedueklubben for Grenaa og Omegn",
    "wof:placetype":"venue"
},
  "geometry": {"coordinates":[10.8774929047,56.4126853943],"type":"Point"}
}