{
  "type": "Feature",
  "properties": {
    "iso:country":"DK",
    "sg:address":"Alsikevej 16 ",
    "sg:city":"Randers",
    "sg:classifiers":[
        {
            "category":"Wholesale",
            "subcategory":"Medical Equipment & Supplies",
            "type":"Manufacturing & Wholesale Goods"
        }
    ],
    "sg:phone":"+45 86 42 65 55",
    "sg:postcode":"8900",
    "sg:province":"Danmark",
    "sg:tags":[
        "-",
        "health",
        "instrument"
    ],
    "wof:name":"C, M\u00c6RSK ANDERSENS EFTF A/S",
    "wof:placetype":"venue"
},
  "geometry": {"coordinates":[10.0228662491,56.4885787964],"type":"Point"}
}