{
  "type": "Feature",
  "properties": {
    "iso:country":"DK",
    "sg:address":"Fmd.: Ole Lusty, P\u00e6revangen 6",
    "sg:city":"Havdrup",
    "sg:orig_category":"Grundejerforeninger",
    "sg:phone":"+45 46 18 61 10",
    "sg:postcode":"4622",
    "sg:province":"Danmark",
    "wof:name":"Akacievangen/Humlevangens Vejlaug",
    "wof:placetype":"venue"
},
  "geometry": {"coordinates":[12.1158895493,55.5443534851],"type":"Point"}
}