{
  "type": "Feature",
  "properties": {
    "iso:country":"DK",
    "sg:address":"Ringvejen 1, Skovby",
    "sg:city":"Galten",
    "sg:orig_category":"Bagere",
    "sg:phone":"+45 86 94 30 58",
    "sg:postcode":"8464",
    "sg:province":"Danmark",
    "wof:name":"Skovby Bageri",
    "wof:placetype":"venue"
},
  "geometry": {"coordinates":[9.903475,56.155884],"type":"Point"}
}