{
  "type": "Feature",
  "properties": {
    "addr:full":"Peder Rimmens Gade 7 Hirtshals Danmark 9850",
    "addr:housenumber":"7",
    "addr:postcode":"9850",
    "addr:street":"Peder Rimmens Gade",
    "iso:country":"DK",
    "sg:address":"Peder Rimmens Gade 7",
    "sg:city":"Hirtshals",
    "sg:orig_category":"Farve og tapet",
    "sg:phone":"+45 40 84 30 52",
    "sg:postcode":"9850",
    "sg:province":"Danmark",
    "sg:website":"www.jensmaler.dk",
    "wof:name":"Malerbutikken",
    "wof:placetype":"venue"
},
  "geometry": {"coordinates":[9.9666652679,57.589466095],"type":"Point"}
}