{
  "type": "Feature",
  "properties": {
    "addr:full":"Rye Byvej 10, Rye G\u00f8rlev Danmark 4281",
    "addr:housenumber":"10",
    "addr:postcode":"4281",
    "addr:street":"Rye Byvej",
    "iso:country":"DK",
    "sg:address":"Rye Byvej 10, Rye",
    "sg:city":"G\u00f8rlev",
    "sg:orig_category":"Autoreparation og -service",
    "sg:phone":"+45 58 85 54 43",
    "sg:postcode":"4281",
    "sg:province":"Danmark",
    "wof:name":"Rye Autov\u00e6rksted",
    "wof:placetype":"venue"
},
  "geometry": {"coordinates":[11.1143903732,55.5207710266],"type":"Point"}
}