{
  "type": "Feature",
  "properties": {
    "addr:full":"Vestre Gade 32, Br\u00f8ndby\u00f8ster Br\u00f8ndby Danmark 2605",
    "addr:housenumber":"32",
    "addr:postcode":"2605",
    "addr:street":"Vestre Gade",
    "iso:country":"DK",
    "sg:address":"Vestre Gade 32, Br\u00f8ndby\u00f8ster",
    "sg:city":"Br\u00f8ndby",
    "sg:classifiers":[
        {
            "category":"Restaurant",
            "type":"Food & Drink"
        }
    ],
    "sg:phone":"+45 36 47 33 17",
    "sg:postcode":"2605",
    "sg:province":"Danmark",
    "wof:name":"Br\u00f8ndby Skovens Restaurant Engtofteg\u00e5rd",
    "wof:placetype":"venue"
},
  "geometry": {"coordinates":[6.8762898445,62.4602813721],"type":"Point"}
}