{
  "type": "Feature",
  "properties": {
    "addr:full":"M\u00f8lleparkvej 1 Aalborg Danmark 9000",
    "addr:housenumber":"1",
    "addr:postcode":"9000",
    "addr:street":"Molleparkvej",
    "iso:country":"DK",
    "sg:address":"M\u00f8lleparkvej 1",
    "sg:city":"Aalborg",
    "sg:orig_category":"Bodegaer",
    "sg:phone":"+45 98 12 52 56",
    "sg:postcode":"9000",
    "sg:province":"Danmark",
    "wof:name":"Siesta",
    "wof:placetype":"venue"
},
  "geometry": {"coordinates":[9.9090166092,57.0358734131],"type":"Point"}
}