{
  "type": "Feature",
  "properties": {
    "iso:country":"DK",
    "sg:address":"Flegmade 20",
    "sg:city":"Vejle",
    "sg:orig_category":"Bilpleje",
    "sg:phone":"+45 75 82 91 00",
    "sg:postcode":"7100",
    "sg:province":"Danmark",
    "wof:name":"Tidy Car",
    "wof:placetype":"venue"
},
  "geometry": {"coordinates":[9.523893,55.710011],"type":"Point"}
}