{
  "type": "Feature",
  "properties": {
    "iso:country":"DK",
    "sg:address":"Egesholm 5",
    "sg:city":"Horsens",
    "sg:orig_category":"Integrerede institutioner",
    "sg:phone":"+45 75 65 65 05",
    "sg:postcode":"8700",
    "sg:province":"Danmark",
    "wof:name":"Kaskelotten, aldersintegreret institution",
    "wof:placetype":"venue"
},
  "geometry": {"coordinates":[9.8341531754,55.9037437439],"type":"Point"}
}