{
  "type": "Feature",
  "properties": {
    "iso:country":"DK",
    "sg:address":"Bredgade 62-64",
    "sg:city":"Aarup",
    "sg:orig_category":"Blomsterhandlere",
    "sg:phone":"+45 64 43 24 84",
    "sg:postcode":"5560",
    "sg:province":"Danmark",
    "wof:name":"Gr\u00f8ntmanden",
    "wof:placetype":"venue"
},
  "geometry": {"coordinates":[10.0472688675,55.378780365],"type":"Point"}
}