{
  "type": "Feature",
  "properties": {
    "addr:full":"v/ Birte Mikkelsen, Kl\u00f8vh\u00f8jvej 6, Veggerslev Grenaa Danmark 8500",
    "addr:housenumber":"6",
    "addr:postcode":"8500",
    "addr:street":"Klovhojvej;Veggerslev",
    "iso:country":"DK",
    "sg:address":"v/ Birte Mikkelsen, Kl\u00f8vh\u00f8jvej 6, Veggerslev",
    "sg:city":"Grenaa",
    "sg:orig_category":"Forsamlingshuse",
    "sg:phone":"+45 86 33 22 27",
    "sg:postcode":"8500",
    "sg:province":"Danmark",
    "wof:name":"Veggerslev Forsamlingshus I/S",
    "wof:placetype":"venue"
},
  "geometry": {"coordinates":[10.8774929047,56.4126853943],"type":"Point"}
}