{
  "type": "Feature",
  "properties": {
    "addr:full":"Hyldeg\u00e5rdsvej 4 Charlottenlund Danmark 2920",
    "addr:housenumber":"4",
    "addr:postcode":"2920",
    "addr:street":"Hyldegaardsvej",
    "iso:country":"DK",
    "sg:address":"Hyldeg\u00e5rdsvej 4",
    "sg:city":"Charlottenlund",
    "sg:orig_category":"Gymnastikskoler",
    "sg:phone":"+45 39 64 46 94",
    "sg:postcode":"2920",
    "sg:province":"Danmark",
    "wof:name":"London Gymnastik Studio",
    "wof:placetype":"venue"
},
  "geometry": {"coordinates":[12.5741519928,55.7610626221],"type":"Point"}
}