{
  "type": "Feature",
  "properties": {
    "addr:full":"Baneskellet 1, Hammersh\u00f8j Tjele Danmark 8830",
    "addr:housenumber":"1",
    "addr:postcode":"8830",
    "addr:street":"Baneskellet;Hammershoj",
    "iso:country":"DK",
    "sg:address":"Baneskellet 1, Hammersh\u00f8j",
    "sg:city":"Tjele",
    "sg:classifiers":[
        {
            "category":"Banks & Credit Unions",
            "subcategory":"Bank",
            "type":"Services"
        }
    ],
    "sg:phone":"+45 87 99 30 00",
    "sg:postcode":"8830",
    "sg:province":"Danmark",
    "sg:tags":[
        "banker"
    ],
    "sg:website":"www.dabank.dk",
    "wof:name":"Danske Andelskassers Bank A/S",
    "wof:placetype":"venue"
},
  "geometry": {"coordinates":[9.6264801025,56.4818611145],"type":"Point"}
}