{
  "type": "Feature",
  "properties": {
    "addr:full":"Vestergade 14 - 16 Faaborg Danmark 5600",
    "addr:housenumber":"14 16",
    "addr:postcode":"5600",
    "addr:street":"Vestergade",
    "iso:country":"DK",
    "sg:address":"Vestergade 14 - 16",
    "sg:city":"Faaborg",
    "sg:classifiers":[
        {
            "category":"Communications",
            "type":"Services"
        }
    ],
    "sg:phone":"+45 62 61 09 48",
    "sg:postcode":"5600",
    "sg:province":"Danmark",
    "sg:tags":[
        "og",
        "tv",
        "radio"
    ],
    "wof:name":"Expert Tukj\u00e6r Radio ApS",
    "wof:placetype":"venue"
},
  "geometry": {"coordinates":[10.2395572662,55.0969619751],"type":"Point"}
}