{
  "type": "Feature",
  "properties": {
    "addr:full":"Niels M\u00f8rchs Gade 13, st. Frederikshavn Danmark 9900",
    "addr:housenumber":"13",
    "addr:postcode":"9900",
    "addr:street":"Niels Morchs Gade;St.",
    "iso:country":"DK",
    "sg:address":"Niels M\u00f8rchs Gade 13, st.",
    "sg:city":"Frederikshavn",
    "sg:orig_category":"Malermestre",
    "sg:phone":"+45 98 42 80 56",
    "sg:postcode":"9900",
    "sg:province":"Danmark",
    "wof:name":"Andersen, Lillian",
    "wof:placetype":"venue"
},
  "geometry": {"coordinates":[10.5362997055,57.4396400452],"type":"Point"}
}