{
  "type": "Feature",
  "properties": {
    "iso:country":"DK",
    "sg:address":"Danmarksgade 5",
    "sg:city":"Vojens",
    "sg:orig_category":"Supermarkeder",
    "sg:phone":"+45 74 54 36 33",
    "sg:postcode":"6500",
    "sg:province":"Danmark",
    "wof:name":"Rema 1000",
    "wof:placetype":"venue"
},
  "geometry": {"coordinates":[9.2986049652,55.2397460938],"type":"Point"}
}