{
  "type": "Feature",
  "properties": {
    "iso:country":"DK",
    "sg:address":"Simmersted Byvej 6",
    "sg:city":"Vojens",
    "sg:orig_category":"Kommunale folkeskoler",
    "sg:phone":"+45 74 50 61 22",
    "sg:postcode":"6500",
    "sg:province":"Danmark",
    "wof:name":"Simmersted Skole",
    "wof:placetype":"venue"
},
  "geometry": {"coordinates":[9.3795070648,55.3001823425],"type":"Point"}
}