{
  "type": "Feature",
  "properties": {
    "addr:full":"Ryvangs Alle 50 Hellerup Danmark 2900",
    "addr:housenumber":"50",
    "addr:postcode":"2900",
    "addr:street":"Ryvangs Alle",
    "iso:country":"DK",
    "sg:address":"Ryvangs Alle 50",
    "sg:city":"Hellerup",
    "sg:orig_category":"Jobformidling",
    "sg:phone":"+45 39 46 03 30",
    "sg:postcode":"2900",
    "sg:province":"Danmark",
    "sg:website":"www.job-link.dk",
    "wof:name":"Job-Link ApS",
    "wof:placetype":"venue"
},
  "geometry": {"coordinates":[12.5695705414,55.7253608704],"type":"Point"}
}