{
  "type": "Feature",
  "properties": {
    "addr:full":"Fmd.: Rolf Slot-Henriksen, M\u00f8lg\u00e5rdsvej 38 Vejle \u00d8 Danmark 7120",
    "addr:housenumber":"38",
    "addr:postcode":"7120",
    "addr:street":"Molgaardsvej",
    "iso:country":"DK",
    "sg:address":"Fmd.: Rolf Slot-Henriksen, M\u00f8lg\u00e5rdsvej 38",
    "sg:city":"Vejle \u00d8",
    "sg:orig_category":"Kulturelle foreninger",
    "sg:phone":"+45 75 81 67 50",
    "sg:postcode":"7120",
    "sg:province":"Danmark",
    "sg:website":"www.danskkultur.dk",
    "wof:name":"Foreningen Dansk Kultur (Forening til v\u00e6rn om dansk kultur og identitet)",
    "wof:placetype":"venue"
},
  "geometry": {"coordinates":[9.6571302414,55.7422103882],"type":"Point"}
}