{
  "type": "Feature",
  "properties": {
    "addr:full":"Tingagervej 2, Mejdal Holstebro Danmark 7500",
    "addr:housenumber":"2",
    "addr:postcode":"7500",
    "addr:street":"Tingagervej;Mejdal",
    "iso:country":"DK",
    "sg:address":"Tingagervej 2, Mejdal",
    "sg:city":"Holstebro",
    "sg:orig_category":"Hundepensioner",
    "sg:phone":"+45 97 40 17 80",
    "sg:postcode":"7500",
    "sg:province":"Danmark",
    "wof:name":"Mejdal Hundepension",
    "wof:placetype":"venue"
},
  "geometry": {"coordinates":[8.6202583313,56.3625221252],"type":"Point"}
}