{
  "type": "Feature",
  "properties": {
    "addr:full":"Lillegade 8, Hald Gjerlev Danmark 8983",
    "addr:housenumber":"8",
    "addr:postcode":"8983",
    "addr:street":"Lillegade",
    "iso:country":"DK",
    "sg:address":"Lillegade 8, Hald",
    "sg:city":"Gjerlev",
    "sg:orig_category":"Landbrugsmaskiner",
    "sg:phone":"+45 86 47 46 57",
    "sg:postcode":"8983",
    "sg:province":"Danmark",
    "wof:name":"Agergaard, Hvede",
    "wof:placetype":"venue"
},
  "geometry": {"coordinates":[10.1887750626,56.5788421631],"type":"Point"}
}