{
  "type": "Feature",
  "properties": {
    "addr:full":"Magle Alle 1 Kastrup Danmark 2770",
    "addr:housenumber":"1",
    "addr:postcode":"2770",
    "addr:street":"Magle Alle",
    "iso:country":"DK",
    "sg:address":"Magle Alle 1",
    "sg:city":"Kastrup",
    "sg:orig_category":"Autoreparation og -service",
    "sg:phone":"+45 32 50 67 23",
    "sg:postcode":"2770",
    "sg:province":"Danmark",
    "wof:name":"Dorn\u00f8 Autocenter",
    "wof:placetype":"venue"
},
  "geometry": {"coordinates":[12.6253175735,55.6248779297],"type":"Point"}
}