{
  "type": "Feature",
  "properties": {
    "addr:full":"N\u00f8rregade 29 K\u00f8ge Danmark 4600",
    "addr:housenumber":"29",
    "addr:postcode":"4600",
    "addr:street":"Norregade",
    "iso:country":"DK",
    "sg:address":"N\u00f8rregade 29",
    "sg:city":"K\u00f8ge",
    "sg:orig_category":"Museer",
    "sg:phone":"+45 56 67 60 20",
    "sg:postcode":"4600",
    "sg:province":"Danmark",
    "sg:website":"www.skitsesamlingen.dk",
    "wof:name":"Kunstmuseet K\u00f8ge Skitsesamling",
    "wof:placetype":"venue"
},
  "geometry": {"coordinates":[12.1834440231,55.4586715698],"type":"Point"}
}