{
  "type": "Feature",
  "properties": {
    "iso:country":"DK",
    "sg:address":"H. H. Seedorffs Str\u00e6de 6 - 8",
    "sg:city":"\u00c5rhus C",
    "sg:classifiers":[
        {
            "category":"Banks & Credit Unions",
            "subcategory":"Bank",
            "type":"Services"
        }
    ],
    "sg:phone":"+45 87 30 20 70",
    "sg:postcode":"8000",
    "sg:province":"Danmark",
    "sg:tags":[
        "banker"
    ],
    "wof:name":"Alm. Brand Bank",
    "wof:placetype":"venue"
},
  "geometry": {"coordinates":[4.7174,49.758801],"type":"Point"}
}