{
  "type": "Feature",
  "properties": {
    "addr:full":"Roskildevej 268 R\u00f8dovre Danmark 2610",
    "addr:housenumber":"268",
    "addr:postcode":"2610",
    "addr:street":"Roskildevej",
    "iso:country":"DK",
    "sg:address":"Roskildevej 268",
    "sg:city":"R\u00f8dovre",
    "sg:classifiers":[
        {
            "category":"Home & Garden",
            "subcategory":"Home Furnishings",
            "type":"Retail Goods"
        }
    ],
    "sg:phone":"+45 36 70 12 00",
    "sg:postcode":"2610",
    "sg:province":"Danmark",
    "sg:tags":[
        "gardiner"
    ],
    "wof:name":"S.P. Boligtextiler",
    "wof:placetype":"venue"
},
  "geometry": {"coordinates":[10.6992139816,61.1027755737],"type":"Point"}
}