{
  "type": "Feature",
  "properties": {
    "addr:full":"Toldbodgade 10 Hvide Sande Danmark 6960",
    "addr:housenumber":"10",
    "addr:postcode":"6960",
    "addr:street":"Toldbodgade",
    "iso:country":"DK",
    "sg:address":"Toldbodgade 10",
    "sg:city":"Hvide Sande",
    "sg:orig_category":"Non-Classified Establishments",
    "sg:phone":"+45 97 31 32 12",
    "sg:postcode":"6960",
    "sg:province":"Danmark",
    "wof:name":"Texaco Marine",
    "wof:placetype":"venue"
},
  "geometry": {"coordinates":[8.127790451,56.000213623],"type":"Point"}
}