{
  "type": "Feature",
  "properties": {
    "addr:full":"Knudevejen 22 Vejen Danmark 6600",
    "addr:housenumber":"22",
    "addr:postcode":"6600",
    "addr:street":"Knudevejen",
    "iso:country":"DK",
    "sg:address":"Knudevejen 22",
    "sg:city":"Vejen",
    "sg:orig_category":"Autoreparation og -service",
    "sg:phone":"+45 75 36 25 00",
    "sg:postcode":"6600",
    "sg:province":"Danmark",
    "wof:name":"Autog\u00e5rden Vejen ApS",
    "wof:placetype":"venue"
},
  "geometry": {"coordinates":[9.1448888779,55.4675865173],"type":"Point"}
}