{
  "type": "Feature",
  "properties": {
    "addr:full":"\u00d8stre Stationsvej 1 Odense C Danmark 5000",
    "addr:housenumber":"1",
    "addr:postcode":"5000",
    "addr:street":"Ostre Stationsvej",
    "iso:country":"DK",
    "sg:address":"\u00d8stre Stationsvej 1",
    "sg:city":"Odense C",
    "sg:orig_category":"Revisorer",
    "sg:phone":"+45 63 11 66 11",
    "sg:postcode":"5000",
    "sg:province":"Danmark",
    "wof:name":"Deloitte & Touche",
    "wof:placetype":"venue"
},
  "geometry": {"coordinates":[10.3898859024,55.4010658264],"type":"Point"}
}