{
  "type": "Feature",
  "properties": {
    "iso:country":"DK",
    "sg:address":"Vestergade 8",
    "sg:city":"Varde",
    "sg:orig_category":"Sko",
    "sg:phone":"+45 75 22 10 44",
    "sg:postcode":"6800",
    "sg:province":"Danmark",
    "wof:name":"Team Sko",
    "wof:placetype":"venue"
},
  "geometry": {"coordinates":[8.479590416,55.6210975647],"type":"Point"}
}