{
  "type": "Feature",
  "properties": {
    "addr:full":"Vals\u00f8maglevej 19, Vals\u00f8magle Ringsted Danmark 4100",
    "addr:housenumber":"19",
    "addr:postcode":"4100",
    "addr:street":"Valsomaglevej;Valsomagle",
    "iso:country":"DK",
    "sg:address":"Vals\u00f8maglevej 19, Vals\u00f8magle",
    "sg:city":"Ringsted",
    "sg:orig_category":"Revisorer",
    "sg:phone":"+45 57 52 85 85",
    "sg:postcode":"4100",
    "sg:province":"Danmark",
    "wof:name":"Rasmussen, Gunnar",
    "wof:placetype":"venue"
},
  "geometry": {"coordinates":[11.7875862122,55.4458961487],"type":"Point"}
}