{
  "type": "Feature",
  "properties": {
    "addr:full":"Fasanvej 18 Skjern Danmark 6900",
    "addr:housenumber":"18",
    "addr:postcode":"6900",
    "addr:street":"Fasanvej",
    "iso:country":"DK",
    "sg:address":"Fasanvej 18",
    "sg:city":"Skjern",
    "sg:orig_category":"Private- og friskoler",
    "sg:phone":"+45 97 35 13 60",
    "sg:postcode":"6900",
    "sg:province":"Danmark",
    "wof:name":"Skjern Kristne Friskole",
    "wof:placetype":"venue"
},
  "geometry": {"coordinates":[8.5098800659,55.9415855408],"type":"Point"}
}