{
  "type": "Feature",
  "properties": {
    "addr:full":"Fmd.: Ove M. Pedersen, Skovlytoften 24, \u00d8ver\u00f8d Holte Danmark 2840",
    "addr:housenumber":"24",
    "addr:postcode":"2840",
    "addr:street":"Ove;Pedersen Skovlytoften",
    "iso:country":"DK",
    "sg:address":"Fmd.: Ove M. Pedersen, Skovlytoften 24, \u00d8ver\u00f8d",
    "sg:city":"Holte",
    "sg:orig_category":"Grundejerforeninger",
    "sg:phone":"+45 45 42 00 40",
    "sg:postcode":"2840",
    "sg:province":"Danmark",
    "wof:name":"\u00d8ver\u00f8d Industrikvarter Ejerlaug",
    "wof:placetype":"venue"
},
  "geometry": {"coordinates":[12.4706554413,55.8122367859],"type":"Point"}
}