{
  "type": "Feature",
  "properties": {
    "addr:full":"Havnepladsen 15 Rudk\u00f8bing Danmark 5900",
    "addr:housenumber":"15",
    "addr:postcode":"5900",
    "addr:street":"Havnepladsen",
    "iso:country":"DK",
    "sg:address":"Havnepladsen 15",
    "sg:city":"Rudk\u00f8bing",
    "sg:orig_category":"Kiosker",
    "sg:phone":"+45 62 51 16 85",
    "sg:postcode":"5900",
    "sg:province":"Danmark",
    "wof:name":"Havnekiosken",
    "wof:placetype":"venue"
},
  "geometry": {"coordinates":[-114.0767440796,46.4432487488],"type":"Point"}
}