{
  "type": "Feature",
  "properties": {
    "addr:full":"Fmd.: Morten Kj\u00e6r, Skippergade 25 Asaa Danmark 9340",
    "addr:housenumber":"25",
    "addr:postcode":"9340",
    "addr:street":"Morten Kjaer Skippergade",
    "iso:country":"DK",
    "sg:address":"Fmd.: Morten Kj\u00e6r, Skippergade 25",
    "sg:city":"Asaa",
    "sg:orig_category":"Kulturelle foreninger",
    "sg:phone":"+45 98 85 22 66",
    "sg:postcode":"9340",
    "sg:province":"Danmark",
    "wof:name":"H\u00f8vlen",
    "wof:placetype":"venue"
},
  "geometry": {"coordinates":[10.4039297104,57.1481704712],"type":"Point"}
}