{
  "type": "Feature",
  "properties": {
    "addr:full":"Risb\u00f8ge 32, 1, H\u00f8jrup Lunderskov Danmark 6640",
    "addr:housenumber":"32 1",
    "addr:postcode":"6640",
    "addr:street":"Risboge;Hojrup",
    "iso:country":"DK",
    "sg:address":"Risb\u00f8ge 32, 1, H\u00f8jrup",
    "sg:city":"Lunderskov",
    "sg:orig_category":"Antikviteter",
    "sg:phone":"+45 75 55 94 99",
    "sg:postcode":"6640",
    "sg:province":"Danmark",
    "wof:name":"Nettotal Handel",
    "wof:placetype":"venue"
},
  "geometry": {"coordinates":[9.2983627319,55.4793586731],"type":"Point"}
}