{
  "type": "Feature",
  "properties": {
    "addr:full":"Fmd.: Steen Skieller, B\u00f8gebjergvej 45, V. \u00c5by Faaborg Danmark 5600",
    "addr:housenumber":"45",
    "addr:postcode":"5600",
    "addr:street":"Bogebjergvej;Aaby",
    "iso:country":"DK",
    "sg:address":"Fmd.: Steen Skieller, B\u00f8gebjergvej 45, V. \u00c5by",
    "sg:city":"Faaborg",
    "sg:orig_category":"Spejderkorps",
    "sg:phone":"+45 62 61 63 63",
    "sg:postcode":"5600",
    "sg:province":"Danmark",
    "wof:name":"Det Danske Spejderkorps, Krage S\u00f8, Vester Aaby",
    "wof:placetype":"venue"
},
  "geometry": {"coordinates":[10.2400531769,55.0950622559],"type":"Point"}
}