{
  "type": "Feature",
  "properties": {
    "iso:country":"DK",
    "sg:address":"S\u00f8ndergade 1",
    "sg:city":"Vildbjerg",
    "sg:orig_category":"Belysning",
    "sg:phone":"+45 97 13 31 00",
    "sg:postcode":"7480",
    "sg:province":"Danmark",
    "wof:name":"Vildbjerg El-Center",
    "wof:placetype":"venue"
},
  "geometry": {"coordinates":[8.767242,56.196938],"type":"Point"}
}