{
  "type": "Feature",
  "properties": {
    "iso:country":"DK",
    "sg:address":"Kirkevej 3",
    "sg:city":"Gedved",
    "sg:orig_category":"Tandklinikker, Kommunale",
    "sg:phone":"+45 75 66 55 00",
    "sg:postcode":"8751",
    "sg:province":"Danmark",
    "wof:name":"Gedved Skoletandklinik",
    "wof:placetype":"venue"
},
  "geometry": {"coordinates":[9.8466062546,55.9348068237],"type":"Point"}
}