{
  "type": "Feature",
  "properties": {
    "addr:full":"Gravene 30 Haderslev Danmark 6100",
    "addr:housenumber":"30",
    "addr:postcode":"6100",
    "addr:street":"Gravene",
    "iso:country":"DK",
    "sg:address":"Gravene 30",
    "sg:city":"Haderslev",
    "sg:orig_category":"Optikere",
    "sg:phone":"+45 74 52 33 14",
    "sg:postcode":"6100",
    "sg:province":"Danmark",
    "wof:name":"Brillecaf\u00e9en",
    "wof:placetype":"venue"
},
  "geometry": {"coordinates":[9.4856309891,55.2509994507],"type":"Point"}
}