{
  "type": "Feature",
  "properties": {
    "iso:country":"DK",
    "sg:address":"St\u00f8berivej 4",
    "sg:city":"Aars",
    "sg:orig_category":"Landbrugsmaskiner",
    "sg:phone":"+45 98 62 13 00",
    "sg:postcode":"9600",
    "sg:province":"Danmark",
    "wof:name":"Johnsen , Erik",
    "wof:placetype":"venue"
},
  "geometry": {"coordinates":[9.4975242615,56.8003807068],"type":"Point"}
}