{
  "type": "Feature",
  "properties": {
    "iso:country":"DK",
    "sg:address":"Kvalsholmvej 29",
    "sg:city":"Sunds",
    "sg:classifiers":[
        {
            "category":"Taxi",
            "type":"Transportation"
        }
    ],
    "sg:phone":"+45 97 14 11 24",
    "sg:postcode":"7451",
    "sg:province":"Danmark",
    "wof:name":"Sunds Taxi",
    "wof:placetype":"venue"
},
  "geometry": {"coordinates":[9.0224294662,56.2066116333],"type":"Point"}
}