{
  "type": "Feature",
  "properties": {
    "addr:full":"v/ Niels Bunkenborg, Kongensgade 49 Christiansfeld Danmark 6070",
    "addr:housenumber":"49",
    "addr:postcode":"6070",
    "addr:street":"Kongensgade",
    "iso:country":"DK",
    "sg:address":"v/ Niels Bunkenborg, Kongensgade 49",
    "sg:city":"Christiansfeld",
    "sg:orig_category":"Kulturelle foreninger",
    "sg:phone":"+45 74 56 18 41",
    "sg:postcode":"6070",
    "sg:province":"Danmark",
    "wof:name":"Dobbeltkvartetten Lyren",
    "wof:placetype":"venue"
},
  "geometry": {"coordinates":[9.4834346771,55.3550567627],"type":"Point"}
}