{
  "type": "Feature",
  "properties": {
    "addr:full":"Dynnesvej 11, Barritskovby Barrit Danmark 7150",
    "addr:housenumber":"11",
    "addr:postcode":"7150",
    "addr:street":"Dynnesvej",
    "iso:country":"DK",
    "sg:address":"Dynnesvej 11, Barritskovby",
    "sg:city":"Barrit",
    "sg:orig_category":"Murermestre",
    "sg:phone":"+45 75 69 15 62",
    "sg:postcode":"7150",
    "sg:province":"Danmark",
    "wof:name":"Barrit Murerforretning",
    "wof:placetype":"venue"
},
  "geometry": {"coordinates":[9.9013900757,55.7076950073],"type":"Point"}
}