{
  "type": "Feature",
  "properties": {
    "addr:full":"Skolevej 1, Pindstrup Ryomg\u00e5rd Danmark 8550",
    "addr:housenumber":"1",
    "addr:postcode":"8550",
    "addr:street":"Skolevej",
    "iso:country":"DK",
    "sg:address":"Skolevej 1, Pindstrup",
    "sg:city":"Ryomg\u00e5rd",
    "sg:orig_category":"Kommunale folkeskoler",
    "sg:phone":"+45 86 39 61 13",
    "sg:postcode":"8550",
    "sg:province":"Danmark",
    "wof:name":"Pindstrup Skole",
    "wof:placetype":"venue"
},
  "geometry": {"coordinates":[10.5041999817,56.3809814453],"type":"Point"}
}