{
  "type": "Feature",
  "properties": {
    "addr:full":"Karl Withs Vej 7 Odense C Danmark 5000",
    "addr:housenumber":"7",
    "addr:postcode":"5000",
    "addr:street":"Karl Withs Vej",
    "iso:country":"DK",
    "sg:address":"Karl Withs Vej 7",
    "sg:city":"Odense C",
    "sg:orig_category":"Psykologer, praktiserende",
    "sg:phone":"+45 66 12 66 87",
    "sg:postcode":"5000",
    "sg:province":"Danmark",
    "wof:name":"Aagaard, Lotte Sch\u00f8ler",
    "wof:placetype":"venue"
},
  "geometry": {"coordinates":[10.3571405411,55.4000473022],"type":"Point"}
}