{
  "type": "Feature",
  "properties": {
    "iso:country":"DK",
    "sg:address":"Fmd.: Carrie Cederbye, Poppelvej 18",
    "sg:city":"Vordingborg",
    "sg:orig_category":"\u00c3\u2020ldreorganisationer og klubber",
    "sg:phone":"+45 55 34 25 04",
    "sg:postcode":"4760",
    "sg:province":"Danmark",
    "wof:name":"Vordingborg Seniordanser Forening",
    "wof:placetype":"venue"
},
  "geometry": {"coordinates":[11.9124183655,55.0085449219],"type":"Point"}
}