{
  "type": "Feature",
  "properties": {
    "addr:full":"Bjerrevej 73 Horsens Danmark 8700",
    "addr:housenumber":"73",
    "addr:postcode":"8700",
    "addr:street":"Bjerrevej",
    "iso:country":"DK",
    "sg:address":"Bjerrevej 73",
    "sg:city":"Horsens",
    "sg:orig_category":"Pizzeriaer",
    "sg:phone":"+45 75 63 16 10",
    "sg:postcode":"8700",
    "sg:province":"Danmark",
    "wof:name":"Valhalla",
    "wof:placetype":"venue"
},
  "geometry": {"coordinates":[9.8465690613,55.8462257385],"type":"Point"}
}