{
  "type": "Feature",
  "properties": {
    "addr:full":"Bilds\u00f8vej 80, Kr. Stillinge Slagelse Danmark 4200",
    "addr:housenumber":"80 kr.",
    "addr:postcode":"4200",
    "addr:street":"Bildsovej;Stillinge",
    "iso:country":"DK",
    "sg:address":"Bilds\u00f8vej 80, Kr. Stillinge",
    "sg:city":"Slagelse",
    "sg:orig_category":"Skoler",
    "sg:phone":"+45 58 54 70 58",
    "sg:postcode":"4200",
    "sg:province":"Danmark",
    "sg:website":"www.stillingeskole.dk",
    "wof:name":"Stillinge Skole",
    "wof:placetype":"venue"
},
  "geometry": {"coordinates":[11.3569850922,55.4050865173],"type":"Point"}
}