{
  "type": "Feature",
  "properties": {
    "addr:full":"Fmd.: Steen Stidsen Jensen, Skovvej 40, Kragelund L\u00f8sning Danmark 8723",
    "addr:housenumber":"40",
    "addr:postcode":"8723",
    "addr:street":"Stidsen Jensen Skovvej",
    "iso:country":"DK",
    "sg:address":"Fmd.: Steen Stidsen Jensen, Skovvej 40, Kragelund",
    "sg:city":"L\u00f8sning",
    "sg:orig_category":"Kirkelige foreninger",
    "sg:phone":"+45 75 89 33 50",
    "sg:postcode":"8723",
    "sg:province":"Danmark",
    "wof:name":"Indre Missions Unge i Kragelund",
    "wof:placetype":"venue"
},
  "geometry": {"coordinates":[9.7620611191,55.8105201721],"type":"Point"}
}