{
  "type": "Feature",
  "properties": {
    "iso:country":"DK",
    "sg:address":"Jordl\u00f8se Skole, Jordl\u00f8se M\u00f8llevej 14, Jordl\u00f8se",
    "sg:city":"Haarby",
    "sg:orig_category":"Kulturelle foreninger",
    "sg:phone":"+45 64 73 18 27",
    "sg:postcode":"5683",
    "sg:province":"Danmark",
    "wof:name":"L\u00e6re-V\u00e6re Stedet",
    "wof:placetype":"venue"
},
  "geometry": {"coordinates":[10.1234750748,55.2234535217],"type":"Point"}
}