{
  "type": "Feature",
  "properties": {
    "addr:full":"Rundbjergvej 11, True Tilst Danmark 8381",
    "addr:housenumber":"11",
    "addr:postcode":"8381",
    "addr:street":"Rundbjergvej;True",
    "iso:country":"DK",
    "sg:address":"Rundbjergvej 11, True",
    "sg:city":"Tilst",
    "sg:orig_category":"Autoreservedele",
    "sg:phone":"+45 86 24 83 44",
    "sg:postcode":"8381",
    "sg:province":"Danmark",
    "wof:name":"Becker Autodele Engros",
    "wof:placetype":"venue"
},
  "geometry": {"coordinates":[10.1078147888,56.1882019043],"type":"Point"}
}