{
  "type": "Feature",
  "properties": {
    "addr:full":"Holb\u00e6kvej 11 Slagelse Danmark 4200",
    "addr:housenumber":"11",
    "addr:postcode":"4200",
    "addr:street":"Holbaekvej",
    "iso:country":"DK",
    "sg:address":"Holb\u00e6kvej 11",
    "sg:city":"Slagelse",
    "sg:orig_category":"Mobiltelefoner",
    "sg:phone":"+45 58 53 54 11",
    "sg:postcode":"4200",
    "sg:province":"Danmark",
    "wof:name":"Unitalk",
    "wof:placetype":"venue"
},
  "geometry": {"coordinates":[11.3710184097,55.4113960266],"type":"Point"}
}