{
  "type": "Feature",
  "properties": {
    "addr:full":"(Kjeld K Jensen), Rugv\u00e6nget 2 A Slagelse Danmark 4200",
    "addr:housenumber":"2 a",
    "addr:postcode":"4200",
    "addr:street":"Kjeld",
    "iso:country":"DK",
    "sg:address":"(Kjeld K Jensen), Rugv\u00e6nget 2 A",
    "sg:city":"Slagelse",
    "sg:orig_category":"Trykkerier",
    "sg:phone":"+45 58 52 08 29",
    "sg:postcode":"4200",
    "sg:province":"Danmark",
    "wof:name":"SP Media Aps, Slagelse",
    "wof:placetype":"venue"
},
  "geometry": {"coordinates":[11.3569850922,55.4050865173],"type":"Point"}
}