{
  "type": "Feature",
  "properties": {
    "iso:country":"DK",
    "sg:address":"Hadsundvej 27",
    "sg:city":"Aalborg",
    "sg:classifiers":[
        {
            "category":"Banks & Credit Unions",
            "subcategory":"Bank",
            "type":"Services"
        }
    ],
    "sg:phone":"+45 96 31 09 40",
    "sg:postcode":"9000",
    "sg:province":"Danmark",
    "sg:tags":[
        "banker"
    ],
    "sg:website":"jyskebank.dk",
    "wof:name":"Jyske Bank A/S",
    "wof:placetype":"venue"
},
  "geometry": {"coordinates":[9.950547,57.04253],"type":"Point"}
}