{
  "type": "Feature",
  "properties": {
    "addr:full":"Lundholmvej 9 Holstebro Danmark 7500",
    "addr:housenumber":"9",
    "addr:postcode":"7500",
    "addr:street":"Lundholmvej",
    "iso:country":"DK",
    "sg:address":"Lundholmvej 9",
    "sg:city":"Holstebro",
    "sg:orig_category":"Autoforhandlere",
    "sg:phone":"+45 97 42 39 11",
    "sg:postcode":"7500",
    "sg:province":"Danmark",
    "wof:name":"Poulsen, Arne",
    "wof:placetype":"venue"
},
  "geometry": {"coordinates":[8.6164360046,56.379524231],"type":"Point"}
}