{
  "type": "Feature",
  "properties": {
    "iso:country":"DK",
    "sg:address":"Kirkestr\u00e6de 3",
    "sg:city":"Holstebro",
    "sg:classifiers":[
        {
            "category":"Restaurant",
            "type":"Food & Drink"
        }
    ],
    "sg:phone":"+45 97 41 43 40",
    "sg:postcode":"7500",
    "sg:province":"Danmark",
    "wof:name":"Raadhusk\u00e6lderen",
    "wof:placetype":"venue"
},
  "geometry": {"coordinates":[8.6202583313,56.3625221252],"type":"Point"}
}