{
  "type": "Feature",
  "properties": {
    "addr:full":"R\u00f8nneb\u00e6rvej 1 Holte Danmark 2840",
    "addr:housenumber":"1",
    "addr:postcode":"2840",
    "addr:street":"Ronnebaervej",
    "iso:country":"DK",
    "sg:address":"R\u00f8nneb\u00e6rvej 1",
    "sg:city":"Holte",
    "sg:orig_category":"Blomsterhandlere",
    "sg:phone":"+45 45 42 25 26",
    "sg:postcode":"2840",
    "sg:province":"Danmark",
    "wof:name":"Holte Blomsteratelier",
    "wof:placetype":"venue"
},
  "geometry": {"coordinates":[12.4706554413,55.8122367859],"type":"Point"}
}