{
  "type": "Feature",
  "properties": {
    "addr:full":"B\u00f8gildvej 10 Ikast Danmark 7430",
    "addr:housenumber":"10",
    "addr:postcode":"7430",
    "addr:street":"Bogildvej",
    "iso:country":"DK",
    "sg:address":"B\u00f8gildvej 10",
    "sg:city":"Ikast",
    "sg:orig_category":"\u00c3\u02dcvrige skoler",
    "sg:phone":"+45 96 60 33 33",
    "sg:postcode":"7430",
    "sg:province":"Danmark",
    "wof:name":"Ikast-Seminariet",
    "wof:placetype":"venue"
},
  "geometry": {"coordinates":[9.1559419632,56.1394767761],"type":"Point"}
}