{
  "type": "Feature",
  "properties": {
    "addr:full":"Silkeborgvej 29 Herning Danmark 7400",
    "addr:housenumber":"29",
    "addr:postcode":"7400",
    "addr:street":"Silkeborgvej",
    "iso:country":"DK",
    "sg:address":"Silkeborgvej 29",
    "sg:city":"Herning",
    "sg:orig_category":"Alternativ behandling",
    "sg:phone":"+45 97 21 61 85",
    "sg:postcode":"7400",
    "sg:province":"Danmark",
    "wof:name":"Helseklinikken",
    "wof:placetype":"venue"
},
  "geometry": {"coordinates":[8.9866600037,56.135017395],"type":"Point"}
}