{
  "type": "Feature",
  "properties": {
    "iso:country":"DK",
    "sg:address":"Kst.fmd.: Knud H.P. Jacobsen, Hovedgaden 5",
    "sg:city":"Gadstrup",
    "sg:orig_category":"Borger- og beboerforeninger",
    "sg:phone":"+45 46 19 02 59",
    "sg:postcode":"4621",
    "sg:province":"Danmark",
    "sg:website":"www.remrev.dk",
    "wof:name":"Gadstrup Borgerforening",
    "wof:placetype":"venue"
},
  "geometry": {"coordinates":[12.0978450775,55.5737800598],"type":"Point"}
}