{
  "type": "Feature",
  "properties": {
    "iso:country":"DK",
    "sg:address":"N\u00f8rretorv 4",
    "sg:city":"Thisted",
    "sg:orig_category":"Cafeer",
    "sg:phone":"+45 97 91 01 09",
    "sg:postcode":"7700",
    "sg:province":"Danmark",
    "wof:name":"Gr\u00f8nne Under Linden, Caf\u00e9",
    "wof:placetype":"venue"
},
  "geometry": {"coordinates":[8.6919784546,56.9556121826],"type":"Point"}
}