{
  "type": "Feature",
  "properties": {
    "addr:full":"S\u00f8ren Kannes Vej 6 Hornb\u00e6k Danmark 3100",
    "addr:housenumber":"6",
    "addr:postcode":"3100",
    "addr:street":"Kannes Vej",
    "iso:country":"DK",
    "sg:address":"S\u00f8ren Kannes Vej 6",
    "sg:city":"Hornb\u00e6k",
    "sg:orig_category":"Fritidshjem",
    "sg:phone":"+45 49 28 11 54",
    "sg:postcode":"3100",
    "sg:province":"Danmark",
    "wof:name":"S\u00f8ren Kanne, Fritidshjemmet",
    "wof:placetype":"venue"
},
  "geometry": {"coordinates":[12.4300451279,56.0916366577],"type":"Point"}
}