{
  "type": "Feature",
  "properties": {
    "addr:full":"Viborgvej 316, Herrup Vinderup Danmark 7830",
    "addr:housenumber":"316",
    "addr:postcode":"7830",
    "addr:street":"Viborgvej",
    "iso:country":"DK",
    "sg:address":"Viborgvej 316, Herrup",
    "sg:city":"Vinderup",
    "sg:orig_category":"Farve- og stilanalyse",
    "sg:phone":"+45 97 45 25 64",
    "sg:postcode":"7830",
    "sg:province":"Danmark",
    "wof:name":"Color Me Beautiful",
    "wof:placetype":"venue"
},
  "geometry": {"coordinates":[8.7796897888,56.482635498],"type":"Point"}
}