{
  "type": "Feature",
  "properties": {
    "addr:full":"Havnegade 4 Frederikshavn Danmark 9900",
    "addr:housenumber":"4",
    "addr:postcode":"9900",
    "addr:street":"Havnegade",
    "iso:country":"DK",
    "sg:address":"Havnegade 4",
    "sg:city":"Frederikshavn",
    "sg:orig_category":"Sportsartikler",
    "sg:phone":"+45 98 42 33 55",
    "sg:postcode":"9900",
    "sg:province":"Danmark",
    "wof:name":"Sportmaster",
    "wof:placetype":"venue"
},
  "geometry": {"coordinates":[10.5349626541,57.4376182556],"type":"Point"}
}