{
  "type": "Feature",
  "properties": {
    "addr:full":"Nedergade 33, 2 Odense C Danmark 5000",
    "addr:housenumber":"33 2",
    "addr:postcode":"5000",
    "addr:street":"Nedergade",
    "iso:country":"DK",
    "sg:address":"Nedergade 33, 2",
    "sg:city":"Odense C",
    "sg:orig_category":"Dag- og distriktsblade",
    "sg:phone":"+45 63 13 60 80",
    "sg:postcode":"5000",
    "sg:province":"Danmark",
    "wof:name":"EjendomsAvisen A/S",
    "wof:placetype":"venue"
},
  "geometry": {"coordinates":[10.3945598602,55.3968772888],"type":"Point"}
}