{
  "type": "Feature",
  "properties": {
    "addr:full":"Banev\u00e6nget 48 Slangerup Danmark 3550",
    "addr:housenumber":"48",
    "addr:postcode":"3550",
    "addr:street":"Banevaenget",
    "iso:country":"DK",
    "sg:address":"Banev\u00e6nget 48",
    "sg:city":"Slangerup",
    "sg:orig_category":"Elektronik",
    "sg:phone":"+45 47 38 00 43",
    "sg:postcode":"3550",
    "sg:province":"Danmark",
    "wof:name":"Danwill",
    "wof:placetype":"venue"
},
  "geometry": {"coordinates":[12.1717596054,55.8460769653],"type":"Point"}
}