{
  "type": "Feature",
  "properties": {
    "addr:full":"Rugv\u00e6nget 5D Slagelse Danmark 4200",
    "addr:housenumber":"5d",
    "addr:postcode":"4200",
    "iso:country":"DK",
    "sg:address":"Rugv\u00e6nget 5D",
    "sg:city":"Slagelse",
    "sg:orig_category":"Mejerier",
    "sg:phone":"+45 58 50 07 83",
    "sg:postcode":"4200",
    "sg:province":"Danmark",
    "wof:name":"Mejerig\u00e5rden",
    "wof:placetype":"venue"
},
  "geometry": {"coordinates":[11.3569850922,55.4050865173],"type":"Point"}
}