{
  "type": "Feature",
  "properties": {
    "addr:full":"Helgesvej 36 Herlufmagle Danmark 4160",
    "addr:housenumber":"36",
    "addr:postcode":"4160",
    "addr:street":"Helgesvej",
    "iso:country":"DK",
    "sg:address":"Helgesvej 36",
    "sg:city":"Herlufmagle",
    "sg:orig_category":"Distriktsbiblioteker",
    "sg:phone":"+45 57 69 01 91",
    "sg:postcode":"4160",
    "sg:province":"Danmark",
    "wof:name":"Herlufmagle bibliotek",
    "wof:placetype":"venue"
},
  "geometry": {"coordinates":[11.7523603439,55.3134002686],"type":"Point"}
}