{
  "type": "Feature",
  "properties": {
    "iso:country":"DK",
    "sg:address":"Lyngbyvej 343",
    "sg:city":"Gentofte",
    "sg:orig_category":"Diners transportables",
    "sg:phone":"+45 39 68 02 03",
    "sg:postcode":"2820",
    "sg:province":"Danmark",
    "wof:name":"J.B. Diner",
    "wof:placetype":"venue"
},
  "geometry": {"coordinates":[12.5349521637,55.7414207458],"type":"Point"}
}