{
  "type": "Feature",
  "properties": {
    "iso:country":"DK",
    "sg:address":"Slagelsevej 14",
    "sg:city":"Snertinge",
    "sg:orig_category":"Apoteker og -udsalg",
    "sg:phone":"+45 59 26 80 12",
    "sg:postcode":"4460",
    "sg:province":"Danmark",
    "wof:name":"Snertinge Apotek",
    "wof:placetype":"venue"
},
  "geometry": {"coordinates":[11.3837413788,55.7097320557],"type":"Point"}
}