{
  "type": "Feature",
  "properties": {
    "addr:full":"Sundvej 37, Hvalpsund Fars\u00f8 Danmark 9640",
    "addr:housenumber":"37",
    "addr:postcode":"9640",
    "addr:street":"Sundvej",
    "iso:country":"DK",
    "sg:address":"Sundvej 37, Hvalpsund",
    "sg:city":"Fars\u00f8",
    "sg:orig_category":"Malermestre",
    "sg:phone":"+45 98 63 81 12",
    "sg:postcode":"9640",
    "sg:province":"Danmark",
    "wof:name":"Schmidt, H.",
    "wof:placetype":"venue"
},
  "geometry": {"coordinates":[9.1937885284,56.6945037842],"type":"Point"}
}