{
  "type": "Feature",
  "properties": {
    "addr:full":"Klintedalsvej 60 Kalundborg Danmark 4400",
    "addr:housenumber":"60",
    "addr:postcode":"4400",
    "addr:street":"Klintedalsvej",
    "iso:country":"DK",
    "sg:address":"Klintedalsvej 60",
    "sg:city":"Kalundborg",
    "sg:classifiers":[
        {
            "category":"Travel",
            "subcategory":"Hotels & Motels",
            "type":"Entertainment"
        }
    ],
    "sg:phone":"+45 59 50 80 67",
    "sg:postcode":"4400",
    "sg:province":"Danmark",
    "sg:website":"www.roesnaes.dk",
    "wof:name":"Kursuscenter R\u00f8sn\u00e6s",
    "wof:placetype":"venue"
},
  "geometry": {"coordinates":[11.0239877701,55.7027702332],"type":"Point"}
}