{
  "type": "Feature",
  "properties": {
    "addr:full":"Skolegyden 4, Herringl\u00f8se Veks\u00f8 Sj\u00e6lland Danmark 3670",
    "addr:housenumber":"4",
    "addr:postcode":"3670",
    "addr:street":"Skolegyden",
    "iso:country":"DK",
    "sg:address":"Skolegyden 4, Herringl\u00f8se",
    "sg:city":"Veks\u00f8 Sj\u00e6lland",
    "sg:orig_category":"Murermestre",
    "sg:phone":"+45 46 76 94 14",
    "sg:postcode":"3670",
    "sg:province":"Danmark",
    "wof:name":"Rasmussen, Keld",
    "wof:placetype":"venue"
},
  "geometry": {"coordinates":[-76.0886383057,38.7291030884],"type":"Point"}
}