{
  "type": "Feature",
  "properties": {
    "addr:full":"H. Christoffersens Vej 3 Holeby Danmark 4960",
    "addr:housenumber":"3",
    "addr:postcode":"4960",
    "addr:street":"H. Christoffersens Vej",
    "iso:country":"DK",
    "sg:address":"H. Christoffersens Vej 3",
    "sg:city":"Holeby",
    "sg:orig_category":"Faglige organisationer og foreninger",
    "sg:phone":"+45 54 60 64 49",
    "sg:postcode":"4960",
    "sg:province":"Danmark",
    "wof:name":"Dansk Metalarbejder Forbund",
    "wof:placetype":"venue"
},
  "geometry": {"coordinates":[11.4765930176,54.7076339722],"type":"Point"}
}