{
  "type": "Feature",
  "properties": {
    "addr:full":"Godth\u00e5bsvej 131 Frederiksberg Danmark 2000",
    "addr:housenumber":"131",
    "addr:postcode":"2000",
    "addr:street":"Godthaabsvej",
    "iso:country":"DK",
    "sg:address":"Godth\u00e5bsvej 131",
    "sg:city":"Frederiksberg",
    "sg:orig_category":"Hobbyartikler",
    "sg:phone":"+45 38 19 42 90",
    "sg:postcode":"2000",
    "sg:province":"Danmark",
    "sg:website":"www.sitecenter.dk/hjemmebryg",
    "wof:name":"Vin\u00f8l Hobby ApS",
    "wof:placetype":"venue"
},
  "geometry": {"coordinates":[12.5169496536,55.6901702881],"type":"Point"}
}