{
  "type": "Feature",
  "properties": {
    "addr:full":"Jernbanegade 27 - 29 Brovst Danmark 9460",
    "addr:housenumber":"27 29",
    "addr:postcode":"9460",
    "addr:street":"Jernbanegade",
    "iso:country":"DK",
    "sg:address":"Jernbanegade 27 - 29",
    "sg:city":"Brovst",
    "sg:orig_category":"Belysning",
    "sg:phone":"+45 98 23 10 39",
    "sg:postcode":"9460",
    "sg:province":"Danmark",
    "wof:name":"Brovst Isenkram & Belysning",
    "wof:placetype":"venue"
},
  "geometry": {"coordinates":[9.5218467712,57.0984306335],"type":"Point"}
}