{
  "type": "Feature",
  "properties": {
    "addr:full":"Fmd.: Steen B. Larsen, Ahlervej 14, Borris Skjern Danmark 6900",
    "addr:housenumber":"14",
    "addr:postcode":"6900",
    "addr:street":"Ahlervej;Borris",
    "iso:country":"DK",
    "sg:address":"Fmd.: Steen B. Larsen, Ahlervej 14, Borris",
    "sg:city":"Skjern",
    "sg:orig_category":"El-forsyning",
    "sg:phone":"+45 97 36 60 67",
    "sg:postcode":"6900",
    "sg:province":"Danmark",
    "wof:name":"Borris Elforsyning",
    "wof:placetype":"venue"
},
  "geometry": {"coordinates":[8.492972374,55.9485740662],"type":"Point"}
}