{
  "type": "Feature",
  "properties": {
    "addr:full":"Heimdalsgade 22 K\u00f8benhavn N Danmark 2200",
    "addr:housenumber":"22",
    "addr:postcode":"2200",
    "addr:street":"Heimdalsgade;N Danmark",
    "iso:country":"DK",
    "sg:address":"Heimdalsgade 22",
    "sg:city":"K\u00f8benhavn N",
    "sg:orig_category":"Kiosker",
    "sg:phone":"+45 35 81 71 45",
    "sg:postcode":"2200",
    "sg:province":"Danmark",
    "wof:name":"Super D\u00f8gn Kiosk I/S",
    "wof:placetype":"venue"
},
  "geometry": {"coordinates":[-76.4168395996,37.452419281],"type":"Point"}
}