{
  "type": "Feature",
  "properties": {
    "addr:full":"\u00c5rhusvej 41, N\u00e5rup Gjern Danmark 8883",
    "addr:housenumber":"41",
    "addr:postcode":"8883",
    "addr:street":"Aarhusvej",
    "iso:country":"DK",
    "sg:address":"\u00c5rhusvej 41, N\u00e5rup",
    "sg:city":"Gjern",
    "sg:orig_category":"Cafeterier",
    "sg:phone":"+45 86 87 19 66",
    "sg:postcode":"8883",
    "sg:province":"Danmark",
    "wof:name":"Midtvejs Cafeteriet",
    "wof:placetype":"venue"
},
  "geometry": {"coordinates":[9.7394037247,56.2305335999],"type":"Point"}
}