{
  "type": "Feature",
  "properties": {
    "addr:full":"Roskildevej 152 Frederikssund Danmark 3600",
    "addr:housenumber":"152",
    "addr:postcode":"3600",
    "addr:street":"Roskildevej",
    "iso:country":"DK",
    "sg:address":"Roskildevej 152",
    "sg:city":"Frederikssund",
    "sg:orig_category":"Autoforhandlere",
    "sg:phone":"+45 47 31 18 08",
    "sg:postcode":"3600",
    "sg:province":"Danmark",
    "sg:website":"www.pahansen.dk",
    "wof:name":"Hansen Automobiler A/S, Povl Arne",
    "wof:placetype":"venue"
},
  "geometry": {"coordinates":[12.0825433731,55.826965332],"type":"Point"}
}