{
  "type": "Feature",
  "properties": {
    "addr:full":"Lundg\u00e5rdsparken 38 Aulum Danmark 7490",
    "addr:housenumber":"38",
    "addr:postcode":"7490",
    "addr:street":"Lundgaardsparken",
    "iso:country":"DK",
    "sg:address":"Lundg\u00e5rdsparken 38",
    "sg:city":"Aulum",
    "sg:orig_category":"Malermestre",
    "sg:phone":"+45 97 47 33 45",
    "sg:postcode":"7490",
    "sg:province":"Danmark",
    "wof:name":"Carstens Malerservice",
    "wof:placetype":"venue"
},
  "geometry": {"coordinates":[8.7853879929,56.263885498],"type":"Point"}
}