{
  "type": "Feature",
  "properties": {
    "addr:full":"Adelgade 7 Randers Danmark 8900",
    "addr:housenumber":"7",
    "addr:postcode":"8900",
    "addr:street":"Adelgade",
    "iso:country":"DK",
    "sg:address":"Adelgade 7",
    "sg:city":"Randers",
    "sg:orig_category":"Antikvariater",
    "sg:phone":"+45 86 41 98 48",
    "sg:postcode":"8900",
    "sg:province":"Danmark",
    "wof:name":"Bogcentrum",
    "wof:placetype":"venue"
},
  "geometry": {"coordinates":[10.0344905853,56.4621772766],"type":"Point"}
}