{
  "type": "Feature",
  "properties": {
    "addr:full":"Drewsensvej 15 Silkeborg Danmark 8600",
    "addr:housenumber":"15",
    "addr:postcode":"8600",
    "addr:street":"Drewsensvej",
    "iso:country":"DK",
    "sg:address":"Drewsensvej 15",
    "sg:city":"Silkeborg",
    "sg:orig_category":"Elektro",
    "sg:phone":"+45 86 82 19 55",
    "sg:postcode":"8600",
    "sg:province":"Danmark",
    "wof:name":"Elektro Mekano",
    "wof:placetype":"venue"
},
  "geometry": {"coordinates":[9.5486574173,56.1647644043],"type":"Point"}
}