{
  "type": "Feature",
  "properties": {
    "addr:full":"Dalbynedervej 1, Udbyover Havndal Danmark 8970",
    "addr:housenumber":"1",
    "addr:postcode":"8970",
    "addr:street":"Dalbynedervej",
    "iso:country":"DK",
    "sg:address":"Dalbynedervej 1, Udbyover",
    "sg:city":"Havndal",
    "sg:orig_category":"Hestestalde, udlejning",
    "sg:phone":"+45 86 47 00 98",
    "sg:postcode":"8970",
    "sg:province":"Danmark",
    "wof:name":"Hj\u00f8rnely",
    "wof:placetype":"venue"
},
  "geometry": {"coordinates":[10.1937646866,56.6534461975],"type":"Point"}
}