{
  "type": "Feature",
  "properties": {
    "addr:full":"Algade 18 Roskilde Danmark 4000",
    "addr:housenumber":"18",
    "addr:postcode":"4000",
    "addr:street":"Algade",
    "iso:country":"DK",
    "sg:address":"Algade 18",
    "sg:city":"Roskilde",
    "sg:orig_category":"Telebutikker",
    "sg:phone":"+45 46 32 26 99",
    "sg:postcode":"4000",
    "sg:province":"Danmark",
    "wof:name":"Sonofon",
    "wof:placetype":"venue"
},
  "geometry": {"coordinates":[12.0846805573,55.6409759521],"type":"Point"}
}