{
  "type": "Feature",
  "properties": {
    "addr:full":"Hovedgaden 35 Alling\u00e5bro Danmark 8961",
    "addr:housenumber":"35",
    "addr:postcode":"8961",
    "addr:street":"Hovedgaden",
    "iso:country":"DK",
    "sg:address":"Hovedgaden 35",
    "sg:city":"Alling\u00e5bro",
    "sg:orig_category":"Slagter og viktualie",
    "sg:phone":"+45 86 48 11 57",
    "sg:postcode":"8961",
    "sg:province":"Danmark",
    "wof:name":"Slagteriudsalget",
    "wof:placetype":"venue"
},
  "geometry": {"coordinates":[-73.92324829099999,40.8257446289],"type":"Point"}
}