{
  "type": "Feature",
  "properties": {
    "addr:full":"Leder: Alice W. Rasmussen, S\u00f8ndermarksvej 212 Billund Danmark 7190",
    "addr:housenumber":"212",
    "addr:postcode":"7190",
    "addr:street":"Sondermarksvej",
    "iso:country":"DK",
    "sg:address":"Leder: Alice W. Rasmussen, S\u00f8ndermarksvej 212",
    "sg:city":"Billund",
    "sg:orig_category":"\u00c3\u02dcvrig fritidsundervisning",
    "sg:phone":"+45 75 33 19 24",
    "sg:postcode":"7190",
    "sg:province":"Danmark",
    "wof:name":"Billund Sy- og Tilsk\u00e6rerskole",
    "wof:placetype":"venue"
},
  "geometry": {"coordinates":[9.1138372421,55.7316017151],"type":"Point"}
}