{
  "type": "Feature",
  "properties": {
    "addr:full":"H\u00f8jdedraget 2, Taulov Fredericia Danmark 7000",
    "addr:housenumber":"2",
    "addr:postcode":"7000",
    "addr:street":"Hojdedraget;Taulov",
    "iso:country":"DK",
    "sg:address":"H\u00f8jdedraget 2, Taulov",
    "sg:city":"Fredericia",
    "sg:orig_category":"Filialbiblioteker",
    "sg:phone":"+45 72 10 52 40",
    "sg:postcode":"7000",
    "sg:province":"Danmark",
    "wof:name":"Taulov Bibliotek",
    "wof:placetype":"venue"
},
  "geometry": {"coordinates":[9.7591047287,55.566368103],"type":"Point"}
}