{
  "type": "Feature",
  "properties": {
    "addr:full":"Klovbygade 8 Jerslev Sj\u00e6lland Danmark 4490",
    "addr:housenumber":"8",
    "addr:postcode":"4490",
    "addr:street":"Klovbygade",
    "iso:country":"DK",
    "sg:address":"Klovbygade 8",
    "sg:city":"Jerslev Sj\u00e6lland",
    "sg:orig_category":"Malermestre",
    "sg:phone":"+45 59 59 58 02",
    "sg:postcode":"4490",
    "sg:province":"Danmark",
    "wof:name":"Kjelds Maler Forretning",
    "wof:placetype":"venue"
},
  "geometry": {"coordinates":[11.2239027023,55.630657196],"type":"Point"}
}