{
  "type": "Feature",
  "properties": {
    "addr:full":"Frederikssundsvej 156 A Br\u00f8nsh\u00f8j Danmark 2700",
    "addr:housenumber":"156 a",
    "addr:postcode":"2700",
    "addr:street":"Frederikssundsvej",
    "iso:country":"DK",
    "sg:address":"Frederikssundsvej 156 A",
    "sg:city":"Br\u00f8nsh\u00f8j",
    "sg:orig_category":"Ejendomshandel",
    "sg:phone":"+45 38 80 00 40",
    "sg:postcode":"2700",
    "sg:province":"Danmark",
    "sg:website":"www.bec.safeonline.dk",
    "wof:name":"BEC EjendomsM\u00e6glerne Bolig & Erhverv",
    "wof:placetype":"venue"
},
  "geometry": {"coordinates":[-65.6866531372,-23.1981296539],"type":"Point"}
}