{
  "type": "Feature",
  "properties": {
    "addr:full":"N\u00f8rremarksvej 17 Viborg Danmark 8800",
    "addr:housenumber":"17",
    "addr:postcode":"8800",
    "addr:street":"Norremarksvej",
    "iso:country":"DK",
    "sg:address":"N\u00f8rremarksvej 17",
    "sg:city":"Viborg",
    "sg:orig_category":"Distriktspsykiatri",
    "sg:phone":"+45 86 61 59 00",
    "sg:postcode":"8800",
    "sg:province":"Danmark",
    "wof:name":"N\u00f8rremarken",
    "wof:placetype":"venue"
},
  "geometry": {"coordinates":[9.4010791779,56.4741325378],"type":"Point"}
}