{
  "type": "Feature",
  "properties": {
    "iso:country":"DK",
    "sg:address":"N\u00f8rrebro 2",
    "sg:city":"S\u00f8by",
    "sg:orig_category":"Bagere",
    "sg:phone":"+45 62 58 10 65",
    "sg:postcode":"5985",
    "sg:province":"Danmark",
    "wof:name":"Finn's Bageri",
    "wof:placetype":"venue"
},
  "geometry": {"coordinates":[-78.063751,43.049847],"type":"Point"}
}