{
  "type": "Feature",
  "properties": {
    "addr:full":"Lummerb\u00e6kvej 71, Kvong Varde Danmark 6800",
    "addr:housenumber":"71",
    "addr:postcode":"6800",
    "addr:street":"Lummerbaekvej;Kvong",
    "iso:country":"DK",
    "sg:address":"Lummerb\u00e6kvej 71, Kvong",
    "sg:city":"Varde",
    "sg:orig_category":"Laminering",
    "sg:phone":"+45 75 25 41 94",
    "sg:postcode":"6800",
    "sg:province":"Danmark",
    "sg:website":"www.texelgarden.dk",
    "wof:name":"Texelgarden Import",
    "wof:placetype":"venue"
},
  "geometry": {"coordinates":[8.482629776,55.6220741272],"type":"Point"}
}