{
  "type": "Feature",
  "properties": {
    "iso:country":"DK",
    "sg:address":"Hesselager 11",
    "sg:city":"Br\u00f8ndby",
    "sg:orig_category":"Non-Classified Establishments",
    "sg:phone":"+45 43 45 66 22",
    "sg:postcode":"2605",
    "sg:province":"Danmark",
    "wof:name":"V\u00e6rkstedet",
    "wof:placetype":"venue"
},
  "geometry": {"coordinates":[12.3979711533,55.6424064636],"type":"Point"}
}