{
  "type": "Feature",
  "properties": {
    "iso:country":"DK",
    "sg:address":"Chr. Schr\u00f8ders Gade 22",
    "sg:city":"Hanstholm",
    "sg:orig_category":"Maskinfabrikker",
    "sg:phone":"+45 97 96 24 99",
    "sg:postcode":"7730",
    "sg:province":"Danmark",
    "wof:name":"Hymaco, Maskinfabrikken",
    "wof:placetype":"venue"
},
  "geometry": {"coordinates":[8.6015138626,57.1189460754],"type":"Point"}
}