{
  "type": "Feature",
  "properties": {
    "addr:full":"Algade 63 Middelfart Danmark 5500",
    "addr:housenumber":"63",
    "addr:postcode":"5500",
    "addr:street":"Algade",
    "iso:country":"DK",
    "sg:address":"Algade 63",
    "sg:city":"Middelfart",
    "sg:orig_category":"Sko",
    "sg:phone":"+45 64 41 03 75",
    "sg:postcode":"5500",
    "sg:province":"Danmark",
    "wof:name":"Gr\u00f8nne Skobutik, Din",
    "wof:placetype":"venue"
},
  "geometry": {"coordinates":[9.7329702377,55.5053100586],"type":"Point"}
}