{
  "type": "Feature",
  "properties": {
    "addr:full":"Labyrinten 29 Klarup Danmark 9270",
    "addr:housenumber":"29",
    "addr:postcode":"9270",
    "addr:street":"Labyrinten",
    "iso:country":"DK",
    "sg:address":"Labyrinten 29",
    "sg:city":"Klarup",
    "sg:orig_category":"Glarmestre og glarmagere",
    "sg:phone":"+45 98 31 87 88",
    "sg:postcode":"9270",
    "sg:province":"Danmark",
    "wof:name":"Klarup Bygningsglas",
    "wof:placetype":"venue"
},
  "geometry": {"coordinates":[10.0520305634,57.0157661438],"type":"Point"}
}