{
  "type": "Feature",
  "properties": {
    "addr:full":"Kantatevej 26 B Herlev Danmark 2730",
    "addr:housenumber":"26 b",
    "addr:postcode":"2730",
    "addr:street":"Kantatevej",
    "iso:country":"DK",
    "sg:address":"Kantatevej 26 B",
    "sg:city":"Herlev",
    "sg:orig_category":"Reproduktioner",
    "sg:phone":"+45 44 94 78 58",
    "sg:postcode":"2730",
    "sg:province":"Danmark",
    "wof:name":"Hansen Grafik ApS, Kaj",
    "wof:placetype":"venue"
},
  "geometry": {"coordinates":[12.4469566345,55.7160186768],"type":"Point"}
}