{
  "type": "Feature",
  "properties": {
    "addr:full":"Fmd: Lis Jensen, Borgergade 45 Stakroge Danmark 7270",
    "addr:housenumber":"45",
    "addr:postcode":"7270",
    "addr:street":"Fmd Lis;Borgergade",
    "iso:country":"DK",
    "sg:address":"Fmd: Lis Jensen, Borgergade 45",
    "sg:city":"Stakroge",
    "sg:orig_category":"Beboerhuse",
    "sg:phone":"+45 73 34 70 60",
    "sg:postcode":"7270",
    "sg:province":"Danmark",
    "wof:name":"Stakroge Beboerhus",
    "wof:placetype":"venue"
},
  "geometry": {"coordinates":[8.848015,55.889935],"type":"Point"}
}