{
  "type": "Feature",
  "properties": {
    "addr:full":"Kongstedvej 28, Dovenr\u00f8d Ruds Vedby Danmark 4291",
    "addr:housenumber":"28",
    "addr:postcode":"4291",
    "addr:street":"Kongstedvej;Dovenrod",
    "iso:country":"DK",
    "sg:address":"Kongstedvej 28, Dovenr\u00f8d",
    "sg:city":"Ruds Vedby",
    "sg:orig_category":"Kursussteder",
    "sg:phone":"+45 58 25 58 70",
    "sg:postcode":"4291",
    "sg:province":"Danmark",
    "sg:website":"www.skabditliv.dk",
    "wof:name":"Skab Dit Liv - Tr\u00e6ningen",
    "wof:placetype":"venue"
},
  "geometry": {"coordinates":[11.3734693527,55.5409049988],"type":"Point"}
}