{
  "type": "Feature",
  "properties": {
    "addr:full":"Jernbanegade 35 Fjerritslev Danmark 9690",
    "addr:housenumber":"35",
    "addr:postcode":"9690",
    "addr:street":"Jernbanegade",
    "iso:country":"DK",
    "sg:address":"Jernbanegade 35",
    "sg:city":"Fjerritslev",
    "sg:orig_category":"Fiskeriudstyr",
    "sg:phone":"+45 98 21 16 31",
    "sg:postcode":"9690",
    "sg:province":"Danmark",
    "wof:name":"Piesens Fiskeriartikler I/S",
    "wof:placetype":"venue"
},
  "geometry": {"coordinates":[9.2587337494,57.0866088867],"type":"Point"}
}