{
  "type": "Feature",
  "properties": {
    "addr:full":"v/ Hugo Svart, Vesterhavsgade 3, Ferring Lemvig Danmark 7620",
    "addr:housenumber":"3",
    "addr:postcode":"7620",
    "addr:street":"Vesterhavsgade;Ferring",
    "iso:country":"DK",
    "sg:address":"v/ Hugo Svart, Vesterhavsgade 3, Ferring",
    "sg:city":"Lemvig",
    "sg:orig_category":"Apoteker og -udsalg",
    "sg:phone":"+45 97 89 51 52",
    "sg:postcode":"7620",
    "sg:province":"Danmark",
    "wof:name":"Ferring H\u00e5ndk\u00f8bsudsalg",
    "wof:placetype":"venue"
},
  "geometry": {"coordinates":[8.3073654175,56.5505104065],"type":"Point"}
}