{
  "type": "Feature",
  "properties": {
    "iso:country":"DK",
    "sg:address":"v/ Lars Andreassen, Grundtvigsvej 14",
    "sg:city":"Helsing\u00f8r",
    "sg:orig_category":"Hobbybetonede foreninger",
    "sg:phone":"+45 49 26 49 28",
    "sg:postcode":"3000",
    "sg:province":"Danmark",
    "sg:website":"www.dcf.dk/lokalafd/helsingor",
    "wof:name":"Dansk Cyklist Forbund, Helsing\u00f8r Afdeling",
    "wof:placetype":"venue"
},
  "geometry": {"coordinates":[12.6133747101,56.0334091187],"type":"Point"}
}