{
  "type": "Feature",
  "properties": {
    "addr:full":"Havnegade 4 Odense C Danmark 5000",
    "addr:housenumber":"4",
    "addr:postcode":"5000",
    "addr:street":"Havnegade",
    "iso:country":"DK",
    "sg:address":"Havnegade 4",
    "sg:city":"Odense C",
    "sg:orig_category":"Diners transportables",
    "sg:phone":"+45 66 14 40 06",
    "sg:postcode":"5000",
    "sg:province":"Danmark",
    "wof:name":"Havnens Gourmet",
    "wof:placetype":"venue"
},
  "geometry": {"coordinates":[10.4085979462,55.4275131226],"type":"Point"}
}