{
  "type": "Feature",
  "properties": {
    "addr:full":"Egemosevej 3 Grevinge Danmark 4571",
    "addr:housenumber":"3",
    "addr:postcode":"4571",
    "addr:street":"Egemosevej",
    "iso:country":"DK",
    "sg:address":"Egemosevej 3",
    "sg:city":"Grevinge",
    "sg:orig_category":"Autoreparation og -service",
    "sg:phone":"+45 59 65 90 73",
    "sg:postcode":"4571",
    "sg:province":"Danmark",
    "wof:name":"Grevinge Autoelektro",
    "wof:placetype":"venue"
},
  "geometry": {"coordinates":[11.5508813858,55.7999992371],"type":"Point"}
}