{
  "type": "Feature",
  "properties": {
    "addr:full":"Holmboes Alle 2 A Horsens Danmark 8700",
    "addr:housenumber":"2 a",
    "addr:postcode":"8700",
    "addr:street":"Holmboes Alle",
    "iso:country":"DK",
    "sg:address":"Holmboes Alle 2 A",
    "sg:city":"Horsens",
    "sg:orig_category":"\u00c3\u02dcvrig fritidsundervisning",
    "sg:phone":"+45 76 25 89 88",
    "sg:postcode":"8700",
    "sg:province":"Danmark",
    "wof:name":"FOF Rosing R\u00e6derske",
    "wof:placetype":"venue"
},
  "geometry": {"coordinates":[9.8477392197,55.8569869995],"type":"Point"}
}