{
  "type": "Feature",
  "properties": {
    "addr:full":"Pr\u00e6stemarken 1 Frederikssund Danmark 3600",
    "addr:housenumber":"1",
    "addr:postcode":"3600",
    "addr:street":"Praestemarken",
    "iso:country":"DK",
    "sg:address":"Pr\u00e6stemarken 1",
    "sg:city":"Frederikssund",
    "sg:orig_category":"Autoreparation og -service",
    "sg:phone":"+45 47 31 79 77",
    "sg:postcode":"3600",
    "sg:province":"Danmark",
    "sg:website":"www.leif-jensen-auto.dk",
    "wof:name":"Jensen, Leif",
    "wof:placetype":"venue"
},
  "geometry": {"coordinates":[12.099357605,55.863571167],"type":"Point"}
}