{
  "type": "Feature",
  "properties": {
    "iso:country":"DK",
    "sg:address":"Vognporten 14",
    "sg:city":"Albertslund",
    "sg:orig_category":"Kollegier",
    "sg:postcode":"2620",
    "sg:province":"Danmark",
    "wof:name":"Danmarks Internationale Kollegium",
    "wof:placetype":"venue"
},
  "geometry": {"coordinates":[12.3561229706,55.657459259],"type":"Point"}
}