{
  "type": "Feature",
  "properties": {
    "iso:country":"DK",
    "sg:address":"Kommunekontoret, Skovsholm 1, H\u00f8rup",
    "sg:city":"Sydals",
    "sg:orig_category":"Dagplejeformidling",
    "sg:phone":"+45 73 11 50 00",
    "sg:postcode":"6470",
    "sg:province":"Danmark",
    "wof:name":"Dagplejeformidlingen",
    "wof:placetype":"venue"
},
  "geometry": {"coordinates":[9.8924627304,54.9105377197],"type":"Point"}
}