{
  "type": "Feature",
  "properties": {
    "addr:full":"Fmd.: Hans J\u00f8rgen Jensen, Maig\u00e5rdsvej 17 Frederikshavn Danmark 9900",
    "addr:housenumber":"17",
    "addr:postcode":"9900",
    "addr:street":"Maigaardsvej",
    "iso:country":"DK",
    "sg:address":"Fmd.: Hans J\u00f8rgen Jensen, Maig\u00e5rdsvej 17",
    "sg:city":"Frederikshavn",
    "sg:orig_category":"\u00c3\u02dcvrige foreninger",
    "sg:phone":"+45 98 42 83 60",
    "sg:postcode":"9900",
    "sg:province":"Danmark",
    "wof:name":"Personlig Friheds V\u00e6rn, Frederikshavn",
    "wof:placetype":"venue"
},
  "geometry": {"coordinates":[10.5362997055,57.4396400452],"type":"Point"}
}