{
  "type": "Feature",
  "properties": {
    "addr:full":"Sdr. Vilstrupvej 26, H\u00f8jrup Mark Fredericia Danmark 7000",
    "addr:housenumber":"26",
    "addr:postcode":"7000",
    "addr:street":"Sdr. Vilstrupvej;Mark",
    "iso:country":"DK",
    "sg:address":"Sdr. Vilstrupvej 26, H\u00f8jrup Mark",
    "sg:city":"Fredericia",
    "sg:orig_category":"Fotografer",
    "sg:phone":"+45 75 51 40 36",
    "sg:postcode":"7000",
    "sg:province":"Danmark",
    "wof:name":"Jochumsen Film, Kurt",
    "wof:placetype":"venue"
},
  "geometry": {"coordinates":[9.7591047287,55.566368103],"type":"Point"}
}