{
  "type": "Feature",
  "properties": {
    "addr:full":"S\u00f8ndergade 41 B Kjellerup Danmark 8620",
    "addr:housenumber":"41 b",
    "addr:postcode":"8620",
    "addr:street":"Sondergade",
    "iso:country":"DK",
    "sg:address":"S\u00f8ndergade 41 B",
    "sg:city":"Kjellerup",
    "sg:orig_category":"Brugskunst",
    "sg:phone":"+45 86 88 35 77",
    "sg:postcode":"8620",
    "sg:province":"Danmark",
    "wof:name":"Form og Farve",
    "wof:placetype":"venue"
},
  "geometry": {"coordinates":[9.4318399429,56.286151886],"type":"Point"}
}