{
  "type": "Feature",
  "properties": {
    "addr:full":"Jegstrupvej 96 B  Hasselager Danmark 8361",
    "addr:housenumber":"96 b",
    "addr:postcode":"8361",
    "addr:street":"Jegstrupvej",
    "iso:country":"DK",
    "sg:address":"Jegstrupvej 96 B ",
    "sg:city":"Hasselager",
    "sg:classifiers":[
        {
            "category":"Retail",
            "subcategory":"Animal Services",
            "type":"Services"
        }
    ],
    "sg:phone":"+45 87 38 25 50",
    "sg:postcode":"8361",
    "sg:province":"Danmark",
    "sg:tags":[
        "breeding"
    ],
    "wof:name":"DLG S\u00c6DEKORNSFABRIK",
    "wof:placetype":"venue"
},
  "geometry": {"coordinates":[10.1113443375,56.1010818481],"type":"Point"}
}