{
  "type": "Feature",
  "properties": {
    "iso:country":"DK",
    "sg:address":"Birkeg\u00e5rdsvej 5, Birk",
    "sg:city":"Herning",
    "sg:classifiers":[
        {
            "category":"Arts & Performance",
            "subcategory":"Festival",
            "type":"Entertainment"
        }
    ],
    "sg:phone":"+45 97 11 67 11",
    "sg:postcode":"7400",
    "sg:province":"Danmark",
    "sg:tags":[
        "tekstilindustri"
    ],
    "sg:website":"www.andersen-stender.dk",
    "wof:name":"Andersen & Stender A/S",
    "wof:placetype":"venue"
},
  "geometry": {"coordinates":[8.9768896103,56.1374168396],"type":"Point"}
}