{
  "type": "Feature",
  "properties": {
    "addr:full":"Pederstrupvej 5, L\u00f8vel Tjele Danmark 8830",
    "addr:housenumber":"5",
    "addr:postcode":"8830",
    "addr:street":"Pederstrupvej;Lovel",
    "iso:country":"DK",
    "sg:address":"Pederstrupvej 5, L\u00f8vel",
    "sg:city":"Tjele",
    "sg:orig_category":"Korn og foderstoffer",
    "sg:phone":"+45 86 69 93 55",
    "sg:postcode":"8830",
    "sg:province":"Danmark",
    "wof:name":"Storm\u00f8llen A/S",
    "wof:placetype":"venue"
},
  "geometry": {"coordinates":[9.6264801025,56.4818611145],"type":"Point"}
}