{
  "type": "Feature",
  "properties": {
    "iso:country":"DK",
    "sg:address":"Tornerosevej 127",
    "sg:city":"Herlev",
    "sg:orig_category":"Skibsmalere",
    "sg:phone":"+45 44 92 94 00",
    "sg:postcode":"2730",
    "sg:province":"Danmark",
    "wof:name":"Jotun Paints",
    "wof:placetype":"venue"
},
  "geometry": {"coordinates":[12.447971344,55.7310447693],"type":"Point"}
}