{
  "type": "Feature",
  "properties": {
    "addr:full":"\u00c5boulevarden 70 \u00c5rhus C Danmark 8000",
    "addr:housenumber":"70",
    "addr:postcode":"8000",
    "addr:street":"Aaboulevarden",
    "iso:country":"DK",
    "sg:address":"\u00c5boulevarden 70",
    "sg:city":"\u00c5rhus C",
    "sg:orig_category":"Farve og tapet",
    "sg:phone":"+45 86 76 11 30",
    "sg:postcode":"8000",
    "sg:province":"Danmark",
    "wof:name":"Interi\u00f8r",
    "wof:placetype":"venue"
},
  "geometry": {"coordinates":[4.717400074,49.7588005066],"type":"Point"}
}