{
  "type": "Feature",
  "properties": {
    "addr:full":"Byst\u00e6vneparken 25 Br\u00f8nsh\u00f8j Danmark 2700",
    "addr:housenumber":"25",
    "addr:postcode":"2700",
    "addr:street":"Bystaevneparken",
    "iso:country":"DK",
    "sg:address":"Byst\u00e6vneparken 25",
    "sg:city":"Br\u00f8nsh\u00f8j",
    "sg:orig_category":"Plejehjem",
    "sg:phone":"+45 38 27 42 90",
    "sg:postcode":"2700",
    "sg:province":"Danmark",
    "wof:name":"Pilehuset, Demenscenter",
    "wof:placetype":"venue"
},
  "geometry": {"coordinates":[-65.6866531372,-23.1981296539],"type":"Point"}
}