{
  "type": "Feature",
  "properties": {
    "addr:full":"Danmarksgade 1, Postboks 507 6701",
    "addr:housenumber":"1;507",
    "addr:postcode":"6701",
    "addr:street":"Danmarksgade",
    "iso:country":"DK",
    "sg:address":"Danmarksgade 1, Postboks 507",
    "sg:classifiers":[
        {
            "category":"Communications",
            "type":"Services"
        }
    ],
    "sg:phone":"+45 75 45 04 00",
    "sg:postcode":"6701",
    "sg:tags":[
        "radio-",
        "og",
        "tv-stationer"
    ],
    "wof:name":"Radio Victor K/S",
    "wof:placetype":"venue"
},
  "geometry": {"coordinates":[8.456905365,55.465221405],"type":"Point"}
}