{
  "type": "Feature",
  "properties": {
    "addr:full":"Kragenakkevej 14 Horslunde Danmark 4913",
    "addr:housenumber":"14",
    "addr:postcode":"4913",
    "addr:street":"Kragenakkevej",
    "iso:country":"DK",
    "sg:address":"Kragenakkevej 14",
    "sg:city":"Horslunde",
    "sg:orig_category":"Murermestre",
    "sg:phone":"+45 54 93 53 79",
    "sg:postcode":"4913",
    "sg:province":"Danmark",
    "wof:name":"Antonsen, Ejner",
    "wof:placetype":"venue"
},
  "geometry": {"coordinates":[11.1879558563,54.9475288391],"type":"Point"}
}