{
  "type": "Feature",
  "properties": {
    "addr:full":"Aaby Centret 2 Aabybro Danmark 9440",
    "addr:housenumber":"2",
    "addr:postcode":"9440",
    "addr:street":"Aaby Centret",
    "iso:country":"DK",
    "sg:address":"Aaby Centret 2",
    "sg:city":"Aabybro",
    "sg:orig_category":"Materialister",
    "sg:phone":"+45 98 24 23 48",
    "sg:postcode":"9440",
    "sg:province":"Danmark",
    "wof:name":"Matas",
    "wof:placetype":"venue"
},
  "geometry": {"coordinates":[9.7341356277,57.1588287354],"type":"Point"}
}