{
  "type": "Feature",
  "properties": {
    "addr:full":"S\u00e6lvig 48 Sams\u00f8 Danmark 8305",
    "addr:housenumber":"48",
    "addr:postcode":"8305",
    "addr:street":"Saelvig",
    "iso:country":"DK",
    "sg:address":"S\u00e6lvig 48",
    "sg:city":"Sams\u00f8",
    "sg:classifiers":[
        {
            "category":"Restaurant",
            "type":"Food & Drink"
        }
    ],
    "sg:phone":"+45 86 59 25 00",
    "sg:postcode":"8305",
    "sg:province":"Danmark",
    "wof:name":"Caf\u00e8 Perlen",
    "wof:placetype":"venue"
},
  "geometry": {"coordinates":[-107.9639587402,38.1021232605],"type":"Point"}
}