{
  "type": "Feature",
  "properties": {
    "addr:full":"Florasvej 2 A Glostrup Danmark 2600",
    "addr:housenumber":"2 a",
    "addr:postcode":"2600",
    "addr:street":"Florasvej",
    "iso:country":"DK",
    "sg:address":"Florasvej 2 A",
    "sg:city":"Glostrup",
    "sg:orig_category":"Skolefritidsordninger",
    "sg:phone":"+45 43 45 10 99",
    "sg:postcode":"2600",
    "sg:province":"Danmark",
    "wof:name":"Villaen, SFO",
    "wof:placetype":"venue"
},
  "geometry": {"coordinates":[12.4074897766,55.6654548645],"type":"Point"}
}