{
  "type": "Feature",
  "properties": {
    "addr:full":"Rytterstaldstr\u00e6de 3 Slagelse Danmark 4200",
    "addr:housenumber":"3",
    "addr:postcode":"4200",
    "addr:street":"Rytterstaldstraede",
    "iso:country":"DK",
    "sg:address":"Rytterstaldstr\u00e6de 3",
    "sg:city":"Slagelse",
    "sg:classifiers":[
        {
            "category":"Communications",
            "type":"Services"
        }
    ],
    "sg:phone":"+45 58 53 53 88",
    "sg:postcode":"4200",
    "sg:province":"Danmark",
    "sg:tags":[
        "radio-",
        "og",
        "tv-stationer"
    ],
    "wof:name":"TvDanmark Vestsj\u00e6lland",
    "wof:placetype":"venue"
},
  "geometry": {"coordinates":[11.3541498184,55.400592804],"type":"Point"}
}