{
  "type": "Feature",
  "properties": {
    "addr:full":"Torvet 5 Maribo Danmark 4930",
    "addr:housenumber":"5",
    "addr:postcode":"4930",
    "addr:street":"Torvet",
    "iso:country":"DK",
    "sg:address":"Torvet 5",
    "sg:city":"Maribo",
    "sg:orig_category":"Advokater",
    "sg:phone":"+45 54 78 11 00",
    "sg:postcode":"4930",
    "sg:province":"Danmark",
    "sg:website":"www.mariboadvokaten.dk",
    "wof:name":"Advokaterne Simonsen - S\u00f8rensen og S\u00f8ndergaard",
    "wof:placetype":"venue"
},
  "geometry": {"coordinates":[11.5017080307,54.7746887207],"type":"Point"}
}