{
  "type": "Feature",
  "properties": {
    "addr:full":"Skovsvinget 17 A Kongens Lyngby Danmark 2800",
    "addr:housenumber":"17 a",
    "addr:postcode":"2800",
    "addr:street":"Skovsvinget",
    "iso:country":"DK",
    "sg:address":"Skovsvinget 17 A",
    "sg:city":"Kongens Lyngby",
    "sg:orig_category":"Ejendomshandel",
    "sg:phone":"+45 45 88 37 17",
    "sg:postcode":"2800",
    "sg:province":"Danmark",
    "wof:name":"Petersen, Garfiel",
    "wof:placetype":"venue"
},
  "geometry": {"coordinates":[12.5392875671,55.7904434204],"type":"Point"}
}