{
  "type": "Feature",
  "properties": {
    "addr:full":"Fmd.: Bent H. Sielemann, Haderslevvej 149 Kolding Danmark 6000",
    "addr:housenumber":"149",
    "addr:postcode":"6000",
    "addr:street":"Haderslevvej",
    "iso:country":"DK",
    "sg:address":"Fmd.: Bent H. Sielemann, Haderslevvej 149",
    "sg:city":"Kolding",
    "sg:orig_category":"Soldaterforeninger",
    "sg:phone":"+45 75 50 53 80",
    "sg:postcode":"6000",
    "sg:province":"Danmark",
    "wof:name":"De danske Forsvarsbr\u00f8dre for Kolding og Omegn",
    "wof:placetype":"venue"
},
  "geometry": {"coordinates":[9.4733953476,55.4863586426],"type":"Point"}
}