{
  "type": "Feature",
  "properties": {
    "iso:country":"DK",
    "sg:address":"Hovedgaden 10, N\u00e6sbjerg",
    "sg:city":"Varde",
    "sg:orig_category":"Autoreparation og -service",
    "sg:phone":"+45 75 26 74 10",
    "sg:postcode":"6800",
    "sg:province":"Danmark",
    "wof:name":"N\u00e6sbjerg Auto",
    "wof:placetype":"venue"
},
  "geometry": {"coordinates":[8.482629776,55.6220741272],"type":"Point"}
}