{
  "type": "Feature",
  "properties": {
    "iso:country":"DK",
    "sg:address":"Hovedgaden 23 - 25",
    "sg:city":"Snedsted",
    "sg:orig_category":"Servicestationer",
    "sg:phone":"+45 97 93 40 30",
    "sg:postcode":"7752",
    "sg:province":"Danmark",
    "wof:name":"Q8 Service",
    "wof:placetype":"venue"
},
  "geometry": {"coordinates":[8.5305328369,56.8925590515],"type":"Point"}
}