{
  "type": "Feature",
  "properties": {
    "addr:full":"Amerikavej 3 a, 2.th. K\u00f8benhavn Danmark 1756",
    "addr:housenumber":"3 a 2.th;1756",
    "addr:street":"Amerikavej",
    "iso:country":"DK",
    "sg:address":"Amerikavej 3 a, 2.th.",
    "sg:city":"K\u00f8benhavn",
    "sg:orig_category":"Designere",
    "sg:phone":"+45 33 26 27 44",
    "sg:postcode":"1756",
    "sg:province":"Danmark",
    "wof:name":"Ladeby-Designstue",
    "wof:placetype":"venue"
},
  "geometry": {"coordinates":[12.5423002243,55.6689987183],"type":"Point"}
}