{
  "type": "Feature",
  "properties": {
    "iso:country":"DK",
    "sg:address":"Fmd.: Anna Kristensen, Falkevej 9",
    "sg:city":"Haderup",
    "sg:orig_category":"\u00c3\u02dcvrig fritidsundervisning",
    "sg:phone":"+45 97 45 24 07",
    "sg:postcode":"7540",
    "sg:province":"Danmark",
    "wof:name":"Haderup Husholdningsforening",
    "wof:placetype":"venue"
},
  "geometry": {"coordinates":[8.9933700562,56.3879814148],"type":"Point"}
}