{
  "type": "Feature",
  "properties": {
    "addr:full":"Br\u00f8deskovvej 39, Nr. Herlev Hiller\u00f8d Danmark 3400",
    "addr:housenumber":"39",
    "addr:postcode":"3400",
    "addr:street":"Brodeskovvej",
    "iso:country":"DK",
    "sg:address":"Br\u00f8deskovvej 39, Nr. Herlev",
    "sg:city":"Hiller\u00f8d",
    "sg:orig_category":"Kommunale folkeskoler",
    "sg:phone":"+45 48 26 65 93",
    "sg:postcode":"3400",
    "sg:province":"Danmark",
    "sg:website":"www.nerherlevskole.dk",
    "wof:name":"Br\u00f8deskov Skolen",
    "wof:placetype":"venue"
},
  "geometry": {"coordinates":[12.3056097031,55.9288215637],"type":"Point"}
}