{
  "type": "Feature",
  "properties": {
    "addr:full":"Fredensgade 74 B Skjern Danmark 6900",
    "addr:housenumber":"74 b",
    "addr:postcode":"6900",
    "addr:street":"Fredensgade",
    "iso:country":"DK",
    "sg:address":"Fredensgade 74 B",
    "sg:city":"Skjern",
    "sg:orig_category":"Kontormaskiner",
    "sg:phone":"+45 97 35 37 10",
    "sg:postcode":"6900",
    "sg:province":"Danmark",
    "wof:name":"Kontorcenter West",
    "wof:placetype":"venue"
},
  "geometry": {"coordinates":[8.5020503998,55.951259613],"type":"Point"}
}