{
  "type": "Feature",
  "properties": {
    "iso:country":"DK",
    "sg:address":"Vester Voldgade 123, 3.",
    "sg:city":"K\u00f8benhavn",
    "sg:orig_category":"Statslige direktorater og styrelser",
    "sg:phone":"+45 33 92 72 30",
    "sg:postcode":"1552",
    "sg:province":"Danmark",
    "wof:name":"Kommissarius ved Statens Ekspropriationer p\u00e5 \u00d8erne",
    "wof:placetype":"venue"
},
  "geometry": {"coordinates":[12.570400238,55.6759986877],"type":"Point"}
}