{
  "type": "Feature",
  "properties": {
    "iso:country":"DK",
    "sg:address":"Amagerbrogade 206",
    "sg:city":"K\u00f8benhavn S",
    "sg:classifiers":[
        {
            "category":"Home & Garden",
            "subcategory":"Home Furnishings",
            "type":"Retail Goods"
        }
    ],
    "sg:phone":"+45 32 55 86 21",
    "sg:postcode":"2300",
    "sg:province":"Danmark",
    "sg:tags":[
        "gardiner"
    ],
    "wof:name":"Magasin Oxford",
    "wof:placetype":"venue"
},
  "geometry": {"coordinates":[-78.1299133301,36.7267417908],"type":"Point"}
}