{
  "type": "Feature",
  "properties": {
    "addr:full":"Mors\u00f8gade 3 Esbjerg Danmark 6700",
    "addr:housenumber":"3",
    "addr:postcode":"6700",
    "addr:street":"Morsogade",
    "iso:country":"DK",
    "sg:address":"Mors\u00f8gade 3",
    "sg:city":"Esbjerg",
    "sg:orig_category":"Karrosserifabrikker",
    "sg:phone":"+45 75 12 32 66",
    "sg:postcode":"6700",
    "sg:province":"Danmark",
    "wof:name":"HL K\u00f8levogne Transportmateriel A/S",
    "wof:placetype":"venue"
},
  "geometry": {"coordinates":[8.4314718246,55.476184845],"type":"Point"}
}