{
  "type": "Feature",
  "properties": {
    "addr:full":"S\u00f8by Strandvej 31, S\u00f8by Odder Danmark 8300",
    "addr:housenumber":"31",
    "addr:postcode":"8300",
    "addr:street":"Soby Strandvej;Soby",
    "iso:country":"DK",
    "sg:address":"S\u00f8by Strandvej 31, S\u00f8by",
    "sg:city":"Odder",
    "sg:orig_category":"Malermestre",
    "sg:phone":"+45 86 55 17 55",
    "sg:postcode":"8300",
    "sg:province":"Danmark",
    "wof:name":"Alh\u00f8j, Ole",
    "wof:placetype":"venue"
},
  "geometry": {"coordinates":[10.1497612,55.9733161926],"type":"Point"}
}