{
  "type": "Feature",
  "properties": {
    "iso:country":"DK",
    "sg:address":"Vandv\u00e6rksvej 3, Nr. S\u00f8by",
    "sg:city":"\u00c5rslev",
    "sg:orig_category":"Antikviteter",
    "sg:phone":"+45 40 15 73 72",
    "sg:postcode":"5792",
    "sg:province":"Danmark",
    "wof:name":"Berthelsen, Jens-Herluf",
    "wof:placetype":"venue"
},
  "geometry": {"coordinates":[166.9221496582,-0.5282999873],"type":"Point"}
}