{
  "type": "Feature",
  "properties": {
    "addr:full":"Fynsgade 23 Ikast Danmark 7430",
    "addr:housenumber":"23",
    "addr:postcode":"7430",
    "addr:street":"Fynsgade",
    "iso:country":"DK",
    "sg:address":"Fynsgade 23",
    "sg:city":"Ikast",
    "sg:orig_category":"Vinduespolering",
    "sg:phone":"+45 97 15 12 17",
    "sg:postcode":"7430",
    "sg:province":"Danmark",
    "wof:name":"Bille's Vinduespolering",
    "wof:placetype":"venue"
},
  "geometry": {"coordinates":[9.1515226364,56.1374397278],"type":"Point"}
}