{
  "type": "Feature",
  "properties": {
    "addr:full":"Teknik og Milj\u00f8, Vangen 1-3 Nyk\u00f8bing Danmark 4500",
    "addr:housenumber":"1-3",
    "addr:postcode":"4500",
    "addr:street":"Vangen",
    "iso:country":"DK",
    "sg:address":"Teknik og Milj\u00f8, Vangen 1-3",
    "sg:city":"Nyk\u00f8bing",
    "sg:orig_category":"Redningsberedskab",
    "sg:phone":"+45 59 98 01 40",
    "sg:postcode":"4500",
    "sg:province":"Danmark",
    "wof:name":"Redningsberedskabet i Nyk\u00f8bing-R\u00f8rvig Kommune",
    "wof:placetype":"venue"
},
  "geometry": {"coordinates":[16.0969600677,78.3159866333],"type":"Point"}
}