{
  "type": "Feature",
  "properties": {
    "addr:full":"V\u00f8lundsgade 1 K\u00f8benhavn N Danmark 2200",
    "addr:housenumber":"1",
    "addr:postcode":"2200",
    "addr:street":"Volundsgade;N Danmark",
    "iso:country":"DK",
    "sg:address":"V\u00f8lundsgade 1",
    "sg:city":"K\u00f8benhavn N",
    "sg:orig_category":"Pizzeriaer",
    "sg:phone":"+45 35 83 99 49",
    "sg:postcode":"2200",
    "sg:province":"Danmark",
    "wof:name":"Mama Mia Pizza & Grill",
    "wof:placetype":"venue"
},
  "geometry": {"coordinates":[12.5484800339,55.7002563477],"type":"Point"}
}