{
  "type": "Feature",
  "properties": {
    "addr:full":"Adelgade 78, 2. Skanderborg Danmark 8660",
    "addr:housenumber":"78 2",
    "addr:postcode":"8660",
    "addr:street":"Adelgade",
    "iso:country":"DK",
    "sg:address":"Adelgade 78, 2.",
    "sg:city":"Skanderborg",
    "sg:orig_category":"Tandteknikere, Kliniske",
    "sg:phone":"+45 86 51 15 10",
    "sg:postcode":"8660",
    "sg:province":"Danmark",
    "wof:name":"Lenith, Tove",
    "wof:placetype":"venue"
},
  "geometry": {"coordinates":[9.9320688248,56.0341110229],"type":"Point"}
}