{
  "type": "Feature",
  "properties": {
    "addr:full":"Nytorv 24 Aalborg Danmark 9000",
    "addr:housenumber":"24",
    "addr:postcode":"9000",
    "addr:street":"Nytorv",
    "iso:country":"DK",
    "sg:address":"Nytorv 24",
    "sg:city":"Aalborg",
    "sg:orig_category":"Engros handel",
    "sg:phone":"+45 98 16 62 11",
    "sg:postcode":"9000",
    "sg:province":"Danmark",
    "wof:name":"Red/Green A/S",
    "wof:placetype":"venue"
},
  "geometry": {"coordinates":[9.9263677597,57.0473709106],"type":"Point"}
}