{
  "type": "Feature",
  "properties": {
    "addr:full":"H\u00f8gelsbjerg 56 Aabenraa Danmark 6200",
    "addr:housenumber":"56",
    "addr:postcode":"6200",
    "addr:street":"Hogelsbjerg",
    "iso:country":"DK",
    "sg:address":"H\u00f8gelsbjerg 56",
    "sg:city":"Aabenraa",
    "sg:orig_category":"Virksomhedskonsulenter",
    "sg:phone":"+45 74 62 77 80",
    "sg:postcode":"6200",
    "sg:province":"Danmark",
    "wof:name":"Hove Consult",
    "wof:placetype":"venue"
},
  "geometry": {"coordinates":[9.3879976273,55.0565185547],"type":"Point"}
}