{
  "type": "Feature",
  "properties": {
    "addr:full":"\u00c5rl\u00f8sevej 1, Terslev Haslev Danmark 4690",
    "addr:housenumber":"1",
    "addr:postcode":"4690",
    "addr:street":"Aarlosevej;Terslev",
    "iso:country":"DK",
    "sg:address":"\u00c5rl\u00f8sevej 1, Terslev",
    "sg:city":"Haslev",
    "sg:orig_category":"Murermestre",
    "sg:phone":"+45 56 38 10 19",
    "sg:postcode":"4690",
    "sg:province":"Danmark",
    "sg:website":"www.murerfirmaet-nissen.dk",
    "wof:name":"Det Lille Murerfirma",
    "wof:placetype":"venue"
},
  "geometry": {"coordinates":[11.9678049088,55.3230895996],"type":"Point"}
}