{
  "type": "Feature",
  "properties": {
    "iso:country":"DK",
    "sg:address":"Solvej 4",
    "sg:city":"Grindsted",
    "sg:orig_category":"Erhvervslokaler, Udlejning af",
    "sg:phone":"+45 75 32 40 15",
    "sg:postcode":"7200",
    "sg:province":"Danmark",
    "wof:name":"Christensen, Eva",
    "wof:placetype":"venue"
},
  "geometry": {"coordinates":[8.9310045242,55.7559013367],"type":"Point"}
}