{
  "type": "Feature",
  "properties": {
    "addr:full":"Bredegade 44 Slagelse Danmark 4200",
    "addr:housenumber":"44",
    "addr:postcode":"4200",
    "addr:street":"Bredegade",
    "iso:country":"DK",
    "sg:address":"Bredegade 44",
    "sg:city":"Slagelse",
    "sg:orig_category":"Pizzeriaer",
    "sg:phone":"+45 58 50 13 31",
    "sg:postcode":"4200",
    "sg:province":"Danmark",
    "wof:name":"Piccola Napoli",
    "wof:placetype":"venue"
},
  "geometry": {"coordinates":[11.3486948013,55.4013137817],"type":"Point"}
}