{
  "type": "Feature",
  "properties": {
    "iso:country":"DK",
    "sg:address":"\u00d8resundsvej 12",
    "sg:city":"Esbjerg N",
    "sg:orig_category":"El-en gros",
    "sg:phone":"+45 76 14 17 00",
    "sg:postcode":"6715",
    "sg:province":"Danmark",
    "wof:name":"Solar A/S",
    "wof:placetype":"venue"
},
  "geometry": {"coordinates":[8.4740409851,55.5105628967],"type":"Point"}
}