{
  "type": "Feature",
  "properties": {
    "addr:full":"Jenningvej 7, Friskmark Gram Danmark 6510",
    "addr:housenumber":"7",
    "addr:postcode":"6510",
    "addr:street":"Jenningvej",
    "iso:country":"DK",
    "sg:address":"Jenningvej 7, Friskmark",
    "sg:city":"Gram",
    "sg:orig_category":"Isolering",
    "sg:phone":"+45 74 82 24 16",
    "sg:postcode":"6510",
    "sg:province":"Danmark",
    "wof:name":"Gram Isolering",
    "wof:placetype":"venue"
},
  "geometry": {"coordinates":[9.0481977463,55.2877807617],"type":"Point"}
}