{
  "type": "Feature",
  "properties": {
    "addr:full":"Hundige Storcenter 2 A Greve Danmark 2670",
    "addr:housenumber":"2 a",
    "addr:postcode":"2670",
    "addr:street":"Storcenter",
    "iso:country":"DK",
    "sg:address":"Hundige Storcenter 2 A",
    "sg:city":"Greve",
    "sg:orig_category":"Advokater",
    "sg:phone":"+45 43 90 73 23",
    "sg:postcode":"2670",
    "sg:province":"Danmark",
    "wof:name":"Kandler, Advokatfirmaet Lennart",
    "wof:placetype":"venue"
},
  "geometry": {"coordinates":[12.3270778656,55.5990715027],"type":"Point"}
}