{
  "type": "Feature",
  "properties": {
    "addr:full":"Engvej 12 Skals Danmark 8832",
    "addr:housenumber":"12",
    "addr:postcode":"8832",
    "addr:street":"Engvej",
    "iso:country":"DK",
    "sg:address":"Engvej 12",
    "sg:city":"Skals",
    "sg:orig_category":"Dag- og distriktsblade",
    "sg:phone":"+45 86 69 45 00",
    "sg:postcode":"8832",
    "sg:province":"Danmark",
    "wof:name":"Gedsted Avis - Ugeavisen",
    "wof:placetype":"venue"
},
  "geometry": {"coordinates":[9.401432991,56.5574226379],"type":"Point"}
}