{
  "type": "Feature",
  "properties": {
    "iso:country":"DK",
    "sg:address":"Fjordparken 1",
    "sg:city":"Nyborg",
    "sg:orig_category":"Oplysningsforbund",
    "sg:phone":"+45 65 31 61 91",
    "sg:postcode":"5800",
    "sg:province":"Danmark",
    "wof:name":"L.O.F. Nyborg Fritidsskole",
    "wof:placetype":"venue"
},
  "geometry": {"coordinates":[10.7746286392,55.3036727905],"type":"Point"}
}