{
  "type": "Feature",
  "properties": {
    "addr:full":"S\u00f8vejen 9, Herrup Vinderup Danmark 7830",
    "addr:housenumber":"9",
    "addr:postcode":"7830",
    "addr:street":"Sovejen;Herrup",
    "iso:country":"DK",
    "sg:address":"S\u00f8vejen 9, Herrup",
    "sg:city":"Vinderup",
    "sg:orig_category":"Autoreparation og -service",
    "sg:phone":"+45 97 45 22 00",
    "sg:postcode":"7830",
    "sg:province":"Danmark",
    "wof:name":"Herrup Auto",
    "wof:placetype":"venue"
},
  "geometry": {"coordinates":[8.7796897888,56.482635498],"type":"Point"}
}