{
  "type": "Feature",
  "properties": {
    "addr:full":"Bredgade 67 N\u00f8rager Danmark 9610",
    "addr:housenumber":"67",
    "addr:postcode":"9610",
    "addr:street":"Bredgade",
    "iso:country":"DK",
    "sg:address":"Bredgade 67",
    "sg:city":"N\u00f8rager",
    "sg:orig_category":"Mejerier",
    "sg:phone":"+45 96 72 26 00",
    "sg:postcode":"9610",
    "sg:province":"Danmark",
    "wof:name":"N\u00f8rager Mejeri A/S",
    "wof:placetype":"venue"
},
  "geometry": {"coordinates":[9.6190252304,56.7122612],"type":"Point"}
}