{
  "type": "Feature",
  "properties": {
    "addr:full":"Pr\u00e6stbrovej 251 Erslev Danmark 7950",
    "addr:housenumber":"251",
    "addr:postcode":"7950",
    "addr:street":"Praestbrovej",
    "iso:country":"DK",
    "sg:address":"Pr\u00e6stbrovej 251",
    "sg:city":"Erslev",
    "sg:orig_category":"EDB - udstyr",
    "sg:phone":"+45 97 74 14 59",
    "sg:postcode":"7950",
    "sg:province":"Danmark",
    "wof:name":"Data Mors",
    "wof:placetype":"venue"
},
  "geometry": {"coordinates":[8.7255964279,56.8345718384],"type":"Point"}
}