{
  "type": "Feature",
  "properties": {
    "iso:country":"DK",
    "sg:address":"Valdemarsgade 35",
    "sg:city":"\u00c5rhus C",
    "sg:orig_category":"Revisorer",
    "sg:phone":"+45 86 19 96 66",
    "sg:postcode":"8000",
    "sg:province":"Danmark",
    "wof:name":"Castelli, Jonna",
    "wof:placetype":"venue"
},
  "geometry": {"coordinates":[10.1974544525,56.1504402161],"type":"Point"}
}