{
  "type": "Feature",
  "properties": {
    "iso:country":"DK",
    "sg:address":"Lundvej 7",
    "sg:city":"Varde",
    "sg:orig_category":"Vinduer",
    "sg:phone":"+45 75 25 98 88",
    "sg:postcode":"6800",
    "sg:province":"Danmark",
    "sg:website":"www.nl-vinduer.dk",
    "wof:name":"NL Vinduer og D\u00f8re",
    "wof:placetype":"venue"
},
  "geometry": {"coordinates":[8.4858560562,55.6229972839],"type":"Point"}
}