{
  "type": "Feature",
  "properties": {
    "addr:full":"Hadbjergvej 12 Hadsten Danmark 8370",
    "addr:housenumber":"12",
    "addr:postcode":"8370",
    "addr:street":"Hadbjergvej",
    "iso:country":"DK",
    "sg:address":"Hadbjergvej 12",
    "sg:city":"Hadsten",
    "sg:orig_category":"Skolefritidsordninger",
    "sg:phone":"+45 86 98 22 40",
    "sg:postcode":"8370",
    "sg:province":"Danmark",
    "wof:name":"Skolefritidsordningen ved Hadsten Skole",
    "wof:placetype":"venue"
},
  "geometry": {"coordinates":[10.0564155579,56.3343925476],"type":"Point"}
}