{
  "type": "Feature",
  "properties": {
    "addr:full":"Spurvestien 7 Haderslev Danmark 6100",
    "addr:housenumber":"7",
    "addr:postcode":"6100",
    "addr:street":"Spurvestien",
    "iso:country":"DK",
    "sg:address":"Spurvestien 7",
    "sg:city":"Haderslev",
    "sg:orig_category":"Revisorer",
    "sg:phone":"+45 74 52 63 49",
    "sg:postcode":"6100",
    "sg:province":"Danmark",
    "wof:name":"B\u00f8tker, Revisionsfirmaet Thorkild",
    "wof:placetype":"venue"
},
  "geometry": {"coordinates":[9.4678459167,55.2575454712],"type":"Point"}
}