{
  "type": "Feature",
  "properties": {
    "iso:country":"DK",
    "sg:address":"St\u00e6remosen 43",
    "sg:city":"Gilleleje",
    "sg:orig_category":"Snedkermestre",
    "sg:phone":"+45 48 30 15 85",
    "sg:postcode":"3250",
    "sg:province":"Danmark",
    "wof:name":"Snedker- og T\u00f8mrerfirma Lars Petersen",
    "wof:placetype":"venue"
},
  "geometry": {"coordinates":[12.3236112595,56.1118965149],"type":"Point"}
}