{
  "type": "Feature",
  "properties": {
    "addr:full":"Adelgade 27 Skanderborg Danmark 8660",
    "addr:housenumber":"27",
    "addr:postcode":"8660",
    "addr:street":"Adelgade",
    "iso:country":"DK",
    "sg:address":"Adelgade 27",
    "sg:city":"Skanderborg",
    "sg:orig_category":"Apoteker og -udsalg",
    "sg:phone":"+45 86 52 03 11",
    "sg:postcode":"8660",
    "sg:province":"Danmark",
    "wof:name":"Skanderborg Apotek",
    "wof:placetype":"venue"
},
  "geometry": {"coordinates":[9.9331407547,56.0309104919],"type":"Point"}
}