{
  "type": "Feature",
  "properties": {
    "iso:country":"DK",
    "sg:address":"Teknikerbyen 38 ",
    "sg:city":"Virum",
    "sg:classifiers":[
        {
            "category":"Wholesale",
            "subcategory":"Drugs",
            "type":"Manufacturing & Wholesale Goods"
        }
    ],
    "sg:phone":"+45 45 95 06 00",
    "sg:postcode":"2830",
    "sg:province":"Danmark",
    "sg:tags":[
        "chemical",
        "pharmaceutical"
    ],
    "wof:name":"CIBA SPECIALTY CHEMICALS DENMARK A/S",
    "wof:placetype":"venue"
},
  "geometry": {"coordinates":[12.4992351532,55.8010139465],"type":"Point"}
}