{
  "type": "Feature",
  "properties": {
    "addr:full":"Landmandsgade 34, Nr. Kongerslev Kongerslev Danmark 9293",
    "addr:housenumber":"34",
    "addr:postcode":"9293",
    "addr:street":"Landmandsgade",
    "iso:country":"DK",
    "sg:address":"Landmandsgade 34, Nr. Kongerslev",
    "sg:city":"Kongerslev",
    "sg:orig_category":"Kommunale folkeskoler",
    "sg:phone":"+45 98 33 13 43",
    "sg:postcode":"9293",
    "sg:province":"Danmark",
    "wof:name":"Nr. Kongerslev Skole",
    "wof:placetype":"venue"
},
  "geometry": {"coordinates":[10.1150007248,56.8851165771],"type":"Point"}
}