{
  "type": "Feature",
  "properties": {
    "iso:country":"DK",
    "sg:address":"Skolegade 41",
    "sg:city":"Esbjerg",
    "sg:classifiers":[
        {
            "category":"Banks & Credit Unions",
            "subcategory":"Bank",
            "type":"Services"
        }
    ],
    "sg:phone":"+45 75 45 98 88",
    "sg:postcode":"6700",
    "sg:province":"Danmark",
    "sg:tags":[
        "banker"
    ],
    "sg:website":"www.skjern.dk",
    "wof:name":"Skjern Bank, Aktieselskabet",
    "wof:placetype":"venue"
},
  "geometry": {"coordinates":[8.451187,55.467052],"type":"Point"}
}