{
  "type": "Feature",
  "properties": {
    "addr:full":"Stendyssevej 1 B, Vallekilde H\u00f8rve Danmark 4534",
    "addr:housenumber":"1 b",
    "addr:postcode":"4534",
    "addr:street":"Stendyssevej",
    "iso:country":"DK",
    "sg:address":"Stendyssevej 1 B, Vallekilde",
    "sg:city":"H\u00f8rve",
    "sg:orig_category":"Gaveartikler",
    "sg:phone":"+45 59 26 87 97",
    "sg:postcode":"4534",
    "sg:province":"Danmark",
    "wof:name":"Vaikuntha",
    "wof:placetype":"venue"
},
  "geometry": {"coordinates":[11.4255342484,55.7444572449],"type":"Point"}
}