{
  "type": "Feature",
  "properties": {
    "iso:country":"DK",
    "sg:address":"Havnegade 35",
    "sg:city":"Vejle",
    "sg:orig_category":"Skilte",
    "sg:phone":"+45 75 83 02 37",
    "sg:postcode":"7100",
    "sg:province":"Danmark",
    "wof:name":"Bysted, Vagn Kristian",
    "wof:placetype":"venue"
},
  "geometry": {"coordinates":[9.5407934189,55.707195282],"type":"Point"}
}