{
  "type": "Feature",
  "properties": {
    "addr:full":"Kongevejen 242 Virum Danmark 2830",
    "addr:housenumber":"242",
    "addr:postcode":"2830",
    "addr:street":"Kongevejen",
    "iso:country":"DK",
    "sg:address":"Kongevejen 242",
    "sg:city":"Virum",
    "sg:orig_category":"Servicestationer",
    "sg:phone":"+45 45 85 63 27",
    "sg:postcode":"2830",
    "sg:province":"Danmark",
    "wof:name":"Hydro Texaco - Virum",
    "wof:placetype":"venue"
},
  "geometry": {"coordinates":[12.4824132919,55.7968292236],"type":"Point"}
}