{
  "type": "Feature",
  "properties": {
    "iso:country":"DK",
    "sg:address":"Flynders\u00f8vej 12, Estvad",
    "sg:city":"Skive",
    "sg:orig_category":"Tyverisikring",
    "sg:phone":"+45 97 51 08 01",
    "sg:postcode":"7800",
    "sg:province":"Danmark",
    "wof:name":"L\u00e5s & Sl\u00e5 Tyverisikring",
    "wof:placetype":"venue"
},
  "geometry": {"coordinates":[9.0320358276,56.5666427612],"type":"Point"}
}