{
  "type": "Feature",
  "properties": {
    "addr:full":"Vejlbjergvej 8 Risskov Danmark 8240",
    "addr:housenumber":"8",
    "addr:postcode":"8240",
    "addr:street":"Vejlbjergvej",
    "iso:country":"DK",
    "sg:address":"Vejlbjergvej 8",
    "sg:city":"Risskov",
    "sg:orig_category":"Bogtrykkerier",
    "sg:phone":"+45 86 17 47 40",
    "sg:postcode":"8240",
    "sg:province":"Danmark",
    "wof:name":"PP Tryk & Papir",
    "wof:placetype":"venue"
},
  "geometry": {"coordinates":[10.2336826324,56.2072944641],"type":"Point"}
}