{
  "type": "Feature",
  "properties": {
    "addr:full":"Fiskerihavnsgade 23 Esbjerg Danmark 6700",
    "addr:housenumber":"23",
    "addr:postcode":"6700",
    "addr:street":"Fiskerihavnsgade",
    "iso:country":"DK",
    "sg:address":"Fiskerihavnsgade 23",
    "sg:city":"Esbjerg",
    "sg:orig_category":"Skoler",
    "sg:phone":"+45 75 13 14 88",
    "sg:postcode":"6700",
    "sg:province":"Danmark",
    "wof:name":"Havneskolen",
    "wof:placetype":"venue"
},
  "geometry": {"coordinates":[8.4250850677,55.4759483337],"type":"Point"}
}