{
  "type": "Feature",
  "properties": {
    "addr:full":"R\u00f8nbjerghage 2, N\u00f8rlem Lemvig Danmark 7620",
    "addr:housenumber":"2",
    "addr:postcode":"7620",
    "addr:street":"Ronbjerghage",
    "iso:country":"DK",
    "sg:address":"R\u00f8nbjerghage 2, N\u00f8rlem",
    "sg:city":"Lemvig",
    "sg:orig_category":"Fodterapeuter",
    "sg:phone":"+45 21 84 43 74",
    "sg:postcode":"7620",
    "sg:province":"Danmark",
    "wof:name":"Hansen, Line Heine",
    "wof:placetype":"venue"
},
  "geometry": {"coordinates":[8.3073654175,56.5505104065],"type":"Point"}
}