{
  "type": "Feature",
  "properties": {
    "addr:full":"N\u00f8rre \u00c5strupvej 3 Glejbjerg Danmark 6752",
    "addr:housenumber":"3",
    "addr:postcode":"6752",
    "addr:street":"Aastrupvej",
    "iso:country":"DK",
    "sg:address":"N\u00f8rre \u00c5strupvej 3",
    "sg:city":"Glejbjerg",
    "sg:orig_category":"Murermestre",
    "sg:phone":"+45 75 19 85 23",
    "sg:postcode":"6752",
    "sg:province":"Danmark",
    "wof:name":"Mortensen, Jan Qvist",
    "wof:placetype":"venue"
},
  "geometry": {"coordinates":[8.8449859619,55.5814590454],"type":"Point"}
}