{
  "type": "Feature",
  "properties": {
    "addr:full":"Fiskerikajerne 22 Grenaa Danmark 8500",
    "addr:housenumber":"22",
    "addr:postcode":"8500",
    "addr:street":"Fiskerikajerne",
    "iso:country":"DK",
    "sg:address":"Fiskerikajerne 22",
    "sg:city":"Grenaa",
    "sg:orig_category":"Redningskorps",
    "sg:phone":"+45 86 32 39 55",
    "sg:postcode":"8500",
    "sg:province":"Danmark",
    "wof:name":"Redningsstationen Grenaa Havn",
    "wof:placetype":"venue"
},
  "geometry": {"coordinates":[10.9252595901,56.4090995789],"type":"Point"}
}