{
  "type": "Feature",
  "properties": {
    "addr:full":"Strandvejen 407 Asaa Danmark 9340",
    "addr:housenumber":"407",
    "addr:postcode":"9340",
    "addr:street":"Strandvejen",
    "iso:country":"DK",
    "sg:address":"Strandvejen 407",
    "sg:city":"Asaa",
    "sg:orig_category":"Apoteker og -udsalg",
    "sg:phone":"+45 98 85 14 26",
    "sg:postcode":"9340",
    "sg:province":"Danmark",
    "wof:name":"H\u00e5ndk\u00f8bsudsalg, Asaa",
    "wof:placetype":"venue"
},
  "geometry": {"coordinates":[10.4030818939,57.1478347778],"type":"Point"}
}