{
  "type": "Feature",
  "properties": {
    "addr:full":"Lind\u00f8alleen 49 Munkebo Danmark 5330",
    "addr:housenumber":"49",
    "addr:postcode":"5330",
    "addr:street":"Lindoalleen",
    "iso:country":"DK",
    "sg:address":"Lind\u00f8alleen 49",
    "sg:city":"Munkebo",
    "sg:orig_category":"Forsamlingshuse",
    "sg:postcode":"5330",
    "sg:province":"Danmark",
    "wof:name":"Munkebo Forsamlingshus",
    "wof:placetype":"venue"
},
  "geometry": {"coordinates":[10.5576171875,55.4594764709],"type":"Point"}
}