{
  "type": "Feature",
  "properties": {
    "addr:full":"Finsensvej 8 Frederiksberg Danmark 2000",
    "addr:housenumber":"8",
    "addr:postcode":"2000",
    "addr:street":"Finsensvej",
    "iso:country":"DK",
    "sg:address":"Finsensvej 8",
    "sg:city":"Frederiksberg",
    "sg:orig_category":"Pizzeriaer",
    "sg:phone":"+45 38 87 97 87",
    "sg:postcode":"2000",
    "sg:province":"Danmark",
    "wof:name":"Pescara, Pizzeria",
    "wof:placetype":"venue"
},
  "geometry": {"coordinates":[12.5204219818,55.6811256409],"type":"Point"}
}