{
  "type": "Feature",
  "properties": {
    "addr:full":"N. P. Josiassens Vej 44 Grenaa Danmark 8500",
    "addr:housenumber":"44",
    "addr:postcode":"8500",
    "addr:street":"N. P. Josiassens Vej",
    "iso:country":"DK",
    "sg:address":"N. P. Josiassens Vej 44",
    "sg:city":"Grenaa",
    "sg:orig_category":"Erhvervsskoler",
    "sg:phone":"+45 87 58 04 00",
    "sg:postcode":"8500",
    "sg:province":"Danmark",
    "sg:website":"www.ghs.dk",
    "wof:name":"Grenaa Handelsskole",
    "wof:placetype":"venue"
},
  "geometry": {"coordinates":[10.8866300583,56.4120597839],"type":"Point"}
}