{
  "type": "Feature",
  "properties": {
    "addr:full":"Enghavevej 1 A Fjerritslev Danmark 9690",
    "addr:housenumber":"1 a",
    "addr:postcode":"9690",
    "addr:street":"Enghavevej",
    "iso:country":"DK",
    "sg:address":"Enghavevej 1 A",
    "sg:city":"Fjerritslev",
    "sg:orig_category":"Advokater",
    "sg:phone":"+45 98 21 39 90",
    "sg:postcode":"9690",
    "sg:province":"Danmark",
    "wof:name":"Advokatfirmaet Anne-Lisa Andersen",
    "wof:placetype":"venue"
},
  "geometry": {"coordinates":[9.2662668228,57.0871772766],"type":"Point"}
}