{
  "type": "Feature",
  "properties": {
    "iso:country":"DK",
    "sg:address":"Brordrupvej 32",
    "sg:city":"Gadstrup",
    "sg:orig_category":"Brugskunst",
    "sg:phone":"+45 46 19 12 67",
    "sg:postcode":"4621",
    "sg:province":"Danmark",
    "wof:name":"Cons Art ApS",
    "wof:placetype":"venue"
},
  "geometry": {"coordinates":[12.0749168396,55.5784111023],"type":"Point"}
}