{
  "type": "Feature",
  "properties": {
    "addr:full":"Dyssev\u00e6nget 47 B Br\u00f8nsh\u00f8j Danmark 2700",
    "addr:housenumber":"47 b",
    "addr:postcode":"2700",
    "addr:street":"Dyssevaenget",
    "iso:country":"DK",
    "sg:address":"Dyssev\u00e6nget 47 B",
    "sg:city":"Br\u00f8nsh\u00f8j",
    "sg:orig_category":"Psykoanalyse",
    "sg:phone":"+45 38 28 89 40",
    "sg:postcode":"2700",
    "sg:province":"Danmark",
    "wof:name":"Suwalski, Martin",
    "wof:placetype":"venue"
},
  "geometry": {"coordinates":[77.2480392456,14.1354398727],"type":"Point"}
}