{
  "type": "Feature",
  "properties": {
    "addr:full":"I. P. Nielsensvej 1 A Broager Danmark 6310",
    "addr:housenumber":"1 a",
    "addr:postcode":"6310",
    "addr:street":"I. P. Nielsensvej",
    "iso:country":"DK",
    "sg:address":"I. P. Nielsensvej 1 A",
    "sg:city":"Broager",
    "sg:orig_category":"Fodterapeuter",
    "sg:phone":"+45 74 44 28 23",
    "sg:postcode":"6310",
    "sg:province":"Danmark",
    "wof:name":"Rasmussen, Inger",
    "wof:placetype":"venue"
},
  "geometry": {"coordinates":[9.6632614136,54.8893356323],"type":"Point"}
}