{
  "type": "Feature",
  "properties": {
    "iso:country":"DK",
    "sg:address":"Jens Baggesens Vej 4 C",
    "sg:city":"Fredericia",
    "sg:orig_category":"Boligselskaber",
    "sg:phone":"+45 75 92 13 88",
    "sg:postcode":"7000",
    "sg:province":"Danmark",
    "sg:website":"www.selvbyggerbo.dk",
    "wof:name":"Selvbyggerbo",
    "wof:placetype":"venue"
},
  "geometry": {"coordinates":[9.726401329,55.5645484924],"type":"Point"}
}