{
  "type": "Feature",
  "properties": {
    "addr:full":"Gr\u00f8nl\u00f8kken 1 Odense C Danmark 5000",
    "addr:housenumber":"1",
    "addr:postcode":"5000",
    "addr:street":"Gronlokken",
    "iso:country":"DK",
    "sg:address":"Gr\u00f8nl\u00f8kken 1",
    "sg:city":"Odense C",
    "sg:orig_category":"Motionscentre",
    "sg:phone":"+45 66 13 77 25",
    "sg:postcode":"5000",
    "sg:province":"Danmark",
    "sg:website":"www.motionogtrivsel.dk",
    "wof:name":"Motion og Trivsel",
    "wof:placetype":"venue"
},
  "geometry": {"coordinates":[10.390794754,55.3961715698],"type":"Point"}
}