{
  "type": "Feature",
  "properties": {
    "addr:full":"Sj\u00e6llandsgade 25 A Vejle Danmark 7100",
    "addr:housenumber":"25 a",
    "addr:postcode":"7100",
    "addr:street":"Sjaellandsgade",
    "iso:country":"DK",
    "sg:address":"Sj\u00e6llandsgade 25 A",
    "sg:city":"Vejle",
    "sg:orig_category":"Faglige organisationer og foreninger",
    "sg:phone":"+45 75 82 15 88",
    "sg:postcode":"7100",
    "sg:province":"Danmark",
    "wof:name":"Chauff\u00f8rernes Fagforening, SID afd. C-Vejle",
    "wof:placetype":"venue"
},
  "geometry": {"coordinates":[9.54155159,55.7047729492],"type":"Point"}
}