{
  "type": "Feature",
  "properties": {
    "addr:full":"v/ Eva Guldmann, F\u00e5rupvej 26 Jelling Danmark 7300",
    "addr:housenumber":"26",
    "addr:postcode":"7300",
    "addr:street":"Faarupvej",
    "iso:country":"DK",
    "sg:address":"v/ Eva Guldmann, F\u00e5rupvej 26",
    "sg:city":"Jelling",
    "sg:orig_category":"Kulturelle foreninger",
    "sg:phone":"+45 75 87 22 00",
    "sg:postcode":"7300",
    "sg:province":"Danmark",
    "wof:name":"Jelling Kunstforening",
    "wof:placetype":"venue"
},
  "geometry": {"coordinates":[9.4184103012,55.7558555603],"type":"Point"}
}