{
  "type": "Feature",
  "properties": {
    "addr:full":"Jernbanegade 46 S\u00f8nderborg Danmark 6400",
    "addr:housenumber":"46",
    "addr:postcode":"6400",
    "addr:street":"Jernbanegade",
    "iso:country":"DK",
    "sg:address":"Jernbanegade 46",
    "sg:city":"S\u00f8nderborg",
    "sg:orig_category":"Mobiltelefoner",
    "sg:phone":"+45 74 43 55 65",
    "sg:postcode":"6400",
    "sg:province":"Danmark",
    "wof:name":"Unitalk",
    "wof:placetype":"venue"
},
  "geometry": {"coordinates":[9.7888145447,54.9112281799],"type":"Point"}
}