{
  "type": "Feature",
  "properties": {
    "addr:full":"Sognepr\u00e6st: Svend Kj\u00e6rgaard (K/B), Sygehusvej 5, Esb\u00f8nderup Gr\u00e6sted Danmark 3230",
    "addr:housenumber":"5",
    "addr:postcode":"3230",
    "addr:street":"Sygehusvej",
    "iso:country":"DK",
    "sg:address":"Sognepr\u00e6st: Svend Kj\u00e6rgaard (K/B), Sygehusvej 5, Esb\u00f8nderup",
    "sg:city":"Gr\u00e6sted",
    "sg:orig_category":"Kirkesogne",
    "sg:phone":"+45 48 39 00 24",
    "sg:postcode":"3230",
    "sg:province":"Danmark",
    "wof:name":"Esb\u00f8nderup og Villinger\u00f8d pastorat",
    "wof:placetype":"venue"
},
  "geometry": {"coordinates":[-78.6975326538,35.0151481628],"type":"Point"}
}