{
  "type": "Feature",
  "properties": {
    "iso:country":"DK",
    "sg:address":"Nordre Fasanvej 76",
    "sg:city":"Frederiksberg",
    "sg:orig_category":"Begravelsesforretninger",
    "sg:phone":"+45 38 86 60 56",
    "sg:postcode":"2000",
    "sg:province":"Danmark",
    "sg:website":"www.bedemandsforretning.dk",
    "wof:name":"Frederiksberg Bedemandsforretning",
    "wof:placetype":"venue"
},
  "geometry": {"coordinates":[12.526287,55.686104],"type":"Point"}
}