{
  "type": "Feature",
  "properties": {
    "addr:full":"Klaregade 1 B Odense C Danmark 5000",
    "addr:housenumber":"1 b",
    "addr:postcode":"5000",
    "addr:street":"Klaregade",
    "iso:country":"DK",
    "sg:address":"Klaregade 1 B",
    "sg:city":"Odense C",
    "sg:orig_category":"Garn",
    "sg:phone":"+45 66 13 48 98",
    "sg:postcode":"5000",
    "sg:province":"Danmark",
    "wof:name":"Kiva Garn",
    "wof:placetype":"venue"
},
  "geometry": {"coordinates":[10.385008812,55.3953132629],"type":"Point"}
}