{
  "type": "Feature",
  "properties": {
    "addr:full":"Lyngvej 24 Kongens Lyngby Danmark 2800",
    "addr:housenumber":"24",
    "addr:postcode":"2800",
    "addr:street":"Lyngvej",
    "iso:country":"DK",
    "sg:address":"Lyngvej 24",
    "sg:city":"Kongens Lyngby",
    "sg:classifiers":[
        {
            "category":"Organizations",
            "subcategory":"Community Association",
            "type":"Services"
        }
    ],
    "sg:phone":"+45 45 87 56 50",
    "sg:postcode":"2800",
    "sg:province":"Danmark",
    "sg:tags":[
        "relation",
        "public"
    ],
    "wof:name":"Skou, Eigil",
    "wof:placetype":"venue"
},
  "geometry": {"coordinates":[12.5137901306,55.7801856995],"type":"Point"}
}