{
  "type": "Feature",
  "properties": {
    "addr:full":"Langelandsgade 218 \u00c5rhus N Danmark 8200",
    "addr:housenumber":"218",
    "addr:postcode":"8200",
    "addr:street":"Langelandsgade",
    "iso:country":"DK",
    "sg:address":"Langelandsgade 218",
    "sg:city":"\u00c5rhus N",
    "sg:orig_category":"Fotografer",
    "sg:phone":"+45 86 10 63 23",
    "sg:postcode":"8200",
    "sg:province":"Danmark",
    "sg:website":"www.leneesthave.dk",
    "wof:name":"Pedersen Fotografi, Lene Esthave",
    "wof:placetype":"venue"
},
  "geometry": {"coordinates":[4.9393601418,49.7092018127],"type":"Point"}
}