{
  "type": "Feature",
  "properties": {
    "iso:country":"DK",
    "sg:address":"Parkvej 78",
    "sg:city":"Taastrup",
    "sg:orig_category":"Selskabslokaler",
    "sg:phone":"+45 43 99 33 06",
    "sg:postcode":"2630",
    "sg:province":"Danmark",
    "sg:website":"www.stopuret.dk",
    "wof:name":"Stopuret, Restaurant",
    "wof:placetype":"venue"
},
  "geometry": {"coordinates":[12.317652,55.652451],"type":"Point"}
}