{
  "type": "Feature",
  "properties": {
    "addr:full":"Baunesvinget 12 Lynge Danmark 3540",
    "addr:housenumber":"12",
    "addr:postcode":"3540",
    "addr:street":"Baunesvinget",
    "iso:country":"DK",
    "sg:address":"Baunesvinget 12",
    "sg:city":"Lynge",
    "sg:orig_category":"Malermestre",
    "sg:phone":"+45 48 16 08 01",
    "sg:postcode":"3540",
    "sg:province":"Danmark",
    "wof:name":"Zielke, Malerfirmaet Per",
    "wof:placetype":"venue"
},
  "geometry": {"coordinates":[12.2800731659,55.847026825],"type":"Point"}
}