{
  "type": "Feature",
  "properties": {
    "addr:full":"B\u00f8gev\u00e6nget 24 Lunderskov Danmark 6640",
    "addr:housenumber":"24",
    "addr:postcode":"6640",
    "addr:street":"Bogevaenget",
    "iso:country":"DK",
    "sg:address":"B\u00f8gev\u00e6nget 24",
    "sg:city":"Lunderskov",
    "sg:orig_category":"Zoneterapeuter",
    "sg:phone":"+45 75 58 64 58",
    "sg:postcode":"6640",
    "sg:province":"Danmark",
    "wof:name":"Bolsgaard Nielsen, Dorit",
    "wof:placetype":"venue"
},
  "geometry": {"coordinates":[9.2983627319,55.4793586731],"type":"Point"}
}