{
  "type": "Feature",
  "properties": {
    "addr:full":"Birkevang 127 Gilleleje Danmark 3250",
    "addr:housenumber":"127",
    "addr:postcode":"3250",
    "addr:street":"Birkevang",
    "iso:country":"DK",
    "sg:address":"Birkevang 127",
    "sg:city":"Gilleleje",
    "sg:orig_category":"Farve- og stilanalyse",
    "sg:phone":"+45 48 30 23 30",
    "sg:postcode":"3250",
    "sg:province":"Danmark",
    "wof:name":"Color Me Beautiful",
    "wof:placetype":"venue"
},
  "geometry": {"coordinates":[12.3049201965,56.1172142029],"type":"Point"}
}