{
  "type": "Feature",
  "properties": {
    "addr:full":"Industrivej 11 Skjern Danmark 6900",
    "addr:housenumber":"11",
    "addr:postcode":"6900",
    "addr:street":"Industrivej",
    "iso:country":"DK",
    "sg:address":"Industrivej 11",
    "sg:city":"Skjern",
    "sg:orig_category":"Ost en gros",
    "sg:phone":"+45 96 80 02 88",
    "sg:postcode":"6900",
    "sg:province":"Danmark",
    "wof:name":"Skjern Ostelager A/S",
    "wof:placetype":"venue"
},
  "geometry": {"coordinates":[8.4917869568,55.9581222534],"type":"Point"}
}