{
  "type": "Feature",
  "properties": {
    "addr:full":"Kl\u00f8verprisvej 3 Hvidovre Danmark 2650",
    "addr:housenumber":"3",
    "addr:postcode":"2650",
    "addr:street":"Kloverprisvej",
    "iso:country":"DK",
    "sg:address":"Kl\u00f8verprisvej 3",
    "sg:city":"Hvidovre",
    "sg:orig_category":"Hunde, artikler for",
    "sg:phone":"+45 36 75 78 60",
    "sg:postcode":"2650",
    "sg:province":"Danmark",
    "sg:website":"www.kw.dk",
    "wof:name":"KW Hunde & Katteartikler A/S",
    "wof:placetype":"venue"
},
  "geometry": {"coordinates":[12.4726009369,55.6633110046],"type":"Point"}
}