{
  "type": "Feature",
  "properties": {
    "addr:full":"Sognepr\u00e6st: Henrik Andersen (K/B), Lintrupvej 19 Lintrup Danmark 6660",
    "addr:housenumber":"k / b;19",
    "addr:postcode":"6660",
    "addr:street":"Henrik;Lintrupvej",
    "iso:country":"DK",
    "sg:address":"Sognepr\u00e6st: Henrik Andersen (K/B), Lintrupvej 19",
    "sg:city":"Lintrup",
    "sg:orig_category":"Kirkesogne",
    "sg:phone":"+45 74 85 51 17",
    "sg:postcode":"6660",
    "sg:province":"Danmark",
    "wof:name":"Lintrup og Hjerting Sogne",
    "wof:placetype":"venue"
},
  "geometry": {"coordinates":[8.9733600616,55.408870697],"type":"Point"}
}