{
  "type": "Feature",
  "properties": {
    "addr:full":"Kanstrupvej 3, Hillerslev Thisted Danmark 7700",
    "addr:housenumber":"3",
    "addr:postcode":"7700",
    "addr:street":"Kanstrupvej;Hillerslev",
    "iso:country":"DK",
    "sg:address":"Kanstrupvej 3, Hillerslev",
    "sg:city":"Thisted",
    "sg:orig_category":"Lossepladser",
    "sg:phone":"+45 97 98 52 86",
    "sg:postcode":"7700",
    "sg:province":"Danmark",
    "wof:name":"Skovsted Losseplads, I/S",
    "wof:placetype":"venue"
},
  "geometry": {"coordinates":[8.6919784546,56.9556121826],"type":"Point"}
}