{
  "type": "Feature",
  "properties": {
    "iso:country":"DK",
    "sg:address":"J\u00e6gervangen 13",
    "sg:city":"Gentofte",
    "sg:orig_category":"El-motorer",
    "sg:phone":"+45 39 65 15 02",
    "sg:postcode":"2820",
    "sg:province":"Danmark",
    "wof:name":"J\u00e6gersborg Elektro",
    "wof:placetype":"venue"
},
  "geometry": {"coordinates":[12.5353870392,55.7610626221],"type":"Point"}
}