{
  "type": "Feature",
  "properties": {
    "iso:country":"DK",
    "sg:address":"Valh\u00f8jvej 15",
    "sg:city":"Valby",
    "sg:classifiers":[
        {
            "category":"Home & Garden",
            "subcategory":"Carpets & Floor Coverings",
            "type":"Retail Goods"
        }
    ],
    "sg:phone":"+45 36 44 10 05",
    "sg:postcode":"2500",
    "sg:province":"Danmark",
    "sg:tags":[
        "linoleum"
    ],
    "sg:website":"www.arkolit.dk",
    "wof:name":"Arkolit Gulvbel\u00e6gning ApS",
    "wof:placetype":"venue"
},
  "geometry": {"coordinates":[12.5194692612,55.6656570435],"type":"Point"}
}