{
  "type": "Feature",
  "properties": {
    "addr:full":"Havnegade 3 Hobro Danmark 9500",
    "addr:housenumber":"3",
    "addr:postcode":"9500",
    "addr:street":"Havnegade",
    "iso:country":"DK",
    "sg:address":"Havnegade 3",
    "sg:city":"Hobro",
    "sg:orig_category":"Renserier",
    "sg:phone":"+45 98 52 51 99",
    "sg:postcode":"9500",
    "sg:province":"Danmark",
    "wof:name":"Centrum Renseriet/Vaskeriet",
    "wof:placetype":"venue"
},
  "geometry": {"coordinates":[9.7943277359,56.638343811],"type":"Point"}
}