{
  "type": "Feature",
  "properties": {
    "addr:full":"Ravsted Hovedgade 44 A Bylderup-Bov Danmark 6372",
    "addr:housenumber":"44 a",
    "addr:postcode":"6372",
    "addr:street":"Ravsted Hovedgade",
    "iso:country":"DK",
    "sg:address":"Ravsted Hovedgade 44 A",
    "sg:city":"Bylderup-Bov",
    "sg:orig_category":"Private skoler",
    "sg:phone":"+45 74 64 71 19",
    "sg:postcode":"6372",
    "sg:province":"Danmark",
    "wof:name":"Deutsche Privatschule Rapstedt",
    "wof:placetype":"venue"
},
  "geometry": {"coordinates":[9.1312246323,54.9980316162],"type":"Point"}
}