{
  "type": "Feature",
  "properties": {
    "addr:full":"Havnegade 20, Jegind\u00f8 Thyholm Danmark 7790",
    "addr:housenumber":"20",
    "addr:postcode":"7790",
    "addr:street":"Havnegade",
    "iso:country":"DK",
    "sg:address":"Havnegade 20, Jegind\u00f8",
    "sg:city":"Thyholm",
    "sg:orig_category":"Fiskeeksport",
    "sg:phone":"+45 97 87 90 06",
    "sg:postcode":"7790",
    "sg:province":"Danmark",
    "sg:website":"www.muslinger.dk",
    "wof:name":"Johs. Jensen Fiske- og Muslingeeksport A/S",
    "wof:placetype":"venue"
},
  "geometry": {"coordinates":[8.525765419,56.6507072449],"type":"Point"}
}