{
  "type": "Feature",
  "properties": {
    "addr:full":"Fmd.: J\u00f8rgen Jensen, Birkelundsvej 2 Albertslund Danmark 2620",
    "addr:housenumber":"2",
    "addr:postcode":"2620",
    "addr:street":"Birkelundsvej",
    "iso:country":"DK",
    "sg:address":"Fmd.: J\u00f8rgen Jensen, Birkelundsvej 2",
    "sg:city":"Albertslund",
    "sg:orig_category":"Faglige organisationer og foreninger",
    "sg:phone":"+45 43 62 14 48",
    "sg:postcode":"2620",
    "sg:province":"Danmark",
    "wof:name":"Glostrup Politiforening",
    "wof:placetype":"venue"
},
  "geometry": {"coordinates":[12.3517179489,55.6568450928],"type":"Point"}
}