{
  "type": "Feature",
  "properties": {
    "iso:country":"DK",
    "sg:address":"Howitzvej 25",
    "sg:city":"Frederiksberg",
    "sg:orig_category":"Kursussteder",
    "sg:phone":"+45 38 16 28 82",
    "sg:postcode":"2000",
    "sg:province":"Danmark",
    "wof:name":"Data Activity Center",
    "wof:placetype":"venue"
},
  "geometry": {"coordinates":[12.5299119949,55.6795501709],"type":"Point"}
}