{
  "type": "Feature",
  "properties": {
    "addr:full":"Eskemosegyden 46, \u00c5strup Faaborg Danmark 5600",
    "addr:housenumber":"46",
    "addr:postcode":"5600",
    "addr:street":"Eskemosegyden;Aastrup",
    "iso:country":"DK",
    "sg:address":"Eskemosegyden 46, \u00c5strup",
    "sg:city":"Faaborg",
    "sg:orig_category":"Kommunale folkeskoler",
    "sg:phone":"+45 62 61 60 16",
    "sg:postcode":"5600",
    "sg:province":"Danmark",
    "wof:name":"Aastrup skole",
    "wof:placetype":"venue"
},
  "geometry": {"coordinates":[10.2400531769,55.0950622559],"type":"Point"}
}