{
  "type": "Feature",
  "properties": {
    "addr:full":"v/ Finn Pedersen, Musvitvej 5, Kollund Krus\u00e5 Danmark 6340",
    "addr:housenumber":"5",
    "addr:postcode":"6340",
    "addr:street":"Musvitvej",
    "iso:country":"DK",
    "sg:address":"v/ Finn Pedersen, Musvitvej 5, Kollund",
    "sg:city":"Krus\u00e5",
    "sg:orig_category":"Musik og sang",
    "sg:phone":"+45 74 67 85 42",
    "sg:postcode":"6340",
    "sg:province":"Danmark",
    "wof:name":"Padborg Jernbaneorkester",
    "wof:placetype":"venue"
},
  "geometry": {"coordinates":[9.3991203308,54.8500900269],"type":"Point"}
}