{
  "type": "Feature",
  "properties": {
    "iso:country":"DK",
    "sg:address":"\u00d8stergade 36",
    "sg:city":"Herning",
    "sg:orig_category":"Grillbarer",
    "sg:phone":"+45 97 22 49 12",
    "sg:postcode":"7400",
    "sg:province":"Danmark",
    "wof:name":"Birgits P\u00f8lsebar",
    "wof:placetype":"venue"
},
  "geometry": {"coordinates":[8.9809932709,56.1354141235],"type":"Point"}
}