{
  "type": "Feature",
  "properties": {
    "addr:full":"Fmd.: Michael Feddersen, Irisvej 6 Kirke Hyllinge Danmark 4070",
    "addr:housenumber":"6",
    "addr:postcode":"4070",
    "addr:street":"Irisvej",
    "iso:country":"DK",
    "sg:address":"Fmd.: Michael Feddersen, Irisvej 6",
    "sg:city":"Kirke Hyllinge",
    "sg:orig_category":"Grundejerforeninger",
    "sg:phone":"+45 46 40 30 08",
    "sg:postcode":"4070",
    "sg:province":"Danmark",
    "wof:name":"Irisvej Grundejerforening",
    "wof:placetype":"venue"
},
  "geometry": {"coordinates":[11.9004745483,55.7080039978],"type":"Point"}
}