{
  "type": "Feature",
  "properties": {
    "addr:full":"Topasdalen 20 Randers Danmark 8900",
    "addr:housenumber":"20",
    "addr:postcode":"8900",
    "addr:street":"Topasdalen",
    "iso:country":"DK",
    "sg:address":"Topasdalen 20",
    "sg:city":"Randers",
    "sg:orig_category":"Dentallaboratorier",
    "sg:phone":"+45 86 43 90 80",
    "sg:postcode":"8900",
    "sg:province":"Danmark",
    "wof:name":"Adent Dental Teknik",
    "wof:placetype":"venue"
},
  "geometry": {"coordinates":[10.0885124207,56.4748153687],"type":"Point"}
}