{
  "type": "Feature",
  "properties": {
    "iso:country":"DK",
    "sg:address":"Roskildevej 46 1.",
    "sg:city":"Frederiksberg",
    "sg:orig_category":"Oplysningsforbund",
    "sg:phone":"+45 36 46 71 90",
    "sg:postcode":"2000",
    "sg:province":"Danmark",
    "wof:name":"Valby oplysnings Forbund",
    "wof:placetype":"venue"
},
  "geometry": {"coordinates":[12.5129070282,55.6722412109],"type":"Point"}
}