{
  "type": "Feature",
  "properties": {
    "iso:country":"DK",
    "sg:address":"Middelfartvej 82, Skovsh\u00f8jrup",
    "sg:city":"Brenderup",
    "sg:classifiers":[
        {
            "category":"Communications",
            "type":"Services"
        }
    ],
    "sg:phone":"+45 64 44 17 05",
    "sg:postcode":"5464",
    "sg:province":"Danmark",
    "sg:tags":[
        "og",
        "tv",
        "radio"
    ],
    "wof:name":"Pennerup Radio & TV",
    "wof:placetype":"venue"
},
  "geometry": {"coordinates":[9.956905365,55.5179595947],"type":"Point"}
}