{
  "type": "Feature",
  "properties": {
    "addr:full":"Bryggerivej 7 Thisted Danmark 7700",
    "addr:housenumber":"7",
    "addr:postcode":"7700",
    "addr:street":"Bryggerivej",
    "iso:country":"DK",
    "sg:address":"Bryggerivej 7",
    "sg:city":"Thisted",
    "sg:orig_category":"Dyrehandlere",
    "sg:phone":"+45 97 92 67 03",
    "sg:postcode":"7700",
    "sg:province":"Danmark",
    "wof:name":"Tropehuset",
    "wof:placetype":"venue"
},
  "geometry": {"coordinates":[8.6820993423,56.9536170959],"type":"Point"}
}