{
  "type": "Feature",
  "properties": {
    "addr:full":"Holsted Park 15 B N\u00e6stved Danmark 4700",
    "addr:housenumber":"15 b",
    "addr:postcode":"4700",
    "addr:street":"Holsted Park",
    "iso:country":"DK",
    "sg:address":"Holsted Park 15 B",
    "sg:city":"N\u00e6stved",
    "sg:orig_category":"Kontorartikler",
    "sg:phone":"+45 55 77 22 23",
    "sg:postcode":"4700",
    "sg:province":"Danmark",
    "sg:website":"www.kontorprestige.dk",
    "wof:name":"Kontor Prestige",
    "wof:placetype":"venue"
},
  "geometry": {"coordinates":[11.7713499069,55.2490882874],"type":"Point"}
}