{
  "type": "Feature",
  "properties": {
    "addr:full":"Enrumvej 5, S\u00f8hus Odense N Danmark 5270",
    "addr:housenumber":"5",
    "addr:postcode":"5270",
    "addr:street":"Enrumvej;Sohus",
    "iso:country":"DK",
    "sg:address":"Enrumvej 5, S\u00f8hus",
    "sg:city":"Odense N",
    "sg:orig_category":"Vinduespolering",
    "sg:phone":"+45 66 18 95 75",
    "sg:postcode":"5270",
    "sg:province":"Danmark",
    "wof:name":"Bertelsen, Peder",
    "wof:placetype":"venue"
},
  "geometry": {"coordinates":[10.3306798935,55.4711418152],"type":"Point"}
}