{
  "type": "Feature",
  "properties": {
    "addr:full":"Vestergade 3 Helsinge Danmark 3200",
    "addr:housenumber":"3",
    "addr:postcode":"3200",
    "addr:street":"Vestergade",
    "iso:country":"DK",
    "sg:address":"Vestergade 3",
    "sg:city":"Helsinge",
    "sg:orig_category":"Blomsterhandlere",
    "sg:phone":"+45 48 79 42 23",
    "sg:postcode":"3200",
    "sg:province":"Danmark",
    "wof:name":"J\u00f8rgensen, Viggo",
    "wof:placetype":"venue"
},
  "geometry": {"coordinates":[12.1981401443,56.0220031738],"type":"Point"}
}