{
  "type": "Feature",
  "properties": {
    "addr:full":"Dalgasgade 41 Herning Danmark 7400",
    "addr:housenumber":"41",
    "addr:postcode":"7400",
    "addr:street":"Dalgasgade",
    "iso:country":"DK",
    "sg:address":"Dalgasgade 41",
    "sg:city":"Herning",
    "sg:orig_category":"Dentallaboratorier",
    "sg:phone":"+45 97 22 35 82",
    "sg:postcode":"7400",
    "sg:province":"Danmark",
    "wof:name":"S\u00f8rensen - Dentallab, Kirsten",
    "wof:placetype":"venue"
},
  "geometry": {"coordinates":[8.9690542221,56.1347389221],"type":"Point"}
}