{
  "type": "Feature",
  "properties": {
    "iso:country":"DK",
    "sg:address":"Stationsvej 7 ",
    "sg:city":"Thisted",
    "sg:classifiers":[
        {
            "category":"Wholesale",
            "subcategory":"Machinery & Supplies",
            "type":"Manufacturing & Wholesale Goods"
        }
    ],
    "sg:phone":"+45 97 98 12 33",
    "sg:postcode":"7700",
    "sg:province":"Danmark",
    "sg:tags":[
        "-",
        "agriculture",
        "equipment"
    ],
    "wof:name":"NB HUNDAHL APS",
    "wof:placetype":"venue"
},
  "geometry": {"coordinates":[8.6792297363,57.0203971863],"type":"Point"}
}