{
  "type": "Feature",
  "properties": {
    "addr:full":"Hjerting Byvej 6 Esbjerg V Danmark 6710",
    "addr:housenumber":"6",
    "addr:postcode":"6710",
    "addr:street":"Hjerting Byvej",
    "iso:country":"DK",
    "sg:address":"Hjerting Byvej 6",
    "sg:city":"Esbjerg V",
    "sg:orig_category":"Fotografer",
    "sg:phone":"+45 75 11 71 59",
    "sg:postcode":"6710",
    "sg:province":"Danmark",
    "wof:name":"Orionfoto-Atelier",
    "wof:placetype":"venue"
},
  "geometry": {"coordinates":[8.3552303314,55.5242271423],"type":"Point"}
}