{
  "type": "Feature",
  "properties": {
    "addr:full":"v/ Ulla Rasmussen, Engestoftevej 47, Slemminge Saksk\u00f8bing Danmark 4990",
    "addr:housenumber":"47",
    "addr:postcode":"4990",
    "addr:street":"Engestoftevej",
    "iso:country":"DK",
    "sg:address":"v/ Ulla Rasmussen, Engestoftevej 47, Slemminge",
    "sg:city":"Saksk\u00f8bing",
    "sg:orig_category":"Spejderkorps",
    "sg:phone":"+45 54 76 31 01",
    "sg:postcode":"4990",
    "sg:province":"Danmark",
    "wof:name":"KFUK-spejderne i Slemminge",
    "wof:placetype":"venue"
},
  "geometry": {"coordinates":[11.6875448227,54.7894821167],"type":"Point"}
}