{
  "type": "Feature",
  "properties": {
    "addr:full":"Administrationsbygningen, Borgerv\u00e6nget 12 Brovst Danmark 9460",
    "addr:housenumber":"12",
    "addr:postcode":"9460",
    "iso:country":"DK",
    "sg:address":"Administrationsbygningen, Borgerv\u00e6nget 12",
    "sg:city":"Brovst",
    "sg:orig_category":"Dagplejeformidling",
    "sg:phone":"+45 96 44 56 00",
    "sg:postcode":"9460",
    "sg:province":"Danmark",
    "wof:name":"Dagplejeformidlingen i Brovst Kommune",
    "wof:placetype":"venue"
},
  "geometry": {"coordinates":[9.5220241547,57.097366333],"type":"Point"}
}