{
  "type": "Feature",
  "properties": {
    "addr:full":"Poppelhegnet 10 Kongens Lyngby Danmark 2800",
    "addr:housenumber":"10",
    "addr:postcode":"2800",
    "addr:street":"Poppelhegnet",
    "iso:country":"DK",
    "sg:address":"Poppelhegnet 10",
    "sg:city":"Kongens Lyngby",
    "sg:orig_category":"Malermestre",
    "sg:phone":"+45 45 88 82 47",
    "sg:postcode":"2800",
    "sg:province":"Danmark",
    "wof:name":"Christensen, Ib",
    "wof:placetype":"venue"
},
  "geometry": {"coordinates":[12.5131063461,55.7782287598],"type":"Point"}
}