{
  "type": "Feature",
  "properties": {
    "addr:full":"Fmd.: Ulla Christensen, R\u00e6vk\u00e6rvej 27, Hyllebjerg Fars\u00f8 Danmark 9640",
    "addr:housenumber":"27",
    "addr:postcode":"9640",
    "addr:street":"Raevkaervej",
    "iso:country":"DK",
    "sg:address":"Fmd.: Ulla Christensen, R\u00e6vk\u00e6rvej 27, Hyllebjerg",
    "sg:city":"Fars\u00f8",
    "sg:orig_category":"Borger- og beboerforeninger",
    "sg:phone":"+45 98 67 84 02",
    "sg:postcode":"9640",
    "sg:province":"Danmark",
    "wof:name":"Hyllebjerg Borger- og Idr\u00e6tsforening",
    "wof:placetype":"venue"
},
  "geometry": {"coordinates":[9.1937885284,56.6945037842],"type":"Point"}
}