{
  "type": "Feature",
  "properties": {
    "iso:country":"DK",
    "sg:address":"H\u00f8je Gladsaxe Torv 3",
    "sg:city":"S\u00f8borg",
    "sg:orig_category":"Kirker",
    "sg:phone":"+45 39 69 03 70",
    "sg:postcode":"2860",
    "sg:province":"Danmark",
    "wof:name":"Haraldskirken",
    "wof:placetype":"venue"
},
  "geometry": {"coordinates":[12.4987678528,55.729309082],"type":"Point"}
}