{
  "type": "Feature",
  "properties": {
    "iso:country":"DK",
    "sg:address":"Adelgade 61",
    "sg:city":"Nysted",
    "sg:orig_category":"Redningsberedskab",
    "sg:phone":"+45 54 87 12 22",
    "sg:postcode":"4880",
    "sg:province":"Danmark",
    "wof:name":"Nysted Redningsberedskab",
    "wof:placetype":"venue"
},
  "geometry": {"coordinates":[11.72955513,54.6664276123],"type":"Point"}
}