{
  "type": "Feature",
  "properties": {
    "addr:full":"Tofteg\u00e5rds Alle 9 A Valby Danmark 2500",
    "addr:housenumber":"9 a",
    "addr:postcode":"2500",
    "addr:street":"Toftegaards Alle",
    "iso:country":"DK",
    "sg:address":"Tofteg\u00e5rds Alle 9 A",
    "sg:city":"Valby",
    "sg:orig_category":"Videoudstyr",
    "sg:phone":"+45 36 45 36 92",
    "sg:postcode":"2500",
    "sg:province":"Danmark",
    "sg:website":"www.blockbuster.dk",
    "wof:name":"Blockbuster Video Danmark A/S",
    "wof:placetype":"venue"
},
  "geometry": {"coordinates":[12.5172557831,55.6659164429],"type":"Point"}
}