{
  "type": "Feature",
  "properties": {
    "addr:full":"Sommerstedgade 4,4 th. K\u00f8benhavn Danmark 1718",
    "addr:housenumber":"4,4 th.",
    "addr:postcode":"1718",
    "addr:street":"Sommerstedgade",
    "iso:country":"DK",
    "sg:address":"Sommerstedgade 4,4 th.",
    "sg:city":"K\u00f8benhavn",
    "sg:orig_category":"Tegnere og tegnestuer",
    "sg:phone":"+45 33 22 10 58",
    "sg:postcode":"1718",
    "sg:province":"Danmark",
    "wof:name":"Private Tegneskole, Den",
    "wof:placetype":"venue"
},
  "geometry": {"coordinates":[12.5574998856,55.6661987305],"type":"Point"}
}