{
  "type": "Feature",
  "properties": {
    "addr:full":"Solbjerg Hovedgade 21 Solbjerg Danmark 8355",
    "addr:housenumber":"21",
    "addr:postcode":"8355",
    "addr:street":"Solbjerg Hovedgade",
    "iso:country":"DK",
    "sg:address":"Solbjerg Hovedgade 21",
    "sg:city":"Solbjerg",
    "sg:orig_category":"Servicestationer",
    "sg:phone":"+45 86 92 75 44",
    "sg:postcode":"8355",
    "sg:province":"Danmark",
    "wof:name":"Statoil Servicenter",
    "wof:placetype":"venue"
},
  "geometry": {"coordinates":[10.0818080902,56.0436820984],"type":"Point"}
}