{
  "type": "Feature",
  "properties": {
    "addr:full":"Kindhestegade 1 Assens Danmark 5610",
    "addr:housenumber":"1",
    "addr:postcode":"5610",
    "addr:street":"Kindhestegade",
    "iso:country":"DK",
    "sg:address":"Kindhestegade 1",
    "sg:city":"Assens",
    "sg:orig_category":"Lokalarkiver",
    "sg:phone":"+45 64 71 31 90",
    "sg:postcode":"5610",
    "sg:province":"Danmark",
    "wof:name":"Assens Lokalhistoriske Arkiv",
    "wof:placetype":"venue"
},
  "geometry": {"coordinates":[9.8963537216,55.2698783875],"type":"Point"}
}