{
  "type": "Feature",
  "properties": {
    "addr:full":"Tarp Hovedvej 70 Esbjerg N Danmark 6715",
    "addr:housenumber":"70",
    "addr:postcode":"6715",
    "addr:street":"Tarp Hovedvej",
    "iso:country":"DK",
    "sg:address":"Tarp Hovedvej 70",
    "sg:city":"Esbjerg N",
    "sg:orig_category":"Gartnerier",
    "sg:phone":"+45 75 16 70 77",
    "sg:postcode":"6715",
    "sg:province":"Danmark",
    "wof:name":"Karstensen, Christian",
    "wof:placetype":"venue"
},
  "geometry": {"coordinates":[8.464302063,55.5420684814],"type":"Point"}
}