{
  "type": "Feature",
  "properties": {
    "addr:full":"Eriksholmsvej 4 Svendborg Danmark 5700",
    "addr:housenumber":"4",
    "addr:postcode":"5700",
    "addr:street":"Eriksholmsvej",
    "iso:country":"DK",
    "sg:address":"Eriksholmsvej 4",
    "sg:city":"Svendborg",
    "sg:orig_category":"Frugt en gros",
    "sg:phone":"+45 62 20 70 75",
    "sg:postcode":"5700",
    "sg:province":"Danmark",
    "wof:name":"\u00c6bel\u00f8's Frugt & Gr\u00f8nt Engros",
    "wof:placetype":"venue"
},
  "geometry": {"coordinates":[10.6545886993,55.0474433899],"type":"Point"}
}