{
  "type": "Feature",
  "properties": {
    "addr:full":"Torvegade 9 Maribo Danmark 4930",
    "addr:housenumber":"9",
    "addr:postcode":"4930",
    "addr:street":"Torvegade",
    "iso:country":"DK",
    "sg:address":"Torvegade 9",
    "sg:city":"Maribo",
    "sg:orig_category":"Ejendomshandel",
    "sg:phone":"+45 54 78 16 11",
    "sg:postcode":"4930",
    "sg:province":"Danmark",
    "sg:website":"www.edc.dk",
    "wof:name":"Jensen, M\u00f8ller",
    "wof:placetype":"venue"
},
  "geometry": {"coordinates":[11.5051698685,54.77368927],"type":"Point"}
}