{
  "type": "Feature",
  "properties": {
    "addr:full":"v/ Birthe Hjorth Hansen, Engl\u00f8kken 5 Nex\u00f8 Danmark 3730",
    "addr:housenumber":"5",
    "addr:postcode":"3730",
    "addr:street":"Englokken",
    "iso:country":"DK",
    "sg:address":"v/ Birthe Hjorth Hansen, Engl\u00f8kken 5",
    "sg:city":"Nex\u00f8",
    "sg:orig_category":"Kolonihaveforeninger",
    "sg:postcode":"3730",
    "sg:province":"Danmark",
    "wof:name":"Nex\u00f8 S\u00f8ndre Haveforening",
    "wof:placetype":"venue"
},
  "geometry": {"coordinates":[15.1096076965,55.0267219543],"type":"Point"}
}