{
  "type": "Feature",
  "properties": {
    "iso:country":"DK",
    "sg:address":"K\u00e6rvej 1 ",
    "sg:city":"Herning",
    "sg:classifiers":[
        {
            "category":"Wholesale",
            "subcategory":"Drugs",
            "type":"Manufacturing & Wholesale Goods"
        }
    ],
    "sg:phone":"+45 97 12 46 22",
    "sg:postcode":"7400",
    "sg:province":"Danmark",
    "sg:tags":[
        "chemical",
        "pharmaceutical"
    ],
    "wof:name":"NCC ROADS A/S",
    "wof:placetype":"venue"
},
  "geometry": {"coordinates":[8.9486865997,56.1242256165],"type":"Point"}
}