{
  "type": "Feature",
  "properties": {
    "addr:full":"Stavnk\u00e6rvej 12, \u00c5st Vandel Danmark 7184",
    "addr:housenumber":"12",
    "addr:postcode":"7184",
    "addr:street":"Stavnkaervej",
    "iso:country":"DK",
    "sg:address":"Stavnk\u00e6rvej 12, \u00c5st",
    "sg:city":"Vandel",
    "sg:orig_category":"Maskinstationer",
    "sg:phone":"+45 75 88 52 17",
    "sg:postcode":"7184",
    "sg:province":"Danmark",
    "wof:name":"Hansen Maskinstation, Frede",
    "wof:placetype":"venue"
},
  "geometry": {"coordinates":[9.2151947021,55.708984375],"type":"Point"}
}