{
  "type": "Feature",
  "properties": {
    "addr:full":"Betty Nansens Alle 51 Frederiksberg Danmark 2000",
    "addr:housenumber":"51",
    "addr:postcode":"2000",
    "addr:street":"Betty Nansens Alle",
    "iso:country":"DK",
    "sg:address":"Betty Nansens Alle 51",
    "sg:city":"Frederiksberg",
    "sg:orig_category":"Plejehjem",
    "sg:phone":"+45 36 13 30 30",
    "sg:postcode":"2000",
    "sg:province":"Danmark",
    "wof:name":"Bette Nansen",
    "wof:placetype":"venue"
},
  "geometry": {"coordinates":[12.5011310577,55.670009613],"type":"Point"}
}