{
  "type": "Feature",
  "properties": {
    "addr:full":"Jens Baggesens Vej 88 F \u00c5rhus N Danmark 8200",
    "addr:housenumber":"88 f",
    "addr:postcode":"8200",
    "addr:street":"Jens Baggesens Vej",
    "iso:country":"DK",
    "sg:address":"Jens Baggesens Vej 88 F",
    "sg:city":"\u00c5rhus N",
    "sg:orig_category":"Private hospitaler and klinikker",
    "sg:phone":"+45 86 10 80 11",
    "sg:postcode":"8200",
    "sg:province":"Danmark",
    "sg:website":"www.grymer.dk",
    "wof:name":"Grymer Plastikkirurgisk Klinik",
    "wof:placetype":"venue"
},
  "geometry": {"coordinates":[-76.4168395996,37.452419281],"type":"Point"}
}