{
  "type": "Feature",
  "properties": {
    "addr:full":"Oustrupvej 28 Aars Danmark 9600",
    "addr:housenumber":"28",
    "addr:postcode":"9600",
    "addr:street":"Oustrupvej",
    "iso:country":"DK",
    "sg:address":"Oustrupvej 28",
    "sg:city":"Aars",
    "sg:orig_category":"Arkitekter",
    "sg:phone":"+45 98 62 18 66",
    "sg:postcode":"9600",
    "sg:province":"Danmark",
    "wof:name":"Madsen A/S, Arkitektfirmaet Niels Krogh",
    "wof:placetype":"venue"
},
  "geometry": {"coordinates":[9.5241270065,56.8097190857],"type":"Point"}
}