{
  "type": "Feature",
  "properties": {
    "addr:full":"Amager Centeret, Reberbanegade 2 K\u00f8benhavn S Danmark 2300",
    "addr:housenumber":"2",
    "addr:postcode":"2300",
    "addr:street":"Amager Centeret Reberbanegade;S Danmark",
    "iso:country":"DK",
    "sg:address":"Amager Centeret, Reberbanegade 2",
    "sg:city":"K\u00f8benhavn S",
    "sg:classifiers":[
        {
            "category":"Communications",
            "type":"Services"
        }
    ],
    "sg:phone":"+45 32 96 73 13",
    "sg:postcode":"2300",
    "sg:province":"Danmark",
    "sg:tags":[
        "og",
        "tv",
        "radio"
    ],
    "wof:name":"Merlin A/S",
    "wof:placetype":"venue"
},
  "geometry": {"coordinates":[12.5925598145,55.6268196106],"type":"Point"}
}