{
  "type": "Feature",
  "properties": {
    "addr:full":"Rosenv\u00e6nget 11 Nyk\u00f8bing Danmark 4800",
    "addr:housenumber":"11",
    "addr:postcode":"4800",
    "addr:street":"Rosenvaenget",
    "iso:country":"DK",
    "sg:address":"Rosenv\u00e6nget 11",
    "sg:city":"Nyk\u00f8bing",
    "sg:orig_category":"Faglige organisationer og foreninger",
    "sg:phone":"+45 54 85 36 41",
    "sg:postcode":"4800",
    "sg:province":"Danmark",
    "wof:name":"Kvindeligt Arbejderforbund",
    "wof:placetype":"venue"
},
  "geometry": {"coordinates":[-114.0768203735,46.4432411194],"type":"Point"}
}