{
  "type": "Feature",
  "properties": {
    "iso:country":"DK",
    "sg:address":"N\u00f8rre Boulevard 20",
    "sg:city":"Randers",
    "sg:orig_category":"Servicestationer",
    "sg:phone":"+45 86 43 30 35",
    "sg:postcode":"8900",
    "sg:province":"Danmark",
    "wof:name":"Texaco Trafikcenter",
    "wof:placetype":"venue"
},
  "geometry": {"coordinates":[10.0406522751,56.4710083008],"type":"Point"}
}