{
  "type": "Feature",
  "properties": {
    "addr:full":"Vester Tv\u00e6rvej 11-13 Randers Danmark 8900",
    "addr:postcode":"11-13;8900",
    "addr:street":"Tvaervej",
    "iso:country":"DK",
    "sg:address":"Vester Tv\u00e6rvej 11-13",
    "sg:city":"Randers",
    "sg:orig_category":"\u00c3\u02dcvrige institutioner",
    "sg:phone":"+45 86 42 44 88",
    "sg:postcode":"8900",
    "sg:province":"Danmark",
    "wof:name":"Vesterbo, Psykiatrisk Bosted",
    "wof:placetype":"venue"
},
  "geometry": {"coordinates":[10.0244045258,56.4639472961],"type":"Point"}
}