{
  "type": "Feature",
  "properties": {
    "iso:country":"DK",
    "sg:address":"Elsenbakken 8 ",
    "sg:city":"Frederikssund",
    "sg:classifiers":[
        {
            "category":"Autos & Motor Vehicles",
            "subcategory":"Automobile Sales",
            "type":"Retail Goods"
        }
    ],
    "sg:phone":"+45 47 36 54 11",
    "sg:postcode":"3600",
    "sg:province":"Danmark",
    "sg:tags":[
        "industrial"
    ],
    "wof:name":"A/S FREDERIKSSUND AUTODELE",
    "wof:placetype":"venue"
},
  "geometry": {"coordinates":[12.0653982162,55.8498687744],"type":"Point"}
}