{
  "type": "Feature",
  "properties": {
    "iso:country":"DK",
    "sg:address":"Nordre Strandvej 11 A",
    "sg:city":"Risskov",
    "sg:orig_category":"Bagere",
    "sg:phone":"+45 86 17 98 72",
    "sg:postcode":"8240",
    "sg:province":"Danmark",
    "wof:name":"Strandvejens Bageri",
    "wof:placetype":"venue"
},
  "geometry": {"coordinates":[10.24088,56.191921],"type":"Point"}
}