{
  "type": "Feature",
  "properties": {
    "addr:full":"N\u00f8rre Alle 18 \u00c5rhus C Danmark 8000",
    "addr:housenumber":"18",
    "addr:postcode":"8000",
    "addr:street":"Norre Alle",
    "iso:country":"DK",
    "sg:address":"N\u00f8rre Alle 18",
    "sg:city":"\u00c5rhus C",
    "sg:orig_category":"Cafeer",
    "sg:phone":"+45 86 19 04 44",
    "sg:postcode":"8000",
    "sg:province":"Danmark",
    "wof:name":"\u00c5rhus, Caf\u00e9",
    "wof:placetype":"venue"
},
  "geometry": {"coordinates":[4.717400074,49.7588005066],"type":"Point"}
}