{
  "type": "Feature",
  "properties": {
    "addr:full":"Fmd.: B\u00f8rge Madsen, Bendtsens G\u00e5rd 21 Ruds Vedby Danmark 4291",
    "addr:housenumber":"21",
    "addr:postcode":"4291",
    "addr:street":"Borge;Bendtsens Gaard",
    "iso:country":"DK",
    "sg:address":"Fmd.: B\u00f8rge Madsen, Bendtsens G\u00e5rd 21",
    "sg:city":"Ruds Vedby",
    "sg:orig_category":"Kulturelle foreninger",
    "sg:phone":"+45 58 26 16 34",
    "sg:postcode":"4291",
    "sg:province":"Danmark",
    "wof:name":"Arbejdernes Radio- og Fjernsynsklub, Ruds-Vedby",
    "wof:placetype":"venue"
},
  "geometry": {"coordinates":[11.3734693527,55.5409049988],"type":"Point"}
}