{
  "type": "Feature",
  "properties": {
    "addr:full":"Maglekildevej 13 A, Postboks 222 Roskilde Danmark 4000",
    "addr:housenumber":"13 a;222",
    "addr:postcode":"4000",
    "addr:street":"Maglekildevej;Postboks",
    "iso:country":"DK",
    "sg:address":"Maglekildevej 13 A, Postboks 222",
    "sg:city":"Roskilde",
    "sg:orig_category":"Vandbesparende produkter, BRUGSVAND",
    "sg:phone":"+45 46 35 00 02",
    "sg:postcode":"4000",
    "sg:province":"Danmark",
    "wof:name":"EB-merceng",
    "wof:placetype":"venue"
},
  "geometry": {"coordinates":[12.0909376144,55.6404838562],"type":"Point"}
}