{
  "type": "Feature",
  "properties": {
    "addr:full":"F\u00e6gangsvej 32, B\u00f8nnerup Str Glesborg Danmark 8585",
    "addr:housenumber":"32",
    "addr:postcode":"8585",
    "addr:street":"Faegangsvej;Str Glesborg Danmark",
    "iso:country":"DK",
    "sg:address":"F\u00e6gangsvej 32, B\u00f8nnerup Str",
    "sg:city":"Glesborg",
    "sg:orig_category":"Murermestre",
    "sg:phone":"+45 86 38 61 82",
    "sg:postcode":"8585",
    "sg:province":"Danmark",
    "wof:name":"Mogensen, Chris",
    "wof:placetype":"venue"
},
  "geometry": {"coordinates":[10.5884723663,56.5124320984],"type":"Point"}
}