{
  "type": "Feature",
  "properties": {
    "addr:full":"Kramnitse, Noret 2 R\u00f8dby Danmark 4970",
    "addr:housenumber":"2",
    "addr:postcode":"4970",
    "addr:street":"Kramnitse Noret",
    "iso:country":"DK",
    "sg:address":"Kramnitse, Noret 2",
    "sg:city":"R\u00f8dby",
    "sg:orig_category":"Campingpladser",
    "sg:phone":"+45 54 94 61 00",
    "sg:postcode":"4970",
    "sg:province":"Danmark",
    "sg:website":"www.westerncamp.dk",
    "wof:name":"Western Camp",
    "wof:placetype":"venue"
},
  "geometry": {"coordinates":[11.3586397171,54.6630592346],"type":"Point"}
}