{
  "type": "Feature",
  "properties": {
    "addr:full":"Sandk\u00e6rvej 2, Kulhuse J\u00e6gerspris Danmark 3630",
    "addr:housenumber":"2",
    "addr:postcode":"3630",
    "addr:street":"Sandkaervej",
    "iso:country":"DK",
    "sg:address":"Sandk\u00e6rvej 2, Kulhuse",
    "sg:city":"J\u00e6gerspris",
    "sg:orig_category":"Fisk og vildt",
    "sg:phone":"+45 40 53 32 28",
    "sg:postcode":"3630",
    "sg:province":"Danmark",
    "wof:name":"Frisk fisk fra Kulhuse",
    "wof:placetype":"venue"
},
  "geometry": {"coordinates":[11.9136800766,55.9269866943],"type":"Point"}
}