{
  "type": "Feature",
  "properties": {
    "addr:full":"Fjordvejen 1 A, G\u00f8rding Vemb Danmark 7570",
    "addr:housenumber":"1 a",
    "addr:postcode":"7570",
    "addr:street":"Fjordvejen;Gording",
    "iso:country":"DK",
    "sg:address":"Fjordvejen 1 A, G\u00f8rding",
    "sg:city":"Vemb",
    "sg:orig_category":"Forsamlingshuse",
    "sg:phone":"+45 97 48 15 67",
    "sg:postcode":"7570",
    "sg:province":"Danmark",
    "wof:name":"G\u00f8rding Forsamlingshus",
    "wof:placetype":"venue"
},
  "geometry": {"coordinates":[8.343793869,56.343082428],"type":"Point"}
}