{
  "type": "Feature",
  "properties": {
    "addr:full":"S\u00f8ndre St\u00e6nge 4, Skar\u00f8 Svendborg Danmark 5700",
    "addr:housenumber":"4",
    "addr:postcode":"5700",
    "addr:street":"Staenge;Skaro",
    "iso:country":"DK",
    "sg:address":"S\u00f8ndre St\u00e6nge 4, Skar\u00f8",
    "sg:city":"Svendborg",
    "sg:orig_category":"Kirker",
    "sg:postcode":"5700",
    "sg:province":"Danmark",
    "wof:name":"Skar\u00f8 Kirke",
    "wof:placetype":"venue"
},
  "geometry": {"coordinates":[10.6065101624,55.0595970154],"type":"Point"}
}