{
  "type": "Feature",
  "properties": {
    "addr:full":"Alsgade 60 - 62 S\u00f8nderborg Danmark 6400",
    "addr:housenumber":"60 62",
    "addr:postcode":"6400",
    "addr:street":"Alsgade",
    "iso:country":"DK",
    "sg:address":"Alsgade 60 - 62",
    "sg:city":"S\u00f8nderborg",
    "sg:orig_category":"Autoforhandlere",
    "sg:phone":"+45 74 42 36 40",
    "sg:postcode":"6400",
    "sg:province":"Danmark",
    "wof:name":"Iversen, Martin",
    "wof:placetype":"venue"
},
  "geometry": {"coordinates":[9.8048877716,54.918056488],"type":"Point"}
}