{
  "type": "Feature",
  "properties": {
    "addr:full":"\u00d8rsted Bygade 7 Havdrup Danmark 4622",
    "addr:housenumber":"7",
    "addr:postcode":"4622",
    "addr:street":"Orsted Bygade",
    "iso:country":"DK",
    "sg:address":"\u00d8rsted Bygade 7",
    "sg:city":"Havdrup",
    "sg:orig_category":"Trykkerier",
    "sg:phone":"+45 46 18 15 18",
    "sg:postcode":"4622",
    "sg:province":"Danmark",
    "wof:name":"StigWe Trykshoppen",
    "wof:placetype":"venue"
},
  "geometry": {"coordinates":[12.1158895493,55.5443534851],"type":"Point"}
}