{
  "type": "Feature",
  "properties": {
    "addr:full":"S\u00f8lystvej 3 Jyderup Danmark 4450",
    "addr:housenumber":"3",
    "addr:postcode":"4450",
    "addr:street":"Solystvej",
    "iso:country":"DK",
    "sg:address":"S\u00f8lystvej 3",
    "sg:city":"Jyderup",
    "sg:orig_category":"Ejendomshandel",
    "sg:phone":"+45 59 27 74 84",
    "sg:postcode":"4450",
    "sg:province":"Danmark",
    "wof:name":"Real M\u00e6glerne",
    "wof:placetype":"venue"
},
  "geometry": {"coordinates":[11.3957967758,55.6597251892],"type":"Point"}
}