{
  "type": "Feature",
  "properties": {
    "addr:full":"M\u00f8llevej 3 H\u00f8ng Danmark 4270",
    "addr:housenumber":"3",
    "addr:postcode":"4270",
    "addr:street":"Mollevej;Hong Danmark",
    "iso:country":"DK",
    "sg:address":"M\u00f8llevej 3",
    "sg:city":"H\u00f8ng",
    "sg:orig_category":"Rejsebureauer",
    "sg:phone":"+45 58 84 12 34",
    "sg:postcode":"4270",
    "sg:province":"Danmark",
    "sg:website":"www.rejsekontoret.dk",
    "wof:name":"RejseKontoret",
    "wof:placetype":"venue"
},
  "geometry": {"coordinates":[11.2887563705,55.5075683594],"type":"Point"}
}