{
  "type": "Feature",
  "properties": {
    "addr:full":"Tj\u00f8rnevej 39, Mejdal Holstebro Danmark 7500",
    "addr:housenumber":"39",
    "addr:postcode":"7500",
    "addr:street":"Tjornevej;Mejdal",
    "iso:country":"DK",
    "sg:address":"Tj\u00f8rnevej 39, Mejdal",
    "sg:city":"Holstebro",
    "sg:orig_category":"Fodplejere",
    "sg:phone":"+45 97 40 35 65",
    "sg:postcode":"7500",
    "sg:province":"Danmark",
    "wof:name":"Mejdal Fodklinik",
    "wof:placetype":"venue"
},
  "geometry": {"coordinates":[8.6202583313,56.3625221252],"type":"Point"}
}