{
  "type": "Feature",
  "properties": {
    "iso:country":"DK",
    "sg:address":"Administrationsbygningen, Ravnsgade 5",
    "sg:city":"Aakirkeby",
    "sg:orig_category":"Kommunen",
    "sg:phone":"+45 56 97 47 47",
    "sg:postcode":"3720",
    "sg:province":"Danmark",
    "sg:website":"www.aakirkeby.dk",
    "wof:name":"Aakirkeby Kommune",
    "wof:placetype":"venue"
},
  "geometry": {"coordinates":[14.9202880859,55.070110321],"type":"Point"}
}