{
  "type": "Feature",
  "properties": {
    "addr:full":"Fredensborgvej 12 Skanderborg Danmark 8660",
    "addr:housenumber":"12",
    "addr:postcode":"8660",
    "addr:street":"Fredensborgvej",
    "iso:country":"DK",
    "sg:address":"Fredensborgvej 12",
    "sg:city":"Skanderborg",
    "sg:orig_category":"Tandteknikere, Kliniske",
    "sg:phone":"+45 86 52 01 64",
    "sg:postcode":"8660",
    "sg:province":"Danmark",
    "wof:name":"Christensen, Kamma",
    "wof:placetype":"venue"
},
  "geometry": {"coordinates":[9.9398078918,56.0457572937],"type":"Point"}
}