{
  "type": "Feature",
  "properties": {
    "addr:full":"Haugb\u00f8llevej 14, Haugb\u00f8lle Rudk\u00f8bing Danmark 5900",
    "addr:housenumber":"14",
    "addr:postcode":"5900",
    "addr:street":"Haugbollevej",
    "iso:country":"DK",
    "sg:address":"Haugb\u00f8llevej 14, Haugb\u00f8lle",
    "sg:city":"Rudk\u00f8bing",
    "sg:orig_category":"Maskinstationer",
    "sg:phone":"+45 62 57 10 45",
    "sg:postcode":"5900",
    "sg:province":"Danmark",
    "wof:name":"Ovre Smede og Maskinstation",
    "wof:placetype":"venue"
},
  "geometry": {"coordinates":[-121.42538452150001,45.7001037598],"type":"Point"}
}