{
  "type": "Feature",
  "properties": {
    "addr:full":"Arres\u00f8vej 20 Risskov Danmark 8240",
    "addr:housenumber":"20",
    "addr:postcode":"8240",
    "addr:street":"Arresovej",
    "iso:country":"DK",
    "sg:address":"Arres\u00f8vej 20",
    "sg:city":"Risskov",
    "sg:orig_category":"Havebrugsmaskiner",
    "sg:phone":"+45 86 17 65 77",
    "sg:postcode":"8240",
    "sg:province":"Danmark",
    "wof:name":"Enemark A/S",
    "wof:placetype":"venue"
},
  "geometry": {"coordinates":[10.2325401306,56.2027778625],"type":"Point"}
}