{
  "type": "Feature",
  "properties": {
    "addr:full":"Christoffer Bog\u00f8, Gr\u00f8nnegade 18 K\u00f8benhavn Danmark 1107",
    "addr:housenumber":"18;1107",
    "addr:street":"Christoffer;Gronnegade",
    "iso:country":"DK",
    "sg:address":"Christoffer Bog\u00f8, Gr\u00f8nnegade 18",
    "sg:city":"K\u00f8benhavn",
    "sg:orig_category":"Aviser",
    "sg:phone":"+45 33 45 46 00",
    "sg:postcode":"1107",
    "sg:province":"Danmark",
    "wof:name":"Forlag Nyt for Danmark ApS",
    "wof:placetype":"venue"
},
  "geometry": {"coordinates":[76.3070983887,14.277130127],"type":"Point"}
}