{
  "type": "Feature",
  "properties": {
    "addr:full":"Frederiks All\u00e9 26, 1. \u00c5rhus C Danmark 8000",
    "addr:housenumber":"26 1",
    "addr:postcode":"8000",
    "addr:street":"Frederiks Alle\u0301",
    "iso:country":"DK",
    "sg:address":"Frederiks All\u00e9 26, 1.",
    "sg:city":"\u00c5rhus C",
    "sg:orig_category":"Logistik",
    "sg:phone":"+45 86 10 95 22",
    "sg:postcode":"8000",
    "sg:province":"Danmark",
    "sg:website":"www.cappit.dk",
    "wof:name":"Cappit A/S",
    "wof:placetype":"venue"
},
  "geometry": {"coordinates":[10.1994009018,56.1507759094],"type":"Point"}
}