{
  "type": "Feature",
  "properties": {
    "iso:country":"DK",
    "sg:address":"N\u00f8rregade 73",
    "sg:city":"Esbjerg",
    "sg:orig_category":"Bagere",
    "sg:phone":"+45 75 12 28 66",
    "sg:postcode":"6700",
    "sg:province":"Danmark",
    "wof:name":"Guldbageren",
    "wof:placetype":"venue"
},
  "geometry": {"coordinates":[8.447114,55.47007],"type":"Point"}
}