{
  "type": "Feature",
  "properties": {
    "addr:full":"Merkurvej 3 Jyllinge Danmark 4040",
    "addr:housenumber":"3",
    "addr:postcode":"4040",
    "addr:street":"Merkurvej",
    "iso:country":"DK",
    "sg:address":"Merkurvej 3",
    "sg:city":"Jyllinge",
    "sg:orig_category":"Engros handel",
    "sg:phone":"+45 30 45 43 99",
    "sg:postcode":"4040",
    "sg:province":"Danmark",
    "wof:name":"Jyllinge Champignon Aps",
    "wof:placetype":"venue"
},
  "geometry": {"coordinates":[12.1075658798,55.7475395203],"type":"Point"}
}