{
  "type": "Feature",
  "properties": {
    "addr:full":"Algade 9 Roskilde Danmark 4000",
    "addr:housenumber":"9",
    "addr:postcode":"4000",
    "addr:street":"Algade",
    "iso:country":"DK",
    "sg:address":"Algade 9",
    "sg:city":"Roskilde",
    "sg:orig_category":"Musikinstrumenter",
    "sg:phone":"+45 46 35 06 24",
    "sg:postcode":"4000",
    "sg:province":"Danmark",
    "wof:name":"Stokvis Musik Danmark",
    "wof:placetype":"venue"
},
  "geometry": {"coordinates":[12.0825185776,55.6413078308],"type":"Point"}
}