{
  "type": "Feature",
  "properties": {
    "iso:country":"DK",
    "sg:address":"Helligkorsgade 9",
    "sg:city":"Kolding",
    "sg:orig_category":"Sko",
    "sg:phone":"+45 75 52 00 08",
    "sg:postcode":"6000",
    "sg:province":"Danmark",
    "wof:name":"Bruhn Sko / Din Gr\u00f8nne Skobutik",
    "wof:placetype":"venue"
},
  "geometry": {"coordinates":[9.4736995697,55.4892234802],"type":"Point"}
}