{
  "type": "Feature",
  "properties": {
    "addr:full":"Stolbergvej 13 Gentofte Danmark 2820",
    "addr:housenumber":"13",
    "addr:postcode":"2820",
    "addr:street":"Stolbergvej",
    "iso:country":"DK",
    "sg:address":"Stolbergvej 13",
    "sg:city":"Gentofte",
    "sg:orig_category":"CD-ROM, Forhandling af",
    "sg:phone":"+45 39 65 62 64",
    "sg:postcode":"2820",
    "sg:province":"Danmark",
    "wof:name":"PCG-Consult, Gentofte",
    "wof:placetype":"venue"
},
  "geometry": {"coordinates":[12.515704155,55.7515792847],"type":"Point"}
}