{
  "type": "Feature",
  "properties": {
    "addr:full":"Kjeldsg\u00e5rdsvej 40 Valby Danmark 2500",
    "addr:housenumber":"40",
    "addr:postcode":"2500",
    "addr:street":"Kjeldsgaardsvej",
    "iso:country":"DK",
    "sg:address":"Kjeldsg\u00e5rdsvej 40",
    "sg:city":"Valby",
    "sg:orig_category":"Diners transportables",
    "sg:phone":"+45 36 45 86 86",
    "sg:postcode":"2500",
    "sg:province":"Danmark",
    "sg:website":"www.madogvin.dk",
    "wof:name":"Mad & Vin selskabet",
    "wof:placetype":"venue"
},
  "geometry": {"coordinates":[12.5209598541,55.6608200073],"type":"Point"}
}