{
  "type": "Feature",
  "properties": {
    "addr:full":"Kollelevbakken 14 Virum Danmark 2830",
    "addr:housenumber":"14",
    "addr:postcode":"2830",
    "addr:street":"Kollelevbakken",
    "iso:country":"DK",
    "sg:address":"Kollelevbakken 14",
    "sg:city":"Virum",
    "sg:orig_category":"Fodterapeuter",
    "sg:phone":"+45 45 85 49 99",
    "sg:postcode":"2830",
    "sg:province":"Danmark",
    "wof:name":"Fodterapeuterne",
    "wof:placetype":"venue"
},
  "geometry": {"coordinates":[12.4623308182,55.7916221619],"type":"Point"}
}