{
  "type": "Feature",
  "properties": {
    "addr:full":"Attrupvej 21, Attrup Ryomg\u00e5rd Danmark 8550",
    "addr:housenumber":"21",
    "addr:postcode":"8550",
    "addr:street":"Attrupvej",
    "iso:country":"DK",
    "sg:address":"Attrupvej 21, Attrup",
    "sg:city":"Ryomg\u00e5rd",
    "sg:orig_category":"Murermestre",
    "sg:phone":"+45 86 39 45 98",
    "sg:postcode":"8550",
    "sg:province":"Danmark",
    "wof:name":"Simonsen, S\u00f8ren",
    "wof:placetype":"venue"
},
  "geometry": {"coordinates":[10.5041999817,56.3809814453],"type":"Point"}
}