{
  "type": "Feature",
  "properties": {
    "iso:country":"DK",
    "sg:address":"Eksportvej 6",
    "sg:city":"Padborg",
    "sg:orig_category":"Spedition",
    "sg:phone":"+45 73 30 23 00",
    "sg:postcode":"6330",
    "sg:province":"Danmark",
    "wof:name":"UNIQUE Transport & Spedition A/S",
    "wof:placetype":"venue"
},
  "geometry": {"coordinates":[9.3508806229,54.8353767395],"type":"Point"}
}