{
  "type": "Feature",
  "properties": {
    "iso:country":"DK",
    "sg:address":"S\u00f8nderbro 8",
    "sg:city":"Bindslev",
    "sg:orig_category":"Selskabslokaler",
    "sg:phone":"+45 98 93 88 28",
    "sg:postcode":"9881",
    "sg:province":"Danmark",
    "wof:name":"Aaen, Selskabslokalet",
    "wof:placetype":"venue"
},
  "geometry": {"coordinates":[10.1971940994,57.5394058228],"type":"Point"}
}