{
  "type": "Feature",
  "properties": {
    "addr:full":"Store Tingbakke 134 Vodskov Danmark 9310",
    "addr:housenumber":"134",
    "addr:postcode":"9310",
    "addr:street":"Tingbakke",
    "iso:country":"DK",
    "sg:address":"Store Tingbakke 134",
    "sg:city":"Vodskov",
    "sg:orig_category":"Skibskonsulenter",
    "sg:phone":"+45 98 29 21 04",
    "sg:postcode":"9310",
    "sg:province":"Danmark",
    "wof:name":"Naval Service",
    "wof:placetype":"venue"
},
  "geometry": {"coordinates":[10.0105056763,57.1092720032],"type":"Point"}
}