{
  "type": "Feature",
  "properties": {
    "addr:full":"Sejlmagerv\u00e6nget 4, Horne Hirtshals Danmark 9850",
    "addr:housenumber":"4",
    "addr:postcode":"9850",
    "addr:street":"Sejlmagervaenget;Horne",
    "iso:country":"DK",
    "sg:address":"Sejlmagerv\u00e6nget 4, Horne",
    "sg:city":"Hirtshals",
    "sg:orig_category":"Vinduespolering",
    "sg:phone":"+45 98 94 99 97",
    "sg:postcode":"9850",
    "sg:province":"Danmark",
    "wof:name":"Horne Vinduespolering",
    "wof:placetype":"venue"
},
  "geometry": {"coordinates":[9.9599866867,57.5884933472],"type":"Point"}
}