{
  "type": "Feature",
  "properties": {
    "iso:country":"DK",
    "sg:address":"Bredgade 9",
    "sg:city":"Pandrup",
    "sg:orig_category":"Glarmestre og glarmagere",
    "sg:phone":"+45 98 24 68 99",
    "sg:postcode":"9490",
    "sg:province":"Danmark",
    "wof:name":"MGS Glas",
    "wof:placetype":"venue"
},
  "geometry": {"coordinates":[9.6761198044,57.2142181396],"type":"Point"}
}