{
  "type": "Feature",
  "properties": {
    "addr:full":"N\u00f8rregade 23 Skive Danmark 7800",
    "addr:housenumber":"23",
    "addr:postcode":"7800",
    "addr:street":"Norregade",
    "iso:country":"DK",
    "sg:address":"N\u00f8rregade 23",
    "sg:city":"Skive",
    "sg:orig_category":"Gaveartikler",
    "sg:phone":"+45 97 52 11 22",
    "sg:postcode":"7800",
    "sg:province":"Danmark",
    "wof:name":"La Casa",
    "wof:placetype":"venue"
},
  "geometry": {"coordinates":[9.0276851654,56.5692977905],"type":"Point"}
}