{
  "type": "Feature",
  "properties": {
    "addr:full":"Fyrrevej 7 Helsinge Danmark 3200",
    "addr:housenumber":"7",
    "addr:postcode":"3200",
    "addr:street":"Fyrrevej",
    "iso:country":"DK",
    "sg:address":"Fyrrevej 7",
    "sg:city":"Helsinge",
    "sg:orig_category":"Frugt en gros",
    "sg:phone":"+45 48 79 37 67",
    "sg:postcode":"3200",
    "sg:province":"Danmark",
    "wof:name":"Frugt & Gr\u00f8ntbussen",
    "wof:placetype":"venue"
},
  "geometry": {"coordinates":[12.1899385452,56.0177497864],"type":"Point"}
}