{
  "type": "Feature",
  "properties": {
    "addr:full":"Springvandspladsen 2 A Hj\u00f8rring Danmark 9800",
    "addr:housenumber":"2 a",
    "addr:postcode":"9800",
    "addr:street":"Springvandspladsen",
    "iso:country":"DK",
    "sg:address":"Springvandspladsen 2 A",
    "sg:city":"Hj\u00f8rring",
    "sg:orig_category":"Forsikringer",
    "sg:phone":"+45 70 11 25 25",
    "sg:postcode":"9800",
    "sg:province":"Danmark",
    "wof:name":"Danica Pension",
    "wof:placetype":"venue"
},
  "geometry": {"coordinates":[29.7519645691,70.07415008540001],"type":"Point"}
}