{
  "type": "Feature",
  "properties": {
    "addr:full":"Bl\u00e5g\u00e5rdsgade 44, 1.tv. K\u00f8benhavn N Danmark 2200",
    "addr:housenumber":"44",
    "addr:postcode":"2200",
    "addr:street":"Blaagaardsgade;Kobenhavn N Danmark",
    "iso:country":"DK",
    "sg:address":"Bl\u00e5g\u00e5rdsgade 44, 1.tv.",
    "sg:city":"K\u00f8benhavn N",
    "sg:orig_category":"Kurerservice",
    "sg:phone":"+45 20 66 87 70",
    "sg:postcode":"2200",
    "sg:province":"Danmark",
    "wof:name":"EEE Budcentral",
    "wof:placetype":"venue"
},
  "geometry": {"coordinates":[-97.77504730219999,47.7084159851],"type":"Point"}
}