{
  "type": "Feature",
  "properties": {
    "addr:full":"Boulevarden 21 Vejle Danmark 7100",
    "addr:housenumber":"21",
    "addr:postcode":"7100",
    "addr:street":"Boulevarden",
    "iso:country":"DK",
    "sg:address":"Boulevarden 21",
    "sg:city":"Vejle",
    "sg:orig_category":"Maskinfabrikker",
    "sg:phone":"+45 75 82 05 88",
    "sg:postcode":"7100",
    "sg:province":"Danmark",
    "sg:website":"www.gustav-oestergaard.dk",
    "wof:name":"\u00d8stergaards Maskinfabrik A/S, Gustav",
    "wof:placetype":"venue"
},
  "geometry": {"coordinates":[9.5231122971,55.7080955505],"type":"Point"}
}