{
  "type": "Feature",
  "properties": {
    "iso:country":"DK",
    "sg:address":"Enghave Plads 8",
    "sg:city":"K\u00f8benhavn",
    "sg:orig_category":"Sportsartikler",
    "sg:phone":"+45 33 23 04 42",
    "sg:postcode":"1670",
    "sg:province":"Danmark",
    "wof:name":"3 Bj\u00f8rne Sport",
    "wof:placetype":"venue"
},
  "geometry": {"coordinates":[12.5459003448,55.6660003662],"type":"Point"}
}