{
  "type": "Feature",
  "properties": {
    "iso:country":"DK",
    "sg:address":"Kronprinsensgade 24",
    "sg:city":"Esbjerg",
    "sg:orig_category":"Glarmestre og glarmagere",
    "sg:phone":"+45 75 12 06 61",
    "sg:postcode":"6700",
    "sg:province":"Danmark",
    "sg:website":"www.fredegodthomsen.dk",
    "wof:name":"Fredegod-Thomsen & S\u00f8nner",
    "wof:placetype":"venue"
},
  "geometry": {"coordinates":[8.445315361,55.4672355652],"type":"Point"}
}