{
  "type": "Feature",
  "properties": {
    "addr:full":"Metodistkirken, Vissingsgade 15 Vejle Danmark 7100",
    "addr:housenumber":"15",
    "addr:postcode":"7100",
    "addr:street":"Vissingsgade",
    "iso:country":"DK",
    "sg:address":"Metodistkirken, Vissingsgade 15",
    "sg:city":"Vejle",
    "sg:orig_category":"Musik og sang",
    "sg:postcode":"7100",
    "sg:province":"Danmark",
    "wof:name":"Musikalsk legestue, Mulerne",
    "wof:placetype":"venue"
},
  "geometry": {"coordinates":[9.5368051529,55.7113952637],"type":"Point"}
}