{
  "type": "Feature",
  "properties": {
    "addr:full":"H\u00f8jagervej 6 A, K\u00e6rby Gjerlev Danmark 8983",
    "addr:housenumber":"6 a",
    "addr:postcode":"8983",
    "addr:street":"Hojagervej;Kaerby Gjerlev Danmark",
    "iso:country":"DK",
    "sg:address":"H\u00f8jagervej 6 A, K\u00e6rby",
    "sg:city":"Gjerlev",
    "sg:orig_category":"Zoneterapeuter",
    "sg:phone":"+45 98 55 00 12",
    "sg:postcode":"8983",
    "sg:province":"Danmark",
    "wof:name":"K\u00e6rby Zoneterapi",
    "wof:placetype":"venue"
},
  "geometry": {"coordinates":[10.1887750626,56.5788421631],"type":"Point"}
}