{
  "type": "Feature",
  "properties": {
    "addr:full":"Hjulmagervej 2 Thisted Danmark 7700",
    "addr:housenumber":"2",
    "addr:postcode":"7700",
    "addr:street":"Hjulmagervej",
    "iso:country":"DK",
    "sg:address":"Hjulmagervej 2",
    "sg:city":"Thisted",
    "sg:orig_category":"Autoforhandlere",
    "sg:phone":"+45 96 17 23 88",
    "sg:postcode":"7700",
    "sg:province":"Danmark",
    "sg:website":"www.thybo-biler.dk",
    "wof:name":"Thybo Biler",
    "wof:placetype":"venue"
},
  "geometry": {"coordinates":[8.6451215744,56.9375457764],"type":"Point"}
}