{
  "type": "Feature",
  "properties": {
    "addr:full":"Hannenovvej 15, Taaderup Nyk\u00f8bing Danmark 4800",
    "addr:housenumber":"15",
    "addr:postcode":"4800",
    "addr:street":"Hannenovvej",
    "iso:country":"DK",
    "sg:address":"Hannenovvej 15, Taaderup",
    "sg:city":"Nyk\u00f8bing",
    "sg:orig_category":"Betonelementer",
    "sg:phone":"+45 54 41 85 00",
    "sg:postcode":"4800",
    "sg:province":"Danmark",
    "wof:name":"Leo Nielsen Elementfabrik A/S",
    "wof:placetype":"venue"
},
  "geometry": {"coordinates":[11.867854,54.769241],"type":"Point"}
}