{
  "type": "Feature",
  "properties": {
    "addr:full":"\u00d8stergade 58 Assens Danmark 5610",
    "addr:housenumber":"58",
    "addr:postcode":"5610",
    "addr:street":"Ostergade",
    "iso:country":"DK",
    "sg:address":"\u00d8stergade 58",
    "sg:city":"Assens",
    "sg:orig_category":"Garn",
    "sg:phone":"+45 64 71 12 72",
    "sg:postcode":"5610",
    "sg:province":"Danmark",
    "wof:name":"Sy og Strik",
    "wof:placetype":"venue"
},
  "geometry": {"coordinates":[9.8987045288,55.2700271606],"type":"Point"}
}