{
  "type": "Feature",
  "properties": {
    "iso:country":"DK",
    "sg:address":"Valdemarsvej 3 B",
    "sg:city":"Randers",
    "sg:orig_category":"Slagter og viktualie",
    "sg:phone":"+45 86 42 31 97",
    "sg:postcode":"8900",
    "sg:province":"Danmark",
    "wof:name":"Valdemarsvejs K\u00f8dudsalg",
    "wof:placetype":"venue"
},
  "geometry": {"coordinates":[10.054151535,56.4470481873],"type":"Point"}
}