{
  "type": "Feature",
  "properties": {
    "iso:country":"DK",
    "sg:address":"Strandvejen 20",
    "sg:city":"Aalborg",
    "sg:orig_category":"Arkitekter",
    "sg:phone":"+45 98 16 20 11",
    "sg:postcode":"9000",
    "sg:province":"Danmark",
    "wof:name":"Venndt A/S, Arkitekterne",
    "wof:placetype":"venue"
},
  "geometry": {"coordinates":[9.9095611572,57.0538711548],"type":"Point"}
}