{
  "type": "Feature",
  "properties": {
    "addr:full":"Skovdalsvej 3 K\u00f8ge Danmark 4600",
    "addr:housenumber":"3",
    "addr:postcode":"4600",
    "addr:street":"Skovdalsvej",
    "iso:country":"DK",
    "sg:address":"Skovdalsvej 3",
    "sg:city":"K\u00f8ge",
    "sg:orig_category":"Malermestre",
    "sg:phone":"+45 56 65 98 77",
    "sg:postcode":"4600",
    "sg:province":"Danmark",
    "wof:name":"Erik Petersen ApS",
    "wof:placetype":"venue"
},
  "geometry": {"coordinates":[12.1818380356,55.4918746948],"type":"Point"}
}