{
  "type": "Feature",
  "properties": {
    "addr:full":"Marielyst Strandvej 50 V\u00e6ggerl\u00f8se Danmark 4873",
    "addr:housenumber":"50",
    "addr:postcode":"4873",
    "addr:street":"Marielyst Strandvej",
    "iso:country":"DK",
    "sg:address":"Marielyst Strandvej 50",
    "sg:city":"V\u00e6ggerl\u00f8se",
    "sg:classifiers":[
        {
            "category":"Restaurant",
            "type":"Food & Drink"
        }
    ],
    "sg:phone":"+45 54 13 28 29",
    "sg:postcode":"4873",
    "sg:province":"Danmark",
    "wof:name":"Himmelbl\u00e5, Caf\u00e9",
    "wof:placetype":"venue"
},
  "geometry": {"coordinates":[11.9238767624,54.7119483948],"type":"Point"}
}