{
  "type": "Feature",
  "properties": {
    "addr:full":"R\u00e6dersgade 4 Horsens Danmark 8700",
    "addr:housenumber":"4",
    "addr:postcode":"8700",
    "addr:street":"Raedersgade",
    "iso:country":"DK",
    "sg:address":"R\u00e6dersgade 4",
    "sg:city":"Horsens",
    "sg:orig_category":"Advokater",
    "sg:phone":"+45 75 62 16 44",
    "sg:postcode":"8700",
    "sg:province":"Danmark",
    "wof:name":"Advodan",
    "wof:placetype":"venue"
},
  "geometry": {"coordinates":[9.8460350037,55.8637657166],"type":"Point"}
}