{
  "type": "Feature",
  "properties": {
    "addr:full":"Leder: Niels Kjeldsen, Rosenholmvej 70 Hornslet Danmark 8543",
    "addr:housenumber":"70",
    "addr:postcode":"8543",
    "addr:street":"Rosenholmvej",
    "iso:country":"DK",
    "sg:address":"Leder: Niels Kjeldsen, Rosenholmvej 70",
    "sg:city":"Hornslet",
    "sg:orig_category":"Oplysningsforbund",
    "sg:phone":"+45 86 99 52 04",
    "sg:postcode":"8543",
    "sg:province":"Danmark",
    "wof:name":"LOF Rosenholm",
    "wof:placetype":"venue"
},
  "geometry": {"coordinates":[10.3180999756,56.3159866333],"type":"Point"}
}