{
  "type": "Feature",
  "properties": {
    "addr:full":"Plantagevej 22 Ribe Danmark 6760",
    "addr:housenumber":"22",
    "addr:postcode":"6760",
    "addr:street":"Plantagevej",
    "iso:country":"DK",
    "sg:address":"Plantagevej 22",
    "sg:city":"Ribe",
    "sg:orig_category":"Grillbarer",
    "sg:phone":"+45 75 42 22 04",
    "sg:postcode":"6760",
    "sg:province":"Danmark",
    "wof:name":"Skovgrillen Ribe",
    "wof:placetype":"venue"
},
  "geometry": {"coordinates":[8.7729654312,55.3389358521],"type":"Point"}
}