{
  "type": "Feature",
  "properties": {
    "addr:full":"Gl. Vardevej 20 Esbjerg Danmark 6700",
    "addr:housenumber":"20",
    "addr:postcode":"6700",
    "addr:street":"Gl. Vardevej",
    "iso:country":"DK",
    "sg:address":"Gl. Vardevej 20",
    "sg:city":"Esbjerg",
    "sg:classifiers":[
        {
            "category":"Restaurant",
            "type":"Food & Drink"
        }
    ],
    "sg:phone":"+45 75 45 17 21",
    "sg:postcode":"6700",
    "sg:province":"Danmark",
    "wof:name":"Corners Pub",
    "wof:placetype":"venue"
},
  "geometry": {"coordinates":[8.4366579056,55.475440979],"type":"Point"}
}