{
  "type": "Feature",
  "properties": {
    "iso:country":"DK",
    "sg:address":"J. F. Willumsens Vej 40, Engb\u00e6k",
    "sg:city":"Frederikssund",
    "sg:orig_category":"Totalentreprise",
    "sg:phone":"+45 47 38 38 95",
    "sg:postcode":"3600",
    "sg:province":"Danmark",
    "wof:name":"HS Byggeentreprise ApS",
    "wof:placetype":"venue"
},
  "geometry": {"coordinates":[12.0661621094,55.8370323181],"type":"Point"}
}