{
  "type": "Feature",
  "properties": {
    "addr:full":"Lyngbygade 28 Silkeborg Danmark 8600",
    "addr:housenumber":"28",
    "addr:postcode":"8600",
    "addr:street":"Lyngbygade",
    "iso:country":"DK",
    "sg:address":"Lyngbygade 28",
    "sg:city":"Silkeborg",
    "sg:orig_category":"Faglige organisationer og foreninger",
    "sg:phone":"+45 86 82 06 44",
    "sg:postcode":"8600",
    "sg:province":"Danmark",
    "sg:website":"home6.inet.tele.dk/metalsil/",
    "wof:name":"Dansk Metalarbejderforbund",
    "wof:placetype":"venue"
},
  "geometry": {"coordinates":[9.5470743179,56.1625442505],"type":"Point"}
}