{
  "type": "Feature",
  "properties": {
    "iso:country":"DK",
    "sg:address":"Herreg\u00e5rdsalle 6, Nysted",
    "sg:city":"Thors\u00f8",
    "sg:orig_category":"Blomsterhandlere",
    "sg:phone":"+45 86 87 14 65",
    "sg:postcode":"8881",
    "sg:province":"Danmark",
    "wof:name":"Nysted Blomster",
    "wof:placetype":"venue"
},
  "geometry": {"coordinates":[-86.71593475340001,32.916103363],"type":"Point"}
}