{
  "type": "Feature",
  "properties": {
    "addr:full":"Kongebrogade 13 Kolding Danmark 6000",
    "addr:housenumber":"13",
    "addr:postcode":"6000",
    "addr:street":"Kongebrogade",
    "iso:country":"DK",
    "sg:address":"Kongebrogade 13",
    "sg:city":"Kolding",
    "sg:orig_category":"Kiosker",
    "sg:phone":"+45 75 53 99 75",
    "sg:postcode":"6000",
    "sg:province":"Danmark",
    "wof:name":"Bixen",
    "wof:placetype":"venue"
},
  "geometry": {"coordinates":[9.4777784348,55.4871673584],"type":"Point"}
}