{
  "type": "Feature",
  "properties": {
    "addr:full":"Prinsessegade 4 B K\u00f8benhavn Danmark 1422",
    "addr:housenumber":"4 b",
    "addr:postcode":"1422",
    "addr:street":"Prinsessegade",
    "iso:country":"DK",
    "sg:address":"Prinsessegade 4 B",
    "sg:city":"K\u00f8benhavn",
    "sg:orig_category":"Alternativ behandling",
    "sg:phone":"+45 32 95 69 18",
    "sg:postcode":"1422",
    "sg:province":"Danmark",
    "wof:name":"M\u00fchlhausen's Hom\u00f8opatiske Klinik, Eva",
    "wof:placetype":"venue"
},
  "geometry": {"coordinates":[12.6005001068,55.6741981506],"type":"Point"}
}