{
  "type": "Feature",
  "properties": {
    "addr:full":"Stenagervej 3, 1. Roskilde Danmark 4000",
    "addr:housenumber":"3 1",
    "addr:postcode":"4000",
    "addr:street":"Stenagervej",
    "iso:country":"DK",
    "sg:address":"Stenagervej 3, 1.",
    "sg:city":"Roskilde",
    "sg:orig_category":"Fotolaboratorier",
    "sg:phone":"+45 46 32 50 35",
    "sg:postcode":"4000",
    "sg:province":"Danmark",
    "wof:name":"Roskilde Fotolab ApS",
    "wof:placetype":"venue"
},
  "geometry": {"coordinates":[12.1122589111,55.6418800354],"type":"Point"}
}