{
  "type": "Feature",
  "properties": {
    "addr:full":"N\u00f8rreskov Bakke 1 Silkeborg Danmark 8600",
    "addr:housenumber":"1",
    "addr:postcode":"8600",
    "addr:street":"Norreskov Bakke",
    "iso:country":"DK",
    "sg:address":"N\u00f8rreskov Bakke 1",
    "sg:city":"Silkeborg",
    "sg:orig_category":"Asfalt",
    "sg:phone":"+45 87 22 15 00",
    "sg:postcode":"8600",
    "sg:province":"Danmark",
    "sg:website":"www.icopal.dk",
    "wof:name":"LEMMINK\u00c4INEN A/S",
    "wof:placetype":"venue"
},
  "geometry": {"coordinates":[9.5771255493,56.1890411377],"type":"Point"}
}