{
  "type": "Feature",
  "properties": {
    "iso:country":"DK",
    "sg:address":"Duvad Bro Vej 6, \u00d8ls",
    "sg:city":"Hobro",
    "sg:orig_category":"Hunde",
    "sg:phone":"+45 98 52 47 27",
    "sg:postcode":"9500",
    "sg:province":"Danmark",
    "wof:name":"Duvadg\u00e5rds Hundecenter",
    "wof:placetype":"venue"
},
  "geometry": {"coordinates":[9.7946596146,56.6382789612],"type":"Point"}
}