{
  "type": "Feature",
  "properties": {
    "iso:country":"DK",
    "sg:address":"Stenderupvej 125, Stenderup",
    "sg:city":"S\u00f8nder Stenderup",
    "sg:orig_category":"Gallerier",
    "sg:phone":"+45 75 57 14 75",
    "sg:postcode":"6092",
    "sg:province":"Danmark",
    "sg:website":"www.ateljes.com",
    "wof:name":"Ateljes",
    "wof:placetype":"venue"
},
  "geometry": {"coordinates":[9.6103696823,55.4608459473],"type":"Point"}
}