{
  "type": "Feature",
  "properties": {
    "iso:country":"DK",
    "sg:address":"Bagsv\u00e6rd M\u00f8llevej 9",
    "sg:city":"Kongens Lyngby",
    "sg:orig_category":"Omsorgscentre",
    "sg:phone":"+45 39 57 47 01",
    "sg:postcode":"2800",
    "sg:province":"Danmark",
    "wof:name":"Omsorgscentret M\u00f8lleg\u00e5rden",
    "wof:placetype":"venue"
},
  "geometry": {"coordinates":[12.5368299484,55.7949905396],"type":"Point"}
}