{
  "type": "Feature",
  "properties": {
    "iso:country":"DK",
    "sg:address":"Sognepr\u00e6st: Vinni Gaarn-Larsen, Frederiksmindevej 9, Fuglse",
    "sg:city":"Holeby",
    "sg:orig_category":"Kirkesogne",
    "sg:phone":"+45 54 60 63 61",
    "sg:postcode":"4960",
    "sg:province":"Danmark",
    "wof:name":"Fuglse-Kr\u00f8nge og Torslunde sogne",
    "wof:placetype":"venue"
},
  "geometry": {"coordinates":[11.4715652466,54.7092895508],"type":"Point"}
}