{
  "type": "Feature",
  "properties": {
    "addr:full":"Granh\u00f8jvej 8 Silkeborg Danmark 8600",
    "addr:housenumber":"8",
    "addr:postcode":"8600",
    "addr:street":"Granhojvej",
    "iso:country":"DK",
    "sg:address":"Granh\u00f8jvej 8",
    "sg:city":"Silkeborg",
    "sg:orig_category":"Asylcentre",
    "sg:phone":"+45 86 81 81 88",
    "sg:postcode":"8600",
    "sg:province":"Danmark",
    "wof:name":"Dansk R\u00f8de Kors",
    "wof:placetype":"venue"
},
  "geometry": {"coordinates":[9.5799398422,56.1872177124],"type":"Point"}
}