{
  "type": "Feature",
  "properties": {
    "addr:full":"Brob\u00e6ksgade 2 Slangerup Danmark 3550",
    "addr:housenumber":"2",
    "addr:postcode":"3550",
    "addr:street":"Brobaeksgade",
    "iso:country":"DK",
    "sg:address":"Brob\u00e6ksgade 2",
    "sg:city":"Slangerup",
    "sg:orig_category":"Renserier",
    "sg:phone":"+45 47 33 30 05",
    "sg:postcode":"3550",
    "sg:province":"Danmark",
    "wof:name":"E -Rens",
    "wof:placetype":"venue"
},
  "geometry": {"coordinates":[12.1709594727,55.8442993164],"type":"Point"}
}