{
  "type": "Feature",
  "properties": {
    "addr:full":"Nordre Fasanvej 204 Frederiksberg Danmark 2000",
    "addr:housenumber":"204",
    "addr:postcode":"2000",
    "addr:street":"Nordre Fasanvej",
    "iso:country":"DK",
    "sg:address":"Nordre Fasanvej 204",
    "sg:city":"Frederiksberg",
    "sg:orig_category":"Autoreparation og -service",
    "sg:phone":"+45 38 34 70 62",
    "sg:postcode":"2000",
    "sg:province":"Danmark",
    "wof:name":"Frederiksberg Auto",
    "wof:placetype":"venue"
},
  "geometry": {"coordinates":[12.5357513428,55.6970939636],"type":"Point"}
}