{
  "type": "Feature",
  "properties": {
    "addr:full":"Gerritsgade 22 B, 1 sal Svendborg Danmark 5700",
    "addr:housenumber":"22 b 1 sal",
    "addr:postcode":"5700",
    "addr:street":"Gerritsgade",
    "iso:country":"DK",
    "sg:address":"Gerritsgade 22 B, 1 sal",
    "sg:city":"Svendborg",
    "sg:orig_category":"\u00c3\u02dcvrige foreninger",
    "sg:phone":"+45 51 96 32 72",
    "sg:postcode":"5700",
    "sg:province":"Danmark",
    "wof:name":"Single Klubben Evig Glad",
    "wof:placetype":"venue"
},
  "geometry": {"coordinates":[10.6065101624,55.0595970154],"type":"Point"}
}