{
  "type": "Feature",
  "properties": {
    "addr:full":"Fmd.: Jens Nygaard Jensen, Langk\u00e6rvej 43 Brande Danmark 7330",
    "addr:housenumber":"43",
    "addr:postcode":"7330",
    "addr:street":"Langkaervej",
    "iso:country":"DK",
    "sg:address":"Fmd.: Jens Nygaard Jensen, Langk\u00e6rvej 43",
    "sg:city":"Brande",
    "sg:orig_category":"Kulturelle foreninger",
    "sg:phone":"+45 97 18 20 42",
    "sg:postcode":"7330",
    "sg:province":"Danmark",
    "wof:name":"Arbejdernes Oplysningsforbund AOF",
    "wof:placetype":"venue"
},
  "geometry": {"coordinates":[9.1280345917,55.942779541],"type":"Point"}
}