{
  "type": "Feature",
  "properties": {
    "addr:full":"Miehesgade 78 Arden Danmark 9510",
    "addr:housenumber":"78",
    "addr:postcode":"9510",
    "addr:street":"Miehesgade",
    "iso:country":"DK",
    "sg:address":"Miehesgade 78",
    "sg:city":"Arden",
    "sg:orig_category":"INGENI\u00c3\u02dcRER",
    "sg:phone":"+45 98 56 26 29",
    "sg:postcode":"9510",
    "sg:province":"Danmark",
    "wof:name":"JBH Contech",
    "wof:placetype":"venue"
},
  "geometry": {"coordinates":[9.8646945953,56.7726020813],"type":"Point"}
}