{
  "type": "Feature",
  "properties": {
    "addr:full":"Mosekrogen 36 Vinderup Danmark 7830",
    "addr:housenumber":"36",
    "addr:postcode":"7830",
    "addr:street":"Mosekrogen",
    "iso:country":"DK",
    "sg:address":"Mosekrogen 36",
    "sg:city":"Vinderup",
    "sg:orig_category":"El-automatik",
    "sg:phone":"+45 97 44 25 05",
    "sg:postcode":"7830",
    "sg:province":"Danmark",
    "wof:name":"Suntech",
    "wof:placetype":"venue"
},
  "geometry": {"coordinates":[8.7744379044,56.4815559387],"type":"Point"}
}