{
  "type": "Feature",
  "properties": {
    "addr:full":"Generatorv. 9  Herlev Danmark 2730",
    "addr:housenumber":"9",
    "addr:postcode":"2730",
    "addr:street":"Generatorv.",
    "iso:country":"DK",
    "sg:address":"Generatorv. 9 ",
    "sg:city":"Herlev",
    "sg:classifiers":[
        {
            "category":"Travel",
            "subcategory":"Travel Agent",
            "type":"Entertainment"
        }
    ],
    "sg:phone":"+45 44 92 98 00",
    "sg:postcode":"2730",
    "sg:province":"Danmark",
    "sg:tags":[
        "business"
    ],
    "wof:name":"TELETECH CONGRESS SERVICE A/S",
    "wof:placetype":"venue"
},
  "geometry": {"coordinates":[12.4674987793,55.7301368713],"type":"Point"}
}