{
  "type": "Feature",
  "properties": {
    "addr:full":"Lyngby Hovedgade 80 Kongens Lyngby Danmark 2800",
    "addr:housenumber":"80",
    "addr:postcode":"2800",
    "addr:street":"Lyngby Hovedgade",
    "iso:country":"DK",
    "sg:address":"Lyngby Hovedgade 80",
    "sg:city":"Kongens Lyngby",
    "sg:classifiers":[
        {
            "category":"Communications",
            "type":"Services"
        }
    ],
    "sg:phone":"+45 45 87 86 00",
    "sg:postcode":"2800",
    "sg:province":"Danmark",
    "sg:tags":[
        "og",
        "tv",
        "radio"
    ],
    "wof:name":"Bang & Olufsen",
    "wof:placetype":"venue"
},
  "geometry": {"coordinates":[12.5055370331,55.7687072754],"type":"Point"}
}