{
  "type": "Feature",
  "properties": {
    "addr:full":"Mimersvej 23 Viborg Danmark 8800",
    "addr:housenumber":"23",
    "addr:postcode":"8800",
    "addr:street":"Mimersvej",
    "iso:country":"DK",
    "sg:address":"Mimersvej 23",
    "sg:city":"Viborg",
    "sg:orig_category":"EDB - udstyr",
    "sg:phone":"+45 86 60 00 71",
    "sg:postcode":"8800",
    "sg:province":"Danmark",
    "wof:name":"UG Data",
    "wof:placetype":"venue"
},
  "geometry": {"coordinates":[9.4191846848,56.4700698853],"type":"Point"}
}