{
  "type": "Feature",
  "properties": {
    "iso:country":"DK",
    "sg:address":"Hedvigslundsvej 2",
    "sg:city":"Odense C",
    "sg:orig_category":"Autoelektro",
    "sg:phone":"+45 66 13 25 60",
    "sg:postcode":"5000",
    "sg:province":"Danmark",
    "wof:name":"Odense Auto-El ApS",
    "wof:placetype":"venue"
},
  "geometry": {"coordinates":[10.3863449097,55.4236297607],"type":"Point"}
}