{
  "type": "Feature",
  "properties": {
    "addr:full":"Glarmestervej 47 Slagelse Danmark 4200",
    "addr:housenumber":"47",
    "addr:postcode":"4200",
    "addr:street":"Glarmestervej",
    "iso:country":"DK",
    "sg:address":"Glarmestervej 47",
    "sg:city":"Slagelse",
    "sg:classifiers":[
        {
            "category":"Personal",
            "subcategory":"Massage",
            "type":"Services"
        }
    ],
    "sg:phone":"+45 58 53 23 34",
    "sg:postcode":"4200",
    "sg:province":"Danmark",
    "wof:name":"Andersen, Bente S\u00f8e",
    "wof:placetype":"venue"
},
  "geometry": {"coordinates":[11.3696746826,55.4136390686],"type":"Point"}
}