{
  "type": "Feature",
  "properties": {
    "addr:full":"Holmensvej 7 A Frederikssund Danmark 3600",
    "addr:housenumber":"7 a",
    "addr:postcode":"3600",
    "addr:street":"Holmensvej",
    "iso:country":"DK",
    "sg:address":"Holmensvej 7 A",
    "sg:city":"Frederikssund",
    "sg:orig_category":"Autolakering",
    "sg:phone":"+45 47 31 19 58",
    "sg:postcode":"3600",
    "sg:province":"Danmark",
    "wof:name":"Nielsen, Jan",
    "wof:placetype":"venue"
},
  "geometry": {"coordinates":[12.069018364,55.8477859497],"type":"Point"}
}