{
  "type": "Feature",
  "properties": {
    "addr:full":"Sportsvej 2, Arnborg Herning Danmark 7400",
    "addr:housenumber":"2",
    "addr:postcode":"7400",
    "addr:street":"Sportsvej;Arnborg",
    "iso:country":"DK",
    "sg:address":"Sportsvej 2, Arnborg",
    "sg:city":"Herning",
    "sg:orig_category":"Autoreparation og -service",
    "sg:phone":"+45 97 14 98 60",
    "sg:postcode":"7400",
    "sg:province":"Danmark",
    "wof:name":"Monzes Auto",
    "wof:placetype":"venue"
},
  "geometry": {"coordinates":[8.9768896103,56.1374168396],"type":"Point"}
}