{
  "type": "Feature",
  "properties": {
    "addr:full":"Vestergade 28 Vojens Danmark 6500",
    "addr:housenumber":"28",
    "addr:postcode":"6500",
    "addr:street":"Vestergade",
    "iso:country":"DK",
    "sg:address":"Vestergade 28",
    "sg:city":"Vojens",
    "sg:orig_category":"Malermestre",
    "sg:phone":"+45 73 54 35 43",
    "sg:postcode":"6500",
    "sg:province":"Danmark",
    "sg:website":"www.matthiesens-malerfirma.dk",
    "wof:name":"Matthiesen's Malerfirma ApS",
    "wof:placetype":"venue"
},
  "geometry": {"coordinates":[9.3000621796,55.2460632324],"type":"Point"}
}