{
  "type": "Feature",
  "properties": {
    "addr:full":"Strandvangen 4 Kerteminde Danmark 5300",
    "addr:housenumber":"4",
    "addr:postcode":"5300",
    "addr:street":"Strandvangen",
    "iso:country":"DK",
    "sg:address":"Strandvangen 4",
    "sg:city":"Kerteminde",
    "sg:orig_category":"Slagterier",
    "sg:phone":"+45 65 32 44 34",
    "sg:postcode":"5300",
    "sg:province":"Danmark",
    "wof:name":"Olsen Oksek\u00f8d ApS, Hans",
    "wof:placetype":"venue"
},
  "geometry": {"coordinates":[10.6502485275,55.4598388672],"type":"Point"}
}