{
  "type": "Feature",
  "properties": {
    "addr:full":"Kongensgade 66 Slangerup Danmark 3550",
    "addr:housenumber":"66",
    "addr:postcode":"3550",
    "addr:street":"Kongensgade",
    "iso:country":"DK",
    "sg:address":"Kongensgade 66",
    "sg:city":"Slangerup",
    "sg:orig_category":"Landbrugsmaskiner",
    "sg:phone":"+45 47 33 43 04",
    "sg:postcode":"3550",
    "sg:province":"Danmark",
    "wof:name":"Firh\u00f8js Maskinstation",
    "wof:placetype":"venue"
},
  "geometry": {"coordinates":[12.1732988358,55.8525428772],"type":"Point"}
}