{
  "type": "Feature",
  "properties": {
    "addr:full":"Storegade 20 Aabenraa Danmark 6200",
    "addr:housenumber":"20",
    "addr:postcode":"6200",
    "addr:street":"Storegade",
    "iso:country":"DK",
    "sg:address":"Storegade 20",
    "sg:city":"Aabenraa",
    "sg:orig_category":"Metervarer",
    "sg:phone":"+45 74 62 45 11",
    "sg:postcode":"6200",
    "sg:province":"Danmark",
    "wof:name":"Saksen",
    "wof:placetype":"venue"
},
  "geometry": {"coordinates":[9.4185209274,55.0437927246],"type":"Point"}
}