{
  "type": "Feature",
  "properties": {
    "addr:full":"Sundforvalter: Martin Heltborg, D\u00e6mningen 44, Fannerup Kolind Danmark 8560",
    "addr:housenumber":"44",
    "addr:postcode":"8560",
    "addr:street":"Daemningen",
    "iso:country":"DK",
    "sg:address":"Sundforvalter: Martin Heltborg, D\u00e6mningen 44, Fannerup",
    "sg:city":"Kolind",
    "sg:orig_category":"\u00c3\u02dcvrige foreninger",
    "sg:phone":"+45 86 33 90 13",
    "sg:postcode":"8560",
    "sg:province":"Danmark",
    "wof:name":"Pumpelaget Kolindsund",
    "wof:placetype":"venue"
},
  "geometry": {"coordinates":[10.5873975754,56.3618812561],"type":"Point"}
}