{
  "type": "Feature",
  "properties": {
    "iso:country":"DK",
    "sg:address":"Algade 12",
    "sg:city":"Vordingborg",
    "sg:orig_category":"Revisorer",
    "sg:phone":"+45 55 36 51 00",
    "sg:postcode":"4760",
    "sg:province":"Danmark",
    "wof:name":"P. R. Revision Registreret Revisionsaktieselskab",
    "wof:placetype":"venue"
},
  "geometry": {"coordinates":[11.9017782211,55.0122833252],"type":"Point"}
}