{
  "type": "Feature",
  "properties": {
    "iso:country":"DK",
    "sg:address":"\u00c5lholm Plads 7",
    "sg:city":"Valby",
    "sg:orig_category":"Blomsterhandlere",
    "sg:phone":"+45 36 46 87 67",
    "sg:postcode":"2500",
    "sg:province":"Danmark",
    "sg:website":"www.interflora.dk",
    "wof:name":"Blomsterkomponisten",
    "wof:placetype":"venue"
},
  "geometry": {"coordinates":[12.4894895554,55.672000885],"type":"Point"}
}