{
  "type": "Feature",
  "properties": {
    "addr:full":"Indre Ringvej 8 Aarup Danmark 5560",
    "addr:housenumber":"8",
    "addr:postcode":"5560",
    "addr:street":"Indre Ringvej",
    "iso:country":"DK",
    "sg:address":"Indre Ringvej 8",
    "sg:city":"Aarup",
    "sg:orig_category":"Plejehjem",
    "sg:phone":"+45 64 43 35 00",
    "sg:postcode":"5560",
    "sg:province":"Danmark",
    "wof:name":"Sundhedsafdelingen i Aarup",
    "wof:placetype":"venue"
},
  "geometry": {"coordinates":[10.0493068695,55.376739502],"type":"Point"}
}