{
  "type": "Feature",
  "properties": {
    "addr:full":"Neptunvej 1 Kongerslev Danmark 9293",
    "addr:housenumber":"1",
    "addr:postcode":"9293",
    "addr:street":"Neptunvej",
    "iso:country":"DK",
    "sg:address":"Neptunvej 1",
    "sg:city":"Kongerslev",
    "sg:orig_category":"Isolering",
    "sg:phone":"+45 98 33 18 22",
    "sg:postcode":"9293",
    "sg:province":"Danmark",
    "wof:name":"Nielsen Kongerslev ApS, Carl",
    "wof:placetype":"venue"
},
  "geometry": {"coordinates":[10.1163511276,56.8831748962],"type":"Point"}
}