{
  "type": "Feature",
  "properties": {
    "addr:full":"Violvej 8 Ry Danmark 8680",
    "addr:housenumber":"8",
    "addr:postcode":"8680",
    "addr:street":"Violvej",
    "iso:country":"DK",
    "sg:address":"Violvej 8",
    "sg:city":"Ry",
    "sg:orig_category":"Fotografer",
    "sg:phone":"+45 86 89 31 39",
    "sg:postcode":"8680",
    "sg:province":"Danmark",
    "wof:name":"Weiling Fotografi",
    "wof:placetype":"venue"
},
  "geometry": {"coordinates":[9.7742023468,56.0870399475],"type":"Point"}
}