{
  "type": "Feature",
  "properties": {
    "addr:full":"\u00d8ver\u00f8dvej 21, 2. Holte Danmark 2840",
    "addr:housenumber":"21 2",
    "addr:postcode":"2840",
    "addr:street":"Overodvej",
    "iso:country":"DK",
    "sg:address":"\u00d8ver\u00f8dvej 21, 2.",
    "sg:city":"Holte",
    "sg:orig_category":"Regnskabsassistance",
    "sg:phone":"+45 45 41 08 78",
    "sg:postcode":"2840",
    "sg:province":"Danmark",
    "wof:name":"Carlsen, Randi",
    "wof:placetype":"venue"
},
  "geometry": {"coordinates":[12.4706554413,55.8122367859],"type":"Point"}
}