{
  "type": "Feature",
  "properties": {
    "iso:country":"DK",
    "sg:address":"Nyg\u00e5rdsvej 112 A",
    "sg:city":"Esbjerg",
    "sg:orig_category":"Integrerede institutioner",
    "sg:phone":"+45 75 13 00 77",
    "sg:postcode":"6700",
    "sg:province":"Danmark",
    "wof:name":"Nyg\u00e5rdsvej, Aldersintegreret",
    "wof:placetype":"venue"
},
  "geometry": {"coordinates":[8.4433164597,55.4713287354],"type":"Point"}
}