{
  "type": "Feature",
  "properties": {
    "addr:full":"Nibevej 20 Aars Danmark 9600",
    "addr:housenumber":"20",
    "addr:postcode":"9600",
    "addr:street":"Nibevej",
    "iso:country":"DK",
    "sg:address":"Nibevej 20",
    "sg:city":"Aars",
    "sg:orig_category":"Autoreparation og -service",
    "sg:phone":"+45 98 62 35 97",
    "sg:postcode":"9600",
    "sg:province":"Danmark",
    "wof:name":"Aars Autocenter",
    "wof:placetype":"venue"
},
  "geometry": {"coordinates":[9.5126276016,56.8053627014],"type":"Point"}
}