{
  "type": "Feature",
  "properties": {
    "addr:full":"R\u00f8dk\u00e6lkevej 4 Skagen Danmark 9990",
    "addr:housenumber":"4",
    "addr:postcode":"9990",
    "addr:street":"Rodkaelkevej",
    "iso:country":"DK",
    "sg:address":"R\u00f8dk\u00e6lkevej 4",
    "sg:city":"Skagen",
    "sg:classifiers":[
        {
            "category":"Communications",
            "type":"Services"
        }
    ],
    "sg:phone":"+45 98 45 00 55",
    "sg:postcode":"9990",
    "sg:province":"Danmark",
    "sg:tags":[
        "radio-",
        "og",
        "tv-stationer"
    ],
    "wof:name":"Skagen N\u00e6rradio s.m.b.a.",
    "wof:placetype":"venue"
},
  "geometry": {"coordinates":[10.5958003998,57.7247200012],"type":"Point"}
}