{
  "type": "Feature",
  "properties": {
    "addr:full":"N\u00f8rregade 16 B, Balling Sp\u00f8ttrup Danmark 7860",
    "addr:housenumber":"16 b",
    "addr:postcode":"7860",
    "addr:street":"Norregade",
    "iso:country":"DK",
    "sg:address":"N\u00f8rregade 16 B, Balling",
    "sg:city":"Sp\u00f8ttrup",
    "sg:orig_category":"Pizzeriaer",
    "sg:phone":"+45 97 56 56 56",
    "sg:postcode":"7860",
    "sg:province":"Danmark",
    "wof:name":"Balling Pizzeria",
    "wof:placetype":"venue"
},
  "geometry": {"coordinates":[8.7428588867,56.5733261108],"type":"Point"}
}