{
  "type": "Feature",
  "properties": {
    "addr:full":"\u00c5boulevard 55 Frederiksberg Danmark 1960",
    "addr:housenumber":"55",
    "addr:postcode":"1960",
    "addr:street":"Aaboulevard",
    "iso:country":"DK",
    "sg:address":"\u00c5boulevard 55",
    "sg:city":"Frederiksberg",
    "sg:orig_category":"Motorcykler",
    "sg:phone":"+45 35 35 81 31",
    "sg:postcode":"1960",
    "sg:province":"Danmark",
    "sg:website":"www.fisker-mc.dk",
    "wof:name":"Fisker Motorcykler",
    "wof:placetype":"venue"
},
  "geometry": {"coordinates":[12.5475330353,55.6851196289],"type":"Point"}
}