{
  "type": "Feature",
  "properties": {
    "addr:full":"Harring Bro Vej 21 Snedsted Danmark 7752",
    "addr:housenumber":"21",
    "addr:postcode":"7752",
    "addr:street":"Harring Bro Vej",
    "iso:country":"DK",
    "sg:address":"Harring Bro Vej 21",
    "sg:city":"Snedsted",
    "sg:orig_category":"Genbrugsbutikker",
    "sg:phone":"+45 97 93 64 37",
    "sg:postcode":"7752",
    "sg:province":"Danmark",
    "wof:name":"Thy Flaskecentral",
    "wof:placetype":"venue"
},
  "geometry": {"coordinates":[8.533285141,56.8627243042],"type":"Point"}
}