{
  "type": "Feature",
  "properties": {
    "iso:country":"DK",
    "sg:address":"Skovvej 5",
    "sg:city":"Gudbjerg",
    "sg:orig_category":"Blomsterhandlere",
    "sg:phone":"+45 62 25 37 75",
    "sg:postcode":"5892",
    "sg:province":"Danmark",
    "wof:name":"Pia's Blomsterbinderi",
    "wof:placetype":"venue"
},
  "geometry": {"coordinates":[10.6537256241,55.1532516479],"type":"Point"}
}