{
  "type": "Feature",
  "properties": {
    "addr:full":"Frederiksberg Alle 62 Frederiksberg Danmark 1820",
    "addr:housenumber":"62",
    "addr:postcode":"1820",
    "addr:street":"Frederiksberg Alle",
    "iso:country":"DK",
    "sg:address":"Frederiksberg Alle 62",
    "sg:city":"Frederiksberg",
    "sg:orig_category":"Yogaundervisning",
    "sg:phone":"+45 33 22 27 92",
    "sg:postcode":"1820",
    "sg:province":"Danmark",
    "wof:name":"S\u00f8rensen, Tove",
    "wof:placetype":"venue"
},
  "geometry": {"coordinates":[12.5392494202,55.6743164062],"type":"Point"}
}