{
  "type": "Feature",
  "properties": {
    "addr:full":"Hovvej 7, Hjedding \u00d8lgod Danmark 6870",
    "addr:housenumber":"7",
    "addr:postcode":"6870",
    "addr:street":"Hovvej",
    "iso:country":"DK",
    "sg:address":"Hovvej 7, Hjedding",
    "sg:city":"\u00d8lgod",
    "sg:orig_category":"Planteskoler",
    "sg:phone":"+45 75 24 11 17",
    "sg:postcode":"6870",
    "sg:province":"Danmark",
    "wof:name":"Friis planteskole",
    "wof:placetype":"venue"
},
  "geometry": {"coordinates":[8.6109304428,55.764125824],"type":"Point"}
}