{
  "type": "Feature",
  "properties": {
    "addr:full":"Sj\u00f8rslevvej 79, Sj\u00f8rslev Kjellerup Danmark 8620",
    "addr:housenumber":"79",
    "addr:postcode":"8620",
    "addr:street":"Sjorslevvej;Sjorslev",
    "iso:country":"DK",
    "sg:address":"Sj\u00f8rslevvej 79, Sj\u00f8rslev",
    "sg:city":"Kjellerup",
    "sg:orig_category":"Maskinstationer",
    "sg:phone":"+45 86 66 80 00",
    "sg:postcode":"8620",
    "sg:province":"Danmark",
    "wof:name":"Sj\u00f8rslev Maskinstation Riisbak I/S",
    "wof:placetype":"venue"
},
  "geometry": {"coordinates":[9.430934906,56.2877655029],"type":"Point"}
}