{
  "type": "Feature",
  "properties": {
    "addr:full":"Hjulmagervej 2 B Vejle Danmark 7100",
    "addr:housenumber":"2 b",
    "addr:postcode":"7100",
    "addr:street":"Hjulmagervej",
    "iso:country":"DK",
    "sg:address":"Hjulmagervej 2 B",
    "sg:city":"Vejle",
    "sg:orig_category":"El-artikler",
    "sg:phone":"+45 75 85 98 11",
    "sg:postcode":"7100",
    "sg:province":"Danmark",
    "wof:name":"Louis Poulsen El-teknik A/S",
    "wof:placetype":"venue"
},
  "geometry": {"coordinates":[9.5368051529,55.7113952637],"type":"Point"}
}