{
  "type": "Feature",
  "properties": {
    "addr:full":"Bredgade 38, 2. th. Br\u00f8nderslev Danmark 9700",
    "addr:housenumber":"38 2 th.",
    "addr:postcode":"9700",
    "addr:street":"Bredgade;Danmark",
    "iso:country":"DK",
    "sg:address":"Bredgade 38, 2. th.",
    "sg:city":"Br\u00f8nderslev",
    "sg:orig_category":"Akupunktur",
    "sg:phone":"+45 98 80 23 80",
    "sg:postcode":"9700",
    "sg:province":"Danmark",
    "wof:name":"Knold, Lars",
    "wof:placetype":"venue"
},
  "geometry": {"coordinates":[9.7584476471,57.2860298157],"type":"Point"}
}