{
  "type": "Feature",
  "properties": {
    "addr:full":"\u00d8stergade 11 Aulum Danmark 7490",
    "addr:housenumber":"11",
    "addr:postcode":"7490",
    "addr:street":"Ostergade",
    "iso:country":"DK",
    "sg:address":"\u00d8stergade 11",
    "sg:city":"Aulum",
    "sg:orig_category":"Private- og friskoler",
    "sg:phone":"+45 97 47 32 00",
    "sg:postcode":"7490",
    "sg:province":"Danmark",
    "sg:website":"www.aulum-kristne-friskole.dk",
    "wof:name":"Aulum Kristne Friskole",
    "wof:placetype":"venue"
},
  "geometry": {"coordinates":[8.8008813858,56.2614822388],"type":"Point"}
}