{
  "type": "Feature",
  "properties": {
    "addr:full":"Borrids\u00f8vej 14 Bjerringbro Danmark 8850",
    "addr:housenumber":"14",
    "addr:postcode":"8850",
    "addr:street":"Borridsovej",
    "iso:country":"DK",
    "sg:address":"Borrids\u00f8vej 14",
    "sg:city":"Bjerringbro",
    "sg:orig_category":"Hundekenneler",
    "sg:phone":"+45 86 68 02 67",
    "sg:postcode":"8850",
    "sg:province":"Danmark",
    "wof:name":"Capriosos, Kennel",
    "wof:placetype":"venue"
},
  "geometry": {"coordinates":[9.7014007568,56.3343276978],"type":"Point"}
}