{
  "type": "Feature",
  "properties": {
    "iso:country":"DK",
    "sg:address":"Strandgade 37 B",
    "sg:city":"Horsens",
    "sg:orig_category":"Indretningsarkitekter",
    "sg:phone":"+45 75 61 28 56",
    "sg:postcode":"8700",
    "sg:province":"Danmark",
    "wof:name":"Rod & Wulff",
    "wof:placetype":"venue"
},
  "geometry": {"coordinates":[9.8639211655,55.8624572754],"type":"Point"}
}