{
  "type": "Feature",
  "properties": {
    "iso:country":"DK",
    "sg:address":"Arkonagade 11",
    "sg:city":"K\u00f8benhavn",
    "sg:orig_category":"Snedkermestre",
    "sg:phone":"+45 33 22 19 05",
    "sg:postcode":"1726",
    "sg:province":"Danmark",
    "wof:name":"A Snedkeriet",
    "wof:placetype":"venue"
},
  "geometry": {"coordinates":[12.553899765,55.6647987366],"type":"Point"}
}