{
  "type": "Feature",
  "properties": {
    "addr:full":"Motelvej 4, Karlstrup Karlslunde Danmark 2690",
    "addr:housenumber":"4",
    "addr:postcode":"2690",
    "addr:street":"Motelvej;Karlstrup",
    "iso:country":"DK",
    "sg:address":"Motelvej 4, Karlstrup",
    "sg:city":"Karlslunde",
    "sg:orig_category":"Autoreparation og -service",
    "sg:phone":"+45 56 14 26 00",
    "sg:postcode":"2690",
    "sg:province":"Danmark",
    "wof:name":"Titan Lastvogne A/S",
    "wof:placetype":"venue"
},
  "geometry": {"coordinates":[12.2294149399,55.5701599121],"type":"Point"}
}