{
  "type": "Feature",
  "properties": {
    "addr:full":"\u00d8resundsvej 114 K\u00f8benhavn S Danmark 2300",
    "addr:housenumber":"114",
    "addr:postcode":"2300",
    "addr:street":"Oresundsvej;S Danmark",
    "iso:country":"DK",
    "sg:address":"\u00d8resundsvej 114",
    "sg:city":"K\u00f8benhavn S",
    "sg:orig_category":"Kiosker",
    "sg:phone":"+45 32 55 45 47",
    "sg:postcode":"2300",
    "sg:province":"Danmark",
    "wof:name":"Kiosken",
    "wof:placetype":"venue"
},
  "geometry": {"coordinates":[-82.5997924805,38.4714622498],"type":"Point"}
}