{
  "type": "Feature",
  "properties": {
    "addr:full":"Leder: Hans Hermansen, Oluf L\u00e6rches Vej 18, Korning Horsens Danmark 8700",
    "addr:housenumber":"18",
    "addr:postcode":"8700",
    "addr:street":"Laerches Vej;Korning",
    "iso:country":"DK",
    "sg:address":"Leder: Hans Hermansen, Oluf L\u00e6rches Vej 18, Korning",
    "sg:city":"Horsens",
    "sg:orig_category":"Fritidsklubber",
    "sg:phone":"+45 75 67 39 39",
    "sg:postcode":"8700",
    "sg:province":"Danmark",
    "wof:name":"Korning B\u00f8rneklub",
    "wof:placetype":"venue"
},
  "geometry": {"coordinates":[9.8432445526,55.8621063232],"type":"Point"}
}