{
  "type": "Feature",
  "properties": {
    "addr:full":"Holsted Park 24 N\u00e6stved Danmark 4700",
    "addr:housenumber":"24",
    "addr:postcode":"4700",
    "addr:street":"Holsted Park",
    "iso:country":"DK",
    "sg:address":"Holsted Park 24",
    "sg:city":"N\u00e6stved",
    "sg:orig_category":"Metaller",
    "sg:phone":"+45 55 72 14 91",
    "sg:postcode":"4700",
    "sg:province":"Danmark",
    "wof:name":"Klemas Kleinsmedie ApS",
    "wof:placetype":"venue"
},
  "geometry": {"coordinates":[11.7794342041,55.2481460571],"type":"Point"}
}