{
  "type": "Feature",
  "properties": {
    "addr:full":"Seminarievej 31 Ranum Danmark 9681",
    "addr:housenumber":"31",
    "addr:postcode":"9681",
    "addr:street":"Seminarievej",
    "iso:country":"DK",
    "sg:address":"Seminarievej 31",
    "sg:city":"Ranum",
    "sg:orig_category":"Kommunale folkeskoler",
    "sg:phone":"+45 98 67 60 23",
    "sg:postcode":"9681",
    "sg:province":"Danmark",
    "wof:name":"Ranum Skole",
    "wof:placetype":"venue"
},
  "geometry": {"coordinates":[9.240893364,56.9010696411],"type":"Point"}
}