{
  "type": "Feature",
  "properties": {
    "addr:full":"Kordilgade 42 Kalundborg Danmark 4400",
    "addr:housenumber":"42",
    "addr:postcode":"4400",
    "addr:street":"Kordilgade",
    "iso:country":"DK",
    "sg:address":"Kordilgade 42",
    "sg:city":"Kalundborg",
    "sg:orig_category":"Pengeskabe",
    "sg:phone":"+45 59 51 63 00",
    "sg:postcode":"4400",
    "sg:province":"Danmark",
    "wof:name":"Bagger L\u00e5se & Alarm",
    "wof:placetype":"venue"
},
  "geometry": {"coordinates":[11.0929431915,55.6796531677],"type":"Point"}
}