{
  "type": "Feature",
  "properties": {
    "addr:full":"Kirkeleddet 345 Fredensborg Danmark 3480",
    "addr:housenumber":"345",
    "addr:postcode":"3480",
    "addr:street":"Kirkeleddet",
    "iso:country":"DK",
    "sg:address":"Kirkeleddet 345",
    "sg:city":"Fredensborg",
    "sg:orig_category":"Arkitekter",
    "sg:phone":"+45 48 48 86 26",
    "sg:postcode":"3480",
    "sg:province":"Danmark",
    "wof:name":"J.B. Tegnestue",
    "wof:placetype":"venue"
},
  "geometry": {"coordinates":[12.4236335754,55.9744606018],"type":"Point"}
}