{
  "type": "Feature",
  "properties": {
    "addr:full":"Absalonsgade 7 Vordingborg Danmark 4760",
    "addr:housenumber":"7",
    "addr:postcode":"4760",
    "addr:street":"Absalonsgade",
    "iso:country":"DK",
    "sg:address":"Absalonsgade 7",
    "sg:city":"Vordingborg",
    "sg:orig_category":"Psykologer, praktiserende",
    "sg:phone":"+45 55 34 55 38",
    "sg:postcode":"4760",
    "sg:province":"Danmark",
    "wof:name":"Psykologhuset",
    "wof:placetype":"venue"
},
  "geometry": {"coordinates":[11.9056053162,55.0134277344],"type":"Point"}
}