{
  "type": "Feature",
  "properties": {
    "iso:country":"DK",
    "sg:address":"Ejlersvej 24",
    "sg:city":"Kolding",
    "sg:orig_category":"Tryksager",
    "sg:phone":"+45 76 33 91 00",
    "sg:postcode":"6000",
    "sg:province":"Danmark",
    "wof:name":"Formula A/S",
    "wof:placetype":"venue"
},
  "geometry": {"coordinates":[9.478012085,55.4932403564],"type":"Point"}
}