{
  "type": "Feature",
  "properties": {
    "addr:full":"Fmd.: Bent Terkelsen, Haarlevvejen 21, Endeslev H\u00e5rlev Danmark 4652",
    "addr:housenumber":"21",
    "addr:postcode":"4652",
    "addr:street":"Haarlevvejen",
    "iso:country":"DK",
    "sg:address":"Fmd.: Bent Terkelsen, Haarlevvejen 21, Endeslev",
    "sg:city":"H\u00e5rlev",
    "sg:orig_category":"\u00c3\u2020ldreorganisationer og klubber",
    "sg:phone":"+45 56 28 69 14",
    "sg:postcode":"4652",
    "sg:province":"Danmark",
    "wof:name":"SiD Vall\u00f8 Pensionist/Efterl\u00f8nsklub",
    "wof:placetype":"venue"
},
  "geometry": {"coordinates":[12.2393083572,55.3467025757],"type":"Point"}
}