{
  "type": "Feature",
  "properties": {
    "addr:full":"Skovv\u00e6nget 10 Hasselager Danmark 8361",
    "addr:housenumber":"10",
    "addr:postcode":"8361",
    "addr:street":"Skovvaenget",
    "iso:country":"DK",
    "sg:address":"Skovv\u00e6nget 10",
    "sg:city":"Hasselager",
    "sg:orig_category":"Murermestre",
    "sg:phone":"+45 86 28 39 15",
    "sg:postcode":"8361",
    "sg:province":"Danmark",
    "wof:name":"Mathiesen, Karlo",
    "wof:placetype":"venue"
},
  "geometry": {"coordinates":[10.094414711,56.105014801],"type":"Point"}
}