{
  "type": "Feature",
  "properties": {
    "addr:full":"Fmd.: Mini Pedersen, Nymindegabvej 161 Outrup Danmark 6855",
    "addr:housenumber":"161",
    "addr:postcode":"6855",
    "addr:street":"Nymindegabvej",
    "iso:country":"DK",
    "sg:address":"Fmd.: Mini Pedersen, Nymindegabvej 161",
    "sg:city":"Outrup",
    "sg:orig_category":"Kulturelle foreninger",
    "sg:phone":"+45 51 78 27 71",
    "sg:postcode":"6855",
    "sg:province":"Danmark",
    "wof:name":"Outrup Sogneforening",
    "wof:placetype":"venue"
},
  "geometry": {"coordinates":[8.3423900604,55.7216491699],"type":"Point"}
}