{
  "type": "Feature",
  "properties": {
    "iso:country":"DK",
    "sg:address":"Thorvaldsensvej 27",
    "sg:city":"Frederiksberg",
    "sg:orig_category":"Alternativ behandling",
    "sg:phone":"+45 70 20 00 03",
    "sg:postcode":"1871",
    "sg:province":"Danmark",
    "sg:website":"www.clairvoyance.dk",
    "wof:name":"Harthimmer, Jette",
    "wof:placetype":"venue"
},
  "geometry": {"coordinates":[12.5448646545,55.6809120178],"type":"Point"}
}