{
  "type": "Feature",
  "properties": {
    "addr:full":"Ormslevvej 287 Viby Danmark 8260",
    "addr:housenumber":"287",
    "addr:postcode":"8260",
    "addr:street":"Ormslevvej",
    "iso:country":"DK",
    "sg:address":"Ormslevvej 287",
    "sg:city":"Viby",
    "sg:orig_category":"Trykluft",
    "sg:phone":"+45 86 28 11 82",
    "sg:postcode":"8260",
    "sg:province":"Danmark",
    "wof:name":"Ardua ApS",
    "wof:placetype":"venue"
},
  "geometry": {"coordinates":[10.1132745743,56.1285133362],"type":"Point"}
}