{
  "type": "Feature",
  "properties": {
    "iso:country":"DK",
    "sg:address":"Rungsted Bytorv 3",
    "sg:city":"Rungsted Kyst",
    "sg:orig_category":"Brugskunst",
    "sg:phone":"+45 45 86 81 02",
    "sg:postcode":"2960",
    "sg:province":"Danmark",
    "sg:website":"www.tikken.dk",
    "wof:name":"Tikken",
    "wof:placetype":"venue"
},
  "geometry": {"coordinates":[12.5282850266,55.8836288452],"type":"Point"}
}