{
  "type": "Feature",
  "properties": {
    "addr:full":"Hvedemarken 9 S\u00f8borg Danmark 2860",
    "addr:housenumber":"9",
    "addr:postcode":"2860",
    "addr:street":"Hvedemarken",
    "iso:country":"DK",
    "sg:address":"Hvedemarken 9",
    "sg:city":"S\u00f8borg",
    "sg:orig_category":"Parykker",
    "sg:phone":"+45 39 66 14 18",
    "sg:postcode":"2860",
    "sg:province":"Danmark",
    "wof:name":"H\u00e5rteknikken",
    "wof:placetype":"venue"
},
  "geometry": {"coordinates":[-101.3893203735,35.6754798889],"type":"Point"}
}