{
  "type": "Feature",
  "properties": {
    "iso:country":"DK",
    "sg:address":"Kontaktpers.: Poul S\u00f8rensen, Holmevej 3",
    "sg:city":"Ribe",
    "sg:orig_category":"Hobbybetonede foreninger",
    "sg:phone":"+45 75 42 24 79",
    "sg:postcode":"6760",
    "sg:province":"Danmark",
    "wof:name":"Dansk Cyklist Forbund - Ribe afd.",
    "wof:placetype":"venue"
},
  "geometry": {"coordinates":[8.7656240463,55.3297042847],"type":"Point"}
}