{
  "type": "Feature",
  "properties": {
    "addr:full":"Vestre Landevej 103 N\u00f8rreballe Danmark 4951",
    "addr:housenumber":"103",
    "addr:postcode":"4951",
    "addr:street":"Vestre Landevej",
    "iso:country":"DK",
    "sg:address":"Vestre Landevej 103",
    "sg:city":"N\u00f8rreballe",
    "sg:orig_category":"Symaskiner",
    "sg:phone":"+45 54 78 62 12",
    "sg:postcode":"4951",
    "sg:province":"Danmark",
    "sg:website":"www.mssdesign.dk",
    "wof:name":"MSS Design",
    "wof:placetype":"venue"
},
  "geometry": {"coordinates":[6.8762898445,62.4602813721],"type":"Point"}
}