{
  "type": "Feature",
  "properties": {
    "iso:country":"DK",
    "sg:address":"Sortebrovej 1",
    "sg:city":"Tommerup",
    "sg:orig_category":"Handicap-daginstitutioner",
    "sg:phone":"+45 64 76 11 20",
    "sg:postcode":"5690",
    "sg:province":"Danmark",
    "sg:website":"www.tommerup.dk/paletten.htm",
    "wof:name":"Paletten Aktivitetshuset",
    "wof:placetype":"venue"
},
  "geometry": {"coordinates":[10.1989746094,55.3255615234],"type":"Point"}
}