{
  "type": "Feature",
  "properties": {
    "addr:full":"Strandvejen 82 Hellerup Danmark 2900",
    "addr:housenumber":"82",
    "addr:postcode":"2900",
    "addr:street":"Strandvejen",
    "iso:country":"DK",
    "sg:address":"Strandvejen 82",
    "sg:city":"Hellerup",
    "sg:orig_category":"Videobutikker og -klubber",
    "sg:phone":"+45 39 40 19 84",
    "sg:postcode":"2900",
    "sg:province":"Danmark",
    "wof:name":"Blockbuster",
    "wof:placetype":"venue"
},
  "geometry": {"coordinates":[12.5765571594,55.7305145264],"type":"Point"}
}