{
  "type": "Feature",
  "properties": {
    "addr:full":"Vestergade 45 \u00c5rhus C Danmark 8000",
    "addr:housenumber":"45",
    "addr:postcode":"8000",
    "addr:street":"Vestergade",
    "iso:country":"DK",
    "sg:address":"Vestergade 45",
    "sg:city":"\u00c5rhus C",
    "sg:orig_category":"Yogaundervisning",
    "sg:phone":"+45 70 27 10 12",
    "sg:postcode":"8000",
    "sg:province":"Danmark",
    "wof:name":"Yogaskolen i Aarhus",
    "wof:placetype":"venue"
},
  "geometry": {"coordinates":[9.5455904007,56.1682090759],"type":"Point"}
}