{
  "type": "Feature",
  "properties": {
    "addr:full":"Torvet 11,2.th. K\u00f8ge Danmark 4600",
    "addr:housenumber":"11,2",
    "addr:postcode":"4600",
    "addr:street":"Torvet",
    "iso:country":"DK",
    "sg:address":"Torvet 11,2.th.",
    "sg:city":"K\u00f8ge",
    "sg:orig_category":"Dentallaboratorier",
    "sg:phone":"+45 56 66 11 70",
    "sg:postcode":"4600",
    "sg:province":"Danmark",
    "wof:name":"B + B Dentallaboratorium",
    "wof:placetype":"venue"
},
  "geometry": {"coordinates":[10.6905498505,59.8094596863],"type":"Point"}
}