{
  "type": "Feature",
  "properties": {
    "addr:full":"v/ \u00d8rslev Brugsf., \u00d8rslevvej 129 Vordingborg Danmark 4760",
    "addr:housenumber":"129",
    "addr:postcode":"4760",
    "addr:street":"Orslevvej",
    "iso:country":"DK",
    "sg:address":"v/ \u00d8rslev Brugsf., \u00d8rslevvej 129",
    "sg:city":"Vordingborg",
    "sg:orig_category":"Posthuse",
    "sg:phone":"+45 55 98 50 08",
    "sg:postcode":"4760",
    "sg:province":"Danmark",
    "wof:name":"Post Danmark, \u00d8rslev Postekspedition",
    "wof:placetype":"venue"
},
  "geometry": {"coordinates":[11.9124183655,55.0085449219],"type":"Point"}
}