{
  "type": "Feature",
  "properties": {
    "addr:full":"Borgergade 10 Silkeborg Danmark 8600",
    "addr:housenumber":"10",
    "addr:postcode":"8600",
    "addr:street":"Borgergade",
    "iso:country":"DK",
    "sg:address":"Borgergade 10",
    "sg:city":"Silkeborg",
    "sg:orig_category":"Kontormaskiner",
    "sg:phone":"+45 86 80 68 14",
    "sg:postcode":"8600",
    "sg:province":"Danmark",
    "wof:name":"KC Service",
    "wof:placetype":"venue"
},
  "geometry": {"coordinates":[9.5550947189,56.1765937805],"type":"Point"}
}