{
  "type": "Feature",
  "properties": {
    "iso:country":"DK",
    "sg:address":"Gl. Hobrovej 26",
    "sg:city":"Randers",
    "sg:orig_category":"Slagter og viktualie",
    "sg:phone":"+45 86 42 38 09",
    "sg:postcode":"8900",
    "sg:province":"Danmark",
    "wof:name":"Olesen, S\u00f8ren",
    "wof:placetype":"venue"
},
  "geometry": {"coordinates":[10.0280990601,56.464389801],"type":"Point"}
}