{
  "type": "Feature",
  "properties": {
    "addr:full":"Amagerbrogade 10 K\u00f8benhavn S Danmark 2300",
    "addr:housenumber":"10",
    "addr:postcode":"2300",
    "addr:street":"Amagerbrogade;S Danmark",
    "iso:country":"DK",
    "sg:address":"Amagerbrogade 10",
    "sg:city":"K\u00f8benhavn S",
    "sg:classifiers":[
        {
            "category":"Professional",
            "subcategory":"Computer Services",
            "type":"Services"
        }
    ],
    "sg:phone":"+45 32 95 91 10",
    "sg:postcode":"2300",
    "sg:province":"Danmark",
    "sg:tags":[
        "edb",
        "-",
        "software"
    ],
    "wof:name":"Knas Web-design",
    "wof:placetype":"venue"
},
  "geometry": {"coordinates":[-78.1299133301,36.7267417908],"type":"Point"}
}