{
  "type": "Feature",
  "properties": {
    "addr:full":"Sofienbergvej 17, Pilshuse Nyborg Danmark 5800",
    "addr:housenumber":"17",
    "addr:postcode":"5800",
    "addr:street":"Sofienbergvej;Pilshuse",
    "iso:country":"DK",
    "sg:address":"Sofienbergvej 17, Pilshuse",
    "sg:city":"Nyborg",
    "sg:orig_category":"Murermestre",
    "sg:phone":"+45 65 31 34 92",
    "sg:postcode":"5800",
    "sg:province":"Danmark",
    "wof:name":"Hansen, Hans Gr\u00f8nbech",
    "wof:placetype":"venue"
},
  "geometry": {"coordinates":[10.7923851013,55.3111801147],"type":"Point"}
}