{
  "type": "Feature",
  "properties": {
    "addr:full":"Stadionvej 2 Toftlund Danmark 6520",
    "addr:housenumber":"2",
    "addr:postcode":"6520",
    "addr:street":"Stadionvej",
    "iso:country":"DK",
    "sg:address":"Stadionvej 2",
    "sg:city":"Toftlund",
    "sg:orig_category":"Grillbarer",
    "sg:phone":"+45 74 83 24 81",
    "sg:postcode":"6520",
    "sg:province":"Danmark",
    "wof:name":"Central-Grill",
    "wof:placetype":"venue"
},
  "geometry": {"coordinates":[9.0640354156,55.1929168701],"type":"Point"}
}