{
  "type": "Feature",
  "properties": {
    "addr:full":"Strandvejen 354 Esperg\u00e6rde Danmark 3060",
    "addr:housenumber":"354",
    "addr:postcode":"3060",
    "addr:street":"Strandvejen",
    "iso:country":"DK",
    "sg:address":"Strandvejen 354",
    "sg:city":"Esperg\u00e6rde",
    "sg:orig_category":"Ejendomshandel",
    "sg:phone":"+45 49 13 01 00",
    "sg:postcode":"3060",
    "sg:province":"Danmark",
    "wof:name":"DanBolig - Laugmann & L\u00f8gstrup",
    "wof:placetype":"venue"
},
  "geometry": {"coordinates":[11.6512403488,47.8390617371],"type":"Point"}
}