{
  "type": "Feature",
  "properties": {
    "addr:full":"Vennelystvej 56 B Randers Danmark 8900",
    "addr:housenumber":"56 b",
    "addr:postcode":"8900",
    "addr:street":"Vennelystvej",
    "iso:country":"DK",
    "sg:address":"Vennelystvej 56 B",
    "sg:city":"Randers",
    "sg:orig_category":"Supermarkeder",
    "sg:phone":"+45 86 43 14 20",
    "sg:postcode":"8900",
    "sg:province":"Danmark",
    "wof:name":"Kristrup Supermarked",
    "wof:placetype":"venue"
},
  "geometry": {"coordinates":[10.0580768585,56.4447822571],"type":"Point"}
}