{
  "type": "Feature",
  "properties": {
    "iso:country":"DK",
    "sg:address":"Gislumvej 114, Nyrup",
    "sg:city":"Aars",
    "sg:orig_category":"Maskinstationer",
    "sg:phone":"+45 98 65 82 00",
    "sg:postcode":"9600",
    "sg:province":"Danmark",
    "wof:name":"Mogensen, Allan Krogh",
    "wof:placetype":"venue"
},
  "geometry": {"coordinates":[9.5170412064,56.8031692505],"type":"Point"}
}