{
  "type": "Feature",
  "properties": {
    "addr:full":"K\u00e6rg\u00e5rdsvej 4 Solbjerg Danmark 8355",
    "addr:housenumber":"4",
    "addr:postcode":"8355",
    "addr:street":"Kaergaardsvej",
    "iso:country":"DK",
    "sg:address":"K\u00e6rg\u00e5rdsvej 4",
    "sg:city":"Solbjerg",
    "sg:orig_category":"Ungdomsklubber",
    "sg:phone":"+45 86 92 85 43",
    "sg:postcode":"8355",
    "sg:province":"Danmark",
    "wof:name":"Solbjerg Ungdomsklub",
    "wof:placetype":"venue"
},
  "geometry": {"coordinates":[10.0810050964,56.0374946594],"type":"Point"}
}