{
  "type": "Feature",
  "properties": {
    "addr:full":"Hellerupvej 5 B, 2. Hellerup Danmark 2900",
    "addr:housenumber":"5 b 2",
    "addr:postcode":"2900",
    "addr:street":"Hellerupvej",
    "iso:country":"DK",
    "sg:address":"Hellerupvej 5 B, 2.",
    "sg:city":"Hellerup",
    "sg:classifiers":[
        {
            "category":"Personal",
            "subcategory":"Massage",
            "type":"Services"
        }
    ],
    "sg:phone":"+45 39 61 21 68",
    "sg:postcode":"2900",
    "sg:province":"Danmark",
    "wof:name":"Mobile klinik, Den",
    "wof:placetype":"venue"
},
  "geometry": {"coordinates":[12.5744533539,55.7314376831],"type":"Point"}
}