{
  "type": "Feature",
  "properties": {
    "addr:full":"Hovedgaden 18, Ubby Jerslev Sj\u00e6lland Danmark 4490",
    "addr:housenumber":"18",
    "addr:postcode":"4490",
    "addr:street":"Hovedgaden;Ubby Jerslev Sjaelland Danmark",
    "iso:country":"DK",
    "sg:address":"Hovedgaden 18, Ubby",
    "sg:city":"Jerslev Sj\u00e6lland",
    "sg:orig_category":"Begravelsesforretninger",
    "sg:phone":"+45 58 85 55 20",
    "sg:postcode":"4490",
    "sg:province":"Danmark",
    "wof:name":"Hvideb\u00e6k Begravelsesforretning",
    "wof:placetype":"venue"
},
  "geometry": {"coordinates":[11.213265,55.619179],"type":"Point"}
}