{
  "type": "Feature",
  "properties": {
    "iso:country":"DK",
    "sg:address":"Kirkegade 1",
    "sg:city":"Nyk\u00f8bing",
    "sg:orig_category":"Biografer",
    "sg:phone":"+45 97 72 02 64",
    "sg:postcode":"7900",
    "sg:province":"Danmark",
    "sg:website":"www.biomors.dk",
    "wof:name":"Bio Mors",
    "wof:placetype":"venue"
},
  "geometry": {"coordinates":[-114.07682,46.443241],"type":"Point"}
}