{
  "type": "Feature",
  "properties": {
    "addr:full":"Granstuevej 16, \u00d8ver\u00f8d Holte Danmark 2840",
    "addr:housenumber":"16",
    "addr:postcode":"2840",
    "addr:street":"Granstuevej",
    "iso:country":"DK",
    "sg:address":"Granstuevej 16, \u00d8ver\u00f8d",
    "sg:city":"Holte",
    "sg:orig_category":"Tegnere og tegnestuer",
    "sg:phone":"+45 45 42 52 29",
    "sg:postcode":"2840",
    "sg:province":"Danmark",
    "sg:website":"www.vi-iv.dk",
    "wof:name":"Iversen, Rasmus",
    "wof:placetype":"venue"
},
  "geometry": {"coordinates":[12.4706554413,55.8122367859],"type":"Point"}
}