{
  "type": "Feature",
  "properties": {
    "addr:full":"Bredgade 147 Br\u00f8nderslev Danmark 9700",
    "addr:housenumber":"147",
    "addr:postcode":"9700",
    "addr:street":"Bredgade",
    "iso:country":"DK",
    "sg:address":"Bredgade 147",
    "sg:city":"Br\u00f8nderslev",
    "sg:orig_category":"\u00c3\u2020ldreorganisationer og klubber",
    "sg:phone":"+45 98 82 05 44",
    "sg:postcode":"9700",
    "sg:province":"Danmark",
    "wof:name":"Brugergruppen i Risagerlunds k\u00e6lder",
    "wof:placetype":"venue"
},
  "geometry": {"coordinates":[9.9582777023,57.2681808472],"type":"Point"}
}