{
  "type": "Feature",
  "properties": {
    "addr:full":"Casinotorvet 2 Slagelse Danmark 4200",
    "addr:housenumber":"2",
    "addr:postcode":"4200",
    "addr:street":"Casinotorvet",
    "iso:country":"DK",
    "sg:address":"Casinotorvet 2",
    "sg:city":"Slagelse",
    "sg:orig_category":"Rejsebureauer",
    "sg:phone":"+45 70 25 11 15",
    "sg:postcode":"4200",
    "sg:province":"Danmark",
    "wof:name":"Kisbye Rejser A/S",
    "wof:placetype":"venue"
},
  "geometry": {"coordinates":[11.354516983,55.4055366516],"type":"Point"}
}