{
  "type": "Feature",
  "properties": {
    "iso:country":"DK",
    "sg:address":"Torvegade 8",
    "sg:city":"Esbjerg",
    "sg:classifiers":[
        {
            "category":"Banks & Credit Unions",
            "subcategory":"Bank",
            "type":"Services"
        }
    ],
    "sg:phone":"+45 75 45 22 77",
    "sg:postcode":"6700",
    "sg:province":"Danmark",
    "sg:tags":[
        "banker"
    ],
    "wof:name":"Den jyske Sparekasse",
    "wof:placetype":"venue"
},
  "geometry": {"coordinates":[8.451353,55.465458],"type":"Point"}
}