{
  "type": "Feature",
  "properties": {
    "iso:country":"DK",
    "sg:address":"Houvej 164, Ulsted",
    "sg:city":"Hals",
    "sg:orig_category":"Betonelementer",
    "sg:phone":"+45 70 26 62 11",
    "sg:postcode":"9370",
    "sg:province":"Danmark",
    "wof:name":"Ph-staldprodukter A/S",
    "wof:placetype":"venue"
},
  "geometry": {"coordinates":[10.366935,57.059799],"type":"Point"}
}