{
  "type": "Feature",
  "properties": {
    "iso:country":"DK",
    "sg:address":"Skibhusvej 142-144",
    "sg:city":"Odense C",
    "sg:orig_category":"Rejsebureauer",
    "sg:phone":"+45 63 13 03 03",
    "sg:postcode":"5000",
    "sg:province":"Danmark",
    "sg:website":"www.traintravel.dk",
    "wof:name":"Train Travel ApS",
    "wof:placetype":"venue"
},
  "geometry": {"coordinates":[10.394525528,55.411693573],"type":"Point"}
}