{
  "type": "Feature",
  "properties": {
    "addr:full":"v/ Lars Graub\u00e6k, Gl. Skivevej 43, Bajlum Roslev Danmark 7870",
    "addr:housenumber":"43",
    "addr:postcode":"7870",
    "addr:street":"Gl. Skivevej",
    "iso:country":"DK",
    "sg:address":"v/ Lars Graub\u00e6k, Gl. Skivevej 43, Bajlum",
    "sg:city":"Roslev",
    "sg:orig_category":"\u00c3\u02dcvrig fritidsundervisning",
    "sg:phone":"+45 97 57 90 45",
    "sg:postcode":"7870",
    "sg:province":"Danmark",
    "wof:name":"Hjerk-Harre Beboerforening",
    "wof:placetype":"venue"
},
  "geometry": {"coordinates":[8.8715353012,56.7570304871],"type":"Point"}
}