{
  "type": "Feature",
  "properties": {
    "addr:full":"Jomfrustien 2 Haderslev Danmark 6100",
    "addr:housenumber":"2",
    "addr:postcode":"6100",
    "addr:street":"Jomfrustien",
    "iso:country":"DK",
    "sg:address":"Jomfrustien 2",
    "sg:city":"Haderslev",
    "sg:orig_category":"Pizzeriaer",
    "sg:phone":"+45 74 52 22 46",
    "sg:postcode":"6100",
    "sg:province":"Danmark",
    "wof:name":"Pinocchio Pizza og Pasta House",
    "wof:placetype":"venue"
},
  "geometry": {"coordinates":[9.4884471893,55.2508811951],"type":"Point"}
}