{
  "type": "Feature",
  "properties": {
    "addr:full":"Fmd.: Birthe Olsen, R\u00e5gelundevej 54 Kettinge Danmark 4892",
    "addr:housenumber":"54",
    "addr:postcode":"4892",
    "addr:street":"Raagelundevej",
    "iso:country":"DK",
    "sg:address":"Fmd.: Birthe Olsen, R\u00e5gelundevej 54",
    "sg:city":"Kettinge",
    "sg:orig_category":"Husflidsforeninger",
    "sg:phone":"+45 54 87 36 37",
    "sg:postcode":"4892",
    "sg:province":"Danmark",
    "wof:name":"Familie og Samfund, Frejlev - \u00d8. Ulslev",
    "wof:placetype":"venue"
},
  "geometry": {"coordinates":[11.7293653488,54.694984436],"type":"Point"}
}