{
  "type": "Feature",
  "properties": {
    "iso:country":"DK",
    "sg:address":"Hovedgaden 55",
    "sg:city":"Tisvildeleje",
    "sg:classifiers":[
        {
            "category":"Restaurant",
            "type":"Food & Drink"
        }
    ],
    "sg:phone":"+45 48 70 88 86",
    "sg:postcode":"3220",
    "sg:province":"Danmark",
    "wof:name":"Tisvildeleje Cafeen",
    "wof:placetype":"venue"
},
  "geometry": {"coordinates":[12.0736513138,56.0595054626],"type":"Point"}
}