{
  "type": "Feature",
  "properties": {
    "addr:full":"Odensevej 13 Middelfart Danmark 5500",
    "addr:housenumber":"13",
    "addr:postcode":"5500",
    "addr:street":"Odensevej",
    "iso:country":"DK",
    "sg:address":"Odensevej 13",
    "sg:city":"Middelfart",
    "sg:orig_category":"Bagere",
    "sg:phone":"+45 64 41 02 48",
    "sg:postcode":"5500",
    "sg:province":"Danmark",
    "wof:name":"Bageren p\u00e5 Odensevej",
    "wof:placetype":"venue"
},
  "geometry": {"coordinates":[9.74253,55.502995],"type":"Point"}
}