{
  "type": "Feature",
  "properties": {
    "addr:full":"Gammel K\u00f8ge Landevej 55 Valby Danmark 2500",
    "addr:housenumber":"55",
    "addr:postcode":"2500",
    "addr:street":"Gammel Koge Landevej",
    "iso:country":"DK",
    "sg:address":"Gammel K\u00f8ge Landevej 55",
    "sg:city":"Valby",
    "sg:orig_category":"Teleselskaber",
    "sg:phone":"+45 77 30 12 00",
    "sg:postcode":"2500",
    "sg:province":"Danmark",
    "sg:website":"www.tele2.dk",
    "wof:name":"TELE 2 A/S",
    "wof:placetype":"venue"
},
  "geometry": {"coordinates":[12.5140161514,55.6579818726],"type":"Point"}
}