{
  "type": "Feature",
  "properties": {
    "addr:full":"Sanderumvej 16, Sanderum Odense SV Danmark 5250",
    "addr:housenumber":"16",
    "addr:postcode":"5250",
    "addr:street":"Sanderumvej;Sanderum",
    "iso:country":"DK",
    "sg:address":"Sanderumvej 16, Sanderum",
    "sg:city":"Odense SV",
    "sg:orig_category":"El-forsyning",
    "sg:phone":"+45 63 17 19 00",
    "sg:postcode":"5250",
    "sg:province":"Danmark",
    "sg:website":"www.energifyn.dk",
    "wof:name":"Energi Fyn a.m.b.a.",
    "wof:placetype":"venue"
},
  "geometry": {"coordinates":[10.3153953552,55.3362998962],"type":"Point"}
}