{
  "type": "Feature",
  "properties": {
    "addr:full":"Fmd.: Bent Bernardi S\u00f8rensen, Fonnesbechsgade 1, 2. Herning Danmark 7400",
    "addr:housenumber":"1 2",
    "addr:postcode":"7400",
    "addr:street":"Fonnesbechsgade",
    "iso:country":"DK",
    "sg:address":"Fmd.: Bent Bernardi S\u00f8rensen, Fonnesbechsgade 1, 2.",
    "sg:city":"Herning",
    "sg:orig_category":"Faglige organisationer og foreninger",
    "sg:phone":"+45 97 21 63 97",
    "sg:postcode":"7400",
    "sg:province":"Danmark",
    "wof:name":"Midtjyske Systemkritikere",
    "wof:placetype":"venue"
},
  "geometry": {"coordinates":[8.9768896103,56.1374168396],"type":"Point"}
}