{
  "type": "Feature",
  "properties": {
    "addr:full":"v/ Niels Radion, Park Alle 4 \u00d8lstykke Danmark 3650",
    "addr:housenumber":"4",
    "addr:postcode":"3650",
    "addr:street":"Park Alle",
    "iso:country":"DK",
    "sg:address":"v/ Niels Radion, Park Alle 4",
    "sg:city":"\u00d8lstykke",
    "sg:orig_category":"Grundejerforeninger",
    "sg:phone":"+45 47 17 86 87",
    "sg:postcode":"3650",
    "sg:province":"Danmark",
    "wof:name":"Park Alle",
    "wof:placetype":"venue"
},
  "geometry": {"coordinates":[11.2520399094,53.3618812561],"type":"Point"}
}