{
  "type": "Feature",
  "properties": {
    "addr:full":"Gentoftegade 17 Gentofte Danmark 2820",
    "addr:housenumber":"17",
    "addr:postcode":"2820",
    "addr:street":"Gentoftegade",
    "iso:country":"DK",
    "sg:address":"Gentoftegade 17",
    "sg:city":"Gentofte",
    "sg:orig_category":"Tekstilmaskiner",
    "sg:phone":"+45 39 65 24 00",
    "sg:postcode":"2820",
    "sg:province":"Danmark",
    "wof:name":"Dematex",
    "wof:placetype":"venue"
},
  "geometry": {"coordinates":[12.541885376,55.7506408691],"type":"Point"}
}