{
  "type": "Feature",
  "properties": {
    "addr:full":"Industrivej 8 Jyderup Danmark 4450",
    "addr:housenumber":"8",
    "addr:postcode":"4450",
    "addr:street":"Industrivej",
    "iso:country":"DK",
    "sg:address":"Industrivej 8",
    "sg:city":"Jyderup",
    "sg:orig_category":"Markiser",
    "sg:phone":"+45 59 27 61 42",
    "sg:postcode":"4450",
    "sg:province":"Danmark",
    "wof:name":"Foldor Markise Center",
    "wof:placetype":"venue"
},
  "geometry": {"coordinates":[11.4116725922,55.6598968506],"type":"Point"}
}