{
  "type": "Feature",
  "properties": {
    "addr:full":"L\u00f8gumklostervej 34 Aabenraa Danmark 6200",
    "addr:housenumber":"34",
    "addr:postcode":"6200",
    "addr:street":"Logumklostervej",
    "iso:country":"DK",
    "sg:address":"L\u00f8gumklostervej 34",
    "sg:city":"Aabenraa",
    "sg:orig_category":"Psykologer, praktiserende",
    "sg:phone":"+45 74 62 47 49",
    "sg:postcode":"6200",
    "sg:province":"Danmark",
    "wof:name":"Boisen, Birgitte",
    "wof:placetype":"venue"
},
  "geometry": {"coordinates":[9.4134140015,55.050945282],"type":"Point"}
}