{
  "type": "Feature",
  "properties": {
    "iso:country":"DK",
    "sg:address":"M\u00e5gevej 29",
    "sg:city":"Hadsten",
    "sg:orig_category":"Blikkenslagere",
    "sg:phone":"+45 87 61 28 50",
    "sg:postcode":"8370",
    "sg:province":"Danmark",
    "wof:name":"Byens Blikkenslager ApS",
    "wof:placetype":"venue"
},
  "geometry": {"coordinates":[10.028443,56.3316],"type":"Point"}
}