{
  "type": "Feature",
  "properties": {
    "addr:full":"Fuglsangsgade 1 Mariager Danmark 9550",
    "addr:housenumber":"1",
    "addr:postcode":"9550",
    "addr:street":"Fuglsangsgade",
    "iso:country":"DK",
    "sg:address":"Fuglsangsgade 1",
    "sg:city":"Mariager",
    "sg:orig_category":"Advokater",
    "sg:phone":"+45 98 54 13 00",
    "sg:postcode":"9550",
    "sg:province":"Danmark",
    "wof:name":"Kirch & Hanne B\u00e6rentsen, Advokatfirmaet Pauli",
    "wof:placetype":"venue"
},
  "geometry": {"coordinates":[9.9830360413,56.6501846313],"type":"Point"}
}