{
  "type": "Feature",
  "properties": {
    "addr:full":"Henv.: Lilian Vinther, Skolev\u00e6nget 39 B, Borris Skjern Danmark 6900",
    "addr:housenumber":"39 b",
    "addr:postcode":"6900",
    "addr:street":"Henv.;Skolevaenget;Borris",
    "iso:country":"DK",
    "sg:address":"Henv.: Lilian Vinther, Skolev\u00e6nget 39 B, Borris",
    "sg:city":"Skjern",
    "sg:orig_category":"\u00c3\u2020ldreorganisationer og klubber",
    "sg:phone":"+45 97 36 63 13",
    "sg:postcode":"6900",
    "sg:province":"Danmark",
    "wof:name":"Boris Hyggeklub",
    "wof:placetype":"venue"
},
  "geometry": {"coordinates":[8.492972374,55.9485740662],"type":"Point"}
}