{
  "type": "Feature",
  "properties": {
    "addr:full":"Fmd.: Lene Kristoffersen, Eveldrupvej 114, Eveldrup Aalestrup Danmark 9620",
    "addr:housenumber":"114",
    "addr:postcode":"9620",
    "addr:street":"Eveldrupvej;Eveldrup",
    "iso:country":"DK",
    "sg:address":"Fmd.: Lene Kristoffersen, Eveldrupvej 114, Eveldrup",
    "sg:city":"Aalestrup",
    "sg:orig_category":"Husflidsforeninger",
    "sg:phone":"+45 98 64 92 28",
    "sg:postcode":"9620",
    "sg:province":"Danmark",
    "wof:name":"Aalestrupegnens Familiebrugs Familieudvalg",
    "wof:placetype":"venue"
},
  "geometry": {"coordinates":[9.4901504517,56.6938285828],"type":"Point"}
}