{
  "type": "Feature",
  "properties": {
    "addr:full":"Gedvad 10 E Kongens Lyngby Danmark 2800",
    "addr:housenumber":"10 e",
    "addr:postcode":"2800",
    "addr:street":"Gedvad",
    "iso:country":"DK",
    "sg:address":"Gedvad 10 E",
    "sg:city":"Kongens Lyngby",
    "sg:orig_category":"Vinduespolering",
    "sg:phone":"+45 26 20 39 00",
    "sg:postcode":"2800",
    "sg:province":"Danmark",
    "wof:name":"B & W Polering",
    "wof:placetype":"venue"
},
  "geometry": {"coordinates":[12.5368299484,55.7949905396],"type":"Point"}
}