{
  "type": "Feature",
  "properties": {
    "iso:country":"DK",
    "sg:address":"Bjerredevej 22",
    "sg:city":"Tureby",
    "sg:orig_category":"Korn og foderstoffer",
    "sg:phone":"+45 56 28 35 72",
    "sg:postcode":"4682",
    "sg:province":"Danmark",
    "wof:name":"Gl. Tofteg\u00e5rd Halm",
    "wof:placetype":"venue"
},
  "geometry": {"coordinates":[12.0354166031,55.3868331909],"type":"Point"}
}