{
  "type": "Feature",
  "properties": {
    "addr:full":"Algade 59 Aalborg Danmark 9000",
    "addr:housenumber":"59",
    "addr:postcode":"9000",
    "addr:street":"Algade",
    "iso:country":"DK",
    "sg:address":"Algade 59",
    "sg:city":"Aalborg",
    "sg:orig_category":"Symaskiner",
    "sg:phone":"+45 98 12 00 89",
    "sg:postcode":"9000",
    "sg:province":"Danmark",
    "wof:name":"Design og Sycenter",
    "wof:placetype":"venue"
},
  "geometry": {"coordinates":[9.916642189,57.0481452942],"type":"Point"}
}