{
  "type": "Feature",
  "properties": {
    "addr:full":"Kirkegaardsvej 5 Gr\u00e5sten Danmark 6300",
    "addr:housenumber":"5",
    "addr:postcode":"6300",
    "addr:street":"Kirkegaardsvej",
    "iso:country":"DK",
    "sg:address":"Kirkegaardsvej 5",
    "sg:city":"Gr\u00e5sten",
    "sg:orig_category":"Snedkermestre",
    "sg:phone":"+45 74 65 26 16",
    "sg:postcode":"6300",
    "sg:province":"Danmark",
    "wof:name":"Brandt's M\u00f8belsnedkeri",
    "wof:placetype":"venue"
},
  "geometry": {"coordinates":[25.3302497864,60.2151107788],"type":"Point"}
}