{
  "type": "Feature",
  "properties": {
    "addr:full":"Egemosevej 11, Lindersvold Fakse Danmark 4640",
    "addr:housenumber":"11",
    "addr:postcode":"4640",
    "addr:street":"Egemosevej",
    "iso:country":"DK",
    "sg:address":"Egemosevej 11, Lindersvold",
    "sg:city":"Fakse",
    "sg:orig_category":"Revisorer",
    "sg:phone":"+45 56 72 55 92",
    "sg:postcode":"4640",
    "sg:province":"Danmark",
    "wof:name":"Egholm Regnskabskontor",
    "wof:placetype":"venue"
},
  "geometry": {"coordinates":[12.1203422546,55.2574195862],"type":"Point"}
}