{
  "type": "Feature",
  "properties": {
    "addr:full":"Banegaardsvej 5 Hobro Danmark 9500",
    "addr:housenumber":"5",
    "addr:postcode":"9500",
    "addr:street":"Banegaardsvej",
    "iso:country":"DK",
    "sg:address":"Banegaardsvej 5",
    "sg:city":"Hobro",
    "sg:orig_category":"Autoforhandlere",
    "sg:phone":"+45 98 52 42 26",
    "sg:postcode":"9500",
    "sg:province":"Danmark",
    "wof:name":"H. J. Biler",
    "wof:placetype":"venue"
},
  "geometry": {"coordinates":[9.791893959,56.6430587769],"type":"Point"}
}