{
  "type": "Feature",
  "properties": {
    "iso:country":"DK",
    "sg:address":"Fmd.: Bente Bach, Egedal 16, Finderup",
    "sg:city":"Viborg",
    "sg:orig_category":"Borger- og beboerforeninger",
    "sg:phone":"+45 86 64 74 99",
    "sg:postcode":"8800",
    "sg:province":"Danmark",
    "wof:name":"Finderup Borgerforening",
    "wof:placetype":"venue"
},
  "geometry": {"coordinates":[9.4071502686,56.452671051],"type":"Point"}
}