{
  "type": "Feature",
  "properties": {
    "addr:full":"Frederiksborgvej 27 K\u00f8benhavn NV Danmark 2400",
    "addr:housenumber":"27",
    "addr:postcode":"2400",
    "addr:street":"Frederiksborgvej",
    "iso:country":"DK",
    "sg:address":"Frederiksborgvej 27",
    "sg:city":"K\u00f8benhavn NV",
    "sg:classifiers":[
        {
            "category":"Restaurant",
            "type":"Food & Drink"
        }
    ],
    "sg:phone":"+45 38 10 16 59",
    "sg:postcode":"2400",
    "sg:province":"Danmark",
    "wof:name":"Bondestuen",
    "wof:placetype":"venue"
},
  "geometry": {"coordinates":[-117.02272033689999,38.5024604797],"type":"Point"}
}