{
  "type": "Feature",
  "properties": {
    "addr:full":"Brogade 6-8 Odense C Danmark 5000",
    "addr:housenumber":"6-8",
    "addr:postcode":"5000",
    "addr:street":"Brogade",
    "iso:country":"DK",
    "sg:address":"Brogade 6-8",
    "sg:city":"Odense C",
    "sg:classifiers":[
        {
            "category":"Communications",
            "type":"Services"
        }
    ],
    "sg:phone":"+45 66 17 80 00",
    "sg:postcode":"5000",
    "sg:province":"Danmark",
    "sg:tags":[
        "radio-",
        "og",
        "tv-stationer"
    ],
    "wof:name":"Voice Odense, The & Nordisk Radioreklame A/S",
    "wof:placetype":"venue"
},
  "geometry": {"coordinates":[10.3962850571,55.3967475891],"type":"Point"}
}