{
  "type": "Feature",
  "properties": {
    "iso:country":"DK",
    "sg:address":"Oliefabriksvej 29 - 43 ",
    "sg:city":"Kastrup",
    "sg:classifiers":[
        {
            "category":"Parking",
            "subcategory":"Lot",
            "type":"Transportation"
        }
    ],
    "sg:phone":"+45 32 51 75 11",
    "sg:postcode":"2770",
    "sg:province":"Danmark",
    "sg:tags":[
        "transport",
        "road"
    ],
    "wof:name":"WILSON LOGISTICS A/S",
    "wof:placetype":"venue"
},
  "geometry": {"coordinates":[12.5926828384,55.6267127991],"type":"Point"}
}