{
  "type": "Feature",
  "properties": {
    "addr:full":"H.C.\u00d8rsteds Vej 13  Kolding Danmark 6000",
    "addr:housenumber":"13",
    "addr:postcode":"6000",
    "addr:street":"H.C.Orsteds Vej",
    "iso:country":"DK",
    "sg:address":"H.C.\u00d8rsteds Vej 13 ",
    "sg:city":"Kolding",
    "sg:classifiers":[
        {
            "category":"Shopping",
            "subcategory":"Crafts & Fabrics",
            "type":"Retail Goods"
        }
    ],
    "sg:phone":"+45 75 52 90 11",
    "sg:postcode":"6000",
    "sg:province":"Danmark",
    "sg:tags":[
        "ceramic"
    ],
    "wof:name":"ALFIX A/S",
    "wof:placetype":"venue"
},
  "geometry": {"coordinates":[9.4733953476,55.4863586426],"type":"Point"}
}