{
  "type": "Feature",
  "properties": {
    "iso:country":"DK",
    "sg:address":"Skovparken 4",
    "sg:city":"Vejle",
    "sg:orig_category":"Snedkermestre",
    "sg:phone":"+45 75 86 35 17",
    "sg:postcode":"7100",
    "sg:province":"Danmark",
    "wof:name":"Panduro Snedker & t\u00f8mmerforretning, Conny",
    "wof:placetype":"venue"
},
  "geometry": {"coordinates":[9.5157909393,55.6720924377],"type":"Point"}
}