{
  "type": "Feature",
  "properties": {
    "addr:full":"\u00d8ster\u00e5gade 11 Aalborg Danmark 9000",
    "addr:housenumber":"11",
    "addr:postcode":"9000",
    "addr:street":"Osteraagade",
    "iso:country":"DK",
    "sg:address":"\u00d8ster\u00e5gade 11",
    "sg:city":"Aalborg",
    "sg:orig_category":"Materialister",
    "sg:phone":"+45 98 13 47 22",
    "sg:postcode":"9000",
    "sg:province":"Danmark",
    "wof:name":"Matas",
    "wof:placetype":"venue"
},
  "geometry": {"coordinates":[9.921248436,57.0485687256],"type":"Point"}
}