{
  "type": "Feature",
  "properties": {
    "addr:full":"Skolevangen 9 A Ulstrup Danmark 8860",
    "addr:housenumber":"9 a",
    "addr:postcode":"8860",
    "addr:street":"Skolevangen",
    "iso:country":"DK",
    "sg:address":"Skolevangen 9 A",
    "sg:city":"Ulstrup",
    "sg:orig_category":"Psykologer, praktiserende",
    "sg:phone":"+45 23 72 97 46",
    "sg:postcode":"8860",
    "sg:province":"Danmark",
    "wof:name":"Riisager, Helle",
    "wof:placetype":"venue"
},
  "geometry": {"coordinates":[9.7880868912,56.3857803345],"type":"Point"}
}