{
  "type": "Feature",
  "properties": {
    "addr:full":"Engvej 15 Hinnerup Danmark 8382",
    "addr:housenumber":"15",
    "addr:postcode":"8382",
    "addr:street":"Engvej",
    "iso:country":"DK",
    "sg:address":"Engvej 15",
    "sg:city":"Hinnerup",
    "sg:orig_category":"Vaskemaskiner og service",
    "sg:phone":"+45 86 98 61 35",
    "sg:postcode":"8382",
    "sg:province":"Danmark",
    "wof:name":"Kiehl Hvidevareservice, G\u00fcnter",
    "wof:placetype":"venue"
},
  "geometry": {"coordinates":[10.0633554459,56.256313324],"type":"Point"}
}