{
  "type": "Feature",
  "properties": {
    "iso:country":"DK",
    "sg:address":"G\u00f8ttrupvej 15",
    "sg:city":"Toftlund",
    "sg:orig_category":"Cykler",
    "sg:phone":"+45 73 83 20 10",
    "sg:postcode":"6520",
    "sg:province":"Danmark",
    "sg:website":"www.toftlundmaskinforretning.dk",
    "wof:name":"Toftlund Maskinforretning A/S",
    "wof:placetype":"venue"
},
  "geometry": {"coordinates":[9.0629367828,55.1926651001],"type":"Point"}
}