{
  "type": "Feature",
  "properties": {
    "addr:full":"Fmd.: Lisbeth S. Nielsen, S\u00f8nderklit 5 Skagen Danmark 9990",
    "addr:housenumber":"5",
    "addr:postcode":"9990",
    "addr:street":"Lisbeth S. Nielsen Sonderklit",
    "iso:country":"DK",
    "sg:address":"Fmd.: Lisbeth S. Nielsen, S\u00f8nderklit 5",
    "sg:city":"Skagen",
    "sg:orig_category":"Hobbybetonede foreninger",
    "sg:phone":"+45 98 44 46 97",
    "sg:postcode":"9990",
    "sg:province":"Danmark",
    "wof:name":"Patchworkforeningen Skaw-quilt",
    "wof:placetype":"venue"
},
  "geometry": {"coordinates":[10.5958003998,57.7247200012],"type":"Point"}
}