{
  "type": "Feature",
  "properties": {
    "addr:full":"Heimdalsgade 44 Aalborg Danmark 9000",
    "addr:housenumber":"44",
    "addr:postcode":"9000",
    "addr:street":"Heimdalsgade",
    "iso:country":"DK",
    "sg:address":"Heimdalsgade 44",
    "sg:city":"Aalborg",
    "sg:orig_category":"Autoforhandlere",
    "sg:phone":"+45 98 16 77 66",
    "sg:postcode":"9000",
    "sg:province":"Danmark",
    "wof:name":"J. J. Auto",
    "wof:placetype":"venue"
},
  "geometry": {"coordinates":[9.953953743,57.0376167297],"type":"Point"}
}