{
  "type": "Feature",
  "properties": {
    "addr:full":"Bygaden 29, Lejre, Postboks 39 Lejre Danmark 4320",
    "addr:housenumber":"29;39",
    "addr:postcode":"4320",
    "addr:street":"Bygaden;Postboks",
    "iso:country":"DK",
    "sg:address":"Bygaden 29, Lejre, Postboks 39",
    "sg:city":"Lejre",
    "sg:orig_category":"Politi",
    "sg:phone":"+45 46 48 05 68",
    "sg:postcode":"4320",
    "sg:province":"Danmark",
    "wof:name":"Landpolitistationen for Lejre kommune",
    "wof:placetype":"venue"
},
  "geometry": {"coordinates":[11.9678316116,55.6005630493],"type":"Point"}
}