{
  "type": "Feature",
  "properties": {
    "addr:full":"Nyvej 36, Ulb\u00f8lle Vester Skerninge Danmark 5762",
    "addr:housenumber":"36",
    "addr:postcode":"5762",
    "addr:street":"Nyvej",
    "iso:country":"DK",
    "sg:address":"Nyvej 36, Ulb\u00f8lle",
    "sg:city":"Vester Skerninge",
    "sg:orig_category":"Andelsboligforeninger",
    "sg:phone":"+45 62 24 36 19",
    "sg:postcode":"5762",
    "sg:province":"Danmark",
    "wof:name":"Andelsforeningen Gr\u00f8nt Samvirke M\u00f8llen",
    "wof:placetype":"venue"
},
  "geometry": {"coordinates":[10.5008449554,55.070400238],"type":"Point"}
}