{
  "type": "Feature",
  "properties": {
    "addr:full":"N\u00f8rregade 7 Ranum Danmark 9681",
    "addr:housenumber":"7",
    "addr:postcode":"9681",
    "addr:street":"Norregade",
    "iso:country":"DK",
    "sg:address":"N\u00f8rregade 7",
    "sg:city":"Ranum",
    "sg:orig_category":"Fodplejere",
    "sg:phone":"+45 98 67 63 66",
    "sg:postcode":"9681",
    "sg:province":"Danmark",
    "wof:name":"Ranum Fodklinik",
    "wof:placetype":"venue"
},
  "geometry": {"coordinates":[9.2296209335,56.8970336914],"type":"Point"}
}