{
  "type": "Feature",
  "properties": {
    "addr:full":"Ndr. Ringvej 9 Nyk\u00f8bing Danmark 4800",
    "addr:housenumber":"9",
    "addr:postcode":"4800",
    "addr:street":"Ndr. Ringvej",
    "iso:country":"DK",
    "sg:address":"Ndr. Ringvej 9",
    "sg:city":"Nyk\u00f8bing",
    "sg:classifiers":[
        {
            "category":"Taxi",
            "type":"Transportation"
        }
    ],
    "sg:phone":"+45 54 85 43 44",
    "sg:postcode":"4800",
    "sg:province":"Danmark",
    "wof:name":"Taxa Nyk\u00f8bing F.",
    "wof:placetype":"venue"
},
  "geometry": {"coordinates":[14.2974796295,36.0507698059],"type":"Point"}
}