{
  "type": "Feature",
  "properties": {
    "addr:full":"\u00c5boulevard 11 C K\u00f8benhavn Danmark 1635",
    "addr:housenumber":"11 c;1635",
    "addr:street":"Aaboulevard",
    "iso:country":"DK",
    "sg:address":"\u00c5boulevard 11 C",
    "sg:city":"K\u00f8benhavn",
    "sg:orig_category":"Revisorer",
    "sg:phone":"+45 35 35 71 31",
    "sg:postcode":"1635",
    "sg:province":"Danmark",
    "wof:name":"S\u00f8ernes Revision ApS",
    "wof:placetype":"venue"
},
  "geometry": {"coordinates":[-116.27327728269999,32.6635398865],"type":"Point"}
}