{
  "type": "Feature",
  "properties": {
    "iso:country":"DK",
    "sg:address":"\u00d8stre Paradisvej 74, \u00d8ver\u00f8d",
    "sg:city":"Holte",
    "sg:orig_category":"Regnskabsassistance",
    "sg:phone":"+45 45 42 58 10",
    "sg:postcode":"2840",
    "sg:province":"Danmark",
    "wof:name":"Holte Erhvervs Service",
    "wof:placetype":"venue"
},
  "geometry": {"coordinates":[12.4706554413,55.8122367859],"type":"Point"}
}