{
  "type": "Feature",
  "properties": {
    "iso:country":"DK",
    "sg:address":"Hadsundvej 19",
    "sg:city":"Aalborg",
    "sg:orig_category":"Glasfiberindustri",
    "sg:phone":"+45 98 11 31 73",
    "sg:postcode":"9000",
    "sg:province":"Danmark",
    "wof:name":"L\u00f8ga",
    "wof:placetype":"venue"
},
  "geometry": {"coordinates":[9.950252533,57.0430831909],"type":"Point"}
}