{
  "type": "Feature",
  "properties": {
    "iso:country":"DK",
    "sg:address":"Havnegade 51",
    "sg:city":"Odense C",
    "sg:orig_category":"Spedition",
    "sg:phone":"+45 66 17 89 00",
    "sg:postcode":"5000",
    "sg:province":"Danmark",
    "wof:name":"Hansen Spedition Odense ApS, Ove",
    "wof:placetype":"venue"
},
  "geometry": {"coordinates":[10.3806400299,55.4169578552],"type":"Point"}
}