{
  "type": "Feature",
  "properties": {
    "addr:full":"Portalen 2 Greve Danmark 2670",
    "addr:housenumber":"2",
    "addr:postcode":"2670",
    "addr:street":"Portalen",
    "iso:country":"DK",
    "sg:address":"Portalen 2",
    "sg:city":"Greve",
    "sg:orig_category":"Biblioteker",
    "sg:phone":"+45 43 95 80 00",
    "sg:postcode":"2670",
    "sg:province":"Danmark",
    "sg:website":"www.grevebib.dk",
    "wof:name":"Greve Bibliotek",
    "wof:placetype":"venue"
},
  "geometry": {"coordinates":[12.332156,55.5979],"type":"Point"}
}