{
  "type": "Feature",
  "properties": {
    "iso:country":"DK",
    "sg:address":"Bredgade 63-65",
    "sg:city":"K\u00f8benhavn",
    "sg:classifiers":[
        {
            "category":"Restaurant",
            "type":"Food & Drink"
        }
    ],
    "sg:phone":"+45 33 11 45 15",
    "sg:postcode":"1260",
    "sg:province":"Danmark",
    "sg:website":"WWW.lesommelier.dk",
    "wof:name":"Le Sommelier",
    "wof:placetype":"venue"
},
  "geometry": {"coordinates":[12.5931997299,55.6845016479],"type":"Point"}
}