{
  "type": "Feature",
  "properties": {
    "addr:full":"Gl. Randersvej 2 Viborg Danmark 8800",
    "addr:housenumber":"2",
    "addr:postcode":"8800",
    "addr:street":"Gl. Randersvej",
    "iso:country":"DK",
    "sg:address":"Gl. Randersvej 2",
    "sg:city":"Viborg",
    "sg:orig_category":"Forsikringer",
    "sg:phone":"+45 86 67 14 44",
    "sg:postcode":"8800",
    "sg:province":"Danmark",
    "sg:website":"www.skovbrand.dk",
    "wof:name":"Dansk Plantageforsikring",
    "wof:placetype":"venue"
},
  "geometry": {"coordinates":[9.4182834625,56.4497756958],"type":"Point"}
}