{
  "type": "Feature",
  "properties": {
    "addr:full":"Kristrup Engvej 40 Randers Danmark 8900",
    "addr:housenumber":"40",
    "addr:postcode":"8900",
    "addr:street":"Kristrup Engvej",
    "iso:country":"DK",
    "sg:address":"Kristrup Engvej 40",
    "sg:city":"Randers",
    "sg:orig_category":"Havebrugsmaskiner",
    "sg:phone":"+45 70 25 00 20",
    "sg:postcode":"8900",
    "sg:province":"Danmark",
    "sg:website":"www.kiba.dk",
    "wof:name":"Kiba Parkmaskiner",
    "wof:placetype":"venue"
},
  "geometry": {"coordinates":[10.07908535,56.4555053711],"type":"Point"}
}