{
  "type": "Feature",
  "properties": {
    "addr:full":"Vejers Havvej 7 Vejers Strand Danmark 6853",
    "addr:housenumber":"7",
    "addr:postcode":"6853",
    "addr:street":"Vejers Havvej",
    "iso:country":"DK",
    "sg:address":"Vejers Havvej 7",
    "sg:city":"Vejers Strand",
    "sg:orig_category":"Campingpladser",
    "sg:phone":"+45 75 27 70 54",
    "sg:postcode":"6853",
    "sg:province":"Danmark",
    "sg:website":"www.stjernecamping.dk",
    "wof:name":"Stjerne Camping",
    "wof:placetype":"venue"
},
  "geometry": {"coordinates":[8.1420097351,55.6191062927],"type":"Point"}
}