{
  "type": "Feature",
  "properties": {
    "addr:full":"Nylandsvej 33 Karlslunde Danmark 2690",
    "addr:housenumber":"33",
    "addr:postcode":"2690",
    "addr:street":"Nylandsvej",
    "iso:country":"DK",
    "sg:address":"Nylandsvej 33",
    "sg:city":"Karlslunde",
    "sg:orig_category":"Malermestre",
    "sg:phone":"+45 43 43 10 45",
    "sg:postcode":"2690",
    "sg:province":"Danmark",
    "wof:name":"Br\u00f8ndby Malerservice",
    "wof:placetype":"venue"
},
  "geometry": {"coordinates":[12.2221069336,55.5720901489],"type":"Point"}
}