{
  "type": "Feature",
  "properties": {
    "addr:full":"Borgergade 17 Grindsted Danmark 7200",
    "addr:housenumber":"17",
    "addr:postcode":"7200",
    "addr:street":"Borgergade",
    "iso:country":"DK",
    "sg:address":"Borgergade 17",
    "sg:city":"Grindsted",
    "sg:orig_category":"Boghandlere",
    "sg:phone":"+45 75 32 01 52",
    "sg:postcode":"7200",
    "sg:province":"Danmark",
    "wof:name":"Overgaard B\u00f8ger",
    "wof:placetype":"venue"
},
  "geometry": {"coordinates":[8.9293355942,55.7566413879],"type":"Point"}
}