{
  "type": "Feature",
  "properties": {
    "addr:full":"v/ Ove Madsen, Tinningvej 19, Foldby Hinnerup Danmark 8382",
    "addr:housenumber":"19",
    "addr:postcode":"8382",
    "addr:street":"Tinningvej;Foldby",
    "iso:country":"DK",
    "sg:address":"v/ Ove Madsen, Tinningvej 19, Foldby",
    "sg:city":"Hinnerup",
    "sg:orig_category":"Grundejerforeninger",
    "sg:phone":"+45 86 98 79 83",
    "sg:postcode":"8382",
    "sg:province":"Danmark",
    "wof:name":"Grundejerforeningen Tinningv\u00e6nget",
    "wof:placetype":"venue"
},
  "geometry": {"coordinates":[10.0614156723,56.2650604248],"type":"Point"}
}