{
  "type": "Feature",
  "properties": {
    "addr:full":"Fmd.: Jens Erik Jensen, Topsh\u00f8jvej 84 Sor\u00f8 Danmark 4180",
    "addr:housenumber":"84",
    "addr:postcode":"4180",
    "addr:street":"Topshojvej",
    "iso:country":"DK",
    "sg:address":"Fmd.: Jens Erik Jensen, Topsh\u00f8jvej 84",
    "sg:city":"Sor\u00f8",
    "sg:orig_category":"Landboorganisationer",
    "sg:phone":"+45 57 84 92 55",
    "sg:postcode":"4180",
    "sg:province":"Danmark",
    "wof:name":"Sor\u00f8egnens Familielandbrug/Husmandsforening",
    "wof:placetype":"venue"
},
  "geometry": {"coordinates":[-102.94467926030001,45.4534721375],"type":"Point"}
}