{
  "type": "Feature",
  "properties": {
    "addr:full":"Dalvej 2, Aidt Thors\u00f8 Danmark 8881",
    "addr:housenumber":"2",
    "addr:postcode":"8881",
    "addr:street":"Dalvej",
    "iso:country":"DK",
    "sg:address":"Dalvej 2, Aidt",
    "sg:city":"Thors\u00f8",
    "sg:orig_category":"Forsamlingshuse",
    "sg:phone":"+45 86 96 69 42",
    "sg:postcode":"8881",
    "sg:province":"Danmark",
    "wof:name":"Aidt Forsamlingshus",
    "wof:placetype":"venue"
},
  "geometry": {"coordinates":[9.7878103256,56.2985954285],"type":"Point"}
}