{
  "type": "Feature",
  "properties": {
    "addr:full":"Bredgade 21 Karise Danmark 4653",
    "addr:housenumber":"21",
    "addr:postcode":"4653",
    "addr:street":"Bredgade",
    "iso:country":"DK",
    "sg:address":"Bredgade 21",
    "sg:city":"Karise",
    "sg:orig_category":"Bodegaer",
    "sg:phone":"+45 56 78 87 88",
    "sg:postcode":"4653",
    "sg:province":"Danmark",
    "wof:name":"Karise Bodega",
    "wof:placetype":"venue"
},
  "geometry": {"coordinates":[12.2003030777,55.307384491],"type":"Point"}
}