{
  "type": "Feature",
  "properties": {
    "addr:full":"Hovedgaden 30 Spjald Danmark 6971",
    "addr:housenumber":"30",
    "addr:postcode":"6971",
    "addr:street":"Hovedgaden",
    "iso:country":"DK",
    "sg:address":"Hovedgaden 30",
    "sg:city":"Spjald",
    "sg:orig_category":"Farve og tapet",
    "sg:phone":"+45 97 38 15 26",
    "sg:postcode":"6971",
    "sg:province":"Danmark",
    "wof:name":"Fl\u00fcgger farver",
    "wof:placetype":"venue"
},
  "geometry": {"coordinates":[8.5057544708,56.1241264343],"type":"Point"}
}