{
  "type": "Feature",
  "properties": {
    "addr:full":"\u00d8rkebyvej 8 Otterup Danmark 5450",
    "addr:housenumber":"8",
    "addr:postcode":"5450",
    "addr:street":"Orkebyvej",
    "iso:country":"DK",
    "sg:address":"\u00d8rkebyvej 8",
    "sg:city":"Otterup",
    "sg:orig_category":"Snedkermestre",
    "sg:phone":"+45 64 82 25 84",
    "sg:postcode":"5450",
    "sg:province":"Danmark",
    "wof:name":"PhP Snedkeren",
    "wof:placetype":"venue"
},
  "geometry": {"coordinates":[10.3950157166,55.5037994385],"type":"Point"}
}