{
  "type": "Feature",
  "properties": {
    "addr:full":"Fmd.: S\u00f8ren Eg J\u00f8rgensen, Varde Landevej 64, Eg Grindsted Danmark 7200",
    "addr:housenumber":"64",
    "addr:postcode":"eg;7200",
    "addr:street":"Jorgensen Varde Landevej",
    "iso:country":"DK",
    "sg:address":"Fmd.: S\u00f8ren Eg J\u00f8rgensen, Varde Landevej 64, Eg",
    "sg:city":"Grindsted",
    "sg:orig_category":"Hobbybetonede foreninger",
    "sg:phone":"+45 75 33 00 56",
    "sg:postcode":"7200",
    "sg:province":"Danmark",
    "wof:name":"M\u00f8lby-Eg Fiskeriforening",
    "wof:placetype":"venue"
},
  "geometry": {"coordinates":[8.9288702011,55.7560272217],"type":"Point"}
}