{
  "type": "Feature",
  "properties": {
    "iso:country":"DK",
    "sg:address":"Sm\u00f8rumvej 197",
    "sg:city":"Br\u00f8nsh\u00f8j",
    "sg:orig_category":"Vuggestuer",
    "sg:phone":"+45 38 28 17 62",
    "sg:postcode":"2700",
    "sg:province":"Danmark",
    "wof:name":"Vuggestuen i Ungdomsg\u00e5rden",
    "wof:placetype":"venue"
},
  "geometry": {"coordinates":[30.0104103088,60.1411018372],"type":"Point"}
}