{
  "type": "Feature",
  "properties": {
    "addr:full":"Sindalsvej 17 Risskov Danmark 8240",
    "addr:housenumber":"17",
    "addr:postcode":"8240",
    "addr:street":"Sindalsvej",
    "iso:country":"DK",
    "sg:address":"Sindalsvej 17",
    "sg:city":"Risskov",
    "sg:orig_category":"Bijouterier",
    "sg:phone":"+45 86 21 30 11",
    "sg:postcode":"8240",
    "sg:province":"Danmark",
    "wof:name":"Jens E. Bijouterie A/S",
    "wof:placetype":"venue"
},
  "geometry": {"coordinates":[10.219396,56.208675],"type":"Point"}
}