{
  "type": "Feature",
  "properties": {
    "addr:full":"Valby Langgade 117 A Valby Danmark 2500",
    "addr:housenumber":"117 a",
    "addr:postcode":"2500",
    "addr:street":"Valby Langgade",
    "iso:country":"DK",
    "sg:address":"Valby Langgade 117 A",
    "sg:city":"Valby",
    "sg:orig_category":"Skoler",
    "sg:phone":"+45 36 46 85 16",
    "sg:postcode":"2500",
    "sg:province":"Danmark",
    "sg:website":"www.freinetskolen.dk",
    "wof:name":"Freinetskolen",
    "wof:placetype":"venue"
},
  "geometry": {"coordinates":[12.5059270859,55.6662521362],"type":"Point"}
}