{
  "type": "Feature",
  "properties": {
    "addr:full":"\u00d8stergade 3 Fjerritslev Danmark 9690",
    "addr:housenumber":"3",
    "addr:postcode":"9690",
    "addr:street":"Ostergade",
    "iso:country":"DK",
    "sg:address":"\u00d8stergade 3",
    "sg:city":"Fjerritslev",
    "sg:classifiers":[
        {
            "category":"Food & Beverages",
            "subcategory":"Liquor & Beverages",
            "type":"Retail Goods"
        }
    ],
    "sg:phone":"+45 98 21 11 50",
    "sg:postcode":"9690",
    "sg:province":"Danmark",
    "sg:tags":[
        "vin"
    ],
    "wof:name":"Skjold Burne Vin og Tobak",
    "wof:placetype":"venue"
},
  "geometry": {"coordinates":[9.2667350769,57.0882301331],"type":"Point"}
}