{
  "type": "Feature",
  "properties": {
    "addr:full":"Dronning Sofies Vej 114 Roskilde Danmark 4000",
    "addr:housenumber":"114",
    "addr:postcode":"4000",
    "addr:street":"Dronning Sofies Vej",
    "iso:country":"DK",
    "sg:address":"Dronning Sofies Vej 114",
    "sg:city":"Roskilde",
    "sg:orig_category":"Musikinstrumenter",
    "sg:phone":"+45 46 35 08 31",
    "sg:postcode":"4000",
    "sg:province":"Danmark",
    "wof:name":"IBSEN musikinstrumenter",
    "wof:placetype":"venue"
},
  "geometry": {"coordinates":[12.0966663361,55.6530151367],"type":"Point"}
}