{
  "type": "Feature",
  "properties": {
    "addr:full":"Hvid\u00f8revej 62 Klampenborg Danmark 2930",
    "addr:housenumber":"62",
    "addr:postcode":"2930",
    "addr:street":"Hvidorevej",
    "iso:country":"DK",
    "sg:address":"Hvid\u00f8revej 62",
    "sg:city":"Klampenborg",
    "sg:classifiers":[
        {
            "category":"Professional",
            "subcategory":"Computer Services",
            "type":"Services"
        }
    ],
    "sg:phone":"+45 70 20 19 91",
    "sg:postcode":"2930",
    "sg:province":"Danmark",
    "sg:tags":[
        "edb",
        "-",
        "software"
    ],
    "sg:website":"www.1stfordata.dk",
    "wof:name":"1stForData ApS",
    "wof:placetype":"venue"
},
  "geometry": {"coordinates":[12.5791149139,55.7700881958],"type":"Point"}
}