{
  "type": "Feature",
  "properties": {
    "addr:full":"Edisonvej 5 Vejle Danmark 7100",
    "addr:housenumber":"5",
    "addr:postcode":"7100",
    "addr:street":"Edisonvej",
    "iso:country":"DK",
    "sg:address":"Edisonvej 5",
    "sg:city":"Vejle",
    "sg:orig_category":"Spedition",
    "sg:phone":"+45 79 42 99 99",
    "sg:postcode":"7100",
    "sg:province":"Danmark",
    "wof:name":"Hansen & Co. a/s, Otto",
    "wof:placetype":"venue"
},
  "geometry": {"coordinates":[9.5703887939,55.7327232361],"type":"Point"}
}