{
  "type": "Feature",
  "properties": {
    "addr:full":"Hartmannsvej 19 Hellerup Danmark 2900",
    "addr:housenumber":"19",
    "addr:postcode":"2900",
    "addr:street":"Hartmannsvej",
    "iso:country":"DK",
    "sg:address":"Hartmannsvej 19",
    "sg:city":"Hellerup",
    "sg:orig_category":"Arkitekter",
    "sg:phone":"+45 39 62 56 27",
    "sg:postcode":"2900",
    "sg:province":"Danmark",
    "wof:name":"Hagedorn, Thomas",
    "wof:placetype":"venue"
},
  "geometry": {"coordinates":[12.5656290054,55.7415733337],"type":"Point"}
}