{
  "type": "Feature",
  "properties": {
    "iso:country":"DK",
    "sg:address":"Aftensang 10 ",
    "sg:city":"Egtved",
    "sg:classifiers":[
        {
            "category":"Shopping",
            "subcategory":"Clothing, Apparel, & Fashions",
            "type":"Retail Goods"
        }
    ],
    "sg:phone":"+45 75 55 13 00",
    "sg:postcode":"6040",
    "sg:province":"Danmark",
    "sg:tags":[
        "clothes"
    ],
    "wof:name":"EGTVED STR\u00d8MPEFABRIK A/S",
    "wof:placetype":"venue"
},
  "geometry": {"coordinates":[9.3064680099,55.6195678711],"type":"Point"}
}