{
  "type": "Feature",
  "properties": {
    "iso:country":"DK",
    "sg:address":"Adamsgavevej 80, Branderslev",
    "sg:city":"Nakskov",
    "sg:orig_category":"Kirker",
    "sg:postcode":"4900",
    "sg:province":"Danmark",
    "wof:name":"Branderslev Kirke",
    "wof:placetype":"venue"
},
  "geometry": {"coordinates":[11.1359500885,54.8330116272],"type":"Point"}
}