{
  "type": "Feature",
  "properties": {
    "addr:full":"v/ Erik B. Jensen, Hvidovrevej 22 A R\u00f8dovre Danmark 2610",
    "addr:housenumber":"22 a",
    "addr:postcode":"2610",
    "addr:street":"Hvidovrevej",
    "iso:country":"DK",
    "sg:address":"v/ Erik B. Jensen, Hvidovrevej 22 A",
    "sg:city":"R\u00f8dovre",
    "sg:orig_category":"Hobbybetonede foreninger",
    "sg:phone":"+45 36 72 04 64",
    "sg:postcode":"2610",
    "sg:province":"Danmark",
    "wof:name":"Peugeot Club Denmark",
    "wof:placetype":"venue"
},
  "geometry": {"coordinates":[10.6992139816,61.1027755737],"type":"Point"}
}