{
  "type": "Feature",
  "properties": {
    "addr:full":"Landsbygaden 48 A, Sengel\u00f8se Taastrup Danmark 2630",
    "addr:housenumber":"48 a",
    "addr:postcode":"2630",
    "addr:street":"Landsbygaden;Sengelose",
    "iso:country":"DK",
    "sg:address":"Landsbygaden 48 A, Sengel\u00f8se",
    "sg:city":"Taastrup",
    "sg:orig_category":"Zoneterapeuter",
    "sg:phone":"+45 43 52 80 06",
    "sg:postcode":"2630",
    "sg:province":"Danmark",
    "wof:name":"Zone- & Vacuumklinik",
    "wof:placetype":"venue"
},
  "geometry": {"coordinates":[12.3020896912,55.6506767273],"type":"Point"}
}