{
  "type": "Feature",
  "properties": {
    "iso:country":"DK",
    "sg:address":"Bl\u00e5g\u00e5rdsvej 106",
    "sg:city":"Greve",
    "sg:orig_category":"Integrerede institutioner",
    "sg:phone":"+45 43 40 50 02",
    "sg:postcode":"2670",
    "sg:province":"Danmark",
    "wof:name":"Dammen",
    "wof:placetype":"venue"
},
  "geometry": {"coordinates":[12.2941808701,55.5844078064],"type":"Point"}
}