{
  "type": "Feature",
  "properties": {
    "iso:country":"DK",
    "sg:address":"Nybrovej 2",
    "sg:city":"Gentofte",
    "sg:orig_category":"Sengeudstyr",
    "sg:phone":"+45 39 76 33 60",
    "sg:postcode":"2820",
    "sg:province":"Danmark",
    "wof:name":"Jysk Senget\u00f8jslager",
    "wof:placetype":"venue"
},
  "geometry": {"coordinates":[12.51856,55.754379],"type":"Point"}
}