{
  "type": "Feature",
  "properties": {
    "addr:full":"Damvej 116 Sabro Danmark 8471",
    "addr:housenumber":"116",
    "addr:postcode":"8471",
    "addr:street":"Damvej",
    "iso:country":"DK",
    "sg:address":"Damvej 116",
    "sg:city":"Sabro",
    "sg:orig_category":"Trykluft",
    "sg:phone":"+45 70 22 11 99",
    "sg:postcode":"8471",
    "sg:province":"Danmark",
    "sg:website":"www.trykluftcentret.dk",
    "wof:name":"TC\u00c5 Trykluft Centret A/S",
    "wof:placetype":"venue"
},
  "geometry": {"coordinates":[10.0289163589,56.2097740173],"type":"Point"}
}