{
  "type": "Feature",
  "properties": {
    "addr:full":"Farum Bytorv 14 Farum Danmark 3520",
    "addr:housenumber":"14",
    "addr:postcode":"3520",
    "addr:street":"Farum Bytorv",
    "iso:country":"DK",
    "sg:address":"Farum Bytorv 14",
    "sg:city":"Farum",
    "sg:orig_category":"Materialister",
    "sg:phone":"+45 44 95 16 17",
    "sg:postcode":"3520",
    "sg:province":"Danmark",
    "wof:name":"Matas Materialisten",
    "wof:placetype":"venue"
},
  "geometry": {"coordinates":[12.3809757233,55.8150405884],"type":"Point"}
}