{
  "type": "Feature",
  "properties": {
    "addr:full":"Gr\u00f8nnegade 29 Nibe Danmark 9240",
    "addr:housenumber":"29",
    "addr:postcode":"9240",
    "addr:street":"Gronnegade",
    "iso:country":"DK",
    "sg:address":"Gr\u00f8nnegade 29",
    "sg:city":"Nibe",
    "sg:orig_category":"Dommerkontorer",
    "sg:phone":"+45 98 35 11 99",
    "sg:postcode":"9240",
    "sg:province":"Danmark",
    "wof:name":"Dommerkontoret",
    "wof:placetype":"venue"
},
  "geometry": {"coordinates":[9.6351261139,56.9845581055],"type":"Point"}
}