{
  "type": "Feature",
  "properties": {
    "iso:country":"DK",
    "sg:address":"Klitrosevej 4, Thorsminde",
    "sg:city":"Ulfborg",
    "sg:orig_category":"Campingpladser",
    "sg:phone":"+45 97 49 70 56",
    "sg:postcode":"6990",
    "sg:province":"Danmark",
    "sg:website":"www.dk-camp.dk/thorsminde",
    "wof:name":"Thorsminde Camping & Sv\u00f8mmehal",
    "wof:placetype":"venue"
},
  "geometry": {"coordinates":[8.3210029602,56.2727661133],"type":"Point"}
}