{
  "type": "Feature",
  "properties": {
    "addr:full":"Marselis Boulevard 175 \u00c5rhus C Danmark 8000",
    "addr:housenumber":"175",
    "addr:postcode":"8000",
    "addr:street":"Marselis Boulevard",
    "iso:country":"DK",
    "sg:address":"Marselis Boulevard 175",
    "sg:city":"\u00c5rhus C",
    "sg:orig_category":"Elektronik",
    "sg:phone":"+45 86 11 28 88",
    "sg:postcode":"8000",
    "sg:province":"Danmark",
    "sg:website":"www.kelvinhughes.dk",
    "wof:name":"A/S Kelvin Hughes",
    "wof:placetype":"venue"
},
  "geometry": {"coordinates":[-116.27327728269999,32.6635398865],"type":"Point"}
}