{
  "type": "Feature",
  "properties": {
    "addr:full":"Saltv\u00e6rksvej 62 Kastrup Danmark 2770",
    "addr:housenumber":"62",
    "addr:postcode":"2770",
    "addr:street":"Saltvaerksvej",
    "iso:country":"DK",
    "sg:address":"Saltv\u00e6rksvej 62",
    "sg:city":"Kastrup",
    "sg:orig_category":"Servicestationer",
    "sg:phone":"+45 32 51 03 44",
    "sg:postcode":"2770",
    "sg:province":"Danmark",
    "wof:name":"Shell Service",
    "wof:placetype":"venue"
},
  "geometry": {"coordinates":[12.6387443542,55.6381835938],"type":"Point"}
}