{
  "type": "Feature",
  "properties": {
    "iso:country":"DK",
    "sg:address":"Gasv\u00e6rksvej 12",
    "sg:city":"Kongens Lyngby",
    "sg:orig_category":"Begravelsesforretninger",
    "sg:phone":"+45 45 87 12 35",
    "sg:postcode":"2800",
    "sg:province":"Danmark",
    "sg:website":"www.begravelsesfirma.dk",
    "wof:name":"Begravelsesforretning Kgs. Lyngby",
    "wof:placetype":"venue"
},
  "geometry": {"coordinates":[12.503831,55.77177],"type":"Point"}
}