{
  "type": "Feature",
  "properties": {
    "iso:country":"DK",
    "sg:address":"Vestervej 52",
    "sg:city":"Nibe",
    "sg:classifiers":[
        {
            "category":"Building & Trades",
            "subcategory":"Construction",
            "type":"Services"
        }
    ],
    "sg:phone":"+45 96 37 75 75",
    "sg:postcode":"9240",
    "sg:province":"Danmark",
    "sg:tags":[
        "ventilation"
    ],
    "sg:website":"www.ventek-as.dk",
    "wof:name":"Ventek Ventilation A/S",
    "wof:placetype":"venue"
},
  "geometry": {"coordinates":[9.7293968201,57.0048904419],"type":"Point"}
}