{
  "type": "Feature",
  "properties": {
    "addr:full":"F\u00e6lledvej 17 K\u00f8benhavn N Danmark 2200",
    "addr:housenumber":"17",
    "addr:postcode":"2200",
    "addr:street":"Faelledvej;N Danmark",
    "iso:country":"DK",
    "sg:address":"F\u00e6lledvej 17",
    "sg:city":"K\u00f8benhavn N",
    "sg:orig_category":"Ejendomshandel",
    "sg:phone":"+45 35 35 85 00",
    "sg:postcode":"2200",
    "sg:province":"Danmark",
    "wof:name":"Ejendomsfirmaet 2V",
    "wof:placetype":"venue"
},
  "geometry": {"coordinates":[-96.80657196040001,46.9477157593],"type":"Point"}
}