{
  "type": "Feature",
  "properties": {
    "addr:full":"Hovedgade 12, Snogeb\u00e6k Nex\u00f8 Danmark 3730",
    "addr:housenumber":"12",
    "addr:postcode":"3730",
    "addr:street":"Hovedgade",
    "iso:country":"DK",
    "sg:address":"Hovedgade 12, Snogeb\u00e6k",
    "sg:city":"Nex\u00f8",
    "sg:orig_category":"Forsamlingshuse",
    "sg:phone":"+45 56 48 88 72",
    "sg:postcode":"3730",
    "sg:province":"Danmark",
    "wof:name":"Folkets Hus",
    "wof:placetype":"venue"
},
  "geometry": {"coordinates":[15.1096076965,55.0267219543],"type":"Point"}
}