{
  "type": "Feature",
  "properties": {
    "addr:full":"N\u00f8rregade 53 Hundested Danmark 3390",
    "addr:housenumber":"53",
    "addr:postcode":"3390",
    "addr:street":"Norregade",
    "iso:country":"DK",
    "sg:address":"N\u00f8rregade 53",
    "sg:city":"Hundested",
    "sg:orig_category":"Brugsforeninger",
    "sg:phone":"+45 47 93 78 00",
    "sg:postcode":"3390",
    "sg:province":"Danmark",
    "sg:website":"www.fdb.dk",
    "wof:name":"SuperBrugsen",
    "wof:placetype":"venue"
},
  "geometry": {"coordinates":[11.8524122238,55.9604911804],"type":"Point"}
}