{
  "type": "Feature",
  "properties": {
    "addr:full":"Langelinie 159 Odense M Danmark 5230",
    "addr:housenumber":"159",
    "addr:postcode":"5230",
    "addr:street":"Langelinie",
    "iso:country":"DK",
    "sg:address":"Langelinie 159",
    "sg:city":"Odense M",
    "sg:orig_category":"Ejendomshandel",
    "sg:phone":"+45 66 14 64 00",
    "sg:postcode":"5230",
    "sg:province":"Danmark",
    "wof:name":"Thobo-Carlsen & Partnere ApS",
    "wof:placetype":"venue"
},
  "geometry": {"coordinates":[10.3769483566,55.3748321533],"type":"Point"}
}