{
  "type": "Feature",
  "properties": {
    "addr:full":"Stokholmsvej 10 Esperg\u00e6rde Danmark 3060",
    "addr:housenumber":"10",
    "addr:postcode":"3060",
    "addr:street":"Stokholmsvej",
    "iso:country":"DK",
    "sg:address":"Stokholmsvej 10",
    "sg:city":"Esperg\u00e6rde",
    "sg:orig_category":"Kommunale folkeskoler",
    "sg:phone":"+45 49 28 12 14",
    "sg:postcode":"3060",
    "sg:province":"Danmark",
    "wof:name":"Esperg\u00e6rdeskolen",
    "wof:placetype":"venue"
},
  "geometry": {"coordinates":[11.6512403488,47.8390617371],"type":"Point"}
}