{
  "type": "Feature",
  "properties": {
    "addr:full":"v/ Jan Rasmussen, I Bakkerne 16 C, Aarsdale Svaneke Danmark 3740",
    "addr:housenumber":"16 c",
    "addr:postcode":"3740",
    "addr:street":"Bakkerne;Aarsdale",
    "iso:country":"DK",
    "sg:address":"v/ Jan Rasmussen, I Bakkerne 16 C, Aarsdale",
    "sg:city":"Svaneke",
    "sg:orig_category":"Kirkelige foreninger",
    "sg:phone":"+45 56 49 73 53",
    "sg:postcode":"3740",
    "sg:province":"Danmark",
    "wof:name":"Evangelisk Luthersk Missionsforening \u00c5rsdale",
    "wof:placetype":"venue"
},
  "geometry": {"coordinates":[15.140504837,55.1364555359],"type":"Point"}
}