{
  "type": "Feature",
  "properties": {
    "addr:full":"Estrupsgade 12 Silkeborg Danmark 8600",
    "addr:housenumber":"12",
    "addr:postcode":"8600",
    "addr:street":"Estrupsgade",
    "iso:country":"DK",
    "sg:address":"Estrupsgade 12",
    "sg:city":"Silkeborg",
    "sg:orig_category":"Boligselskaber",
    "sg:phone":"+45 87 22 72 72",
    "sg:postcode":"8600",
    "sg:province":"Danmark",
    "sg:website":"www.aab-silkeborg.dk",
    "wof:name":"Arbejdernes Andelsboligforening",
    "wof:placetype":"venue"
},
  "geometry": {"coordinates":[9.5445632935,56.1657447815],"type":"Point"}
}