{
  "type": "Feature",
  "properties": {
    "iso:country":"DK",
    "sg:address":"N\u00f8rregade 9",
    "sg:city":"Stoholm",
    "sg:orig_category":"Selskabslokaler",
    "sg:phone":"+45 97 54 10 26",
    "sg:postcode":"7850",
    "sg:province":"Danmark",
    "wof:name":"Stoholm Selskabslokaler",
    "wof:placetype":"venue"
},
  "geometry": {"coordinates":[9.151196,56.486435],"type":"Point"}
}