{
  "type": "Feature",
  "properties": {
    "addr:full":"Gl. Stationsvej 12, Burs\u00f8 Maribo Danmark 4930",
    "addr:housenumber":"12",
    "addr:postcode":"4930",
    "addr:street":"Gl. Stationsvej",
    "iso:country":"DK",
    "sg:address":"Gl. Stationsvej 12, Burs\u00f8",
    "sg:city":"Maribo",
    "sg:orig_category":"Snedkermestre",
    "sg:phone":"+45 54 75 65 13",
    "sg:postcode":"4930",
    "sg:province":"Danmark",
    "wof:name":"Strate, Bent",
    "wof:placetype":"venue"
},
  "geometry": {"coordinates":[11.502035141,54.7743835449],"type":"Point"}
}