{
  "type": "Feature",
  "properties": {
    "addr:full":"Nygade 12 Silkeborg Danmark 8600",
    "addr:housenumber":"12",
    "addr:postcode":"8600",
    "addr:street":"Nygade",
    "iso:country":"DK",
    "sg:address":"Nygade 12",
    "sg:city":"Silkeborg",
    "sg:orig_category":"Garn",
    "sg:phone":"+45 86 82 57 07",
    "sg:postcode":"8600",
    "sg:province":"Danmark",
    "wof:name":"\u00d8nskegarn",
    "wof:placetype":"venue"
},
  "geometry": {"coordinates":[9.5483446121,56.167640686],"type":"Point"}
}