{
  "type": "Feature",
  "properties": {
    "addr:full":"Slagelse Landevej 3, Hulby Kors\u00f8r Danmark 4220",
    "addr:housenumber":"3",
    "addr:postcode":"4220",
    "addr:street":"Slagelse Landevej",
    "iso:country":"DK",
    "sg:address":"Slagelse Landevej 3, Hulby",
    "sg:city":"Kors\u00f8r",
    "sg:orig_category":"Redningsberedskab",
    "sg:phone":"+45 88 51 97 24",
    "sg:postcode":"4220",
    "sg:province":"Danmark",
    "wof:name":"Beredskabsafdelingen",
    "wof:placetype":"venue"
},
  "geometry": {"coordinates":[11.2105474472,55.3797225952],"type":"Point"}
}