{
  "type": "Feature",
  "properties": {
    "addr:full":"Vestre Strandvej 7 Tj\u00e6reborg Danmark 6731",
    "addr:housenumber":"7",
    "addr:postcode":"6731",
    "addr:street":"Vestre Strandvej",
    "iso:country":"DK",
    "sg:address":"Vestre Strandvej 7",
    "sg:city":"Tj\u00e6reborg",
    "sg:orig_category":"Posthuse",
    "sg:phone":"+45 75 17 62 94",
    "sg:postcode":"6731",
    "sg:province":"Danmark",
    "wof:name":"Post Danmark, Tj\u00e6reborg Postburik",
    "wof:placetype":"venue"
},
  "geometry": {"coordinates":[6.8762898445,62.4602813721],"type":"Point"}
}