{
  "type": "Feature",
  "properties": {
    "addr:full":"\u00d8stervang 51, Mollerup Nyk\u00f8bing Danmark 7900",
    "addr:housenumber":"51",
    "addr:postcode":"7900",
    "addr:street":"Ostervang;Mollerup Nykobing Danmark",
    "iso:country":"DK",
    "sg:address":"\u00d8stervang 51, Mollerup",
    "sg:city":"Nyk\u00f8bing",
    "sg:orig_category":"Korn og foderstoffer",
    "sg:phone":"+45 97 74 43 11",
    "sg:postcode":"7900",
    "sg:province":"Danmark",
    "sg:website":"www.mollerup.dk",
    "wof:name":"Mollerup M\u00f8lle",
    "wof:placetype":"venue"
},
  "geometry": {"coordinates":[-114.0768203735,46.4432411194],"type":"Point"}
}