{
  "type": "Feature",
  "properties": {
    "iso:country":"DK",
    "sg:address":"Gerritsgade 23 A",
    "sg:city":"Svendborg",
    "sg:orig_category":"Bijouterier",
    "sg:phone":"+45 62 21 49 90",
    "sg:postcode":"5700",
    "sg:province":"Danmark",
    "wof:name":"Modesmykker",
    "wof:placetype":"venue"
},
  "geometry": {"coordinates":[10.607754,55.058922],"type":"Point"}
}