{
  "type": "Feature",
  "properties": {
    "addr:full":"Gr\u00e6stedg\u00e5rdsvej 1 Kokkedal Danmark 2980",
    "addr:housenumber":"1",
    "addr:postcode":"2980",
    "addr:street":"Graestedgaardsvej",
    "iso:country":"DK",
    "sg:address":"Gr\u00e6stedg\u00e5rdsvej 1",
    "sg:city":"Kokkedal",
    "sg:orig_category":"Integrerede institutioner",
    "sg:phone":"+45 49 14 71 56",
    "sg:postcode":"2980",
    "sg:province":"Danmark",
    "wof:name":"Gr\u00e6stedg\u00e5rd, Vuggestue",
    "wof:placetype":"venue"
},
  "geometry": {"coordinates":[12.4769096375,55.9091339111],"type":"Point"}
}