{
  "type": "Feature",
  "properties": {
    "addr:full":"Askevej 3, Skuldelev Skibby Danmark 4050",
    "addr:housenumber":"3",
    "addr:postcode":"4050",
    "addr:street":"Askevej",
    "iso:country":"DK",
    "sg:address":"Askevej 3, Skuldelev",
    "sg:city":"Skibby",
    "sg:orig_category":"Alternativ behandling",
    "sg:phone":"+45 47 52 05 38",
    "sg:postcode":"4050",
    "sg:province":"Danmark",
    "wof:name":"Ny Energi",
    "wof:placetype":"venue"
},
  "geometry": {"coordinates":[11.9594116211,55.7502975464],"type":"Point"}
}