{
  "type": "Feature",
  "properties": {
    "iso:country":"DK",
    "sg:address":"Vestergade 25 - 27",
    "sg:city":"K\u00f8ge",
    "sg:orig_category":"Supermarkeder",
    "sg:phone":"+45 56 65 71 00",
    "sg:postcode":"4600",
    "sg:province":"Danmark",
    "wof:name":"Kvickly",
    "wof:placetype":"venue"
},
  "geometry": {"coordinates":[9.5455904007,56.1682090759],"type":"Point"}
}