{
  "type": "Feature",
  "properties": {
    "addr:full":"Sognepr\u00e6st: Mette Trankj\u00e6r (K/B), B\u00f8nnetvej 6, Horbelev Horbelev Danmark 4871",
    "addr:housenumber":"6",
    "addr:postcode":"4871",
    "addr:street":"Bonnetvej",
    "iso:country":"DK",
    "sg:address":"Sognepr\u00e6st: Mette Trankj\u00e6r (K/B), B\u00f8nnetvej 6, Horbelev",
    "sg:city":"Horbelev",
    "sg:orig_category":"Kirkesogne",
    "sg:phone":"+45 54 44 51 24",
    "sg:postcode":"4871",
    "sg:province":"Danmark",
    "wof:name":"Horbelev og Falkerslev sogne",
    "wof:placetype":"venue"
},
  "geometry": {"coordinates":[12.0557804108,54.8232345581],"type":"Point"}
}