{
  "type": "Feature",
  "properties": {
    "iso:country":"DK",
    "sg:address":"Stokkebro 83, Gjerrild",
    "sg:city":"Grenaa",
    "sg:orig_category":"Distriktsbiblioteker",
    "sg:phone":"+45 87 79 61 61",
    "sg:postcode":"8500",
    "sg:province":"Danmark",
    "wof:name":"Gjerrild Bibliotek",
    "wof:placetype":"venue"
},
  "geometry": {"coordinates":[10.8774929047,56.4126853943],"type":"Point"}
}