{
  "type": "Feature",
  "properties": {
    "addr:full":"Brinck Seidelins Gade 2 Hj\u00f8rring Danmark 9800",
    "addr:housenumber":"2",
    "addr:postcode":"9800",
    "addr:street":"Brinck Seidelins Gade",
    "iso:country":"DK",
    "sg:address":"Brinck Seidelins Gade 2",
    "sg:city":"Hj\u00f8rring",
    "sg:orig_category":"Revisorer",
    "sg:phone":"+45 98 90 38 00",
    "sg:postcode":"9800",
    "sg:province":"Danmark",
    "sg:website":"www.revinet.dk",
    "wof:name":"Andersen, Revisionsfirmaet Steen",
    "wof:placetype":"venue"
},
  "geometry": {"coordinates":[99.92501068120001,34.2430114746],"type":"Point"}
}