{
  "type": "Feature",
  "properties": {
    "addr:full":"Fejlereg\u00e5rdsvejen 5 A, Nylars Aakirkeby Danmark 3720",
    "addr:housenumber":"5 a",
    "addr:postcode":"3720",
    "addr:street":"Fejleregaardsvejen;Nylars",
    "iso:country":"DK",
    "sg:address":"Fejlereg\u00e5rdsvejen 5 A, Nylars",
    "sg:city":"Aakirkeby",
    "sg:orig_category":"Autoreparation og -service",
    "sg:phone":"+45 56 97 25 56",
    "sg:postcode":"3720",
    "sg:province":"Danmark",
    "wof:name":"Lobb\u00e6k Auto",
    "wof:placetype":"venue"
},
  "geometry": {"coordinates":[14.9202880859,55.070110321],"type":"Point"}
}