{
  "type": "Feature",
  "properties": {
    "addr:full":"St\u00e6rkendevej 145, Reerslev Hedehusene Danmark 2640",
    "addr:housenumber":"145",
    "addr:postcode":"2640",
    "addr:street":"Staerkendevej;Reerslev",
    "iso:country":"DK",
    "sg:address":"St\u00e6rkendevej 145, Reerslev",
    "sg:city":"Hedehusene",
    "sg:orig_category":"Stutterier",
    "sg:phone":"+45 46 13 93 55",
    "sg:postcode":"2640",
    "sg:province":"Danmark",
    "wof:name":"Nielsen, Mogens",
    "wof:placetype":"venue"
},
  "geometry": {"coordinates":[12.1993551254,55.6496009827],"type":"Point"}
}