{
  "type": "Feature",
  "properties": {
    "addr:full":"Storegade 25 Bjerringbro Danmark 8850",
    "addr:housenumber":"25",
    "addr:postcode":"8850",
    "addr:street":"Storegade",
    "iso:country":"DK",
    "sg:address":"Storegade 25",
    "sg:city":"Bjerringbro",
    "sg:classifiers":[
        {
            "category":"Home & Garden",
            "subcategory":"Home Furnishings",
            "type":"Retail Goods"
        }
    ],
    "sg:phone":"+45 86 68 01 57",
    "sg:postcode":"8850",
    "sg:province":"Danmark",
    "sg:tags":[
        "gardiner"
    ],
    "wof:name":"Bjerringbro Gulvbel\u00e6gning",
    "wof:placetype":"venue"
},
  "geometry": {"coordinates":[9.6548242569,56.374130249],"type":"Point"}
}