{
  "type": "Feature",
  "properties": {
    "addr:full":"Borgergade 10 B, Magleby Klippinge Danmark 4672",
    "addr:housenumber":"10 b",
    "addr:postcode":"4672",
    "addr:street":"Borgergade;Magleby",
    "iso:country":"DK",
    "sg:address":"Borgergade 10 B, Magleby",
    "sg:city":"Klippinge",
    "sg:orig_category":"Zoneterapeuter",
    "sg:phone":"+45 56 57 85 64",
    "sg:postcode":"4672",
    "sg:province":"Danmark",
    "wof:name":"Anita Sol- og Zoneterapicenter",
    "wof:placetype":"venue"
},
  "geometry": {"coordinates":[12.3291807175,55.3516769409],"type":"Point"}
}