{
  "type": "Feature",
  "properties": {
    "addr:full":"Fmd.: Jesper Poulsen, Egerishave 27 Skive Danmark 7800",
    "addr:housenumber":"27",
    "addr:postcode":"7800",
    "addr:street":"Egerishave",
    "iso:country":"DK",
    "sg:address":"Fmd.: Jesper Poulsen, Egerishave 27",
    "sg:city":"Skive",
    "sg:orig_category":"Kulturelle foreninger",
    "sg:phone":"+45 97 52 29 79",
    "sg:postcode":"7800",
    "sg:province":"Danmark",
    "wof:name":"Kristelig Lytter- og Fjernseerforening",
    "wof:placetype":"venue"
},
  "geometry": {"coordinates":[9.0320358276,56.5666427612],"type":"Point"}
}