{
  "type": "Feature",
  "properties": {
    "addr:full":"Skydebanevej 1 Aalborg Danmark 9000",
    "addr:housenumber":"1",
    "addr:postcode":"9000",
    "addr:street":"Skydebanevej",
    "iso:country":"DK",
    "sg:address":"Skydebanevej 1",
    "sg:city":"Aalborg",
    "sg:orig_category":"Tandklinikker, Kommunale",
    "sg:phone":"+45 98 13 59 65",
    "sg:postcode":"9000",
    "sg:province":"Danmark",
    "wof:name":"Tandklinikken ved Vesterk\u00e6ret Skole",
    "wof:placetype":"venue"
},
  "geometry": {"coordinates":[9.8903512955,57.0554084778],"type":"Point"}
}