{
  "type": "Feature",
  "properties": {
    "addr:full":"Branderup Bygade 20 Branderup Danmark 6535",
    "addr:housenumber":"20",
    "addr:postcode":"6535",
    "addr:street":"Branderup Bygade",
    "iso:country":"DK",
    "sg:address":"Branderup Bygade 20",
    "sg:city":"Branderup",
    "sg:orig_category":"Apoteker og -udsalg",
    "sg:phone":"+45 74 83 52 31",
    "sg:postcode":"6535",
    "sg:province":"Danmark",
    "wof:name":"H\u00e5ndk\u00f8bsudsalg fra Toftlund Apotek",
    "wof:placetype":"venue"
},
  "geometry": {"coordinates":[9.0685100555,55.1202011108],"type":"Point"}
}