{
  "type": "Feature",
  "properties": {
    "addr:full":"Bytoften 29 Hvidovre Danmark 2650",
    "addr:housenumber":"29",
    "addr:postcode":"2650",
    "addr:street":"Bytoften",
    "iso:country":"DK",
    "sg:address":"Bytoften 29",
    "sg:city":"Hvidovre",
    "sg:orig_category":"Politi",
    "sg:phone":"+45 36 75 14 48",
    "sg:postcode":"2650",
    "sg:province":"Danmark",
    "wof:name":"Hvidovre Politikreds",
    "wof:placetype":"venue"
},
  "geometry": {"coordinates":[12.4764709473,55.6549949646],"type":"Point"}
}