{
  "type": "Feature",
  "properties": {
    "addr:full":"Holstebrovej 91 Skive Danmark 7800",
    "addr:housenumber":"91",
    "addr:postcode":"7800",
    "addr:street":"Holstebrovej",
    "iso:country":"DK",
    "sg:address":"Holstebrovej 91",
    "sg:city":"Skive",
    "sg:orig_category":"Autoforhandlere",
    "sg:phone":"+45 97 52 23 88",
    "sg:postcode":"7800",
    "sg:province":"Danmark",
    "wof:name":"Bolding Biler A/S VW-Audi",
    "wof:placetype":"venue"
},
  "geometry": {"coordinates":[9.0032167435,56.5684890747],"type":"Point"}
}