{
  "type": "Feature",
  "properties": {
    "addr:full":"M\u00f8llevejen 20, \u00c5leg\u00e5rdsmark Fjerritslev Danmark 9690",
    "addr:housenumber":"20",
    "addr:postcode":"9690",
    "addr:street":"Mollevejen;Aalegaardsmark",
    "iso:country":"DK",
    "sg:address":"M\u00f8llevejen 20, \u00c5leg\u00e5rdsmark",
    "sg:city":"Fjerritslev",
    "sg:orig_category":"Fodplejere",
    "sg:phone":"+45 98 21 16 03",
    "sg:postcode":"9690",
    "sg:province":"Danmark",
    "wof:name":"Fod- & Hudpleje",
    "wof:placetype":"venue"
},
  "geometry": {"coordinates":[9.2667350769,57.0882301331],"type":"Point"}
}