{
  "type": "Feature",
  "properties": {
    "addr:full":"Herredsvej 19 - 23, Kragelund L\u00f8sning Danmark 8723",
    "addr:housenumber":"19 23",
    "addr:postcode":"8723",
    "addr:street":"Herredsvej;Kragelund Losning Danmark",
    "iso:country":"DK",
    "sg:address":"Herredsvej 19 - 23, Kragelund",
    "sg:city":"L\u00f8sning",
    "sg:orig_category":"Maskinfabrikker",
    "sg:phone":"+45 75 89 35 00",
    "sg:postcode":"8723",
    "sg:province":"Danmark",
    "wof:name":"E.L.M Kragelund A/S",
    "wof:placetype":"venue"
},
  "geometry": {"coordinates":[9.7620611191,55.8105201721],"type":"Point"}
}