{
  "type": "Feature",
  "properties": {
    "addr:full":"Forteledet 27 Risskov Danmark 8240",
    "addr:housenumber":"27",
    "addr:postcode":"8240",
    "addr:street":"Forteledet",
    "iso:country":"DK",
    "sg:address":"Forteledet 27",
    "sg:city":"Risskov",
    "sg:orig_category":"Vuggestuer",
    "sg:phone":"+45 86 17 64 35",
    "sg:postcode":"8240",
    "sg:province":"Danmark",
    "wof:name":"Forteleddet, Vuggestue",
    "wof:placetype":"venue"
},
  "geometry": {"coordinates":[10.2368030548,56.1942329407],"type":"Point"}
}