{
  "type": "Feature",
  "properties": {
    "addr:full":"Godth\u00e5bsvej 62 A Frederiksberg Danmark 2000",
    "addr:housenumber":"62 a",
    "addr:postcode":"2000",
    "addr:street":"Godthaabsvej",
    "iso:country":"DK",
    "sg:address":"Godth\u00e5bsvej 62 A",
    "sg:city":"Frederiksberg",
    "sg:orig_category":"Farve og tapet",
    "sg:phone":"+45 38 86 00 31",
    "sg:postcode":"2000",
    "sg:province":"Danmark",
    "sg:website":"www.glodi-farvecenter.dk",
    "wof:name":"Dinesen & Dinesen",
    "wof:placetype":"venue"
},
  "geometry": {"coordinates":[12.5290584564,55.6876754761],"type":"Point"}
}