{
  "type": "Feature",
  "properties": {
    "addr:full":"Bytoften 80  Herning Danmark 7400",
    "addr:housenumber":"80",
    "addr:postcode":"7400",
    "addr:street":"Bytoften",
    "iso:country":"DK",
    "sg:address":"Bytoften 80 ",
    "sg:city":"Herning",
    "sg:classifiers":[
        {
            "category":"Professional",
            "subcategory":"Computer Services",
            "type":"Services"
        }
    ],
    "sg:phone":"+45 97 26 76 77",
    "sg:postcode":"7400",
    "sg:province":"Danmark",
    "sg:tags":[
        "information",
        "technology"
    ],
    "wof:name":"SKOV KONTORSYSTEMER A/S",
    "wof:placetype":"venue"
},
  "geometry": {"coordinates":[8.9234476089,56.1608505249],"type":"Point"}
}