{
  "type": "Feature",
  "properties": {
    "addr:full":"Vesterbrogade 179 Frederiksberg Danmark 1800",
    "addr:housenumber":"179;1800",
    "addr:street":"Vesterbrogade",
    "iso:country":"DK",
    "sg:address":"Vesterbrogade 179",
    "sg:city":"Frederiksberg",
    "sg:orig_category":"Fotohandlere",
    "sg:phone":"+45 33 21 44 76",
    "sg:postcode":"1800",
    "sg:province":"Danmark",
    "wof:name":"Platan Foto",
    "wof:placetype":"venue"
},
  "geometry": {"coordinates":[12.5334939957,55.6705970764],"type":"Point"}
}