{
  "type": "Feature",
  "properties": {
    "iso:country":"DK",
    "sg:address":"K\u00f8benhavnsvej 127",
    "sg:city":"Roskilde",
    "sg:orig_category":"Vinduer",
    "sg:phone":"+45 46 74 19 00",
    "sg:postcode":"4000",
    "sg:province":"Danmark",
    "wof:name":"Vinduescentret",
    "wof:placetype":"venue"
},
  "geometry": {"coordinates":[12.1159210205,55.642665863],"type":"Point"}
}