{
  "type": "Feature",
  "properties": {
    "addr:full":"Numitvej 25 Hvide Sande Danmark 6960",
    "addr:housenumber":"25",
    "addr:postcode":"6960",
    "addr:street":"Numitvej",
    "iso:country":"DK",
    "sg:address":"Numitvej 25",
    "sg:city":"Hvide Sande",
    "sg:orig_category":"Varmeforsyning",
    "sg:phone":"+45 97 31 16 61",
    "sg:postcode":"6960",
    "sg:province":"Danmark",
    "wof:name":"Hvide Sande Fjernvarme a.m.b.a.",
    "wof:placetype":"venue"
},
  "geometry": {"coordinates":[8.1242656708,56.0070610046],"type":"Point"}
}