{
  "type": "Feature",
  "properties": {
    "addr:full":"\u00d8stergade 55 K\u00f8benhavn Danmark 1100",
    "addr:housenumber":"55;1100",
    "addr:street":"Ostergade",
    "iso:country":"DK",
    "sg:address":"\u00d8stergade 55",
    "sg:city":"K\u00f8benhavn",
    "sg:orig_category":"Advokater",
    "sg:phone":"+45 33 13 15 11",
    "sg:postcode":"1100",
    "sg:province":"Danmark",
    "sg:website":"www.denlaw.dk",
    "wof:name":"Advokaterne \u00d8stergade 55",
    "wof:placetype":"venue"
},
  "geometry": {"coordinates":[76.3070983887,14.277130127],"type":"Point"}
}