{
  "type": "Feature",
  "properties": {
    "addr:full":"\u00c5bogade 36 \u00c5rhus N Danmark 8200",
    "addr:housenumber":"36",
    "addr:postcode":"8200",
    "addr:street":"Aabogade",
    "iso:country":"DK",
    "sg:address":"\u00c5bogade 36",
    "sg:city":"\u00c5rhus N",
    "sg:orig_category":"Murermestre",
    "sg:phone":"+45 86 10 01 11",
    "sg:postcode":"8200",
    "sg:province":"Danmark",
    "wof:name":"Falck/Eskildsen ApS",
    "wof:placetype":"venue"
},
  "geometry": {"coordinates":[4.9393601418,49.7092018127],"type":"Point"}
}