{
  "type": "Feature",
  "properties": {
    "addr:full":"P\u00e6onvej 53 K\u00f8benhavn S Danmark 2300",
    "addr:housenumber":"53",
    "addr:postcode":"2300",
    "addr:street":"Paeonvej;S Danmark",
    "iso:country":"DK",
    "sg:address":"P\u00e6onvej 53",
    "sg:city":"K\u00f8benhavn S",
    "sg:orig_category":"Liftudlejning",
    "sg:phone":"+45 33 12 44 18",
    "sg:postcode":"2300",
    "sg:province":"Danmark",
    "wof:name":"F.A. Liftudlejning",
    "wof:placetype":"venue"
},
  "geometry": {"coordinates":[-78.1299133301,36.7267417908],"type":"Point"}
}