{
  "type": "Feature",
  "properties": {
    "addr:full":"Henv.: Elise J\u00f8rgensen, Bym\u00f8llevej 54, K\u00f8belev Nakskov Danmark 4900",
    "addr:housenumber":"54",
    "addr:postcode":"4900",
    "addr:street":"Henv.;Bymollevej",
    "iso:country":"DK",
    "sg:address":"Henv.: Elise J\u00f8rgensen, Bym\u00f8llevej 54, K\u00f8belev",
    "sg:city":"Nakskov",
    "sg:orig_category":"Trossamfund uden for folkekirken",
    "sg:phone":"+45 54 93 24 46",
    "sg:postcode":"4900",
    "sg:province":"Danmark",
    "wof:name":"Baptistkirken",
    "wof:placetype":"venue"
},
  "geometry": {"coordinates":[11.1359500885,54.8330116272],"type":"Point"}
}