{
  "type": "Feature",
  "properties": {
    "addr:full":"Frilandsvej 10, Lind Herning Danmark 7400",
    "addr:housenumber":"10",
    "addr:postcode":"7400",
    "addr:street":"Frilandsvej",
    "iso:country":"DK",
    "sg:address":"Frilandsvej 10, Lind",
    "sg:city":"Herning",
    "sg:orig_category":"Fotografer",
    "sg:phone":"+45 97 12 34 07",
    "sg:postcode":"7400",
    "sg:province":"Danmark",
    "wof:name":"Haugsted, Ole",
    "wof:placetype":"venue"
},
  "geometry": {"coordinates":[8.9768896103,56.1374168396],"type":"Point"}
}