{
  "type": "Feature",
  "properties": {
    "addr:full":"Strandvejen 808 Klampenborg Danmark 2930",
    "addr:housenumber":"808",
    "addr:postcode":"2930",
    "addr:street":"Strandvejen",
    "iso:country":"DK",
    "sg:address":"Strandvejen 808",
    "sg:city":"Klampenborg",
    "sg:classifiers":[
        {
            "category":"Restaurant",
            "type":"Food & Drink"
        }
    ],
    "sg:phone":"+45 39 63 01 04",
    "sg:postcode":"2930",
    "sg:province":"Danmark",
    "wof:name":"Strandm\u00f8llekroen",
    "wof:placetype":"venue"
},
  "geometry": {"coordinates":[12.5839195251,55.8053321838],"type":"Point"}
}