{
  "type": "Feature",
  "properties": {
    "addr:full":"Torvegade 30 Brande Danmark 7330",
    "addr:housenumber":"30",
    "addr:postcode":"7330",
    "addr:street":"Torvegade",
    "iso:country":"DK",
    "sg:address":"Torvegade 30",
    "sg:city":"Brande",
    "sg:orig_category":"Bogtrykkerier",
    "sg:phone":"+45 97 18 04 55",
    "sg:postcode":"7330",
    "sg:province":"Danmark",
    "wof:name":"Brande Off-Set & Reklamecenter",
    "wof:placetype":"venue"
},
  "geometry": {"coordinates":[9.1313114166,55.9427261353],"type":"Point"}
}