{
  "type": "Feature",
  "properties": {
    "addr:full":"F\u00e5borgvej 40 Vester Skerninge Danmark 5762",
    "addr:housenumber":"40",
    "addr:postcode":"5762",
    "addr:street":"Faaborgvej",
    "iso:country":"DK",
    "sg:address":"F\u00e5borgvej 40",
    "sg:city":"Vester Skerninge",
    "sg:classifiers":[
        {
            "category":"Banks & Credit Unions",
            "subcategory":"Bank",
            "type":"Services"
        }
    ],
    "sg:phone":"+45 63 24 51 00",
    "sg:postcode":"5762",
    "sg:province":"Danmark",
    "sg:tags":[
        "banker"
    ],
    "wof:name":"BG Bank",
    "wof:placetype":"venue"
},
  "geometry": {"coordinates":[10.4542989731,55.0742225647],"type":"Point"}
}