{
  "type": "Feature",
  "properties": {
    "addr:full":"Klubhuset, Havnen 32 Thisted Danmark 7700",
    "addr:housenumber":"32",
    "addr:postcode":"7700",
    "addr:street":"Havnen",
    "iso:country":"DK",
    "sg:address":"Klubhuset, Havnen 32",
    "sg:city":"Thisted",
    "sg:orig_category":"Havne",
    "sg:phone":"+45 97 92 16 87",
    "sg:postcode":"7700",
    "sg:province":"Danmark",
    "wof:name":"Thisted Lystb\u00e5dehavn",
    "wof:placetype":"venue"
},
  "geometry": {"coordinates":[8.6919784546,56.9556121826],"type":"Point"}
}