{
  "type": "Feature",
  "properties": {
    "iso:country":"DK",
    "sg:address":"Skautrupvej 32B, Tvis",
    "sg:city":"Holstebro",
    "sg:orig_category":"Korn og foderstoffer",
    "sg:phone":"+45 96 13 56 00",
    "sg:postcode":"7500",
    "sg:province":"Danmark",
    "wof:name":"\u00d8A Vestjylland",
    "wof:placetype":"venue"
},
  "geometry": {"coordinates":[8.6202583313,56.3625221252],"type":"Point"}
}