{
  "type": "Feature",
  "properties": {
    "addr:full":"Porsager 110 Albertslund Danmark 2620",
    "addr:housenumber":"110",
    "addr:postcode":"2620",
    "addr:street":"Porsager",
    "iso:country":"DK",
    "sg:address":"Porsager 110",
    "sg:city":"Albertslund",
    "sg:orig_category":"Arkitekter",
    "sg:phone":"+45 43 64 65 66",
    "sg:postcode":"2620",
    "sg:province":"Danmark",
    "wof:name":"Friis, S\u00f8ren",
    "wof:placetype":"venue"
},
  "geometry": {"coordinates":[12.3319072723,55.6666526794],"type":"Point"}
}