{
  "type": "Feature",
  "properties": {
    "addr:full":"Magleh\u00f8jen 19 Roskilde Danmark 4000",
    "addr:housenumber":"19",
    "addr:postcode":"4000",
    "addr:street":"Maglehojen",
    "iso:country":"DK",
    "sg:address":"Magleh\u00f8jen 19",
    "sg:city":"Roskilde",
    "sg:orig_category":"\u00c3\u02dcvrig fritidsundervisning",
    "sg:phone":"+45 46 37 11 12",
    "sg:postcode":"4000",
    "sg:province":"Danmark",
    "wof:name":"F.O.K., Familielandbrugets Oplysnings- og Kursusvirksomhed",
    "wof:placetype":"venue"
},
  "geometry": {"coordinates":[12.0768251419,55.6301460266],"type":"Point"}
}