{
  "type": "Feature",
  "properties": {
    "addr:full":"KFUM-Hallen, Under Lien 77 Aalborg Danmark 9000",
    "addr:housenumber":"77",
    "addr:postcode":"9000",
    "addr:street":"Under Lien",
    "iso:country":"DK",
    "sg:address":"KFUM-Hallen, Under Lien 77",
    "sg:city":"Aalborg",
    "sg:orig_category":"Legestuer",
    "sg:phone":"+45 99 31 52 90",
    "sg:postcode":"9000",
    "sg:province":"Danmark",
    "wof:name":"Legestuen i Hasseris",
    "wof:placetype":"venue"
},
  "geometry": {"coordinates":[9.86714077,57.0356826782],"type":"Point"}
}