{
  "type": "Feature",
  "properties": {
    "addr:full":"T\u00f8vlingvej 33 Snedsted Danmark 7752",
    "addr:housenumber":"33",
    "addr:postcode":"7752",
    "addr:street":"Tovlingvej",
    "iso:country":"DK",
    "sg:address":"T\u00f8vlingvej 33",
    "sg:city":"Snedsted",
    "sg:orig_category":"Bogtrykkerier",
    "sg:phone":"+45 97 93 40 69",
    "sg:postcode":"7752",
    "sg:province":"Danmark",
    "wof:name":"Nordjysk Tryk",
    "wof:placetype":"venue"
},
  "geometry": {"coordinates":[8.5193843842,56.8790740967],"type":"Point"}
}