{
  "type": "Feature",
  "properties": {
    "addr:full":"Hans Jensens Alle 3 Hirtshals Danmark 9850",
    "addr:housenumber":"3",
    "addr:postcode":"9850",
    "addr:street":"Hans Jensens Alle",
    "iso:country":"DK",
    "sg:address":"Hans Jensens Alle 3",
    "sg:city":"Hirtshals",
    "sg:orig_category":"Revisorer",
    "sg:phone":"+45 98 94 55 54",
    "sg:postcode":"9850",
    "sg:province":"Danmark",
    "wof:name":"St\u00f8rup, Kaj",
    "wof:placetype":"venue"
},
  "geometry": {"coordinates":[9.957406044,57.5878181458],"type":"Point"}
}