{
  "type": "Feature",
  "properties": {
    "addr:full":"Hasserisvej 143 Aalborg Danmark 9000",
    "addr:housenumber":"143",
    "addr:postcode":"9000",
    "addr:street":"Hasserisvej",
    "iso:country":"DK",
    "sg:address":"Hasserisvej 143",
    "sg:city":"Aalborg",
    "sg:orig_category":"Ejendomshandel",
    "sg:phone":"+45 96 31 60 00",
    "sg:postcode":"9000",
    "sg:province":"Danmark",
    "wof:name":"Kristensen, Ejendomsm\u00e6glerfirmaet Thorkild",
    "wof:placetype":"venue"
},
  "geometry": {"coordinates":[9.8896551132,57.0417938232],"type":"Point"}
}