{
  "type": "Feature",
  "properties": {
    "addr:full":"Blindebomsvej 7 Middelfart Danmark 5500",
    "addr:housenumber":"7",
    "addr:postcode":"5500",
    "addr:street":"Blindebomsvej",
    "iso:country":"DK",
    "sg:address":"Blindebomsvej 7",
    "sg:city":"Middelfart",
    "sg:orig_category":"Malermestre",
    "sg:phone":"+45 64 41 48 84",
    "sg:postcode":"5500",
    "sg:province":"Danmark",
    "wof:name":"Rasmussen, Dennis Anders",
    "wof:placetype":"venue"
},
  "geometry": {"coordinates":[9.7303524017,55.5037384033],"type":"Point"}
}