{
  "type": "Feature",
  "properties": {
    "iso:country":"DK",
    "sg:address":"Rub\u00e6k 1, Skovbyballe",
    "sg:city":"Sydals",
    "sg:orig_category":"Sommerhustilsyn",
    "sg:phone":"+45 74 40 48 49",
    "sg:postcode":"6470",
    "sg:province":"Danmark",
    "wof:name":"Als Sommerhusservice",
    "wof:placetype":"venue"
},
  "geometry": {"coordinates":[9.8924627304,54.9105377197],"type":"Point"}
}