{
  "type": "Feature",
  "properties": {
    "addr:full":"Egemosevej 22, Jystrup Jystrup Danmark 4174",
    "addr:housenumber":"22",
    "addr:postcode":"4174",
    "addr:street":"Egemosevej;Jystrup Jystrup Danmark",
    "iso:country":"DK",
    "sg:address":"Egemosevej 22, Jystrup",
    "sg:city":"Jystrup",
    "sg:orig_category":"Zoneterapeuter",
    "sg:phone":"+45 57 52 86 27",
    "sg:postcode":"4174",
    "sg:province":"Danmark",
    "wof:name":"Rasmussen, Pernille Probst",
    "wof:placetype":"venue"
},
  "geometry": {"coordinates":[11.8870201111,55.5071754456],"type":"Point"}
}