{
  "type": "Feature",
  "properties": {
    "addr:full":"Fmd.: Lis Oudrup Nielsen, Jernbanegade 16 Gr\u00e5sten Danmark 6300",
    "addr:housenumber":"16",
    "addr:postcode":"6300",
    "addr:street":"Fmd. Lis;Jernbanegade",
    "iso:country":"DK",
    "sg:address":"Fmd.: Lis Oudrup Nielsen, Jernbanegade 16",
    "sg:city":"Gr\u00e5sten",
    "sg:orig_category":"Spejderkorps",
    "sg:phone":"+45 74 65 01 00",
    "sg:postcode":"6300",
    "sg:province":"Danmark",
    "wof:name":"Sct. Georgs Gildet, S\u00f8nderjyllands Distrikt",
    "wof:placetype":"venue"
},
  "geometry": {"coordinates":[9.5919456482,54.9212341309],"type":"Point"}
}