{
  "type": "Feature",
  "properties": {
    "addr:full":"Kirkegade Broager Danmark 6310",
    "addr:postcode":"6310",
    "addr:street":"Kirkegade",
    "iso:country":"DK",
    "sg:address":"Kirkegade",
    "sg:city":"Broager",
    "sg:orig_category":"Kirker",
    "sg:postcode":"6310",
    "sg:province":"Danmark",
    "wof:name":"Broager Kirke",
    "wof:placetype":"venue"
},
  "geometry": {"coordinates":[9.6750488281,54.8918151855],"type":"Point"}
}