{
  "type": "Feature",
  "properties": {
    "addr:full":"\u00c5benr\u00e5vej 195, Uge Tinglev Danmark 6360",
    "addr:housenumber":"195",
    "addr:postcode":"6360",
    "addr:street":"Aabenraavej;Uge",
    "iso:country":"DK",
    "sg:address":"\u00c5benr\u00e5vej 195, Uge",
    "sg:city":"Tinglev",
    "sg:orig_category":"Gartnerier",
    "sg:phone":"+45 74 64 61 11",
    "sg:postcode":"6360",
    "sg:province":"Danmark",
    "wof:name":"Tinglev Gartneri & Plantecenter",
    "wof:placetype":"venue"
},
  "geometry": {"coordinates":[9.2476491928,54.9349365234],"type":"Point"}
}