{
  "type": "Feature",
  "properties": {
    "addr:full":"Olievej 12 Struer Danmark 7600",
    "addr:housenumber":"12",
    "addr:postcode":"7600",
    "addr:street":"Olievej",
    "iso:country":"DK",
    "sg:address":"Olievej 12",
    "sg:city":"Struer",
    "sg:orig_category":"Non-Classified Establishments",
    "sg:phone":"+45 97 85 15 88",
    "sg:postcode":"7600",
    "sg:province":"Danmark",
    "wof:name":"OK Nordvestjylland",
    "wof:placetype":"venue"
},
  "geometry": {"coordinates":[8.603644371,56.4948654175],"type":"Point"}
}