{
  "type": "Feature",
  "properties": {
    "iso:country":"DK",
    "sg:address":"v/ Henrik H\u00f8gstrup, M\u00f8rbjergparken 41, Vindinge",
    "sg:city":"Roskilde",
    "sg:orig_category":"Grundejerforeninger",
    "sg:phone":"+45 46 36 02 39",
    "sg:postcode":"4000",
    "sg:province":"Danmark",
    "wof:name":"Grundejerforeningen M\u00f8rbjergg\u00e5rd",
    "wof:placetype":"venue"
},
  "geometry": {"coordinates":[12.0909376144,55.6404838562],"type":"Point"}
}