{
  "type": "Feature",
  "properties": {
    "addr:full":"Vester Alle 15 \u00c5rhus C Danmark 8000",
    "addr:housenumber":"15",
    "addr:postcode":"8000",
    "addr:street":"Vester Alle",
    "iso:country":"DK",
    "sg:address":"Vester Alle 15",
    "sg:city":"\u00c5rhus C",
    "sg:orig_category":"\u00c3\u02dcvrig fritidsundervisning",
    "sg:phone":"+45 86 12 54 75",
    "sg:postcode":"8000",
    "sg:province":"Danmark",
    "sg:website":"www.aarhusbilledskole.dk",
    "wof:name":"Billedskole, \u00c5rhus",
    "wof:placetype":"venue"
},
  "geometry": {"coordinates":[-85.2299499512,37.1363105774],"type":"Point"}
}