{
  "type": "Feature",
  "properties": {
    "addr:full":"Sognevej 95, Himmelev Roskilde Danmark 4000",
    "addr:housenumber":"95",
    "addr:postcode":"4000",
    "addr:street":"Sognevej;Himmelev",
    "iso:country":"DK",
    "sg:address":"Sognevej 95, Himmelev",
    "sg:city":"Roskilde",
    "sg:orig_category":"Pizzeriaer",
    "sg:phone":"+45 46 36 62 71",
    "sg:postcode":"4000",
    "sg:province":"Danmark",
    "wof:name":"Magosa Pizzabar",
    "wof:placetype":"venue"
},
  "geometry": {"coordinates":[12.0909376144,55.6404838562],"type":"Point"}
}