{
  "type": "Feature",
  "properties": {
    "iso:country":"DK",
    "sg:address":"Gothersgade 35",
    "sg:city":"Fredericia",
    "sg:orig_category":"Ejendomshandel",
    "sg:phone":"+45 75 92 55 44",
    "sg:postcode":"7000",
    "sg:province":"Danmark",
    "wof:name":"BT Boligcenter",
    "wof:placetype":"venue"
},
  "geometry": {"coordinates":[9.7567863464,55.5646934509],"type":"Point"}
}