{
  "type": "Feature",
  "properties": {
    "addr:full":"Kokmose 7 Kolding Danmark 6000",
    "addr:housenumber":"7",
    "addr:postcode":"6000",
    "addr:street":"Kokmose",
    "iso:country":"DK",
    "sg:address":"Kokmose 7",
    "sg:city":"Kolding",
    "sg:orig_category":"Autoforhandlere",
    "sg:phone":"+45 75 51 72 00",
    "sg:postcode":"6000",
    "sg:province":"Danmark",
    "wof:name":"Bus Center Vest A/S",
    "wof:placetype":"venue"
},
  "geometry": {"coordinates":[9.4733953476,55.4863586426],"type":"Point"}
}