{
  "type": "Feature",
  "properties": {
    "addr:full":"Industrivej 31, Nr. Broby Broby Danmark 5672",
    "addr:housenumber":"31",
    "addr:postcode":"5672",
    "addr:street":"Industrivej",
    "iso:country":"DK",
    "sg:address":"Industrivej 31, Nr. Broby",
    "sg:city":"Broby",
    "sg:orig_category":"Maskinfabrikker",
    "sg:phone":"+45 62 63 18 63",
    "sg:postcode":"5672",
    "sg:province":"Danmark",
    "wof:name":"Inventech",
    "wof:placetype":"venue"
},
  "geometry": {"coordinates":[10.3131303787,55.2695846558],"type":"Point"}
}