{
  "type": "Feature",
  "properties": {
    "addr:full":"Benl\u00f8separken 163, 1. tv., Benl\u00f8se Ringsted Danmark 4100",
    "addr:housenumber":"163 1 tv.",
    "addr:postcode":"4100",
    "addr:street":"Benloseparken;Benlose",
    "iso:country":"DK",
    "sg:address":"Benl\u00f8separken 163, 1. tv., Benl\u00f8se",
    "sg:city":"Ringsted",
    "sg:orig_category":"Revisorer",
    "sg:phone":"+45 57 61 17 48",
    "sg:postcode":"4100",
    "sg:province":"Danmark",
    "wof:name":"U. F. Carlsen, Revisionsfirmaet",
    "wof:placetype":"venue"
},
  "geometry": {"coordinates":[11.7875862122,55.4458961487],"type":"Point"}
}