{
  "type": "Feature",
  "properties": {
    "addr:full":"Egevej 3, Tune Roskilde Danmark 4000",
    "addr:housenumber":"3",
    "addr:postcode":"4000",
    "addr:street":"Egevej",
    "iso:country":"DK",
    "sg:address":"Egevej 3, Tune",
    "sg:city":"Roskilde",
    "sg:orig_category":"Kommunikation",
    "sg:phone":"+45 23 84 80 83",
    "sg:postcode":"4000",
    "sg:province":"Danmark",
    "wof:name":"Danish Business Communication",
    "wof:placetype":"venue"
},
  "geometry": {"coordinates":[12.0909376144,55.6404838562],"type":"Point"}
}