{
  "type": "Feature",
  "properties": {
    "iso:country":"DK",
    "sg:address":"Ny Vestergade 21,2",
    "sg:city":"Odense C",
    "sg:orig_category":"Videobutikker og -klubber",
    "sg:phone":"+45 65 91 11 21",
    "sg:postcode":"5000",
    "sg:province":"Danmark",
    "wof:name":"Bergstr\u00f8m Video Trading ApS",
    "wof:placetype":"venue"
},
  "geometry": {"coordinates":[10.3808603287,55.3927116394],"type":"Point"}
}