{
  "type": "Feature",
  "properties": {
    "addr:full":"Torvegade 11 Hals Danmark 9370",
    "addr:housenumber":"11",
    "addr:postcode":"9370",
    "addr:street":"Torvegade",
    "iso:country":"DK",
    "sg:address":"Torvegade 11",
    "sg:city":"Hals",
    "sg:orig_category":"Slagter og viktualie",
    "sg:phone":"+45 98 25 10 30",
    "sg:postcode":"9370",
    "sg:province":"Danmark",
    "wof:name":"Hals R\u00f8geri",
    "wof:placetype":"venue"
},
  "geometry": {"coordinates":[10.3069267273,56.9956703186],"type":"Point"}
}