{
  "type": "Feature",
  "properties": {
    "addr:full":"Prinsessegade 43 Fredericia Danmark 7000",
    "addr:housenumber":"43",
    "addr:postcode":"7000",
    "addr:street":"Prinsessegade",
    "iso:country":"DK",
    "sg:address":"Prinsessegade 43",
    "sg:city":"Fredericia",
    "sg:orig_category":"Lingeri",
    "sg:phone":"+45 75 92 35 32",
    "sg:postcode":"7000",
    "sg:province":"Danmark",
    "wof:name":"BH Magasinet",
    "wof:placetype":"venue"
},
  "geometry": {"coordinates":[9.7578105927,55.5658607483],"type":"Point"}
}