{
  "type": "Feature",
  "properties": {
    "addr:full":"Ewaldsvej 15 Silkeborg Danmark 8600",
    "addr:housenumber":"15",
    "addr:postcode":"8600",
    "addr:street":"Ewaldsvej",
    "iso:country":"DK",
    "sg:address":"Ewaldsvej 15",
    "sg:city":"Silkeborg",
    "sg:orig_category":"Kommunale folkeskoler",
    "sg:phone":"+45 87 20 63 60",
    "sg:postcode":"8600",
    "sg:province":"Danmark",
    "sg:website":"www.vestre.skole.silkeborg.dk",
    "wof:name":"Vestre Skole",
    "wof:placetype":"venue"
},
  "geometry": {"coordinates":[9.5358161926,56.1624336243],"type":"Point"}
}