{
  "type": "Feature",
  "properties": {
    "iso:country":"DK",
    "sg:address":"Sandbakken 1-3, Ganl\u00f8se",
    "sg:city":"Stenl\u00f8se",
    "sg:orig_category":"Hospital, udstyr til",
    "sg:phone":"+45 48 18 12 74",
    "sg:postcode":"3660",
    "sg:province":"Danmark",
    "sg:website":"www.dansu.com",
    "wof:name":"Dansu Trade Development A/S",
    "wof:placetype":"venue"
},
  "geometry": {"coordinates":[8.5934295654,59.878528595],"type":"Point"}
}