{
  "type": "Feature",
  "properties": {
    "addr:full":"Estrupvej 17, S\u00f8by Hornslet Danmark 8543",
    "addr:housenumber":"17",
    "addr:postcode":"8543",
    "addr:street":"Estrupvej;Soby",
    "iso:country":"DK",
    "sg:address":"Estrupvej 17, S\u00f8by",
    "sg:city":"Hornslet",
    "sg:orig_category":"Autoophug",
    "sg:phone":"+45 86 97 43 44",
    "sg:postcode":"8543",
    "sg:province":"Danmark",
    "sg:website":"www.pn-autoophug.dk",
    "wof:name":"P.N. Autoophug & -Import",
    "wof:placetype":"venue"
},
  "geometry": {"coordinates":[10.3180999756,56.3159866333],"type":"Point"}
}