{
  "type": "Feature",
  "properties": {
    "addr:full":"Valdemarstorvet 1 Vordingborg Danmark 4760",
    "addr:housenumber":"1",
    "addr:postcode":"4760",
    "addr:street":"Valdemarstorvet",
    "iso:country":"DK",
    "sg:address":"Valdemarstorvet 1",
    "sg:city":"Vordingborg",
    "sg:orig_category":"Forlag",
    "sg:phone":"+45 55 37 44 34",
    "sg:postcode":"4760",
    "sg:province":"Danmark",
    "wof:name":"Krydsordsforlaget",
    "wof:placetype":"venue"
},
  "geometry": {"coordinates":[11.9072523117,55.0108528137],"type":"Point"}
}