{
  "type": "Feature",
  "properties": {
    "iso:country":"DK",
    "sg:address":"Nannasgade 20",
    "sg:city":"K\u00f8benhavn N",
    "sg:classifiers":[
        {
            "category":"Communications",
            "type":"Services"
        }
    ],
    "sg:phone":"+45 35 82 75 76",
    "sg:postcode":"2200",
    "sg:province":"Danmark",
    "sg:tags":[
        "radio-",
        "og",
        "tv-stationer"
    ],
    "wof:name":"Radio Lotus Foreningen",
    "wof:placetype":"venue"
},
  "geometry": {"coordinates":[-94.49351501460001,47.8772392273],"type":"Point"}
}