{
  "type": "Feature",
  "properties": {
    "iso:country":"DK",
    "sg:address":"Fmd.: Ole Rasmussen, Lunde Bygade 137, \u00d8ster Lunde",
    "sg:city":"Otterup",
    "sg:orig_category":"Turistforeninger",
    "sg:phone":"+45 65 95 55 11",
    "sg:postcode":"5450",
    "sg:province":"Danmark",
    "wof:name":"Otterup Turistforening",
    "wof:placetype":"venue"
},
  "geometry": {"coordinates":[10.4545049667,55.5641746521],"type":"Point"}
}