{
  "type": "Feature",
  "properties": {
    "addr:full":"Tranevej 1 Struer Danmark 7600",
    "addr:housenumber":"1",
    "addr:postcode":"7600",
    "addr:street":"Tranevej",
    "iso:country":"DK",
    "sg:address":"Tranevej 1",
    "sg:city":"Struer",
    "sg:orig_category":"Autoudlejning",
    "sg:phone":"+45 97 84 01 56",
    "sg:postcode":"7600",
    "sg:province":"Danmark",
    "wof:name":"HL Biludlejning",
    "wof:placetype":"venue"
},
  "geometry": {"coordinates":[8.583483696,56.5094566345],"type":"Point"}
}