{
  "type": "Feature",
  "properties": {
    "addr:full":"Fmd.: Kjeld Espersen, Arendalsv\u00e6nget 2, Bullerup Agedrup Danmark 5320",
    "addr:housenumber":"2",
    "addr:postcode":"5320",
    "addr:street":"Arendalsvaenget;Bullerup",
    "iso:country":"DK",
    "sg:address":"Fmd.: Kjeld Espersen, Arendalsv\u00e6nget 2, Bullerup",
    "sg:city":"Agedrup",
    "sg:orig_category":"Soldaterforeninger",
    "sg:phone":"+45 66 10 93 52",
    "sg:postcode":"5320",
    "sg:province":"Danmark",
    "wof:name":"Luftv\u00e6rns Artilleri Foreningen",
    "wof:placetype":"venue"
},
  "geometry": {"coordinates":[10.4700860977,55.4257240295],"type":"Point"}
}