{
  "type": "Feature",
  "properties": {
    "addr:full":"Algade 19 Roskilde Danmark 4000",
    "addr:housenumber":"19",
    "addr:postcode":"4000",
    "addr:street":"Algade",
    "iso:country":"DK",
    "sg:address":"Algade 19",
    "sg:city":"Roskilde",
    "sg:orig_category":"Rejsebureauer",
    "sg:phone":"+45 46 35 33 66",
    "sg:postcode":"4000",
    "sg:province":"Danmark",
    "wof:name":"ComTravel Roskilde",
    "wof:placetype":"venue"
},
  "geometry": {"coordinates":[12.0845508575,55.6411437988],"type":"Point"}
}