{
  "type": "Feature",
  "properties": {
    "addr:full":"Gimsinglundvej 10 Struer Danmark 7600",
    "addr:housenumber":"10",
    "addr:postcode":"7600",
    "addr:street":"Gimsinglundvej",
    "iso:country":"DK",
    "sg:address":"Gimsinglundvej 10",
    "sg:city":"Struer",
    "sg:classifiers":[
        {
            "category":"Home & Garden",
            "subcategory":"Home Furnishings",
            "type":"Retail Goods"
        }
    ],
    "sg:phone":"+45 97 85 29 50",
    "sg:postcode":"7600",
    "sg:province":"Danmark",
    "sg:tags":[
        "gardiner"
    ],
    "wof:name":"Olesen Gardiner",
    "wof:placetype":"venue"
},
  "geometry": {"coordinates":[8.5867834091,56.4761314392],"type":"Point"}
}