{
  "type": "Feature",
  "properties": {
    "addr:full":"Nygade 43 Silkeborg Danmark 8600",
    "addr:housenumber":"43",
    "addr:postcode":"8600",
    "addr:street":"Nygade",
    "iso:country":"DK",
    "sg:address":"Nygade 43",
    "sg:city":"Silkeborg",
    "sg:classifiers":[
        {
            "category":"Restaurant",
            "type":"Food & Drink"
        }
    ],
    "sg:phone":"+45 86 81 70 55",
    "sg:postcode":"8600",
    "sg:province":"Danmark",
    "wof:name":"Pakhuset",
    "wof:placetype":"venue"
},
  "geometry": {"coordinates":[9.5457248688,56.1667175293],"type":"Point"}
}