{
  "type": "Feature",
  "properties": {
    "addr:full":"Rudbjergvej 12 Dannemare Danmark 4983",
    "addr:housenumber":"12",
    "addr:postcode":"4983",
    "addr:street":"Rudbjergvej",
    "iso:country":"DK",
    "sg:address":"Rudbjergvej 12",
    "sg:city":"Dannemare",
    "sg:orig_category":"Autoopretning",
    "sg:phone":"+45 54 94 43 53",
    "sg:postcode":"4983",
    "sg:province":"Danmark",
    "wof:name":"Majb\u00f8lle Autoopretning",
    "wof:placetype":"venue"
},
  "geometry": {"coordinates":[11.1370763779,54.7600059509],"type":"Point"}
}