{
  "type": "Feature",
  "properties": {
    "addr:full":"Fuglev\u00e6nget 4, Klejtrup Hobro Danmark 9500",
    "addr:housenumber":"4",
    "addr:postcode":"9500",
    "addr:street":"Fuglevaenget",
    "iso:country":"DK",
    "sg:address":"Fuglev\u00e6nget 4, Klejtrup",
    "sg:city":"Hobro",
    "sg:orig_category":"Fodplejere",
    "sg:phone":"+45 98 54 65 43",
    "sg:postcode":"9500",
    "sg:province":"Danmark",
    "wof:name":"Hanne's Fodklinik",
    "wof:placetype":"venue"
},
  "geometry": {"coordinates":[9.7946596146,56.6382789612],"type":"Point"}
}