{
  "type": "Feature",
  "properties": {
    "addr:full":"Magle Alle 7 - 9 Kastrup Danmark 2770",
    "addr:housenumber":"7 9",
    "addr:postcode":"2770",
    "addr:street":"Magle Alle",
    "iso:country":"DK",
    "sg:address":"Magle Alle 7 - 9",
    "sg:city":"Kastrup",
    "sg:orig_category":"Fabrikker",
    "sg:phone":"+45 32 50 76 67",
    "sg:postcode":"2770",
    "sg:province":"Danmark",
    "wof:name":"Ria Metalvare",
    "wof:placetype":"venue"
},
  "geometry": {"coordinates":[12.6261062622,55.6248779297],"type":"Point"}
}