{
  "type": "Feature",
  "properties": {
    "addr:full":"Helgolandsgade 8 A K\u00f8benhavn Danmark 1653",
    "addr:housenumber":"8 a",
    "addr:postcode":"1653",
    "addr:street":"Helgolandsgade",
    "iso:country":"DK",
    "sg:address":"Helgolandsgade 8 A",
    "sg:city":"K\u00f8benhavn",
    "sg:classifiers":[
        {
            "category":"Restaurant",
            "type":"Food & Drink"
        }
    ],
    "sg:phone":"+45 33 22 96 15",
    "sg:postcode":"1653",
    "sg:province":"Danmark",
    "wof:name":"Gelins K\u00e6lder",
    "wof:placetype":"venue"
},
  "geometry": {"coordinates":[12.5621004105,55.6717987061],"type":"Point"}
}