{
  "type": "Feature",
  "properties": {
    "addr:full":"Viemose Gade 7 Kalvehave Danmark 4771",
    "addr:housenumber":"7",
    "addr:postcode":"4771",
    "addr:street":"Viemose Gade",
    "iso:country":"DK",
    "sg:address":"Viemose Gade 7",
    "sg:city":"Kalvehave",
    "sg:orig_category":"Forsamlingshuse",
    "sg:postcode":"4771",
    "sg:province":"Danmark",
    "wof:name":"Viemose Forsamlingshus",
    "wof:placetype":"venue"
},
  "geometry": {"coordinates":[12.14316082,55.0078201294],"type":"Point"}
}