{
  "type": "Feature",
  "properties": {
    "addr:full":"Stadionvej 2, Vivild Alling\u00e5bro Danmark 8961",
    "addr:housenumber":"2",
    "addr:postcode":"8961",
    "addr:street":"Stadionvej",
    "iso:country":"DK",
    "sg:address":"Stadionvej 2, Vivild",
    "sg:city":"Alling\u00e5bro",
    "sg:orig_category":"Autoreparation og -service",
    "sg:phone":"+45 86 48 62 28",
    "sg:postcode":"8961",
    "sg:province":"Danmark",
    "wof:name":"Hydro Texaco",
    "wof:placetype":"venue"
},
  "geometry": {"coordinates":[10.3230552673,56.4639511108],"type":"Point"}
}