{
  "type": "Feature",
  "properties": {
    "addr:full":"E. Christensens Vej 82 Ikast Danmark 7430",
    "addr:housenumber":"82",
    "addr:postcode":"7430",
    "addr:street":"E. Christensens Vej",
    "iso:country":"DK",
    "sg:address":"E. Christensens Vej 82",
    "sg:city":"Ikast",
    "sg:orig_category":"Autoelektro",
    "sg:phone":"+45 97 15 33 33",
    "sg:postcode":"7430",
    "sg:province":"Danmark",
    "wof:name":"Ikast Elektro & Autoelektro",
    "wof:placetype":"venue"
},
  "geometry": {"coordinates":[9.1301612854,56.138343811],"type":"Point"}
}