{
  "type": "Feature",
  "properties": {
    "addr:full":"v/ Bodil W\u00f6hnert, Frodesgade 132 Esbjerg Danmark 6700",
    "addr:housenumber":"132",
    "addr:postcode":"6700",
    "addr:street":"Frodesgade",
    "iso:country":"DK",
    "sg:address":"v/ Bodil W\u00f6hnert, Frodesgade 132",
    "sg:city":"Esbjerg",
    "sg:orig_category":"Kulturelle foreninger",
    "sg:phone":"+45 75 13 58 23",
    "sg:postcode":"6700",
    "sg:province":"Danmark",
    "sg:website":"home13.inet.tele.dk/wohnert",
    "wof:name":"Operaens Venner i Esbjerg",
    "wof:placetype":"venue"
},
  "geometry": {"coordinates":[8.456905365,55.465221405],"type":"Point"}
}