{
  "type": "Feature",
  "properties": {
    "addr:full":"\u00c5rhusvej 241, Skovby Galten Danmark 8464",
    "addr:housenumber":"241",
    "addr:postcode":"8464",
    "addr:street":"Aarhusvej;Skovby",
    "iso:country":"DK",
    "sg:address":"\u00c5rhusvej 241, Skovby",
    "sg:city":"Galten",
    "sg:orig_category":"Reklame",
    "sg:phone":"+45 86 94 72 22",
    "sg:postcode":"8464",
    "sg:province":"Danmark",
    "wof:name":"Mac-Inhouse ApS Tryksager og Reklame",
    "wof:placetype":"venue"
},
  "geometry": {"coordinates":[9.9034748077,56.1558837891],"type":"Point"}
}