{
  "type": "Feature",
  "properties": {
    "iso:country":"DK",
    "sg:address":"Gentoftegade 60",
    "sg:city":"Gentofte",
    "sg:orig_category":"Advokater",
    "sg:phone":"+45 39 65 02 88",
    "sg:postcode":"2820",
    "sg:province":"Danmark",
    "wof:name":"Andersen, J\u00f8rgen Steen",
    "wof:placetype":"venue"
},
  "geometry": {"coordinates":[12.5407419205,55.7466926575],"type":"Point"}
}