{
  "type": "Feature",
  "properties": {
    "iso:country":"DK",
    "sg:address":"Fmd.: Egon Hansen, Hegnet 17, L\u00f8rslev",
    "sg:city":"Hj\u00f8rring",
    "sg:orig_category":"Spejderkorps",
    "sg:phone":"+45 98 96 31 64",
    "sg:postcode":"9800",
    "sg:province":"Danmark",
    "wof:name":"KFUM-spejderne, L\u00f8rslev",
    "wof:placetype":"venue"
},
  "geometry": {"coordinates":[9.9885387421,57.4594764709],"type":"Point"}
}