{
  "type": "Feature",
  "properties": {
    "addr:full":"Gl. Torv 6 Nysted Danmark 4880",
    "addr:housenumber":"6",
    "addr:postcode":"4880",
    "addr:street":"Gl. Torv",
    "iso:country":"DK",
    "sg:address":"Gl. Torv 6",
    "sg:city":"Nysted",
    "sg:orig_category":"Slagter og viktualie",
    "sg:phone":"+45 54 87 10 76",
    "sg:postcode":"4880",
    "sg:province":"Danmark",
    "wof:name":"Hansen & S\u00f8n",
    "wof:placetype":"venue"
},
  "geometry": {"coordinates":[11.7297554016,54.6671638489],"type":"Point"}
}