{
  "type": "Feature",
  "properties": {
    "iso:country":"DK",
    "sg:address":"Essen 31 ",
    "sg:city":"Kolding",
    "sg:classifiers":[
        {
            "category":"Real Estate",
            "subcategory":"Surveying",
            "type":"Services"
        }
    ],
    "sg:phone":"+45 75 56 70 77",
    "sg:postcode":"6000",
    "sg:province":"Danmark",
    "sg:tags":[
        "equipment",
        "material",
        "good",
        "-",
        "handling"
    ],
    "wof:name":"HANDY TRANSPORTVOGNE, KOLDING A/S",
    "wof:placetype":"venue"
},
  "geometry": {"coordinates":[9.4857807159,55.4611244202],"type":"Point"}
}