{
  "type": "Feature",
  "properties": {
    "iso:country":"DK",
    "sg:address":"Fmd.: Erik Andreassen, Blichersvej 54, Thorning",
    "sg:city":"Kjellerup",
    "sg:orig_category":"Hobbybetonede foreninger",
    "sg:phone":"+45 86 88 90 38",
    "sg:postcode":"8620",
    "sg:province":"Danmark",
    "wof:name":"Kjellerup Akvarieforening",
    "wof:placetype":"venue"
},
  "geometry": {"coordinates":[9.430934906,56.2877655029],"type":"Point"}
}