{
  "type": "Feature",
  "properties": {
    "addr:full":"Kirkevej 26, Rindum Ringk\u00f8bing Danmark 6950",
    "addr:housenumber":"26",
    "addr:postcode":"6950",
    "addr:street":"Kirkevej",
    "iso:country":"DK",
    "sg:address":"Kirkevej 26, Rindum",
    "sg:city":"Ringk\u00f8bing",
    "sg:orig_category":"Fritidsklubber",
    "sg:phone":"+45 97 32 46 99",
    "sg:postcode":"6950",
    "sg:province":"Danmark",
    "wof:name":"Fritidsklub i Rindum",
    "wof:placetype":"venue"
},
  "geometry": {"coordinates":[-114.0767440796,46.4432487488],"type":"Point"}
}