{
  "type": "Feature",
  "properties": {
    "addr:full":"Firskovvej 9 Kongens Lyngby Danmark 2800",
    "addr:housenumber":"9",
    "addr:postcode":"2800",
    "addr:street":"Firskovvej",
    "iso:country":"DK",
    "sg:address":"Firskovvej 9",
    "sg:city":"Kongens Lyngby",
    "sg:orig_category":"Genbrugspladser",
    "sg:phone":"+45 45 93 06 93",
    "sg:postcode":"2800",
    "sg:province":"Danmark",
    "wof:name":"Genbrugsstationen",
    "wof:placetype":"venue"
},
  "geometry": {"coordinates":[12.5368299484,55.7949905396],"type":"Point"}
}