{
  "type": "Feature",
  "properties": {
    "addr:full":"Dronningensgade 34 K\u00f8benhavn Danmark 1420",
    "addr:housenumber":"34",
    "addr:postcode":"1420",
    "addr:street":"Dronningensgade",
    "iso:country":"DK",
    "sg:address":"Dronningensgade 34",
    "sg:city":"K\u00f8benhavn",
    "sg:orig_category":"Selskabslokaler",
    "sg:phone":"+45 32 57 88 18",
    "sg:postcode":"1420",
    "sg:province":"Danmark",
    "wof:name":"Christianshavns Beboerhus",
    "wof:placetype":"venue"
},
  "geometry": {"coordinates":[12.5927000046,55.6703987122],"type":"Point"}
}