{
  "type": "Feature",
  "properties": {
    "addr:full":"Hovedgaden 13 Lille Skensved Danmark 4623",
    "addr:housenumber":"13",
    "addr:postcode":"4623",
    "addr:street":"Hovedgaden",
    "iso:country":"DK",
    "sg:address":"Hovedgaden 13",
    "sg:city":"Lille Skensved",
    "sg:orig_category":"Slagter og viktualie",
    "sg:phone":"+45 56 16 90 17",
    "sg:postcode":"4623",
    "sg:province":"Danmark",
    "wof:name":"Skensved Slagteren",
    "wof:placetype":"venue"
},
  "geometry": {"coordinates":[12.1375389099,55.5122146606],"type":"Point"}
}