{
  "type": "Feature",
  "properties": {
    "addr:full":"Liseborgvej 63 Viborg Danmark 8800",
    "addr:housenumber":"63",
    "addr:postcode":"8800",
    "addr:street":"Liseborgvej",
    "iso:country":"DK",
    "sg:address":"Liseborgvej 63",
    "sg:city":"Viborg",
    "sg:orig_category":"Plantecentre",
    "sg:phone":"+45 87 27 10 00",
    "sg:postcode":"8800",
    "sg:province":"Danmark",
    "wof:name":"Plantorama 2000",
    "wof:placetype":"venue"
},
  "geometry": {"coordinates":[9.3668146133,56.4402961731],"type":"Point"}
}