{
  "type": "Feature",
  "properties": {
    "addr:full":"Hovedgaden 116 A, Poulstrup Vr\u00e5 Danmark 9760",
    "addr:housenumber":"116 a",
    "addr:postcode":"9760",
    "addr:street":"Hovedgaden;Poulstrup Vraa Danmark",
    "iso:country":"DK",
    "sg:address":"Hovedgaden 116 A, Poulstrup",
    "sg:city":"Vr\u00e5",
    "sg:orig_category":"Plejehjem",
    "sg:phone":"+45 98 98 80 40",
    "sg:postcode":"9760",
    "sg:province":"Danmark",
    "wof:name":"Poulstruplund Plejehjem",
    "wof:placetype":"venue"
},
  "geometry": {"coordinates":[9.9477567673,57.3534927368],"type":"Point"}
}