{
  "type": "Feature",
  "properties": {
    "addr:full":"Landevejen 5 Hundslund Danmark 8350",
    "addr:housenumber":"5",
    "addr:postcode":"8350",
    "addr:street":"Landevejen",
    "iso:country":"DK",
    "sg:address":"Landevejen 5",
    "sg:city":"Hundslund",
    "sg:orig_category":"Kirker",
    "sg:postcode":"8350",
    "sg:province":"Danmark",
    "wof:name":"Hundslund Kirke",
    "wof:placetype":"venue"
},
  "geometry": {"coordinates":[10.0574798584,55.9160194397],"type":"Point"}
}