{
  "type": "Feature",
  "properties": {
    "addr:full":"Ibsvej 21 Lundby Danmark 4750",
    "addr:housenumber":"21",
    "addr:postcode":"4750",
    "addr:street":"Ibsvej",
    "iso:country":"DK",
    "sg:address":"Ibsvej 21",
    "sg:city":"Lundby",
    "sg:orig_category":"\u00c3\u02dcvrige institutioner",
    "sg:phone":"+45 55 76 72 32",
    "sg:postcode":"4750",
    "sg:province":"Danmark",
    "wof:name":"Storstr\u00f8mmens Sundhedscenters Aftenskole",
    "wof:placetype":"venue"
},
  "geometry": {"coordinates":[11.8788633347,55.1082305908],"type":"Point"}
}