{
  "type": "Feature",
  "properties": {
    "iso:country":"DK",
    "sg:address":"S\u00f8nderbrogade 29",
    "sg:city":"Horsens",
    "sg:orig_category":"Genbrugsbutikker",
    "sg:phone":"+45 76 29 36 97",
    "sg:postcode":"8700",
    "sg:province":"Danmark",
    "wof:name":"Genbrugs- og Kunstbutikken",
    "wof:placetype":"venue"
},
  "geometry": {"coordinates":[9.8430070877,55.8591461182],"type":"Point"}
}