{
  "type": "Feature",
  "properties": {
    "addr:full":"Medelbyvej 3 D R\u00f8dovre Danmark 2610",
    "addr:housenumber":"3 d",
    "addr:postcode":"2610",
    "addr:street":"Medelbyvej;Danmark",
    "iso:country":"DK",
    "sg:address":"Medelbyvej 3 D",
    "sg:city":"R\u00f8dovre",
    "sg:orig_category":"Revisorer",
    "sg:phone":"+45 36 70 87 57",
    "sg:postcode":"2610",
    "sg:province":"Danmark",
    "wof:name":"T. S. Revision",
    "wof:placetype":"venue"
},
  "geometry": {"coordinates":[10.6992139816,61.1027755737],"type":"Point"}
}