{
  "type": "Feature",
  "properties": {
    "addr:full":"Funderholmevej 31 Silkeborg Danmark 8600",
    "addr:housenumber":"31",
    "addr:postcode":"8600",
    "addr:street":"Funderholmevej",
    "iso:country":"DK",
    "sg:address":"Funderholmevej 31",
    "sg:city":"Silkeborg",
    "sg:orig_category":"Sportsartikler",
    "sg:phone":"+45 86 81 76 30",
    "sg:postcode":"8600",
    "sg:province":"Danmark",
    "wof:name":"Mak, Stald",
    "wof:placetype":"venue"
},
  "geometry": {"coordinates":[9.5051403046,56.1424636841],"type":"Point"}
}