{
  "type": "Feature",
  "properties": {
    "addr:full":"Eriksmindevej 20 Greve Danmark 2670",
    "addr:housenumber":"20",
    "addr:postcode":"2670",
    "addr:street":"Eriksmindevej",
    "iso:country":"DK",
    "sg:address":"Eriksmindevej 20",
    "sg:city":"Greve",
    "sg:orig_category":"Kirkesogne",
    "sg:phone":"+45 43 90 55 77",
    "sg:postcode":"2670",
    "sg:province":"Danmark",
    "wof:name":"Kildebr\u00f8nde Sogns Kirkekontor",
    "wof:placetype":"venue"
},
  "geometry": {"coordinates":[12.3181829453,55.5942153931],"type":"Point"}
}