{
  "type": "Feature",
  "properties": {
    "addr:full":"Nordborg Nordborg Danmark 6430",
    "addr:postcode":"6430",
    "iso:country":"DK",
    "sg:address":"Nordborg",
    "sg:city":"Nordborg",
    "sg:orig_category":"Kulturelle foreninger",
    "sg:phone":"+45 74 88 22 22",
    "sg:postcode":"6430",
    "sg:province":"Danmark",
    "wof:name":"Danfoss Kunstforening",
    "wof:placetype":"venue"
},
  "geometry": {"coordinates":[9.7496204376,55.054271698],"type":"Point"}
}