{
  "type": "Feature",
  "properties": {
    "addr:full":"Finsensvej 75 Frederiksberg Danmark 2000",
    "addr:housenumber":"75",
    "addr:postcode":"2000",
    "addr:street":"Finsensvej",
    "iso:country":"DK",
    "sg:address":"Finsensvej 75",
    "sg:city":"Frederiksberg",
    "sg:orig_category":"Psykoterapi",
    "sg:phone":"+45 38 87 86 36",
    "sg:postcode":"2000",
    "sg:province":"Danmark",
    "wof:name":"Grenander, Gerda",
    "wof:placetype":"venue"
},
  "geometry": {"coordinates":[12.5032081604,55.682144165],"type":"Point"}
}