{
  "type": "Feature",
  "properties": {
    "iso:country":"DK",
    "sg:address":"Tj\u00f8rnevej 12",
    "sg:city":"Viborg",
    "sg:classifiers":[
        {
            "category":"Banks & Credit Unions",
            "subcategory":"Financial Services",
            "type":"Services"
        }
    ],
    "sg:phone":"+45 86 62 16 81",
    "sg:postcode":"8800",
    "sg:province":"Danmark",
    "sg:tags":[
        "banking",
        "finance",
        "insurance"
    ],
    "wof:name":"NIELS J\u00d8RGEN & J\u00d8RGEN NIELSEN HANDELSELSKAB VIBORG APS",
    "wof:placetype":"venue"
},
  "geometry": {"coordinates":[9.3975505829,56.4549102783],"type":"Point"}
}