{
  "type": "Feature",
  "properties": {
    "addr:full":"Kaslundvej 22, \u00d8rsbjerg Aarup Danmark 5560",
    "addr:housenumber":"22",
    "addr:postcode":"5560",
    "addr:street":"Kaslundvej",
    "iso:country":"DK",
    "sg:address":"Kaslundvej 22, \u00d8rsbjerg",
    "sg:city":"Aarup",
    "sg:orig_category":"Autoopretning",
    "sg:phone":"+45 64 43 12 03",
    "sg:postcode":"5560",
    "sg:province":"Danmark",
    "wof:name":"\u00d8rsbjerg Karosseri",
    "wof:placetype":"venue"
},
  "geometry": {"coordinates":[10.0490245819,55.3808059692],"type":"Point"}
}