{
  "type": "Feature",
  "properties": {
    "addr:full":"Vester Torv 19, Esperg\u00e6rde Centret Esperg\u00e6rde Danmark 3060",
    "addr:housenumber":"19",
    "addr:postcode":"3060",
    "addr:street":"Vester Torv",
    "iso:country":"DK",
    "sg:address":"Vester Torv 19, Esperg\u00e6rde Centret",
    "sg:city":"Esperg\u00e6rde",
    "sg:classifiers":[
        {
            "category":"Food & Beverages",
            "subcategory":"Liquor & Beverages",
            "type":"Retail Goods"
        }
    ],
    "sg:phone":"+45 49 13 24 21",
    "sg:postcode":"3060",
    "sg:province":"Danmark",
    "sg:tags":[
        "vin"
    ],
    "wof:name":"Esperg\u00e6rde Vinhandel",
    "wof:placetype":"venue"
},
  "geometry": {"coordinates":[11.6512403488,47.8390617371],"type":"Point"}
}