{
  "type": "Feature",
  "properties": {
    "addr:full":"Stationsvej 30 Vejby Danmark 3210",
    "addr:housenumber":"30",
    "addr:postcode":"3210",
    "addr:street":"Stationsvej",
    "iso:country":"DK",
    "sg:address":"Stationsvej 30",
    "sg:city":"Vejby",
    "sg:orig_category":"Jernbaner",
    "sg:postcode":"3210",
    "sg:province":"Danmark",
    "wof:name":"Gribskovbanen, Vejby Station",
    "wof:placetype":"venue"
},
  "geometry": {"coordinates":[12.136048317,56.0629081726],"type":"Point"}
}