{
  "type": "Feature",
  "properties": {
    "addr:full":"Skolevej 1 Stensved Danmark 4773",
    "addr:housenumber":"1",
    "addr:postcode":"4773",
    "addr:street":"Skolevej",
    "iso:country":"DK",
    "sg:address":"Skolevej 1",
    "sg:city":"Stensved",
    "sg:orig_category":"Skolefritidsordninger",
    "sg:phone":"+45 55 38 63 43",
    "sg:postcode":"4773",
    "sg:province":"Danmark",
    "wof:name":"Stensved SFO",
    "wof:placetype":"venue"
},
  "geometry": {"coordinates":[12.0201730728,54.9963951111],"type":"Point"}
}