{
  "type": "Feature",
  "properties": {
    "addr:full":"\u00c5brinken 15 Uldum Danmark 7171",
    "addr:housenumber":"15",
    "addr:postcode":"7171",
    "addr:street":"Aabrinken",
    "iso:country":"DK",
    "sg:address":"\u00c5brinken 15",
    "sg:city":"Uldum",
    "sg:orig_category":"Zoneterapeuter",
    "sg:phone":"+45 75 67 83 79",
    "sg:postcode":"7171",
    "sg:province":"Danmark",
    "wof:name":"Birthe's Fodpleje & Zoneterapi",
    "wof:placetype":"venue"
},
  "geometry": {"coordinates":[9.5957050323,55.8521881104],"type":"Point"}
}