{
  "type": "Feature",
  "properties": {
    "addr:full":"Finlandsvej 4 Skanderborg Danmark 8660",
    "addr:housenumber":"4",
    "addr:postcode":"8660",
    "addr:street":"Finlandsvej",
    "iso:country":"DK",
    "sg:address":"Finlandsvej 4",
    "sg:city":"Skanderborg",
    "sg:orig_category":"Stilladser",
    "sg:phone":"+45 86 52 15 50",
    "sg:postcode":"8660",
    "sg:province":"Danmark",
    "wof:name":"Skanderborg Stilladser",
    "wof:placetype":"venue"
},
  "geometry": {"coordinates":[9.9510011673,56.0517921448],"type":"Point"}
}