{
  "type": "Feature",
  "properties": {
    "iso:country":"DK",
    "sg:address":"Siriusvej 5",
    "sg:city":"Ikast",
    "sg:orig_category":"Autoforhandlere",
    "sg:phone":"+45 96 60 15 66",
    "sg:postcode":"7430",
    "sg:province":"Danmark",
    "sg:website":"www.toyota.dk/ikast",
    "wof:name":"Toyota",
    "wof:placetype":"venue"
},
  "geometry": {"coordinates":[9.1405382156,56.1378669739],"type":"Point"}
}