{
  "type": "Feature",
  "properties": {
    "addr:full":"Uldum Hedevej 18 Uldum Danmark 7171",
    "addr:housenumber":"18",
    "addr:postcode":"7171",
    "addr:street":"Uldum Hedevej",
    "iso:country":"DK",
    "sg:address":"Uldum Hedevej 18",
    "sg:city":"Uldum",
    "sg:orig_category":"Maskinstationer",
    "sg:phone":"+45 75 89 33 14",
    "sg:postcode":"7171",
    "sg:province":"Danmark",
    "wof:name":"B\u00f8gballe Maskinstation",
    "wof:placetype":"venue"
},
  "geometry": {"coordinates":[9.6040296555,55.8315696716],"type":"Point"}
}