{
  "type": "Feature",
  "properties": {
    "addr:full":"Industrivej 29, Nr. Broby Broby Danmark 5672",
    "addr:housenumber":"29",
    "addr:postcode":"5672",
    "addr:street":"Industrivej",
    "iso:country":"DK",
    "sg:address":"Industrivej 29, Nr. Broby",
    "sg:city":"Broby",
    "sg:orig_category":"Affald",
    "sg:phone":"+45 65 95 82 03",
    "sg:postcode":"5672",
    "sg:province":"Danmark",
    "wof:name":"Nr. Broby Autogenbrug",
    "wof:placetype":"venue"
},
  "geometry": {"coordinates":[10.3131303787,55.2695846558],"type":"Point"}
}