{
  "type": "Feature",
  "properties": {
    "addr:full":"v/ Harriet S\u00f8rensen, Ly\u00f8 Bygade 22, Ly\u00f8 Faaborg Danmark 5600",
    "addr:housenumber":"22",
    "addr:postcode":"5600",
    "addr:street":"Lyo Bygade",
    "iso:country":"DK",
    "sg:address":"v/ Harriet S\u00f8rensen, Ly\u00f8 Bygade 22, Ly\u00f8",
    "sg:city":"Faaborg",
    "sg:orig_category":"\u00c3\u2020ldreorganisationer og klubber",
    "sg:phone":"+45 62 61 80 07",
    "sg:postcode":"5600",
    "sg:province":"Danmark",
    "wof:name":"Ly\u00f8 \u00c6ldreklub",
    "wof:placetype":"venue"
},
  "geometry": {"coordinates":[10.2400531769,55.0950622559],"type":"Point"}
}