{
  "type": "Feature",
  "properties": {
    "iso:country":"DK",
    "sg:address":"Skovvej 66",
    "sg:city":"Vordingborg",
    "sg:orig_category":"Kiropraktorer",
    "sg:phone":"+45 55 34 10 57",
    "sg:postcode":"4760",
    "sg:province":"Danmark",
    "wof:name":"Selander, D.C. Steen",
    "wof:placetype":"venue"
},
  "geometry": {"coordinates":[11.9064149857,55.0064888],"type":"Point"}
}