{
  "type": "Feature",
  "properties": {
    "addr:full":"Fmd.: Mogens Maagaard, Skovsgaardsvej 20 Nakskov Danmark 4900",
    "addr:housenumber":"20",
    "addr:postcode":"4900",
    "addr:street":"Skovsgaardsvej",
    "iso:country":"DK",
    "sg:address":"Fmd.: Mogens Maagaard, Skovsgaardsvej 20",
    "sg:city":"Nakskov",
    "sg:orig_category":"Trossamfund uden for folkekirken",
    "sg:phone":"+45 54 92 10 65",
    "sg:postcode":"4900",
    "sg:province":"Danmark",
    "wof:name":"Indre Mission",
    "wof:placetype":"venue"
},
  "geometry": {"coordinates":[11.1359500885,54.8330116272],"type":"Point"}
}