{
  "type": "Feature",
  "properties": {
    "addr:full":"Rengegade 2 Store Heddinge Danmark 4660",
    "addr:housenumber":"2",
    "addr:postcode":"4660",
    "addr:street":"Rengegade",
    "iso:country":"DK",
    "sg:address":"Rengegade 2",
    "sg:city":"Store Heddinge",
    "sg:orig_category":"Advokater",
    "sg:phone":"+45 56 50 29 00",
    "sg:postcode":"4660",
    "sg:province":"Danmark",
    "wof:name":"Advokaterne p\u00e5 Trianglen",
    "wof:placetype":"venue"
},
  "geometry": {"coordinates":[12.3892621994,55.2986717224],"type":"Point"}
}