{
  "type": "Feature",
  "properties": {
    "addr:full":"Niv\u00e5 Center 25 Niv\u00e5 Danmark 2990",
    "addr:housenumber":"25",
    "addr:postcode":"2990",
    "addr:street":"Nivaa Danmark",
    "iso:country":"DK",
    "sg:address":"Niv\u00e5 Center 25",
    "sg:city":"Niv\u00e5",
    "sg:orig_category":"Materialister",
    "sg:phone":"+45 49 14 21 00",
    "sg:postcode":"2990",
    "sg:province":"Danmark",
    "wof:name":"Matas",
    "wof:placetype":"venue"
},
  "geometry": {"coordinates":[12.5068225861,55.9346847534],"type":"Point"}
}