{
  "type": "Feature",
  "properties": {
    "addr:full":"Lumbyesvej 20 Fredericia Danmark 7000",
    "addr:housenumber":"20",
    "addr:postcode":"7000",
    "addr:street":"Lumbyesvej",
    "iso:country":"DK",
    "sg:address":"Lumbyesvej 20",
    "sg:city":"Fredericia",
    "sg:orig_category":"Plejehjem",
    "sg:phone":"+45 72 10 59 94",
    "sg:postcode":"7000",
    "sg:province":"Danmark",
    "wof:name":"Bof\u00e6llesskabet Madsbyhus",
    "wof:placetype":"venue"
},
  "geometry": {"coordinates":[9.7291698456,55.5727729797],"type":"Point"}
}