{
  "type": "Feature",
  "properties": {
    "addr:full":"Energivej 23 Ballerup Danmark 2750",
    "addr:housenumber":"23",
    "addr:postcode":"2750",
    "addr:street":"Energivej",
    "iso:country":"DK",
    "sg:address":"Energivej 23",
    "sg:city":"Ballerup",
    "sg:orig_category":"Paller",
    "sg:phone":"+45 44 66 02 60",
    "sg:postcode":"2750",
    "sg:province":"Danmark",
    "wof:name":"Wenco Pak ApS",
    "wof:placetype":"venue"
},
  "geometry": {"coordinates":[12.376411438,55.7244644165],"type":"Point"}
}