{
  "type": "Feature",
  "properties": {
    "addr:full":"S\u00f8ndergade 17 Kjellerup Danmark 8620",
    "addr:housenumber":"17",
    "addr:postcode":"8620",
    "addr:street":"Sondergade",
    "iso:country":"DK",
    "sg:address":"S\u00f8ndergade 17",
    "sg:city":"Kjellerup",
    "sg:orig_category":"Posthuse",
    "sg:phone":"+45 89 28 88 00",
    "sg:postcode":"8620",
    "sg:province":"Danmark",
    "wof:name":"Post Danmark, Kjellerup Posthus",
    "wof:placetype":"venue"
},
  "geometry": {"coordinates":[9.4308576584,56.2883758545],"type":"Point"}
}