{
  "type": "Feature",
  "properties": {
    "addr:full":"Kretavej 23 K\u00f8benhavn S Danmark 2300",
    "addr:housenumber":"23",
    "addr:postcode":"2300",
    "addr:street":"Kretavej;S Danmark",
    "iso:country":"DK",
    "sg:address":"Kretavej 23",
    "sg:city":"K\u00f8benhavn S",
    "sg:orig_category":"Trossamfund uden for folkekirken",
    "sg:phone":"+45 22 55 35 40",
    "sg:postcode":"2300",
    "sg:province":"Danmark",
    "wof:name":"Jehovas Vidner",
    "wof:placetype":"venue"
},
  "geometry": {"coordinates":[-78.1299133301,36.7267417908],"type":"Point"}
}