{
  "type": "Feature",
  "properties": {
    "addr:full":"Handelscentret, Byst\u00e6vnet 1 Lystrup Danmark 8520",
    "addr:housenumber":"1",
    "addr:postcode":"8520",
    "addr:street":"Bystaevnet",
    "iso:country":"DK",
    "sg:address":"Handelscentret, Byst\u00e6vnet 1",
    "sg:city":"Lystrup",
    "sg:classifiers":[
        {
            "category":"Banks & Credit Unions",
            "subcategory":"Bank",
            "type":"Services"
        }
    ],
    "sg:phone":"+45 86 22 15 88",
    "sg:postcode":"8520",
    "sg:province":"Danmark",
    "sg:tags":[
        "banker"
    ],
    "wof:name":"Nordea",
    "wof:placetype":"venue"
},
  "geometry": {"coordinates":[10.2295379639,56.234172821],"type":"Point"}
}