{
  "type": "Feature",
  "properties": {
    "addr:full":"Brostykkevej 133 Hvidovre Danmark 2650",
    "addr:housenumber":"133",
    "addr:postcode":"2650",
    "addr:street":"Brostykkevej",
    "iso:country":"DK",
    "sg:address":"Brostykkevej 133",
    "sg:city":"Hvidovre",
    "sg:orig_category":"Pizzeriaer",
    "sg:phone":"+45 36 77 34 02",
    "sg:postcode":"2650",
    "sg:province":"Danmark",
    "wof:name":"Gourmet",
    "wof:placetype":"venue"
},
  "geometry": {"coordinates":[12.478313446,55.6374053955],"type":"Point"}
}