{
  "type": "Feature",
  "properties": {
    "addr:full":"Hobrovej 801 Svenstrup Danmark 9230",
    "addr:housenumber":"801",
    "addr:postcode":"9230",
    "addr:street":"Hobrovej",
    "iso:country":"DK",
    "sg:address":"Hobrovej 801",
    "sg:city":"Svenstrup",
    "sg:classifiers":[
        {
            "category":"Personal",
            "subcategory":"Massage",
            "type":"Services"
        }
    ],
    "sg:phone":"+45 98 38 00 92",
    "sg:postcode":"9230",
    "sg:province":"Danmark",
    "wof:name":"Hertz, Elsebeth",
    "wof:placetype":"venue"
},
  "geometry": {"coordinates":[9.8557806015,56.9676628113],"type":"Point"}
}