{
  "type": "Feature",
  "properties": {
    "addr:full":"Gammel K\u00f8ge Landevej 20 D, 2. Valby Danmark 2500",
    "addr:housenumber":"20 d 2",
    "addr:postcode":"2500",
    "addr:street":"Gammel Koge Landevej",
    "iso:country":"DK",
    "sg:address":"Gammel K\u00f8ge Landevej 20 D, 2.",
    "sg:city":"Valby",
    "sg:orig_category":"Rejsebureauer",
    "sg:phone":"+45 36 18 38 38",
    "sg:postcode":"2500",
    "sg:province":"Danmark",
    "sg:website":"www.dfd-travel.com",
    "wof:name":"TQ3 Travel Solutions",
    "wof:placetype":"venue"
},
  "geometry": {"coordinates":[12.514383316,55.6590423584],"type":"Point"}
}