{
  "type": "Feature",
  "properties": {
    "addr:full":"N\u00f8rreport 14 Aabenraa Danmark 6200",
    "addr:housenumber":"14",
    "addr:postcode":"6200",
    "addr:street":"Norreport",
    "iso:country":"DK",
    "sg:address":"N\u00f8rreport 14",
    "sg:city":"Aabenraa",
    "sg:orig_category":"INGENI\u00c3\u02dcRER",
    "sg:phone":"+45 74 63 17 50",
    "sg:postcode":"6200",
    "sg:province":"Danmark",
    "wof:name":"Pedersen, John E. R\u00e5dg. Ingeni\u00f8rfirma ApS F.R.I.",
    "wof:placetype":"venue"
},
  "geometry": {"coordinates":[9.4189119339,55.0483703613],"type":"Point"}
}