{
  "type": "Feature",
  "properties": {
    "addr:full":"Brandevej 18, Brande Them Danmark 8653",
    "addr:housenumber":"18",
    "addr:postcode":"8653",
    "addr:street":"Brandevej",
    "iso:country":"DK",
    "sg:address":"Brandevej 18, Brande",
    "sg:city":"Them",
    "sg:orig_category":"Kirker",
    "sg:postcode":"8653",
    "sg:province":"Danmark",
    "wof:name":"Brande Kirke (Them Sogn)",
    "wof:placetype":"venue"
},
  "geometry": {"coordinates":[9.5489425659,56.0950088501],"type":"Point"}
}