{
  "type": "Feature",
  "properties": {
    "addr:full":"Stadionvej 2 A Hadsund Danmark 9560",
    "addr:housenumber":"2 a",
    "addr:postcode":"9560",
    "addr:street":"Stadionvej",
    "iso:country":"DK",
    "sg:address":"Stadionvej 2 A",
    "sg:city":"Hadsund",
    "sg:orig_category":"Databehandling",
    "sg:phone":"+45 96 53 10 00",
    "sg:postcode":"9560",
    "sg:province":"Danmark",
    "wof:name":"Dator A/S",
    "wof:placetype":"venue"
},
  "geometry": {"coordinates":[10.1278762817,56.7217330933],"type":"Point"}
}