{
  "type": "Feature",
  "properties": {
    "addr:full":"Geding S\u00f8vej 19, Geding Tilst Danmark 8381",
    "addr:housenumber":"19",
    "addr:postcode":"8381",
    "addr:street":"Sovej;Geding",
    "iso:country":"DK",
    "sg:address":"Geding S\u00f8vej 19, Geding",
    "sg:city":"Tilst",
    "sg:orig_category":"Ejendomshandel",
    "sg:phone":"+45 86 24 18 67",
    "sg:postcode":"8381",
    "sg:province":"Danmark",
    "wof:name":"Tilst Ejendomshandel",
    "wof:placetype":"venue"
},
  "geometry": {"coordinates":[10.1078147888,56.1882019043],"type":"Point"}
}