{
  "type": "Feature",
  "properties": {
    "addr:full":"Maglemervej 83 Maribo Danmark 4930",
    "addr:housenumber":"83",
    "addr:postcode":"4930",
    "addr:street":"Maglemervej",
    "iso:country":"DK",
    "sg:address":"Maglemervej 83",
    "sg:city":"Maribo",
    "sg:orig_category":"Solcentre",
    "sg:phone":"+45 54 78 34 46",
    "sg:postcode":"4930",
    "sg:province":"Danmark",
    "wof:name":"Fris\u00f8r og Sol K\u00e6lderen",
    "wof:placetype":"venue"
},
  "geometry": {"coordinates":[11.4998188019,54.7831535339],"type":"Point"}
}