{
  "type": "Feature",
  "properties": {
    "addr:full":"Ulrikkenborg Plads 1 Kongens Lyngby Danmark 2800",
    "addr:housenumber":"1",
    "addr:postcode":"2800",
    "addr:street":"Ulrikkenborg Plads",
    "iso:country":"DK",
    "sg:address":"Ulrikkenborg Plads 1",
    "sg:city":"Kongens Lyngby",
    "sg:orig_category":"Renserier",
    "sg:phone":"+45 45 87 14 03",
    "sg:postcode":"2800",
    "sg:province":"Danmark",
    "wof:name":"Lyngby Renseri",
    "wof:placetype":"venue"
},
  "geometry": {"coordinates":[12.5025444031,55.7679252625],"type":"Point"}
}