{
  "type": "Feature",
  "properties": {
    "addr:full":"Valbyvej 29 Helsinge Danmark 3200",
    "addr:housenumber":"29",
    "addr:postcode":"3200",
    "addr:street":"Valbyvej",
    "iso:country":"DK",
    "sg:address":"Valbyvej 29",
    "sg:city":"Helsinge",
    "sg:orig_category":"Hobbybetonede foreninger",
    "sg:phone":"+45 48 79 70 54",
    "sg:postcode":"3200",
    "sg:province":"Danmark",
    "wof:name":"Helsinge Motorcykelklub",
    "wof:placetype":"venue"
},
  "geometry": {"coordinates":[12.1974000931,56.0335731506],"type":"Point"}
}