{
  "type": "Feature",
  "properties": {
    "iso:country":"DK",
    "sg:address":"H\u00f8je Gladsaxe 5, mf.",
    "sg:city":"S\u00f8borg",
    "sg:orig_category":"Vinduespolering",
    "sg:phone":"+45 39 66 35 33",
    "sg:postcode":"2860",
    "sg:province":"Danmark",
    "wof:name":"Hansen, A. Rud",
    "wof:placetype":"venue"
},
  "geometry": {"coordinates":[12.4819698334,55.7465934753],"type":"Point"}
}