{
  "type": "Feature",
  "properties": {
    "addr:full":"S\u00f8ndergade 25 Vojens Danmark 6500",
    "addr:housenumber":"25",
    "addr:postcode":"6500",
    "addr:street":"Sondergade",
    "iso:country":"DK",
    "sg:address":"S\u00f8ndergade 25",
    "sg:city":"Vojens",
    "sg:orig_category":"Grillbarer",
    "sg:phone":"+45 74 59 16 60",
    "sg:postcode":"6500",
    "sg:province":"Danmark",
    "wof:name":"Kino Cafeteria",
    "wof:placetype":"venue"
},
  "geometry": {"coordinates":[9.2993087769,55.2439346313],"type":"Point"}
}