{
  "type": "Feature",
  "properties": {
    "addr:full":"Middelfartvej 591, Spedsbjerg Blommenslyst Danmark 5491",
    "addr:housenumber":"591",
    "addr:postcode":"5491",
    "addr:street":"Middelfartvej",
    "iso:country":"DK",
    "sg:address":"Middelfartvej 591, Spedsbjerg",
    "sg:city":"Blommenslyst",
    "sg:orig_category":"Brugsforeninger",
    "sg:phone":"+45 65 96 70 51",
    "sg:postcode":"5491",
    "sg:province":"Danmark",
    "wof:name":"Ubberud Brugsforening",
    "wof:placetype":"venue"
},
  "geometry": {"coordinates":[10.2299203873,55.3889007568],"type":"Point"}
}