{
  "type": "Feature",
  "properties": {
    "iso:country":"DK",
    "sg:address":"Landsgravvej 27",
    "sg:city":"Slagelse",
    "sg:orig_category":"Selskabslokaler",
    "sg:phone":"+45 58 50 51 88",
    "sg:postcode":"4200",
    "sg:province":"Danmark",
    "wof:name":"H\u00e5ndv\u00e6rkerg\u00e5rden",
    "wof:placetype":"venue"
},
  "geometry": {"coordinates":[11.3303480148,55.3978042603],"type":"Point"}
}