{
  "type": "Feature",
  "properties": {
    "addr:full":"Mariagervej 72 Randers Danmark 8900",
    "addr:housenumber":"72",
    "addr:postcode":"8900",
    "addr:street":"Mariagervej",
    "iso:country":"DK",
    "sg:address":"Mariagervej 72",
    "sg:city":"Randers",
    "sg:orig_category":"Pizzeriaer",
    "sg:phone":"+45 86 43 67 32",
    "sg:postcode":"8900",
    "sg:province":"Danmark",
    "wof:name":"Pizza Barbaros",
    "wof:placetype":"venue"
},
  "geometry": {"coordinates":[10.0315341949,56.4695091248],"type":"Point"}
}