{
  "type": "Feature",
  "properties": {
    "iso:country":"DK",
    "sg:address":"Tofth\u00f8jvej 28",
    "sg:city":"Storvorde",
    "sg:orig_category":"Lokalcentre",
    "sg:phone":"+45 98 31 83 82",
    "sg:postcode":"9280",
    "sg:province":"Danmark",
    "wof:name":"Storvorde Plejecenter",
    "wof:placetype":"venue"
},
  "geometry": {"coordinates":[10.1022796631,56.9982719421],"type":"Point"}
}