{
  "type": "Feature",
  "properties": {
    "addr:full":"Industrivej 4 A, Ejby Ejby Danmark 5592",
    "addr:housenumber":"4 a",
    "addr:postcode":"5592",
    "addr:street":"Industrivej",
    "iso:country":"DK",
    "sg:address":"Industrivej 4 A, Ejby",
    "sg:city":"Ejby",
    "sg:orig_category":"Motorfabrikker",
    "sg:postcode":"5592",
    "sg:province":"Danmark",
    "wof:name":"Maraton ApS",
    "wof:placetype":"venue"
},
  "geometry": {"coordinates":[9.9277296066,55.4288444519],"type":"Point"}
}