{
  "type": "Feature",
  "properties": {
    "addr:full":"Jernbanegade 9, Hammerum Herning Danmark 7400",
    "addr:housenumber":"9",
    "addr:postcode":"7400",
    "addr:street":"Jernbanegade;Hammerum",
    "iso:country":"DK",
    "sg:address":"Jernbanegade 9, Hammerum",
    "sg:city":"Herning",
    "sg:orig_category":"Posthuse",
    "sg:phone":"+45 97 11 60 08",
    "sg:postcode":"7400",
    "sg:province":"Danmark",
    "wof:name":"Post Danmark, Hammerum Posthus",
    "wof:placetype":"venue"
},
  "geometry": {"coordinates":[8.9768896103,56.1374168396],"type":"Point"}
}