{
  "type": "Feature",
  "properties": {
    "iso:country":"DK",
    "sg:address":"Vesterbro 57",
    "sg:city":"Odense C",
    "sg:orig_category":"Bagere",
    "sg:phone":"+45 66 12 18 33",
    "sg:postcode":"5000",
    "sg:province":"Danmark",
    "wof:name":"Br\u00f8dkrummen",
    "wof:placetype":"venue"
},
  "geometry": {"coordinates":[10.374558,55.394215],"type":"Point"}
}