{
  "type": "Feature",
  "properties": {
    "addr:full":"Majsv\u00e6nget 120 Malling Danmark 8340",
    "addr:housenumber":"120",
    "addr:postcode":"8340",
    "iso:country":"DK",
    "sg:address":"Majsv\u00e6nget 120",
    "sg:city":"Malling",
    "sg:orig_category":"Zoneterapeuter",
    "sg:phone":"+45 86 93 18 39",
    "sg:postcode":"8340",
    "sg:province":"Danmark",
    "wof:name":"Ager, Tove",
    "wof:placetype":"venue"
},
  "geometry": {"coordinates":[10.193353653,56.0378875732],"type":"Point"}
}