{
  "type": "Feature",
  "properties": {
    "addr:full":"Torvet 4 B Frederiksv\u00e6rk Danmark 3300",
    "addr:housenumber":"4 b",
    "addr:postcode":"3300",
    "addr:street":"Torvet",
    "iso:country":"DK",
    "sg:address":"Torvet 4 B",
    "sg:city":"Frederiksv\u00e6rk",
    "sg:orig_category":"Advokater",
    "sg:phone":"+45 47 76 00 90",
    "sg:postcode":"3300",
    "sg:province":"Danmark",
    "wof:name":"Andersen & Thoregaard",
    "wof:placetype":"venue"
},
  "geometry": {"coordinates":[9.9058914185,59.7713279724],"type":"Point"}
}