{
  "type": "Feature",
  "properties": {
    "addr:full":"Toften 4 Otterup Danmark 5450",
    "addr:housenumber":"4",
    "addr:postcode":"5450",
    "addr:street":"Toften",
    "iso:country":"DK",
    "sg:address":"Toften 4",
    "sg:city":"Otterup",
    "sg:orig_category":"Slankecentre",
    "sg:phone":"+45 64 82 28 18",
    "sg:postcode":"5450",
    "sg:province":"Danmark",
    "wof:name":"Ny livsstil",
    "wof:placetype":"venue"
},
  "geometry": {"coordinates":[10.3984470367,55.5211677551],"type":"Point"}
}