{
  "type": "Feature",
  "properties": {
    "iso:country":"DK",
    "sg:address":"Rosenlundvej 21, Moseg\u00e5rd",
    "sg:city":"N\u00f8rre Aaby",
    "sg:orig_category":"Hunde",
    "sg:phone":"+45 64 42 20 20",
    "sg:postcode":"5580",
    "sg:province":"Danmark",
    "wof:name":"Kennel Grandly",
    "wof:placetype":"venue"
},
  "geometry": {"coordinates":[12.0131797791,57.6498298645],"type":"Point"}
}