{
  "type": "Feature",
  "properties": {
    "iso:country":"DK",
    "sg:address":"Svendborgvej 306, H\u00f8jby",
    "sg:city":"Odense S",
    "sg:classifiers":[
        {
            "category":"Utilities",
            "subcategory":"Refuse",
            "type":"Services"
        }
    ],
    "sg:phone":"+45 65 95 80 80",
    "sg:postcode":"5260",
    "sg:province":"Danmark",
    "sg:tags":[
        "catering"
    ],
    "wof:name":"Dennek Fyn H\u00f8jby",
    "wof:placetype":"venue"
},
  "geometry": {"coordinates":[10.3157806396,55.3122825623],"type":"Point"}
}