{
  "type": "Feature",
  "properties": {
    "addr:full":"Fmd.: Inge Warming, Korsk\u00e6rvej 200 Fredericia Danmark 7000",
    "addr:housenumber":"200",
    "addr:postcode":"7000",
    "addr:street":"Korskaervej",
    "iso:country":"DK",
    "sg:address":"Fmd.: Inge Warming, Korsk\u00e6rvej 200",
    "sg:city":"Fredericia",
    "sg:orig_category":"\u00c3\u02dcvrige foreninger",
    "sg:phone":"+45 76 91 48 64",
    "sg:postcode":"7000",
    "sg:province":"Danmark",
    "wof:name":"KADs Efterl\u00f8ns Og Legatklub Fredericia",
    "wof:placetype":"venue"
},
  "geometry": {"coordinates":[9.7591047287,55.566368103],"type":"Point"}
}