{
  "type": "Feature",
  "properties": {
    "addr:full":"Fmd.: Torben Petterson, S\u00f8vej 38, Kulhuse J\u00e6gerspris Danmark 3630",
    "addr:postcode":"38;3630",
    "addr:street":"Sovej;Kulhuse;Danmark",
    "iso:country":"DK",
    "sg:address":"Fmd.: Torben Petterson, S\u00f8vej 38, Kulhuse",
    "sg:city":"J\u00e6gerspris",
    "sg:orig_category":"Grundejerforeninger",
    "sg:phone":"+45 47 53 62 80",
    "sg:postcode":"3630",
    "sg:province":"Danmark",
    "wof:name":"Hornsved Grundejerforening",
    "wof:placetype":"venue"
},
  "geometry": {"coordinates":[11.9136800766,55.9269866943],"type":"Point"}
}