{
  "type": "Feature",
  "properties": {
    "addr:full":"Skovvej 1 Bogense Danmark 5400",
    "addr:housenumber":"1",
    "addr:postcode":"5400",
    "addr:street":"Skovvej",
    "iso:country":"DK",
    "sg:address":"Skovvej 1",
    "sg:city":"Bogense",
    "sg:orig_category":"Plejecentre",
    "sg:phone":"+45 64 81 18 57",
    "sg:postcode":"5400",
    "sg:province":"Danmark",
    "wof:name":"Aktivitetscenter",
    "wof:placetype":"venue"
},
  "geometry": {"coordinates":[10.093454361,55.5660438538],"type":"Point"}
}