{
  "type": "Feature",
  "properties": {
    "iso:country":"DK",
    "sg:address":"St. Sct. Mikkels Gade 31",
    "sg:city":"Viborg",
    "sg:classifiers":[
        {
            "category":"Professional",
            "subcategory":"Art Services",
            "type":"Services"
        }
    ],
    "sg:phone":"+45 86 60 17 37",
    "sg:postcode":"8800",
    "sg:province":"Danmark",
    "sg:tags":[
        "vin"
    ],
    "sg:website":"www.alliancevin.dk",
    "wof:name":"Alliancevin",
    "wof:placetype":"venue"
},
  "geometry": {"coordinates":[9.4092636108,56.4504318237],"type":"Point"}
}