{
  "type": "Feature",
  "properties": {
    "addr:full":"Baneg\u00e5rdsgade 21 Odder Danmark 8300",
    "addr:housenumber":"21",
    "addr:postcode":"8300",
    "addr:street":"Banegaardsgade",
    "iso:country":"DK",
    "sg:address":"Baneg\u00e5rdsgade 21",
    "sg:city":"Odder",
    "sg:orig_category":"Autoreparation og -service",
    "sg:phone":"+45 86 54 17 07",
    "sg:postcode":"8300",
    "sg:province":"Danmark",
    "wof:name":"Q8 Service",
    "wof:placetype":"venue"
},
  "geometry": {"coordinates":[10.1493062973,55.9693107605],"type":"Point"}
}