{
  "type": "Feature",
  "properties": {
    "addr:full":"Skolev\u00e6nget 3, Vejrup Bramming Danmark 6740",
    "addr:housenumber":"3",
    "addr:postcode":"6740",
    "addr:street":"Skolevaenget;Vejrup",
    "iso:country":"DK",
    "sg:address":"Skolev\u00e6nget 3, Vejrup",
    "sg:city":"Bramming",
    "sg:orig_category":"Kommunale folkeskoler",
    "sg:phone":"+45 75 19 00 97",
    "sg:postcode":"6740",
    "sg:province":"Danmark",
    "wof:name":"Vejrup Skole",
    "wof:placetype":"venue"
},
  "geometry": {"coordinates":[8.6974096298,55.4655303955],"type":"Point"}
}