{
  "type": "Feature",
  "properties": {
    "addr:full":"Avder\u00f8dvej 10 Kokkedal Danmark 2980",
    "addr:housenumber":"10",
    "addr:postcode":"2980",
    "addr:street":"Avderodvej",
    "iso:country":"DK",
    "sg:address":"Avder\u00f8dvej 10",
    "sg:city":"Kokkedal",
    "sg:orig_category":"Revisorer",
    "sg:phone":"+45 48 28 10 34",
    "sg:postcode":"2980",
    "sg:province":"Danmark",
    "wof:name":"Nielsen, Revisoranpartselskabet Flemming Juhl",
    "wof:placetype":"venue"
},
  "geometry": {"coordinates":[12.4769096375,55.9091339111],"type":"Point"}
}