{
  "type": "Feature",
  "properties": {
    "addr:full":"R\u00e5dhusvej 10 Charlottenlund Danmark 2920",
    "addr:housenumber":"10",
    "addr:postcode":"2920",
    "addr:street":"Raadhusvej",
    "iso:country":"DK",
    "sg:address":"R\u00e5dhusvej 10",
    "sg:city":"Charlottenlund",
    "sg:orig_category":"Slagter og viktualie",
    "sg:phone":"+45 39 63 58 45",
    "sg:postcode":"2920",
    "sg:province":"Danmark",
    "wof:name":"Slagterforretningen",
    "wof:placetype":"venue"
},
  "geometry": {"coordinates":[12.5714550018,55.752281189],"type":"Point"}
}