{
  "type": "Feature",
  "properties": {
    "addr:full":"Holstebrovej 81 Viborg Danmark 8800",
    "addr:housenumber":"81",
    "addr:postcode":"8800",
    "addr:street":"Holstebrovej",
    "iso:country":"DK",
    "sg:address":"Holstebrovej 81",
    "sg:city":"Viborg",
    "sg:orig_category":"Sengeudstyr",
    "sg:phone":"+45 86 61 08 00",
    "sg:postcode":"8800",
    "sg:province":"Danmark",
    "wof:name":"Jysk Senget\u00f8jslager",
    "wof:placetype":"venue"
},
  "geometry": {"coordinates":[9.363732338,56.4473571777],"type":"Point"}
}