{
  "type": "Feature",
  "properties": {
    "addr:full":"Mejlgade 95 \u00c5rhus C Danmark 8000",
    "addr:housenumber":"95",
    "addr:postcode":"8000",
    "addr:street":"Mejlgade",
    "iso:country":"DK",
    "sg:address":"Mejlgade 95",
    "sg:city":"\u00c5rhus C",
    "sg:orig_category":"Faglige organisationer og foreninger",
    "sg:phone":"+45 89 30 77 00",
    "sg:postcode":"8000",
    "sg:province":"Danmark",
    "sg:website":"www.metalaarhus1.dk",
    "wof:name":"Dansk Metalarbejderforbund, \u00c5rhus Afdeling",
    "wof:placetype":"venue"
},
  "geometry": {"coordinates":[4.717400074,49.7588005066],"type":"Point"}
}