{
  "type": "Feature",
  "properties": {
    "addr:full":"Viborgvej 36, Daugbjerg Viborg Danmark 8800",
    "addr:housenumber":"36",
    "addr:postcode":"8800",
    "addr:street":"Viborgvej",
    "iso:country":"DK",
    "sg:address":"Viborgvej 36, Daugbjerg",
    "sg:city":"Viborg",
    "sg:orig_category":"Murermestre",
    "sg:phone":"+45 97 54 83 94",
    "sg:postcode":"8800",
    "sg:province":"Danmark",
    "wof:name":"Vesterg\u00e5rd I/S, Ib og Hans",
    "wof:placetype":"venue"
},
  "geometry": {"coordinates":[9.4071502686,56.452671051],"type":"Point"}
}