{
  "type": "Feature",
  "properties": {
    "iso:country":"DK",
    "sg:address":"Industrikrogen 9, Kongsted",
    "sg:city":"R\u00f8nnede",
    "sg:orig_category":"Skoleborde",
    "sg:phone":"+45 56 71 17 54",
    "sg:postcode":"4683",
    "sg:province":"Danmark",
    "sg:website":"www.dica.dk",
    "wof:name":"DICA A/S",
    "wof:placetype":"venue"
},
  "geometry": {"coordinates":[12.040017128,55.2451210022],"type":"Point"}
}