{
  "type": "Feature",
  "properties": {
    "addr:full":"Skiftevej 27 Gentofte Danmark 2820",
    "addr:housenumber":"27",
    "addr:postcode":"2820",
    "addr:street":"Skiftevej",
    "iso:country":"DK",
    "sg:address":"Skiftevej 27",
    "sg:city":"Gentofte",
    "sg:classifiers":[
        {
            "category":"Professional",
            "subcategory":"Computer Services",
            "type":"Services"
        }
    ],
    "sg:phone":"+45 39 56 27 33",
    "sg:postcode":"2820",
    "sg:province":"Danmark",
    "sg:tags":[
        "edb",
        "-",
        "software"
    ],
    "wof:name":"Fix Data ApS",
    "wof:placetype":"venue"
},
  "geometry": {"coordinates":[12.5198287964,55.7416763306],"type":"Point"}
}