{
  "type": "Feature",
  "properties": {
    "addr:full":"Strandvejen 9 Thisted Danmark 7700",
    "addr:housenumber":"9",
    "addr:postcode":"7700",
    "addr:street":"Strandvejen",
    "iso:country":"DK",
    "sg:address":"Strandvejen 9",
    "sg:city":"Thisted",
    "sg:orig_category":"Faglige organisationer og foreninger",
    "sg:phone":"+45 97 91 16 24",
    "sg:postcode":"7700",
    "sg:province":"Danmark",
    "wof:name":"NNF-Nordvest",
    "wof:placetype":"venue"
},
  "geometry": {"coordinates":[8.6991109848,56.9548568726],"type":"Point"}
}