{
  "type": "Feature",
  "properties": {
    "addr:full":"Hammervej 88 Vodskov Danmark 9310",
    "addr:housenumber":"88",
    "addr:postcode":"9310",
    "addr:street":"Hammervej",
    "iso:country":"DK",
    "sg:address":"Hammervej 88",
    "sg:city":"Vodskov",
    "sg:orig_category":"Skolefritidsordninger",
    "sg:phone":"+45 98 28 61 49",
    "sg:postcode":"9310",
    "sg:province":"Danmark",
    "wof:name":"DUS Spor A - Grindsted Skole",
    "wof:placetype":"venue"
},
  "geometry": {"coordinates":[10.0416669846,57.1501579285],"type":"Point"}
}