{
  "type": "Feature",
  "properties": {
    "addr:full":"Valby Langgade 192 Valby Danmark 2500",
    "addr:housenumber":"192",
    "addr:postcode":"2500",
    "addr:street":"Valby Langgade",
    "iso:country":"DK",
    "sg:address":"Valby Langgade 192",
    "sg:city":"Valby",
    "sg:orig_category":"Teatre, Artikler for",
    "sg:phone":"+45 36 46 57 77",
    "sg:postcode":"2500",
    "sg:province":"Danmark",
    "wof:name":"Audilux ApS",
    "wof:placetype":"venue"
},
  "geometry": {"coordinates":[12.4933052063,55.6694717407],"type":"Point"}
}