{
  "type": "Feature",
  "properties": {
    "addr:full":"Ringebyvejen 5, Vestermarie R\u00f8nne Danmark 3700",
    "addr:housenumber":"5",
    "addr:postcode":"3700",
    "addr:street":"Ringebyvejen",
    "iso:country":"DK",
    "sg:address":"Ringebyvejen 5, Vestermarie",
    "sg:city":"R\u00f8nne",
    "sg:orig_category":"Pelsdyravl",
    "sg:phone":"+45 56 99 93 20",
    "sg:postcode":"3700",
    "sg:province":"Danmark",
    "wof:name":"Virkelyst Pelsfarm ApS",
    "wof:placetype":"venue"
},
  "geometry": {"coordinates":[14.6975498199,55.0993003845],"type":"Point"}
}