{
  "type": "Feature",
  "properties": {
    "iso:country":"DK",
    "sg:address":"D\u00e6mningen 23",
    "sg:city":"Vejle",
    "sg:orig_category":"Benzinstationer",
    "sg:phone":"+45 75 83 60 33",
    "sg:postcode":"7100",
    "sg:province":"Danmark",
    "wof:name":"Hydro Texaco Benzin",
    "wof:placetype":"venue"
},
  "geometry": {"coordinates":[9.535642,55.708935],"type":"Point"}
}