{
  "type": "Feature",
  "properties": {
    "addr:full":"Risk\u00e6r 3, Sm\u00f8rumnedre Sm\u00f8rum Danmark 2765",
    "addr:housenumber":"3",
    "addr:postcode":"2765",
    "addr:street":"Riskaer",
    "iso:country":"DK",
    "sg:address":"Risk\u00e6r 3, Sm\u00f8rumnedre",
    "sg:city":"Sm\u00f8rum",
    "sg:orig_category":"Trykkerier",
    "sg:phone":"+45 44 97 10 80",
    "sg:postcode":"2765",
    "sg:province":"Danmark",
    "sg:website":"www.abc-tryk.dk",
    "wof:name":"ABC-Tryk",
    "wof:placetype":"venue"
},
  "geometry": {"coordinates":[-89.9980316162,38.1397895813],"type":"Point"}
}