{
  "type": "Feature",
  "properties": {
    "addr:full":"Navervej 14 Sunds Danmark 7451",
    "addr:housenumber":"14",
    "addr:postcode":"7451",
    "addr:street":"Navervej",
    "iso:country":"DK",
    "sg:address":"Navervej 14",
    "sg:city":"Sunds",
    "sg:orig_category":"Trailere",
    "sg:phone":"+45 97 14 43 33",
    "sg:postcode":"7451",
    "sg:province":"Danmark",
    "wof:name":"Herning Trailercenter",
    "wof:placetype":"venue"
},
  "geometry": {"coordinates":[9.019821167,56.1954154968],"type":"Point"}
}