{
  "type": "Feature",
  "properties": {
    "addr:full":"Stationsvej 3 Stenlille Danmark 4295",
    "addr:housenumber":"3",
    "addr:postcode":"4295",
    "addr:street":"Stationsvej",
    "iso:country":"DK",
    "sg:address":"Stationsvej 3",
    "sg:city":"Stenlille",
    "sg:orig_category":"Maskinfabrikker",
    "sg:phone":"+45 57 80 44 00",
    "sg:postcode":"4295",
    "sg:province":"Danmark",
    "wof:name":"J\u00f8rgensen A/S, Asger G.",
    "wof:placetype":"venue"
},
  "geometry": {"coordinates":[11.5930614471,55.5390014648],"type":"Point"}
}