{
  "type": "Feature",
  "properties": {
    "addr:full":"Bredgade 143 Hurup Danmark 7760",
    "addr:housenumber":"143",
    "addr:postcode":"7760",
    "addr:street":"Bredgade",
    "iso:country":"DK",
    "sg:address":"Bredgade 143",
    "sg:city":"Hurup",
    "sg:orig_category":"Sko",
    "sg:phone":"+45 97 95 12 51",
    "sg:postcode":"7760",
    "sg:province":"Danmark",
    "wof:name":"Kjeld Sko",
    "wof:placetype":"venue"
},
  "geometry": {"coordinates":[8.4191045761,56.7498588562],"type":"Point"}
}