{
  "type": "Feature",
  "properties": {
    "iso:country":"DK",
    "sg:address":"Bernstorffsvej 13 A",
    "sg:city":"Hellerup",
    "sg:orig_category":"\u00c3\u02dcl- og mineralvandsdepoter",
    "sg:phone":"+45 39 61 71 74",
    "sg:postcode":"2900",
    "sg:province":"Danmark",
    "sg:website":"www.danskkildevand.dk",
    "wof:name":"Dansk Kildevand ApS",
    "wof:placetype":"venue"
},
  "geometry": {"coordinates":[12.5546894073,55.72631073],"type":"Point"}
}