{
  "type": "Feature",
  "properties": {
    "iso:country":"DK",
    "sg:address":"Silkeborggade 34, 1. tv.",
    "sg:city":"K\u00f8benhavn \u00d8",
    "sg:orig_category":"Engros handel",
    "sg:phone":"+45 28 40 14 16",
    "sg:postcode":"2100",
    "sg:province":"Danmark",
    "wof:name":"Messina, Morten",
    "wof:placetype":"venue"
},
  "geometry": {"coordinates":[178.69096374509999,-7.4715299606],"type":"Point"}
}