{
  "type": "Feature",
  "properties": {
    "addr:full":"Fmd.: Edith Nielsen, Herredsvej 13 Vamdrup Danmark 6580",
    "addr:housenumber":"13",
    "addr:postcode":"6580",
    "addr:street":"Herredsvej",
    "iso:country":"DK",
    "sg:address":"Fmd.: Edith Nielsen, Herredsvej 13",
    "sg:city":"Vamdrup",
    "sg:orig_category":"\u00c3\u2020ldreorganisationer og klubber",
    "sg:phone":"+45 75 58 14 34",
    "sg:postcode":"6580",
    "sg:province":"Danmark",
    "wof:name":"\u00c6ldres Hyggeeftermiddag",
    "wof:placetype":"venue"
},
  "geometry": {"coordinates":[9.2839107513,55.4266548157],"type":"Point"}
}