{
  "type": "Feature",
  "properties": {
    "addr:full":"Fmd.: Bjarne S\u00f8rensen, \u00d8lstrupvej 47, \u00d8lstrup Ringk\u00f8bing Danmark 6950",
    "addr:housenumber":"47",
    "addr:postcode":"6950",
    "addr:street":"Bjarne;Olstrupvej",
    "iso:country":"DK",
    "sg:address":"Fmd.: Bjarne S\u00f8rensen, \u00d8lstrupvej 47, \u00d8lstrup",
    "sg:city":"Ringk\u00f8bing",
    "sg:orig_category":"Borger- og beboerforeninger",
    "sg:phone":"+45 97 34 62 60",
    "sg:postcode":"6950",
    "sg:province":"Danmark",
    "wof:name":"\u00d8lstrup Sogneforening",
    "wof:placetype":"venue"
},
  "geometry": {"coordinates":[-114.0767440796,46.4432487488],"type":"Point"}
}