{
  "type": "Feature",
  "properties": {
    "addr:full":"Bavnevej 27 A Hvidovre Danmark 2650",
    "addr:housenumber":"27 a",
    "addr:postcode":"2650",
    "addr:street":"Bavnevej",
    "iso:country":"DK",
    "sg:address":"Bavnevej 27 A",
    "sg:city":"Hvidovre",
    "sg:orig_category":"Revisorer",
    "sg:phone":"+45 36 77 83 50",
    "sg:postcode":"2650",
    "sg:province":"Danmark",
    "wof:name":"Nielsen, Bent Erik",
    "wof:placetype":"venue"
},
  "geometry": {"coordinates":[12.4902334213,55.6233596802],"type":"Point"}
}