{
  "type": "Feature",
  "properties": {
    "addr:full":"Kildemosevej 12 A Esperg\u00e6rde Danmark 3060",
    "addr:housenumber":"12 a",
    "addr:postcode":"3060",
    "addr:street":"Kildemosevej",
    "iso:country":"DK",
    "sg:address":"Kildemosevej 12 A",
    "sg:city":"Esperg\u00e6rde",
    "sg:orig_category":"Snedkermestre",
    "sg:phone":"+45 49 13 63 03",
    "sg:postcode":"3060",
    "sg:province":"Danmark",
    "wof:name":"Albertsen, Karsten",
    "wof:placetype":"venue"
},
  "geometry": {"coordinates":[11.6512403488,47.8390617371],"type":"Point"}
}