{
  "type": "Feature",
  "properties": {
    "addr:full":"Fmd.: Jens Ullits Larsen, N\u00f8rb\u00e6ksgade 14 Nibe Danmark 9240",
    "addr:housenumber":"14",
    "addr:postcode":"9240",
    "addr:street":"Norbaeksgade",
    "iso:country":"DK",
    "sg:address":"Fmd.: Jens Ullits Larsen, N\u00f8rb\u00e6ksgade 14",
    "sg:city":"Nibe",
    "sg:orig_category":"Faglige organisationer og foreninger",
    "sg:phone":"+45 98 35 22 86",
    "sg:postcode":"9240",
    "sg:province":"Danmark",
    "wof:name":"Nibe Arbejderforening",
    "wof:placetype":"venue"
},
  "geometry": {"coordinates":[9.6393280029,56.982421875],"type":"Point"}
}