{
  "type": "Feature",
  "properties": {
    "addr:full":"G\u00e6rumvej 54 Frederikshavn Danmark 9900",
    "addr:housenumber":"54",
    "addr:postcode":"9900",
    "addr:street":"Gaerumvej",
    "iso:country":"DK",
    "sg:address":"G\u00e6rumvej 54",
    "sg:city":"Frederikshavn",
    "sg:orig_category":"Autoreparation og -service",
    "sg:phone":"+45 98 42 76 78",
    "sg:postcode":"9900",
    "sg:province":"Danmark",
    "wof:name":"G\u00e6rumvejens Auto",
    "wof:placetype":"venue"
},
  "geometry": {"coordinates":[10.5103302002,57.4273719788],"type":"Point"}
}