{
  "type": "Feature",
  "properties": {
    "iso:country":"DK",
    "sg:address":"Lodsvej 27",
    "sg:city":"Hals",
    "sg:orig_category":"Lodseri",
    "sg:phone":"+45 98 25 10 06",
    "sg:postcode":"9370",
    "sg:province":"Danmark",
    "wof:name":"Limfjorden Lodseri",
    "wof:placetype":"venue"
},
  "geometry": {"coordinates":[10.3087739944,56.9900856018],"type":"Point"}
}