{
  "type": "Feature",
  "properties": {
    "addr:full":"Havnevej 18 Nyk\u00f8bing Danmark 4500",
    "addr:housenumber":"18",
    "addr:postcode":"4500",
    "addr:street":"Havnevej",
    "iso:country":"DK",
    "sg:address":"Havnevej 18",
    "sg:city":"Nyk\u00f8bing",
    "sg:orig_category":"\u00c3\u02dcvrige skoler",
    "sg:phone":"+45 59 91 04 50",
    "sg:postcode":"4500",
    "sg:province":"Danmark",
    "wof:name":"Skolen p\u00e5 Molen",
    "wof:placetype":"venue"
},
  "geometry": {"coordinates":[16.0969600677,78.3159866333],"type":"Point"}
}