{
  "type": "Feature",
  "properties": {
    "addr:full":"Odinvej 5 Stoholm Danmark 7850",
    "addr:housenumber":"5",
    "addr:postcode":"7850",
    "addr:street":"Odinvej",
    "iso:country":"DK",
    "sg:address":"Odinvej 5",
    "sg:city":"Stoholm",
    "sg:orig_category":"Autoreparation og -service",
    "sg:phone":"+45 97 54 12 27",
    "sg:postcode":"7850",
    "sg:province":"Danmark",
    "wof:name":"Stoholm Autov\u00e6rksted ApS",
    "wof:placetype":"venue"
},
  "geometry": {"coordinates":[9.148730278,56.4856910706],"type":"Point"}
}