{
  "type": "Feature",
  "properties": {
    "iso:country":"DK",
    "sg:address":"Lunikvej 24 E",
    "sg:city":"Greve",
    "sg:orig_category":"Billard",
    "sg:phone":"+45 43 60 11 88",
    "sg:postcode":"2670",
    "sg:province":"Danmark",
    "wof:name":"ABC Billard Service",
    "wof:placetype":"venue"
},
  "geometry": {"coordinates":[12.294181,55.584408],"type":"Point"}
}