{
  "type": "Feature",
  "properties": {
    "addr:full":"Dyssev\u00e6nget 4 Assens Danmark 5610",
    "addr:housenumber":"4",
    "addr:postcode":"5610",
    "addr:street":"Dyssevaenget",
    "iso:country":"DK",
    "sg:address":"Dyssev\u00e6nget 4",
    "sg:city":"Assens",
    "sg:classifiers":[
        {
            "category":"Taxi",
            "type":"Transportation"
        }
    ],
    "sg:phone":"+45 64 71 45 40",
    "sg:postcode":"5610",
    "sg:province":"Danmark",
    "wof:name":"L\u00e6gteskov, Leif",
    "wof:placetype":"venue"
},
  "geometry": {"coordinates":[9.8998937607,55.2702522278],"type":"Point"}
}