{
  "type": "Feature",
  "properties": {
    "addr:full":"Madevej 9 Aabenraa Danmark 6200",
    "addr:housenumber":"9",
    "addr:postcode":"6200",
    "addr:street":"Madevej",
    "iso:country":"DK",
    "sg:address":"Madevej 9",
    "sg:city":"Aabenraa",
    "sg:orig_category":"Konsulentvirksomheder",
    "sg:phone":"+45 74 62 99 23",
    "sg:postcode":"6200",
    "sg:province":"Danmark",
    "wof:name":"K2-Consult",
    "wof:placetype":"venue"
},
  "geometry": {"coordinates":[9.4204702377,55.0435523987],"type":"Point"}
}