{
  "type": "Feature",
  "properties": {
    "addr:full":"Bagg\u00e5rde 7, Ommel Marstal Danmark 5960",
    "addr:housenumber":"7",
    "addr:postcode":"5960",
    "addr:street":"Baggaarde",
    "iso:country":"DK",
    "sg:address":"Bagg\u00e5rde 7, Ommel",
    "sg:city":"Marstal",
    "sg:orig_category":"Murermestre",
    "sg:phone":"+45 62 53 19 97",
    "sg:postcode":"5960",
    "sg:province":"Danmark",
    "wof:name":"Andersen, Murermester Helmuth",
    "wof:placetype":"venue"
},
  "geometry": {"coordinates":[10.5212097168,54.8543815613],"type":"Point"}
}