{
  "type": "Feature",
  "properties": {
    "addr:full":"T\u00e5stumv\u00e6nget 17 Tilst Danmark 8381",
    "addr:housenumber":"17",
    "addr:postcode":"8381",
    "addr:street":"Taastumvaenget",
    "iso:country":"DK",
    "sg:address":"T\u00e5stumv\u00e6nget 17",
    "sg:city":"Tilst",
    "sg:orig_category":"Fotografer",
    "sg:phone":"+45 86 24 70 00",
    "sg:postcode":"8381",
    "sg:province":"Danmark",
    "wof:name":"Knud E Reklamefotografi",
    "wof:placetype":"venue"
},
  "geometry": {"coordinates":[10.1078147888,56.1882019043],"type":"Point"}
}