{
  "type": "Feature",
  "properties": {
    "addr:full":"N\u00f8rregade 22 E K\u00f8ge Danmark 4600",
    "addr:housenumber":"22 e",
    "addr:postcode":"4600",
    "addr:street":"Norregade",
    "iso:country":"DK",
    "sg:address":"N\u00f8rregade 22 E",
    "sg:city":"K\u00f8ge",
    "sg:orig_category":"Netcafeer",
    "sg:phone":"+45 56 65 10 10",
    "sg:postcode":"4600",
    "sg:province":"Danmark",
    "sg:website":"www.pc-junglen.dk",
    "wof:name":"PC-Junglen",
    "wof:placetype":"venue"
},
  "geometry": {"coordinates":[12.183713913,55.458152771],"type":"Point"}
}