{
  "type": "Feature",
  "properties": {
    "addr:full":"H\u00e5rbyvej 10 B, H\u00e5rby Skanderborg Danmark 8660",
    "addr:housenumber":"10 b",
    "addr:postcode":"8660",
    "addr:street":"Haarbyvej",
    "iso:country":"DK",
    "sg:address":"H\u00e5rbyvej 10 B, H\u00e5rby",
    "sg:city":"Skanderborg",
    "sg:orig_category":"\u00c3\u2020ldreorganisationer og klubber",
    "sg:phone":"+45 86 52 34 37",
    "sg:postcode":"8660",
    "sg:province":"Danmark",
    "wof:name":"\u00c6ldre- og Handicapr\u00e5det",
    "wof:placetype":"venue"
},
  "geometry": {"coordinates":[9.929974556,56.0380249023],"type":"Point"}
}