{
  "type": "Feature",
  "properties": {
    "addr:full":"Anne Marie Vej 15 Fuglebjerg Danmark 4250",
    "addr:housenumber":"15",
    "addr:postcode":"4250",
    "addr:street":"Anne Marie Vej",
    "iso:country":"DK",
    "sg:address":"Anne Marie Vej 15",
    "sg:city":"Fuglebjerg",
    "sg:classifiers":[
        {
            "category":"Taxi",
            "type":"Transportation"
        }
    ],
    "sg:phone":"+45 55 45 40 22",
    "sg:postcode":"4250",
    "sg:province":"Danmark",
    "wof:name":"Fuglebjerg Taxi",
    "wof:placetype":"venue"
},
  "geometry": {"coordinates":[11.5510063171,55.3031387329],"type":"Point"}
}