{
  "type": "Feature",
  "properties": {
    "addr:full":"G\u00e5sk\u00e6rgade 42 Haderslev Danmark 6100",
    "addr:housenumber":"42",
    "addr:postcode":"6100",
    "addr:street":"Gaaskaergade",
    "iso:country":"DK",
    "sg:address":"G\u00e5sk\u00e6rgade 42",
    "sg:city":"Haderslev",
    "sg:orig_category":"Faglige organisationer og foreninger",
    "sg:phone":"+45 74 53 07 34",
    "sg:postcode":"6100",
    "sg:province":"Danmark",
    "wof:name":"Arbejdsl\u00f8shedskassen for Selvst. Erhvervsdrivende",
    "wof:placetype":"venue"
},
  "geometry": {"coordinates":[9.4879703522,55.2505493164],"type":"Point"}
}