{
  "type": "Feature",
  "properties": {
    "iso:country":"DK",
    "sg:address":"Storegade 12",
    "sg:city":"Bjerringbro",
    "sg:classifiers":[
        {
            "category":"Banks & Credit Unions",
            "subcategory":"Bank",
            "type":"Services"
        }
    ],
    "sg:phone":"+45 86 68 15 22",
    "sg:postcode":"8850",
    "sg:province":"Danmark",
    "sg:tags":[
        "banker"
    ],
    "wof:name":"Nordea",
    "wof:placetype":"venue"
},
  "geometry": {"coordinates":[9.6565246582,56.3746147156],"type":"Point"}
}