{
  "type": "Feature",
  "properties": {
    "addr:full":"Langelandsgade 193 \u00c5rhus N Danmark 8200",
    "addr:housenumber":"193",
    "addr:postcode":"8200",
    "addr:street":"Langelandsgade",
    "iso:country":"DK",
    "sg:address":"Langelandsgade 193",
    "sg:city":"\u00c5rhus N",
    "sg:classifiers":[
        {
            "category":"Arts & Performance",
            "subcategory":"Arts Center",
            "type":"Entertainment"
        }
    ],
    "sg:phone":"+45 86 16 90 63",
    "sg:postcode":"8200",
    "sg:province":"Danmark",
    "sg:tags":[
        "patchwork"
    ],
    "wof:name":"Kreativ H\u00e5ndarbejde",
    "wof:placetype":"venue"
},
  "geometry": {"coordinates":[-112.59702301030001,36.6954040527],"type":"Point"}
}