{
  "type": "Feature",
  "properties": {
    "addr:full":"Barsmark Bygade 232 Aabenraa Danmark 6200",
    "addr:housenumber":"232",
    "addr:postcode":"6200",
    "addr:street":"Barsmark Bygade",
    "iso:country":"DK",
    "sg:address":"Barsmark Bygade 232",
    "sg:city":"Aabenraa",
    "sg:orig_category":"Beslagsmede",
    "sg:phone":"+45 74 61 82 02",
    "sg:postcode":"6200",
    "sg:province":"Danmark",
    "wof:name":"Smedjeriet",
    "wof:placetype":"venue"
},
  "geometry": {"coordinates":[9.477536,55.091068],"type":"Point"}
}