{
  "type": "Feature",
  "properties": {
    "iso:country":"DK",
    "sg:address":"Rahbeksvej 3",
    "sg:city":"Odense M",
    "sg:orig_category":"Isolering",
    "sg:phone":"+45 66 11 64 30",
    "sg:postcode":"5230",
    "sg:province":"Danmark",
    "sg:website":"www.lyac.dk",
    "wof:name":"Lydac Akustik ApS",
    "wof:placetype":"venue"
},
  "geometry": {"coordinates":[10.3921260834,55.3797683716],"type":"Point"}
}