{
  "type": "Feature",
  "properties": {
    "addr:full":"Frisegade 10 Nyk\u00f8bing Danmark 4800",
    "addr:housenumber":"10",
    "addr:postcode":"4800",
    "addr:street":"Frisegade",
    "iso:country":"DK",
    "sg:address":"Frisegade 10",
    "sg:city":"Nyk\u00f8bing",
    "sg:classifiers":[
        {
            "category":"Restaurant",
            "type":"Food & Drink"
        }
    ],
    "sg:phone":"+45 54 82 20 02",
    "sg:postcode":"4800",
    "sg:province":"Danmark",
    "sg:website":"www.koekkenartisten.dk",
    "wof:name":"Liva",
    "wof:placetype":"venue"
},
  "geometry": {"coordinates":[-114.0768203735,46.4432411194],"type":"Point"}
}