{
  "type": "Feature",
  "properties": {
    "addr:full":"\u00d8ster\u00e5gade 16 Aalborg Danmark 9000",
    "addr:housenumber":"16",
    "addr:postcode":"9000",
    "addr:street":"Osteraagade",
    "iso:country":"DK",
    "sg:address":"\u00d8ster\u00e5gade 16",
    "sg:city":"Aalborg",
    "sg:orig_category":"Garn",
    "sg:phone":"+45 98 16 03 34",
    "sg:postcode":"9000",
    "sg:province":"Danmark",
    "wof:name":"Madam Strik",
    "wof:placetype":"venue"
},
  "geometry": {"coordinates":[9.9222307205,57.049282074],"type":"Point"}
}