{
  "type": "Feature",
  "properties": {
    "addr:full":"Gadevangsvej 145, Gadevang Hiller\u00f8d Danmark 3400",
    "addr:housenumber":"145",
    "addr:postcode":"3400",
    "addr:street":"Gadevangsvej;Gadevang Hillerod Danmark",
    "iso:country":"DK",
    "sg:address":"Gadevangsvej 145, Gadevang",
    "sg:city":"Hiller\u00f8d",
    "sg:orig_category":"Forsamlingshuse",
    "sg:phone":"+45 48 24 66 86",
    "sg:postcode":"3400",
    "sg:province":"Danmark",
    "wof:name":"Gadevang Forsamlingshus",
    "wof:placetype":"venue"
},
  "geometry": {"coordinates":[12.3056097031,55.9288215637],"type":"Point"}
}