{
  "type": "Feature",
  "properties": {
    "addr:full":"Rosenv\u00e6nget 23, St. Nyk\u00f8bing Danmark 4800",
    "addr:housenumber":"23",
    "addr:postcode":"4800",
    "addr:street":"Rosenvaenget",
    "iso:country":"DK",
    "sg:address":"Rosenv\u00e6nget 23, St.",
    "sg:city":"Nyk\u00f8bing",
    "sg:orig_category":"Faglige organisationer og foreninger",
    "sg:phone":"+45 54 84 00 60",
    "sg:postcode":"4800",
    "sg:province":"Danmark",
    "wof:name":"Dansk Sygeplejer\u00e5ds Amtskreds",
    "wof:placetype":"venue"
},
  "geometry": {"coordinates":[-114.0768203735,46.4432411194],"type":"Point"}
}