{
  "type": "Feature",
  "properties": {
    "addr:full":"v/ Janne Hedegaard, \u00d8land Bro Vej 2 Snedsted Danmark 7752",
    "addr:housenumber":"2",
    "addr:postcode":"7752",
    "addr:street":"Oland Bro Vej",
    "iso:country":"DK",
    "sg:address":"v/ Janne Hedegaard, \u00d8land Bro Vej 2",
    "sg:city":"Snedsted",
    "sg:orig_category":"\u00c3\u2020ldreorganisationer og klubber",
    "sg:phone":"+45 97 93 44 21",
    "sg:postcode":"7752",
    "sg:province":"Danmark",
    "wof:name":"Pensionistforeningen for Snedsted og omegn",
    "wof:placetype":"venue"
},
  "geometry": {"coordinates":[8.5276002884,56.8460388184],"type":"Point"}
}