{
  "type": "Feature",
  "properties": {
    "addr:full":"Fmd: Gunnar Stenb\u00e6k, S\u00f8nderlundsvej 67 Roskilde Danmark 4000",
    "addr:housenumber":"67",
    "addr:postcode":"4000",
    "addr:street":"Sonderlundsvej",
    "iso:country":"DK",
    "sg:address":"Fmd: Gunnar Stenb\u00e6k, S\u00f8nderlundsvej 67",
    "sg:city":"Roskilde",
    "sg:orig_category":"\u00c3\u2020ldreorganisationer og klubber",
    "sg:phone":"+45 46 35 48 77",
    "sg:postcode":"4000",
    "sg:province":"Danmark",
    "wof:name":"Roskilde \u00c6ldre Motion",
    "wof:placetype":"venue"
},
  "geometry": {"coordinates":[12.0909376144,55.6404838562],"type":"Point"}
}