{
  "type": "Feature",
  "properties": {
    "addr:full":"Enghaven 2 Asn\u00e6s Danmark 4550",
    "addr:housenumber":"2",
    "addr:postcode":"4550",
    "addr:street":"Enghaven",
    "iso:country":"DK",
    "sg:address":"Enghaven 2",
    "sg:city":"Asn\u00e6s",
    "sg:orig_category":"Grundejerforeninger",
    "sg:phone":"+45 59 65 13 25",
    "sg:postcode":"4550",
    "sg:province":"Danmark",
    "wof:name":"Asn\u00e6s By's Grundejerforening",
    "wof:placetype":"venue"
},
  "geometry": {"coordinates":[-80.0115890503,40.2900466919],"type":"Point"}
}