{
  "type": "Feature",
  "properties": {
    "addr:full":"N\u00f8rregade 67 K\u00f8ge Danmark 4600",
    "addr:housenumber":"67",
    "addr:postcode":"4600",
    "addr:street":"Norregade",
    "iso:country":"DK",
    "sg:address":"N\u00f8rregade 67",
    "sg:city":"K\u00f8ge",
    "sg:orig_category":"Autoreparation og -service",
    "sg:phone":"+45 56 65 91 28",
    "sg:postcode":"4600",
    "sg:province":"Danmark",
    "wof:name":"Peter's Auto",
    "wof:placetype":"venue"
},
  "geometry": {"coordinates":[12.1827278137,55.456615448],"type":"Point"}
}