{
  "type": "Feature",
  "properties": {
    "addr:full":"Jernbanevej 6 Ringsted Danmark 4100",
    "addr:housenumber":"6",
    "addr:postcode":"4100",
    "addr:street":"Jernbanevej",
    "iso:country":"DK",
    "sg:address":"Jernbanevej 6",
    "sg:city":"Ringsted",
    "sg:orig_category":"\u00c3\u02dcvrige institutioner",
    "sg:phone":"+45 57 62 79 55",
    "sg:postcode":"4100",
    "sg:province":"Danmark",
    "wof:name":"Bof\u00e6llesskab I og II",
    "wof:placetype":"venue"
},
  "geometry": {"coordinates":[11.790602684,55.4386405945],"type":"Point"}
}