{
  "type": "Feature",
  "properties": {
    "addr:full":"Torvet 1 B Nibe Danmark 9240",
    "addr:housenumber":"1 b",
    "addr:postcode":"9240",
    "addr:street":"Torvet",
    "iso:country":"DK",
    "sg:address":"Torvet 1 B",
    "sg:city":"Nibe",
    "sg:classifiers":[
        {
            "category":"Restaurant",
            "type":"Food & Drink"
        }
    ],
    "sg:phone":"+45 98 35 33 33",
    "sg:postcode":"9240",
    "sg:province":"Danmark",
    "wof:name":"Torvecaf\u00e9en",
    "wof:placetype":"venue"
},
  "geometry": {"coordinates":[9.6394309998,56.9825248718],"type":"Point"}
}