{
  "type": "Feature",
  "properties": {
    "addr:full":"Vestergade 1 Haslev Danmark 4690",
    "addr:housenumber":"1",
    "addr:postcode":"4690",
    "addr:street":"Vestergade",
    "iso:country":"DK",
    "sg:address":"Vestergade 1",
    "sg:city":"Haslev",
    "sg:orig_category":"Pizzeriaer",
    "sg:phone":"+45 56 31 00 85",
    "sg:postcode":"4690",
    "sg:province":"Danmark",
    "wof:name":"Rey Pizzeria & Burger House",
    "wof:placetype":"venue"
},
  "geometry": {"coordinates":[11.9629564285,55.3268127441],"type":"Point"}
}