{
  "type": "Feature",
  "properties": {
    "iso:country":"DK",
    "sg:address":"Fmd.: Else Bloch Larsen, F\u00e5borgvej 12, Heden",
    "sg:city":"Ringe",
    "sg:orig_category":"Kulturelle foreninger",
    "sg:phone":"+45 62 66 13 47",
    "sg:postcode":"5750",
    "sg:province":"Danmark",
    "wof:name":"KULU - Kvindernes U-Landsudvalg",
    "wof:placetype":"venue"
},
  "geometry": {"coordinates":[10.4781074524,55.2356643677],"type":"Point"}
}