{
  "type": "Feature",
  "properties": {
    "addr:full":"Faurskovvej 3, Balle Hadsten Danmark 8370",
    "addr:housenumber":"3",
    "addr:postcode":"8370",
    "addr:street":"Faurskovvej",
    "iso:country":"DK",
    "sg:address":"Faurskovvej 3, Balle",
    "sg:city":"Hadsten",
    "sg:orig_category":"Maskinstationer",
    "sg:phone":"+45 86 98 17 68",
    "sg:postcode":"8370",
    "sg:province":"Danmark",
    "wof:name":"Maskinstationen",
    "wof:placetype":"venue"
},
  "geometry": {"coordinates":[10.047659874,56.3287239075],"type":"Point"}
}