{
  "type": "Feature",
  "properties": {
    "addr:full":"Jernbaneg. 4  Haderslev Danmark 6100",
    "addr:housenumber":"4",
    "addr:postcode":"6100",
    "addr:street":"Jernbaneg.",
    "iso:country":"DK",
    "sg:address":"Jernbaneg. 4 ",
    "sg:city":"Haderslev",
    "sg:classifiers":[
        {
            "category":"Parking",
            "subcategory":"Lot",
            "type":"Transportation"
        }
    ],
    "sg:phone":"+45 74 52 11 63",
    "sg:postcode":"6100",
    "sg:province":"Danmark",
    "sg:tags":[
        "transport",
        "road"
    ],
    "wof:name":"GODSTRANSPORT E. SCHONDELMEIER APS",
    "wof:placetype":"venue"
},
  "geometry": {"coordinates":[9.4746923447,55.2521743774],"type":"Point"}
}