{
  "type": "Feature",
  "properties": {
    "addr:full":"Sankt Ibs Vej 1 Roskilde Danmark 4000",
    "addr:housenumber":"1",
    "addr:postcode":"4000",
    "addr:street":"Sankt Ibs Vej",
    "iso:country":"DK",
    "sg:address":"Sankt Ibs Vej 1",
    "sg:city":"Roskilde",
    "sg:orig_category":"Kirker",
    "sg:postcode":"4000",
    "sg:province":"Danmark",
    "wof:name":"Sankt Ibs Kirke",
    "wof:placetype":"venue"
},
  "geometry": {"coordinates":[12.0832643509,55.6471939087],"type":"Point"}
}