{
  "type": "Feature",
  "properties": {
    "addr:full":"Thrigesvej 8 - 16 Ikast Danmark 7430",
    "addr:housenumber":"8 16",
    "addr:postcode":"7430",
    "addr:street":"Thrigesvej",
    "iso:country":"DK",
    "sg:address":"Thrigesvej 8 - 16",
    "sg:city":"Ikast",
    "sg:orig_category":"Listefabrikker",
    "sg:phone":"+45 97 25 07 66",
    "sg:postcode":"7430",
    "sg:province":"Danmark",
    "wof:name":"Skovhus A/S",
    "wof:placetype":"venue"
},
  "geometry": {"coordinates":[9.1434583664,56.1241874695],"type":"Point"}
}