{
  "type": "Feature",
  "properties": {
    "addr:full":"Sognepr\u00e6st: B\u00f8rge E. Sveigaard (K/B), Pr\u00e6stelundsvej 3, Marvede N\u00e6stved Danmark 4700",
    "addr:housenumber":"3",
    "addr:postcode":"4700",
    "addr:street":"Praestelundsvej",
    "iso:country":"DK",
    "sg:address":"Sognepr\u00e6st: B\u00f8rge E. Sveigaard (K/B), Pr\u00e6stelundsvej 3, Marvede",
    "sg:city":"N\u00e6stved",
    "sg:orig_category":"Kirkesogne",
    "sg:phone":"+45 55 44 30 67",
    "sg:postcode":"4700",
    "sg:province":"Danmark",
    "wof:name":"Marvede og Hyllinge sogne",
    "wof:placetype":"venue"
},
  "geometry": {"coordinates":[11.7542486191,55.2315444946],"type":"Point"}
}