{
  "type": "Feature",
  "properties": {
    "addr:full":"Overgade 49 Odense C Danmark 5000",
    "addr:housenumber":"49",
    "addr:postcode":"5000",
    "addr:street":"Overgade",
    "iso:country":"DK",
    "sg:address":"Overgade 49",
    "sg:city":"Odense C",
    "sg:orig_category":"Trikotage",
    "sg:phone":"+45 66 12 66 88",
    "sg:postcode":"5000",
    "sg:province":"Danmark",
    "wof:name":"Spar Trikotage",
    "wof:placetype":"venue"
},
  "geometry": {"coordinates":[10.3937501907,55.3977661133],"type":"Point"}
}