{
  "type": "Feature",
  "properties": {
    "addr:full":"v/ Kaj Bredahl J\u00f8rgensen, Tavleager 31 Greve Danmark 2670",
    "addr:housenumber":"31",
    "addr:postcode":"2670",
    "addr:street":"Bredahl;Tavleager",
    "iso:country":"DK",
    "sg:address":"v/ Kaj Bredahl J\u00f8rgensen, Tavleager 31",
    "sg:city":"Greve",
    "sg:orig_category":"\u00c3\u02dcvrige foreninger",
    "sg:phone":"+45 43 90 29 00",
    "sg:postcode":"2670",
    "sg:province":"Danmark",
    "wof:name":"Danish Shortwave Club Int.",
    "wof:placetype":"venue"
},
  "geometry": {"coordinates":[12.2941808701,55.5844078064],"type":"Point"}
}