{
  "type": "Feature",
  "properties": {
    "addr:full":"P\u00e5rupvej 25 B, Skellerup Ullerslev Danmark 5540",
    "addr:housenumber":"25 b",
    "addr:postcode":"5540",
    "addr:street":"Paarupvej;Skellerup",
    "iso:country":"DK",
    "sg:address":"P\u00e5rupvej 25 B, Skellerup",
    "sg:city":"Ullerslev",
    "sg:orig_category":"Sammensatte institutioner",
    "sg:phone":"+45 63 35 12 60",
    "sg:postcode":"5540",
    "sg:province":"Danmark",
    "wof:name":"Spiloppen - Skellerup Skole",
    "wof:placetype":"venue"
},
  "geometry": {"coordinates":[10.6675348282,55.3605728149],"type":"Point"}
}