{
  "type": "Feature",
  "properties": {
    "addr:full":"Vinkelvej 60, Bruunsh\u00e5b Viborg Danmark 8800",
    "addr:housenumber":"60",
    "addr:postcode":"8800",
    "addr:street":"Vinkelvej;Bruunshaab",
    "iso:country":"DK",
    "sg:address":"Vinkelvej 60, Bruunsh\u00e5b",
    "sg:city":"Viborg",
    "sg:orig_category":"Musikere",
    "sg:phone":"+45 86 67 21 17",
    "sg:postcode":"8800",
    "sg:province":"Danmark",
    "wof:name":"Treoband",
    "wof:placetype":"venue"
},
  "geometry": {"coordinates":[9.4071502686,56.452671051],"type":"Point"}
}