{
  "type": "Feature",
  "properties": {
    "addr:full":"Tyge Brahes Vej 43 Aalborg Danmark 9000",
    "addr:housenumber":"43",
    "addr:postcode":"9000",
    "addr:street":"Tyge Brahes Vej",
    "iso:country":"DK",
    "sg:address":"Tyge Brahes Vej 43",
    "sg:city":"Aalborg",
    "sg:orig_category":"Murermestre",
    "sg:phone":"+45 40 52 57 01",
    "sg:postcode":"9000",
    "sg:province":"Danmark",
    "wof:name":"Rosenkilde, Murer- og Byggefirmaet Jens",
    "wof:placetype":"venue"
},
  "geometry": {"coordinates":[9.9103116989,57.0340309143],"type":"Point"}
}