{
  "type": "Feature",
  "properties": {
    "addr:full":"Engdalsvej 61 Brabrand Danmark 8220",
    "addr:housenumber":"61",
    "addr:postcode":"8220",
    "addr:street":"Engdalsvej",
    "iso:country":"DK",
    "sg:address":"Engdalsvej 61",
    "sg:city":"Brabrand",
    "sg:orig_category":"Revisorer",
    "sg:phone":"+45 86 26 30 99",
    "sg:postcode":"8220",
    "sg:province":"Danmark",
    "wof:name":"Krabbe, Henning",
    "wof:placetype":"venue"
},
  "geometry": {"coordinates":[10.1186246872,56.1506118774],"type":"Point"}
}