{
  "type": "Feature",
  "properties": {
    "iso:country":"DK",
    "sg:address":"Roskildevej 325 A ",
    "sg:city":"Taastrup",
    "sg:classifiers":[
        {
            "category":"Banks & Credit Unions",
            "subcategory":"Investment Brokerage",
            "type":"Services"
        }
    ],
    "sg:phone":"+45 43 52 52 77",
    "sg:postcode":"2630",
    "sg:province":"Danmark",
    "sg:tags":[
        "-",
        "transport",
        "related"
    ],
    "wof:name":"POST DANMARK NORDSJ\u00c6LLANDS POSTCENTER",
    "wof:placetype":"venue"
},
  "geometry": {"coordinates":[12.2543735504,55.6539268494],"type":"Point"}
}