{
  "type": "Feature",
  "properties": {
    "addr:full":"K\u00f8benhavnsvej 239 K\u00f8ge Danmark 4600",
    "addr:housenumber":"239",
    "addr:postcode":"4600",
    "addr:street":"Kobenhavnsvej",
    "iso:country":"DK",
    "sg:address":"K\u00f8benhavnsvej 239",
    "sg:city":"K\u00f8ge",
    "sg:orig_category":"Autoforhandlere",
    "sg:phone":"+45 56 65 40 54",
    "sg:postcode":"4600",
    "sg:province":"Danmark",
    "sg:website":"www.espensen-auto.dk",
    "wof:name":"Espensen Autmobiler",
    "wof:placetype":"venue"
},
  "geometry": {"coordinates":[121.35167694090001,24.9587898254],"type":"Point"}
}