{
  "type": "Feature",
  "properties": {
    "addr:full":"Glasmagervej 20, Fensmark N\u00e6stved Danmark 4700",
    "addr:housenumber":"20",
    "addr:postcode":"4700",
    "addr:street":"Glasmagervej",
    "iso:country":"DK",
    "sg:address":"Glasmagervej 20, Fensmark",
    "sg:city":"N\u00e6stved",
    "sg:orig_category":"Teltudlejning",
    "sg:phone":"+45 55 54 66 27",
    "sg:postcode":"4700",
    "sg:province":"Danmark",
    "wof:name":"Pedersen, A.A.",
    "wof:placetype":"venue"
},
  "geometry": {"coordinates":[11.7542486191,55.2315444946],"type":"Point"}
}