{
  "type": "Feature",
  "properties": {
    "addr:full":"Tingh\u00f8jvej 48, Vinstrup Havndal Danmark 8970",
    "addr:housenumber":"48",
    "addr:postcode":"8970",
    "addr:street":"Tinghojvej",
    "iso:country":"DK",
    "sg:address":"Tingh\u00f8jvej 48, Vinstrup",
    "sg:city":"Havndal",
    "sg:orig_category":"Autoforhandlere",
    "sg:phone":"+45 86 47 32 07",
    "sg:postcode":"8970",
    "sg:province":"Danmark",
    "wof:name":"Schmidt, Hans",
    "wof:placetype":"venue"
},
  "geometry": {"coordinates":[10.1937646866,56.6534461975],"type":"Point"}
}