{
  "type": "Feature",
  "properties": {
    "addr:full":"Fmd.: Martin Nissen, Vesteralle 48, Laurbjerg Lang\u00e5 Danmark 8870",
    "addr:housenumber":"48",
    "addr:postcode":"8870",
    "addr:street":"Vesteralle",
    "iso:country":"DK",
    "sg:address":"Fmd.: Martin Nissen, Vesteralle 48, Laurbjerg",
    "sg:city":"Lang\u00e5",
    "sg:orig_category":"Hobbybetonede foreninger",
    "sg:phone":"+45 86 46 84 27",
    "sg:postcode":"8870",
    "sg:province":"Danmark",
    "wof:name":"Lang\u00e5 B\u00e5delaug",
    "wof:placetype":"venue"
},
  "geometry": {"coordinates":[9.8955049515,56.3900756836],"type":"Point"}
}