{
  "type": "Feature",
  "properties": {
    "addr:full":"Markedsvej 19 Aars Danmark 9600",
    "addr:housenumber":"19",
    "addr:postcode":"9600",
    "addr:street":"Markedsvej",
    "iso:country":"DK",
    "sg:address":"Markedsvej 19",
    "sg:city":"Aars",
    "sg:orig_category":"Bedriftssundhedstjenester",
    "sg:phone":"+45 98 62 41 66",
    "sg:postcode":"9600",
    "sg:province":"Danmark",
    "sg:website":"www.bst-vesthimmerland.dk",
    "wof:name":"Vesthimmerlands BST",
    "wof:placetype":"venue"
},
  "geometry": {"coordinates":[9.5059213638,56.7972946167],"type":"Point"}
}