{
  "type": "Feature",
  "properties": {
    "addr:full":"Dagstrupvej 23, Dagstrup M\u00f8rke Danmark 8544",
    "addr:housenumber":"23",
    "addr:postcode":"8544",
    "addr:street":"Dagstrupvej",
    "iso:country":"DK",
    "sg:address":"Dagstrupvej 23, Dagstrup",
    "sg:city":"M\u00f8rke",
    "sg:orig_category":"Maskintransport",
    "sg:phone":"+45 86 37 76 33",
    "sg:postcode":"8544",
    "sg:province":"Danmark",
    "wof:name":"Bech ApS, Per",
    "wof:placetype":"venue"
},
  "geometry": {"coordinates":[10.2458581924,56.3858413696],"type":"Point"}
}