{
  "type": "Feature",
  "properties": {
    "addr:full":"S\u00f8ndergade 43 Aalborg Danmark 9000",
    "addr:housenumber":"43",
    "addr:postcode":"9000",
    "addr:street":"Sondergade",
    "iso:country":"DK",
    "sg:address":"S\u00f8ndergade 43",
    "sg:city":"Aalborg",
    "sg:orig_category":"Bagere",
    "sg:postcode":"9000",
    "sg:province":"Danmark",
    "wof:name":"Pita Bageren - Rafael Pita",
    "wof:placetype":"venue"
},
  "geometry": {"coordinates":[9.929475,57.045685],"type":"Point"}
}