{
  "type": "Feature",
  "properties": {
    "addr:full":"Torstedalle 177 Horsens Danmark 8700",
    "addr:housenumber":"177",
    "addr:postcode":"8700",
    "addr:street":"Torstedalle",
    "iso:country":"DK",
    "sg:address":"Torstedalle 177",
    "sg:city":"Horsens",
    "sg:orig_category":"Autoruder",
    "sg:phone":"+45 75 63 15 00",
    "sg:postcode":"8700",
    "sg:province":"Danmark",
    "wof:name":"Dansk Bilglas",
    "wof:placetype":"venue"
},
  "geometry": {"coordinates":[9.8076715469,55.8354187012],"type":"Point"}
}