{
  "type": "Feature",
  "properties": {
    "addr:full":"Sommervej 10, Hasle \u00c5rhus V Danmark 8210",
    "addr:housenumber":"10",
    "addr:postcode":"8210",
    "addr:street":"Sommervej",
    "iso:country":"DK",
    "sg:address":"Sommervej 10, Hasle",
    "sg:city":"\u00c5rhus V",
    "sg:classifiers":[
        {
            "category":"Taxi",
            "type":"Transportation"
        }
    ],
    "sg:phone":"+45 89 48 48 48",
    "sg:postcode":"8210",
    "sg:province":"Danmark",
    "sg:website":"www.aarhus-taxa.dk",
    "wof:name":"Aarhus Taxa",
    "wof:placetype":"venue"
},
  "geometry": {"coordinates":[14.7065896988,55.1830787659],"type":"Point"}
}