{
  "type": "Feature",
  "properties": {
    "iso:country":"DK",
    "sg:address":"Holl\u00e6ndervej 56",
    "sg:city":"Middelfart",
    "sg:orig_category":"Tekstiltrykkerier",
    "sg:phone":"+45 64 41 79 77",
    "sg:postcode":"5500",
    "sg:province":"Danmark",
    "wof:name":"Tekstil Tryk",
    "wof:placetype":"venue"
},
  "geometry": {"coordinates":[9.7576265335,55.4941558838],"type":"Point"}
}