{
  "type": "Feature",
  "properties": {
    "addr:full":"Vestergade 5 Helsinge Danmark 3200",
    "addr:housenumber":"5",
    "addr:postcode":"3200",
    "addr:street":"Vestergade",
    "iso:country":"DK",
    "sg:address":"Vestergade 5",
    "sg:city":"Helsinge",
    "sg:orig_category":"Bagere",
    "sg:phone":"+45 48 79 48 48",
    "sg:postcode":"3200",
    "sg:province":"Danmark",
    "wof:name":"Gadek\u00e6rets Konditori",
    "wof:placetype":"venue"
},
  "geometry": {"coordinates":[12.1978378296,56.0220146179],"type":"Point"}
}