{
  "type": "Feature",
  "properties": {
    "addr:full":"Kalundborgvej 70 B Slagelse Danmark 4200",
    "addr:housenumber":"70 b",
    "addr:postcode":"4200",
    "addr:street":"Kalundborgvej",
    "iso:country":"DK",
    "sg:address":"Kalundborgvej 70 B",
    "sg:city":"Slagelse",
    "sg:orig_category":"Autoophug",
    "sg:phone":"+45 58 52 31 44",
    "sg:postcode":"4200",
    "sg:province":"Danmark",
    "sg:website":"www.ravnskjaer-autoophug.dk",
    "wof:name":"Ravnskj\u00e6r's Autogenbrug Slagelse",
    "wof:placetype":"venue"
},
  "geometry": {"coordinates":[11.3372011185,55.4143028259],"type":"Point"}
}