{
  "type": "Feature",
  "properties": {
    "addr:full":"Kai Lindbergs Gade 37  Hanstholm Danmark 7730",
    "addr:housenumber":"37",
    "addr:postcode":"7730",
    "addr:street":"Kai Lindbergs Gade",
    "iso:country":"DK",
    "sg:address":"Kai Lindbergs Gade 37 ",
    "sg:city":"Hanstholm",
    "sg:classifiers":[
        {
            "category":"Farming",
            "subcategory":"Livestock Farm",
            "type":"Manufacturing & Wholesale Goods"
        }
    ],
    "sg:phone":"+45 97 96 17 82",
    "sg:postcode":"7730",
    "sg:province":"Danmark",
    "sg:tags":[
        "agriculture"
    ],
    "wof:name":"A GERHARD JENSENS FISKEEKSPORT APS",
    "wof:placetype":"venue"
},
  "geometry": {"coordinates":[8.6032676697,57.1202774048],"type":"Point"}
}