{
  "type": "Feature",
  "properties": {
    "addr:full":"Gl. Tved 14, Tved Kolding Danmark 6000",
    "addr:housenumber":"14",
    "addr:postcode":"6000",
    "addr:street":"Gl. Tved;Tved",
    "iso:country":"DK",
    "sg:address":"Gl. Tved 14, Tved",
    "sg:city":"Kolding",
    "sg:orig_category":"INGENI\u00c3\u02dcRER",
    "sg:phone":"+45 75 53 44 18",
    "sg:postcode":"6000",
    "sg:province":"Danmark",
    "wof:name":"Fosco",
    "wof:placetype":"venue"
},
  "geometry": {"coordinates":[9.4733953476,55.4863586426],"type":"Point"}
}