{
  "type": "Feature",
  "properties": {
    "addr:full":"Holstebrovej 28, Gr\u00f8nbjerg Spjald Danmark 6971",
    "addr:housenumber":"28",
    "addr:postcode":"6971",
    "addr:street":"Holstebrovej;Gronbjerg",
    "iso:country":"DK",
    "sg:address":"Holstebrovej 28, Gr\u00f8nbjerg",
    "sg:city":"Spjald",
    "sg:orig_category":"Grusgrave",
    "sg:phone":"+45 97 38 43 86",
    "sg:postcode":"6971",
    "sg:province":"Danmark",
    "wof:name":"Gr\u00f8nbjerg Sand- og Grusgrav",
    "wof:placetype":"venue"
},
  "geometry": {"coordinates":[8.5089349747,56.1276893616],"type":"Point"}
}