{
  "type": "Feature",
  "properties": {
    "addr:full":"Fmd.: Erik Bertelsen, Thors\u00f8lundvej 23 Thors\u00f8 Danmark 8881",
    "addr:housenumber":"23",
    "addr:postcode":"8881",
    "addr:street":"Thorsolundvej",
    "iso:country":"DK",
    "sg:address":"Fmd.: Erik Bertelsen, Thors\u00f8lundvej 23",
    "sg:city":"Thors\u00f8",
    "sg:orig_category":"Kirkelige foreninger",
    "sg:phone":"+45 86 96 64 23",
    "sg:postcode":"8881",
    "sg:province":"Danmark",
    "wof:name":"Indre Mission, Thors\u00f8",
    "wof:placetype":"venue"
},
  "geometry": {"coordinates":[9.7878103256,56.2985954285],"type":"Point"}
}