{
  "type": "Feature",
  "properties": {
    "addr:full":"Grantoftestr\u00e6de 11 Ballerup Danmark 2750",
    "addr:housenumber":"11",
    "addr:postcode":"2750",
    "addr:street":"Grantoftestraede",
    "iso:country":"DK",
    "sg:address":"Grantoftestr\u00e6de 11",
    "sg:city":"Ballerup",
    "sg:orig_category":"Apoteker og -udsalg",
    "sg:phone":"+45 44 97 01 80",
    "sg:postcode":"2750",
    "sg:province":"Danmark",
    "wof:name":"Apoteksudsalget Grantoften",
    "wof:placetype":"venue"
},
  "geometry": {"coordinates":[12.343170166,55.7273292542],"type":"Point"}
}