{
  "type": "Feature",
  "properties": {
    "iso:country":"DK",
    "sg:address":"Jenlevej 7, N\u00f8rrevejle",
    "sg:city":"Roslev",
    "sg:orig_category":"Oliefyr og service",
    "sg:phone":"+45 97 58 43 31",
    "sg:postcode":"7870",
    "sg:province":"Danmark",
    "wof:name":"Jenlevejs Mekaniske V\u00e6rksted",
    "wof:placetype":"venue"
},
  "geometry": {"coordinates":[8.8715353012,56.7570304871],"type":"Point"}
}