{
  "type": "Feature",
  "properties": {
    "addr:full":"Koldingvej 441 Vejle Danmark 7100",
    "addr:housenumber":"441",
    "addr:postcode":"7100",
    "addr:street":"Koldingvej",
    "iso:country":"DK",
    "sg:address":"Koldingvej 441",
    "sg:city":"Vejle",
    "sg:classifiers":[
        {
            "category":"Restaurant",
            "type":"Food & Drink"
        }
    ],
    "sg:phone":"+45 75 86 35 22",
    "sg:postcode":"7100",
    "sg:province":"Danmark",
    "wof:name":"H\u00f8jen Spisested",
    "wof:placetype":"venue"
},
  "geometry": {"coordinates":[9.5037889481,55.6523590088],"type":"Point"}
}