{
  "type": "Feature",
  "properties": {
    "addr:full":"\u00d8ver\u00f8dvej 44 C, \u00d8ver\u00f8d Holte Danmark 2840",
    "addr:housenumber":"44 c",
    "addr:postcode":"2840",
    "addr:street":"Overodvej;Overod",
    "iso:country":"DK",
    "sg:address":"\u00d8ver\u00f8dvej 44 C, \u00d8ver\u00f8d",
    "sg:city":"Holte",
    "sg:classifiers":[
        {
            "category":"Food & Beverages",
            "subcategory":"Liquor & Beverages",
            "type":"Retail Goods"
        }
    ],
    "sg:phone":"+45 45 42 19 50",
    "sg:postcode":"2840",
    "sg:province":"Danmark",
    "sg:tags":[
        "vin"
    ],
    "sg:website":"www.drinkit.dk",
    "wof:name":"DrinkIt",
    "wof:placetype":"venue"
},
  "geometry": {"coordinates":[12.4706554413,55.8122367859],"type":"Point"}
}