{
  "type": "Feature",
  "properties": {
    "iso:country":"DK",
    "sg:address":"Lindeengen 22",
    "sg:city":"Skovlunde",
    "sg:orig_category":"Revisorer",
    "sg:phone":"+45 44 91 68 67",
    "sg:postcode":"2740",
    "sg:province":"Danmark",
    "wof:name":"Drejer, Revisionsfirmaet Mogens",
    "wof:placetype":"venue"
},
  "geometry": {"coordinates":[12.3896131516,55.7097091675],"type":"Point"}
}