{
  "type": "Feature",
  "properties": {
    "iso:country":"DK",
    "sg:address":"Klakkebjerg 1 C",
    "sg:city":"Ballerup",
    "sg:orig_category":"Legesteder",
    "sg:phone":"+45 44 77 17 20",
    "sg:postcode":"2750",
    "sg:province":"Danmark",
    "wof:name":"Byggelegeplads",
    "wof:placetype":"venue"
},
  "geometry": {"coordinates":[12.3339834213,55.7508888245],"type":"Point"}
}