{
  "type": "Feature",
  "properties": {
    "addr:full":"Sandbakken 28, Appen\u00e6s N\u00e6stved Danmark 4700",
    "addr:housenumber":"28",
    "addr:postcode":"4700",
    "addr:street":"Sandbakken",
    "iso:country":"DK",
    "sg:address":"Sandbakken 28, Appen\u00e6s",
    "sg:city":"N\u00e6stved",
    "sg:classifiers":[
        {
            "category":"Professional",
            "subcategory":"Computer Services",
            "type":"Services"
        }
    ],
    "sg:phone":"+45 55 70 20 20",
    "sg:postcode":"4700",
    "sg:province":"Danmark",
    "sg:tags":[
        "edb",
        "-",
        "software"
    ],
    "wof:name":"Opus Software",
    "wof:placetype":"venue"
},
  "geometry": {"coordinates":[7.976249218,58.2725791931],"type":"Point"}
}