{
  "type": "Feature",
  "properties": {
    "addr:full":"Elmevej 20 Frederikshavn Danmark 9900",
    "addr:housenumber":"20",
    "addr:postcode":"9900",
    "addr:street":"Elmevej",
    "iso:country":"DK",
    "sg:address":"Elmevej 20",
    "sg:city":"Frederikshavn",
    "sg:orig_category":"Murermestre",
    "sg:phone":"+45 98 42 35 15",
    "sg:postcode":"9900",
    "sg:province":"Danmark",
    "wof:name":"Carlsen, Henrik",
    "wof:placetype":"venue"
},
  "geometry": {"coordinates":[10.52709198,57.4371948242],"type":"Point"}
}