{
  "type": "Feature",
  "properties": {
    "iso:country":"DK",
    "sg:address":"Hindborgvej 145 ",
    "sg:city":"Skive",
    "sg:classifiers":[
        {
            "category":"Home & Garden",
            "subcategory":"Home Furnishings",
            "type":"Retail Goods"
        }
    ],
    "sg:phone":"+45 97 53 12 55",
    "sg:postcode":"7800",
    "sg:province":"Danmark",
    "sg:tags":[
        "household"
    ],
    "wof:name":"ROULET MASKINFABRIK APS",
    "wof:placetype":"venue"
},
  "geometry": {"coordinates":[8.9596300125,56.598400116],"type":"Point"}
}