{
  "type": "Feature",
  "properties": {
    "iso:country":"DK",
    "sg:address":"V\u00e6rkstedsvej 6, Gelsted",
    "sg:city":"Gelsted",
    "sg:orig_category":"Vinduer",
    "sg:phone":"+45 64 49 11 14",
    "sg:postcode":"5591",
    "sg:province":"Danmark",
    "sg:website":"www.det-er-nemt.dk",
    "wof:name":"Gelsted K\u00f8kken- og byggecenter",
    "wof:placetype":"venue"
},
  "geometry": {"coordinates":[9.9734048843,55.3995094299],"type":"Point"}
}