{
  "type": "Feature",
  "properties": {
    "addr:full":"Torvegade 16, 1 Struer Danmark 7600",
    "addr:housenumber":"16 1",
    "addr:postcode":"7600",
    "addr:street":"Torvegade",
    "iso:country":"DK",
    "sg:address":"Torvegade 16, 1",
    "sg:city":"Struer",
    "sg:orig_category":"INGENI\u00c3\u02dcRER",
    "sg:phone":"+45 97 84 19 15",
    "sg:postcode":"7600",
    "sg:province":"Danmark",
    "wof:name":"NBL-Engineering",
    "wof:placetype":"venue"
},
  "geometry": {"coordinates":[8.5922174454,56.4903831482],"type":"Point"}
}