{
  "type": "Feature",
  "properties": {
    "addr:full":"Asminder\u00f8dgade 30 B Fredensborg Danmark 3480",
    "addr:housenumber":"30 b",
    "addr:postcode":"3480",
    "addr:street":"Asminderodgade",
    "iso:country":"DK",
    "sg:address":"Asminder\u00f8dgade 30 B",
    "sg:city":"Fredensborg",
    "sg:orig_category":"Solvarme",
    "sg:phone":"+45 48 47 50 44",
    "sg:postcode":"3480",
    "sg:province":"Danmark",
    "sg:website":"www.palys.dk",
    "wof:name":"Willerslev-Milj\u00f8 & Energi",
    "wof:placetype":"venue"
},
  "geometry": {"coordinates":[12.407412529,55.9717330933],"type":"Point"}
}