{
  "type": "Feature",
  "properties": {
    "addr:full":"Leder: Christien v.d. Hoeven, Emmelev K\u00e6rvej 3 Grenaa Danmark 8500",
    "addr:housenumber":"3",
    "addr:postcode":"8500",
    "addr:street":"Kaervej",
    "iso:country":"DK",
    "sg:address":"Leder: Christien v.d. Hoeven, Emmelev K\u00e6rvej 3",
    "sg:city":"Grenaa",
    "sg:orig_category":"\u00c3\u02dcvrig fritidsundervisning",
    "sg:phone":"+45 86 38 75 15",
    "sg:postcode":"8500",
    "sg:province":"Danmark",
    "wof:name":"N\u00f8rre Djurs Musikskole",
    "wof:placetype":"venue"
},
  "geometry": {"coordinates":[10.8774929047,56.4126853943],"type":"Point"}
}