{
  "type": "Feature",
  "properties": {
    "addr:full":"Storgade 19 A Sor\u00f8 Danmark 4180",
    "addr:housenumber":"19 a",
    "addr:postcode":"4180",
    "addr:street":"Storgade",
    "iso:country":"DK",
    "sg:address":"Storgade 19 A",
    "sg:city":"Sor\u00f8",
    "sg:orig_category":"Apoteker og -udsalg",
    "sg:phone":"+45 57 83 00 12",
    "sg:postcode":"4180",
    "sg:province":"Danmark",
    "wof:name":"Sor\u00f8 Apotek",
    "wof:placetype":"venue"
},
  "geometry": {"coordinates":[-102.94467926030001,45.4534721375],"type":"Point"}
}