{
  "type": "Feature",
  "properties": {
    "addr:full":"Lindeg\u00e5rdsvej 6 Farum Danmark 3520",
    "addr:housenumber":"6",
    "addr:postcode":"3520",
    "addr:street":"Lindegaardsvej",
    "iso:country":"DK",
    "sg:address":"Lindeg\u00e5rdsvej 6",
    "sg:city":"Farum",
    "sg:orig_category":"Konditorier",
    "sg:phone":"+45 44 95 46 44",
    "sg:postcode":"3520",
    "sg:province":"Danmark",
    "wof:name":"T.H.C. Kager",
    "wof:placetype":"venue"
},
  "geometry": {"coordinates":[12.350317955,55.8087348938],"type":"Point"}
}