{
  "type": "Feature",
  "properties": {
    "addr:full":"Storetorv 1 Aabenraa Danmark 6200",
    "addr:housenumber":"1",
    "addr:postcode":"6200",
    "addr:street":"Storetorv",
    "iso:country":"DK",
    "sg:address":"Storetorv 1",
    "sg:city":"Aabenraa",
    "sg:orig_category":"Apoteker og -udsalg",
    "sg:phone":"+45 74 62 22 24",
    "sg:postcode":"6200",
    "sg:province":"Danmark",
    "wof:name":"L\u00f8ve-Apoteket",
    "wof:placetype":"venue"
},
  "geometry": {"coordinates":[9.4189348221,55.0426330566],"type":"Point"}
}