{
  "type": "Feature",
  "properties": {
    "addr:full":"\u00d8sterbo 2, Herringl\u00f8se Veks\u00f8 Sj\u00e6lland Danmark 3670",
    "addr:housenumber":"2",
    "addr:postcode":"3670",
    "addr:street":"Osterbo",
    "iso:country":"DK",
    "sg:address":"\u00d8sterbo 2, Herringl\u00f8se",
    "sg:city":"Veks\u00f8 Sj\u00e6lland",
    "sg:orig_category":"Murermestre",
    "sg:phone":"+45 46 76 92 80",
    "sg:postcode":"3670",
    "sg:province":"Danmark",
    "wof:name":"S\u00f8rensen, Knud H\u00f8rdum",
    "wof:placetype":"venue"
},
  "geometry": {"coordinates":[-76.0886383057,38.7291030884],"type":"Point"}
}