{
  "type": "Feature",
  "properties": {
    "addr:full":"Grundtvigs Alle 16 Vordingborg Danmark 4760",
    "addr:housenumber":"16",
    "addr:postcode":"4760",
    "addr:street":"Grundtvigs Alle",
    "iso:country":"DK",
    "sg:address":"Grundtvigs Alle 16",
    "sg:city":"Vordingborg",
    "sg:orig_category":"Akupunktur",
    "sg:phone":"+45 55 34 06 08",
    "sg:postcode":"4760",
    "sg:province":"Danmark",
    "wof:name":"Naturmedicinsk Klinik",
    "wof:placetype":"venue"
},
  "geometry": {"coordinates":[11.9066696167,55.0148429871],"type":"Point"}
}