{
  "type": "Feature",
  "properties": {
    "addr:full":"Hundige Storcenter 15 G Greve Danmark 2670",
    "addr:housenumber":"15",
    "addr:postcode":"2670",
    "addr:street":"G",
    "iso:country":"DK",
    "sg:address":"Hundige Storcenter 15 G",
    "sg:city":"Greve",
    "sg:orig_category":"Pizzeriaer",
    "sg:phone":"+45 43 69 09 89",
    "sg:postcode":"2670",
    "sg:province":"Danmark",
    "wof:name":"Roma Pizzeria & Grillbar 2",
    "wof:placetype":"venue"
},
  "geometry": {"coordinates":[12.2941808701,55.5844078064],"type":"Point"}
}