{
  "type": "Feature",
  "properties": {
    "iso:country":"DK",
    "sg:address":"Degnehusene 53",
    "sg:city":"Albertslund",
    "sg:orig_category":"Sammensatte institutioner",
    "sg:phone":"+45 43 45 40 58",
    "sg:postcode":"2620",
    "sg:province":"Danmark",
    "wof:name":"Degnehuset B\u00f8rnehus",
    "wof:placetype":"venue"
},
  "geometry": {"coordinates":[12.3643903732,55.6708297729],"type":"Point"}
}