{
  "type": "Feature",
  "properties": {
    "iso:country":"DK",
    "sg:address":"Flensborgvej 16",
    "sg:city":"Krus\u00e5",
    "sg:orig_category":"Bodegaer",
    "sg:phone":"+45 74 67 15 33",
    "sg:postcode":"6340",
    "sg:province":"Danmark",
    "wof:name":"Smugkroen",
    "wof:placetype":"venue"
},
  "geometry": {"coordinates":[9.4012641907,54.8431282043],"type":"Point"}
}