{
  "type": "Feature",
  "properties": {
    "addr:full":"Bredgade 61 Hejnsvig Danmark 7250",
    "addr:housenumber":"61",
    "addr:postcode":"7250",
    "addr:street":"Bredgade",
    "iso:country":"DK",
    "sg:address":"Bredgade 61",
    "sg:city":"Hejnsvig",
    "sg:orig_category":"HOTELS: OG MOTELLER",
    "sg:phone":"+45 75 33 58 23",
    "sg:postcode":"7250",
    "sg:province":"Danmark",
    "wof:name":"Hejnsvig Hotel",
    "wof:placetype":"venue"
},
  "geometry": {"coordinates":[8.9971399307,55.6949424744],"type":"Point"}
}