{
  "type": "Feature",
  "properties": {
    "iso:country":"DK",
    "sg:address":"Anl\u00e6gsvej 4, Ejby",
    "sg:city":"Ejby",
    "sg:orig_category":"Distriktsbiblioteker",
    "sg:phone":"+45 63 46 49 00",
    "sg:postcode":"5592",
    "sg:province":"Danmark",
    "wof:name":"Ejby Bibliotek",
    "wof:placetype":"venue"
},
  "geometry": {"coordinates":[9.9277296066,55.4288444519],"type":"Point"}
}