{
  "type": "Feature",
  "properties": {
    "iso:country":"DK",
    "sg:address":"Valenciavej 4",
    "sg:city":"Hedensted",
    "sg:orig_category":"Genbrugscentre",
    "sg:phone":"+45 75 89 05 30",
    "sg:postcode":"8722",
    "sg:province":"Danmark",
    "wof:name":"GenBrug",
    "wof:placetype":"venue"
},
  "geometry": {"coordinates":[9.6944437027,55.7782058716],"type":"Point"}
}