{
  "type": "Feature",
  "properties": {
    "addr:full":"Fmd.: J\u00f8rgen Elmkj\u00e6r, Askev\u00e6nget 20, Skrillinge Middelfart Danmark 5500",
    "addr:housenumber":"20",
    "addr:postcode":"5500",
    "addr:street":"Askevaenget;Skrillinge",
    "iso:country":"DK",
    "sg:address":"Fmd.: J\u00f8rgen Elmkj\u00e6r, Askev\u00e6nget 20, Skrillinge",
    "sg:city":"Middelfart",
    "sg:orig_category":"Kulturelle foreninger",
    "sg:phone":"+45 64 41 16 86",
    "sg:postcode":"5500",
    "sg:province":"Danmark",
    "wof:name":"Middelfart Amat\u00f8rteater",
    "wof:placetype":"venue"
},
  "geometry": {"coordinates":[9.7417497635,55.5030250549],"type":"Point"}
}