{
  "type": "Feature",
  "properties": {
    "iso:country":"DK",
    "sg:address":"Aalborgvej 27",
    "sg:city":"Terndrup",
    "sg:orig_category":"Maskinstationer",
    "sg:phone":"+45 98 33 58 22",
    "sg:postcode":"9575",
    "sg:province":"Danmark",
    "wof:name":"Terndrup Maskinstation",
    "wof:placetype":"venue"
},
  "geometry": {"coordinates":[10.0523424149,56.8202629089],"type":"Point"}
}