{
  "type": "Feature",
  "properties": {
    "addr:full":"Havfruevej 31 Herlev Danmark 2730",
    "addr:housenumber":"31",
    "addr:postcode":"2730",
    "addr:street":"Havfruevej",
    "iso:country":"DK",
    "sg:address":"Havfruevej 31",
    "sg:city":"Herlev",
    "sg:orig_category":"\u00c3\u2020ldreorganisationer og klubber",
    "sg:phone":"+45 44 94 73 99",
    "sg:postcode":"2730",
    "sg:province":"Danmark",
    "wof:name":"Herlev-Hjortespring Pensionistforening",
    "wof:placetype":"venue"
},
  "geometry": {"coordinates":[12.4545087814,55.720249176],"type":"Point"}
}