{
  "type": "Feature",
  "properties": {
    "iso:country":"DK",
    "sg:address":"Gammel Kongevej 119",
    "sg:city":"Frederiksberg",
    "sg:orig_category":"Optikere",
    "sg:phone":"+45 33 25 60 93",
    "sg:postcode":"1850",
    "sg:province":"Danmark",
    "wof:name":"BlicOptik",
    "wof:placetype":"venue"
},
  "geometry": {"coordinates":[12.5432167053,55.6758995056],"type":"Point"}
}