{
  "type": "Feature",
  "properties": {
    "iso:country":"DK",
    "sg:address":"Vejlevej 18",
    "sg:city":"Fredericia",
    "sg:orig_category":"Benzinstationer",
    "sg:postcode":"7000",
    "sg:province":"Danmark",
    "wof:name":"JET",
    "wof:placetype":"venue"
},
  "geometry": {"coordinates":[9.728317,55.569469],"type":"Point"}
}