{
  "type": "Feature",
  "properties": {
    "addr:full":"Jagtvej 52 Esbjerg \u00d8 Danmark 6705",
    "addr:housenumber":"52",
    "addr:postcode":"6705",
    "addr:street":"Jagtvej;Danmark",
    "iso:country":"DK",
    "sg:address":"Jagtvej 52",
    "sg:city":"Esbjerg \u00d8",
    "sg:orig_category":"Dykkerudstyr",
    "sg:phone":"+45 75 12 12 99",
    "sg:postcode":"6705",
    "sg:province":"Danmark",
    "wof:name":"Esbjerg Dykkercenter",
    "wof:placetype":"venue"
},
  "geometry": {"coordinates":[8.478767395,55.4790458679],"type":"Point"}
}