{
  "type": "Feature",
  "properties": {
    "addr:full":"Faursh\u00f8jvej 11, V. \u00c5by Faaborg Danmark 5600",
    "addr:housenumber":"11",
    "addr:postcode":"5600",
    "addr:street":"Faurshojvej;Aaby",
    "iso:country":"DK",
    "sg:address":"Faursh\u00f8jvej 11, V. \u00c5by",
    "sg:city":"Faaborg",
    "sg:orig_category":"Zoneterapeuter",
    "sg:phone":"+45 62 61 63 60",
    "sg:postcode":"5600",
    "sg:province":"Danmark",
    "wof:name":"Zoneterapi",
    "wof:placetype":"venue"
},
  "geometry": {"coordinates":[10.2400531769,55.0950622559],"type":"Point"}
}