{
  "type": "Feature",
  "properties": {
    "iso:country":"DK",
    "sg:address":"Holte Midtpunkt 16",
    "sg:city":"Holte",
    "sg:orig_category":"Materialister",
    "sg:phone":"+45 45 42 04 01",
    "sg:postcode":"2840",
    "sg:province":"Danmark",
    "wof:name":"Matas",
    "wof:placetype":"venue"
},
  "geometry": {"coordinates":[12.470580101,55.8110694885],"type":"Point"}
}