{
  "type": "Feature",
  "properties": {
    "addr:full":"Kronborgvej 32  Vejen Danmark 6600",
    "addr:housenumber":"32",
    "addr:postcode":"6600",
    "addr:street":"Kronborgvej",
    "iso:country":"DK",
    "sg:address":"Kronborgvej 32 ",
    "sg:city":"Vejen",
    "sg:classifiers":[
        {
            "category":"Building & Trades",
            "subcategory":"Construction",
            "type":"Services"
        }
    ],
    "sg:phone":"+45 75 55 50 55",
    "sg:postcode":"6600",
    "sg:province":"Danmark",
    "sg:tags":[
        "work",
        "public"
    ],
    "wof:name":"CCI-CALBAR CONTRACTING INTERNATIONAL A/S",
    "wof:placetype":"venue"
},
  "geometry": {"coordinates":[9.2455101013,55.5570602417],"type":"Point"}
}