{
  "type": "Feature",
  "properties": {
    "addr:full":"Fuglebakken 119, Snestrup Odense NV Danmark 5210",
    "addr:housenumber":"119",
    "addr:postcode":"5210",
    "addr:street":"Fuglebakken;Snestrup",
    "iso:country":"DK",
    "sg:address":"Fuglebakken 119, Snestrup",
    "sg:city":"Odense NV",
    "sg:orig_category":"EDB - udstyr",
    "sg:phone":"+45 66 16 24 14",
    "sg:postcode":"5210",
    "sg:province":"Danmark",
    "wof:name":"Freund Data",
    "wof:placetype":"venue"
},
  "geometry": {"coordinates":[10.274764061,55.4303321838],"type":"Point"}
}