{
  "type": "Feature",
  "properties": {
    "addr:full":"v/ Kirsten S\u00f8nderg\u00e5rd, \u00c5svej 55 Thisted Danmark 7700",
    "addr:housenumber":"55",
    "addr:postcode":"7700",
    "addr:street":"Aasvej",
    "iso:country":"DK",
    "sg:address":"v/ Kirsten S\u00f8nderg\u00e5rd, \u00c5svej 55",
    "sg:city":"Thisted",
    "sg:orig_category":"Spejderkorps",
    "sg:phone":"+45 97 93 13 39",
    "sg:postcode":"7700",
    "sg:province":"Danmark",
    "wof:name":"KFUM spejderne i Skjoldborg",
    "wof:placetype":"venue"
},
  "geometry": {"coordinates":[8.6919784546,56.9556121826],"type":"Point"}
}