{
  "type": "Feature",
  "properties": {
    "addr:full":"Lethenborgvej 9 Solbjerg Danmark 8355",
    "addr:housenumber":"9",
    "addr:postcode":"8355",
    "addr:street":"Lethenborgvej",
    "iso:country":"DK",
    "sg:address":"Lethenborgvej 9",
    "sg:city":"Solbjerg",
    "sg:orig_category":"Malermestre",
    "sg:phone":"+45 87 94 47 47",
    "sg:postcode":"8355",
    "sg:province":"Danmark",
    "wof:name":"Laursen, Malerfirma Kurt B.",
    "wof:placetype":"venue"
},
  "geometry": {"coordinates":[10.0410881042,56.0042610168],"type":"Point"}
}