{
  "type": "Feature",
  "properties": {
    "addr:full":"Stemannsgade 9 c Randers Danmark 8900",
    "addr:housenumber":"9 c",
    "addr:postcode":"8900",
    "addr:street":"Stemannsgade",
    "iso:country":"DK",
    "sg:address":"Stemannsgade 9 c",
    "sg:city":"Randers",
    "sg:orig_category":"Cafeer",
    "sg:phone":"+45 86 43 86 17",
    "sg:postcode":"8900",
    "sg:province":"Danmark",
    "wof:name":"Caf\u00e9 Underv\u00e6rket",
    "wof:placetype":"venue"
},
  "geometry": {"coordinates":[10.0412101746,56.4611587524],"type":"Point"}
}