{
  "type": "Feature",
  "properties": {
    "addr:full":"Store Kongensgade 118 K\u00f8benhavn Danmark 1264",
    "addr:housenumber":"118;1264",
    "addr:street":"Store Kongensgade",
    "iso:country":"DK",
    "sg:address":"Store Kongensgade 118",
    "sg:city":"K\u00f8benhavn",
    "sg:orig_category":"Blomster og planter, kunstige",
    "sg:phone":"+45 33 91 80 02",
    "sg:postcode":"1264",
    "sg:province":"Danmark",
    "sg:website":"www.silkeblomster.dk",
    "wof:name":"Skov, Jette",
    "wof:placetype":"venue"
},
  "geometry": {"coordinates":[12.5924,55.686501],"type":"Point"}
}