{
  "type": "Feature",
  "properties": {
    "addr:full":"\u00d8sterg\u00e5rdsvej 5 Glums\u00f8 Danmark 4171",
    "addr:housenumber":"5",
    "addr:postcode":"4171",
    "addr:street":"Ostergaardsvej",
    "iso:country":"DK",
    "sg:address":"\u00d8sterg\u00e5rdsvej 5",
    "sg:city":"Glums\u00f8",
    "sg:orig_category":"Kirketjenere/Gravere",
    "sg:phone":"+45 57 64 64 10",
    "sg:postcode":"4171",
    "sg:province":"Danmark",
    "wof:name":"Madsen, Falch",
    "wof:placetype":"venue"
},
  "geometry": {"coordinates":[11.6862697601,55.3553962708],"type":"Point"}
}