{
  "type": "Feature",
  "properties": {
    "addr:full":"Nyg\u00e5rdsvej 30 Bramming Danmark 6740",
    "addr:housenumber":"30",
    "addr:postcode":"6740",
    "addr:street":"Nygaardsvej",
    "iso:country":"DK",
    "sg:address":"Nyg\u00e5rdsvej 30",
    "sg:city":"Bramming",
    "sg:orig_category":"Zoneterapeuter",
    "sg:phone":"+45 75 10 20 03",
    "sg:postcode":"6740",
    "sg:province":"Danmark",
    "wof:name":"L\u00f8nne, Lise Hollesen",
    "wof:placetype":"venue"
},
  "geometry": {"coordinates":[8.7157812119,55.4777793884],"type":"Point"}
}