{
  "type": "Feature",
  "properties": {
    "addr:full":"v/ Erik Pihl, Tj\u00f8rnev\u00e6nget 3 Nex\u00f8 Danmark 3730",
    "addr:housenumber":"3",
    "addr:postcode":"3730",
    "addr:street":"Tjornevaenget",
    "iso:country":"DK",
    "sg:address":"v/ Erik Pihl, Tj\u00f8rnev\u00e6nget 3",
    "sg:city":"Nex\u00f8",
    "sg:orig_category":"Kirkelige foreninger",
    "sg:phone":"+45 56 49 21 82",
    "sg:postcode":"3730",
    "sg:province":"Danmark",
    "wof:name":"Luthersk Missionsforening Snogeb\u00e6k",
    "wof:placetype":"venue"
},
  "geometry": {"coordinates":[15.1096076965,55.0267219543],"type":"Point"}
}