{
  "type": "Feature",
  "properties": {
    "addr:full":"Solsortevej 16 Hinnerup Danmark 8382",
    "addr:housenumber":"16",
    "addr:postcode":"8382",
    "addr:street":"Solsortevej",
    "iso:country":"DK",
    "sg:address":"Solsortevej 16",
    "sg:city":"Hinnerup",
    "sg:orig_category":"INGENI\u00c3\u02dcRER",
    "sg:phone":"+45 87 64 02 10",
    "sg:postcode":"8382",
    "sg:province":"Danmark",
    "wof:name":"Pli-Consult",
    "wof:placetype":"venue"
},
  "geometry": {"coordinates":[10.067647934,56.2743301392],"type":"Point"}
}