{
  "type": "Feature",
  "properties": {
    "iso:country":"DK",
    "sg:address":"Gyldenl\u00f8vesgade 16",
    "sg:city":"Slagelse",
    "sg:orig_category":"Vinduespolering",
    "sg:phone":"+45 58 52 71 05",
    "sg:postcode":"4200",
    "sg:province":"Danmark",
    "wof:name":"Hansens Vinduespolering, Helweg",
    "wof:placetype":"venue"
},
  "geometry": {"coordinates":[11.3373155594,55.4091339111],"type":"Point"}
}