{
  "type": "Feature",
  "properties": {
    "addr:full":"Lystrup Centervej 256 Lystrup Danmark 8520",
    "addr:housenumber":"256",
    "addr:postcode":"8520",
    "addr:street":"Lystrup Centervej",
    "iso:country":"DK",
    "sg:address":"Lystrup Centervej 256",
    "sg:city":"Lystrup",
    "sg:orig_category":"Tandklinikker, Kommunale",
    "sg:phone":"+45 86 22 48 46",
    "sg:postcode":"8520",
    "sg:province":"Danmark",
    "wof:name":"Tandklinikken Lystrup Skole",
    "wof:placetype":"venue"
},
  "geometry": {"coordinates":[10.235824585,56.237159729],"type":"Point"}
}