{
  "type": "Feature",
  "properties": {
    "addr:full":"Herredsvejen 178, H\u00e6rup Hobro Danmark 9500",
    "addr:housenumber":"178",
    "addr:postcode":"9500",
    "addr:street":"Herredsvejen",
    "iso:country":"DK",
    "sg:address":"Herredsvejen 178, H\u00e6rup",
    "sg:city":"Hobro",
    "sg:orig_category":"Maskinudlejning",
    "sg:phone":"+45 98 54 65 89",
    "sg:postcode":"9500",
    "sg:province":"Danmark",
    "wof:name":"N\u00f8hr, Leif",
    "wof:placetype":"venue"
},
  "geometry": {"coordinates":[9.7946596146,56.6382789612],"type":"Point"}
}