{
  "type": "Feature",
  "properties": {
    "addr:full":"Frederiksgade 29 Odense C Danmark 5000",
    "addr:housenumber":"29",
    "addr:postcode":"5000",
    "addr:street":"Frederiksgade",
    "iso:country":"DK",
    "sg:address":"Frederiksgade 29",
    "sg:city":"Odense C",
    "sg:orig_category":"Psykologer, praktiserende",
    "sg:phone":"+45 66 13 28 56",
    "sg:postcode":"5000",
    "sg:province":"Danmark",
    "wof:name":"Psykologisk R\u00e5dgivning",
    "wof:placetype":"venue"
},
  "geometry": {"coordinates":[10.3982372284,55.3956642151],"type":"Point"}
}