{
  "type": "Feature",
  "properties": {
    "iso:country":"DK",
    "sg:address":"Gr\u00f8nlandsvej 6 ",
    "sg:city":"Frederikshavn",
    "sg:classifiers":[
        {
            "category":"Manufacturing",
            "subcategory":"Lumber",
            "type":"Manufacturing & Wholesale Goods"
        }
    ],
    "sg:phone":"+45 98 42 10 82",
    "sg:postcode":"9900",
    "sg:province":"Danmark",
    "sg:tags":[
        "wood"
    ],
    "wof:name":"RICHARD REINERT APS",
    "wof:placetype":"venue"
},
  "geometry": {"coordinates":[10.5089349747,57.4453468323],"type":"Point"}
}