{
  "type": "Feature",
  "properties": {
    "addr:full":"Fan\u00f8gade 11 Hirtshals Danmark 9850",
    "addr:housenumber":"11",
    "addr:postcode":"9850",
    "addr:street":"Fanogade",
    "iso:country":"DK",
    "sg:address":"Fan\u00f8gade 11",
    "sg:city":"Hirtshals",
    "sg:orig_category":"Menighedshuse",
    "sg:postcode":"9850",
    "sg:province":"Danmark",
    "wof:name":"Baptistmenighedens Ungdomshus",
    "wof:placetype":"venue"
},
  "geometry": {"coordinates":[9.9641017914,57.5853614807],"type":"Point"}
}