{
  "type": "Feature",
  "properties": {
    "addr:full":"Jernbanegade 4 S\u00f8nderborg Danmark 6400",
    "addr:housenumber":"4",
    "addr:postcode":"6400",
    "addr:street":"Jernbanegade",
    "iso:country":"DK",
    "sg:address":"Jernbanegade 4",
    "sg:city":"S\u00f8nderborg",
    "sg:orig_category":"Skomagere",
    "sg:phone":"+45 74 42 28 88",
    "sg:postcode":"6400",
    "sg:province":"Danmark",
    "sg:website":"www.sahva.dk",
    "wof:name":"Sahva H\u00e5ndskomageren",
    "wof:placetype":"venue"
},
  "geometry": {"coordinates":[9.7934846878,54.9107704163],"type":"Point"}
}