{
  "type": "Feature",
  "properties": {
    "addr:full":"Gartnertoften 29 Kastrup Danmark 2770",
    "addr:housenumber":"29",
    "addr:postcode":"2770",
    "addr:street":"Gartnertoften",
    "iso:country":"DK",
    "sg:address":"Gartnertoften 29",
    "sg:city":"Kastrup",
    "sg:orig_category":"Ejendomsservice",
    "sg:phone":"+45 32 50 74 75",
    "sg:postcode":"2770",
    "sg:province":"Danmark",
    "wof:name":"T\u00e5rnby Ejendomsservice",
    "wof:placetype":"venue"
},
  "geometry": {"coordinates":[12.6261148453,55.6206932068],"type":"Point"}
}