{
  "type": "Feature",
  "properties": {
    "addr:full":"Bregentved All\u00e9 2 Gentofte Danmark 2820",
    "addr:housenumber":"2",
    "addr:postcode":"2820",
    "addr:street":"Bregentved Alle\u0301",
    "iso:country":"DK",
    "sg:address":"Bregentved All\u00e9 2",
    "sg:city":"Gentofte",
    "sg:orig_category":"Skolefritidsordninger",
    "sg:phone":"+45 39 65 77 75",
    "sg:postcode":"2820",
    "sg:province":"Danmark",
    "wof:name":"Gentofte Fritidscenter",
    "wof:placetype":"venue"
},
  "geometry": {"coordinates":[12.5472240448,55.7434463501],"type":"Point"}
}