{
  "type": "Feature",
  "properties": {
    "addr:full":"Fmd.: John Lundberg, S\u00f8ndervangen 59 Viby Danmark 8260",
    "addr:housenumber":"59",
    "addr:postcode":"8260",
    "addr:street":"Sondervangen",
    "iso:country":"DK",
    "sg:address":"Fmd.: John Lundberg, S\u00f8ndervangen 59",
    "sg:city":"Viby",
    "sg:orig_category":"Kolonihaveforeninger",
    "sg:phone":"+45 86 11 07 84",
    "sg:postcode":"8260",
    "sg:province":"Danmark",
    "wof:name":"Haveforeningen af 1940",
    "wof:placetype":"venue"
},
  "geometry": {"coordinates":[10.1164493561,56.1353530884],"type":"Point"}
}