{
  "type": "Feature",
  "properties": {
    "addr:full":"Roers All\u00e9 2, Tarup Odense NV Danmark 5210",
    "addr:housenumber":"2",
    "addr:postcode":"5210",
    "addr:street":"Roers Alle\u0301",
    "iso:country":"DK",
    "sg:address":"Roers All\u00e9 2, Tarup",
    "sg:city":"Odense NV",
    "sg:orig_category":"Bijouterier",
    "sg:phone":"+45 66 16 02 24",
    "sg:postcode":"5210",
    "sg:province":"Danmark",
    "wof:name":"Andersen, Charlotte",
    "wof:placetype":"venue"
},
  "geometry": {"coordinates":[10.274764,55.430332],"type":"Point"}
}