{
  "type": "Feature",
  "properties": {
    "iso:country":"DK",
    "sg:address":"Sct. Hansgade 39",
    "sg:city":"Ringsted",
    "sg:orig_category":"Slagter og viktualie",
    "sg:phone":"+45 57 61 04 34",
    "sg:postcode":"4100",
    "sg:province":"Danmark",
    "wof:name":"Slagterg\u00e5rden Aps",
    "wof:placetype":"venue"
},
  "geometry": {"coordinates":[11.7928848267,55.4432144165],"type":"Point"}
}