{
  "type": "Feature",
  "properties": {
    "addr:full":"Essen 4  Kolding Danmark 6000",
    "addr:housenumber":"4",
    "addr:postcode":"6000",
    "addr:street":"Essen",
    "iso:country":"DK",
    "sg:address":"Essen 4 ",
    "sg:city":"Kolding",
    "sg:classifiers":[
        {
            "category":"Building & Trades",
            "subcategory":"Construction",
            "type":"Services"
        }
    ],
    "sg:phone":"+45 75 56 63 44",
    "sg:postcode":"6000",
    "sg:province":"Danmark",
    "sg:tags":[
        "work",
        "public"
    ],
    "wof:name":"JORTON A/S ENTREPREN\u00d8R-MURER-INGENI\u00d8R",
    "wof:placetype":"venue"
},
  "geometry": {"coordinates":[9.4820632935,55.463684082],"type":"Point"}
}