{
  "type": "Feature",
  "properties": {
    "addr:full":"H\u00f8jvangen 2 Skanderborg Danmark 8660",
    "addr:housenumber":"2",
    "addr:postcode":"8660",
    "addr:street":"Hojvangen",
    "iso:country":"DK",
    "sg:address":"H\u00f8jvangen 2",
    "sg:city":"Skanderborg",
    "sg:orig_category":"Grillbarer",
    "sg:phone":"+45 86 51 20 44",
    "sg:postcode":"8660",
    "sg:province":"Danmark",
    "wof:name":"Grill House",
    "wof:placetype":"venue"
},
  "geometry": {"coordinates":[9.9479322433,56.0438346863],"type":"Point"}
}