{
  "type": "Feature",
  "properties": {
    "addr:full":"\u00d8stergade 6 - 8 Mariager Danmark 9550",
    "addr:housenumber":"6 8",
    "addr:postcode":"9550",
    "addr:street":"Ostergade",
    "iso:country":"DK",
    "sg:address":"\u00d8stergade 6 - 8",
    "sg:city":"Mariager",
    "sg:classifiers":[
        {
            "category":"Banks & Credit Unions",
            "subcategory":"Bank",
            "type":"Services"
        }
    ],
    "sg:phone":"+45 98 54 14 44",
    "sg:postcode":"9550",
    "sg:province":"Danmark",
    "sg:tags":[
        "banker"
    ],
    "sg:website":"www.oestjydskbank.dk",
    "wof:name":"\u00d8stjydsk Bank A/S",
    "wof:placetype":"venue"
},
  "geometry": {"coordinates":[9.982998848,56.6510047913],"type":"Point"}
}