{
  "type": "Feature",
  "properties": {
    "addr:full":"\u00d8sterbrogade 7 Faaborg Danmark 5600",
    "addr:housenumber":"7",
    "addr:postcode":"5600",
    "addr:street":"Osterbrogade",
    "iso:country":"DK",
    "sg:address":"\u00d8sterbrogade 7",
    "sg:city":"Faaborg",
    "sg:orig_category":"INGENI\u00c3\u02dcRER",
    "sg:phone":"+45 62 61 00 71",
    "sg:postcode":"5600",
    "sg:province":"Danmark",
    "wof:name":"Vett R\u00e5dg. Ingeni\u00f8rfirma F.R.I., J\u00f8rgen",
    "wof:placetype":"venue"
},
  "geometry": {"coordinates":[10.2478494644,55.0933494568],"type":"Point"}
}