{
  "type": "Feature",
  "properties": {
    "addr:full":"Skovs\u00f8gade 1 Slagelse Danmark 4200",
    "addr:housenumber":"1",
    "addr:postcode":"4200",
    "addr:street":"Skovsogade",
    "iso:country":"DK",
    "sg:address":"Skovs\u00f8gade 1",
    "sg:city":"Slagelse",
    "sg:orig_category":"Advokater",
    "sg:phone":"+45 58 52 02 41",
    "sg:postcode":"4200",
    "sg:province":"Danmark",
    "wof:name":"Larsen (L) & Helge S.Poulsen (H), S\u00f8ren",
    "wof:placetype":"venue"
},
  "geometry": {"coordinates":[11.3554458618,55.4030914307],"type":"Point"}
}