{
  "type": "Feature",
  "properties": {
    "addr:full":"\u00c5lborgvej 30 Hals Danmark 9370",
    "addr:housenumber":"30",
    "addr:postcode":"9370",
    "addr:street":"Aalborgvej",
    "iso:country":"DK",
    "sg:address":"\u00c5lborgvej 30",
    "sg:city":"Hals",
    "sg:orig_category":"Fodplejere",
    "sg:phone":"+45 98 25 22 21",
    "sg:postcode":"9370",
    "sg:province":"Danmark",
    "wof:name":"Clausen, Tina Groes",
    "wof:placetype":"venue"
},
  "geometry": {"coordinates":[10.3053197861,56.9990119934],"type":"Point"}
}