{
  "type": "Feature",
  "properties": {
    "addr:full":"Frederiksberggade 67 Silkeborg Danmark 8600",
    "addr:housenumber":"67",
    "addr:postcode":"8600",
    "addr:street":"Frederiksberggade",
    "iso:country":"DK",
    "sg:address":"Frederiksberggade 67",
    "sg:city":"Silkeborg",
    "sg:classifiers":[
        {
            "category":"Communications",
            "subcategory":"Film & Video Production",
            "type":"Services"
        }
    ],
    "sg:phone":"+45 86 82 05 37",
    "sg:postcode":"8600",
    "sg:province":"Danmark",
    "sg:tags":[
        "radio-",
        "og",
        "tv-service"
    ],
    "wof:name":"Madsens TV Service",
    "wof:placetype":"venue"
},
  "geometry": {"coordinates":[9.550075531,56.1590919495],"type":"Point"}
}