{
  "type": "Feature",
  "properties": {
    "addr:full":"V\u00e6rksted og kontor, Tjalkavej 7 Melby Danmark 3370",
    "addr:housenumber":"7",
    "addr:postcode":"3370",
    "addr:street":"Tjalkavej",
    "iso:country":"DK",
    "sg:address":"V\u00e6rksted og kontor, Tjalkavej 7",
    "sg:city":"Melby",
    "sg:orig_category":"Malermestre",
    "sg:phone":"+45 47 92 40 30",
    "sg:postcode":"3370",
    "sg:province":"Danmark",
    "sg:website":"www.sv-aa-sorensen.dk",
    "wof:name":"S\u00f8rensen A/S, Sv. Aage",
    "wof:placetype":"venue"
},
  "geometry": {"coordinates":[11.9925775528,55.9966087341],"type":"Point"}
}