{
  "type": "Feature",
  "properties": {
    "iso:country":"DK",
    "sg:address":"Spanien 19 C, th.",
    "sg:city":"\u00c5rhus C",
    "sg:orig_category":"Billedhuggere",
    "sg:phone":"+45 86 19 19 37",
    "sg:postcode":"8000",
    "sg:province":"Danmark",
    "wof:name":"Steen-Andersen, Gudrun",
    "wof:placetype":"venue"
},
  "geometry": {"coordinates":[-2.98868,39.89502],"type":"Point"}
}