{
  "type": "Feature",
  "properties": {
    "addr:full":"Brogade 37 Svendborg Danmark 5700",
    "addr:housenumber":"37",
    "addr:postcode":"5700",
    "addr:street":"Brogade",
    "iso:country":"DK",
    "sg:address":"Brogade 37",
    "sg:city":"Svendborg",
    "sg:classifiers":[
        {
            "category":"Food & Beverages",
            "subcategory":"Liquor & Beverages",
            "type":"Retail Goods"
        }
    ],
    "sg:phone":"+45 62 22 34 48",
    "sg:postcode":"5700",
    "sg:province":"Danmark",
    "sg:tags":[
        "vin"
    ],
    "wof:name":"Vintapperiet",
    "wof:placetype":"venue"
},
  "geometry": {"coordinates":[10.6106386185,55.0585403442],"type":"Point"}
}