{
  "type": "Feature",
  "properties": {
    "addr:full":"Sleipnersvej 11 Silkeborg Danmark 8600",
    "addr:housenumber":"11",
    "addr:postcode":"8600",
    "addr:street":"Sleipnersvej",
    "iso:country":"DK",
    "sg:address":"Sleipnersvej 11",
    "sg:city":"Silkeborg",
    "sg:orig_category":"Musikinstrumenter",
    "sg:phone":"+45 86 82 11 17",
    "sg:postcode":"8600",
    "sg:province":"Danmark",
    "wof:name":"Dansk Musik Center",
    "wof:placetype":"venue"
},
  "geometry": {"coordinates":[9.5094861984,56.1699562073],"type":"Point"}
}