{
  "type": "Feature",
  "properties": {
    "addr:full":"N\u00f8rregade 2 Grindsted Danmark 7200",
    "addr:housenumber":"2",
    "addr:postcode":"7200",
    "addr:street":"Norregade",
    "iso:country":"DK",
    "sg:address":"N\u00f8rregade 2",
    "sg:city":"Grindsted",
    "sg:orig_category":"Advokater",
    "sg:phone":"+45 75 32 28 33",
    "sg:postcode":"7200",
    "sg:province":"Danmark",
    "wof:name":"Pedersen, Helge",
    "wof:placetype":"venue"
},
  "geometry": {"coordinates":[8.9272603989,55.7573699951],"type":"Point"}
}