{
  "type": "Feature",
  "properties": {
    "addr:full":"Jyllandsgade 20 Fredericia Danmark 7000",
    "addr:housenumber":"20",
    "addr:postcode":"7000",
    "addr:street":"Jyllandsgade",
    "iso:country":"DK",
    "sg:address":"Jyllandsgade 20",
    "sg:city":"Fredericia",
    "sg:orig_category":"Tandklinikker, Kommunale",
    "sg:phone":"+45 72 10 67 30",
    "sg:postcode":"7000",
    "sg:province":"Danmark",
    "wof:name":"Fredericia Kommunale Tandpleje",
    "wof:placetype":"venue"
},
  "geometry": {"coordinates":[9.7579221725,55.5655136108],"type":"Point"}
}