{
  "type": "Feature",
  "properties": {
    "addr:full":"Korsk\u00e6rvej 25 Fredericia Danmark 7000",
    "addr:housenumber":"25",
    "addr:postcode":"7000",
    "addr:street":"Korskaervej",
    "iso:country":"DK",
    "sg:address":"Korsk\u00e6rvej 25",
    "sg:city":"Fredericia",
    "sg:orig_category":"Kirkelige foreninger",
    "sg:phone":"+45 75 92 61 00",
    "sg:postcode":"7000",
    "sg:province":"Danmark",
    "sg:website":"www.indremission.dk",
    "wof:name":"Kirkelig Forening for Indre Mission i Danmark",
    "wof:placetype":"venue"
},
  "geometry": {"coordinates":[9.7170267105,55.570350647],"type":"Point"}
}