{
  "type": "Feature",
  "properties": {
    "addr:full":"Veddum Hovedgade 42, Veddum Hadsund Danmark 9560",
    "addr:housenumber":"42",
    "addr:postcode":"9560",
    "addr:street":"Veddum Hovedgade",
    "iso:country":"DK",
    "sg:address":"Veddum Hovedgade 42, Veddum",
    "sg:city":"Hadsund",
    "sg:orig_category":"Ungdomsklubber",
    "sg:phone":"+45 98 58 54 38",
    "sg:postcode":"9560",
    "sg:province":"Danmark",
    "wof:name":"Veddum-Skelund Ungdoms- Og Juniorklub",
    "wof:placetype":"venue"
},
  "geometry": {"coordinates":[10.115904808,56.7150764465],"type":"Point"}
}