{
  "type": "Feature",
  "properties": {
    "addr:full":"Graabjergvej 3 A Ryslinge Danmark 5856",
    "addr:housenumber":"3 a",
    "addr:postcode":"5856",
    "addr:street":"Graabjergvej",
    "iso:country":"DK",
    "sg:address":"Graabjergvej 3 A",
    "sg:city":"Ryslinge",
    "sg:orig_category":"Dagplejeformidling",
    "sg:phone":"+45 63 67 57 40",
    "sg:postcode":"5856",
    "sg:province":"Danmark",
    "wof:name":"Dagplejeformidlingen",
    "wof:placetype":"venue"
},
  "geometry": {"coordinates":[10.5324344635,55.2319641113],"type":"Point"}
}