{
  "type": "Feature",
  "properties": {
    "addr:full":"Nytorv 2 Viborg Danmark 8800",
    "addr:housenumber":"2",
    "addr:postcode":"8800",
    "addr:street":"Nytorv",
    "iso:country":"DK",
    "sg:address":"Nytorv 2",
    "sg:city":"Viborg",
    "sg:orig_category":"Ejendomshandel",
    "sg:phone":"+45 86 61 38 38",
    "sg:postcode":"8800",
    "sg:province":"Danmark",
    "sg:website":"www.danbolig.dk",
    "wof:name":"DanBolig",
    "wof:placetype":"venue"
},
  "geometry": {"coordinates":[9.2260465622,56.4748077393],"type":"Point"}
}