{
  "type": "Feature",
  "properties": {
    "addr:full":"Knuthenborgvej 24 Valby Danmark 2500",
    "addr:housenumber":"24",
    "addr:postcode":"2500",
    "addr:street":"Knuthenborgvej",
    "iso:country":"DK",
    "sg:address":"Knuthenborgvej 24",
    "sg:city":"Valby",
    "sg:orig_category":"Foreninger og organisationer",
    "sg:phone":"+45 36 16 46 00",
    "sg:postcode":"2500",
    "sg:province":"Danmark",
    "wof:name":"K\u00f8benhavns Funktion\u00e6r Idr\u00e6ts Union, KFIU",
    "wof:placetype":"venue"
},
  "geometry": {"coordinates":[12.4893913269,55.6683197021],"type":"Point"}
}