{
  "type": "Feature",
  "properties": {
    "addr:full":"Kongensgade 84 Esbjerg Danmark 6700",
    "addr:housenumber":"84",
    "addr:postcode":"6700",
    "addr:street":"Kongensgade",
    "iso:country":"DK",
    "sg:address":"Kongensgade 84",
    "sg:city":"Esbjerg",
    "sg:orig_category":"Sko",
    "sg:phone":"+45 75 13 60 44",
    "sg:postcode":"6700",
    "sg:province":"Danmark",
    "wof:name":"Venini",
    "wof:placetype":"venue"
},
  "geometry": {"coordinates":[8.446097374,55.466506958],"type":"Point"}
}