{
  "type": "Feature",
  "properties": {
    "addr:full":"Export Vej 3  Padborg Danmark 6330",
    "addr:housenumber":"3",
    "addr:postcode":"6330",
    "addr:street":"Export Vej",
    "iso:country":"DK",
    "sg:address":"Export Vej 3 ",
    "sg:city":"Padborg",
    "sg:classifiers":[
        {
            "category":"Banks & Credit Unions",
            "subcategory":"Investment Brokerage",
            "type":"Services"
        }
    ],
    "sg:phone":"+45 73 30 35 89",
    "sg:postcode":"6330",
    "sg:province":"Danmark",
    "sg:tags":[
        "-",
        "transport",
        "related"
    ],
    "wof:name":"K\u00dcHNE & NAGEL A/S",
    "wof:placetype":"venue"
},
  "geometry": {"coordinates":[9.3522472382,54.8346595764],"type":"Point"}
}