{
  "type": "Feature",
  "properties": {
    "addr:full":"Otiumvej 7 Aalborg Danmark 9000",
    "addr:housenumber":"7",
    "addr:postcode":"9000",
    "addr:street":"Otiumvej",
    "iso:country":"DK",
    "sg:address":"Otiumvej 7",
    "sg:city":"Aalborg",
    "sg:orig_category":"Plejehjemsboliger",
    "sg:phone":"+45 98 18 03 56",
    "sg:postcode":"9000",
    "sg:province":"Danmark",
    "wof:name":"Otiumg\u00e5rden",
    "wof:placetype":"venue"
},
  "geometry": {"coordinates":[9.8923778534,57.0336418152],"type":"Point"}
}