{
  "type": "Feature",
  "properties": {
    "addr:full":"Storegade 35 Glums\u00f8 Danmark 4171",
    "addr:housenumber":"35",
    "addr:postcode":"4171",
    "addr:street":"Storegade",
    "iso:country":"DK",
    "sg:address":"Storegade 35",
    "sg:city":"Glums\u00f8",
    "sg:orig_category":"Malermestre",
    "sg:phone":"+45 57 64 66 97",
    "sg:postcode":"4171",
    "sg:province":"Danmark",
    "sg:website":"www.naalund.dk",
    "wof:name":"Naalund A/S, Lars",
    "wof:placetype":"venue"
},
  "geometry": {"coordinates":[11.6865577698,55.3549919128],"type":"Point"}
}