{
  "type": "Feature",
  "properties": {
    "addr:full":"Fortuna Alle 88 Esbjerg \u00d8 Danmark 6705",
    "addr:housenumber":"88",
    "addr:postcode":"6705",
    "addr:street":"Fortuna Alle;Danmark",
    "iso:country":"DK",
    "sg:address":"Fortuna Alle 88",
    "sg:city":"Esbjerg \u00d8",
    "sg:orig_category":"Vinduespolering",
    "sg:phone":"+45 40 91 76 26",
    "sg:postcode":"6705",
    "sg:province":"Danmark",
    "wof:name":"M's Reng\u00f8ring & Vinduespolering",
    "wof:placetype":"venue"
},
  "geometry": {"coordinates":[8.4823160172,55.4812088013],"type":"Point"}
}