{
  "type": "Feature",
  "properties": {
    "addr:full":"Pr\u00e6steg\u00e5rdsvejen 2, Vestermarie R\u00f8nne Danmark 3700",
    "addr:housenumber":"2",
    "addr:postcode":"3700",
    "addr:street":"Praestegaardsvejen",
    "iso:country":"DK",
    "sg:address":"Pr\u00e6steg\u00e5rdsvejen 2, Vestermarie",
    "sg:city":"R\u00f8nne",
    "sg:orig_category":"Arkitekter",
    "sg:phone":"+45 56 99 00 99",
    "sg:postcode":"3700",
    "sg:province":"Danmark",
    "wof:name":"Ipsen, Mogens",
    "wof:placetype":"venue"
},
  "geometry": {"coordinates":[14.6975498199,55.0993003845],"type":"Point"}
}