{
  "type": "Feature",
  "properties": {
    "addr:full":"Kongevejen 27 Holte Danmark 2840",
    "addr:housenumber":"27",
    "addr:postcode":"2840",
    "addr:street":"Kongevejen",
    "iso:country":"DK",
    "sg:address":"Kongevejen 27",
    "sg:city":"Holte",
    "sg:orig_category":"Glarmestre og glarmagere",
    "sg:phone":"+45 45 42 02 20",
    "sg:postcode":"2840",
    "sg:province":"Danmark",
    "wof:name":"Hansen & S\u00f8n, H.",
    "wof:placetype":"venue"
},
  "geometry": {"coordinates":[12.4712400436,55.812789917],"type":"Point"}
}