{
  "type": "Feature",
  "properties": {
    "addr:full":"Kongensgade 11 Christiansfeld Danmark 6070",
    "addr:housenumber":"11",
    "addr:postcode":"6070",
    "addr:street":"Kongensgade",
    "iso:country":"DK",
    "sg:address":"Kongensgade 11",
    "sg:city":"Christiansfeld",
    "sg:orig_category":"Blomsterhandlere",
    "sg:phone":"+45 74 56 25 40",
    "sg:postcode":"6070",
    "sg:province":"Danmark",
    "wof:name":"Anemonen",
    "wof:placetype":"venue"
},
  "geometry": {"coordinates":[9.4823703766,55.3645401001],"type":"Point"}
}