{
  "type": "Feature",
  "properties": {
    "addr:full":"Ydingvej 25, Yding \u00d8stbirk Danmark 8752",
    "addr:housenumber":"25",
    "addr:postcode":"8752",
    "addr:street":"Ydingvej",
    "iso:country":"DK",
    "sg:address":"Ydingvej 25, Yding",
    "sg:city":"\u00d8stbirk",
    "sg:orig_category":"Produkthandlere",
    "sg:phone":"+45 75 78 24 77",
    "sg:postcode":"8752",
    "sg:province":"Danmark",
    "wof:name":"Skanderborg Produkthandel",
    "wof:placetype":"venue"
},
  "geometry": {"coordinates":[9.7709598541,56.0007743835],"type":"Point"}
}