{
  "type": "Feature",
  "properties": {
    "addr:full":"\u00d8stergade 30 Lemvig Danmark 7620",
    "addr:housenumber":"30",
    "addr:postcode":"7620",
    "addr:street":"Ostergade",
    "iso:country":"DK",
    "sg:address":"\u00d8stergade 30",
    "sg:city":"Lemvig",
    "sg:orig_category":"Offentlige sygehuse",
    "sg:phone":"+45 96 63 47 00",
    "sg:postcode":"7620",
    "sg:province":"Danmark",
    "wof:name":"Lemvig Sygehus.",
    "wof:placetype":"venue"
},
  "geometry": {"coordinates":[8.3149032593,56.5499954224],"type":"Point"}
}