{
  "type": "Feature",
  "properties": {
    "addr:full":"v/ Henning Schou, Steen Blicher Vej 32 Bredsten Danmark 7182",
    "addr:housenumber":"32",
    "addr:postcode":"7182",
    "addr:street":"Steen Blicher Vej",
    "iso:country":"DK",
    "sg:address":"v/ Henning Schou, Steen Blicher Vej 32",
    "sg:city":"Bredsten",
    "sg:orig_category":"\u00c3\u2020ldreorganisationer og klubber",
    "sg:phone":"+45 75 88 10 72",
    "sg:postcode":"7182",
    "sg:province":"Danmark",
    "wof:name":"Bredsten Pensionistforening Klub 89",
    "wof:placetype":"venue"
},
  "geometry": {"coordinates":[9.3807411194,55.702331543],"type":"Point"}
}