{
  "type": "Feature",
  "properties": {
    "addr:full":"Aalborgvej 8, Mou Storvorde Danmark 9280",
    "addr:housenumber":"8",
    "addr:postcode":"9280",
    "addr:street":"Aalborgvej",
    "iso:country":"DK",
    "sg:address":"Aalborgvej 8, Mou",
    "sg:city":"Storvorde",
    "sg:orig_category":"Ejendomshandel",
    "sg:phone":"+45 98 31 15 77",
    "sg:postcode":"9280",
    "sg:province":"Danmark",
    "sg:website":"www.realmaeglerne.dk",
    "wof:name":"Cortsen, Hans",
    "wof:placetype":"venue"
},
  "geometry": {"coordinates":[10.1014204025,57.0045547485],"type":"Point"}
}