{
  "type": "Feature",
  "properties": {
    "iso:country":"DK",
    "sg:address":"Oesterbrogade ",
    "sg:classifiers":[
        {
            "category":"Banks & Credit Unions",
            "subcategory":"Bank",
            "type":"Services"
        }
    ],
    "sg:phone":"+45 98 67 17 77",
    "sg:postcode":"19",
    "wof:name":"Unibank A/S",
    "wof:placetype":"venue"
},
  "geometry": {"coordinates":[9.252663,56.967903],"type":"Point"}
}