{
  "type": "Feature",
  "properties": {
    "addr:full":"Marielundvej 46 D Herlev Danmark 2730",
    "addr:housenumber":"46 d",
    "addr:postcode":"2730",
    "addr:street":"Marielundvej",
    "iso:country":"DK",
    "sg:address":"Marielundvej 46 D",
    "sg:city":"Herlev",
    "sg:orig_category":"Prepress",
    "sg:phone":"+45 44 85 89 49",
    "sg:postcode":"2730",
    "sg:province":"Danmark",
    "wof:name":"Tech Tegn A/S",
    "wof:placetype":"venue"
},
  "geometry": {"coordinates":[12.4278926849,55.7131996155],"type":"Point"}
}