{
  "type": "Feature",
  "properties": {
    "addr:full":"Gr\u00f8nnevej 112 Virum Danmark 2830",
    "addr:housenumber":"112",
    "addr:postcode":"2830",
    "addr:street":"Gronnevej",
    "iso:country":"DK",
    "sg:address":"Gr\u00f8nnevej 112",
    "sg:city":"Virum",
    "sg:orig_category":"Vuggestuer",
    "sg:phone":"+45 45 85 62 58",
    "sg:postcode":"2830",
    "sg:province":"Danmark",
    "wof:name":"B\u00f8rnereden Vuggestue",
    "wof:placetype":"venue"
},
  "geometry": {"coordinates":[12.4726381302,55.7916412354],"type":"Point"}
}