{
  "type": "Feature",
  "properties": {
    "addr:full":"B\u00f8ge All\u00e9 6-8  H\u00f8rsholm Danmark 2970",
    "addr:housenumber":"6-8",
    "addr:postcode":"2970",
    "addr:street":"Boge Alle\u0301",
    "iso:country":"DK",
    "sg:address":"B\u00f8ge All\u00e9 6-8 ",
    "sg:city":"H\u00f8rsholm",
    "sg:classifiers":[
        {
            "category":"Wholesale",
            "subcategory":"Drugs",
            "type":"Manufacturing & Wholesale Goods"
        }
    ],
    "sg:phone":"+45 45 74 74 45",
    "sg:postcode":"2970",
    "sg:province":"Danmark",
    "sg:tags":[
        "chemical",
        "pharmaceutical"
    ],
    "wof:name":"ALK-ABELLO A/S",
    "wof:placetype":"venue"
},
  "geometry": {"coordinates":[12.4879140854,55.8738136292],"type":"Point"}
}