{
  "type": "Feature",
  "properties": {
    "addr:full":"Gammel Kongevej 167 D Frederiksberg Danmark 1850",
    "addr:housenumber":"167 d",
    "addr:postcode":"1850",
    "addr:street":"Gammel Kongevej",
    "iso:country":"DK",
    "sg:address":"Gammel Kongevej 167 D",
    "sg:city":"Frederiksberg",
    "sg:classifiers":[
        {
            "category":"Communications",
            "type":"Services"
        }
    ],
    "sg:phone":"+45 33 24 40 44",
    "sg:postcode":"1850",
    "sg:province":"Danmark",
    "sg:tags":[
        "og",
        "tv",
        "radio"
    ],
    "wof:name":"Tonika Radio",
    "wof:placetype":"venue"
},
  "geometry": {"coordinates":[12.5353889465,55.6777000427],"type":"Point"}
}