{
  "type": "Feature",
  "properties": {
    "addr:full":"N\u00f8rre Boulevard 152 K\u00f8ge Danmark 4600",
    "addr:housenumber":"152",
    "addr:postcode":"4600",
    "addr:street":"Norre Boulevard",
    "iso:country":"DK",
    "sg:address":"N\u00f8rre Boulevard 152",
    "sg:city":"K\u00f8ge",
    "sg:orig_category":"Markiser",
    "sg:phone":"+45 56 66 22 11",
    "sg:postcode":"4600",
    "sg:province":"Danmark",
    "wof:name":"Miga Gardiner ApS",
    "wof:placetype":"venue"
},
  "geometry": {"coordinates":[-116.27327728269999,32.6635398865],"type":"Point"}
}