{
  "type": "Feature",
  "properties": {
    "addr:full":"Munkes\u00f8gade 3 Kalundborg Danmark 4400",
    "addr:housenumber":"3",
    "addr:postcode":"4400",
    "addr:street":"Munkesogade",
    "iso:country":"DK",
    "sg:address":"Munkes\u00f8gade 3",
    "sg:city":"Kalundborg",
    "sg:classifiers":[
        {
            "category":"Restaurant",
            "type":"Food & Drink"
        }
    ],
    "sg:phone":"+45 59 51 23 75",
    "sg:postcode":"4400",
    "sg:province":"Danmark",
    "wof:name":"Kalundborg Hallernes Restaurant",
    "wof:placetype":"venue"
},
  "geometry": {"coordinates":[11.0834197998,55.6806488037],"type":"Point"}
}