{
  "type": "Feature",
  "properties": {
    "iso:country":"DK",
    "sg:address":"Bilg\u00e5rdsvej 25",
    "sg:city":"Tylstrup",
    "sg:orig_category":"Genbrugsbutikker",
    "sg:phone":"+45 96 39 18 73",
    "sg:postcode":"9382",
    "sg:province":"Danmark",
    "wof:name":"ABC Genbrug og Antik",
    "wof:placetype":"venue"
},
  "geometry": {"coordinates":[9.9577474594,57.196647644],"type":"Point"}
}