{
  "type": "Feature",
  "properties": {
    "addr:full":"Rynkebyvej 238 Rynkeby Danmark 5350",
    "addr:housenumber":"238",
    "addr:postcode":"5350",
    "addr:street":"Rynkebyvej",
    "iso:country":"DK",
    "sg:address":"Rynkebyvej 238",
    "sg:city":"Rynkeby",
    "sg:orig_category":"Maskinfabrikker",
    "sg:phone":"+45 65 39 11 15",
    "sg:postcode":"5350",
    "sg:province":"Danmark",
    "wof:name":"Rynkeby Maskinfabrik A/S",
    "wof:placetype":"venue"
},
  "geometry": {"coordinates":[10.6239700317,55.4088973999],"type":"Point"}
}