{
  "type": "Feature",
  "properties": {
    "addr:full":"Reventlowsvej 50 Odense C Danmark 5000",
    "addr:housenumber":"50",
    "addr:postcode":"5000",
    "addr:street":"Reventlowsvej",
    "iso:country":"DK",
    "sg:address":"Reventlowsvej 50",
    "sg:city":"Odense C",
    "sg:classifiers":[
        {
            "category":"Communications",
            "type":"Services"
        }
    ],
    "sg:phone":"+45 66 11 47 10",
    "sg:postcode":"5000",
    "sg:province":"Danmark",
    "sg:tags":[
        "og",
        "tv",
        "radio"
    ],
    "wof:name":"O.K. Radio og TV",
    "wof:placetype":"venue"
},
  "geometry": {"coordinates":[10.4024486542,55.3923606873],"type":"Point"}
}