{
  "type": "Feature",
  "properties": {
    "addr:full":"S\u00f8ndergade 26 Fars\u00f8 Danmark 9640",
    "addr:housenumber":"26",
    "addr:postcode":"9640",
    "addr:street":"Sondergade",
    "iso:country":"DK",
    "sg:address":"S\u00f8ndergade 26",
    "sg:city":"Fars\u00f8",
    "sg:orig_category":"Pizzeriaer",
    "sg:phone":"+45 98 63 26 26",
    "sg:postcode":"9640",
    "sg:province":"Danmark",
    "wof:name":"Roma",
    "wof:placetype":"venue"
},
  "geometry": {"coordinates":[-109.44831848139999,42.1062355042],"type":"Point"}
}