{
  "type": "Feature",
  "properties": {
    "addr:full":"Baltorpvej 160 Ballerup Danmark 2750",
    "addr:housenumber":"160",
    "addr:postcode":"2750",
    "addr:street":"Baltorpvej",
    "iso:country":"DK",
    "sg:address":"Baltorpvej 160",
    "sg:city":"Ballerup",
    "sg:orig_category":"Maskinfabrikker",
    "sg:phone":"+45 44 89 02 00",
    "sg:postcode":"2750",
    "sg:province":"Danmark",
    "wof:name":"Atlas industries A/S",
    "wof:placetype":"venue"
},
  "geometry": {"coordinates":[12.3419246674,55.7288627625],"type":"Point"}
}