{
  "type": "Feature",
  "properties": {
    "addr:full":"Fmd.: Erling Truelsen, Gyntelsbjerg 9 Faaborg Danmark 5600",
    "addr:housenumber":"9",
    "addr:postcode":"5600",
    "addr:street":"Erling Truelsen Gyntelsbjerg",
    "iso:country":"DK",
    "sg:address":"Fmd.: Erling Truelsen, Gyntelsbjerg 9",
    "sg:city":"Faaborg",
    "sg:orig_category":"Kolonihaveforeninger",
    "sg:phone":"+45 62 61 33 37",
    "sg:postcode":"5600",
    "sg:province":"Danmark",
    "wof:name":"Haveselskabet Pr\u00e6stevangen",
    "wof:placetype":"venue"
},
  "geometry": {"coordinates":[10.2400531769,55.0950622559],"type":"Point"}
}