{
  "type": "Feature",
  "properties": {
    "addr:full":"Uslev Markvej 171, Bjergby Hj\u00f8rring Danmark 9800",
    "addr:housenumber":"171",
    "addr:postcode":"9800",
    "addr:street":"Uslev Markvej;Bjergby Hjorring Danmark",
    "iso:country":"DK",
    "sg:address":"Uslev Markvej 171, Bjergby",
    "sg:city":"Hj\u00f8rring",
    "sg:orig_category":"Forsikringer",
    "sg:phone":"+45 96 24 91 75",
    "sg:postcode":"9800",
    "sg:province":"Danmark",
    "wof:name":"Topdanmark A/S",
    "wof:placetype":"venue"
},
  "geometry": {"coordinates":[9.9885387421,57.4594764709],"type":"Point"}
}