{
  "type": "Feature",
  "properties": {
    "addr:full":"Fmd.: Erik Storgaard Rasmussen, Hvissingeparken 24 Glostrup Danmark 2600",
    "addr:housenumber":"24",
    "addr:postcode":"2600",
    "addr:street":"Hvissingeparken",
    "iso:country":"DK",
    "sg:address":"Fmd.: Erik Storgaard Rasmussen, Hvissingeparken 24",
    "sg:city":"Glostrup",
    "sg:orig_category":"Grundejerforeninger",
    "sg:phone":"+45 43 45 41 42",
    "sg:postcode":"2600",
    "sg:province":"Danmark",
    "wof:name":"Hvissingeparken",
    "wof:placetype":"venue"
},
  "geometry": {"coordinates":[12.3957901001,55.6654663086],"type":"Point"}
}