{
  "type": "Feature",
  "properties": {
    "iso:country":"DK",
    "sg:address":"Formervangen 28 ",
    "sg:city":"Glostrup",
    "sg:classifiers":[
        {
            "category":"Wholesale",
            "subcategory":"Drugs",
            "type":"Manufacturing & Wholesale Goods"
        }
    ],
    "sg:phone":"+45 43 29 94 00",
    "sg:postcode":"2600",
    "sg:province":"Danmark",
    "sg:tags":[
        "chemical",
        "pharmaceutical"
    ],
    "wof:name":"DOMS A/S",
    "wof:placetype":"venue"
},
  "geometry": {"coordinates":[12.3720960617,55.6815986633],"type":"Point"}
}