{
  "type": "Feature",
  "properties": {
    "addr:full":"Fmd.: Hans Kr. \u00d8stergaard, Horsbjergvej 32, Lindet Give Danmark 7323",
    "addr:housenumber":"32",
    "addr:postcode":"7323",
    "addr:street":"Kr. Ostergaard Horsbjergvej;Lindet",
    "iso:country":"DK",
    "sg:address":"Fmd.: Hans Kr. \u00d8stergaard, Horsbjergvej 32, Lindet",
    "sg:city":"Give",
    "sg:orig_category":"Kirkelige foreninger",
    "sg:phone":"+45 75 73 60 81",
    "sg:postcode":"7323",
    "sg:province":"Danmark",
    "wof:name":"Give Soldatervennekreds, KFUMs Soldatermission",
    "wof:placetype":"venue"
},
  "geometry": {"coordinates":[9.2362060547,55.845413208],"type":"Point"}
}