{
  "type": "Feature",
  "properties": {
    "addr:full":"Damgade 7 Assens Danmark 5610",
    "addr:housenumber":"7",
    "addr:postcode":"5610",
    "addr:street":"Damgade",
    "iso:country":"DK",
    "sg:address":"Damgade 7",
    "sg:city":"Assens",
    "sg:orig_category":"Pizzeriaer",
    "sg:phone":"+45 64 71 49 71",
    "sg:postcode":"5610",
    "sg:province":"Danmark",
    "wof:name":"Pizza Express",
    "wof:placetype":"venue"
},
  "geometry": {"coordinates":[9.8931827545,55.2702064514],"type":"Point"}
}