{
  "type": "Feature",
  "properties": {
    "addr:full":"S\u00f8ndergade 65 Hundested Danmark 3390",
    "addr:housenumber":"65",
    "addr:postcode":"3390",
    "addr:street":"Sondergade",
    "iso:country":"DK",
    "sg:address":"S\u00f8ndergade 65",
    "sg:city":"Hundested",
    "sg:orig_category":"Arkitekter",
    "sg:phone":"+45 47 98 30 40",
    "sg:postcode":"3390",
    "sg:province":"Danmark",
    "wof:name":"Lyn\u00e6s Tegnestue",
    "wof:placetype":"venue"
},
  "geometry": {"coordinates":[11.8530349731,55.958530426],"type":"Point"}
}