{
  "type": "Feature",
  "properties": {
    "addr:full":"Hemmed Kirkevej 5, Hemmed Glesborg Danmark 8585",
    "addr:housenumber":"5",
    "addr:postcode":"8585",
    "addr:street":"Hemmed Kirkevej;Hemmed",
    "iso:country":"DK",
    "sg:address":"Hemmed Kirkevej 5, Hemmed",
    "sg:city":"Glesborg",
    "sg:orig_category":"Malermestre",
    "sg:phone":"+45 86 38 37 33",
    "sg:postcode":"8585",
    "sg:province":"Danmark",
    "wof:name":"Hemmed Malerfirma",
    "wof:placetype":"venue"
},
  "geometry": {"coordinates":[10.5884723663,56.5124320984],"type":"Point"}
}