{
  "type": "Feature",
  "properties": {
    "addr:full":"Strandgade 4 Nex\u00f8 Danmark 3730",
    "addr:housenumber":"4",
    "addr:postcode":"3730",
    "addr:street":"Strandgade",
    "iso:country":"DK",
    "sg:address":"Strandgade 4",
    "sg:city":"Nex\u00f8",
    "sg:orig_category":"Kiosker",
    "sg:phone":"+45 56 49 22 45",
    "sg:postcode":"3730",
    "sg:province":"Danmark",
    "sg:website":"www.torvetskiosk.dk",
    "wof:name":"Torvets Kiosk",
    "wof:placetype":"venue"
},
  "geometry": {"coordinates":[15.1329832077,55.0628433228],"type":"Point"}
}