{
  "type": "Feature",
  "properties": {
    "iso:country":"DK",
    "sg:address":"Fmd.: Lilly Jensen, Pr\u00f8vensvej 16, Stenbjerg",
    "sg:city":"Snedsted",
    "sg:orig_category":"Borger- og beboerforeninger",
    "sg:phone":"+45 97 93 84 89",
    "sg:postcode":"7752",
    "sg:province":"Danmark",
    "wof:name":"Stenbjerg Beboerforening",
    "wof:placetype":"venue"
},
  "geometry": {"coordinates":[8.5276002884,56.8460388184],"type":"Point"}
}