{
  "type": "Feature",
  "properties": {
    "addr:full":"v/ Landpolitiassistent Steen K. Gunnarson, H\u00f8gevej 5, Kongsted R\u00f8nnede Danmark 4683",
    "addr:housenumber":"5",
    "addr:postcode":"4683",
    "addr:street":"K. Gunnarson Hogevej",
    "iso:country":"DK",
    "sg:address":"v/ Landpolitiassistent Steen K. Gunnarson, H\u00f8gevej 5, Kongsted",
    "sg:city":"R\u00f8nnede",
    "sg:orig_category":"Politi",
    "sg:phone":"+45 56 71 15 79",
    "sg:postcode":"4683",
    "sg:province":"Danmark",
    "wof:name":"Landpolitistationen i R\u00f8nnede",
    "wof:placetype":"venue"
},
  "geometry": {"coordinates":[12.040017128,55.2451210022],"type":"Point"}
}