{
  "type": "Feature",
  "properties": {
    "addr:full":"Ryttervejen 2, Aasum Odense N\u00d8 Danmark 5240",
    "addr:housenumber":"2",
    "addr:postcode":"5240",
    "addr:street":"Ryttervejen;Aasum",
    "iso:country":"DK",
    "sg:address":"Ryttervejen 2, Aasum",
    "sg:city":"Odense N\u00d8",
    "sg:orig_category":"Kirker",
    "sg:postcode":"5240",
    "sg:province":"Danmark",
    "wof:name":"\u00c5sum Kirke",
    "wof:placetype":"venue"
},
  "geometry": {"coordinates":[10.444185257,55.4261131287],"type":"Point"}
}