{
  "type": "Feature",
  "properties": {
    "iso:country":"DK",
    "sg:address":"M\u00f8gelholtvej 70, Als",
    "sg:city":"Hadsund",
    "sg:orig_category":"Antikviteter",
    "sg:phone":"+45 98 58 20 21",
    "sg:postcode":"9560",
    "sg:province":"Danmark",
    "wof:name":"Fidus Antik",
    "wof:placetype":"venue"
},
  "geometry": {"coordinates":[10.115904808,56.7150764465],"type":"Point"}
}