{
  "type": "Feature",
  "properties": {
    "addr:full":"Gammelting 1 Haderslev Danmark 6100",
    "addr:housenumber":"1",
    "addr:postcode":"6100",
    "addr:street":"Gammelting",
    "iso:country":"DK",
    "sg:address":"Gammelting 1",
    "sg:city":"Haderslev",
    "sg:orig_category":"Skifteret",
    "sg:phone":"+45 73 52 38 26",
    "sg:postcode":"6100",
    "sg:province":"Danmark",
    "wof:name":"Skifteretten i Haderslev.",
    "wof:placetype":"venue"
},
  "geometry": {"coordinates":[9.4893321991,55.253742218],"type":"Point"}
}