{
  "type": "Feature",
  "properties": {
    "addr:full":"Ahornvej 17 Vamdrup Danmark 6580",
    "addr:housenumber":"17",
    "addr:postcode":"6580",
    "addr:street":"Ahornvej",
    "iso:country":"DK",
    "sg:address":"Ahornvej 17",
    "sg:city":"Vamdrup",
    "sg:orig_category":"Delikatesser",
    "sg:phone":"+45 20 14 28 83",
    "sg:postcode":"6580",
    "sg:province":"Danmark",
    "wof:name":"Kandi",
    "wof:placetype":"venue"
},
  "geometry": {"coordinates":[9.2988739014,55.4231872559],"type":"Point"}
}