{
  "type": "Feature",
  "properties": {
    "addr:full":"Adventkirken, Absalonsgade 18 Slagelse Danmark 4200",
    "addr:housenumber":"18",
    "addr:postcode":"4200",
    "addr:street":"Absalonsgade",
    "iso:country":"DK",
    "sg:address":"Adventkirken, Absalonsgade 18",
    "sg:city":"Slagelse",
    "sg:orig_category":"Trossamfund uden for folkekirken",
    "sg:phone":"+45 59 46 55 75",
    "sg:postcode":"4200",
    "sg:province":"Danmark",
    "wof:name":"Adventistsamfundet",
    "wof:placetype":"venue"
},
  "geometry": {"coordinates":[11.3569850922,55.4050865173],"type":"Point"}
}