{
  "type": "Feature",
  "properties": {
    "addr:full":"Ryesgade 3 A, 3. sal K\u00f8benhavn N Danmark 2200",
    "addr:housenumber":"3 a 3 sal",
    "addr:postcode":"2200",
    "addr:street":"Ryesgade;Kobenhavn N Danmark",
    "iso:country":"DK",
    "sg:address":"Ryesgade 3 A, 3. sal",
    "sg:city":"K\u00f8benhavn N",
    "sg:orig_category":"Fabrikker",
    "sg:phone":"+45 35 35 43 30",
    "sg:postcode":"2200",
    "sg:province":"Danmark",
    "wof:name":"Fjernsynsfabrikken",
    "wof:placetype":"venue"
},
  "geometry": {"coordinates":[-81.1823883057,33.6566963196],"type":"Point"}
}