{
  "type": "Feature",
  "properties": {
    "addr:full":"Skydebanegade 44, 1. tv. K\u00f8benhavn Danmark 1709",
    "addr:housenumber":"44 1 tv.",
    "addr:postcode":"1709",
    "addr:street":"Skydebanegade",
    "iso:country":"DK",
    "sg:address":"Skydebanegade 44, 1. tv.",
    "sg:city":"K\u00f8benhavn",
    "sg:orig_category":"Kontorartikler",
    "sg:phone":"+45 33 21 60 12",
    "sg:postcode":"1709",
    "sg:province":"Danmark",
    "wof:name":"Camre & Camre",
    "wof:placetype":"venue"
},
  "geometry": {"coordinates":[12.5557003021,55.6678009033],"type":"Point"}
}