{
  "type": "Feature",
  "properties": {
    "addr:full":"Storegade 23 Lunderskov Danmark 6640",
    "addr:housenumber":"23",
    "addr:postcode":"6640",
    "addr:street":"Storegade",
    "iso:country":"DK",
    "sg:address":"Storegade 23",
    "sg:city":"Lunderskov",
    "sg:orig_category":"Bagere",
    "sg:phone":"+45 75 58 66 88",
    "sg:postcode":"6640",
    "sg:province":"Danmark",
    "wof:name":"Lunderskov Bageri",
    "wof:placetype":"venue"
},
  "geometry": {"coordinates":[9.2997274399,55.4793701172],"type":"Point"}
}