{
  "type": "Feature",
  "properties": {
    "addr:full":"Jernbanegade 37 Kolding Danmark 6000",
    "addr:housenumber":"37",
    "addr:postcode":"6000",
    "addr:street":"Jernbanegade",
    "iso:country":"DK",
    "sg:address":"Jernbanegade 37",
    "sg:city":"Kolding",
    "sg:orig_category":"Kiropraktorer",
    "sg:phone":"+45 75 52 00 76",
    "sg:postcode":"6000",
    "sg:province":"Danmark",
    "wof:name":"S\u00f8rensen, Jesper V.",
    "wof:placetype":"venue"
},
  "geometry": {"coordinates":[9.4793634415,55.4904823303],"type":"Point"}
}