{
  "type": "Feature",
  "properties": {
    "addr:full":"Windfeld-Hansens Gade 1 Vejle Danmark 7100",
    "addr:housenumber":"1",
    "addr:postcode":"7100",
    "addr:street":"Windfeld-Hansens Gade",
    "iso:country":"DK",
    "sg:address":"Windfeld-Hansens Gade 1",
    "sg:city":"Vejle",
    "sg:orig_category":"Varehuse",
    "sg:phone":"+45 75 84 03 00",
    "sg:postcode":"7100",
    "sg:province":"Danmark",
    "wof:name":"F\u00f8tex",
    "wof:placetype":"venue"
},
  "geometry": {"coordinates":[9.5429086685,55.7075424194],"type":"Point"}
}