{
  "type": "Feature",
  "properties": {
    "addr:full":"Fmd.: Jesper Heilskov, Nordstrandvej 6 Anholt Danmark 8592",
    "addr:housenumber":"6",
    "addr:postcode":"8592",
    "addr:street":"Nordstrandvej",
    "iso:country":"DK",
    "sg:address":"Fmd.: Jesper Heilskov, Nordstrandvej 6",
    "sg:city":"Anholt",
    "sg:orig_category":"Faglige organisationer og foreninger",
    "sg:phone":"+45 86 31 91 41",
    "sg:postcode":"8592",
    "sg:province":"Danmark",
    "wof:name":"Anholt Fiskeriforening",
    "wof:placetype":"venue"
},
  "geometry": {"coordinates":[11.5436906815,56.7031402588],"type":"Point"}
}