{
  "type": "Feature",
  "properties": {
    "addr:full":"Hovedgaden 33 Fakse Ladeplads Danmark 4654",
    "addr:housenumber":"33",
    "addr:postcode":"4654",
    "addr:street":"Hovedgaden",
    "iso:country":"DK",
    "sg:address":"Hovedgaden 33",
    "sg:city":"Fakse Ladeplads",
    "sg:orig_category":"Servicestationer",
    "sg:phone":"+45 56 71 60 40",
    "sg:postcode":"4654",
    "sg:province":"Danmark",
    "wof:name":"Statoil Servicenter",
    "wof:placetype":"venue"
},
  "geometry": {"coordinates":[12.1680984497,55.2183074951],"type":"Point"}
}