{
  "type": "Feature",
  "properties": {
    "addr:full":"Smedeg\u00e5rden 10, Lejre Lejre Danmark 4320",
    "addr:housenumber":"10",
    "addr:postcode":"4320",
    "addr:street":"Smedegaarden",
    "iso:country":"DK",
    "sg:address":"Smedeg\u00e5rden 10, Lejre",
    "sg:city":"Lejre",
    "sg:orig_category":"Psykologer, praktiserende",
    "sg:phone":"+45 46 48 00 07",
    "sg:postcode":"4320",
    "sg:province":"Danmark",
    "wof:name":"Dietrich, Lisbeeth",
    "wof:placetype":"venue"
},
  "geometry": {"coordinates":[11.9678316116,55.6005630493],"type":"Point"}
}