{
  "type": "Feature",
  "properties": {
    "iso:country":"DK",
    "sg:address":"Grol\u00f8kkev\u00e6nget 4, S\u00f8hus",
    "sg:city":"Odense N",
    "sg:classifiers":[
        {
            "category":"Retail",
            "subcategory":"Storage",
            "type":"Services"
        }
    ],
    "sg:phone":"+45 26 25 54 63",
    "sg:postcode":"5270",
    "sg:province":"Danmark",
    "sg:tags":[
        "edb",
        "hardware",
        "-"
    ],
    "wof:name":"Millenrium",
    "wof:placetype":"venue"
},
  "geometry": {"coordinates":[10.3306798935,55.4711418152],"type":"Point"}
}