{
  "type": "Feature",
  "properties": {
    "addr:full":"Boulevarden 34 Aalborg Danmark 9000",
    "addr:housenumber":"34",
    "addr:postcode":"9000",
    "addr:street":"Boulevarden",
    "iso:country":"DK",
    "sg:address":"Boulevarden 34",
    "sg:city":"Aalborg",
    "sg:orig_category":"Elektronik",
    "sg:phone":"+45 98 16 07 10",
    "sg:postcode":"9000",
    "sg:province":"Danmark",
    "wof:name":"R.C.E. Elektronikcenter",
    "wof:placetype":"venue"
},
  "geometry": {"coordinates":[9.918012619,57.0446052551],"type":"Point"}
}