{
  "type": "Feature",
  "properties": {
    "iso:country":"DK",
    "sg:address":"S\u00f8nders\u00f8parken 1",
    "sg:city":"Viborg",
    "sg:orig_category":"Offentlige sygehuse",
    "sg:phone":"+45 89 27 33 00",
    "sg:postcode":"8800",
    "sg:province":"Danmark",
    "wof:name":"Psykiatrisk Sygehus",
    "wof:placetype":"venue"
},
  "geometry": {"coordinates":[9.4103326797,56.446598053],"type":"Point"}
}