{
  "type": "Feature",
  "properties": {
    "addr:full":"Nyg\u00e5rdsvej 15 Aars Danmark 9600",
    "addr:housenumber":"15",
    "addr:postcode":"9600",
    "addr:street":"Nygaardsvej",
    "iso:country":"DK",
    "sg:address":"Nyg\u00e5rdsvej 15",
    "sg:city":"Aars",
    "sg:orig_category":"Metalvarefabrikker",
    "sg:phone":"+45 98 62 55 33",
    "sg:postcode":"9600",
    "sg:province":"Danmark",
    "wof:name":"Vikatech",
    "wof:placetype":"venue"
},
  "geometry": {"coordinates":[9.5082740784,56.7966651917],"type":"Point"}
}