{
  "type": "Feature",
  "properties": {
    "iso:country":"DK",
    "sg:address":"Sct. Laurentii Vej 60 E",
    "sg:city":"Skagen",
    "sg:orig_category":"Ravslibere",
    "sg:phone":"+45 98 44 66 99",
    "sg:postcode":"9990",
    "sg:province":"Danmark",
    "sg:website":"www.ravmuseum.dk",
    "wof:name":"Ravbutikken Skagen",
    "wof:placetype":"venue"
},
  "geometry": {"coordinates":[10.5958003998,57.7247200012],"type":"Point"}
}