{
  "type": "Feature",
  "properties": {
    "addr:full":"Thur\u00f8vej 3 Hobro Danmark 9500",
    "addr:housenumber":"3",
    "addr:postcode":"9500",
    "addr:street":"Thurovej",
    "iso:country":"DK",
    "sg:address":"Thur\u00f8vej 3",
    "sg:city":"Hobro",
    "sg:orig_category":"Autolakering",
    "sg:phone":"+45 98 52 53 46",
    "sg:postcode":"9500",
    "sg:province":"Danmark",
    "wof:name":"Bruun's Autolakering A/S",
    "wof:placetype":"venue"
},
  "geometry": {"coordinates":[9.8082361221,56.6257171631],"type":"Point"}
}