{
  "type": "Feature",
  "properties": {
    "addr:full":"Nyhavnsgade 15 Esbjerg Danmark 6700",
    "addr:housenumber":"15",
    "addr:postcode":"6700",
    "addr:street":"Nyhavnsgade",
    "iso:country":"DK",
    "sg:address":"Nyhavnsgade 15",
    "sg:city":"Esbjerg",
    "sg:orig_category":"Skibselektronik",
    "sg:phone":"+45 75 45 96 00",
    "sg:postcode":"6700",
    "sg:province":"Danmark",
    "wof:name":"M & W Elektronik ApS",
    "wof:placetype":"venue"
},
  "geometry": {"coordinates":[8.4340600967,55.473033905],"type":"Point"}
}