{
  "type": "Feature",
  "properties": {
    "addr:full":"Fmd.: Arvid Nilausen, Eg\u00f8jevej 116 K\u00f8ge Danmark 4600",
    "addr:housenumber":"116",
    "addr:postcode":"4600",
    "addr:street":"Arvid;Egojevej",
    "iso:country":"DK",
    "sg:address":"Fmd.: Arvid Nilausen, Eg\u00f8jevej 116",
    "sg:city":"K\u00f8ge",
    "sg:orig_category":"Hobbybetonede foreninger",
    "sg:phone":"+45 56 66 04 68",
    "sg:postcode":"4600",
    "sg:province":"Danmark",
    "wof:name":"Dansk Retriver Klub Midtsj\u00e6lland",
    "wof:placetype":"venue"
},
  "geometry": {"coordinates":[152.23190307620001,-26.0755596161],"type":"Point"}
}