{
  "type": "Feature",
  "properties": {
    "addr:full":"Ahornvej 20 Saksk\u00f8bing Danmark 4990",
    "addr:housenumber":"20",
    "addr:postcode":"4990",
    "addr:street":"Ahornvej",
    "iso:country":"DK",
    "sg:address":"Ahornvej 20",
    "sg:city":"Saksk\u00f8bing",
    "sg:orig_category":"Murermestre",
    "sg:phone":"+45 54 70 50 53",
    "sg:postcode":"4990",
    "sg:province":"Danmark",
    "wof:name":"Christensen, Robin",
    "wof:placetype":"venue"
},
  "geometry": {"coordinates":[-89.1670303345,39.1174697876],"type":"Point"}
}