{
  "type": "Feature",
  "properties": {
    "addr:full":"Amager Landevej 246 Kastrup Danmark 2770",
    "addr:housenumber":"246",
    "addr:postcode":"2770",
    "addr:street":"Amager Landevej",
    "iso:country":"DK",
    "sg:address":"Amager Landevej 246",
    "sg:city":"Kastrup",
    "sg:orig_category":"Elektronik",
    "sg:phone":"+45 32 46 11 60",
    "sg:postcode":"2770",
    "sg:province":"Danmark",
    "sg:website":"www.walbom.dk",
    "wof:name":"Walbom A/S",
    "wof:placetype":"venue"
},
  "geometry": {"coordinates":[12.6278781891,55.6180725098],"type":"Point"}
}