{
  "type": "Feature",
  "properties": {
    "addr:full":"K\u00f8gevej 52 B Taastrup Danmark 2630",
    "addr:housenumber":"52 b",
    "addr:postcode":"2630",
    "addr:street":"Kogevej",
    "iso:country":"DK",
    "sg:address":"K\u00f8gevej 52 B",
    "sg:city":"Taastrup",
    "sg:orig_category":"Optikere",
    "sg:phone":"+45 43 52 00 74",
    "sg:postcode":"2630",
    "sg:province":"Danmark",
    "sg:website":"www.thiele.dk",
    "wof:name":"Thiele Briller & Kontaktlinser",
    "wof:placetype":"venue"
},
  "geometry": {"coordinates":[12.3020896912,55.6506767273],"type":"Point"}
}