{
  "type": "Feature",
  "properties": {
    "addr:full":"Fmd.: Kurt Nielsen, Askevej 6, Aale T\u00f8rring Danmark 7160",
    "addr:housenumber":"6",
    "addr:postcode":"7160",
    "addr:street":"Askevej",
    "iso:country":"DK",
    "sg:address":"Fmd.: Kurt Nielsen, Askevej 6, Aale",
    "sg:city":"T\u00f8rring",
    "sg:orig_category":"Antenneforeninger",
    "sg:phone":"+45 75 67 64 92",
    "sg:postcode":"7160",
    "sg:province":"Danmark",
    "wof:name":"\u00c5le Antenneforening",
    "wof:placetype":"venue"
},
  "geometry": {"coordinates":[9.4808645248,55.8502807617],"type":"Point"}
}