{
  "type": "Feature",
  "properties": {
    "iso:country":"DK",
    "sg:address":"Hj\u00f8rringvej 12",
    "sg:city":"Frederikshavn",
    "sg:orig_category":"Servicestationer",
    "sg:phone":"+45 98 41 01 00",
    "sg:postcode":"9900",
    "sg:province":"Danmark",
    "wof:name":"DK - Benzin",
    "wof:placetype":"venue"
},
  "geometry": {"coordinates":[10.528288,57.448418],"type":"Point"}
}