{
  "type": "Feature",
  "properties": {
    "addr:full":"Ringvejen 1 Rudk\u00f8bing Danmark 5900",
    "addr:housenumber":"1",
    "addr:postcode":"5900",
    "addr:street":"Ringvejen",
    "iso:country":"DK",
    "sg:address":"Ringvejen 1",
    "sg:city":"Rudk\u00f8bing",
    "sg:orig_category":"Rutebilstationer",
    "sg:phone":"+45 62 51 50 41",
    "sg:postcode":"5900",
    "sg:province":"Danmark",
    "wof:name":"Rudk\u00f8bing Busterminal",
    "wof:placetype":"venue"
},
  "geometry": {"coordinates":[-114.0767440796,46.4432487488],"type":"Point"}
}