{
  "type": "Feature",
  "properties": {
    "iso:country":"DK",
    "sg:address":"Charles-Lindbergh-Vej 9 POSTBOKS 10 ",
    "sg:city":"Vadum",
    "sg:classifiers":[
        {
            "category":"Professional",
            "subcategory":"Engineering",
            "type":"Services"
        }
    ],
    "sg:phone":"+45 96 38 06 38",
    "sg:postcode":"9430",
    "sg:province":"Danmark",
    "sg:tags":[
        "machine",
        "-",
        "mechanical"
    ],
    "wof:name":"COLOR PRINT A/S",
    "wof:placetype":"venue"
},
  "geometry": {"coordinates":[9.8614330292,57.1187477112],"type":"Point"}
}