{
  "type": "Feature",
  "properties": {
    "addr:full":"Adelvej 57 Lem Danmark 6940",
    "addr:housenumber":"57",
    "addr:postcode":"6940",
    "addr:street":"Adelvej",
    "iso:country":"DK",
    "sg:address":"Adelvej 57",
    "sg:city":"Lem",
    "sg:orig_category":"Kirker",
    "sg:postcode":"6940",
    "sg:province":"Danmark",
    "wof:name":"Sdr. Lem kirke",
    "wof:placetype":"venue"
},
  "geometry": {"coordinates":[8.4062318802,56.0519065857],"type":"Point"}
}