{
  "type": "Feature",
  "properties": {
    "addr:full":"Valby Langgade 19 Valby Danmark 2500",
    "addr:housenumber":"19",
    "addr:postcode":"2500",
    "addr:street":"Valby Langgade",
    "iso:country":"DK",
    "sg:address":"Valby Langgade 19",
    "sg:city":"Valby",
    "sg:orig_category":"Forlag",
    "sg:phone":"+45 36 16 64 81",
    "sg:postcode":"2500",
    "sg:province":"Danmark",
    "wof:name":"Unitas Forlag",
    "wof:placetype":"venue"
},
  "geometry": {"coordinates":[12.5226097107,55.6662521362],"type":"Point"}
}