{
  "type": "Feature",
  "properties": {
    "addr:full":"\u00c5lborggade 21 \u00c5rhus C Danmark 8000",
    "addr:housenumber":"21",
    "addr:postcode":"8000",
    "addr:street":"Aalborggade",
    "iso:country":"DK",
    "sg:address":"\u00c5lborggade 21",
    "sg:city":"\u00c5rhus C",
    "sg:orig_category":"Malermestre",
    "sg:phone":"+45 21 46 19 30",
    "sg:postcode":"8000",
    "sg:province":"Danmark",
    "sg:website":"www.manillahuset.dk",
    "wof:name":"Frederiksbjerg Malerforretning",
    "wof:placetype":"venue"
},
  "geometry": {"coordinates":[4.717400074,49.7588005066],"type":"Point"}
}