{
  "type": "Feature",
  "properties": {
    "addr:full":"S\u00f8rupvej 64 C, S\u00f8rup Fredensborg Danmark 3480",
    "addr:housenumber":"64 c sorup",
    "addr:postcode":"3480",
    "addr:street":"Sorupvej",
    "iso:country":"DK",
    "sg:address":"S\u00f8rupvej 64 C, S\u00f8rup",
    "sg:city":"Fredensborg",
    "sg:orig_category":"Havnebygninger og vedligeholdelse",
    "sg:phone":"+45 48 48 01 03",
    "sg:postcode":"3480",
    "sg:province":"Danmark",
    "wof:name":"Fredensborg Bro & Havneentreprise",
    "wof:placetype":"venue"
},
  "geometry": {"coordinates":[12.4020547867,55.9782943726],"type":"Point"}
}