{
  "type": "Feature",
  "properties": {
    "iso:country":"DK",
    "sg:address":"Kass.: Carl Chr. Larsen, Holmegaardsvej 35, Fensmark",
    "sg:city":"N\u00e6stved",
    "sg:orig_category":"Spejderkorps",
    "sg:phone":"+45 55 54 75 37",
    "sg:postcode":"4700",
    "sg:province":"Danmark",
    "wof:name":"KFUM-Spejderne Fensmark gruppe",
    "wof:placetype":"venue"
},
  "geometry": {"coordinates":[11.7542486191,55.2315444946],"type":"Point"}
}