{
  "type": "Feature",
  "properties": {
    "addr:full":"Kontaktpers.: Tove Hansen, M\u00e5nsgade 8, Arnager R\u00f8nne Danmark 3700",
    "addr:housenumber":"8",
    "addr:postcode":"3700",
    "addr:street":"Maansgade",
    "iso:country":"DK",
    "sg:address":"Kontaktpers.: Tove Hansen, M\u00e5nsgade 8, Arnager",
    "sg:city":"R\u00f8nne",
    "sg:orig_category":"Afholdsforeninger",
    "sg:phone":"+45 56 97 21 97",
    "sg:postcode":"3700",
    "sg:province":"Danmark",
    "wof:name":"Bornholms Afholdskreds",
    "wof:placetype":"venue"
},
  "geometry": {"coordinates":[14.6975498199,55.0993003845],"type":"Point"}
}