{
  "type": "Feature",
  "properties": {
    "addr:full":"Helsinge, Postboks 5 Tisvildeleje Danmark 3220",
    "addr:housenumber":"5",
    "addr:postcode":"3220",
    "addr:street":"Postboks",
    "iso:country":"DK",
    "sg:address":"Helsinge, Postboks 5",
    "sg:city":"Tisvildeleje",
    "sg:orig_category":"Grundejerforeninger",
    "sg:postcode":"3220",
    "sg:province":"Danmark",
    "wof:name":"Grundejerforeningen for Tisvilde og Omegn",
    "wof:placetype":"venue"
},
  "geometry": {"coordinates":[12.0764846802,56.0589904785],"type":"Point"}
}