{
  "type": "Feature",
  "properties": {
    "addr:full":"Snemandsvej 7 Herlev Danmark 2730",
    "addr:housenumber":"7",
    "addr:postcode":"2730",
    "addr:street":"Snemandsvej",
    "iso:country":"DK",
    "sg:address":"Snemandsvej 7",
    "sg:city":"Herlev",
    "sg:orig_category":"Transport",
    "sg:phone":"+45 44 53 22 88",
    "sg:postcode":"2730",
    "sg:province":"Danmark",
    "wof:name":"Herlev Transport",
    "wof:placetype":"venue"
},
  "geometry": {"coordinates":[12.4495630264,55.7301979065],"type":"Point"}
}