{
  "type": "Feature",
  "properties": {
    "iso:country":"DK",
    "sg:address":"Ribovej 4 ",
    "sg:city":"Ringk\u00f8bing",
    "sg:classifiers":[
        {
            "category":"Manufacturing",
            "subcategory":"Glass & Minerals",
            "type":"Manufacturing & Wholesale Goods"
        }
    ],
    "sg:phone":"+45 96 74 29 00",
    "sg:postcode":"6950",
    "sg:province":"Danmark",
    "wof:name":"NCD OFFSHORE A/S",
    "wof:placetype":"venue"
},
  "geometry": {"coordinates":[-114.0767440796,46.4432487488],"type":"Point"}
}