{
  "type": "Feature",
  "properties": {
    "addr:full":"Pottemagerporten 1 Hvidovre Danmark 2650",
    "addr:housenumber":"1",
    "addr:postcode":"2650",
    "addr:street":"Pottemagerporten",
    "iso:country":"DK",
    "sg:address":"Pottemagerporten 1",
    "sg:city":"Hvidovre",
    "sg:orig_category":"Sammensatte institutioner",
    "sg:phone":"+45 36 49 00 51",
    "sg:postcode":"2650",
    "sg:province":"Danmark",
    "wof:name":"Pindsvinet B\u00f8rneinstitution",
    "wof:placetype":"venue"
},
  "geometry": {"coordinates":[12.4458351135,55.62840271],"type":"Point"}
}