{
  "type": "Feature",
  "properties": {
    "addr:full":"Pilevej 37 Struer Danmark 7600",
    "addr:housenumber":"37",
    "addr:postcode":"7600",
    "addr:street":"Pilevej",
    "iso:country":"DK",
    "sg:address":"Pilevej 37",
    "sg:city":"Struer",
    "sg:orig_category":"Zoneterapeuter",
    "sg:phone":"+45 97 85 29 14",
    "sg:postcode":"7600",
    "sg:province":"Danmark",
    "wof:name":"Bojsen, Steen",
    "wof:placetype":"venue"
},
  "geometry": {"coordinates":[8.5970525742,56.4800453186],"type":"Point"}
}