{
  "type": "Feature",
  "properties": {
    "addr:full":"Fjordparken 412 Horsens Danmark 8700",
    "addr:housenumber":"412",
    "addr:postcode":"8700",
    "addr:street":"Fjordparken",
    "iso:country":"DK",
    "sg:address":"Fjordparken 412",
    "sg:city":"Horsens",
    "sg:orig_category":"Forsikringer",
    "sg:phone":"+45 76 26 02 76",
    "sg:postcode":"8700",
    "sg:province":"Danmark",
    "wof:name":"Aros Forsikring",
    "wof:placetype":"venue"
},
  "geometry": {"coordinates":[9.8594589233,55.8446769714],"type":"Point"}
}