{
  "type": "Feature",
  "properties": {
    "iso:country":"DK",
    "sg:address":"Fmd.: Lillian Olsen, Lundeparken 14, 2. th.",
    "sg:city":"Frederikssund",
    "sg:orig_category":"Husflidsforeninger",
    "sg:phone":"+45 47 31 15 13",
    "sg:postcode":"3600",
    "sg:province":"Danmark",
    "wof:name":"Husmoderforeningen",
    "wof:placetype":"venue"
},
  "geometry": {"coordinates":[12.0661621094,55.8370323181],"type":"Point"}
}