{
  "type": "Feature",
  "properties": {
    "iso:country":"DK",
    "sg:address":"Elmevej 1",
    "sg:city":"Sandved",
    "sg:orig_category":"Revisorer",
    "sg:phone":"+45 55 45 63 37",
    "sg:postcode":"4262",
    "sg:province":"Danmark",
    "wof:name":"Frederiksen, Svend",
    "wof:placetype":"venue"
},
  "geometry": {"coordinates":[11.516658783,55.2607040405],"type":"Point"}
}