{
  "type": "Feature",
  "properties": {
    "iso:country":"DK",
    "sg:address":"Oldermand: Jan Erik Nielsen, Aggerupvej 1, Kisserup",
    "sg:city":"Kirke Hvals\u00f8",
    "sg:orig_category":"Borger- og beboerforeninger",
    "sg:phone":"+45 46 40 82 88",
    "sg:postcode":"4330",
    "sg:province":"Danmark",
    "wof:name":"Kisserup Bylaug",
    "wof:placetype":"venue"
},
  "geometry": {"coordinates":[11.8626852036,55.5937385559],"type":"Point"}
}