{
  "type": "Feature",
  "properties": {
    "addr:full":"Tinghusgade 33 C Svendborg Danmark 5700",
    "addr:housenumber":"33 c",
    "addr:postcode":"5700",
    "addr:street":"Tinghusgade",
    "iso:country":"DK",
    "sg:address":"Tinghusgade 33 C",
    "sg:city":"Svendborg",
    "sg:orig_category":"RESTAURANTS: CAFEER",
    "sg:phone":"+45 62 21 00 49",
    "sg:postcode":"5700",
    "sg:province":"Danmark",
    "wof:name":"Cafe'Svanen",
    "wof:placetype":"venue"
},
  "geometry": {"coordinates":[10.603726387,55.060344696],"type":"Point"}
}