{
  "type": "Feature",
  "properties": {
    "iso:country":"DK",
    "sg:address":"Schubertsvej 18",
    "sg:city":"Aalborg SV",
    "sg:orig_category":"Boliger med kald",
    "sg:phone":"+45 98 38 28 86",
    "sg:postcode":"9200",
    "sg:province":"Danmark",
    "wof:name":"Schubertsvej",
    "wof:placetype":"venue"
},
  "geometry": {"coordinates":[9.8189029694,57.0094871521],"type":"Point"}
}