{
  "type": "Feature",
  "properties": {
    "iso:country":"DK",
    "sg:address":"Skolegade 39",
    "sg:city":"Esbjerg",
    "sg:orig_category":"Kulturelle foreninger",
    "sg:phone":"+45 75 12 24 98",
    "sg:postcode":"6700",
    "sg:province":"Danmark",
    "wof:name":"Esbjerg Teaterkreds",
    "wof:placetype":"venue"
},
  "geometry": {"coordinates":[8.4516525269,55.466999054],"type":"Point"}
}