{
  "type": "Feature",
  "properties": {
    "addr:full":"N\u00f8rregade 54, 2. Holstebro Danmark 7500",
    "addr:housenumber":"54 2",
    "addr:postcode":"7500",
    "addr:street":"Norregade",
    "iso:country":"DK",
    "sg:address":"N\u00f8rregade 54, 2.",
    "sg:city":"Holstebro",
    "sg:orig_category":"Faglige organisationer og foreninger",
    "sg:phone":"+45 97 42 99 42",
    "sg:postcode":"7500",
    "sg:province":"Danmark",
    "wof:name":"LO-Ringk\u00f8bing Amt",
    "wof:placetype":"venue"
},
  "geometry": {"coordinates":[8.6192131042,56.3620185852],"type":"Point"}
}