{
  "type": "Feature",
  "properties": {
    "addr:full":"Ugandavej 111 Kastrup Danmark 2770",
    "addr:housenumber":"111",
    "addr:postcode":"2770",
    "addr:street":"Ugandavej",
    "iso:country":"DK",
    "sg:address":"Ugandavej 111",
    "sg:city":"Kastrup",
    "sg:orig_category":"Posthuse",
    "sg:postcode":"2770",
    "sg:province":"Danmark",
    "wof:name":"Post Danmark, Vestamagers Postekspedition",
    "wof:placetype":"venue"
},
  "geometry": {"coordinates":[12.5883588791,55.6041717529],"type":"Point"}
}