{
  "type": "Feature",
  "properties": {
    "addr:full":"Kristrupvej 60 A Randers Danmark 8900",
    "addr:housenumber":"60 a",
    "addr:postcode":"8900",
    "addr:street":"Kristrupvej",
    "iso:country":"DK",
    "sg:address":"Kristrupvej 60 A",
    "sg:city":"Randers",
    "sg:orig_category":"Apoteker og -udsalg",
    "sg:phone":"+45 86 41 29 12",
    "sg:postcode":"8900",
    "sg:province":"Danmark",
    "wof:name":"Apoteksudsalget",
    "wof:placetype":"venue"
},
  "geometry": {"coordinates":[10.0544147491,56.4477615356],"type":"Point"}
}