{
  "type": "Feature",
  "properties": {
    "addr:full":"Nygade 20 Nakskov Danmark 4900",
    "addr:housenumber":"20",
    "addr:postcode":"4900",
    "addr:street":"Nygade",
    "iso:country":"DK",
    "sg:address":"Nygade 20",
    "sg:city":"Nakskov",
    "sg:orig_category":"Akupunktur",
    "sg:phone":"+45 54 95 29 49",
    "sg:postcode":"4900",
    "sg:province":"Danmark",
    "wof:name":"Randy's Akupunkturklinik",
    "wof:placetype":"venue"
},
  "geometry": {"coordinates":[11.1402759552,54.831161499],"type":"Point"}
}