{
  "type": "Feature",
  "properties": {
    "addr:full":"Urvej 10 Hammel Danmark 8450",
    "addr:housenumber":"10",
    "addr:postcode":"8450",
    "addr:street":"Urvej",
    "iso:country":"DK",
    "sg:address":"Urvej 10",
    "sg:city":"Hammel",
    "sg:orig_category":"\u00c3\u02dcvrige institutioner",
    "sg:phone":"+45 86 96 90 98",
    "sg:postcode":"8450",
    "sg:province":"Danmark",
    "wof:name":"Bof\u00e6llesskabet Urvej 10",
    "wof:placetype":"venue"
},
  "geometry": {"coordinates":[9.8709897995,56.2565307617],"type":"Point"}
}