{
  "type": "Feature",
  "properties": {
    "addr:full":"\u00d8stergade 24, Hvidbjerg Thyholm Danmark 7790",
    "addr:housenumber":"24",
    "addr:postcode":"7790",
    "addr:street":"Ostergade;Hvidbjerg",
    "iso:country":"DK",
    "sg:address":"\u00d8stergade 24, Hvidbjerg",
    "sg:city":"Thyholm",
    "sg:orig_category":"Vinduer",
    "sg:phone":"+45 96 91 22 22",
    "sg:postcode":"7790",
    "sg:province":"Danmark",
    "sg:website":"www.hvidbjervinduet.dk",
    "wof:name":"Hvidbjerg Vinduet A/S",
    "wof:placetype":"venue"
},
  "geometry": {"coordinates":[8.525765419,56.6507072449],"type":"Point"}
}