{
  "type": "Feature",
  "properties": {
    "iso:country":"DK",
    "sg:address":"N\u00f8rregade 53 - 55",
    "sg:city":"Vejle",
    "sg:orig_category":"Solcentre",
    "sg:phone":"+45 75 72 22 28",
    "sg:postcode":"7100",
    "sg:province":"Danmark",
    "wof:name":"Amazing Sun",
    "wof:placetype":"venue"
},
  "geometry": {"coordinates":[9.5353059769,55.7117576599],"type":"Point"}
}