{
  "type": "Feature",
  "properties": {
    "addr:full":"Stationsvej 9 Fars\u00f8 Danmark 9640",
    "addr:housenumber":"9",
    "addr:postcode":"9640",
    "addr:street":"Stationsvej",
    "iso:country":"DK",
    "sg:address":"Stationsvej 9",
    "sg:city":"Fars\u00f8",
    "sg:orig_category":"Posthuse",
    "sg:phone":"+45 98 63 16 33",
    "sg:postcode":"9640",
    "sg:province":"Danmark",
    "wof:name":"Post Danmark, Fars\u00f8 Postkontor",
    "wof:placetype":"venue"
},
  "geometry": {"coordinates":[-109.44831848139999,42.1062355042],"type":"Point"}
}