{
  "type": "Feature",
  "properties": {
    "addr:full":"Kirkevangen 14, Vrinners Knebel Danmark 8420",
    "addr:housenumber":"14",
    "addr:postcode":"8420",
    "addr:street":"Kirkevangen;Vrinners",
    "iso:country":"DK",
    "sg:address":"Kirkevangen 14, Vrinners",
    "sg:city":"Knebel",
    "sg:orig_category":"Solcentre",
    "sg:phone":"+45 86 36 52 46",
    "sg:postcode":"8420",
    "sg:province":"Danmark",
    "wof:name":"Vrinners Kosmetik & Sol",
    "wof:placetype":"venue"
},
  "geometry": {"coordinates":[10.3770122528,56.1816596985],"type":"Point"}
}