{
  "type": "Feature",
  "properties": {
    "addr:full":"Egelundvej 6, Egelund Karup Danmark 7470",
    "addr:housenumber":"6",
    "addr:postcode":"7470",
    "addr:street":"Egelundvej;Egelund Karup Danmark",
    "iso:country":"DK",
    "sg:address":"Egelundvej 6, Egelund",
    "sg:city":"Karup",
    "sg:orig_category":"Maskinstationer",
    "sg:phone":"+45 97 45 62 70",
    "sg:postcode":"7470",
    "sg:province":"Danmark",
    "wof:name":"Egelund Maskinsation ApS",
    "wof:placetype":"venue"
},
  "geometry": {"coordinates":[9.2525548935,56.3398017883],"type":"Point"}
}