{
  "type": "Feature",
  "properties": {
    "addr:full":"Vesterbro 101 Aalborg Danmark 9000",
    "addr:housenumber":"101",
    "addr:postcode":"9000",
    "addr:street":"Vesterbro",
    "iso:country":"DK",
    "sg:address":"Vesterbro 101",
    "sg:city":"Aalborg",
    "sg:orig_category":"Sprogskoler",
    "sg:phone":"+45 98 12 30 99",
    "sg:postcode":"9000",
    "sg:province":"Danmark",
    "wof:name":"Sprog-Gruppen Danmark",
    "wof:placetype":"venue"
},
  "geometry": {"coordinates":[9.9162416458,57.050403595],"type":"Point"}
}