{
  "type": "Feature",
  "properties": {
    "iso:country":"DK",
    "sg:address":"Fmd.: N. P. Nielsen, N\u00f8rrevej 21",
    "sg:city":"H\u00f8jer",
    "sg:orig_category":"Kulturelle foreninger",
    "sg:phone":"+45 74 78 24 54",
    "sg:postcode":"6280",
    "sg:province":"Danmark",
    "wof:name":"Fonden til bevarelse af H\u00f8jer M\u00f8lle",
    "wof:placetype":"venue"
},
  "geometry": {"coordinates":[-2.1972899437,49.2049789429],"type":"Point"}
}