{
  "type": "Feature",
  "properties": {
    "addr:full":"J\u00e6gerg\u00e5rdsgade 88 \u00c5rhus C Danmark 8000",
    "addr:housenumber":"88",
    "addr:postcode":"8000",
    "addr:street":"Jaegergaardsgade",
    "iso:country":"DK",
    "sg:address":"J\u00e6gerg\u00e5rdsgade 88",
    "sg:city":"\u00c5rhus C",
    "sg:orig_category":"Pizzeriaer",
    "sg:phone":"+45 86 19 67 77",
    "sg:postcode":"8000",
    "sg:province":"Danmark",
    "wof:name":"Sorento, Restaurant",
    "wof:placetype":"venue"
},
  "geometry": {"coordinates":[4.717400074,49.7588005066],"type":"Point"}
}