{
  "type": "Feature",
  "properties": {
    "addr:full":"Fmd.: J\u00f8rn Andersen, Gr\u00f8ftager 7 Ringe Danmark 5750",
    "addr:housenumber":"7",
    "addr:postcode":"5750",
    "addr:street":"Groftager",
    "iso:country":"DK",
    "sg:address":"Fmd.: J\u00f8rn Andersen, Gr\u00f8ftager 7",
    "sg:city":"Ringe",
    "sg:orig_category":"Boligselskaber",
    "sg:phone":"+45 62 62 45 13",
    "sg:postcode":"5750",
    "sg:province":"Danmark",
    "wof:name":"Ejerlejlighedsforeningen Gr\u00f8ftager",
    "wof:placetype":"venue"
},
  "geometry": {"coordinates":[10.4781074524,55.2356643677],"type":"Point"}
}