{
  "type": "Feature",
  "properties": {
    "addr:full":"Bregningevej 25 Jyderup Danmark 4450",
    "addr:housenumber":"25",
    "addr:postcode":"4450",
    "addr:street":"Bregningevej",
    "iso:country":"DK",
    "sg:address":"Bregningevej 25",
    "sg:city":"Jyderup",
    "sg:orig_category":"Skolefritidsordninger",
    "sg:phone":"+45 59 29 20 91",
    "sg:postcode":"4450",
    "sg:province":"Danmark",
    "wof:name":"Skolefritidsordningen Bregnen",
    "wof:placetype":"venue"
},
  "geometry": {"coordinates":[11.329990387,55.6767883301],"type":"Point"}
}