{
  "type": "Feature",
  "properties": {
    "addr:full":"Skoletoften 17 Knebel Danmark 8420",
    "addr:housenumber":"17",
    "addr:postcode":"8420",
    "addr:street":"Skoletoften",
    "iso:country":"DK",
    "sg:address":"Skoletoften 17",
    "sg:city":"Knebel",
    "sg:orig_category":"Kommunale ungdomsskoler",
    "sg:phone":"+45 86 35 17 01",
    "sg:postcode":"8420",
    "sg:province":"Danmark",
    "wof:name":"Ungdomsskolen Mols",
    "wof:placetype":"venue"
},
  "geometry": {"coordinates":[10.4873943329,56.2121543884],"type":"Point"}
}