{
  "type": "Feature",
  "properties": {
    "addr:full":"Hobrovej 12 D Randers Danmark 8900",
    "addr:housenumber":"12 d",
    "addr:postcode":"8900",
    "addr:street":"Hobrovej",
    "iso:country":"DK",
    "sg:address":"Hobrovej 12 D",
    "sg:city":"Randers",
    "sg:orig_category":"Pianostemmere",
    "sg:phone":"+45 86 42 21 20",
    "sg:postcode":"8900",
    "sg:province":"Danmark",
    "wof:name":"Hedegaard, Steen",
    "wof:placetype":"venue"
},
  "geometry": {"coordinates":[10.0300397873,56.4637756348],"type":"Point"}
}