{
  "type": "Feature",
  "properties": {
    "addr:full":"Stationsholmen 6 H Greve Danmark 2670",
    "addr:housenumber":"6 h",
    "addr:postcode":"2670",
    "addr:street":"Stationsholmen",
    "iso:country":"DK",
    "sg:address":"Stationsholmen 6 H",
    "sg:city":"Greve",
    "sg:orig_category":"Boghandlere",
    "sg:phone":"+45 43 90 25 12",
    "sg:postcode":"2670",
    "sg:province":"Danmark",
    "wof:name":"Boghandleren i Greve",
    "wof:placetype":"venue"
},
  "geometry": {"coordinates":[12.2941808701,55.5844078064],"type":"Point"}
}