{
  "type": "Feature",
  "properties": {
    "addr:full":"Fmd.: Carl Erik J\u00f8rgensen, Bjergev\u00e6nget 76, Andst Vejen Danmark 6600",
    "addr:housenumber":"76",
    "addr:postcode":"6600",
    "addr:street":"Andst",
    "iso:country":"DK",
    "sg:address":"Fmd.: Carl Erik J\u00f8rgensen, Bjergev\u00e6nget 76, Andst",
    "sg:city":"Vejen",
    "sg:orig_category":"Kulturelle foreninger",
    "sg:phone":"+45 75 58 82 01",
    "sg:postcode":"6600",
    "sg:province":"Danmark",
    "wof:name":"Arbejdernes Radio- og fjernsynsklub - B\u00e6kke Vejen og Omegn",
    "wof:placetype":"venue"
},
  "geometry": {"coordinates":[9.1396121979,55.4778175354],"type":"Point"}
}