{
  "type": "Feature",
  "properties": {
    "addr:full":"S\u00f8nderlandsgade 19 Holstebro Danmark 7500",
    "addr:housenumber":"19",
    "addr:postcode":"7500",
    "addr:street":"Sonderlandsgade",
    "iso:country":"DK",
    "sg:address":"S\u00f8nderlandsgade 19",
    "sg:city":"Holstebro",
    "sg:orig_category":"Senge",
    "sg:phone":"+45 97 42 02 77",
    "sg:postcode":"7500",
    "sg:province":"Danmark",
    "wof:name":"S\u00f8vn og Comfort",
    "wof:placetype":"venue"
},
  "geometry": {"coordinates":[8.618302,56.355556],"type":"Point"}
}