{
  "type": "Feature",
  "properties": {
    "iso:country":"DK",
    "sg:address":"Hovedgaden 21, Skovsgaard",
    "sg:city":"Brovst",
    "sg:orig_category":"Konsulentvirksomheder",
    "sg:phone":"+45 98 23 06 60",
    "sg:postcode":"9460",
    "sg:province":"Danmark",
    "wof:name":"R\u00e5d og D\u00e5d Butikken",
    "wof:placetype":"venue"
},
  "geometry": {"coordinates":[9.5220241547,57.097366333],"type":"Point"}
}