{
  "type": "Feature",
  "properties": {
    "addr:full":"Sdr. Rind Vej 38 Viborg Danmark 8800",
    "addr:housenumber":"38",
    "addr:postcode":"8800",
    "addr:street":"Sdr. Rind Vej",
    "iso:country":"DK",
    "sg:address":"Sdr. Rind Vej 38",
    "sg:city":"Viborg",
    "sg:orig_category":"Biavlere",
    "sg:phone":"+45 86 63 94 86",
    "sg:postcode":"8800",
    "sg:province":"Danmark",
    "wof:name":"Thorsen Bisygdomsinspekt\u00f8r, Vagn",
    "wof:placetype":"venue"
},
  "geometry": {"coordinates":[9.4645824432,56.3940505981],"type":"Point"}
}