{
  "type": "Feature",
  "properties": {
    "addr:full":"\u00d8stergade 26 Herning Danmark 7400",
    "addr:housenumber":"26",
    "addr:postcode":"7400",
    "addr:street":"Ostergade",
    "iso:country":"DK",
    "sg:address":"\u00d8stergade 26",
    "sg:city":"Herning",
    "sg:orig_category":"Rejsebureauer",
    "sg:phone":"+45 96 26 61 10",
    "sg:postcode":"7400",
    "sg:province":"Danmark",
    "sg:website":"www.tq3.dk",
    "wof:name":"TQ3 Travel Solutions",
    "wof:placetype":"venue"
},
  "geometry": {"coordinates":[8.9791212082,56.1356964111],"type":"Point"}
}