{
  "type": "Feature",
  "properties": {
    "addr:full":"Njalsgade 21F Copenhagen 2300",
    "addr:housenumber":"21f",
    "addr:postcode":"2300",
    "addr:street":"Njalsgade",
    "iso:country":"DK",
    "sg:address":"Njalsgade 21F",
    "sg:city":"Copenhagen",
    "sg:classifiers":[
        {
            "category":"Professional",
            "subcategory":"Computer Services",
            "type":"Services"
        }
    ],
    "sg:postcode":"2300",
    "sg:tags":[
        "preview-networks",
        "online",
        "video",
        "syndication",
        "preview",
        "content",
        "film",
        "trailer",
        "trailers",
        "movie"
    ],
    "sg:website":"http://previewnetworks.com",
    "wof:name":"Preview Networks",
    "wof:placetype":"venue"
},
  "geometry": {"coordinates":[12.5800751,55.6659813],"type":"Point"}
}