{
  "type": "Feature",
  "properties": {
    "addr:full":"Voldgade 11 Jerslev Danmark 9740",
    "addr:housenumber":"11",
    "addr:postcode":"9740",
    "addr:street":"Voldgade",
    "iso:country":"DK",
    "sg:address":"Voldgade 11",
    "sg:city":"Jerslev",
    "sg:orig_category":"Sparekasser",
    "sg:phone":"+45 98 83 14 11",
    "sg:postcode":"9740",
    "sg:province":"Danmark",
    "sg:website":"www.jerslevspar.dk",
    "wof:name":"Jerslev Sparekasse",
    "wof:placetype":"venue"
},
  "geometry": {"coordinates":[10.0922088623,57.2843971252],"type":"Point"}
}