{
  "type": "Feature",
  "properties": {
    "iso:country":"DK",
    "sg:address":"\u00d8ster Hassing Vej 1",
    "sg:city":"Vodskov",
    "sg:orig_category":"Kommunale folkeskoler",
    "sg:phone":"+45 98 25 64 79",
    "sg:postcode":"9310",
    "sg:province":"Danmark",
    "wof:name":"Langholt Skole",
    "wof:placetype":"venue"
},
  "geometry": {"coordinates":[10.0885944366,57.1030197144],"type":"Point"}
}