{
  "type": "Feature",
  "properties": {
    "addr:full":"Gannebro 5 Fakse Danmark 4640",
    "addr:housenumber":"5",
    "addr:postcode":"4640",
    "addr:street":"Gannebro",
    "iso:country":"DK",
    "sg:address":"Gannebro 5",
    "sg:city":"Fakse",
    "sg:orig_category":"Hundekenneler",
    "sg:phone":"+45 56 73 03 10",
    "sg:postcode":"4640",
    "sg:province":"Danmark",
    "wof:name":"Nimo, Kennel",
    "wof:placetype":"venue"
},
  "geometry": {"coordinates":[12.1203422546,55.2574195862],"type":"Point"}
}