{
  "type": "Feature",
  "properties": {
    "addr:full":"Tornebuskegade 7 K\u00f8benhavn Danmark 1131",
    "addr:housenumber":"7;1131",
    "addr:street":"Tornebuskegade",
    "iso:country":"DK",
    "sg:address":"Tornebuskegade 7",
    "sg:city":"K\u00f8benhavn",
    "sg:orig_category":"Ejendomshandel",
    "sg:phone":"+45 33 30 10 50",
    "sg:postcode":"1131",
    "sg:province":"Danmark",
    "wof:name":"LaCour og Lykke",
    "wof:placetype":"venue"
},
  "geometry": {"coordinates":[12.5761995316,55.6833992004],"type":"Point"}
}