{
  "type": "Feature",
  "properties": {
    "addr:full":"Langgade 22 Nyk\u00f8bing Danmark 4800",
    "addr:housenumber":"22",
    "addr:postcode":"4800",
    "addr:street":"Langgade",
    "iso:country":"DK",
    "sg:address":"Langgade 22",
    "sg:city":"Nyk\u00f8bing",
    "sg:orig_category":"Papirvarer",
    "sg:phone":"+45 54 85 23 22",
    "sg:postcode":"4800",
    "sg:province":"Danmark",
    "wof:name":"Papirlageret Nyk\u00f8bing Falster, ApS",
    "wof:placetype":"venue"
},
  "geometry": {"coordinates":[-114.0768203735,46.4432411194],"type":"Point"}
}