{
  "type": "Feature",
  "properties": {
    "addr:full":"Fmd.: Bitten Petersen, Kirkevej 283, Tolne Sindal Danmark 9870",
    "addr:housenumber":"283",
    "addr:postcode":"tolne;9870",
    "addr:street":"Kirkevej",
    "iso:country":"DK",
    "sg:address":"Fmd.: Bitten Petersen, Kirkevej 283, Tolne",
    "sg:city":"Sindal",
    "sg:orig_category":"Borger- og beboerforeninger",
    "sg:phone":"+45 98 93 00 06",
    "sg:postcode":"9870",
    "sg:province":"Danmark",
    "wof:name":"Tolne & Omegns Borgerforening",
    "wof:placetype":"venue"
},
  "geometry": {"coordinates":[10.2032299042,57.470916748],"type":"Point"}
}