{
  "type": "Feature",
  "properties": {
    "addr:full":"v/ Ingrid Andresen, Stationsvej 19, Vrensted L\u00f8kken Danmark 9480",
    "addr:housenumber":"19",
    "addr:postcode":"9480",
    "addr:street":"Stationsvej",
    "iso:country":"DK",
    "sg:address":"v/ Ingrid Andresen, Stationsvej 19, Vrensted",
    "sg:city":"L\u00f8kken",
    "sg:orig_category":"Lokalarkiver",
    "sg:phone":"+45 98 88 92 05",
    "sg:postcode":"9480",
    "sg:province":"Danmark",
    "wof:name":"Lokal- & Sl\u00e6gtshistorisk Forening for Vrensted",
    "wof:placetype":"venue"
},
  "geometry": {"coordinates":[9.715880394,57.3703308105],"type":"Point"}
}