{
  "type": "Feature",
  "properties": {
    "iso:country":"DK",
    "sg:address":"Hovvej 69",
    "sg:city":"Esperg\u00e6rde",
    "sg:classifiers":[
        {
            "category":"Professional",
            "subcategory":"Advertising",
            "type":"Services"
        }
    ],
    "sg:phone":"+45 49 13 60 32",
    "sg:postcode":"3060",
    "sg:province":"Danmark",
    "sg:tags":[
        "telemarketing"
    ],
    "wof:name":"Tele Marketing",
    "wof:placetype":"venue"
},
  "geometry": {"coordinates":[11.6512403488,47.8390617371],"type":"Point"}
}