{
  "type": "Feature",
  "properties": {
    "addr:full":"Floras Alle 17 Vanl\u00f8se Danmark 2720",
    "addr:housenumber":"17",
    "addr:postcode":"2720",
    "addr:street":"Floras Alle",
    "iso:country":"DK",
    "sg:address":"Floras Alle 17",
    "sg:city":"Vanl\u00f8se",
    "sg:orig_category":"Sko",
    "sg:phone":"+45 38 71 71 88",
    "sg:postcode":"2720",
    "sg:province":"Danmark",
    "wof:name":"Kiwi/Tana",
    "wof:placetype":"venue"
},
  "geometry": {"coordinates":[10.4985952377,60.3006744385],"type":"Point"}
}