{
  "type": "Feature",
  "properties": {
    "addr:full":"Gammel Kongevej 151 Frederiksberg Danmark 1850",
    "addr:housenumber":"151",
    "addr:postcode":"1850",
    "addr:street":"Gammel Kongevej",
    "iso:country":"DK",
    "sg:address":"Gammel Kongevej 151",
    "sg:city":"Frederiksberg",
    "sg:orig_category":"Autoforhandlere",
    "sg:phone":"+45 33 21 12 27",
    "sg:postcode":"1850",
    "sg:province":"Danmark",
    "wof:name":"High Class Automobile",
    "wof:placetype":"venue"
},
  "geometry": {"coordinates":[12.5374794006,55.677230835],"type":"Point"}
}