{
  "type": "Feature",
  "properties": {
    "addr:full":"N\u00f8rre Alle 96 \u00c5rhus C Danmark 8000",
    "addr:housenumber":"96",
    "addr:postcode":"8000",
    "addr:street":"Norre Alle",
    "iso:country":"DK",
    "sg:address":"N\u00f8rre Alle 96",
    "sg:city":"\u00c5rhus C",
    "sg:orig_category":"Cykler",
    "sg:phone":"+45 86 12 86 52",
    "sg:postcode":"8000",
    "sg:province":"Danmark",
    "wof:name":"Hermansen Cykelsport",
    "wof:placetype":"venue"
},
  "geometry": {"coordinates":[4.717400074,49.7588005066],"type":"Point"}
}