{
  "type": "Feature",
  "properties": {
    "addr:full":"Ny Carlsberg Vej 5-7 K\u00f8benhavn Danmark 1760",
    "addr:housenumber":"5-7;1760",
    "addr:street":"Carlsberg Vej",
    "iso:country":"DK",
    "sg:address":"Ny Carlsberg Vej 5-7",
    "sg:city":"K\u00f8benhavn",
    "sg:orig_category":"Farvehandlere",
    "sg:phone":"+45 33 24 49 07",
    "sg:postcode":"1760",
    "sg:province":"Danmark",
    "wof:name":"Fl\u00fcgger Farver",
    "wof:placetype":"venue"
},
  "geometry": {"coordinates":[-76.50189208979999,42.8563194275],"type":"Point"}
}