{
  "type": "Feature",
  "properties": {
    "iso:country":"DK",
    "sg:address":"Brogaardsgade 2C, Kaas",
    "sg:city":"Pandrup",
    "sg:classifiers":[
        {
            "category":"Communications",
            "type":"Services"
        }
    ],
    "sg:phone":"+45 98 24 56 22",
    "sg:postcode":"9490",
    "sg:province":"Danmark",
    "sg:tags":[
        "og",
        "tv",
        "radio"
    ],
    "sg:website":"www.expert.dk",
    "wof:name":"Expert Radio og TV",
    "wof:placetype":"venue"
},
  "geometry": {"coordinates":[9.6769151688,57.223815918],"type":"Point"}
}