{
  "type": "Feature",
  "properties": {
    "iso:country":"DK",
    "sg:address":"T\u00e5singevej 10 ",
    "sg:city":"Nyborg",
    "sg:classifiers":[
        {
            "category":"Farming",
            "subcategory":"Livestock Farm",
            "type":"Manufacturing & Wholesale Goods"
        }
    ],
    "sg:phone":"+45 65 30 12 60",
    "sg:postcode":"5800",
    "sg:province":"Danmark",
    "sg:tags":[
        "agriculture"
    ],
    "wof:name":"TENAX SILD A/S",
    "wof:placetype":"venue"
},
  "geometry": {"coordinates":[10.7632780075,55.3116760254],"type":"Point"}
}