{
  "type": "Feature",
  "properties": {
    "addr:full":"Astridsvej 70 Kastrup Danmark 2770",
    "addr:housenumber":"70",
    "addr:postcode":"2770",
    "addr:street":"Astridsvej",
    "iso:country":"DK",
    "sg:address":"Astridsvej 70",
    "sg:city":"Kastrup",
    "sg:classifiers":[
        {
            "category":"Restaurant",
            "type":"Food & Drink"
        }
    ],
    "sg:phone":"+45 70 26 66 67",
    "sg:postcode":"2770",
    "sg:province":"Danmark",
    "wof:name":"T\u00e5rnby Bowling Center",
    "wof:placetype":"venue"
},
  "geometry": {"coordinates":[12.5998506546,55.6307029724],"type":"Point"}
}