{
  "type": "Feature",
  "properties": {
    "addr:full":"Bredgade 47 Herning Danmark 7400",
    "addr:housenumber":"47",
    "addr:postcode":"7400",
    "addr:street":"Bredgade",
    "iso:country":"DK",
    "sg:address":"Bredgade 47",
    "sg:city":"Herning",
    "sg:orig_category":"Cykler",
    "sg:phone":"+45 97 12 11 14",
    "sg:postcode":"7400",
    "sg:province":"Danmark",
    "sg:website":"www.mosquito-herning.dk",
    "wof:name":"Mosquito Cykelcenter",
    "wof:placetype":"venue"
},
  "geometry": {"coordinates":[8.9692401886,56.1361541748],"type":"Point"}
}