{
  "type": "Feature",
  "properties": {
    "addr:full":"R\u00e5dhuscentret 5 Vojens Danmark 6500",
    "addr:housenumber":"5",
    "addr:postcode":"6500",
    "addr:street":"Raadhuscentret",
    "iso:country":"DK",
    "sg:address":"R\u00e5dhuscentret 5",
    "sg:city":"Vojens",
    "sg:orig_category":"Distriktsbiblioteker",
    "sg:phone":"+45 74 54 16 80",
    "sg:postcode":"6500",
    "sg:province":"Danmark",
    "wof:name":"Vojens Bibliotek",
    "wof:placetype":"venue"
},
  "geometry": {"coordinates":[9.2918519974,55.2469406128],"type":"Point"}
}