{
  "type": "Feature",
  "properties": {
    "iso:country":"DK",
    "sg:address":"Kags\u00e5brinken 27",
    "sg:city":"Herlev",
    "sg:orig_category":"Reklamebureauer",
    "sg:phone":"+45 44 84 27 63",
    "sg:postcode":"2730",
    "sg:province":"Danmark",
    "wof:name":"R.H. Grafik",
    "wof:placetype":"venue"
},
  "geometry": {"coordinates":[12.4495830536,55.740020752],"type":"Point"}
}