{
  "type": "Feature",
  "properties": {
    "addr:full":"Fmd.: Poul Thrane, St\u00e6revej 4 Skagen Danmark 9990",
    "addr:housenumber":"4",
    "addr:postcode":"9990",
    "addr:street":"Poul Thrane Staerevej",
    "iso:country":"DK",
    "sg:address":"Fmd.: Poul Thrane, St\u00e6revej 4",
    "sg:city":"Skagen",
    "sg:orig_category":"Hobbybetonede foreninger",
    "sg:phone":"+45 98 44 34 92",
    "sg:postcode":"9990",
    "sg:province":"Danmark",
    "wof:name":"Skagen M\u00f8ntsamlerforening",
    "wof:placetype":"venue"
},
  "geometry": {"coordinates":[10.5958003998,57.7247200012],"type":"Point"}
}