{
  "type": "Feature",
  "properties": {
    "addr:full":"Stamholmen 151 Hvidovre Danmark 2650",
    "addr:housenumber":"151",
    "addr:postcode":"2650",
    "addr:street":"Stamholmen",
    "iso:country":"DK",
    "sg:address":"Stamholmen 151",
    "sg:city":"Hvidovre",
    "sg:orig_category":"Telebutikker",
    "sg:phone":"+45 33 88 42 42",
    "sg:postcode":"2650",
    "sg:province":"Danmark",
    "sg:website":"www.felxtronics.com",
    "wof:name":"Flextronics International Denmark ApS",
    "wof:placetype":"venue"
},
  "geometry": {"coordinates":[12.474029541,55.6143875122],"type":"Point"}
}