{
  "type": "Feature",
  "properties": {
    "addr:full":"L\u00f8vagervej 20, Errits\u00f8 Fredericia Danmark 7000",
    "addr:housenumber":"20",
    "addr:postcode":"7000",
    "addr:street":"Lovagervej",
    "iso:country":"DK",
    "sg:address":"L\u00f8vagervej 20, Errits\u00f8",
    "sg:city":"Fredericia",
    "sg:orig_category":"Vinduespolering",
    "sg:phone":"+45 75 94 07 57",
    "sg:postcode":"7000",
    "sg:province":"Danmark",
    "wof:name":"Broe, Jon",
    "wof:placetype":"venue"
},
  "geometry": {"coordinates":[9.7591047287,55.566368103],"type":"Point"}
}