{
  "type": "Feature",
  "properties": {
    "addr:full":"Kratbjerg 304 Fredensborg Danmark 3480",
    "addr:housenumber":"304",
    "addr:postcode":"3480",
    "addr:street":"Kratbjerg",
    "iso:country":"DK",
    "sg:address":"Kratbjerg 304",
    "sg:city":"Fredensborg",
    "sg:orig_category":"Emballage",
    "sg:phone":"+45 48 48 36 00",
    "sg:postcode":"3480",
    "sg:province":"Danmark",
    "wof:name":"Berggreen & Co. A/S, S\u00f8ren",
    "wof:placetype":"venue"
},
  "geometry": {"coordinates":[12.391084671,55.9673728943],"type":"Point"}
}