{
  "type": "Feature",
  "properties": {
    "iso:country":"DK",
    "sg:address":"N\u00f8rregade 35",
    "sg:city":"Bramming",
    "sg:orig_category":"Landbrugsmaskiner",
    "sg:phone":"+45 75 17 31 38",
    "sg:postcode":"6740",
    "sg:province":"Danmark",
    "wof:name":"Toxv\u00e6rd Maskinforretning",
    "wof:placetype":"venue"
},
  "geometry": {"coordinates":[8.6966466904,55.4672698975],"type":"Point"}
}