{
  "type": "Feature",
  "properties": {
    "addr:full":"v/ J\u00f8rgen Edvard Jensen, Vemmedrupvej 205, Vemmedrup Bj\u00e6verskov Danmark 4632",
    "addr:housenumber":"205",
    "addr:postcode":"4632",
    "addr:street":"Edvard Jensen Vemmedrupvej",
    "iso:country":"DK",
    "sg:address":"v/ J\u00f8rgen Edvard Jensen, Vemmedrupvej 205, Vemmedrup",
    "sg:city":"Bj\u00e6verskov",
    "sg:orig_category":"Politi",
    "sg:phone":"+45 56 87 08 47",
    "sg:postcode":"4632",
    "sg:province":"Danmark",
    "wof:name":"Landpolitiet i Vemmedrup",
    "wof:placetype":"venue"
},
  "geometry": {"coordinates":[12.032699585,55.461265564],"type":"Point"}
}