{
  "type": "Feature",
  "properties": {
    "addr:full":"Sdr. Rind Vej 70 Viborg Danmark 8800",
    "addr:housenumber":"70",
    "addr:postcode":"8800",
    "addr:street":"Sdr. Rind Vej",
    "iso:country":"DK",
    "sg:address":"Sdr. Rind Vej 70",
    "sg:city":"Viborg",
    "sg:orig_category":"Murermestre",
    "sg:phone":"+45 86 63 96 04",
    "sg:postcode":"8800",
    "sg:province":"Danmark",
    "wof:name":"B\u00f8vling, Henry",
    "wof:placetype":"venue"
},
  "geometry": {"coordinates":[9.4700584412,56.3916358948],"type":"Point"}
}