{
  "type": "Feature",
  "properties": {
    "addr:full":"Danmarksgade 31 Frederikshavn Danmark 9900",
    "addr:housenumber":"31",
    "addr:postcode":"9900",
    "addr:street":"Danmarksgade",
    "iso:country":"DK",
    "sg:address":"Danmarksgade 31",
    "sg:city":"Frederikshavn",
    "sg:orig_category":"Gallerier",
    "sg:phone":"+45 98 42 72 00",
    "sg:postcode":"9900",
    "sg:province":"Danmark",
    "wof:name":"Ramme Galleriet",
    "wof:placetype":"venue"
},
  "geometry": {"coordinates":[10.5380163193,57.4425163269],"type":"Point"}
}