{
  "type": "Feature",
  "properties": {
    "addr:full":"Sverigesvej 22 Middelfart Danmark 5500",
    "addr:housenumber":"22",
    "addr:postcode":"5500",
    "addr:street":"Sverigesvej",
    "iso:country":"DK",
    "sg:address":"Sverigesvej 22",
    "sg:city":"Middelfart",
    "sg:orig_category":"Kiosker",
    "sg:phone":"+45 64 41 84 40",
    "sg:postcode":"5500",
    "sg:province":"Danmark",
    "wof:name":"Melfar D\u00f8gnkiosk",
    "wof:placetype":"venue"
},
  "geometry": {"coordinates":[9.7343053818,55.4979934692],"type":"Point"}
}