{
  "type": "Feature",
  "properties": {
    "addr:full":"Vesterparken 3 Ringe Danmark 5750",
    "addr:housenumber":"3",
    "addr:postcode":"5750",
    "addr:street":"Vesterparken",
    "iso:country":"DK",
    "sg:address":"Vesterparken 3",
    "sg:city":"Ringe",
    "sg:orig_category":"\u00c3\u02dcvrige institutioner",
    "sg:phone":"+45 62 62 31 11",
    "sg:postcode":"5750",
    "sg:province":"Danmark",
    "wof:name":"Bof\u00e6llesskabet Vesterparken",
    "wof:placetype":"venue"
},
  "geometry": {"coordinates":[10.4780225754,55.235786438],"type":"Point"}
}