{
  "type": "Feature",
  "properties": {
    "addr:full":"J\u00e6gersborgvej 53 Kongens Lyngby Danmark 2800",
    "addr:housenumber":"53",
    "addr:postcode":"2800",
    "addr:street":"Jaegersborgvej",
    "iso:country":"DK",
    "sg:address":"J\u00e6gersborgvej 53",
    "sg:city":"Kongens Lyngby",
    "sg:orig_category":"Rideskoler",
    "sg:phone":"+45 45 88 44 80",
    "sg:postcode":"2800",
    "sg:province":"Danmark",
    "wof:name":"Lyngby-Taarb\u00e6k Ridecenter Stenr\u00f8dg\u00e5rd",
    "wof:placetype":"venue"
},
  "geometry": {"coordinates":[12.5368299484,55.7949905396],"type":"Point"}
}