{
  "type": "Feature",
  "properties": {
    "addr:full":"Svanens Kvarter 24 Albertslund Danmark 2620",
    "addr:housenumber":"24",
    "addr:postcode":"2620",
    "addr:street":"Svanens Kvarter",
    "iso:country":"DK",
    "sg:address":"Svanens Kvarter 24",
    "sg:city":"Albertslund",
    "sg:orig_category":"Fritidsklubber",
    "sg:phone":"+45 43 64 63 41",
    "sg:postcode":"2620",
    "sg:province":"Danmark",
    "wof:name":"Svanen",
    "wof:placetype":"venue"
},
  "geometry": {"coordinates":[12.3405170441,55.6527061462],"type":"Point"}
}