{
  "type": "Feature",
  "properties": {
    "addr:full":"Trinnerupvej 15, Vester Korup Terndrup Danmark 9575",
    "addr:housenumber":"15",
    "addr:postcode":"9575",
    "addr:street":"Trinnerupvej;Vester Korup;Danmark",
    "iso:country":"DK",
    "sg:address":"Trinnerupvej 15, Vester Korup",
    "sg:city":"Terndrup",
    "sg:orig_category":"Gartnerier",
    "sg:phone":"+45 98 58 90 16",
    "sg:postcode":"9575",
    "sg:province":"Danmark",
    "wof:name":"Korup, Erling",
    "wof:placetype":"venue"
},
  "geometry": {"coordinates":[10.058382988,56.8162651062],"type":"Point"}
}