{
  "type": "Feature",
  "properties": {
    "addr:full":"Blomstermarken 17, M\u00f8rdrup Esperg\u00e6rde Danmark 3060",
    "addr:housenumber":"17",
    "addr:postcode":"3060",
    "addr:street":"Blomstermarken",
    "iso:country":"DK",
    "sg:address":"Blomstermarken 17, M\u00f8rdrup",
    "sg:city":"Esperg\u00e6rde",
    "sg:orig_category":"Arkitekter",
    "sg:phone":"+45 49 13 59 87",
    "sg:postcode":"3060",
    "sg:province":"Danmark",
    "wof:name":"Frederiksen, Peter M.",
    "wof:placetype":"venue"
},
  "geometry": {"coordinates":[11.6512403488,47.8390617371],"type":"Point"}
}