{
  "type": "Feature",
  "properties": {
    "addr:full":"Strandboulevarden 59 K\u00f8benhavn \u00d8 Danmark 2100",
    "addr:housenumber":"59",
    "addr:postcode":"2100",
    "addr:street":"Strandboulevarden",
    "iso:country":"DK",
    "sg:address":"Strandboulevarden 59",
    "sg:city":"K\u00f8benhavn \u00d8",
    "sg:orig_category":"Pengeinstitutter",
    "sg:phone":"+45 35 25 32 70",
    "sg:postcode":"2100",
    "sg:province":"Danmark",
    "wof:name":"Danske Bank",
    "wof:placetype":"venue"
},
  "geometry": {"coordinates":[12.5865697861,55.7065696716],"type":"Point"}
}