{
  "type": "Feature",
  "properties": {
    "addr:full":"Jordb\u00e6rvangen 42, Sm\u00f8rumnedre Sm\u00f8rum Danmark 2765",
    "addr:housenumber":"42",
    "addr:postcode":"2765",
    "addr:street":"Jordbaervangen",
    "iso:country":"DK",
    "sg:address":"Jordb\u00e6rvangen 42, Sm\u00f8rumnedre",
    "sg:city":"Sm\u00f8rum",
    "sg:orig_category":"Snedkermestre",
    "sg:phone":"+45 44 65 35 45",
    "sg:postcode":"2765",
    "sg:province":"Danmark",
    "wof:name":"Vibe Snedker-og T\u00f8mrerfirma ApS, J",
    "wof:placetype":"venue"
},
  "geometry": {"coordinates":[-89.99810791020001,38.1321372986],"type":"Point"}
}