{
  "type": "Feature",
  "properties": {
    "iso:country":"DK",
    "sg:address":"Leder: Anna Elisse Graversen, \u00d8stparken 61, Ejsing",
    "sg:city":"Vinderup",
    "sg:orig_category":"\u00c3\u02dcvrig fritidsundervisning",
    "sg:phone":"+45 97 44 62 09",
    "sg:postcode":"7830",
    "sg:province":"Danmark",
    "wof:name":"Vinderup Aftenskole",
    "wof:placetype":"venue"
},
  "geometry": {"coordinates":[8.7796897888,56.482635498],"type":"Point"}
}