{
  "type": "Feature",
  "properties": {
    "addr:full":"Bagergade 34 Svendborg Danmark 5700",
    "addr:housenumber":"34",
    "addr:postcode":"5700",
    "addr:street":"Bagergade",
    "iso:country":"DK",
    "sg:address":"Bagergade 34",
    "sg:city":"Svendborg",
    "sg:orig_category":"Loger",
    "sg:phone":"+45 62 22 40 54",
    "sg:postcode":"5700",
    "sg:province":"Danmark",
    "wof:name":"Odd Fellow Logerne",
    "wof:placetype":"venue"
},
  "geometry": {"coordinates":[10.6075792313,55.0617027283],"type":"Point"}
}