{
  "type": "Feature",
  "properties": {
    "addr:full":"Borumvej 12, Skivholme Galten Danmark 8464",
    "addr:housenumber":"12",
    "addr:postcode":"8464",
    "addr:street":"Borumvej;Skivholme",
    "iso:country":"DK",
    "sg:address":"Borumvej 12, Skivholme",
    "sg:city":"Galten",
    "sg:orig_category":"Murermestre",
    "sg:phone":"+45 86 95 41 86",
    "sg:postcode":"8464",
    "sg:province":"Danmark",
    "wof:name":"Kristensen, Ove",
    "wof:placetype":"venue"
},
  "geometry": {"coordinates":[9.9034748077,56.1558837891],"type":"Point"}
}