{
  "type": "Feature",
  "properties": {
    "addr:full":"Bj\u00f8rstrupvej 50 Gr\u00e6sted Danmark 3230",
    "addr:housenumber":"50",
    "addr:postcode":"3230",
    "addr:street":"Bjorstrupvej",
    "iso:country":"DK",
    "sg:address":"Bj\u00f8rstrupvej 50",
    "sg:city":"Gr\u00e6sted",
    "sg:orig_category":"Virksomhedskonsulenter",
    "sg:phone":"+45 48 39 48 47",
    "sg:postcode":"3230",
    "sg:province":"Danmark",
    "wof:name":"Feldt Consulting A/S, Niels",
    "wof:placetype":"venue"
},
  "geometry": {"coordinates":[-78.6975326538,35.0151481628],"type":"Point"}
}