{
  "type": "Feature",
  "properties": {
    "iso:country":"DK",
    "sg:address":"D. Lauritzens Vej 8",
    "sg:city":"Esbjerg",
    "sg:orig_category":"Lufttransport",
    "sg:phone":"+45 76 11 48 88",
    "sg:postcode":"6700",
    "sg:province":"Danmark",
    "sg:website":"www.leman.dk",
    "wof:name":"Leman System Transport A/S",
    "wof:placetype":"venue"
},
  "geometry": {"coordinates":[8.4378528595,55.4653968811],"type":"Point"}
}