{
  "type": "Feature",
  "properties": {
    "addr:full":"Dyssevej 3, Kongsted R\u00f8nnede Danmark 4683",
    "addr:housenumber":"3",
    "addr:postcode":"4683",
    "addr:street":"Dyssevej",
    "iso:country":"DK",
    "sg:address":"Dyssevej 3, Kongsted",
    "sg:city":"R\u00f8nnede",
    "sg:orig_category":"Sparekasser",
    "sg:phone":"+45 56 71 11 38",
    "sg:postcode":"4683",
    "sg:province":"Danmark",
    "wof:name":"Kongsted Sparekasse",
    "wof:placetype":"venue"
},
  "geometry": {"coordinates":[12.040017128,55.2451210022],"type":"Point"}
}