{
  "type": "Feature",
  "properties": {
    "addr:full":"Bolbrovej 64 Rungsted Kyst Danmark 2960",
    "addr:housenumber":"64",
    "addr:postcode":"2960",
    "addr:street":"Bolbrovej",
    "iso:country":"DK",
    "sg:address":"Bolbrovej 64",
    "sg:city":"Rungsted Kyst",
    "sg:classifiers":[
        {
            "category":"Restaurant",
            "type":"Food & Drink"
        }
    ],
    "sg:phone":"+45 45 76 54 11",
    "sg:postcode":"2960",
    "sg:province":"Danmark",
    "wof:name":"All Happy Wongs Take Away Restaurant",
    "wof:placetype":"venue"
},
  "geometry": {"coordinates":[12.5257329941,55.891078949],"type":"Point"}
}