{
  "type": "Feature",
  "properties": {
    "addr:full":"H\u00f8jmose V\u00e6nge 2 A H\u00f8rsholm Danmark 2970",
    "addr:housenumber":"2 a",
    "addr:postcode":"2970",
    "addr:street":"Vaenge",
    "iso:country":"DK",
    "sg:address":"H\u00f8jmose V\u00e6nge 2 A",
    "sg:city":"H\u00f8rsholm",
    "sg:orig_category":"Kirker",
    "sg:postcode":"2970",
    "sg:province":"Danmark",
    "wof:name":"Kokkedal Kirke",
    "wof:placetype":"venue"
},
  "geometry": {"coordinates":[12.4917097092,55.8894538879],"type":"Point"}
}