{
  "type": "Feature",
  "properties": {
    "addr:full":"Parkvej 6 Herning Danmark 7400",
    "addr:housenumber":"6",
    "addr:postcode":"7400",
    "addr:street":"Parkvej",
    "iso:country":"DK",
    "sg:address":"Parkvej 6",
    "sg:city":"Herning",
    "sg:classifiers":[
        {
            "category":"Arts & Performance",
            "subcategory":"Festival",
            "type":"Entertainment"
        }
    ],
    "sg:phone":"+45 97 12 47 11",
    "sg:postcode":"7400",
    "sg:province":"Danmark",
    "sg:tags":[
        "tekstilindustri"
    ],
    "sg:website":"www.textiles.dk",
    "wof:name":"Textiles A/S",
    "wof:placetype":"venue"
},
  "geometry": {"coordinates":[8.9892187119,56.1373558044],"type":"Point"}
}