{
  "type": "Feature",
  "properties": {
    "addr:full":"F\u00f8lfodvej 29 Vodskov Danmark 9310",
    "addr:housenumber":"29",
    "addr:postcode":"9310",
    "addr:street":"Folfodvej",
    "iso:country":"DK",
    "sg:address":"F\u00f8lfodvej 29",
    "sg:city":"Vodskov",
    "sg:orig_category":"Faglige organisationer og foreninger",
    "sg:phone":"+45 98 29 32 11",
    "sg:postcode":"9310",
    "sg:province":"Danmark",
    "wof:name":"Elinstallat\u00f8rforeningen For Sydvendsyssel",
    "wof:placetype":"venue"
},
  "geometry": {"coordinates":[10.0231132507,57.1020278931],"type":"Point"}
}