{
  "type": "Feature",
  "properties": {
    "iso:country":"DK",
    "sg:address":"Algade 6",
    "sg:city":"Vordingborg",
    "sg:orig_category":"Solcentre",
    "sg:phone":"+45 70 23 10 03",
    "sg:postcode":"4760",
    "sg:province":"Danmark",
    "wof:name":"Byens Solcenter",
    "wof:placetype":"venue"
},
  "geometry": {"coordinates":[11.9011764526,55.0125045776],"type":"Point"}
}