{
  "type": "Feature",
  "properties": {
    "addr:full":"S\u00f8ndre Viaduktvej 17 K\u00f8ge Danmark 4600",
    "addr:housenumber":"17",
    "addr:postcode":"4600",
    "addr:street":"Viaduktvej",
    "iso:country":"DK",
    "sg:address":"S\u00f8ndre Viaduktvej 17",
    "sg:city":"K\u00f8ge",
    "sg:orig_category":"Autolakering",
    "sg:phone":"+45 56 65 33 23",
    "sg:postcode":"4600",
    "sg:province":"Danmark",
    "wof:name":"K\u00f8ge Autolak Center",
    "wof:placetype":"venue"
},
  "geometry": {"coordinates":[12.1809616089,55.4491577148],"type":"Point"}
}