{
  "type": "Feature",
  "properties": {
    "addr:full":"Energivej 13 Esbjerg Danmark 6700",
    "addr:housenumber":"13",
    "addr:postcode":"6700",
    "addr:street":"Energivej",
    "iso:country":"DK",
    "sg:address":"Energivej 13",
    "sg:city":"Esbjerg",
    "sg:orig_category":"Farve- og lakfabrikker",
    "sg:phone":"+45 75 12 86 00",
    "sg:postcode":"6700",
    "sg:province":"Danmark",
    "sg:website":"www.esbjergpaints.dk",
    "wof:name":"Esbjerg Farve- & Lakfabrik A/S",
    "wof:placetype":"venue"
},
  "geometry": {"coordinates":[8.4994792938,55.4639663696],"type":"Point"}
}