{
  "type": "Feature",
  "properties": {
    "iso:country":"DK",
    "sg:address":"Vestergade 22 B",
    "sg:city":"Thisted",
    "sg:orig_category":"Dentallaboratorier",
    "sg:phone":"+45 97 92 30 15",
    "sg:postcode":"7700",
    "sg:province":"Danmark",
    "wof:name":"Thisted Dental Laboratorium",
    "wof:placetype":"venue"
},
  "geometry": {"coordinates":[8.6874818802,56.95495224],"type":"Point"}
}