{
  "type": "Feature",
  "properties": {
    "addr:full":"Hjultorvet 11 Viborg Danmark 8800",
    "addr:housenumber":"11",
    "addr:postcode":"8800",
    "addr:street":"Hjultorvet",
    "iso:country":"DK",
    "sg:address":"Hjultorvet 11",
    "sg:city":"Viborg",
    "sg:orig_category":"Lokalarkiver",
    "sg:phone":"+45 87 25 26 25",
    "sg:postcode":"8800",
    "sg:province":"Danmark",
    "sg:website":"www.viborgstiftsmuseum.dk",
    "wof:name":"Lokalhistorisk Arkiv for Viborg Kommune",
    "wof:placetype":"venue"
},
  "geometry": {"coordinates":[9.4086904526,56.450138092],"type":"Point"}
}