{
  "type": "Feature",
  "properties": {
    "addr:full":"Fmd. Torben Holst, D\u00f8nnerg\u00e5rds Alle 12 Greve Danmark 2670",
    "addr:housenumber":"12",
    "addr:postcode":"2670",
    "addr:street":"Donnergaards Alle",
    "iso:country":"DK",
    "sg:address":"Fmd. Torben Holst, D\u00f8nnerg\u00e5rds Alle 12",
    "sg:city":"Greve",
    "sg:orig_category":"Grundejerforeninger",
    "sg:phone":"+45 43 61 18 08",
    "sg:postcode":"2670",
    "sg:province":"Danmark",
    "wof:name":"Allene Grundejerforening",
    "wof:placetype":"venue"
},
  "geometry": {"coordinates":[12.2869987488,55.5893821716],"type":"Point"}
}