{
  "type": "Feature",
  "properties": {
    "iso:country":"DK",
    "sg:address":"Hortensiavej 11",
    "sg:city":"Ebeltoft",
    "sg:orig_category":"INGENI\u00c3\u02dcRER",
    "sg:phone":"+45 86 34 66 67",
    "sg:postcode":"8400",
    "sg:province":"Danmark",
    "wof:name":"Toria ApS",
    "wof:placetype":"venue"
},
  "geometry": {"coordinates":[10.6771450043,56.1881446838],"type":"Point"}
}