{
  "type": "Feature",
  "properties": {
    "addr:full":"Svendborgvej 44, Ollerup Vester Skerninge Danmark 5762",
    "addr:housenumber":"44",
    "addr:postcode":"5762",
    "addr:street":"Svendborgvej",
    "iso:country":"DK",
    "sg:address":"Svendborgvej 44, Ollerup",
    "sg:city":"Vester Skerninge",
    "sg:orig_category":"Blomsterhandlere",
    "sg:phone":"+45 62 24 20 10",
    "sg:postcode":"5762",
    "sg:province":"Danmark",
    "wof:name":"Anemonen",
    "wof:placetype":"venue"
},
  "geometry": {"coordinates":[10.5008449554,55.070400238],"type":"Point"}
}