{
  "type": "Feature",
  "properties": {
    "addr:full":"Stenager Alle 1, Hj\u00f8rring Hj\u00f8rring Danmark 9800",
    "addr:housenumber":"1",
    "addr:postcode":"9800",
    "addr:street":"Stenager Alle",
    "iso:country":"DK",
    "sg:address":"Stenager Alle 1, Hj\u00f8rring",
    "sg:city":"Hj\u00f8rring",
    "sg:orig_category":"Medicinalvareindustri",
    "sg:phone":"+45 44 44 88 88",
    "sg:postcode":"9800",
    "sg:province":"Danmark",
    "wof:name":"Novo-Nordisk A/S",
    "wof:placetype":"venue"
},
  "geometry": {"coordinates":[9.9885387421,57.4594764709],"type":"Point"}
}