{
  "type": "Feature",
  "properties": {
    "addr:full":"Themsvej 15 Risskov Danmark 8240",
    "addr:housenumber":"15",
    "addr:postcode":"8240",
    "addr:street":"Themsvej",
    "iso:country":"DK",
    "sg:address":"Themsvej 15",
    "sg:city":"Risskov",
    "sg:orig_category":"Pengeinstitutter",
    "sg:phone":"+45 86 17 52 62",
    "sg:postcode":"8240",
    "sg:province":"Danmark",
    "wof:name":"\u00c5rhus Nordre Kontor",
    "wof:placetype":"venue"
},
  "geometry": {"coordinates":[10.2500677109,56.1944618225],"type":"Point"}
}