{
  "type": "Feature",
  "properties": {
    "addr:full":"Granskoven 201 Glostrup Danmark 2600",
    "addr:housenumber":"201",
    "addr:postcode":"2600",
    "addr:street":"Granskoven",
    "iso:country":"DK",
    "sg:address":"Granskoven 201",
    "sg:city":"Glostrup",
    "sg:orig_category":"Malermestre",
    "sg:phone":"+45 43 45 31 31",
    "sg:postcode":"2600",
    "sg:province":"Danmark",
    "wof:name":"Poul E. Pedersen",
    "wof:placetype":"venue"
},
  "geometry": {"coordinates":[12.4115524292,55.6821174622],"type":"Point"}
}