{
  "type": "Feature",
  "properties": {
    "addr:full":"Permelille 14 Sams\u00f8 Danmark 8305",
    "addr:housenumber":"14",
    "addr:postcode":"8305",
    "addr:street":"Permelille",
    "iso:country":"DK",
    "sg:address":"Permelille 14",
    "sg:city":"Sams\u00f8",
    "sg:orig_category":"Ridning",
    "sg:phone":"+45 86 59 10 71",
    "sg:postcode":"8305",
    "sg:province":"Danmark",
    "wof:name":"Sams\u00f8 Ridecenter",
    "wof:placetype":"venue"
},
  "geometry": {"coordinates":[10.5801362991,55.8080635071],"type":"Point"}
}