{
  "type": "Feature",
  "properties": {
    "iso:country":"DK",
    "sg:address":"Omorikavej 6",
    "sg:city":"Hjallerup",
    "sg:orig_category":"Autolakering",
    "sg:phone":"+45 98 28 10 60",
    "sg:postcode":"9320",
    "sg:province":"Danmark",
    "wof:name":"Hjallerup Autolakering",
    "wof:placetype":"venue"
},
  "geometry": {"coordinates":[10.1404018402,57.1692314148],"type":"Point"}
}