{
  "type": "Feature",
  "properties": {
    "addr:full":"Bregnevej 11 Frederikssund Danmark 3600",
    "addr:housenumber":"11",
    "addr:postcode":"3600",
    "addr:street":"Bregnevej",
    "iso:country":"DK",
    "sg:address":"Bregnevej 11",
    "sg:city":"Frederikssund",
    "sg:orig_category":"Malermestre",
    "sg:phone":"+45 47 31 38 38",
    "sg:postcode":"3600",
    "sg:province":"Danmark",
    "wof:name":"Bojsen-M\u00f8ller, Helge",
    "wof:placetype":"venue"
},
  "geometry": {"coordinates":[12.0753326416,55.83959198],"type":"Point"}
}