{
  "type": "Feature",
  "properties": {
    "addr:full":"Langgade 14 Hesselager Danmark 5874",
    "addr:housenumber":"14",
    "addr:postcode":"5874",
    "addr:street":"Langgade",
    "iso:country":"DK",
    "sg:address":"Langgade 14",
    "sg:city":"Hesselager",
    "sg:orig_category":"Autoreparation og -service",
    "sg:phone":"+45 62 25 12 56",
    "sg:postcode":"5874",
    "sg:province":"Danmark",
    "wof:name":"Hesselager Autov\u00e6rksted",
    "wof:placetype":"venue"
},
  "geometry": {"coordinates":[10.734172821,55.1698989868],"type":"Point"}
}