{
  "type": "Feature",
  "properties": {
    "addr:full":"v/ Edith S\u00f8rensen, Svalev\u00e6nget 22, Hogager Holstebro Danmark 7500",
    "addr:housenumber":"22",
    "addr:postcode":"7500",
    "addr:street":"Hogager",
    "iso:country":"DK",
    "sg:address":"v/ Edith S\u00f8rensen, Svalev\u00e6nget 22, Hogager",
    "sg:city":"Holstebro",
    "sg:orig_category":"Forsamlingshuse",
    "sg:phone":"+45 97 46 84 31",
    "sg:postcode":"7500",
    "sg:province":"Danmark",
    "wof:name":"Hogager Sogneg\u00e5rd",
    "wof:placetype":"venue"
},
  "geometry": {"coordinates":[8.6202583313,56.3625221252],"type":"Point"}
}