{
  "type": "Feature",
  "properties": {
    "addr:full":"Brandmosevej 11 Ballerup Danmark 2750",
    "addr:housenumber":"11",
    "addr:postcode":"2750",
    "addr:street":"Brandmosevej",
    "iso:country":"DK",
    "sg:address":"Brandmosevej 11",
    "sg:city":"Ballerup",
    "sg:orig_category":"Fritidshuse",
    "sg:phone":"+45 44 65 11 92",
    "sg:postcode":"2750",
    "sg:province":"Danmark",
    "wof:name":"Ejly Fritidshuse",
    "wof:placetype":"venue"
},
  "geometry": {"coordinates":[12.3449659348,55.7427635193],"type":"Point"}
}