{
  "type": "Feature",
  "properties": {
    "iso:country":"DK",
    "sg:address":"v/ Sven-Henrik Brandstrup, Truust Gade 16, Truust",
    "sg:city":"F\u00e5rvang",
    "sg:orig_category":"Kulturelle foreninger",
    "sg:phone":"+45 86 87 16 20",
    "sg:postcode":"8882",
    "sg:province":"Danmark",
    "wof:name":"Kultursamvirket",
    "wof:placetype":"venue"
},
  "geometry": {"coordinates":[9.7311849594,56.2691383362],"type":"Point"}
}