{
  "type": "Feature",
  "properties": {
    "addr:full":"Madeskovvej 9 Krus\u00e5 Danmark 6340",
    "addr:housenumber":"9",
    "addr:postcode":"6340",
    "addr:street":"Madeskovvej",
    "iso:country":"DK",
    "sg:address":"Madeskovvej 9",
    "sg:city":"Krus\u00e5",
    "sg:orig_category":"Antikviteter",
    "sg:phone":"+45 74 67 09 99",
    "sg:postcode":"6340",
    "sg:province":"Danmark",
    "sg:website":"www.krusaa-antik.dk",
    "wof:name":"Krus\u00e5 Antikvitets Lager ApS",
    "wof:placetype":"venue"
},
  "geometry": {"coordinates":[9.4024801254,54.8428726196],"type":"Point"}
}