{
  "type": "Feature",
  "properties": {
    "addr:full":"N\u00f8rrevoldgade 48 Nyborg Danmark 5800",
    "addr:housenumber":"48",
    "addr:postcode":"5800",
    "addr:street":"Norrevoldgade",
    "iso:country":"DK",
    "sg:address":"N\u00f8rrevoldgade 48",
    "sg:city":"Nyborg",
    "sg:classifiers":[
        {
            "category":"Communications",
            "type":"Services"
        }
    ],
    "sg:phone":"+45 65 31 44 11",
    "sg:postcode":"5800",
    "sg:province":"Danmark",
    "sg:tags":[
        "radio-",
        "og",
        "tv-stationer"
    ],
    "wof:name":"Fyns Musikradio",
    "wof:placetype":"venue"
},
  "geometry": {"coordinates":[10.7940073013,55.3122787476],"type":"Point"}
}