{
  "type": "Feature",
  "properties": {
    "addr:full":"v/Else H. Thomsen, Egelandvej 11, Starup Egtved Danmark 6040",
    "addr:housenumber":"11",
    "addr:postcode":"6040",
    "addr:street":"Egelandvej",
    "iso:country":"DK",
    "sg:address":"v/Else H. Thomsen, Egelandvej 11, Starup",
    "sg:city":"Egtved",
    "sg:orig_category":"Kulturelle foreninger",
    "sg:phone":"+45 75 55 35 18",
    "sg:postcode":"6040",
    "sg:province":"Danmark",
    "wof:name":"Kulturelt Samvirke i Egtved Kommune",
    "wof:placetype":"venue"
},
  "geometry": {"coordinates":[9.3087482452,55.6161613464],"type":"Point"}
}