{
  "type": "Feature",
  "properties": {
    "addr:full":"Storskoven 11, Annisse Helsinge Danmark 3200",
    "addr:housenumber":"11",
    "addr:postcode":"3200",
    "addr:street":"Storskoven;Annisse",
    "iso:country":"DK",
    "sg:address":"Storskoven 11, Annisse",
    "sg:city":"Helsinge",
    "sg:orig_category":"Revisorer",
    "sg:phone":"+45 48 79 13 33",
    "sg:postcode":"3200",
    "sg:province":"Danmark",
    "wof:name":"Andersen, Torben",
    "wof:placetype":"venue"
},
  "geometry": {"coordinates":[12.196846962,56.0224456787],"type":"Point"}
}