{
  "type": "Feature",
  "properties": {
    "addr:full":"Ellingevej 1 H\u00f8jby Danmark 4573",
    "addr:housenumber":"1",
    "addr:postcode":"4573",
    "addr:street":"Ellingevej",
    "iso:country":"DK",
    "sg:address":"Ellingevej 1",
    "sg:city":"H\u00f8jby",
    "sg:orig_category":"Keramik",
    "sg:phone":"+45 59 30 36 17",
    "sg:postcode":"4573",
    "sg:province":"Danmark",
    "wof:name":"H\u00f8iby Keramik og Galleri",
    "wof:placetype":"venue"
},
  "geometry": {"coordinates":[11.5910835266,55.9083175659],"type":"Point"}
}