{
  "type": "Feature",
  "properties": {
    "addr:full":"Skt. Gertruds Str\u00e6de 4 Odense C Danmark 5000",
    "addr:housenumber":"4",
    "addr:postcode":"5000",
    "addr:street":"Skt. Gertruds Straede",
    "iso:country":"DK",
    "sg:address":"Skt. Gertruds Str\u00e6de 4",
    "sg:city":"Odense C",
    "sg:orig_category":"Psykologer, praktiserende",
    "sg:phone":"+45 66 12 15 50",
    "sg:postcode":"5000",
    "sg:province":"Danmark",
    "wof:name":"Kropsdynamisk Analyse og Psykoterapi",
    "wof:placetype":"venue"
},
  "geometry": {"coordinates":[10.3852519989,55.3962745667],"type":"Point"}
}