{
  "type": "Feature",
  "properties": {
    "iso:country":"DK",
    "sg:address":"Sct. Clemens Vej 67",
    "sg:city":"Vordingborg",
    "sg:orig_category":"Kirker",
    "sg:postcode":"4760",
    "sg:province":"Danmark",
    "wof:name":"Kastrup Kirke",
    "wof:placetype":"venue"
},
  "geometry": {"coordinates":[11.892115593,55.0379829407],"type":"Point"}
}