{
  "type": "Feature",
  "properties": {
    "addr:full":"Hundige Storcenter 15 Greve Danmark 2670",
    "addr:housenumber":"15",
    "addr:postcode":"2670",
    "iso:country":"DK",
    "sg:address":"Hundige Storcenter 15",
    "sg:city":"Greve",
    "sg:orig_category":"Non-Classified Establishments",
    "sg:phone":"+45 43 90 73 03",
    "sg:postcode":"2670",
    "sg:province":"Danmark",
    "wof:name":"Pub 2",
    "wof:placetype":"venue"
},
  "geometry": {"coordinates":[12.3288841248,55.5985870361],"type":"Point"}
}