{
  "type": "Feature",
  "properties": {
    "iso:country":"DK",
    "sg:address":"Sogneg\u00e5rdsvej 6",
    "sg:city":"Horsens",
    "sg:orig_category":"Glarmestre og glarmagere",
    "sg:phone":"+45 75 64 70 55",
    "sg:postcode":"8700",
    "sg:province":"Danmark",
    "wof:name":"Dagn\u00e6s Glaslager",
    "wof:placetype":"venue"
},
  "geometry": {"coordinates":[9.8435144424,55.8474655151],"type":"Point"}
}