{
  "type": "Feature",
  "properties": {
    "addr:full":"Fuglev\u00e6nget 25 Hornslet Danmark 8543",
    "addr:housenumber":"25",
    "addr:postcode":"8543",
    "addr:street":"Fuglevaenget",
    "iso:country":"DK",
    "sg:address":"Fuglev\u00e6nget 25",
    "sg:city":"Hornslet",
    "sg:orig_category":"Foder",
    "sg:phone":"+45 86 97 50 05",
    "sg:postcode":"8543",
    "sg:province":"Danmark",
    "wof:name":"St. Hippolyt",
    "wof:placetype":"venue"
},
  "geometry": {"coordinates":[10.3180999756,56.3159866333],"type":"Point"}
}