{
  "type": "Feature",
  "properties": {
    "addr:full":"Dybdalsvej 6, Daugbjerg Viborg Danmark 8800",
    "addr:housenumber":"6",
    "addr:postcode":"8800",
    "addr:street":"Dybdalsvej;Daugbjerg",
    "iso:country":"DK",
    "sg:address":"Dybdalsvej 6, Daugbjerg",
    "sg:city":"Viborg",
    "sg:orig_category":"Forsamlingshuse",
    "sg:phone":"+45 97 54 80 19",
    "sg:postcode":"8800",
    "sg:province":"Danmark",
    "wof:name":"Daugbjerg Forsamlingshus",
    "wof:placetype":"venue"
},
  "geometry": {"coordinates":[9.4071502686,56.452671051],"type":"Point"}
}