{
  "type": "Feature",
  "properties": {
    "addr:full":"Kollundvej 3 Silkeborg Danmark 8600",
    "addr:housenumber":"3",
    "addr:postcode":"8600",
    "addr:street":"Kollundvej",
    "iso:country":"DK",
    "sg:address":"Kollundvej 3",
    "sg:city":"Silkeborg",
    "sg:orig_category":"Integrerede institutioner",
    "sg:phone":"+45 86 82 70 65",
    "sg:postcode":"8600",
    "sg:province":"Danmark",
    "wof:name":"K\u00e6rsg\u00e5rd",
    "wof:placetype":"venue"
},
  "geometry": {"coordinates":[9.5135755539,56.1761398315],"type":"Point"}
}