{
  "type": "Feature",
  "properties": {
    "addr:full":"Danmarksgade 6 Fredericia Danmark 7000",
    "addr:housenumber":"6",
    "addr:postcode":"7000",
    "addr:street":"Danmarksgade",
    "iso:country":"DK",
    "sg:address":"Danmarksgade 6",
    "sg:city":"Fredericia",
    "sg:orig_category":"INGENI\u00c3\u02dcRER",
    "sg:phone":"+45 75 91 55 88",
    "sg:postcode":"7000",
    "sg:province":"Danmark",
    "wof:name":"DAI Gruppen A/S",
    "wof:placetype":"venue"
},
  "geometry": {"coordinates":[9.7539720535,55.5670204163],"type":"Point"}
}