{
  "type": "Feature",
  "properties": {
    "addr:full":"Gl. Landevej 78 Herning Danmark 7400",
    "addr:housenumber":"78",
    "addr:postcode":"7400",
    "addr:street":"Gl. Landevej",
    "iso:country":"DK",
    "sg:address":"Gl. Landevej 78",
    "sg:city":"Herning",
    "sg:orig_category":"El-automatik",
    "sg:phone":"+45 97 21 18 89",
    "sg:postcode":"7400",
    "sg:province":"Danmark",
    "wof:name":"J.H.I. Wire",
    "wof:placetype":"venue"
},
  "geometry": {"coordinates":[8.9711503983,56.1413459778],"type":"Point"}
}