{
  "type": "Feature",
  "properties": {
    "addr:full":"\u00d8disvej 38, Taps Christiansfeld Danmark 6070",
    "addr:housenumber":"38",
    "addr:postcode":"6070",
    "addr:street":"Odisvej",
    "iso:country":"DK",
    "sg:address":"\u00d8disvej 38, Taps",
    "sg:city":"Christiansfeld",
    "sg:orig_category":"Kirker",
    "sg:postcode":"6070",
    "sg:province":"Danmark",
    "wof:name":"Taps Kirke",
    "wof:placetype":"venue"
},
  "geometry": {"coordinates":[9.4834346771,55.3550567627],"type":"Point"}
}