{
  "type": "Feature",
  "properties": {
    "iso:country":"DK",
    "sg:address":"Skagen Butikscenter, Skr\u00e5vej 6 E",
    "sg:city":"Skagen",
    "sg:orig_category":"Blomsterhandlere",
    "sg:phone":"+45 98 44 35 33",
    "sg:postcode":"9990",
    "sg:province":"Danmark",
    "wof:name":"Tonny's Blomster",
    "wof:placetype":"venue"
},
  "geometry": {"coordinates":[10.5958,57.72472],"type":"Point"}
}