{
  "type": "Feature",
  "properties": {
    "iso:country":"DK",
    "sg:address":"Kjeldsmarkvej 11",
    "sg:city":"Struer",
    "sg:orig_category":"Tekstilindustri",
    "sg:phone":"+45 97 85 22 11",
    "sg:postcode":"7600",
    "sg:province":"Danmark",
    "wof:name":"Refsgaard, A/S Lykke",
    "wof:placetype":"venue"
},
  "geometry": {"coordinates":[8.5921802521,56.4817657471],"type":"Point"}
}