{
  "type": "Feature",
  "properties": {
    "addr:full":"Solskr\u00e6nten 8 Hundested Danmark 3390",
    "addr:housenumber":"8",
    "addr:postcode":"3390",
    "addr:street":"Solskraenten",
    "iso:country":"DK",
    "sg:address":"Solskr\u00e6nten 8",
    "sg:city":"Hundested",
    "sg:orig_category":"Non-Classified Establishments",
    "sg:phone":"+45 47 98 05 54",
    "sg:postcode":"3390",
    "sg:province":"Danmark",
    "wof:name":"Kiwi Dataservice",
    "wof:placetype":"venue"
},
  "geometry": {"coordinates":[11.8530349731,55.958530426],"type":"Point"}
}