{
  "type": "Feature",
  "properties": {
    "addr:full":"Nordvejen 1, Morup M\u00f8lle Bedsted Danmark 7755",
    "addr:housenumber":"1",
    "addr:postcode":"7755",
    "addr:street":"Nordvejen",
    "iso:country":"DK",
    "sg:address":"Nordvejen 1, Morup M\u00f8lle",
    "sg:city":"Bedsted",
    "sg:orig_category":"Sparekasser",
    "sg:phone":"+45 97 94 80 24",
    "sg:postcode":"7755",
    "sg:province":"Danmark",
    "sg:website":"www.hvidbjergoerumsparekasse.dk",
    "wof:name":"Hvidbjerg-\u00d8rum Sparekasse",
    "wof:placetype":"venue"
},
  "geometry": {"coordinates":[8.4905691147,56.8179664612],"type":"Point"}
}