{
  "type": "Feature",
  "properties": {
    "addr:full":"S\u00f8ndergade 8 2. Nyborg Danmark 5800",
    "addr:housenumber":"8 2",
    "addr:postcode":"5800",
    "addr:street":"Sondergade",
    "iso:country":"DK",
    "sg:address":"S\u00f8ndergade 8 2.",
    "sg:city":"Nyborg",
    "sg:orig_category":"Zoneterapeuter",
    "sg:phone":"+45 65 30 25 32",
    "sg:postcode":"5800",
    "sg:province":"Danmark",
    "wof:name":"Eriksen, Bjerne",
    "wof:placetype":"venue"
},
  "geometry": {"coordinates":[10.7959632874,55.3091163635],"type":"Point"}
}