{
  "type": "Feature",
  "properties": {
    "iso:country":"DK",
    "sg:address":"Brede Alle 60",
    "sg:city":"Kongens Lyngby",
    "sg:orig_category":"Arkitekter",
    "sg:phone":"+45 45 85 98 16",
    "sg:postcode":"2800",
    "sg:province":"Danmark",
    "wof:name":"Nielsens Tegnestue, Michael H.",
    "wof:placetype":"venue"
},
  "geometry": {"coordinates":[12.4988050461,55.7912368774],"type":"Point"}
}