{
  "type": "Feature",
  "properties": {
    "addr:full":"Byvejen 39 Greve Danmark 2670",
    "addr:housenumber":"39",
    "addr:postcode":"2670",
    "addr:street":"Byvejen",
    "iso:country":"DK",
    "sg:address":"Byvejen 39",
    "sg:city":"Greve",
    "sg:orig_category":"Elektronik",
    "sg:phone":"+45 43 40 50 55",
    "sg:postcode":"2670",
    "sg:province":"Danmark",
    "sg:website":"www.nickelectronic.dk",
    "wof:name":"Nick Electronic ApS",
    "wof:placetype":"venue"
},
  "geometry": {"coordinates":[12.2688102722,55.6099815369],"type":"Point"}
}