{
  "type": "Feature",
  "properties": {
    "addr:full":"Dalbovej 6, Dalby Haslev Danmark 4690",
    "addr:housenumber":"6",
    "addr:postcode":"4690",
    "addr:street":"Dalbovej",
    "iso:country":"DK",
    "sg:address":"Dalbovej 6, Dalby",
    "sg:city":"Haslev",
    "sg:orig_category":"Blikkenslagere",
    "sg:phone":"+45 56 39 85 56",
    "sg:postcode":"4690",
    "sg:province":"Danmark",
    "wof:name":"Borg, Ejgil",
    "wof:placetype":"venue"
},
  "geometry": {"coordinates":[11.967805,55.32309],"type":"Point"}
}