{
  "type": "Feature",
  "properties": {
    "addr:full":"Attrupvej 12 Vodskov Danmark 9310",
    "addr:housenumber":"12",
    "addr:postcode":"9310",
    "addr:street":"Attrupvej",
    "iso:country":"DK",
    "sg:address":"Attrupvej 12",
    "sg:city":"Vodskov",
    "sg:orig_category":"Handicapboliger",
    "sg:phone":"+45 98 29 31 44",
    "sg:postcode":"9310",
    "sg:province":"Danmark",
    "wof:name":"Bof\u00e6llesskabet",
    "wof:placetype":"venue"
},
  "geometry": {"coordinates":[10.0536737442,57.1150436401],"type":"Point"}
}