{
  "type": "Feature",
  "properties": {
    "addr:full":"Hovedgaden 18 Tisvildeleje Danmark 3220",
    "addr:housenumber":"18",
    "addr:postcode":"3220",
    "addr:street":"Hovedgaden",
    "iso:country":"DK",
    "sg:address":"Hovedgaden 18",
    "sg:city":"Tisvildeleje",
    "sg:orig_category":"Zoneterapeuter",
    "sg:phone":"+45 48 70 90 92",
    "sg:postcode":"3220",
    "sg:province":"Danmark",
    "wof:name":"Njust, Rikke",
    "wof:placetype":"venue"
},
  "geometry": {"coordinates":[12.0831127167,56.0566215515],"type":"Point"}
}