{
  "type": "Feature",
  "properties": {
    "iso:country":"DK",
    "sg:address":"M\u00f8llevangsvej 2",
    "sg:city":"Liseleje",
    "sg:orig_category":"Cykler",
    "sg:phone":"+45 47 74 74 16",
    "sg:postcode":"3360",
    "sg:province":"Danmark",
    "wof:name":"Levy's Servicehj\u00f8rne",
    "wof:placetype":"venue"
},
  "geometry": {"coordinates":[11.987783432,56.0065879822],"type":"Point"}
}