{
  "type": "Feature",
  "properties": {
    "addr:full":"Hedemarken 11 Grindsted Danmark 7200",
    "addr:housenumber":"11",
    "addr:postcode":"7200",
    "addr:street":"Hedemarken",
    "iso:country":"DK",
    "sg:address":"Hedemarken 11",
    "sg:city":"Grindsted",
    "sg:orig_category":"Revisorer",
    "sg:phone":"+45 75 32 39 44",
    "sg:postcode":"7200",
    "sg:province":"Danmark",
    "wof:name":"Krogh & Thomsen",
    "wof:placetype":"venue"
},
  "geometry": {"coordinates":[8.8333358765,55.6998329163],"type":"Point"}
}