{
  "type": "Feature",
  "properties": {
    "addr:full":"Sognepr\u00e6st: Provst Nils Christensen Roland (KB), Alleen 11, Radsted Saksk\u00f8bing Danmark 4990",
    "addr:housenumber":"11",
    "addr:postcode":"4990",
    "addr:street":"Provst;Kb Alleen",
    "iso:country":"DK",
    "sg:address":"Sognepr\u00e6st: Provst Nils Christensen Roland (KB), Alleen 11, Radsted",
    "sg:city":"Saksk\u00f8bing",
    "sg:orig_category":"Kirkesogne",
    "sg:phone":"+45 54 70 54 08",
    "sg:postcode":"4990",
    "sg:province":"Danmark",
    "wof:name":"Radsted Sogn",
    "wof:placetype":"venue"
},
  "geometry": {"coordinates":[11.6875448227,54.7894821167],"type":"Point"}
}