{
  "type": "Feature",
  "properties": {
    "addr:full":"Egebjergvej 21 Horsens Danmark 8700",
    "addr:housenumber":"21",
    "addr:postcode":"8700",
    "addr:street":"Egebjergvej",
    "iso:country":"DK",
    "sg:address":"Egebjergvej 21",
    "sg:city":"Horsens",
    "sg:orig_category":"Autoreparation og -service",
    "sg:phone":"+45 75 66 56 44",
    "sg:postcode":"8700",
    "sg:province":"Danmark",
    "wof:name":"Texaco Gedvad",
    "wof:placetype":"venue"
},
  "geometry": {"coordinates":[9.84283638,55.8832778931],"type":"Point"}
}