{
  "type": "Feature",
  "properties": {
    "addr:full":"Strandvejen 232, Skotterup Snekkersten Danmark 3070",
    "addr:housenumber":"232",
    "addr:postcode":"3070",
    "addr:street":"Strandvejen;Skotterup",
    "iso:country":"DK",
    "sg:address":"Strandvejen 232, Skotterup",
    "sg:city":"Snekkersten",
    "sg:orig_category":"Diners transportables",
    "sg:phone":"+45 49 22 50 60",
    "sg:postcode":"3070",
    "sg:province":"Danmark",
    "sg:website":"www.skotterupkro.dk",
    "wof:name":"Skotterup Kro",
    "wof:placetype":"venue"
},
  "geometry": {"coordinates":[12.5851154327,56.0076637268],"type":"Point"}
}