{
  "type": "Feature",
  "properties": {
    "addr:full":"\u00d8stermarken 12 Storvorde Danmark 9280",
    "addr:housenumber":"12",
    "addr:postcode":"9280",
    "addr:street":"Ostermarken",
    "iso:country":"DK",
    "sg:address":"\u00d8stermarken 12",
    "sg:city":"Storvorde",
    "sg:orig_category":"Antenneforeninger",
    "sg:phone":"+45 98 31 86 53",
    "sg:postcode":"9280",
    "sg:province":"Danmark",
    "sg:website":"www.baandbyernes-antenneforening.dk",
    "wof:name":"B\u00e5ndbyernes Antenneforening",
    "wof:placetype":"venue"
},
  "geometry": {"coordinates":[10.104970932,57.0045509338],"type":"Point"}
}