{
  "type": "Feature",
  "properties": {
    "addr:full":"Fmd.: Andreas Reinholtz, Muskatv\u00e6nget 23 Tinglev Danmark 6360",
    "addr:housenumber":"23",
    "addr:postcode":"6360",
    "addr:street":"Muskatvaenget",
    "iso:country":"DK",
    "sg:address":"Fmd.: Andreas Reinholtz, Muskatv\u00e6nget 23",
    "sg:city":"Tinglev",
    "sg:orig_category":"Erhvervs- og brancheforeninger",
    "sg:phone":"+45 74 64 26 73",
    "sg:postcode":"6360",
    "sg:province":"Danmark",
    "wof:name":"Deutscher Lehrerverein",
    "wof:placetype":"venue"
},
  "geometry": {"coordinates":[9.2476491928,54.9349365234],"type":"Point"}
}