{
  "type": "Feature",
  "properties": {
    "addr:full":"Herredsvej 118 Fej\u00f8 Danmark 4944",
    "addr:housenumber":"118",
    "addr:postcode":"4944",
    "addr:street":"Herredsvej",
    "iso:country":"DK",
    "sg:address":"Herredsvej 118",
    "sg:city":"Fej\u00f8",
    "sg:orig_category":"Gallerier",
    "sg:phone":"+45 54 71 30 53",
    "sg:postcode":"4944",
    "sg:province":"Danmark",
    "wof:name":"Blommegalleriet",
    "wof:placetype":"venue"
},
  "geometry": {"coordinates":[11.3942956924,54.9442596436],"type":"Point"}
}