{
  "type": "Feature",
  "properties": {
    "iso:country":"DK",
    "sg:address":"N\u00f8rholmsvej 171",
    "sg:city":"Aalborg",
    "sg:orig_category":"Revisorer",
    "sg:phone":"+45 98 34 18 70",
    "sg:postcode":"9000",
    "sg:province":"Danmark",
    "wof:name":"Broekhoff Raaby",
    "wof:placetype":"venue"
},
  "geometry": {"coordinates":[9.8134031296,57.0336494446],"type":"Point"}
}