{
  "type": "Feature",
  "properties": {
    "addr:full":"S\u00f8ndervangen 29 Viby Danmark 8260",
    "addr:housenumber":"29",
    "addr:postcode":"8260",
    "addr:street":"Sondervangen",
    "iso:country":"DK",
    "sg:address":"S\u00f8ndervangen 29",
    "sg:city":"Viby",
    "sg:orig_category":"Malermestre",
    "sg:phone":"+45 86 14 28 49",
    "sg:postcode":"8260",
    "sg:province":"Danmark",
    "wof:name":"Olesen, Malerfirma Fl.",
    "wof:placetype":"venue"
},
  "geometry": {"coordinates":[10.1563777924,56.1140708923],"type":"Point"}
}