{
  "type": "Feature",
  "properties": {
    "iso:country":"DK",
    "sg:address":"Kokkedal Industripark 11",
    "sg:city":"Kokkedal",
    "sg:orig_category":"Serigrafi",
    "sg:phone":"+45 45 86 76 81",
    "sg:postcode":"2980",
    "sg:province":"Danmark",
    "wof:name":"Spellerberg Serigrafi ApS",
    "wof:placetype":"venue"
},
  "geometry": {"coordinates":[12.47691,55.909134],"type":"Point"}
}