{
  "type": "Feature",
  "properties": {
    "addr:full":"Vestergade 5 Stubbek\u00f8bing Danmark 4850",
    "addr:housenumber":"5",
    "addr:postcode":"4850",
    "addr:street":"Vestergade",
    "iso:country":"DK",
    "sg:address":"Vestergade 5",
    "sg:city":"Stubbek\u00f8bing",
    "sg:orig_category":"Vaskerier",
    "sg:phone":"+45 54 44 15 30",
    "sg:postcode":"4850",
    "sg:province":"Danmark",
    "wof:name":"Den Varme Stue",
    "wof:placetype":"venue"
},
  "geometry": {"coordinates":[-114.0767440796,46.4432487488],"type":"Point"}
}