{
  "type": "Feature",
  "properties": {
    "addr:full":"S\u00f8nderbrogade 76 Horsens Danmark 8700",
    "addr:housenumber":"76",
    "addr:postcode":"8700",
    "addr:street":"Sonderbrogade",
    "iso:country":"DK",
    "sg:address":"S\u00f8nderbrogade 76",
    "sg:city":"Horsens",
    "sg:orig_category":"Tobak",
    "sg:phone":"+45 75 62 42 88",
    "sg:postcode":"8700",
    "sg:province":"Danmark",
    "wof:name":"S\u00f8rensen, Thomas",
    "wof:placetype":"venue"
},
  "geometry": {"coordinates":[9.8289680481,55.8539619446],"type":"Point"}
}