{
  "type": "Feature",
  "properties": {
    "iso:country":"DK",
    "sg:address":"Bispegade 18",
    "sg:city":"Haderslev",
    "sg:orig_category":"Konfekture",
    "sg:phone":"+45 74 52 29 43",
    "sg:postcode":"6100",
    "sg:province":"Danmark",
    "wof:name":"Frellsen Konfekture, I. M.",
    "wof:placetype":"venue"
},
  "geometry": {"coordinates":[9.4858026505,55.250831604],"type":"Point"}
}