{
  "type": "Feature",
  "properties": {
    "iso:country":"DK",
    "sg:address":"Lundvej 26",
    "sg:city":"Varde",
    "sg:orig_category":"Sommerhusudlejning",
    "sg:phone":"+45 75 22 41 64",
    "sg:postcode":"6800",
    "sg:province":"Danmark",
    "wof:name":"DanCenter",
    "wof:placetype":"venue"
},
  "geometry": {"coordinates":[8.4906311035,55.6255111694],"type":"Point"}
}