{
  "type": "Feature",
  "properties": {
    "addr:full":"Storegade 32 Brande Danmark 7330",
    "addr:housenumber":"32",
    "addr:postcode":"7330",
    "addr:street":"Storegade",
    "iso:country":"DK",
    "sg:address":"Storegade 32",
    "sg:city":"Brande",
    "sg:orig_category":"Bagere",
    "sg:phone":"+45 97 18 00 38",
    "sg:postcode":"7330",
    "sg:province":"Danmark",
    "wof:name":"Torvet's Bageri",
    "wof:placetype":"venue"
},
  "geometry": {"coordinates":[9.1270027161,55.9432907104],"type":"Point"}
}