{
  "type": "Feature",
  "properties": {
    "iso:country":"DK",
    "sg:address":"Gl. Havdrupvej 5",
    "sg:city":"Gadstrup",
    "sg:orig_category":"Kursussteder",
    "sg:phone":"+45 46 16 10 04",
    "sg:postcode":"4621",
    "sg:province":"Danmark",
    "sg:website":"www.hastrup-centret.dk",
    "wof:name":"Kofod-Jensen, Jan Helge",
    "wof:placetype":"venue"
},
  "geometry": {"coordinates":[12.1664867401,55.5597114563],"type":"Point"}
}