{
  "type": "Feature",
  "properties": {
    "iso:country":"DK",
    "sg:address":"Fmd.: Hanne Fedders, Tved 173",
    "sg:city":"T\u00f8nder",
    "sg:orig_category":"Spejderkorps",
    "sg:phone":"+45 74 72 00 88",
    "sg:postcode":"6270",
    "sg:province":"Danmark",
    "wof:name":"Det Danske Spejderkorps, T\u00f8nder Pigegruppe",
    "wof:placetype":"venue"
},
  "geometry": {"coordinates":[8.6816797256,57.055480957],"type":"Point"}
}