{
  "type": "Feature",
  "properties": {
    "iso:country":"DK",
    "sg:address":"Skolevej 7",
    "sg:city":"Thybor\u00f8n",
    "sg:orig_category":"Tandklinikker, Kommunale",
    "sg:phone":"+45 97 83 16 82",
    "sg:postcode":"7680",
    "sg:province":"Danmark",
    "wof:name":"Thybor\u00f8n b\u00f8rnetandklinik",
    "wof:placetype":"venue"
},
  "geometry": {"coordinates":[-76.5318984985,38.7085647583],"type":"Point"}
}