{
  "type": "Feature",
  "properties": {
    "addr:full":"J. Chr. Juliussens Vej 7 Horsens Danmark 8700",
    "addr:housenumber":"7",
    "addr:postcode":"8700",
    "addr:street":"J. Chr. Juliussens Vej",
    "iso:country":"DK",
    "sg:address":"J. Chr. Juliussens Vej 7",
    "sg:city":"Horsens",
    "sg:orig_category":"Supermarkeder",
    "sg:phone":"+45 75 62 39 66",
    "sg:postcode":"8700",
    "sg:province":"Danmark",
    "wof:name":"K\u00f8bmandsgaarden",
    "wof:placetype":"venue"
},
  "geometry": {"coordinates":[9.8502397537,55.860244751],"type":"Point"}
}