{
  "type": "Feature",
  "properties": {
    "iso:country":"DK",
    "sg:address":"Elleg\u00e5rdspark 19",
    "sg:city":"Farum",
    "sg:orig_category":"INGENI\u00c3\u02dcRER",
    "sg:phone":"+45 44 95 22 67",
    "sg:postcode":"3520",
    "sg:province":"Danmark",
    "wof:name":"Haraldsted Ingeni\u00f8r- & Handelsfirma, Hans H.",
    "wof:placetype":"venue"
},
  "geometry": {"coordinates":[12.3969097137,55.8177032471],"type":"Point"}
}