{
  "type": "Feature",
  "properties": {
    "addr:full":"Traneg\u00e5rdsvej 68 Hellerup Danmark 2900",
    "addr:housenumber":"68",
    "addr:postcode":"2900",
    "addr:street":"Tranegaardsvej",
    "iso:country":"DK",
    "sg:address":"Traneg\u00e5rdsvej 68",
    "sg:city":"Hellerup",
    "sg:orig_category":"Pizzeriaer",
    "sg:phone":"+45 39 61 26 36",
    "sg:postcode":"2900",
    "sg:province":"Danmark",
    "wof:name":"Con Amore",
    "wof:placetype":"venue"
},
  "geometry": {"coordinates":[12.5626907349,55.7413673401],"type":"Point"}
}