{
  "type": "Feature",
  "properties": {
    "addr:full":"N\u00f8rrek\u00e6r 27 Vejle Danmark 7100",
    "addr:housenumber":"27",
    "addr:postcode":"7100",
    "addr:street":"Norrekaer",
    "iso:country":"DK",
    "sg:address":"N\u00f8rrek\u00e6r 27",
    "sg:city":"Vejle",
    "sg:orig_category":"INGENI\u00c3\u02dcRER",
    "sg:phone":"+45 75 82 05 51",
    "sg:postcode":"7100",
    "sg:province":"Danmark",
    "wof:name":"Hein, Hans Kurt",
    "wof:placetype":"venue"
},
  "geometry": {"coordinates":[9.5368051529,55.7113952637],"type":"Point"}
}