{
  "type": "Feature",
  "properties": {
    "addr:full":"v/H. R. Andersen, Dronning Margrethes Vej 64 \u00d8lstykke Danmark 3650",
    "addr:housenumber":"64",
    "addr:postcode":"3650",
    "addr:street":"Dronning Margrethes Vej",
    "iso:country":"DK",
    "sg:address":"v/H. R. Andersen, Dronning Margrethes Vej 64",
    "sg:city":"\u00d8lstykke",
    "sg:orig_category":"Grundejerforeninger",
    "sg:phone":"+45 47 17 66 40",
    "sg:postcode":"3650",
    "sg:province":"Danmark",
    "wof:name":"Gl. Toftg\u00e5rd",
    "wof:placetype":"venue"
},
  "geometry": {"coordinates":[-122.61585998539999,45.6801795959],"type":"Point"}
}