{
  "type": "Feature",
  "properties": {
    "iso:country":"DK",
    "sg:address":"Siriusvej 17",
    "sg:city":"Ikast",
    "sg:orig_category":"Belysning",
    "sg:phone":"+45 70 22 29 00",
    "sg:postcode":"7430",
    "sg:province":"Danmark",
    "sg:website":"www.halodan.dk",
    "wof:name":"Halodan A/S",
    "wof:placetype":"venue"
},
  "geometry": {"coordinates":[9.129924,56.137123],"type":"Point"}
}