{
  "type": "Feature",
  "properties": {
    "addr:full":"Albuen 23 Kolding Danmark 6000",
    "addr:housenumber":"23",
    "addr:postcode":"6000",
    "addr:street":"Albuen",
    "iso:country":"DK",
    "sg:address":"Albuen 23",
    "sg:city":"Kolding",
    "sg:orig_category":"Forsikringer",
    "sg:phone":"+45 70 12 14 16",
    "sg:postcode":"6000",
    "sg:province":"Danmark",
    "sg:website":"www.alka.dk",
    "wof:name":"ALKA forsikring",
    "wof:placetype":"venue"
},
  "geometry": {"coordinates":[9.4551820755,55.5153884888],"type":"Point"}
}