{
  "type": "Feature",
  "properties": {
    "iso:country":"DK",
    "sg:address":"Klostervej 87, Kloster",
    "sg:city":"Ringk\u00f8bing",
    "sg:orig_category":"Skolefritidsordninger",
    "sg:phone":"+45 97 33 72 10",
    "sg:postcode":"6950",
    "sg:province":"Danmark",
    "wof:name":"Regnbuen Skolefritidsordning v. Holmsland Skole",
    "wof:placetype":"venue"
},
  "geometry": {"coordinates":[8.2507953644,56.0878334045],"type":"Point"}
}