{
  "type": "Feature",
  "properties": {
    "addr:full":"K\u00f8bmagergade 65  Fredericia Danmark 7000",
    "addr:housenumber":"65",
    "addr:postcode":"7000",
    "addr:street":"Kobmagergade",
    "iso:country":"DK",
    "sg:address":"K\u00f8bmagergade 65 ",
    "sg:city":"Fredericia",
    "sg:classifiers":[
        {
            "category":"Professional",
            "subcategory":"Business Services",
            "type":"Services"
        }
    ],
    "sg:phone":"+45 72 10 65 46",
    "sg:postcode":"7000",
    "sg:province":"Danmark",
    "sg:tags":[
        "advice"
    ],
    "wof:name":"K\u00d8BMAGERGADES SKOLE",
    "wof:placetype":"venue"
},
  "geometry": {"coordinates":[9.7593421936,55.5644226074],"type":"Point"}
}