{
  "type": "Feature",
  "properties": {
    "iso:country":"DK",
    "sg:address":"Strandvejen 152",
    "sg:city":"Charlottenlund",
    "sg:classifiers":[
        {
            "category":"Restaurant",
            "type":"Food & Drink"
        }
    ],
    "sg:phone":"+45 39 63 73 81",
    "sg:postcode":"2920",
    "sg:province":"Danmark",
    "wof:name":"Jorden, Caf\u00e9 Rundt",
    "wof:placetype":"venue"
},
  "geometry": {"coordinates":[12.5890483856,55.7498092651],"type":"Point"}
}