{
  "type": "Feature",
  "properties": {
    "addr:full":"Vigerslev Alle 214 Valby Danmark 2500",
    "addr:housenumber":"214",
    "addr:postcode":"2500",
    "addr:street":"Vigerslev Alle",
    "iso:country":"DK",
    "sg:address":"Vigerslev Alle 214",
    "sg:city":"Valby",
    "sg:orig_category":"Flytteforretninger",
    "sg:phone":"+45 70 20 00 50",
    "sg:postcode":"2500",
    "sg:province":"Danmark",
    "sg:website":"www.kft-transport.dk",
    "wof:name":"KFT",
    "wof:placetype":"venue"
},
  "geometry": {"coordinates":[12.4889860153,55.6580734253],"type":"Point"}
}