{
  "type": "Feature",
  "properties": {
    "addr:full":"Gl. Landevej 34, Birkelse Aabybro Danmark 9440",
    "addr:housenumber":"34",
    "addr:postcode":"9440",
    "addr:street":"Gl. Landevej",
    "iso:country":"DK",
    "sg:address":"Gl. Landevej 34, Birkelse",
    "sg:city":"Aabybro",
    "sg:orig_category":"Antikviteter",
    "sg:phone":"+45 98 24 33 32",
    "sg:postcode":"9440",
    "sg:province":"Danmark",
    "wof:name":"Diges Antik & Genbrug",
    "wof:placetype":"venue"
},
  "geometry": {"coordinates":[9.7341356277,57.1588287354],"type":"Point"}
}