{
  "type": "Feature",
  "properties": {
    "addr:full":"Sintrupvej 21 A  Brabrand Danmark 8220",
    "addr:housenumber":"21 a",
    "addr:postcode":"8220",
    "addr:street":"Sintrupvej",
    "iso:country":"DK",
    "sg:address":"Sintrupvej 21 A ",
    "sg:city":"Brabrand",
    "sg:classifiers":[
        {
            "category":"Wholesale",
            "subcategory":"Medical Equipment & Supplies",
            "type":"Manufacturing & Wholesale Goods"
        }
    ],
    "sg:phone":"+45 86 24 21 00",
    "sg:postcode":"8220",
    "sg:province":"Danmark",
    "sg:tags":[
        "-",
        "health",
        "instrument"
    ],
    "wof:name":"CARFIX BRABRAND FREDY LAUSTSEN APS",
    "wof:placetype":"venue"
},
  "geometry": {"coordinates":[10.1109018326,56.1671524048],"type":"Point"}
}