{
  "type": "Feature",
  "properties": {
    "addr:full":"Kontaktpers.: Peer Mikkelsen, Dagmarsgade 24 Ringsted Danmark 4100",
    "addr:housenumber":"24",
    "addr:postcode":"4100",
    "addr:street":"Dagmarsgade",
    "iso:country":"DK",
    "sg:address":"Kontaktpers.: Peer Mikkelsen, Dagmarsgade 24",
    "sg:city":"Ringsted",
    "sg:orig_category":"Kirkelige foreninger",
    "sg:phone":"+45 57 67 68 75",
    "sg:postcode":"4100",
    "sg:province":"Danmark",
    "wof:name":"Ringsted Indre Mission",
    "wof:placetype":"venue"
},
  "geometry": {"coordinates":[11.7875862122,55.4458961487],"type":"Point"}
}