{
  "type": "Feature",
  "properties": {
    "iso:country":"DK",
    "sg:address":"\u00d8rstedsvej 43",
    "sg:city":"Ribe",
    "sg:orig_category":"Maskinfabrikker",
    "sg:phone":"+45 75 41 09 81",
    "sg:postcode":"6760",
    "sg:province":"Danmark",
    "wof:name":"Miltek A/S",
    "wof:placetype":"venue"
},
  "geometry": {"coordinates":[8.7709960938,55.352558136],"type":"Point"}
}