{
  "type": "Feature",
  "properties": {
    "addr:full":"Gammel Landevej 1  Lemvig Danmark 7620",
    "addr:housenumber":"1",
    "addr:postcode":"7620",
    "addr:street":"Gammel Landevej",
    "iso:country":"DK",
    "sg:address":"Gammel Landevej 1 ",
    "sg:city":"Lemvig",
    "sg:classifiers":[
        {
            "category":"Real Estate",
            "subcategory":"Surveying",
            "type":"Services"
        }
    ],
    "sg:phone":"+45 76 90 09 00",
    "sg:postcode":"7620",
    "sg:province":"Danmark",
    "sg:tags":[
        "equipment",
        "material",
        "good",
        "-",
        "handling"
    ],
    "wof:name":"DANTRUCK HEDEN A/S",
    "wof:placetype":"venue"
},
  "geometry": {"coordinates":[8.3074064255,56.5139427185],"type":"Point"}
}