{
  "type": "Feature",
  "properties": {
    "addr:full":"Sankt Clara Vej 1 Roskilde Danmark 4000",
    "addr:housenumber":"1",
    "addr:postcode":"4000",
    "addr:street":"Sankt Clara Vej",
    "iso:country":"DK",
    "sg:address":"Sankt Clara Vej 1",
    "sg:city":"Roskilde",
    "sg:orig_category":"Trossamfund uden for folkekirken",
    "sg:postcode":"4000",
    "sg:province":"Danmark",
    "wof:name":"Adventkirken",
    "wof:placetype":"venue"
},
  "geometry": {"coordinates":[12.0810136795,55.649936676],"type":"Point"}
}