{
  "type": "Feature",
  "properties": {
    "addr:full":"Skjoldborgsvej 25 Fredericia Danmark 7000",
    "addr:housenumber":"25",
    "addr:postcode":"7000",
    "addr:street":"Skjoldborgsvej",
    "iso:country":"DK",
    "sg:address":"Skjoldborgsvej 25",
    "sg:city":"Fredericia",
    "sg:orig_category":"Skolefritidsordninger",
    "sg:postcode":"7000",
    "sg:province":"Danmark",
    "wof:name":"Skjoldborgvejens skoles skolefritidsordning",
    "wof:placetype":"venue"
},
  "geometry": {"coordinates":[9.7310523987,55.5658454895],"type":"Point"}
}