{
  "type": "Feature",
  "properties": {
    "addr:full":"v/ Bj\u00f8rn Jakobsen, Gl. Slimmingevej 4, Slimminge Ringsted Danmark 4100",
    "addr:housenumber":"4",
    "addr:postcode":"4100",
    "addr:street":"Gl. Slimmingevej;Slimminge",
    "iso:country":"DK",
    "sg:address":"v/ Bj\u00f8rn Jakobsen, Gl. Slimmingevej 4, Slimminge",
    "sg:city":"Ringsted",
    "sg:orig_category":"Musik og sang",
    "sg:phone":"+45 56 87 91 15",
    "sg:postcode":"4100",
    "sg:province":"Danmark",
    "wof:name":"DSB Musik - Kors\u00f8r Jernbaneorkester",
    "wof:placetype":"venue"
},
  "geometry": {"coordinates":[11.7875862122,55.4458961487],"type":"Point"}
}