{
  "type": "Feature",
  "properties": {
    "iso:country":"DK",
    "sg:address":"Glentevej 10",
    "sg:city":"Greve",
    "sg:orig_category":"Ejendomshandel",
    "sg:phone":"+45 21 43 10 80",
    "sg:postcode":"2670",
    "sg:province":"Danmark",
    "wof:name":"Semelin EjendomsCenter",
    "wof:placetype":"venue"
},
  "geometry": {"coordinates":[12.3272619247,55.5861701965],"type":"Point"}
}