{
  "type": "Feature",
  "properties": {
    "addr:full":"Nordre Ringvej 58 - 60 Kerteminde Danmark 5300",
    "addr:housenumber":"58 60",
    "addr:postcode":"5300",
    "addr:street":"Nordre Ringvej",
    "iso:country":"DK",
    "sg:address":"Nordre Ringvej 58 - 60",
    "sg:city":"Kerteminde",
    "sg:orig_category":"Autoforhandlere",
    "sg:phone":"+45 65 32 22 44",
    "sg:postcode":"5300",
    "sg:province":"Danmark",
    "wof:name":"Petersen, Jens",
    "wof:placetype":"venue"
},
  "geometry": {"coordinates":[10.6524848938,55.4562797546],"type":"Point"}
}