{
  "type": "Feature",
  "properties": {
    "addr:full":"Fmd.: Verner Nielsen, N\u00f8rregade 20, B 1 Haderslev Danmark 6100",
    "addr:housenumber":"20 b 1",
    "addr:postcode":"6100",
    "addr:street":"Fmd. Verner Nielsen Norregade",
    "iso:country":"DK",
    "sg:address":"Fmd.: Verner Nielsen, N\u00f8rregade 20, B 1",
    "sg:city":"Haderslev",
    "sg:orig_category":"\u00c3\u2020ldreorganisationer og klubber",
    "sg:phone":"+45 74 53 02 47",
    "sg:postcode":"6100",
    "sg:province":"Danmark",
    "wof:name":"NNF Pensionist og Efterl\u00f8nsklub",
    "wof:placetype":"venue"
},
  "geometry": {"coordinates":[9.4879703522,55.2505493164],"type":"Point"}
}