{
  "type": "Feature",
  "properties": {
    "addr:full":"Asylgade 16 Odense C Danmark 5000",
    "addr:housenumber":"16",
    "addr:postcode":"5000",
    "addr:street":"Asylgade",
    "iso:country":"DK",
    "sg:address":"Asylgade 16",
    "sg:city":"Odense C",
    "sg:orig_category":"Sportsartikler",
    "sg:phone":"+45 66 13 00 48",
    "sg:postcode":"5000",
    "sg:province":"Danmark",
    "wof:name":"Diving 2000 A/S",
    "wof:placetype":"venue"
},
  "geometry": {"coordinates":[10.3874635696,55.3979873657],"type":"Point"}
}