{
  "type": "Feature",
  "properties": {
    "addr:full":"v/ Heidi Corinth, Birkebakken 2 Ballerup Danmark 2750",
    "addr:housenumber":"2",
    "addr:postcode":"2750",
    "addr:street":"Birkebakken",
    "iso:country":"DK",
    "sg:address":"v/ Heidi Corinth, Birkebakken 2",
    "sg:city":"Ballerup",
    "sg:orig_category":"Fredsgrupper",
    "sg:phone":"+45 44 65 29 88",
    "sg:postcode":"2750",
    "sg:province":"Danmark",
    "wof:name":"Ballerup Fredsgruppe",
    "wof:placetype":"venue"
},
  "geometry": {"coordinates":[12.361000061,55.7301216125],"type":"Point"}
}