{
  "type": "Feature",
  "properties": {
    "addr:full":"Storegade 1 Aabenraa Danmark 6200",
    "addr:housenumber":"1",
    "addr:postcode":"6200",
    "addr:street":"Storegade",
    "iso:country":"DK",
    "sg:address":"Storegade 1",
    "sg:city":"Aabenraa",
    "sg:orig_category":"Parfumerier",
    "sg:phone":"+45 74 62 23 73",
    "sg:postcode":"6200",
    "sg:province":"Danmark",
    "wof:name":"Matas Materialisten",
    "wof:placetype":"venue"
},
  "geometry": {"coordinates":[9.4188261032,55.0447006226],"type":"Point"}
}