{
  "type": "Feature",
  "properties": {
    "addr:full":"Jernbanegade 18 S\u00f8llested Danmark 4920",
    "addr:housenumber":"18",
    "addr:postcode":"4920",
    "addr:street":"Jernbanegade",
    "iso:country":"DK",
    "sg:address":"Jernbanegade 18",
    "sg:city":"S\u00f8llested",
    "sg:orig_category":"Supermarkeder",
    "sg:phone":"+45 54 94 13 16",
    "sg:postcode":"4920",
    "sg:province":"Danmark",
    "wof:name":"Super Best",
    "wof:placetype":"venue"
},
  "geometry": {"coordinates":[11.267706871,54.8111228943],"type":"Point"}
}