{
  "type": "Feature",
  "properties": {
    "addr:full":"Danmarksgade 63 Fredericia Danmark 7000",
    "addr:housenumber":"63",
    "addr:postcode":"7000",
    "addr:street":"Danmarksgade",
    "iso:country":"DK",
    "sg:address":"Danmarksgade 63",
    "sg:city":"Fredericia",
    "sg:classifiers":[
        {
            "category":"Food & Beverages",
            "subcategory":"Liquor & Beverages",
            "type":"Retail Goods"
        }
    ],
    "sg:phone":"+45 75 92 06 44",
    "sg:postcode":"7000",
    "sg:province":"Danmark",
    "sg:tags":[
        "vin"
    ],
    "wof:name":"Cort Trap Vin-Import ApS",
    "wof:placetype":"venue"
},
  "geometry": {"coordinates":[9.7634162903,55.567199707],"type":"Point"}
}