{
  "type": "Feature",
  "properties": {
    "iso:country":"DK",
    "sg:address":"Gammel Jernbanevej 11",
    "sg:city":"Valby",
    "sg:orig_category":"Bagere",
    "sg:phone":"+45 36 46 11 02",
    "sg:postcode":"2500",
    "sg:province":"Danmark",
    "wof:name":"Petit Four",
    "wof:placetype":"venue"
},
  "geometry": {"coordinates":[12.520356,55.665672],"type":"Point"}
}