{
  "type": "Feature",
  "properties": {
    "iso:country":"DK",
    "sg:address":"Fmd.: Karen Christensen, J\u00f8rslevvej 1",
    "sg:city":"Karise",
    "sg:orig_category":"Husflidsforeninger",
    "sg:phone":"+45 56 78 81 09",
    "sg:postcode":"4653",
    "sg:province":"Danmark",
    "wof:name":"Familie og Samfund, Karise",
    "wof:placetype":"venue"
},
  "geometry": {"coordinates":[12.1990203857,55.3030395508],"type":"Point"}
}