{
  "type": "Feature",
  "properties": {
    "iso:country":"DK",
    "sg:address":"v/Jens Harald Jensen, Gr\u00f8nlandsgade 36",
    "sg:city":"Ringk\u00f8bing",
    "sg:orig_category":"Grundejerforeninger",
    "sg:phone":"+45 97 32 31 86",
    "sg:postcode":"6950",
    "sg:province":"Danmark",
    "wof:name":"Grundejerforeningen Danmarksgade",
    "wof:placetype":"venue"
},
  "geometry": {"coordinates":[-114.0767440796,46.4432487488],"type":"Point"}
}