{
  "type": "Feature",
  "properties": {
    "addr:full":"\u00d8stervej 24 Ballerup Danmark 2750",
    "addr:housenumber":"24",
    "addr:postcode":"2750",
    "addr:street":"Ostervej",
    "iso:country":"DK",
    "sg:address":"\u00d8stervej 24",
    "sg:city":"Ballerup",
    "sg:orig_category":"Malermestre",
    "sg:phone":"+45 21 44 47 79",
    "sg:postcode":"2750",
    "sg:province":"Danmark",
    "wof:name":"Robertsen A/S, Malerfirmaet Brandt",
    "wof:placetype":"venue"
},
  "geometry": {"coordinates":[12.366558075,55.7285079956],"type":"Point"}
}