{
  "type": "Feature",
  "properties": {
    "iso:country":"DK",
    "sg:address":"Fruerlund 11",
    "sg:city":"N\u00e6rum",
    "sg:orig_category":"Revisorer",
    "sg:phone":"+45 45 80 15 18",
    "sg:postcode":"2850",
    "sg:province":"Danmark",
    "wof:name":"Haid, Hans",
    "wof:placetype":"venue"
},
  "geometry": {"coordinates":[12.53931427,55.8140335083],"type":"Point"}
}