{
  "type": "Feature",
  "properties": {
    "addr:full":"Valby Langgade 136 Valby Danmark 2500",
    "addr:housenumber":"136",
    "addr:postcode":"2500",
    "addr:street":"Valby Langgade",
    "iso:country":"DK",
    "sg:address":"Valby Langgade 136",
    "sg:city":"Valby",
    "sg:orig_category":"Pengeinstitutter",
    "sg:phone":"+45 36 16 88 77",
    "sg:postcode":"2500",
    "sg:province":"Danmark",
    "wof:name":"Arbejdernes Landsbank",
    "wof:placetype":"venue"
},
  "geometry": {"coordinates":[12.5023393631,55.6673164368],"type":"Point"}
}