{
  "type": "Feature",
  "properties": {
    "addr:full":"Jernbanevej 42 1, Tarup Odense NV Danmark 5210",
    "addr:housenumber":"42 1",
    "addr:postcode":"5210",
    "addr:street":"Jernbanevej",
    "iso:country":"DK",
    "sg:address":"Jernbanevej 42 1, Tarup",
    "sg:city":"Odense NV",
    "sg:classifiers":[
        {
            "category":"Professional",
            "subcategory":"Computer Services",
            "type":"Services"
        }
    ],
    "sg:phone":"+45 66 19 33 45",
    "sg:postcode":"5210",
    "sg:province":"Danmark",
    "sg:tags":[
        "edb",
        "-",
        "software"
    ],
    "wof:name":"Tekno I/S",
    "wof:placetype":"venue"
},
  "geometry": {"coordinates":[10.274764061,55.4303321838],"type":"Point"}
}