{
  "type": "Feature",
  "properties": {
    "addr:full":"Kredsleder: Dora Bjerrum, Egemosevej 9 Grevinge Danmark 4571",
    "addr:housenumber":"9",
    "addr:postcode":"4571",
    "addr:street":"Egemosevej",
    "iso:country":"DK",
    "sg:address":"Kredsleder: Dora Bjerrum, Egemosevej 9",
    "sg:city":"Grevinge",
    "sg:orig_category":"Beredskabsforbund",
    "sg:phone":"+45 59 65 92 16",
    "sg:postcode":"4571",
    "sg:province":"Danmark",
    "wof:name":"Beredskabsforbundet",
    "wof:placetype":"venue"
},
  "geometry": {"coordinates":[11.559365,55.787315],"type":"Point"}
}