{
  "type": "Feature",
  "properties": {
    "iso:country":"DK",
    "sg:address":"Hvedemarken 12 ",
    "sg:city":"Farum",
    "sg:classifiers":[
        {
            "category":"Wholesale",
            "subcategory":"Drugs",
            "type":"Manufacturing & Wholesale Goods"
        }
    ],
    "sg:phone":"+45 44 39 50 00",
    "sg:postcode":"3520",
    "sg:province":"Danmark",
    "sg:tags":[
        "chemical",
        "pharmaceutical"
    ],
    "wof:name":"SCHERING-PLOUGH A/S",
    "wof:placetype":"venue"
},
  "geometry": {"coordinates":[12.3751192093,55.8182830811],"type":"Point"}
}