{
  "type": "Feature",
  "properties": {
    "addr:full":"Gl. Odensevej 3, Gelsted Gelsted Danmark 5591",
    "addr:housenumber":"3",
    "addr:postcode":"5591",
    "addr:street":"Gl. Odensevej",
    "iso:country":"DK",
    "sg:address":"Gl. Odensevej 3, Gelsted",
    "sg:city":"Gelsted",
    "sg:orig_category":"Jernbaner",
    "sg:phone":"+45 64 49 26 20",
    "sg:postcode":"5591",
    "sg:province":"Danmark",
    "wof:name":"Gelsted Postbutik (DSB)",
    "wof:placetype":"venue"
},
  "geometry": {"coordinates":[9.9734048843,55.3995094299],"type":"Point"}
}