{
  "type": "Feature",
  "properties": {
    "addr:full":"N\u00f8rrebrogade 46 Esbjerg Danmark 6700",
    "addr:housenumber":"46",
    "addr:postcode":"6700",
    "addr:street":"Norrebrogade",
    "iso:country":"DK",
    "sg:address":"N\u00f8rrebrogade 46",
    "sg:city":"Esbjerg",
    "sg:orig_category":"Grillbarer",
    "sg:phone":"+45 75 45 26 08",
    "sg:postcode":"6700",
    "sg:province":"Danmark",
    "wof:name":"Brogrillen",
    "wof:placetype":"venue"
},
  "geometry": {"coordinates":[8.4609203339,55.4748458862],"type":"Point"}
}