{
  "type": "Feature",
  "properties": {
    "addr:full":"Trekronervej 10 Viborg Danmark 8800",
    "addr:housenumber":"10",
    "addr:postcode":"8800",
    "addr:street":"Trekronervej",
    "iso:country":"DK",
    "sg:address":"Trekronervej 10",
    "sg:city":"Viborg",
    "sg:orig_category":"Dagcentre",
    "sg:phone":"+45 86 61 15 96",
    "sg:postcode":"8800",
    "sg:province":"Danmark",
    "wof:name":"Pensionistg\u00e5rden - K.F.U.M.'s anneks",
    "wof:placetype":"venue"
},
  "geometry": {"coordinates":[9.4018573761,56.4486999512],"type":"Point"}
}