{
  "type": "Feature",
  "properties": {
    "addr:full":"Funder Skolevej 3 Silkeborg Danmark 8600",
    "addr:housenumber":"3",
    "addr:postcode":"8600",
    "addr:street":"Funder Skolevej",
    "iso:country":"DK",
    "sg:address":"Funder Skolevej 3",
    "sg:city":"Silkeborg",
    "sg:orig_category":"Skolefritidsordninger",
    "sg:phone":"+45 86 85 13 69",
    "sg:postcode":"8600",
    "sg:province":"Danmark",
    "wof:name":"Funder Skoles SFO",
    "wof:placetype":"venue"
},
  "geometry": {"coordinates":[9.4776058197,56.1468658447],"type":"Point"}
}