{
  "type": "Feature",
  "properties": {
    "addr:full":"Socialforvaltningen, \u00d8stergade 18, 1. Assens Danmark 5610",
    "addr:housenumber":"18 1",
    "addr:postcode":"5610",
    "addr:street":"Ostergade",
    "iso:country":"DK",
    "sg:address":"Socialforvaltningen, \u00d8stergade 18, 1.",
    "sg:city":"Assens",
    "sg:orig_category":"Dagplejeformidling",
    "sg:phone":"+45 63 71 71 71",
    "sg:postcode":"5610",
    "sg:province":"Danmark",
    "wof:name":"Dagplejeformidlingen",
    "wof:placetype":"venue"
},
  "geometry": {"coordinates":[9.8998937607,55.2702522278],"type":"Point"}
}