{
  "type": "Feature",
  "properties": {
    "addr:full":"L\u00e5sbygade 61 Kolding Danmark 6000",
    "addr:housenumber":"61",
    "addr:postcode":"6000",
    "addr:street":"Laasbygade",
    "iso:country":"DK",
    "sg:address":"L\u00e5sbygade 61",
    "sg:city":"Kolding",
    "sg:orig_category":"Fotokopiering",
    "sg:phone":"+45 75 54 32 30",
    "sg:postcode":"6000",
    "sg:province":"Danmark",
    "wof:name":"Kopien",
    "wof:placetype":"venue"
},
  "geometry": {"coordinates":[9.4683408737,55.4929351807],"type":"Point"}
}