{
  "type": "Feature",
  "properties": {
    "addr:full":"Sivlandv\u00e6nget 2, Hjallese Odense S Danmark 5260",
    "addr:housenumber":"2",
    "addr:postcode":"5260",
    "addr:street":"Sivlandvaenget;Hjallese",
    "iso:country":"DK",
    "sg:address":"Sivlandv\u00e6nget 2, Hjallese",
    "sg:city":"Odense S",
    "sg:orig_category":"Redningskorps",
    "sg:phone":"+45 66 19 20 45",
    "sg:postcode":"5260",
    "sg:province":"Danmark",
    "wof:name":"Falcks Redningskorps",
    "wof:placetype":"venue"
},
  "geometry": {"coordinates":[10.3157806396,55.3122825623],"type":"Point"}
}