{
  "type": "Feature",
  "properties": {
    "addr:full":"Klostergade 11 Vestervig Danmark 7770",
    "addr:housenumber":"11",
    "addr:postcode":"7770",
    "addr:street":"Klostergade",
    "iso:country":"DK",
    "sg:address":"Klostergade 11",
    "sg:city":"Vestervig",
    "sg:orig_category":"Skolefritidsordninger",
    "sg:phone":"+45 97 94 10 27",
    "sg:postcode":"7770",
    "sg:province":"Danmark",
    "wof:name":"Fluen, Vestervig Skoles SFO",
    "wof:placetype":"venue"
},
  "geometry": {"coordinates":[8.3203105927,56.7655639648],"type":"Point"}
}