{
  "type": "Feature",
  "properties": {
    "addr:full":"Toften 22, Tastum Stoholm Danmark 7850",
    "addr:housenumber":"22",
    "addr:postcode":"7850",
    "addr:street":"Toften;Stoholm",
    "iso:country":"DK",
    "sg:address":"Toften 22, Tastum",
    "sg:city":"Stoholm",
    "sg:orig_category":"Murermestre",
    "sg:phone":"+45 97 54 12 20",
    "sg:postcode":"7850",
    "sg:province":"Danmark",
    "wof:name":"Kristensen, Bjarne Toft",
    "wof:placetype":"venue"
},
  "geometry": {"coordinates":[9.148730278,56.4856910706],"type":"Point"}
}