{
  "type": "Feature",
  "properties": {
    "addr:full":"Insp.: Benny Svendsen, H\u00f8neballevej 10, Langemark Sams\u00f8 Danmark 8305",
    "addr:housenumber":"10",
    "addr:postcode":"8305",
    "addr:street":"Honeballevej",
    "iso:country":"DK",
    "sg:address":"Insp.: Benny Svendsen, H\u00f8neballevej 10, Langemark",
    "sg:city":"Sams\u00f8",
    "sg:orig_category":"Kommunale ungdomsskoler",
    "sg:phone":"+45 86 59 02 73",
    "sg:postcode":"8305",
    "sg:province":"Danmark",
    "wof:name":"Sams\u00f8 Ungdomsskole",
    "wof:placetype":"venue"
},
  "geometry": {"coordinates":[10.5885000229,55.8320198059],"type":"Point"}
}