{
  "type": "Feature",
  "properties": {
    "addr:full":"Ternevej 59 Horsens Danmark 8700",
    "addr:housenumber":"59",
    "addr:postcode":"8700",
    "addr:street":"Ternevej",
    "iso:country":"DK",
    "sg:address":"Ternevej 59",
    "sg:city":"Horsens",
    "sg:orig_category":"Frugt en gros",
    "sg:phone":"+45 75 64 31 66",
    "sg:postcode":"8700",
    "sg:province":"Danmark",
    "wof:name":"Frandsen Frugt",
    "wof:placetype":"venue"
},
  "geometry": {"coordinates":[9.8372974396,55.8409729004],"type":"Point"}
}