{
  "type": "Feature",
  "properties": {
    "addr:full":"Overdrevsvej 11 Store Heddinge Danmark 4660",
    "addr:housenumber":"11",
    "addr:postcode":"4660",
    "addr:street":"Overdrevsvej",
    "iso:country":"DK",
    "sg:address":"Overdrevsvej 11",
    "sg:city":"Store Heddinge",
    "sg:orig_category":"Fodterapeuter",
    "sg:phone":"+45 56 50 25 86",
    "sg:postcode":"4660",
    "sg:province":"Danmark",
    "wof:name":"Christiansen, Ulla",
    "wof:placetype":"venue"
},
  "geometry": {"coordinates":[12.38194561,55.3075790405],"type":"Point"}
}