{
  "type": "Feature",
  "properties": {
    "addr:full":"Fmd.: Louis H\u00f8y, Gartnersvinget 12 \u00d8lstykke Danmark 3650",
    "addr:housenumber":"12",
    "addr:postcode":"3650",
    "addr:street":"Gartnersvinget",
    "iso:country":"DK",
    "sg:address":"Fmd.: Louis H\u00f8y, Gartnersvinget 12",
    "sg:city":"\u00d8lstykke",
    "sg:orig_category":"Grundejerforeninger",
    "sg:phone":"+45 47 17 87 16",
    "sg:postcode":"3650",
    "sg:province":"Danmark",
    "wof:name":"Grundejerforeningen Gartnersvinget",
    "wof:placetype":"venue"
},
  "geometry": {"coordinates":[-93.1404495239,37.757900238],"type":"Point"}
}