{
  "type": "Feature",
  "properties": {
    "addr:full":"Peter Bangs Vej 97 Frederiksberg Danmark 2000",
    "addr:housenumber":"97",
    "addr:postcode":"2000",
    "addr:street":"Peter Bangs Vej",
    "iso:country":"DK",
    "sg:address":"Peter Bangs Vej 97",
    "sg:city":"Frederiksberg",
    "sg:orig_category":"Ejendomshandel",
    "sg:phone":"+45 38 71 00 42",
    "sg:postcode":"2000",
    "sg:province":"Danmark",
    "wof:name":"Vex\u00f8e Bolig Frederiksberg",
    "wof:placetype":"venue"
},
  "geometry": {"coordinates":[12.5010795593,55.6784362793],"type":"Point"}
}