{
  "type": "Feature",
  "properties": {
    "iso:country":"DK",
    "sg:address":"Officersbygningen, v\u00e6r. 214, Vester Alle 3 C",
    "sg:city":"\u00c5rhus C",
    "sg:orig_category":"Teatre",
    "sg:phone":"+45 86 13 02 64",
    "sg:postcode":"8000",
    "sg:province":"Danmark",
    "wof:name":"Teater MU",
    "wof:placetype":"venue"
},
  "geometry": {"coordinates":[-85.2299499512,37.1363105774],"type":"Point"}
}