{
  "type": "Feature",
  "properties": {
    "iso:country":"DK",
    "sg:address":"Torvet 10",
    "sg:city":"Odder",
    "sg:orig_category":"Revisorer",
    "sg:phone":"+45 86 54 15 44",
    "sg:postcode":"8300",
    "sg:province":"Danmark",
    "sg:website":"www.nd-revision.dk",
    "wof:name":"ND Revision Odder",
    "wof:placetype":"venue"
},
  "geometry": {"coordinates":[10.146697998,55.9717063904],"type":"Point"}
}