{
  "type": "Feature",
  "properties": {
    "addr:full":"Niels Finsensvej 7 A Vejle Danmark 7100",
    "addr:housenumber":"7 a",
    "addr:postcode":"7100",
    "addr:street":"Niels Finsensvej",
    "iso:country":"DK",
    "sg:address":"Niels Finsensvej 7 A",
    "sg:city":"Vejle",
    "sg:orig_category":"Rustbeskyttelse",
    "sg:phone":"+45 76 40 03 40",
    "sg:postcode":"7100",
    "sg:province":"Danmark",
    "wof:name":"Vejle Autoglas & Anti-Rust Center",
    "wof:placetype":"venue"
},
  "geometry": {"coordinates":[9.5703325272,55.7250595093],"type":"Point"}
}