{
  "type": "Feature",
  "properties": {
    "addr:full":"Gl. Landevej 13, Melholt Asaa Danmark 9340",
    "addr:housenumber":"13",
    "addr:postcode":"9340",
    "addr:street":"Gl. Landevej;Melholt",
    "iso:country":"DK",
    "sg:address":"Gl. Landevej 13, Melholt",
    "sg:city":"Asaa",
    "sg:orig_category":"Solcentre",
    "sg:phone":"+45 98 85 17 58",
    "sg:postcode":"9340",
    "sg:province":"Danmark",
    "wof:name":"Melholt Solcenter",
    "wof:placetype":"venue"
},
  "geometry": {"coordinates":[10.4039297104,57.1481704712],"type":"Point"}
}