{
  "type": "Feature",
  "properties": {
    "addr:full":"Bredgade 5 Horsens Danmark 8700",
    "addr:housenumber":"5",
    "addr:postcode":"8700",
    "addr:street":"Bredgade",
    "iso:country":"DK",
    "sg:address":"Bredgade 5",
    "sg:city":"Horsens",
    "sg:classifiers":[
        {
            "category":"Communications",
            "type":"Services"
        }
    ],
    "sg:phone":"+45 75 62 69 51",
    "sg:postcode":"8700",
    "sg:province":"Danmark",
    "sg:tags":[
        "og",
        "tv",
        "radio"
    ],
    "wof:name":"Asger's Radio",
    "wof:placetype":"venue"
},
  "geometry": {"coordinates":[9.6114768982,55.9727668762],"type":"Point"}
}