{
  "type": "Feature",
  "properties": {
    "addr:full":"Lin\u00e5vej 7 Silkeborg Danmark 8600",
    "addr:housenumber":"7",
    "addr:postcode":"8600",
    "addr:street":"Linaavej",
    "iso:country":"DK",
    "sg:address":"Lin\u00e5vej 7",
    "sg:city":"Silkeborg",
    "sg:orig_category":"Produkthandlere",
    "sg:phone":"+45 86 80 43 22",
    "sg:postcode":"8600",
    "sg:province":"Danmark",
    "wof:name":"Silkeborg Produkt- og Genbrugsforretning",
    "wof:placetype":"venue"
},
  "geometry": {"coordinates":[9.6293964386,56.157081604],"type":"Point"}
}