{
  "type": "Feature",
  "properties": {
    "addr:full":"Svansmosen 2, \u00d8rby Helsinge Danmark 3200",
    "addr:housenumber":"2",
    "addr:postcode":"3200",
    "addr:street":"Svansmosen;Orby",
    "iso:country":"DK",
    "sg:address":"Svansmosen 2, \u00d8rby",
    "sg:city":"Helsinge",
    "sg:orig_category":"Hundepensioner",
    "sg:phone":"+45 48 70 54 27",
    "sg:postcode":"3200",
    "sg:province":"Danmark",
    "sg:website":"www.kameludl.dk",
    "wof:name":"Hastig, Hanne",
    "wof:placetype":"venue"
},
  "geometry": {"coordinates":[12.196846962,56.0224456787],"type":"Point"}
}