{
  "type": "Feature",
  "properties": {
    "addr:full":"L\u00f8rstedvej 20, Bonderup Fjerritslev Danmark 9690",
    "addr:housenumber":"20",
    "addr:postcode":"9690",
    "addr:street":"Lorstedvej;Bonderup",
    "iso:country":"DK",
    "sg:address":"L\u00f8rstedvej 20, Bonderup",
    "sg:city":"Fjerritslev",
    "sg:orig_category":"Autovask",
    "sg:phone":"+45 98 21 50 99",
    "sg:postcode":"9690",
    "sg:province":"Danmark",
    "wof:name":"Statoil Center Limfjorden",
    "wof:placetype":"venue"
},
  "geometry": {"coordinates":[9.2667350769,57.0882301331],"type":"Point"}
}