{
  "type": "Feature",
  "properties": {
    "addr:full":"Karen Blixens Vej 92 Ikast Danmark 7430",
    "addr:housenumber":"92",
    "addr:postcode":"7430",
    "addr:street":"Karen Blixens Vej",
    "iso:country":"DK",
    "sg:address":"Karen Blixens Vej 92",
    "sg:city":"Ikast",
    "sg:orig_category":"Tekstilindustri",
    "sg:phone":"+45 97 15 28 19",
    "sg:postcode":"7430",
    "sg:province":"Danmark",
    "wof:name":"Vi-Ka",
    "wof:placetype":"venue"
},
  "geometry": {"coordinates":[9.1495599747,56.1220016479],"type":"Point"}
}