{
  "type": "Feature",
  "properties": {
    "addr:full":"M\u00f8lleagervej 2, \u00d8rsted Havdrup Danmark 4622",
    "addr:housenumber":"2",
    "addr:postcode":"4622",
    "addr:street":"Molleagervej",
    "iso:country":"DK",
    "sg:address":"M\u00f8lleagervej 2, \u00d8rsted",
    "sg:city":"Havdrup",
    "sg:classifiers":[
        {
            "category":"Taxi",
            "type":"Transportation"
        }
    ],
    "sg:phone":"+45 46 18 58 18",
    "sg:postcode":"4622",
    "sg:province":"Danmark",
    "wof:name":"\u00d8rsted Taxi",
    "wof:placetype":"venue"
},
  "geometry": {"coordinates":[12.1158895493,55.5443534851],"type":"Point"}
}