{
  "type": "Feature",
  "properties": {
    "addr:full":"Vandv\u00e6rksvej 2 Karup Danmark 7470",
    "addr:housenumber":"2",
    "addr:postcode":"7470",
    "addr:street":"Vandvaerksvej",
    "iso:country":"DK",
    "sg:address":"Vandv\u00e6rksvej 2",
    "sg:city":"Karup",
    "sg:orig_category":"Autoreparation og -service",
    "sg:phone":"+45 97 10 01 57",
    "sg:postcode":"7470",
    "sg:province":"Danmark",
    "wof:name":"Eigil's Cykel - Autoservice",
    "wof:placetype":"venue"
},
  "geometry": {"coordinates":[9.1831493378,56.3207321167],"type":"Point"}
}