{
  "type": "Feature",
  "properties": {
    "addr:full":"Enghavevej 57 K\u00f8benhavn Danmark 1674",
    "addr:housenumber":"57;1674",
    "addr:street":"Enghavevej",
    "iso:country":"DK",
    "sg:address":"Enghavevej 57",
    "sg:city":"K\u00f8benhavn",
    "sg:orig_category":"Blomsterhandlere",
    "sg:phone":"+45 33 24 06 85",
    "sg:postcode":"1674",
    "sg:province":"Danmark",
    "wof:name":"Fr\u00f8jks Blomster",
    "wof:placetype":"venue"
},
  "geometry": {"coordinates":[12.5454101562,55.6696586609],"type":"Point"}
}