{
  "type": "Feature",
  "properties": {
    "iso:country":"DK",
    "sg:address":"N\u00f8rregade 95, Gl. Ejby",
    "sg:city":"Ejby",
    "sg:orig_category":"Blikkenslagere",
    "sg:phone":"+45 64 46 13 08",
    "sg:postcode":"5592",
    "sg:province":"Danmark",
    "wof:name":"Ejby VVS",
    "wof:placetype":"venue"
},
  "geometry": {"coordinates":[9.92773,55.428844],"type":"Point"}
}