{
  "type": "Feature",
  "properties": {
    "addr:full":"v/ Lars Haahr Andersen, Galten Hedevej 19, Vinterslev Hadsten Danmark 8370",
    "addr:housenumber":"19",
    "addr:postcode":"8370",
    "addr:street":"Andersen Galten Hedevej;Vinterslev",
    "iso:country":"DK",
    "sg:address":"v/ Lars Haahr Andersen, Galten Hedevej 19, Vinterslev",
    "sg:city":"Hadsten",
    "sg:orig_category":"Kirkelige foreninger",
    "sg:phone":"+45 23 46 44 14",
    "sg:postcode":"8370",
    "sg:province":"Danmark",
    "sg:website":"www.lmu.dk",
    "wof:name":"Luthersk Missions Ungdom",
    "wof:placetype":"venue"
},
  "geometry": {"coordinates":[10.047659874,56.3287239075],"type":"Point"}
}