{
  "type": "Feature",
  "properties": {
    "iso:country":"DK",
    "sg:address":"Hovedvejen 140",
    "sg:city":"Glostrup",
    "sg:orig_category":"Brugsforeninger",
    "sg:phone":"+45 43 96 51 77",
    "sg:postcode":"2600",
    "sg:province":"Danmark",
    "wof:name":"Kvickly",
    "wof:placetype":"venue"
},
  "geometry": {"coordinates":[12.392660141,55.6656036377],"type":"Point"}
}