{
  "type": "Feature",
  "properties": {
    "iso:country":"DK",
    "sg:address":"Platanvej 15",
    "sg:city":"Odense M",
    "sg:orig_category":"Behandlingshjem",
    "sg:phone":"+45 66 11 54 43",
    "sg:postcode":"5230",
    "sg:province":"Danmark",
    "wof:name":"Platanhaven",
    "wof:placetype":"venue"
},
  "geometry": {"coordinates":[10.3847036362,55.3866958618],"type":"Point"}
}