{
  "type": "Feature",
  "properties": {
    "addr:full":"Fmd.: B\u00f8rge Mikkelsen, Amagergade 3 Br\u00f8nderslev Danmark 9700",
    "addr:housenumber":"3",
    "addr:postcode":"9700",
    "addr:street":"Amagergade",
    "iso:country":"DK",
    "sg:address":"Fmd.: B\u00f8rge Mikkelsen, Amagergade 3",
    "sg:city":"Br\u00f8nderslev",
    "sg:orig_category":"Grundejerforeninger",
    "sg:phone":"+45 98 82 21 48",
    "sg:postcode":"9700",
    "sg:province":"Danmark",
    "wof:name":"Ejerlauget Edelweis",
    "wof:placetype":"venue"
},
  "geometry": {"coordinates":[9.7584476471,57.2860298157],"type":"Point"}
}