{
  "type": "Feature",
  "properties": {
    "addr:full":"N\u00e6ldebjerg Alle 97 Greve Danmark 2670",
    "addr:housenumber":"97",
    "addr:postcode":"2670",
    "addr:street":"Naeldebjerg Alle",
    "iso:country":"DK",
    "sg:address":"N\u00e6ldebjerg Alle 97",
    "sg:city":"Greve",
    "sg:orig_category":"Murermestre",
    "sg:phone":"+45 43 90 74 72",
    "sg:postcode":"2670",
    "sg:province":"Danmark",
    "wof:name":"Hansen, Hans",
    "wof:placetype":"venue"
},
  "geometry": {"coordinates":[12.2768239975,55.5818328857],"type":"Point"}
}