{
  "type": "Feature",
  "properties": {
    "addr:full":"v/ Jens Richard Jensen, \u00c5dalen 21 Grindsted Danmark 7200",
    "addr:housenumber":"21",
    "addr:postcode":"7200",
    "addr:street":"Aadalen",
    "iso:country":"DK",
    "sg:address":"v/ Jens Richard Jensen, \u00c5dalen 21",
    "sg:city":"Grindsted",
    "sg:orig_category":"Kolonihaveforeninger",
    "sg:phone":"+45 75 32 15 52",
    "sg:postcode":"7200",
    "sg:province":"Danmark",
    "wof:name":"Kolonihaveforeningen Heden",
    "wof:placetype":"venue"
},
  "geometry": {"coordinates":[8.9288702011,55.7560272217],"type":"Point"}
}