{
  "type": "Feature",
  "properties": {
    "addr:full":"\u00c5lekistevej 27 Vordingborg Danmark 4760",
    "addr:housenumber":"27",
    "addr:postcode":"4760",
    "addr:street":"Aalekistevej",
    "iso:country":"DK",
    "sg:address":"\u00c5lekistevej 27",
    "sg:city":"Vordingborg",
    "sg:orig_category":"Autotransport",
    "sg:phone":"+45 40 16 90 61",
    "sg:postcode":"4760",
    "sg:province":"Danmark",
    "wof:name":"Id\u00e9 - Trans",
    "wof:placetype":"venue"
},
  "geometry": {"coordinates":[11.8722677231,55.0647392273],"type":"Point"}
}