{
  "type": "Feature",
  "properties": {
    "addr:full":"Elboparken 6, Pjedsted Fredericia Danmark 7000",
    "addr:housenumber":"6",
    "addr:postcode":"7000",
    "addr:street":"Elboparken;Pjedsted",
    "iso:country":"DK",
    "sg:address":"Elboparken 6, Pjedsted",
    "sg:city":"Fredericia",
    "sg:orig_category":"Sportsartikler",
    "sg:phone":"+45 75 95 44 33",
    "sg:postcode":"7000",
    "sg:province":"Danmark",
    "sg:website":"www.havkajakken.dk",
    "wof:name":"Havkajakken & Friluftsliv",
    "wof:placetype":"venue"
},
  "geometry": {"coordinates":[9.7591047287,55.566368103],"type":"Point"}
}