{
  "type": "Feature",
  "properties": {
    "addr:full":"Klostergade 34 \u00c5rhus C Danmark 8000",
    "addr:housenumber":"34",
    "addr:postcode":"8000",
    "addr:street":"Klostergade",
    "iso:country":"DK",
    "sg:address":"Klostergade 34",
    "sg:city":"\u00c5rhus C",
    "sg:orig_category":"Cafeer",
    "sg:phone":"+45 86 76 17 17",
    "sg:postcode":"8000",
    "sg:province":"Danmark",
    "wof:name":"Independent",
    "wof:placetype":"venue"
},
  "geometry": {"coordinates":[4.717400074,49.7588005066],"type":"Point"}
}