{
  "type": "Feature",
  "properties": {
    "addr:full":"Karetmagerporten 8 Hvidovre Danmark 2650",
    "addr:housenumber":"8",
    "addr:postcode":"2650",
    "addr:street":"Karetmagerporten",
    "iso:country":"DK",
    "sg:address":"Karetmagerporten 8",
    "sg:city":"Hvidovre",
    "sg:orig_category":"\u00c3\u02dcvrige foreninger",
    "sg:phone":"+45 36 49 48 20",
    "sg:postcode":"2650",
    "sg:province":"Danmark",
    "wof:name":"For\u00e6ldreforeningen ved B\u00f8rnehuset M\u00e5gen",
    "wof:placetype":"venue"
},
  "geometry": {"coordinates":[12.4466257095,55.6268615723],"type":"Point"}
}