{
  "type": "Feature",
  "properties": {
    "addr:full":"Kidingvej 2, Bovrup Aabenraa Danmark 6200",
    "addr:housenumber":"2",
    "addr:postcode":"6200",
    "addr:street":"Kidingvej;Bovrup",
    "iso:country":"DK",
    "sg:address":"Kidingvej 2, Bovrup",
    "sg:city":"Aabenraa",
    "sg:classifiers":[
        {
            "category":"Banks & Credit Unions",
            "subcategory":"Bank",
            "type":"Services"
        }
    ],
    "sg:phone":"+45 74 68 03 25",
    "sg:postcode":"6200",
    "sg:province":"Danmark",
    "sg:tags":[
        "banker"
    ],
    "wof:name":"Sydbank, Bovrup Afd.",
    "wof:placetype":"venue"
},
  "geometry": {"coordinates":[9.4213867188,55.0449562073],"type":"Point"}
}