{
  "type": "Feature",
  "properties": {
    "addr:full":"S\u00f8ndergade 9 Frederikshavn Danmark 9900",
    "addr:housenumber":"9",
    "addr:postcode":"9900",
    "addr:street":"Sondergade",
    "iso:country":"DK",
    "sg:address":"S\u00f8ndergade 9",
    "sg:city":"Frederikshavn",
    "sg:orig_category":"Diskoteker",
    "sg:phone":"+45 98 41 03 73",
    "sg:postcode":"9900",
    "sg:province":"Danmark",
    "wof:name":"Buddy Holly",
    "wof:placetype":"venue"
},
  "geometry": {"coordinates":[10.5338106155,57.4368782043],"type":"Point"}
}