{
  "type": "Feature",
  "properties": {
    "addr:full":"Bredh\u00f8jvej 17 - 19 Silkeborg Danmark 8600",
    "addr:housenumber":"17 19",
    "addr:postcode":"8600",
    "addr:street":"Bredhojvej",
    "iso:country":"DK",
    "sg:address":"Bredh\u00f8jvej 17 - 19",
    "sg:city":"Silkeborg",
    "sg:orig_category":"Autoforhandlere",
    "sg:phone":"+45 86 82 21 44",
    "sg:postcode":"8600",
    "sg:province":"Danmark",
    "wof:name":"Dieselhuset A/S",
    "wof:placetype":"venue"
},
  "geometry": {"coordinates":[9.5511026382,56.1885490417],"type":"Point"}
}