{
  "type": "Feature",
  "properties": {
    "addr:full":"\u00d8stre Kirkevej 1 Herning Danmark 7400",
    "addr:housenumber":"1",
    "addr:postcode":"7400",
    "addr:street":"Ostre Kirkevej",
    "iso:country":"DK",
    "sg:address":"\u00d8stre Kirkevej 1",
    "sg:city":"Herning",
    "sg:orig_category":"Musik og sang",
    "sg:phone":"+45 97 12 23 38",
    "sg:postcode":"7400",
    "sg:province":"Danmark",
    "wof:name":"Herning Kirkes Drengekor",
    "wof:placetype":"venue"
},
  "geometry": {"coordinates":[8.9757032394,56.1379394531],"type":"Point"}
}