{
  "type": "Feature",
  "properties": {
    "addr:full":"Juls\u00f8vej 10 Grindsted Danmark 7200",
    "addr:housenumber":"10",
    "addr:postcode":"7200",
    "addr:street":"Julsovej",
    "iso:country":"DK",
    "sg:address":"Juls\u00f8vej 10",
    "sg:city":"Grindsted",
    "sg:orig_category":"Murermestre",
    "sg:phone":"+45 75 32 29 85",
    "sg:postcode":"7200",
    "sg:province":"Danmark",
    "wof:name":"Jensen, Gunnar",
    "wof:placetype":"venue"
},
  "geometry": {"coordinates":[8.9030914307,55.7699699402],"type":"Point"}
}