{
  "type": "Feature",
  "properties": {
    "iso:country":"DK",
    "sg:address":"\u00d8stergade 7",
    "sg:city":"Store Heddinge",
    "sg:orig_category":"Bagere",
    "sg:phone":"+45 56 50 34 44",
    "sg:postcode":"4660",
    "sg:province":"Danmark",
    "wof:name":"Fog Bageri",
    "wof:placetype":"venue"
},
  "geometry": {"coordinates":[12.390337,55.309254],"type":"Point"}
}