{
  "type": "Feature",
  "properties": {
    "addr:full":"Fmd.: Grethe Nielsen, Holmev\u00e6nget 5 Gislev Danmark 5854",
    "addr:housenumber":"5",
    "addr:postcode":"5854",
    "iso:country":"DK",
    "sg:address":"Fmd.: Grethe Nielsen, Holmev\u00e6nget 5",
    "sg:city":"Gislev",
    "sg:orig_category":"Kulturelle foreninger",
    "sg:phone":"+45 62 29 15 53",
    "sg:postcode":"5854",
    "sg:province":"Danmark",
    "wof:name":"N\u00f8rrev\u00e6nget's Venner",
    "wof:placetype":"venue"
},
  "geometry": {"coordinates":[10.5988063812,55.2191352844],"type":"Point"}
}