{
  "type": "Feature",
  "properties": {
    "addr:full":"Klokkerfaldet 102, Hasle \u00c5rhus V Danmark 8210",
    "addr:housenumber":"102",
    "addr:postcode":"8210",
    "addr:street":"Klokkerfaldet",
    "iso:country":"DK",
    "sg:address":"Klokkerfaldet 102, Hasle",
    "sg:city":"\u00c5rhus V",
    "sg:orig_category":"Arkitekter",
    "sg:phone":"+45 86 15 12 01",
    "sg:postcode":"8210",
    "sg:province":"Danmark",
    "wof:name":"Pedersen, Kaj",
    "wof:placetype":"venue"
},
  "geometry": {"coordinates":[14.7065896988,55.1830787659],"type":"Point"}
}