{
  "type": "Feature",
  "properties": {
    "iso:country":"DK",
    "sg:address":"Vestergade 1",
    "sg:city":"Stoholm",
    "sg:classifiers":[
        {
            "category":"Banks & Credit Unions",
            "subcategory":"Bank",
            "type":"Services"
        }
    ],
    "sg:phone":"+45 97 54 13 66",
    "sg:postcode":"7850",
    "sg:province":"Danmark",
    "sg:tags":[
        "banker"
    ],
    "wof:name":"Salling Bank, Stoholm afd.",
    "wof:placetype":"venue"
},
  "geometry": {"coordinates":[9.150803566,56.4853897095],"type":"Point"}
}