{
  "type": "Feature",
  "properties": {
    "addr:full":"Fmd.: Jens Thygesen, \u00d8stergade 16, 3. mf. Silkeborg Danmark 8600",
    "addr:housenumber":"16 3 mf.",
    "addr:postcode":"8600",
    "addr:street":"Ostergade",
    "iso:country":"DK",
    "sg:address":"Fmd.: Jens Thygesen, \u00d8stergade 16, 3. mf.",
    "sg:city":"Silkeborg",
    "sg:orig_category":"Hobbybetonede foreninger",
    "sg:phone":"+45 86 82 44 70",
    "sg:postcode":"8600",
    "sg:province":"Danmark",
    "wof:name":"Vikingebadeklubben H.A.C. Neptun",
    "wof:placetype":"venue"
},
  "geometry": {"coordinates":[9.5524425507,56.1693305969],"type":"Point"}
}