{
  "type": "Feature",
  "properties": {
    "addr:full":"Lundebakkevej 1 Holmegaard Danmark 4684",
    "addr:housenumber":"1",
    "addr:postcode":"4684",
    "addr:street":"Lundebakkevej",
    "iso:country":"DK",
    "sg:address":"Lundebakkevej 1",
    "sg:city":"Holmegaard",
    "sg:orig_category":"Gartnerier",
    "sg:phone":"+45 55 56 11 61",
    "sg:postcode":"4684",
    "sg:province":"Danmark",
    "wof:name":"B\u00f8nnemose, Gartneriet",
    "wof:placetype":"venue"
},
  "geometry": {"coordinates":[11.873295784,55.2468185425],"type":"Point"}
}