{
  "type": "Feature",
  "properties": {
    "iso:country":"DK",
    "sg:address":"Torvestr\u00e6de 1",
    "sg:city":"N\u00e6stved",
    "sg:orig_category":"Sko",
    "sg:phone":"+45 55 77 63 83",
    "sg:postcode":"4700",
    "sg:province":"Danmark",
    "wof:name":"Bianco Footwear",
    "wof:placetype":"venue"
},
  "geometry": {"coordinates":[-73.5234451294,41.9641532898],"type":"Point"}
}