{
  "type": "Feature",
  "properties": {
    "iso:country":"DK",
    "sg:address":"L\u00f8ven\u00f8rnsgade 11",
    "sg:city":"Horsens",
    "sg:orig_category":"Babyudstyr",
    "sg:phone":"+45 75 61 05 06",
    "sg:postcode":"8700",
    "sg:province":"Danmark",
    "sg:website":"www.krible-krable.dk",
    "wof:name":"Krible-Krable Babyland",
    "wof:placetype":"venue"
},
  "geometry": {"coordinates":[9.843245,55.862106],"type":"Point"}
}