{
  "type": "Feature",
  "properties": {
    "addr:full":"Lyngby Hovedgade 86 A Kongens Lyngby Danmark 2800",
    "addr:housenumber":"86 a",
    "addr:postcode":"2800",
    "addr:street":"Lyngby Hovedgade",
    "iso:country":"DK",
    "sg:address":"Lyngby Hovedgade 86 A",
    "sg:city":"Kongens Lyngby",
    "sg:orig_category":"Senge",
    "sg:phone":"+45 45 88 45 00",
    "sg:postcode":"2800",
    "sg:province":"Danmark",
    "wof:name":"Sahva",
    "wof:placetype":"venue"
},
  "geometry": {"coordinates":[12.5066623688,55.7677955627],"type":"Point"}
}