{
  "type": "Feature",
  "properties": {
    "iso:country":"DK",
    "sg:address":"Gr\u00e5bynkevej 7",
    "sg:city":"Greve",
    "sg:orig_category":"Bogtrykkerier",
    "sg:phone":"+45 43 90 38 63",
    "sg:postcode":"2670",
    "sg:province":"Danmark",
    "wof:name":"Petit-Tryk",
    "wof:placetype":"venue"
},
  "geometry": {"coordinates":[12.2801179886,55.5708084106],"type":"Point"}
}