{
  "type": "Feature",
  "properties": {
    "addr:full":"Tj\u00f8rneparken 3, Svinninge N\u00f8rre Asmindrup Danmark 4572",
    "addr:housenumber":"3",
    "addr:postcode":"4572",
    "addr:street":"Tjorneparken",
    "iso:country":"DK",
    "sg:address":"Tj\u00f8rneparken 3, Svinninge",
    "sg:city":"N\u00f8rre Asmindrup",
    "sg:orig_category":"Plejecentre",
    "sg:phone":"+45 59 36 64 09",
    "sg:postcode":"4572",
    "sg:province":"Danmark",
    "wof:name":"\u00c6ldreteknisk afdeling",
    "wof:placetype":"venue"
},
  "geometry": {"coordinates":[11.6075077057,55.8814544678],"type":"Point"}
}