{
  "type": "Feature",
  "properties": {
    "iso:country":"DK",
    "sg:address":"Gadek\u00e6rsvej 12 ",
    "sg:city":"Storvorde",
    "sg:classifiers":[
        {
            "category":"Wholesale",
            "subcategory":"Machinery & Supplies",
            "type":"Manufacturing & Wholesale Goods"
        }
    ],
    "sg:phone":"+45 98 31 62 44",
    "sg:postcode":"9280",
    "sg:province":"Danmark",
    "sg:tags":[
        "-",
        "agriculture",
        "equipment"
    ],
    "wof:name":"INDUSTRIVARME A/S",
    "wof:placetype":"venue"
},
  "geometry": {"coordinates":[10.0998029709,56.9800033569],"type":"Point"}
}