{
  "type": "Feature",
  "properties": {
    "iso:country":"DK",
    "sg:address":"Borgm N Jensens Vej 6",
    "sg:city":"Varde",
    "sg:orig_category":"Bilinspektion",
    "sg:phone":"+45 75 22 12 42",
    "sg:postcode":"6800",
    "sg:province":"Danmark",
    "sg:website":"www.bilsyn.dk",
    "wof:name":"Statens Bilinspektion",
    "wof:placetype":"venue"
},
  "geometry": {"coordinates":[8.464344,55.624226],"type":"Point"}
}