{
  "type": "Feature",
  "properties": {
    "iso:country":"DK",
    "sg:address":"Amalie Skrams Alle 32",
    "sg:city":"Valby",
    "sg:orig_category":"Malermestre",
    "sg:phone":"+45 36 16 02 05",
    "sg:postcode":"2500",
    "sg:province":"Danmark",
    "wof:name":"Hansen, Arne & T Dahm Hansen",
    "wof:placetype":"venue"
},
  "geometry": {"coordinates":[12.4976968765,55.6654968262],"type":"Point"}
}