{
  "type": "Feature",
  "properties": {
    "addr:full":"Nytorv 18 Aalborg Danmark 9000",
    "addr:housenumber":"18",
    "addr:postcode":"9000",
    "addr:street":"Nytorv",
    "iso:country":"DK",
    "sg:address":"Nytorv 18",
    "sg:city":"Aalborg",
    "sg:orig_category":"Rejsebureauer",
    "sg:phone":"+45 98 10 00 22",
    "sg:postcode":"9000",
    "sg:province":"Danmark",
    "wof:name":"Check Point Travel",
    "wof:placetype":"venue"
},
  "geometry": {"coordinates":[9.9237928391,57.0478897095],"type":"Point"}
}