{
  "type": "Feature",
  "properties": {
    "addr:full":"Nygade 18 B Silkeborg Danmark 8600",
    "addr:housenumber":"18 b",
    "addr:postcode":"8600",
    "addr:street":"Nygade",
    "iso:country":"DK",
    "sg:address":"Nygade 18 B",
    "sg:city":"Silkeborg",
    "sg:orig_category":"Cafeer",
    "sg:phone":"+45 86 82 12 73",
    "sg:postcode":"8600",
    "sg:province":"Danmark",
    "wof:name":"Chaplin, Grammofon-Caf\u00e9en",
    "wof:placetype":"venue"
},
  "geometry": {"coordinates":[9.5474481583,56.167427063],"type":"Point"}
}