{
  "type": "Feature",
  "properties": {
    "addr:full":"Storegade 56 Varde Danmark 6800",
    "addr:housenumber":"56",
    "addr:postcode":"6800",
    "addr:street":"Storegade",
    "iso:country":"DK",
    "sg:address":"Storegade 56",
    "sg:city":"Varde",
    "sg:orig_category":"Renserier",
    "sg:phone":"+45 75 21 08 88",
    "sg:postcode":"6800",
    "sg:province":"Danmark",
    "wof:name":"Robe Rens & M\u00f8ntvask",
    "wof:placetype":"venue"
},
  "geometry": {"coordinates":[8.4823207855,55.6231231689],"type":"Point"}
}