{
  "type": "Feature",
  "properties": {
    "addr:full":"Pr\u00e6st\u00f8vej 25 Kalvehave Danmark 4771",
    "addr:housenumber":"25",
    "addr:postcode":"4771",
    "addr:street":"Praestovej",
    "iso:country":"DK",
    "sg:address":"Pr\u00e6st\u00f8vej 25",
    "sg:city":"Kalvehave",
    "sg:orig_category":"Autoreparation og -service",
    "sg:phone":"+45 40 63 32 10",
    "sg:postcode":"4771",
    "sg:province":"Danmark",
    "wof:name":"Mobil-Mekanikeren",
    "wof:placetype":"venue"
},
  "geometry": {"coordinates":[12.1575527191,55.0004501343],"type":"Point"}
}