{
  "type": "Feature",
  "properties": {
    "addr:full":"Lang\u00f8revej 9 Sams\u00f8 Danmark 8305",
    "addr:housenumber":"9",
    "addr:postcode":"8305",
    "addr:street":"Langorevej",
    "iso:country":"DK",
    "sg:address":"Lang\u00f8revej 9",
    "sg:city":"Sams\u00f8",
    "sg:orig_category":"Kirker",
    "sg:postcode":"8305",
    "sg:province":"Danmark",
    "wof:name":"Lang\u00f8re Kirke",
    "wof:placetype":"venue"
},
  "geometry": {"coordinates":[-107.9639587402,38.1021232605],"type":"Point"}
}