{
  "type": "Feature",
  "properties": {
    "addr:full":"Cikorievej 22 B Odense S\u00d8 Danmark 5220",
    "addr:housenumber":"22 b",
    "addr:postcode":"5220",
    "addr:street":"Cikorievej",
    "iso:country":"DK",
    "sg:address":"Cikorievej 22 B",
    "sg:city":"Odense S\u00d8",
    "sg:orig_category":"Malervarer",
    "sg:phone":"+45 65 91 44 77",
    "sg:postcode":"5220",
    "sg:province":"Danmark",
    "wof:name":"Sadolin Grossist Center",
    "wof:placetype":"venue"
},
  "geometry": {"coordinates":[10.4401607513,55.3935203552],"type":"Point"}
}