{
  "type": "Feature",
  "properties": {
    "addr:full":"N\u00f8rretorv 3 Aabenraa Danmark 6200",
    "addr:housenumber":"3",
    "addr:postcode":"6200",
    "addr:street":"Norretorv",
    "iso:country":"DK",
    "sg:address":"N\u00f8rretorv 3",
    "sg:city":"Aabenraa",
    "sg:orig_category":"Oplysningsforbund",
    "sg:phone":"+45 74 62 24 23",
    "sg:postcode":"6200",
    "sg:province":"Danmark",
    "wof:name":"AOF Aabenraa, Bov, Lundtoft og R\u00f8dekro",
    "wof:placetype":"venue"
},
  "geometry": {"coordinates":[9.4176530838,55.0461387634],"type":"Point"}
}