{
  "type": "Feature",
  "properties": {
    "addr:full":"Bredgade 48 Lang\u00e5 Danmark 8870",
    "addr:housenumber":"48",
    "addr:postcode":"8870",
    "addr:street":"Bredgade",
    "iso:country":"DK",
    "sg:address":"Bredgade 48",
    "sg:city":"Lang\u00e5",
    "sg:orig_category":"Revisorer",
    "sg:phone":"+45 86 46 12 44",
    "sg:postcode":"8870",
    "sg:province":"Danmark",
    "wof:name":"Kvist, Ib Aamann",
    "wof:placetype":"venue"
},
  "geometry": {"coordinates":[9.8963975906,56.3882675171],"type":"Point"}
}