{
  "type": "Feature",
  "properties": {
    "addr:full":"Danmarksvej 26 Skanderborg Danmark 8660",
    "addr:housenumber":"26",
    "addr:postcode":"8660",
    "addr:street":"Danmarksvej",
    "iso:country":"DK",
    "sg:address":"Danmarksvej 26",
    "sg:city":"Skanderborg",
    "sg:orig_category":"Faglige organisationer og -foreninger",
    "sg:phone":"+45 70 21 00 55",
    "sg:postcode":"8660",
    "sg:province":"Danmark",
    "wof:name":"Danske Vandv\u00e6rkers Forening",
    "wof:placetype":"venue"
},
  "geometry": {"coordinates":[9.9499416351,56.0504150391],"type":"Point"}
}