{
  "type": "Feature",
  "properties": {
    "addr:full":"Adidasvej 1  Them Danmark 8653",
    "addr:housenumber":"1",
    "addr:postcode":"8653",
    "addr:street":"Adidasvej",
    "iso:country":"DK",
    "sg:address":"Adidasvej 1 ",
    "sg:city":"Them",
    "sg:classifiers":[
        {
            "category":"Shopping",
            "subcategory":"Clothing, Apparel, & Fashions",
            "type":"Retail Goods"
        }
    ],
    "sg:phone":"+45 86 84 77 77",
    "sg:postcode":"8653",
    "sg:province":"Danmark",
    "sg:tags":[
        "clothes"
    ],
    "wof:name":"ADIDAS DENMARK A/S",
    "wof:placetype":"venue"
},
  "geometry": {"coordinates":[9.5846643448,56.0999336243],"type":"Point"}
}