{
  "type": "Feature",
  "properties": {
    "addr:full":"N\u00f8rre Landevej 78, Kegn\u00e6s Sydals Danmark 6470",
    "addr:housenumber":"78",
    "addr:postcode":"6470",
    "addr:street":"Norre Landevej;Kegnaes",
    "iso:country":"DK",
    "sg:address":"N\u00f8rre Landevej 78, Kegn\u00e6s",
    "sg:city":"Sydals",
    "sg:orig_category":"Keramik",
    "sg:phone":"+45 74 40 54 32",
    "sg:postcode":"6470",
    "sg:province":"Danmark",
    "sg:website":"www.keramik-lis.dk",
    "wof:name":"Kegn\u00e6s Keramik",
    "wof:placetype":"venue"
},
  "geometry": {"coordinates":[9.8924627304,54.9105377197],"type":"Point"}
}