{
  "type": "Feature",
  "properties": {
    "addr:full":"Algade 23 Aalborg Danmark 9000",
    "addr:housenumber":"23",
    "addr:postcode":"9000",
    "addr:street":"Algade",
    "iso:country":"DK",
    "sg:address":"Algade 23",
    "sg:city":"Aalborg",
    "sg:orig_category":"Fisk og vildt",
    "sg:phone":"+45 98 12 35 92",
    "sg:postcode":"9000",
    "sg:province":"Danmark",
    "wof:name":"Skibsted's Eftf.",
    "wof:placetype":"venue"
},
  "geometry": {"coordinates":[9.9212141037,57.0472068787],"type":"Point"}
}