{
  "type": "Feature",
  "properties": {
    "addr:full":"\u00d8stergade 16 Lemvig Danmark 7620",
    "addr:housenumber":"16",
    "addr:postcode":"7620",
    "addr:street":"Ostergade",
    "iso:country":"DK",
    "sg:address":"\u00d8stergade 16",
    "sg:city":"Lemvig",
    "sg:orig_category":"Sparekasser",
    "sg:phone":"+45 97 81 17 77",
    "sg:postcode":"7620",
    "sg:province":"Danmark",
    "wof:name":"Thyholm Sparekasse",
    "wof:placetype":"venue"
},
  "geometry": {"coordinates":[8.3121938705,56.5502815247],"type":"Point"}
}