{
  "type": "Feature",
  "properties": {
    "iso:country":"DK",
    "sg:address":"Stadionv\u00e6nget 6",
    "sg:city":"Tommerup",
    "sg:orig_category":"Varmeforsyning",
    "sg:phone":"+45 64 76 10 03",
    "sg:postcode":"5690",
    "sg:province":"Danmark",
    "wof:name":"Tommerup By's Fjernvarmeforsyning",
    "wof:placetype":"venue"
},
  "geometry": {"coordinates":[10.2489509583,55.3236503601],"type":"Point"}
}