{
  "type": "Feature",
  "properties": {
    "iso:country":"DK",
    "sg:address":"Idomvej 22",
    "sg:city":"Holstebro",
    "sg:orig_category":"Malermestre",
    "sg:phone":"+45 97 40 23 76",
    "sg:postcode":"7500",
    "sg:province":"Danmark",
    "wof:name":"Pilgaard, Ove",
    "wof:placetype":"venue"
},
  "geometry": {"coordinates":[8.6024532318,56.3523406982],"type":"Point"}
}