{
  "type": "Feature",
  "properties": {
    "addr:full":"Marstrup Bygade 115 Haderslev Danmark 6100",
    "addr:housenumber":"115",
    "addr:postcode":"6100",
    "addr:street":"Marstrup Bygade",
    "iso:country":"DK",
    "sg:address":"Marstrup Bygade 115",
    "sg:city":"Haderslev",
    "sg:orig_category":"Skolefritidsordninger",
    "sg:phone":"+45 74 57 59 15",
    "sg:postcode":"6100",
    "sg:province":"Danmark",
    "wof:name":"Marstrup Skoles Skolefritidsordning",
    "wof:placetype":"venue"
},
  "geometry": {"coordinates":[9.4267196655,55.1997261047],"type":"Point"}
}