{
  "type": "Feature",
  "properties": {
    "iso:country":"DK",
    "sg:address":"Ingerslevs Boulevard 15",
    "sg:city":"\u00c5rhus C",
    "sg:orig_category":"Bagere",
    "sg:phone":"+45 86 13 56 56",
    "sg:postcode":"8000",
    "sg:province":"Danmark",
    "wof:name":"Lucasg\u00e5rdens Bageri",
    "wof:placetype":"venue"
},
  "geometry": {"coordinates":[-116.27327728269999,32.6635398865],"type":"Point"}
}