{
  "type": "Feature",
  "properties": {
    "addr:full":"Amagertorv 19 Copenhagen 1160",
    "addr:housenumber":"19",
    "addr:postcode":"1160",
    "addr:street":"Amagertorv",
    "iso:country":"DK",
    "sg:address":"Amagertorv 19",
    "sg:city":"Copenhagen",
    "sg:classifiers":[
        {
            "category":"Professional",
            "subcategory":"Computer Services",
            "type":"Services"
        }
    ],
    "sg:postcode":"1160",
    "sg:tags":[
        "travel",
        "local"
    ],
    "sg:website":"http://www.momondo.com",
    "wof:name":"Momondo",
    "wof:placetype":"venue"
},
  "geometry": {"coordinates":[12.577576,55.678645],"type":"Point"}
}