{
  "type": "Feature",
  "properties": {
    "addr:full":"Louisevej 2 Brabrand Danmark 8220",
    "addr:housenumber":"2",
    "addr:postcode":"8220",
    "addr:street":"Louisevej",
    "iso:country":"DK",
    "sg:address":"Louisevej 2",
    "sg:city":"Brabrand",
    "sg:orig_category":"Renserier",
    "sg:phone":"+45 86 25 42 84",
    "sg:postcode":"8220",
    "sg:province":"Danmark",
    "wof:name":"S\u00f8vangens Renseri",
    "wof:placetype":"venue"
},
  "geometry": {"coordinates":[10.1333627701,56.1525535583],"type":"Point"}
}