{
  "type": "Feature",
  "properties": {
    "addr:full":"Hjermvej 29 Struer Danmark 7600",
    "addr:housenumber":"29",
    "addr:postcode":"7600",
    "addr:street":"Hjermvej",
    "iso:country":"DK",
    "sg:address":"Hjermvej 29",
    "sg:city":"Struer",
    "sg:classifiers":[
        {
            "category":"Taxi",
            "type":"Transportation"
        }
    ],
    "sg:phone":"+45 70 22 06 06",
    "sg:postcode":"7600",
    "sg:province":"Danmark",
    "wof:name":"Struer Taxi",
    "wof:placetype":"venue"
},
  "geometry": {"coordinates":[8.6050138474,56.4787750244],"type":"Point"}
}