{
  "type": "Feature",
  "properties": {
    "iso:country":"DK",
    "sg:address":"Godth\u00e5bsvej 41",
    "sg:city":"Frederiksberg",
    "sg:orig_category":"Bodegaer",
    "sg:phone":"+45 38 19 29 78",
    "sg:postcode":"2000",
    "sg:province":"Danmark",
    "wof:name":"Alhambra Pub",
    "wof:placetype":"venue"
},
  "geometry": {"coordinates":[12.5323734283,55.686630249],"type":"Point"}
}