{
  "type": "Feature",
  "properties": {
    "addr:full":"v/ Kirsten Egebjerg Andersen, Krotoften 7 Borup Danmark 4140",
    "addr:housenumber":"7",
    "addr:postcode":"4140",
    "addr:street":"Krotoften",
    "iso:country":"DK",
    "sg:address":"v/ Kirsten Egebjerg Andersen, Krotoften 7",
    "sg:city":"Borup",
    "sg:orig_category":"\u00c3\u02dcvrig fritidsundervisning",
    "sg:phone":"+45 57 52 66 99",
    "sg:postcode":"4140",
    "sg:province":"Danmark",
    "wof:name":"Kromatisk Forening i K\u00f8ge",
    "wof:placetype":"venue"
},
  "geometry": {"coordinates":[11.9749145508,55.4920845032],"type":"Point"}
}