{
  "type": "Feature",
  "properties": {
    "iso:country":"DK",
    "sg:address":"Fmd.: Kristian Hansen, Skejbyparken 362, 1. sal nr. 10",
    "sg:city":"\u00c5rhus N",
    "sg:orig_category":"Hobbybetonede foreninger",
    "sg:phone":"+45 86 78 28 41",
    "sg:postcode":"8200",
    "sg:province":"Danmark",
    "sg:website":"www.habermasforum.dk",
    "wof:name":"Habermas Forum",
    "wof:placetype":"venue"
},
  "geometry": {"coordinates":[166.9221496582,-0.5282999873],"type":"Point"}
}