{
  "type": "Feature",
  "properties": {
    "addr:full":"Ryg\u00e5rdsvej 11, Lang\u00e5 Hesselager Danmark 5874",
    "addr:housenumber":"11",
    "addr:postcode":"5874",
    "addr:street":"Rygaardsvej;Langaa",
    "iso:country":"DK",
    "sg:address":"Ryg\u00e5rdsvej 11, Lang\u00e5",
    "sg:city":"Hesselager",
    "sg:orig_category":"Forsamlingshuse",
    "sg:phone":"+45 62 25 32 45",
    "sg:postcode":"5874",
    "sg:province":"Danmark",
    "wof:name":"Lang\u00e5 Forsamlingshus",
    "wof:placetype":"venue"
},
  "geometry": {"coordinates":[10.7344398499,55.1688804626],"type":"Point"}
}