{
  "type": "Feature",
  "properties": {
    "iso:country":"DK",
    "sg:address":"Rustkammervej 10",
    "sg:city":"Sor\u00f8",
    "sg:orig_category":"Beregnere",
    "sg:phone":"+45 57 82 03 25",
    "sg:postcode":"4180",
    "sg:province":"Danmark",
    "wof:name":"K\u00e6szner Konsulentfirma, Ernst W.",
    "wof:placetype":"venue"
},
  "geometry": {"coordinates":[-102.944679,45.453472],"type":"Point"}
}