{
  "type": "Feature",
  "properties": {
    "addr:full":"B\u00f8gesvinget 65 Skovlunde Danmark 2740",
    "addr:housenumber":"65",
    "addr:postcode":"2740",
    "addr:street":"Bogesvinget",
    "iso:country":"DK",
    "sg:address":"B\u00f8gesvinget 65",
    "sg:city":"Skovlunde",
    "sg:orig_category":"Tegnere og tegnestuer",
    "sg:phone":"+45 44 91 23 55",
    "sg:postcode":"2740",
    "sg:province":"Danmark",
    "wof:name":"Moltke, A.",
    "wof:placetype":"venue"
},
  "geometry": {"coordinates":[12.4148845673,55.7143287659],"type":"Point"}
}