{
  "type": "Feature",
  "properties": {
    "addr:full":"Vestergade 44 Grindsted Danmark 7200",
    "addr:housenumber":"44",
    "addr:postcode":"7200",
    "addr:street":"Vestergade",
    "iso:country":"DK",
    "sg:address":"Vestergade 44",
    "sg:city":"Grindsted",
    "sg:orig_category":"Elektronik",
    "sg:phone":"+45 75 32 03 15",
    "sg:postcode":"7200",
    "sg:province":"Danmark",
    "wof:name":"Lauridsen & S\u00f8n, Niels",
    "wof:placetype":"venue"
},
  "geometry": {"coordinates":[8.9215192795,55.7590713501],"type":"Point"}
}