{
  "type": "Feature",
  "properties": {
    "addr:full":"Pr\u00e6sident: Gunnar Jakobsen, L\u00f8rstedvej 19, Bonderup Fjerritslev Danmark 9690",
    "addr:housenumber":"19",
    "addr:postcode":"9690",
    "addr:street":"Lorstedvej;Bonderup",
    "iso:country":"DK",
    "sg:address":"Pr\u00e6sident: Gunnar Jakobsen, L\u00f8rstedvej 19, Bonderup",
    "sg:city":"Fjerritslev",
    "sg:orig_category":"Loger",
    "sg:phone":"+45 98 21 51 15",
    "sg:postcode":"9690",
    "sg:province":"Danmark",
    "wof:name":"Hanherreds Y's mens Club",
    "wof:placetype":"venue"
},
  "geometry": {"coordinates":[9.2667350769,57.0882301331],"type":"Point"}
}