{
  "type": "Feature",
  "properties": {
    "addr:full":"Stenbrudsvej 23 Nex\u00f8 Danmark 3730",
    "addr:housenumber":"23",
    "addr:postcode":"3730",
    "addr:street":"Stenbrudsvej",
    "iso:country":"DK",
    "sg:address":"Stenbrudsvej 23",
    "sg:city":"Nex\u00f8",
    "sg:orig_category":"\u00c3\u02dcvrige institutioner",
    "sg:phone":"+45 56 49 20 04",
    "sg:postcode":"3730",
    "sg:province":"Danmark",
    "wof:name":"Nex\u00f8huset",
    "wof:placetype":"venue"
},
  "geometry": {"coordinates":[15.1398105621,55.0717353821],"type":"Point"}
}