{
  "type": "Feature",
  "properties": {
    "addr:full":"Knasten, Svenstrup Skolevej 28 Svenstrup Danmark 9230",
    "addr:housenumber":"28",
    "addr:postcode":"9230",
    "addr:street":"Knasten Svenstrup Skolevej",
    "iso:country":"DK",
    "sg:address":"Knasten, Svenstrup Skolevej 28",
    "sg:city":"Svenstrup",
    "sg:orig_category":"Legestuer",
    "sg:phone":"+45 99 31 52 90",
    "sg:postcode":"9230",
    "sg:province":"Danmark",
    "wof:name":"Svenstrup Legestue",
    "wof:placetype":"venue"
},
  "geometry": {"coordinates":[9.8465156555,56.9750328064],"type":"Point"}
}