{
  "type": "Feature",
  "properties": {
    "addr:full":"Saksk\u00f8bingvej 51 C, Herritslev Nysted Danmark 4880",
    "addr:housenumber":"51 c",
    "addr:postcode":"4880",
    "addr:street":"Sakskobingvej;Herritslev",
    "iso:country":"DK",
    "sg:address":"Saksk\u00f8bingvej 51 C, Herritslev",
    "sg:city":"Nysted",
    "sg:orig_category":"Kirker",
    "sg:postcode":"4880",
    "sg:province":"Danmark",
    "wof:name":"Herritslev Kirke",
    "wof:placetype":"venue"
},
  "geometry": {"coordinates":[11.7297554016,54.6671638489],"type":"Point"}
}