{
  "type": "Feature",
  "properties": {
    "addr:full":"Tranehusene 77 Albertslund Danmark 2620",
    "addr:housenumber":"77",
    "addr:postcode":"2620",
    "addr:street":"Tranehusene",
    "iso:country":"DK",
    "sg:address":"Tranehusene 77",
    "sg:city":"Albertslund",
    "sg:orig_category":"Sammensatte institutioner",
    "sg:phone":"+45 43 62 02 15",
    "sg:postcode":"2620",
    "sg:province":"Danmark",
    "wof:name":"Tranek\u00e6ret B\u00f8rnehus",
    "wof:placetype":"venue"
},
  "geometry": {"coordinates":[12.350528717,55.6745605469],"type":"Point"}
}