{
  "type": "Feature",
  "properties": {
    "addr:full":"Skibsbyggervej 6 B, B\u00f8nnerup Str Glesborg Danmark 8585",
    "addr:housenumber":"6 b",
    "addr:postcode":"8585",
    "addr:street":"Skibsbyggervej;Bonnerup Str Glesborg Danmark",
    "iso:country":"DK",
    "sg:address":"Skibsbyggervej 6 B, B\u00f8nnerup Str",
    "sg:city":"Glesborg",
    "sg:orig_category":"Forsamlingshuse",
    "sg:postcode":"8585",
    "sg:province":"Danmark",
    "wof:name":"B\u00f8nnerup Huset",
    "wof:placetype":"venue"
},
  "geometry": {"coordinates":[10.5884723663,56.5124320984],"type":"Point"}
}