{
  "type": "Feature",
  "properties": {
    "addr:full":"Strandhavevej 3 Hvidovre Danmark 2650",
    "addr:housenumber":"3",
    "addr:postcode":"2650",
    "addr:street":"Strandhavevej",
    "iso:country":"DK",
    "sg:address":"Strandhavevej 3",
    "sg:city":"Hvidovre",
    "sg:orig_category":"Cykler",
    "sg:phone":"+45 36 49 01 39",
    "sg:postcode":"2650",
    "sg:province":"Danmark",
    "wof:name":"Balleby Cykler",
    "wof:placetype":"venue"
},
  "geometry": {"coordinates":[12.4864902496,55.626537323],"type":"Point"}
}