{
  "type": "Feature",
  "properties": {
    "addr:full":"Toftholmv\u00e6nget 13 Skovlunde Danmark 2740",
    "addr:housenumber":"13",
    "addr:postcode":"2740",
    "addr:street":"Toftholmvaenget",
    "iso:country":"DK",
    "sg:address":"Toftholmv\u00e6nget 13",
    "sg:city":"Skovlunde",
    "sg:orig_category":"Murermestre",
    "sg:phone":"+45 40 82 19 25",
    "sg:postcode":"2740",
    "sg:province":"Danmark",
    "wof:name":"Rasmussen, Keld",
    "wof:placetype":"venue"
},
  "geometry": {"coordinates":[12.3980283737,55.7117385864],"type":"Point"}
}