{
  "type": "Feature",
  "properties": {
    "addr:full":"\u00d8stergade 7 Struer Danmark 7600",
    "addr:housenumber":"7",
    "addr:postcode":"7600",
    "addr:street":"Ostergade",
    "iso:country":"DK",
    "sg:address":"\u00d8stergade 7",
    "sg:city":"Struer",
    "sg:orig_category":"Dag- og distriktsblade",
    "sg:phone":"+45 96 84 22 00",
    "sg:postcode":"7600",
    "sg:province":"Danmark",
    "wof:name":"Dagbladet Holstebro - Struer",
    "wof:placetype":"venue"
},
  "geometry": {"coordinates":[8.5930690765,56.4922637939],"type":"Point"}
}