{
  "type": "Feature",
  "properties": {
    "addr:full":"Industrivej 28 Roskilde Danmark 4000",
    "addr:housenumber":"28",
    "addr:postcode":"4000",
    "addr:street":"Industrivej",
    "iso:country":"DK",
    "sg:address":"Industrivej 28",
    "sg:city":"Roskilde",
    "sg:orig_category":"Posthuse",
    "sg:phone":"+45 70 12 40 00",
    "sg:postcode":"4000",
    "sg:province":"Danmark",
    "wof:name":"Post Danmark, Roskilde \u00d8st Posthus",
    "wof:placetype":"venue"
},
  "geometry": {"coordinates":[12.1227550507,55.64427948],"type":"Point"}
}