{
  "type": "Feature",
  "properties": {
    "iso:country":"DK",
    "sg:address":"N\u00f8rregade 51",
    "sg:city":"Holstebro",
    "sg:orig_category":"Apoteker og -udsalg",
    "sg:phone":"+45 97 42 22 22",
    "sg:postcode":"7500",
    "sg:province":"Danmark",
    "wof:name":"Svaneapoteket",
    "wof:placetype":"venue"
},
  "geometry": {"coordinates":[8.6186857224,56.3618049622],"type":"Point"}
}