{
  "type": "Feature",
  "properties": {
    "addr:full":"v/ J\u00f8rn Lauge Pedersen, S\u00f8lvgade 24, 4. tv. K\u00f8benhavn Danmark 1307",
    "addr:housenumber":"24 4 tv.;1307",
    "addr:street":"Lauge;Solvgade",
    "iso:country":"DK",
    "sg:address":"v/ J\u00f8rn Lauge Pedersen, S\u00f8lvgade 24, 4. tv.",
    "sg:city":"K\u00f8benhavn",
    "sg:orig_category":"Musik og sang",
    "sg:phone":"+45 33 15 45 99",
    "sg:postcode":"1307",
    "sg:province":"Danmark",
    "wof:name":"S\u00f8borg Harmoniorkester",
    "wof:placetype":"venue"
},
  "geometry": {"coordinates":[-36.775188446,-5.9064798355],"type":"Point"}
}