{
  "type": "Feature",
  "properties": {
    "addr:full":"Adelgade 78 Skanderborg Danmark 8660",
    "addr:housenumber":"78",
    "addr:postcode":"8660",
    "addr:street":"Adelgade",
    "iso:country":"DK",
    "sg:address":"Adelgade 78",
    "sg:city":"Skanderborg",
    "sg:classifiers":[
        {
            "category":"Banks & Credit Unions",
            "subcategory":"Bank",
            "type":"Services"
        }
    ],
    "sg:phone":"+45 87 93 25 00",
    "sg:postcode":"8660",
    "sg:province":"Danmark",
    "sg:tags":[
        "banker"
    ],
    "wof:name":"BG Bank",
    "wof:placetype":"venue"
},
  "geometry": {"coordinates":[9.9320688248,56.0341110229],"type":"Point"}
}