{
  "type": "Feature",
  "properties": {
    "addr:full":"Holsted Park 15 A 2 sal N\u00e6stved Danmark 4700",
    "addr:housenumber":"15 a 2",
    "addr:postcode":"4700",
    "addr:street":"Holsted Park",
    "iso:country":"DK",
    "sg:address":"Holsted Park 15 A 2 sal",
    "sg:city":"N\u00e6stved",
    "sg:orig_category":"Informationsformidling",
    "sg:phone":"+45 55 73 20 00",
    "sg:postcode":"4700",
    "sg:province":"Danmark",
    "sg:website":"www.bygge-dias.dk",
    "wof:name":"BYGGE-DIAS, Dansk Bygge Oplysning Aps.",
    "wof:placetype":"venue"
},
  "geometry": {"coordinates":[11.7542486191,55.2315444946],"type":"Point"}
}