{
  "type": "Feature",
  "properties": {
    "addr:full":"Parkvej 101 Gilleleje Danmark 3250",
    "addr:housenumber":"101",
    "addr:postcode":"3250",
    "addr:street":"Parkvej",
    "iso:country":"DK",
    "sg:address":"Parkvej 101",
    "sg:city":"Gilleleje",
    "sg:orig_category":"Kommunale ungdomsskoler",
    "sg:phone":"+45 48 30 15 62",
    "sg:postcode":"3250",
    "sg:province":"Danmark",
    "wof:name":"Gr\u00e6sted-Gilleleje ungdomsskole",
    "wof:placetype":"venue"
},
  "geometry": {"coordinates":[12.3067140579,56.1167678833],"type":"Point"}
}