{
  "type": "Feature",
  "properties": {
    "addr:full":"Tinggade 4 Hadsund Danmark 9560",
    "addr:housenumber":"4",
    "addr:postcode":"9560",
    "addr:street":"Tinggade",
    "iso:country":"DK",
    "sg:address":"Tinggade 4",
    "sg:city":"Hadsund",
    "sg:orig_category":"Politi",
    "sg:phone":"+45 98 57 17 11",
    "sg:postcode":"9560",
    "sg:province":"Danmark",
    "wof:name":"Landpolitiet i Hadsund",
    "wof:placetype":"venue"
},
  "geometry": {"coordinates":[10.1167469025,56.7180099487],"type":"Point"}
}