{
  "type": "Feature",
  "properties": {
    "addr:full":"Smedemestervej 2 Faaborg Danmark 5600",
    "addr:housenumber":"2",
    "addr:postcode":"5600",
    "addr:street":"Smedemestervej",
    "iso:country":"DK",
    "sg:address":"Smedemestervej 2",
    "sg:city":"Faaborg",
    "sg:orig_category":"Autoforhandlere",
    "sg:phone":"+45 62 61 95 88",
    "sg:postcode":"5600",
    "sg:province":"Danmark",
    "wof:name":"M\u00f8llegaard Biler",
    "wof:placetype":"venue"
},
  "geometry": {"coordinates":[10.2325439453,55.108959198],"type":"Point"}
}