{
  "type": "Feature",
  "properties": {
    "addr:full":"B\u00f8nfeltvej 29, Tisted Arden Danmark 9510",
    "addr:housenumber":"29",
    "addr:postcode":"9510",
    "addr:street":"Bonfeltvej;Tisted;Danmark",
    "iso:country":"DK",
    "sg:address":"B\u00f8nfeltvej 29, Tisted",
    "sg:city":"Arden",
    "sg:orig_category":"Tegnere og tegnestuer",
    "sg:phone":"+45 98 56 55 75",
    "sg:postcode":"9510",
    "sg:province":"Danmark",
    "sg:website":"www.gn-tegneservice.dk",
    "wof:name":"GN Tegneservice",
    "wof:placetype":"venue"
},
  "geometry": {"coordinates":[9.8580989838,56.7683296204],"type":"Point"}
}