{
  "type": "Feature",
  "properties": {
    "iso:country":"DK",
    "sg:address":"Industrim\u00e6rsken 2, Vemmelev",
    "sg:city":"Vemmelev",
    "sg:orig_category":"Jordrensning",
    "sg:phone":"+45 58 38 32 94",
    "sg:postcode":"4241",
    "sg:province":"Danmark",
    "sg:website":"www.dsv.dk",
    "wof:name":"Dansk Jordrens A/S",
    "wof:placetype":"venue"
},
  "geometry": {"coordinates":[11.2580623627,55.363407135],"type":"Point"}
}