{
  "type": "Feature",
  "properties": {
    "addr:full":"Borgergade 22 Horsens Danmark 8700",
    "addr:housenumber":"22",
    "addr:postcode":"8700",
    "addr:street":"Borgergade",
    "iso:country":"DK",
    "sg:address":"Borgergade 22",
    "sg:city":"Horsens",
    "sg:orig_category":"Renserier",
    "sg:phone":"+45 75 62 52 28",
    "sg:postcode":"8700",
    "sg:province":"Danmark",
    "wof:name":"Pressejernet",
    "wof:placetype":"venue"
},
  "geometry": {"coordinates":[9.8550167084,55.861289978],"type":"Point"}
}