{
  "type": "Feature",
  "properties": {
    "addr:full":"S\u00f8ndre Ringvej 12 Hobro Danmark 9500",
    "addr:housenumber":"12",
    "addr:postcode":"9500",
    "addr:street":"Sondre Ringvej",
    "iso:country":"DK",
    "sg:address":"S\u00f8ndre Ringvej 12",
    "sg:city":"Hobro",
    "sg:orig_category":"Supermarkeder",
    "sg:phone":"+45 98 52 29 00",
    "sg:postcode":"9500",
    "sg:province":"Danmark",
    "wof:name":"SuperBest I/S",
    "wof:placetype":"venue"
},
  "geometry": {"coordinates":[9.8045282364,56.6277923584],"type":"Point"}
}