{
  "type": "Feature",
  "properties": {
    "addr:full":"Frederiksdalsvej 76 A Virum Danmark 2830",
    "addr:housenumber":"76 a",
    "addr:postcode":"2830",
    "addr:street":"Frederiksdalsvej",
    "iso:country":"DK",
    "sg:address":"Frederiksdalsvej 76 A",
    "sg:city":"Virum",
    "sg:orig_category":"Malermestre",
    "sg:phone":"+45 45 85 42 92",
    "sg:postcode":"2830",
    "sg:province":"Danmark",
    "wof:name":"Wager, John",
    "wof:placetype":"venue"
},
  "geometry": {"coordinates":[12.4709186554,55.7953414917],"type":"Point"}
}