{
  "type": "Feature",
  "properties": {
    "addr:full":"Storgade 28 Sor\u00f8 Danmark 4180",
    "addr:housenumber":"28",
    "addr:postcode":"4180",
    "addr:street":"Storgade",
    "iso:country":"DK",
    "sg:address":"Storgade 28",
    "sg:city":"Sor\u00f8",
    "sg:orig_category":"Pengeinstitutter",
    "sg:phone":"+45 57 86 02 00",
    "sg:postcode":"4180",
    "sg:province":"Danmark",
    "sg:website":"www.danskebank.dk",
    "wof:name":"Danske Bank",
    "wof:placetype":"venue"
},
  "geometry": {"coordinates":[-102.94467926030001,45.4534721375],"type":"Point"}
}