{
  "type": "Feature",
  "properties": {
    "addr:full":"Jagtvej 61 K\u00f8benhavn N Danmark 2200",
    "addr:housenumber":"61",
    "addr:postcode":"2200",
    "addr:street":"Jagtvej;Kobenhavn N Danmark",
    "iso:country":"DK",
    "sg:address":"Jagtvej 61",
    "sg:city":"K\u00f8benhavn N",
    "sg:orig_category":"Dyreklinikker og -hospitaler",
    "sg:phone":"+45 35 83 84 72",
    "sg:postcode":"2200",
    "sg:province":"Danmark",
    "wof:name":"Jagtvejens Dyreklinik",
    "wof:placetype":"venue"
},
  "geometry": {"coordinates":[-76.4168395996,37.452419281],"type":"Point"}
}