{
  "type": "Feature",
  "properties": {
    "addr:full":"Hovedvejen 112 Glostrup Danmark 2600",
    "addr:housenumber":"112",
    "addr:postcode":"2600",
    "addr:street":"Hovedvejen",
    "iso:country":"DK",
    "sg:address":"Hovedvejen 112",
    "sg:city":"Glostrup",
    "sg:orig_category":"Forsikringer",
    "sg:phone":"+45 70 11 25 25",
    "sg:postcode":"2600",
    "sg:province":"Danmark",
    "wof:name":"Danica Pension",
    "wof:placetype":"venue"
},
  "geometry": {"coordinates":[12.3984050751,55.6661300659],"type":"Point"}
}