{
  "type": "Feature",
  "properties": {
    "iso:country":"DK",
    "sg:address":"Gormsgade 8",
    "sg:city":"Vejle",
    "sg:orig_category":"Zoneterapeuter",
    "sg:phone":"+45 75 72 02 55",
    "sg:postcode":"7100",
    "sg:province":"Danmark",
    "wof:name":"Svingel, Maria",
    "wof:placetype":"venue"
},
  "geometry": {"coordinates":[9.5365390778,55.7147598267],"type":"Point"}
}