{
  "type": "Feature",
  "properties": {
    "addr:full":"Skads Byvej 94 Esbjerg \u00d8 Danmark 6705",
    "addr:housenumber":"94",
    "addr:postcode":"6705",
    "addr:street":"Skads Byvej;Danmark",
    "iso:country":"DK",
    "sg:address":"Skads Byvej 94",
    "sg:city":"Esbjerg \u00d8",
    "sg:orig_category":"Porte",
    "sg:phone":"+45 75 16 05 67",
    "sg:postcode":"6705",
    "sg:province":"Danmark",
    "wof:name":"Dansk Port Service",
    "wof:placetype":"venue"
},
  "geometry": {"coordinates":[8.5688381195,55.5166854858],"type":"Point"}
}