{
  "type": "Feature",
  "properties": {
    "addr:full":"v/ Morten Krogager-Nielsen, Gr\u00f8ndalvej 17, Nr. Hvidbjerg Thyholm Danmark 7790",
    "addr:housenumber":"17",
    "addr:postcode":"7790",
    "addr:street":"Grondalvej",
    "iso:country":"DK",
    "sg:address":"v/ Morten Krogager-Nielsen, Gr\u00f8ndalvej 17, Nr. Hvidbjerg",
    "sg:city":"Thyholm",
    "sg:orig_category":"Hobbybetonede foreninger",
    "sg:phone":"+45 97 87 20 29",
    "sg:postcode":"7790",
    "sg:province":"Danmark",
    "wof:name":"Dansk Landrover Klub, Region Vestjylland",
    "wof:placetype":"venue"
},
  "geometry": {"coordinates":[8.525765419,56.6507072449],"type":"Point"}
}