{
  "type": "Feature",
  "properties": {
    "addr:full":"Dommerv\u00e6nget 14 A Roskilde Danmark 4000",
    "addr:housenumber":"14 a",
    "addr:postcode":"4000",
    "addr:street":"Dommervaenget",
    "iso:country":"DK",
    "sg:address":"Dommerv\u00e6nget 14 A",
    "sg:city":"Roskilde",
    "sg:orig_category":"Databehandling",
    "sg:phone":"+45 46 35 80 07",
    "sg:postcode":"4000",
    "sg:province":"Danmark",
    "wof:name":"TH Data",
    "wof:placetype":"venue"
},
  "geometry": {"coordinates":[12.0909376144,55.6404838562],"type":"Point"}
}