{
  "type": "Feature",
  "properties": {
    "iso:country":"DK",
    "sg:address":"Mulvadvej 59",
    "sg:city":"Bramming",
    "sg:orig_category":"Malermestre",
    "sg:phone":"+45 75 10 10 60",
    "sg:postcode":"6740",
    "sg:province":"Danmark",
    "sg:website":"www.p-e-rasmussen.dk",
    "wof:name":"Rasmussen Aps, Malerfirmaet Poul Erik",
    "wof:placetype":"venue"
},
  "geometry": {"coordinates":[8.6877727509,55.456199646],"type":"Point"}
}