{
  "type": "Feature",
  "properties": {
    "addr:full":"\u00c5rhus Hovedbaneg\u00e5rd, Ny Baneg\u00e5rdsgade 48 \u00c5rhus C Danmark 8000",
    "addr:housenumber":"48",
    "addr:postcode":"8000",
    "addr:street":"Banegaardsgade",
    "iso:country":"DK",
    "sg:address":"\u00c5rhus Hovedbaneg\u00e5rd, Ny Baneg\u00e5rdsgade 48",
    "sg:city":"\u00c5rhus C",
    "sg:orig_category":"Kiosker",
    "sg:phone":"+45 86 12 76 43",
    "sg:postcode":"8000",
    "sg:province":"Danmark",
    "wof:name":"DSB Kiosken",
    "wof:placetype":"venue"
},
  "geometry": {"coordinates":[-76.50189208979999,42.8563194275],"type":"Point"}
}