{
  "type": "Feature",
  "properties": {
    "addr:full":"Fmd.: Anette Vollesen, Tirslund Sognevej 14 Toftlund Danmark 6520",
    "addr:housenumber":"14",
    "addr:postcode":"6520",
    "addr:street":"Tirslund Sognevej",
    "iso:country":"DK",
    "sg:address":"Fmd.: Anette Vollesen, Tirslund Sognevej 14",
    "sg:city":"Toftlund",
    "sg:orig_category":"Legestuer",
    "sg:phone":"+45 74 83 26 28",
    "sg:postcode":"6520",
    "sg:province":"Danmark",
    "wof:name":"Toftlund Legestue",
    "wof:placetype":"venue"
},
  "geometry": {"coordinates":[9.0629367828,55.1926651001],"type":"Point"}
}