{
  "type": "Feature",
  "properties": {
    "iso:country":"DK",
    "sg:address":"\u00d8stervej 7, Harte",
    "sg:city":"Kolding",
    "sg:orig_category":"Reklamebureauer",
    "sg:phone":"+45 75 50 14 48",
    "sg:postcode":"6000",
    "sg:province":"Danmark",
    "wof:name":"MTC Grafisk",
    "wof:placetype":"venue"
},
  "geometry": {"coordinates":[9.4733953476,55.4863586426],"type":"Point"}
}