{
  "type": "Feature",
  "properties": {
    "addr:full":"Svendsgade 21 Odense C Danmark 5000",
    "addr:housenumber":"21",
    "addr:postcode":"5000",
    "addr:street":"Svendsgade",
    "iso:country":"DK",
    "sg:address":"Svendsgade 21",
    "sg:city":"Odense C",
    "sg:orig_category":"Botilbud",
    "sg:phone":"+45 66 12 24 11",
    "sg:postcode":"5000",
    "sg:province":"Danmark",
    "wof:name":"KFUM's beskyttede pensionat \u00c5g\u00e5rden",
    "wof:placetype":"venue"
},
  "geometry": {"coordinates":[10.4144382477,55.3961181641],"type":"Point"}
}