{
  "type": "Feature",
  "properties": {
    "addr:full":"Tallerupvej 17, Tommerup St Tommerup Danmark 5690",
    "addr:housenumber":"17",
    "addr:postcode":"5690",
    "addr:street":"Tallerupvej;St",
    "iso:country":"DK",
    "sg:address":"Tallerupvej 17, Tommerup St",
    "sg:city":"Tommerup",
    "sg:orig_category":"Pizzeriaer",
    "sg:phone":"+45 64 76 13 18",
    "sg:postcode":"5690",
    "sg:province":"Danmark",
    "wof:name":"Sivas Pizzaria",
    "wof:placetype":"venue"
},
  "geometry": {"coordinates":[10.2489509583,55.3236503601],"type":"Point"}
}