{
  "type": "Feature",
  "properties": {
    "addr:full":"Kirkestien 4 Ryslinge Danmark 5856",
    "addr:housenumber":"4",
    "addr:postcode":"5856",
    "addr:street":"Kirkestien",
    "iso:country":"DK",
    "sg:address":"Kirkestien 4",
    "sg:city":"Ryslinge",
    "sg:orig_category":"Spejderkorps",
    "sg:postcode":"5856",
    "sg:province":"Danmark",
    "wof:name":"FDF/FPF, Ryslinge",
    "wof:placetype":"venue"
},
  "geometry": {"coordinates":[10.5372467041,55.242477417],"type":"Point"}
}