{
  "type": "Feature",
  "properties": {
    "addr:full":"Karlemosevej 48 K\u00f8ge Danmark 4600",
    "addr:housenumber":"48",
    "addr:postcode":"4600",
    "addr:street":"Karlemosevej",
    "iso:country":"DK",
    "sg:address":"Karlemosevej 48",
    "sg:city":"K\u00f8ge",
    "sg:orig_category":"Integrerede institutioner",
    "sg:phone":"+45 56 65 72 62",
    "sg:postcode":"4600",
    "sg:province":"Danmark",
    "wof:name":"Kernehuset",
    "wof:placetype":"venue"
},
  "geometry": {"coordinates":[12.1695289612,55.4823646545],"type":"Point"}
}