{
  "type": "Feature",
  "properties": {
    "iso:country":"DK",
    "sg:address":"Valdemar Sejrs Vej 6",
    "sg:city":"Holb\u00e6k",
    "sg:orig_category":"Benzinstationer",
    "sg:phone":"+45 59 43 13 90",
    "sg:postcode":"4300",
    "sg:province":"Danmark",
    "wof:name":"Shell",
    "wof:placetype":"venue"
},
  "geometry": {"coordinates":[11.705961,55.71743],"type":"Point"}
}