{
  "type": "Feature",
  "properties": {
    "addr:full":"Lyngevej 1, Nr. Herlev Hiller\u00f8d Danmark 3400",
    "addr:housenumber":"1",
    "addr:postcode":"3400",
    "addr:street":"Lyngevej",
    "iso:country":"DK",
    "sg:address":"Lyngevej 1, Nr. Herlev",
    "sg:city":"Hiller\u00f8d",
    "sg:orig_category":"Snedkermestre",
    "sg:phone":"+45 48 24 75 28",
    "sg:postcode":"3400",
    "sg:province":"Danmark",
    "wof:name":"H\u00e5ndv\u00e6rkshj\u00e6lpen ApS",
    "wof:placetype":"venue"
},
  "geometry": {"coordinates":[12.3056097031,55.9288215637],"type":"Point"}
}