{
  "type": "Feature",
  "properties": {
    "addr:full":"Houmarksvej 14, \u00c5strup Juelsminde Danmark 7130",
    "addr:housenumber":"14",
    "addr:postcode":"7130",
    "addr:street":"Houmarksvej;Aastrup",
    "iso:country":"DK",
    "sg:address":"Houmarksvej 14, \u00c5strup",
    "sg:city":"Juelsminde",
    "sg:orig_category":"Alternativ behandling",
    "sg:phone":"+45 75 68 56 65",
    "sg:postcode":"7130",
    "sg:province":"Danmark",
    "wof:name":"Hansen, Gitte-Connie",
    "wof:placetype":"venue"
},
  "geometry": {"coordinates":[10.0143985748,55.7135848999],"type":"Point"}
}