{
  "type": "Feature",
  "properties": {
    "addr:full":"Att.: Jette Skovbjerg, Vesterled 30 Janderup Danmark 6851",
    "addr:housenumber":"30",
    "addr:postcode":"6851",
    "addr:street":"Att.;Vesterled",
    "iso:country":"DK",
    "sg:address":"Att.: Jette Skovbjerg, Vesterled 30",
    "sg:city":"Janderup",
    "sg:orig_category":"Posthuse",
    "sg:phone":"+45 75 25 80 03",
    "sg:postcode":"6851",
    "sg:province":"Danmark",
    "wof:name":"Post Danmark, Postomr\u00e5de Esbjerg,Janderup postbutik",
    "wof:placetype":"venue"
},
  "geometry": {"coordinates":[8.3593254089,55.6500740051],"type":"Point"}
}