{
  "type": "Feature",
  "properties": {
    "iso:country":"DK",
    "sg:address":"Langelinie 40",
    "sg:city":"Vejle",
    "sg:orig_category":"Genbrugsbutikker",
    "sg:postcode":"7100",
    "sg:province":"Danmark",
    "wof:name":"Folkekirkens N\u00f8dhj\u00e6lp",
    "wof:placetype":"venue"
},
  "geometry": {"coordinates":[9.5413503647,55.7094764709],"type":"Point"}
}