{
  "type": "Feature",
  "properties": {
    "addr:full":"Benediktevej 22 Fredensborg Danmark 3480",
    "addr:housenumber":"22",
    "addr:postcode":"3480",
    "addr:street":"Benediktevej",
    "iso:country":"DK",
    "sg:address":"Benediktevej 22",
    "sg:city":"Fredensborg",
    "sg:orig_category":"Kontormaskineservice",
    "sg:phone":"+45 48 48 26 19",
    "sg:postcode":"3480",
    "sg:province":"Danmark",
    "wof:name":"CenterService",
    "wof:placetype":"venue"
},
  "geometry": {"coordinates":[12.4074363708,55.9731864929],"type":"Point"}
}