{
  "type": "Feature",
  "properties": {
    "addr:full":"Svanekevej 42, \u00d8stermarie Svaneke Danmark 3740",
    "addr:housenumber":"42",
    "addr:postcode":"3740",
    "addr:street":"Svanekevej",
    "iso:country":"DK",
    "sg:address":"Svanekevej 42, \u00d8stermarie",
    "sg:city":"Svaneke",
    "sg:orig_category":"Reklamebureauer",
    "sg:phone":"+45 56 44 33 33",
    "sg:postcode":"3740",
    "sg:province":"Danmark",
    "wof:name":"Baltisk Bureau ApS",
    "wof:placetype":"venue"
},
  "geometry": {"coordinates":[15.140504837,55.1364555359],"type":"Point"}
}