{
  "type": "Feature",
  "properties": {
    "addr:full":"Humlestien 16, Tune Roskilde Danmark 4000",
    "addr:housenumber":"16",
    "addr:postcode":"4000",
    "addr:street":"Humlestien",
    "iso:country":"DK",
    "sg:address":"Humlestien 16, Tune",
    "sg:city":"Roskilde",
    "sg:orig_category":"Glarmestre og glarmagere",
    "sg:phone":"+45 46 13 63 42",
    "sg:postcode":"4000",
    "sg:province":"Danmark",
    "sg:website":"www.dancarlsson.dk",
    "wof:name":"Carlsson, Dan",
    "wof:placetype":"venue"
},
  "geometry": {"coordinates":[12.0909376144,55.6404838562],"type":"Point"}
}