{
  "type": "Feature",
  "properties": {
    "iso:country":"DK",
    "sg:address":"Jupitervej 26, Uglev",
    "sg:city":"Thyholm",
    "sg:orig_category":"Kommunale folkeskoler",
    "sg:phone":"+45 97 87 50 09",
    "sg:postcode":"7790",
    "sg:province":"Danmark",
    "sg:website":"www.thyholm.dk",
    "wof:name":"Odby Skole",
    "wof:placetype":"venue"
},
  "geometry": {"coordinates":[8.525765419,56.6507072449],"type":"Point"}
}