{
  "type": "Feature",
  "properties": {
    "iso:country":"DK",
    "sg:address":"Stationsvej 17",
    "sg:city":"Ejstrupholm",
    "sg:orig_category":"Rutebiler",
    "sg:postcode":"7361",
    "sg:province":"Danmark",
    "wof:name":"Ejstrupholm Rutebilstation",
    "wof:placetype":"venue"
},
  "geometry": {"coordinates":[9.2911186218,55.9820671082],"type":"Point"}
}