{
  "type": "Feature",
  "properties": {
    "addr:full":"Vindingvej 115 Vejle Danmark 7100",
    "addr:housenumber":"115",
    "addr:postcode":"7100",
    "addr:street":"Vindingvej",
    "iso:country":"DK",
    "sg:address":"Vindingvej 115",
    "sg:city":"Vejle",
    "sg:orig_category":"Autovask",
    "sg:phone":"+45 75 85 88 22",
    "sg:postcode":"7100",
    "sg:province":"Danmark",
    "wof:name":"Arklow A/S",
    "wof:placetype":"venue"
},
  "geometry": {"coordinates":[9.5754404068,55.6703109741],"type":"Point"}
}