{
  "type": "Feature",
  "properties": {
    "addr:full":"Dr. Louises Alle 1 Fredensborg Danmark 3480",
    "addr:housenumber":"1",
    "addr:postcode":"3480",
    "addr:street":"Louises Alle",
    "iso:country":"DK",
    "sg:address":"Dr. Louises Alle 1",
    "sg:city":"Fredensborg",
    "sg:orig_category":"Arkitekter",
    "sg:phone":"+45 48 48 31 70",
    "sg:postcode":"3480",
    "sg:province":"Danmark",
    "wof:name":"D-84 Byggeadministration ApS",
    "wof:placetype":"venue"
},
  "geometry": {"coordinates":[12.4044466019,55.9796257019],"type":"Point"}
}