{
  "type": "Feature",
  "properties": {
    "addr:full":"Fmd.: Alma Kolditz Hansen, Skolegade 10, Assens Mariager Danmark 9550",
    "addr:housenumber":"10",
    "addr:postcode":"9550",
    "addr:street":"Skolegade",
    "iso:country":"DK",
    "sg:address":"Fmd.: Alma Kolditz Hansen, Skolegade 10, Assens",
    "sg:city":"Mariager",
    "sg:orig_category":"\u00c3\u2020ldreorganisationer og klubber",
    "sg:phone":"+45 98 58 31 11",
    "sg:postcode":"9550",
    "sg:province":"Danmark",
    "wof:name":"Assens Pensionistforening",
    "wof:placetype":"venue"
},
  "geometry": {"coordinates":[10.0618648529,56.676902771],"type":"Point"}
}