{
  "type": "Feature",
  "properties": {
    "iso:country":"DK",
    "sg:address":"Br\u00e5dalvej 80",
    "sg:city":"Gistrup",
    "sg:orig_category":"Legestuer",
    "sg:phone":"+45 99 31 52 90",
    "sg:postcode":"9260",
    "sg:province":"Danmark",
    "wof:name":"N\u00f8vling Legestue",
    "wof:placetype":"venue"
},
  "geometry": {"coordinates":[9.9558496475,56.9736824036],"type":"Point"}
}