{
  "type": "Feature",
  "properties": {
    "addr:full":"Wichmandsgade 15, Postboks 50 5100",
    "addr:housenumber":"15;50",
    "addr:postcode":"5100",
    "addr:street":"Wichmandsgade",
    "iso:country":"DK",
    "sg:address":"Wichmandsgade 15, Postboks 50",
    "sg:orig_category":"Arbejderbeskyttelse",
    "sg:phone":"+45 66 11 70 30",
    "sg:postcode":"5100",
    "wof:name":"N\u00f8rgaard's Eftf. A/S, C.",
    "wof:placetype":"venue"
},
  "geometry": {"coordinates":[10.3908996582,55.3960914612],"type":"Point"}
}