{
  "type": "Feature",
  "properties": {
    "addr:full":"Fmd.: J\u00f8rgen Dahl Pedersen, Viborgvej 2 Skive Danmark 7800",
    "addr:housenumber":"2",
    "addr:postcode":"7800",
    "addr:street":"Viborgvej",
    "iso:country":"DK",
    "sg:address":"Fmd.: J\u00f8rgen Dahl Pedersen, Viborgvej 2",
    "sg:city":"Skive",
    "sg:orig_category":"Faglige organisationer og foreninger",
    "sg:phone":"+45 97 52 25 55",
    "sg:postcode":"7800",
    "sg:province":"Danmark",
    "wof:name":"Automobilhandlerforeningen",
    "wof:placetype":"venue"
},
  "geometry": {"coordinates":[9.0320358276,56.5666427612],"type":"Point"}
}