{
  "type": "Feature",
  "properties": {
    "addr:full":"Degnestr\u00e6de 1 Greve Danmark 2670",
    "addr:housenumber":"1",
    "addr:postcode":"2670",
    "addr:street":"Degnestraede",
    "iso:country":"DK",
    "sg:address":"Degnestr\u00e6de 1",
    "sg:city":"Greve",
    "sg:orig_category":"Plejecentre",
    "sg:phone":"+45 43 41 50 00",
    "sg:postcode":"2670",
    "sg:province":"Danmark",
    "wof:name":"Hedebo, Plejecentret",
    "wof:placetype":"venue"
},
  "geometry": {"coordinates":[12.2941808701,55.5844078064],"type":"Point"}
}