{
  "type": "Feature",
  "properties": {
    "addr:full":"N\u00f8rrebrogade 39 K\u00f8benhavn N Danmark 2200",
    "addr:housenumber":"39",
    "addr:postcode":"2200",
    "addr:street":"Norrebrogade;Kobenhavn N Danmark",
    "iso:country":"DK",
    "sg:address":"N\u00f8rrebrogade 39",
    "sg:city":"K\u00f8benhavn N",
    "sg:orig_category":"Boghandlere",
    "sg:phone":"+45 35 35 29 18",
    "sg:postcode":"2200",
    "sg:province":"Danmark",
    "wof:name":"Tidens Boghandel",
    "wof:placetype":"venue"
},
  "geometry": {"coordinates":[-76.4168395996,37.452419281],"type":"Point"}
}