{
  "type": "Feature",
  "properties": {
    "iso:country":"DK",
    "sg:address":"Rantzausgade 47",
    "sg:city":"Aalborg",
    "sg:orig_category":"EDB - udstyr",
    "sg:phone":"+45 98 10 33 01",
    "sg:postcode":"9000",
    "sg:province":"Danmark",
    "wof:name":"Computershoppen ApS, Datafirmaet",
    "wof:placetype":"venue"
},
  "geometry": {"coordinates":[9.9200658798,57.0426368713],"type":"Point"}
}