{
  "type": "Feature",
  "properties": {
    "addr:full":"Elektronvej 10 Greve Danmark 2670",
    "addr:housenumber":"10",
    "addr:postcode":"2670",
    "addr:street":"Elektronvej",
    "iso:country":"DK",
    "sg:address":"Elektronvej 10",
    "sg:city":"Greve",
    "sg:orig_category":"Plastvarefabrikker",
    "sg:phone":"+45 43 95 05 00",
    "sg:postcode":"2670",
    "sg:province":"Danmark",
    "sg:website":"www.thermoform.dk",
    "wof:name":"Thermoform",
    "wof:placetype":"venue"
},
  "geometry": {"coordinates":[12.3013105392,55.6059188843],"type":"Point"}
}