{
  "type": "Feature",
  "properties": {
    "addr:full":"Nybodalen 10 Holstebro Danmark 7500",
    "addr:housenumber":"10",
    "addr:postcode":"7500",
    "addr:street":"Nybodalen",
    "iso:country":"DK",
    "sg:address":"Nybodalen 10",
    "sg:city":"Holstebro",
    "sg:orig_category":"Reklamefoto",
    "sg:phone":"+45 97 40 66 44",
    "sg:postcode":"7500",
    "sg:province":"Danmark",
    "wof:name":"Prolight Reklamefoto",
    "wof:placetype":"venue"
},
  "geometry": {"coordinates":[8.6303939819,56.3424453735],"type":"Point"}
}