{
  "type": "Feature",
  "properties": {
    "addr:full":"Pr\u00e6stemarken 2 Stubbek\u00f8bing Danmark 4850",
    "addr:housenumber":"2",
    "addr:postcode":"4850",
    "addr:street":"Praestemarken",
    "iso:country":"DK",
    "sg:address":"Pr\u00e6stemarken 2",
    "sg:city":"Stubbek\u00f8bing",
    "sg:orig_category":"Revisorer",
    "sg:phone":"+45 54 44 15 03",
    "sg:postcode":"4850",
    "sg:province":"Danmark",
    "wof:name":"Revisionskontoret",
    "wof:placetype":"venue"
},
  "geometry": {"coordinates":[-102.0896530151,42.0193557739],"type":"Point"}
}