{
  "type": "Feature",
  "properties": {
    "iso:country":"DK",
    "sg:address":"Klingenberg 14",
    "sg:city":"Odense C",
    "sg:classifiers":[
        {
            "category":"Restaurant",
            "type":"Food & Drink"
        }
    ],
    "sg:phone":"+45 66 12 17 12",
    "sg:postcode":"5000",
    "sg:province":"Danmark",
    "wof:name":"Madam Lunds B\u00f8fk\u00e6lder",
    "wof:placetype":"venue"
},
  "geometry": {"coordinates":[10.3874893188,55.3952217102],"type":"Point"}
}