{
  "type": "Feature",
  "properties": {
    "addr:full":"Fmd.: Per Hermansen, Platanvej 16 Vordingborg Danmark 4760",
    "addr:housenumber":"16",
    "addr:postcode":"4760",
    "addr:street":"Platanvej",
    "iso:country":"DK",
    "sg:address":"Fmd.: Per Hermansen, Platanvej 16",
    "sg:city":"Vordingborg",
    "sg:orig_category":"Teatre",
    "sg:phone":"+45 55 34 11 01",
    "sg:postcode":"4760",
    "sg:province":"Danmark",
    "sg:website":"www.vordingborg.dk/foreninger/spektakulus.htlm",
    "wof:name":"Spektakulus, Vordingborg Amat\u00f8rscene",
    "wof:placetype":"venue"
},
  "geometry": {"coordinates":[11.9124183655,55.0085449219],"type":"Point"}
}