{
  "type": "Feature",
  "properties": {
    "addr:full":"Lyngby STORcenter 256 Kongens Lyngby Danmark 2800",
    "addr:housenumber":"256",
    "addr:postcode":"2800",
    "addr:street":"Lyngby Storcenter",
    "iso:country":"DK",
    "sg:address":"Lyngby STORcenter 256",
    "sg:city":"Kongens Lyngby",
    "sg:orig_category":"Garn",
    "sg:phone":"+45 45 87 36 33",
    "sg:postcode":"2800",
    "sg:province":"Danmark",
    "wof:name":"Princess Garn",
    "wof:placetype":"venue"
},
  "geometry": {"coordinates":[12.5368299484,55.7949905396],"type":"Point"}
}