{
  "type": "Feature",
  "properties": {
    "addr:full":"Engelsborgvej 4 Kongens Lyngby Danmark 2800",
    "addr:housenumber":"4",
    "addr:postcode":"2800",
    "addr:street":"Engelsborgvej",
    "iso:country":"DK",
    "sg:address":"Engelsborgvej 4",
    "sg:city":"Kongens Lyngby",
    "sg:orig_category":"Ure og urmagere",
    "sg:phone":"+45 45 87 49 30",
    "sg:postcode":"2800",
    "sg:province":"Danmark",
    "wof:name":"Nils Kuni's Eftf.",
    "wof:placetype":"venue"
},
  "geometry": {"coordinates":[12.5006465912,55.7674026489],"type":"Point"}
}