{
  "type": "Feature",
  "properties": {
    "addr:full":"Kalkv\u00e6rksvej 4, Postboks 117 Frederikshavn Danmark 9900",
    "addr:housenumber":"4;117",
    "addr:postcode":"9900",
    "addr:street":"Kalkvaerksvej",
    "iso:country":"DK",
    "sg:address":"Kalkv\u00e6rksvej 4, Postboks 117",
    "sg:city":"Frederikshavn",
    "sg:orig_category":"Boligselskaber",
    "sg:phone":"+45 96 20 19 45",
    "sg:postcode":"9900",
    "sg:province":"Danmark",
    "sg:website":"www.frh-boligforening.dk",
    "wof:name":"Frederikshavns Boligforening af 1945",
    "wof:placetype":"venue"
},
  "geometry": {"coordinates":[10.5362997055,57.4396400452],"type":"Point"}
}