{
  "type": "Feature",
  "properties": {
    "addr:full":"Nederballe 2, Brandsb\u00f8l Nordborg Danmark 6430",
    "addr:housenumber":"2",
    "addr:postcode":"6430",
    "addr:street":"Nederballe;Brandsbol",
    "iso:country":"DK",
    "sg:address":"Nederballe 2, Brandsb\u00f8l",
    "sg:city":"Nordborg",
    "sg:orig_category":"Antikviteter",
    "sg:phone":"+45 74 45 60 15",
    "sg:postcode":"6430",
    "sg:province":"Danmark",
    "wof:name":"Loppehuset",
    "wof:placetype":"venue"
},
  "geometry": {"coordinates":[9.7496232986,55.0542755127],"type":"Point"}
}