{
  "type": "Feature",
  "properties": {
    "addr:full":"Vinkelvej 8 Slangerup Danmark 3550",
    "addr:housenumber":"8",
    "addr:postcode":"3550",
    "addr:street":"Vinkelvej",
    "iso:country":"DK",
    "sg:address":"Vinkelvej 8",
    "sg:city":"Slangerup",
    "sg:classifiers":[
        {
            "category":"Personal",
            "subcategory":"Massage",
            "type":"Services"
        }
    ],
    "sg:phone":"+45 47 33 58 98",
    "sg:postcode":"3550",
    "sg:province":"Danmark",
    "wof:name":"Johansen, Tina Hee",
    "wof:placetype":"venue"
},
  "geometry": {"coordinates":[12.1843709946,55.842880249],"type":"Point"}
}