{
  "type": "Feature",
  "properties": {
    "iso:country":"DK",
    "sg:address":"Michael Drewsens Vej 1 PB 1809 ",
    "sg:city":"H\u00f8jbjerg",
    "sg:classifiers":[
        {
            "category":"Wholesale",
            "subcategory":"Drugs",
            "type":"Manufacturing & Wholesale Goods"
        }
    ],
    "sg:phone":"+45 70 22 05 55",
    "sg:postcode":"8270",
    "sg:province":"Danmark",
    "sg:tags":[
        "chemical",
        "pharmaceutical"
    ],
    "wof:name":"SUN CHEMICAL HARTMANN A/S",
    "wof:placetype":"venue"
},
  "geometry": {"coordinates":[10.2088699341,56.1132011414],"type":"Point"}
}