{
  "type": "Feature",
  "properties": {
    "addr:full":"Kolind Midtpunkt 7 - 9, Kolind Kolind Danmark 8560",
    "addr:housenumber":"7 9",
    "addr:postcode":"8560",
    "addr:street":"Kolind Midtpunkt",
    "iso:country":"DK",
    "sg:address":"Kolind Midtpunkt 7 - 9, Kolind",
    "sg:city":"Kolind",
    "sg:orig_category":"Sportsartikler",
    "sg:phone":"+45 86 39 27 44",
    "sg:postcode":"8560",
    "sg:province":"Danmark",
    "wof:name":"Sport 1",
    "wof:placetype":"venue"
},
  "geometry": {"coordinates":[10.5873975754,56.3618812561],"type":"Point"}
}