{
  "type": "Feature",
  "properties": {
    "addr:full":"Fmd.: Peer Mogensen, Orupgade 20, Orup Fakse Danmark 4640",
    "addr:housenumber":"20",
    "addr:postcode":"4640",
    "addr:street":"Orupgade",
    "iso:country":"DK",
    "sg:address":"Fmd.: Peer Mogensen, Orupgade 20, Orup",
    "sg:city":"Fakse",
    "sg:orig_category":"Soldaterforeninger",
    "sg:phone":"+45 56 72 52 45",
    "sg:postcode":"4640",
    "sg:province":"Danmark",
    "wof:name":"Fakse Hjemmev\u00e6rnsforening",
    "wof:placetype":"venue"
},
  "geometry": {"coordinates":[12.1203422546,55.2574195862],"type":"Point"}
}