{
  "type": "Feature",
  "properties": {
    "addr:full":"Vesterbrogade 13 Viborg Danmark 8800",
    "addr:housenumber":"13",
    "addr:postcode":"8800",
    "addr:street":"Vesterbrogade",
    "iso:country":"DK",
    "sg:address":"Vesterbrogade 13",
    "sg:city":"Viborg",
    "sg:orig_category":"Medborgerhuse",
    "sg:phone":"+45 86 61 45 99",
    "sg:postcode":"8800",
    "sg:province":"Danmark",
    "wof:name":"Medborgerhuset i Viborg",
    "wof:placetype":"venue"
},
  "geometry": {"coordinates":[9.3990812302,56.4498214722],"type":"Point"}
}