{
  "type": "Feature",
  "properties": {
    "addr:full":"Thybor\u00f8nvej 36, Klinkby Lemvig Danmark 7620",
    "addr:housenumber":"36",
    "addr:postcode":"7620",
    "addr:street":"Thyboronvej",
    "iso:country":"DK",
    "sg:address":"Thybor\u00f8nvej 36, Klinkby",
    "sg:city":"Lemvig",
    "sg:orig_category":"Forsamlingshuse",
    "sg:phone":"+45 97 83 61 10",
    "sg:postcode":"7620",
    "sg:province":"Danmark",
    "wof:name":"Klinkby Forsamlingshus",
    "wof:placetype":"venue"
},
  "geometry": {"coordinates":[8.3073654175,56.5505104065],"type":"Point"}
}