{
  "type": "Feature",
  "properties": {
    "addr:full":"Fmd.: Hanne J\u00f8rgensen, Anemonevej 4 Skibby Danmark 4050",
    "addr:housenumber":"4",
    "addr:postcode":"4050",
    "addr:street":"Anemonevej",
    "iso:country":"DK",
    "sg:address":"Fmd.: Hanne J\u00f8rgensen, Anemonevej 4",
    "sg:city":"Skibby",
    "sg:orig_category":"Oplysningsforbund",
    "sg:phone":"+45 47 52 70 23",
    "sg:postcode":"4050",
    "sg:province":"Danmark",
    "wof:name":"Skibby musikaftenskole",
    "wof:placetype":"venue"
},
  "geometry": {"coordinates":[11.9594116211,55.7502975464],"type":"Point"}
}