{
  "type": "Feature",
  "properties": {
    "addr:full":"Kildeg\u00e5rden 8 Struer Danmark 7600",
    "addr:housenumber":"8",
    "addr:postcode":"7600",
    "addr:street":"Kildegaarden",
    "iso:country":"DK",
    "sg:address":"Kildeg\u00e5rden 8",
    "sg:city":"Struer",
    "sg:orig_category":"Pizzeriaer",
    "sg:phone":"+45 97 85 03 03",
    "sg:postcode":"7600",
    "sg:province":"Danmark",
    "wof:name":"Amore Restaurant & Pizzaria",
    "wof:placetype":"venue"
},
  "geometry": {"coordinates":[8.5946903229,56.491191864],"type":"Point"}
}