{
  "type": "Feature",
  "properties": {
    "addr:full":"Hestehaven 17 Kalundborg Danmark 4400",
    "addr:housenumber":"17",
    "addr:postcode":"4400",
    "addr:street":"Hestehaven",
    "iso:country":"DK",
    "sg:address":"Hestehaven 17",
    "sg:city":"Kalundborg",
    "sg:orig_category":"Revisorer",
    "sg:phone":"+45 59 51 39 72",
    "sg:postcode":"4400",
    "sg:province":"Danmark",
    "wof:name":"Knud E. Hemmingsen",
    "wof:placetype":"venue"
},
  "geometry": {"coordinates":[11.0676584244,55.6839981079],"type":"Point"}
}