{
  "type": "Feature",
  "properties": {
    "iso:country":"DK",
    "sg:address":"\u00d8stergade 114",
    "sg:city":"Skjern",
    "sg:orig_category":"Skorstensfejere",
    "sg:phone":"+45 97 35 26 96",
    "sg:postcode":"6900",
    "sg:province":"Danmark",
    "wof:name":"Eis, Svend \u00c5ge",
    "wof:placetype":"venue"
},
  "geometry": {"coordinates":[8.492972374,55.9485740662],"type":"Point"}
}