{
  "type": "Feature",
  "properties": {
    "addr:full":"Fmd.: J\u00f8rgen Mathiesen, Ved Skellet 9 Greve Danmark 2670",
    "addr:housenumber":"9",
    "addr:postcode":"2670",
    "addr:street":"Ved Skellet",
    "iso:country":"DK",
    "sg:address":"Fmd.: J\u00f8rgen Mathiesen, Ved Skellet 9",
    "sg:city":"Greve",
    "sg:orig_category":"Hobbybetonede foreninger",
    "sg:phone":"+45 43 60 05 95",
    "sg:postcode":"2670",
    "sg:province":"Danmark",
    "wof:name":"Greve Strands Skyttelaug",
    "wof:placetype":"venue"
},
  "geometry": {"coordinates":[12.2941808701,55.5844078064],"type":"Point"}
}