{
  "type": "Feature",
  "properties": {
    "addr:full":"v/ Vagn Ove Thomsen, Dortheavej 15, Klintholm Havn Borre Danmark 4791",
    "addr:housenumber":"15",
    "addr:postcode":"4791",
    "addr:street":"Ove;Dortheavej;Klintholm Havn",
    "iso:country":"DK",
    "sg:address":"v/ Vagn Ove Thomsen, Dortheavej 15, Klintholm Havn",
    "sg:city":"Borre",
    "sg:orig_category":"Havne",
    "sg:postcode":"4791",
    "sg:province":"Danmark",
    "wof:name":"Klintholm Havn",
    "wof:placetype":"venue"
},
  "geometry": {"coordinates":[12.4392347336,54.9952545166],"type":"Point"}
}