{
  "type": "Feature",
  "properties": {
    "iso:country":"DK",
    "sg:address":"Fmd.: Bjarne K. Hansen, \u00d8rslevvej 86",
    "sg:city":"Vordingborg",
    "sg:orig_category":"Hobbybetonede foreninger",
    "sg:phone":"+45 55 98 59 09",
    "sg:postcode":"4760",
    "sg:province":"Danmark",
    "wof:name":"Vordingborg Fotoklub",
    "wof:placetype":"venue"
},
  "geometry": {"coordinates":[11.9124183655,55.0085449219],"type":"Point"}
}