{
  "type": "Feature",
  "properties": {
    "iso:country":"DK",
    "sg:address":"Hovedvejen 47, Sdr. H\u00f8jrup",
    "sg:city":"Ringe",
    "sg:orig_category":"Konsulentvirksomheder",
    "sg:phone":"+45 65 99 30 60",
    "sg:postcode":"5750",
    "sg:province":"Danmark",
    "wof:name":"InFocus",
    "wof:placetype":"venue"
},
  "geometry": {"coordinates":[10.4781074524,55.2356643677],"type":"Point"}
}