{
  "type": "Feature",
  "properties": {
    "iso:country":"DK",
    "sg:address":"Lyb\u00e6kvej 3, No",
    "sg:city":"Ringk\u00f8bing",
    "sg:orig_category":"Kirker",
    "sg:postcode":"6950",
    "sg:province":"Danmark",
    "wof:name":"No kirke",
    "wof:placetype":"venue"
},
  "geometry": {"coordinates":[8.2507953644,56.0878334045],"type":"Point"}
}