{
  "type": "Feature",
  "properties": {
    "addr:full":"Engvej 14 Storvorde Danmark 9280",
    "addr:housenumber":"14",
    "addr:postcode":"9280",
    "addr:street":"Engvej",
    "iso:country":"DK",
    "sg:address":"Engvej 14",
    "sg:city":"Storvorde",
    "sg:orig_category":"Advokater",
    "sg:phone":"+45 98 31 76 88",
    "sg:postcode":"9280",
    "sg:province":"Danmark",
    "sg:website":"www.jokabiler.dk",
    "wof:name":"Hasseriis, John",
    "wof:placetype":"venue"
},
  "geometry": {"coordinates":[10.1110458374,57.0008583069],"type":"Point"}
}