{
  "type": "Feature",
  "properties": {
    "addr:full":"Hobro Landevej 90, Tjele Tjele Danmark 8830",
    "addr:housenumber":"90",
    "addr:postcode":"8830",
    "addr:street":"Hobro Landevej",
    "iso:country":"DK",
    "sg:address":"Hobro Landevej 90, Tjele",
    "sg:city":"Tjele",
    "sg:orig_category":"Planteskoler",
    "sg:phone":"+45 86 65 21 44",
    "sg:postcode":"8830",
    "sg:province":"Danmark",
    "sg:website":"www.tjele-gods.dk",
    "wof:name":"Tjele Planteskole",
    "wof:placetype":"venue"
},
  "geometry": {"coordinates":[9.6264801025,56.4818611145],"type":"Point"}
}