{
  "type": "Feature",
  "properties": {
    "iso:country":"DK",
    "sg:address":"Stationsvej 2",
    "sg:city":"Holstebro",
    "sg:orig_category":"Jagt- og fiskeudstyr",
    "sg:phone":"+45 97 42 54 11",
    "sg:postcode":"7500",
    "sg:province":"Danmark",
    "wof:name":"Vestjysk Jagt & Fritid A/S",
    "wof:placetype":"venue"
},
  "geometry": {"coordinates":[8.6201848984,56.3630638123],"type":"Point"}
}