{
  "type": "Feature",
  "properties": {
    "addr:full":"Vesterbro 34 Aalborg Danmark 9000",
    "addr:housenumber":"34",
    "addr:postcode":"9000",
    "addr:street":"Vesterbro",
    "iso:country":"DK",
    "sg:address":"Vesterbro 34",
    "sg:city":"Aalborg",
    "sg:orig_category":"Ejendomshandel",
    "sg:phone":"+45 98 13 82 00",
    "sg:postcode":"9000",
    "sg:province":"Danmark",
    "sg:website":"www.realmaeglerne.dk",
    "wof:name":"Realm\u00e6gler ApS - Lis Kristoffersen",
    "wof:placetype":"venue"
},
  "geometry": {"coordinates":[9.91447258,57.0468063354],"type":"Point"}
}