{
  "type": "Feature",
  "properties": {
    "addr:full":"Norgesvej 3 Skive Danmark 7800",
    "addr:housenumber":"3",
    "addr:postcode":"7800",
    "addr:street":"Norgesvej",
    "iso:country":"DK",
    "sg:address":"Norgesvej 3",
    "sg:city":"Skive",
    "sg:orig_category":"Betonelementer",
    "sg:phone":"+45 96 15 54 00",
    "sg:postcode":"7800",
    "sg:province":"Danmark",
    "sg:website":"www.perstrup-koebeton.com",
    "wof:name":"K\u00d8 Beton A/S",
    "wof:placetype":"venue"
},
  "geometry": {"coordinates":[9.0396404266,56.5652084351],"type":"Point"}
}