{
  "type": "Feature",
  "properties": {
    "addr:full":"Sandhusvej 17 Odense C Danmark 5000",
    "addr:housenumber":"17",
    "addr:postcode":"5000",
    "addr:street":"Sandhusvej",
    "iso:country":"DK",
    "sg:address":"Sandhusvej 17",
    "sg:city":"Odense C",
    "sg:orig_category":"Snedkermestre",
    "sg:phone":"+45 65 90 41 52",
    "sg:postcode":"5000",
    "sg:province":"Danmark",
    "wof:name":"Hansen, B\u00f8rge",
    "wof:placetype":"venue"
},
  "geometry": {"coordinates":[10.4043426514,55.4177627563],"type":"Point"}
}