{
  "type": "Feature",
  "properties": {
    "iso:country":"DK",
    "sg:address":"Fmd.: Poul Jensen, Gloslunde Gade 27 D",
    "sg:city":"Dannemare",
    "sg:orig_category":"\u00c3\u2020ldreorganisationer og klubber",
    "sg:phone":"+45 54 94 44 91",
    "sg:postcode":"4983",
    "sg:province":"Danmark",
    "wof:name":"Rudbjerg Pensionistforening",
    "wof:placetype":"venue"
},
  "geometry": {"coordinates":[11.1882724762,54.7605667114],"type":"Point"}
}