{
  "type": "Feature",
  "properties": {
    "addr:full":"M\u00f8ngevej 9 Vejby Danmark 3210",
    "addr:housenumber":"9",
    "addr:postcode":"3210",
    "addr:street":"Mongevej",
    "iso:country":"DK",
    "sg:address":"M\u00f8ngevej 9",
    "sg:city":"Vejby",
    "sg:orig_category":"Varmeforsyning",
    "sg:phone":"+45 48 70 53 35",
    "sg:postcode":"3210",
    "sg:province":"Danmark",
    "wof:name":"Vejby-Tisvilde Fjernvarme",
    "wof:placetype":"venue"
},
  "geometry": {"coordinates":[12.148109436,56.0666160583],"type":"Point"}
}