{
  "type": "Feature",
  "properties": {
    "addr:full":"Fmd.: Finn Refsgaard, Emil Bojsens Gade 10 Horsens Danmark 8700",
    "addr:housenumber":"10",
    "addr:postcode":"8700",
    "addr:street":"Emil Bojsens Gade",
    "iso:country":"DK",
    "sg:address":"Fmd.: Finn Refsgaard, Emil Bojsens Gade 10",
    "sg:city":"Horsens",
    "sg:orig_category":"Musik og sang",
    "sg:phone":"+45 75 61 40 80",
    "sg:postcode":"8700",
    "sg:province":"Danmark",
    "wof:name":"Bl\u00e6seorkestret Nord for Alperne",
    "wof:placetype":"venue"
},
  "geometry": {"coordinates":[9.8432445526,55.8621063232],"type":"Point"}
}