{
  "type": "Feature",
  "properties": {
    "addr:full":"Grusgravvej 10, Tommestrup Store Heddinge Danmark 4660",
    "addr:housenumber":"10",
    "addr:postcode":"4660",
    "addr:street":"Grusgravvej",
    "iso:country":"DK",
    "sg:address":"Grusgravvej 10, Tommestrup",
    "sg:city":"Store Heddinge",
    "sg:orig_category":"Arkitekter",
    "sg:phone":"+45 56 50 41 82",
    "sg:postcode":"4660",
    "sg:province":"Danmark",
    "wof:name":"Erdmann, Ole",
    "wof:placetype":"venue"
},
  "geometry": {"coordinates":[12.3895797729,55.3113174438],"type":"Point"}
}