{
  "type": "Feature",
  "properties": {
    "iso:country":"DK",
    "sg:address":"Rosenkildevej 88 A",
    "sg:city":"Slagelse",
    "sg:orig_category":"Skoler",
    "sg:phone":"+45 58 53 20 02",
    "sg:postcode":"4200",
    "sg:province":"Danmark",
    "wof:name":"Slagelse Ungdomsskole",
    "wof:placetype":"venue"
},
  "geometry": {"coordinates":[11.3624973297,55.4158706665],"type":"Point"}
}