{
  "type": "Feature",
  "properties": {
    "addr:full":"Skomagergade 20 Roskilde Danmark 4000",
    "addr:housenumber":"20",
    "addr:postcode":"4000",
    "addr:street":"Skomagergade",
    "iso:country":"DK",
    "sg:address":"Skomagergade 20",
    "sg:city":"Roskilde",
    "sg:orig_category":"Spilleautomater",
    "sg:phone":"+45 46 32 31 11",
    "sg:postcode":"4000",
    "sg:province":"Danmark",
    "wof:name":"Gevinsten",
    "wof:placetype":"venue"
},
  "geometry": {"coordinates":[12.0785417557,55.6410102844],"type":"Point"}
}