{
  "type": "Feature",
  "properties": {
    "iso:country":"DK",
    "sg:address":"Ametystvej 18",
    "sg:city":"Herlev",
    "sg:orig_category":"\u00c3\u02dcvrige institutioner",
    "sg:phone":"+45 44 92 90 44",
    "sg:postcode":"2730",
    "sg:province":"Danmark",
    "wof:name":"Juvelhuset",
    "wof:placetype":"venue"
},
  "geometry": {"coordinates":[12.4394760132,55.7351913452],"type":"Point"}
}