{
  "type": "Feature",
  "properties": {
    "addr:full":"Skr\u00e6nten 7, S\u00f8nderup Suldrup Danmark 9541",
    "addr:housenumber":"7",
    "addr:postcode":"9541",
    "addr:street":"Skraenten",
    "iso:country":"DK",
    "sg:address":"Skr\u00e6nten 7, S\u00f8nderup",
    "sg:city":"Suldrup",
    "sg:orig_category":"Psykologer, praktiserende",
    "sg:phone":"+45 20 77 16 27",
    "sg:postcode":"9541",
    "sg:province":"Danmark",
    "wof:name":"Rasmussen, Marie",
    "wof:placetype":"venue"
},
  "geometry": {"coordinates":[9.701379776,56.8489303589],"type":"Point"}
}