{
  "type": "Feature",
  "properties": {
    "addr:full":"Fmd.: Niels Pontoppidan, Helsebakken 8 Vejle Danmark 7100",
    "addr:housenumber":"8",
    "addr:postcode":"7100",
    "addr:street":"Helsebakken",
    "iso:country":"DK",
    "sg:address":"Fmd.: Niels Pontoppidan, Helsebakken 8",
    "sg:city":"Vejle",
    "sg:orig_category":"Antenneforeninger",
    "sg:phone":"+45 75 72 49 04",
    "sg:postcode":"7100",
    "sg:province":"Danmark",
    "wof:name":"Tr\u00e6dballe/Uhrh\u00f8j Antenneforening",
    "wof:placetype":"venue"
},
  "geometry": {"coordinates":[9.5368051529,55.7113952637],"type":"Point"}
}