{
  "type": "Feature",
  "properties": {
    "addr:full":"Rammevej 52, Ramme Lemvig Danmark 7620",
    "addr:housenumber":"52",
    "addr:postcode":"7620",
    "addr:street":"Rammevej",
    "iso:country":"DK",
    "sg:address":"Rammevej 52, Ramme",
    "sg:city":"Lemvig",
    "sg:orig_category":"Haveartikler",
    "sg:phone":"+45 97 88 94 21",
    "sg:postcode":"7620",
    "sg:province":"Danmark",
    "wof:name":"Lemvig-egnens Fr\u00f8lager",
    "wof:placetype":"venue"
},
  "geometry": {"coordinates":[8.3073654175,56.5505104065],"type":"Point"}
}