{
  "type": "Feature",
  "properties": {
    "addr:full":"Bygaden 7 Lystrup Danmark 8520",
    "addr:housenumber":"7",
    "addr:postcode":"8520",
    "addr:street":"Bygaden",
    "iso:country":"DK",
    "sg:address":"Bygaden 7",
    "sg:city":"Lystrup",
    "sg:orig_category":"Arkitekter",
    "sg:phone":"+45 86 22 37 30",
    "sg:postcode":"8520",
    "sg:province":"Danmark",
    "wof:name":"Archiplan ApS, Arkitektfirmaet",
    "wof:placetype":"venue"
},
  "geometry": {"coordinates":[10.2330160141,56.2319259644],"type":"Point"}
}