{
  "type": "Feature",
  "properties": {
    "addr:full":"\u00d8stergade 57 Struer Danmark 7600",
    "addr:housenumber":"57",
    "addr:postcode":"7600",
    "addr:street":"Ostergade",
    "iso:country":"DK",
    "sg:address":"\u00d8stergade 57",
    "sg:city":"Struer",
    "sg:orig_category":"Jernbaner",
    "sg:phone":"+45 70 13 14 15",
    "sg:postcode":"7600",
    "sg:province":"Danmark",
    "sg:website":"www.dsb.dk",
    "wof:name":"DSB, Struer Station",
    "wof:placetype":"venue"
},
  "geometry": {"coordinates":[8.6011533737,56.4914855957],"type":"Point"}
}