{
  "type": "Feature",
  "properties": {
    "addr:full":"Tagt\u00e6kkervej 2 Viborg Danmark 8800",
    "addr:housenumber":"2",
    "addr:postcode":"8800",
    "addr:street":"Tagtaekkervej",
    "iso:country":"DK",
    "sg:address":"Tagt\u00e6kkervej 2",
    "sg:city":"Viborg",
    "sg:orig_category":"Murermestre",
    "sg:phone":"+45 86 62 49 77",
    "sg:postcode":"8800",
    "sg:province":"Danmark",
    "wof:name":"Jereminsen, Henning",
    "wof:placetype":"venue"
},
  "geometry": {"coordinates":[9.3998661041,56.4713630676],"type":"Point"}
}