{
  "type": "Feature",
  "properties": {
    "iso:country":"DK",
    "sg:address":"Haderslevvej 13 A",
    "sg:city":"Aabenraa",
    "sg:orig_category":"Advokater",
    "sg:phone":"+45 74 63 08 00",
    "sg:postcode":"6200",
    "sg:province":"Danmark",
    "wof:name":"Advokaterne",
    "wof:placetype":"venue"
},
  "geometry": {"coordinates":[9.4216470718,55.0503959656],"type":"Point"}
}