{
  "type": "Feature",
  "properties": {
    "addr:full":"Stormgade 10 - 12 Aalborg Danmark 9000",
    "addr:housenumber":"10 12",
    "addr:postcode":"9000",
    "addr:street":"Stormgade",
    "iso:country":"DK",
    "sg:address":"Stormgade 10 - 12",
    "sg:city":"Aalborg",
    "sg:orig_category":"Ost en gros",
    "sg:phone":"+45 98 12 89 11",
    "sg:postcode":"9000",
    "sg:province":"Danmark",
    "wof:name":"Christensen ApS, Sigfred",
    "wof:placetype":"venue"
},
  "geometry": {"coordinates":[9.943561554,57.0462760925],"type":"Point"}
}