{
  "type": "Feature",
  "properties": {
    "addr:full":"Arres\u00f8gade 2 K\u00f8benhavn N Danmark 2200",
    "addr:housenumber":"2",
    "addr:postcode":"2200",
    "addr:street":"Arresogade;N Danmark",
    "iso:country":"DK",
    "sg:address":"Arres\u00f8gade 2",
    "sg:city":"K\u00f8benhavn N",
    "sg:orig_category":"Malermestre",
    "sg:phone":"+45 43 69 44 36",
    "sg:postcode":"2200",
    "sg:province":"Danmark",
    "wof:name":"Petersen & Flodin A/S",
    "wof:placetype":"venue"
},
  "geometry": {"coordinates":[99.92501068120001,34.2430114746],"type":"Point"}
}