{
  "type": "Feature",
  "properties": {
    "addr:full":"Mads Bjerres Vej 10 Holstebro Danmark 7500",
    "addr:housenumber":"10",
    "addr:postcode":"7500",
    "addr:street":"Mads Bjerres Vej",
    "iso:country":"DK",
    "sg:address":"Mads Bjerres Vej 10",
    "sg:city":"Holstebro",
    "sg:orig_category":"Hobbyartikler",
    "sg:phone":"+45 97 42 49 77",
    "sg:postcode":"7500",
    "sg:province":"Danmark",
    "wof:name":"Kreativ Hobby A/S",
    "wof:placetype":"venue"
},
  "geometry": {"coordinates":[8.6433973312,56.3677368164],"type":"Point"}
}