{
  "type": "Feature",
  "properties": {
    "addr:full":"Parkvej 1, Visby Bredebro Danmark 6261",
    "addr:housenumber":"1",
    "addr:postcode":"6261",
    "addr:street":"Parkvej",
    "iso:country":"DK",
    "sg:address":"Parkvej 1, Visby",
    "sg:city":"Bredebro",
    "sg:orig_category":"Forsamlingshuse",
    "sg:phone":"+45 74 78 31 63",
    "sg:postcode":"6261",
    "sg:province":"Danmark",
    "wof:name":"Visby Forsamlingshus",
    "wof:placetype":"venue"
},
  "geometry": {"coordinates":[8.8284835815,55.0566978455],"type":"Point"}
}