{
  "type": "Feature",
  "properties": {
    "addr:full":"Hunderupvej 22 Odense C Danmark 5000",
    "addr:housenumber":"22",
    "addr:postcode":"5000",
    "addr:street":"Hunderupvej",
    "iso:country":"DK",
    "sg:address":"Hunderupvej 22",
    "sg:city":"Odense C",
    "sg:orig_category":"Arkitekter",
    "sg:phone":"+45 66 11 65 20",
    "sg:postcode":"5000",
    "sg:province":"Danmark",
    "wof:name":"Henneberg",
    "wof:placetype":"venue"
},
  "geometry": {"coordinates":[10.3878984451,55.3916549683],"type":"Point"}
}