{
  "type": "Feature",
  "properties": {
    "iso:country":"DK",
    "sg:address":"Herlev Bygade 90 ",
    "sg:city":"Herlev",
    "sg:classifiers":[
        {
            "category":"Parking",
            "subcategory":"Lot",
            "type":"Transportation"
        }
    ],
    "sg:phone":"+45 44 52 70 00",
    "sg:postcode":"2730",
    "sg:province":"Danmark",
    "sg:tags":[
        "transport",
        "road"
    ],
    "wof:name":"HERLEV KOMMUNE R\u00c5DHUSET",
    "wof:placetype":"venue"
},
  "geometry": {"coordinates":[12.4330396652,55.7249717712],"type":"Point"}
}