{
  "type": "Feature",
  "properties": {
    "iso:country":"DK",
    "sg:address":"Lilleh\u00f8jvej 11 -13 ",
    "sg:city":"Silkeborg",
    "sg:classifiers":[
        {
            "category":"Food & Beverages",
            "subcategory":"Dairy",
            "type":"Retail Goods"
        }
    ],
    "sg:phone":"+45 86 82 42 22",
    "sg:postcode":"8600",
    "sg:province":"Danmark",
    "sg:tags":[
        "product"
    ],
    "wof:name":"LC LAURITZEN A/S",
    "wof:placetype":"venue"
},
  "geometry": {"coordinates":[9.5710344315,56.1884231567],"type":"Point"}
}