{
  "type": "Feature",
  "properties": {
    "addr:full":"Glamb\u00e6ksvej 3 Vordingborg Danmark 4760",
    "addr:housenumber":"3",
    "addr:postcode":"4760",
    "addr:street":"Glambaeksvej",
    "iso:country":"DK",
    "sg:address":"Glamb\u00e6ksvej 3",
    "sg:city":"Vordingborg",
    "sg:orig_category":"Lokalarkiver",
    "sg:phone":"+45 55 37 06 38",
    "sg:postcode":"4760",
    "sg:province":"Danmark",
    "wof:name":"Vordingborg Lokalhistoriske Arkiv",
    "wof:placetype":"venue"
},
  "geometry": {"coordinates":[11.9132986069,55.0076065063],"type":"Point"}
}