{
  "type": "Feature",
  "properties": {
    "addr:full":"Forum Hovedvej 104 Esbjerg N Danmark 6715",
    "addr:housenumber":"104",
    "addr:postcode":"6715",
    "addr:street":"Forum Hovedvej",
    "iso:country":"DK",
    "sg:address":"Forum Hovedvej 104",
    "sg:city":"Esbjerg N",
    "sg:orig_category":"Murermestre",
    "sg:phone":"+45 75 16 84 84",
    "sg:postcode":"6715",
    "sg:province":"Danmark",
    "wof:name":"Finn Thomsen",
    "wof:placetype":"venue"
},
  "geometry": {"coordinates":[8.4758052826,55.5559463501],"type":"Point"}
}