{
  "type": "Feature",
  "properties": {
    "iso:country":"DK",
    "sg:address":"Elmelunden 1",
    "sg:city":"Jyderup",
    "sg:orig_category":"\u00c3\u2020ldrecentre",
    "sg:phone":"+45 59 27 77 76",
    "sg:postcode":"4450",
    "sg:province":"Danmark",
    "wof:name":"Elmelunden, \u00c6ldrecentret",
    "wof:placetype":"venue"
},
  "geometry": {"coordinates":[11.4068517685,55.6619720459],"type":"Point"}
}