{
  "type": "Feature",
  "properties": {
    "addr:full":"v/ Arne S\u00f8nderg\u00e5rd, Annexvej 2 Billund Danmark 7190",
    "addr:housenumber":"2",
    "addr:postcode":"7190",
    "addr:street":"Annexvej",
    "iso:country":"DK",
    "sg:address":"v/ Arne S\u00f8nderg\u00e5rd, Annexvej 2",
    "sg:city":"Billund",
    "sg:orig_category":"Menighedshuse",
    "sg:phone":"+45 75 33 12 96",
    "sg:postcode":"7190",
    "sg:province":"Danmark",
    "wof:name":"L\u00f8vlund Missionshus",
    "wof:placetype":"venue"
},
  "geometry": {"coordinates":[9.1138372421,55.7316017151],"type":"Point"}
}