{
  "type": "Feature",
  "properties": {
    "addr:full":"Griffenfeldsgade 29, 2. th. K\u00f8benhavn N Danmark 2200",
    "addr:housenumber":"29 2 th. kobenhavn",
    "addr:postcode":"2200",
    "addr:street":"Griffenfeldsgade;N Danmark",
    "iso:country":"DK",
    "sg:address":"Griffenfeldsgade 29, 2. th.",
    "sg:city":"K\u00f8benhavn N",
    "sg:orig_category":"Politiske foreninger, \u00c3\u02dcvrige",
    "sg:phone":"+45 35 34 60 33",
    "sg:postcode":"2200",
    "sg:province":"Danmark",
    "sg:website":"www.ru.dk",
    "wof:name":"R\u00f8d Ungdom",
    "wof:placetype":"venue"
},
  "geometry": {"coordinates":[-73.986366272,43.6946678162],"type":"Point"}
}