{
  "type": "Feature",
  "properties": {
    "addr:full":"Fmd.: Lasse Berg, Baltorpvej 120 Ballerup Danmark 2750",
    "addr:housenumber":"120",
    "addr:postcode":"2750",
    "addr:street":"Fmd. Lasse Berg Baltorpvej",
    "iso:country":"DK",
    "sg:address":"Fmd.: Lasse Berg, Baltorpvej 120",
    "sg:city":"Ballerup",
    "sg:orig_category":"Hobbybetonede foreninger",
    "sg:phone":"+45 44 97 68 35",
    "sg:postcode":"2750",
    "sg:province":"Danmark",
    "wof:name":"Ballerup og Omegns Frim\u00e6rkeklub",
    "wof:placetype":"venue"
},
  "geometry": {"coordinates":[12.361000061,55.7301216125],"type":"Point"}
}