{
  "type": "Feature",
  "properties": {
    "addr:full":"Systemvej 8 Aalborg SV Danmark 9200",
    "addr:housenumber":"8",
    "addr:postcode":"9200",
    "addr:street":"Systemvej",
    "iso:country":"DK",
    "sg:address":"Systemvej 8",
    "sg:city":"Aalborg SV",
    "sg:orig_category":"El-artikler",
    "sg:phone":"+45 98 18 96 08",
    "sg:postcode":"9200",
    "sg:province":"Danmark",
    "wof:name":"Duelco Aalborg a/s",
    "wof:placetype":"venue"
},
  "geometry": {"coordinates":[9.8884067535,57.0007858276],"type":"Point"}
}