{
  "type": "Feature",
  "properties": {
    "addr:full":"Aldersrovej 45 \u00c5rhus N Danmark 8200",
    "addr:housenumber":"45",
    "addr:postcode":"8200",
    "addr:street":"Aldersrovej",
    "iso:country":"DK",
    "sg:address":"Aldersrovej 45",
    "sg:city":"\u00c5rhus N",
    "sg:orig_category":"Fritidsklubber",
    "sg:phone":"+45 86 16 33 91",
    "sg:postcode":"8200",
    "sg:province":"Danmark",
    "wof:name":"A 45 Fritids-, Ungdoms- og Handicapklubben",
    "wof:placetype":"venue"
},
  "geometry": {"coordinates":[4.9393601418,49.7092018127],"type":"Point"}
}