{
  "type": "Feature",
  "properties": {
    "addr:full":"Industrivej 8 Skjern Danmark 6900",
    "addr:housenumber":"8",
    "addr:postcode":"6900",
    "addr:street":"Industrivej",
    "iso:country":"DK",
    "sg:address":"Industrivej 8",
    "sg:city":"Skjern",
    "sg:orig_category":"Non-Classified Establishments",
    "sg:phone":"+45 97 35 11 92",
    "sg:postcode":"6900",
    "sg:province":"Danmark",
    "wof:name":"Reva-Skjern Maskinfabrik",
    "wof:placetype":"venue"
},
  "geometry": {"coordinates":[8.4913358688,55.9566345215],"type":"Point"}
}