{
  "type": "Feature",
  "properties": {
    "addr:full":"Tingvadvej 21 Vojens Danmark 6500",
    "addr:housenumber":"21",
    "addr:postcode":"6500",
    "addr:street":"Tingvadvej",
    "iso:country":"DK",
    "sg:address":"Tingvadvej 21",
    "sg:city":"Vojens",
    "sg:orig_category":"Planteskoler",
    "sg:phone":"+45 74 87 12 91",
    "sg:postcode":"6500",
    "sg:province":"Danmark",
    "wof:name":"Flisb\u00e6k Planteskole",
    "wof:placetype":"venue"
},
  "geometry": {"coordinates":[9.1999025345,55.2806892395],"type":"Point"}
}