{
  "type": "Feature",
  "properties": {
    "addr:full":"S\u00f8gade 2 Ringsted Danmark 4100",
    "addr:housenumber":"2",
    "addr:postcode":"4100",
    "addr:street":"Sogade",
    "iso:country":"DK",
    "sg:address":"S\u00f8gade 2",
    "sg:city":"Ringsted",
    "sg:orig_category":"Genbrugsbutikker",
    "sg:phone":"+45 57 67 27 70",
    "sg:postcode":"4100",
    "sg:province":"Danmark",
    "wof:name":"R\u00f8de Kors Genbrug",
    "wof:placetype":"venue"
},
  "geometry": {"coordinates":[11.8881902695,55.3920097351],"type":"Point"}
}