{
  "type": "Feature",
  "properties": {
    "addr:full":"Vieb\u00e6ltet 1-3 Svendborg Danmark 5700",
    "addr:housenumber":"1-3",
    "addr:postcode":"5700",
    "addr:street":"Viebaeltet",
    "iso:country":"DK",
    "sg:address":"Vieb\u00e6ltet 1-3",
    "sg:city":"Svendborg",
    "sg:orig_category":"Hvidevarer",
    "sg:phone":"+45 62 21 56 31",
    "sg:postcode":"5700",
    "sg:province":"Danmark",
    "wof:name":"Skousen Husholdningsmaskiner",
    "wof:placetype":"venue"
},
  "geometry": {"coordinates":[10.6018257141,55.0606842041],"type":"Point"}
}