{
  "type": "Feature",
  "properties": {
    "iso:country":"DK",
    "sg:address":"Skolebakken 19 - 21",
    "sg:city":"Odder",
    "sg:classifiers":[
        {
            "category":"Banks & Credit Unions",
            "subcategory":"Financial Services",
            "type":"Services"
        }
    ],
    "sg:phone":"+45 87 80 24 24",
    "sg:postcode":"8300",
    "sg:province":"Danmark",
    "sg:tags":[
        "banking",
        "finance",
        "insurance"
    ],
    "wof:name":"NORS\u00c6NK-AALYKKE",
    "wof:placetype":"venue"
},
  "geometry": {"coordinates":[10.1024312973,55.9636726379],"type":"Point"}
}