{
  "type": "Feature",
  "properties": {
    "addr:full":"Overdammen 11 Ribe Danmark 6760",
    "addr:housenumber":"11",
    "addr:postcode":"6760",
    "addr:street":"Overdammen",
    "iso:country":"DK",
    "sg:address":"Overdammen 11",
    "sg:city":"Ribe",
    "sg:classifiers":[
        {
            "category":"Restaurant",
            "type":"Food & Drink"
        }
    ],
    "sg:phone":"+45 75 42 22 81",
    "sg:postcode":"6760",
    "sg:province":"Danmark",
    "wof:name":"Nielsen, Caf\u00e9",
    "wof:placetype":"venue"
},
  "geometry": {"coordinates":[8.7631225586,55.3290252686],"type":"Point"}
}