{
  "type": "Feature",
  "properties": {
    "addr:full":"Brittavej 1 Greve Danmark 2670",
    "addr:housenumber":"1",
    "addr:postcode":"2670",
    "addr:street":"Brittavej",
    "iso:country":"DK",
    "sg:address":"Brittavej 1",
    "sg:city":"Greve",
    "sg:orig_category":"Reklamebureauer",
    "sg:phone":"+45 43 90 44 12",
    "sg:postcode":"2670",
    "sg:province":"Danmark",
    "wof:name":"H. Design ApS",
    "wof:placetype":"venue"
},
  "geometry": {"coordinates":[12.3049726486,55.5831222534],"type":"Point"}
}