{
  "type": "Feature",
  "properties": {
    "iso:country":"DK",
    "sg:address":"Skolegade 2, Holb\u00f8l",
    "sg:city":"Krus\u00e5",
    "sg:orig_category":"Integrerede institutioner",
    "sg:phone":"+45 74 60 81 36",
    "sg:postcode":"6340",
    "sg:province":"Danmark",
    "wof:name":"Svalen",
    "wof:placetype":"venue"
},
  "geometry": {"coordinates":[9.3991203308,54.8500900269],"type":"Point"}
}