{
  "type": "Feature",
  "properties": {
    "iso:country":"DK",
    "sg:address":"Bredgade 34",
    "sg:city":"N\u00f8rre Nebel",
    "sg:orig_category":"Sportsartikler",
    "sg:phone":"+45 75 28 75 75",
    "sg:postcode":"6830",
    "sg:province":"Danmark",
    "wof:name":"Sportspartner",
    "wof:placetype":"venue"
},
  "geometry": {"coordinates":[8.2894668579,55.7791748047],"type":"Point"}
}