{
  "type": "Feature",
  "properties": {
    "iso:country":"DK",
    "sg:address":"Petersmindevej 8",
    "sg:city":"Juelsminde",
    "sg:orig_category":"Skolefritidsordninger",
    "sg:phone":"+45 75 69 35 05",
    "sg:postcode":"7130",
    "sg:province":"Danmark",
    "wof:name":"Sandbjerg Skolefritidsordning",
    "wof:placetype":"venue"
},
  "geometry": {"coordinates":[9.9951686859,55.7047424316],"type":"Point"}
}