{
  "type": "Feature",
  "properties": {
    "addr:full":"R\u00f8debro 1, Velling Ringk\u00f8bing Danmark 6950",
    "addr:housenumber":"1",
    "addr:postcode":"6950",
    "addr:street":"Rodebro",
    "iso:country":"DK",
    "sg:address":"R\u00f8debro 1, Velling",
    "sg:city":"Ringk\u00f8bing",
    "sg:orig_category":"Murermestre",
    "sg:phone":"+45 97 32 20 19",
    "sg:postcode":"6950",
    "sg:province":"Danmark",
    "wof:name":"Mastrup, Bent",
    "wof:placetype":"venue"
},
  "geometry": {"coordinates":[8.2507953644,56.0878334045],"type":"Point"}
}