{
  "type": "Feature",
  "properties": {
    "addr:full":"Ryg\u00e5rds All\u00e9 92 Hellerup Danmark 2900",
    "addr:housenumber":"92",
    "addr:postcode":"2900",
    "addr:street":"Rygaards Alle\u0301",
    "iso:country":"DK",
    "sg:address":"Ryg\u00e5rds All\u00e9 92",
    "sg:city":"Hellerup",
    "sg:orig_category":"Psykologer, praktiserende",
    "sg:postcode":"2900",
    "sg:province":"Danmark",
    "wof:name":"Andres, Anette",
    "wof:placetype":"venue"
},
  "geometry": {"coordinates":[12.5600585938,55.7236442566],"type":"Point"}
}