{
  "type": "Feature",
  "properties": {
    "addr:full":"Kuskevej 1 A Vordingborg Danmark 4760",
    "addr:housenumber":"1 a",
    "addr:postcode":"4760",
    "addr:street":"Kuskevej",
    "iso:country":"DK",
    "sg:address":"Kuskevej 1 A",
    "sg:city":"Vordingborg",
    "sg:orig_category":"\u00c3\u02dcvrige biblioteker",
    "sg:phone":"+45 55 37 16 88",
    "sg:postcode":"4760",
    "sg:province":"Danmark",
    "wof:name":"Danmarks P\u00e6dagogiske Bibliotek, Afdelingen i Vordingborg",
    "wof:placetype":"venue"
},
  "geometry": {"coordinates":[11.8966188431,55.0126609802],"type":"Point"}
}