{
  "type": "Feature",
  "properties": {
    "addr:full":"M\u00f8lles\u00f8vej 7 Vemmelev Danmark 4241",
    "addr:housenumber":"7",
    "addr:postcode":"4241",
    "addr:street":"Mollesovej",
    "iso:country":"DK",
    "sg:address":"M\u00f8lles\u00f8vej 7",
    "sg:city":"Vemmelev",
    "sg:orig_category":"Lossepladser",
    "sg:phone":"+45 58 38 28 00",
    "sg:postcode":"4241",
    "sg:province":"Danmark",
    "wof:name":"Det f\u00e6lleskommunale affaldsselskab I/S KAVO",
    "wof:placetype":"venue"
},
  "geometry": {"coordinates":[11.2445354462,55.387008667],"type":"Point"}
}