{
  "type": "Feature",
  "properties": {
    "addr:full":"B\u00f8rupvej 2 Tranbjerg Danmark 8310",
    "addr:housenumber":"2",
    "addr:postcode":"8310",
    "addr:street":"Borupvej",
    "iso:country":"DK",
    "sg:address":"B\u00f8rupvej 2",
    "sg:city":"Tranbjerg",
    "sg:orig_category":"Integrerede institutioner",
    "sg:phone":"+45 86 29 96 00",
    "sg:postcode":"8310",
    "sg:province":"Danmark",
    "wof:name":"Legehuset Regnbuen, Integreret Inst.",
    "wof:placetype":"venue"
},
  "geometry": {"coordinates":[10.115650177,56.0600318909],"type":"Point"}
}