{
  "type": "Feature",
  "properties": {
    "addr:full":"N\u00f8rregade 12 Skanderborg Danmark 8660",
    "addr:housenumber":"12",
    "addr:postcode":"8660",
    "addr:street":"Norregade",
    "iso:country":"DK",
    "sg:address":"N\u00f8rregade 12",
    "sg:city":"Skanderborg",
    "sg:orig_category":"Arkitekter",
    "sg:phone":"+45 86 52 18 22",
    "sg:postcode":"8660",
    "sg:province":"Danmark",
    "wof:name":"Larsen M.A.A. A/S, Jette & J\u00f8rgen Frost",
    "wof:placetype":"venue"
},
  "geometry": {"coordinates":[9.9297237396,56.0385284424],"type":"Point"}
}