{
  "type": "Feature",
  "properties": {
    "addr:full":"Eg\u00f8je Byvej 7 K\u00f8ge Danmark 4600",
    "addr:housenumber":"7",
    "addr:postcode":"4600",
    "addr:street":"Egoje Byvej",
    "iso:country":"DK",
    "sg:address":"Eg\u00f8je Byvej 7",
    "sg:city":"K\u00f8ge",
    "sg:orig_category":"Rideskoler",
    "sg:phone":"+45 56 21 40 10",
    "sg:postcode":"4600",
    "sg:province":"Danmark",
    "wof:name":"Eg\u00f8je Ridecenter",
    "wof:placetype":"venue"
},
  "geometry": {"coordinates":[134.49911499020001,-6.9317002296],"type":"Point"}
}