{
  "type": "Feature",
  "properties": {
    "addr:full":"Metalgangen 6 E Karlslunde Danmark 2690",
    "addr:housenumber":"6 e",
    "addr:postcode":"2690",
    "addr:street":"Metalgangen",
    "iso:country":"DK",
    "sg:address":"Metalgangen 6 E",
    "sg:city":"Karlslunde",
    "sg:orig_category":"Isolering",
    "sg:phone":"+45 54 91 01 90",
    "sg:postcode":"2690",
    "sg:province":"Danmark",
    "sg:website":"www.activ-as.dk",
    "wof:name":"Activ A/S, Isoleringsfirmaet",
    "wof:placetype":"venue"
},
  "geometry": {"coordinates":[12.2294149399,55.5701599121],"type":"Point"}
}