{
  "type": "Feature",
  "properties": {
    "addr:full":"Vestergade 22 - 24 Lemvig Danmark 7620",
    "addr:housenumber":"22 24",
    "addr:postcode":"7620",
    "addr:street":"Vestergade",
    "iso:country":"DK",
    "sg:address":"Vestergade 22 - 24",
    "sg:city":"Lemvig",
    "sg:orig_category":"Cafeer",
    "sg:phone":"+45 97 82 08 30",
    "sg:postcode":"7620",
    "sg:province":"Danmark",
    "wof:name":"Larsen, Caf\u00e9",
    "wof:placetype":"venue"
},
  "geometry": {"coordinates":[8.3063106537,56.550037384],"type":"Point"}
}