{
  "type": "Feature",
  "properties": {
    "addr:full":"Havrevej 5 Randers Danmark 8900",
    "addr:housenumber":"5",
    "addr:postcode":"8900",
    "addr:street":"Havrevej",
    "iso:country":"DK",
    "sg:address":"Havrevej 5",
    "sg:city":"Randers",
    "sg:classifiers":[
        {
            "category":"Building & Trades",
            "subcategory":"Construction",
            "type":"Services"
        }
    ],
    "sg:phone":"+45 86 42 00 11",
    "sg:postcode":"8900",
    "sg:province":"Danmark",
    "sg:tags":[
        "renovation"
    ],
    "wof:name":"Renovadan Milj\u00f8service A/S",
    "wof:placetype":"venue"
},
  "geometry": {"coordinates":[10.0223989487,56.4790840149],"type":"Point"}
}