{
  "type": "Feature",
  "properties": {
    "iso:country":"DK",
    "sg:address":"Asminder\u00f8dgade 53",
    "sg:city":"Fredensborg",
    "sg:orig_category":"Selskabslokaler",
    "sg:phone":"+45 48 48 00 02",
    "sg:postcode":"3480",
    "sg:province":"Danmark",
    "wof:name":"Asminder\u00f8d Kro & Hotel",
    "wof:placetype":"venue"
},
  "geometry": {"coordinates":[12.4081268311,55.9689826965],"type":"Point"}
}