{
  "type": "Feature",
  "properties": {
    "iso:country":"DK",
    "sg:address":"Lindvigsvej 4",
    "sg:city":"Horsens",
    "sg:orig_category":"Skolefritidsordninger",
    "sg:phone":"+45 76 25 52 31",
    "sg:postcode":"8700",
    "sg:province":"Danmark",
    "wof:name":"S\u00f8ndermarkskolens Skolefritidsordning",
    "wof:placetype":"venue"
},
  "geometry": {"coordinates":[9.8339443207,55.8571853638],"type":"Point"}
}