{
  "type": "Feature",
  "properties": {
    "iso:country":"DK",
    "sg:address":"Dunk\u00e6rgade 22",
    "sg:city":"\u00c6r\u00f8sk\u00f8bing",
    "sg:orig_category":"Landbrugsmaskiner",
    "sg:phone":"+45 62 52 14 40",
    "sg:postcode":"5970",
    "sg:province":"Danmark",
    "wof:name":"Dunk\u00e6r Maskinforretning Aps",
    "wof:placetype":"venue"
},
  "geometry": {"coordinates":[-114.0767440796,46.4432487488],"type":"Point"}
}