{
  "type": "Feature",
  "properties": {
    "addr:full":"Mads Jensens Vej 3 Vordingborg Danmark 4760",
    "addr:housenumber":"3",
    "addr:postcode":"4760",
    "addr:street":"Mads Jensens Vej",
    "iso:country":"DK",
    "sg:address":"Mads Jensens Vej 3",
    "sg:city":"Vordingborg",
    "sg:orig_category":"Zoneterapeuter",
    "sg:phone":"+45 55 37 34 10",
    "sg:postcode":"4760",
    "sg:province":"Danmark",
    "wof:name":"Larsen, Mette Wever",
    "wof:placetype":"venue"
},
  "geometry": {"coordinates":[11.9677877426,55.0023460388],"type":"Point"}
}