{
  "type": "Feature",
  "properties": {
    "iso:country":"DK",
    "sg:address":"S\u00f8ndergade 14, City 1 - Biledgaard Centret",
    "sg:city":"Horsens",
    "sg:orig_category":"Skomagere",
    "sg:phone":"+45 75 62 26 37",
    "sg:postcode":"8700",
    "sg:province":"Danmark",
    "wof:name":"Henrik's H\u00e6le- & N\u00f8glebar",
    "wof:placetype":"venue"
},
  "geometry": {"coordinates":[9.8432445526,55.8621063232],"type":"Point"}
}