{
  "type": "Feature",
  "properties": {
    "addr:full":"Vonsildvej 17, Vonsild Kolding Danmark 6000",
    "addr:housenumber":"17",
    "addr:postcode":"6000",
    "addr:street":"Vonsildvej;Vonsild",
    "iso:country":"DK",
    "sg:address":"Vonsildvej 17, Vonsild",
    "sg:city":"Kolding",
    "sg:orig_category":"Autoforhandlere",
    "sg:phone":"+45 75 52 78 00",
    "sg:postcode":"6000",
    "sg:province":"Danmark",
    "wof:name":"S\u00f8rensen Iveco-Fiat Speciale",
    "wof:placetype":"venue"
},
  "geometry": {"coordinates":[9.4733953476,55.4863586426],"type":"Point"}
}