{
  "type": "Feature",
  "properties": {
    "addr:full":"Vestbuen 159 Ballerup Danmark 2750",
    "addr:housenumber":"159",
    "addr:postcode":"2750",
    "addr:street":"Vestbuen",
    "iso:country":"DK",
    "sg:address":"Vestbuen 159",
    "sg:city":"Ballerup",
    "sg:orig_category":"Benzinstationer",
    "sg:phone":"+45 44 65 06 26",
    "sg:postcode":"2750",
    "sg:province":"Danmark",
    "wof:name":"Q8 Service",
    "wof:placetype":"venue"
},
  "geometry": {"coordinates":[12.3455181122,55.7269515991],"type":"Point"}
}