{
  "type": "Feature",
  "properties": {
    "iso:country":"DK",
    "sg:address":"Leder: Elin Nilsson, Tusk\u00e6rvej 9, Fjaltring",
    "sg:city":"Lemvig",
    "sg:orig_category":"Kulturcentre",
    "sg:phone":"+45 97 88 71 48",
    "sg:postcode":"7620",
    "sg:province":"Danmark",
    "wof:name":"Kulturcentret Tusk\u00e6r",
    "wof:placetype":"venue"
},
  "geometry": {"coordinates":[8.3073654175,56.5505104065],"type":"Point"}
}