{
  "type": "Feature",
  "properties": {
    "iso:country":"DK",
    "sg:address":"Christiansborg Slot 0",
    "sg:orig_category":"Oplysningsforbund",
    "sg:phone":"+45 33 37 33 37",
    "sg:postcode":"1240",
    "wof:name":"Folketingets EU-Oplysning",
    "wof:placetype":"venue"
},
  "geometry": {"coordinates":[12.5808296204,55.6763801575],"type":"Point"}
}