{
  "type": "Feature",
  "properties": {
    "iso:country":"DK",
    "sg:address":"Vestergade 60",
    "sg:city":"Brovst",
    "sg:orig_category":"Vinduespolering",
    "sg:phone":"+45 98 23 30 87",
    "sg:postcode":"9460",
    "sg:province":"Danmark",
    "wof:name":"Jensen Vinduespolering, John",
    "wof:placetype":"venue"
},
  "geometry": {"coordinates":[9.5171041489,57.096988678],"type":"Point"}
}