{
  "type": "Feature",
  "properties": {
    "addr:full":"Skodsborgparken 39 Skodsborg Danmark 2942",
    "addr:housenumber":"39",
    "addr:postcode":"2942",
    "addr:street":"Skodsborgparken",
    "iso:country":"DK",
    "sg:address":"Skodsborgparken 39",
    "sg:city":"Skodsborg",
    "sg:orig_category":"Autoreparation og -service",
    "sg:phone":"+45 45 80 31 13",
    "sg:postcode":"2942",
    "sg:province":"Danmark",
    "wof:name":"Skodsborg Service-Station",
    "wof:placetype":"venue"
},
  "geometry": {"coordinates":[12.576458931,55.811794281],"type":"Point"}
}