{
  "type": "Feature",
  "properties": {
    "addr:full":"\u00d8ster\u00e5gade 3 Aalborg Danmark 9000",
    "addr:housenumber":"3",
    "addr:postcode":"9000",
    "addr:street":"Osteraagade",
    "iso:country":"DK",
    "sg:address":"\u00d8ster\u00e5gade 3",
    "sg:city":"Aalborg",
    "sg:orig_category":"Bandagister",
    "sg:phone":"+45 98 12 24 88",
    "sg:postcode":"9000",
    "sg:province":"Danmark",
    "wof:name":"M\u00e6rsk-Andersens Eftf., C.",
    "wof:placetype":"venue"
},
  "geometry": {"coordinates":[9.920964,57.048138],"type":"Point"}
}