{
  "type": "Feature",
  "properties": {
    "addr:full":"S\u00f8lvgade 17, \u00d8. Kippinge N\u00f8rre Alslev Danmark 4840",
    "addr:housenumber":"17 o.",
    "addr:postcode":"4840",
    "addr:street":"Solvgade;Kippinge Norre",
    "iso:country":"DK",
    "sg:address":"S\u00f8lvgade 17, \u00d8. Kippinge",
    "sg:city":"N\u00f8rre Alslev",
    "sg:orig_category":"Alternativ behandling",
    "sg:phone":"+45 54 45 33 93",
    "sg:postcode":"4840",
    "sg:province":"Danmark",
    "sg:website":"www.kristellaliv.dk",
    "wof:name":"Rosenkilden",
    "wof:placetype":"venue"
},
  "geometry": {"coordinates":[11.8542251587,54.9528236389],"type":"Point"}
}