{
  "type": "Feature",
  "properties": {
    "addr:full":"Saltv\u00e6rksvej 45 Kastrup Danmark 2770",
    "addr:housenumber":"45",
    "addr:postcode":"2770",
    "addr:street":"Saltvaerksvej",
    "iso:country":"DK",
    "sg:address":"Saltv\u00e6rksvej 45",
    "sg:city":"Kastrup",
    "sg:orig_category":"Blomsterhandlere",
    "sg:phone":"+45 32 52 80 70",
    "sg:postcode":"2770",
    "sg:province":"Danmark",
    "wof:name":"Blomsterforretningen",
    "wof:placetype":"venue"
},
  "geometry": {"coordinates":[12.6406745911,55.6382980347],"type":"Point"}
}