{
  "type": "Feature",
  "properties": {
    "addr:full":"Skansen Varde Danmark 6800",
    "addr:postcode":"6800",
    "addr:street":"Skansen",
    "iso:country":"DK",
    "sg:address":"Skansen",
    "sg:city":"Varde",
    "sg:orig_category":"Legesteder",
    "sg:postcode":"6800",
    "sg:province":"Danmark",
    "wof:name":"Legepladsen",
    "wof:placetype":"venue"
},
  "geometry": {"coordinates":[8.4843149185,55.6209640503],"type":"Point"}
}