{
  "type": "Feature",
  "properties": {
    "addr:full":"v/ Kamma Rasmussen, B\u00e6la 3 Hasle Danmark 3790",
    "addr:housenumber":"3",
    "addr:postcode":"3790",
    "iso:country":"DK",
    "sg:address":"v/ Kamma Rasmussen, B\u00e6la 3",
    "sg:city":"Hasle",
    "sg:orig_category":"Husflidsforeninger",
    "sg:phone":"+45 56 96 43 68",
    "sg:postcode":"3790",
    "sg:province":"Danmark",
    "wof:name":"Aktive Kvinder i Danmark",
    "wof:placetype":"venue"
},
  "geometry": {"coordinates":[14.7065896988,55.1830863953],"type":"Point"}
}