{
  "type": "Feature",
  "properties": {
    "addr:full":"Sdr. Landevej 47 Aakirkeby Danmark 3720",
    "addr:housenumber":"47",
    "addr:postcode":"3720",
    "addr:street":"Sdr. Landevej",
    "iso:country":"DK",
    "sg:address":"Sdr. Landevej 47",
    "sg:city":"Aakirkeby",
    "sg:orig_category":"Solvarme",
    "sg:phone":"+45 56 97 47 43",
    "sg:postcode":"3720",
    "sg:province":"Danmark",
    "wof:name":"\u00c5ker VVS",
    "wof:placetype":"venue"
},
  "geometry": {"coordinates":[14.8953552246,55.0383262634],"type":"Point"}
}