{
  "type": "Feature",
  "properties": {
    "addr:full":"Amagerbrogade 49 K\u00f8benhavn S Danmark 2300",
    "addr:housenumber":"49",
    "addr:postcode":"2300",
    "addr:street":"Amagerbrogade;Kobenhavn S Danmark",
    "iso:country":"DK",
    "sg:address":"Amagerbrogade 49",
    "sg:city":"K\u00f8benhavn S",
    "sg:classifiers":[
        {
            "category":"Communications",
            "type":"Services"
        }
    ],
    "sg:phone":"+45 32 54 40 00",
    "sg:postcode":"2300",
    "sg:province":"Danmark",
    "sg:tags":[
        "og",
        "tv",
        "radio"
    ],
    "sg:website":"www.der.dk",
    "wof:name":"D:E:R",
    "wof:placetype":"venue"
},
  "geometry": {"coordinates":[-78.1299133301,36.7267417908],"type":"Point"}
}