{
  "type": "Feature",
  "properties": {
    "addr:full":"Gimming Kirkevej 2 Randers Danmark 8900",
    "addr:housenumber":"2",
    "addr:postcode":"8900",
    "addr:street":"Gimming Kirkevej",
    "iso:country":"DK",
    "sg:address":"Gimming Kirkevej 2",
    "sg:city":"Randers",
    "sg:orig_category":"Kirker",
    "sg:postcode":"8900",
    "sg:province":"Danmark",
    "wof:name":"Gimming Kirke",
    "wof:placetype":"venue"
},
  "geometry": {"coordinates":[10.0966501236,56.4936065674],"type":"Point"}
}