{
  "type": "Feature",
  "properties": {
    "iso:country":"DK",
    "sg:address":"Nytorv 1",
    "sg:city":"Sk\u00e6lsk\u00f8r",
    "sg:orig_category":"Begravelsesforretninger",
    "sg:phone":"+45 58 19 44 46",
    "sg:postcode":"4230",
    "sg:province":"Danmark",
    "wof:name":"Bedem\u00e6ndene Vald. Nielsen & S\u00f8n Eftf.",
    "wof:placetype":"venue"
},
  "geometry": {"coordinates":[11.191504,55.211975],"type":"Point"}
}