{
  "type": "Feature",
  "properties": {
    "addr:full":"Sct. Bendtsgade 10 3. Th Ringsted Danmark 4100",
    "addr:housenumber":"10 3",
    "addr:postcode":"4100",
    "addr:street":"Bendtsgade;Th",
    "iso:country":"DK",
    "sg:address":"Sct. Bendtsgade 10 3. Th",
    "sg:city":"Ringsted",
    "sg:orig_category":"Zoneterapeuter",
    "sg:phone":"+45 57 61 84 81",
    "sg:postcode":"4100",
    "sg:province":"Danmark",
    "wof:name":"Nielsen, Lina",
    "wof:placetype":"venue"
},
  "geometry": {"coordinates":[11.7875862122,55.4458961487],"type":"Point"}
}