{
  "type": "Feature",
  "properties": {
    "addr:full":"Skagensvej 448 Jerup Danmark 9981",
    "addr:housenumber":"448",
    "addr:postcode":"9981",
    "addr:street":"Skagensvej",
    "iso:country":"DK",
    "sg:address":"Skagensvej 448",
    "sg:city":"Jerup",
    "sg:orig_category":"Forsamlingshuse",
    "sg:phone":"+45 98 48 36 24",
    "sg:postcode":"9981",
    "sg:province":"Danmark",
    "wof:name":"Jerup Forsamlingshus",
    "wof:placetype":"venue"
},
  "geometry": {"coordinates":[10.4194793701,57.5354576111],"type":"Point"}
}