{
  "type": "Feature",
  "properties": {
    "addr:full":"Man\u00f8gade 24 Esbjerg Danmark 6700",
    "addr:housenumber":"24",
    "addr:postcode":"6700",
    "addr:street":"Manogade",
    "iso:country":"DK",
    "sg:address":"Man\u00f8gade 24",
    "sg:city":"Esbjerg",
    "sg:orig_category":"Vuggestuer",
    "sg:phone":"+45 75 12 43 88",
    "sg:postcode":"6700",
    "sg:province":"Danmark",
    "wof:name":"Vuggestuen",
    "wof:placetype":"venue"
},
  "geometry": {"coordinates":[8.4682512283,55.4657287598],"type":"Point"}
}