{
  "type": "Feature",
  "properties": {
    "addr:full":"Fmd.: Preben Pedersen Maare, S\u00f8ller\u00f8dlund 23, S\u00f8ller\u00f8d Holte Danmark 2840",
    "addr:housenumber":"23",
    "addr:postcode":"2840",
    "addr:street":"Preben;Sollerodlund",
    "iso:country":"DK",
    "sg:address":"Fmd.: Preben Pedersen Maare, S\u00f8ller\u00f8dlund 23, S\u00f8ller\u00f8d",
    "sg:city":"Holte",
    "sg:orig_category":"Grundejerforeninger",
    "sg:phone":"+45 45 42 18 21",
    "sg:postcode":"2840",
    "sg:province":"Danmark",
    "wof:name":"S\u00f8ller\u00f8dlund Ejerlaug",
    "wof:placetype":"venue"
},
  "geometry": {"coordinates":[12.4706554413,55.8122367859],"type":"Point"}
}