{
  "type": "Feature",
  "properties": {
    "iso:country":"DK",
    "sg:address":"Tingvej 3 - 5",
    "sg:city":"Hornslet",
    "sg:orig_category":"Materialister",
    "sg:phone":"+45 86 99 43 28",
    "sg:postcode":"8543",
    "sg:province":"Danmark",
    "wof:name":"Matas Hornslet",
    "wof:placetype":"venue"
},
  "geometry": {"coordinates":[10.317990303,56.3161315918],"type":"Point"}
}