{
  "type": "Feature",
  "properties": {
    "addr:full":"\u00c5boulevarden 3 \u00c5rhus C Danmark 8000",
    "addr:housenumber":"3",
    "addr:postcode":"8000",
    "addr:street":"Aaboulevarden",
    "iso:country":"DK",
    "sg:address":"\u00c5boulevarden 3",
    "sg:city":"\u00c5rhus C",
    "sg:orig_category":"Kirurgi",
    "sg:phone":"+45 86 19 93 30",
    "sg:postcode":"8000",
    "sg:province":"Danmark",
    "wof:name":"R\u00f8pcke, G\u00fcnther",
    "wof:placetype":"venue"
},
  "geometry": {"coordinates":[4.717400074,49.7588005066],"type":"Point"}
}