{
  "type": "Feature",
  "properties": {
    "addr:full":"M\u00f8llegade 45, Lyngs Thyholm Danmark 7790",
    "addr:housenumber":"45",
    "addr:postcode":"7790",
    "addr:street":"Mollegade",
    "iso:country":"DK",
    "sg:address":"M\u00f8llegade 45, Lyngs",
    "sg:city":"Thyholm",
    "sg:orig_category":"Fotografer",
    "sg:phone":"+45 97 87 80 38",
    "sg:postcode":"7790",
    "sg:province":"Danmark",
    "wof:name":"Fotografen i Lyngs",
    "wof:placetype":"venue"
},
  "geometry": {"coordinates":[8.525765419,56.6507072449],"type":"Point"}
}