{
  "type": "Feature",
  "properties": {
    "iso:country":"DK",
    "sg:address":"Skimminge 19",
    "sg:city":"Maribo",
    "sg:orig_category":"Voksenuddannelsescentre",
    "sg:phone":"+45 54 75 51 11",
    "sg:postcode":"4930",
    "sg:province":"Danmark",
    "wof:name":"VUC Storstr\u00f8m Maribo",
    "wof:placetype":"venue"
},
  "geometry": {"coordinates":[11.5074300766,54.7730941772],"type":"Point"}
}