{
  "type": "Feature",
  "properties": {
    "addr:full":"Klitfyrren 20 Kjellerup Danmark 8620",
    "addr:housenumber":"20",
    "addr:postcode":"8620",
    "addr:street":"Klitfyrren",
    "iso:country":"DK",
    "sg:address":"Klitfyrren 20",
    "sg:city":"Kjellerup",
    "sg:orig_category":"Maskinudlejning",
    "sg:phone":"+45 86 88 23 78",
    "sg:postcode":"8620",
    "sg:province":"Danmark",
    "wof:name":"Kjellerup Maskinudlejning",
    "wof:placetype":"venue"
},
  "geometry": {"coordinates":[9.448636055,56.2771148682],"type":"Point"}
}