{
  "type": "Feature",
  "properties": {
    "addr:full":"Nordrupvej 12 Br\u00f8nsh\u00f8j Danmark 2700",
    "addr:housenumber":"12",
    "addr:postcode":"2700",
    "addr:street":"Nordrupvej",
    "iso:country":"DK",
    "sg:address":"Nordrupvej 12",
    "sg:city":"Br\u00f8nsh\u00f8j",
    "sg:orig_category":"Integrerede institutioner",
    "sg:phone":"+45 38 60 61 77",
    "sg:postcode":"2700",
    "sg:province":"Danmark",
    "wof:name":"Trommen",
    "wof:placetype":"venue"
},
  "geometry": {"coordinates":[-65.6866531372,-23.1981296539],"type":"Point"}
}