{
  "type": "Feature",
  "properties": {
    "addr:full":"Borgergade 103 - 109 Silkeborg Danmark 8600",
    "addr:housenumber":"103 109",
    "addr:postcode":"8600",
    "addr:street":"Borgergade",
    "iso:country":"DK",
    "sg:address":"Borgergade 103 - 109",
    "sg:city":"Silkeborg",
    "sg:orig_category":"Autoforhandlere",
    "sg:phone":"+45 86 82 23 22",
    "sg:postcode":"8600",
    "sg:province":"Danmark",
    "wof:name":"Jakobsen A/S, J\u00f8rgen",
    "wof:placetype":"venue"
},
  "geometry": {"coordinates":[9.5460109711,56.1830215454],"type":"Point"}
}