{
  "type": "Feature",
  "properties": {
    "iso:country":"DK",
    "sg:address":"Skolev\u00e6nget 1, Gr\u00f8nbjerg",
    "sg:city":"Spjald",
    "sg:orig_category":"Kommunale folkeskoler",
    "sg:phone":"+45 97 38 41 77",
    "sg:postcode":"6971",
    "sg:province":"Danmark",
    "wof:name":"Gr\u00f8nbjerg Skole",
    "wof:placetype":"venue"
},
  "geometry": {"coordinates":[8.5089349747,56.1276893616],"type":"Point"}
}