{
  "type": "Feature",
  "properties": {
    "addr:full":"Engen 4 Fjenneslev Danmark 4173",
    "addr:housenumber":"4",
    "addr:postcode":"4173",
    "addr:street":"Engen",
    "iso:country":"DK",
    "sg:address":"Engen 4",
    "sg:city":"Fjenneslev",
    "sg:orig_category":"Revisorer",
    "sg:phone":"+45 57 80 80 50",
    "sg:postcode":"4173",
    "sg:province":"Danmark",
    "sg:website":"www.lk-revision.dk",
    "wof:name":"LK Revision",
    "wof:placetype":"venue"
},
  "geometry": {"coordinates":[11.6656417847,55.4409103394],"type":"Point"}
}