{
  "type": "Feature",
  "properties": {
    "addr:full":"Kongensgade 48 Esbjerg Danmark 6700",
    "addr:housenumber":"48",
    "addr:postcode":"6700",
    "addr:street":"Kongensgade",
    "iso:country":"DK",
    "sg:address":"Kongensgade 48",
    "sg:city":"Esbjerg",
    "sg:classifiers":[
        {
            "category":"Banks & Credit Unions",
            "subcategory":"Bank",
            "type":"Services"
        }
    ],
    "sg:phone":"+45 79 12 60 00",
    "sg:postcode":"6700",
    "sg:province":"Danmark",
    "sg:tags":[
        "banker"
    ],
    "wof:name":"Nordea",
    "wof:placetype":"venue"
},
  "geometry": {"coordinates":[8.4508533478,55.4659805298],"type":"Point"}
}