{
  "type": "Feature",
  "properties": {
    "addr:full":"Kattesundet 15 Aalborg Danmark 9000",
    "addr:housenumber":"15",
    "addr:postcode":"9000",
    "addr:street":"Kattesundet",
    "iso:country":"DK",
    "sg:address":"Kattesundet 15",
    "sg:city":"Aalborg",
    "sg:orig_category":"Antikviteter",
    "sg:phone":"+45 98 13 85 40",
    "sg:postcode":"9000",
    "sg:province":"Danmark",
    "wof:name":"Antikhuset",
    "wof:placetype":"venue"
},
  "geometry": {"coordinates":[9.9170751572,57.0502586365],"type":"Point"}
}