{
  "type": "Feature",
  "properties": {
    "addr:full":"M\u00f8llev\u00e6nget 9, Lyngs Thyholm Danmark 7790",
    "addr:housenumber":"9",
    "addr:postcode":"7790",
    "addr:street":"Mollevaenget;Lyngs",
    "iso:country":"DK",
    "sg:address":"M\u00f8llev\u00e6nget 9, Lyngs",
    "sg:city":"Thyholm",
    "sg:orig_category":"Skorstensfejere",
    "sg:phone":"+45 97 87 81 35",
    "sg:postcode":"7790",
    "sg:province":"Danmark",
    "wof:name":"St\u00f8ttrup, Christen",
    "wof:placetype":"venue"
},
  "geometry": {"coordinates":[8.525765419,56.6507072449],"type":"Point"}
}