{
  "type": "Feature",
  "properties": {
    "addr:full":"Gyvelvej 3, Rebild Sk\u00f8rping Danmark 9520",
    "addr:housenumber":"3",
    "addr:postcode":"9520",
    "addr:street":"Gyvelvej",
    "iso:country":"DK",
    "sg:address":"Gyvelvej 3, Rebild",
    "sg:city":"Sk\u00f8rping",
    "sg:orig_category":"Psykologer, praktiserende",
    "sg:phone":"+45 98 39 17 10",
    "sg:postcode":"9520",
    "sg:province":"Danmark",
    "wof:name":"Overgaard, John",
    "wof:placetype":"venue"
},
  "geometry": {"coordinates":[9.8477077484,56.8337860107],"type":"Point"}
}