{
  "type": "Feature",
  "properties": {
    "iso:country":"DK",
    "sg:address":"v/ Jens Otto Dam-Larsen, Klinteby Kirkevej 2, Ibsker",
    "sg:city":"Nex\u00f8",
    "sg:orig_category":"Kirkelige foreninger",
    "sg:phone":"+45 56 49 40 64",
    "sg:postcode":"3730",
    "sg:province":"Danmark",
    "wof:name":"Indre Mission Nex\u00f8",
    "wof:placetype":"venue"
},
  "geometry": {"coordinates":[15.1096076965,55.0267219543],"type":"Point"}
}