{
  "type": "Feature",
  "properties": {
    "addr:full":"Fmd.: Finn Vester, Dunhammervej 29 Frederikssund Danmark 3600",
    "addr:housenumber":"29",
    "addr:postcode":"3600",
    "addr:street":"Dunhammervej",
    "iso:country":"DK",
    "sg:address":"Fmd.: Finn Vester, Dunhammervej 29",
    "sg:city":"Frederikssund",
    "sg:orig_category":"Festivaler",
    "sg:phone":"+45 47 31 23 32",
    "sg:postcode":"3600",
    "sg:province":"Danmark",
    "sg:website":"www.frederikssund-festival.dk",
    "wof:name":"Frederikssund Festival",
    "wof:placetype":"venue"
},
  "geometry": {"coordinates":[12.0661621094,55.8370323181],"type":"Point"}
}