{
  "type": "Feature",
  "properties": {
    "iso:country":"DK",
    "sg:address":"Industriv\u00e6nget 9",
    "sg:city":"Hornsyld",
    "sg:orig_category":"Genbrugspladser",
    "sg:phone":"+45 75 68 85 88",
    "sg:postcode":"8783",
    "sg:province":"Danmark",
    "wof:name":"Genbrugsstationen",
    "wof:placetype":"venue"
},
  "geometry": {"coordinates":[9.8499288559,55.7597198486],"type":"Point"}
}