{
  "type": "Feature",
  "properties": {
    "addr:full":"Korningvej 65 Horsens Danmark 8700",
    "addr:housenumber":"65",
    "addr:postcode":"8700",
    "addr:street":"Korningvej",
    "iso:country":"DK",
    "sg:address":"Korningvej 65",
    "sg:city":"Horsens",
    "sg:orig_category":"Maskinservice",
    "sg:phone":"+45 75 67 34 20",
    "sg:postcode":"8700",
    "sg:province":"Danmark",
    "wof:name":"Korning Smede- & Maskinforretning Aps.",
    "wof:placetype":"venue"
},
  "geometry": {"coordinates":[9.7341499329,55.8556213379],"type":"Point"}
}