{
  "type": "Feature",
  "properties": {
    "addr:full":"Lykkesholms Alle 37 Frederiksberg Danmark 1902",
    "addr:housenumber":"37;1902",
    "addr:street":"Lykkesholms Alle",
    "iso:country":"DK",
    "sg:address":"Lykkesholms Alle 37",
    "sg:city":"Frederiksberg",
    "sg:orig_category":"Skilte",
    "sg:phone":"+45 33 24 86 66",
    "sg:postcode":"1902",
    "sg:province":"Danmark",
    "wof:name":"PS Skilte",
    "wof:placetype":"venue"
},
  "geometry": {"coordinates":[12.549197197,55.6794967651],"type":"Point"}
}