{
  "type": "Feature",
  "properties": {
    "addr:full":"Bethaniagade 6-8 Herning Danmark 7400",
    "addr:housenumber":"6-8",
    "addr:postcode":"7400",
    "addr:street":"Bethaniagade",
    "iso:country":"DK",
    "sg:address":"Bethaniagade 6-8",
    "sg:city":"Herning",
    "sg:orig_category":"Arkitekter",
    "sg:phone":"+45 97 22 42 27",
    "sg:postcode":"7400",
    "sg:province":"Danmark",
    "wof:name":"\u00c5rstiderne Arkitekter A/S",
    "wof:placetype":"venue"
},
  "geometry": {"coordinates":[8.9725904465,56.1372299194],"type":"Point"}
}