{
  "type": "Feature",
  "properties": {
    "addr:full":"Harreh\u00f8jvej 32, L\u00f8dderup Nyk\u00f8bing Danmark 7900",
    "addr:housenumber":"32",
    "addr:postcode":"7900",
    "addr:street":"Harrehojvej",
    "iso:country":"DK",
    "sg:address":"Harreh\u00f8jvej 32, L\u00f8dderup",
    "sg:city":"Nyk\u00f8bing",
    "sg:orig_category":"Trailere",
    "sg:phone":"+45 97 72 18 83",
    "sg:postcode":"7900",
    "sg:province":"Danmark",
    "wof:name":"Hovm\u00f8ller, Herluf St\u00f8vring",
    "wof:placetype":"venue"
},
  "geometry": {"coordinates":[-114.0768203735,46.4432411194],"type":"Point"}
}