{
  "type": "Feature",
  "properties": {
    "addr:full":"Reberbanen 14 Ringk\u00f8bing Danmark 6950",
    "addr:housenumber":"14",
    "addr:postcode":"6950",
    "addr:street":"Reberbanen",
    "iso:country":"DK",
    "sg:address":"Reberbanen 14",
    "sg:city":"Ringk\u00f8bing",
    "sg:orig_category":"Uldforhandlere",
    "sg:phone":"+45 97 32 30 14",
    "sg:postcode":"6950",
    "sg:province":"Danmark",
    "wof:name":"Sund S\u00f8vn",
    "wof:placetype":"venue"
},
  "geometry": {"coordinates":[-121.4510421753,45.7085266113],"type":"Point"}
}