{
  "type": "Feature",
  "properties": {
    "addr:full":"Svendborgvej 63 Ullerslev Danmark 5540",
    "addr:housenumber":"63",
    "addr:postcode":"5540",
    "addr:street":"Svendborgvej",
    "iso:country":"DK",
    "sg:address":"Svendborgvej 63",
    "sg:city":"Ullerslev",
    "sg:classifiers":[
        {
            "category":"Food & Beverages",
            "subcategory":"Meat & Fish",
            "type":"Retail Goods"
        }
    ],
    "sg:phone":"+45 65 35 39 49",
    "sg:postcode":"5540",
    "sg:province":"Danmark",
    "sg:tags":[
        "fisk",
        "en",
        "gros"
    ],
    "wof:name":"Karlsson Import, H.",
    "wof:placetype":"venue"
},
  "geometry": {"coordinates":[10.6686048508,55.3549118042],"type":"Point"}
}