{
  "type": "Feature",
  "properties": {
    "addr:full":"\u00c5rhusvej 184, Lund Trustrup Danmark 8570",
    "addr:housenumber":"184",
    "addr:postcode":"8570",
    "addr:street":"Aarhusvej",
    "iso:country":"DK",
    "sg:address":"\u00c5rhusvej 184, Lund",
    "sg:city":"Trustrup",
    "sg:orig_category":"Skorstensfejere",
    "sg:phone":"+45 86 33 46 53",
    "sg:postcode":"8570",
    "sg:province":"Danmark",
    "wof:name":"Christensen, Knud E.",
    "wof:placetype":"venue"
},
  "geometry": {"coordinates":[10.7718954086,56.3482666016],"type":"Point"}
}