{
  "type": "Feature",
  "properties": {
    "addr:full":"Jyllands Alle 135 Viby Danmark 8260",
    "addr:housenumber":"135",
    "addr:postcode":"8260",
    "addr:street":"Jyllands Alle",
    "iso:country":"DK",
    "sg:address":"Jyllands Alle 135",
    "sg:city":"Viby",
    "sg:orig_category":"Fodterapeuter",
    "sg:phone":"+45 86 14 16 14",
    "sg:postcode":"8260",
    "sg:province":"Danmark",
    "wof:name":"Klinik for Fodterapi",
    "wof:placetype":"venue"
},
  "geometry": {"coordinates":[10.1822748184,56.1253013611],"type":"Point"}
}