{
  "type": "Feature",
  "properties": {
    "iso:country":"DK",
    "sg:address":"Hegnet 6, H\u00f8bjerg",
    "sg:city":"Helsinge",
    "sg:orig_category":"Arkitekter",
    "sg:phone":"+45 48 76 11 77",
    "sg:postcode":"3200",
    "sg:province":"Danmark",
    "wof:name":"Nielsen, J\u00f8rgen Gert",
    "wof:placetype":"venue"
},
  "geometry": {"coordinates":[12.196846962,56.0224456787],"type":"Point"}
}