{
  "type": "Feature",
  "properties": {
    "addr:full":"Teglv\u00e6rksvej 4, Brundby Sams\u00f8 Danmark 8305",
    "addr:housenumber":"4",
    "addr:postcode":"8305",
    "addr:street":"Teglvaerksvej",
    "iso:country":"DK",
    "sg:address":"Teglv\u00e6rksvej 4, Brundby",
    "sg:city":"Sams\u00f8",
    "sg:orig_category":"Trossamfund uden for folkekirken",
    "sg:phone":"+45 86 59 15 30",
    "sg:postcode":"8305",
    "sg:province":"Danmark",
    "wof:name":"Jehovas Vidners Rigssal",
    "wof:placetype":"venue"
},
  "geometry": {"coordinates":[10.5885000229,55.8320198059],"type":"Point"}
}