{
  "type": "Feature",
  "properties": {
    "iso:country":"DK",
    "sg:address":"Kr\u00e6mmergade 3",
    "sg:city":"Varde",
    "sg:orig_category":"Grillbarer",
    "sg:phone":"+45 75 22 00 57",
    "sg:postcode":"6800",
    "sg:province":"Danmark",
    "wof:name":"P\u00f8lseboden",
    "wof:placetype":"venue"
},
  "geometry": {"coordinates":[8.4813108444,55.6204147339],"type":"Point"}
}