{
  "type": "Feature",
  "properties": {
    "addr:full":"v/ Knud Vad, Sasserbrovej 10 Fjenneslev Danmark 4173",
    "addr:housenumber":"10",
    "addr:postcode":"4173",
    "addr:street":"Vad Sasserbrovej",
    "iso:country":"DK",
    "sg:address":"v/ Knud Vad, Sasserbrovej 10",
    "sg:city":"Fjenneslev",
    "sg:orig_category":"Musik og sang",
    "sg:phone":"+45 57 80 96 39",
    "sg:postcode":"4173",
    "sg:province":"Danmark",
    "wof:name":"Sor\u00f8 Internationale Musikfestival",
    "wof:placetype":"venue"
},
  "geometry": {"coordinates":[11.6678848267,55.4402961731],"type":"Point"}
}