{
  "type": "Feature",
  "properties": {
    "addr:full":"Gl. R\u00f8rbyvej 2, R\u00f8rby Kalundborg Danmark 4400",
    "addr:housenumber":"2",
    "addr:postcode":"4400",
    "addr:street":"Rorbyvej;Rorby",
    "iso:country":"DK",
    "sg:address":"Gl. R\u00f8rbyvej 2, R\u00f8rby",
    "sg:city":"Kalundborg",
    "sg:orig_category":"Posthuse",
    "sg:phone":"+45 59 50 40 02",
    "sg:postcode":"4400",
    "sg:province":"Danmark",
    "wof:name":"Post Danmark, R\u00f8rby Posthus",
    "wof:placetype":"venue"
},
  "geometry": {"coordinates":[11.0934085846,55.6797485352],"type":"Point"}
}