{
  "type": "Feature",
  "properties": {
    "addr:full":"Julius Bloms Gade 49, 4. th. K\u00f8benhavn N Danmark 2200",
    "addr:housenumber":"49 4 th. kobenhavn",
    "addr:postcode":"2200",
    "addr:street":"Julius Bloms Gade;N Danmark",
    "iso:country":"DK",
    "sg:address":"Julius Bloms Gade 49, 4. th.",
    "sg:city":"K\u00f8benhavn N",
    "sg:orig_category":"Musikere",
    "sg:phone":"+45 35 85 84 34",
    "sg:postcode":"2200",
    "sg:province":"Danmark",
    "wof:name":"R\u00f8mer, Ole",
    "wof:placetype":"venue"
},
  "geometry": {"coordinates":[-75.7513656616,43.2285461426],"type":"Point"}
}