{
  "type": "Feature",
  "properties": {
    "addr:full":"N\u00f8rre Alle 25, 1. Kalundborg Danmark 4400",
    "addr:housenumber":"25 1",
    "addr:postcode":"4400",
    "addr:street":"Norre Alle",
    "iso:country":"DK",
    "sg:address":"N\u00f8rre Alle 25, 1.",
    "sg:city":"Kalundborg",
    "sg:orig_category":"Distriktspsykiatri",
    "sg:phone":"+45 59 51 45 46",
    "sg:postcode":"4400",
    "sg:province":"Danmark",
    "wof:name":"Distriktspsykiatrisk Center",
    "wof:placetype":"venue"
},
  "geometry": {"coordinates":[11.0975170135,55.6838340759],"type":"Point"}
}