{
  "type": "Feature",
  "properties": {
    "addr:full":"Skolegade 33 - 35 \u00c5rhus C Danmark 8000",
    "addr:housenumber":"33 35",
    "addr:postcode":"8000",
    "addr:street":"Skolegade",
    "iso:country":"DK",
    "sg:address":"Skolegade 33 - 35",
    "sg:city":"\u00c5rhus C",
    "sg:classifiers":[
        {
            "category":"Restaurant",
            "type":"Food & Drink"
        }
    ],
    "sg:phone":"+45 86 13 27 55",
    "sg:postcode":"8000",
    "sg:province":"Danmark",
    "wof:name":"Bone's",
    "wof:placetype":"venue"
},
  "geometry": {"coordinates":[9.5235595703,55.7128295898],"type":"Point"}
}