{
  "type": "Feature",
  "properties": {
    "addr:full":"Torvet 5 Gr\u00e5sten Danmark 6300",
    "addr:housenumber":"5",
    "addr:postcode":"6300",
    "addr:street":"Torvet",
    "iso:country":"DK",
    "sg:address":"Torvet 5",
    "sg:city":"Gr\u00e5sten",
    "sg:orig_category":"Cafeer",
    "sg:phone":"+45 74 65 34 15",
    "sg:postcode":"6300",
    "sg:province":"Danmark",
    "wof:name":"Slotscaf\u00e9en",
    "wof:placetype":"venue"
},
  "geometry": {"coordinates":[7.6853618622,62.5582695007],"type":"Point"}
}