{
  "type": "Feature",
  "properties": {
    "addr:full":"Lyngby STORcenter 81 Kongens Lyngby Danmark 2800",
    "addr:housenumber":"81",
    "addr:postcode":"2800",
    "addr:street":"Lyngby Storcenter",
    "iso:country":"DK",
    "sg:address":"Lyngby STORcenter 81",
    "sg:city":"Kongens Lyngby",
    "sg:orig_category":"Konfekture",
    "sg:phone":"+45 45 87 00 53",
    "sg:postcode":"2800",
    "sg:province":"Danmark",
    "wof:name":"Sv.Michelsen Chokolade",
    "wof:placetype":"venue"
},
  "geometry": {"coordinates":[12.5042438507,55.7721824646],"type":"Point"}
}