{
  "type": "Feature",
  "properties": {
    "addr:full":"\u00d8rnebjergvej 25 Glostrup Danmark 2600",
    "addr:housenumber":"25",
    "addr:postcode":"2600",
    "addr:street":"Ornebjergvej",
    "iso:country":"DK",
    "sg:address":"\u00d8rnebjergvej 25",
    "sg:city":"Glostrup",
    "sg:orig_category":"Zoneterapeuter",
    "sg:phone":"+45 43 45 13 78",
    "sg:postcode":"2600",
    "sg:province":"Danmark",
    "sg:website":"www.alternativ-behandling.dk",
    "wof:name":"Pedersen, Edel",
    "wof:placetype":"venue"
},
  "geometry": {"coordinates":[12.4099359512,55.6622962952],"type":"Point"}
}