{
  "type": "Feature",
  "properties": {
    "addr:full":"Betulavej 5 Helsinge Danmark 3200",
    "addr:housenumber":"5",
    "addr:postcode":"3200",
    "addr:street":"Betulavej",
    "iso:country":"DK",
    "sg:address":"Betulavej 5",
    "sg:city":"Helsinge",
    "sg:orig_category":"Katte",
    "sg:phone":"+45 48 79 64 68",
    "sg:postcode":"3200",
    "sg:province":"Danmark",
    "sg:website":"www.persefelis.dk",
    "wof:name":"Katteri de' Perse'felis",
    "wof:placetype":"venue"
},
  "geometry": {"coordinates":[12.2115030289,56.012046814],"type":"Point"}
}