{
  "type": "Feature",
  "properties": {
    "addr:full":"Frueled 56 Nyk\u00f8bing Danmark 7900",
    "addr:housenumber":"56",
    "addr:postcode":"7900",
    "addr:street":"Frueled",
    "iso:country":"DK",
    "sg:address":"Frueled 56",
    "sg:city":"Nyk\u00f8bing",
    "sg:orig_category":"Daginstitution for voksne",
    "sg:phone":"+45 97 72 21 91",
    "sg:postcode":"7900",
    "sg:province":"Danmark",
    "wof:name":"Frueled 56",
    "wof:placetype":"venue"
},
  "geometry": {"coordinates":[-114.0768203735,46.4432411194],"type":"Point"}
}