{
  "type": "Feature",
  "properties": {
    "addr:full":"Kildebjerget, Sanatorievej 1 Stouby Danmark 7140",
    "addr:housenumber":"1",
    "addr:postcode":"7140",
    "addr:street":"Sanatorievej",
    "iso:country":"DK",
    "sg:address":"Kildebjerget, Sanatorievej 1",
    "sg:city":"Stouby",
    "sg:orig_category":"Handicapboliger",
    "sg:phone":"+45 75 89 74 55",
    "sg:postcode":"7140",
    "sg:province":"Danmark",
    "sg:website":"www.kildebjerget.dk",
    "wof:name":"Vejle Amts Kostskole",
    "wof:placetype":"venue"
},
  "geometry": {"coordinates":[9.7896795273,55.7045059204],"type":"Point"}
}