{
  "type": "Feature",
  "properties": {
    "addr:full":"Jegstrupvej 80 Viborg Danmark 8800",
    "addr:housenumber":"80",
    "addr:postcode":"8800",
    "addr:street":"Jegstrupvej",
    "iso:country":"DK",
    "sg:address":"Jegstrupvej 80",
    "sg:city":"Viborg",
    "sg:classifiers":[
        {
            "category":"Home & Garden",
            "subcategory":"Home Furnishings",
            "type":"Retail Goods"
        }
    ],
    "sg:phone":"+45 86 62 97 35",
    "sg:postcode":"8800",
    "sg:province":"Danmark",
    "sg:tags":[
        "gardiner"
    ],
    "wof:name":"Viborg Gardinservice",
    "wof:placetype":"venue"
},
  "geometry": {"coordinates":[9.3819770813,56.455909729],"type":"Point"}
}