{
  "type": "Feature",
  "properties": {
    "iso:country":"DK",
    "sg:address":"S\u00f8ndergade 6",
    "sg:city":"Vejle",
    "sg:classifiers":[
        {
            "category":"Restaurant",
            "type":"Food & Drink"
        }
    ],
    "sg:phone":"+45 75 83 97 77",
    "sg:postcode":"7100",
    "sg:province":"Danmark",
    "wof:name":"Asian Wok House",
    "wof:placetype":"venue"
},
  "geometry": {"coordinates":[9.5325622559,55.7075996399],"type":"Point"}
}