{
  "type": "Feature",
  "properties": {
    "iso:country":"DK",
    "sg:address":"Parallelvej 63",
    "sg:city":"Hvide Sande",
    "sg:orig_category":"Blomsterhandlere",
    "sg:phone":"+45 97 31 22 61",
    "sg:postcode":"6960",
    "sg:province":"Danmark",
    "wof:name":"Vitas Blomster",
    "wof:placetype":"venue"
},
  "geometry": {"coordinates":[8.1222438812,56.0879821777],"type":"Point"}
}