{
  "type": "Feature",
  "properties": {
    "addr:full":"v/ Erik Busk, \u00c6blehaven 118 Egtved Danmark 6040",
    "addr:housenumber":"118",
    "addr:postcode":"6040",
    "addr:street":"Aeblehaven",
    "iso:country":"DK",
    "sg:address":"v/ Erik Busk, \u00c6blehaven 118",
    "sg:city":"Egtved",
    "sg:orig_category":"Musik og sang",
    "sg:phone":"+45 75 55 23 50",
    "sg:postcode":"6040",
    "sg:province":"Danmark",
    "wof:name":"Egtved Harmonikaforening",
    "wof:placetype":"venue"
},
  "geometry": {"coordinates":[9.3087482452,55.6161613464],"type":"Point"}
}