{
  "type": "Feature",
  "properties": {
    "iso:country":"DK",
    "sg:address":"\u00d8stervangsvej 1, Fausing",
    "sg:city":"Alling\u00e5bro",
    "sg:orig_category":"Autoforhandlere",
    "sg:phone":"+45 86 48 10 66",
    "sg:postcode":"8961",
    "sg:province":"Danmark",
    "wof:name":"Thomsen A/S, Tage",
    "wof:placetype":"venue"
},
  "geometry": {"coordinates":[10.3230552673,56.4639511108],"type":"Point"}
}