{
  "type": "Feature",
  "properties": {
    "addr:full":"S\u00f8stersvej 8, Ejby Kirke Hyllinge Danmark 4070",
    "addr:housenumber":"8",
    "addr:postcode":"4070",
    "addr:street":"Sostersvej",
    "iso:country":"DK",
    "sg:address":"S\u00f8stersvej 8, Ejby",
    "sg:city":"Kirke Hyllinge",
    "sg:orig_category":"Vinduespolering",
    "sg:phone":"+45 46 40 56 24",
    "sg:postcode":"4070",
    "sg:province":"Danmark",
    "wof:name":"Andersen, Frank",
    "wof:placetype":"venue"
},
  "geometry": {"coordinates":[11.9004745483,55.7080039978],"type":"Point"}
}