{
  "type": "Feature",
  "properties": {
    "iso:country":"DK",
    "sg:address":"Om\u00f8gade 1-3",
    "sg:city":"K\u00f8benhavn \u00d8",
    "sg:orig_category":"Benzinstationer",
    "sg:phone":"+45 39 29 59 22",
    "sg:postcode":"2100",
    "sg:province":"Danmark",
    "wof:name":"Danry's Autocenter",
    "wof:placetype":"venue"
},
  "geometry": {"coordinates":[55.859261,20.81435],"type":"Point"}
}