{
  "type": "Feature",
  "properties": {
    "addr:full":"v/ Herdis Jensen, Mellemlundvej 17, K\u00f8lk\u00e6r Herning Danmark 7400",
    "addr:housenumber":"17",
    "addr:postcode":"7400",
    "addr:street":"Mellemlundvej;Kolkaer",
    "iso:country":"DK",
    "sg:address":"v/ Herdis Jensen, Mellemlundvej 17, K\u00f8lk\u00e6r",
    "sg:city":"Herning",
    "sg:orig_category":"Legestuer",
    "sg:phone":"+45 97 14 71 48",
    "sg:postcode":"7400",
    "sg:province":"Danmark",
    "wof:name":"Lind FDF/FPF Legestue",
    "wof:placetype":"venue"
},
  "geometry": {"coordinates":[8.9768896103,56.1374168396],"type":"Point"}
}