{
  "type": "Feature",
  "properties": {
    "addr:full":"Gammel R\u00f8nnebjergvej 9, Poulstrup Vr\u00e5 Danmark 9760",
    "addr:housenumber":"9",
    "addr:postcode":"9760",
    "addr:street":"Gammel Ronnebjergvej",
    "iso:country":"DK",
    "sg:address":"Gammel R\u00f8nnebjergvej 9, Poulstrup",
    "sg:city":"Vr\u00e5",
    "sg:orig_category":"Dagcentre",
    "sg:phone":"+45 98 98 80 11",
    "sg:postcode":"9760",
    "sg:province":"Danmark",
    "wof:name":"Aktivitetscentret",
    "wof:placetype":"venue"
},
  "geometry": {"coordinates":[9.9477567673,57.3534927368],"type":"Point"}
}