{
  "type": "Feature",
  "properties": {
    "addr:full":"Vongevej 39, Sandvad Jelling Danmark 7300",
    "addr:housenumber":"39",
    "addr:postcode":"7300",
    "addr:street":"Vongevej",
    "iso:country":"DK",
    "sg:address":"Vongevej 39, Sandvad",
    "sg:city":"Jelling",
    "sg:orig_category":"Autoreparation og -service",
    "sg:phone":"+45 75 87 30 65",
    "sg:postcode":"7300",
    "sg:province":"Danmark",
    "wof:name":"Sandvad Autov\u00e6rksted",
    "wof:placetype":"venue"
},
  "geometry": {"coordinates":[9.4184103012,55.7558555603],"type":"Point"}
}