{
  "type": "Feature",
  "properties": {
    "addr:full":"Strandparksvej 2, Saksild Str. Odder Danmark 8300",
    "addr:housenumber":"2",
    "addr:postcode":"8300",
    "addr:street":"Strandparksvej;Str.",
    "iso:country":"DK",
    "sg:address":"Strandparksvej 2, Saksild Str.",
    "sg:city":"Odder",
    "sg:orig_category":"Kiosker",
    "sg:phone":"+45 86 55 86 33",
    "sg:postcode":"8300",
    "sg:province":"Danmark",
    "wof:name":"Strandparkens Kiosk",
    "wof:placetype":"venue"
},
  "geometry": {"coordinates":[10.1497612,55.9733161926],"type":"Point"}
}