{
  "type": "Feature",
  "properties": {
    "iso:country":"DK",
    "sg:address":"Vestre Strandvej 6",
    "sg:city":"Skagen",
    "sg:classifiers":[
        {
            "category":"Food & Beverages",
            "subcategory":"Liquor & Beverages",
            "type":"Retail Goods"
        }
    ],
    "sg:phone":"+45 98 44 13 33",
    "sg:postcode":"9990",
    "sg:province":"Danmark",
    "sg:tags":[
        "vin"
    ],
    "wof:name":"Christiansens Eftf., Harald",
    "wof:placetype":"venue"
},
  "geometry": {"coordinates":[10.587761879,57.7197608948],"type":"Point"}
}