{
  "type": "Feature",
  "properties": {
    "addr:full":"Industrivej 42 Thisted Danmark 7700",
    "addr:housenumber":"42",
    "addr:postcode":"7700",
    "addr:street":"Industrivej",
    "iso:country":"DK",
    "sg:address":"Industrivej 42",
    "sg:city":"Thisted",
    "sg:orig_category":"Skadeservice",
    "sg:phone":"+45 70 11 21 12",
    "sg:postcode":"7700",
    "sg:province":"Danmark",
    "wof:name":"Skadeservice Danmark",
    "wof:placetype":"venue"
},
  "geometry": {"coordinates":[8.7175140381,56.9624633789],"type":"Point"}
}