{
  "type": "Feature",
  "properties": {
    "addr:full":"Vestergade 37 Randers Danmark 8900",
    "addr:housenumber":"37",
    "addr:postcode":"8900",
    "addr:street":"Vestergade",
    "iso:country":"DK",
    "sg:address":"Vestergade 37",
    "sg:city":"Randers",
    "sg:orig_category":"Genbrugsbutikker",
    "sg:phone":"+45 87 12 04 07",
    "sg:postcode":"8900",
    "sg:province":"Danmark",
    "wof:name":"Bl\u00e5 Kors M\u00f8bler",
    "wof:placetype":"venue"
},
  "geometry": {"coordinates":[10.0269870758,56.461265564],"type":"Point"}
}