{
  "type": "Feature",
  "properties": {
    "addr:full":"Banevej 8 Tisvildeleje Danmark 3220",
    "addr:housenumber":"8",
    "addr:postcode":"3220",
    "addr:street":"Banevej",
    "iso:country":"DK",
    "sg:address":"Banevej 8",
    "sg:city":"Tisvildeleje",
    "sg:orig_category":"Jernbaner",
    "sg:phone":"+45 48 70 71 06",
    "sg:postcode":"3220",
    "sg:province":"Danmark",
    "wof:name":"Gribskovbanen, Tisvildeleje Station",
    "wof:placetype":"venue"
},
  "geometry": {"coordinates":[12.0777082443,56.0589675903],"type":"Point"}
}