{
  "type": "Feature",
  "properties": {
    "addr:full":"Engdalsvej 12 Brabrand Danmark 8220",
    "addr:housenumber":"12",
    "addr:postcode":"8220",
    "addr:street":"Engdalsvej",
    "iso:country":"DK",
    "sg:address":"Engdalsvej 12",
    "sg:city":"Brabrand",
    "sg:orig_category":"Plejehjem",
    "sg:phone":"+45 87 47 73 10",
    "sg:postcode":"8220",
    "sg:province":"Danmark",
    "wof:name":"Engg\u00e5rden Plejehjem",
    "wof:placetype":"venue"
},
  "geometry": {"coordinates":[10.1063346863,56.1520767212],"type":"Point"}
}