{
  "type": "Feature",
  "properties": {
    "addr:full":"Sdr. Boulevard 85 Odense C Danmark 5000",
    "addr:housenumber":"85",
    "addr:postcode":"5000",
    "addr:street":"Sdr. Boulevard",
    "iso:country":"DK",
    "sg:address":"Sdr. Boulevard 85",
    "sg:city":"Odense C",
    "sg:orig_category":"Flytteforretninger",
    "sg:phone":"+45 66 11 05 66",
    "sg:postcode":"5000",
    "sg:province":"Danmark",
    "wof:name":"Odense ny Flytteforretning",
    "wof:placetype":"venue"
},
  "geometry": {"coordinates":[10.3709096909,55.3770866394],"type":"Point"}
}