{
  "type": "Feature",
  "properties": {
    "addr:full":"Halsskov Tv\u00e6rvej 1 Kors\u00f8r Danmark 4220",
    "addr:housenumber":"1",
    "addr:postcode":"4220",
    "addr:street":"Tvaervej",
    "iso:country":"DK",
    "sg:address":"Halsskov Tv\u00e6rvej 1",
    "sg:city":"Kors\u00f8r",
    "sg:orig_category":"Tandklinikker, Kommunale",
    "sg:phone":"+45 58 37 76 76",
    "sg:postcode":"4220",
    "sg:province":"Danmark",
    "wof:name":"Halskovskolens Tandklinik",
    "wof:placetype":"venue"
},
  "geometry": {"coordinates":[11.2105474472,55.3797225952],"type":"Point"}
}