{
  "type": "Feature",
  "properties": {
    "addr:full":"Horsensvej 148, \u00d8rting Odder Danmark 8300",
    "addr:housenumber":"148",
    "addr:postcode":"8300",
    "addr:street":"Horsensvej",
    "iso:country":"DK",
    "sg:address":"Horsensvej 148, \u00d8rting",
    "sg:city":"Odder",
    "sg:orig_category":"Autoreparation og -service",
    "sg:phone":"+45 86 55 42 25",
    "sg:postcode":"8300",
    "sg:province":"Danmark",
    "wof:name":"Sejersb\u00f8l, Peter",
    "wof:placetype":"venue"
},
  "geometry": {"coordinates":[10.1497612,55.9733161926],"type":"Point"}
}