{
  "type": "Feature",
  "properties": {
    "addr:full":"v/ Tommy Holm, Asylgade 28, st.mf. Roskilde Danmark 4000",
    "addr:housenumber":"28",
    "addr:postcode":"4000",
    "addr:street":"Asylgade",
    "iso:country":"DK",
    "sg:address":"v/ Tommy Holm, Asylgade 28, st.mf.",
    "sg:city":"Roskilde",
    "sg:orig_category":"\u00c3\u2020ldreorganisationer og klubber",
    "sg:phone":"+45 46 36 49 14",
    "sg:postcode":"4000",
    "sg:province":"Danmark",
    "wof:name":"Tv\u00e6rfaglig Efterl\u00f8n-og Pensionistklub",
    "wof:placetype":"venue"
},
  "geometry": {"coordinates":[12.0909376144,55.6404838562],"type":"Point"}
}