{
  "type": "Feature",
  "properties": {
    "iso:country":"DK",
    "sg:address":"\u00d8sterled 38",
    "sg:city":"Hals",
    "sg:orig_category":"Zoneterapeuter",
    "sg:phone":"+45 98 25 16 09",
    "sg:postcode":"9370",
    "sg:province":"Danmark",
    "wof:name":"Christiansen, Tove",
    "wof:placetype":"venue"
},
  "geometry": {"coordinates":[10.3162403107,56.993927002],"type":"Point"}
}