{
  "type": "Feature",
  "properties": {
    "addr:full":"Langes\u00f8vej 148, Langes\u00f8 Morud Danmark 5462",
    "addr:housenumber":"148",
    "addr:postcode":"5462",
    "addr:street":"Langesovej;Langeso",
    "iso:country":"DK",
    "sg:address":"Langes\u00f8vej 148, Langes\u00f8",
    "sg:city":"Morud",
    "sg:orig_category":"Maskinstationer",
    "sg:phone":"+45 65 96 42 49",
    "sg:postcode":"5462",
    "sg:province":"Danmark",
    "wof:name":"Bl\u00e6sbjerg, Mogens",
    "wof:placetype":"venue"
},
  "geometry": {"coordinates":[10.1872348785,55.44323349],"type":"Point"}
}