{
  "type": "Feature",
  "properties": {
    "addr:full":"Nytorv 2 Thisted Danmark 7700",
    "addr:housenumber":"2",
    "addr:postcode":"7700",
    "addr:street":"Nytorv",
    "iso:country":"DK",
    "sg:address":"Nytorv 2",
    "sg:city":"Thisted",
    "sg:orig_category":"Systuer",
    "sg:phone":"+45 97 92 11 50",
    "sg:postcode":"7700",
    "sg:province":"Danmark",
    "wof:name":"Skr\u00e6dderiet",
    "wof:placetype":"venue"
},
  "geometry": {"coordinates":[8.6925373077,56.9557189941],"type":"Point"}
}