{
  "type": "Feature",
  "properties": {
    "addr:full":"Gindeskovvej 22, Feldborg Haderup Danmark 7540",
    "addr:housenumber":"22",
    "addr:postcode":"7540",
    "addr:street":"Gindeskovvej",
    "iso:country":"DK",
    "sg:address":"Gindeskovvej 22, Feldborg",
    "sg:city":"Haderup",
    "sg:orig_category":"Planteskoler",
    "sg:phone":"+45 97 45 43 21",
    "sg:postcode":"7540",
    "sg:province":"Danmark",
    "sg:website":"www.lundhede.com",
    "wof:name":"Lundhede Planteskole",
    "wof:placetype":"venue"
},
  "geometry": {"coordinates":[8.9933700562,56.3879814148],"type":"Point"}
}