{
  "type": "Feature",
  "properties": {
    "addr:full":"Ellehammers Alle 3, 2. tv. Billund Danmark 7190",
    "addr:housenumber":"3 2 tv.",
    "addr:postcode":"7190",
    "addr:street":"Ellehammers Alle",
    "iso:country":"DK",
    "sg:address":"Ellehammers Alle 3, 2. tv.",
    "sg:city":"Billund",
    "sg:orig_category":"Jordemodercentre",
    "sg:phone":"+45 75 35 31 65",
    "sg:postcode":"7190",
    "sg:province":"Danmark",
    "wof:name":"Billund Jordemoderkonsultation",
    "wof:placetype":"venue"
},
  "geometry": {"coordinates":[9.1138372421,55.7316017151],"type":"Point"}
}