{
  "type": "Feature",
  "properties": {
    "addr:full":"Snejbjerg Hovedgade 28 Herning Danmark 7400",
    "addr:housenumber":"28",
    "addr:postcode":"7400",
    "addr:street":"Snejbjerg Hovedgade",
    "iso:country":"DK",
    "sg:address":"Snejbjerg Hovedgade 28",
    "sg:city":"Herning",
    "sg:orig_category":"Kunsthandlere",
    "sg:phone":"+45 97 16 13 59",
    "sg:postcode":"7400",
    "sg:province":"Danmark",
    "wof:name":"Malericentralen",
    "wof:placetype":"venue"
},
  "geometry": {"coordinates":[8.8821210861,56.1303520203],"type":"Point"}
}