{
  "type": "Feature",
  "properties": {
    "addr:full":"Vesterbrogade 4 B Gilleleje Danmark 3250",
    "addr:housenumber":"4 b",
    "addr:postcode":"3250",
    "addr:street":"Vesterbrogade",
    "iso:country":"DK",
    "sg:address":"Vesterbrogade 4 B",
    "sg:city":"Gilleleje",
    "sg:orig_category":"HOTELS: OG MOTELLER",
    "sg:phone":"+45 48 30 05 12",
    "sg:postcode":"3250",
    "sg:province":"Danmark",
    "sg:website":"www.hotel-strand.dk",
    "wof:name":"Hotel Strand A/S",
    "wof:placetype":"venue"
},
  "geometry": {"coordinates":[12.3053741455,56.125793457],"type":"Point"}
}