{
  "type": "Feature",
  "properties": {
    "addr:full":"Gammel Klausdalsbrovej 480 Herlev Danmark 2730",
    "addr:housenumber":"480",
    "addr:postcode":"2730",
    "addr:street":"Gammel Klausdalsbrovej",
    "iso:country":"DK",
    "sg:address":"Gammel Klausdalsbrovej 480",
    "sg:city":"Herlev",
    "sg:orig_category":"Oliefyr og service",
    "sg:phone":"+45 44 53 53 44",
    "sg:postcode":"2730",
    "sg:province":"Danmark",
    "sg:website":"www.kaidigebach.dk",
    "wof:name":"bach olie a-s, kai dige",
    "wof:placetype":"venue"
},
  "geometry": {"coordinates":[12.4160985947,55.743270874],"type":"Point"}
}