{
  "type": "Feature",
  "properties": {
    "addr:full":"\u00d8ster Madevej 8 Aabenraa Danmark 6200",
    "addr:housenumber":"8",
    "addr:postcode":"6200",
    "addr:street":"Oster Madevej",
    "iso:country":"DK",
    "sg:address":"\u00d8ster Madevej 8",
    "sg:city":"Aabenraa",
    "sg:orig_category":"Kemisk industri",
    "sg:phone":"+45 74 62 91 92",
    "sg:postcode":"6200",
    "sg:province":"Danmark",
    "wof:name":"Chemex Products A/S",
    "wof:placetype":"venue"
},
  "geometry": {"coordinates":[9.4314155579,55.0465774536],"type":"Point"}
}