{
  "type": "Feature",
  "properties": {
    "iso:country":"DK",
    "sg:address":"Assensvej 461",
    "sg:city":"Millinge",
    "sg:orig_category":"Campingpladser",
    "sg:phone":"+45 62 68 10 95",
    "sg:postcode":"5642",
    "sg:province":"Danmark",
    "wof:name":"Faldsled Strand Camping",
    "wof:placetype":"venue"
},
  "geometry": {"coordinates":[10.1537866592,55.1472816467],"type":"Point"}
}