{
  "type": "Feature",
  "properties": {
    "addr:full":"Bakkedalsvej 25, R\u00e5rup Juelsminde Danmark 7130",
    "addr:housenumber":"25",
    "addr:postcode":"7130",
    "addr:street":"Bakkedalsvej;Raarup",
    "iso:country":"DK",
    "sg:address":"Bakkedalsvej 25, R\u00e5rup",
    "sg:city":"Juelsminde",
    "sg:orig_category":"Skolefritidsordninger",
    "sg:phone":"+45 75 68 59 52",
    "sg:postcode":"7130",
    "sg:province":"Danmark",
    "wof:name":"R\u00e5rup Skolefritidsordning",
    "wof:placetype":"venue"
},
  "geometry": {"coordinates":[10.0143985748,55.7135848999],"type":"Point"}
}