{
  "type": "Feature",
  "properties": {
    "addr:full":"Jernbanegade 55 Hadsund Danmark 9560",
    "addr:housenumber":"55",
    "addr:postcode":"9560",
    "addr:street":"Jernbanegade",
    "iso:country":"DK",
    "sg:address":"Jernbanegade 55",
    "sg:city":"Hadsund",
    "sg:orig_category":"Skilte",
    "sg:phone":"+45 21 91 21 35",
    "sg:postcode":"9560",
    "sg:province":"Danmark",
    "wof:name":"William Skilte",
    "wof:placetype":"venue"
},
  "geometry": {"coordinates":[10.1234140396,56.72032547],"type":"Point"}
}