{
  "type": "Feature",
  "properties": {
    "addr:full":"Algade 28 B Roskilde Danmark 4000",
    "addr:housenumber":"28 b",
    "addr:postcode":"4000",
    "addr:street":"Algade",
    "iso:country":"DK",
    "sg:address":"Algade 28 B",
    "sg:city":"Roskilde",
    "sg:orig_category":"Kiropraktorer",
    "sg:phone":"+45 46 35 23 80",
    "sg:postcode":"4000",
    "sg:province":"Danmark",
    "wof:name":"Bolding, Kirsten",
    "wof:placetype":"venue"
},
  "geometry": {"coordinates":[12.0859203339,55.6410293579],"type":"Point"}
}