{
  "type": "Feature",
  "properties": {
    "addr:full":"Fmd.: Erik Breum Petersen, Vistorpvej 31, S\u00f8llested Glamsbjerg Danmark 5620",
    "addr:housenumber":"31",
    "addr:postcode":"5620",
    "addr:street":"Vistorpvej;Sollested",
    "iso:country":"DK",
    "sg:address":"Fmd.: Erik Breum Petersen, Vistorpvej 31, S\u00f8llested",
    "sg:city":"Glamsbjerg",
    "sg:orig_category":"Hobbybetonede foreninger",
    "sg:phone":"+45 64 79 22 88",
    "sg:postcode":"5620",
    "sg:province":"Danmark",
    "wof:name":"Odense Go-klub",
    "wof:placetype":"venue"
},
  "geometry": {"coordinates":[10.1052503586,55.2783317566],"type":"Point"}
}