{
  "type": "Feature",
  "properties": {
    "addr:full":"Teglovnsvej 40 Ringsted Danmark 4100",
    "addr:housenumber":"40",
    "addr:postcode":"4100",
    "addr:street":"Teglovnsvej",
    "iso:country":"DK",
    "sg:address":"Teglovnsvej 40",
    "sg:city":"Ringsted",
    "sg:orig_category":"Advokater",
    "sg:phone":"+45 57 67 63 03",
    "sg:postcode":"4100",
    "sg:province":"Danmark",
    "wof:name":"Olsen, Ole Karsten",
    "wof:placetype":"venue"
},
  "geometry": {"coordinates":[11.7977666855,55.4485244751],"type":"Point"}
}