{
  "type": "Feature",
  "properties": {
    "addr:full":"Smedev\u00e6nget 13, Stenstrup N\u00e6stved Danmark 4700",
    "addr:housenumber":"13",
    "addr:postcode":"4700",
    "addr:street":"Smedevaenget",
    "iso:country":"DK",
    "sg:address":"Smedev\u00e6nget 13, Stenstrup",
    "sg:city":"N\u00e6stved",
    "sg:orig_category":"Isolering",
    "sg:phone":"+45 55 70 24 25",
    "sg:postcode":"4700",
    "sg:province":"Danmark",
    "wof:name":"Revsb\u00e6k A/S",
    "wof:placetype":"venue"
},
  "geometry": {"coordinates":[11.7542486191,55.2315444946],"type":"Point"}
}