{
  "type": "Feature",
  "properties": {
    "addr:full":"K\u00e6lderbjergvej 9 Vejby Danmark 3210",
    "addr:housenumber":"9",
    "addr:postcode":"3210",
    "addr:street":"Kaelderbjergvej",
    "iso:country":"DK",
    "sg:address":"K\u00e6lderbjergvej 9",
    "sg:city":"Vejby",
    "sg:orig_category":"Dag- og distriktsblade",
    "sg:phone":"+45 48 70 53 03",
    "sg:postcode":"3210",
    "sg:province":"Danmark",
    "wof:name":"Bladgruppen for Vejby Nyt I/S",
    "wof:placetype":"venue"
},
  "geometry": {"coordinates":[12.1404037476,56.0654792786],"type":"Point"}
}