{
  "type": "Feature",
  "properties": {
    "addr:full":"Drosselvej 13 Kolding Danmark 6000",
    "addr:housenumber":"13",
    "addr:postcode":"6000",
    "addr:street":"Drosselvej",
    "iso:country":"DK",
    "sg:address":"Drosselvej 13",
    "sg:city":"Kolding",
    "sg:orig_category":"Flytteforretninger",
    "sg:phone":"+45 75 52 14 40",
    "sg:postcode":"6000",
    "sg:province":"Danmark",
    "wof:name":"Ulrichs Flytteforretning",
    "wof:placetype":"venue"
},
  "geometry": {"coordinates":[9.4639358521,55.5005683899],"type":"Point"}
}