{
  "type": "Feature",
  "properties": {
    "addr:full":"Knapholm 8 Herlev Danmark 2730",
    "addr:housenumber":"8",
    "addr:postcode":"2730",
    "addr:street":"Knapholm",
    "iso:country":"DK",
    "sg:address":"Knapholm 8",
    "sg:city":"Herlev",
    "sg:orig_category":"Hydraulik",
    "sg:phone":"+45 44 54 07 66",
    "sg:postcode":"2730",
    "sg:province":"Danmark",
    "sg:website":"www.sawo.dk",
    "wof:name":"Sawo Hydraulic A/S",
    "wof:placetype":"venue"
},
  "geometry": {"coordinates":[12.4253749847,55.7192001343],"type":"Point"}
}