{
  "type": "Feature",
  "properties": {
    "iso:country":"DK",
    "sg:address":"Ahlgade 28",
    "sg:city":"Holb\u00e6k",
    "sg:classifiers":[
        {
            "category":"Banks & Credit Unions",
            "subcategory":"Bank",
            "type":"Services"
        }
    ],
    "sg:phone":"+45 59 48 82 00",
    "sg:postcode":"4300",
    "sg:province":"Danmark",
    "sg:tags":[
        "banker"
    ],
    "sg:website":"www.danskebank.dk",
    "wof:name":"Danske Bank",
    "wof:placetype":"venue"
},
  "geometry": {"coordinates":[76.307098,14.27713],"type":"Point"}
}