{
  "type": "Feature",
  "properties": {
    "iso:country":"DK",
    "sg:address":"Nygade 11",
    "sg:city":"Kors\u00f8r",
    "sg:orig_category":"Dag- og distriktsblade",
    "sg:phone":"+45 58 37 00 68",
    "sg:postcode":"4220",
    "sg:province":"Danmark",
    "wof:name":"Sj\u00e6llands Tidende",
    "wof:placetype":"venue"
},
  "geometry": {"coordinates":[11.2105474472,55.3797225952],"type":"Point"}
}