{
  "type": "Feature",
  "properties": {
    "addr:full":"Fmd.: Kurt Nielsen, Benl\u00f8se By 22, Benl\u00f8se Ringsted Danmark 4100",
    "addr:housenumber":"22",
    "addr:postcode":"4100",
    "addr:street":"Benlose",
    "iso:country":"DK",
    "sg:address":"Fmd.: Kurt Nielsen, Benl\u00f8se By 22, Benl\u00f8se",
    "sg:city":"Ringsted",
    "sg:orig_category":"Spejderkorps",
    "sg:phone":"+45 57 61 92 11",
    "sg:postcode":"4100",
    "sg:province":"Danmark",
    "wof:name":"DDS, Ringsted gruppe",
    "wof:placetype":"venue"
},
  "geometry": {"coordinates":[11.7875862122,55.4458961487],"type":"Point"}
}