{
  "type": "Feature",
  "properties": {
    "addr:full":"Gren\u00e5vej 26 Randers Danmark 8900",
    "addr:housenumber":"26",
    "addr:postcode":"8900",
    "addr:street":"Grenaavej",
    "iso:country":"DK",
    "sg:address":"Gren\u00e5vej 26",
    "sg:city":"Randers",
    "sg:orig_category":"Industrilakering",
    "sg:phone":"+45 86 41 40 44",
    "sg:postcode":"8900",
    "sg:province":"Danmark",
    "wof:name":"Ranlak ApS",
    "wof:placetype":"venue"
},
  "geometry": {"coordinates":[10.0488061905,56.4526977539],"type":"Point"}
}