{
  "type": "Feature",
  "properties": {
    "addr:full":"Bl\u00e5mejsevej 7 Skagen Danmark 9990",
    "addr:housenumber":"7",
    "addr:postcode":"9990",
    "addr:street":"Blaamejsevej",
    "iso:country":"DK",
    "sg:address":"Bl\u00e5mejsevej 7",
    "sg:city":"Skagen",
    "sg:orig_category":"Zoneterapeuter",
    "sg:phone":"+45 98 44 55 36",
    "sg:postcode":"9990",
    "sg:province":"Danmark",
    "wof:name":"Madsen, Elsebeth C.",
    "wof:placetype":"venue"
},
  "geometry": {"coordinates":[10.578666687,57.7310409546],"type":"Point"}
}