{
  "type": "Feature",
  "properties": {
    "iso:country":"DK",
    "sg:address":"v/ Marcy Pedersen, Hanehovedvej 89",
    "sg:city":"Frederiksv\u00e6rk",
    "sg:orig_category":"Kulturelle foreninger",
    "sg:phone":"+45 47 72 34 21",
    "sg:postcode":"3300",
    "sg:province":"Danmark",
    "wof:name":"Den Gr\u00e6sk-Danske Klub",
    "wof:placetype":"venue"
},
  "geometry": {"coordinates":[-75.2916183472,43.1694488525],"type":"Point"}
}