{
  "type": "Feature",
  "properties": {
    "iso:country":"DK",
    "sg:address":"Borgergade 2",
    "sg:city":"Silkeborg",
    "sg:classifiers":[
        {
            "category":"Banks & Credit Unions",
            "subcategory":"Bank",
            "type":"Services"
        }
    ],
    "sg:phone":"+45 87 20 64 00",
    "sg:postcode":"8600",
    "sg:province":"Danmark",
    "sg:tags":[
        "banker"
    ],
    "wof:name":"BG-Bank",
    "wof:placetype":"venue"
},
  "geometry": {"coordinates":[9.555335,56.17588],"type":"Point"}
}