{
  "type": "Feature",
  "properties": {
    "addr:full":"Adelgade 56 Bogense Danmark 5400",
    "addr:housenumber":"56",
    "addr:postcode":"5400",
    "addr:street":"Adelgade",
    "iso:country":"DK",
    "sg:address":"Adelgade 56",
    "sg:city":"Bogense",
    "sg:classifiers":[
        {
            "category":"Banks & Credit Unions",
            "subcategory":"Bank",
            "type":"Services"
        }
    ],
    "sg:phone":"+45 63 81 11 00",
    "sg:postcode":"5400",
    "sg:province":"Danmark",
    "sg:tags":[
        "banker"
    ],
    "sg:website":"www.danskebank.dk",
    "wof:name":"Danske Bank",
    "wof:placetype":"venue"
},
  "geometry": {"coordinates":[10.0904111862,55.5651817322],"type":"Point"}
}