{
  "type": "Feature",
  "properties": {
    "iso:country":"DK",
    "sg:address":"Fmd.: Henry H\u00f8jgaard, Hornsmarken 14, Br\u00f8ndum",
    "sg:city":"Hobro",
    "sg:orig_category":"\u00c3\u2020ldreorganisationer og klubber",
    "sg:phone":"+45 98 54 83 94",
    "sg:postcode":"9500",
    "sg:province":"Danmark",
    "wof:name":"Klejtrup Seniordanserforening",
    "wof:placetype":"venue"
},
  "geometry": {"coordinates":[9.7946596146,56.6382789612],"type":"Point"}
}