{
  "type": "Feature",
  "properties": {
    "addr:full":"Finsensvej 82 Frederiksberg Danmark 2000",
    "addr:housenumber":"82",
    "addr:postcode":"2000",
    "addr:street":"Finsensvej",
    "iso:country":"DK",
    "sg:address":"Finsensvej 82",
    "sg:city":"Frederiksberg",
    "sg:orig_category":"Sammensatte institutioner",
    "sg:phone":"+45 38 21 16 60",
    "sg:postcode":"2000",
    "sg:province":"Danmark",
    "wof:name":"Lindehuset, Frederiksberg Kommunes Kombinerede Institution",
    "wof:placetype":"venue"
},
  "geometry": {"coordinates":[12.5034408569,55.6823997498],"type":"Point"}
}