{
  "type": "Feature",
  "properties": {
    "addr:full":"Fmd.: Susanne Marx Hoe, Nordkystvejen 35, Vivild Alling\u00e5bro Danmark 8961",
    "addr:housenumber":"35",
    "addr:postcode":"8961",
    "addr:street":"Hoe Nordkystvejen",
    "iso:country":"DK",
    "sg:address":"Fmd.: Susanne Marx Hoe, Nordkystvejen 35, Vivild",
    "sg:city":"Alling\u00e5bro",
    "sg:orig_category":"Husflidsforeninger",
    "sg:phone":"+45 86 48 69 89",
    "sg:postcode":"8961",
    "sg:province":"Danmark",
    "wof:name":"Familie og Samfund - Rougs\u00f8-S\u00f8nderhald",
    "wof:placetype":"venue"
},
  "geometry": {"coordinates":[10.3230552673,56.4639511108],"type":"Point"}
}