{
  "type": "Feature",
  "properties": {
    "addr:full":"T\u00f8mrervej 11 Varde Danmark 6800",
    "addr:housenumber":"11",
    "addr:postcode":"6800",
    "addr:street":"Tomrervej",
    "iso:country":"DK",
    "sg:address":"T\u00f8mrervej 11",
    "sg:city":"Varde",
    "sg:orig_category":"Undervognsbehandling",
    "sg:phone":"+45 75 22 36 33",
    "sg:postcode":"6800",
    "sg:province":"Danmark",
    "wof:name":"Varde Antirust",
    "wof:placetype":"venue"
},
  "geometry": {"coordinates":[8.5045852661,55.6066551208],"type":"Point"}
}