{
  "type": "Feature",
  "properties": {
    "addr:full":"R\u00f8rmosevej 4, Tulstrup Hiller\u00f8d Danmark 3400",
    "addr:housenumber":"4",
    "addr:postcode":"3400",
    "addr:street":"Rormosevej",
    "iso:country":"DK",
    "sg:address":"R\u00f8rmosevej 4, Tulstrup",
    "sg:city":"Hiller\u00f8d",
    "sg:orig_category":"Konservatorer",
    "sg:phone":"+45 48 28 61 68",
    "sg:postcode":"3400",
    "sg:province":"Danmark",
    "wof:name":"J.V. Tr\u00e6",
    "wof:placetype":"venue"
},
  "geometry": {"coordinates":[12.3056097031,55.9288215637],"type":"Point"}
}