{
  "type": "Feature",
  "properties": {
    "addr:full":"Hvedevangen 20, Thorsager R\u00f8nde Danmark 8410",
    "addr:housenumber":"20 thorsager",
    "addr:postcode":"8410",
    "addr:street":"Hvedevangen",
    "iso:country":"DK",
    "sg:address":"Hvedevangen 20, Thorsager",
    "sg:city":"R\u00f8nde",
    "sg:orig_category":"Autoforhandlere",
    "sg:phone":"+45 86 37 94 99",
    "sg:postcode":"8410",
    "sg:province":"Danmark",
    "wof:name":"Sch\u00f8ler Automobiler, E.",
    "wof:placetype":"venue"
},
  "geometry": {"coordinates":[10.4288892746,56.295917511],"type":"Point"}
}