{
  "type": "Feature",
  "properties": {
    "addr:full":"v/ Jens Erik Starup, Horsb\u00f8lvej 13, Horsb\u00f8l Grindsted Danmark 7200",
    "addr:housenumber":"13",
    "addr:postcode":"7200",
    "addr:street":"Horsbolvej;Horsbol",
    "iso:country":"DK",
    "sg:address":"v/ Jens Erik Starup, Horsb\u00f8lvej 13, Horsb\u00f8l",
    "sg:city":"Grindsted",
    "sg:orig_category":"Lokalarkiver",
    "sg:phone":"+45 75 32 09 00",
    "sg:postcode":"7200",
    "sg:province":"Danmark",
    "wof:name":"Grindsted Lokalhistoriske Arkiv",
    "wof:placetype":"venue"
},
  "geometry": {"coordinates":[8.9288702011,55.7560272217],"type":"Point"}
}