{
  "type": "Feature",
  "properties": {
    "addr:full":"Mellemvej 7 Nordborg Danmark 6430",
    "addr:housenumber":"7",
    "addr:postcode":"6430",
    "addr:street":"Mellemvej",
    "iso:country":"DK",
    "sg:address":"Mellemvej 7",
    "sg:city":"Nordborg",
    "sg:orig_category":"Autoreparation og -service",
    "sg:phone":"+45 74 45 30 94",
    "sg:postcode":"6430",
    "sg:province":"Danmark",
    "wof:name":"HC Autov\u00e6rksted",
    "wof:placetype":"venue"
},
  "geometry": {"coordinates":[9.7523078918,55.0492210388],"type":"Point"}
}