{
  "type": "Feature",
  "properties": {
    "addr:full":"Gammel Lundtoftevej 1 C, 1. Kongens Lyngby Danmark 2800",
    "addr:housenumber":"1 c 1",
    "addr:postcode":"2800",
    "addr:street":"Gammel Lundtoftevej",
    "iso:country":"DK",
    "sg:address":"Gammel Lundtoftevej 1 C, 1.",
    "sg:city":"Kongens Lyngby",
    "sg:orig_category":"Faglige organisationer og foreninger",
    "sg:phone":"+45 45 88 87 86",
    "sg:postcode":"2800",
    "sg:province":"Danmark",
    "sg:website":"www.krifa.dk",
    "wof:name":"Kristelig Fagforening og Kristelig A-kasse",
    "wof:placetype":"venue"
},
  "geometry": {"coordinates":[12.5001382828,55.7744522095],"type":"Point"}
}