{
  "type": "Feature",
  "properties": {
    "addr:full":"Pastor: Arne Bidstrup, Udsigten 12, Lihme Sp\u00f8ttrup Danmark 7860",
    "addr:housenumber":"12",
    "addr:postcode":"7860",
    "addr:street":"Pastor Arne Bidstrup Udsigten",
    "iso:country":"DK",
    "sg:address":"Pastor: Arne Bidstrup, Udsigten 12, Lihme",
    "sg:city":"Sp\u00f8ttrup",
    "sg:orig_category":"Kirkelige foreninger",
    "sg:phone":"+45 97 56 04 13",
    "sg:postcode":"7860",
    "sg:province":"Danmark",
    "wof:name":"Dansk Kirke i Udlandet, Distrikt Skive",
    "wof:placetype":"venue"
},
  "geometry": {"coordinates":[8.7428588867,56.5733261108],"type":"Point"}
}