{
  "type": "Feature",
  "properties": {
    "addr:full":"Esplanaden 4 K\u00f8benhavn Danmark 1263",
    "addr:housenumber":"4",
    "addr:postcode":"1263",
    "addr:street":"Esplanaden",
    "iso:country":"DK",
    "sg:address":"Esplanaden 4",
    "sg:city":"K\u00f8benhavn",
    "sg:classifiers":[
        {
            "category":"Restaurant",
            "type":"Food & Drink"
        }
    ],
    "sg:phone":"+45 33 12 93 31",
    "sg:postcode":"1263",
    "sg:province":"Danmark",
    "wof:name":"Toldbod Bodega",
    "wof:placetype":"venue"
},
  "geometry": {"coordinates":[12.5975999832,55.6869010925],"type":"Point"}
}