{
  "type": "Feature",
  "properties": {
    "iso:country":"DK",
    "sg:address":"Frydenh\u00f8j Alle 73",
    "sg:city":"Greve",
    "sg:orig_category":"\u00c3\u02dcvrig fritidsundervisning",
    "sg:phone":"+45 43 97 87 00",
    "sg:postcode":"2670",
    "sg:province":"Danmark",
    "wof:name":"Greve Sprogcenter",
    "wof:placetype":"venue"
},
  "geometry": {"coordinates":[12.3371963501,55.5945472717],"type":"Point"}
}