{
  "type": "Feature",
  "properties": {
    "addr:full":"Gammel Kongevej 150 Frederiksberg Danmark 1850",
    "addr:housenumber":"150",
    "addr:postcode":"1850",
    "addr:street":"Gammel Kongevej",
    "iso:country":"DK",
    "sg:address":"Gammel Kongevej 150",
    "sg:city":"Frederiksberg",
    "sg:orig_category":"Fodterapeuter",
    "sg:phone":"+45 33 24 24 33",
    "sg:postcode":"1850",
    "sg:province":"Danmark",
    "wof:name":"Klinik for Fodterapi",
    "wof:placetype":"venue"
},
  "geometry": {"coordinates":[12.5376205444,55.6774482727],"type":"Point"}
}