{
  "type": "Feature",
  "properties": {
    "addr:full":"Skovsbov\u00e6nget 7 Odense M Danmark 5230",
    "addr:housenumber":"7",
    "addr:postcode":"5230",
    "addr:street":"Skovsbovaenget",
    "iso:country":"DK",
    "sg:address":"Skovsbov\u00e6nget 7",
    "sg:city":"Odense M",
    "sg:orig_category":"Ungdomsklubber",
    "sg:phone":"+45 65 91 21 03",
    "sg:postcode":"5230",
    "sg:province":"Danmark",
    "wof:name":"Hinderuplund",
    "wof:placetype":"venue"
},
  "geometry": {"coordinates":[10.3990526199,55.3762321472],"type":"Point"}
}