{
  "type": "Feature",
  "properties": {
    "iso:country":"DK",
    "sg:address":"Koldingvej 195",
    "sg:city":"Viborg",
    "sg:orig_category":"Begravelsesforretninger",
    "sg:phone":"+45 86 62 01 96",
    "sg:postcode":"8800",
    "sg:province":"Danmark",
    "sg:website":"www.bedemand-perrasmussen.dk",
    "wof:name":"Rasmussen, Per",
    "wof:placetype":"venue"
},
  "geometry": {"coordinates":[9.3822526932,56.4245948792],"type":"Point"}
}