{
  "type": "Feature",
  "properties": {
    "addr:full":"Helsingevej 23 Virum Danmark 2830",
    "addr:housenumber":"23",
    "addr:postcode":"2830",
    "addr:street":"Helsingevej",
    "iso:country":"DK",
    "sg:address":"Helsingevej 23",
    "sg:city":"Virum",
    "sg:orig_category":"Kongresservice",
    "sg:phone":"+45 45 85 97 27",
    "sg:postcode":"2830",
    "sg:province":"Danmark",
    "wof:name":"MiaCon",
    "wof:placetype":"venue"
},
  "geometry": {"coordinates":[12.4499025345,55.7971611023],"type":"Point"}
}