{
  "type": "Feature",
  "properties": {
    "addr:full":"Alb\u00e6kvej 42, Snejbjerg Herning Danmark 7400",
    "addr:housenumber":"42",
    "addr:postcode":"7400",
    "addr:street":"Albaekvej;Snejbjerg",
    "iso:country":"DK",
    "sg:address":"Alb\u00e6kvej 42, Snejbjerg",
    "sg:city":"Herning",
    "sg:orig_category":"Fiskeriudstyr",
    "sg:phone":"+45 97 16 86 02",
    "sg:postcode":"7400",
    "sg:province":"Danmark",
    "wof:name":"Grejbiksen Alb\u00e6k",
    "wof:placetype":"venue"
},
  "geometry": {"coordinates":[8.9768896103,56.1374168396],"type":"Point"}
}