{
  "type": "Feature",
  "properties": {
    "addr:full":"v/ Hanne Madsen, Liselundvej 3, Tj\u00f8rring Herning Danmark 7400",
    "addr:housenumber":"3",
    "addr:postcode":"7400",
    "addr:street":"Liselundvej;Tjorring",
    "iso:country":"DK",
    "sg:address":"v/ Hanne Madsen, Liselundvej 3, Tj\u00f8rring",
    "sg:city":"Herning",
    "sg:orig_category":"Spejderkorps",
    "sg:phone":"+45 97 26 99 87",
    "sg:postcode":"7400",
    "sg:province":"Danmark",
    "wof:name":"Det Danske Spejderkorps Tj\u00f8rring Gruppe",
    "wof:placetype":"venue"
},
  "geometry": {"coordinates":[8.9768896103,56.1374168396],"type":"Point"}
}