{
  "type": "Feature",
  "properties": {
    "addr:full":"Harrebjergvej 13, Harre Roslev Danmark 7870",
    "addr:housenumber":"13",
    "addr:postcode":"7870",
    "addr:street":"Harrebjergvej;Harre",
    "iso:country":"DK",
    "sg:address":"Harrebjergvej 13, Harre",
    "sg:city":"Roslev",
    "sg:classifiers":[
        {
            "category":"Sports & Exercise",
            "subcategory":"Sports Center",
            "type":"Entertainment"
        }
    ],
    "sg:phone":"+45 97 57 11 66",
    "sg:postcode":"7870",
    "sg:province":"Danmark",
    "sg:tags":[
        "golf"
    ],
    "wof:name":"Harre Vig Golfklub",
    "wof:placetype":"venue"
},
  "geometry": {"coordinates":[8.8715353012,56.7570304871],"type":"Point"}
}