{
  "type": "Feature",
  "properties": {
    "addr:full":"M\u00f8lmarksvej 155 Svendborg Danmark 5700",
    "addr:housenumber":"155",
    "addr:postcode":"5700",
    "addr:street":"Molmarksvej",
    "iso:country":"DK",
    "sg:address":"M\u00f8lmarksvej 155",
    "sg:city":"Svendborg",
    "sg:orig_category":"Ejendomsadministration",
    "sg:phone":"+45 33 18 17 50",
    "sg:postcode":"5700",
    "sg:province":"Danmark",
    "sg:website":"www.bsb.dk",
    "wof:name":"Boligselskabet BSB, Region Fyn",
    "wof:placetype":"venue"
},
  "geometry": {"coordinates":[10.5954046249,55.0658073425],"type":"Point"}
}