{
  "type": "Feature",
  "properties": {
    "addr:full":"Gersagerparken 71 Greve Danmark 2670",
    "addr:housenumber":"71",
    "addr:postcode":"2670",
    "addr:street":"Gersagerparken",
    "iso:country":"DK",
    "sg:address":"Gersagerparken 71",
    "sg:city":"Greve",
    "sg:orig_category":"Musik- og sangundervisning",
    "sg:phone":"+45 43 90 01 02",
    "sg:postcode":"2670",
    "sg:province":"Danmark",
    "wof:name":"Flemming's Musikskole",
    "wof:placetype":"venue"
},
  "geometry": {"coordinates":[12.3302087784,55.5956802368],"type":"Point"}
}