{
  "type": "Feature",
  "properties": {
    "addr:full":"T\u00f8mmergangen 7, 1. Ribe Danmark 6760",
    "addr:housenumber":"7 1",
    "addr:postcode":"6760",
    "addr:street":"Tommergangen",
    "iso:country":"DK",
    "sg:address":"T\u00f8mmergangen 7, 1.",
    "sg:city":"Ribe",
    "sg:orig_category":"Revisorer",
    "sg:phone":"+45 75 41 17 11",
    "sg:postcode":"6760",
    "sg:province":"Danmark",
    "wof:name":"Schmidt Statsaut. Revisionsanpartselskab, J\u00f8rn M.",
    "wof:placetype":"venue"
},
  "geometry": {"coordinates":[8.767334938,55.3309555054],"type":"Point"}
}