{
  "type": "Feature",
  "properties": {
    "addr:full":"Fjordgade 12 Hobro Danmark 9500",
    "addr:housenumber":"12",
    "addr:postcode":"9500",
    "addr:street":"Fjordgade",
    "iso:country":"DK",
    "sg:address":"Fjordgade 12",
    "sg:city":"Hobro",
    "sg:orig_category":"Handicapboliger",
    "sg:phone":"+45 98 52 54 50",
    "sg:postcode":"9500",
    "sg:province":"Danmark",
    "wof:name":"Boenheden",
    "wof:placetype":"venue"
},
  "geometry": {"coordinates":[9.8070421219,56.6488037109],"type":"Point"}
}