{
  "type": "Feature",
  "properties": {
    "addr:full":"Alstrup Alle 1 Hasselager Danmark 8361",
    "addr:housenumber":"1",
    "addr:postcode":"8361",
    "addr:street":"Alstrup Alle",
    "iso:country":"DK",
    "sg:address":"Alstrup Alle 1",
    "sg:city":"Hasselager",
    "sg:orig_category":"Skilte",
    "sg:phone":"+45 86 28 01 00",
    "sg:postcode":"8361",
    "sg:province":"Danmark",
    "sg:website":"www.harboe-skilte.dk",
    "wof:name":"Harboe Skilte",
    "wof:placetype":"venue"
},
  "geometry": {"coordinates":[10.0953464508,56.1047554016],"type":"Point"}
}