{
  "type": "Feature",
  "properties": {
    "addr:full":"Store Torvegade 101, 2.tv. R\u00f8nne Danmark 3700",
    "addr:housenumber":"101",
    "addr:postcode":"2.tv;3700",
    "addr:street":"Store Torvegade",
    "iso:country":"DK",
    "sg:address":"Store Torvegade 101, 2.tv.",
    "sg:city":"R\u00f8nne",
    "sg:orig_category":"Trossamfund uden for folkekirken",
    "sg:phone":"+45 56 95 09 99",
    "sg:postcode":"3700",
    "sg:province":"Danmark",
    "wof:name":"Baha'ei Samfundet i R\u00f8nne",
    "wof:placetype":"venue"
},
  "geometry": {"coordinates":[14.6975498199,55.0993003845],"type":"Point"}
}