{
  "type": "Feature",
  "properties": {
    "addr:full":"Arres\u00f8vej 10 Risskov Danmark 8240",
    "addr:housenumber":"10",
    "addr:postcode":"8240",
    "addr:street":"Arresovej",
    "iso:country":"DK",
    "sg:address":"Arres\u00f8vej 10",
    "sg:city":"Risskov",
    "sg:orig_category":"Fabrikker",
    "sg:phone":"+45 86 17 51 85",
    "sg:postcode":"8240",
    "sg:province":"Danmark",
    "wof:name":"Jydsk Ligkistefabrik",
    "wof:placetype":"venue"
},
  "geometry": {"coordinates":[10.2346420288,56.2023963928],"type":"Point"}
}