{
  "type": "Feature",
  "properties": {
    "addr:full":"R\u00f8m\u00f8vej 11 Billum Danmark 6852",
    "addr:housenumber":"11",
    "addr:postcode":"6852",
    "addr:street":"Romovej",
    "iso:country":"DK",
    "sg:address":"R\u00f8m\u00f8vej 11",
    "sg:city":"Billum",
    "sg:orig_category":"Vinduespolering",
    "sg:phone":"+45 75 25 85 27",
    "sg:postcode":"6852",
    "sg:province":"Danmark",
    "wof:name":"K. C. Vinduespolering og Reng\u00f8ringsselskab",
    "wof:placetype":"venue"
},
  "geometry": {"coordinates":[8.3299703598,55.6177101135],"type":"Point"}
}