{
  "type": "Feature",
  "properties": {
    "iso:country":"DK",
    "sg:address":"Melvang 3",
    "sg:city":"Toftlund",
    "sg:orig_category":"Benzinstationer",
    "sg:phone":"+45 74 83 17 18",
    "sg:postcode":"6520",
    "sg:province":"Danmark",
    "wof:name":"DK-Benzin & N\u00e6rk\u00f8b",
    "wof:placetype":"venue"
},
  "geometry": {"coordinates":[9.068622,55.18454],"type":"Point"}
}