{
  "type": "Feature",
  "properties": {
    "addr:full":"Pr\u00e6stevangen 4, Gr\u00f8nb\u00e6k Ans Danmark 8643",
    "addr:housenumber":"4",
    "addr:postcode":"8643",
    "addr:street":"Praestevangen",
    "iso:country":"DK",
    "sg:address":"Pr\u00e6stevangen 4, Gr\u00f8nb\u00e6k",
    "sg:city":"Ans",
    "sg:orig_category":"Maskinfabrikker",
    "sg:phone":"+45 86 87 73 00",
    "sg:postcode":"8643",
    "sg:province":"Danmark",
    "wof:name":"Duks Industri",
    "wof:placetype":"venue"
},
  "geometry": {"coordinates":[9.6200656891,56.2750320435],"type":"Point"}
}