{
  "type": "Feature",
  "properties": {
    "addr:full":"Bredgade 108 Skjern Danmark 6900",
    "addr:housenumber":"108",
    "addr:postcode":"6900",
    "addr:street":"Bredgade",
    "iso:country":"DK",
    "sg:address":"Bredgade 108",
    "sg:city":"Skjern",
    "sg:classifiers":[
        {
            "category":"Communications",
            "type":"Services"
        }
    ],
    "sg:phone":"+45 97 35 17 44",
    "sg:postcode":"6900",
    "sg:province":"Danmark",
    "sg:tags":[
        "radio-",
        "og",
        "tv-stationer"
    ],
    "sg:website":"www.dnk1.dk",
    "wof:name":"Det Ny Kanal 1 - Skjerns Radio",
    "wof:placetype":"venue"
},
  "geometry": {"coordinates":[8.4892244339,55.951385498],"type":"Point"}
}