{
  "type": "Feature",
  "properties": {
    "iso:country":"DK",
    "sg:address":"Bredgade 15",
    "sg:city":"Pandrup",
    "sg:orig_category":"Ejendomshandel",
    "sg:phone":"+45 98 24 74 48",
    "sg:postcode":"9490",
    "sg:province":"Danmark",
    "sg:website":"www.realmaeglerne.dk/lynnerup.htm",
    "wof:name":"Lynnerup, J\u00f8rgen",
    "wof:placetype":"venue"
},
  "geometry": {"coordinates":[9.6770410538,57.2236824036],"type":"Point"}
}