{
  "type": "Feature",
  "properties": {
    "addr:full":"Gr\u00f8ndalscentret, Gr\u00f8ndalsvej 1, Ulbjerg Skals Danmark 8832",
    "addr:housenumber":"1",
    "addr:postcode":"8832",
    "addr:street":"Grondalsvej;Ulbjerg",
    "iso:country":"DK",
    "sg:address":"Gr\u00f8ndalscentret, Gr\u00f8ndalsvej 1, Ulbjerg",
    "sg:city":"Skals",
    "sg:orig_category":"Lokalarkiver",
    "sg:phone":"+45 86 69 75 42",
    "sg:postcode":"8832",
    "sg:province":"Danmark",
    "wof:name":"Ulbjerg-Lynderup lokalhistoriske Arkiv",
    "wof:placetype":"venue"
},
  "geometry": {"coordinates":[9.4030599594,56.5558166504],"type":"Point"}
}