{
  "type": "Feature",
  "properties": {
    "addr:full":"Gugvej 168 Aalborg S\u00d8 Danmark 9210",
    "addr:housenumber":"168",
    "addr:postcode":"9210",
    "addr:street":"Gugvej",
    "iso:country":"DK",
    "sg:address":"Gugvej 168",
    "sg:city":"Aalborg S\u00d8",
    "sg:orig_category":"Servicestationer",
    "sg:phone":"+45 98 14 16 50",
    "sg:postcode":"9210",
    "sg:province":"Danmark",
    "wof:name":"Q8",
    "wof:placetype":"venue"
},
  "geometry": {"coordinates":[9.9257106781,57.0102043152],"type":"Point"}
}