{
  "type": "Feature",
  "properties": {
    "addr:full":"Nr. Lindvej 22, Lind Herning Danmark 7400",
    "addr:housenumber":"22",
    "addr:postcode":"7400",
    "addr:street":"Nr. Lindvej",
    "iso:country":"DK",
    "sg:address":"Nr. Lindvej 22, Lind",
    "sg:city":"Herning",
    "sg:orig_category":"Maskinfabrikker",
    "sg:phone":"+45 97 12 33 03",
    "sg:postcode":"7400",
    "sg:province":"Danmark",
    "wof:name":"Christensen Metalvarer & Maskinfabrik, C. H.",
    "wof:placetype":"venue"
},
  "geometry": {"coordinates":[8.9768896103,56.1374168396],"type":"Point"}
}