{
  "type": "Feature",
  "properties": {
    "addr:full":"Mejsevej 3 Kolding Danmark 6000",
    "addr:housenumber":"3",
    "addr:postcode":"6000",
    "addr:street":"Mejsevej",
    "iso:country":"DK",
    "sg:address":"Mejsevej 3",
    "sg:city":"Kolding",
    "sg:orig_category":"INGENI\u00c3\u02dcRER",
    "sg:phone":"+45 75 50 34 00",
    "sg:postcode":"6000",
    "sg:province":"Danmark",
    "wof:name":"Kj\u00e6r Kolding Ingeni\u00f8rfirma ApS",
    "wof:placetype":"venue"
},
  "geometry": {"coordinates":[9.483001709,55.4962654114],"type":"Point"}
}