{
  "type": "Feature",
  "properties": {
    "addr:full":"Hjortebjergvej 33 - 35 Odense M Danmark 5230",
    "addr:housenumber":"33 35",
    "addr:postcode":"5230",
    "addr:street":"Hjortebjergvej",
    "iso:country":"DK",
    "sg:address":"Hjortebjergvej 33 - 35",
    "sg:city":"Odense M",
    "sg:orig_category":"Malervarer",
    "sg:phone":"+45 66 13 40 78",
    "sg:postcode":"5230",
    "sg:province":"Danmark",
    "wof:name":"Johannsen ApS, E. S.",
    "wof:placetype":"venue"
},
  "geometry": {"coordinates":[10.4120931625,55.3867034912],"type":"Point"}
}