{
  "type": "Feature",
  "properties": {
    "addr:full":"Herredsgade 41 Ulfborg Danmark 6990",
    "addr:housenumber":"41",
    "addr:postcode":"6990",
    "addr:street":"Herredsgade",
    "iso:country":"DK",
    "sg:address":"Herredsgade 41",
    "sg:city":"Ulfborg",
    "sg:orig_category":"Plejehjem",
    "sg:phone":"+45 97 49 17 44",
    "sg:postcode":"6990",
    "sg:province":"Danmark",
    "wof:name":"R\u00f8de Kors Plejehjem",
    "wof:placetype":"venue"
},
  "geometry": {"coordinates":[8.3210029602,56.2727661133],"type":"Point"}
}