{
  "type": "Feature",
  "properties": {
    "addr:full":"Hundstrupvej 61 Stenstrup Danmark 5771",
    "addr:housenumber":"61",
    "addr:postcode":"5771",
    "addr:street":"Hundstrupvej",
    "iso:country":"DK",
    "sg:address":"Hundstrupvej 61",
    "sg:city":"Stenstrup",
    "sg:orig_category":"Autoforhandlere",
    "sg:phone":"+45 62 26 13 91",
    "sg:postcode":"5771",
    "sg:province":"Danmark",
    "wof:name":"Jan's Auto",
    "wof:placetype":"venue"
},
  "geometry": {"coordinates":[10.4511289597,55.1152267456],"type":"Point"}
}