{
  "type": "Feature",
  "properties": {
    "iso:country":"DK",
    "sg:address":"Bytoften 64, Tj\u00f8rring",
    "sg:city":"Herning",
    "sg:orig_category":"Skilte",
    "sg:phone":"+45 97 26 83 00",
    "sg:postcode":"7400",
    "sg:province":"Danmark",
    "wof:name":"Total Skilte",
    "wof:placetype":"venue"
},
  "geometry": {"coordinates":[8.9768896103,56.1374168396],"type":"Point"}
}