{
  "type": "Feature",
  "properties": {
    "addr:full":"Gl. Kirkevej 31-33 Herning Danmark 7400",
    "addr:postcode":"31-33;7400",
    "addr:street":"Gl. Kirkevej",
    "iso:country":"DK",
    "sg:address":"Gl. Kirkevej 31-33",
    "sg:city":"Herning",
    "sg:orig_category":"Kirker",
    "sg:postcode":"7400",
    "sg:province":"Danmark",
    "wof:name":"Hedeager Kirke",
    "wof:placetype":"venue"
},
  "geometry": {"coordinates":[8.9531583786,56.143573761],"type":"Point"}
}