{
  "type": "Feature",
  "properties": {
    "addr:full":"Baneg\u00e5rdspladsen 6 C Herning Danmark 7400",
    "addr:housenumber":"6 c",
    "addr:postcode":"7400",
    "addr:street":"Banegaardspladsen",
    "iso:country":"DK",
    "sg:address":"Baneg\u00e5rdspladsen 6 C",
    "sg:city":"Herning",
    "sg:orig_category":"Jernbaner",
    "sg:phone":"+45 97 22 55 88",
    "sg:postcode":"7400",
    "sg:province":"Danmark",
    "wof:name":"DSB, Rejsecenter Herning Station",
    "wof:placetype":"venue"
},
  "geometry": {"coordinates":[8.9787321091,56.1337471008],"type":"Point"}
}