{
  "type": "Feature",
  "properties": {
    "addr:full":"Vestergade 75 Silkeborg Danmark 8600",
    "addr:housenumber":"75",
    "addr:postcode":"8600",
    "addr:street":"Vestergade",
    "iso:country":"DK",
    "sg:address":"Vestergade 75",
    "sg:city":"Silkeborg",
    "sg:orig_category":"Servicestationer",
    "sg:phone":"+45 86 82 54 55",
    "sg:postcode":"8600",
    "sg:province":"Danmark",
    "wof:name":"Q8",
    "wof:placetype":"venue"
},
  "geometry": {"coordinates":[9.5394487381,56.1667785645],"type":"Point"}
}