{
  "type": "Feature",
  "properties": {
    "iso:country":"DK",
    "sg:address":"Kornvej 21",
    "sg:city":"Jyllinge",
    "sg:orig_category":"Energikonsulenter",
    "sg:phone":"+45 46 73 11 20",
    "sg:postcode":"4040",
    "sg:province":"Danmark",
    "wof:name":"Clement, Hans",
    "wof:placetype":"venue"
},
  "geometry": {"coordinates":[12.0971059799,55.7614479065],"type":"Point"}
}