{
  "type": "Feature",
  "properties": {
    "addr:full":"Sadelmagervej 25 Vejle Danmark 7100",
    "addr:housenumber":"25",
    "addr:postcode":"7100",
    "addr:street":"Sadelmagervej",
    "iso:country":"DK",
    "sg:address":"Sadelmagervej 25",
    "sg:city":"Vejle",
    "sg:orig_category":"Bogtrykkerier",
    "sg:phone":"+45 75 85 75 99",
    "sg:postcode":"7100",
    "sg:province":"Danmark",
    "wof:name":"Schweitzer A/S Grafisk Produktion",
    "wof:placetype":"venue"
},
  "geometry": {"coordinates":[9.4672698975,55.6950187683],"type":"Point"}
}