{
  "type": "Feature",
  "properties": {
    "addr:full":"Hold-An Vej 2 Ballerup Danmark 2750",
    "addr:housenumber":"2",
    "addr:postcode":"2750",
    "addr:street":"Hold-An Vej",
    "iso:country":"DK",
    "sg:address":"Hold-An Vej 2",
    "sg:city":"Ballerup",
    "sg:orig_category":"Servicestationer",
    "sg:phone":"+45 44 97 11 51",
    "sg:postcode":"2750",
    "sg:province":"Danmark",
    "wof:name":"Shell Service",
    "wof:placetype":"venue"
},
  "geometry": {"coordinates":[12.362780571,55.7357292175],"type":"Point"}
}