{
  "type": "Feature",
  "properties": {
    "addr:full":"I. C. Christensens Vej 15 A, Hee Ringk\u00f8bing Danmark 6950",
    "addr:housenumber":"15 a",
    "addr:postcode":"6950",
    "addr:street":"I. C. Christensens Vej;Hee Ringkobing Danmark",
    "iso:country":"DK",
    "sg:address":"I. C. Christensens Vej 15 A, Hee",
    "sg:city":"Ringk\u00f8bing",
    "sg:orig_category":"Kirker",
    "sg:postcode":"6950",
    "sg:province":"Danmark",
    "wof:name":"Hee kirke",
    "wof:placetype":"venue"
},
  "geometry": {"coordinates":[8.2810201645,56.145450592],"type":"Point"}
}