{
  "type": "Feature",
  "properties": {
    "iso:country":"DK",
    "sg:address":"Firehusevej 8",
    "sg:city":"Karup",
    "sg:orig_category":"Landboorganisationer",
    "sg:phone":"+45 86 66 15 74",
    "sg:postcode":"7470",
    "sg:province":"Danmark",
    "wof:name":"Landbrugets F\u00e6llesorganisation af 1966",
    "wof:placetype":"venue"
},
  "geometry": {"coordinates":[9.19049263,56.341632843],"type":"Point"}
}