{
  "type": "Feature",
  "properties": {
    "addr:full":"Lamborgvej 27, Urup Grindsted Danmark 7200",
    "addr:housenumber":"27",
    "addr:postcode":"7200",
    "addr:street":"Lamborgvej;Urup",
    "iso:country":"DK",
    "sg:address":"Lamborgvej 27, Urup",
    "sg:city":"Grindsted",
    "sg:orig_category":"Erhvervslokaler, Udlejning af",
    "sg:phone":"+45 75 33 01 51",
    "sg:postcode":"7200",
    "sg:province":"Danmark",
    "wof:name":"Christensen/Ragnar Knudsen, Helle M",
    "wof:placetype":"venue"
},
  "geometry": {"coordinates":[8.9288702011,55.7560272217],"type":"Point"}
}