{
  "type": "Feature",
  "properties": {
    "addr:full":"Thur\u00f8vej 12 Thybor\u00f8n Danmark 7680",
    "addr:housenumber":"12",
    "addr:postcode":"7680",
    "addr:street":"Thurovej",
    "iso:country":"DK",
    "sg:address":"Thur\u00f8vej 12",
    "sg:city":"Thybor\u00f8n",
    "sg:orig_category":"Malermestre",
    "sg:phone":"+45 97 83 13 86",
    "sg:postcode":"7680",
    "sg:province":"Danmark",
    "wof:name":"Rasmussen, Malerfirmaet K.",
    "wof:placetype":"venue"
},
  "geometry": {"coordinates":[-76.5370025635,38.7129592896],"type":"Point"}
}