{
  "type": "Feature",
  "properties": {
    "addr:full":"Forum Kirkevej 50 Esbjerg N Danmark 6715",
    "addr:housenumber":"50",
    "addr:postcode":"6715",
    "addr:street":"Forum Kirkevej",
    "iso:country":"DK",
    "sg:address":"Forum Kirkevej 50",
    "sg:city":"Esbjerg N",
    "sg:orig_category":"Pelsdyravl",
    "sg:phone":"+45 75 16 78 97",
    "sg:postcode":"6715",
    "sg:province":"Danmark",
    "wof:name":"Pedersen, Henning",
    "wof:placetype":"venue"
},
  "geometry": {"coordinates":[8.4739923477,55.5511894226],"type":"Point"}
}