{
  "type": "Feature",
  "properties": {
    "iso:country":"DK",
    "sg:address":"Pr\u00e6steg\u00e5rdsv\u00e6nget 6",
    "sg:city":"Bedsted",
    "sg:orig_category":"Kirker",
    "sg:postcode":"7755",
    "sg:province":"Danmark",
    "wof:name":"Bedsted Kirke",
    "wof:placetype":"venue"
},
  "geometry": {"coordinates":[8.4905691147,56.8179664612],"type":"Point"}
}