{
  "type": "Feature",
  "properties": {
    "iso:country":"DK",
    "sg:address":"Udhavnsvej 38 ",
    "sg:city":"\u00c5rhus C",
    "sg:classifiers":[
        {
            "category":"Parking",
            "subcategory":"Lot",
            "type":"Transportation"
        }
    ],
    "sg:phone":"+45 70 20 84 00",
    "sg:postcode":"8000",
    "sg:province":"Danmark",
    "sg:tags":[
        "transport",
        "road"
    ],
    "wof:name":"SKANOL A/S",
    "wof:placetype":"venue"
},
  "geometry": {"coordinates":[4.717400074,49.7588005066],"type":"Point"}
}