{
  "type": "Feature",
  "properties": {
    "iso:country":"DK",
    "sg:address":"\u00d8stergade 42",
    "sg:city":"Assens",
    "sg:classifiers":[
        {
            "category":"Banks & Credit Unions",
            "subcategory":"Bank",
            "type":"Services"
        }
    ],
    "sg:phone":"+45 63 71 50 50",
    "sg:postcode":"5610",
    "sg:province":"Danmark",
    "sg:tags":[
        "banker"
    ],
    "wof:name":"Vestfyns Bank, A/S",
    "wof:placetype":"venue"
},
  "geometry": {"coordinates":[9.8976945877,55.2699317932],"type":"Point"}
}