{
  "type": "Feature",
  "properties": {
    "addr:full":"\u00c5dalen 4, Havrebjerg Slagelse Danmark 4200",
    "addr:housenumber":"4",
    "addr:postcode":"4200",
    "addr:street":"Aadalen;Havrebjerg",
    "iso:country":"DK",
    "sg:address":"\u00c5dalen 4, Havrebjerg",
    "sg:city":"Slagelse",
    "sg:orig_category":"Overfladebehandling",
    "sg:phone":"+45 58 86 94 86",
    "sg:postcode":"4200",
    "sg:province":"Danmark",
    "wof:name":"Topfinish",
    "wof:placetype":"venue"
},
  "geometry": {"coordinates":[11.3569850922,55.4050865173],"type":"Point"}
}