{
  "type": "Feature",
  "properties": {
    "addr:full":"Amager Landevej 195 Kastrup Danmark 2770",
    "addr:housenumber":"195",
    "addr:postcode":"2770",
    "addr:street":"Amager Landevej",
    "iso:country":"DK",
    "sg:address":"Amager Landevej 195",
    "sg:city":"Kastrup",
    "sg:orig_category":"Fabrikker",
    "sg:phone":"+45 32 51 14 87",
    "sg:postcode":"2770",
    "sg:province":"Danmark",
    "wof:name":"Beng\u00e5rd's Eftf.",
    "wof:placetype":"venue"
},
  "geometry": {"coordinates":[12.6259346008,55.6232223511],"type":"Point"}
}