{
  "type": "Feature",
  "properties": {
    "addr:full":"Svoldrupvej 104, Vognsild Aars Danmark 9600",
    "addr:housenumber":"104",
    "addr:postcode":"9600",
    "addr:street":"Svoldrupvej",
    "iso:country":"DK",
    "sg:address":"Svoldrupvej 104, Vognsild",
    "sg:city":"Aars",
    "sg:orig_category":"Affald",
    "sg:phone":"+45 98 65 86 02",
    "sg:postcode":"9600",
    "sg:province":"Danmark",
    "wof:name":"Auto Auto Danmark",
    "wof:placetype":"venue"
},
  "geometry": {"coordinates":[9.5170412064,56.8031692505],"type":"Point"}
}