{
  "type": "Feature",
  "properties": {
    "addr:full":"K\u00e6rvej 503 Billund Danmark 7190",
    "addr:housenumber":"503",
    "addr:postcode":"7190",
    "addr:street":"Kaervej",
    "iso:country":"DK",
    "sg:address":"K\u00e6rvej 503",
    "sg:city":"Billund",
    "sg:orig_category":"Tandklinikker, Kommunale",
    "sg:phone":"+45 72 13 17 80",
    "sg:postcode":"7190",
    "sg:province":"Danmark",
    "wof:name":"Billund Kommunale Tandpleje",
    "wof:placetype":"venue"
},
  "geometry": {"coordinates":[9.1041097641,55.7261505127],"type":"Point"}
}