{
  "type": "Feature",
  "properties": {
    "addr:full":"Farvervej 12 Viborg Danmark 8800",
    "addr:housenumber":"12",
    "addr:postcode":"8800",
    "addr:street":"Farvervej",
    "iso:country":"DK",
    "sg:address":"Farvervej 12",
    "sg:city":"Viborg",
    "sg:orig_category":"Traktorer",
    "sg:phone":"+45 86 61 24 99",
    "sg:postcode":"8800",
    "sg:province":"Danmark",
    "wof:name":"Viborg Mini Traktor",
    "wof:placetype":"venue"
},
  "geometry": {"coordinates":[9.3969745636,56.4630050659],"type":"Point"}
}