{
  "type": "Feature",
  "properties": {
    "addr:full":"N\u00f8rre Alle 66 B, kld. \u00c5rhus C Danmark 8000",
    "addr:housenumber":"66 b kld.",
    "addr:postcode":"8000",
    "addr:street":"Norre Alle",
    "iso:country":"DK",
    "sg:address":"N\u00f8rre Alle 66 B, kld.",
    "sg:city":"\u00c5rhus C",
    "sg:classifiers":[
        {
            "category":"Food & Beverages",
            "subcategory":"Liquor & Beverages",
            "type":"Retail Goods"
        }
    ],
    "sg:phone":"+45 86 20 96 22",
    "sg:postcode":"8000",
    "sg:province":"Danmark",
    "sg:tags":[
        "vin"
    ],
    "wof:name":"Strobel Vinimport",
    "wof:placetype":"venue"
},
  "geometry": {"coordinates":[77.2480392456,14.1354398727],"type":"Point"}
}