{
  "type": "Feature",
  "properties": {
    "addr:full":"Fyrrely 17 Sunds Danmark 7451",
    "addr:housenumber":"17",
    "addr:postcode":"7451",
    "addr:street":"Fyrrely",
    "iso:country":"DK",
    "sg:address":"Fyrrely 17",
    "sg:city":"Sunds",
    "sg:orig_category":"Vinduer",
    "sg:phone":"+45 97 14 16 28",
    "sg:postcode":"7451",
    "sg:province":"Danmark",
    "wof:name":"Laursen, Tage",
    "wof:placetype":"venue"
},
  "geometry": {"coordinates":[9.0249128342,56.2026062012],"type":"Point"}
}