{
  "type": "Feature",
  "properties": {
    "addr:full":"Viborgvej 36 \u00c5rhus C Danmark 8000",
    "addr:housenumber":"36",
    "addr:postcode":"8000",
    "addr:street":"Viborgvej",
    "iso:country":"DK",
    "sg:address":"Viborgvej 36",
    "sg:city":"\u00c5rhus C",
    "sg:orig_category":"Grillbarer",
    "sg:postcode":"8000",
    "sg:province":"Danmark",
    "wof:name":"Ditten Fast-Food",
    "wof:placetype":"venue"
},
  "geometry": {"coordinates":[4.717400074,49.7588005066],"type":"Point"}
}