{
  "type": "Feature",
  "properties": {
    "addr:full":"Oddenvej 272, Havnebyen Sj\u00e6llands Odde Danmark 4583",
    "addr:housenumber":"272",
    "addr:postcode":"4583",
    "addr:street":"Oddenvej;Sjaellands Odde Danmark",
    "iso:country":"DK",
    "sg:address":"Oddenvej 272, Havnebyen",
    "sg:city":"Sj\u00e6llands Odde",
    "sg:orig_category":"Sommerhusudlejning",
    "sg:phone":"+45 59 32 64 18",
    "sg:postcode":"4583",
    "sg:province":"Danmark",
    "wof:name":"Willemoes",
    "wof:placetype":"venue"
},
  "geometry": {"coordinates":[11.3198680878,55.9799728394],"type":"Point"}
}