{
  "type": "Feature",
  "properties": {
    "addr:full":"(Klinisk Tandtekniker), Fruegade 5 Slagelse Danmark 4200",
    "addr:housenumber":"5",
    "addr:postcode":"4200",
    "addr:street":"Fruegade",
    "iso:country":"DK",
    "sg:address":"(Klinisk Tandtekniker), Fruegade 5",
    "sg:city":"Slagelse",
    "sg:orig_category":"Tandteknikere, Kliniske",
    "sg:phone":"+45 58 52 29 85",
    "sg:postcode":"4200",
    "sg:province":"Danmark",
    "wof:name":"Helseby, Erling",
    "wof:placetype":"venue"
},
  "geometry": {"coordinates":[11.3572292328,55.4022674561],"type":"Point"}
}