{
  "type": "Feature",
  "properties": {
    "addr:full":"Fmd.: Mary Christensen, Bollegade 40 Dronninglund Danmark 9330",
    "addr:housenumber":"40",
    "addr:postcode":"9330",
    "addr:street":"Bollegade",
    "iso:country":"DK",
    "sg:address":"Fmd.: Mary Christensen, Bollegade 40",
    "sg:city":"Dronninglund",
    "sg:orig_category":"Kulturelle foreninger",
    "sg:phone":"+45 98 84 23 78",
    "sg:postcode":"9330",
    "sg:province":"Danmark",
    "wof:name":"St\u00f8tteforening for Lokalhistorisk Arkiv",
    "wof:placetype":"venue"
},
  "geometry": {"coordinates":[10.2918195724,57.1594543457],"type":"Point"}
}