{
  "type": "Feature",
  "properties": {
    "addr:full":"Rolfsgade 123 Esbjerg Danmark 6700",
    "addr:housenumber":"123",
    "addr:postcode":"6700",
    "addr:street":"Rolfsgade",
    "iso:country":"DK",
    "sg:address":"Rolfsgade 123",
    "sg:city":"Esbjerg",
    "sg:orig_category":"Trossamfund uden for folkekirken",
    "sg:postcode":"6700",
    "sg:province":"Danmark",
    "wof:name":"Adventskirken",
    "wof:placetype":"venue"
},
  "geometry": {"coordinates":[8.4429779053,55.4740905762],"type":"Point"}
}