{
  "type": "Feature",
  "properties": {
    "addr:full":"Pr\u00e6sth\u00f8jvej 137, Torrild Odder Danmark 8300",
    "addr:housenumber":"137",
    "addr:postcode":"8300",
    "addr:street":"Praesthojvej;Torrild",
    "iso:country":"DK",
    "sg:address":"Pr\u00e6sth\u00f8jvej 137, Torrild",
    "sg:city":"Odder",
    "sg:orig_category":"Trailere",
    "sg:phone":"+45 87 81 32 90",
    "sg:postcode":"8300",
    "sg:province":"Danmark",
    "wof:name":"JTF Jydsk Trailer Fabrik",
    "wof:placetype":"venue"
},
  "geometry": {"coordinates":[10.1497612,55.9733161926],"type":"Point"}
}