{
  "type": "Feature",
  "properties": {
    "addr:full":"Hjertingvej 70 Varde Danmark 6800",
    "addr:housenumber":"70",
    "addr:postcode":"6800",
    "addr:street":"Hjertingvej",
    "iso:country":"DK",
    "sg:address":"Hjertingvej 70",
    "sg:city":"Varde",
    "sg:orig_category":"Soldaterhjem",
    "sg:phone":"+45 75 22 52 53",
    "sg:postcode":"6800",
    "sg:province":"Danmark",
    "wof:name":"KFUM Soldaterhjem",
    "wof:placetype":"venue"
},
  "geometry": {"coordinates":[8.4705438614,55.6107635498],"type":"Point"}
}