{
  "type": "Feature",
  "properties": {
    "iso:country":"DK",
    "sg:address":"N\u00f8rrebrogade 176",
    "sg:city":"K\u00f8benhavn N",
    "sg:orig_category":"Bagere",
    "sg:phone":"+45 35 83 57 57",
    "sg:postcode":"2200",
    "sg:province":"Danmark",
    "wof:name":"Z\u00f8llner Hus, Konditori",
    "wof:placetype":"venue"
},
  "geometry": {"coordinates":[-76.41683999999999,37.452419],"type":"Point"}
}