{
  "type": "Feature",
  "properties": {
    "addr:full":"\u00d8stre Stationsvej 29 Odense C Danmark 5000",
    "addr:housenumber":"29",
    "addr:postcode":"5000",
    "addr:street":"Ostre Stationsvej",
    "iso:country":"DK",
    "sg:address":"\u00d8stre Stationsvej 29",
    "sg:city":"Odense C",
    "sg:orig_category":"Cafeterier",
    "sg:phone":"+45 66 14 58 00",
    "sg:postcode":"5000",
    "sg:province":"Danmark",
    "wof:name":"McDonalds",
    "wof:placetype":"venue"
},
  "geometry": {"coordinates":[10.3836584091,55.4007453918],"type":"Point"}
}