{
  "type": "Feature",
  "properties": {
    "addr:full":"Brandts Passage 33 Odense C Danmark 5000",
    "addr:housenumber":"33",
    "addr:postcode":"5000",
    "addr:street":"Brandts Passage",
    "iso:country":"DK",
    "sg:address":"Brandts Passage 33",
    "sg:city":"Odense C",
    "sg:classifiers":[
        {
            "category":"Restaurant",
            "type":"Food & Drink"
        }
    ],
    "sg:phone":"+45 66 14 00 91",
    "sg:postcode":"5000",
    "sg:province":"Danmark",
    "wof:name":"Scene 33, Caf\u00e9 & Restaurant",
    "wof:placetype":"venue"
},
  "geometry": {"coordinates":[10.3813619614,55.3955230713],"type":"Point"}
}