{
  "type": "Feature",
  "properties": {
    "iso:country":"DK",
    "sg:address":"Lik\u00f8rstr\u00e6de 5",
    "sg:city":"Kongens Lyngby",
    "sg:orig_category":"Delikatesser",
    "sg:phone":"+45 45 87 93 01",
    "sg:postcode":"2800",
    "sg:province":"Danmark",
    "wof:name":"Hurup, Fru",
    "wof:placetype":"venue"
},
  "geometry": {"coordinates":[12.5368299484,55.7949905396],"type":"Point"}
}