{
  "type": "Feature",
  "properties": {
    "addr:full":"Plantagen 28, Osted Roskilde Danmark 4000",
    "addr:housenumber":"28",
    "addr:postcode":"4000",
    "addr:street":"Plantagen;Osted",
    "iso:country":"DK",
    "sg:address":"Plantagen 28, Osted",
    "sg:city":"Roskilde",
    "sg:orig_category":"Non-Classified Establishments",
    "sg:phone":"+45 46 49 62 00",
    "sg:postcode":"4000",
    "sg:province":"Danmark",
    "wof:name":"Nitram Oil A/S",
    "wof:placetype":"venue"
},
  "geometry": {"coordinates":[12.0909376144,55.6404838562],"type":"Point"}
}