{
  "type": "Feature",
  "properties": {
    "addr:full":"Kredsleder: Hans Peter Nielsen, Jernbanegade 34 Agerb\u00e6k Danmark 6753",
    "addr:housenumber":"34",
    "addr:postcode":"6753",
    "addr:street":"Jernbanegade",
    "iso:country":"DK",
    "sg:address":"Kredsleder: Hans Peter Nielsen, Jernbanegade 34",
    "sg:city":"Agerb\u00e6k",
    "sg:orig_category":"Spejderkorps",
    "sg:phone":"+45 75 19 67 53",
    "sg:postcode":"6753",
    "sg:province":"Danmark",
    "wof:name":"Frivilligt drenge og pige forbund, FDF",
    "wof:placetype":"venue"
},
  "geometry": {"coordinates":[8.802646637,55.6009178162],"type":"Point"}
}