{
  "type": "Feature",
  "properties": {
    "addr:full":"Jernbanegade 6 Hundested Danmark 3390",
    "addr:housenumber":"6",
    "addr:postcode":"3390",
    "addr:street":"Jernbanegade",
    "iso:country":"DK",
    "sg:address":"Jernbanegade 6",
    "sg:city":"Hundested",
    "sg:orig_category":"Posthuse",
    "sg:phone":"+45 48 10 34 50",
    "sg:postcode":"3390",
    "sg:province":"Danmark",
    "wof:name":"Post Danmark, Hundested Posthus",
    "wof:placetype":"venue"
},
  "geometry": {"coordinates":[11.8522815704,55.9635353088],"type":"Point"}
}