{
  "type": "Feature",
  "properties": {
    "addr:full":"Hundige Storcenter 9 C Greve Danmark 2670",
    "addr:housenumber":"9 c",
    "addr:postcode":"2670",
    "addr:street":"Storcenter",
    "iso:country":"DK",
    "sg:address":"Hundige Storcenter 9 C",
    "sg:city":"Greve",
    "sg:orig_category":"Renserier",
    "sg:phone":"+45 43 90 97 50",
    "sg:postcode":"2670",
    "sg:province":"Danmark",
    "wof:name":"Center Rens",
    "wof:placetype":"venue"
},
  "geometry": {"coordinates":[12.3281173706,55.5986785889],"type":"Point"}
}