{
  "type": "Feature",
  "properties": {
    "addr:full":"Amagerbrogade 290 K\u00f8benhavn S Danmark 2300",
    "addr:housenumber":"290",
    "addr:postcode":"2300",
    "addr:street":"Amagerbrogade;S Danmark",
    "iso:country":"DK",
    "sg:address":"Amagerbrogade 290",
    "sg:city":"K\u00f8benhavn S",
    "sg:orig_category":"Autoforhandlere",
    "sg:phone":"+45 32 50 14 11",
    "sg:postcode":"2300",
    "sg:province":"Danmark",
    "sg:website":"www.oluf-svendsen.dk",
    "wof:name":"Opel A/S",
    "wof:placetype":"venue"
},
  "geometry": {"coordinates":[-78.1299133301,36.7267417908],"type":"Point"}
}