{
  "type": "Feature",
  "properties": {
    "iso:country":"DK",
    "sg:address":"Rundbjergvej 11, True",
    "sg:city":"Tilst",
    "sg:orig_category":"Babyudstyr",
    "sg:phone":"+45 86 24 60 55",
    "sg:postcode":"8381",
    "sg:province":"Danmark",
    "wof:name":"Baby-Vest",
    "wof:placetype":"venue"
},
  "geometry": {"coordinates":[10.107815,56.188202],"type":"Point"}
}