{
  "type": "Feature",
  "properties": {
    "iso:country":"DK",
    "sg:address":"Amaliegade 6",
    "sg:city":"K\u00f8benhavn",
    "sg:orig_category":"Liftudlejning",
    "sg:phone":"+45 33 11 19 12",
    "sg:postcode":"1256",
    "sg:province":"Danmark",
    "wof:name":"K\u00f8benhavns Liftudlejning I/S",
    "wof:placetype":"venue"
},
  "geometry": {"coordinates":[12.5926704407,55.6827011108],"type":"Point"}
}