{
  "type": "Feature",
  "properties": {
    "iso:country":"DK",
    "sg:address":"Kongevejen 1, Vorgod",
    "sg:city":"Videb\u00e6k",
    "sg:orig_category":"Slagter og viktualie",
    "sg:phone":"+45 97 17 52 94",
    "sg:postcode":"6920",
    "sg:province":"Danmark",
    "wof:name":"Lange, Uffe",
    "wof:placetype":"venue"
},
  "geometry": {"coordinates":[8.7436800003,55.9904136658],"type":"Point"}
}