{
  "type": "Feature",
  "properties": {
    "iso:country":"DK",
    "sg:address":"Rytterhaven 13",
    "sg:city":"Farum",
    "sg:orig_category":"Ejendomsservice",
    "sg:phone":"+45 44 95 54 25",
    "sg:postcode":"3520",
    "sg:province":"Danmark",
    "wof:name":"Ejendomsservice",
    "wof:placetype":"venue"
},
  "geometry": {"coordinates":[12.3584022522,55.8181533813],"type":"Point"}
}