{
  "type": "Feature",
  "properties": {
    "addr:full":"H\u00f8jbuen 29 H\u00f8ng Danmark 4270",
    "addr:housenumber":"29",
    "addr:postcode":"4270",
    "addr:street":"Hojbuen;Hong Danmark",
    "iso:country":"DK",
    "sg:address":"H\u00f8jbuen 29",
    "sg:city":"H\u00f8ng",
    "sg:orig_category":"Malermestre",
    "sg:phone":"+45 58 85 31 85",
    "sg:postcode":"4270",
    "sg:province":"Danmark",
    "wof:name":"Jensen, Ejnar Juhl",
    "wof:placetype":"venue"
},
  "geometry": {"coordinates":[153.13444519039999,-27.8704795837],"type":"Point"}
}