{
  "type": "Feature",
  "properties": {
    "addr:full":"Bredgade 25 Skjern Danmark 6900",
    "addr:housenumber":"25",
    "addr:postcode":"6900",
    "addr:street":"Bredgade",
    "iso:country":"DK",
    "sg:address":"Bredgade 25",
    "sg:city":"Skjern",
    "sg:classifiers":[
        {
            "category":"Communications",
            "type":"Services"
        }
    ],
    "sg:phone":"+45 97 35 03 13",
    "sg:postcode":"6900",
    "sg:province":"Danmark",
    "sg:tags":[
        "og",
        "tv",
        "radio"
    ],
    "wof:name":"Expert",
    "wof:placetype":"venue"
},
  "geometry": {"coordinates":[8.4946889877,55.9457893372],"type":"Point"}
}