{
  "type": "Feature",
  "properties": {
    "addr:full":"S\u00f8ndergade 22 Herning Danmark 7400",
    "addr:housenumber":"22",
    "addr:postcode":"7400",
    "addr:street":"Sondergade",
    "iso:country":"DK",
    "sg:address":"S\u00f8ndergade 22",
    "sg:city":"Herning",
    "sg:orig_category":"Dyrehandlere",
    "sg:phone":"+45 97 12 85 27",
    "sg:postcode":"7400",
    "sg:province":"Danmark",
    "wof:name":"Zoo-Aqua Dyrecenter",
    "wof:placetype":"venue"
},
  "geometry": {"coordinates":[8.975774765,56.1346473694],"type":"Point"}
}