{
  "type": "Feature",
  "properties": {
    "addr:full":"Baune Alle 9 Kongens Lyngby Danmark 2800",
    "addr:housenumber":"9",
    "addr:postcode":"2800",
    "addr:street":"Baune Alle",
    "iso:country":"DK",
    "sg:address":"Baune Alle 9",
    "sg:city":"Kongens Lyngby",
    "sg:orig_category":"Fritidsklubber",
    "sg:phone":"+45 45 87 96 88",
    "sg:postcode":"2800",
    "sg:province":"Danmark",
    "wof:name":"Baune Fritids- og Ungdomsklub",
    "wof:placetype":"venue"
},
  "geometry": {"coordinates":[12.4951868057,55.7711486816],"type":"Point"}
}