{
  "type": "Feature",
  "properties": {
    "addr:full":"Bredgade 108 Skjern Danmark 6900",
    "addr:housenumber":"108",
    "addr:postcode":"6900",
    "addr:street":"Bredgade",
    "iso:country":"DK",
    "sg:address":"Bredgade 108",
    "sg:city":"Skjern",
    "sg:orig_category":"Tandklinikker, Kommunale",
    "sg:phone":"+45 97 35 04 58",
    "sg:postcode":"6900",
    "sg:province":"Danmark",
    "wof:name":"Skjern Kommunale Tandpleje",
    "wof:placetype":"venue"
},
  "geometry": {"coordinates":[8.4892244339,55.951385498],"type":"Point"}
}