{
  "type": "Feature",
  "properties": {
    "addr:full":"Enghavevej 9 D Vejle Danmark 7100",
    "addr:housenumber":"9 d",
    "addr:postcode":"7100",
    "addr:street":"Enghavevej",
    "iso:country":"DK",
    "sg:address":"Enghavevej 9 D",
    "sg:city":"Vejle",
    "sg:orig_category":"Revisorer",
    "sg:phone":"+45 76 43 73 10",
    "sg:postcode":"7100",
    "sg:province":"Danmark",
    "sg:website":"g-revision.dk",
    "wof:name":"Graungaard & Partnere Reigstreret Revisionsanpartsselskab",
    "wof:placetype":"venue"
},
  "geometry": {"coordinates":[9.5289201736,55.7062759399],"type":"Point"}
}