{
  "type": "Feature",
  "properties": {
    "addr:full":"Lejrvejen 4 Padborg Danmark 6330",
    "addr:housenumber":"4",
    "addr:postcode":"6330",
    "addr:street":"Lejrvejen",
    "iso:country":"DK",
    "sg:address":"Lejrvejen 4",
    "sg:city":"Padborg",
    "sg:orig_category":"Vikarbureauer",
    "sg:phone":"+45 74 67 01 77",
    "sg:postcode":"6330",
    "sg:province":"Danmark",
    "sg:website":"www.eurodriver.dk",
    "wof:name":"Euro Driver Service",
    "wof:placetype":"venue"
},
  "geometry": {"coordinates":[9.345205307,54.8311500549],"type":"Point"}
}