{
  "type": "Feature",
  "properties": {
    "iso:country":"DK",
    "sg:address":"Havredalsvej 7, Skelh\u00f8je",
    "sg:city":"Karup",
    "sg:orig_category":"Blomsterhandlere",
    "sg:phone":"+45 86 66 15 22",
    "sg:postcode":"7470",
    "sg:province":"Danmark",
    "wof:name":"Hedeg\u00e5rdens Blomster",
    "wof:placetype":"venue"
},
  "geometry": {"coordinates":[9.2525548935,56.3398017883],"type":"Point"}
}