{
  "type": "Feature",
  "properties": {
    "addr:full":"Skolegade 64 Esbjerg Danmark 6700",
    "addr:housenumber":"64",
    "addr:postcode":"6700",
    "addr:street":"Skolegade",
    "iso:country":"DK",
    "sg:address":"Skolegade 64",
    "sg:city":"Esbjerg",
    "sg:orig_category":"Autoreparation og -service",
    "sg:phone":"+45 75 13 56 22",
    "sg:postcode":"6700",
    "sg:province":"Danmark",
    "wof:name":"Autov\u00e6rkstedet Frikke & Grundahl ApS",
    "wof:placetype":"venue"
},
  "geometry": {"coordinates":[8.4464893341,55.4673461914],"type":"Point"}
}