{
  "type": "Feature",
  "properties": {
    "addr:full":"Skolevej 2, Havnbjerg Nordborg Danmark 6430",
    "addr:housenumber":"2",
    "addr:postcode":"6430",
    "addr:street":"Skolevej;Havnbjerg",
    "iso:country":"DK",
    "sg:address":"Skolevej 2, Havnbjerg",
    "sg:city":"Nordborg",
    "sg:orig_category":"Faglige organisationer og foreninger",
    "sg:phone":"+45 74 45 07 44",
    "sg:postcode":"6430",
    "sg:province":"Danmark",
    "wof:name":"Dansk Metal",
    "wof:placetype":"venue"
},
  "geometry": {"coordinates":[9.7496232986,55.0542755127],"type":"Point"}
}