{
  "type": "Feature",
  "properties": {
    "iso:country":"DK",
    "sg:address":"Hovedgaden 12",
    "sg:city":"H\u00f8rsholm",
    "sg:orig_category":"Slagter og viktualie",
    "sg:phone":"+45 45 86 01 21",
    "sg:postcode":"2970",
    "sg:province":"Danmark",
    "wof:name":"Abben",
    "wof:placetype":"venue"
},
  "geometry": {"coordinates":[9.2555503845,54.9375686646],"type":"Point"}
}