{
  "type": "Feature",
  "properties": {
    "addr:full":"M\u00e5gevej 20 Fjerritslev Danmark 9690",
    "addr:housenumber":"20",
    "addr:postcode":"9690",
    "addr:street":"Maagevej",
    "iso:country":"DK",
    "sg:address":"M\u00e5gevej 20",
    "sg:city":"Fjerritslev",
    "sg:orig_category":"EDB - udstyr",
    "sg:phone":"+45 98 21 38 22",
    "sg:postcode":"9690",
    "sg:province":"Danmark",
    "wof:name":"KS-Data",
    "wof:placetype":"venue"
},
  "geometry": {"coordinates":[9.2596797943,57.0836486816],"type":"Point"}
}