{
  "type": "Feature",
  "properties": {
    "addr:full":"\u00d8stboulevarden 35 \u00c5rhus C Danmark 8000",
    "addr:housenumber":"35",
    "addr:postcode":"8000",
    "addr:street":"Ostboulevarden",
    "iso:country":"DK",
    "sg:address":"\u00d8stboulevarden 35",
    "sg:city":"\u00c5rhus C",
    "sg:orig_category":"Blomsterhandlere",
    "sg:phone":"+45 86 19 79 46",
    "sg:postcode":"8000",
    "sg:province":"Danmark",
    "wof:name":"Forglem Mig Ej",
    "wof:placetype":"venue"
},
  "geometry": {"coordinates":[4.717400074,49.7588005066],"type":"Point"}
}