{
  "type": "Feature",
  "properties": {
    "addr:full":"Hadsundvej 131 Aalborg Danmark 9000",
    "addr:housenumber":"131",
    "addr:postcode":"9000",
    "addr:street":"Hadsundvej",
    "iso:country":"DK",
    "sg:address":"Hadsundvej 131",
    "sg:city":"Aalborg",
    "sg:orig_category":"Malerforretninger",
    "sg:phone":"+45 98 14 48 15",
    "sg:postcode":"9000",
    "sg:province":"Danmark",
    "wof:name":"Andersen, Malerfirmaet Brian",
    "wof:placetype":"venue"
},
  "geometry": {"coordinates":[9.955780983,57.0313453674],"type":"Point"}
}