{
  "type": "Feature",
  "properties": {
    "addr:full":"Fmd.: Kirsten Bollerup, Borgergade 27 Aalestrup Danmark 9620",
    "addr:housenumber":"27",
    "addr:postcode":"9620",
    "addr:street":"Borgergade",
    "iso:country":"DK",
    "sg:address":"Fmd.: Kirsten Bollerup, Borgergade 27",
    "sg:city":"Aalestrup",
    "sg:orig_category":"Kulturelle foreninger",
    "sg:phone":"+45 98 64 14 63",
    "sg:postcode":"9620",
    "sg:province":"Danmark",
    "wof:name":"Foreningen Norden",
    "wof:placetype":"venue"
},
  "geometry": {"coordinates":[9.4901504517,56.6938285828],"type":"Point"}
}