{
  "type": "Feature",
  "properties": {
    "iso:country":"DK",
    "sg:address":"Melchiorsvej 18",
    "sg:city":"Charlottenlund",
    "sg:orig_category":"Telte",
    "sg:phone":"+45 39 64 31 46",
    "sg:postcode":"2920",
    "sg:province":"Danmark",
    "sg:website":"www.charlottenlund-udlejning.dk",
    "wof:name":"Charlottenlund Serviceudlejning",
    "wof:placetype":"venue"
},
  "geometry": {"coordinates":[12.591173172,55.7601165771],"type":"Point"}
}