{
  "type": "Feature",
  "properties": {
    "addr:full":"Gladsaxe M\u00f8llevej 28 S\u00f8borg Danmark 2860",
    "addr:housenumber":"28",
    "addr:postcode":"2860",
    "addr:street":"Mollevej",
    "iso:country":"DK",
    "sg:address":"Gladsaxe M\u00f8llevej 28",
    "sg:city":"S\u00f8borg",
    "sg:orig_category":"Dag- og distriktsblade",
    "sg:phone":"+45 39 57 75 00",
    "sg:postcode":"2860",
    "sg:province":"Danmark",
    "wof:name":"S\u00f8ndagsavisen A/S",
    "wof:placetype":"venue"
},
  "geometry": {"coordinates":[12.4756612778,55.7364654541],"type":"Point"}
}