{
  "type": "Feature",
  "properties": {
    "addr:full":"Langgade 14, Vivild Alling\u00e5bro Danmark 8961",
    "addr:housenumber":"14",
    "addr:postcode":"8961",
    "addr:street":"Langgade",
    "iso:country":"DK",
    "sg:address":"Langgade 14, Vivild",
    "sg:city":"Alling\u00e5bro",
    "sg:orig_category":"Bodegaer",
    "sg:phone":"+45 86 48 69 41",
    "sg:postcode":"8961",
    "sg:province":"Danmark",
    "wof:name":"Lokale Bodega, Den",
    "wof:placetype":"venue"
},
  "geometry": {"coordinates":[10.3230552673,56.4639511108],"type":"Point"}
}