{
  "type": "Feature",
  "properties": {
    "addr:full":"H\u00f8jbjergvej 164, H\u00f8jbjerg Odense V Danmark 5200",
    "addr:housenumber":"164",
    "addr:postcode":"5200",
    "addr:street":"Hojbjergvej;Hojbjerg",
    "iso:country":"DK",
    "sg:address":"H\u00f8jbjergvej 164, H\u00f8jbjerg",
    "sg:city":"Odense V",
    "sg:orig_category":"Erhvervslokaler, Udlejning af",
    "sg:phone":"+45 65 96 70 36",
    "sg:postcode":"5200",
    "sg:province":"Danmark",
    "wof:name":"Anker, Keld",
    "wof:placetype":"venue"
},
  "geometry": {"coordinates":[10.2629547119,55.4070854187],"type":"Point"}
}