{
  "type": "Feature",
  "properties": {
    "addr:full":"T\u00f8ndervej 11, Arnitlund Vojens Danmark 6500",
    "addr:housenumber":"11",
    "addr:postcode":"6500",
    "addr:street":"Tondervej;Arnitlund",
    "iso:country":"DK",
    "sg:address":"T\u00f8ndervej 11, Arnitlund",
    "sg:city":"Vojens",
    "sg:orig_category":"El-motorer",
    "sg:phone":"+45 74 54 74 94",
    "sg:postcode":"6500",
    "sg:province":"Danmark",
    "sg:website":"www.arnitlund-handel.dk",
    "wof:name":"Arnitlund Handels ApS",
    "wof:placetype":"venue"
},
  "geometry": {"coordinates":[9.2987146378,55.2457237244],"type":"Point"}
}