{
  "type": "Feature",
  "properties": {
    "addr:full":"Hovedgaden 52 A Brabrand Danmark 8220",
    "addr:housenumber":"52 a",
    "addr:postcode":"8220",
    "addr:street":"Hovedgaden",
    "iso:country":"DK",
    "sg:address":"Hovedgaden 52 A",
    "sg:city":"Brabrand",
    "sg:orig_category":"Fodterapeuter",
    "sg:phone":"+45 86 26 30 77",
    "sg:postcode":"8220",
    "sg:province":"Danmark",
    "wof:name":"Klinik for Fodterapi",
    "wof:placetype":"venue"
},
  "geometry": {"coordinates":[10.1045627594,56.153465271],"type":"Point"}
}