{
  "type": "Feature",
  "properties": {
    "iso:country":"DK",
    "sg:address":"Hundige Storcenter 15 H",
    "sg:city":"Greve",
    "sg:classifiers":[
        {
            "category":"Banks & Credit Unions",
            "subcategory":"Bank",
            "type":"Services"
        }
    ],
    "sg:phone":"+45 43 97 29 50",
    "sg:postcode":"2670",
    "sg:province":"Danmark",
    "sg:tags":[
        "banker"
    ],
    "wof:name":"Bikuben A/S Hundige Center Afd.",
    "wof:placetype":"venue"
},
  "geometry": {"coordinates":[12.294181,55.584408],"type":"Point"}
}