{
  "type": "Feature",
  "properties": {
    "addr:full":"Byvej 14 Bryrup Danmark 8654",
    "addr:housenumber":"14",
    "addr:postcode":"8654",
    "addr:street":"Byvej",
    "iso:country":"DK",
    "sg:address":"Byvej 14",
    "sg:city":"Bryrup",
    "sg:classifiers":[
        {
            "category":"Communications",
            "type":"Services"
        }
    ],
    "sg:phone":"+45 75 75 64 96",
    "sg:postcode":"8654",
    "sg:province":"Danmark",
    "sg:tags":[
        "og",
        "tv",
        "radio"
    ],
    "wof:name":"Bryrup Radio & TV",
    "wof:placetype":"venue"
},
  "geometry": {"coordinates":[9.5135335922,56.0244216919],"type":"Point"}
}