{
  "type": "Feature",
  "properties": {
    "iso:country":"DK",
    "sg:address":"v/ Jens Toft Nielsen, Toftager 8, Vejby",
    "sg:city":"Vr\u00e5",
    "sg:orig_category":"Borger- og beboerforeninger",
    "sg:phone":"+45 98 99 43 85",
    "sg:postcode":"9760",
    "sg:province":"Danmark",
    "wof:name":"Vejby Beboerforening",
    "wof:placetype":"venue"
},
  "geometry": {"coordinates":[9.9477567673,57.3534927368],"type":"Point"}
}