{
  "type": "Feature",
  "properties": {
    "addr:full":"Fmd.: William Jensen, Vesterled 8, Laurbjerg Lang\u00e5 Danmark 8870",
    "addr:housenumber":"8",
    "addr:postcode":"8870",
    "addr:street":"Vesterled",
    "iso:country":"DK",
    "sg:address":"Fmd.: William Jensen, Vesterled 8, Laurbjerg",
    "sg:city":"Lang\u00e5",
    "sg:orig_category":"Politiske foreninger, \u00c3\u02dcvrige",
    "sg:phone":"+45 86 46 83 37",
    "sg:postcode":"8870",
    "sg:province":"Danmark",
    "wof:name":"Folkebev\u00e6gelsen Mod EF-Unionen - Lang\u00e5",
    "wof:placetype":"venue"
},
  "geometry": {"coordinates":[9.8955049515,56.3900756836],"type":"Point"}
}