{
  "type": "Feature",
  "properties": {
    "iso:country":"DK",
    "sg:address":"Teknikerbyen 45 ",
    "sg:city":"Virum",
    "sg:classifiers":[
        {
            "category":"Professional",
            "subcategory":"Business Services",
            "type":"Services"
        }
    ],
    "sg:phone":"+45 38 34 30 40",
    "sg:postcode":"2830",
    "sg:province":"Danmark",
    "sg:tags":[
        "advice"
    ],
    "wof:name":"FORENINGEN FOR ERNEGI MILJO",
    "wof:placetype":"venue"
},
  "geometry": {"coordinates":[12.500041008,55.801612854],"type":"Point"}
}