{
  "type": "Feature",
  "properties": {
    "iso:country":"DK",
    "sg:address":"Sydholmen 2 - 6 ",
    "sg:city":"Hvidovre",
    "sg:classifiers":[
        {
            "category":"Home & Garden",
            "subcategory":"Home Furnishings",
            "type":"Retail Goods"
        }
    ],
    "sg:phone":"+45 36 77 75 00",
    "sg:postcode":"2650",
    "sg:province":"Danmark",
    "sg:tags":[
        "household"
    ],
    "wof:name":"OVE C BJERREGAARD A/S",
    "wof:placetype":"venue"
},
  "geometry": {"coordinates":[12.469171524,55.6079978943],"type":"Point"}
}