{
  "type": "Feature",
  "properties": {
    "addr:full":"Fmd.: Leif Vest Pedersen, S\u00f8ndergade 42 Br\u00f8rup Danmark 6650",
    "addr:housenumber":"42",
    "addr:postcode":"6650",
    "addr:street":"Leif;Sondergade",
    "iso:country":"DK",
    "sg:address":"Fmd.: Leif Vest Pedersen, S\u00f8ndergade 42",
    "sg:city":"Br\u00f8rup",
    "sg:orig_category":"Hobbybetonede foreninger",
    "sg:phone":"+45 75 38 11 81",
    "sg:postcode":"6650",
    "sg:province":"Danmark",
    "wof:name":"Danske Pladesamlere, Foreningen af",
    "wof:placetype":"venue"
},
  "geometry": {"coordinates":[-93.1630935669,32.8507347107],"type":"Point"}
}