{
  "type": "Feature",
  "properties": {
    "addr:full":"v/Super Brugsen Gedved, Skovvej 2 Gedved Danmark 8751",
    "addr:housenumber":"2",
    "addr:postcode":"8751",
    "addr:street":"Gedved Skovvej",
    "iso:country":"DK",
    "sg:address":"v/Super Brugsen Gedved, Skovvej 2",
    "sg:city":"Gedved",
    "sg:orig_category":"Apoteker og -udsalg",
    "sg:phone":"+45 75 66 52 22",
    "sg:postcode":"8751",
    "sg:province":"Danmark",
    "wof:name":"H\u00e5ndk\u00f8bsudsalget Gedved",
    "wof:placetype":"venue"
},
  "geometry": {"coordinates":[9.8441801071,55.9348068237],"type":"Point"}
}