{
  "type": "Feature",
  "properties": {
    "iso:country":"DK",
    "sg:address":"T\u00e5rngade 4",
    "sg:city":"Randers",
    "sg:orig_category":"Antikviteter",
    "sg:phone":"+45 86 42 45 68",
    "sg:postcode":"8900",
    "sg:province":"Danmark",
    "wof:name":"Kj\u00e6rsgaard Antik",
    "wof:placetype":"venue"
},
  "geometry": {"coordinates":[10.037560463,56.4590873718],"type":"Point"}
}