{
  "type": "Feature",
  "properties": {
    "iso:country":"DK",
    "sg:address":"Mads Clausens Vej 28",
    "sg:city":"Hj\u00f8rring",
    "sg:classifiers":[
        {
            "category":"Building & Trades",
            "subcategory":"Construction",
            "type":"Services"
        }
    ],
    "sg:phone":"+45 98 90 13 10",
    "sg:postcode":"9800",
    "sg:province":"Danmark",
    "sg:tags":[
        "ventilation"
    ],
    "wof:name":"Nord - Vent ApS",
    "wof:placetype":"venue"
},
  "geometry": {"coordinates":[10.0073289871,57.4408035278],"type":"Point"}
}