{
  "type": "Feature",
  "properties": {
    "addr:full":"Mors\u00f8gade 1 Esbjerg Danmark 6700",
    "addr:housenumber":"1",
    "addr:postcode":"6700",
    "addr:street":"Morsogade",
    "iso:country":"DK",
    "sg:address":"Mors\u00f8gade 1",
    "sg:city":"Esbjerg",
    "sg:orig_category":"Gaffeltrucks",
    "sg:phone":"+45 75 13 66 75",
    "sg:postcode":"6700",
    "sg:province":"Danmark",
    "wof:name":"Kristensen Yale Gaffeltrucks ApS, Uffe",
    "wof:placetype":"venue"
},
  "geometry": {"coordinates":[8.4321184158,55.4755859375],"type":"Point"}
}