{
  "type": "Feature",
  "properties": {
    "addr:full":"v/ Kamilla Mortensen, Kirkerupvej 50, Kirkerup Slagelse Danmark 4200",
    "addr:housenumber":"50",
    "addr:postcode":"4200",
    "addr:street":"Kirkerupvej;Kirkerup",
    "iso:country":"DK",
    "sg:address":"v/ Kamilla Mortensen, Kirkerupvej 50, Kirkerup",
    "sg:city":"Slagelse",
    "sg:orig_category":"Husflidsforeninger",
    "sg:phone":"+45 58 54 51 09",
    "sg:postcode":"4200",
    "sg:province":"Danmark",
    "wof:name":"Hash\u00f8j Husmandsforenings husholdningsudvalg",
    "wof:placetype":"venue"
},
  "geometry": {"coordinates":[11.3569850922,55.4050865173],"type":"Point"}
}