{
  "type": "Feature",
  "properties": {
    "addr:full":"N\u00f8rre Tranders Vej 27 Aalborg Danmark 9000",
    "addr:housenumber":"27",
    "addr:postcode":"9000",
    "addr:street":"Tranders Vej",
    "iso:country":"DK",
    "sg:address":"N\u00f8rre Tranders Vej 27",
    "sg:city":"Aalborg",
    "sg:orig_category":"Rejsebureauer",
    "sg:phone":"+45 98 12 53 53",
    "sg:postcode":"9000",
    "sg:province":"Danmark",
    "sg:website":"www.all-travel.dk",
    "wof:name":"All-Travel",
    "wof:placetype":"venue"
},
  "geometry": {"coordinates":[9.9536886215,57.0411758423],"type":"Point"}
}