{
  "type": "Feature",
  "properties": {
    "addr:full":"Trondhjems Plads 3 K\u00f8benhavn \u00d8 Danmark 2100",
    "addr:housenumber":"3",
    "addr:postcode":"2100",
    "addr:street":"Trondhjems Plads;O",
    "iso:country":"DK",
    "sg:address":"Trondhjems Plads 3",
    "sg:city":"K\u00f8benhavn \u00d8",
    "sg:orig_category":"Advokater",
    "sg:phone":"+45 33 12 11 33",
    "sg:postcode":"2100",
    "sg:province":"Danmark",
    "wof:name":"Hassel, Helge",
    "wof:placetype":"venue"
},
  "geometry": {"coordinates":[11.6836299896,60.2548065186],"type":"Point"}
}