{
  "type": "Feature",
  "properties": {
    "addr:full":"Niels Ebbesens Vej 6 Holstebro Danmark 7500",
    "addr:housenumber":"6",
    "addr:postcode":"7500",
    "addr:street":"Niels Ebbesens Vej",
    "iso:country":"DK",
    "sg:address":"Niels Ebbesens Vej 6",
    "sg:city":"Holstebro",
    "sg:orig_category":"Non-Classified Establishments",
    "sg:phone":"+45 97 42 69 33",
    "sg:postcode":"7500",
    "sg:province":"Danmark",
    "wof:name":"Holstebro Montagev\u00e6rksted",
    "wof:placetype":"venue"
},
  "geometry": {"coordinates":[8.6120328903,56.3479347229],"type":"Point"}
}