{
  "type": "Feature",
  "properties": {
    "addr:full":"Knudrisgade 7 B \u00c5rhus C Danmark 8000",
    "addr:housenumber":"7 b",
    "addr:postcode":"8000",
    "addr:street":"Knudrisgade",
    "iso:country":"DK",
    "sg:address":"Knudrisgade 7 B",
    "sg:city":"\u00c5rhus C",
    "sg:orig_category":"Integrerede institutioner",
    "sg:phone":"+45 86 18 46 17",
    "sg:postcode":"8000",
    "sg:province":"Danmark",
    "wof:name":"Knudrisgade, Integreret Inst.",
    "wof:placetype":"venue"
},
  "geometry": {"coordinates":[77.2480392456,14.1354398727],"type":"Point"}
}