{
  "type": "Feature",
  "properties": {
    "addr:full":"Himmerlandsgade 38 Aars Danmark 9600",
    "addr:housenumber":"38",
    "addr:postcode":"9600",
    "addr:street":"Himmerlandsgade",
    "iso:country":"DK",
    "sg:address":"Himmerlandsgade 38",
    "sg:city":"Aars",
    "sg:orig_category":"El-forsyning",
    "sg:phone":"+45 98 62 19 33",
    "sg:postcode":"9600",
    "sg:province":"Danmark",
    "wof:name":"Aars El-Forsyning",
    "wof:placetype":"venue"
},
  "geometry": {"coordinates":[9.5215358734,56.8031158447],"type":"Point"}
}