{
  "type": "Feature",
  "properties": {
    "addr:full":"Storegade 55 B Varde Danmark 6800",
    "addr:housenumber":"55 b",
    "addr:postcode":"6800",
    "addr:street":"Storegade",
    "iso:country":"DK",
    "sg:address":"Storegade 55 B",
    "sg:city":"Varde",
    "sg:orig_category":"Malermestre",
    "sg:phone":"+45 75 21 18 94",
    "sg:postcode":"6800",
    "sg:province":"Danmark",
    "wof:name":"Anja's Malerfirma",
    "wof:placetype":"venue"
},
  "geometry": {"coordinates":[8.4820833206,55.6228294373],"type":"Point"}
}