{
  "type": "Feature",
  "properties": {
    "addr:full":"K\u00f8lk\u00e6rvej 35, Hammerum Herning Danmark 7400",
    "addr:housenumber":"35",
    "addr:postcode":"7400",
    "addr:street":"Kolkaervej",
    "iso:country":"DK",
    "sg:address":"K\u00f8lk\u00e6rvej 35, Hammerum",
    "sg:city":"Herning",
    "sg:orig_category":"Maskinstationer",
    "sg:phone":"+45 97 11 61 91",
    "sg:postcode":"7400",
    "sg:province":"Danmark",
    "wof:name":"Hauge Maskinstation, I/S",
    "wof:placetype":"venue"
},
  "geometry": {"coordinates":[8.9768896103,56.1374168396],"type":"Point"}
}