{
  "type": "Feature",
  "properties": {
    "addr:full":"R\u00e5dhuscentret 15 A Vojens Danmark 6500",
    "addr:housenumber":"15 a",
    "addr:postcode":"6500",
    "addr:street":"Raadhuscentret",
    "iso:country":"DK",
    "sg:address":"R\u00e5dhuscentret 15 A",
    "sg:city":"Vojens",
    "sg:orig_category":"Grillbarer",
    "sg:phone":"+45 74 54 10 88",
    "sg:postcode":"6500",
    "sg:province":"Danmark",
    "wof:name":"Gulles Grill & Cafe",
    "wof:placetype":"venue"
},
  "geometry": {"coordinates":[9.2923994064,55.2456207275],"type":"Point"}
}