{
  "type": "Feature",
  "properties": {
    "addr:full":"Gruppeleder: Pia Conny S\u00f8rensen, M\u00f8llev\u00e6nget 30 Thors\u00f8 Danmark 8881",
    "addr:housenumber":"30",
    "addr:postcode":"8881",
    "addr:street":"Thorso Danmark",
    "iso:country":"DK",
    "sg:address":"Gruppeleder: Pia Conny S\u00f8rensen, M\u00f8llev\u00e6nget 30",
    "sg:city":"Thors\u00f8",
    "sg:orig_category":"Spejderkorps",
    "sg:phone":"+45 86 96 61 89",
    "sg:postcode":"8881",
    "sg:province":"Danmark",
    "wof:name":"KFUM-spejderne i Thors\u00f8",
    "wof:placetype":"venue"
},
  "geometry": {"coordinates":[9.7878103256,56.2985954285],"type":"Point"}
}