{
  "type": "Feature",
  "properties": {
    "addr:full":"S\u00f8ndergade 20 A Ansager Danmark 6823",
    "addr:housenumber":"20 a",
    "addr:postcode":"6823",
    "addr:street":"Sondergade",
    "iso:country":"DK",
    "sg:address":"S\u00f8ndergade 20 A",
    "sg:city":"Ansager",
    "sg:orig_category":"Gallerier",
    "sg:phone":"+45 75 29 70 15",
    "sg:postcode":"6823",
    "sg:province":"Danmark",
    "wof:name":"Musik Galleriet",
    "wof:placetype":"venue"
},
  "geometry": {"coordinates":[8.7533082962,55.7048492432],"type":"Point"}
}