{
  "type": "Feature",
  "properties": {
    "addr:full":"Sj\u00e6llandsgade 31 Fredericia Danmark 7000",
    "addr:housenumber":"31",
    "addr:postcode":"7000",
    "addr:street":"Sjaellandsgade",
    "iso:country":"DK",
    "sg:address":"Sj\u00e6llandsgade 31",
    "sg:city":"Fredericia",
    "sg:orig_category":"Arbejdsformidling",
    "sg:phone":"+45 70 10 26 26",
    "sg:postcode":"7000",
    "sg:province":"Danmark",
    "wof:name":"Arbejdsformidlingen.",
    "wof:placetype":"venue"
},
  "geometry": {"coordinates":[9.7568254471,55.56432724],"type":"Point"}
}