{
  "type": "Feature",
  "properties": {
    "addr:full":"Hyttefadsvej 6 Strandby Danmark 9970",
    "addr:housenumber":"6",
    "addr:postcode":"9970",
    "addr:street":"Hyttefadsvej",
    "iso:country":"DK",
    "sg:address":"Hyttefadsvej 6",
    "sg:city":"Strandby",
    "sg:orig_category":"Fiskeeksport",
    "sg:phone":"+45 98 48 10 20",
    "sg:postcode":"9970",
    "sg:province":"Danmark",
    "wof:name":"Thomsen A/S, Knud",
    "wof:placetype":"venue"
},
  "geometry": {"coordinates":[10.5022678375,57.4949684143],"type":"Point"}
}