{
  "type": "Feature",
  "properties": {
    "addr:full":"J. A. Schwartz Gade 31 K\u00f8benhavn \u00d8 Danmark 2100",
    "addr:housenumber":"31",
    "addr:postcode":"2100",
    "addr:street":"J. A. Schwartz Gade;O",
    "iso:country":"DK",
    "sg:address":"J. A. Schwartz Gade 31",
    "sg:city":"K\u00f8benhavn \u00d8",
    "sg:orig_category":"Designere",
    "sg:phone":"+45 35 43 92 00",
    "sg:postcode":"2100",
    "sg:province":"Danmark",
    "wof:name":"Grafisk Design ApS",
    "wof:placetype":"venue"
},
  "geometry": {"coordinates":[99.92501068120001,34.2430114746],"type":"Point"}
}