{
  "type": "Feature",
  "properties": {
    "addr:full":"Slotsholmen 11 Skanderborg Danmark 8660",
    "addr:housenumber":"11",
    "addr:postcode":"8660",
    "addr:street":"Slotsholmen",
    "iso:country":"DK",
    "sg:address":"Slotsholmen 11",
    "sg:city":"Skanderborg",
    "sg:orig_category":"Smykker",
    "sg:phone":"+45 86 52 33 33",
    "sg:postcode":"8660",
    "sg:province":"Danmark",
    "wof:name":"Pilgrim",
    "wof:placetype":"venue"
},
  "geometry": {"coordinates":[9.9325895309,56.0263214111],"type":"Point"}
}