{
  "type": "Feature",
  "properties": {
    "addr:full":"Vestervej 7 Ebeltoft Danmark 8400",
    "addr:housenumber":"7",
    "addr:postcode":"8400",
    "addr:street":"Vestervej",
    "iso:country":"DK",
    "sg:address":"Vestervej 7",
    "sg:city":"Ebeltoft",
    "sg:orig_category":"Betonvarer",
    "sg:phone":"+45 86 34 19 55",
    "sg:postcode":"8400",
    "sg:province":"Danmark",
    "wof:name":"Ebeltoft Beton 4. K.",
    "wof:placetype":"venue"
},
  "geometry": {"coordinates":[10.5989694595,56.2296867371],"type":"Point"}
}