{
  "type": "Feature",
  "properties": {
    "addr:full":"Middelfartvej 494, Blommenslyst Blommenslyst Danmark 5491",
    "addr:housenumber":"494",
    "addr:postcode":"5491",
    "addr:street":"Middelfartvej",
    "iso:country":"DK",
    "sg:address":"Middelfartvej 494, Blommenslyst",
    "sg:city":"Blommenslyst",
    "sg:orig_category":"Campingpladser",
    "sg:phone":"+45 65 96 76 41",
    "sg:postcode":"5491",
    "sg:province":"Danmark",
    "wof:name":"Camp Blommenlyst",
    "wof:placetype":"venue"
},
  "geometry": {"coordinates":[10.2299203873,55.3889007568],"type":"Point"}
}