{
  "type": "Feature",
  "properties": {
    "addr:full":"Anelystparken 26, True Tilst Danmark 8381",
    "addr:housenumber":"26",
    "addr:postcode":"8381",
    "addr:street":"Anelystparken;True",
    "iso:country":"DK",
    "sg:address":"Anelystparken 26, True",
    "sg:city":"Tilst",
    "sg:orig_category":"Sko",
    "sg:phone":"+45 87 45 13 68",
    "sg:postcode":"8381",
    "sg:province":"Danmark",
    "sg:website":"www.brantano.dk",
    "wof:name":"Brantano",
    "wof:placetype":"venue"
},
  "geometry": {"coordinates":[10.1078147888,56.1882019043],"type":"Point"}
}