{
  "type": "Feature",
  "properties": {
    "addr:full":"Tinksmedevej 5 Janderup Danmark 6851",
    "addr:housenumber":"5",
    "addr:postcode":"6851",
    "addr:street":"Tinksmedevej",
    "iso:country":"DK",
    "sg:address":"Tinksmedevej 5",
    "sg:city":"Janderup",
    "sg:orig_category":"Autoreparation og -service",
    "sg:phone":"+45 75 25 86 38",
    "sg:postcode":"6851",
    "sg:province":"Danmark",
    "wof:name":"Janderup Auto-Service",
    "wof:placetype":"venue"
},
  "geometry": {"coordinates":[8.3672170639,55.6256446838],"type":"Point"}
}