{
  "type": "Feature",
  "properties": {
    "addr:full":"Tordenskjoldsgade 11 K\u00f8benhavn Danmark 1055",
    "addr:housenumber":"11;1055",
    "addr:street":"Tordenskjoldsgade",
    "iso:country":"DK",
    "sg:address":"Tordenskjoldsgade 11",
    "sg:city":"K\u00f8benhavn",
    "sg:classifiers":[
        {
            "category":"Personal",
            "subcategory":"Massage",
            "type":"Services"
        }
    ],
    "sg:phone":"+45 70 25 30 25",
    "sg:postcode":"1055",
    "sg:province":"Danmark",
    "wof:name":"Tre Sm\u00e5 Kinesere",
    "wof:placetype":"venue"
},
  "geometry": {"coordinates":[12.589099884,55.6777992249],"type":"Point"}
}