{
  "type": "Feature",
  "properties": {
    "addr:full":"Barfredsvej 5 - 11 Frederikshavn Danmark 9900",
    "addr:housenumber":"5 11",
    "addr:postcode":"9900",
    "addr:street":"Barfredsvej",
    "iso:country":"DK",
    "sg:address":"Barfredsvej 5 - 11",
    "sg:city":"Frederikshavn",
    "sg:orig_category":"Autoforhandlere",
    "sg:phone":"+45 98 43 26 00",
    "sg:postcode":"9900",
    "sg:province":"Danmark",
    "wof:name":"Frederikshavn Auto A/S",
    "wof:placetype":"venue"
},
  "geometry": {"coordinates":[10.5253295898,57.4384803772],"type":"Point"}
}