{
  "type": "Feature",
  "properties": {
    "addr:full":"Sct. Pauli 30 Broager Danmark 6310",
    "addr:housenumber":"30",
    "addr:postcode":"6310",
    "addr:street":"Sct. Pauli",
    "iso:country":"DK",
    "sg:address":"Sct. Pauli 30",
    "sg:city":"Broager",
    "sg:orig_category":"Autoreparation og -service",
    "sg:phone":"+45 74 44 11 21",
    "sg:postcode":"6310",
    "sg:province":"Danmark",
    "wof:name":"Broager Karrosseri & Motorv\u00e6rksted ApS",
    "wof:placetype":"venue"
},
  "geometry": {"coordinates":[9.6726722717,54.8843345642],"type":"Point"}
}