{
  "type": "Feature",
  "properties": {
    "addr:full":"Gl. Kirkevej 9, Kollund Krus\u00e5 Danmark 6340",
    "addr:housenumber":"9",
    "addr:postcode":"6340",
    "addr:street":"Gl. Kirkevej",
    "iso:country":"DK",
    "sg:address":"Gl. Kirkevej 9, Kollund",
    "sg:city":"Krus\u00e5",
    "sg:orig_category":"Forsamlingshuse",
    "sg:phone":"+45 74 67 87 68",
    "sg:postcode":"6340",
    "sg:province":"Danmark",
    "wof:name":"Kollund Forsamlingshus",
    "wof:placetype":"venue"
},
  "geometry": {"coordinates":[9.3991203308,54.8500900269],"type":"Point"}
}