{
  "type": "Feature",
  "properties": {
    "addr:full":"Stationsvej 12 Kirke Hyllinge Danmark 4070",
    "addr:housenumber":"12",
    "addr:postcode":"4070",
    "addr:street":"Stationsvej",
    "iso:country":"DK",
    "sg:address":"Stationsvej 12",
    "sg:city":"Kirke Hyllinge",
    "sg:orig_category":"Integrerede institutioner",
    "sg:phone":"+45 46 40 45 18",
    "sg:postcode":"4070",
    "sg:province":"Danmark",
    "wof:name":"Hyllinge-Lyndby B\u00f8rnehave",
    "wof:placetype":"venue"
},
  "geometry": {"coordinates":[11.9032707214,55.704460144],"type":"Point"}
}