{
  "type": "Feature",
  "properties": {
    "addr:full":"Italiensvej 72 K\u00f8benhavn S Danmark 2300",
    "addr:housenumber":"72",
    "addr:postcode":"2300",
    "addr:street":"Italiensvej;Kobenhavn S Danmark",
    "iso:country":"DK",
    "sg:address":"Italiensvej 72",
    "sg:city":"K\u00f8benhavn S",
    "sg:orig_category":"Snedkermestre",
    "sg:phone":"+45 32 55 46 40",
    "sg:postcode":"2300",
    "sg:province":"Danmark",
    "wof:name":"Rendb\u00e6k, Knud Erik",
    "wof:placetype":"venue"
},
  "geometry": {"coordinates":[-82.59252166749999,38.4454154968],"type":"Point"}
}