{
  "type": "Feature",
  "properties": {
    "addr:full":"v/ Rita Tomra Nielsen, Vibevej 5, \u00d8. Hurup Hadsund Danmark 9560",
    "addr:housenumber":"5 o.",
    "addr:postcode":"9560",
    "addr:street":"Vibevej",
    "iso:country":"DK",
    "sg:address":"v/ Rita Tomra Nielsen, Vibevej 5, \u00d8. Hurup",
    "sg:city":"Hadsund",
    "sg:orig_category":"Spejderkorps",
    "sg:phone":"+45 98 58 82 39",
    "sg:postcode":"9560",
    "sg:province":"Danmark",
    "wof:name":"FDF/FPF, \u00d8. Hurup",
    "wof:placetype":"venue"
},
  "geometry": {"coordinates":[10.115904808,56.7150764465],"type":"Point"}
}