{
  "type": "Feature",
  "properties": {
    "addr:full":"Pr\u00e6stev\u00e6nget 4, Kirkebyen Ulfborg Danmark 6990",
    "addr:housenumber":"4",
    "addr:postcode":"6990",
    "addr:street":"Praestevaenget;Kirkebyen",
    "iso:country":"DK",
    "sg:address":"Pr\u00e6stev\u00e6nget 4, Kirkebyen",
    "sg:city":"Ulfborg",
    "sg:orig_category":"Autoopretning",
    "sg:phone":"+45 97 49 21 31",
    "sg:postcode":"6990",
    "sg:province":"Danmark",
    "wof:name":"Jensen, Jens Erik",
    "wof:placetype":"venue"
},
  "geometry": {"coordinates":[8.3210029602,56.2727661133],"type":"Point"}
}