{
  "type": "Feature",
  "properties": {
    "addr:full":"Sct. Nicolaj Gade 16 Ribe Danmark 6760",
    "addr:housenumber":"16",
    "addr:postcode":"6760",
    "addr:street":"Sct. Nicolaj Gade",
    "iso:country":"DK",
    "sg:address":"Sct. Nicolaj Gade 16",
    "sg:city":"Ribe",
    "sg:orig_category":"Biografer",
    "sg:phone":"+45 75 42 07 27",
    "sg:postcode":"6760",
    "sg:province":"Danmark",
    "wof:name":"Panorama",
    "wof:placetype":"venue"
},
  "geometry": {"coordinates":[8.768915,55.328373],"type":"Point"}
}