{
  "type": "Feature",
  "properties": {
    "addr:full":"Fmd.: Elma Lindberg, Naverhaven 4 Slagelse Danmark 4200",
    "addr:housenumber":"4",
    "addr:postcode":"4200",
    "addr:street":"Naverhaven",
    "iso:country":"DK",
    "sg:address":"Fmd.: Elma Lindberg, Naverhaven 4",
    "sg:city":"Slagelse",
    "sg:orig_category":"Politiske foreninger, \u00c3\u02dcvrige",
    "sg:phone":"+45 58 50 50 63",
    "sg:postcode":"4200",
    "sg:province":"Danmark",
    "sg:website":"www.folkebevaegelsen.dk",
    "wof:name":"Folkebev\u00e6gelsen Mod EU Slagelse/Kors\u00f8r/Sk\u00e6lsk\u00f8r/Sor\u00f8",
    "wof:placetype":"venue"
},
  "geometry": {"coordinates":[11.3569850922,55.4050865173],"type":"Point"}
}