{
  "type": "Feature",
  "properties": {
    "addr:full":"N\u00f8rrebrogade 9 Vejle Danmark 7100",
    "addr:housenumber":"9",
    "addr:postcode":"7100",
    "addr:street":"Norrebrogade",
    "iso:country":"DK",
    "sg:address":"N\u00f8rrebrogade 9",
    "sg:city":"Vejle",
    "sg:orig_category":"Begravelsesforretninger",
    "sg:phone":"+45 75 82 07 25",
    "sg:postcode":"7100",
    "sg:province":"Danmark",
    "wof:name":"Boesens Begravelsesforretning",
    "wof:placetype":"venue"
},
  "geometry": {"coordinates":[9.5382480621,55.7117042542],"type":"Point"}
}