{
  "type": "Feature",
  "properties": {
    "addr:full":"Rug\u00e5rdsvej 26 Odense C Danmark 5000",
    "addr:housenumber":"26",
    "addr:postcode":"5000",
    "addr:street":"Rugaardsvej",
    "iso:country":"DK",
    "sg:address":"Rug\u00e5rdsvej 26",
    "sg:city":"Odense C",
    "sg:orig_category":"Autoforhandlere",
    "sg:phone":"+45 66 12 69 22",
    "sg:postcode":"5000",
    "sg:province":"Danmark",
    "wof:name":"Nielsen, John Auto & Sport Parts ApS",
    "wof:placetype":"venue"
},
  "geometry": {"coordinates":[10.3739299774,55.3992195129],"type":"Point"}
}