{
  "type": "Feature",
  "properties": {
    "addr:full":"S\u00f8ndergade 58 A Toftlund Danmark 6520",
    "addr:housenumber":"58 a",
    "addr:postcode":"6520",
    "addr:street":"Sondergade",
    "iso:country":"DK",
    "sg:address":"S\u00f8ndergade 58 A",
    "sg:city":"Toftlund",
    "sg:orig_category":"Revisorer",
    "sg:phone":"+45 74 83 12 17",
    "sg:postcode":"6520",
    "sg:province":"Danmark",
    "sg:website":"www.frr.dk",
    "wof:name":"Feddersen ApS, Revisionsfirmaet",
    "wof:placetype":"venue"
},
  "geometry": {"coordinates":[9.0657062531,55.1867752075],"type":"Point"}
}