{
  "type": "Feature",
  "properties": {
    "addr:full":"Jernbanegade 4 Grindsted Danmark 7200",
    "addr:housenumber":"4",
    "addr:postcode":"7200",
    "addr:street":"Jernbanegade",
    "iso:country":"DK",
    "sg:address":"Jernbanegade 4",
    "sg:city":"Grindsted",
    "sg:orig_category":"Ejendomshandel",
    "sg:phone":"+45 75 32 09 42",
    "sg:postcode":"7200",
    "sg:province":"Danmark",
    "wof:name":"Kristiansen, Leo",
    "wof:placetype":"venue"
},
  "geometry": {"coordinates":[8.9281330109,55.7574234009],"type":"Point"}
}