{
  "type": "Feature",
  "properties": {
    "iso:country":"DK",
    "sg:address":"v/ Anni Vinding, Skolegade 6",
    "sg:city":"Bagenkop",
    "sg:orig_category":"Kulturelle foreninger",
    "sg:phone":"+45 62 56 13 63",
    "sg:postcode":"5935",
    "sg:province":"Danmark",
    "wof:name":"Magleby-Bagenkop Lokalhistoriske Forening",
    "wof:placetype":"venue"
},
  "geometry": {"coordinates":[10.6733856201,54.7496795654],"type":"Point"}
}