{
  "type": "Feature",
  "properties": {
    "addr:full":"Byhavevej 33 Svendborg Danmark 5700",
    "addr:housenumber":"33",
    "addr:postcode":"5700",
    "addr:street":"Byhavevej",
    "iso:country":"DK",
    "sg:address":"Byhavevej 33",
    "sg:city":"Svendborg",
    "sg:orig_category":"Pizzeriaer",
    "sg:phone":"+45 63 21 09 09",
    "sg:postcode":"5700",
    "sg:province":"Danmark",
    "wof:name":"Pappa's Pizzeria & Grill House Nr.2",
    "wof:placetype":"venue"
},
  "geometry": {"coordinates":[10.6366996765,55.078578949],"type":"Point"}
}