{
  "type": "Feature",
  "properties": {
    "addr:full":"Fmd.: Kirsten Kolby, Storegade 6 Tarm Danmark 6880",
    "addr:housenumber":"6",
    "addr:postcode":"6880",
    "addr:street":"Storegade",
    "iso:country":"DK",
    "sg:address":"Fmd.: Kirsten Kolby, Storegade 6",
    "sg:city":"Tarm",
    "sg:orig_category":"Teatre",
    "sg:phone":"+45 99 48 20 83",
    "sg:postcode":"6880",
    "sg:province":"Danmark",
    "wof:name":"Skjern/Egvad Teaterforening",
    "wof:placetype":"venue"
},
  "geometry": {"coordinates":[8.5200052261,55.9060554504],"type":"Point"}
}