{
  "type": "Feature",
  "properties": {
    "addr:full":"Turneringsleder: Carl Mortensen, Lysh\u00f8j M\u00f8llevej 31, Udbyover Havndal Danmark 8970",
    "addr:housenumber":"31",
    "addr:postcode":"8970",
    "addr:street":"Carl;Mollevej",
    "iso:country":"DK",
    "sg:address":"Turneringsleder: Carl Mortensen, Lysh\u00f8j M\u00f8llevej 31, Udbyover",
    "sg:city":"Havndal",
    "sg:orig_category":"Hobbybetonede foreninger",
    "sg:phone":"+45 86 47 00 34",
    "sg:postcode":"8970",
    "sg:province":"Danmark",
    "wof:name":"Hadsund Bridgeklub",
    "wof:placetype":"venue"
},
  "geometry": {"coordinates":[10.1937646866,56.6534461975],"type":"Point"}
}