{
  "type": "Feature",
  "properties": {
    "iso:country":"DK",
    "sg:address":"Skibbrogade 9",
    "sg:city":"Haderslev",
    "sg:orig_category":"Arkitekter",
    "sg:phone":"+45 74 53 15 63",
    "sg:postcode":"6100",
    "sg:province":"Danmark",
    "wof:name":"Th\u00f8gersen, Leif",
    "wof:placetype":"venue"
},
  "geometry": {"coordinates":[9.4960222244,55.2495346069],"type":"Point"}
}