{
  "type": "Feature",
  "properties": {
    "addr:full":"Mindelundsvej 2, Seden Odense N\u00d8 Danmark 5240",
    "addr:housenumber":"2",
    "addr:postcode":"5240",
    "addr:street":"Mindelundsvej;Seden",
    "iso:country":"DK",
    "sg:address":"Mindelundsvej 2, Seden",
    "sg:city":"Odense N\u00d8",
    "sg:classifiers":[
        {
            "category":"Communications",
            "subcategory":"Film & Video Production",
            "type":"Services"
        }
    ],
    "sg:phone":"+45 66 10 99 10",
    "sg:postcode":"5240",
    "sg:province":"Danmark",
    "sg:tags":[
        "radio-",
        "og",
        "tv-service"
    ],
    "wof:name":"Poulsen, Hans K.",
    "wof:placetype":"venue"
},
  "geometry": {"coordinates":[10.444185257,55.4261131287],"type":"Point"}
}