{
  "type": "Feature",
  "properties": {
    "addr:full":"Danmarksgade 23, st. tv. Randers Danmark 8900",
    "addr:housenumber":"23 st. tv.",
    "addr:postcode":"8900",
    "addr:street":"Danmarksgade",
    "iso:country":"DK",
    "sg:address":"Danmarksgade 23, st. tv.",
    "sg:city":"Randers",
    "sg:orig_category":"Revisorer",
    "sg:phone":"+45 86 40 44 36",
    "sg:postcode":"8900",
    "sg:province":"Danmark",
    "wof:name":"Hansen, S\u00f8ren J.",
    "wof:placetype":"venue"
},
  "geometry": {"coordinates":[10.0357952118,56.4593734741],"type":"Point"}
}