{
  "type": "Feature",
  "properties": {
    "addr:full":"Valkendorfsgade 22 K\u00f8benhavn Danmark 1151",
    "addr:housenumber":"22;1151",
    "addr:street":"Valkendorfsgade",
    "iso:country":"DK",
    "sg:address":"Valkendorfsgade 22",
    "sg:city":"K\u00f8benhavn",
    "sg:classifiers":[
        {
            "category":"Restaurant",
            "type":"Food & Drink"
        }
    ],
    "sg:phone":"+45 33 11 21 31",
    "sg:postcode":"1151",
    "sg:province":"Danmark",
    "sg:website":"www.pastabasta.dk",
    "wof:name":"Pasta Basta",
    "wof:placetype":"venue"
},
  "geometry": {"coordinates":[12.5801000595,55.6787986755],"type":"Point"}
}