{
  "type": "Feature",
  "properties": {
    "addr:full":"Hjertingvej 17 Varde Danmark 6800",
    "addr:housenumber":"17",
    "addr:postcode":"6800",
    "addr:street":"Hjertingvej",
    "iso:country":"DK",
    "sg:address":"Hjertingvej 17",
    "sg:city":"Varde",
    "sg:orig_category":"Forsikringer",
    "sg:phone":"+45 75 22 57 53",
    "sg:postcode":"6800",
    "sg:province":"Danmark",
    "wof:name":"Juul Poulsens Assurance",
    "wof:placetype":"venue"
},
  "geometry": {"coordinates":[8.4849538803,55.6154060364],"type":"Point"}
}