{
  "type": "Feature",
  "properties": {
    "addr:full":"Vinkelvej 17 Viborg Danmark 8800",
    "addr:housenumber":"17",
    "addr:postcode":"8800",
    "addr:street":"Vinkelvej",
    "iso:country":"DK",
    "sg:address":"Vinkelvej 17",
    "sg:city":"Viborg",
    "sg:orig_category":"Zoneterapeuter",
    "sg:phone":"+45 86 62 24 90",
    "sg:postcode":"8800",
    "sg:province":"Danmark",
    "sg:website":"www.zoneterapi.brask-nielsen.dk",
    "wof:name":"Brask - Nielsen, Gerda",
    "wof:placetype":"venue"
},
  "geometry": {"coordinates":[9.4506282806,56.4223632812],"type":"Point"}
}