{
  "type": "Feature",
  "properties": {
    "iso:country":"DK",
    "sg:address":"Rymarksvej 1",
    "sg:city":"Hellerup",
    "sg:orig_category":"Statslige direktorater og styrelser",
    "sg:phone":"+45 39 45 24 00",
    "sg:postcode":"2900",
    "sg:province":"Danmark",
    "sg:website":"www.visaid.dk",
    "wof:name":"Statens \u00d8jenklinik",
    "wof:placetype":"venue"
},
  "geometry": {"coordinates":[12.5634317398,55.7277107239],"type":"Point"}
}