{
  "type": "Feature",
  "properties": {
    "iso:country":"DK",
    "sg:address":"Valby Langgade 34 ",
    "sg:city":"Valby",
    "sg:classifiers":[
        {
            "category":"Shopping",
            "subcategory":"Clothing, Apparel, & Fashions",
            "type":"Retail Goods"
        }
    ],
    "sg:phone":"+45 36 16 48 17",
    "sg:postcode":"2500",
    "sg:province":"Danmark",
    "sg:tags":[
        "clothes"
    ],
    "wof:name":"ROBERT APS AF 1JUNI 1988",
    "wof:placetype":"venue"
},
  "geometry": {"coordinates":[12.5182199478,55.666683197],"type":"Point"}
}