{
  "type": "Feature",
  "properties": {
    "addr:full":"Hovedgaden \u00d8st 67 E, Over Jerstal Vojens Danmark 6500",
    "addr:housenumber":"67 e",
    "addr:postcode":"6500",
    "addr:street":"Hovedgaden Ost;Over Jerstal",
    "iso:country":"DK",
    "sg:address":"Hovedgaden \u00d8st 67 E, Over Jerstal",
    "sg:city":"Vojens",
    "sg:orig_category":"Forsamlingshuse",
    "sg:postcode":"6500",
    "sg:province":"Danmark",
    "wof:name":"Over Jerstal Borger- & Forsamlingshus",
    "wof:placetype":"venue"
},
  "geometry": {"coordinates":[9.2987146378,55.2457237244],"type":"Point"}
}