{
  "type": "Feature",
  "properties": {
    "addr:full":"R\u00e5dmands Boulevard 3 Randers Danmark 8900",
    "addr:housenumber":"3",
    "addr:postcode":"8900",
    "addr:street":"Boulevard",
    "iso:country":"DK",
    "sg:address":"R\u00e5dmands Boulevard 3",
    "sg:city":"Randers",
    "sg:orig_category":"Posthuse",
    "sg:phone":"+45 89 12 89 00",
    "sg:postcode":"8900",
    "sg:province":"Danmark",
    "wof:name":"Post Danmark",
    "wof:placetype":"venue"
},
  "geometry": {"coordinates":[10.0310811996,56.4690933228],"type":"Point"}
}