{
  "type": "Feature",
  "properties": {
    "addr:full":"Hadsundvej 123 Aalborg Danmark 9000",
    "addr:housenumber":"123",
    "addr:postcode":"9000",
    "addr:street":"Hadsundvej",
    "iso:country":"DK",
    "sg:address":"Hadsundvej 123",
    "sg:city":"Aalborg",
    "sg:classifiers":[
        {
            "category":"Restaurant",
            "type":"Food & Drink"
        }
    ],
    "sg:phone":"+45 98 14 25 87",
    "sg:postcode":"9000",
    "sg:province":"Danmark",
    "wof:name":"Jydepotten, Restaurant",
    "wof:placetype":"venue"
},
  "geometry": {"coordinates":[9.9551753998,57.0325698853],"type":"Point"}
}