{
  "type": "Feature",
  "properties": {
    "addr:full":"v/ Henning Berget, H\u00f8jeloft V\u00e6nge 20 V\u00e6rl\u00f8se Danmark 3500",
    "addr:housenumber":"20",
    "addr:postcode":"3500",
    "addr:street":"Vaenge",
    "iso:country":"DK",
    "sg:address":"v/ Henning Berget, H\u00f8jeloft V\u00e6nge 20",
    "sg:city":"V\u00e6rl\u00f8se",
    "sg:orig_category":"Kirkesogne",
    "sg:phone":"+45 44 48 01 25",
    "sg:postcode":"3500",
    "sg:province":"Danmark",
    "wof:name":"V\u00e6rl\u00f8se Sogns Kirkekontor",
    "wof:placetype":"venue"
},
  "geometry": {"coordinates":[-89.5733413696,35.6730995178],"type":"Point"}
}