{
  "type": "Feature",
  "properties": {
    "addr:full":"Markedsgade 10 A Bjerringbro Danmark 8850",
    "addr:housenumber":"10 a",
    "addr:postcode":"8850",
    "addr:street":"Markedsgade",
    "iso:country":"DK",
    "sg:address":"Markedsgade 10 A",
    "sg:city":"Bjerringbro",
    "sg:orig_category":"El-forsyning",
    "sg:phone":"+45 86 68 36 66",
    "sg:postcode":"8850",
    "sg:province":"Danmark",
    "wof:name":"Bjerringbro Elv\u00e6rk",
    "wof:placetype":"venue"
},
  "geometry": {"coordinates":[9.654129982,56.3771705627],"type":"Point"}
}