{
  "type": "Feature",
  "properties": {
    "addr:full":"Aarsballe By 5, Aarsballe R\u00f8nne Danmark 3700",
    "addr:housenumber":"5",
    "addr:postcode":"3700",
    "addr:street":"Aarsballe By",
    "iso:country":"DK",
    "sg:address":"Aarsballe By 5, Aarsballe",
    "sg:city":"R\u00f8nne",
    "sg:classifiers":[
        {
            "category":"Taxi",
            "type":"Transportation"
        }
    ],
    "sg:phone":"+45 56 99 92 41",
    "sg:postcode":"3700",
    "sg:province":"Danmark",
    "wof:name":"\u00c5rsballe Taxi",
    "wof:placetype":"venue"
},
  "geometry": {"coordinates":[14.6975498199,55.0993003845],"type":"Point"}
}