{
  "type": "Feature",
  "properties": {
    "addr:full":"Fmd.: J\u00f8rgen Haagen Nielsen, Havnevej 34 Hornb\u00e6k Danmark 3100",
    "addr:housenumber":"34",
    "addr:postcode":"3100",
    "addr:street":"Havnevej",
    "iso:country":"DK",
    "sg:address":"Fmd.: J\u00f8rgen Haagen Nielsen, Havnevej 34",
    "sg:city":"Hornb\u00e6k",
    "sg:orig_category":"Havne",
    "sg:phone":"+45 49 70 23 78",
    "sg:postcode":"3100",
    "sg:province":"Danmark",
    "wof:name":"Hornb\u00e6k Havn",
    "wof:placetype":"venue"
},
  "geometry": {"coordinates":[7.6789798737,47.6370315552],"type":"Point"}
}