{
  "type": "Feature",
  "properties": {
    "addr:full":"Mariendalsvej 9 Frederikshavn Danmark 9900",
    "addr:housenumber":"9",
    "addr:postcode":"9900",
    "addr:street":"Mariendalsvej",
    "iso:country":"DK",
    "sg:address":"Mariendalsvej 9",
    "sg:city":"Frederikshavn",
    "sg:orig_category":"Vinduespolering",
    "sg:phone":"+45 98 48 03 06",
    "sg:postcode":"9900",
    "sg:province":"Danmark",
    "wof:name":"M\u00f8ller, Tommy",
    "wof:placetype":"venue"
},
  "geometry": {"coordinates":[10.4696998596,57.4716491699],"type":"Point"}
}