{
  "type": "Feature",
  "properties": {
    "iso:country":"DK",
    "sg:address":"Engg\u00e5rdsvej 27, Kragelund",
    "sg:city":"L\u00f8sning",
    "sg:orig_category":"Maskinfabrikker",
    "sg:phone":"+45 75 89 35 33",
    "sg:postcode":"8723",
    "sg:province":"Danmark",
    "wof:name":"Jymika ApS",
    "wof:placetype":"venue"
},
  "geometry": {"coordinates":[9.7620611191,55.8105201721],"type":"Point"}
}