{
  "type": "Feature",
  "properties": {
    "addr:full":"Frederiksgade 16 Thisted Danmark 7700",
    "addr:housenumber":"16",
    "addr:postcode":"7700",
    "addr:street":"Frederiksgade",
    "iso:country":"DK",
    "sg:address":"Frederiksgade 16",
    "sg:city":"Thisted",
    "sg:orig_category":"HOTELS: OG MOTELLER",
    "sg:phone":"+45 97 92 52 00",
    "sg:postcode":"7700",
    "sg:province":"Danmark",
    "wof:name":"Thisted, Hotel",
    "wof:placetype":"venue"
},
  "geometry": {"coordinates":[8.6872520447,56.9536361694],"type":"Point"}
}