{
  "type": "Feature",
  "properties": {
    "addr:full":"Boholtevej 95 K\u00f8ge Danmark 4600",
    "addr:housenumber":"95",
    "addr:postcode":"4600",
    "addr:street":"Boholtevej",
    "iso:country":"DK",
    "sg:address":"Boholtevej 95",
    "sg:city":"K\u00f8ge",
    "sg:orig_category":"Erhvervsskoler",
    "sg:phone":"+45 56 63 10 00",
    "sg:postcode":"4600",
    "sg:province":"Danmark",
    "sg:website":"www.eucsj.dk",
    "wof:name":"EUC Sj\u00e6lland",
    "wof:placetype":"venue"
},
  "geometry": {"coordinates":[12.1647586823,55.4452514648],"type":"Point"}
}