{
  "type": "Feature",
  "properties": {
    "addr:full":"v/ Sonja og B\u00f8rge Rasmussen, Bygaden 21, Jegerup Vojens Danmark 6500",
    "addr:housenumber":"21",
    "addr:postcode":"6500",
    "addr:street":"Bygaden;Jegerup",
    "iso:country":"DK",
    "sg:address":"v/ Sonja og B\u00f8rge Rasmussen, Bygaden 21, Jegerup",
    "sg:city":"Vojens",
    "sg:orig_category":"Forsamlingshuse",
    "sg:phone":"+45 74 54 08 48",
    "sg:postcode":"6500",
    "sg:province":"Danmark",
    "wof:name":"Jegerup Forsamlingshus",
    "wof:placetype":"venue"
},
  "geometry": {"coordinates":[9.2987146378,55.2457237244],"type":"Point"}
}