{
  "type": "Feature",
  "properties": {
    "addr:full":"Bibliotekvej 49 Hvidovre Danmark 2650",
    "addr:housenumber":"49",
    "addr:postcode":"2650",
    "addr:street":"Bibliotekvej",
    "iso:country":"DK",
    "sg:address":"Bibliotekvej 49",
    "sg:city":"Hvidovre",
    "sg:orig_category":"Reklamegaver",
    "sg:phone":"+45 36 77 06 66",
    "sg:postcode":"2650",
    "sg:province":"Danmark",
    "wof:name":"Selection ApS",
    "wof:placetype":"venue"
},
  "geometry": {"coordinates":[12.470870018,55.641078949],"type":"Point"}
}