{
  "type": "Feature",
  "properties": {
    "addr:full":"Stationsvej 5 Hedensted Danmark 8722",
    "addr:housenumber":"5",
    "addr:postcode":"8722",
    "addr:street":"Stationsvej",
    "iso:country":"DK",
    "sg:address":"Stationsvej 5",
    "sg:city":"Hedensted",
    "sg:orig_category":"Hudpleje",
    "sg:phone":"+45 75 89 28 11",
    "sg:postcode":"8722",
    "sg:province":"Danmark",
    "wof:name":"Image, Clinique",
    "wof:placetype":"venue"
},
  "geometry": {"coordinates":[9.6986093521,55.7675018311],"type":"Point"}
}