{
  "type": "Feature",
  "properties": {
    "addr:full":"Gravl\u00f8kke 63 Bylderup-Bov Danmark 6372",
    "addr:housenumber":"63",
    "addr:postcode":"6372",
    "addr:street":"Gravlokke",
    "iso:country":"DK",
    "sg:address":"Gravl\u00f8kke 63",
    "sg:city":"Bylderup-Bov",
    "sg:orig_category":"EDB - udstyr",
    "sg:phone":"+45 74 76 14 15",
    "sg:postcode":"6372",
    "sg:province":"Danmark",
    "sg:website":"www.privatdata.dk",
    "wof:name":"Privat Data",
    "wof:placetype":"venue"
},
  "geometry": {"coordinates":[9.0920448303,54.9443130493],"type":"Point"}
}