{
  "type": "Feature",
  "properties": {
    "addr:full":"Svalevej 11 Aabybro Danmark 9440",
    "addr:housenumber":"11",
    "addr:postcode":"9440",
    "addr:street":"Svalevej",
    "iso:country":"DK",
    "sg:address":"Svalevej 11",
    "sg:city":"Aabybro",
    "sg:orig_category":"Zoneterapeuter",
    "sg:phone":"+45 98 24 25 62",
    "sg:postcode":"9440",
    "sg:province":"Danmark",
    "wof:name":"Simonsen, Inga",
    "wof:placetype":"venue"
},
  "geometry": {"coordinates":[9.731584549,57.1587982178],"type":"Point"}
}