{
  "type": "Feature",
  "properties": {
    "addr:full":"Pr\u00e6stehusene 111 Albertslund Danmark 2620",
    "addr:housenumber":"111",
    "addr:postcode":"2620",
    "iso:country":"DK",
    "sg:address":"Pr\u00e6stehusene 111",
    "sg:city":"Albertslund",
    "sg:orig_category":"Forlag",
    "sg:phone":"+45 43 45 23 83",
    "sg:postcode":"2620",
    "sg:province":"Danmark",
    "wof:name":"Tingluti Forlag",
    "wof:placetype":"venue"
},
  "geometry": {"coordinates":[12.3679094315,55.6717071533],"type":"Point"}
}