{
  "type": "Feature",
  "properties": {
    "addr:full":"Bogensevej 9 B Randers Danmark 8900",
    "addr:housenumber":"9 b",
    "addr:postcode":"8900",
    "addr:street":"Bogensevej",
    "iso:country":"DK",
    "sg:address":"Bogensevej 9 B",
    "sg:city":"Randers",
    "sg:orig_category":"Fabrikker",
    "sg:phone":"+45 86 42 82 77",
    "sg:postcode":"8900",
    "sg:province":"Danmark",
    "wof:name":"Eghoff M\u00f8belfabrik",
    "wof:placetype":"venue"
},
  "geometry": {"coordinates":[10.0296163559,56.4359512329],"type":"Point"}
}