{
  "type": "Feature",
  "properties": {
    "addr:full":"Tytteb\u00e6rvej 3 Viborg Danmark 8800",
    "addr:housenumber":"3",
    "addr:postcode":"8800",
    "addr:street":"Tyttebaervej",
    "iso:country":"DK",
    "sg:address":"Tytteb\u00e6rvej 3",
    "sg:city":"Viborg",
    "sg:orig_category":"Isolering",
    "sg:phone":"+45 86 62 21 18",
    "sg:postcode":"8800",
    "sg:province":"Danmark",
    "wof:name":"Viborg Isolering",
    "wof:placetype":"venue"
},
  "geometry": {"coordinates":[9.3948173523,56.4337158203],"type":"Point"}
}