{
  "type": "Feature",
  "properties": {
    "addr:full":"Leopardvej 8 Thisted Danmark 7700",
    "addr:housenumber":"8",
    "addr:postcode":"7700",
    "addr:street":"Leopardvej",
    "iso:country":"DK",
    "sg:address":"Leopardvej 8",
    "sg:city":"Thisted",
    "sg:orig_category":"Autolakering",
    "sg:phone":"+45 97 91 02 88",
    "sg:postcode":"7700",
    "sg:province":"Danmark",
    "wof:name":"Andersen, Knud",
    "wof:placetype":"venue"
},
  "geometry": {"coordinates":[8.7376127243,56.9618873596],"type":"Point"}
}