{
  "type": "Feature",
  "properties": {
    "addr:full":"Bolderslev Hovedgade 26 Bolderslev Danmark 6392",
    "addr:housenumber":"26",
    "addr:postcode":"6392",
    "addr:street":"Bolderslev Hovedgade",
    "iso:country":"DK",
    "sg:address":"Bolderslev Hovedgade 26",
    "sg:city":"Bolderslev",
    "sg:orig_category":"Autoreparation og -service",
    "sg:phone":"+45 74 64 64 99",
    "sg:postcode":"6392",
    "sg:province":"Danmark",
    "wof:name":"Bolderslev Autov\u00e6rksted",
    "wof:placetype":"venue"
},
  "geometry": {"coordinates":[9.2862300873,54.9915809631],"type":"Point"}
}