{
  "type": "Feature",
  "properties": {
    "addr:full":"Lyngby Hovedgade 78 Kongens Lyngby Danmark 2800",
    "addr:housenumber":"78",
    "addr:postcode":"2800",
    "addr:street":"Lyngby Hovedgade",
    "iso:country":"DK",
    "sg:address":"Lyngby Hovedgade 78",
    "sg:city":"Kongens Lyngby",
    "sg:orig_category":"Diners transportables",
    "sg:phone":"+45 45 87 01 95",
    "sg:postcode":"2800",
    "sg:province":"Danmark",
    "wof:name":"Post-Pub",
    "wof:placetype":"venue"
},
  "geometry": {"coordinates":[12.5053129196,55.7688713074],"type":"Point"}
}