{
  "type": "Feature",
  "properties": {
    "iso:country":"DK",
    "sg:address":"Thune Nielsens Vej 23, N\u00e6sby",
    "sg:city":"Odense N",
    "sg:orig_category":"Redningskorps",
    "sg:phone":"+45 66 18 06 63",
    "sg:postcode":"5270",
    "sg:province":"Danmark",
    "wof:name":"International Scuba Training",
    "wof:placetype":"venue"
},
  "geometry": {"coordinates":[10.3306798935,55.4711418152],"type":"Point"}
}