{
  "type": "Feature",
  "properties": {
    "addr:full":"Galgebakken Torv 2-6 Albertslund Danmark 2620",
    "addr:housenumber":"2-6",
    "addr:postcode":"2620",
    "addr:street":"Galgebakken Torv",
    "iso:country":"DK",
    "sg:address":"Galgebakken Torv 2-6",
    "sg:city":"Albertslund",
    "sg:orig_category":"Ungdomsklubber",
    "sg:phone":"+45 43 64 10 25",
    "sg:postcode":"2620",
    "sg:province":"Danmark",
    "wof:name":"Bakkens Hjerte",
    "wof:placetype":"venue"
},
  "geometry": {"coordinates":[12.3468732834,55.6789550781],"type":"Point"}
}