{
  "type": "Feature",
  "properties": {
    "addr:full":"N\u00f8rrebrogade 185 K\u00f8benhavn N Danmark 2200",
    "addr:housenumber":"185",
    "addr:postcode":"2200",
    "addr:street":"Norrebrogade;Kobenhavn N Danmark",
    "iso:country":"DK",
    "sg:address":"N\u00f8rrebrogade 185",
    "sg:city":"K\u00f8benhavn N",
    "sg:orig_category":"Slagter og viktualie",
    "sg:phone":"+45 35 85 23 43",
    "sg:postcode":"2200",
    "sg:province":"Danmark",
    "sg:website":"www.halalslagter.dk",
    "wof:name":"Slagterforretningen",
    "wof:placetype":"venue"
},
  "geometry": {"coordinates":[-76.4168395996,37.452419281],"type":"Point"}
}