{
  "type": "Feature",
  "properties": {
    "addr:full":"Ramsherred 15 Aabenraa Danmark 6200",
    "addr:housenumber":"15",
    "addr:postcode":"6200",
    "addr:street":"Ramsherred",
    "iso:country":"DK",
    "sg:address":"Ramsherred 15",
    "sg:city":"Aabenraa",
    "sg:orig_category":"Materialister",
    "sg:phone":"+45 74 62 27 27",
    "sg:postcode":"6200",
    "sg:province":"Danmark",
    "wof:name":"Matas Ramsherred",
    "wof:placetype":"venue"
},
  "geometry": {"coordinates":[9.4183635712,55.0469398499],"type":"Point"}
}