{
  "type": "Feature",
  "properties": {
    "iso:country":"DK",
    "sg:address":"S\u00f8ndre Ringvej 1 ",
    "sg:city":"Vejen",
    "sg:classifiers":[
        {
            "category":"Home & Garden",
            "subcategory":"Home Furnishings",
            "type":"Retail Goods"
        }
    ],
    "sg:phone":"+45 79 96 33 33",
    "sg:postcode":"6600",
    "sg:province":"Danmark",
    "sg:tags":[
        "household"
    ],
    "wof:name":"PLUS A/S",
    "wof:placetype":"venue"
},
  "geometry": {"coordinates":[9.1395540237,55.4621772766],"type":"Point"}
}