{
  "type": "Feature",
  "properties": {
    "addr:full":"Himmelbjergvej 69 Silkeborg Danmark 8600",
    "addr:housenumber":"69",
    "addr:postcode":"8600",
    "addr:street":"Himmelbjergvej",
    "iso:country":"DK",
    "sg:address":"Himmelbjergvej 69",
    "sg:city":"Silkeborg",
    "sg:orig_category":"Pressebureauer",
    "sg:phone":"+45 86 84 13 36",
    "sg:postcode":"8600",
    "sg:province":"Danmark",
    "wof:name":"Mediemageriet",
    "wof:placetype":"venue"
},
  "geometry": {"coordinates":[9.705742836,56.1245269775],"type":"Point"}
}