{
  "type": "Feature",
  "properties": {
    "addr:full":"Strandporten 5 Assens Danmark 5610",
    "addr:housenumber":"5",
    "addr:postcode":"5610",
    "addr:street":"Strandporten",
    "iso:country":"DK",
    "sg:address":"Strandporten 5",
    "sg:city":"Assens",
    "sg:orig_category":"Autoreparation og -service",
    "sg:phone":"+45 64 71 12 60",
    "sg:postcode":"5610",
    "sg:province":"Danmark",
    "wof:name":"Strandportens Auto",
    "wof:placetype":"venue"
},
  "geometry": {"coordinates":[9.8913984299,55.2702713013],"type":"Point"}
}