{
  "type": "Feature",
  "properties": {
    "addr:full":"Kontaktpers: Jette Foldager, Teglg\u00e5rdvej 32 Sunds Danmark 7451",
    "addr:housenumber":"32",
    "addr:postcode":"7451",
    "addr:street":"Kontaktpers;Teglgaardvej",
    "iso:country":"DK",
    "sg:address":"Kontaktpers: Jette Foldager, Teglg\u00e5rdvej 32",
    "sg:city":"Sunds",
    "sg:orig_category":"Husflidsforeninger",
    "sg:phone":"+45 97 14 29 30",
    "sg:postcode":"7451",
    "sg:province":"Danmark",
    "wof:name":"Sunds Husmoderforening",
    "wof:placetype":"venue"
},
  "geometry": {"coordinates":[9.0151100159,56.2057800293],"type":"Point"}
}