{
  "type": "Feature",
  "properties": {
    "addr:full":"J\u00e6gerg\u00e5rdsgade 154 \u00c5rhus C Danmark 8000",
    "addr:housenumber":"154",
    "addr:postcode":"8000",
    "addr:street":"Jaegergaardsgade",
    "iso:country":"DK",
    "sg:address":"J\u00e6gerg\u00e5rdsgade 154",
    "sg:city":"\u00c5rhus C",
    "sg:classifiers":[
        {
            "category":"Restaurant",
            "type":"Food & Drink"
        }
    ],
    "sg:phone":"+45 86 12 14 81",
    "sg:postcode":"8000",
    "sg:province":"Danmark",
    "wof:name":"Kohalen, Restaurant",
    "wof:placetype":"venue"
},
  "geometry": {"coordinates":[4.717400074,49.7588005066],"type":"Point"}
}