{
  "type": "Feature",
  "properties": {
    "iso:country":"DK",
    "sg:address":"Adelgade 78",
    "sg:city":"Hobro",
    "sg:orig_category":"Daginstitution for voksne",
    "sg:phone":"+45 96 57 67 66",
    "sg:postcode":"9500",
    "sg:province":"Danmark",
    "wof:name":"V\u00e6restedet Bl\u00e6ksprutten",
    "wof:placetype":"venue"
},
  "geometry": {"coordinates":[9.7972459793,56.6359939575],"type":"Point"}
}