{
  "type": "Feature",
  "properties": {
    "iso:country":"DK",
    "sg:address":"Annebergvej 71",
    "sg:city":"Aalborg",
    "sg:orig_category":"Behandlingshjem",
    "sg:phone":"+45 98 13 45 66",
    "sg:postcode":"9000",
    "sg:province":"Danmark",
    "wof:name":"Amtsspecialet, Familier - Toppen",
    "wof:placetype":"venue"
},
  "geometry": {"coordinates":[9.895589,57.050762],"type":"Point"}
}