{
  "type": "Feature",
  "properties": {
    "iso:country":"DK",
    "sg:address":"Kertemindevej 33 ",
    "sg:city":"Marslev",
    "sg:classifiers":[
        {
            "category":"Farming",
            "subcategory":"Livestock Farm",
            "type":"Manufacturing & Wholesale Goods"
        }
    ],
    "sg:phone":"+45 65 95 14 33",
    "sg:postcode":"5290",
    "sg:province":"Danmark",
    "sg:tags":[
        "agriculture"
    ],
    "wof:name":"GARTNERIET BENT HALBY A/S",
    "wof:placetype":"venue"
},
  "geometry": {"coordinates":[10.55534935,55.3986053467],"type":"Point"}
}