{
  "type": "Feature",
  "properties": {
    "addr:full":"Birkevangen 5 Esbjerg N Danmark 6715",
    "addr:housenumber":"5",
    "addr:postcode":"6715",
    "addr:street":"Birkevangen",
    "iso:country":"DK",
    "sg:address":"Birkevangen 5",
    "sg:city":"Esbjerg N",
    "sg:orig_category":"Kontorartikler",
    "sg:phone":"+45 75 15 49 80",
    "sg:postcode":"6715",
    "sg:province":"Danmark",
    "sg:website":"www.resultsys.suite.dk",
    "wof:name":"Result System",
    "wof:placetype":"venue"
},
  "geometry": {"coordinates":[8.4346323013,55.5027122498],"type":"Point"}
}