{
  "type": "Feature",
  "properties": {
    "iso:country":"DK",
    "sg:address":"Bernstorffsvej 10",
    "sg:city":"Odense C",
    "sg:orig_category":"Advokater",
    "sg:phone":"+45 66 14 12 01",
    "sg:postcode":"5000",
    "sg:province":"Danmark",
    "wof:name":"L\u00f8nkj\u00e6r, Niels",
    "wof:placetype":"venue"
},
  "geometry": {"coordinates":[10.3974647522,55.3895568848],"type":"Point"}
}