{
  "type": "Feature",
  "properties": {
    "addr:full":"Holl\u00e6ndervej 4 Skagen Danmark 9990",
    "addr:housenumber":"4",
    "addr:postcode":"9990",
    "addr:street":"Hollaendervej",
    "iso:country":"DK",
    "sg:address":"Holl\u00e6ndervej 4",
    "sg:city":"Skagen",
    "sg:orig_category":"Kunstmalere",
    "sg:phone":"+45 98 44 56 40",
    "sg:postcode":"9990",
    "sg:province":"Danmark",
    "wof:name":"Winther, Poul",
    "wof:placetype":"venue"
},
  "geometry": {"coordinates":[10.6019506454,57.7275238037],"type":"Point"}
}