{
  "type": "Feature",
  "properties": {
    "iso:country":"DK",
    "sg:address":"Havnefoged: Thorkild Byriel Jensen, Vangled 30, Nordby",
    "sg:city":"Fan\u00f8",
    "sg:orig_category":"Havne",
    "sg:phone":"+45 75 16 26 50",
    "sg:postcode":"6720",
    "sg:province":"Danmark",
    "wof:name":"Nordby Havn",
    "wof:placetype":"venue"
},
  "geometry": {"coordinates":[8.4069461823,55.4484786987],"type":"Point"}
}