{
  "type": "Feature",
  "properties": {
    "addr:full":"Centerholmen 12 E Greve Danmark 2670",
    "addr:housenumber":"12 e",
    "addr:postcode":"2670",
    "addr:street":"Centerholmen",
    "iso:country":"DK",
    "sg:address":"Centerholmen 12 E",
    "sg:city":"Greve",
    "sg:classifiers":[
        {
            "category":"Communications",
            "type":"Services"
        }
    ],
    "sg:phone":"+45 43 97 77 47",
    "sg:postcode":"2670",
    "sg:province":"Danmark",
    "sg:tags":[
        "og",
        "tv",
        "radio"
    ],
    "sg:website":"www.kbimport.dk",
    "wof:name":"KB Audio",
    "wof:placetype":"venue"
},
  "geometry": {"coordinates":[12.2941808701,55.5844078064],"type":"Point"}
}