{
  "type": "Feature",
  "properties": {
    "addr:full":"Rolighedsvej 4, Femm\u00f8ller Ebeltoft Danmark 8400",
    "addr:housenumber":"4",
    "addr:postcode":"8400",
    "addr:street":"Rolighedsvej",
    "iso:country":"DK",
    "sg:address":"Rolighedsvej 4, Femm\u00f8ller",
    "sg:city":"Ebeltoft",
    "sg:orig_category":"Arkitekter",
    "sg:phone":"+45 86 36 26 55",
    "sg:postcode":"8400",
    "sg:province":"Danmark",
    "wof:name":"Intern-Design Tegnestue",
    "wof:placetype":"venue"
},
  "geometry": {"coordinates":[10.6778745651,56.199798584],"type":"Point"}
}