{
  "type": "Feature",
  "properties": {
    "addr:full":"Strandvejen 94 Henne Danmark 6854",
    "addr:housenumber":"94",
    "addr:postcode":"6854",
    "addr:street":"Strandvejen",
    "iso:country":"DK",
    "sg:address":"Strandvejen 94",
    "sg:city":"Henne",
    "sg:orig_category":"Murermestre",
    "sg:phone":"+45 75 25 50 16",
    "sg:postcode":"6854",
    "sg:province":"Danmark",
    "wof:name":"Kj\u00e6r Henne ApS, B.",
    "wof:placetype":"venue"
},
  "geometry": {"coordinates":[8.301779747,55.7115211487],"type":"Point"}
}