{
  "type": "Feature",
  "properties": {
    "addr:full":"Over Hadstenvej 26 - 28 Hadsten Danmark 8370",
    "addr:housenumber":"26 28",
    "addr:postcode":"8370",
    "addr:street":"Over Hadstenvej",
    "iso:country":"DK",
    "sg:address":"Over Hadstenvej 26 - 28",
    "sg:city":"Hadsten",
    "sg:orig_category":"Autoforhandlere",
    "sg:phone":"+45 86 98 09 22",
    "sg:postcode":"8370",
    "sg:province":"Danmark",
    "wof:name":"Autohuset Hadsten A/S",
    "wof:placetype":"venue"
},
  "geometry": {"coordinates":[10.0383558273,56.3179244995],"type":"Point"}
}