{
  "type": "Feature",
  "properties": {
    "addr:full":"Hegnet 4 - 6, H\u00f8bjerg Helsinge Danmark 3200",
    "addr:housenumber":"4 6",
    "addr:postcode":"3200",
    "addr:street":"Hegnet;Hobjerg",
    "iso:country":"DK",
    "sg:address":"Hegnet 4 - 6, H\u00f8bjerg",
    "sg:city":"Helsinge",
    "sg:orig_category":"Snedkermestre",
    "sg:phone":"+45 48 79 44 18",
    "sg:postcode":"3200",
    "sg:province":"Danmark",
    "wof:name":"Nielsen, Henning",
    "wof:placetype":"venue"
},
  "geometry": {"coordinates":[12.196846962,56.0224456787],"type":"Point"}
}