{
  "type": "Feature",
  "properties": {
    "addr:full":"Ved Stranden 7 Aalborg Danmark 9000",
    "addr:housenumber":"7",
    "addr:postcode":"9000",
    "addr:street":"Ved Stranden",
    "iso:country":"DK",
    "sg:address":"Ved Stranden 7",
    "sg:city":"Aalborg",
    "sg:classifiers":[
        {
            "category":"Restaurant",
            "type":"Food & Drink"
        }
    ],
    "sg:phone":"+45 98 16 17 77",
    "sg:postcode":"9000",
    "sg:province":"Danmark",
    "wof:name":"Boldt, Hos",
    "wof:placetype":"venue"
},
  "geometry": {"coordinates":[9.9211463928,57.0503425598],"type":"Point"}
}