{
  "type": "Feature",
  "properties": {
    "addr:full":"Tuksh\u00f8jen 41 Herlev Danmark 2730",
    "addr:housenumber":"41",
    "addr:postcode":"2730",
    "addr:street":"Tukshojen",
    "iso:country":"DK",
    "sg:address":"Tuksh\u00f8jen 41",
    "sg:city":"Herlev",
    "sg:orig_category":"Revisorer",
    "sg:phone":"+45 44 91 74 30",
    "sg:postcode":"2730",
    "sg:province":"Danmark",
    "wof:name":"AW-Revision",
    "wof:placetype":"venue"
},
  "geometry": {"coordinates":[12.4530467987,55.7207794189],"type":"Point"}
}