{
  "type": "Feature",
  "properties": {
    "addr:full":"Horseballevej 13, Ny Stenderup Broby Danmark 5672",
    "addr:housenumber":"13",
    "addr:postcode":"5672",
    "addr:street":"Horseballevej",
    "iso:country":"DK",
    "sg:address":"Horseballevej 13, Ny Stenderup",
    "sg:city":"Broby",
    "sg:orig_category":"Autoreparation og -service",
    "sg:phone":"+45 62 68 15 63",
    "sg:postcode":"5672",
    "sg:province":"Danmark",
    "wof:name":"TP Tuning",
    "wof:placetype":"venue"
},
  "geometry": {"coordinates":[10.3131303787,55.2695846558],"type":"Point"}
}