{
  "type": "Feature",
  "properties": {
    "iso:country":"DK",
    "sg:address":"\u00d8stergade 30",
    "sg:city":"Silkeborg",
    "sg:classifiers":[
        {
            "category":"Food & Beverages",
            "subcategory":"Liquor & Beverages",
            "type":"Retail Goods"
        }
    ],
    "sg:phone":"+45 86 80 63 63",
    "sg:postcode":"8600",
    "sg:province":"Danmark",
    "sg:tags":[
        "vin"
    ],
    "wof:name":"Vink\u00e6lderen",
    "wof:placetype":"venue"
},
  "geometry": {"coordinates":[9.5532855988,56.1703186035],"type":"Point"}
}