{
  "type": "Feature",
  "properties": {
    "iso:country":"DK",
    "sg:address":"Kamillevej 10",
    "sg:city":"Kastrup",
    "sg:orig_category":"Biblioteker",
    "sg:phone":"+45 32 46 05 00",
    "sg:postcode":"2770",
    "sg:province":"Danmark",
    "wof:name":"T\u00e5rnby Kommunebiblioteker Hovedbiblioteket",
    "wof:placetype":"venue"
},
  "geometry": {"coordinates":[12.622909,55.633106],"type":"Point"}
}