{
  "type": "Feature",
  "properties": {
    "iso:country":"DK",
    "sg:address":"Husumvej 58",
    "sg:city":"Br\u00f8nsh\u00f8j",
    "sg:orig_category":"Blomsterhandlere",
    "sg:phone":"+45 38 60 39 15",
    "sg:postcode":"2700",
    "sg:province":"Danmark",
    "wof:name":"Brostr\u00f8m, Svend",
    "wof:placetype":"venue"
},
  "geometry": {"coordinates":[-65.6866531372,-23.1981296539],"type":"Point"}
}