{
  "type": "Feature",
  "properties": {
    "addr:full":"Peter Bangs Vej 57 Frederiksberg Danmark 2000",
    "addr:housenumber":"57",
    "addr:postcode":"2000",
    "addr:street":"Peter Bangs Vej",
    "iso:country":"DK",
    "sg:address":"Peter Bangs Vej 57",
    "sg:city":"Frederiksberg",
    "sg:orig_category":"Blomsterhandlere",
    "sg:phone":"+45 38 86 18 29",
    "sg:postcode":"2000",
    "sg:province":"Danmark",
    "wof:name":"Fr\u00f8kapslen",
    "wof:placetype":"venue"
},
  "geometry": {"coordinates":[12.5097112656,55.6786766052],"type":"Point"}
}