{
  "type": "Feature",
  "properties": {
    "addr:full":"Fynshovedvej 301 Dalby Danmark 5380",
    "addr:housenumber":"301",
    "addr:postcode":"5380",
    "addr:street":"Fynshovedvej",
    "iso:country":"DK",
    "sg:address":"Fynshovedvej 301",
    "sg:city":"Dalby",
    "sg:orig_category":"Malermestre",
    "sg:phone":"+45 65 34 12 13",
    "sg:postcode":"5380",
    "sg:province":"Danmark",
    "wof:name":"Andersen, J\u00f8rn",
    "wof:placetype":"venue"
},
  "geometry": {"coordinates":[10.655040741,55.5158996582],"type":"Point"}
}