{
  "type": "Feature",
  "properties": {
    "addr:full":"Beltoften 18 Gistrup Danmark 9260",
    "addr:housenumber":"18",
    "addr:postcode":"9260",
    "addr:street":"Beltoften",
    "iso:country":"DK",
    "sg:address":"Beltoften 18",
    "sg:city":"Gistrup",
    "sg:orig_category":"Handicapboliger",
    "sg:phone":"+45 98 32 35 66",
    "sg:postcode":"9260",
    "sg:province":"Danmark",
    "wof:name":"Boenheden Beltoften",
    "wof:placetype":"venue"
},
  "geometry": {"coordinates":[9.9970588684,56.9986343384],"type":"Point"}
}