{
  "type": "Feature",
  "properties": {
    "iso:country":"DK",
    "sg:address":"Torvet 3",
    "sg:city":"Ansager",
    "sg:orig_category":"Slagter og viktualie",
    "sg:phone":"+45 75 29 70 60",
    "sg:postcode":"6823",
    "sg:province":"Danmark",
    "wof:name":"Slagteren i Ansager",
    "wof:placetype":"venue"
},
  "geometry": {"coordinates":[8.7517995834,55.7050704956],"type":"Point"}
}