{
  "type": "Feature",
  "properties": {
    "addr:full":"Reventlowsgade 8 K\u00f8benhavn Danmark 1651",
    "addr:housenumber":"8;1651",
    "addr:street":"Reventlowsgade",
    "iso:country":"DK",
    "sg:address":"Reventlowsgade 8",
    "sg:city":"K\u00f8benhavn",
    "sg:orig_category":"Rejsebureauer",
    "sg:phone":"+45 33 88 70 00",
    "sg:postcode":"1651",
    "sg:province":"Danmark",
    "wof:name":"Thinggaard Rejser",
    "wof:placetype":"venue"
},
  "geometry": {"coordinates":[12.5645904541,55.6723899841],"type":"Point"}
}