{
  "type": "Feature",
  "properties": {
    "addr:full":"Fmd.: Jesper Hansen, Smedeparken 12, Slimminge Ringsted Danmark 4100",
    "addr:housenumber":"12",
    "addr:postcode":"4100",
    "addr:street":"Smedeparken;Slimminge",
    "iso:country":"DK",
    "sg:address":"Fmd.: Jesper Hansen, Smedeparken 12, Slimminge",
    "sg:city":"Ringsted",
    "sg:orig_category":"Grundejerforeninger",
    "sg:phone":"+45 56 87 97 02",
    "sg:postcode":"4100",
    "sg:province":"Danmark",
    "wof:name":"Gammel Slimminge Grundejerforening",
    "wof:placetype":"venue"
},
  "geometry": {"coordinates":[11.7875862122,55.4458961487],"type":"Point"}
}