{
  "type": "Feature",
  "properties": {
    "addr:full":"Sognepr\u00e6st: Hans Peter Bandholm (K/B), Skippergade 21 Asaa Danmark 9340",
    "addr:housenumber":"21",
    "addr:postcode":"9340",
    "addr:street":"Skippergade",
    "iso:country":"DK",
    "sg:address":"Sognepr\u00e6st: Hans Peter Bandholm (K/B), Skippergade 21",
    "sg:city":"Asaa",
    "sg:orig_category":"Kirkesogne",
    "sg:phone":"+45 98 85 10 18",
    "sg:postcode":"9340",
    "sg:province":"Danmark",
    "wof:name":"Asaa-Melholt Sogn",
    "wof:placetype":"venue"
},
  "geometry": {"coordinates":[10.4039297104,57.1481704712],"type":"Point"}
}