{
  "type": "Feature",
  "properties": {
    "addr:full":"Sahure Okur, Mimersgade 115 K\u00f8benhavn N Danmark 2200",
    "addr:housenumber":"115",
    "addr:postcode":"2200",
    "addr:street":"Mimersgade;N Danmark",
    "iso:country":"DK",
    "sg:address":"Sahure Okur, Mimersgade 115",
    "sg:city":"K\u00f8benhavn N",
    "sg:orig_category":"Grillbarer",
    "sg:phone":"+45 35 83 47 01",
    "sg:postcode":"2200",
    "sg:province":"Danmark",
    "wof:name":"Borgmestergrillen",
    "wof:placetype":"venue"
},
  "geometry": {"coordinates":[12.5400104523,55.701259613],"type":"Point"}
}