{
  "type": "Feature",
  "properties": {
    "addr:full":"Mand\u00f8vej 2, V. Vedsted Ribe Danmark 6760",
    "addr:housenumber":"2",
    "addr:postcode":"6760",
    "addr:street":"Mandovej;V. Vedsted",
    "iso:country":"DK",
    "sg:address":"Mand\u00f8vej 2, V. Vedsted",
    "sg:city":"Ribe",
    "sg:orig_category":"Trikotage",
    "sg:phone":"+45 75 44 50 15",
    "sg:postcode":"6760",
    "sg:province":"Danmark",
    "wof:name":"Guldberg, Karen M.",
    "wof:placetype":"venue"
},
  "geometry": {"coordinates":[8.7656240463,55.3297042847],"type":"Point"}
}