{
  "type": "Feature",
  "properties": {
    "iso:country":"DK",
    "sg:address":"N\u00f8rregade 12",
    "sg:city":"Vejle",
    "sg:orig_category":"Tandteknikere, Kliniske",
    "sg:phone":"+45 75 82 15 11",
    "sg:postcode":"7100",
    "sg:province":"Danmark",
    "wof:name":"Andersen, Birgith",
    "wof:placetype":"venue"
},
  "geometry": {"coordinates":[9.5343780518,55.7100906372],"type":"Point"}
}