{
  "type": "Feature",
  "properties": {
    "iso:country":"DK",
    "sg:address":"Provstistr\u00e6de 14",
    "sg:city":"Assens",
    "sg:orig_category":"Skolefritidsordninger",
    "sg:phone":"+45 64 71 14 52",
    "sg:postcode":"5610",
    "sg:province":"Danmark",
    "wof:name":"Borgerskolens fritidsordning",
    "wof:placetype":"venue"
},
  "geometry": {"coordinates":[9.8947944641,55.2685394287],"type":"Point"}
}