{
  "type": "Feature",
  "properties": {
    "addr:full":"Husby Alle 8 Taastrup Danmark 2630",
    "addr:housenumber":"8",
    "addr:postcode":"2630",
    "addr:street":"Husby Alle",
    "iso:country":"DK",
    "sg:address":"Husby Alle 8",
    "sg:city":"Taastrup",
    "sg:orig_category":"Kommunikationsudstyr",
    "sg:phone":"+45 43 71 64 64",
    "sg:postcode":"2630",
    "sg:province":"Danmark",
    "wof:name":"Aage Hempel A/S",
    "wof:placetype":"venue"
},
  "geometry": {"coordinates":[12.2949867249,55.6594848633],"type":"Point"}
}