{
  "type": "Feature",
  "properties": {
    "addr:full":"Glostrupvej 21, Egebjerg Nyk\u00f8bing Danmark 4500",
    "addr:housenumber":"21",
    "addr:postcode":"4500",
    "addr:street":"Glostrupvej",
    "iso:country":"DK",
    "sg:address":"Glostrupvej 21, Egebjerg",
    "sg:city":"Nyk\u00f8bing",
    "sg:orig_category":"Murermestre",
    "sg:phone":"+45 59 32 88 31",
    "sg:postcode":"4500",
    "sg:province":"Danmark",
    "wof:name":"Din Murermester ApS",
    "wof:placetype":"venue"
},
  "geometry": {"coordinates":[11.6107749939,55.938621521],"type":"Point"}
}