{
  "type": "Feature",
  "properties": {
    "addr:full":"Lilleholm 1 Greve Danmark 2670",
    "addr:housenumber":"1",
    "addr:postcode":"2670",
    "addr:street":"Lilleholm",
    "iso:country":"DK",
    "sg:address":"Lilleholm 1",
    "sg:city":"Greve",
    "sg:orig_category":"Supermarkeder",
    "sg:postcode":"2670",
    "sg:province":"Danmark",
    "wof:name":"Netto",
    "wof:placetype":"venue"
},
  "geometry": {"coordinates":[12.2755794525,55.5776329041],"type":"Point"}
}