{
  "type": "Feature",
  "properties": {
    "addr:full":"N\u00f8rregade 39 Holstebro Danmark 7500",
    "addr:housenumber":"39",
    "addr:postcode":"7500",
    "addr:street":"Norregade",
    "iso:country":"DK",
    "sg:address":"N\u00f8rregade 39",
    "sg:city":"Holstebro",
    "sg:orig_category":"Psykologer, praktiserende",
    "sg:phone":"+45 97 40 20 04",
    "sg:postcode":"7500",
    "sg:province":"Danmark",
    "wof:name":"Jensen ApS, Psykolog Sonja",
    "wof:placetype":"venue"
},
  "geometry": {"coordinates":[8.6182126999,56.3609886169],"type":"Point"}
}