{
  "type": "Feature",
  "properties": {
    "iso:country":"DK",
    "sg:address":"Fmd.: J\u00f8rgen Hansen, Smedebjergevej 86, Vejerslev",
    "sg:city":"Vils",
    "sg:orig_category":"Borger- og beboerforeninger",
    "sg:phone":"+45 97 76 70 19",
    "sg:postcode":"7980",
    "sg:province":"Danmark",
    "wof:name":"Vejerslev Beboerforening",
    "wof:placetype":"venue"
},
  "geometry": {"coordinates":[8.7282047272,56.7638053894],"type":"Point"}
}