{
  "type": "Feature",
  "properties": {
    "addr:full":"Borgergade 8 A Lang\u00e5 Danmark 8870",
    "addr:housenumber":"8 a",
    "addr:postcode":"8870",
    "addr:street":"Borgergade",
    "iso:country":"DK",
    "sg:address":"Borgergade 8 A",
    "sg:city":"Lang\u00e5",
    "sg:orig_category":"Kaffe en gros",
    "sg:phone":"+45 86 46 24 64",
    "sg:postcode":"8870",
    "sg:province":"Danmark",
    "sg:website":"www.frellsen.dk",
    "wof:name":"Frellsen Kaffe",
    "wof:placetype":"venue"
},
  "geometry": {"coordinates":[9.896856308,56.3905677795],"type":"Point"}
}