{
  "type": "Feature",
  "properties": {
    "iso:country":"DK",
    "sg:address":"Idr\u00e6tsvej 1",
    "sg:city":"Snedsted",
    "sg:orig_category":"Varmeforsyning",
    "sg:phone":"+45 97 93 43 01",
    "sg:postcode":"7752",
    "sg:province":"Danmark",
    "wof:name":"Snedsted Varmev\u00e6rk A.m.b.A.",
    "wof:placetype":"venue"
},
  "geometry": {"coordinates":[8.5253038406,56.8930015564],"type":"Point"}
}