{
  "type": "Feature",
  "properties": {
    "addr:full":"Brentingevej 12 Tisvildeleje Danmark 3220",
    "addr:housenumber":"12",
    "addr:postcode":"3220",
    "addr:street":"Brentingevej",
    "iso:country":"DK",
    "sg:address":"Brentingevej 12",
    "sg:city":"Tisvildeleje",
    "sg:orig_category":"Reparationer",
    "sg:phone":"+45 48 70 75 35",
    "sg:postcode":"3220",
    "sg:province":"Danmark",
    "wof:name":"Bents Stork\u00f8kken Service",
    "wof:placetype":"venue"
},
  "geometry": {"coordinates":[12.1024665833,56.0589637756],"type":"Point"}
}