{
  "type": "Feature",
  "properties": {
    "iso:country":"DK",
    "sg:address":"Vesterbro 79",
    "sg:city":"Aalborg",
    "sg:classifiers":[
        {
            "category":"Banks & Credit Unions",
            "subcategory":"Bank",
            "type":"Services"
        }
    ],
    "sg:phone":"+45 98 12 17 33",
    "sg:postcode":"9000",
    "sg:province":"Danmark",
    "sg:tags":[
        "banker"
    ],
    "wof:name":"N\u00f8rresundby Bank Vesterbro Afd.",
    "wof:placetype":"venue"
},
  "geometry": {"coordinates":[9.915728,57.048656],"type":"Point"}
}