{
  "type": "Feature",
  "properties": {
    "addr:full":"Krebseparken 127 Esbjerg V Danmark 6710",
    "addr:housenumber":"127",
    "addr:postcode":"6710",
    "addr:street":"Krebseparken",
    "iso:country":"DK",
    "sg:address":"Krebseparken 127",
    "sg:city":"Esbjerg V",
    "sg:orig_category":"Vinduespolering",
    "sg:phone":"+45 20 28 47 64",
    "sg:postcode":"6710",
    "sg:province":"Danmark",
    "wof:name":"Bjarne`s Vinduespolering",
    "wof:placetype":"venue"
},
  "geometry": {"coordinates":[8.4237165451,55.5033035278],"type":"Point"}
}