{
  "type": "Feature",
  "properties": {
    "addr:full":"N\u00f8rregade 8 Hornsyld Danmark 8783",
    "addr:housenumber":"8",
    "addr:postcode":"8783",
    "addr:street":"Norregade",
    "iso:country":"DK",
    "sg:address":"N\u00f8rregade 8",
    "sg:city":"Hornsyld",
    "sg:orig_category":"Tandklinikker, Kommunale",
    "sg:phone":"+45 75 68 77 27",
    "sg:postcode":"8783",
    "sg:province":"Danmark",
    "wof:name":"Tandplejen i Hornsyld",
    "wof:placetype":"venue"
},
  "geometry": {"coordinates":[9.8625202179,55.7569007874],"type":"Point"}
}