{
  "type": "Feature",
  "properties": {
    "addr:full":"Bernhard Bangs Alle 29 Frederiksberg Danmark 2000",
    "addr:housenumber":"29",
    "addr:postcode":"2000",
    "addr:street":"Bernhard Bangs Alle",
    "iso:country":"DK",
    "sg:address":"Bernhard Bangs Alle 29",
    "sg:city":"Frederiksberg",
    "sg:orig_category":"Reklame",
    "sg:phone":"+45 38 86 75 77",
    "sg:postcode":"2000",
    "sg:province":"Danmark",
    "sg:website":"www.sponsormatic.dk",
    "wof:name":"Sponsormatic A/S",
    "wof:placetype":"venue"
},
  "geometry": {"coordinates":[12.5085773468,55.6848144531],"type":"Point"}
}