{
  "type": "Feature",
  "properties": {
    "addr:full":"Rantzausgade 72 K\u00f8benhavn N Danmark 2200",
    "addr:housenumber":"72",
    "addr:postcode":"2200",
    "addr:street":"Rantzausgade;Kobenhavn N Danmark",
    "iso:country":"DK",
    "sg:address":"Rantzausgade 72",
    "sg:city":"K\u00f8benhavn N",
    "sg:orig_category":"Elektronik",
    "sg:phone":"+45 35 35 05 45",
    "sg:postcode":"2200",
    "sg:province":"Danmark",
    "wof:name":"Larsen, H B",
    "wof:placetype":"venue"
},
  "geometry": {"coordinates":[-94.444190979,47.9254951477],"type":"Point"}
}