{
  "type": "Feature",
  "properties": {
    "addr:full":"Pergolavej 4 Virum Danmark 2830",
    "addr:housenumber":"4",
    "addr:postcode":"2830",
    "addr:street":"Pergolavej",
    "iso:country":"DK",
    "sg:address":"Pergolavej 4",
    "sg:city":"Virum",
    "sg:orig_category":"Fodterapeuter",
    "sg:phone":"+45 45 83 01 51",
    "sg:postcode":"2830",
    "sg:province":"Danmark",
    "wof:name":"Andersen, Elisabeth Kjems",
    "wof:placetype":"venue"
},
  "geometry": {"coordinates":[12.4623394012,55.7838363647],"type":"Point"}
}