{
  "type": "Feature",
  "properties": {
    "addr:full":"Gr\u00f8ndal Centret, Hvidkildevej 64 K\u00f8benhavn NV Danmark 2400",
    "addr:housenumber":"64",
    "addr:postcode":"2400",
    "addr:street":"Hvidkildevej",
    "iso:country":"DK",
    "sg:address":"Gr\u00f8ndal Centret, Hvidkildevej 64",
    "sg:city":"K\u00f8benhavn NV",
    "sg:orig_category":"Fagforbund og -foreninger",
    "sg:phone":"+45 38 10 07 17",
    "sg:postcode":"2400",
    "sg:province":"Danmark",
    "wof:name":"Stoftrykker og V\u00e6verlaugets Landsforening",
    "wof:placetype":"venue"
},
  "geometry": {"coordinates":[-117.02272033689999,38.5024604797],"type":"Point"}
}