{
  "type": "Feature",
  "properties": {
    "addr:full":"Fmd.: Julie Stilling, \u00d8resundsvej 20 Hornb\u00e6k Danmark 3100",
    "addr:housenumber":"20",
    "addr:postcode":"3100",
    "addr:street":"Oresundsvej",
    "iso:country":"DK",
    "sg:address":"Fmd.: Julie Stilling, \u00d8resundsvej 20",
    "sg:city":"Hornb\u00e6k",
    "sg:orig_category":"Politiske foreninger, \u00c3\u02dcvrige",
    "sg:phone":"+45 27 12 87 17",
    "sg:postcode":"3100",
    "sg:province":"Danmark",
    "wof:name":"Helsing\u00f8r KU",
    "wof:placetype":"venue"
},
  "geometry": {"coordinates":[12.4300451279,56.0916366577],"type":"Point"}
}