{
  "type": "Feature",
  "properties": {
    "addr:full":"Kogsvej 3, Rejsby Sk\u00e6rb\u00e6k Danmark 6780",
    "addr:housenumber":"3",
    "addr:postcode":"6780",
    "addr:street":"Kogsvej",
    "iso:country":"DK",
    "sg:address":"Kogsvej 3, Rejsby",
    "sg:city":"Sk\u00e6rb\u00e6k",
    "sg:orig_category":"Efterskoler",
    "sg:phone":"+45 74 75 36 22",
    "sg:postcode":"6780",
    "sg:province":"Danmark",
    "wof:name":"Rejsby Europ\u00e6iske Efterskole",
    "wof:placetype":"venue"
},
  "geometry": {"coordinates":[8.7272148132,55.1943397522],"type":"Point"}
}