{
  "type": "Feature",
  "properties": {
    "addr:full":"Fmd.: Evan Lynnerup, Fjordager 13 Jyllinge Danmark 4040",
    "addr:housenumber":"13",
    "addr:postcode":"4040",
    "addr:street":"Fjordager",
    "iso:country":"DK",
    "sg:address":"Fmd.: Evan Lynnerup, Fjordager 13",
    "sg:city":"Jyllinge",
    "sg:orig_category":"Grundejerforeninger",
    "sg:phone":"+45 46 73 39 91",
    "sg:postcode":"4040",
    "sg:province":"Danmark",
    "wof:name":"Grundejerforeningen Fjordager",
    "wof:placetype":"venue"
},
  "geometry": {"coordinates":[12.1163625717,55.7643737793],"type":"Point"}
}