{
  "type": "Feature",
  "properties": {
    "addr:full":"Blenstrupvej 15, Gjerlev Gjerlev Danmark 8983",
    "addr:housenumber":"15",
    "addr:postcode":"8983",
    "addr:street":"Blenstrupvej;Gjerlev Gjerlev Danmark",
    "iso:country":"DK",
    "sg:address":"Blenstrupvej 15, Gjerlev",
    "sg:city":"Gjerlev",
    "sg:orig_category":"Autoforhandlere",
    "sg:phone":"+45 86 47 50 11",
    "sg:postcode":"8983",
    "sg:province":"Danmark",
    "wof:name":"Paulsen & S\u00f8n",
    "wof:placetype":"venue"
},
  "geometry": {"coordinates":[10.1887750626,56.5788421631],"type":"Point"}
}