{
  "type": "Feature",
  "properties": {
    "iso:country":"DK",
    "sg:address":"Hessgade 31",
    "sg:city":"Middelfart",
    "sg:orig_category":"Rejsebureauer",
    "sg:phone":"+45 64 41 98 98",
    "sg:postcode":"5500",
    "sg:province":"Danmark",
    "sg:website":"www.nordiske-rejser.dk",
    "wof:name":"Nordiske Rejser",
    "wof:placetype":"venue"
},
  "geometry": {"coordinates":[9.727473259,55.5028419495],"type":"Point"}
}