{
  "type": "Feature",
  "properties": {
    "addr:full":"Fmd.: Svend Lundsberg, Gr\u00f8nningen 19 Struer Danmark 7600",
    "addr:housenumber":"19",
    "addr:postcode":"7600",
    "addr:street":"Gronningen",
    "iso:country":"DK",
    "sg:address":"Fmd.: Svend Lundsberg, Gr\u00f8nningen 19",
    "sg:city":"Struer",
    "sg:orig_category":"Faglige organisationer og foreninger",
    "sg:phone":"+45 97 84 10 05",
    "sg:postcode":"7600",
    "sg:province":"Danmark",
    "wof:name":"Struer Fris\u00f8rlaug",
    "wof:placetype":"venue"
},
  "geometry": {"coordinates":[8.5946903229,56.491191864],"type":"Point"}
}