{
  "type": "Feature",
  "properties": {
    "addr:full":"v/ Per Hagelund, Solnavej 7 S\u00f8borg Danmark 2860",
    "addr:housenumber":"7",
    "addr:postcode":"2860",
    "addr:street":"Solnavej",
    "iso:country":"DK",
    "sg:address":"v/ Per Hagelund, Solnavej 7",
    "sg:city":"S\u00f8borg",
    "sg:orig_category":"Grundejerforeninger",
    "sg:phone":"+45 39 69 12 83",
    "sg:postcode":"2860",
    "sg:province":"Danmark",
    "wof:name":"Hesselbjerg Grundejerforening af 9.9. 1969",
    "wof:placetype":"venue"
},
  "geometry": {"coordinates":[-101.39041900629999,35.6679611206],"type":"Point"}
}