{
  "type": "Feature",
  "properties": {
    "addr:full":"N\u00f8rregade 156 Ringsted Danmark 4100",
    "addr:housenumber":"156",
    "addr:postcode":"4100",
    "addr:street":"Norregade",
    "iso:country":"DK",
    "sg:address":"N\u00f8rregade 156",
    "sg:city":"Ringsted",
    "sg:orig_category":"Murermestre",
    "sg:phone":"+45 57 61 32 83",
    "sg:postcode":"4100",
    "sg:province":"Danmark",
    "wof:name":"Andersen Entrepren\u00f8rfirmaet ApS, John",
    "wof:placetype":"venue"
},
  "geometry": {"coordinates":[11.7912635803,55.4548110962],"type":"Point"}
}