{
  "type": "Feature",
  "properties": {
    "iso:country":"DK",
    "sg:address":"Solvang 21",
    "sg:city":"S\u00f8nderborg",
    "sg:orig_category":"Diners transportables",
    "sg:phone":"+45 74 43 22 52",
    "sg:postcode":"6400",
    "sg:province":"Danmark",
    "wof:name":"Franske Hus, Det",
    "wof:placetype":"venue"
},
  "geometry": {"coordinates":[-120.1445617676,34.5960617065],"type":"Point"}
}