{
  "type": "Feature",
  "properties": {
    "iso:country":"DK",
    "sg:address":"R\u00e5dhusgade 5",
    "sg:city":"Aabenraa",
    "sg:classifiers":[
        {
            "category":"Restaurant",
            "type":"Food & Drink"
        }
    ],
    "sg:phone":"+45 74 62 44 22",
    "sg:postcode":"6200",
    "sg:province":"Danmark",
    "wof:name":"Nelson, Restaurant",
    "wof:placetype":"venue"
},
  "geometry": {"coordinates":[9.4197587967,55.0433807373],"type":"Point"}
}