{
  "type": "Feature",
  "properties": {
    "iso:country":"DK",
    "sg:address":"Rosenholmvej 18",
    "sg:city":"Hornslet",
    "sg:orig_category":"Blomsterhandlere",
    "sg:phone":"+45 86 99 40 67",
    "sg:postcode":"8543",
    "sg:province":"Danmark",
    "wof:name":"Hornslet Blomster",
    "wof:placetype":"venue"
},
  "geometry": {"coordinates":[10.3215532303,56.3162193298],"type":"Point"}
}