{
  "type": "Feature",
  "properties": {
    "addr:full":"Kuldyssen 19 Taastrup Danmark 2630",
    "addr:housenumber":"19",
    "addr:postcode":"2630",
    "addr:street":"Kuldyssen",
    "iso:country":"DK",
    "sg:address":"Kuldyssen 19",
    "sg:city":"Taastrup",
    "sg:orig_category":"Autolakering",
    "sg:phone":"+45 43 52 88 58",
    "sg:postcode":"2630",
    "sg:province":"Danmark",
    "wof:name":"Mugges Autolakering",
    "wof:placetype":"venue"
},
  "geometry": {"coordinates":[12.2876186371,55.649055481],"type":"Point"}
}