{
  "type": "Feature",
  "properties": {
    "addr:full":"Fmd.: Ib Work Christensen, Mikkelborg Park 11, 2.th. H\u00f8rsholm Danmark 2970",
    "addr:housenumber":"11 2.th",
    "addr:postcode":"2970",
    "addr:street":"Mikkelborg Park",
    "iso:country":"DK",
    "sg:address":"Fmd.: Ib Work Christensen, Mikkelborg Park 11, 2.th.",
    "sg:city":"H\u00f8rsholm",
    "sg:orig_category":"Grundejerforeninger",
    "sg:phone":"+45 45 76 65 48",
    "sg:postcode":"2970",
    "sg:province":"Danmark",
    "wof:name":"Grundejerforeningen Daleh\u00f8j",
    "wof:placetype":"venue"
},
  "geometry": {"coordinates":[-120.56749725340001,41.2807998657],"type":"Point"}
}