{
  "type": "Feature",
  "properties": {
    "addr:full":"N\u00f8rregade 28 C, 1.tv. Vejle Danmark 7100",
    "addr:housenumber":"28 c",
    "addr:postcode":"7100",
    "addr:street":"Norregade;1.Tv",
    "iso:country":"DK",
    "sg:address":"N\u00f8rregade 28 C, 1.tv.",
    "sg:city":"Vejle",
    "sg:orig_category":"Faglige organisationer og -foreninger",
    "sg:phone":"+45 75 84 11 19",
    "sg:postcode":"7100",
    "sg:province":"Danmark",
    "wof:name":"Kordegneforening, Danmarks",
    "wof:placetype":"venue"
},
  "geometry": {"coordinates":[9.5368051529,55.7113952637],"type":"Point"}
}