{
  "type": "Feature",
  "properties": {
    "addr:full":"Holsteinborgvej 55 Rude Danmark 4243",
    "addr:housenumber":"55",
    "addr:postcode":"4243",
    "addr:street":"Holsteinborgvej",
    "iso:country":"DK",
    "sg:address":"Holsteinborgvej 55",
    "sg:city":"Rude",
    "sg:orig_category":"Murermestre",
    "sg:phone":"+45 40 14 94 18",
    "sg:postcode":"4243",
    "sg:province":"Danmark",
    "wof:name":"Rasmussen, Bjarne",
    "wof:placetype":"venue"
},
  "geometry": {"coordinates":[11.4722423553,55.2255516052],"type":"Point"}
}