{
  "type": "Feature",
  "properties": {
    "addr:full":"Aabenraavej 9 Silkeborg Danmark 8600",
    "addr:housenumber":"9",
    "addr:postcode":"8600",
    "addr:street":"Aabenraavej",
    "iso:country":"DK",
    "sg:address":"Aabenraavej 9",
    "sg:city":"Silkeborg",
    "sg:classifiers":[
        {
            "category":"Professional",
            "subcategory":"Computer Services",
            "type":"Services"
        }
    ],
    "sg:phone":"+45 86 80 68 07",
    "sg:postcode":"8600",
    "sg:province":"Danmark",
    "sg:tags":[
        "edb",
        "-",
        "software"
    ],
    "wof:name":"EDB Manden",
    "wof:placetype":"venue"
},
  "geometry": {"coordinates":[9.4938201904,56.1703300476],"type":"Point"}
}