{
  "type": "Feature",
  "properties": {
    "addr:full":"Baneledet 32 Virum Danmark 2830",
    "addr:housenumber":"32",
    "addr:postcode":"2830",
    "addr:street":"Baneledet",
    "iso:country":"DK",
    "sg:address":"Baneledet 32",
    "sg:city":"Virum",
    "sg:orig_category":"Finansiering",
    "sg:phone":"+45 45 85 40 31",
    "sg:postcode":"2830",
    "sg:province":"Danmark",
    "wof:name":"Hh Consult",
    "wof:placetype":"venue"
},
  "geometry": {"coordinates":[12.4747085571,55.7910194397],"type":"Point"}
}