{
  "type": "Feature",
  "properties": {
    "addr:full":"Hvidkl\u00f8vervej 2 \u00c5rhus N Danmark 8200",
    "addr:housenumber":"2",
    "addr:postcode":"8200",
    "addr:street":"Hvidklovervej",
    "iso:country":"DK",
    "sg:address":"Hvidkl\u00f8vervej 2",
    "sg:city":"\u00c5rhus N",
    "sg:orig_category":"Fodterapeuter",
    "sg:phone":"+45 86 16 78 09",
    "sg:postcode":"8200",
    "sg:province":"Danmark",
    "wof:name":"Klinik for Fodterapi",
    "wof:placetype":"venue"
},
  "geometry": {"coordinates":[4.9393601418,49.7092018127],"type":"Point"}
}