{
  "type": "Feature",
  "properties": {
    "addr:full":"F\u00e6lledvej 4 K\u00f8benhavn N Danmark 2200",
    "addr:housenumber":"4",
    "addr:postcode":"2200",
    "addr:street":"Faelledvej;N Danmark",
    "iso:country":"DK",
    "sg:address":"F\u00e6lledvej 4",
    "sg:city":"K\u00f8benhavn N",
    "sg:orig_category":"Antikviteter",
    "sg:phone":"+45 35 37 41 42",
    "sg:postcode":"2200",
    "sg:province":"Danmark",
    "wof:name":"K\u00f8benhavns Antikcenter",
    "wof:placetype":"venue"
},
  "geometry": {"coordinates":[-74.1068115234,43.7170639038],"type":"Point"}
}