{
  "type": "Feature",
  "properties": {
    "addr:full":"Vestvejen 168 Aabenraa Danmark 6200",
    "addr:housenumber":"168",
    "addr:postcode":"6200",
    "addr:street":"Vestvejen",
    "iso:country":"DK",
    "sg:address":"Vestvejen 168",
    "sg:city":"Aabenraa",
    "sg:orig_category":"Sikkerhedsudstyr",
    "sg:phone":"+45 74 31 18 88",
    "sg:postcode":"6200",
    "sg:province":"Danmark",
    "wof:name":"S\u00e6kko Industri A/S",
    "wof:placetype":"venue"
},
  "geometry": {"coordinates":[9.4043359756,55.0502891541],"type":"Point"}
}