{
  "type": "Feature",
  "properties": {
    "addr:full":"T\u00f8rskindvej 1, Ny N\u00f8rup Bredsten Danmark 7182",
    "addr:housenumber":"1",
    "addr:postcode":"norup;7182",
    "addr:street":"Torskindvej",
    "iso:country":"DK",
    "sg:address":"T\u00f8rskindvej 1, Ny N\u00f8rup",
    "sg:city":"Bredsten",
    "sg:orig_category":"Ungdomsklubber",
    "sg:postcode":"7182",
    "sg:province":"Danmark",
    "wof:name":"N\u00f8rup Ungdomsklub",
    "wof:placetype":"venue"
},
  "geometry": {"coordinates":[9.3807411194,55.702331543],"type":"Point"}
}