{
  "type": "Feature",
  "properties": {
    "addr:full":"Fdm.: Gunnar Kaspersen, Ligustervej 13, Fl\u00f8ng Hedehusene Danmark 2640",
    "addr:housenumber":"13",
    "addr:postcode":"2640",
    "addr:street":"Ligustervej;Flong",
    "iso:country":"DK",
    "sg:address":"Fdm.: Gunnar Kaspersen, Ligustervej 13, Fl\u00f8ng",
    "sg:city":"Hedehusene",
    "sg:orig_category":"Kirkelige foreninger",
    "sg:phone":"+45 46 56 13 01",
    "sg:postcode":"2640",
    "sg:province":"Danmark",
    "wof:name":"St\u00f8ttekreds for Fl\u00f8ng Kirkes Ungdom",
    "wof:placetype":"venue"
},
  "geometry": {"coordinates":[12.1993551254,55.6496009827],"type":"Point"}
}