{
  "type": "Feature",
  "properties": {
    "addr:full":"Strandvejen 354 F Esperg\u00e6rde Danmark 3060",
    "addr:housenumber":"354 f",
    "addr:postcode":"3060",
    "addr:street":"Strandvejen;Espergaerde Danmark",
    "iso:country":"DK",
    "sg:address":"Strandvejen 354 F",
    "sg:city":"Esperg\u00e6rde",
    "sg:orig_category":"Antikviteter",
    "sg:phone":"+45 49 13 15 03",
    "sg:postcode":"3060",
    "sg:province":"Danmark",
    "wof:name":"Havfruen, Butik",
    "wof:placetype":"venue"
},
  "geometry": {"coordinates":[11.6512403488,47.8390617371],"type":"Point"}
}