{
  "type": "Feature",
  "properties": {
    "addr:full":"Byvejen 14 Asperup Danmark 5466",
    "addr:housenumber":"14",
    "addr:postcode":"5466",
    "addr:street":"Byvejen",
    "iso:country":"DK",
    "sg:address":"Byvejen 14",
    "sg:city":"Asperup",
    "sg:orig_category":"Malermestre",
    "sg:phone":"+45 64 48 11 36",
    "sg:postcode":"5466",
    "sg:province":"Danmark",
    "wof:name":"Rasmussen, Per",
    "wof:placetype":"venue"
},
  "geometry": {"coordinates":[9.9074459076,55.4858474731],"type":"Point"}
}