{
  "type": "Feature",
  "properties": {
    "addr:full":"Lindeall\u00e9 23 - 25 Odense M Danmark 5230",
    "addr:housenumber":"23 25",
    "addr:postcode":"5230",
    "addr:street":"Lindealle\u0301",
    "iso:country":"DK",
    "sg:address":"Lindeall\u00e9 23 - 25",
    "sg:city":"Odense M",
    "sg:orig_category":"Plejehjem",
    "sg:phone":"+45 66 12 30 95",
    "sg:postcode":"5230",
    "sg:province":"Danmark",
    "wof:name":"OK-plejehjemmet Gurli/Vibeke",
    "wof:placetype":"venue"
},
  "geometry": {"coordinates":[10.3966598511,55.3816184998],"type":"Point"}
}