{
  "type": "Feature",
  "properties": {
    "addr:full":"Ymersvej 18 Randers Danmark 8900",
    "addr:housenumber":"18",
    "addr:postcode":"8900",
    "addr:street":"Ymersvej",
    "iso:country":"DK",
    "sg:address":"Ymersvej 18",
    "sg:city":"Randers",
    "sg:orig_category":"Vinduespolering",
    "sg:phone":"+45 86 41 47 51",
    "sg:postcode":"8900",
    "sg:province":"Danmark",
    "wof:name":"Ibs Vinduespolering",
    "wof:placetype":"venue"
},
  "geometry": {"coordinates":[10.0256986618,56.4733314514],"type":"Point"}
}