{
  "type": "Feature",
  "properties": {
    "addr:full":"Damhus Boulevard 85 R\u00f8dovre Danmark 2610",
    "addr:housenumber":"85",
    "addr:postcode":"2610",
    "addr:street":"Damhus Boulevard",
    "iso:country":"DK",
    "sg:address":"Damhus Boulevard 85",
    "sg:city":"R\u00f8dovre",
    "sg:orig_category":"Glarmestre og glarmagere",
    "sg:phone":"+45 36 70 06 35",
    "sg:postcode":"2610",
    "sg:province":"Danmark",
    "wof:name":"Hansens Eftf., K. V.",
    "wof:placetype":"venue"
},
  "geometry": {"coordinates":[10.6992139816,61.1027755737],"type":"Point"}
}