{
  "type": "Feature",
  "properties": {
    "iso:country":"DK",
    "sg:address":"N\u00f8rremarken 50 A, M\u00f8rdrup",
    "sg:city":"Esperg\u00e6rde",
    "sg:orig_category":"Vuggestuer",
    "sg:phone":"+45 49 28 12 79",
    "sg:postcode":"3060",
    "sg:province":"Danmark",
    "wof:name":"N\u00f8rremarken, Vuggestuen",
    "wof:placetype":"venue"
},
  "geometry": {"coordinates":[11.6512403488,47.8390617371],"type":"Point"}
}