{
  "type": "Feature",
  "properties": {
    "addr:full":"Lille V\u00e6rl\u00f8sevej 49 V\u00e6rl\u00f8se Danmark 3500",
    "addr:housenumber":"49",
    "addr:postcode":"3500",
    "addr:street":"Vaerlosevej",
    "iso:country":"DK",
    "sg:address":"Lille V\u00e6rl\u00f8sevej 49",
    "sg:city":"V\u00e6rl\u00f8se",
    "sg:orig_category":"Lederudvikling",
    "sg:phone":"+45 44 47 17 41",
    "sg:postcode":"3500",
    "sg:province":"Danmark",
    "wof:name":"K & K Lederudvikling",
    "wof:placetype":"venue"
},
  "geometry": {"coordinates":[3.274189949,46.3210792542],"type":"Point"}
}