{
  "type": "Feature",
  "properties": {
    "iso:country":"DK",
    "sg:address":"Viborg Hovedvej 44, Ulk\u00e6r",
    "sg:city":"Vejle",
    "sg:orig_category":"Servicestationer",
    "sg:phone":"+45 75 85 13 93",
    "sg:postcode":"7100",
    "sg:province":"Danmark",
    "wof:name":"STATOIL Servicenter & Cafeteria",
    "wof:placetype":"venue"
},
  "geometry": {"coordinates":[9.5368051529,55.7113952637],"type":"Point"}
}