{
  "type": "Feature",
  "properties": {
    "addr:full":"Skovbrinken 11, Englerup Kirke S\u00e5by Danmark 4060",
    "addr:housenumber":"11",
    "addr:postcode":"4060",
    "addr:street":"Skovbrinken;Englerup Kirke",
    "iso:country":"DK",
    "sg:address":"Skovbrinken 11, Englerup",
    "sg:city":"Kirke S\u00e5by",
    "sg:orig_category":"Regnskabsassistance",
    "sg:phone":"+45 46 49 23 84",
    "sg:postcode":"4060",
    "sg:province":"Danmark",
    "wof:name":"Algin - Handel og Service",
    "wof:placetype":"venue"
},
  "geometry": {"coordinates":[11.8739786148,55.6341285706],"type":"Point"}
}