{
  "type": "Feature",
  "properties": {
    "iso:country":"DK",
    "sg:address":"Toften 4",
    "sg:city":"Nordborg",
    "sg:orig_category":"Zoneterapeuter",
    "sg:phone":"+45 74 45 40 43",
    "sg:postcode":"6430",
    "sg:province":"Danmark",
    "wof:name":"Hansen, Alice",
    "wof:placetype":"venue"
},
  "geometry": {"coordinates":[9.7513952255,55.0562934875],"type":"Point"}
}