{
  "type": "Feature",
  "properties": {
    "addr:full":"Vestergade 9 Gudme Danmark 5884",
    "addr:housenumber":"9",
    "addr:postcode":"5884",
    "addr:street":"Vestergade",
    "iso:country":"DK",
    "sg:address":"Vestergade 9",
    "sg:city":"Gudme",
    "sg:orig_category":"Autoreparation og -service",
    "sg:phone":"+45 62 25 17 85",
    "sg:postcode":"5884",
    "sg:province":"Danmark",
    "wof:name":"Gudme Autoservice",
    "wof:placetype":"venue"
},
  "geometry": {"coordinates":[10.7030382156,55.1543769836],"type":"Point"}
}