{
  "type": "Feature",
  "properties": {
    "addr:full":"Strandk\u00e6rvej 87 Horsens Danmark 8700",
    "addr:housenumber":"87",
    "addr:postcode":"8700",
    "addr:street":"Strandkaervej",
    "iso:country":"DK",
    "sg:address":"Strandk\u00e6rvej 87",
    "sg:city":"Horsens",
    "sg:orig_category":"Bowlingcentre",
    "sg:phone":"+45 75 64 56 55",
    "sg:postcode":"8700",
    "sg:province":"Danmark",
    "wof:name":"Bowl'n Fun",
    "wof:placetype":"venue"
},
  "geometry": {"coordinates":[9.8437623978,55.8429641724],"type":"Point"}
}