{
  "type": "Feature",
  "properties": {
    "addr:full":"Nordre Fasanvej 132 Frederiksberg Danmark 2000",
    "addr:housenumber":"132",
    "addr:postcode":"2000",
    "addr:street":"Nordre Fasanvej",
    "iso:country":"DK",
    "sg:address":"Nordre Fasanvej 132",
    "sg:city":"Frederiksberg",
    "sg:classifiers":[
        {
            "category":"Restaurant",
            "type":"Food & Drink"
        }
    ],
    "sg:phone":"+45 38 10 63 54",
    "sg:postcode":"2000",
    "sg:province":"Danmark",
    "wof:name":"Saray Restaurant & Pizzabar",
    "wof:placetype":"venue"
},
  "geometry": {"coordinates":[12.5307617188,55.6910057068],"type":"Point"}
}