{
  "type": "Feature",
  "properties": {
    "addr:full":"Gruppeleder: Bodil M\u00f8gelmose, Lilleardenvej 2 Arden Danmark 9510",
    "addr:housenumber":"2",
    "addr:postcode":"9510",
    "addr:street":"Lilleardenvej",
    "iso:country":"DK",
    "sg:address":"Gruppeleder: Bodil M\u00f8gelmose, Lilleardenvej 2",
    "sg:city":"Arden",
    "sg:orig_category":"Spejderkorps",
    "sg:phone":"+45 98 56 27 77",
    "sg:postcode":"9510",
    "sg:province":"Danmark",
    "wof:name":"KFUK-spejderne i St. Br\u00f8ndum",
    "wof:placetype":"venue"
},
  "geometry": {"coordinates":[9.8580989838,56.7683296204],"type":"Point"}
}