{
  "type": "Feature",
  "properties": {
    "addr:full":"Gravene 10 A Haderslev Danmark 6100",
    "addr:housenumber":"10 a",
    "addr:postcode":"6100",
    "addr:street":"Gravene",
    "iso:country":"DK",
    "sg:address":"Gravene 10 A",
    "sg:city":"Haderslev",
    "sg:orig_category":"Grillbarer",
    "sg:phone":"+45 74 52 27 28",
    "sg:postcode":"6100",
    "sg:province":"Danmark",
    "wof:name":"Finns P\u00f8lsehus",
    "wof:placetype":"venue"
},
  "geometry": {"coordinates":[9.4879703522,55.2505493164],"type":"Point"}
}