{
  "type": "Feature",
  "properties": {
    "iso:country":"DK",
    "sg:address":"Gasv\u00e6rksvej 2",
    "sg:city":"Maribo",
    "sg:orig_category":"Isolering",
    "sg:phone":"+45 54 78 21 88",
    "sg:postcode":"4930",
    "sg:province":"Danmark",
    "wof:name":"Christensen's Monterings & Isoleringsfirma, Brdr.",
    "wof:placetype":"venue"
},
  "geometry": {"coordinates":[11.4912891388,54.7757225037],"type":"Point"}
}