{
  "type": "Feature",
  "properties": {
    "iso:country":"DK",
    "sg:address":"Borups Alle 134 C",
    "sg:city":"Frederiksberg",
    "sg:orig_category":"Malermestre",
    "sg:phone":"+45 38 88 43 19",
    "sg:postcode":"2000",
    "sg:province":"Danmark",
    "wof:name":"Svenningsen, Ole",
    "wof:placetype":"venue"
},
  "geometry": {"coordinates":[12.531867981,55.6940956116],"type":"Point"}
}