{
  "type": "Feature",
  "properties": {
    "addr:full":"Industrivej 7, Thorsager R\u00f8nde Danmark 8410",
    "addr:housenumber":"7 thorsager",
    "addr:postcode":"8410",
    "addr:street":"Industrivej",
    "iso:country":"DK",
    "sg:address":"Industrivej 7, Thorsager",
    "sg:city":"R\u00f8nde",
    "sg:classifiers":[
        {
            "category":"Taxi",
            "type":"Transportation"
        }
    ],
    "sg:phone":"+45 86 37 90 82",
    "sg:postcode":"8410",
    "sg:province":"Danmark",
    "wof:name":"Thorsager Taxi",
    "wof:placetype":"venue"
},
  "geometry": {"coordinates":[10.4288892746,56.295917511],"type":"Point"}
}