{
  "type": "Feature",
  "properties": {
    "addr:full":"Bispensgade 29 Aalborg Danmark 9000",
    "addr:housenumber":"29",
    "addr:postcode":"9000",
    "addr:street":"Bispensgade",
    "iso:country":"DK",
    "sg:address":"Bispensgade 29",
    "sg:city":"Aalborg",
    "sg:orig_category":"Konfekture",
    "sg:phone":"+45 98 12 99 25",
    "sg:postcode":"9000",
    "sg:province":"Danmark",
    "wof:name":"Bonbonnieren",
    "wof:placetype":"venue"
},
  "geometry": {"coordinates":[9.9167585373,57.0493469238],"type":"Point"}
}