{
  "type": "Feature",
  "properties": {
    "addr:full":"Toldbodgade 6 Silkeborg Danmark 8600",
    "addr:housenumber":"6",
    "addr:postcode":"8600",
    "addr:street":"Toldbodgade",
    "iso:country":"DK",
    "sg:address":"Toldbodgade 6",
    "sg:city":"Silkeborg",
    "sg:classifiers":[
        {
            "category":"Professional",
            "subcategory":"Computer Services",
            "type":"Services"
        }
    ],
    "sg:phone":"+45 86 81 80 21",
    "sg:postcode":"8600",
    "sg:province":"Danmark",
    "sg:tags":[
        "edb",
        "-",
        "software"
    ],
    "wof:name":"Vingaard-Data",
    "wof:placetype":"venue"
},
  "geometry": {"coordinates":[9.5397577286,56.1667671204],"type":"Point"}
}