{
  "type": "Feature",
  "properties": {
    "addr:full":"Sandvadvej 6, Vindelev Jelling Danmark 7300",
    "addr:housenumber":"6",
    "addr:postcode":"7300",
    "addr:street":"Sandvadvej",
    "iso:country":"DK",
    "sg:address":"Sandvadvej 6, Vindelev",
    "sg:city":"Jelling",
    "sg:orig_category":"Pelsdyravl",
    "sg:phone":"+45 75 87 34 67",
    "sg:postcode":"7300",
    "sg:province":"Danmark",
    "wof:name":"Kristiansholms Pelsdyrfarm ApS",
    "wof:placetype":"venue"
},
  "geometry": {"coordinates":[9.4184103012,55.7558555603],"type":"Point"}
}