{
  "type": "Feature",
  "properties": {
    "addr:full":"Frydenh\u00f8j Alle 100 Greve Danmark 2670",
    "addr:housenumber":"100",
    "addr:postcode":"2670",
    "addr:street":"Frydenhoj Alle",
    "iso:country":"DK",
    "sg:address":"Frydenh\u00f8j Alle 100",
    "sg:city":"Greve",
    "sg:orig_category":"Fodterapeuter",
    "sg:phone":"+45 43 95 90 96",
    "sg:postcode":"2670",
    "sg:province":"Danmark",
    "wof:name":"Klinik for Fodterapi",
    "wof:placetype":"venue"
},
  "geometry": {"coordinates":[12.2941808701,55.5844078064],"type":"Point"}
}