{
  "type": "Feature",
  "properties": {
    "iso:country":"DK",
    "sg:address":"Smedeskovvej 38",
    "sg:city":"Galten",
    "sg:orig_category":"Laboratorier",
    "sg:phone":"+45 70 22 42 66",
    "sg:postcode":"8464",
    "sg:province":"Danmark",
    "sg:website":"www.miljo-kemi.dk",
    "wof:name":"Milj\u00f8-Kemi, Dansk Milj\u00f8 Center A/S",
    "wof:placetype":"venue"
},
  "geometry": {"coordinates":[9.915804863,56.1593322754],"type":"Point"}
}