{
  "type": "Feature",
  "properties": {
    "iso:country":"DK",
    "sg:address":"Torvet 3",
    "sg:city":"Mariager",
    "sg:orig_category":"Optikere",
    "sg:phone":"+45 98 54 18 40",
    "sg:postcode":"9550",
    "sg:province":"Danmark",
    "wof:name":"Nyt Syn",
    "wof:placetype":"venue"
},
  "geometry": {"coordinates":[9.9824304581,56.6504821777],"type":"Point"}
}