{
  "type": "Feature",
  "properties": {
    "addr:full":"Krogsagervej 8, Nordrup Slagelse Danmark 4200",
    "addr:housenumber":"8",
    "addr:postcode":"4200",
    "addr:street":"Krogsagervej;Nordrup",
    "iso:country":"DK",
    "sg:address":"Krogsagervej 8, Nordrup",
    "sg:city":"Slagelse",
    "sg:orig_category":"Gartnerier",
    "sg:phone":"+45 58 26 72 07",
    "sg:postcode":"4200",
    "sg:province":"Danmark",
    "wof:name":"I/S Krogsager",
    "wof:placetype":"venue"
},
  "geometry": {"coordinates":[11.3569850922,55.4050865173],"type":"Point"}
}