{
  "type": "Feature",
  "properties": {
    "addr:full":"Slotsvej 6 Gram Danmark 6510",
    "addr:housenumber":"6",
    "addr:postcode":"6510",
    "addr:street":"Slotsvej",
    "iso:country":"DK",
    "sg:address":"Slotsvej 6",
    "sg:city":"Gram",
    "sg:orig_category":"Kommunale ungdomsskoler",
    "sg:phone":"+45 73 82 12 85",
    "sg:postcode":"6510",
    "sg:province":"Danmark",
    "wof:name":"Den Kommunale Ungdomsskole",
    "wof:placetype":"venue"
},
  "geometry": {"coordinates":[9.0505418777,55.2887496948],"type":"Point"}
}