{
  "type": "Feature",
  "properties": {
    "addr:full":"Trommesalen 5, 5. tv. K\u00f8benhavn Danmark 1614",
    "addr:housenumber":"5 5 tv.",
    "addr:postcode":"1614",
    "addr:street":"Trommesalen",
    "iso:country":"DK",
    "sg:address":"Trommesalen 5, 5. tv.",
    "sg:city":"K\u00f8benhavn",
    "sg:orig_category":"Flyvning",
    "sg:phone":"+45 33 25 45 56",
    "sg:postcode":"1614",
    "sg:province":"Danmark",
    "wof:name":"Qatar Airways",
    "wof:placetype":"venue"
},
  "geometry": {"coordinates":[12.5607299805,55.674079895],"type":"Point"}
}