{
  "type": "Feature",
  "properties": {
    "addr:full":"Sj\u00e6llandsgade 45 Aalborg Danmark 9000",
    "addr:housenumber":"45",
    "addr:postcode":"9000",
    "addr:street":"Sjaellandsgade",
    "iso:country":"DK",
    "sg:address":"Sj\u00e6llandsgade 45",
    "sg:city":"Aalborg",
    "sg:orig_category":"Supermarkeder",
    "sg:phone":"+45 98 11 71 00",
    "sg:postcode":"9000",
    "sg:province":"Danmark",
    "wof:name":"Super Brugsen",
    "wof:placetype":"venue"
},
  "geometry": {"coordinates":[9.938615799,57.0413894653],"type":"Point"}
}