{
  "type": "Feature",
  "properties": {
    "addr:full":"V\u00e5gebjergvej 2 Humble Danmark 5932",
    "addr:housenumber":"2",
    "addr:postcode":"5932",
    "addr:street":"Vaagebjergvej",
    "iso:country":"DK",
    "sg:address":"V\u00e5gebjergvej 2",
    "sg:city":"Humble",
    "sg:orig_category":"Engros handel",
    "sg:phone":"+45 62 57 22 00",
    "sg:postcode":"5932",
    "sg:province":"Danmark",
    "wof:name":"Diclos Trading Center",
    "wof:placetype":"venue"
},
  "geometry": {"coordinates":[10.6936063766,54.825843811],"type":"Point"}
}