{
  "type": "Feature",
  "properties": {
    "addr:full":"Folke Bernadottes All\u00e9 4 K\u00f8benhavn \u00d8 Danmark 2100",
    "addr:housenumber":"4",
    "addr:postcode":"2100",
    "addr:street":"Folke Bernadottes Alle\u0301;O",
    "iso:country":"DK",
    "sg:address":"Folke Bernadottes All\u00e9 4",
    "sg:city":"K\u00f8benhavn \u00d8",
    "sg:orig_category":"Trossamfund uden for folkekirken",
    "sg:phone":"+45 33 15 54 58",
    "sg:postcode":"2100",
    "sg:province":"Danmark",
    "sg:website":"www.skut.org/danmark",
    "wof:name":"Svenska Gustafskyrkan",
    "wof:placetype":"venue"
},
  "geometry": {"coordinates":[-2.4859499931,50.9198799133],"type":"Point"}
}