{
  "type": "Feature",
  "properties": {
    "addr:full":"Brunh\u00f8jvej 9 Ry Danmark 8680",
    "addr:housenumber":"9",
    "addr:postcode":"8680",
    "addr:street":"Brunhojvej",
    "iso:country":"DK",
    "sg:address":"Brunh\u00f8jvej 9",
    "sg:city":"Ry",
    "sg:orig_category":"Private- og friskoler",
    "sg:phone":"+45 86 89 17 59",
    "sg:postcode":"8680",
    "sg:province":"Danmark",
    "sg:website":"www.gudenaaskolen.dk",
    "wof:name":"Guden\u00e5skolen",
    "wof:placetype":"venue"
},
  "geometry": {"coordinates":[9.7593002319,56.0920562744],"type":"Point"}
}