{
  "type": "Feature",
  "properties": {
    "addr:full":"\u00d8stergade 1 Hals Danmark 9370",
    "addr:housenumber":"1",
    "addr:postcode":"9370",
    "addr:street":"Ostergade",
    "iso:country":"DK",
    "sg:address":"\u00d8stergade 1",
    "sg:city":"Hals",
    "sg:orig_category":"Kunsthandlere",
    "sg:phone":"+45 98 25 12 54",
    "sg:postcode":"9370",
    "sg:province":"Danmark",
    "wof:name":"Hansen, Erik",
    "wof:placetype":"venue"
},
  "geometry": {"coordinates":[10.307806015,56.9925613403],"type":"Point"}
}