{
  "type": "Feature",
  "properties": {
    "addr:full":"Silkeborgvej 281 Horsens Danmark 8700",
    "addr:housenumber":"281",
    "addr:postcode":"8700",
    "addr:street":"Silkeborgvej",
    "iso:country":"DK",
    "sg:address":"Silkeborgvej 281",
    "sg:city":"Horsens",
    "sg:orig_category":"Forsamlingshuse",
    "sg:phone":"+45 75 65 45 75",
    "sg:postcode":"8700",
    "sg:province":"Danmark",
    "wof:name":"Vinten Forsamlingshus",
    "wof:placetype":"venue"
},
  "geometry": {"coordinates":[9.7467699051,55.9014091492],"type":"Point"}
}