{
  "type": "Feature",
  "properties": {
    "addr:full":"Fmd.: Bent Olsen, Egevej 1, J\u00f8rlunde Slangerup Danmark 3550",
    "addr:housenumber":"1",
    "addr:postcode":"3550",
    "addr:street":"Egevej",
    "iso:country":"DK",
    "sg:address":"Fmd.: Bent Olsen, Egevej 1, J\u00f8rlunde",
    "sg:city":"Slangerup",
    "sg:orig_category":"Grundejerforeninger",
    "sg:phone":"+45 47 33 31 94",
    "sg:postcode":"3550",
    "sg:province":"Danmark",
    "wof:name":"Egevej, Grundejerforeningen",
    "wof:placetype":"venue"
},
  "geometry": {"coordinates":[12.1717596054,55.8460769653],"type":"Point"}
}