{
  "type": "Feature",
  "properties": {
    "iso:country":"DK",
    "sg:address":"v/ Tove Hansen, G\u00e5rdenes Vej 3, Vester\u00f8",
    "sg:city":"L\u00e6s\u00f8",
    "sg:orig_category":"Voksenuddannelsescentre",
    "sg:phone":"+45 98 49 95 90",
    "sg:postcode":"9940",
    "sg:province":"Danmark",
    "wof:name":"VUC, L\u00e6s\u00f8 afdeling",
    "wof:placetype":"venue"
},
  "geometry": {"coordinates":[-72.3527145386,41.1377334595],"type":"Point"}
}