{
  "type": "Feature",
  "properties": {
    "addr:full":"Havnen 8, Juelsminde Juelsminde Danmark 7130",
    "addr:housenumber":"8",
    "addr:postcode":"7130",
    "addr:street":"Havnen",
    "iso:country":"DK",
    "sg:address":"Havnen 8, Juelsminde",
    "sg:city":"Juelsminde",
    "sg:classifiers":[
        {
            "category":"Restaurant",
            "type":"Food & Drink"
        }
    ],
    "sg:phone":"+45 75 69 36 64",
    "sg:postcode":"7130",
    "sg:province":"Danmark",
    "wof:name":"Bonde's Marina",
    "wof:placetype":"venue"
},
  "geometry": {"coordinates":[10.0143985748,55.7135848999],"type":"Point"}
}