{
  "type": "Feature",
  "properties": {
    "addr:full":"Gammel Glentevej 15 Odense C Danmark 5000",
    "addr:housenumber":"15",
    "addr:postcode":"5000",
    "addr:street":"Gammel Glentevej",
    "iso:country":"DK",
    "sg:address":"Gammel Glentevej 15",
    "sg:city":"Odense C",
    "sg:orig_category":"Elektro",
    "sg:phone":"+45 65 91 48 87",
    "sg:postcode":"5000",
    "sg:province":"Danmark",
    "wof:name":"Alarmtech",
    "wof:placetype":"venue"
},
  "geometry": {"coordinates":[10.4099054337,55.404548645],"type":"Point"}
}