{
  "type": "Feature",
  "properties": {
    "addr:full":"Hyllebjerget 4, Ejby Kirke Hyllinge Danmark 4070",
    "addr:housenumber":"4",
    "addr:postcode":"4070",
    "addr:street":"Hyllebjerget",
    "iso:country":"DK",
    "sg:address":"Hyllebjerget 4, Ejby",
    "sg:city":"Kirke Hyllinge",
    "sg:orig_category":"Integrerede institutioner",
    "sg:phone":"+45 46 40 59 43",
    "sg:postcode":"4070",
    "sg:province":"Danmark",
    "wof:name":"Hyllebjerget",
    "wof:placetype":"venue"
},
  "geometry": {"coordinates":[11.9004745483,55.7080039978],"type":"Point"}
}