{
  "type": "Feature",
  "properties": {
    "iso:country":"DK",
    "sg:address":"Kochsgade 94",
    "sg:city":"Odense C",
    "sg:orig_category":"Servicestationer",
    "sg:phone":"+45 66 13 44 19",
    "sg:postcode":"5000",
    "sg:province":"Danmark",
    "wof:name":"Statoil Service",
    "wof:placetype":"venue"
},
  "geometry": {"coordinates":[10.4037055969,55.4076538086],"type":"Point"}
}