{
  "type": "Feature",
  "properties": {
    "addr:full":"Borups Alle 209 2.th K\u00f8benhavn NV Danmark 2400",
    "addr:housenumber":"209 2.th",
    "addr:postcode":"2400",
    "addr:street":"Borups Alle",
    "iso:country":"DK",
    "sg:address":"Borups Alle 209 2.th",
    "sg:city":"K\u00f8benhavn NV",
    "sg:orig_category":"Psykologer, praktiserende",
    "sg:phone":"+45 38 88 07 83",
    "sg:postcode":"2400",
    "sg:province":"Danmark",
    "wof:name":"Fiig, Evelyn Pettersen",
    "wof:placetype":"venue"
},
  "geometry": {"coordinates":[-117.02272033689999,38.5024604797],"type":"Point"}
}