{
  "type": "Feature",
  "properties": {
    "addr:full":"Dagmarsgade 67, Postboks 49 Ringsted Danmark 4100",
    "addr:housenumber":"67;49",
    "addr:postcode":"4100",
    "addr:street":"Dagmarsgade",
    "iso:country":"DK",
    "sg:address":"Dagmarsgade 67, Postboks 49",
    "sg:city":"Ringsted",
    "sg:classifiers":[
        {
            "category":"Professional",
            "subcategory":"Advertising",
            "type":"Services"
        }
    ],
    "sg:phone":"+45 57 67 27 77",
    "sg:postcode":"4100",
    "sg:province":"Danmark",
    "sg:tags":[
        "marketing"
    ],
    "wof:name":"Klinder Marketing",
    "wof:placetype":"venue"
},
  "geometry": {"coordinates":[11.7875862122,55.4458961487],"type":"Point"}
}