{
  "type": "Feature",
  "properties": {
    "iso:country":"DK",
    "sg:address":"Jakob Dannef\u00e6rds Vej 6 B",
    "sg:city":"Frederiksberg",
    "sg:orig_category":"Revisorer",
    "sg:phone":"+45 35 36 18 19",
    "sg:postcode":"1973",
    "sg:province":"Danmark",
    "wof:name":"Ljungdahl's Eftf., Revisionsfirmaet Valdemar",
    "wof:placetype":"venue"
},
  "geometry": {"coordinates":[12.5539636612,55.6837539673],"type":"Point"}
}