{
  "type": "Feature",
  "properties": {
    "iso:country":"DK",
    "sg:address":"Sognepr\u00e6st: Christian von Tangen Sivertsen, Ryg\u00e5rdsvej 7, Lang\u00e5",
    "sg:city":"Hesselager",
    "sg:orig_category":"Kirkesogne",
    "sg:phone":"+45 62 25 12 80",
    "sg:postcode":"5874",
    "sg:province":"Danmark",
    "wof:name":"Lang\u00e5-\u00d8ksendrup og Svindinge Sogne",
    "wof:placetype":"venue"
},
  "geometry": {"coordinates":[10.7344398499,55.1688804626],"type":"Point"}
}