{
  "type": "Feature",
  "properties": {
    "addr:full":"v/ Skolen p\u00e5 B\u00fclowsvej, B\u00fclowsvej 34 A, bygning A3 Frederiksberg Danmark 1870",
    "addr:housenumber":"34 a bygning a3",
    "addr:postcode":"1870",
    "addr:street":"Buelowsvej Buelowsvej",
    "iso:country":"DK",
    "sg:address":"v/ Skolen p\u00e5 B\u00fclowsvej, B\u00fclowsvej 34 A, bygning A3",
    "sg:city":"Frederiksberg",
    "sg:orig_category":"Tandklinikker, Kommunale",
    "sg:phone":"+45 38 21 02 30",
    "sg:postcode":"1870",
    "sg:province":"Danmark",
    "wof:name":"Tandklinikkerne",
    "wof:placetype":"venue"
},
  "geometry": {"coordinates":[12.5417957306,55.6800537109],"type":"Point"}
}