{
  "type": "Feature",
  "properties": {
    "addr:full":"Fmd.: Jesper Dr\u00f8hse, Drosselvej 14 Bryrup Danmark 8654",
    "addr:housenumber":"14",
    "addr:postcode":"8654",
    "addr:street":"Drosselvej",
    "iso:country":"DK",
    "sg:address":"Fmd.: Jesper Dr\u00f8hse, Drosselvej 14",
    "sg:city":"Bryrup",
    "sg:orig_category":"Hobbybetonede foreninger",
    "sg:phone":"+45 75 75 67 60",
    "sg:postcode":"8654",
    "sg:province":"Danmark",
    "wof:name":"Fodslaw Vrads",
    "wof:placetype":"venue"
},
  "geometry": {"coordinates":[9.5107898712,56.0237388611],"type":"Point"}
}