{
  "type": "Feature",
  "properties": {
    "addr:full":"Lundg\u00e5rdsparken 78 Aulum Danmark 7490",
    "addr:housenumber":"78",
    "addr:postcode":"7490",
    "addr:street":"Lundgaardsparken",
    "iso:country":"DK",
    "sg:address":"Lundg\u00e5rdsparken 78",
    "sg:city":"Aulum",
    "sg:orig_category":"Zoneterapeuter",
    "sg:phone":"+45 97 47 28 28",
    "sg:postcode":"7490",
    "sg:province":"Danmark",
    "wof:name":"Christensen, Anne-Marie Ven\u00f8",
    "wof:placetype":"venue"
},
  "geometry": {"coordinates":[8.7858886719,56.2620506287],"type":"Point"}
}