{
  "type": "Feature",
  "properties": {
    "addr:full":"Seminarieparken 9, 0021 Holb\u00e6k Danmark 4300",
    "addr:housenumber":"9",
    "addr:postcode":"0021;4300",
    "addr:street":"Seminarieparken",
    "iso:country":"DK",
    "sg:address":"Seminarieparken 9, 0021",
    "sg:city":"Holb\u00e6k",
    "sg:orig_category":"Musikere",
    "sg:phone":"+45 20 81 29 89",
    "sg:postcode":"4300",
    "sg:province":"Danmark",
    "wof:name":"Horst, Steen",
    "wof:placetype":"venue"
},
  "geometry": {"coordinates":[5.9380321503,58.9431533813],"type":"Point"}
}