{
  "type": "Feature",
  "properties": {
    "addr:full":"\u00d8stergade 20 Frederikssund Danmark 3600",
    "addr:housenumber":"20",
    "addr:postcode":"3600",
    "addr:street":"Ostergade",
    "iso:country":"DK",
    "sg:address":"\u00d8stergade 20",
    "sg:city":"Frederikssund",
    "sg:classifiers":[
        {
            "category":"Communications",
            "type":"Services"
        }
    ],
    "sg:phone":"+45 47 38 53 00",
    "sg:postcode":"3600",
    "sg:province":"Danmark",
    "sg:tags":[
        "og",
        "tv",
        "radio"
    ],
    "wof:name":"Expert",
    "wof:placetype":"venue"
},
  "geometry": {"coordinates":[12.0604248047,55.83934021],"type":"Point"}
}