{
  "type": "Feature",
  "properties": {
    "addr:full":"Roagervej 1, Frifelt Sk\u00e6rb\u00e6k Danmark 6780",
    "addr:housenumber":"1",
    "addr:postcode":"6780",
    "addr:street":"Roagervej",
    "iso:country":"DK",
    "sg:address":"Roagervej 1, Frifelt",
    "sg:city":"Sk\u00e6rb\u00e6k",
    "sg:orig_category":"HOTELS: OG MOTELLER",
    "sg:phone":"+45 74 75 71 25",
    "sg:postcode":"6780",
    "sg:province":"Danmark",
    "wof:name":"Frifelt Kro",
    "wof:placetype":"venue"
},
  "geometry": {"coordinates":[8.7272148132,55.1943397522],"type":"Point"}
}