{
  "type": "Feature",
  "properties": {
    "addr:full":"N\u00e6sbyhave 39, N\u00e6sby Odense N Danmark 5270",
    "addr:housenumber":"39",
    "addr:postcode":"5270",
    "addr:street":"Naesbyhave;Naesby",
    "iso:country":"DK",
    "sg:address":"N\u00e6sbyhave 39, N\u00e6sby",
    "sg:city":"Odense N",
    "sg:orig_category":"Murermestre",
    "sg:phone":"+45 66 18 09 22",
    "sg:postcode":"5270",
    "sg:province":"Danmark",
    "wof:name":"Hansen, Kurt Verner",
    "wof:placetype":"venue"
},
  "geometry": {"coordinates":[10.3306798935,55.4711418152],"type":"Point"}
}