{
  "type": "Feature",
  "properties": {
    "addr:full":"Korsh\u00f8jvej 2 Silkeborg Danmark 8600",
    "addr:housenumber":"2",
    "addr:postcode":"8600",
    "addr:street":"Korshojvej",
    "iso:country":"DK",
    "sg:address":"Korsh\u00f8jvej 2",
    "sg:city":"Silkeborg",
    "sg:classifiers":[
        {
            "category":"Banks & Credit Unions",
            "subcategory":"Financial Services",
            "type":"Services"
        }
    ],
    "sg:phone":"+45 86 83 69 00",
    "sg:postcode":"8600",
    "sg:province":"Danmark",
    "sg:tags":[
        "banking",
        "finance",
        "insurance"
    ],
    "wof:name":"VIRKLUND SPORT FINANS A/S",
    "wof:placetype":"venue"
},
  "geometry": {"coordinates":[9.4792613983,56.1794662476],"type":"Point"}
}