{
  "type": "Feature",
  "properties": {
    "addr:full":"Frederiksgade 35 \u00c5rhus C Danmark 8000",
    "addr:housenumber":"35",
    "addr:postcode":"8000",
    "addr:street":"Frederiksgade",
    "iso:country":"DK",
    "sg:address":"Frederiksgade 35",
    "sg:city":"\u00c5rhus C",
    "sg:orig_category":"Ejendomshandel",
    "sg:phone":"+45 86 19 16 00",
    "sg:postcode":"8000",
    "sg:province":"Danmark",
    "wof:name":"Ejerlejlighedsbutikken",
    "wof:placetype":"venue"
},
  "geometry": {"coordinates":[10.2055330276,56.1553916931],"type":"Point"}
}