{
  "type": "Feature",
  "properties": {
    "addr:full":"Rosenk\u00e6ret 14 S\u00f8borg Danmark 2860",
    "addr:housenumber":"14",
    "addr:postcode":"2860",
    "addr:street":"Rosenkaeret",
    "iso:country":"DK",
    "sg:address":"Rosenk\u00e6ret 14",
    "sg:city":"S\u00f8borg",
    "sg:orig_category":"Plastemballage",
    "sg:phone":"+45 39 67 02 88",
    "sg:postcode":"2860",
    "sg:province":"Danmark",
    "wof:name":"Ejers Plastemballage A/S",
    "wof:placetype":"venue"
},
  "geometry": {"coordinates":[-101.38994598390001,35.6939697266],"type":"Point"}
}