{
  "type": "Feature",
  "properties": {
    "addr:full":"Skolevej 18, N\u00e6sby Odense N Danmark 5270",
    "addr:housenumber":"18",
    "addr:postcode":"5270",
    "addr:street":"Skolevej;Naesby",
    "iso:country":"DK",
    "sg:address":"Skolevej 18, N\u00e6sby",
    "sg:city":"Odense N",
    "sg:orig_category":"Ejendomshandel",
    "sg:phone":"+45 66 18 32 32",
    "sg:postcode":"5270",
    "sg:province":"Danmark",
    "wof:name":"JM Bolig ApS",
    "wof:placetype":"venue"
},
  "geometry": {"coordinates":[10.3306798935,55.4711418152],"type":"Point"}
}