{
  "type": "Feature",
  "properties": {
    "addr:full":"Gunnar Clausens Vej 62 Viby Danmark 8260",
    "addr:housenumber":"62",
    "addr:postcode":"8260",
    "addr:street":"Gunnar Clausens Vej",
    "iso:country":"DK",
    "sg:address":"Gunnar Clausens Vej 62",
    "sg:city":"Viby",
    "sg:orig_category":"Pengeskabe",
    "sg:phone":"+45 86 29 40 99",
    "sg:postcode":"8260",
    "sg:province":"Danmark",
    "sg:website":"www.jcp.dk",
    "wof:name":"J. C. Pengeskabe A/S",
    "wof:placetype":"venue"
},
  "geometry": {"coordinates":[10.14457798,56.1078338623],"type":"Point"}
}