{
  "type": "Feature",
  "properties": {
    "addr:full":"Strandstr\u00e6de 45 Marstal Danmark 5960",
    "addr:housenumber":"45",
    "addr:postcode":"5960",
    "addr:street":"Strandstraede",
    "iso:country":"DK",
    "sg:address":"Strandstr\u00e6de 45",
    "sg:city":"Marstal",
    "sg:classifiers":[
        {
            "category":"Restaurant",
            "type":"Food & Drink"
        }
    ],
    "sg:phone":"+45 62 53 19 20",
    "sg:postcode":"5960",
    "sg:province":"Danmark",
    "wof:name":"Lanternen",
    "wof:placetype":"venue"
},
  "geometry": {"coordinates":[10.5212097168,54.8543815613],"type":"Point"}
}