{
  "type": "Feature",
  "properties": {
    "addr:full":"Fmd.: Lise S\u00f8rensen, Farvergade 14, 1. th. Horsens Danmark 8700",
    "addr:housenumber":"14 1 th.",
    "addr:postcode":"8700",
    "addr:street":"Farvergade",
    "iso:country":"DK",
    "sg:address":"Fmd.: Lise S\u00f8rensen, Farvergade 14, 1. th.",
    "sg:city":"Horsens",
    "sg:orig_category":"Husholdningsforeninger",
    "sg:phone":"+45 75 62 69 69",
    "sg:postcode":"8700",
    "sg:province":"Danmark",
    "wof:name":"Horsens Husflidsforening",
    "wof:placetype":"venue"
},
  "geometry": {"coordinates":[9.8432445526,55.8621063232],"type":"Point"}
}