{
  "type": "Feature",
  "properties": {
    "addr:full":"Fmd.: John Petersen, K\u00e6rvej 15, Ommel Marstal Danmark 5960",
    "addr:housenumber":"15",
    "addr:postcode":"5960",
    "addr:street":"Kaervej",
    "iso:country":"DK",
    "sg:address":"Fmd.: John Petersen, K\u00e6rvej 15, Ommel",
    "sg:city":"Marstal",
    "sg:orig_category":"Borger- og beboerforeninger",
    "sg:phone":"+45 62 53 10 26",
    "sg:postcode":"5960",
    "sg:province":"Danmark",
    "wof:name":"Ommel og Omegns Beboerforening",
    "wof:placetype":"venue"
},
  "geometry": {"coordinates":[10.5212097168,54.8543815613],"type":"Point"}
}