{
  "type": "Feature",
  "properties": {
    "addr:full":"Gammel Munkegade 1 \u00c5rhus C Danmark 8000",
    "addr:housenumber":"1",
    "addr:postcode":"8000",
    "addr:street":"Gammel Munkegade",
    "iso:country":"DK",
    "sg:address":"Gammel Munkegade 1",
    "sg:city":"\u00c5rhus C",
    "sg:orig_category":"Reklamebureauer",
    "sg:phone":"+45 28 40 55 55",
    "sg:postcode":"8000",
    "sg:province":"Danmark",
    "wof:name":"Very Important Programs",
    "wof:placetype":"venue"
},
  "geometry": {"coordinates":[12.2043600082,48.5182304382],"type":"Point"}
}