{
  "type": "Feature",
  "properties": {
    "addr:full":"v/ Hanne Stagl, S\u00e6byh\u00f8jvej 6, S\u00e6byh\u00f8j H\u00f8ng Danmark 4270",
    "addr:housenumber":"6",
    "addr:postcode":"4270",
    "addr:street":"Saebyhojvej",
    "iso:country":"DK",
    "sg:address":"v/ Hanne Stagl, S\u00e6byh\u00f8jvej 6, S\u00e6byh\u00f8j",
    "sg:city":"H\u00f8ng",
    "sg:orig_category":"Grundejerforeninger",
    "sg:phone":"+45 58 85 32 97",
    "sg:postcode":"4270",
    "sg:province":"Danmark",
    "wof:name":"Dalby Strand, (omr\u00e5de IV)",
    "wof:placetype":"venue"
},
  "geometry": {"coordinates":[10.9256296158,43.8753318787],"type":"Point"}
}