{
  "type": "Feature",
  "properties": {
    "addr:full":"Vesterbro 40 Odense C Danmark 5000",
    "addr:housenumber":"40",
    "addr:postcode":"5000",
    "addr:street":"Vesterbro",
    "iso:country":"DK",
    "sg:address":"Vesterbro 40",
    "sg:city":"Odense C",
    "sg:orig_category":"Dyrehandlere",
    "sg:phone":"+45 66 14 44 01",
    "sg:postcode":"5000",
    "sg:province":"Danmark",
    "wof:name":"Bonnie Dyrecenter",
    "wof:placetype":"venue"
},
  "geometry": {"coordinates":[10.37703228,55.3936653137],"type":"Point"}
}