{
  "type": "Feature",
  "properties": {
    "addr:full":"F\u00e6r\u00f8vej 73 Hj\u00f8rring Danmark 9800",
    "addr:housenumber":"73",
    "addr:postcode":"9800",
    "addr:street":"Faerovej",
    "iso:country":"DK",
    "sg:address":"F\u00e6r\u00f8vej 73",
    "sg:city":"Hj\u00f8rring",
    "sg:orig_category":"Grundejerforeninger",
    "sg:phone":"+45 98 90 42 06",
    "sg:postcode":"9800",
    "sg:province":"Danmark",
    "wof:name":"Grundejerforeningen R\u00f8rlandsv\u00e6nge",
    "wof:placetype":"venue"
},
  "geometry": {"coordinates":[9.9885387421,57.4594764709],"type":"Point"}
}