{
  "type": "Feature",
  "properties": {
    "addr:full":"Stationsvej 14 Nordborg Danmark 6430",
    "addr:housenumber":"14",
    "addr:postcode":"6430",
    "addr:street":"Stationsvej",
    "iso:country":"DK",
    "sg:address":"Stationsvej 14",
    "sg:city":"Nordborg",
    "sg:orig_category":"Turistbureau og -information",
    "sg:phone":"+45 74 45 05 92",
    "sg:postcode":"6430",
    "sg:province":"Danmark",
    "sg:website":"www.visitals.com",
    "wof:name":"Nordborg Turistbureau",
    "wof:placetype":"venue"
},
  "geometry": {"coordinates":[9.7432184219,55.055644989],"type":"Point"}
}