{
  "type": "Feature",
  "properties": {
    "addr:full":"Kongensgade 32 Marstal Danmark 5960",
    "addr:housenumber":"32",
    "addr:postcode":"5960",
    "addr:street":"Kongensgade",
    "iso:country":"DK",
    "sg:address":"Kongensgade 32",
    "sg:city":"Marstal",
    "sg:orig_category":"Faglige organisationer og foreninger",
    "sg:phone":"+45 62 53 11 45",
    "sg:postcode":"5960",
    "sg:province":"Danmark",
    "wof:name":"SID",
    "wof:placetype":"venue"
},
  "geometry": {"coordinates":[10.5174379349,54.8553199768],"type":"Point"}
}