{
  "type": "Feature",
  "properties": {
    "addr:full":"Humlevej 4 K\u00f8ge Danmark 4600",
    "addr:housenumber":"4",
    "addr:postcode":"4600",
    "addr:street":"Humlevej",
    "iso:country":"DK",
    "sg:address":"Humlevej 4",
    "sg:city":"K\u00f8ge",
    "sg:orig_category":"Mensendieckgymnastik",
    "sg:phone":"+45 56 65 02 26",
    "sg:postcode":"4600",
    "sg:province":"Danmark",
    "wof:name":"Pedersen, Ditte",
    "wof:placetype":"venue"
},
  "geometry": {"coordinates":[-6.255022049,53.3377838135],"type":"Point"}
}