{
  "type": "Feature",
  "properties": {
    "addr:full":"Virkelyst 4, Gjellerup Herning Danmark 7400",
    "addr:housenumber":"4",
    "addr:postcode":"7400",
    "addr:street":"Virkelyst;Gjellerup",
    "iso:country":"DK",
    "sg:address":"Virkelyst 4, Gjellerup",
    "sg:city":"Herning",
    "sg:orig_category":"Reklamegaver",
    "sg:phone":"+45 97 20 95 85",
    "sg:postcode":"7400",
    "sg:province":"Danmark",
    "sg:website":"www.bach-firmagaver.dk",
    "wof:name":"Bach firmagaver - reklameartikler",
    "wof:placetype":"venue"
},
  "geometry": {"coordinates":[8.9768896103,56.1374168396],"type":"Point"}
}