{
  "type": "Feature",
  "properties": {
    "addr:full":"H\u00f8jager 7, N\u00e6sby Odense N Danmark 5270",
    "addr:housenumber":"7",
    "addr:postcode":"5270",
    "addr:street":"Hojager;Naesby",
    "iso:country":"DK",
    "sg:address":"H\u00f8jager 7, N\u00e6sby",
    "sg:city":"Odense N",
    "sg:orig_category":"Forlag",
    "sg:phone":"+45 66 18 88 95",
    "sg:postcode":"5270",
    "sg:province":"Danmark",
    "wof:name":"Ejendommen H\u00f8jager 7",
    "wof:placetype":"venue"
},
  "geometry": {"coordinates":[10.3306798935,55.4711418152],"type":"Point"}
}