{
  "type": "Feature",
  "properties": {
    "addr:full":"S\u00e6byvej 1 Asaa Danmark 9340",
    "addr:housenumber":"1",
    "addr:postcode":"9340",
    "addr:street":"Saebyvej",
    "iso:country":"DK",
    "sg:address":"S\u00e6byvej 1",
    "sg:city":"Asaa",
    "sg:classifiers":[
        {
            "category":"Banks & Credit Unions",
            "subcategory":"Bank",
            "type":"Services"
        }
    ],
    "sg:phone":"+45 98 85 13 22",
    "sg:postcode":"9340",
    "sg:province":"Danmark",
    "sg:tags":[
        "banker"
    ],
    "sg:website":"www.egnsbanknord.dk",
    "wof:name":"Egnsbank Nord",
    "wof:placetype":"venue"
},
  "geometry": {"coordinates":[10.409075737,57.1507377625],"type":"Point"}
}