{
  "type": "Feature",
  "properties": {
    "addr:full":"Hovedgaden 63 Horslunde Danmark 4913",
    "addr:housenumber":"63",
    "addr:postcode":"4913",
    "addr:street":"Hovedgaden",
    "iso:country":"DK",
    "sg:address":"Hovedgaden 63",
    "sg:city":"Horslunde",
    "sg:orig_category":"Diners transportables",
    "sg:phone":"+45 54 93 51 49",
    "sg:postcode":"4913",
    "sg:province":"Danmark",
    "wof:name":"Gamle M\u00f8lleg\u00e5rd, Den",
    "wof:placetype":"venue"
},
  "geometry": {"coordinates":[11.2202396393,54.9133453369],"type":"Point"}
}