{
  "type": "Feature",
  "properties": {
    "addr:full":"H\u00e5ndv\u00e6rkervej 18 Langeskov Danmark 5550",
    "addr:housenumber":"18",
    "addr:postcode":"5550",
    "addr:street":"Haandvaerkervej",
    "iso:country":"DK",
    "sg:address":"H\u00e5ndv\u00e6rkervej 18",
    "sg:city":"Langeskov",
    "sg:classifiers":[
        {
            "category":"Arts & Performance",
            "subcategory":"Dance",
            "type":"Entertainment"
        }
    ],
    "sg:phone":"+45 65 38 31 63",
    "sg:postcode":"5550",
    "sg:province":"Danmark",
    "sg:tags":[
        "montage"
    ],
    "wof:name":"Fynsk Montage",
    "wof:placetype":"venue"
},
  "geometry": {"coordinates":[10.5878953934,55.3595466614],"type":"Point"}
}