{
  "type": "Feature",
  "properties": {
    "addr:full":"Flintingevej 19, Flintinge Toreby Danmark 4891",
    "addr:housenumber":"19",
    "addr:postcode":"4891",
    "addr:street":"Flintingevej;Flintinge Toreby Danmark",
    "iso:country":"DK",
    "sg:address":"Flintingevej 19, Flintinge",
    "sg:city":"Toreby",
    "sg:orig_category":"Forsamlingshuse",
    "sg:phone":"+45 54 86 97 87",
    "sg:postcode":"4891",
    "sg:province":"Danmark",
    "wof:name":"Flintinge Gamle Savv\u00e6rk",
    "wof:placetype":"venue"
},
  "geometry": {"coordinates":[11.7701835632,54.7622375488],"type":"Point"}
}