{
  "type": "Feature",
  "properties": {
    "addr:full":"Kalekovej 68 Faaborg Danmark 5600",
    "addr:housenumber":"68",
    "addr:postcode":"5600",
    "addr:street":"Kalekovej",
    "iso:country":"DK",
    "sg:address":"Kalekovej 68",
    "sg:city":"Faaborg",
    "sg:orig_category":"Murermestre",
    "sg:phone":"+45 62 61 28 11",
    "sg:postcode":"5600",
    "sg:province":"Danmark",
    "wof:name":"Gertsen Murer- & Byggeteknik, Jan",
    "wof:placetype":"venue"
},
  "geometry": {"coordinates":[10.2593479156,55.0945587158],"type":"Point"}
}