{
  "type": "Feature",
  "properties": {
    "addr:full":"Rynkebyvej 183, Tvinde Rynkeby Danmark 5350",
    "addr:housenumber":"183",
    "addr:postcode":"5350",
    "addr:street":"Rynkebyvej",
    "iso:country":"DK",
    "sg:address":"Rynkebyvej 183, Tvinde",
    "sg:city":"Rynkeby",
    "sg:orig_category":"Maskinfabrikker",
    "sg:phone":"+45 65 39 11 33",
    "sg:postcode":"5350",
    "sg:province":"Danmark",
    "wof:name":"Pedersen & S\u00f8n ApS, L.",
    "wof:placetype":"venue"
},
  "geometry": {"coordinates":[10.6097211838,55.3985671997],"type":"Point"}
}