{
  "type": "Feature",
  "properties": {
    "iso:country":"DK",
    "sg:address":"Klamborgv. 232 ",
    "sg:city":"Kongens Lyngby",
    "sg:classifiers":[
        {
            "category":"Personal",
            "subcategory":"Shoe Repair & Shine",
            "type":"Services"
        }
    ],
    "sg:phone":"+45 43 44 11 11",
    "sg:postcode":"2800",
    "sg:province":"Danmark",
    "sg:tags":[
        "leather"
    ],
    "wof:name":"F BILLING SKO MODE A/S",
    "wof:placetype":"venue"
},
  "geometry": {"coordinates":[12.51060009,55.7810211182],"type":"Point"}
}