{
  "type": "Feature",
  "properties": {
    "addr:full":"Algade 89 Vordingborg Danmark 4760",
    "addr:housenumber":"89",
    "addr:postcode":"4760",
    "addr:street":"Algade",
    "iso:country":"DK",
    "sg:address":"Algade 89",
    "sg:city":"Vordingborg",
    "sg:orig_category":"Biblioteker",
    "sg:phone":"+45 55 37 06 38",
    "sg:postcode":"4760",
    "sg:province":"Danmark",
    "wof:name":"Vordingborg Hovedbibliotek",
    "wof:placetype":"venue"
},
  "geometry": {"coordinates":[11.909174,55.008633],"type":"Point"}
}