{
  "type": "Feature",
  "properties": {
    "iso:country":"DK",
    "sg:address":"Fmd.: Ole Lassen, R\u00f8dlundvej 34 A, Lillering",
    "sg:city":"Harlev",
    "sg:orig_category":"Hobbybetonede foreninger",
    "sg:phone":"+45 86 94 28 38",
    "sg:postcode":"8462",
    "sg:province":"Danmark",
    "wof:name":"Galten MC klub",
    "wof:placetype":"venue"
},
  "geometry": {"coordinates":[10.0093507767,56.1557807922],"type":"Point"}
}