{
  "type": "Feature",
  "properties": {
    "addr:full":"Valdemarsgade 60 Vordingborg Danmark 4760",
    "addr:housenumber":"60",
    "addr:postcode":"4760",
    "addr:street":"Valdemarsgade",
    "iso:country":"DK",
    "sg:address":"Valdemarsgade 60",
    "sg:city":"Vordingborg",
    "sg:orig_category":"Advokater",
    "sg:phone":"+45 55 37 00 91",
    "sg:postcode":"4760",
    "sg:province":"Danmark",
    "wof:name":"Advokaterne",
    "wof:placetype":"venue"
},
  "geometry": {"coordinates":[11.9083499908,55.0108184814],"type":"Point"}
}