{
  "type": "Feature",
  "properties": {
    "addr:full":"Fmd.: Axel Larsen, Ejdervej 31, Dybb\u00f8l S\u00f8nderborg Danmark 6400",
    "addr:housenumber":"31",
    "addr:postcode":"6400",
    "addr:street":"Ejdervej;Sonderborg",
    "iso:country":"DK",
    "sg:address":"Fmd.: Axel Larsen, Ejdervej 31, Dybb\u00f8l",
    "sg:city":"S\u00f8nderborg",
    "sg:orig_category":"Kulturelle foreninger",
    "sg:phone":"+45 74 48 50 67",
    "sg:postcode":"6400",
    "sg:province":"Danmark",
    "wof:name":"Als Amat\u00f8rgeologiske Forening, Stenklubben Als",
    "wof:placetype":"venue"
},
  "geometry": {"coordinates":[-107.8339996338,40.0480003357],"type":"Point"}
}