{
  "type": "Feature",
  "properties": {
    "addr:full":"\u00d8ver\u00f8dvej 5 Holte Danmark 2840",
    "addr:housenumber":"5",
    "addr:postcode":"2840",
    "addr:street":"Overodvej",
    "iso:country":"DK",
    "sg:address":"\u00d8ver\u00f8dvej 5",
    "sg:city":"Holte",
    "sg:orig_category":"Ejendomshandel",
    "sg:phone":"+45 45 41 01 44",
    "sg:postcode":"2840",
    "sg:province":"Danmark",
    "sg:website":"www.home.dk",
    "wof:name":"Home",
    "wof:placetype":"venue"
},
  "geometry": {"coordinates":[12.4706554413,55.8122367859],"type":"Point"}
}