{
  "type": "Feature",
  "properties": {
    "addr:full":"Heeg\u00e5rdsvej 7 Slangerup Danmark 3550",
    "addr:housenumber":"7",
    "addr:postcode":"3550",
    "addr:street":"Heegaardsvej",
    "iso:country":"DK",
    "sg:address":"Heeg\u00e5rdsvej 7",
    "sg:city":"Slangerup",
    "sg:orig_category":"INGENI\u00c3\u02dcRER",
    "sg:phone":"+45 47 38 03 46",
    "sg:postcode":"3550",
    "sg:province":"Danmark",
    "wof:name":"Bygningsconcept",
    "wof:placetype":"venue"
},
  "geometry": {"coordinates":[12.1786203384,55.8444290161],"type":"Point"}
}