{
  "type": "Feature",
  "properties": {
    "addr:full":"T\u00e5struph\u00f8j 56 Holb\u00e6k Danmark 4300",
    "addr:housenumber":"56",
    "addr:postcode":"4300",
    "addr:street":"Taastruphoj",
    "iso:country":"DK",
    "sg:address":"T\u00e5struph\u00f8j 56",
    "sg:city":"Holb\u00e6k",
    "sg:orig_category":"Engros handel",
    "sg:phone":"+45 59 43 11 13",
    "sg:postcode":"4300",
    "sg:province":"Danmark",
    "wof:name":"Dagrofa S/Engros",
    "wof:placetype":"venue"
},
  "geometry": {"coordinates":[76.3070983887,14.277130127],"type":"Point"}
}