{
  "type": "Feature",
  "properties": {
    "iso:country":"DK",
    "sg:address":"Kuopiovej 20",
    "sg:city":"Svendborg",
    "sg:orig_category":"Hydraulik",
    "sg:phone":"+45 62 21 78 10",
    "sg:postcode":"5700",
    "sg:province":"Danmark",
    "wof:name":"Svendborg Hydraulik as",
    "wof:placetype":"venue"
},
  "geometry": {"coordinates":[10.586016655,55.0778388977],"type":"Point"}
}