{
  "type": "Feature",
  "properties": {
    "addr:full":"Vejlevej 60 Fredericia Danmark 7000",
    "addr:housenumber":"60",
    "addr:postcode":"7000",
    "addr:street":"Vejlevej",
    "iso:country":"DK",
    "sg:address":"Vejlevej 60",
    "sg:city":"Fredericia",
    "sg:orig_category":"Kontorartikler",
    "sg:phone":"+45 75 92 05 55",
    "sg:postcode":"7000",
    "sg:province":"Danmark",
    "wof:name":"Papirkompagniet Ole Holst A/S",
    "wof:placetype":"venue"
},
  "geometry": {"coordinates":[9.7115898132,55.5693778992],"type":"Point"}
}