{
  "type": "Feature",
  "properties": {
    "addr:full":"Gasv\u00e6rksvej 12 Aabenraa Danmark 6200",
    "addr:housenumber":"12",
    "addr:postcode":"6200",
    "addr:street":"Gasvaerksvej",
    "iso:country":"DK",
    "sg:address":"Gasv\u00e6rksvej 12",
    "sg:city":"Aabenraa",
    "sg:orig_category":"Genbrugspladser",
    "sg:phone":"+45 74 63 12 60",
    "sg:postcode":"6200",
    "sg:province":"Danmark",
    "wof:name":"Milj\u00f8stationerne Aabenraa Kommune",
    "wof:placetype":"venue"
},
  "geometry": {"coordinates":[9.4229545593,55.0451965332],"type":"Point"}
}