{
  "type": "Feature",
  "properties": {
    "addr:full":"Landbocentret, Parallelvej 9 A Ry Danmark 8680",
    "addr:housenumber":"9 a",
    "addr:postcode":"8680",
    "addr:street":"Parallelvej",
    "iso:country":"DK",
    "sg:address":"Landbocentret, Parallelvej 9 A",
    "sg:city":"Ry",
    "sg:orig_category":"Faglige organisationer og foreninger",
    "sg:phone":"+45 86 89 18 00",
    "sg:postcode":"8680",
    "sg:province":"Danmark",
    "wof:name":"\u00d8stjydsk Familielandbrug",
    "wof:placetype":"venue"
},
  "geometry": {"coordinates":[9.7593002319,56.0920562744],"type":"Point"}
}