{
  "type": "Feature",
  "properties": {
    "addr:full":"\u00d8stergade 4 \u00c5rhus C Danmark 8000",
    "addr:housenumber":"4",
    "addr:postcode":"8000",
    "addr:street":"Ostergade",
    "iso:country":"DK",
    "sg:address":"\u00d8stergade 4",
    "sg:city":"\u00c5rhus C",
    "sg:classifiers":[
        {
            "category":"Banks & Credit Unions",
            "subcategory":"Bank",
            "type":"Services"
        }
    ],
    "sg:phone":"+45 89 31 50 00",
    "sg:postcode":"8000",
    "sg:province":"Danmark",
    "sg:tags":[
        "banker"
    ],
    "wof:name":"Jyske Bank",
    "wof:placetype":"venue"
},
  "geometry": {"coordinates":[4.7174,49.758801],"type":"Point"}
}