{
  "type": "Feature",
  "properties": {
    "addr:full":"Skolevej 1 Jerslev Sj\u00e6lland Danmark 4490",
    "addr:housenumber":"1",
    "addr:postcode":"4490",
    "addr:street":"Skolevej",
    "iso:country":"DK",
    "sg:address":"Skolevej 1",
    "sg:city":"Jerslev Sj\u00e6lland",
    "sg:orig_category":"Skolefritidsordninger",
    "sg:phone":"+45 59 59 53 35",
    "sg:postcode":"4490",
    "sg:province":"Danmark",
    "sg:website":"www.hvidebaekskolen.dk/sfo",
    "wof:name":"SFO Krudtt\u00f8nden",
    "wof:placetype":"venue"
},
  "geometry": {"coordinates":[11.2286548615,55.6110153198],"type":"Point"}
}