{
  "type": "Feature",
  "properties": {
    "addr:full":"Mosevej 7 D Kolding Danmark 6000",
    "addr:housenumber":"7 d",
    "addr:postcode":"6000",
    "addr:street":"Mosevej",
    "iso:country":"DK",
    "sg:address":"Mosevej 7 D",
    "sg:city":"Kolding",
    "sg:orig_category":"Automater",
    "sg:phone":"+45 20 11 42 11",
    "sg:postcode":"6000",
    "sg:province":"Danmark",
    "wof:name":"Kolding Automat Teknik",
    "wof:placetype":"venue"
},
  "geometry": {"coordinates":[9.4632720947,55.4733924866],"type":"Point"}
}