{
  "type": "Feature",
  "properties": {
    "addr:full":"N\u00f8rrev\u00e6nget 34 Silkeborg Danmark 8600",
    "addr:housenumber":"34",
    "addr:postcode":"8600",
    "addr:street":"Norrevaenget",
    "iso:country":"DK",
    "sg:address":"N\u00f8rrev\u00e6nget 34",
    "sg:city":"Silkeborg",
    "sg:orig_category":"Farve og tapet",
    "sg:phone":"+45 86 81 26 26",
    "sg:postcode":"8600",
    "sg:province":"Danmark",
    "sg:website":"www.farve-lak.dk",
    "wof:name":"Silkeborg Farve & Lak A/S",
    "wof:placetype":"venue"
},
  "geometry": {"coordinates":[9.5524425507,56.1693305969],"type":"Point"}
}