{
  "type": "Feature",
  "properties": {
    "addr:full":"Juelsgade 10 Juelsminde Danmark 7130",
    "addr:housenumber":"10",
    "addr:postcode":"7130",
    "addr:street":"Juelsgade",
    "iso:country":"DK",
    "sg:address":"Juelsgade 10",
    "sg:city":"Juelsminde",
    "sg:orig_category":"Kiosker",
    "sg:phone":"+45 75 69 34 51",
    "sg:postcode":"7130",
    "sg:province":"Danmark",
    "wof:name":"Juelsminde D\u00f8gnkiosk",
    "wof:placetype":"venue"
},
  "geometry": {"coordinates":[10.0111675262,55.7140045166],"type":"Point"}
}