{
  "type": "Feature",
  "properties": {
    "addr:full":"Hastrup Bygade 8 Gadstrup Danmark 4621",
    "addr:housenumber":"8",
    "addr:postcode":"4621",
    "addr:street":"Hastrup Bygade",
    "iso:country":"DK",
    "sg:address":"Hastrup Bygade 8",
    "sg:city":"Gadstrup",
    "sg:orig_category":"Apoteker og -udsalg",
    "sg:phone":"+45 46 15 01 32",
    "sg:postcode":"4621",
    "sg:province":"Danmark",
    "wof:name":"Medicinudleveringssted fra Havdrup Apotek",
    "wof:placetype":"venue"
},
  "geometry": {"coordinates":[12.1754293442,55.5644836426],"type":"Point"}
}