{
  "type": "Feature",
  "properties": {
    "addr:full":"Langvadbjergvej 13, Snejbjerg Herning Danmark 7400",
    "addr:housenumber":"13",
    "addr:postcode":"7400",
    "addr:street":"Langvadbjergvej;Snejbjerg",
    "iso:country":"DK",
    "sg:address":"Langvadbjergvej 13, Snejbjerg",
    "sg:city":"Herning",
    "sg:orig_category":"Plastemballage",
    "sg:phone":"+45 97 16 25 22",
    "sg:postcode":"7400",
    "sg:province":"Danmark",
    "wof:name":"H. S. Plasticemballage",
    "wof:placetype":"venue"
},
  "geometry": {"coordinates":[8.9768896103,56.1374168396],"type":"Point"}
}