{
  "type": "Feature",
  "properties": {
    "iso:country":"DK",
    "sg:address":"Toldbodgade 2",
    "sg:city":"Hvide Sande",
    "sg:orig_category":"Jordemodercentre",
    "sg:phone":"+45 96 75 41 75",
    "sg:postcode":"6960",
    "sg:province":"Danmark",
    "wof:name":"Jordemoderkonsultationen",
    "wof:placetype":"venue"
},
  "geometry": {"coordinates":[8.1281385422,55.9999885559],"type":"Point"}
}