{
  "type": "Feature",
  "properties": {
    "addr:full":"Overdammen 5 Ribe Danmark 6760",
    "addr:housenumber":"5",
    "addr:postcode":"6760",
    "addr:street":"Overdammen",
    "iso:country":"DK",
    "sg:address":"Overdammen 5",
    "sg:city":"Ribe",
    "sg:orig_category":"Antikviteter",
    "sg:phone":"+45 75 41 00 55",
    "sg:postcode":"6760",
    "sg:province":"Danmark",
    "wof:name":"Antikgaarden",
    "wof:placetype":"venue"
},
  "geometry": {"coordinates":[8.7624149323,55.328754425],"type":"Point"}
}