{
  "type": "Feature",
  "properties": {
    "addr:full":"Wiedeveltsvej 8 Fredensborg Danmark 3480",
    "addr:housenumber":"8",
    "addr:postcode":"3480",
    "addr:street":"Wiedeveltsvej",
    "iso:country":"DK",
    "sg:address":"Wiedeveltsvej 8",
    "sg:city":"Fredensborg",
    "sg:orig_category":"Psykologer, praktiserende",
    "sg:phone":"+45 29 25 66 25",
    "sg:postcode":"3480",
    "sg:province":"Danmark",
    "wof:name":"Svensson, Lillian",
    "wof:placetype":"venue"
},
  "geometry": {"coordinates":[12.3988819122,55.9802589417],"type":"Point"}
}