{
  "type": "Feature",
  "properties": {
    "addr:full":"Torvegade 1 Fakse Danmark 4640",
    "addr:housenumber":"1",
    "addr:postcode":"4640",
    "addr:street":"Torvegade",
    "iso:country":"DK",
    "sg:address":"Torvegade 1",
    "sg:city":"Fakse",
    "sg:classifiers":[
        {
            "category":"Banks & Credit Unions",
            "subcategory":"Bank",
            "type":"Services"
        }
    ],
    "sg:phone":"+45 56 76 16 40",
    "sg:postcode":"4640",
    "sg:province":"Danmark",
    "sg:tags":[
        "banker"
    ],
    "sg:website":"www.danskebank.dk",
    "wof:name":"Danske Bank",
    "wof:placetype":"venue"
},
  "geometry": {"coordinates":[12.1203050613,55.2565040588],"type":"Point"}
}