{
  "type": "Feature",
  "properties": {
    "addr:full":"I. P. Jacobsens Plads 4 Thisted Danmark 7700",
    "addr:housenumber":"4",
    "addr:postcode":"7700",
    "addr:street":"I. P. Jacobsens Plads",
    "iso:country":"DK",
    "sg:address":"I. P. Jacobsens Plads 4",
    "sg:city":"Thisted",
    "sg:orig_category":"Faglige organisationer og foreninger",
    "sg:phone":"+45 97 92 34 00",
    "sg:postcode":"7700",
    "sg:province":"Danmark",
    "wof:name":"SID",
    "wof:placetype":"venue"
},
  "geometry": {"coordinates":[8.6918039322,56.9542922974],"type":"Point"}
}