{
  "type": "Feature",
  "properties": {
    "addr:full":"Vendsysselvej 201 Frederikshavn Danmark 9900",
    "addr:housenumber":"201",
    "addr:postcode":"9900",
    "addr:street":"Vendsysselvej",
    "iso:country":"DK",
    "sg:address":"Vendsysselvej 201",
    "sg:city":"Frederikshavn",
    "sg:orig_category":"Affald",
    "sg:phone":"+45 98 43 42 66",
    "sg:postcode":"9900",
    "sg:province":"Danmark",
    "wof:name":"Frederikshavn Affaldskraftvarmev\u00e6rk",
    "wof:placetype":"venue"
},
  "geometry": {"coordinates":[10.4820699692,57.4585990906],"type":"Point"}
}