{
  "type": "Feature",
  "properties": {
    "addr:full":"Industrivej 17 Ribe Danmark 6760",
    "addr:housenumber":"17",
    "addr:postcode":"6760",
    "addr:street":"Industrivej",
    "iso:country":"DK",
    "sg:address":"Industrivej 17",
    "sg:city":"Ribe",
    "sg:orig_category":"Autoreparation og -service",
    "sg:phone":"+45 75 42 32 00",
    "sg:postcode":"6760",
    "sg:province":"Danmark",
    "wof:name":"I T Auto Service",
    "wof:placetype":"venue"
},
  "geometry": {"coordinates":[8.776143074,55.347858429],"type":"Point"}
}