{
  "type": "Feature",
  "properties": {
    "addr:full":"Dronning Sofies Vej 42 Roskilde Danmark 4000",
    "addr:housenumber":"42",
    "addr:postcode":"4000",
    "addr:street":"Dronning Sofies Vej",
    "iso:country":"DK",
    "sg:address":"Dronning Sofies Vej 42",
    "sg:city":"Roskilde",
    "sg:orig_category":"Private skoler",
    "sg:phone":"+45 46 35 86 12",
    "sg:postcode":"4000",
    "sg:province":"Danmark",
    "sg:website":"www.rps.dk",
    "wof:name":"Roskilde Private Skole",
    "wof:placetype":"venue"
},
  "geometry": {"coordinates":[12.0969381332,55.6457977295],"type":"Point"}
}