{
  "type": "Feature",
  "properties": {
    "addr:full":"Kastanievej 26 Karup Danmark 7470",
    "addr:housenumber":"26",
    "addr:postcode":"7470",
    "addr:street":"Kastanievej",
    "iso:country":"DK",
    "sg:address":"Kastanievej 26",
    "sg:city":"Karup",
    "sg:orig_category":"Sikkerhedsudstyr",
    "sg:phone":"+45 97 10 27 02",
    "sg:postcode":"7470",
    "sg:province":"Danmark",
    "sg:website":"www.kaarup.dk",
    "wof:name":"Kaarup, Hanne",
    "wof:placetype":"venue"
},
  "geometry": {"coordinates":[9.1743068695,56.3108482361],"type":"Point"}
}