{
  "type": "Feature",
  "properties": {
    "iso:country":"DK",
    "sg:address":"H\u00f8gevej 5",
    "sg:city":"K\u00f8ge",
    "sg:orig_category":"Belysning",
    "sg:phone":"+45 56 65 13 50",
    "sg:postcode":"4600",
    "sg:province":"Danmark",
    "wof:name":"H. J. Belysning",
    "wof:placetype":"venue"
},
  "geometry": {"coordinates":[43.365791,42.31152],"type":"Point"}
}