{
  "type": "Feature",
  "properties": {
    "iso:country":"DK",
    "sg:address":"Nordre Kongemarksvej 20b ",
    "sg:city":"Nysted",
    "sg:classifiers":[
        {
            "category":"Professional",
            "subcategory":"Business Services",
            "type":"Services"
        }
    ],
    "sg:phone":"+45 54 87 19 86",
    "sg:postcode":"4880",
    "sg:province":"Danmark",
    "sg:tags":[
        "advice"
    ],
    "wof:name":"NYSTED SKOLE",
    "wof:placetype":"venue"
},
  "geometry": {"coordinates":[11.7451400757,54.6611061096],"type":"Point"}
}