{
  "type": "Feature",
  "properties": {
    "addr:full":"Hvidkildevej 9, Mejlby N\u00f8rager Danmark 9610",
    "addr:housenumber":"9",
    "addr:postcode":"9610",
    "addr:street":"Hvidkildevej",
    "iso:country":"DK",
    "sg:address":"Hvidkildevej 9, Mejlby",
    "sg:city":"N\u00f8rager",
    "sg:orig_category":"Murermestre",
    "sg:phone":"+45 98 65 10 92",
    "sg:postcode":"9610",
    "sg:province":"Danmark",
    "wof:name":"Rasmussen ApS, Murer- og Entrepren\u00f8rfirma Henning E.",
    "wof:placetype":"venue"
},
  "geometry": {"coordinates":[9.6815052032,56.7865104675],"type":"Point"}
}