{
  "type": "Feature",
  "properties": {
    "addr:full":"Fmd.: Kristian Terkildsen, S\u00f8g\u00e5rdsvej 34 Gentofte Danmark 2820",
    "addr:housenumber":"34",
    "addr:postcode":"2820",
    "addr:street":"Sogaardsvej",
    "iso:country":"DK",
    "sg:address":"Fmd.: Kristian Terkildsen, S\u00f8g\u00e5rdsvej 34",
    "sg:city":"Gentofte",
    "sg:orig_category":"Grundejerforeninger",
    "sg:phone":"+45 39 65 66 01",
    "sg:postcode":"2820",
    "sg:province":"Danmark",
    "sg:website":"www.gentoftesognsgrundejerforening.dk",
    "wof:name":"Gentofte Sogns Grundejerforening",
    "wof:placetype":"venue"
},
  "geometry": {"coordinates":[12.5409173965,55.7482719421],"type":"Point"}
}