{
  "type": "Feature",
  "properties": {
    "addr:full":"Stavnsholtvej 41 Farum Danmark 3520",
    "addr:housenumber":"41",
    "addr:postcode":"3520",
    "addr:street":"Stavnsholtvej",
    "iso:country":"DK",
    "sg:address":"Stavnsholtvej 41",
    "sg:city":"Farum",
    "sg:orig_category":"Cafeterier",
    "sg:phone":"+45 44 95 61 10",
    "sg:postcode":"3520",
    "sg:province":"Danmark",
    "wof:name":"Stavnsholthallens Cafeteria",
    "wof:placetype":"venue"
},
  "geometry": {"coordinates":[12.3947458267,55.81432724],"type":"Point"}
}