{
  "type": "Feature",
  "properties": {
    "addr:full":"Broengen 6, Br\u00f8nsholm Kokkedal Danmark 2980",
    "addr:housenumber":"6",
    "addr:postcode":"2980",
    "addr:street":"Broengen;Bronsholm",
    "iso:country":"DK",
    "sg:address":"Broengen 6, Br\u00f8nsholm",
    "sg:city":"Kokkedal",
    "sg:orig_category":"Integrerede institutioner",
    "sg:phone":"+45 49 14 33 47",
    "sg:postcode":"2980",
    "sg:province":"Danmark",
    "wof:name":"Pilehuset, Integreret Institution",
    "wof:placetype":"venue"
},
  "geometry": {"coordinates":[12.4769096375,55.9091339111],"type":"Point"}
}