{
  "type": "Feature",
  "properties": {
    "iso:country":"DK",
    "sg:address":"H\u00f8gevej 4",
    "sg:city":"Fredericia",
    "sg:orig_category":"Boligselskaber",
    "sg:phone":"+45 76 20 05 00",
    "sg:postcode":"7000",
    "sg:province":"Danmark",
    "wof:name":"Andelsboligforeningen i Fredericia",
    "wof:placetype":"venue"
},
  "geometry": {"coordinates":[9.7464885712,55.5716133118],"type":"Point"}
}