{
  "type": "Feature",
  "properties": {
    "addr:full":"Sams\u00f8 Kommune, Langgade 1, Tranebjerg Sams\u00f8 Danmark 8305",
    "addr:housenumber":"1",
    "addr:postcode":"8305",
    "addr:street":"Langgade",
    "iso:country":"DK",
    "sg:address":"Sams\u00f8 Kommune, Langgade 1, Tranebjerg",
    "sg:city":"Sams\u00f8",
    "sg:orig_category":"Lufthavn",
    "sg:phone":"+45 86 59 11 40",
    "sg:postcode":"8305",
    "sg:province":"Danmark",
    "wof:name":"Sams\u00f8 Flyveplads",
    "wof:placetype":"venue"
},
  "geometry": {"coordinates":[10.5885000229,55.8320198059],"type":"Point"}
}