{
  "type": "Feature",
  "properties": {
    "addr:full":"Jernbanegade 32 Otterup Danmark 5450",
    "addr:housenumber":"32",
    "addr:postcode":"5450",
    "addr:street":"Jernbanegade",
    "iso:country":"DK",
    "sg:address":"Jernbanegade 32",
    "sg:city":"Otterup",
    "sg:orig_category":"Dag- og distriktsblade",
    "sg:phone":"+45 64 82 19 00",
    "sg:postcode":"5450",
    "sg:province":"Danmark",
    "wof:name":"Fyens Stiftstidende",
    "wof:placetype":"venue"
},
  "geometry": {"coordinates":[10.3981075287,55.5136566162],"type":"Point"}
}