{
  "type": "Feature",
  "properties": {
    "addr:full":"Fmd.: Teddy Rasmussen, Istedgade 69, 5., tv. K\u00f8benhavn Danmark 1650",
    "addr:housenumber":"69 5 tv.;1650",
    "addr:street":"Istedgade",
    "iso:country":"DK",
    "sg:address":"Fmd.: Teddy Rasmussen, Istedgade 69, 5., tv.",
    "sg:city":"K\u00f8benhavn",
    "sg:orig_category":"Grundejerforeninger",
    "sg:phone":"+45 33 24 34 41",
    "sg:postcode":"1650",
    "sg:province":"Danmark",
    "wof:name":"Sommervej Grundejerforening",
    "wof:placetype":"venue"
},
  "geometry": {"coordinates":[12.5565004349,55.6693000793],"type":"Point"}
}