{
  "type": "Feature",
  "properties": {
    "addr:full":"S\u00f8ndergade 8 Silkeborg Danmark 8600",
    "addr:housenumber":"8",
    "addr:postcode":"8600",
    "addr:street":"Sondergade",
    "iso:country":"DK",
    "sg:address":"S\u00f8ndergade 8",
    "sg:city":"Silkeborg",
    "sg:orig_category":"Sko",
    "sg:phone":"+45 86 80 15 60",
    "sg:postcode":"8600",
    "sg:province":"Danmark",
    "wof:name":"Bianco Footwear",
    "wof:placetype":"venue"
},
  "geometry": {"coordinates":[9.5494651794,56.168384552],"type":"Point"}
}