{
  "type": "Feature",
  "properties": {
    "addr:full":"St\u00e6remosen 31 Gilleleje Danmark 3250",
    "addr:housenumber":"31",
    "addr:postcode":"3250",
    "addr:street":"Staeremosen",
    "iso:country":"DK",
    "sg:address":"St\u00e6remosen 31",
    "sg:city":"Gilleleje",
    "sg:orig_category":"Dykkere",
    "sg:phone":"+45 48 35 59 30",
    "sg:postcode":"3250",
    "sg:province":"Danmark",
    "wof:name":"Dyk og Bygservice",
    "wof:placetype":"venue"
},
  "geometry": {"coordinates":[12.3235721588,56.1122016907],"type":"Point"}
}