{
  "type": "Feature",
  "properties": {
    "iso:country":"DK",
    "sg:address":"Industri Vest 15",
    "sg:city":"Dianalund",
    "sg:orig_category":"Genbrugspladser",
    "sg:phone":"+45 58 28 62 81",
    "sg:postcode":"4293",
    "sg:province":"Danmark",
    "wof:name":"Genbrugsstationen",
    "wof:placetype":"venue"
},
  "geometry": {"coordinates":[11.4786310196,55.531993866],"type":"Point"}
}