{
  "type": "Feature",
  "properties": {
    "iso:country":"DK",
    "sg:address":"Palnatokesvej 34 1.",
    "sg:city":"Odense C",
    "sg:classifiers":[
        {
            "category":"Professional",
            "subcategory":"Computer Services",
            "type":"Services"
        }
    ],
    "sg:phone":"+45 66 17 94 76",
    "sg:postcode":"5000",
    "sg:province":"Danmark",
    "sg:tags":[
        "edb",
        "-",
        "software"
    ],
    "wof:name":"Creative Web",
    "wof:placetype":"venue"
},
  "geometry": {"coordinates":[10.4059867859,55.3966674805],"type":"Point"}
}