{
  "type": "Feature",
  "properties": {
    "iso:country":"DK",
    "sg:address":"Helleb\u00e6kgade 27, kld.",
    "sg:city":"K\u00f8benhavn N",
    "sg:orig_category":"Boligselskaber",
    "sg:phone":"+45 35 85 47 65",
    "sg:postcode":"2200",
    "sg:province":"Danmark",
    "wof:name":"K\u00f8benhavns Almindelige Boligs. Stefansg\u00e5rd",
    "wof:placetype":"venue"
},
  "geometry": {"coordinates":[-94.37571716310001,47.9438171387],"type":"Point"}
}