{
  "type": "Feature",
  "properties": {
    "addr:full":"L\u00f8jteg\u00e5rdsvej 150 Kastrup Danmark 2770",
    "addr:housenumber":"150",
    "addr:postcode":"2770",
    "addr:street":"Lojtegaardsvej",
    "iso:country":"DK",
    "sg:address":"L\u00f8jteg\u00e5rdsvej 150",
    "sg:city":"Kastrup",
    "sg:orig_category":"Autoreparation og -service",
    "sg:phone":"+45 32 83 53 53",
    "sg:postcode":"2770",
    "sg:province":"Danmark",
    "wof:name":"Scaniadam",
    "wof:placetype":"venue"
},
  "geometry": {"coordinates":[12.5998506546,55.6307029724],"type":"Point"}
}