{
  "type": "Feature",
  "properties": {
    "addr:full":"Torvegade 5 Oksb\u00f8l Danmark 6840",
    "addr:housenumber":"5",
    "addr:postcode":"6840",
    "addr:street":"Torvegade",
    "iso:country":"DK",
    "sg:address":"Torvegade 5",
    "sg:city":"Oksb\u00f8l",
    "sg:orig_category":"Fodterapeuter",
    "sg:phone":"+45 75 27 12 00",
    "sg:postcode":"6840",
    "sg:province":"Danmark",
    "wof:name":"Klinik For Fodterapi",
    "wof:placetype":"venue"
},
  "geometry": {"coordinates":[8.279294014,55.6258926392],"type":"Point"}
}