{
  "type": "Feature",
  "properties": {
    "addr:full":"Vesterbrogade 18 Viborg Danmark 8800",
    "addr:housenumber":"18",
    "addr:postcode":"8800",
    "addr:street":"Vesterbrogade",
    "iso:country":"DK",
    "sg:address":"Vesterbrogade 18",
    "sg:city":"Viborg",
    "sg:orig_category":"Cykler",
    "sg:phone":"+45 86 62 36 53",
    "sg:postcode":"8800",
    "sg:province":"Danmark",
    "wof:name":"Byens Cykler ApS",
    "wof:placetype":"venue"
},
  "geometry": {"coordinates":[9.3980789185,56.4501686096],"type":"Point"}
}