{
  "type": "Feature",
  "properties": {
    "addr:full":"Odensevej 39, Nr. S\u00f8by \u00c5rslev Danmark 5792",
    "addr:housenumber":"39",
    "addr:postcode":"5792",
    "addr:street":"Odensevej",
    "iso:country":"DK",
    "sg:address":"Odensevej 39, Nr. S\u00f8by",
    "sg:city":"\u00c5rslev",
    "sg:orig_category":"Autoreparation og -service",
    "sg:phone":"+45 65 90 15 96",
    "sg:postcode":"5792",
    "sg:province":"Danmark",
    "wof:name":"N\u00f8rre S\u00f8by Auto",
    "wof:placetype":"venue"
},
  "geometry": {"coordinates":[166.9221496582,-0.5282999873],"type":"Point"}
}