{
  "type": "Feature",
  "properties": {
    "iso:country":"DK",
    "sg:address":"V\u00e6rkstedvej 17 ",
    "sg:city":"Valby",
    "sg:classifiers":[
        {
            "category":"Shopping",
            "subcategory":"Computers & Home Electronics",
            "type":"Retail Goods"
        }
    ],
    "sg:phone":"+45 36 45 83 03",
    "sg:postcode":"2500",
    "sg:province":"Danmark",
    "sg:tags":[
        "electronic",
        "electrical",
        "equipment"
    ],
    "wof:name":"PANDUL APS",
    "wof:placetype":"venue"
},
  "geometry": {"coordinates":[12.503985405,55.6528663635],"type":"Point"}
}