{
  "type": "Feature",
  "properties": {
    "iso:country":"DK",
    "sg:address":"Cikorievej 80",
    "sg:city":"Odense S\u00d8",
    "sg:orig_category":"Reproanstalter",
    "sg:phone":"+45 66 17 78 30",
    "sg:postcode":"5220",
    "sg:province":"Danmark",
    "wof:name":"Gigant Repro",
    "wof:placetype":"venue"
},
  "geometry": {"coordinates":[10.4442491531,55.3922920227],"type":"Point"}
}