{
  "type": "Feature",
  "properties": {
    "addr:full":"Stenumvej 3 K\u00f8ge Danmark 4600",
    "addr:housenumber":"3",
    "addr:postcode":"4600",
    "addr:street":"Stenumvej",
    "iso:country":"DK",
    "sg:address":"Stenumvej 3",
    "sg:city":"K\u00f8ge",
    "sg:orig_category":"Gulvafslibning",
    "sg:phone":"+45 56 66 34 40",
    "sg:postcode":"4600",
    "sg:province":"Danmark",
    "wof:name":"A. N. Gulvservice",
    "wof:placetype":"venue"
},
  "geometry": {"coordinates":[12.1647377014,55.4706573486],"type":"Point"}
}