{
  "type": "Feature",
  "properties": {
    "addr:full":"Hunseby Strandvej 26 Maribo Danmark 4930",
    "addr:housenumber":"26",
    "addr:postcode":"4930",
    "addr:street":"Hunseby Strandvej",
    "iso:country":"DK",
    "sg:address":"Hunseby Strandvej 26",
    "sg:city":"Maribo",
    "sg:orig_category":"Antikviteter",
    "sg:phone":"+45 54 75 87 07",
    "sg:postcode":"4930",
    "sg:province":"Danmark",
    "wof:name":"Petersen, Bodil",
    "wof:placetype":"venue"
},
  "geometry": {"coordinates":[11.5333452225,54.8101806641],"type":"Point"}
}