{
  "type": "Feature",
  "properties": {
    "addr:full":"Vestergade 1 Grindsted Danmark 7200",
    "addr:housenumber":"1",
    "addr:postcode":"7200",
    "addr:street":"Vestergade",
    "iso:country":"DK",
    "sg:address":"Vestergade 1",
    "sg:city":"Grindsted",
    "sg:orig_category":"Gallerier",
    "sg:phone":"+45 75 32 55 77",
    "sg:postcode":"7200",
    "sg:province":"Danmark",
    "wof:name":"Galleri TORVET",
    "wof:placetype":"venue"
},
  "geometry": {"coordinates":[8.9270305634,55.7572135925],"type":"Point"}
}