{
  "type": "Feature",
  "properties": {
    "addr:full":"Hovedgaden 78 Tisvildeleje Danmark 3220",
    "addr:housenumber":"78",
    "addr:postcode":"3220",
    "addr:street":"Hovedgaden",
    "iso:country":"DK",
    "sg:address":"Hovedgaden 78",
    "sg:city":"Tisvildeleje",
    "sg:orig_category":"Pizzeriaer",
    "sg:phone":"+45 48 70 21 27",
    "sg:postcode":"3220",
    "sg:province":"Danmark",
    "wof:name":"Smittys Pizzabar",
    "wof:placetype":"venue"
},
  "geometry": {"coordinates":[12.0698833466,56.0591812134],"type":"Point"}
}