{
  "type": "Feature",
  "properties": {
    "addr:full":"Erdrupvej 3 Boeslunde Danmark 4242",
    "addr:housenumber":"3",
    "addr:postcode":"4242",
    "addr:street":"Erdrupvej",
    "iso:country":"DK",
    "sg:address":"Erdrupvej 3",
    "sg:city":"Boeslunde",
    "sg:orig_category":"Murermestre",
    "sg:phone":"+45 58 14 04 32",
    "sg:postcode":"4242",
    "sg:province":"Danmark",
    "wof:name":"Boeslunde Murerforretning ApS",
    "wof:placetype":"venue"
},
  "geometry": {"coordinates":[11.270362854,55.3057785034],"type":"Point"}
}