{
  "type": "Feature",
  "properties": {
    "addr:full":"Lundeskovsvej 9 Hellerup Danmark 2900",
    "addr:housenumber":"9",
    "addr:postcode":"2900",
    "addr:street":"Lundeskovsvej",
    "iso:country":"DK",
    "sg:address":"Lundeskovsvej 9",
    "sg:city":"Hellerup",
    "sg:orig_category":"Vuggestuer",
    "sg:phone":"+45 39 62 51 98",
    "sg:postcode":"2900",
    "sg:province":"Danmark",
    "wof:name":"Lundehus Vuggestue",
    "wof:placetype":"venue"
},
  "geometry": {"coordinates":[12.5570173264,55.7239151001],"type":"Point"}
}