{
  "type": "Feature",
  "properties": {
    "addr:full":"Gr\u00f8nlandsvej 9 E Horsens Danmark 8700",
    "addr:housenumber":"9 e",
    "addr:postcode":"8700",
    "addr:street":"Gronlandsvej",
    "iso:country":"DK",
    "sg:address":"Gr\u00f8nlandsvej 9 E",
    "sg:city":"Horsens",
    "sg:orig_category":"El-automatik",
    "sg:phone":"+45 75 62 70 00",
    "sg:postcode":"8700",
    "sg:province":"Danmark",
    "wof:name":"Meldgaard Electric A/S",
    "wof:placetype":"venue"
},
  "geometry": {"coordinates":[9.8432445526,55.8621063232],"type":"Point"}
}