{
  "type": "Feature",
  "properties": {
    "addr:full":"Krogsb\u00f8llevej 58, Gundstrup Otterup Danmark 5450",
    "addr:housenumber":"58",
    "addr:postcode":"5450",
    "addr:street":"Krogsbollevej",
    "iso:country":"DK",
    "sg:address":"Krogsb\u00f8llevej 58, Gundstrup",
    "sg:city":"Otterup",
    "sg:orig_category":"Engros handel",
    "sg:phone":"+45 64 87 18 80",
    "sg:postcode":"5450",
    "sg:province":"Danmark",
    "wof:name":"Kalles\u00f8es Handelsfirma",
    "wof:placetype":"venue"
},
  "geometry": {"coordinates":[10.4545049667,55.5641746521],"type":"Point"}
}