{
  "type": "Feature",
  "properties": {
    "addr:full":"Parmagade 31 K\u00f8benhavn S Danmark 2300",
    "addr:housenumber":"31",
    "addr:postcode":"2300",
    "addr:street":"Parmagade;S Danmark",
    "iso:country":"DK",
    "sg:address":"Parmagade 31",
    "sg:city":"K\u00f8benhavn S",
    "sg:orig_category":"\u00c3\u02dcl- og mineralvandsdepoter",
    "sg:phone":"+45 32 59 14 00",
    "sg:postcode":"2300",
    "sg:province":"Danmark",
    "wof:name":"\u00d8l- og vandk\u00e6lderen",
    "wof:placetype":"venue"
},
  "geometry": {"coordinates":[-82.52123260499999,38.4100341797],"type":"Point"}
}