{
  "type": "Feature",
  "properties": {
    "addr:full":"Gothersgade 28 A Fredericia Danmark 7000",
    "addr:housenumber":"28 a",
    "addr:postcode":"7000",
    "addr:street":"Gothersgade",
    "iso:country":"DK",
    "sg:address":"Gothersgade 28 A",
    "sg:city":"Fredericia",
    "sg:classifiers":[
        {
            "category":"Restaurant",
            "type":"Food & Drink"
        }
    ],
    "sg:postcode":"7000",
    "sg:province":"Danmark",
    "wof:name":"Bobby Mcgees",
    "wof:placetype":"venue"
},
  "geometry": {"coordinates":[9.7562770844,55.5635795593],"type":"Point"}
}