{
  "type": "Feature",
  "properties": {
    "addr:full":"Mariedalsvej 4 Brabrand Danmark 8220",
    "addr:housenumber":"4",
    "addr:postcode":"8220",
    "addr:street":"Mariedalsvej",
    "iso:country":"DK",
    "sg:address":"Mariedalsvej 4",
    "sg:city":"Brabrand",
    "sg:orig_category":"Video- og TV-produktion",
    "sg:phone":"+45 86 26 22 88",
    "sg:postcode":"8220",
    "sg:province":"Danmark",
    "sg:website":"www.ptvfilm.dk",
    "wof:name":"PTV Film",
    "wof:placetype":"venue"
},
  "geometry": {"coordinates":[10.0996360779,56.1570701599],"type":"Point"}
}