{
  "type": "Feature",
  "properties": {
    "addr:full":"N\u00f8rremarksvej 7 Klarup Danmark 9270",
    "addr:housenumber":"7",
    "addr:postcode":"9270",
    "addr:street":"Norremarksvej",
    "iso:country":"DK",
    "sg:address":"N\u00f8rremarksvej 7",
    "sg:city":"Klarup",
    "sg:classifiers":[
        {
            "category":"Autos & Motor Vehicles",
            "subcategory":"Automobile Sales",
            "type":"Retail Goods"
        }
    ],
    "sg:phone":"+45 98 38 33 11",
    "sg:postcode":"9270",
    "sg:province":"Danmark",
    "sg:tags":[
        "truck"
    ],
    "wof:name":"N & V Truck A/S",
    "wof:placetype":"venue"
},
  "geometry": {"coordinates":[10.0499897003,57.0173797607],"type":"Point"}
}