{
  "type": "Feature",
  "properties": {
    "iso:country":"DK",
    "sg:address":"Engstrupg\u00e5rdsvej 50",
    "sg:city":"Hvidovre",
    "sg:orig_category":"Reklame",
    "sg:phone":"+45 36 77 73 37",
    "sg:postcode":"2650",
    "sg:province":"Danmark",
    "wof:name":"W J Grafik",
    "wof:placetype":"venue"
},
  "geometry": {"coordinates":[12.4519319534,55.6239814758],"type":"Point"}
}