{
  "type": "Feature",
  "properties": {
    "addr:full":"Tordenskjoldsgade 14 Frederikshavn Danmark 9900",
    "addr:housenumber":"14",
    "addr:postcode":"9900",
    "addr:street":"Tordenskjoldsgade",
    "iso:country":"DK",
    "sg:address":"Tordenskjoldsgade 14",
    "sg:city":"Frederikshavn",
    "sg:classifiers":[
        {
            "category":"Restaurant",
            "type":"Food & Drink"
        }
    ],
    "sg:phone":"+45 98 43 32 33",
    "sg:postcode":"9900",
    "sg:province":"Danmark",
    "wof:name":"Gule Pakhus, Det",
    "wof:placetype":"venue"
},
  "geometry": {"coordinates":[10.5370178223,57.4392471313],"type":"Point"}
}