{
  "type": "Feature",
  "properties": {
    "iso:country":"DK",
    "sg:address":"Boulevarden 6, \u00d8. Kippinge",
    "sg:city":"N\u00f8rre Alslev",
    "sg:orig_category":"Maskinfabrikker",
    "sg:phone":"+45 54 43 22 99",
    "sg:postcode":"4840",
    "sg:province":"Danmark",
    "wof:name":"\u00d8ster Kippinge St\u00e5lindustri",
    "wof:placetype":"venue"
},
  "geometry": {"coordinates":[11.8542251587,54.9528236389],"type":"Point"}
}