{
  "type": "Feature",
  "properties": {
    "addr:full":"V\u00e5rvej 2, Farstrup Nibe Danmark 9240",
    "addr:housenumber":"2",
    "addr:postcode":"9240",
    "addr:street":"Vaarvej;Farstrup",
    "iso:country":"DK",
    "sg:address":"V\u00e5rvej 2, Farstrup",
    "sg:city":"Nibe",
    "sg:orig_category":"Kirker",
    "sg:postcode":"9240",
    "sg:province":"Danmark",
    "wof:name":"Farstrup Kirke",
    "wof:placetype":"venue"
},
  "geometry": {"coordinates":[9.6393280029,56.982421875],"type":"Point"}
}