{
  "type": "Feature",
  "properties": {
    "addr:full":"Amtsvejen 2, Filskov Grindsted Danmark 7200",
    "addr:housenumber":"2",
    "addr:postcode":"7200",
    "addr:street":"Amtsvejen;Filskov",
    "iso:country":"DK",
    "sg:address":"Amtsvejen 2, Filskov",
    "sg:city":"Grindsted",
    "sg:orig_category":"Homeparties",
    "sg:postcode":"7200",
    "sg:province":"Danmark",
    "wof:name":"S\u00f8rensen, Camilla",
    "wof:placetype":"venue"
},
  "geometry": {"coordinates":[8.9288702011,55.7560272217],"type":"Point"}
}