{
  "type": "Feature",
  "properties": {
    "addr:full":"Gribstrupvej 5, Gribstrup Klovborg Danmark 8765",
    "addr:housenumber":"5",
    "addr:postcode":"8765",
    "addr:street":"Gribstrupvej",
    "iso:country":"DK",
    "sg:address":"Gribstrupvej 5, Gribstrup",
    "sg:city":"Klovborg",
    "sg:orig_category":"Produktionsskoler",
    "sg:phone":"+45 75 76 13 33",
    "sg:postcode":"8765",
    "sg:province":"Danmark",
    "sg:website":"www.mollegaardennsp.dk",
    "wof:name":"M\u00f8llegaarden, N\u00f8rre-Snede Produktionsskole",
    "wof:placetype":"venue"
},
  "geometry": {"coordinates":[9.4899053574,55.9317016602],"type":"Point"}
}