{
  "type": "Feature",
  "properties": {
    "addr:full":"Havndalvej 44 Mariager Danmark 9550",
    "addr:housenumber":"44",
    "addr:postcode":"9550",
    "addr:street":"Havndalvej",
    "iso:country":"DK",
    "sg:address":"Havndalvej 44",
    "sg:city":"Mariager",
    "sg:orig_category":"Slagterier",
    "sg:phone":"+45 98 58 37 11",
    "sg:postcode":"9550",
    "sg:province":"Danmark",
    "wof:name":"Edderup Slagteri",
    "wof:placetype":"venue"
},
  "geometry": {"coordinates":[10.0511293411,56.6497344971],"type":"Point"}
}