{
  "type": "Feature",
  "properties": {
    "addr:full":"H\u00f8brovej 9 F Tim Danmark 6980",
    "addr:housenumber":"9 f",
    "addr:postcode":"6980",
    "addr:street":"Hobrovej",
    "iso:country":"DK",
    "sg:address":"H\u00f8brovej 9 F",
    "sg:city":"Tim",
    "sg:orig_category":"Varmeforsyning",
    "sg:phone":"+45 97 33 34 44",
    "sg:postcode":"6980",
    "sg:province":"Danmark",
    "wof:name":"Tim Kraftvarmev\u00e6rk",
    "wof:placetype":"venue"
},
  "geometry": {"coordinates":[8.3066711426,56.1961898804],"type":"Point"}
}