{
  "type": "Feature",
  "properties": {
    "addr:full":"Juelsbjerg 2, Felsted Aabenraa Danmark 6200",
    "addr:housenumber":"2",
    "addr:postcode":"6200",
    "addr:street":"Juelsbjerg;Felsted",
    "iso:country":"DK",
    "sg:address":"Juelsbjerg 2, Felsted",
    "sg:city":"Aabenraa",
    "sg:orig_category":"Landbrugsmaskiner",
    "sg:phone":"+45 74 68 55 02",
    "sg:postcode":"6200",
    "sg:province":"Danmark",
    "sg:website":"www.maskincenter-felsted.dk",
    "wof:name":"Maskincenter Felsted",
    "wof:placetype":"venue"
},
  "geometry": {"coordinates":[9.4213867188,55.0449562073],"type":"Point"}
}