{
  "type": "Feature",
  "properties": {
    "addr:full":"Gruppeleder: Egon Pedersen, Okslundvej 40, Lindknud Br\u00f8rup Danmark 6650",
    "addr:housenumber":"40",
    "addr:postcode":"6650",
    "addr:street":"Okslundvej",
    "iso:country":"DK",
    "sg:address":"Gruppeleder: Egon Pedersen, Okslundvej 40, Lindknud",
    "sg:city":"Br\u00f8rup",
    "sg:orig_category":"Spejderkorps",
    "sg:phone":"+45 75 38 82 59",
    "sg:postcode":"6650",
    "sg:province":"Danmark",
    "wof:name":"KFUM-spejderne i Lindknud",
    "wof:placetype":"venue"
},
  "geometry": {"coordinates":[9.0038452148,55.4421157837],"type":"Point"}
}