{
  "type": "Feature",
  "properties": {
    "iso:country":"DK",
    "sg:address":"v/ J\u00f8rgen Wandel, Trannisvej 29",
    "sg:city":"Egtved",
    "sg:orig_category":"Kulturelle foreninger",
    "sg:phone":"+45 75 55 20 14",
    "sg:postcode":"6040",
    "sg:province":"Danmark",
    "wof:name":"Egtvedegnens Museumsforening",
    "wof:placetype":"venue"
},
  "geometry": {"coordinates":[9.3087482452,55.6161613464],"type":"Point"}
}