{
  "type": "Feature",
  "properties": {
    "addr:full":"Steng\u00e5rdsvej 317 Esbjerg \u00d8 Danmark 6705",
    "addr:housenumber":"317",
    "addr:postcode":"6705",
    "addr:street":"Stengaardsvej;Danmark",
    "iso:country":"DK",
    "sg:address":"Steng\u00e5rdsvej 317",
    "sg:city":"Esbjerg \u00d8",
    "sg:orig_category":"Ungdomsklubber",
    "sg:phone":"+45 75 14 44 89",
    "sg:postcode":"6705",
    "sg:province":"Danmark",
    "wof:name":"Klub Ringg\u00e5rden",
    "wof:placetype":"venue"
},
  "geometry": {"coordinates":[8.4909334183,55.4855041504],"type":"Point"}
}