{
  "type": "Feature",
  "properties": {
    "addr:full":"Hjertingvej 74 Esbjerg Danmark 6700",
    "addr:housenumber":"74",
    "addr:postcode":"6700",
    "addr:street":"Hjertingvej",
    "iso:country":"DK",
    "sg:address":"Hjertingvej 74",
    "sg:city":"Esbjerg",
    "sg:orig_category":"Autoreservedele",
    "sg:phone":"+45 70 10 10 57",
    "sg:postcode":"6700",
    "sg:province":"Danmark",
    "sg:website":"www.hoyer-autodele.dk",
    "wof:name":"H\u00f8yer Autodele Esbjerg ApS",
    "wof:placetype":"venue"
},
  "geometry": {"coordinates":[8.4280357361,55.4802703857],"type":"Point"}
}