{
  "type": "Feature",
  "properties": {
    "addr:full":"Hovedgaden 40 Ulstrup Danmark 8860",
    "addr:housenumber":"40",
    "addr:postcode":"8860",
    "addr:street":"Hovedgaden",
    "iso:country":"DK",
    "sg:address":"Hovedgaden 40",
    "sg:city":"Ulstrup",
    "sg:orig_category":"Servicestationer",
    "sg:phone":"+45 86 46 40 00",
    "sg:postcode":"8860",
    "sg:province":"Danmark",
    "wof:name":"Ulstrup Autoservice",
    "wof:placetype":"venue"
},
  "geometry": {"coordinates":[9.7911567688,56.3892478943],"type":"Point"}
}