{
  "type": "Feature",
  "properties": {
    "addr:full":"Pressalitvej 1 Ry Danmark 8680",
    "addr:housenumber":"1",
    "addr:postcode":"8680",
    "addr:street":"Pressalitvej",
    "iso:country":"DK",
    "sg:address":"Pressalitvej 1",
    "sg:city":"Ry",
    "sg:orig_category":"Fabrikker",
    "sg:phone":"+45 87 88 87 88",
    "sg:postcode":"8680",
    "sg:province":"Danmark",
    "sg:website":"www.pressalit.com",
    "wof:name":"Pressalit A/S",
    "wof:placetype":"venue"
},
  "geometry": {"coordinates":[9.7971782684,56.0860023499],"type":"Point"}
}