{
  "type": "Feature",
  "properties": {
    "addr:full":"Museumsgade 103 Maribo Danmark 4930",
    "addr:housenumber":"103",
    "addr:postcode":"4930",
    "addr:street":"Museumsgade",
    "iso:country":"DK",
    "sg:address":"Museumsgade 103",
    "sg:city":"Maribo",
    "sg:orig_category":"Stenhuggere",
    "sg:phone":"+45 54 75 80 79",
    "sg:postcode":"4930",
    "sg:province":"Danmark",
    "wof:name":"Lolland-Falster Stenhuggeri",
    "wof:placetype":"venue"
},
  "geometry": {"coordinates":[11.513384819,54.7766075134],"type":"Point"}
}