{
  "type": "Feature",
  "properties": {
    "addr:full":"Transportbuen 2, \u00d8verup N\u00e6stved Danmark 4700",
    "addr:housenumber":"2",
    "addr:postcode":"4700",
    "addr:street":"Transportbuen",
    "iso:country":"DK",
    "sg:address":"Transportbuen 2, \u00d8verup",
    "sg:city":"N\u00e6stved",
    "sg:orig_category":"Autoforhandlere",
    "sg:phone":"+45 55 77 40 41",
    "sg:postcode":"4700",
    "sg:province":"Danmark",
    "sg:website":"www.peugeot.dk/naestved",
    "wof:name":"Peugeot N\u00e6stved",
    "wof:placetype":"venue"
},
  "geometry": {"coordinates":[11.7542486191,55.2315444946],"type":"Point"}
}