{
  "type": "Feature",
  "properties": {
    "addr:full":"v/ Erik S\u00f8rensen, Havnevej 63, Postboks 203 Grenaa Danmark 8500",
    "addr:housenumber":"63;203",
    "addr:postcode":"8500",
    "addr:street":"Sorensen Havnevej",
    "iso:country":"DK",
    "sg:address":"v/ Erik S\u00f8rensen, Havnevej 63, Postboks 203",
    "sg:city":"Grenaa",
    "sg:orig_category":"Hobbybetonede foreninger",
    "sg:phone":"+45 86 32 52 56",
    "sg:postcode":"8500",
    "sg:province":"Danmark",
    "sg:website":"www.goof.subnet.dk",
    "wof:name":"Grenaa og Omegns Frim\u00e6rkeklub",
    "wof:placetype":"venue"
},
  "geometry": {"coordinates":[10.8774929047,56.4126853943],"type":"Point"}
}