{
  "type": "Feature",
  "properties": {
    "iso:country":"DK",
    "sg:address":"M\u00f8rkh\u00f8j Bygade 19",
    "sg:city":"S\u00f8borg",
    "sg:orig_category":"Statslige direktorater og styrelser",
    "sg:phone":"+45 33 95 60 00",
    "sg:postcode":"2860",
    "sg:province":"Danmark",
    "sg:website":"www.foedevaredirektoratet.dk",
    "wof:name":"F\u00f8devaredirektoratet",
    "wof:placetype":"venue"
},
  "geometry": {"coordinates":[-101.39041900629999,35.6679611206],"type":"Point"}
}