{
  "type": "Feature",
  "properties": {
    "iso:country":"DK",
    "sg:address":"S\u00f8ndergade 1",
    "sg:city":"Skive",
    "sg:orig_category":"Servicestationer",
    "sg:phone":"+45 97 52 14 22",
    "sg:postcode":"7800",
    "sg:province":"Danmark",
    "wof:name":"A/S Shell Service",
    "wof:placetype":"venue"
},
  "geometry": {"coordinates":[9.02645,56.564663],"type":"Point"}
}