{
  "type": "Feature",
  "properties": {
    "iso:country":"DK",
    "sg:address":"Vestermarken 1",
    "sg:city":"Ballerup",
    "sg:orig_category":"Danseundervisning",
    "sg:phone":"+45 44 97 06 07",
    "sg:postcode":"2750",
    "sg:province":"Danmark",
    "wof:name":"Dancing Team",
    "wof:placetype":"venue"
},
  "geometry": {"coordinates":[12.3574542999,55.726764679],"type":"Point"}
}