{
  "type": "Feature",
  "properties": {
    "addr:full":"Hovedgaden 9 Lille Skensved Danmark 4623",
    "addr:housenumber":"9",
    "addr:postcode":"4623",
    "addr:street":"Hovedgaden",
    "iso:country":"DK",
    "sg:address":"Hovedgaden 9",
    "sg:city":"Lille Skensved",
    "sg:orig_category":"Bagere",
    "sg:phone":"+45 56 16 90 10",
    "sg:postcode":"4623",
    "sg:province":"Danmark",
    "wof:name":"Lille-Skensved Bageri",
    "wof:placetype":"venue"
},
  "geometry": {"coordinates":[12.1382236481,55.5121421814],"type":"Point"}
}