{
  "type": "Feature",
  "properties": {
    "addr:full":"Risbyvej 6 Kastrup Danmark 2770",
    "addr:housenumber":"6",
    "addr:postcode":"2770",
    "addr:street":"Risbyvej",
    "iso:country":"DK",
    "sg:address":"Risbyvej 6",
    "sg:city":"Kastrup",
    "sg:orig_category":"Malermestre",
    "sg:phone":"+45 32 51 63 69",
    "sg:postcode":"2770",
    "sg:province":"Danmark",
    "wof:name":"Gertsen's Malerservice",
    "wof:placetype":"venue"
},
  "geometry": {"coordinates":[12.6153612137,55.6379470825],"type":"Point"}
}