{
  "type": "Feature",
  "properties": {
    "addr:full":"Terndrup Halvej 1 Terndrup Danmark 9575",
    "addr:housenumber":"1",
    "addr:postcode":"9575",
    "addr:street":"Terndrup Halvej;Danmark",
    "iso:country":"DK",
    "sg:address":"Terndrup Halvej 1",
    "sg:city":"Terndrup",
    "sg:orig_category":"Skolefritidsordninger",
    "sg:phone":"+45 99 82 85 28",
    "sg:postcode":"9575",
    "sg:province":"Danmark",
    "wof:name":"Skolefritidsordningen ved Terndrup Skole",
    "wof:placetype":"venue"
},
  "geometry": {"coordinates":[10.0568656921,56.8190879822],"type":"Point"}
}