{
  "type": "Feature",
  "properties": {
    "addr:full":"Jens Bangs Gade 6 - 8 Aalborg Danmark 9000",
    "addr:housenumber":"6 8",
    "addr:postcode":"9000",
    "addr:street":"Jens Bangs Gade",
    "iso:country":"DK",
    "sg:address":"Jens Bangs Gade 6 - 8",
    "sg:city":"Aalborg",
    "sg:orig_category":"Gallerier",
    "sg:phone":"+45 98 10 90 65",
    "sg:postcode":"9000",
    "sg:province":"Danmark",
    "sg:website":"www.gallerigram.dk",
    "wof:name":"Gram Art, Galleri",
    "wof:placetype":"venue"
},
  "geometry": {"coordinates":[9.9155187607,57.0492324829],"type":"Point"}
}