{
  "type": "Feature",
  "properties": {
    "addr:full":"Jomfru Ane Gade 3 Aalborg Danmark 9000",
    "addr:housenumber":"3",
    "addr:postcode":"9000",
    "addr:street":"Jomfru Ane Gade",
    "iso:country":"DK",
    "sg:address":"Jomfru Ane Gade 3",
    "sg:city":"Aalborg",
    "sg:classifiers":[
        {
            "category":"Restaurant",
            "type":"Food & Drink"
        }
    ],
    "sg:phone":"+45 98 13 20 80",
    "sg:postcode":"9000",
    "sg:province":"Danmark",
    "wof:name":"Felix",
    "wof:placetype":"venue"
},
  "geometry": {"coordinates":[9.9183721542,57.0496368408],"type":"Point"}
}