{
  "type": "Feature",
  "properties": {
    "iso:country":"DK",
    "sg:address":"S\u00f8bredden 36 F",
    "sg:city":"Gentofte",
    "sg:orig_category":"Brevskoler",
    "sg:phone":"+45 39 68 32 98",
    "sg:postcode":"2820",
    "sg:province":"Danmark",
    "sg:website":"www.nebelong.com",
    "wof:name":"Nebelong Kommunikation",
    "wof:placetype":"venue"
},
  "geometry": {"coordinates":[12.5409173965,55.7482719421],"type":"Point"}
}