{
  "type": "Feature",
  "properties": {
    "addr:full":"Sct. Nicolaj Gade 10 Ribe Danmark 6760",
    "addr:housenumber":"10",
    "addr:postcode":"6760",
    "addr:street":"Sct. Nicolaj Gade",
    "iso:country":"DK",
    "sg:address":"Sct. Nicolaj Gade 10",
    "sg:city":"Ribe",
    "sg:orig_category":"Museer",
    "sg:phone":"+45 75 42 03 62",
    "sg:postcode":"6760",
    "sg:province":"Danmark",
    "wof:name":"Ribe Kunstmuseum",
    "wof:placetype":"venue"
},
  "geometry": {"coordinates":[8.7676534653,55.3291511536],"type":"Point"}
}