{
  "type": "Feature",
  "properties": {
    "iso:country":"DK",
    "sg:address":"Strandvejen 32",
    "sg:city":"Nyborg",
    "sg:orig_category":"Bagere",
    "sg:phone":"+45 65 31 03 99",
    "sg:postcode":"5800",
    "sg:province":"Danmark",
    "wof:name":"Guldbageren",
    "wof:placetype":"venue"
},
  "geometry": {"coordinates":[10.786872,55.309399],"type":"Point"}
}