{
  "type": "Feature",
  "properties": {
    "addr:full":"Fmd.: Vilmer Karlsen, Rosenvej 130 Tarm Danmark 6880",
    "addr:housenumber":"130",
    "addr:postcode":"6880",
    "addr:street":"Karlsen Rosenvej",
    "iso:country":"DK",
    "sg:address":"Fmd.: Vilmer Karlsen, Rosenvej 130",
    "sg:city":"Tarm",
    "sg:orig_category":"Kirkelige foreninger",
    "sg:phone":"+45 97 37 16 15",
    "sg:postcode":"6880",
    "sg:province":"Danmark",
    "wof:name":"Kirkens Korsh\u00e6r",
    "wof:placetype":"venue"
},
  "geometry": {"coordinates":[8.5200052261,55.9060554504],"type":"Point"}
}