{
  "type": "Feature",
  "properties": {
    "addr:full":"Vestergade 42 A Auning Danmark 8963",
    "addr:housenumber":"42 a",
    "addr:postcode":"8963",
    "addr:street":"Vestergade",
    "iso:country":"DK",
    "sg:address":"Vestergade 42 A",
    "sg:city":"Auning",
    "sg:orig_category":"Autoreparation og -service",
    "sg:phone":"+45 86 48 44 08",
    "sg:postcode":"8963",
    "sg:province":"Danmark",
    "wof:name":"J. P. Biler",
    "wof:placetype":"venue"
},
  "geometry": {"coordinates":[10.3700580597,56.431552887],"type":"Point"}
}