{
  "type": "Feature",
  "properties": {
    "addr:full":"Boulevarden 13 Odder Danmark 8300",
    "addr:housenumber":"13",
    "addr:postcode":"8300",
    "addr:street":"Boulevarden",
    "iso:country":"DK",
    "sg:address":"Boulevarden 13",
    "sg:city":"Odder",
    "sg:orig_category":"Landboorganisationer",
    "sg:phone":"+45 70 15 40 00",
    "sg:postcode":"8300",
    "sg:province":"Danmark",
    "wof:name":"Hads Herreds Landboforening",
    "wof:placetype":"venue"
},
  "geometry": {"coordinates":[10.1475124359,55.9695777893],"type":"Point"}
}