{
  "type": "Feature",
  "properties": {
    "addr:full":"Oustedvej 9, Riis Skanderborg Danmark 8660",
    "addr:housenumber":"9",
    "addr:postcode":"8660",
    "addr:street":"Oustedvej",
    "iso:country":"DK",
    "sg:address":"Oustedvej 9, Riis",
    "sg:city":"Skanderborg",
    "sg:classifiers":[
        {
            "category":"Organizations",
            "subcategory":"Community Association",
            "type":"Services"
        }
    ],
    "sg:phone":"+45 76 69 20 06",
    "sg:postcode":"8660",
    "sg:province":"Danmark",
    "sg:tags":[
        "relation",
        "public"
    ],
    "wof:name":"Pressekontakt",
    "wof:placetype":"venue"
},
  "geometry": {"coordinates":[9.929974556,56.0380249023],"type":"Point"}
}