{
  "type": "Feature",
  "properties": {
    "iso:country":"DK",
    "sg:address":"Gr\u00e6vlingens Kvarter 47",
    "sg:city":"Ballerup",
    "sg:orig_category":"Blomsterhandlere",
    "sg:phone":"+45 44 97 31 81",
    "sg:postcode":"2750",
    "sg:province":"Danmark",
    "wof:name":"Blomsterkransen",
    "wof:placetype":"venue"
},
  "geometry": {"coordinates":[12.3629179001,55.7405967712],"type":"Point"}
}