{
  "type": "Feature",
  "properties": {
    "addr:full":"Lysemosen 16, Allingskovby Silkeborg Danmark 8600",
    "addr:housenumber":"16",
    "addr:postcode":"8600",
    "addr:street":"Lysemosen;Allingskovby",
    "iso:country":"DK",
    "sg:address":"Lysemosen 16, Allingskovby",
    "sg:city":"Silkeborg",
    "sg:orig_category":"Autoreparation og -service",
    "sg:phone":"+45 86 87 71 67",
    "sg:postcode":"8600",
    "sg:province":"Danmark",
    "sg:website":"www.ej-auto.dk",
    "wof:name":"EJ Auto",
    "wof:placetype":"venue"
},
  "geometry": {"coordinates":[9.5524425507,56.1693305969],"type":"Point"}
}