{
  "type": "Feature",
  "properties": {
    "addr:full":"Baneg\u00e5rdspladsen 2 Kolding Danmark 6000",
    "addr:housenumber":"2",
    "addr:postcode":"6000",
    "addr:street":"Banegaardspladsen",
    "iso:country":"DK",
    "sg:address":"Baneg\u00e5rdspladsen 2",
    "sg:city":"Kolding",
    "sg:orig_category":"Kiosker",
    "sg:phone":"+45 75 53 24 21",
    "sg:postcode":"6000",
    "sg:province":"Danmark",
    "wof:name":"Kolding Baneg\u00e5rd",
    "wof:placetype":"venue"
},
  "geometry": {"coordinates":[9.4804868698,55.4905204773],"type":"Point"}
}