{
  "type": "Feature",
  "properties": {
    "addr:full":"Griffenfeldsgade 37 K\u00f8benhavn N Danmark 2200",
    "addr:housenumber":"37",
    "addr:postcode":"2200",
    "addr:street":"Griffenfeldsgade;Kobenhavn N Danmark",
    "iso:country":"DK",
    "sg:address":"Griffenfeldsgade 37",
    "sg:city":"K\u00f8benhavn N",
    "sg:orig_category":"Gaveartikler",
    "sg:phone":"+45 35 35 93 46",
    "sg:postcode":"2200",
    "sg:province":"Danmark",
    "sg:website":"www.lillebror.net",
    "wof:name":"Lillebror Butikken",
    "wof:placetype":"venue"
},
  "geometry": {"coordinates":[-94.4101867676,47.9767036438],"type":"Point"}
}