{
  "type": "Feature",
  "properties": {
    "addr:full":"H\u00f8edvej 22, H\u00f8ed Jyderup Danmark 4450",
    "addr:housenumber":"22",
    "addr:postcode":"4450",
    "addr:street":"Hoedvej",
    "iso:country":"DK",
    "sg:address":"H\u00f8edvej 22, H\u00f8ed",
    "sg:city":"Jyderup",
    "sg:orig_category":"Fugning",
    "sg:phone":"+45 59 27 83 14",
    "sg:postcode":"4450",
    "sg:province":"Danmark",
    "wof:name":"H\u00f8j Fuge Teknik",
    "wof:placetype":"venue"
},
  "geometry": {"coordinates":[11.4029512405,55.6602401733],"type":"Point"}
}