{
  "type": "Feature",
  "properties": {
    "addr:full":"Blomsterv\u00e6nget 5 Dalmose Danmark 4261",
    "addr:housenumber":"5",
    "addr:postcode":"4261",
    "addr:street":"Blomstervaenget",
    "iso:country":"DK",
    "sg:address":"Blomsterv\u00e6nget 5",
    "sg:city":"Dalmose",
    "sg:orig_category":"Biblioteker",
    "sg:postcode":"4261",
    "sg:province":"Danmark",
    "wof:name":"Distriktsbibliotek p\u00e5 Dalmose Centralskole",
    "wof:placetype":"venue"
},
  "geometry": {"coordinates":[11.4164381027,55.2941207886],"type":"Point"}
}