{
  "type": "Feature",
  "properties": {
    "addr:full":"Algade 4 Haarby Danmark 5683",
    "addr:housenumber":"4",
    "addr:postcode":"5683",
    "addr:street":"Algade",
    "iso:country":"DK",
    "sg:address":"Algade 4",
    "sg:city":"Haarby",
    "sg:orig_category":"Sparekasser",
    "sg:phone":"+45 64 73 15 15",
    "sg:postcode":"5683",
    "sg:province":"Danmark",
    "wof:name":"Sparekassen Faaborg",
    "wof:placetype":"venue"
},
  "geometry": {"coordinates":[10.1284170151,55.2231178284],"type":"Point"}
}