{
  "type": "Feature",
  "properties": {
    "iso:country":"DK",
    "sg:address":"Daglig leder: Susanne Riism\u00f8ller, Holmehave 46, Benl\u00f8se",
    "sg:city":"Ringsted",
    "sg:orig_category":"Oplysningsforbund",
    "sg:phone":"+45 57 61 70 07",
    "sg:postcode":"4100",
    "sg:province":"Danmark",
    "wof:name":"Gigtforeningens Oplysningskreds Ringsted",
    "wof:placetype":"venue"
},
  "geometry": {"coordinates":[11.7875862122,55.4458961487],"type":"Point"}
}