{
  "type": "Feature",
  "properties": {
    "iso:country":"DK",
    "sg:address":"\u00d8stervold 28",
    "sg:city":"Randers",
    "sg:orig_category":"Slagter og viktualie",
    "sg:phone":"+45 86 42 14 40",
    "sg:postcode":"8900",
    "sg:province":"Danmark",
    "wof:name":"Lind I/S",
    "wof:placetype":"venue"
},
  "geometry": {"coordinates":[10.0397672653,56.4599571228],"type":"Point"}
}