{
  "type": "Feature",
  "properties": {
    "addr:full":"v/ Carsten P. Lorentsen, Plantagevej 19 Fredensborg Danmark 3480",
    "addr:housenumber":"19",
    "addr:postcode":"3480",
    "addr:street":"Plantagevej",
    "iso:country":"DK",
    "sg:address":"v/ Carsten P. Lorentsen, Plantagevej 19",
    "sg:city":"Fredensborg",
    "sg:orig_category":"Kirkelige foreninger",
    "sg:phone":"+45 48 48 07 31",
    "sg:postcode":"3480",
    "sg:province":"Danmark",
    "wof:name":"Luthersk Missionsforening",
    "wof:placetype":"venue"
},
  "geometry": {"coordinates":[12.4020547867,55.9782943726],"type":"Point"}
}