{
  "type": "Feature",
  "properties": {
    "addr:full":"M\u00f8lbjergvej 1, Handrup Ebeltoft Danmark 8400",
    "addr:housenumber":"1",
    "addr:postcode":"8400",
    "addr:street":"Molbjergvej",
    "iso:country":"DK",
    "sg:address":"M\u00f8lbjergvej 1, Handrup",
    "sg:city":"Ebeltoft",
    "sg:orig_category":"Musikere",
    "sg:phone":"+45 86 36 14 00",
    "sg:postcode":"8400",
    "sg:province":"Danmark",
    "wof:name":"Duo Gaia",
    "wof:placetype":"venue"
},
  "geometry": {"coordinates":[10.6778745651,56.199798584],"type":"Point"}
}