{
  "type": "Feature",
  "properties": {
    "addr:full":"Borups Alle 156 Frederiksberg Danmark 2000",
    "addr:housenumber":"156",
    "addr:postcode":"2000",
    "addr:street":"Borups Alle",
    "iso:country":"DK",
    "sg:address":"Borups Alle 156",
    "sg:city":"Frederiksberg",
    "sg:orig_category":"Autoforhandlere",
    "sg:phone":"+45 38 10 16 11",
    "sg:postcode":"2000",
    "sg:province":"Danmark",
    "wof:name":"Mazda Frederiksberg",
    "wof:placetype":"venue"
},
  "geometry": {"coordinates":[12.5283231735,55.6953620911],"type":"Point"}
}