{
  "type": "Feature",
  "properties": {
    "addr:full":"Jernbanegade 11 Thors\u00f8 Danmark 8881",
    "addr:housenumber":"11",
    "addr:postcode":"8881",
    "addr:street":"Jernbanegade",
    "iso:country":"DK",
    "sg:address":"Jernbanegade 11",
    "sg:city":"Thors\u00f8",
    "sg:orig_category":"Posthuse",
    "sg:phone":"+45 89 28 88 00",
    "sg:postcode":"8881",
    "sg:province":"Danmark",
    "wof:name":"Post Danmark, Thors\u00f8 Postekspedition",
    "wof:placetype":"venue"
},
  "geometry": {"coordinates":[9.7907829285,56.2970619202],"type":"Point"}
}