{
  "type": "Feature",
  "properties": {
    "addr:full":"K\u00f8benhavnsvej 5 Vordingborg Danmark 4760",
    "addr:housenumber":"5",
    "addr:postcode":"4760",
    "addr:street":"Kobenhavnsvej",
    "iso:country":"DK",
    "sg:address":"K\u00f8benhavnsvej 5",
    "sg:city":"Vordingborg",
    "sg:classifiers":[
        {
            "category":"Communications",
            "type":"Services"
        }
    ],
    "sg:phone":"+45 55 36 10 02",
    "sg:postcode":"4760",
    "sg:province":"Danmark",
    "sg:tags":[
        "radio-",
        "og",
        "tv-stationer"
    ],
    "sg:website":"www.tvd2syd.dk",
    "wof:name":"Sydsj\u00e6llands Lokal TV",
    "wof:placetype":"venue"
},
  "geometry": {"coordinates":[11.9123411179,55.0086975098],"type":"Point"}
}