{
  "type": "Feature",
  "properties": {
    "addr:full":"S\u00f8ren M\u00f8llers Gade 36 Randers Danmark 8900",
    "addr:housenumber":"36",
    "addr:postcode":"8900",
    "addr:street":"Mollers Gade",
    "iso:country":"DK",
    "sg:address":"S\u00f8ren M\u00f8llers Gade 36",
    "sg:city":"Randers",
    "sg:orig_category":"Faglige organisationer og foreninger",
    "sg:phone":"+45 86 43 82 46",
    "sg:postcode":"8900",
    "sg:province":"Danmark",
    "wof:name":"Dansk El-Forbund",
    "wof:placetype":"venue"
},
  "geometry": {"coordinates":[10.0307912827,56.4682121277],"type":"Point"}
}