{
  "type": "Feature",
  "properties": {
    "addr:full":"Karensmindevej 3 Middelfart Danmark 5500",
    "addr:housenumber":"3",
    "addr:postcode":"5500",
    "addr:street":"Karensmindevej",
    "iso:country":"DK",
    "sg:address":"Karensmindevej 3",
    "sg:city":"Middelfart",
    "sg:orig_category":"HOTELS: OG MOTELLER",
    "sg:phone":"+45 63 41 81 00",
    "sg:postcode":"5500",
    "sg:province":"Danmark",
    "sg:website":"www.scanticoncomwell-middelfart.dk",
    "wof:name":"Scanticon Comwell Middelfart a-s",
    "wof:placetype":"venue"
},
  "geometry": {"coordinates":[9.7649059296,55.5114898682],"type":"Point"}
}