{
  "type": "Feature",
  "properties": {
    "addr:full":"Asbovej 41, L\u00e6borg Vejen Danmark 6600",
    "addr:housenumber":"41",
    "addr:postcode":"6600",
    "addr:street":"Asbovej;Laeborg",
    "iso:country":"DK",
    "sg:address":"Asbovej 41, L\u00e6borg",
    "sg:city":"Vejen",
    "sg:orig_category":"Grillbarer",
    "sg:phone":"+45 75 36 80 98",
    "sg:postcode":"6600",
    "sg:province":"Danmark",
    "wof:name":"Skovly Grill",
    "wof:placetype":"venue"
},
  "geometry": {"coordinates":[9.1396121979,55.4778175354],"type":"Point"}
}