{
  "type": "Feature",
  "properties": {
    "addr:full":"\u00c5lk\u00e6rg\u00e5rdvej 1 Horsens Danmark 8700",
    "addr:housenumber":"1",
    "addr:postcode":"8700",
    "addr:street":"Aalkaergaardvej",
    "iso:country":"DK",
    "sg:address":"\u00c5lk\u00e6rg\u00e5rdvej 1",
    "sg:city":"Horsens",
    "sg:orig_category":"Brugskunst",
    "sg:phone":"+45 75 65 62 48",
    "sg:postcode":"8700",
    "sg:province":"Danmark",
    "wof:name":"Vin og Glaskunst",
    "wof:placetype":"venue"
},
  "geometry": {"coordinates":[9.8432445526,55.8621063232],"type":"Point"}
}