{
  "type": "Feature",
  "properties": {
    "addr:full":"Svinkl\u00f8vvej 541, Svinkl\u00f8v Fjerritslev Danmark 9690",
    "addr:housenumber":"541",
    "addr:postcode":"9690",
    "addr:street":"Svinklovvej;Svinklov",
    "iso:country":"DK",
    "sg:address":"Svinkl\u00f8vvej 541, Svinkl\u00f8v",
    "sg:city":"Fjerritslev",
    "sg:orig_category":"Campingpladser",
    "sg:phone":"+45 98 21 71 80",
    "sg:postcode":"9690",
    "sg:province":"Danmark",
    "sg:website":"www.publiccamp.dk/svinklov",
    "wof:name":"Svinkl\u00f8v Camping",
    "wof:placetype":"venue"
},
  "geometry": {"coordinates":[9.2667350769,57.0882301331],"type":"Point"}
}