{
  "type": "Feature",
  "properties": {
    "addr:full":"Smedevej 6 Gedser Danmark 4874",
    "addr:housenumber":"6",
    "addr:postcode":"4874",
    "addr:street":"Smedevej",
    "iso:country":"DK",
    "sg:address":"Smedevej 6",
    "sg:city":"Gedser",
    "sg:orig_category":"Varmeforsyning",
    "sg:phone":"+45 54 17 92 78",
    "sg:postcode":"4874",
    "sg:province":"Danmark",
    "wof:name":"Gedser Halmvarmev\u00e6rk",
    "wof:placetype":"venue"
},
  "geometry": {"coordinates":[11.9351186752,54.5765533447],"type":"Point"}
}