{
  "type": "Feature",
  "properties": {
    "iso:country":"DK",
    "sg:address":"Kinovej 1",
    "sg:city":"Vamdrup",
    "sg:orig_category":"Biografer",
    "sg:phone":"+45 75 58 12 02",
    "sg:postcode":"6580",
    "sg:province":"Danmark",
    "wof:name":"Vamdrup Kino",
    "wof:placetype":"venue"
},
  "geometry": {"coordinates":[9.283759,55.425198],"type":"Point"}
}