{
  "type": "Feature",
  "properties": {
    "addr:full":"Smedegade 31 - 33 Horsens Danmark 8700",
    "addr:housenumber":"31 33",
    "addr:postcode":"8700",
    "addr:street":"Smedegade",
    "iso:country":"DK",
    "sg:address":"Smedegade 31 - 33",
    "sg:city":"Horsens",
    "sg:orig_category":"\u00c3\u2020ldreboliger",
    "sg:postcode":"8700",
    "sg:province":"Danmark",
    "wof:name":"\u00c6ldreboliger",
    "wof:placetype":"venue"
},
  "geometry": {"coordinates":[9.8480377197,55.8642921448],"type":"Point"}
}