{
  "type": "Feature",
  "properties": {
    "iso:country":"DK",
    "sg:address":"Vestergade 2",
    "sg:city":"Ejstrupholm",
    "sg:classifiers":[
        {
            "category":"Manufacturing",
            "subcategory":"Tobacco Products",
            "type":"Manufacturing & Wholesale Goods"
        }
    ],
    "sg:phone":"+45 75 77 20 24",
    "sg:postcode":"7361",
    "sg:province":"Danmark",
    "sg:tags":[
        "manufacturer"
    ],
    "wof:name":"Lindberg, B\u00f8rge",
    "wof:placetype":"venue"
},
  "geometry": {"coordinates":[9.2899084091,55.984085083],"type":"Point"}
}