{
  "type": "Feature",
  "properties": {
    "iso:country":"DK",
    "sg:address":"Tv\u00e6rmosevej 10, Ejsing Mark",
    "sg:city":"Vinderup",
    "sg:orig_category":"Varmeforsyning",
    "sg:phone":"+45 97 44 66 61",
    "sg:postcode":"7830",
    "sg:province":"Danmark",
    "wof:name":"Ejsing Fjernvarmeforsyning A.m.b.A.",
    "wof:placetype":"venue"
},
  "geometry": {"coordinates":[8.7796897888,56.482635498],"type":"Point"}
}