{
  "type": "Feature",
  "properties": {
    "iso:country":"DK",
    "sg:address":"Lystrup Stationsvej 7",
    "sg:city":"Lystrup",
    "sg:orig_category":"Grillbarer",
    "sg:phone":"+45 86 22 91 33",
    "sg:postcode":"8520",
    "sg:province":"Danmark",
    "wof:name":"Stationsgrillen",
    "wof:placetype":"venue"
},
  "geometry": {"coordinates":[10.235121727,56.2315979004],"type":"Point"}
}