{
  "type": "Feature",
  "properties": {
    "addr:full":"Trons\u00f8 Parkvej 23 Grindsted Danmark 7200",
    "addr:housenumber":"23",
    "addr:postcode":"7200",
    "addr:street":"Parkvej",
    "iso:country":"DK",
    "sg:address":"Trons\u00f8 Parkvej 23",
    "sg:city":"Grindsted",
    "sg:orig_category":"Foder",
    "sg:postcode":"7200",
    "sg:province":"Danmark",
    "wof:name":"DLG",
    "wof:placetype":"venue"
},
  "geometry": {"coordinates":[8.9206199646,55.7673416138],"type":"Point"}
}