{
  "type": "Feature",
  "properties": {
    "iso:country":"DK",
    "sg:address":"Drejergangen 3 B",
    "sg:city":"Karlslunde",
    "sg:orig_category":"Revisorer",
    "sg:phone":"+45 46 15 05 20",
    "sg:postcode":"2690",
    "sg:province":"Danmark",
    "wof:name":"Johansen, Ea & Jes",
    "wof:placetype":"venue"
},
  "geometry": {"coordinates":[12.2363157272,55.5757484436],"type":"Point"}
}