{
  "type": "Feature",
  "properties": {
    "addr:full":"Steinmannsvej 10 K\u00f8ge Danmark 4600",
    "addr:housenumber":"10",
    "addr:postcode":"4600",
    "addr:street":"Steinmannsvej",
    "iso:country":"DK",
    "sg:address":"Steinmannsvej 10",
    "sg:city":"K\u00f8ge",
    "sg:orig_category":"Alternativ behandling",
    "sg:phone":"+45 56 65 18 54",
    "sg:postcode":"4600",
    "sg:province":"Danmark",
    "wof:name":"Mortensen, Kirsten",
    "wof:placetype":"venue"
},
  "geometry": {"coordinates":[12.1809663773,55.4874534607],"type":"Point"}
}