{
  "type": "Feature",
  "properties": {
    "addr:full":"Hersegade 20, 1. th., Postboks 614 Roskilde Danmark 4000",
    "addr:housenumber":"20 1 th.;614",
    "addr:postcode":"4000",
    "addr:street":"Hersegade",
    "iso:country":"DK",
    "sg:address":"Hersegade 20, 1. th., Postboks 614",
    "sg:city":"Roskilde",
    "sg:orig_category":"Faglige organisationer og foreninger",
    "sg:phone":"+45 46 36 77 25",
    "sg:postcode":"4000",
    "sg:province":"Danmark",
    "wof:name":"Socialp\u00e6dagogernes Landsforbund, Roskilde Amt",
    "wof:placetype":"venue"
},
  "geometry": {"coordinates":[12.0909376144,55.6404838562],"type":"Point"}
}