{
  "type": "Feature",
  "properties": {
    "addr:full":"Kirkegade 21 Gudme Danmark 5884",
    "addr:housenumber":"21",
    "addr:postcode":"5884",
    "addr:street":"Kirkegade",
    "iso:country":"DK",
    "sg:address":"Kirkegade 21",
    "sg:city":"Gudme",
    "sg:orig_category":"Kirker",
    "sg:postcode":"5884",
    "sg:province":"Danmark",
    "wof:name":"Gudme Kirke",
    "wof:placetype":"venue"
},
  "geometry": {"coordinates":[10.7079381943,55.1504821777],"type":"Point"}
}