{
  "type": "Feature",
  "properties": {
    "addr:full":"Fmd.: Henrik \u00d8stergaard, Danmarksgade 12 Kongerslev Danmark 9293",
    "addr:housenumber":"12",
    "addr:postcode":"9293",
    "addr:street":"Henrik;Danmarksgade",
    "iso:country":"DK",
    "sg:address":"Fmd.: Henrik \u00d8stergaard, Danmarksgade 12",
    "sg:city":"Kongerslev",
    "sg:orig_category":"Erhvervs- og brancheforeninger",
    "sg:phone":"+45 98 33 10 01",
    "sg:postcode":"9293",
    "sg:province":"Danmark",
    "wof:name":"Kongerslev Erhvervsforening",
    "wof:placetype":"venue"
},
  "geometry": {"coordinates":[10.1150007248,56.8851165771],"type":"Point"}
}