{
  "type": "Feature",
  "properties": {
    "addr:full":"Marius Jensens Vej 9 Skive Danmark 7800",
    "addr:housenumber":"9",
    "addr:postcode":"7800",
    "addr:street":"Marius Jensens Vej",
    "iso:country":"DK",
    "sg:address":"Marius Jensens Vej 9",
    "sg:city":"Skive",
    "sg:orig_category":"Processtyring",
    "sg:phone":"+45 97 51 29 44",
    "sg:postcode":"7800",
    "sg:province":"Danmark",
    "wof:name":"KC Processtyring ApS",
    "wof:placetype":"venue"
},
  "geometry": {"coordinates":[9.0288639069,56.5620193481],"type":"Point"}
}