{
  "type": "Feature",
  "properties": {
    "addr:full":"L\u00e6hegnet 31 Vestbjerg Danmark 9380",
    "addr:housenumber":"31",
    "addr:postcode":"9380",
    "addr:street":"Laehegnet",
    "iso:country":"DK",
    "sg:address":"L\u00e6hegnet 31",
    "sg:city":"Vestbjerg",
    "sg:orig_category":"Rederier",
    "sg:phone":"+45 98 29 64 29",
    "sg:postcode":"9380",
    "sg:province":"Danmark",
    "wof:name":"Venus, Rederiet",
    "wof:placetype":"venue"
},
  "geometry": {"coordinates":[9.9574556351,57.1312408447],"type":"Point"}
}