{
  "type": "Feature",
  "properties": {
    "addr:full":"Agervej 83, Tj\u00e6reby Kors\u00f8r Danmark 4220",
    "addr:housenumber":"83",
    "addr:postcode":"4220",
    "addr:street":"Agervej",
    "iso:country":"DK",
    "sg:address":"Agervej 83, Tj\u00e6reby",
    "sg:city":"Kors\u00f8r",
    "sg:orig_category":"Fliser",
    "sg:phone":"+45 58 38 08 12",
    "sg:postcode":"4220",
    "sg:province":"Danmark",
    "wof:name":"L\u00e6by Fliser ApS",
    "wof:placetype":"venue"
},
  "geometry": {"coordinates":[11.2130584717,55.3634262085],"type":"Point"}
}