{
  "type": "Feature",
  "properties": {
    "addr:full":"\u00d8stersognsvej 1, Sdr. Nissum Ulfborg Danmark 6990",
    "addr:housenumber":"1",
    "addr:postcode":"6990",
    "addr:street":"Ostersognsvej;Sdr. Nissum",
    "iso:country":"DK",
    "sg:address":"\u00d8stersognsvej 1, Sdr. Nissum",
    "sg:city":"Ulfborg",
    "sg:orig_category":"Brugskunst",
    "sg:phone":"+45 97 49 60 00",
    "sg:postcode":"6990",
    "sg:province":"Danmark",
    "wof:name":"Annex Lys",
    "wof:placetype":"venue"
},
  "geometry": {"coordinates":[8.3210029602,56.2727661133],"type":"Point"}
}