{
  "type": "Feature",
  "properties": {
    "iso:country":"DK",
    "sg:address":"Himmerlandsgade 116",
    "sg:city":"Aars",
    "sg:orig_category":"Supermarkeder",
    "sg:postcode":"9600",
    "sg:province":"Danmark",
    "wof:name":"Aldi Marked",
    "wof:placetype":"venue"
},
  "geometry": {"coordinates":[9.510392189,56.8033256531],"type":"Point"}
}