{
  "type": "Feature",
  "properties": {
    "addr:full":"Fasanvej 10 Slangerup Danmark 3550",
    "addr:housenumber":"10",
    "addr:postcode":"3550",
    "addr:street":"Fasanvej",
    "iso:country":"DK",
    "sg:address":"Fasanvej 10",
    "sg:city":"Slangerup",
    "sg:classifiers":[
        {
            "category":"Utilities",
            "subcategory":"Refuse",
            "type":"Services"
        }
    ],
    "sg:phone":"+45 47 33 50 50",
    "sg:postcode":"3550",
    "sg:province":"Danmark",
    "sg:tags":[
        "catering"
    ],
    "wof:name":"O.G. Catering",
    "wof:placetype":"venue"
},
  "geometry": {"coordinates":[12.1626958847,55.8456497192],"type":"Point"}
}