{
  "type": "Feature",
  "properties": {
    "iso:country":"DK",
    "sg:address":"Stationsvej 19",
    "sg:city":"Gudme",
    "sg:orig_category":"Almen medicin",
    "sg:phone":"+45 62 25 11 25",
    "sg:postcode":"5884",
    "sg:province":"Danmark",
    "wof:name":"M\u00f8rk-Hansen, Jesper",
    "wof:placetype":"venue"
},
  "geometry": {"coordinates":[10.7023935318,55.1537590027],"type":"Point"}
}