{
  "type": "Feature",
  "properties": {
    "addr:full":"Gustav Wieds Vej 7 Grenaa Danmark 8500",
    "addr:housenumber":"7",
    "addr:postcode":"8500",
    "addr:street":"Gustav Wieds Vej",
    "iso:country":"DK",
    "sg:address":"Gustav Wieds Vej 7",
    "sg:city":"Grenaa",
    "sg:orig_category":"Fiskeindustri",
    "sg:phone":"+45 86 32 78 66",
    "sg:postcode":"8500",
    "sg:province":"Danmark",
    "sg:website":"www.dansk-fisk.net",
    "wof:name":"Dansk-Fisk Net",
    "wof:placetype":"venue"
},
  "geometry": {"coordinates":[10.9009370804,56.4094238281],"type":"Point"}
}