{
  "type": "Feature",
  "properties": {
    "addr:full":"Holmeskovvej 6 Fredensborg Danmark 3480",
    "addr:housenumber":"6",
    "addr:postcode":"3480",
    "addr:street":"Holmeskovvej",
    "iso:country":"DK",
    "sg:address":"Holmeskovvej 6",
    "sg:city":"Fredensborg",
    "sg:orig_category":"Psykoterapi",
    "sg:phone":"+45 48 48 36 68",
    "sg:postcode":"3480",
    "sg:province":"Danmark",
    "wof:name":"Bernstein, Irene",
    "wof:placetype":"venue"
},
  "geometry": {"coordinates":[12.4159326553,55.9892349243],"type":"Point"}
}