{
  "type": "Feature",
  "properties": {
    "iso:country":"DK",
    "sg:address":"Dyrehavevej 4",
    "sg:city":"Klampenborg",
    "sg:orig_category":"Boghandlere",
    "sg:phone":"+45 39 64 24 34",
    "sg:postcode":"2930",
    "sg:province":"Danmark",
    "sg:website":"www.parelius.dk",
    "wof:name":"Klampenborg Boghandel og Antikvariat",
    "wof:placetype":"venue"
},
  "geometry": {"coordinates":[12.5873346329,55.7768516541],"type":"Point"}
}