{
  "type": "Feature",
  "properties": {
    "addr:full":"K\u00f8benhavnsvej 33 B Vordingborg Danmark 4760",
    "addr:housenumber":"33 b",
    "addr:postcode":"4760",
    "addr:street":"Kobenhavnsvej",
    "iso:country":"DK",
    "sg:address":"K\u00f8benhavnsvej 33 B",
    "sg:city":"Vordingborg",
    "sg:orig_category":"Fabrikker",
    "sg:phone":"+45 55 37 24 11",
    "sg:postcode":"4760",
    "sg:province":"Danmark",
    "wof:name":"AA Plastpartner A/S",
    "wof:placetype":"venue"
},
  "geometry": {"coordinates":[11.9155750275,55.0110855103],"type":"Point"}
}