{
  "type": "Feature",
  "properties": {
    "addr:full":"Fmd.: Freddy Lauridsen, Nyg\u00e5rdsparken 52 Bramming Danmark 6740",
    "addr:housenumber":"52",
    "addr:postcode":"6740",
    "addr:street":"Nygaardsparken",
    "iso:country":"DK",
    "sg:address":"Fmd.: Freddy Lauridsen, Nyg\u00e5rdsparken 52",
    "sg:city":"Bramming",
    "sg:orig_category":"Hobbybetonede foreninger",
    "sg:phone":"+45 75 17 25 07",
    "sg:postcode":"6740",
    "sg:province":"Danmark",
    "wof:name":"Sch\u00e6ferhundeklubben for Danmark, Kreds 76",
    "wof:placetype":"venue"
},
  "geometry": {"coordinates":[8.6974096298,55.4655303955],"type":"Point"}
}