{
  "type": "Feature",
  "properties": {
    "addr:full":"Koldingvej 151 Vejle Danmark 7100",
    "addr:housenumber":"151",
    "addr:postcode":"7100",
    "addr:street":"Koldingvej",
    "iso:country":"DK",
    "sg:address":"Koldingvej 151",
    "sg:city":"Vejle",
    "sg:orig_category":"Bagere",
    "sg:phone":"+45 75 82 23 23",
    "sg:postcode":"7100",
    "sg:province":"Danmark",
    "wof:name":"Bested's Bageri",
    "wof:placetype":"venue"
},
  "geometry": {"coordinates":[9.5261192322,55.696056366],"type":"Point"}
}