{
  "type": "Feature",
  "properties": {
    "addr:full":"Gyvelvej 8 Vandel Danmark 7184",
    "addr:housenumber":"8",
    "addr:postcode":"7184",
    "addr:street":"Gyvelvej",
    "iso:country":"DK",
    "sg:address":"Gyvelvej 8",
    "sg:city":"Vandel",
    "sg:classifiers":[
        {
            "category":"Personal",
            "subcategory":"Massage",
            "type":"Services"
        }
    ],
    "sg:phone":"+45 75 88 57 50",
    "sg:postcode":"7184",
    "sg:province":"Danmark",
    "wof:name":"Boelsbjerg, Klinik",
    "wof:placetype":"venue"
},
  "geometry": {"coordinates":[9.2239837646,55.7058448792],"type":"Point"}
}