{
  "type": "Feature",
  "properties": {
    "addr:full":"Fmd.: Gitte Vest Barkholt, Kirkev\u00e6nget 23 Horsens Danmark 8700",
    "addr:housenumber":"23",
    "addr:postcode":"8700",
    "addr:street":"Barkholt Kirkevaenget",
    "iso:country":"DK",
    "sg:address":"Fmd.: Gitte Vest Barkholt, Kirkev\u00e6nget 23",
    "sg:city":"Horsens",
    "sg:orig_category":"Faglige organisationer og -foreninger",
    "sg:phone":"+45 75 65 33 16",
    "sg:postcode":"8700",
    "sg:province":"Danmark",
    "sg:website":"www.en.gymfag.dk",
    "wof:name":"Engelskl\u00e6rerforeningen for Gymnasiet og HF",
    "wof:placetype":"venue"
},
  "geometry": {"coordinates":[9.8432445526,55.8621063232],"type":"Point"}
}