{
  "type": "Feature",
  "properties": {
    "addr:full":"V\u00f8lundsvej 24 - 26 Frederikssund Danmark 3600",
    "addr:housenumber":"24 26",
    "addr:postcode":"3600",
    "addr:street":"Volundsvej",
    "iso:country":"DK",
    "sg:address":"V\u00f8lundsvej 24 - 26",
    "sg:city":"Frederikssund",
    "sg:orig_category":"Elektronik",
    "sg:phone":"+45 47 31 48 08",
    "sg:postcode":"3600",
    "sg:province":"Danmark",
    "wof:name":"Zoma Electronic A/S",
    "wof:placetype":"venue"
},
  "geometry": {"coordinates":[12.0588588715,55.8502883911],"type":"Point"}
}