{
  "type": "Feature",
  "properties": {
    "addr:full":"Valby Langgade 32 Valby Danmark 2500",
    "addr:housenumber":"32",
    "addr:postcode":"2500",
    "addr:street":"Valby Langgade",
    "iso:country":"DK",
    "sg:address":"Valby Langgade 32",
    "sg:city":"Valby",
    "sg:orig_category":"Brugskunst",
    "sg:phone":"+45 36 16 61 14",
    "sg:postcode":"2500",
    "sg:province":"Danmark",
    "wof:name":"Trendy",
    "wof:placetype":"venue"
},
  "geometry": {"coordinates":[12.5185756683,55.6666755676],"type":"Point"}
}