{
  "type": "Feature",
  "properties": {
    "addr:full":"Skibelundvej 27 Bjerringbro Danmark 8850",
    "addr:housenumber":"27",
    "addr:postcode":"8850",
    "addr:street":"Skibelundvej",
    "iso:country":"DK",
    "sg:address":"Skibelundvej 27",
    "sg:city":"Bjerringbro",
    "sg:orig_category":"Planteskoler",
    "sg:phone":"+45 87 50 06 00",
    "sg:postcode":"8850",
    "sg:province":"Danmark",
    "sg:website":"www.hoejriis-planteforum.dk",
    "wof:name":"H\u00f8jriis Planteforum",
    "wof:placetype":"venue"
},
  "geometry": {"coordinates":[9.6558933258,56.3645477295],"type":"Point"}
}