{
  "type": "Feature",
  "properties": {
    "addr:full":"Teglv\u00e6rksvej 8 Gudbjerg Danmark 5892",
    "addr:housenumber":"8",
    "addr:postcode":"5892",
    "addr:street":"Teglvaerksvej",
    "iso:country":"DK",
    "sg:address":"Teglv\u00e6rksvej 8",
    "sg:city":"Gudbjerg",
    "sg:orig_category":"Traktorer",
    "sg:phone":"+45 62 25 11 10",
    "sg:postcode":"5892",
    "sg:province":"Danmark",
    "wof:name":"Nielsen ApS, J. Dyhr",
    "wof:placetype":"venue"
},
  "geometry": {"coordinates":[10.6738481522,55.1543464661],"type":"Point"}
}