{
  "type": "Feature",
  "properties": {
    "addr:full":"Helmsvej 4 Silkeborg Danmark 8600",
    "addr:housenumber":"4",
    "addr:postcode":"8600",
    "addr:street":"Helmsvej",
    "iso:country":"DK",
    "sg:address":"Helmsvej 4",
    "sg:city":"Silkeborg",
    "sg:orig_category":"\u00c3\u2020ldreorganisationer og klubber",
    "sg:phone":"+45 86 80 50 80",
    "sg:postcode":"8600",
    "sg:province":"Danmark",
    "wof:name":"Silkeborg Y's Men's Club",
    "wof:placetype":"venue"
},
  "geometry": {"coordinates":[9.5480833054,56.1597251892],"type":"Point"}
}