{
  "type": "Feature",
  "properties": {
    "addr:full":"Hadsundvej 164 Randers Danmark 8900",
    "addr:housenumber":"164",
    "addr:postcode":"8900",
    "addr:street":"Hadsundvej",
    "iso:country":"DK",
    "sg:address":"Hadsundvej 164",
    "sg:city":"Randers",
    "sg:orig_category":"Industrilakering",
    "sg:phone":"+45 86 41 78 88",
    "sg:postcode":"8900",
    "sg:province":"Danmark",
    "sg:website":"www.centerlak.dk",
    "wof:name":"Centerlak ApS",
    "wof:placetype":"venue"
},
  "geometry": {"coordinates":[10.0427360535,56.4839401245],"type":"Point"}
}