{
  "type": "Feature",
  "properties": {
    "iso:country":"DK",
    "sg:address":"M\u00f8lleparken 101",
    "sg:city":"Billund",
    "sg:orig_category":"Malermestre",
    "sg:phone":"+45 75 33 17 71",
    "sg:postcode":"7190",
    "sg:province":"Danmark",
    "wof:name":"Midtjysk Malerfirma A/S",
    "wof:placetype":"venue"
},
  "geometry": {"coordinates":[9.1019935608,55.7295951843],"type":"Point"}
}