{
  "type": "Feature",
  "properties": {
    "addr:full":"Indre Ringvej 175 Fredericia Danmark 7000",
    "addr:housenumber":"175",
    "addr:postcode":"7000",
    "addr:street":"Indre Ringvej",
    "iso:country":"DK",
    "sg:address":"Indre Ringvej 175",
    "sg:city":"Fredericia",
    "sg:orig_category":"Ungdomsklubber",
    "sg:phone":"+45 72 10 63 01",
    "sg:postcode":"7000",
    "sg:province":"Danmark",
    "wof:name":"Klubben",
    "wof:placetype":"venue"
},
  "geometry": {"coordinates":[9.7709884644,55.5784988403],"type":"Point"}
}