{
  "type": "Feature",
  "properties": {
    "addr:full":"Fmd.: Aino Kann Rasmussen, Nyhavn 16 K\u00f8benhavn Danmark 1051",
    "addr:housenumber":"16;1051",
    "addr:street":"Aino Kann;Nyhavn",
    "iso:country":"DK",
    "sg:address":"Fmd.: Aino Kann Rasmussen, Nyhavn 16",
    "sg:city":"K\u00f8benhavn",
    "sg:orig_category":"Kulturelle foreninger",
    "sg:phone":"+45 33 13 44 87",
    "sg:postcode":"1051",
    "sg:province":"Danmark",
    "wof:name":"Faaborg Museums Venner",
    "wof:placetype":"venue"
},
  "geometry": {"coordinates":[12.5919704437,55.679889679],"type":"Point"}
}