{
  "type": "Feature",
  "properties": {
    "addr:full":"Fmd.: Bo Gangelhof, Pr\u00e6stev\u00e6nget 20 Nyborg Danmark 5800",
    "addr:housenumber":"20",
    "addr:postcode":"5800",
    "addr:street":"Praestevaenget",
    "iso:country":"DK",
    "sg:address":"Fmd.: Bo Gangelhof, Pr\u00e6stev\u00e6nget 20",
    "sg:city":"Nyborg",
    "sg:orig_category":"Musik og sang",
    "sg:phone":"+45 65 31 48 75",
    "sg:postcode":"5800",
    "sg:province":"Danmark",
    "wof:name":"Sammus",
    "wof:placetype":"venue"
},
  "geometry": {"coordinates":[10.7923851013,55.3111801147],"type":"Point"}
}