{
  "type": "Feature",
  "properties": {
    "addr:full":"Fmd.: Christian S\u00f8rensen, Alleshavevej 14 Eskebjerg Danmark 4593",
    "addr:housenumber":"14",
    "addr:postcode":"4593",
    "addr:street":"Alleshavevej",
    "iso:country":"DK",
    "sg:address":"Fmd.: Christian S\u00f8rensen, Alleshavevej 14",
    "sg:city":"Eskebjerg",
    "sg:orig_category":"Borger- og beboerforeninger",
    "sg:phone":"+45 59 29 21 47",
    "sg:postcode":"4593",
    "sg:province":"Danmark",
    "wof:name":"Eskebjerg og omegns beboerforening",
    "wof:placetype":"venue"
},
  "geometry": {"coordinates":[11.2637147903,55.7008934021],"type":"Point"}
}