{
  "type": "Feature",
  "properties": {
    "addr:full":"Esbjergvej 42 Kolding Danmark 6000",
    "addr:housenumber":"42",
    "addr:postcode":"6000",
    "addr:street":"Esbjergvej",
    "iso:country":"DK",
    "sg:address":"Esbjergvej 42",
    "sg:city":"Kolding",
    "sg:orig_category":"Plantecentre",
    "sg:phone":"+45 75 53 68 28",
    "sg:postcode":"6000",
    "sg:province":"Danmark",
    "wof:name":"Kolding Plantecenter",
    "wof:placetype":"venue"
},
  "geometry": {"coordinates":[9.4523267746,55.5049095154],"type":"Point"}
}