{
  "type": "Feature",
  "properties": {
    "addr:full":"Si\u00f8v\u00e6nget 21, True Tilst Danmark 8381",
    "addr:housenumber":"21",
    "addr:postcode":"8381",
    "addr:street":"Siovaenget;True",
    "iso:country":"DK",
    "sg:address":"Si\u00f8v\u00e6nget 21, True",
    "sg:city":"Tilst",
    "sg:orig_category":"Murermestre",
    "sg:phone":"+45 86 24 24 45",
    "sg:postcode":"8381",
    "sg:province":"Danmark",
    "wof:name":"MT Murer og Fugeservice",
    "wof:placetype":"venue"
},
  "geometry": {"coordinates":[10.1078147888,56.1882019043],"type":"Point"}
}