{
  "type": "Feature",
  "properties": {
    "addr:full":"Kattegatvej 13 Skagen Danmark 9990",
    "addr:housenumber":"13",
    "addr:postcode":"9990",
    "addr:street":"Kattegatvej",
    "iso:country":"DK",
    "sg:address":"Kattegatvej 13",
    "sg:city":"Skagen",
    "sg:orig_category":"Arbejdsformidling",
    "sg:phone":"+45 96 79 11 00",
    "sg:postcode":"9990",
    "sg:province":"Danmark",
    "wof:name":"Arbejdsformidlingen",
    "wof:placetype":"venue"
},
  "geometry": {"coordinates":[10.5661296844,57.7263298035],"type":"Point"}
}