{
  "type": "Feature",
  "properties": {
    "iso:country":"DK",
    "sg:address":"S\u00f8ndervangsvej 14, Overby",
    "sg:city":"Sj\u00e6llands Odde",
    "sg:orig_category":"Advokater",
    "sg:phone":"+45 59 32 72 01",
    "sg:postcode":"4583",
    "sg:province":"Danmark",
    "wof:name":"Meinertz, Knud Erik",
    "wof:placetype":"venue"
},
  "geometry": {"coordinates":[11.3198680878,55.9799728394],"type":"Point"}
}