{
  "type": "Feature",
  "properties": {
    "addr:full":"Rosen\u00f8rnsgade 6 Randers Danmark 8900",
    "addr:housenumber":"6",
    "addr:postcode":"8900",
    "addr:street":"Rosenornsgade",
    "iso:country":"DK",
    "sg:address":"Rosen\u00f8rnsgade 6",
    "sg:city":"Randers",
    "sg:orig_category":"Revisorer",
    "sg:phone":"+45 86 41 37 44",
    "sg:postcode":"8900",
    "sg:province":"Danmark",
    "wof:name":"Bjerre, M\u00f8ller Petersen & Bering I/S",
    "wof:placetype":"venue"
},
  "geometry": {"coordinates":[10.043513298,56.460559845],"type":"Point"}
}