{
  "type": "Feature",
  "properties": {
    "addr:full":"F\u00f8rslev Kirkestr\u00e6de 12 Haslev Danmark 4690",
    "addr:housenumber":"12",
    "addr:postcode":"4690",
    "iso:country":"DK",
    "sg:address":"F\u00f8rslev Kirkestr\u00e6de 12",
    "sg:city":"Haslev",
    "sg:orig_category":"Kirker",
    "sg:postcode":"4690",
    "sg:province":"Danmark",
    "wof:name":"\u00d8de-F\u00f8rslev Kirke",
    "wof:placetype":"venue"
},
  "geometry": {"coordinates":[11.9678049088,55.3230895996],"type":"Point"}
}