{
  "type": "Feature",
  "properties": {
    "addr:full":"Platanbuen 6 Ballerup Danmark 2750",
    "addr:housenumber":"6",
    "addr:postcode":"2750",
    "addr:street":"Platanbuen",
    "iso:country":"DK",
    "sg:address":"Platanbuen 6",
    "sg:city":"Ballerup",
    "sg:orig_category":"\u00c3\u2020ldreorganisationer og klubber",
    "sg:phone":"+45 44 97 00 91",
    "sg:postcode":"2750",
    "sg:province":"Danmark",
    "wof:name":"Fredagsklubben v. Vestkirken",
    "wof:placetype":"venue"
},
  "geometry": {"coordinates":[12.3458404541,55.72631073],"type":"Point"}
}