{
  "type": "Feature",
  "properties": {
    "iso:country":"DK",
    "sg:address":"Brandevej 10",
    "sg:city":"Aalborg \u00d8",
    "sg:orig_category":"Kollegier",
    "sg:postcode":"9220",
    "sg:province":"Danmark",
    "wof:name":"Aalborg Internationale Kollegium",
    "wof:placetype":"venue"
},
  "geometry": {"coordinates":[9.9776306152,57.0248680115],"type":"Point"}
}