{
  "type": "Feature",
  "properties": {
    "addr:full":"\u00c5toften 59 Esbjerg V Danmark 6710",
    "addr:housenumber":"59",
    "addr:postcode":"6710",
    "addr:street":"Aatoften",
    "iso:country":"DK",
    "sg:address":"\u00c5toften 59",
    "sg:city":"Esbjerg V",
    "sg:orig_category":"Helsekost",
    "sg:phone":"+45 75 15 92 93",
    "sg:postcode":"6710",
    "sg:province":"Danmark",
    "wof:name":"H\u00f8jfeldt, Knud",
    "wof:placetype":"venue"
},
  "geometry": {"coordinates":[8.3957166672,55.5046920776],"type":"Point"}
}