{
  "type": "Feature",
  "properties": {
    "addr:full":"R\u00e5dhuscentret 1 Billund Danmark 7190",
    "addr:housenumber":"1",
    "addr:postcode":"7190",
    "addr:street":"Raadhuscentret",
    "iso:country":"DK",
    "sg:address":"R\u00e5dhuscentret 1",
    "sg:city":"Billund",
    "sg:orig_category":"Dagplejeformidling",
    "sg:phone":"+45 72 13 11 07",
    "sg:postcode":"7190",
    "sg:province":"Danmark",
    "wof:name":"Dagplejeformidlingen",
    "wof:placetype":"venue"
},
  "geometry": {"coordinates":[9.1156101227,55.7308349609],"type":"Point"}
}