{
  "type": "Feature",
  "properties": {
    "addr:full":"\u00d8stergade 32 Egtved Danmark 6040",
    "addr:housenumber":"32",
    "addr:postcode":"6040",
    "addr:street":"Ostergade",
    "iso:country":"DK",
    "sg:address":"\u00d8stergade 32",
    "sg:city":"Egtved",
    "sg:orig_category":"Musikskoler, Kommunale",
    "sg:phone":"+45 75 55 23 41",
    "sg:postcode":"6040",
    "sg:province":"Danmark",
    "wof:name":"Egtved Kommunes Musikskole",
    "wof:placetype":"venue"
},
  "geometry": {"coordinates":[9.3149671555,55.6185417175],"type":"Point"}
}