{
  "type": "Feature",
  "properties": {
    "addr:full":"Fiskerihavnsgade 27 Esbjerg Danmark 6700",
    "addr:housenumber":"27",
    "addr:postcode":"6700",
    "addr:street":"Fiskerihavnsgade",
    "iso:country":"DK",
    "sg:address":"Fiskerihavnsgade 27",
    "sg:city":"Esbjerg",
    "sg:classifiers":[
        {
            "category":"Harbor",
            "type":"Transportation"
        }
    ],
    "sg:phone":"+45 75 13 55 11",
    "sg:postcode":"6700",
    "sg:province":"Danmark",
    "sg:tags":[
        "shipping"
    ],
    "wof:name":"B\u00e6kby Illeborg Shipping",
    "wof:placetype":"venue"
},
  "geometry": {"coordinates":[8.4242095947,55.4765586853],"type":"Point"}
}