{
  "type": "Feature",
  "properties": {
    "addr:full":"Kikkenborg 13 Vejle Danmark 7100",
    "addr:housenumber":"13",
    "addr:postcode":"7100",
    "addr:street":"Kikkenborg",
    "iso:country":"DK",
    "sg:address":"Kikkenborg 13",
    "sg:city":"Vejle",
    "sg:orig_category":"Psykologer, praktiserende",
    "sg:phone":"+45 75 72 18 18",
    "sg:postcode":"7100",
    "sg:province":"Danmark",
    "wof:name":"Psykologisk Klinik",
    "wof:placetype":"venue"
},
  "geometry": {"coordinates":[9.5167169571,55.6917572021],"type":"Point"}
}