{
  "type": "Feature",
  "properties": {
    "iso:country":"DK",
    "sg:address":"Elmeg\u00e5rden 226",
    "sg:city":"Jyderup",
    "sg:orig_category":"Beregnere",
    "sg:phone":"+45 53 47 70 68",
    "sg:postcode":"4450",
    "sg:province":"Danmark",
    "wof:name":"Vestsj\u00e6llands Beregningskontor",
    "wof:placetype":"venue"
},
  "geometry": {"coordinates":[11.402951,55.66024],"type":"Point"}
}