{
  "type": "Feature",
  "properties": {
    "addr:full":"Bredballe Byvej 67 A og B Vejle \u00d8 Danmark 7120",
    "addr:housenumber":"67 a og b",
    "addr:postcode":"7120",
    "addr:street":"Bredballe Byvej",
    "iso:country":"DK",
    "sg:address":"Bredballe Byvej 67 A og B",
    "sg:city":"Vejle \u00d8",
    "sg:orig_category":"Handicapboliger",
    "sg:phone":"+45 75 81 54 33",
    "sg:postcode":"7120",
    "sg:province":"Danmark",
    "wof:name":"Bredballe Bof\u00e6llesskaber",
    "wof:placetype":"venue"
},
  "geometry": {"coordinates":[9.6571302414,55.7422103882],"type":"Point"}
}