{
  "type": "Feature",
  "properties": {
    "addr:full":"Ving\u00e5rdsgade 16 - 20 Aalborg Danmark 9000",
    "addr:housenumber":"16 20",
    "addr:postcode":"9000",
    "addr:street":"Vingaardsgade",
    "iso:country":"DK",
    "sg:address":"Ving\u00e5rdsgade 16 - 20",
    "sg:city":"Aalborg",
    "sg:classifiers":[
        {
            "category":"Communications",
            "type":"Services"
        }
    ],
    "sg:phone":"+45 98 13 19 44",
    "sg:postcode":"9000",
    "sg:province":"Danmark",
    "sg:tags":[
        "og",
        "tv",
        "radio"
    ],
    "wof:name":"Bang & Olufsen",
    "wof:placetype":"venue"
},
  "geometry": {"coordinates":[9.9178524017,57.0473747253],"type":"Point"}
}