{
  "type": "Feature",
  "properties": {
    "addr:full":"N\u00e6stved Landevej 404, Oreby Dalmose Danmark 4261",
    "addr:housenumber":"404",
    "addr:postcode":"4261",
    "addr:street":"Naestved Landevej",
    "iso:country":"DK",
    "sg:address":"N\u00e6stved Landevej 404, Oreby",
    "sg:city":"Dalmose",
    "sg:orig_category":"Murermestre",
    "sg:phone":"+45 58 18 93 85",
    "sg:postcode":"4261",
    "sg:province":"Danmark",
    "wof:name":"Hansen, Kai Faber",
    "wof:placetype":"venue"
},
  "geometry": {"coordinates":[11.423330307,55.2912635803],"type":"Point"}
}