{
  "type": "Feature",
  "properties": {
    "addr:full":"Ventem\u00f8llevej 32 Dianalund Danmark 4293",
    "addr:housenumber":"32",
    "addr:postcode":"4293",
    "addr:street":"Ventemollevej",
    "iso:country":"DK",
    "sg:address":"Ventem\u00f8llevej 32",
    "sg:city":"Dianalund",
    "sg:orig_category":"Plejehjem",
    "sg:phone":"+45 58 26 52 38",
    "sg:postcode":"4293",
    "sg:province":"Danmark",
    "wof:name":"M\u00f8lleparken",
    "wof:placetype":"venue"
},
  "geometry": {"coordinates":[11.4915103912,55.5279006958],"type":"Point"}
}