{
  "type": "Feature",
  "properties": {
    "addr:full":"Hovedgaden 58 Ulstrup Danmark 8860",
    "addr:housenumber":"58",
    "addr:postcode":"8860",
    "addr:street":"Hovedgaden",
    "iso:country":"DK",
    "sg:address":"Hovedgaden 58",
    "sg:city":"Ulstrup",
    "sg:orig_category":"Kommunale folkeskoler",
    "sg:phone":"+45 87 67 52 60",
    "sg:postcode":"8860",
    "sg:province":"Danmark",
    "wof:name":"Ulstrup Skole",
    "wof:placetype":"venue"
},
  "geometry": {"coordinates":[9.7884778976,56.3872909546],"type":"Point"}
}