{
  "type": "Feature",
  "properties": {
    "iso:country":"DK",
    "sg:address":"Vestergade 25",
    "sg:city":"Br\u00f8nderslev",
    "sg:orig_category":"Reklamebureauer",
    "sg:phone":"+45 98 80 08 98",
    "sg:postcode":"9700",
    "sg:province":"Danmark",
    "wof:name":"Paloma Marketing I/S",
    "wof:placetype":"venue"
},
  "geometry": {"coordinates":[9.5455904007,56.1682090759],"type":"Point"}
}