{
  "type": "Feature",
  "properties": {
    "iso:country":"DK",
    "sg:address":"H\u00e5ndv\u00e6rkersvinget 5 ",
    "sg:city":"Tinglev",
    "sg:classifiers":[
        {
            "category":"Real Estate",
            "subcategory":"Surveying",
            "type":"Services"
        }
    ],
    "sg:phone":"+45 74 64 35 05",
    "sg:postcode":"6360",
    "sg:province":"Danmark",
    "sg:tags":[
        "equipment",
        "material",
        "good",
        "-",
        "handling"
    ],
    "wof:name":"KOFF A/S",
    "wof:placetype":"venue"
},
  "geometry": {"coordinates":[9.2476491928,54.9349365234],"type":"Point"}
}