{
  "type": "Feature",
  "properties": {
    "addr:full":"Vistoftvej 36 A, Postboks 3 Sabro Danmark 8471",
    "addr:housenumber":"36 a;3",
    "addr:postcode":"8471",
    "addr:street":"Vistoftvej;Postboks",
    "iso:country":"DK",
    "sg:address":"Vistoftvej 36 A, Postboks 3",
    "sg:city":"Sabro",
    "sg:orig_category":"Integrerede institutioner",
    "sg:phone":"+45 86 94 99 29",
    "sg:postcode":"8471",
    "sg:province":"Danmark",
    "wof:name":"Galaksen, Integreret Inst.",
    "wof:placetype":"venue"
},
  "geometry": {"coordinates":[10.0375204086,56.2109718323],"type":"Point"}
}