{
  "type": "Feature",
  "properties": {
    "addr:full":"R\u00f8dkildevej 42 Vejle Danmark 7100",
    "addr:housenumber":"42",
    "addr:postcode":"7100",
    "addr:street":"Rodkildevej",
    "iso:country":"DK",
    "sg:address":"R\u00f8dkildevej 42",
    "sg:city":"Vejle",
    "sg:orig_category":"Gymnasier og HF-kurser",
    "sg:phone":"+45 75 82 04 88",
    "sg:postcode":"7100",
    "sg:province":"Danmark",
    "wof:name":"R\u00f8dkilde Amtsgymnasium",
    "wof:placetype":"venue"
},
  "geometry": {"coordinates":[9.5576000214,55.7108383179],"type":"Point"}
}