{
  "type": "Feature",
  "properties": {
    "addr:full":"Vesterbrogade 1 A Gilleleje Danmark 3250",
    "addr:housenumber":"1 a",
    "addr:postcode":"3250",
    "addr:street":"Vesterbrogade",
    "iso:country":"DK",
    "sg:address":"Vesterbrogade 1 A",
    "sg:city":"Gilleleje",
    "sg:orig_category":"Supermarkeder",
    "sg:phone":"+45 48 30 11 77",
    "sg:postcode":"3250",
    "sg:province":"Danmark",
    "wof:name":"Irma",
    "wof:placetype":"venue"
},
  "geometry": {"coordinates":[12.3058643341,56.1254425049],"type":"Point"}
}