{
  "type": "Feature",
  "properties": {
    "addr:full":"Slotsvej 15 Gram Danmark 6510",
    "addr:housenumber":"15",
    "addr:postcode":"6510",
    "addr:street":"Slotsvej",
    "iso:country":"DK",
    "sg:address":"Slotsvej 15",
    "sg:city":"Gram",
    "sg:orig_category":"Revisorer",
    "sg:phone":"+45 74 82 27 10",
    "sg:postcode":"6510",
    "sg:province":"Danmark",
    "wof:name":"J. P. Revision",
    "wof:placetype":"venue"
},
  "geometry": {"coordinates":[9.0504236221,55.289100647],"type":"Point"}
}