{
  "type": "Feature",
  "properties": {
    "addr:full":"Mosevej 11, Bred Vissenbjerg Danmark 5492",
    "addr:housenumber":"11",
    "addr:postcode":"5492",
    "addr:street":"Mosevej;Bred",
    "iso:country":"DK",
    "sg:address":"Mosevej 11, Bred",
    "sg:city":"Vissenbjerg",
    "sg:orig_category":"Servicestationer",
    "sg:phone":"+45 65 96 71 28",
    "sg:postcode":"5492",
    "sg:province":"Danmark",
    "wof:name":"Q8 Kildebjerg",
    "wof:placetype":"venue"
},
  "geometry": {"coordinates":[10.1324472427,55.386051178],"type":"Point"}
}