{
  "type": "Feature",
  "properties": {
    "addr:full":"Bentesvej 55 Brabrand Danmark 8220",
    "addr:housenumber":"55",
    "addr:postcode":"8220",
    "addr:street":"Bentesvej",
    "iso:country":"DK",
    "sg:address":"Bentesvej 55",
    "sg:city":"Brabrand",
    "sg:orig_category":"Fodplejere",
    "sg:phone":"+45 86 25 54 01",
    "sg:postcode":"8220",
    "sg:province":"Danmark",
    "wof:name":"S\u00f8rensen, Orla",
    "wof:placetype":"venue"
},
  "geometry": {"coordinates":[10.1365747452,56.1606674194],"type":"Point"}
}