{
  "type": "Feature",
  "properties": {
    "addr:full":"\u00d8sterbrogade 48 Faaborg Danmark 5600",
    "addr:housenumber":"48",
    "addr:postcode":"5600",
    "addr:street":"Osterbrogade",
    "iso:country":"DK",
    "sg:address":"\u00d8sterbrogade 48",
    "sg:city":"Faaborg",
    "sg:orig_category":"Dommerkontorer",
    "sg:phone":"+45 62 61 12 59",
    "sg:postcode":"5600",
    "sg:province":"Danmark",
    "wof:name":"Dommerkontoret",
    "wof:placetype":"venue"
},
  "geometry": {"coordinates":[10.2503709793,55.0911369324],"type":"Point"}
}