{
  "type": "Feature",
  "properties": {
    "addr:full":"Stadionvej 50 Otterup Danmark 5450",
    "addr:housenumber":"50",
    "addr:postcode":"5450",
    "addr:street":"Stadionvej",
    "iso:country":"DK",
    "sg:address":"Stadionvej 50",
    "sg:city":"Otterup",
    "sg:orig_category":"Bowlingcentre",
    "sg:phone":"+45 64 82 23 43",
    "sg:postcode":"5450",
    "sg:province":"Danmark",
    "wof:name":"Otterup Bowling- & Idr\u00e6tscenter",
    "wof:placetype":"venue"
},
  "geometry": {"coordinates":[10.3937206268,55.5066947937],"type":"Point"}
}