{
  "type": "Feature",
  "properties": {
    "addr:full":"Fmd.: Marianne Formsgaard, Reballevej 7, S\u00f8vind Horsens Danmark 8700",
    "addr:housenumber":"7",
    "addr:postcode":"8700",
    "addr:street":"Reballevej;Sovind",
    "iso:country":"DK",
    "sg:address":"Fmd.: Marianne Formsgaard, Reballevej 7, S\u00f8vind",
    "sg:city":"Horsens",
    "sg:orig_category":"Spejderkorps",
    "sg:phone":"+45 75 65 91 83",
    "sg:postcode":"8700",
    "sg:province":"Danmark",
    "wof:name":"KFUM Spejderne, S\u00f8vind Gruppe",
    "wof:placetype":"venue"
},
  "geometry": {"coordinates":[9.8432445526,55.8621063232],"type":"Point"}
}