{
  "type": "Feature",
  "properties": {
    "iso:country":"DK",
    "sg:address":"\u00d8stergade 65 ",
    "sg:city":"Hadsund",
    "sg:classifiers":[
        {
            "category":"Wholesale",
            "subcategory":"Machinery & Supplies",
            "type":"Manufacturing & Wholesale Goods"
        }
    ],
    "sg:phone":"+45 96 52 06 00",
    "sg:postcode":"9560",
    "sg:province":"Danmark",
    "sg:tags":[
        "-",
        "agriculture",
        "equipment"
    ],
    "wof:name":"A/S HADSUND MASKINFORRETNING, JENS L\u00dcBECK",
    "wof:placetype":"venue"
},
  "geometry": {"coordinates":[10.1245126724,56.723575592],"type":"Point"}
}