{
  "type": "Feature",
  "properties": {
    "addr:full":"S\u00f8ndergade 9 Holsted Danmark 6670",
    "addr:housenumber":"9",
    "addr:postcode":"6670",
    "addr:street":"Sondergade",
    "iso:country":"DK",
    "sg:address":"S\u00f8ndergade 9",
    "sg:city":"Holsted",
    "sg:orig_category":"Sko",
    "sg:phone":"+45 75 39 17 01",
    "sg:postcode":"6670",
    "sg:province":"Danmark",
    "wof:name":"No. 9, Boutique",
    "wof:placetype":"venue"
},
  "geometry": {"coordinates":[8.917342186,55.5099525452],"type":"Point"}
}