{
  "type": "Feature",
  "properties": {
    "iso:country":"DK",
    "sg:address":"Hovedgaden 40",
    "sg:city":"Snedsted",
    "sg:orig_category":"Brugsforeninger",
    "sg:phone":"+45 97 93 40 12",
    "sg:postcode":"7752",
    "sg:province":"Danmark",
    "wof:name":"Dagli' Brugsen",
    "wof:placetype":"venue"
},
  "geometry": {"coordinates":[8.5290384293,56.8928146362],"type":"Point"}
}