{
  "type": "Feature",
  "properties": {
    "addr:full":"Mosevej 8 Nakskov Danmark 4900",
    "addr:housenumber":"8",
    "addr:postcode":"4900",
    "addr:street":"Mosevej",
    "iso:country":"DK",
    "sg:address":"Mosevej 8",
    "sg:city":"Nakskov",
    "sg:orig_category":"Musikere",
    "sg:phone":"+45 54 92 63 92",
    "sg:postcode":"4900",
    "sg:province":"Danmark",
    "wof:name":"Nielsen og Lundstr\u00f8m",
    "wof:placetype":"venue"
},
  "geometry": {"coordinates":[11.1611070633,54.847858429],"type":"Point"}
}