{
  "type": "Feature",
  "properties": {
    "addr:full":"H\u00f8jv\u00e6nget 10 Beder Danmark 8330",
    "addr:housenumber":"10",
    "addr:postcode":"8330",
    "addr:street":"Hojvaenget",
    "iso:country":"DK",
    "sg:address":"H\u00f8jv\u00e6nget 10",
    "sg:city":"Beder",
    "sg:orig_category":"Snedkermestre",
    "sg:phone":"+45 86 93 61 06",
    "sg:postcode":"8330",
    "sg:province":"Danmark",
    "wof:name":"Schierup, Gorm",
    "wof:placetype":"venue"
},
  "geometry": {"coordinates":[10.2062501907,56.059173584],"type":"Point"}
}