{
  "type": "Feature",
  "properties": {
    "addr:full":"Rindsvej 2 Randers Danmark 8900",
    "addr:housenumber":"2",
    "addr:postcode":"8900",
    "addr:street":"Rindsvej",
    "iso:country":"DK",
    "sg:address":"Rindsvej 2",
    "sg:city":"Randers",
    "sg:orig_category":"Skolefritidsordninger",
    "sg:phone":"+45 86 41 01 30",
    "sg:postcode":"8900",
    "sg:province":"Danmark",
    "wof:name":"Nyvangs SFO",
    "wof:placetype":"venue"
},
  "geometry": {"coordinates":[10.0240478516,56.4748916626],"type":"Point"}
}