{
  "type": "Feature",
  "properties": {
    "iso:country":"DK",
    "sg:address":"N\u00f8rregade 23",
    "sg:city":"Aalborg",
    "sg:orig_category":"Gaveartikler",
    "sg:phone":"+45 98 77 09 66",
    "sg:postcode":"9000",
    "sg:province":"Danmark",
    "wof:name":"Inside Living / Lab Studio",
    "wof:placetype":"venue"
},
  "geometry": {"coordinates":[9.928024292,57.0465736389],"type":"Point"}
}