{
  "type": "Feature",
  "properties": {
    "iso:country":"DK",
    "sg:address":"Oberst Kochs Alle 11",
    "sg:city":"Kastrup",
    "sg:orig_category":"Snedkermestre",
    "sg:phone":"+45 32 50 02 52",
    "sg:postcode":"2770",
    "sg:province":"Danmark",
    "wof:name":"Louv Snedkeri",
    "wof:placetype":"venue"
},
  "geometry": {"coordinates":[12.6473922729,55.634059906],"type":"Point"}
}