{
  "type": "Feature",
  "properties": {
    "addr:full":"Fmd.: Laue Lund, Toften 15, Hjarup Vamdrup Danmark 6580",
    "addr:housenumber":"15",
    "addr:postcode":"6580",
    "addr:street":"Toften;Hjarup",
    "iso:country":"DK",
    "sg:address":"Fmd.: Laue Lund, Toften 15, Hjarup",
    "sg:city":"Vamdrup",
    "sg:orig_category":"Hobbybetonede foreninger",
    "sg:phone":"+45 75 59 42 60",
    "sg:postcode":"6580",
    "sg:province":"Danmark",
    "wof:name":"Vamdrup og Omegns Biavlerforening",
    "wof:placetype":"venue"
},
  "geometry": {"coordinates":[9.2839107513,55.4266548157],"type":"Point"}
}