{
  "type": "Feature",
  "properties": {
    "iso:country":"DK",
    "sg:address":"Lundsager 20",
    "sg:city":"Ullerslev",
    "sg:orig_category":"Bogtrykkerier",
    "sg:phone":"+45 65 35 15 65",
    "sg:postcode":"5540",
    "sg:province":"Danmark",
    "wof:name":"Ullerslev Tryk ApS",
    "wof:placetype":"venue"
},
  "geometry": {"coordinates":[10.6652326584,55.3582038879],"type":"Point"}
}