{
  "type": "Feature",
  "properties": {
    "iso:country":"DK",
    "sg:address":"Industriv\u00e6nget 12",
    "sg:city":"Havdrup",
    "sg:orig_category":"Maskinfabrikker",
    "sg:phone":"+45 46 18 88 63",
    "sg:postcode":"4622",
    "sg:province":"Danmark",
    "wof:name":"M&M Maskin- & Finmekanik A/S",
    "wof:placetype":"venue"
},
  "geometry": {"coordinates":[12.1229953766,55.5508842468],"type":"Point"}
}