{
  "type": "Feature",
  "properties": {
    "addr:full":"v/ Bent Pedersen, Vestervej 2, \u00d8. L\u00f8gum R\u00f8dekro Danmark 6230",
    "addr:housenumber":"2 o.",
    "addr:postcode":"6230",
    "addr:street":"Vestervej",
    "iso:country":"DK",
    "sg:address":"v/ Bent Pedersen, Vestervej 2, \u00d8. L\u00f8gum",
    "sg:city":"R\u00f8dekro",
    "sg:orig_category":"Redningsberedskab",
    "sg:phone":"+45 74 66 44 80",
    "sg:postcode":"6230",
    "sg:province":"Danmark",
    "wof:name":"\u00d8ster L\u00f8gum Frivillige Brandv\u00e6rn",
    "wof:placetype":"venue"
},
  "geometry": {"coordinates":[-105.85247802729999,33.1596488953],"type":"Point"}
}