{
  "type": "Feature",
  "properties": {
    "iso:country":"DK",
    "sg:address":"Nyelandsvej 13 A",
    "sg:city":"Frederiksberg",
    "sg:orig_category":"Snedkermestre",
    "sg:phone":"+45 38 87 22 10",
    "sg:postcode":"2000",
    "sg:province":"Danmark",
    "wof:name":"ABS B\u00f8dker & Snedkerv\u00e6rksted",
    "wof:placetype":"venue"
},
  "geometry": {"coordinates":[12.5327701569,55.682308197],"type":"Point"}
}