{
  "type": "Feature",
  "properties": {
    "addr:full":"Gjess\u00f8vej 1 Silkeborg Danmark 8600",
    "addr:housenumber":"1",
    "addr:postcode":"8600",
    "addr:street":"Gjessovej",
    "iso:country":"DK",
    "sg:address":"Gjess\u00f8vej 1",
    "sg:city":"Silkeborg",
    "sg:orig_category":"Kiosker",
    "sg:phone":"+45 86 81 36 00",
    "sg:postcode":"8600",
    "sg:province":"Danmark",
    "wof:name":"\u00d8rns\u00f8 D\u00f8gn- og N\u00e6rbutik",
    "wof:placetype":"venue"
},
  "geometry": {"coordinates":[9.530579567,56.1589279175],"type":"Point"}
}