{
  "type": "Feature",
  "properties": {
    "addr:full":"Lundhusvej 20 Vejle Danmark 7100",
    "addr:housenumber":"20",
    "addr:postcode":"7100",
    "addr:street":"Lundhusvej",
    "iso:country":"DK",
    "sg:address":"Lundhusvej 20",
    "sg:city":"Vejle",
    "sg:orig_category":"Arkitekter",
    "sg:phone":"+45 75 82 35 66",
    "sg:postcode":"7100",
    "sg:province":"Danmark",
    "wof:name":"Petersen, Arkitektfirmaet Aage Rossau Lynggaard",
    "wof:placetype":"venue"
},
  "geometry": {"coordinates":[9.5563526154,55.6875762939],"type":"Point"}
}