{
  "type": "Feature",
  "properties": {
    "addr:full":"S\u00f8ndergade 44 Frederikshavn Danmark 9900",
    "addr:housenumber":"44",
    "addr:postcode":"9900",
    "addr:street":"Sondergade",
    "iso:country":"DK",
    "sg:address":"S\u00f8ndergade 44",
    "sg:city":"Frederikshavn",
    "sg:classifiers":[
        {
            "category":"Home & Garden",
            "subcategory":"Home Furnishings",
            "type":"Retail Goods"
        }
    ],
    "sg:phone":"+45 98 42 51 55",
    "sg:postcode":"9900",
    "sg:province":"Danmark",
    "sg:tags":[
        "gardiner"
    ],
    "wof:name":"Jari Gardiner",
    "wof:placetype":"venue"
},
  "geometry": {"coordinates":[10.5309476852,57.4347305298],"type":"Point"}
}