{
  "type": "Feature",
  "properties": {
    "iso:country":"DK",
    "sg:address":"Unionsvej 12",
    "sg:city":"K\u00f8ge",
    "sg:orig_category":"Hydraulik",
    "sg:phone":"+45 56 63 82 96",
    "sg:postcode":"4600",
    "sg:province":"Danmark",
    "wof:name":"Sawo Hydraulic A/S",
    "wof:placetype":"venue"
},
  "geometry": {"coordinates":[12.1944036484,55.5017280579],"type":"Point"}
}