{
  "type": "Feature",
  "properties": {
    "addr:full":"M\u00f8llehaven 6  Jyllinge Danmark 4040",
    "addr:housenumber":"6",
    "addr:postcode":"4040",
    "addr:street":"Mollehaven",
    "iso:country":"DK",
    "sg:address":"M\u00f8llehaven 6 ",
    "sg:city":"Jyllinge",
    "sg:classifiers":[
        {
            "category":"Manufacturing",
            "subcategory":"Lumber",
            "type":"Manufacturing & Wholesale Goods"
        }
    ],
    "sg:phone":"+45 46 73 10 60",
    "sg:postcode":"4040",
    "sg:province":"Danmark",
    "sg:tags":[
        "wood"
    ],
    "wof:name":"UNIVERSAL FASTG\u00d8RELSE A/S",
    "wof:placetype":"venue"
},
  "geometry": {"coordinates":[12.1287059784,55.7579498291],"type":"Point"}
}