{
  "type": "Feature",
  "properties": {
    "addr:full":"Ingstrup Alle 28 B Kastrup Danmark 2770",
    "addr:housenumber":"28 b",
    "addr:postcode":"2770",
    "addr:street":"Ingstrup Alle",
    "iso:country":"DK",
    "sg:address":"Ingstrup Alle 28 B",
    "sg:city":"Kastrup",
    "sg:orig_category":"Vagtbureauer",
    "sg:phone":"+45 21 25 15 43",
    "sg:postcode":"2770",
    "sg:province":"Danmark",
    "sg:website":"www.sikkerhedsraadgivning.dk",
    "wof:name":"T\u00e5rnby Vagt & Alarm",
    "wof:placetype":"venue"
},
  "geometry": {"coordinates":[12.6029071808,55.614906311],"type":"Point"}
}