{
  "type": "Feature",
  "properties": {
    "addr:full":"Kirkealle 22 Gram Danmark 6510",
    "addr:housenumber":"22",
    "addr:postcode":"6510",
    "addr:street":"Kirkealle",
    "iso:country":"DK",
    "sg:address":"Kirkealle 22",
    "sg:city":"Gram",
    "sg:orig_category":"Plejehjem",
    "sg:phone":"+45 73 82 12 00",
    "sg:postcode":"6510",
    "sg:province":"Danmark",
    "wof:name":"Engparken Plejecenter",
    "wof:placetype":"venue"
},
  "geometry": {"coordinates":[9.0452928543,55.2891082764],"type":"Point"}
}