{
  "type": "Feature",
  "properties": {
    "iso:country":"DK",
    "sg:address":"Ilsigvej 21",
    "sg:city":"Blokhus",
    "sg:classifiers":[
        {
            "category":"Banks & Credit Unions",
            "subcategory":"Financial Services",
            "type":"Services"
        }
    ],
    "sg:phone":"+45 99 44 44 44",
    "sg:postcode":"9492",
    "sg:province":"Danmark",
    "sg:tags":[
        "banking",
        "finance",
        "insurance"
    ],
    "wof:name":"SOL OG STRAND HOLDING A/S",
    "wof:placetype":"venue"
},
  "geometry": {"coordinates":[9.6189393997,57.2478713989],"type":"Point"}
}