{
  "type": "Feature",
  "properties": {
    "iso:country":"DK",
    "sg:address":"Gothersgade 31 - 33",
    "sg:city":"Fredericia",
    "sg:classifiers":[
        {
            "category":"Banks & Credit Unions",
            "subcategory":"Bank",
            "type":"Services"
        }
    ],
    "sg:phone":"+45 75 93 07 11",
    "sg:postcode":"7000",
    "sg:province":"Danmark",
    "sg:tags":[
        "banker"
    ],
    "wof:name":"Sydbank",
    "wof:placetype":"venue"
},
  "geometry": {"coordinates":[9.7567892075,55.5649414062],"type":"Point"}
}