{
  "type": "Feature",
  "properties": {
    "iso:country":"DK",
    "sg:address":"Tv\u00e6rgade 4 - 6",
    "sg:city":"Silkeborg",
    "sg:classifiers":[
        {
            "category":"Restaurant",
            "type":"Food & Drink"
        }
    ],
    "sg:phone":"+45 86 82 93 20",
    "sg:postcode":"8600",
    "sg:province":"Danmark",
    "sg:website":"www.restaurant-hjorten.dk",
    "wof:name":"Hjorten & Papa Jones",
    "wof:placetype":"venue"
},
  "geometry": {"coordinates":[9.5472288132,56.1683006287],"type":"Point"}
}