{
  "type": "Feature",
  "properties": {
    "addr:full":"Industrivej 3  Fredericia Danmark 7000",
    "addr:housenumber":"3",
    "addr:postcode":"7000",
    "addr:street":"Industrivej",
    "iso:country":"DK",
    "sg:address":"Industrivej 3 ",
    "sg:city":"Fredericia",
    "sg:classifiers":[
        {
            "category":"Professional",
            "subcategory":"Engineering",
            "type":"Services"
        }
    ],
    "sg:phone":"+45 75 92 47 00",
    "sg:postcode":"7000",
    "sg:province":"Danmark",
    "sg:tags":[
        "machine",
        "-",
        "mechanical"
    ],
    "wof:name":"HOMA MASKINFABRIK A/S",
    "wof:placetype":"venue"
},
  "geometry": {"coordinates":[9.7659015656,55.590045929],"type":"Point"}
}