{
  "type": "Feature",
  "properties": {
    "iso:country":"DK",
    "sg:address":"\u00c5v\u00e6nget 9",
    "sg:city":"K\u00f8ge",
    "sg:orig_category":"Blikkenslagere",
    "sg:phone":"+45 56 65 93 03",
    "sg:postcode":"4600",
    "sg:province":"Danmark",
    "sg:website":"www.john-lund-larsen.dk",
    "wof:name":"John Lund Larsen VVS/Gas ApS",
    "wof:placetype":"venue"
},
  "geometry": {"coordinates":[43.365791,42.31152],"type":"Point"}
}