{
  "type": "Feature",
  "properties": {
    "iso:country":"DK",
    "sg:address":"Naverland 22 ",
    "sg:city":"Glostrup",
    "sg:classifiers":[
        {
            "category":"Sports & Exercise",
            "subcategory":"Playing Field",
            "type":"Entertainment"
        }
    ],
    "sg:phone":"+45 43 27 80 00",
    "sg:postcode":"2600",
    "sg:province":"Danmark",
    "sg:tags":[
        "game"
    ],
    "wof:name":"POBRA A/S",
    "wof:placetype":"venue"
},
  "geometry": {"coordinates":[12.3780460358,55.6804351807],"type":"Point"}
}