{
  "type": "Feature",
  "properties": {
    "iso:country":"DK",
    "sg:address":"Godth\u00e5bsvej 129",
    "sg:city":"Frederiksberg",
    "sg:orig_category":"Tagkonstruktioner",
    "sg:phone":"+45 38 19 36 00",
    "sg:postcode":"2000",
    "sg:province":"Danmark",
    "wof:name":"Mikkelsen S\u00f8rensen A/S",
    "wof:placetype":"venue"
},
  "geometry": {"coordinates":[12.5173921585,55.6900177002],"type":"Point"}
}