{
  "type": "Feature",
  "properties": {
    "iso:country":"DK",
    "sg:address":"\u00d8ster\u00e5gade 6",
    "sg:city":"Aalborg",
    "sg:orig_category":"Boghandlere",
    "sg:phone":"+45 98 12 75 00",
    "sg:postcode":"9000",
    "sg:province":"Danmark",
    "wof:name":"Gad, G. E. C.",
    "wof:placetype":"venue"
},
  "geometry": {"coordinates":[9.9211359024,57.048160553],"type":"Point"}
}