{
  "type": "Feature",
  "properties": {
    "addr:full":"\u00d8stervangs Alle 66 Auning Danmark 8963",
    "addr:housenumber":"66",
    "addr:postcode":"8963",
    "addr:street":"Ostervangs Alle",
    "iso:country":"DK",
    "sg:address":"\u00d8stervangs Alle 66",
    "sg:city":"Auning",
    "sg:orig_category":"Vinduespolering",
    "sg:phone":"+45 86 48 39 56",
    "sg:postcode":"8963",
    "sg:province":"Danmark",
    "wof:name":"\u00c5bo Vinduespolering",
    "wof:placetype":"venue"
},
  "geometry": {"coordinates":[10.389834404,56.4316253662],"type":"Point"}
}