{
  "type": "Feature",
  "properties": {
    "iso:country":"DK",
    "sg:address":"Holsted Park 2",
    "sg:city":"N\u00e6stved",
    "sg:orig_category":"Autoforhandlere",
    "sg:phone":"+45 55 72 14 14",
    "sg:postcode":"4700",
    "sg:province":"Danmark",
    "wof:name":"Selandia Automobiler A/S",
    "wof:placetype":"venue"
},
  "geometry": {"coordinates":[11.7752733231,55.249458313],"type":"Point"}
}