{
  "type": "Feature",
  "properties": {
    "addr:full":"Sogneg\u00e5rdsvej 1, Husby Ulfborg Danmark 6990",
    "addr:housenumber":"1",
    "addr:postcode":"6990",
    "addr:street":"Sognegaardsvej",
    "iso:country":"DK",
    "sg:address":"Sogneg\u00e5rdsvej 1, Husby",
    "sg:city":"Ulfborg",
    "sg:orig_category":"Billedhuggere",
    "sg:phone":"+45 97 49 56 03",
    "sg:postcode":"6990",
    "sg:province":"Danmark",
    "sg:website":"www.voldmester.dk",
    "wof:name":"Henrik Vilhelm Voldmester",
    "wof:placetype":"venue"
},
  "geometry": {"coordinates":[8.321003,56.272766],"type":"Point"}
}