{
  "type": "Feature",
  "properties": {
    "iso:country":"DK",
    "sg:address":"Leder: Anna Marie Olesen, Ryesgade 52",
    "sg:city":"Aalborg",
    "sg:orig_category":"\u00c3\u02dcvrig fritidsundervisning",
    "sg:phone":"+45 98 16 70 77",
    "sg:postcode":"9000",
    "sg:province":"Danmark",
    "wof:name":"rytmiske dag- og aftenskole, Den",
    "wof:placetype":"venue"
},
  "geometry": {"coordinates":[9.9162902832,57.0493545532],"type":"Point"}
}