{
  "type": "Feature",
  "properties": {
    "iso:country":"DK",
    "sg:address":"Torvet 19",
    "sg:city":"K\u00f8ge",
    "sg:orig_category":"Revisorer",
    "sg:phone":"+45 56 65 52 52",
    "sg:postcode":"4600",
    "sg:province":"Danmark",
    "wof:name":"Gyrn, Lops, Brandt Statsautoriseret Revisionsaktieselskab",
    "wof:placetype":"venue"
},
  "geometry": {"coordinates":[10.6905498505,59.8094596863],"type":"Point"}
}