{
  "type": "Feature",
  "properties": {
    "iso:country":"DK",
    "sg:address":"Store Torv 2",
    "sg:city":"Thisted",
    "sg:orig_category":"Optikere",
    "sg:phone":"+45 97 92 10 32",
    "sg:postcode":"7700",
    "sg:province":"Danmark",
    "wof:name":"Wadmann Ure og Optik",
    "wof:placetype":"venue"
},
  "geometry": {"coordinates":[8.6913604736,56.9546585083],"type":"Point"}
}