{
  "type": "Feature",
  "properties": {
    "addr:full":"Str\u00e6det 16, Tejn Allinge Danmark 3770",
    "addr:housenumber":"16",
    "addr:postcode":"3770",
    "addr:street":"Straedet;Tejn",
    "iso:country":"DK",
    "sg:address":"Str\u00e6det 16, Tejn",
    "sg:city":"Allinge",
    "sg:orig_category":"Murermestre",
    "sg:phone":"+45 56 48 13 40",
    "sg:postcode":"3770",
    "sg:province":"Danmark",
    "wof:name":"Sommers Murerforretning",
    "wof:placetype":"venue"
},
  "geometry": {"coordinates":[14.7998552322,55.2743835449],"type":"Point"}
}