{
  "type": "Feature",
  "properties": {
    "addr:full":"N\u00f8rre Torv 1, Esperg\u00e6rde Centret Esperg\u00e6rde Danmark 3060",
    "addr:housenumber":"1",
    "addr:postcode":"3060",
    "addr:street":"Norre Torv",
    "iso:country":"DK",
    "sg:address":"N\u00f8rre Torv 1, Esperg\u00e6rde Centret",
    "sg:city":"Esperg\u00e6rde",
    "sg:classifiers":[
        {
            "category":"Banks & Credit Unions",
            "subcategory":"Bank",
            "type":"Services"
        }
    ],
    "sg:phone":"+45 49 17 64 00",
    "sg:postcode":"3060",
    "sg:province":"Danmark",
    "sg:tags":[
        "banker"
    ],
    "sg:website":"www.danskebank.dk",
    "wof:name":"Danske Bank",
    "wof:placetype":"venue"
},
  "geometry": {"coordinates":[11.65124,47.839062],"type":"Point"}
}