{
  "type": "Feature",
  "properties": {
    "iso:country":"DK",
    "sg:address":"Vindebjergvej 16 A, Harndrup",
    "sg:city":"Harndrup",
    "sg:orig_category":"Betonvarefabrikker",
    "sg:phone":"+45 64 88 13 86",
    "sg:postcode":"5463",
    "sg:province":"Danmark",
    "sg:website":"www.ibf.dk",
    "wof:name":"IBF Harndrup",
    "wof:placetype":"venue"
},
  "geometry": {"coordinates":[10.02055,55.465378],"type":"Point"}
}