{
  "type": "Feature",
  "properties": {
    "addr:full":"Sognepr\u00e6st: Jakob Grandjean (K/B), Fodbygade 39, Fodby N\u00e6stved Danmark 4700",
    "addr:housenumber":"39",
    "addr:postcode":"4700",
    "addr:street":"Fodbygade",
    "iso:country":"DK",
    "sg:address":"Sognepr\u00e6st: Jakob Grandjean (K/B), Fodbygade 39, Fodby",
    "sg:city":"N\u00e6stved",
    "sg:orig_category":"Kirkesogne",
    "sg:phone":"+45 55 44 70 75",
    "sg:postcode":"4700",
    "sg:province":"Danmark",
    "sg:website":"www.folkekirken.dk/sogn/vallensved",
    "wof:name":"Vallensved sogn",
    "wof:placetype":"venue"
},
  "geometry": {"coordinates":[11.7542486191,55.2315444946],"type":"Point"}
}