{
  "type": "Feature",
  "properties": {
    "addr:full":"Lunikvej 5-7 Greve Danmark 2670",
    "addr:housenumber":"5-7",
    "addr:postcode":"2670",
    "addr:street":"Lunikvej",
    "iso:country":"DK",
    "sg:address":"Lunikvej 5-7",
    "sg:city":"Greve",
    "sg:orig_category":"Video- og TV-produktion",
    "sg:phone":"+45 43 90 55 10",
    "sg:postcode":"2670",
    "sg:province":"Danmark",
    "sg:website":"www.toft-fischer.dk",
    "wof:name":"Toft & Fischer A/S",
    "wof:placetype":"venue"
},
  "geometry": {"coordinates":[12.2967739105,55.6054725647],"type":"Point"}
}