{
  "type": "Feature",
  "properties": {
    "addr:full":"Silkeborgvej 39 \u00c5rhus C Danmark 8000",
    "addr:housenumber":"39",
    "addr:postcode":"8000",
    "addr:street":"Silkeborgvej",
    "iso:country":"DK",
    "sg:address":"Silkeborgvej 39",
    "sg:city":"\u00c5rhus C",
    "sg:orig_category":"Senge",
    "sg:phone":"+45 86 75 38 22",
    "sg:postcode":"8000",
    "sg:province":"Danmark",
    "wof:name":"Jensen Senge",
    "wof:placetype":"venue"
},
  "geometry": {"coordinates":[4.717400074,49.7588005066],"type":"Point"}
}