{
  "type": "Feature",
  "properties": {
    "addr:full":"Havblik 3 Asaa Danmark 9340",
    "addr:housenumber":"3",
    "addr:postcode":"9340",
    "addr:street":"Havblik",
    "iso:country":"DK",
    "sg:address":"Havblik 3",
    "sg:city":"Asaa",
    "sg:orig_category":"Scootere",
    "sg:phone":"+45 98 85 19 40",
    "sg:postcode":"9340",
    "sg:province":"Danmark",
    "sg:website":"www.auto-nord.dk",
    "wof:name":"Asaa Auto- & Karosseriv\u00e6rksted",
    "wof:placetype":"venue"
},
  "geometry": {"coordinates":[10.3929233551,57.1403808594],"type":"Point"}
}