{
  "type": "Feature",
  "properties": {
    "addr:full":"N\u00f8rregade 63 Esbjerg Danmark 6700",
    "addr:housenumber":"63",
    "addr:postcode":"6700",
    "addr:street":"Norregade",
    "iso:country":"DK",
    "sg:address":"N\u00f8rregade 63",
    "sg:city":"Esbjerg",
    "sg:orig_category":"Offentlige sygehuse",
    "sg:phone":"+45 79 18 27 90",
    "sg:postcode":"6700",
    "sg:province":"Danmark",
    "wof:name":"Sct. Josephs Hospital",
    "wof:placetype":"venue"
},
  "geometry": {"coordinates":[8.4487409592,55.4698753357],"type":"Point"}
}