{
  "type": "Feature",
  "properties": {
    "addr:full":"Kongensgade 13 Marstal Danmark 5960",
    "addr:housenumber":"13",
    "addr:postcode":"5960",
    "addr:street":"Kongensgade",
    "iso:country":"DK",
    "sg:address":"Kongensgade 13",
    "sg:city":"Marstal",
    "sg:classifiers":[
        {
            "category":"Restaurant",
            "type":"Food & Drink"
        }
    ],
    "sg:phone":"+45 62 53 15 26",
    "sg:postcode":"5960",
    "sg:province":"Danmark",
    "wof:name":"Minde, Restaurant",
    "wof:placetype":"venue"
},
  "geometry": {"coordinates":[10.519367218,54.8555107117],"type":"Point"}
}