{
  "type": "Feature",
  "properties": {
    "addr:full":"Asbovej 23, L\u00e6borg Vejen Danmark 6600",
    "addr:housenumber":"23",
    "addr:postcode":"6600",
    "addr:street":"Asbovej;Laeborg",
    "iso:country":"DK",
    "sg:address":"Asbovej 23, L\u00e6borg",
    "sg:city":"Vejen",
    "sg:orig_category":"Vinduespolering",
    "sg:phone":"+45 75 36 88 97",
    "sg:postcode":"6600",
    "sg:province":"Danmark",
    "wof:name":"L\u00e6borg Vinduespolering",
    "wof:placetype":"venue"
},
  "geometry": {"coordinates":[9.1396121979,55.4778175354],"type":"Point"}
}