{
  "type": "Feature",
  "properties": {
    "addr:full":"Gammel Lundtoftevej 24, 1. Kongens Lyngby Danmark 2800",
    "addr:housenumber":"24 1",
    "addr:postcode":"2800",
    "addr:street":"Gammel Lundtoftevej",
    "iso:country":"DK",
    "sg:address":"Gammel Lundtoftevej 24, 1.",
    "sg:city":"Kongens Lyngby",
    "sg:orig_category":"Revisorer",
    "sg:phone":"+45 45 87 81 00",
    "sg:postcode":"2800",
    "sg:province":"Danmark",
    "wof:name":"Revisionsfirmaet Helge Bom A/S",
    "wof:placetype":"venue"
},
  "geometry": {"coordinates":[12.5039253235,55.7761383057],"type":"Point"}
}