{
  "type": "Feature",
  "properties": {
    "addr:full":"Sct. Mathias Gade 30 Viborg Danmark 8800",
    "addr:housenumber":"30",
    "addr:postcode":"8800",
    "addr:street":"Sct. Mathias Gade",
    "iso:country":"DK",
    "sg:address":"Sct. Mathias Gade 30",
    "sg:city":"Viborg",
    "sg:classifiers":[
        {
            "category":"Communications",
            "type":"Services"
        }
    ],
    "sg:phone":"+45 87 25 09 94",
    "sg:postcode":"8800",
    "sg:province":"Danmark",
    "sg:tags":[
        "og",
        "tv",
        "radio"
    ],
    "wof:name":"Bang & Olufsen",
    "wof:placetype":"venue"
},
  "geometry": {"coordinates":[9.4042797089,56.4493904114],"type":"Point"}
}