{
  "type": "Feature",
  "properties": {
    "addr:full":"Knud Den Stores Vej 35 Roskilde Danmark 4000",
    "addr:housenumber":"35",
    "addr:postcode":"4000",
    "addr:street":"Knud Den Stores Vej",
    "iso:country":"DK",
    "sg:address":"Knud Den Stores Vej 35",
    "sg:city":"Roskilde",
    "sg:classifiers":[
        {
            "category":"Banks & Credit Unions",
            "subcategory":"Bank",
            "type":"Services"
        }
    ],
    "sg:phone":"+45 46 35 96 40",
    "sg:postcode":"4000",
    "sg:province":"Danmark",
    "sg:tags":[
        "banker"
    ],
    "wof:name":"Roskilde Bank A/S",
    "wof:placetype":"venue"
},
  "geometry": {"coordinates":[12.0899658203,55.6489334106],"type":"Point"}
}