{
  "type": "Feature",
  "properties": {
    "addr:full":"S\u00e6beholmsvej 50 Valby Danmark 2500",
    "addr:housenumber":"50",
    "addr:postcode":"2500",
    "addr:street":"Saebeholmsvej",
    "iso:country":"DK",
    "sg:address":"S\u00e6beholmsvej 50",
    "sg:city":"Valby",
    "sg:orig_category":"Skilte",
    "sg:phone":"+45 38 71 21 00",
    "sg:postcode":"2500",
    "sg:province":"Danmark",
    "wof:name":"Giesel, Susanne",
    "wof:placetype":"venue"
},
  "geometry": {"coordinates":[12.490776062,55.6769256592],"type":"Point"}
}