{
  "type": "Feature",
  "properties": {
    "addr:full":"Englandsvej 1 Hammel Danmark 8450",
    "addr:housenumber":"1",
    "addr:postcode":"8450",
    "addr:street":"Englandsvej",
    "iso:country":"DK",
    "sg:address":"Englandsvej 1",
    "sg:city":"Hammel",
    "sg:orig_category":"Autoreparation og -service",
    "sg:phone":"+45 86 96 90 00",
    "sg:postcode":"8450",
    "sg:province":"Danmark",
    "wof:name":"S\u00f8rensen, Kurt Gade",
    "wof:placetype":"venue"
},
  "geometry": {"coordinates":[9.856347084,56.2366333008],"type":"Point"}
}