{
  "type": "Feature",
  "properties": {
    "addr:full":"Fmd.: Ronald Frederiksen, Havl\u00f8kkevej 26 Stokkemarke Danmark 4952",
    "addr:housenumber":"26",
    "addr:postcode":"4952",
    "addr:street":"Havlokkevej",
    "iso:country":"DK",
    "sg:address":"Fmd.: Ronald Frederiksen, Havl\u00f8kkevej 26",
    "sg:city":"Stokkemarke",
    "sg:orig_category":"Kulturelle foreninger",
    "sg:phone":"+45 54 71 16 61",
    "sg:postcode":"4952",
    "sg:province":"Danmark",
    "wof:name":"Kunstforeningen Ravnen",
    "wof:placetype":"venue"
},
  "geometry": {"coordinates":[11.3643407822,54.8373832703],"type":"Point"}
}