{
  "type": "Feature",
  "properties": {
    "addr:full":"Tyndeleddet 5, Voerladeg\u00e5rd Skanderborg Danmark 8660",
    "addr:housenumber":"5",
    "addr:postcode":"8660",
    "addr:street":"Tyndeleddet",
    "iso:country":"DK",
    "sg:address":"Tyndeleddet 5, Voerladeg\u00e5rd",
    "sg:city":"Skanderborg",
    "sg:orig_category":"Kommunale folkeskoler",
    "sg:phone":"+45 75 78 22 74",
    "sg:postcode":"8660",
    "sg:province":"Danmark",
    "wof:name":"Voerladeg\u00e5rd Skole",
    "wof:placetype":"venue"
},
  "geometry": {"coordinates":[9.929974556,56.0380249023],"type":"Point"}
}