{
  "type": "Feature",
  "properties": {
    "addr:full":"S\u00f8vangsvej 3 Solbjerg Danmark 8355",
    "addr:housenumber":"3",
    "addr:postcode":"8355",
    "addr:street":"Sovangsvej",
    "iso:country":"DK",
    "sg:address":"S\u00f8vangsvej 3",
    "sg:city":"Solbjerg",
    "sg:orig_category":"Fabrikker",
    "sg:phone":"+45 86 92 75 55",
    "sg:postcode":"8355",
    "sg:province":"Danmark",
    "wof:name":"M. H. Polsterm\u00f8bler A/S",
    "wof:placetype":"venue"
},
  "geometry": {"coordinates":[10.077586174,56.0463867188],"type":"Point"}
}