{
  "type": "Feature",
  "properties": {
    "addr:full":"Arnold Nielsens Boulevard 126 Hvidovre Danmark 2650",
    "addr:housenumber":"126",
    "addr:postcode":"2650",
    "addr:street":"Arnold Nielsens Boulevard",
    "iso:country":"DK",
    "sg:address":"Arnold Nielsens Boulevard 126",
    "sg:city":"Hvidovre",
    "sg:orig_category":"Diners transportables",
    "sg:phone":"+45 36 77 87 01",
    "sg:postcode":"2650",
    "sg:province":"Danmark",
    "wof:name":"Clemmes Diner Transportable",
    "wof:placetype":"venue"
},
  "geometry": {"coordinates":[12.4679956436,55.6363067627],"type":"Point"}
}