{
  "type": "Feature",
  "properties": {
    "addr:full":"Vestergade 28 Toftlund Danmark 6520",
    "addr:housenumber":"28",
    "addr:postcode":"6520",
    "addr:street":"Vestergade",
    "iso:country":"DK",
    "sg:address":"Vestergade 28",
    "sg:city":"Toftlund",
    "sg:orig_category":"EDB - udstyr",
    "sg:phone":"+45 74 83 13 52",
    "sg:postcode":"6520",
    "sg:province":"Danmark",
    "wof:name":"Rolskov El",
    "wof:placetype":"venue"
},
  "geometry": {"coordinates":[9.0598812103,55.193031311],"type":"Point"}
}