{
  "type": "Feature",
  "properties": {
    "iso:country":"DK",
    "sg:address":"Torvegade 7",
    "sg:city":"Bogense",
    "sg:classifiers":[
        {
            "category":"Communications",
            "type":"Services"
        }
    ],
    "sg:phone":"+45 64 81 17 88",
    "sg:postcode":"5400",
    "sg:province":"Danmark",
    "sg:tags":[
        "og",
        "tv",
        "radio"
    ],
    "wof:name":"Abildg\u00e5rds Radio",
    "wof:placetype":"venue"
},
  "geometry": {"coordinates":[10.088889122,55.5661430359],"type":"Point"}
}