{
  "type": "Feature",
  "properties": {
    "iso:country":"DK",
    "sg:address":"Hvidk\u00e6rvej 27, H\u00f8jme",
    "sg:city":"Odense SV",
    "sg:orig_category":"Spedition",
    "sg:phone":"+45 66 17 16 16",
    "sg:postcode":"5250",
    "sg:province":"Danmark",
    "wof:name":"Scancon A/S",
    "wof:placetype":"venue"
},
  "geometry": {"coordinates":[10.3153953552,55.3362998962],"type":"Point"}
}