{
  "type": "Feature",
  "properties": {
    "addr:full":"Gryderupvej 109, Gryderup Boeslunde Danmark 4242",
    "addr:housenumber":"109",
    "addr:postcode":"4242",
    "addr:street":"Gryderupvej",
    "iso:country":"DK",
    "sg:address":"Gryderupvej 109, Gryderup",
    "sg:city":"Boeslunde",
    "sg:orig_category":"Autoreparation og -service",
    "sg:phone":"+45 58 14 05 56",
    "sg:postcode":"4242",
    "sg:province":"Danmark",
    "wof:name":"Frandsen Biler",
    "wof:placetype":"venue"
},
  "geometry": {"coordinates":[11.2663583755,55.3043022156],"type":"Point"}
}