{
  "type": "Feature",
  "properties": {
    "addr:full":"Skelsg\u00e5rdvej 2, Hjerk Roslev Danmark 7870",
    "addr:housenumber":"2",
    "addr:postcode":"7870",
    "addr:street":"Skelsgaardvej;Hjerk",
    "iso:country":"DK",
    "sg:address":"Skelsg\u00e5rdvej 2, Hjerk",
    "sg:city":"Roslev",
    "sg:orig_category":"Forsamlingshuse",
    "sg:phone":"+45 97 57 91 67",
    "sg:postcode":"7870",
    "sg:province":"Danmark",
    "wof:name":"Hjerk Forsamlingshus",
    "wof:placetype":"venue"
},
  "geometry": {"coordinates":[8.8715353012,56.7570304871],"type":"Point"}
}