{
  "type": "Feature",
  "properties": {
    "addr:full":"Rosenkildevej 92 Slagelse Danmark 4200",
    "addr:housenumber":"92",
    "addr:postcode":"4200",
    "addr:street":"Rosenkildevej",
    "iso:country":"DK",
    "sg:address":"Rosenkildevej 92",
    "sg:city":"Slagelse",
    "sg:orig_category":"Ungdomsklubber",
    "sg:phone":"+45 58 52 97 79",
    "sg:postcode":"4200",
    "sg:province":"Danmark",
    "wof:name":"Ungdomscaf\u00e9en Rosenkildeg\u00e5rden",
    "wof:placetype":"venue"
},
  "geometry": {"coordinates":[11.3646059036,55.4186477661],"type":"Point"}
}