{
  "type": "Feature",
  "properties": {
    "addr:full":"Stuebjerg Alle 19 Tisvildeleje Danmark 3220",
    "addr:housenumber":"19",
    "addr:postcode":"3220",
    "addr:street":"Stuebjerg Alle",
    "iso:country":"DK",
    "sg:address":"Stuebjerg Alle 19",
    "sg:city":"Tisvildeleje",
    "sg:orig_category":"Hestepensioner",
    "sg:phone":"+45 48 70 86 27",
    "sg:postcode":"3220",
    "sg:province":"Danmark",
    "wof:name":"Stuebjerggaard",
    "wof:placetype":"venue"
},
  "geometry": {"coordinates":[12.0906000137,56.0545120239],"type":"Point"}
}