{
  "type": "Feature",
  "properties": {
    "addr:full":"H\u00f8jbjergvej 31, Seest Kolding Danmark 6000",
    "addr:housenumber":"31",
    "addr:postcode":"6000",
    "addr:street":"Hojbjergvej;Seest",
    "iso:country":"DK",
    "sg:address":"H\u00f8jbjergvej 31, Seest",
    "sg:city":"Kolding",
    "sg:classifiers":[
        {
            "category":"Banks & Credit Unions",
            "subcategory":"Investment Brokerage",
            "type":"Services"
        }
    ],
    "sg:phone":"+45 75 53 63 72",
    "sg:postcode":"6000",
    "sg:province":"Danmark",
    "sg:tags":[
        "healing"
    ],
    "wof:name":"AP Healing",
    "wof:placetype":"venue"
},
  "geometry": {"coordinates":[9.4733953476,55.4863586426],"type":"Point"}
}