{
  "type": "Feature",
  "properties": {
    "addr:full":"Herstvej 28, Grundf\u00f8r Hinnerup Danmark 8382",
    "addr:housenumber":"28",
    "addr:postcode":"8382",
    "addr:street":"Herstvej;Grundfor",
    "iso:country":"DK",
    "sg:address":"Herstvej 28, Grundf\u00f8r",
    "sg:city":"Hinnerup",
    "sg:orig_category":"Gartnerier",
    "sg:phone":"+45 86 98 58 33",
    "sg:postcode":"8382",
    "sg:province":"Danmark",
    "wof:name":"Jacobsen I/S, Gartneriet",
    "wof:placetype":"venue"
},
  "geometry": {"coordinates":[10.0614156723,56.2650604248],"type":"Point"}
}