{
  "type": "Feature",
  "properties": {
    "addr:full":"Nytorv 1, 1. Hobro Danmark 9500",
    "addr:housenumber":"1 1",
    "addr:postcode":"9500",
    "addr:street":"Nytorv",
    "iso:country":"DK",
    "sg:address":"Nytorv 1, 1.",
    "sg:city":"Hobro",
    "sg:orig_category":"Advokater",
    "sg:phone":"+45 98 52 08 33",
    "sg:postcode":"9500",
    "sg:province":"Danmark",
    "wof:name":"Advodan S\u00f8ndergaard og Nyborg",
    "wof:placetype":"venue"
},
  "geometry": {"coordinates":[9.7962627411,56.6374359131],"type":"Point"}
}