{
  "type": "Feature",
  "properties": {
    "iso:country":"DK",
    "sg:address":"S\u00f8ndergade 36",
    "sg:city":"Br\u00f8rup",
    "sg:classifiers":[
        {
            "category":"Food & Beverages",
            "subcategory":"Bakery",
            "type":"Retail Goods"
        }
    ],
    "sg:phone":"+45 75 38 17 25",
    "sg:postcode":"6650",
    "sg:province":"Danmark",
    "sg:tags":[
        "biscuit"
    ],
    "wof:name":"S\u00f8rensens Vaffelbageri, Jens",
    "wof:placetype":"venue"
},
  "geometry": {"coordinates":[-93.163094,32.850735],"type":"Point"}
}