{
  "type": "Feature",
  "properties": {
    "addr:full":"Svinget 18 Give Danmark 7323",
    "addr:housenumber":"18",
    "addr:postcode":"7323",
    "addr:street":"Svinget",
    "iso:country":"DK",
    "sg:address":"Svinget 18",
    "sg:city":"Give",
    "sg:orig_category":"Musikere",
    "sg:phone":"+45 75 73 91 97",
    "sg:postcode":"7323",
    "sg:province":"Danmark",
    "wof:name":"PH - Musik",
    "wof:placetype":"venue"
},
  "geometry": {"coordinates":[9.2373199463,55.8476409912],"type":"Point"}
}