{
  "type": "Feature",
  "properties": {
    "iso:country":"DK",
    "sg:address":"Storegade 20",
    "sg:city":"Hadsund",
    "sg:orig_category":"Blomsterhandlere",
    "sg:phone":"+45 98 57 43 33",
    "sg:postcode":"9560",
    "sg:province":"Danmark",
    "sg:website":"www.tusindfryd.net",
    "wof:name":"Blomsterforretningen Tusindfryd",
    "wof:placetype":"venue"
},
  "geometry": {"coordinates":[10.1142654419,56.7161102295],"type":"Point"}
}