{
  "type": "Feature",
  "properties": {
    "addr:full":"Lykkebovej 44 Valby Danmark 2500",
    "addr:housenumber":"44",
    "addr:postcode":"2500",
    "addr:street":"Lykkebovej",
    "iso:country":"DK",
    "sg:address":"Lykkebovej 44",
    "sg:city":"Valby",
    "sg:orig_category":"Reklamebureauer",
    "sg:phone":"+45 36 44 01 07",
    "sg:postcode":"2500",
    "sg:province":"Danmark",
    "sg:website":"www.backhaus.dk",
    "wof:name":"Backhaus Reklamebureau",
    "wof:placetype":"venue"
},
  "geometry": {"coordinates":[12.4808893204,55.65883255],"type":"Point"}
}