{
  "type": "Feature",
  "properties": {
    "iso:country":"DK",
    "sg:address":"Smallegade 12 B",
    "sg:city":"Nyk\u00f8bing",
    "sg:orig_category":"\u00c3\u02dcvrige institutioner",
    "sg:phone":"+45 97 72 44 25",
    "sg:postcode":"7900",
    "sg:province":"Danmark",
    "wof:name":"Bof\u00e6llesskabet",
    "wof:placetype":"venue"
},
  "geometry": {"coordinates":[12.5320100784,55.6786994934],"type":"Point"}
}