{
  "type": "Feature",
  "properties": {
    "addr:full":"Brorsonsvej 3 Vodskov Danmark 9310",
    "addr:housenumber":"3",
    "addr:postcode":"9310",
    "addr:street":"Brorsonsvej",
    "iso:country":"DK",
    "sg:address":"Brorsonsvej 3",
    "sg:city":"Vodskov",
    "sg:orig_category":"Cafeterier",
    "sg:phone":"+45 98 29 34 66",
    "sg:postcode":"9310",
    "sg:province":"Danmark",
    "wof:name":"Vodskovhallen Cafeteria",
    "wof:placetype":"venue"
},
  "geometry": {"coordinates":[10.0211753845,57.1092643738],"type":"Point"}
}