{
  "type": "Feature",
  "properties": {
    "addr:full":"Vennelyst Boulevard 9 \u00c5rhus C Danmark 8000",
    "addr:housenumber":"9",
    "addr:postcode":"8000",
    "addr:street":"Vennelyst Boulevard",
    "iso:country":"DK",
    "sg:address":"Vennelyst Boulevard 9",
    "sg:city":"\u00c5rhus C",
    "sg:orig_category":"Boghandlere",
    "sg:phone":"+45 86 13 08 97",
    "sg:postcode":"8000",
    "sg:province":"Danmark",
    "wof:name":"\u00c5rhus Odontologiske Boghandel",
    "wof:placetype":"venue"
},
  "geometry": {"coordinates":[-116.27327728269999,32.6635398865],"type":"Point"}
}