{
  "type": "Feature",
  "properties": {
    "addr:full":"v/ Margrethe Vigtoft, \u00d8stervang 29 Bryrup Danmark 8654",
    "addr:housenumber":"29",
    "addr:postcode":"8654",
    "addr:street":"Ostervang",
    "iso:country":"DK",
    "sg:address":"v/ Margrethe Vigtoft, \u00d8stervang 29",
    "sg:city":"Bryrup",
    "sg:orig_category":"\u00c3\u2020ldreorganisationer og klubber",
    "sg:phone":"+45 75 75 63 46",
    "sg:postcode":"8654",
    "sg:province":"Danmark",
    "wof:name":"Vinding - Bryrup - Vrads og Hj\u00f8llund Pensionistforening",
    "wof:placetype":"venue"
},
  "geometry": {"coordinates":[9.5107898712,56.0237388611],"type":"Point"}
}