{
  "type": "Feature",
  "properties": {
    "addr:full":"Industrivej Syd 1 C, Birk Herning Danmark 7400",
    "addr:housenumber":"1 c",
    "addr:postcode":"7400",
    "addr:street":"Industrivej Syd",
    "iso:country":"DK",
    "sg:address":"Industrivej Syd 1 C, Birk",
    "sg:city":"Herning",
    "sg:orig_category":"Konsulentvirksomheder",
    "sg:phone":"+45 96 27 01 00",
    "sg:postcode":"7400",
    "sg:province":"Danmark",
    "sg:website":"www.hih-development.dk",
    "wof:name":"HIH Development A/S",
    "wof:placetype":"venue"
},
  "geometry": {"coordinates":[8.9768896103,56.1374168396],"type":"Point"}
}