{
  "type": "Feature",
  "properties": {
    "addr:full":"Vestertorp 4 Thisted Danmark 7700",
    "addr:housenumber":"4",
    "addr:postcode":"7700",
    "addr:street":"Vestertorp",
    "iso:country":"DK",
    "sg:address":"Vestertorp 4",
    "sg:city":"Thisted",
    "sg:orig_category":"Murermestre",
    "sg:phone":"+45 97 92 60 08",
    "sg:postcode":"7700",
    "sg:province":"Danmark",
    "wof:name":"Christensen & S\u00f8n, Peter",
    "wof:placetype":"venue"
},
  "geometry": {"coordinates":[8.6629600525,56.9585838318],"type":"Point"}
}