{
  "type": "Feature",
  "properties": {
    "addr:full":"\u00c5dalsvej 10 Hinnerup Danmark 8382",
    "addr:housenumber":"10",
    "addr:postcode":"8382",
    "addr:street":"Aadalsvej",
    "iso:country":"DK",
    "sg:address":"\u00c5dalsvej 10",
    "sg:city":"Hinnerup",
    "sg:orig_category":"Menighedshuse",
    "sg:phone":"+45 86 98 84 10",
    "sg:postcode":"8382",
    "sg:province":"Danmark",
    "wof:name":"Sogneg\u00e5rden",
    "wof:placetype":"venue"
},
  "geometry": {"coordinates":[10.0638456345,56.2628364563],"type":"Point"}
}