{
  "type": "Feature",
  "properties": {
    "addr:full":"Svendborg Baneg\u00e5rd, Klosterplads 10 Svendborg Danmark 5700",
    "addr:housenumber":"10",
    "addr:postcode":"5700",
    "addr:street":"Klosterplads",
    "iso:country":"DK",
    "sg:address":"Svendborg Baneg\u00e5rd, Klosterplads 10",
    "sg:city":"Svendborg",
    "sg:orig_category":"RESTAURANTS: CAFEER",
    "sg:phone":"+45 62 21 20 20",
    "sg:postcode":"5700",
    "sg:province":"Danmark",
    "wof:name":"DSB Caf\u00e9",
    "wof:placetype":"venue"
},
  "geometry": {"coordinates":[10.6065101624,55.0595970154],"type":"Point"}
}