{
  "type": "Feature",
  "properties": {
    "addr:full":"R\u00e5dhusgade 13 Odder Danmark 8300",
    "addr:housenumber":"13",
    "addr:postcode":"8300",
    "addr:street":"Raadhusgade",
    "iso:country":"DK",
    "sg:address":"R\u00e5dhusgade 13",
    "sg:city":"Odder",
    "sg:orig_category":"Servicestationer",
    "sg:phone":"+45 86 54 11 88",
    "sg:postcode":"8300",
    "sg:province":"Danmark",
    "wof:name":"Shell Service",
    "wof:placetype":"venue"
},
  "geometry": {"coordinates":[10.1499662399,55.975643158],"type":"Point"}
}