{
  "type": "Feature",
  "properties": {
    "addr:full":"Skolebakken 20 Grenaa Danmark 8500",
    "addr:housenumber":"20",
    "addr:postcode":"8500",
    "addr:street":"Skolebakken",
    "iso:country":"DK",
    "sg:address":"Skolebakken 20",
    "sg:city":"Grenaa",
    "sg:orig_category":"Kommunale folkeskoler",
    "sg:phone":"+45 86 32 08 93",
    "sg:postcode":"8500",
    "sg:province":"Danmark",
    "wof:name":"\u00d8stre Skole",
    "wof:placetype":"venue"
},
  "geometry": {"coordinates":[10.7713775635,56.3501205444],"type":"Point"}
}