{
  "type": "Feature",
  "properties": {
    "addr:full":"Egevangen 1 Grindsted Danmark 7200",
    "addr:housenumber":"1",
    "addr:postcode":"7200",
    "addr:street":"Egevangen",
    "iso:country":"DK",
    "sg:address":"Egevangen 1",
    "sg:city":"Grindsted",
    "sg:orig_category":"Erhvervslokaler, Udlejning af",
    "sg:phone":"+45 75 31 09 45",
    "sg:postcode":"7200",
    "sg:province":"Danmark",
    "wof:name":"Madsen, Helge",
    "wof:placetype":"venue"
},
  "geometry": {"coordinates":[8.91842556,55.7516479492],"type":"Point"}
}