{
  "type": "Feature",
  "properties": {
    "addr:full":"\u00d8resundsvej 18 Skagen Danmark 9990",
    "addr:housenumber":"18",
    "addr:postcode":"9990",
    "addr:street":"Oresundsvej",
    "iso:country":"DK",
    "sg:address":"\u00d8resundsvej 18",
    "sg:city":"Skagen",
    "sg:orig_category":"Glarmestre og glarmagere",
    "sg:phone":"+45 98 44 38 55",
    "sg:postcode":"9990",
    "sg:province":"Danmark",
    "wof:name":"Villy J\u00f8rgensen Aps",
    "wof:placetype":"venue"
},
  "geometry": {"coordinates":[10.5659770966,57.7252426147],"type":"Point"}
}