{
  "type": "Feature",
  "properties": {
    "addr:full":"Strandalleen 92 Nyborg Danmark 5800",
    "addr:housenumber":"92",
    "addr:postcode":"5800",
    "addr:street":"Strandalleen",
    "iso:country":"DK",
    "sg:address":"Strandalleen 92",
    "sg:city":"Nyborg",
    "sg:classifiers":[
        {
            "category":"Restaurant",
            "type":"Food & Drink"
        }
    ],
    "sg:phone":"+45 65 31 41 40",
    "sg:postcode":"5800",
    "sg:province":"Danmark",
    "wof:name":"Teglv\u00e6rksskoven, Hotel",
    "wof:placetype":"venue"
},
  "geometry": {"coordinates":[10.8036146164,55.3292160034],"type":"Point"}
}