{
  "type": "Feature",
  "properties": {
    "iso:country":"DK",
    "sg:address":"N\u00f8rrevej 2, Kollund",
    "sg:city":"Krus\u00e5",
    "sg:orig_category":"Brugsforeninger",
    "sg:phone":"+45 74 67 88 40",
    "sg:postcode":"6340",
    "sg:province":"Danmark",
    "wof:name":"Kollund Brugsforening",
    "wof:placetype":"venue"
},
  "geometry": {"coordinates":[9.3991203308,54.8500900269],"type":"Point"}
}