{
  "type": "Feature",
  "properties": {
    "addr:full":"Havnegade 20 Asaa Danmark 9340",
    "addr:housenumber":"20",
    "addr:postcode":"9340",
    "addr:street":"Havnegade",
    "iso:country":"DK",
    "sg:address":"Havnegade 20",
    "sg:city":"Asaa",
    "sg:orig_category":"Havne",
    "sg:phone":"+45 98 85 15 12",
    "sg:postcode":"9340",
    "sg:province":"Danmark",
    "wof:name":"Asaa Lystb\u00e5dehavn",
    "wof:placetype":"venue"
},
  "geometry": {"coordinates":[10.4072914124,57.147518158],"type":"Point"}
}