{
  "type": "Feature",
  "properties": {
    "addr:full":"Ejby Industrivej 2 Glostrup Danmark 2600",
    "addr:housenumber":"2",
    "addr:postcode":"2600",
    "addr:street":"Ejby Industrivej",
    "iso:country":"DK",
    "sg:address":"Ejby Industrivej 2",
    "sg:city":"Glostrup",
    "sg:orig_category":"Fliser",
    "sg:phone":"+45 43 43 43 15",
    "sg:postcode":"2600",
    "sg:province":"Danmark",
    "wof:name":"Evers A/S",
    "wof:placetype":"venue"
},
  "geometry": {"coordinates":[12.4216442108,55.6938896179],"type":"Point"}
}