{
  "type": "Feature",
  "properties": {
    "addr:full":"Islands Brygge 15 K\u00f8benhavn S Danmark 2300",
    "addr:housenumber":"15",
    "addr:postcode":"2300",
    "addr:street":"Islands Brygge;S Danmark",
    "iso:country":"DK",
    "sg:address":"Islands Brygge 15",
    "sg:city":"K\u00f8benhavn S",
    "sg:classifiers":[
        {
            "category":"Restaurant",
            "type":"Food & Drink"
        }
    ],
    "sg:phone":"+45 32 54 69 02",
    "sg:postcode":"2300",
    "sg:province":"Danmark",
    "wof:name":"Cafe Haraldsborg",
    "wof:placetype":"venue"
},
  "geometry": {"coordinates":[12.5801095963,55.6693916321],"type":"Point"}
}