{
  "type": "Feature",
  "properties": {
    "addr:full":"\u00d8stergade 2 A Aabybro Danmark 9440",
    "addr:housenumber":"2 a",
    "addr:postcode":"9440",
    "addr:street":"Ostergade",
    "iso:country":"DK",
    "sg:address":"\u00d8stergade 2 A",
    "sg:city":"Aabybro",
    "sg:classifiers":[
        {
            "category":"Restaurant",
            "type":"Food & Drink"
        }
    ],
    "sg:phone":"+45 98 24 21 93",
    "sg:postcode":"9440",
    "sg:province":"Danmark",
    "wof:name":"Queens Pub",
    "wof:placetype":"venue"
},
  "geometry": {"coordinates":[9.7297954559,57.1623268127],"type":"Point"}
}