{
  "type": "Feature",
  "properties": {
    "addr:full":"Damhusvej 5, Bramdrupdam Kolding Danmark 6000",
    "addr:housenumber":"5",
    "addr:postcode":"6000",
    "addr:street":"Damhusvej",
    "iso:country":"DK",
    "sg:address":"Damhusvej 5, Bramdrupdam",
    "sg:city":"Kolding",
    "sg:orig_category":"Murermestre",
    "sg:phone":"+45 75 51 79 09",
    "sg:postcode":"6000",
    "sg:province":"Danmark",
    "wof:name":"J\u00f8rgensen Murerforretning, Bjarne",
    "wof:placetype":"venue"
},
  "geometry": {"coordinates":[9.4733953476,55.4863586426],"type":"Point"}
}