{
  "type": "Feature",
  "properties": {
    "addr:full":"N\u00f8rrebrogade 9 K\u00f8benhavn N Danmark 2200",
    "addr:housenumber":"9",
    "addr:postcode":"2200",
    "addr:street":"Norrebrogade;N Danmark",
    "iso:country":"DK",
    "sg:address":"N\u00f8rrebrogade 9",
    "sg:city":"K\u00f8benhavn N",
    "sg:orig_category":"Apoteker og -udsalg",
    "sg:phone":"+45 35 39 83 82",
    "sg:postcode":"2200",
    "sg:province":"Danmark",
    "wof:name":"N\u00f8rrebro Apotek",
    "wof:placetype":"venue"
},
  "geometry": {"coordinates":[-80.9769515991,33.6362686157],"type":"Point"}
}