{
  "type": "Feature",
  "properties": {
    "iso:country":"DK",
    "sg:address":"Fmd.: Elmo Myrup, Hybenvej 4",
    "sg:city":"Brovst",
    "sg:orig_category":"Kirkelige foreninger",
    "sg:phone":"+45 98 23 26 32",
    "sg:postcode":"9460",
    "sg:province":"Danmark",
    "wof:name":"Indre Missions Samfund i Brovst",
    "wof:placetype":"venue"
},
  "geometry": {"coordinates":[9.5220241547,57.097366333],"type":"Point"}
}