{
  "type": "Feature",
  "properties": {
    "iso:country":"DK",
    "sg:address":"Sognepr\u00e6st: Benedikte Knudsen, M\u00f8llevej 35",
    "sg:city":"Idestrup",
    "sg:orig_category":"Kirkesogne",
    "sg:phone":"+45 54 14 80 77",
    "sg:postcode":"4872",
    "sg:province":"Danmark",
    "wof:name":"Idestrup sogn",
    "wof:placetype":"venue"
},
  "geometry": {"coordinates":[11.957859993,54.7407112122],"type":"Point"}
}