{
  "type": "Feature",
  "properties": {
    "addr:full":"Ryvangs Alle 44 Hellerup Danmark 2900",
    "addr:housenumber":"44",
    "addr:postcode":"2900",
    "addr:street":"Ryvangs Alle",
    "iso:country":"DK",
    "sg:address":"Ryvangs Alle 44",
    "sg:city":"Hellerup",
    "sg:orig_category":"Advokater",
    "sg:phone":"+45 39 46 35 35",
    "sg:postcode":"2900",
    "sg:province":"Danmark",
    "wof:name":"Andersen, H. Bo",
    "wof:placetype":"venue"
},
  "geometry": {"coordinates":[12.5703163147,55.7238922119],"type":"Point"}
}