{
  "type": "Feature",
  "properties": {
    "addr:full":"R\u00f8m\u00f8vej 24, H\u00f8nning Toftlund Danmark 6520",
    "addr:housenumber":"24",
    "addr:postcode":"6520",
    "addr:street":"Romovej;Honning",
    "iso:country":"DK",
    "sg:address":"R\u00f8m\u00f8vej 24, H\u00f8nning",
    "sg:city":"Toftlund",
    "sg:orig_category":"Vagtbureauer",
    "sg:phone":"+45 20 93 80 40",
    "sg:postcode":"6520",
    "sg:province":"Danmark",
    "sg:website":"www.sydjydsk-vagt.dk",
    "wof:name":"Syd Jydsk Vagt og Sikkerhedsservice",
    "wof:placetype":"venue"
},
  "geometry": {"coordinates":[9.0629367828,55.1926651001],"type":"Point"}
}