{
  "type": "Feature",
  "properties": {
    "iso:country":"DK",
    "sg:address":"Torvegade 112",
    "sg:city":"Esbjerg",
    "sg:orig_category":"Yogaundervisning",
    "sg:phone":"+45 75 45 66 83",
    "sg:postcode":"6700",
    "sg:province":"Danmark",
    "sg:website":"www.yogahuset.com",
    "wof:name":"Yogahuset",
    "wof:placetype":"venue"
},
  "geometry": {"coordinates":[8.4550027847,55.4757614136],"type":"Point"}
}