{
  "type": "Feature",
  "properties": {
    "addr:full":"Torupvejen 90 Hundested Danmark 3390",
    "addr:housenumber":"90",
    "addr:postcode":"3390",
    "addr:street":"Torupvejen",
    "iso:country":"DK",
    "sg:address":"Torupvejen 90",
    "sg:city":"Hundested",
    "sg:orig_category":"Kursussteder",
    "sg:phone":"+45 47 98 70 98",
    "sg:postcode":"3390",
    "sg:province":"Danmark",
    "sg:website":"www.toruplund.dk",
    "wof:name":"Toruplund",
    "wof:placetype":"venue"
},
  "geometry": {"coordinates":[11.9202098846,55.9774131775],"type":"Point"}
}