{
  "type": "Feature",
  "properties": {
    "addr:full":"Fmd.: Harly Yde, H\u00f8jg\u00e5rdsparken 100 Hjerm Danmark 7560",
    "addr:housenumber":"100",
    "addr:postcode":"7560",
    "addr:street":"Yde Hojgaardsparken",
    "iso:country":"DK",
    "sg:address":"Fmd.: Harly Yde, H\u00f8jg\u00e5rdsparken 100",
    "sg:city":"Hjerm",
    "sg:orig_category":"Grundejerforeninger",
    "sg:phone":"+45 97 46 47 09",
    "sg:postcode":"7560",
    "sg:province":"Danmark",
    "wof:name":"Grundejerforeningen H\u00f8jg\u00e5rdsparken",
    "wof:placetype":"venue"
},
  "geometry": {"coordinates":[8.6395950317,56.4384765625],"type":"Point"}
}