{
  "type": "Feature",
  "properties": {
    "iso:country":"DK",
    "sg:address":"Aaparken 14, 1",
    "sg:city":"Herning",
    "sg:orig_category":"Kulturelle foreninger",
    "sg:phone":"+45 77 99 14 76",
    "sg:postcode":"7400",
    "sg:province":"Danmark",
    "wof:name":"Arbejdernes Radio- og Fjernsynsklub",
    "wof:placetype":"venue"
},
  "geometry": {"coordinates":[9.004034996,56.1367912292],"type":"Point"}
}