{
  "type": "Feature",
  "properties": {
    "addr:full":"v/ Ivan Andersen, N\u00f8rg\u00e5rdsvej 293 Strandby Danmark 9970",
    "addr:housenumber":"293",
    "addr:postcode":"9970",
    "addr:street":"Norgaardsvej",
    "iso:country":"DK",
    "sg:address":"v/ Ivan Andersen, N\u00f8rg\u00e5rdsvej 293",
    "sg:city":"Strandby",
    "sg:orig_category":"Musik og sang",
    "sg:phone":"+45 98 48 22 63",
    "sg:postcode":"9970",
    "sg:province":"Danmark",
    "wof:name":"\u00c5lb\u00e6k Harmonikaklub",
    "wof:placetype":"venue"
},
  "geometry": {"coordinates":[10.4970350266,57.4932899475],"type":"Point"}
}