{
  "type": "Feature",
  "properties": {
    "addr:full":"N\u00f8rregade 39 B Haderslev Danmark 6100",
    "addr:housenumber":"39 b",
    "addr:postcode":"6100",
    "addr:street":"Norregade",
    "iso:country":"DK",
    "sg:address":"N\u00f8rregade 39 B",
    "sg:city":"Haderslev",
    "sg:orig_category":"Oplysningsforbund",
    "sg:phone":"+45 74 52 44 04",
    "sg:postcode":"6100",
    "sg:province":"Danmark",
    "sg:website":"www.fof-haderslev.dk",
    "wof:name":"FOF Haderslev",
    "wof:placetype":"venue"
},
  "geometry": {"coordinates":[9.4887781143,55.2527236938],"type":"Point"}
}