{
  "type": "Feature",
  "properties": {
    "addr:full":"Industrivej 13 Fredericia Danmark 7000",
    "addr:housenumber":"13",
    "addr:postcode":"7000",
    "addr:street":"Industrivej",
    "iso:country":"DK",
    "sg:address":"Industrivej 13",
    "sg:city":"Fredericia",
    "sg:orig_category":"Autoforhandlere",
    "sg:phone":"+45 75 92 05 06",
    "sg:postcode":"7000",
    "sg:province":"Danmark",
    "wof:name":"Iveco Fredericia",
    "wof:placetype":"venue"
},
  "geometry": {"coordinates":[9.7579050064,55.5900878906],"type":"Point"}
}