{
  "type": "Feature",
  "properties": {
    "addr:full":"Dronning Olgas Vej 17 Frederiksberg Danmark 2000",
    "addr:housenumber":"17",
    "addr:postcode":"2000",
    "addr:street":"Dronning Olgas Vej",
    "iso:country":"DK",
    "sg:address":"Dronning Olgas Vej 17",
    "sg:city":"Frederiksberg",
    "sg:orig_category":"Psykologer, praktiserende",
    "sg:phone":"+45 20 33 55 46",
    "sg:postcode":"2000",
    "sg:province":"Danmark",
    "wof:name":"Kahlke, Edith",
    "wof:placetype":"venue"
},
  "geometry": {"coordinates":[12.5376729965,55.6880722046],"type":"Point"}
}