{
  "type": "Feature",
  "properties": {
    "addr:full":"Hollandsvej 4, Fabjerg Lemvig Danmark 7620",
    "addr:housenumber":"4",
    "addr:postcode":"7620",
    "addr:street":"Hollandsvej",
    "iso:country":"DK",
    "sg:address":"Hollandsvej 4, Fabjerg",
    "sg:city":"Lemvig",
    "sg:orig_category":"Maskinstationer",
    "sg:phone":"+45 97 89 30 01",
    "sg:postcode":"7620",
    "sg:province":"Danmark",
    "wof:name":"Engelund Maskinstation",
    "wof:placetype":"venue"
},
  "geometry": {"coordinates":[8.3073654175,56.5505104065],"type":"Point"}
}