{
  "type": "Feature",
  "properties": {
    "iso:country":"DK",
    "sg:address":"Spergelvej 33",
    "sg:city":"Klarup",
    "sg:orig_category":"EDB - udstyr",
    "sg:phone":"+45 98 31 85 50",
    "sg:postcode":"9270",
    "sg:province":"Danmark",
    "sg:website":"www.internetvejviser.dk",
    "wof:name":"Villum Data",
    "wof:placetype":"venue"
},
  "geometry": {"coordinates":[10.0391407013,57.0148124695],"type":"Point"}
}