{
  "type": "Feature",
  "properties": {
    "addr:full":"Paradisvej 1 A Nex\u00f8 Danmark 3730",
    "addr:housenumber":"1 a",
    "addr:postcode":"3730",
    "addr:street":"Paradisvej",
    "iso:country":"DK",
    "sg:address":"Paradisvej 1 A",
    "sg:city":"Nex\u00f8",
    "sg:orig_category":"Arbejdsformidling",
    "sg:phone":"+45 56 49 28 46",
    "sg:postcode":"3730",
    "sg:province":"Danmark",
    "wof:name":"AF-Nex\u00f8",
    "wof:placetype":"venue"
},
  "geometry": {"coordinates":[15.1210203171,55.0716781616],"type":"Point"}
}