{
  "type": "Feature",
  "properties": {
    "iso:country":"DK",
    "sg:address":"Fredensborg-Humleb\u00e6k",
    "sg:city":"Fredensborg",
    "sg:orig_category":"Begravelsesforretninger",
    "sg:phone":"+45 48 48 33 91",
    "sg:postcode":"3480",
    "sg:province":"Danmark",
    "wof:name":"Fredensborg Begravelsesforretning",
    "wof:placetype":"venue"
},
  "geometry": {"coordinates":[12.3358068466,55.9582633972],"type":"Point"}
}