{
  "type": "Feature",
  "properties": {
    "iso:country":"DK",
    "sg:address":"N\u00f8rregade 12",
    "sg:city":"Otterup",
    "sg:classifiers":[
        {
            "category":"Communications",
            "type":"Services"
        }
    ],
    "sg:phone":"+45 64 82 15 25",
    "sg:postcode":"5450",
    "sg:province":"Danmark",
    "sg:tags":[
        "og",
        "tv",
        "radio"
    ],
    "wof:name":"K. J. Radio & TV",
    "wof:placetype":"venue"
},
  "geometry": {"coordinates":[10.3988370895,55.5161705017],"type":"Point"}
}