{
  "type": "Feature",
  "properties": {
    "addr:full":"Vardevej 418  Vejle Danmark 7100",
    "addr:housenumber":"418",
    "addr:postcode":"7100",
    "addr:street":"Vardevej",
    "iso:country":"DK",
    "sg:address":"Vardevej 418 ",
    "sg:city":"Vejle",
    "sg:classifiers":[
        {
            "category":"Home & Garden",
            "subcategory":"Home Furnishings",
            "type":"Retail Goods"
        }
    ],
    "sg:phone":"+45 75 88 14 22",
    "sg:postcode":"7100",
    "sg:province":"Danmark",
    "sg:tags":[
        "household"
    ],
    "wof:name":"IDEM\u00d8BLER",
    "wof:placetype":"venue"
},
  "geometry": {"coordinates":[9.4714679718,55.7104377747],"type":"Point"}
}