{
  "type": "Feature",
  "properties": {
    "addr:full":"Magnoliavej 9 Frederiksberg Danmark 2000",
    "addr:housenumber":"9",
    "addr:postcode":"2000",
    "addr:street":"Magnoliavej",
    "iso:country":"DK",
    "sg:address":"Magnoliavej 9",
    "sg:city":"Frederiksberg",
    "sg:orig_category":"Menighedshuse",
    "sg:postcode":"2000",
    "sg:province":"Danmark",
    "wof:name":"Frederiksberg Slotskirkes Menighedshus",
    "wof:placetype":"venue"
},
  "geometry": {"coordinates":[12.5155801773,55.6694641113],"type":"Point"}
}