{
  "type": "Feature",
  "properties": {
    "addr:full":"Aftensang 2 Egtved Danmark 6040",
    "addr:housenumber":"2",
    "addr:postcode":"6040",
    "addr:street":"Aftensang",
    "iso:country":"DK",
    "sg:address":"Aftensang 2",
    "sg:city":"Egtved",
    "sg:orig_category":"Biblioteker",
    "sg:phone":"+45 75 55 23 55",
    "sg:postcode":"6040",
    "sg:province":"Danmark",
    "sg:website":"www.egtvedbib.dk",
    "wof:name":"Egtved Bibliotek",
    "wof:placetype":"venue"
},
  "geometry": {"coordinates":[9.31152,55.618988],"type":"Point"}
}