{
  "type": "Feature",
  "properties": {
    "iso:country":"DK",
    "sg:address":"Ulk\u00e6rvej 37, Nr. S\u00f8by",
    "sg:city":"H\u00f8jslev",
    "sg:orig_category":"EDB - udstyr",
    "sg:phone":"+45 97 53 50 68",
    "sg:postcode":"7840",
    "sg:province":"Danmark",
    "sg:website":"www.lbc-consult.dk",
    "wof:name":"LBC Consult",
    "wof:placetype":"venue"
},
  "geometry": {"coordinates":[166.9221496582,-0.5282999873],"type":"Point"}
}