{
  "type": "Feature",
  "properties": {
    "addr:full":"Overmester: Hans Strunge, Langgade 11 Hesselager Danmark 5874",
    "addr:housenumber":"11",
    "addr:postcode":"5874",
    "addr:street":"Strunge Langgade",
    "iso:country":"DK",
    "sg:address":"Overmester: Hans Strunge, Langgade 11",
    "sg:city":"Hesselager",
    "sg:orig_category":"Loger",
    "sg:phone":"+45 62 25 40 01",
    "sg:postcode":"5874",
    "sg:province":"Danmark",
    "wof:name":"Odd-Fellow logen nr. 33 Caritas",
    "wof:placetype":"venue"
},
  "geometry": {"coordinates":[10.7344398499,55.1688804626],"type":"Point"}
}