{
  "type": "Feature",
  "properties": {
    "addr:full":"Industrivej 6 Bolderslev Danmark 6392",
    "addr:housenumber":"6",
    "addr:postcode":"6392",
    "addr:street":"Industrivej",
    "iso:country":"DK",
    "sg:address":"Industrivej 6",
    "sg:city":"Bolderslev",
    "sg:orig_category":"Autoelektro",
    "sg:phone":"+45 74 64 68 62",
    "sg:postcode":"6392",
    "sg:province":"Danmark",
    "wof:name":"G M Elektro",
    "wof:placetype":"venue"
},
  "geometry": {"coordinates":[9.2711305618,54.9912147522],"type":"Point"}
}