{
  "type": "Feature",
  "properties": {
    "addr:full":"Frijsendalvej 101, Haurum Hammel Danmark 8450",
    "addr:housenumber":"101",
    "addr:postcode":"8450",
    "addr:street":"Frijsendalvej",
    "iso:country":"DK",
    "sg:address":"Frijsendalvej 101, Haurum",
    "sg:city":"Hammel",
    "sg:orig_category":"Autoreparation og -service",
    "sg:phone":"+45 86 96 90 62",
    "sg:postcode":"8450",
    "sg:province":"Danmark",
    "wof:name":"Andersen, Jan Kj\u00e6r",
    "wof:placetype":"venue"
},
  "geometry": {"coordinates":[9.8615541458,56.2554588318],"type":"Point"}
}