{
  "type": "Feature",
  "properties": {
    "iso:country":"DK",
    "sg:address":"Buddinge Hovedgade 321",
    "sg:city":"Bagsv\u00e6rd",
    "sg:orig_category":"Revisorer",
    "sg:phone":"+45 44 98 21 92",
    "sg:postcode":"2880",
    "sg:province":"Danmark",
    "sg:website":"www.lemche-rev.dk",
    "wof:name":"LEMCHE REVISION A/S",
    "wof:placetype":"venue"
},
  "geometry": {"coordinates":[12.4982404709,55.7419395447],"type":"Point"}
}