{
  "type": "Feature",
  "properties": {
    "addr:full":"Fmd.: Aase Paaske, Barrit Langgade 164 Barrit Danmark 7150",
    "addr:housenumber":"164",
    "addr:postcode":"7150",
    "addr:street":"Barrit Langgade",
    "iso:country":"DK",
    "sg:address":"Fmd.: Aase Paaske, Barrit Langgade 164",
    "sg:city":"Barrit",
    "sg:orig_category":"\u00c3\u2020ldreorganisationer og klubber",
    "sg:phone":"+45 75 69 11 17",
    "sg:postcode":"7150",
    "sg:province":"Danmark",
    "wof:name":"Barrit-Vrigsted Pensionistforening",
    "wof:placetype":"venue"
},
  "geometry": {"coordinates":[9.9013900757,55.7076950073],"type":"Point"}
}