{
  "type": "Feature",
  "properties": {
    "addr:full":"Kikkenborgvej 12 Herning Danmark 7400",
    "addr:housenumber":"12",
    "addr:postcode":"7400",
    "addr:street":"Kikkenborgvej",
    "iso:country":"DK",
    "sg:address":"Kikkenborgvej 12",
    "sg:city":"Herning",
    "sg:orig_category":"Tekstilindustri",
    "sg:phone":"+45 97 12 24 11",
    "sg:postcode":"7400",
    "sg:province":"Danmark",
    "sg:website":"www.elton.dk",
    "wof:name":"Elton",
    "wof:placetype":"venue"
},
  "geometry": {"coordinates":[8.956196785,56.132522583],"type":"Point"}
}