{
  "type": "Feature",
  "properties": {
    "addr:full":"Prangervej 67 Fredericia Danmark 7000",
    "addr:housenumber":"67",
    "addr:postcode":"7000",
    "addr:street":"Prangervej",
    "iso:country":"DK",
    "sg:address":"Prangervej 67",
    "sg:city":"Fredericia",
    "sg:orig_category":"Vuggestuer",
    "sg:phone":"+45 75 92 38 99",
    "sg:postcode":"7000",
    "sg:province":"Danmark",
    "wof:name":"Dyrehaveg\u00e5rd vuggestue",
    "wof:placetype":"venue"
},
  "geometry": {"coordinates":[9.7302560806,55.5632514954],"type":"Point"}
}