{
  "type": "Feature",
  "properties": {
    "addr:full":"Rasmus Rasks All\u00e9 97, Bellinge Odense SV Danmark 5250",
    "addr:housenumber":"97",
    "addr:postcode":"5250",
    "addr:street":"Rasmus Rasks Alle\u0301",
    "iso:country":"DK",
    "sg:address":"Rasmus Rasks All\u00e9 97, Bellinge",
    "sg:city":"Odense SV",
    "sg:orig_category":"Kabelfabrikker",
    "sg:phone":"+45 65 96 00 66",
    "sg:postcode":"5250",
    "sg:province":"Danmark",
    "wof:name":"Kabelkompani, Fyns",
    "wof:placetype":"venue"
},
  "geometry": {"coordinates":[10.3153953552,55.3362998962],"type":"Point"}
}