{
  "type": "Feature",
  "properties": {
    "addr:full":"Meinungsgade 8D K\u00f8benhavn N Danmark 2200",
    "addr:housenumber":"8d kobenhavn",
    "addr:postcode":"2200",
    "addr:street":"Meinungsgade;N Danmark",
    "iso:country":"DK",
    "sg:address":"Meinungsgade 8D",
    "sg:city":"K\u00f8benhavn N",
    "sg:orig_category":"Reklamegaver",
    "sg:phone":"+45 35 36 75 16",
    "sg:postcode":"2200",
    "sg:province":"Danmark",
    "wof:name":"Stieler & Co",
    "wof:placetype":"venue"
},
  "geometry": {"coordinates":[-94.2737731934,47.7952270508],"type":"Point"}
}