{
  "type": "Feature",
  "properties": {
    "addr:full":"Indelukket 1, Mulstrup Ringsted Danmark 4100",
    "addr:housenumber":"1",
    "addr:postcode":"4100",
    "addr:street":"Indelukket;Mulstrup",
    "iso:country":"DK",
    "sg:address":"Indelukket 1, Mulstrup",
    "sg:city":"Ringsted",
    "sg:orig_category":"Murermestre",
    "sg:phone":"+45 57 64 03 30",
    "sg:postcode":"4100",
    "sg:province":"Danmark",
    "wof:name":"Olsen, Jim Jesper",
    "wof:placetype":"venue"
},
  "geometry": {"coordinates":[11.7875862122,55.4458961487],"type":"Point"}
}