{
  "type": "Feature",
  "properties": {
    "addr:full":"Bygaden 51 C Jyllinge Danmark 4040",
    "addr:housenumber":"51 c",
    "addr:postcode":"4040",
    "addr:street":"Bygaden",
    "iso:country":"DK",
    "sg:address":"Bygaden 51 C",
    "sg:city":"Jyllinge",
    "sg:orig_category":"Fodterapeuter",
    "sg:phone":"+45 46 76 02 95",
    "sg:postcode":"4040",
    "sg:province":"Danmark",
    "wof:name":"Klinik for fodterapi",
    "wof:placetype":"venue"
},
  "geometry": {"coordinates":[12.1030702591,55.7483863831],"type":"Point"}
}