{
  "type": "Feature",
  "properties": {
    "addr:full":"K\u00f8benhavnsvej 38 Slangerup Danmark 3550",
    "addr:housenumber":"38",
    "addr:postcode":"3550",
    "addr:street":"Kobenhavnsvej",
    "iso:country":"DK",
    "sg:address":"K\u00f8benhavnsvej 38",
    "sg:city":"Slangerup",
    "sg:orig_category":"Murermestre",
    "sg:phone":"+45 47 33 54 27",
    "sg:postcode":"3550",
    "sg:province":"Danmark",
    "sg:website":"www.finnandersen.dk",
    "wof:name":"Andersen, Finn",
    "wof:placetype":"venue"
},
  "geometry": {"coordinates":[12.2037467957,55.8427009583],"type":"Point"}
}