{
  "type": "Feature",
  "properties": {
    "addr:full":"Hovedgaden 35 R\u00f8dvig Stevns Danmark 4673",
    "addr:housenumber":"35",
    "addr:postcode":"4673",
    "addr:street":"Hovedgaden",
    "iso:country":"DK",
    "sg:address":"Hovedgaden 35",
    "sg:city":"R\u00f8dvig Stevns",
    "sg:orig_category":"Ejendomshandel",
    "sg:phone":"+45 56 50 70 20",
    "sg:postcode":"4673",
    "sg:province":"Danmark",
    "wof:name":"EDC M\u00e6glerne Stevns",
    "wof:placetype":"venue"
},
  "geometry": {"coordinates":[12.372546196,55.2562713623],"type":"Point"}
}