{
  "type": "Feature",
  "properties": {
    "addr:full":"Ladeg\u00e5rdsvej 12, S\u00f8nderhede Fur Danmark 7884",
    "addr:housenumber":"12",
    "addr:postcode":"7884",
    "addr:street":"Ladegaardsvej",
    "iso:country":"DK",
    "sg:address":"Ladeg\u00e5rdsvej 12, S\u00f8nderhede",
    "sg:city":"Fur",
    "sg:orig_category":"Snedkermestre",
    "sg:phone":"+45 97 59 33 66",
    "sg:postcode":"7884",
    "sg:province":"Danmark",
    "wof:name":"Christensen, Kristian Dalsg\u00e5rd",
    "wof:placetype":"venue"
},
  "geometry": {"coordinates":[9.0239391327,56.8162612915],"type":"Point"}
}