{
  "type": "Feature",
  "properties": {
    "addr:full":"Generatorvej 6 A Herlev Danmark 2730",
    "addr:housenumber":"6 a",
    "addr:postcode":"2730",
    "addr:street":"Generatorvej",
    "iso:country":"DK",
    "sg:address":"Generatorvej 6 A",
    "sg:city":"Herlev",
    "sg:classifiers":[
        {
            "category":"Professional",
            "subcategory":"Computer Services",
            "type":"Services"
        }
    ],
    "sg:phone":"+45 44 94 81 05",
    "sg:postcode":"2730",
    "sg:province":"Danmark",
    "sg:tags":[
        "edb",
        "-",
        "software"
    ],
    "wof:name":"Sosy A/S",
    "wof:placetype":"venue"
},
  "geometry": {"coordinates":[12.4660215378,55.7303237915],"type":"Point"}
}