{
  "type": "Feature",
  "properties": {
    "iso:country":"DK",
    "sg:address":"Rolfsgade 75",
    "sg:city":"Esbjerg",
    "sg:classifiers":[
        {
            "category":"Building & Trades",
            "subcategory":"Landscaping Services",
            "type":"Services"
        }
    ],
    "sg:phone":"+45 75 45 38 33",
    "sg:postcode":"6700",
    "sg:province":"Danmark",
    "sg:tags":[
        "offshore"
    ],
    "wof:name":"QA Consulting A/S",
    "wof:placetype":"venue"
},
  "geometry": {"coordinates":[8.4508895874,55.4731903076],"type":"Point"}
}