{
  "type": "Feature",
  "properties": {
    "iso:country":"DK",
    "sg:address":"Fmd.: Troels Majlandt, R\u00e5dyrv\u00e6nget 81",
    "sg:city":"Nyborg",
    "sg:orig_category":"Boligselskaber",
    "sg:phone":"+45 65 31 86 88",
    "sg:postcode":"5800",
    "sg:province":"Danmark",
    "wof:name":"Skovparken afd. II, Andelsboligforeningen",
    "wof:placetype":"venue"
},
  "geometry": {"coordinates":[10.7923851013,55.3111801147],"type":"Point"}
}