{
  "type": "Feature",
  "properties": {
    "iso:country":"DK",
    "sg:address":"\u00d8stergade 19",
    "sg:city":"Ringe",
    "sg:orig_category":"Grillbarer",
    "sg:phone":"+45 62 62 44 27",
    "sg:postcode":"5750",
    "sg:province":"Danmark",
    "wof:name":"Stations Grillen",
    "wof:placetype":"venue"
},
  "geometry": {"coordinates":[10.4808921814,55.2386932373],"type":"Point"}
}