{
  "type": "Feature",
  "properties": {
    "addr:full":"Skydebanevej 20 Aalborg Danmark 9000",
    "addr:housenumber":"20",
    "addr:postcode":"9000",
    "addr:street":"Skydebanevej",
    "iso:country":"DK",
    "sg:address":"Skydebanevej 20",
    "sg:city":"Aalborg",
    "sg:orig_category":"Campingpladser",
    "sg:phone":"+45 98 12 76 29",
    "sg:postcode":"9000",
    "sg:province":"Danmark",
    "wof:name":"Strandparken Camping",
    "wof:placetype":"venue"
},
  "geometry": {"coordinates":[9.8848781586,57.0550575256],"type":"Point"}
}