{
  "type": "Feature",
  "properties": {
    "iso:country":"DK",
    "sg:address":"Dalv\u00e6nget 10 ",
    "sg:city":"Assens",
    "sg:classifiers":[
        {
            "category":"Autos & Motor Vehicles",
            "subcategory":"Boat Sales",
            "type":"Retail Goods"
        }
    ],
    "sg:phone":"+45 64 71 55 58",
    "sg:postcode":"5610",
    "sg:province":"Danmark",
    "wof:name":"E. P. SKIBSREPARATION ASSENS A/S",
    "wof:placetype":"venue"
},
  "geometry": {"coordinates":[9.8998937607,55.2702522278],"type":"Point"}
}