{
  "type": "Feature",
  "properties": {
    "iso:country":"DK",
    "sg:address":"Fmd.: Finn Bomholt, Kirkevej 2",
    "sg:city":"L\u00e5sby",
    "sg:orig_category":"Borger- og beboerforeninger",
    "sg:phone":"+45 86 95 13 70",
    "sg:postcode":"8670",
    "sg:province":"Danmark",
    "wof:name":"Flensted Beboerforening",
    "wof:placetype":"venue"
},
  "geometry": {"coordinates":[-76.45445251460001,38.4128417969],"type":"Point"}
}