{
  "type": "Feature",
  "properties": {
    "addr:full":"Vognmarken 3 Helsinge Danmark 3200",
    "addr:housenumber":"3",
    "addr:postcode":"3200",
    "addr:street":"Vognmarken",
    "iso:country":"DK",
    "sg:address":"Vognmarken 3",
    "sg:city":"Helsinge",
    "sg:orig_category":"Trykkerier",
    "sg:phone":"+45 48 79 60 10",
    "sg:postcode":"3200",
    "sg:province":"Danmark",
    "sg:website":"www.buwitryk.dk",
    "wof:name":"Buwi Grafisk ApS",
    "wof:placetype":"venue"
},
  "geometry": {"coordinates":[12.2006845474,56.016166687],"type":"Point"}
}