{
  "type": "Feature",
  "properties": {
    "addr:full":"Kredsleder: Brita Andreasen, Vognmandsvej 4 Gedser Danmark 4874",
    "addr:housenumber":"4",
    "addr:postcode":"4874",
    "addr:street":"Vognmandsvej",
    "iso:country":"DK",
    "sg:address":"Kredsleder: Brita Andreasen, Vognmandsvej 4",
    "sg:city":"Gedser",
    "sg:orig_category":"Beredskabsforbund",
    "sg:phone":"+45 54 17 98 85",
    "sg:postcode":"4874",
    "sg:province":"Danmark",
    "wof:name":"Beredskabsforbundet Sydfalster",
    "wof:placetype":"venue"
},
  "geometry": {"coordinates":[11.9617109299,54.600353241],"type":"Point"}
}