{
  "type": "Feature",
  "properties": {
    "iso:country":"DK",
    "sg:address":"Kongelundsvej 413",
    "sg:city":"Kastrup",
    "sg:orig_category":"Servicestationer",
    "sg:phone":"+45 32 53 33 44",
    "sg:postcode":"2770",
    "sg:province":"Danmark",
    "wof:name":"Hydro Texaco",
    "wof:placetype":"venue"
},
  "geometry": {"coordinates":[12.5839271545,55.6052970886],"type":"Point"}
}