{
  "type": "Feature",
  "properties": {
    "addr:full":"Fures\u00f8 Parkvej 51 Virum Danmark 2830",
    "addr:housenumber":"51",
    "addr:postcode":"2830",
    "addr:street":"Parkvej",
    "iso:country":"DK",
    "sg:address":"Fures\u00f8 Parkvej 51",
    "sg:city":"Virum",
    "sg:orig_category":"Advokater",
    "sg:phone":"+45 45 83 08 81",
    "sg:postcode":"2830",
    "sg:province":"Danmark",
    "wof:name":"Andersen-Rosendal, Jesper",
    "wof:placetype":"venue"
},
  "geometry": {"coordinates":[12.4485683441,55.7908287048],"type":"Point"}
}