{
  "type": "Feature",
  "properties": {
    "addr:full":"\u00d8sterbakken 62 B Thisted Danmark 7700",
    "addr:housenumber":"62 b",
    "addr:postcode":"7700",
    "addr:street":"Osterbakken",
    "iso:country":"DK",
    "sg:address":"\u00d8sterbakken 62 B",
    "sg:city":"Thisted",
    "sg:orig_category":"Knallerter",
    "sg:phone":"+45 97 92 48 88",
    "sg:postcode":"7700",
    "sg:province":"Danmark",
    "wof:name":"\u00d8stbyens Cykel- & Knallertcenter",
    "wof:placetype":"venue"
},
  "geometry": {"coordinates":[8.7065420151,56.9566764832],"type":"Point"}
}