{
  "type": "Feature",
  "properties": {
    "addr:full":"N\u00f8rregade 17 Odense C Danmark 5000",
    "addr:housenumber":"17",
    "addr:postcode":"5000",
    "addr:street":"Norregade",
    "iso:country":"DK",
    "sg:address":"N\u00f8rregade 17",
    "sg:city":"Odense C",
    "sg:orig_category":"Garn",
    "sg:phone":"+45 66 11 11 01",
    "sg:postcode":"5000",
    "sg:province":"Danmark",
    "wof:name":"Gitte Marie",
    "wof:placetype":"venue"
},
  "geometry": {"coordinates":[10.3891448975,55.3976287842],"type":"Point"}
}