{
  "type": "Feature",
  "properties": {
    "addr:full":"Danmarksgade 49 Fredericia Danmark 7000",
    "addr:housenumber":"49",
    "addr:postcode":"7000",
    "addr:street":"Danmarksgade",
    "iso:country":"DK",
    "sg:address":"Danmarksgade 49",
    "sg:city":"Fredericia",
    "sg:classifiers":[
        {
            "category":"Food & Beverages",
            "subcategory":"Liquor & Beverages",
            "type":"Retail Goods"
        }
    ],
    "sg:phone":"+45 75 92 27 67",
    "sg:postcode":"7000",
    "sg:province":"Danmark",
    "sg:tags":[
        "vin"
    ],
    "wof:name":"Fredericia Vinhandel ApS",
    "wof:placetype":"venue"
},
  "geometry": {"coordinates":[9.7614278793,55.567150116],"type":"Point"}
}