{
  "type": "Feature",
  "properties": {
    "addr:full":"Ormslevvej 61 Viby Danmark 8260",
    "addr:housenumber":"61",
    "addr:postcode":"8260",
    "addr:street":"Ormslevvej",
    "iso:country":"DK",
    "sg:address":"Ormslevvej 61",
    "sg:city":"Viby",
    "sg:orig_category":"Servicestationer",
    "sg:phone":"+45 86 14 30 01",
    "sg:postcode":"8260",
    "sg:province":"Danmark",
    "wof:name":"Q8 Service",
    "wof:placetype":"venue"
},
  "geometry": {"coordinates":[10.1584768295,56.1303100586],"type":"Point"}
}