{
  "type": "Feature",
  "properties": {
    "addr:full":"Vodroffsvej 28 Frederiksberg Danmark 1900",
    "addr:housenumber":"28",
    "addr:postcode":"1900",
    "addr:street":"Vodroffsvej",
    "iso:country":"DK",
    "sg:address":"Vodroffsvej 28",
    "sg:city":"Frederiksberg",
    "sg:orig_category":"Bodegaer",
    "sg:phone":"+45 33 21 35 82",
    "sg:postcode":"1900",
    "sg:province":"Danmark",
    "wof:name":"Vodroffslund",
    "wof:placetype":"venue"
},
  "geometry": {"coordinates":[12.555062294,55.6784286499],"type":"Point"}
}