{
  "type": "Feature",
  "properties": {
    "addr:full":"Amager Boulevard 128 B K\u00f8benhavn S Danmark 2300",
    "addr:housenumber":"128 b",
    "addr:postcode":"2300",
    "addr:street":"Amager Boulevard;Kobenhavn S Danmark",
    "iso:country":"DK",
    "sg:address":"Amager Boulevard 128 B",
    "sg:city":"K\u00f8benhavn S",
    "sg:classifiers":[
        {
            "category":"Restaurant",
            "type":"Food & Drink"
        }
    ],
    "sg:phone":"+45 32 54 85 13",
    "sg:postcode":"2300",
    "sg:province":"Danmark",
    "wof:name":"Siam Orchid Thai Restaurant",
    "wof:placetype":"venue"
},
  "geometry": {"coordinates":[12.5925598145,55.6268196106],"type":"Point"}
}