{
  "type": "Feature",
  "properties": {
    "iso:country":"DK",
    "sg:address":"Dalgas Torv, Dalgas Alle 10",
    "sg:city":"Skive",
    "sg:classifiers":[
        {
            "category":"Banks & Credit Unions",
            "subcategory":"Bank",
            "type":"Services"
        }
    ],
    "sg:phone":"+45 97 52 37 66",
    "sg:postcode":"7800",
    "sg:province":"Danmark",
    "sg:tags":[
        "banker"
    ],
    "sg:website":"www.sallingbank.dk",
    "wof:name":"Salling Bank - Egeris Afd.",
    "wof:placetype":"venue"
},
  "geometry": {"coordinates":[9.014542,56.555256],"type":"Point"}
}