{
  "type": "Feature",
  "properties": {
    "addr:full":"Uglevej 6, Tranum Brovst Danmark 9460",
    "addr:housenumber":"6",
    "addr:postcode":"9460",
    "addr:street":"Uglevej;Tranum",
    "iso:country":"DK",
    "sg:address":"Uglevej 6, Tranum",
    "sg:city":"Brovst",
    "sg:orig_category":"Kommunale folkeskoler",
    "sg:phone":"+45 98 23 51 51",
    "sg:postcode":"9460",
    "sg:province":"Danmark",
    "sg:website":"www.tranum-skole-brovst.dk",
    "wof:name":"Tranum Skole",
    "wof:placetype":"venue"
},
  "geometry": {"coordinates":[9.5220241547,57.097366333],"type":"Point"}
}