{
  "type": "Feature",
  "properties": {
    "iso:country":"DK",
    "sg:address":"Storegade 7",
    "sg:city":"Outrup",
    "sg:orig_category":"Solcentre",
    "sg:phone":"+45 75 25 10 08",
    "sg:postcode":"6855",
    "sg:province":"Danmark",
    "wof:name":"Outrup Sol",
    "wof:placetype":"venue"
},
  "geometry": {"coordinates":[8.3448543549,55.7188911438],"type":"Point"}
}