{
  "type": "Feature",
  "properties": {
    "addr:full":"Bl\u00e6sbjerggade 2 A Kolding Danmark 6000",
    "addr:housenumber":"2 a",
    "addr:postcode":"6000",
    "addr:street":"Blaesbjerggade",
    "iso:country":"DK",
    "sg:address":"Bl\u00e6sbjerggade 2 A",
    "sg:city":"Kolding",
    "sg:orig_category":"Boligindretning",
    "sg:phone":"+45 75 50 88 87",
    "sg:postcode":"6000",
    "sg:province":"Danmark",
    "sg:website":"www.furiosa.dk",
    "wof:name":"Furiosa",
    "wof:placetype":"venue"
},
  "geometry": {"coordinates":[9.4710464478,55.4915313721],"type":"Point"}
}