{
  "type": "Feature",
  "properties": {
    "addr:full":"Hanstedvej 11 Horsens Danmark 8700",
    "addr:housenumber":"11",
    "addr:postcode":"8700",
    "addr:street":"Hanstedvej",
    "iso:country":"DK",
    "sg:address":"Hanstedvej 11",
    "sg:city":"Horsens",
    "sg:orig_category":"Vinduespolering",
    "sg:phone":"+45 75 62 35 98",
    "sg:postcode":"8700",
    "sg:province":"Danmark",
    "wof:name":"Allan's Vinduespolering",
    "wof:placetype":"venue"
},
  "geometry": {"coordinates":[9.8440637589,55.8962364197],"type":"Point"}
}