{
  "type": "Feature",
  "properties": {
    "addr:full":"Hobro Landevej 90 H, Tjele Tjele Danmark 8830",
    "addr:housenumber":"90 h",
    "addr:postcode":"8830",
    "addr:street":"Hobro Landevej",
    "iso:country":"DK",
    "sg:address":"Hobro Landevej 90 H, Tjele",
    "sg:city":"Tjele",
    "sg:classifiers":[
        {
            "category":"Restaurant",
            "type":"Food & Drink"
        }
    ],
    "sg:phone":"+45 86 65 22 46",
    "sg:postcode":"8830",
    "sg:province":"Danmark",
    "sg:website":"www.tjele-gods.dk",
    "wof:name":"Marie Grubbe",
    "wof:placetype":"venue"
},
  "geometry": {"coordinates":[9.6264801025,56.4818611145],"type":"Point"}
}