{
  "type": "Feature",
  "properties": {
    "addr:full":"Hedager 52 Greve Danmark 2670",
    "addr:housenumber":"52",
    "addr:postcode":"2670",
    "addr:street":"Hedager",
    "iso:country":"DK",
    "sg:address":"Hedager 52",
    "sg:city":"Greve",
    "sg:orig_category":"Arkitekter",
    "sg:phone":"+45 43 90 16 86",
    "sg:postcode":"2670",
    "sg:province":"Danmark",
    "wof:name":"Thomsen, Peter",
    "wof:placetype":"venue"
},
  "geometry": {"coordinates":[12.3084611893,55.5940208435],"type":"Point"}
}