{
  "type": "Feature",
  "properties": {
    "addr:full":"N\u00f8rrebrogade 14A K\u00f8benhavn N Danmark 2200",
    "addr:housenumber":"14a kobenhavn",
    "addr:postcode":"2200",
    "addr:street":"Norrebrogade;N Danmark",
    "iso:country":"DK",
    "sg:address":"N\u00f8rrebrogade 14A",
    "sg:city":"K\u00f8benhavn N",
    "sg:orig_category":"Rejsebureauer",
    "sg:phone":"+45 35 36 33 48",
    "sg:postcode":"2200",
    "sg:province":"Danmark",
    "wof:name":"Nimbus Travel",
    "wof:placetype":"venue"
},
  "geometry": {"coordinates":[-76.4314880371,37.463104248],"type":"Point"}
}