{
  "type": "Feature",
  "properties": {
    "addr:full":"Skamlingvejen 145 Bjert Danmark 6091",
    "addr:housenumber":"145",
    "addr:postcode":"6091",
    "addr:street":"Skamlingvejen",
    "iso:country":"DK",
    "sg:address":"Skamlingvejen 145",
    "sg:city":"Bjert",
    "sg:orig_category":"Campingpladser",
    "sg:phone":"+45 75 57 21 05",
    "sg:postcode":"6091",
    "sg:province":"Danmark",
    "wof:name":"Skamling Camping",
    "wof:placetype":"venue"
},
  "geometry": {"coordinates":[9.5625591278,55.4214363098],"type":"Point"}
}