{
  "type": "Feature",
  "properties": {
    "addr:full":"S\u00f8nder Alle 30 \u00c5rhus C Danmark 8000",
    "addr:housenumber":"30",
    "addr:postcode":"8000",
    "addr:street":"Sonder Alle",
    "iso:country":"DK",
    "sg:address":"S\u00f8nder Alle 30",
    "sg:city":"\u00c5rhus C",
    "sg:orig_category":"Telebutikker",
    "sg:phone":"+45 86 19 78 78",
    "sg:postcode":"8000",
    "sg:province":"Danmark",
    "wof:name":"Telekiosken og Phone Home Butik",
    "wof:placetype":"venue"
},
  "geometry": {"coordinates":[4.717400074,49.7588005066],"type":"Point"}
}