{
  "type": "Feature",
  "properties": {
    "addr:full":"Baneg\u00e5rdsgade 2 Odder Danmark 8300",
    "addr:housenumber":"2",
    "addr:postcode":"8300",
    "addr:street":"Banegaardsgade",
    "iso:country":"DK",
    "sg:address":"Baneg\u00e5rdsgade 2",
    "sg:city":"Odder",
    "sg:classifiers":[
        {
            "category":"Banks & Credit Unions",
            "subcategory":"Bank",
            "type":"Services"
        }
    ],
    "sg:phone":"+45 86 54 00 00",
    "sg:postcode":"8300",
    "sg:province":"Danmark",
    "sg:tags":[
        "banker"
    ],
    "wof:name":"Nordea",
    "wof:placetype":"venue"
},
  "geometry": {"coordinates":[10.1494407654,55.972454071],"type":"Point"}
}