{
  "type": "Feature",
  "properties": {
    "addr:full":"H\u00f8jagervej 4, Jejsing T\u00f8nder Danmark 6270",
    "addr:housenumber":"4",
    "addr:postcode":"6270",
    "addr:street":"Hojagervej",
    "iso:country":"DK",
    "sg:address":"H\u00f8jagervej 4, Jejsing",
    "sg:city":"T\u00f8nder",
    "sg:orig_category":"Malermestre",
    "sg:phone":"+45 74 73 43 76",
    "sg:postcode":"6270",
    "sg:province":"Danmark",
    "wof:name":"Jacobsen Malerforretning, Robert",
    "wof:placetype":"venue"
},
  "geometry": {"coordinates":[8.9661502838,54.9350318909],"type":"Point"}
}