{
  "type": "Feature",
  "properties": {
    "iso:country":"DK",
    "sg:address":"Voldgade 14 A",
    "sg:city":"Skive",
    "sg:classifiers":[
        {
            "category":"Building & Trades",
            "subcategory":"Construction",
            "type":"Services"
        }
    ],
    "sg:phone":"+45 97 52 67 37",
    "sg:postcode":"7800",
    "sg:province":"Danmark",
    "sg:tags":[
        "ventilation"
    ],
    "wof:name":"St\u00e6rk, J. P. & H. J.",
    "wof:placetype":"venue"
},
  "geometry": {"coordinates":[9.03074646,56.5679550171],"type":"Point"}
}