{
  "type": "Feature",
  "properties": {
    "addr:full":"Hovedgaden 54 Tisvildeleje Danmark 3220",
    "addr:housenumber":"54",
    "addr:postcode":"3220",
    "addr:street":"Hovedgaden",
    "iso:country":"DK",
    "sg:address":"Hovedgaden 54",
    "sg:city":"Tisvildeleje",
    "sg:orig_category":"Benzinstationer",
    "sg:phone":"+45 48 70 80 13",
    "sg:postcode":"3220",
    "sg:province":"Danmark",
    "wof:name":"Hydro-Texaco",
    "wof:placetype":"venue"
},
  "geometry": {"coordinates":[12.074582,56.059814],"type":"Point"}
}