{
  "type": "Feature",
  "properties": {
    "addr:full":"Finderupvej 4 \u00c5rhus C Danmark 8000",
    "addr:housenumber":"4",
    "addr:postcode":"8000",
    "addr:street":"Finderupvej",
    "iso:country":"DK",
    "sg:address":"Finderupvej 4",
    "sg:city":"\u00c5rhus C",
    "sg:orig_category":"Autoreparation og -service",
    "sg:phone":"+45 86 15 85 88",
    "sg:postcode":"8000",
    "sg:province":"Danmark",
    "wof:name":"S\u00f8ndergaards Eftf. ApS, K.",
    "wof:placetype":"venue"
},
  "geometry": {"coordinates":[4.717400074,49.7588005066],"type":"Point"}
}