{
  "type": "Feature",
  "properties": {
    "addr:full":"Stadionalle 4 Rungsted Kyst Danmark 2960",
    "addr:housenumber":"4",
    "addr:postcode":"2960",
    "addr:street":"Stadionalle",
    "iso:country":"DK",
    "sg:address":"Stadionalle 4",
    "sg:city":"Rungsted Kyst",
    "sg:orig_category":"Integrerede institutioner",
    "sg:phone":"+45 45 86 54 12",
    "sg:postcode":"2960",
    "sg:province":"Danmark",
    "wof:name":"\u00c6bleg\u00e5rden",
    "wof:placetype":"venue"
},
  "geometry": {"coordinates":[12.5173864365,55.8935317993],"type":"Point"}
}