{
  "type": "Feature",
  "properties": {
    "addr:full":"Kredsleder: John Michaelsen, Kalkv\u00e6rksvej 6, Helligkilde Thyholm Danmark 7790",
    "addr:housenumber":"6",
    "addr:postcode":"7790",
    "addr:street":"Kalkvaerksvej",
    "iso:country":"DK",
    "sg:address":"Kredsleder: John Michaelsen, Kalkv\u00e6rksvej 6, Helligkilde",
    "sg:city":"Thyholm",
    "sg:orig_category":"Spejderkorps",
    "sg:phone":"+45 97 87 19 59",
    "sg:postcode":"7790",
    "sg:province":"Danmark",
    "wof:name":"FDF Thyholm",
    "wof:placetype":"venue"
},
  "geometry": {"coordinates":[8.525765419,56.6507072449],"type":"Point"}
}