{
  "type": "Feature",
  "properties": {
    "iso:country":"DK",
    "sg:address":"Ankersgade 12, 1.",
    "sg:city":"\u00c5rhus C",
    "sg:orig_category":"Bedriftssundhedstjenester",
    "sg:phone":"+45 87 31 04 50",
    "sg:postcode":"8000",
    "sg:province":"Danmark",
    "wof:name":"Post Danmark, Arbejdsmilj\u00f8- og Personaler\u00e5dgivning",
    "wof:placetype":"venue"
},
  "geometry": {"coordinates":[4.7174,49.758801],"type":"Point"}
}