{
  "type": "Feature",
  "properties": {
    "iso:country":"DK",
    "sg:address":"Glenstrup S\u00f8vej 36, Glenstrup",
    "sg:city":"F\u00e5rup",
    "sg:orig_category":"Kirker",
    "sg:postcode":"8990",
    "sg:province":"Danmark",
    "wof:name":"Glenstrup Kirke",
    "wof:placetype":"venue"
},
  "geometry": {"coordinates":[-93.1630935669,32.8507347107],"type":"Point"}
}