{
  "type": "Feature",
  "properties": {
    "iso:country":"DK",
    "sg:address":"Sognepr\u00e6st: Lissi Aastrup Andersen (K/B), Ringstedvej 66",
    "sg:city":"Fjenneslev",
    "sg:orig_category":"Kirkesogne",
    "sg:phone":"+45 57 80 92 74",
    "sg:postcode":"4173",
    "sg:province":"Danmark",
    "wof:name":"Slaglille, Bjernede, Alsted, og Fjenneslev Sogne",
    "wof:placetype":"venue"
},
  "geometry": {"coordinates":[11.6678848267,55.4402961731],"type":"Point"}
}