{
  "type": "Feature",
  "properties": {
    "addr:full":"Vestergade 14 Vestervig Danmark 7770",
    "addr:housenumber":"14",
    "addr:postcode":"7770",
    "addr:street":"Vestergade",
    "iso:country":"DK",
    "sg:address":"Vestergade 14",
    "sg:city":"Vestervig",
    "sg:orig_category":"Varmeforsyning",
    "sg:phone":"+45 97 94 12 88",
    "sg:postcode":"7770",
    "sg:province":"Danmark",
    "wof:name":"Vestervig Fjernvarmev\u00e6rk",
    "wof:placetype":"venue"
},
  "geometry": {"coordinates":[8.3176498413,56.7627029419],"type":"Point"}
}