{
  "type": "Feature",
  "properties": {
    "iso:country":"DK",
    "sg:address":"Kirksvej 2, Bjerregaard",
    "sg:city":"Hvide Sande",
    "sg:orig_category":"Sommerhusudlejning",
    "sg:phone":"+45 97 31 50 35",
    "sg:postcode":"6960",
    "sg:province":"Danmark",
    "wof:name":"Jensen, Ulla Kirk",
    "wof:placetype":"venue"
},
  "geometry": {"coordinates":[8.1222438812,56.0879821777],"type":"Point"}
}