{
  "type": "Feature",
  "properties": {
    "iso:country":"DK",
    "sg:address":"Hovedgaden 81",
    "sg:city":"Svinninge",
    "sg:orig_category":"Blikkenslagere",
    "sg:phone":"+45 59 26 52 90",
    "sg:postcode":"4520",
    "sg:province":"Danmark",
    "wof:name":"Svinninge Varmeservice ApS",
    "wof:placetype":"venue"
},
  "geometry": {"coordinates":[11.458123,55.721596],"type":"Point"}
}