{
  "type": "Feature",
  "properties": {
    "addr:full":"Jorcks Passage A 4 K\u00f8benhavn Danmark 1162",
    "addr:housenumber":"4;1162",
    "addr:street":"Passage A",
    "iso:country":"DK",
    "sg:address":"Jorcks Passage A 4",
    "sg:city":"K\u00f8benhavn",
    "sg:orig_category":"Geoteknik",
    "sg:phone":"+45 33 14 73 33",
    "sg:postcode":"1162",
    "sg:province":"Danmark",
    "sg:website":"www.bakeratlas.com",
    "wof:name":"Baker Atlas Geoscience",
    "wof:placetype":"venue"
},
  "geometry": {"coordinates":[12.5770998001,55.6783981323],"type":"Point"}
}