{
  "type": "Feature",
  "properties": {
    "addr:full":"Lindevej 2 A, \u00d8ster Lindet R\u00f8dding Danmark 6630",
    "addr:housenumber":"2 a",
    "addr:postcode":"6630",
    "addr:street":"Lindevej;Lindet;Danmark",
    "iso:country":"DK",
    "sg:address":"Lindevej 2 A, \u00d8ster Lindet",
    "sg:city":"R\u00f8dding",
    "sg:orig_category":"Servicestationer",
    "sg:phone":"+45 74 84 63 78",
    "sg:postcode":"6630",
    "sg:province":"Danmark",
    "wof:name":"Uno x",
    "wof:placetype":"venue"
},
  "geometry": {"coordinates":[9.2022953033,55.3564414978],"type":"Point"}
}