{
  "type": "Feature",
  "properties": {
    "iso:country":"DK",
    "sg:address":"B\u00f8llundvej 8",
    "sg:city":"Brande",
    "sg:orig_category":"Maskinudlejning",
    "sg:phone":"+45 97 18 47 48",
    "sg:postcode":"7330",
    "sg:province":"Danmark",
    "wof:name":"Brande Maskinudlejning",
    "wof:placetype":"venue"
},
  "geometry": {"coordinates":[9.1396799088,55.9102973938],"type":"Point"}
}