{
  "type": "Feature",
  "properties": {
    "addr:full":"Holmbjergvej 95 A, Knebelbro Knebel Danmark 8420",
    "addr:housenumber":"95 a",
    "addr:postcode":"8420",
    "addr:street":"Holmbjergvej;Knebelbro",
    "iso:country":"DK",
    "sg:address":"Holmbjergvej 95 A, Knebelbro",
    "sg:city":"Knebel",
    "sg:orig_category":"Gallerier",
    "sg:phone":"+45 86 35 00 88",
    "sg:postcode":"8420",
    "sg:province":"Danmark",
    "wof:name":"Babette, Galleri",
    "wof:placetype":"venue"
},
  "geometry": {"coordinates":[10.3770122528,56.1816596985],"type":"Point"}
}