{
  "type": "Feature",
  "properties": {
    "addr:full":"Fmd.: Svend Kristiansen, \u00d8sterbyvej 32 H\u00f8jer Danmark 6280",
    "addr:housenumber":"32",
    "addr:postcode":"6280",
    "addr:street":"Osterbyvej",
    "iso:country":"DK",
    "sg:address":"Fmd.: Svend Kristiansen, \u00d8sterbyvej 32",
    "sg:city":"H\u00f8jer",
    "sg:orig_category":"Kulturelle foreninger",
    "sg:phone":"+45 74 78 32 15",
    "sg:postcode":"6280",
    "sg:province":"Danmark",
    "wof:name":"H\u00f8jeregnens Lokalhistoriske Forening",
    "wof:placetype":"venue"
},
  "geometry": {"coordinates":[-2.1972899437,49.2049789429],"type":"Point"}
}