{
  "type": "Feature",
  "properties": {
    "addr:full":"Fmd.: Gdr. Knud H. Jensen, N\u00e6bler\u00f8dvej 24 Fuglebjerg Danmark 4250",
    "addr:housenumber":"24",
    "addr:postcode":"4250",
    "addr:street":"Knud H. Jensen Naeblerodvej",
    "iso:country":"DK",
    "sg:address":"Fmd.: Gdr. Knud H. Jensen, N\u00e6bler\u00f8dvej 24",
    "sg:city":"Fuglebjerg",
    "sg:orig_category":"Kulturelle foreninger",
    "sg:phone":"+45 57 84 92 68",
    "sg:postcode":"4250",
    "sg:province":"Danmark",
    "wof:name":"Kristelig Lytter-og Fjernseerforening, Haldagerlille",
    "wof:placetype":"venue"
},
  "geometry": {"coordinates":[11.5452251434,55.3061332703],"type":"Point"}
}