{
  "type": "Feature",
  "properties": {
    "addr:full":"Liden Gunvers Vej 12 Vejle Danmark 7100",
    "addr:housenumber":"12",
    "addr:postcode":"7100",
    "addr:street":"Liden Gunvers Vej",
    "iso:country":"DK",
    "sg:address":"Liden Gunvers Vej 12",
    "sg:city":"Vejle",
    "sg:orig_category":"Psykologer, praktiserende",
    "sg:phone":"+45 75 72 72 08",
    "sg:postcode":"7100",
    "sg:province":"Danmark",
    "wof:name":"Astrup, Erna-Kirstine Berg",
    "wof:placetype":"venue"
},
  "geometry": {"coordinates":[9.5501365662,55.6854286194],"type":"Point"}
}