{
  "type": "Feature",
  "properties": {
    "addr:full":"N\u00f8rremarksvej 2 A Tarm Danmark 6880",
    "addr:housenumber":"2 a",
    "addr:postcode":"6880",
    "addr:street":"Norremarksvej",
    "iso:country":"DK",
    "sg:address":"N\u00f8rremarksvej 2 A",
    "sg:city":"Tarm",
    "sg:orig_category":"Havebrugsmaskiner",
    "sg:phone":"+45 97 37 34 50",
    "sg:postcode":"6880",
    "sg:province":"Danmark",
    "sg:website":"www.ek-mantis.dk",
    "wof:name":"EK Maskiner ApS",
    "wof:placetype":"venue"
},
  "geometry": {"coordinates":[8.5349349976,55.9118804932],"type":"Point"}
}