{
  "type": "Feature",
  "properties": {
    "iso:country":"DK",
    "sg:address":"Fmd.: Dine Nielsen, Skolegade 50",
    "sg:city":"Holsted",
    "sg:orig_category":"Kulturelle foreninger",
    "sg:phone":"+45 75 39 22 99",
    "sg:postcode":"6670",
    "sg:province":"Danmark",
    "wof:name":"Holsted Kommunale Musikskoles St\u00f8tteforening",
    "wof:placetype":"venue"
},
  "geometry": {"coordinates":[8.9169273376,55.5111999512],"type":"Point"}
}