{
  "type": "Feature",
  "properties": {
    "iso:country":"DK",
    "sg:address":"Str\u00e6det 6, Str\u00f8by Egede",
    "sg:city":"K\u00f8ge",
    "sg:orig_category":"\u00c3\u02dcvrige skoler",
    "sg:phone":"+45 56 26 67 51",
    "sg:postcode":"4600",
    "sg:province":"Danmark",
    "wof:name":"FEGU L\u00e6seskole",
    "wof:placetype":"venue"
},
  "geometry": {"coordinates":[6.4543700218,52.4404983521],"type":"Point"}
}