{
  "type": "Feature",
  "properties": {
    "iso:country":"DK",
    "sg:address":"Skovvej 10",
    "sg:city":"Ullerslev",
    "sg:classifiers":[
        {
            "category":"Food & Beverages",
            "subcategory":"Liquor & Beverages",
            "type":"Retail Goods"
        }
    ],
    "sg:phone":"+45 65 35 13 22",
    "sg:postcode":"5540",
    "sg:province":"Danmark",
    "sg:tags":[
        "vin"
    ],
    "wof:name":"Madsen & Riis Vin",
    "wof:placetype":"venue"
},
  "geometry": {"coordinates":[10.660993576,55.3580322266],"type":"Point"}
}