{
  "type": "Feature",
  "properties": {
    "addr:full":"Leder: Inge Marie Holst, Torvet 13 A Kalundborg Danmark 4400",
    "addr:housenumber":"13 a",
    "addr:postcode":"4400",
    "addr:street":"Torvet",
    "iso:country":"DK",
    "sg:address":"Leder: Inge Marie Holst, Torvet 13 A",
    "sg:city":"Kalundborg",
    "sg:orig_category":"Oplysningsforbund",
    "sg:phone":"+45 59 51 40 68",
    "sg:postcode":"4400",
    "sg:province":"Danmark",
    "wof:name":"Aftenskolen p\u00e5 Sigrid Undset Skolen",
    "wof:placetype":"venue"
},
  "geometry": {"coordinates":[11.0934085846,55.6797485352],"type":"Point"}
}