{
  "type": "Feature",
  "properties": {
    "addr:full":"B\u00f8nderg\u00e5rdsvej 6 Esbjerg Danmark 6700",
    "addr:housenumber":"6",
    "addr:postcode":"6700",
    "addr:street":"Bondergaardsvej",
    "iso:country":"DK",
    "sg:address":"B\u00f8nderg\u00e5rdsvej 6",
    "sg:city":"Esbjerg",
    "sg:orig_category":"Fritidsklubber",
    "sg:phone":"+45 75 45 28 13",
    "sg:postcode":"6700",
    "sg:province":"Danmark",
    "wof:name":"Klub B\u00f8nderg\u00e5rdsvej",
    "wof:placetype":"venue"
},
  "geometry": {"coordinates":[8.456905365,55.465221405],"type":"Point"}
}