{
  "type": "Feature",
  "properties": {
    "addr:full":"Ormslevvej 269 Viby Danmark 8260",
    "addr:housenumber":"269",
    "addr:postcode":"8260",
    "addr:street":"Ormslevvej",
    "iso:country":"DK",
    "sg:address":"Ormslevvej 269",
    "sg:city":"Viby",
    "sg:classifiers":[
        {
            "category":"Professional",
            "subcategory":"Advertising",
            "type":"Services"
        }
    ],
    "sg:phone":"+45 86 29 37 73",
    "sg:postcode":"8260",
    "sg:province":"Danmark",
    "sg:tags":[
        "marketing"
    ],
    "sg:website":"www.hjem.get2net.dk/b-jop",
    "wof:name":"B - Jop",
    "wof:placetype":"venue"
},
  "geometry": {"coordinates":[10.1175460815,56.1283912659],"type":"Point"}
}