{
  "type": "Feature",
  "properties": {
    "addr:full":"Fmd.: John Larsen, Sall\u00f8v Gade 5 Gadstrup Danmark 4621",
    "addr:housenumber":"5",
    "addr:postcode":"4621",
    "addr:street":"Sallov Gade",
    "iso:country":"DK",
    "sg:address":"Fmd.: John Larsen, Sall\u00f8v Gade 5",
    "sg:city":"Gadstrup",
    "sg:orig_category":"Borger- og beboerforeninger",
    "sg:phone":"+45 46 19 12 28",
    "sg:postcode":"4621",
    "sg:province":"Danmark",
    "wof:name":"Snoldelev Sogns Borgerforening",
    "wof:placetype":"venue"
},
  "geometry": {"coordinates":[12.0978450775,55.5737800598],"type":"Point"}
}