{
  "type": "Feature",
  "properties": {
    "iso:country":"DK",
    "sg:address":"Kalsensgaardsvej 6",
    "sg:city":"Pandrup",
    "sg:orig_category":"Dag- og distriktsblade",
    "sg:phone":"+45 98 24 77 44",
    "sg:postcode":"9490",
    "sg:province":"Danmark",
    "sg:website":"www.lokalsyd.dk",
    "wof:name":"Sydvestvendsyssel, Lokalavisen",
    "wof:placetype":"venue"
},
  "geometry": {"coordinates":[9.6783437729,57.2099571228],"type":"Point"}
}