{
  "type": "Feature",
  "properties": {
    "iso:country":"DK",
    "sg:address":"B\u00f8gstedvej 271, Astrup",
    "sg:city":"Hj\u00f8rring",
    "sg:orig_category":"Ungdomsklubber",
    "sg:postcode":"9800",
    "sg:province":"Danmark",
    "wof:name":"Astrup Ungdomsklub",
    "wof:placetype":"venue"
},
  "geometry": {"coordinates":[9.9885387421,57.4594764709],"type":"Point"}
}