{
  "type": "Feature",
  "properties": {
    "addr:full":"Fmd.: Henrik Larsen, Gjerager 37 Tarm Danmark 6880",
    "addr:housenumber":"37",
    "addr:postcode":"6880",
    "addr:street":"Henrik Larsen Gjerager",
    "iso:country":"DK",
    "sg:address":"Fmd.: Henrik Larsen, Gjerager 37",
    "sg:city":"Tarm",
    "sg:orig_category":"Grundejerforeninger",
    "sg:phone":"+45 97 37 33 22",
    "sg:postcode":"6880",
    "sg:province":"Danmark",
    "wof:name":"Sofieshvile Beboer- og Grundejerforening",
    "wof:placetype":"venue"
},
  "geometry": {"coordinates":[8.5200052261,55.9060554504],"type":"Point"}
}