{
  "type": "Feature",
  "properties": {
    "addr:full":"Fmd.: Grete Larsen, Moseholmv\u00e6nget 21, Nr. Broby Broby Danmark 5672",
    "addr:housenumber":"21",
    "addr:postcode":"5672",
    "addr:street":"Fmd.;Nr. Broby",
    "iso:country":"DK",
    "sg:address":"Fmd.: Grete Larsen, Moseholmv\u00e6nget 21, Nr. Broby",
    "sg:city":"Broby",
    "sg:orig_category":"\u00c3\u2020ldreorganisationer og klubber",
    "sg:postcode":"5672",
    "sg:province":"Danmark",
    "wof:name":"Aktive \u00c6ldre",
    "wof:placetype":"venue"
},
  "geometry": {"coordinates":[10.3131303787,55.2695846558],"type":"Point"}
}