{
  "type": "Feature",
  "properties": {
    "addr:full":"Haderslevvej 35 Aabenraa Danmark 6200",
    "addr:housenumber":"35",
    "addr:postcode":"6200",
    "addr:street":"Haderslevvej",
    "iso:country":"DK",
    "sg:address":"Haderslevvej 35",
    "sg:city":"Aabenraa",
    "sg:orig_category":"Loger",
    "sg:phone":"+45 74 62 23 75",
    "sg:postcode":"6200",
    "sg:province":"Danmark",
    "wof:name":"Frimurerlogen Sct. Nicolaus",
    "wof:placetype":"venue"
},
  "geometry": {"coordinates":[9.4246559143,55.0535926819],"type":"Point"}
}