{
  "type": "Feature",
  "properties": {
    "addr:full":"Rorupvej 17 A, Rorup Lejre Danmark 4320",
    "addr:housenumber":"17 a",
    "addr:postcode":"4320",
    "addr:street":"Rorupvej;Rorup",
    "iso:country":"DK",
    "sg:address":"Rorupvej 17 A, Rorup",
    "sg:city":"Lejre",
    "sg:orig_category":"Kirker",
    "sg:postcode":"4320",
    "sg:province":"Danmark",
    "wof:name":"Rorup Kirke",
    "wof:placetype":"venue"
},
  "geometry": {"coordinates":[11.9678316116,55.6005630493],"type":"Point"}
}