{
  "type": "Feature",
  "properties": {
    "addr:full":"Haderslevvej 14 Christiansfeld Danmark 6070",
    "addr:housenumber":"14",
    "addr:postcode":"6070",
    "addr:street":"Haderslevvej",
    "iso:country":"DK",
    "sg:address":"Haderslevvej 14",
    "sg:city":"Christiansfeld",
    "sg:orig_category":"Faglige organisationer og foreninger",
    "sg:phone":"+45 74 56 14 27",
    "sg:postcode":"6070",
    "sg:province":"Danmark",
    "wof:name":"SID Christiansfeld Afdeling",
    "wof:placetype":"venue"
},
  "geometry": {"coordinates":[9.4838314056,55.3515625],"type":"Point"}
}