{
  "type": "Feature",
  "properties": {
    "addr:full":"Nyvej 50 Sandved Danmark 4262",
    "addr:housenumber":"50",
    "addr:postcode":"4262",
    "addr:street":"Nyvej",
    "iso:country":"DK",
    "sg:address":"Nyvej 50",
    "sg:city":"Sandved",
    "sg:orig_category":"Arkitekter",
    "sg:phone":"+45 55 45 66 33",
    "sg:postcode":"4262",
    "sg:province":"Danmark",
    "wof:name":"Hansen, Niels C.",
    "wof:placetype":"venue"
},
  "geometry": {"coordinates":[11.5387411118,55.2632217407],"type":"Point"}
}