{
  "type": "Feature",
  "properties": {
    "addr:full":"Jomfrustien 6 Haderslev Danmark 6100",
    "addr:housenumber":"6",
    "addr:postcode":"6100",
    "addr:street":"Jomfrustien",
    "iso:country":"DK",
    "sg:address":"Jomfrustien 6",
    "sg:city":"Haderslev",
    "sg:orig_category":"Regnskabsassistance",
    "sg:phone":"+45 73 52 00 62",
    "sg:postcode":"6100",
    "sg:province":"Danmark",
    "sg:website":"www.hmadm.dk",
    "wof:name":"HM Administration ApS",
    "wof:placetype":"venue"
},
  "geometry": {"coordinates":[9.4891729355,55.2508468628],"type":"Point"}
}