{
  "type": "Feature",
  "properties": {
    "addr:full":"Syrenv\u00e6nget 20 Karise Danmark 4653",
    "addr:housenumber":"20",
    "addr:postcode":"4653",
    "addr:street":"Syrenvaenget",
    "iso:country":"DK",
    "sg:address":"Syrenv\u00e6nget 20",
    "sg:city":"Karise",
    "sg:orig_category":"Postbutikker",
    "sg:phone":"+45 56 78 80 07",
    "sg:postcode":"4653",
    "sg:province":"Danmark",
    "wof:name":"Post Danmark, Karise Postbutik",
    "wof:placetype":"venue"
},
  "geometry": {"coordinates":[12.1990203857,55.3030395508],"type":"Point"}
}