{
  "type": "Feature",
  "properties": {
    "addr:full":"Tv\u00e6rgade 20 Nyk\u00f8bing Danmark 4800",
    "addr:housenumber":"20",
    "addr:postcode":"4800",
    "addr:street":"Tvaergade",
    "iso:country":"DK",
    "sg:address":"Tv\u00e6rgade 20",
    "sg:city":"Nyk\u00f8bing",
    "sg:orig_category":"Dag- og distriktsblade",
    "sg:phone":"+45 54 88 02 00",
    "sg:postcode":"4800",
    "sg:province":"Danmark",
    "sg:website":"www.folketidende.dk",
    "wof:name":"Lolland-Falsters Folketidende A/S",
    "wof:placetype":"venue"
},
  "geometry": {"coordinates":[-114.0768203735,46.4432411194],"type":"Point"}
}