{
  "type": "Feature",
  "properties": {
    "addr:full":"Kongensgade 70 Esbjerg Danmark 6700",
    "addr:housenumber":"70",
    "addr:postcode":"6700",
    "addr:street":"Kongensgade",
    "iso:country":"DK",
    "sg:address":"Kongensgade 70",
    "sg:city":"Esbjerg",
    "sg:orig_category":"Advokater",
    "sg:phone":"+45 75 45 46 00",
    "sg:postcode":"6700",
    "sg:province":"Danmark",
    "wof:name":"Dahl Koch & Boll, Advokatfirmaet",
    "wof:placetype":"venue"
},
  "geometry": {"coordinates":[8.4483337402,55.4662437439],"type":"Point"}
}