{
  "type": "Feature",
  "properties": {
    "addr:full":"Torvet 3 B\u00e6lum Danmark 9574",
    "addr:housenumber":"3",
    "addr:postcode":"9574",
    "addr:street":"Torvet",
    "iso:country":"DK",
    "sg:address":"Torvet 3",
    "sg:city":"B\u00e6lum",
    "sg:orig_category":"Sparekasser",
    "sg:phone":"+45 96 82 11 00",
    "sg:postcode":"9574",
    "sg:province":"Danmark",
    "wof:name":"Spar Nord Bank A/S",
    "wof:placetype":"venue"
},
  "geometry": {"coordinates":[-83.14971160890001,43.0994567871],"type":"Point"}
}