{
  "type": "Feature",
  "properties": {
    "addr:full":"Kofod Anchers Vej 40 Esperg\u00e6rde Danmark 3060",
    "addr:housenumber":"40",
    "addr:postcode":"3060",
    "addr:street":"Kofod Anchers Vej",
    "iso:country":"DK",
    "sg:address":"Kofod Anchers Vej 40",
    "sg:city":"Esperg\u00e6rde",
    "sg:orig_category":"Fodterapeuter",
    "sg:phone":"+45 49 13 28 18",
    "sg:postcode":"3060",
    "sg:province":"Danmark",
    "wof:name":"Klinik For Fodterapi",
    "wof:placetype":"venue"
},
  "geometry": {"coordinates":[11.6512403488,47.8390617371],"type":"Point"}
}