{
  "type": "Feature",
  "properties": {
    "addr:full":"Hammelvej 238, B\u00f8strup Lang\u00e5 Danmark 8870",
    "addr:housenumber":"238",
    "addr:postcode":"8870",
    "addr:street":"Hammelvej",
    "iso:country":"DK",
    "sg:address":"Hammelvej 238, B\u00f8strup",
    "sg:city":"Lang\u00e5",
    "sg:orig_category":"Systuer",
    "sg:phone":"+45 86 96 41 10",
    "sg:postcode":"8870",
    "sg:province":"Danmark",
    "wof:name":"Jensen, Birthe Haudrum",
    "wof:placetype":"venue"
},
  "geometry": {"coordinates":[9.8955049515,56.3900756836],"type":"Point"}
}