{
  "type": "Feature",
  "properties": {
    "addr:full":"Sydhalevej 2 Thybor\u00f8n Danmark 7680",
    "addr:housenumber":"2",
    "addr:postcode":"7680",
    "addr:street":"Sydhalevej",
    "iso:country":"DK",
    "sg:address":"Sydhalevej 2",
    "sg:city":"Thybor\u00f8n",
    "sg:orig_category":"Fiskeindustri",
    "sg:phone":"+45 97 83 22 33",
    "sg:postcode":"7680",
    "sg:province":"Danmark",
    "wof:name":"Vivapesca I/S",
    "wof:placetype":"venue"
},
  "geometry": {"coordinates":[8.2167577744,56.7016296387],"type":"Point"}
}