{
  "type": "Feature",
  "properties": {
    "addr:full":"Doverh\u00f8jvej 12, Gundersted Nibe Danmark 9240",
    "addr:housenumber":"12",
    "addr:postcode":"9240",
    "addr:street":"Doverhojvej;Gundersted",
    "iso:country":"DK",
    "sg:address":"Doverh\u00f8jvej 12, Gundersted",
    "sg:city":"Nibe",
    "sg:orig_category":"Stutterier",
    "sg:phone":"+45 98 66 90 57",
    "sg:postcode":"9240",
    "sg:province":"Danmark",
    "wof:name":"Stutteri Doverh\u00f8j",
    "wof:placetype":"venue"
},
  "geometry": {"coordinates":[9.6393280029,56.982421875],"type":"Point"}
}