{
  "type": "Feature",
  "properties": {
    "addr:full":"Skolev\u00e6nget 14, Ryde Kirkeby Vinderup Danmark 7830",
    "addr:housenumber":"14",
    "addr:postcode":"7830",
    "addr:street":"Skolevaenget;Kirkeby",
    "iso:country":"DK",
    "sg:address":"Skolev\u00e6nget 14, Ryde Kirkeby",
    "sg:city":"Vinderup",
    "sg:orig_category":"Kommunale folkeskoler",
    "sg:phone":"+45 97 44 01 16",
    "sg:postcode":"7830",
    "sg:province":"Danmark",
    "sg:website":"www.ryde-skole.dk",
    "wof:name":"Ryde Skole",
    "wof:placetype":"venue"
},
  "geometry": {"coordinates":[8.7796897888,56.482635498],"type":"Point"}
}