{
  "type": "Feature",
  "properties": {
    "addr:full":"Batterivej 4, Nordby Fan\u00f8 Danmark 6720",
    "addr:housenumber":"4",
    "addr:postcode":"6720",
    "addr:street":"Batterivej",
    "iso:country":"DK",
    "sg:address":"Batterivej 4, Nordby",
    "sg:city":"Fan\u00f8",
    "sg:classifiers":[
        {
            "category":"Taxi",
            "type":"Transportation"
        }
    ],
    "sg:phone":"+45 75 16 62 00",
    "sg:postcode":"6720",
    "sg:province":"Danmark",
    "wof:name":"Fan\u00f8 Taxi",
    "wof:placetype":"venue"
},
  "geometry": {"coordinates":[8.4069461823,55.4484786987],"type":"Point"}
}