{
  "type": "Feature",
  "properties": {
    "iso:country":"DK",
    "sg:address":"Vigerslevvej 244",
    "sg:city":"Valby",
    "sg:orig_category":"Belysning",
    "sg:phone":"+45 36 16 27 27",
    "sg:postcode":"2500",
    "sg:province":"Danmark",
    "wof:name":"Prolite",
    "wof:placetype":"venue"
},
  "geometry": {"coordinates":[12.488487,55.652328],"type":"Point"}
}