{
  "type": "Feature",
  "properties": {
    "addr:full":"Torupvejen 151 Hundested Danmark 3390",
    "addr:housenumber":"151",
    "addr:postcode":"3390",
    "addr:street":"Torupvejen",
    "iso:country":"DK",
    "sg:address":"Torupvejen 151",
    "sg:city":"Hundested",
    "sg:orig_category":"Kirker",
    "sg:postcode":"3390",
    "sg:province":"Danmark",
    "wof:name":"Torup Kirke",
    "wof:placetype":"venue"
},
  "geometry": {"coordinates":[11.9397096634,55.9823188782],"type":"Point"}
}