{
  "type": "Feature",
  "properties": {
    "addr:full":"Farsb\u00f8llevej 18, Gamby S\u00f8nders\u00f8 Danmark 5471",
    "addr:housenumber":"18",
    "addr:postcode":"5471",
    "addr:street":"Farsbollevej",
    "iso:country":"DK",
    "sg:address":"Farsb\u00f8llevej 18, Gamby",
    "sg:city":"S\u00f8nders\u00f8",
    "sg:orig_category":"\u00c3\u2020ldrecentre",
    "sg:phone":"+45 64 83 13 31",
    "sg:postcode":"5471",
    "sg:province":"Danmark",
    "wof:name":"Gambo Boenhed",
    "wof:placetype":"venue"
},
  "geometry": {"coordinates":[10.0971403122,55.5018997192],"type":"Point"}
}