{
  "type": "Feature",
  "properties": {
    "addr:full":"Engg\u00e5rdvej 15, Snejbjerg Herning Danmark 7400",
    "addr:housenumber":"15",
    "addr:postcode":"7400",
    "addr:street":"Enggaardvej;Snejbjerg",
    "iso:country":"DK",
    "sg:address":"Engg\u00e5rdvej 15, Snejbjerg",
    "sg:city":"Herning",
    "sg:classifiers":[
        {
            "category":"Utilities",
            "subcategory":"Cable",
            "type":"Services"
        }
    ],
    "sg:phone":"+45 97 16 15 55",
    "sg:postcode":"7400",
    "sg:province":"Danmark",
    "sg:tags":[
        "trapper"
    ],
    "wof:name":"H B Trapper & St\u00e5l",
    "wof:placetype":"venue"
},
  "geometry": {"coordinates":[8.9768896103,56.1374168396],"type":"Point"}
}