{
  "type": "Feature",
  "properties": {
    "addr:full":"\u00d8stergade 14 Herning Danmark 7400",
    "addr:housenumber":"14",
    "addr:postcode":"7400",
    "addr:street":"Ostergade",
    "iso:country":"DK",
    "sg:address":"\u00d8stergade 14",
    "sg:city":"Herning",
    "sg:orig_category":"Faglige organisationer og foreninger",
    "sg:phone":"+45 97 22 52 88",
    "sg:postcode":"7400",
    "sg:province":"Danmark",
    "wof:name":"Blik og R\u00f8r",
    "wof:placetype":"venue"
},
  "geometry": {"coordinates":[8.977807045,56.1359062195],"type":"Point"}
}