{
  "type": "Feature",
  "properties": {
    "addr:full":"Tiufk\u00e6rvej 130, Tiufk\u00e6r Fredericia Danmark 7000",
    "addr:housenumber":"130",
    "addr:postcode":"7000",
    "addr:street":"Tiufkaervej",
    "iso:country":"DK",
    "sg:address":"Tiufk\u00e6rvej 130, Tiufk\u00e6r",
    "sg:city":"Fredericia",
    "sg:classifiers":[
        {
            "category":"Communications",
            "type":"Services"
        }
    ],
    "sg:phone":"+45 75 86 01 00",
    "sg:postcode":"7000",
    "sg:province":"Danmark",
    "sg:tags":[
        "og",
        "tv",
        "radio"
    ],
    "wof:name":"Olsen, Rich.",
    "wof:placetype":"venue"
},
  "geometry": {"coordinates":[9.7591047287,55.566368103],"type":"Point"}
}