{
  "type": "Feature",
  "properties": {
    "iso:country":"DK",
    "sg:address":"Jernbanevej 3 B",
    "sg:city":"Kongens Lyngby",
    "sg:orig_category":"Antikviteter",
    "sg:phone":"+45 45 88 96 48",
    "sg:postcode":"2800",
    "sg:province":"Danmark",
    "wof:name":"Rasmine Antik",
    "wof:placetype":"venue"
},
  "geometry": {"coordinates":[12.5005102158,55.7719268799],"type":"Point"}
}