{
  "type": "Feature",
  "properties": {
    "addr:full":"Vilsb\u00e6k Engvej 21 Brovst Danmark 9460",
    "addr:housenumber":"21",
    "addr:postcode":"9460",
    "addr:street":"Engvej",
    "iso:country":"DK",
    "sg:address":"Vilsb\u00e6k Engvej 21",
    "sg:city":"Brovst",
    "sg:orig_category":"Produkthandlere",
    "sg:phone":"+45 98 23 30 21",
    "sg:postcode":"9460",
    "sg:province":"Danmark",
    "wof:name":"Vilsb\u00e6k Produkthandel",
    "wof:placetype":"venue"
},
  "geometry": {"coordinates":[9.5220241547,57.097366333],"type":"Point"}
}