{
  "type": "Feature",
  "properties": {
    "addr:full":"B\u00f8llingsvej 30 Ringsted Danmark 4100",
    "addr:housenumber":"30",
    "addr:postcode":"4100",
    "addr:street":"Bollingsvej",
    "iso:country":"DK",
    "sg:address":"B\u00f8llingsvej 30",
    "sg:city":"Ringsted",
    "sg:orig_category":"\u00c3\u02dcvrige skoler",
    "sg:phone":"+45 57 67 12 30",
    "sg:postcode":"4100",
    "sg:province":"Danmark",
    "wof:name":"Social- og Sundhedsskolen i Holb\u00e6k og Ringsted, Ringsted Afdeling",
    "wof:placetype":"venue"
},
  "geometry": {"coordinates":[11.7905225754,55.4494171143],"type":"Point"}
}