{
  "type": "Feature",
  "properties": {
    "addr:full":"Adelgade 28 Ebeltoft Danmark 8400",
    "addr:housenumber":"28",
    "addr:postcode":"8400",
    "addr:street":"Adelgade",
    "iso:country":"DK",
    "sg:address":"Adelgade 28",
    "sg:city":"Ebeltoft",
    "sg:classifiers":[
        {
            "category":"Restaurant",
            "type":"Food & Drink"
        }
    ],
    "sg:phone":"+45 86 34 23 22",
    "sg:postcode":"8400",
    "sg:province":"Danmark",
    "wof:name":"R\u00e5dhuskroen, Restaurant",
    "wof:placetype":"venue"
},
  "geometry": {"coordinates":[10.6788835526,56.1992912292],"type":"Point"}
}