{
  "type": "Feature",
  "properties": {
    "addr:full":"N\u00f8rholm Bygade 10 Nibe Danmark 9240",
    "addr:housenumber":"10",
    "addr:postcode":"9240",
    "addr:street":"Norholm Bygade",
    "iso:country":"DK",
    "sg:address":"N\u00f8rholm Bygade 10",
    "sg:city":"Nibe",
    "sg:orig_category":"Legestuer",
    "sg:phone":"+45 99 31 52 90",
    "sg:postcode":"9240",
    "sg:province":"Danmark",
    "wof:name":"N\u00f8rholm Legestue",
    "wof:placetype":"venue"
},
  "geometry": {"coordinates":[9.6393280029,56.982421875],"type":"Point"}
}