{
  "type": "Feature",
  "properties": {
    "iso:country":"DK",
    "sg:address":"Horsekildevej 19",
    "sg:city":"Valby",
    "sg:classifiers":[
        {
            "category":"Building & Trades",
            "subcategory":"Construction",
            "type":"Services"
        }
    ],
    "sg:phone":"+45 36 30 23 32",
    "sg:postcode":"2500",
    "sg:province":"Danmark",
    "sg:tags":[
        "ventilation"
    ],
    "wof:name":"FJ-Ventilation",
    "wof:placetype":"venue"
},
  "geometry": {"coordinates":[12.5092306137,55.667678833],"type":"Point"}
}