{
  "type": "Feature",
  "properties": {
    "addr:full":"Fmd.: Ole Hartmann Jensen, G\u00e6rdesmuttevej 20 A, Boeslum Ebeltoft Danmark 8400",
    "addr:housenumber":"20 a",
    "addr:postcode":"8400",
    "addr:street":"Gaerdesmuttevej;Boeslum",
    "iso:country":"DK",
    "sg:address":"Fmd.: Ole Hartmann Jensen, G\u00e6rdesmuttevej 20 A, Boeslum",
    "sg:city":"Ebeltoft",
    "sg:orig_category":"Kulturelle foreninger",
    "sg:phone":"+45 86 34 39 34",
    "sg:postcode":"8400",
    "sg:province":"Danmark",
    "wof:name":"Ebeltoft Sommerfestkommite",
    "wof:placetype":"venue"
},
  "geometry": {"coordinates":[10.6778745651,56.199798584],"type":"Point"}
}