{
  "type": "Feature",
  "properties": {
    "addr:full":"Folehaven 2 Valby Danmark 2500",
    "addr:housenumber":"2",
    "addr:postcode":"2500",
    "addr:street":"Folehaven",
    "iso:country":"DK",
    "sg:address":"Folehaven 2",
    "sg:city":"Valby",
    "sg:orig_category":"Cykler",
    "sg:phone":"+45 36 46 82 11",
    "sg:postcode":"2500",
    "sg:province":"Danmark",
    "wof:name":"Folehavens Cykler og Knallerter",
    "wof:placetype":"venue"
},
  "geometry": {"coordinates":[12.5065822601,55.6507759094],"type":"Point"}
}