{
  "type": "Feature",
  "properties": {
    "addr:full":"T\u00e5struph\u00f8j 6 Holb\u00e6k Danmark 4300",
    "addr:housenumber":"6",
    "addr:postcode":"4300",
    "addr:street":"Taastruphoj",
    "iso:country":"DK",
    "sg:address":"T\u00e5struph\u00f8j 6",
    "sg:city":"Holb\u00e6k",
    "sg:orig_category":"Faglige organisationer og foreninger",
    "sg:phone":"+45 59 43 22 10",
    "sg:postcode":"4300",
    "sg:province":"Danmark",
    "wof:name":"Dansk Metal, Holb\u00e6k Afd.",
    "wof:placetype":"venue"
},
  "geometry": {"coordinates":[76.3070983887,14.277130127],"type":"Point"}
}