{
  "type": "Feature",
  "properties": {
    "addr:full":"Hans Jensens Str\u00e6de 37 -45 Odense C Danmark 5000",
    "addr:housenumber":"37 -45",
    "addr:postcode":"5000",
    "addr:street":"Hans Jensens Straede",
    "iso:country":"DK",
    "sg:address":"Hans Jensens Str\u00e6de 37 -45",
    "sg:city":"Odense C",
    "sg:orig_category":"Museer",
    "sg:phone":"+45 66 14 88 14",
    "sg:postcode":"5000",
    "sg:province":"Danmark",
    "wof:name":"H. C. Andersens Hus",
    "wof:placetype":"venue"
},
  "geometry": {"coordinates":[10.3908596039,55.3987998962],"type":"Point"}
}