{
  "type": "Feature",
  "properties": {
    "addr:full":"Raadhustorvet 3 Nyk\u00f8bing Danmark 7900",
    "addr:housenumber":"3",
    "addr:postcode":"7900",
    "addr:street":"Raadhustorvet",
    "iso:country":"DK",
    "sg:address":"Raadhustorvet 3",
    "sg:city":"Nyk\u00f8bing",
    "sg:orig_category":"Ejendomshandel",
    "sg:phone":"+45 97 72 33 44",
    "sg:postcode":"7900",
    "sg:province":"Danmark",
    "wof:name":"Home",
    "wof:placetype":"venue"
},
  "geometry": {"coordinates":[-114.0768203735,46.4432411194],"type":"Point"}
}