{
  "type": "Feature",
  "properties": {
    "addr:full":"Danas Plads 24, 3. Frederiksberg Danmark 1915",
    "addr:housenumber":"24 3;1915",
    "addr:street":"Danas Plads",
    "iso:country":"DK",
    "sg:address":"Danas Plads 24, 3.",
    "sg:city":"Frederiksberg",
    "sg:orig_category":"Psykoanalyse",
    "sg:phone":"+45 33 22 00 62",
    "sg:postcode":"1915",
    "sg:province":"Danmark",
    "wof:name":"Winther, Gerd",
    "wof:placetype":"venue"
},
  "geometry": {"coordinates":[12.5519428253,55.6792259216],"type":"Point"}
}