{
  "type": "Feature",
  "properties": {
    "addr:full":"Storegade 6 Glums\u00f8 Danmark 4171",
    "addr:housenumber":"6",
    "addr:postcode":"4171",
    "addr:street":"Storegade",
    "iso:country":"DK",
    "sg:address":"Storegade 6",
    "sg:city":"Glums\u00f8",
    "sg:orig_category":"Grillbarer",
    "sg:phone":"+45 57 64 72 73",
    "sg:postcode":"4171",
    "sg:province":"Danmark",
    "wof:name":"Glums\u00f8 Grill",
    "wof:placetype":"venue"
},
  "geometry": {"coordinates":[11.6908569336,55.3536567688],"type":"Point"}
}