{
  "type": "Feature",
  "properties": {
    "addr:full":"F\u00e6rgegaardsvej 94 Vordingborg Danmark 4760",
    "addr:housenumber":"94",
    "addr:postcode":"4760",
    "addr:street":"Faergegaardsvej",
    "iso:country":"DK",
    "sg:address":"F\u00e6rgegaardsvej 94",
    "sg:city":"Vordingborg",
    "sg:orig_category":"Motorcykler",
    "sg:phone":"+45 55 37 00 53",
    "sg:postcode":"4760",
    "sg:province":"Danmark",
    "wof:name":"Vordingborg M.C.",
    "wof:placetype":"venue"
},
  "geometry": {"coordinates":[11.8971014023,54.9959716797],"type":"Point"}
}