{
  "type": "Feature",
  "properties": {
    "addr:full":"Danmarksvej 31 Skanderborg Danmark 8660",
    "addr:housenumber":"31",
    "addr:postcode":"8660",
    "addr:street":"Danmarksvej",
    "iso:country":"DK",
    "sg:address":"Danmarksvej 31",
    "sg:city":"Skanderborg",
    "sg:orig_category":"Produktionsskoler",
    "sg:phone":"+45 86 51 08 66",
    "sg:postcode":"8660",
    "sg:province":"Danmark",
    "sg:website":"www.skanpro.dk",
    "wof:name":"Skanderborg Produktionsskole",
    "wof:placetype":"venue"
},
  "geometry": {"coordinates":[9.9533405304,56.0518074036],"type":"Point"}
}