{
  "type": "Feature",
  "properties": {
    "addr:full":"Ole Bruuns Vej 6 Charlottenlund Danmark 2920",
    "addr:housenumber":"6",
    "addr:postcode":"2920",
    "addr:street":"Ole Bruuns Vej",
    "iso:country":"DK",
    "sg:address":"Ole Bruuns Vej 6",
    "sg:city":"Charlottenlund",
    "sg:orig_category":"Psykologer, praktiserende",
    "sg:phone":"+45 39 64 06 47",
    "sg:postcode":"2920",
    "sg:province":"Danmark",
    "wof:name":"Elzbieta Teperowska Monrad",
    "wof:placetype":"venue"
},
  "geometry": {"coordinates":[12.5669536591,55.7544059753],"type":"Point"}
}