{
  "type": "Feature",
  "properties": {
    "addr:full":"Ejstrupvej 47, Lerup Brovst Danmark 9460",
    "addr:housenumber":"47",
    "addr:postcode":"9460",
    "addr:street":"Ejstrupvej;Lerup",
    "iso:country":"DK",
    "sg:address":"Ejstrupvej 47, Lerup",
    "sg:city":"Brovst",
    "sg:orig_category":"Gallerier",
    "sg:phone":"+45 98 23 58 68",
    "sg:postcode":"9460",
    "sg:province":"Danmark",
    "wof:name":"1678, Galleri",
    "wof:placetype":"venue"
},
  "geometry": {"coordinates":[9.5220241547,57.097366333],"type":"Point"}
}