{
  "type": "Feature",
  "properties": {
    "addr:full":"Nyhavn 38 K\u00f8benhavn Danmark 1051",
    "addr:housenumber":"38;1051",
    "addr:street":"Nyhavn",
    "iso:country":"DK",
    "sg:address":"Nyhavn 38",
    "sg:city":"K\u00f8benhavn",
    "sg:classifiers":[
        {
            "category":"Banks & Credit Unions",
            "subcategory":"Bureau De Change",
            "type":"Services"
        }
    ],
    "sg:phone":"+45 33 93 54 74",
    "sg:postcode":"1051",
    "sg:province":"Danmark",
    "sg:tags":[
        "revision"
    ],
    "sg:website":"www.nyhavn.as",
    "wof:name":"Wulff & Kj\u00e6rsgaard A/S",
    "wof:placetype":"venue"
},
  "geometry": {"coordinates":[12.5919704437,55.679889679],"type":"Point"}
}