{
  "type": "Feature",
  "properties": {
    "iso:country":"DK",
    "sg:address":"K\u00f8bkesvej 46",
    "sg:city":"Odense M",
    "sg:classifiers":[
        {
            "category":"Personal",
            "subcategory":"Massage",
            "type":"Services"
        }
    ],
    "sg:phone":"+45 66 11 00 06",
    "sg:postcode":"5230",
    "sg:province":"Danmark",
    "wof:name":"Nielsen, Knud",
    "wof:placetype":"venue"
},
  "geometry": {"coordinates":[10.4182596207,55.3887367249],"type":"Point"}
}