{
  "type": "Feature",
  "properties": {
    "addr:full":"v/ Herman Dam Larsen, Sigtevej 1, \u00d8sterlars Gudhjem Danmark 3760",
    "addr:housenumber":"1",
    "addr:postcode":"3760",
    "addr:street":"Sigtevej;Osterlars",
    "iso:country":"DK",
    "sg:address":"v/ Herman Dam Larsen, Sigtevej 1, \u00d8sterlars",
    "sg:city":"Gudhjem",
    "sg:orig_category":"Kirkelige foreninger",
    "sg:phone":"+45 56 48 56 10",
    "sg:postcode":"3760",
    "sg:province":"Danmark",
    "wof:name":"Indre Mission Gudhjem",
    "wof:placetype":"venue"
},
  "geometry": {"coordinates":[15.1870470047,55.3205566406],"type":"Point"}
}