{
  "type": "Feature",
  "properties": {
    "addr:full":"v/ SuperBrugsen, Storegade 10 Horsens Danmark 8700",
    "addr:housenumber":"10",
    "addr:postcode":"8700",
    "addr:street":"Storegade",
    "iso:country":"DK",
    "sg:address":"v/ SuperBrugsen, Storegade 10",
    "sg:city":"Horsens",
    "sg:orig_category":"Posthuse",
    "sg:phone":"+45 75 65 37 99",
    "sg:postcode":"8700",
    "sg:province":"Danmark",
    "wof:name":"Post Danmark, Hatting Postbutik",
    "wof:placetype":"venue"
},
  "geometry": {"coordinates":[9.8432445526,55.8621063232],"type":"Point"}
}