{
  "type": "Feature",
  "properties": {
    "addr:full":"Hovedgaden 39 H\u00f8ng Danmark 4270",
    "addr:housenumber":"39",
    "addr:postcode":"4270",
    "addr:street":"Hovedgaden;Hong Danmark",
    "iso:country":"DK",
    "sg:address":"Hovedgaden 39",
    "sg:city":"H\u00f8ng",
    "sg:orig_category":"Sportsartikler",
    "sg:phone":"+45 58 85 31 31",
    "sg:postcode":"4270",
    "sg:province":"Danmark",
    "wof:name":"Sportshytten",
    "wof:placetype":"venue"
},
  "geometry": {"coordinates":[9.2555503845,54.9375686646],"type":"Point"}
}