{
  "type": "Feature",
  "properties": {
    "addr:full":"R\u00e5dhuscentret, Th. Eriksens Vej 20 Fars\u00f8 Danmark 9640",
    "addr:housenumber":"20",
    "addr:postcode":"9640",
    "addr:street":"Th. Eriksens Vej",
    "iso:country":"DK",
    "sg:address":"R\u00e5dhuscentret, Th. Eriksens Vej 20",
    "sg:city":"Fars\u00f8",
    "sg:classifiers":[
        {
            "category":"Communications",
            "type":"Services"
        }
    ],
    "sg:phone":"+45 98 63 23 76",
    "sg:postcode":"9640",
    "sg:province":"Danmark",
    "sg:tags":[
        "og",
        "tv",
        "radio"
    ],
    "wof:name":"Center Radio/TV",
    "wof:placetype":"venue"
},
  "geometry": {"coordinates":[-109.44831848139999,42.1062355042],"type":"Point"}
}