{
  "type": "Feature",
  "properties": {
    "addr:full":"Kl\u00f8verbakken 22, R\u00e6kker M\u00f8lle Skjern Danmark 6900",
    "addr:housenumber":"22",
    "addr:postcode":"6900",
    "addr:street":"Kloverbakken;Molle",
    "iso:country":"DK",
    "sg:address":"Kl\u00f8verbakken 22, R\u00e6kker M\u00f8lle",
    "sg:city":"Skjern",
    "sg:orig_category":"Forsamlingshuse",
    "sg:phone":"+45 97 36 20 58",
    "sg:postcode":"6900",
    "sg:province":"Danmark",
    "wof:name":"S\u00e6dding Forsamlingshus",
    "wof:placetype":"venue"
},
  "geometry": {"coordinates":[8.492972374,55.9485740662],"type":"Point"}
}