{
  "type": "Feature",
  "properties": {
    "iso:country":"DK",
    "sg:address":"v/ Christian Christensen, M\u00f8lleparken 151",
    "sg:city":"Billund",
    "sg:orig_category":"Hobbybetonede foreninger",
    "sg:phone":"+45 75 33 86 21",
    "sg:postcode":"7190",
    "sg:province":"Danmark",
    "wof:name":"Eksperimenterende Danske Radioamat\u00f8rer EDR",
    "wof:placetype":"venue"
},
  "geometry": {"coordinates":[9.1138372421,55.7316017151],"type":"Point"}
}