{
  "type": "Feature",
  "properties": {
    "addr:full":"Lise & Steen Christiansen, Liselejevej 60 Liseleje Danmark 3360",
    "addr:housenumber":"60",
    "addr:postcode":"3360",
    "addr:street":"Liselejevej",
    "iso:country":"DK",
    "sg:address":"Lise & Steen Christiansen, Liselejevej 60",
    "sg:city":"Liseleje",
    "sg:orig_category":"Ferielejligheder",
    "sg:phone":"+45 47 74 63 34",
    "sg:postcode":"3360",
    "sg:province":"Danmark",
    "sg:website":"www.edc.dk",
    "wof:name":"EDC M\u00e6glerne Liseleje Ejendomskontor",
    "wof:placetype":"venue"
},
  "geometry": {"coordinates":[11.9649477005,56.0128593445],"type":"Point"}
}