{
  "type": "Feature",
  "properties": {
    "iso:country":"DK",
    "sg:address":"Frederiksdalsvej 136",
    "sg:city":"Virum",
    "sg:orig_category":"Revisorer",
    "sg:phone":"+45 45 83 76 12",
    "sg:postcode":"2830",
    "sg:province":"Danmark",
    "wof:name":"Frederiksen, Bjarne",
    "wof:placetype":"venue"
},
  "geometry": {"coordinates":[12.4652261734,55.7946357727],"type":"Point"}
}