{
  "type": "Feature",
  "properties": {
    "addr:full":"Herstedvang 2 C Albertslund Danmark 2620",
    "addr:housenumber":"2 c",
    "addr:postcode":"2620",
    "addr:street":"Herstedvang",
    "iso:country":"DK",
    "sg:address":"Herstedvang 2 C",
    "sg:city":"Albertslund",
    "sg:orig_category":"Emballage",
    "sg:phone":"+45 43 62 28 11",
    "sg:postcode":"2620",
    "sg:province":"Danmark",
    "wof:name":"SCA Packaging Albertslund",
    "wof:placetype":"venue"
},
  "geometry": {"coordinates":[12.3686857224,55.6647415161],"type":"Point"}
}