{
  "type": "Feature",
  "properties": {
    "addr:full":"Bryrupvej 4, M\u00f8nsted Viborg Danmark 8800",
    "addr:housenumber":"4",
    "addr:postcode":"8800",
    "addr:street":"Bryrupvej",
    "iso:country":"DK",
    "sg:address":"Bryrupvej 4, M\u00f8nsted",
    "sg:city":"Viborg",
    "sg:orig_category":"Legestuer",
    "sg:postcode":"8800",
    "sg:province":"Danmark",
    "wof:name":"M\u00f8nsted Legestue",
    "wof:placetype":"venue"
},
  "geometry": {"coordinates":[9.4071502686,56.452671051],"type":"Point"}
}