{
  "type": "Feature",
  "properties": {
    "addr:full":"Fmd.: Gurli Hansen, Ternevej 5 Stensved Danmark 4773",
    "addr:housenumber":"5",
    "addr:postcode":"4773",
    "addr:street":"Ternevej",
    "iso:country":"DK",
    "sg:address":"Fmd.: Gurli Hansen, Ternevej 5",
    "sg:city":"Stensved",
    "sg:orig_category":"Faglige organisationer og foreninger",
    "sg:phone":"+45 55 38 64 38",
    "sg:postcode":"4773",
    "sg:province":"Danmark",
    "wof:name":"Ledernes Hovedorganisation, Vordingborg Afd.",
    "wof:placetype":"venue"
},
  "geometry": {"coordinates":[12.0289497375,54.9954147339],"type":"Point"}
}