{
  "type": "Feature",
  "properties": {
    "addr:full":"Fredstedvej 70 Haderslev Danmark 6100",
    "addr:housenumber":"70",
    "addr:postcode":"6100",
    "addr:street":"Fredstedvej",
    "iso:country":"DK",
    "sg:address":"Fredstedvej 70",
    "sg:city":"Haderslev",
    "sg:classifiers":[
        {
            "category":"Restaurant",
            "type":"Food & Drink"
        }
    ],
    "sg:phone":"+45 74 53 20 77",
    "sg:postcode":"6100",
    "sg:province":"Danmark",
    "sg:website":"www.damende.dk",
    "wof:name":"Damende, Restaurant",
    "wof:placetype":"venue"
},
  "geometry": {"coordinates":[9.4199123383,55.2344436646],"type":"Point"}
}