{
  "type": "Feature",
  "properties": {
    "addr:full":"Thulebakken 1 Aalborg Danmark 9000",
    "addr:housenumber":"1",
    "addr:postcode":"9000",
    "addr:street":"Thulebakken",
    "iso:country":"DK",
    "sg:address":"Thulebakken 1",
    "sg:city":"Aalborg",
    "sg:orig_category":"Statslige direktorater og styrelser",
    "sg:phone":"+45 98 18 80 88",
    "sg:postcode":"9000",
    "sg:province":"Danmark",
    "wof:name":"Aalborg Stift",
    "wof:placetype":"venue"
},
  "geometry": {"coordinates":[9.8858232498,57.0380897522],"type":"Point"}
}