{
  "type": "Feature",
  "properties": {
    "addr:full":"Rovsingsgade 88 K\u00f8benhavn N Danmark 2200",
    "addr:housenumber":"88",
    "addr:postcode":"2200",
    "addr:street":"Rovsingsgade;Kobenhavn N Danmark",
    "iso:country":"DK",
    "sg:address":"Rovsingsgade 88",
    "sg:city":"K\u00f8benhavn N",
    "sg:orig_category":"Multimedia, Prod. af",
    "sg:phone":"+45 35 86 03 00",
    "sg:postcode":"2200",
    "sg:province":"Danmark",
    "sg:website":"www.m-a-g-i-c.dk",
    "wof:name":"Magic ApS",
    "wof:placetype":"venue"
},
  "geometry": {"coordinates":[-76.4168395996,37.452419281],"type":"Point"}
}