{
  "type": "Feature",
  "properties": {
    "addr:full":"Hvidovrevej 257 Hvidovre Danmark 2650",
    "addr:housenumber":"257",
    "addr:postcode":"2650",
    "addr:street":"Hvidovrevej",
    "iso:country":"DK",
    "sg:address":"Hvidovrevej 257",
    "sg:city":"Hvidovre",
    "sg:orig_category":"Belysning",
    "sg:phone":"+45 36 78 15 23",
    "sg:postcode":"2650",
    "sg:province":"Danmark",
    "wof:name":"Keblovs Installationsforretning",
    "wof:placetype":"venue"
},
  "geometry": {"coordinates":[12.4792900085,55.640045166],"type":"Point"}
}