{
  "type": "Feature",
  "properties": {
    "addr:full":"Hobrovej 9 Randers Danmark 8900",
    "addr:housenumber":"9",
    "addr:postcode":"8900",
    "addr:street":"Hobrovej",
    "iso:country":"DK",
    "sg:address":"Hobrovej 9",
    "sg:city":"Randers",
    "sg:orig_category":"Kiosker",
    "sg:phone":"+45 86 42 19 35",
    "sg:postcode":"8900",
    "sg:province":"Danmark",
    "wof:name":"Hobrovejens Kiosk",
    "wof:placetype":"venue"
},
  "geometry": {"coordinates":[10.0314369202,56.4631118774],"type":"Point"}
}