{
  "type": "Feature",
  "properties": {
    "iso:country":"DK",
    "sg:address":"Eveldrupvej 30, Simested",
    "sg:city":"Aalestrup",
    "sg:orig_category":"Betonvarefabrikker",
    "sg:phone":"+45 98 64 90 63",
    "sg:postcode":"9620",
    "sg:province":"Danmark",
    "wof:name":"Simested Cementst\u00f8beri ApS",
    "wof:placetype":"venue"
},
  "geometry": {"coordinates":[9.49015,56.693829],"type":"Point"}
}