{
  "type": "Feature",
  "properties": {
    "iso:country":"DK",
    "sg:address":"Stagh\u00f8jvej 4, Tebstrup",
    "sg:city":"Skanderborg",
    "sg:orig_category":"Revisorer",
    "sg:phone":"+45 86 53 88 13",
    "sg:postcode":"8660",
    "sg:province":"Danmark",
    "wof:name":"Lipo Bogf\u00f8ring/Regnskab",
    "wof:placetype":"venue"
},
  "geometry": {"coordinates":[9.929974556,56.0380249023],"type":"Point"}
}