{
  "type": "Feature",
  "properties": {
    "addr:full":"S\u00f8nderbyvej 6, Klinkby Lemvig Danmark 7620",
    "addr:housenumber":"6",
    "addr:postcode":"7620",
    "addr:street":"Sonderbyvej",
    "iso:country":"DK",
    "sg:address":"S\u00f8nderbyvej 6, Klinkby",
    "sg:city":"Lemvig",
    "sg:orig_category":"Maskinfabrikker",
    "sg:phone":"+45 97 83 65 99",
    "sg:postcode":"7620",
    "sg:province":"Danmark",
    "wof:name":"Klinkby Maskinfabrik ApS",
    "wof:placetype":"venue"
},
  "geometry": {"coordinates":[8.3073654175,56.5505104065],"type":"Point"}
}