{
  "type": "Feature",
  "properties": {
    "addr:full":"G. C. Amdrups Vej 8 Aalborg S\u00d8 Danmark 9210",
    "addr:housenumber":"8",
    "addr:postcode":"9210",
    "addr:street":"Amdrups Vej",
    "iso:country":"DK",
    "sg:address":"G. C. Amdrups Vej 8",
    "sg:city":"Aalborg S\u00d8",
    "sg:orig_category":"Tagmalere",
    "sg:phone":"+45 98 14 73 32",
    "sg:postcode":"9210",
    "sg:province":"Danmark",
    "wof:name":"Dansk Boligservice",
    "wof:placetype":"venue"
},
  "geometry": {"coordinates":[9.9427528381,57.0191001892],"type":"Point"}
}