{
  "type": "Feature",
  "properties": {
    "addr:full":"Toften 5 Bolderslev Danmark 6392",
    "addr:housenumber":"5",
    "addr:postcode":"6392",
    "addr:street":"Toften",
    "iso:country":"DK",
    "sg:address":"Toften 5",
    "sg:city":"Bolderslev",
    "sg:orig_category":"Fotokopiering",
    "sg:phone":"+45 74 64 61 18",
    "sg:postcode":"6392",
    "sg:province":"Danmark",
    "wof:name":"L T Papir",
    "wof:placetype":"venue"
},
  "geometry": {"coordinates":[9.2897615433,54.9893226624],"type":"Point"}
}