{
  "type": "Feature",
  "properties": {
    "addr:full":"Industrivej 16, Troldhede Videb\u00e6k Danmark 6920",
    "addr:housenumber":"16",
    "addr:postcode":"6920",
    "addr:street":"Industrivej",
    "iso:country":"DK",
    "sg:address":"Industrivej 16, Troldhede",
    "sg:city":"Videb\u00e6k",
    "sg:orig_category":"Maskinstationer",
    "sg:phone":"+45 97 19 42 88",
    "sg:postcode":"6920",
    "sg:province":"Danmark",
    "wof:name":"Troldhede Maskinstation",
    "wof:placetype":"venue"
},
  "geometry": {"coordinates":[8.7436800003,55.9904136658],"type":"Point"}
}