{
  "type": "Feature",
  "properties": {
    "addr:full":"Fmd.: Anette Hunderup, L\u00e6rkevej 1, Vejrup Bramming Danmark 6740",
    "addr:housenumber":"1",
    "addr:postcode":"6740",
    "addr:street":"Laerkevej;Vejrup",
    "iso:country":"DK",
    "sg:address":"Fmd.: Anette Hunderup, L\u00e6rkevej 1, Vejrup",
    "sg:city":"Bramming",
    "sg:orig_category":"Spejderkorps",
    "sg:phone":"+45 75 19 01 67",
    "sg:postcode":"6740",
    "sg:province":"Danmark",
    "wof:name":"KFUM-spejderne, Vejrup gruppe",
    "wof:placetype":"venue"
},
  "geometry": {"coordinates":[8.6974096298,55.4655303955],"type":"Point"}
}