{
  "type": "Feature",
  "properties": {
    "addr:full":"Damvej 5 Gadstrup Danmark 4621",
    "addr:housenumber":"5",
    "addr:postcode":"4621",
    "addr:street":"Damvej",
    "iso:country":"DK",
    "sg:address":"Damvej 5",
    "sg:city":"Gadstrup",
    "sg:orig_category":"Snedkermestre",
    "sg:phone":"+45 46 19 05 12",
    "sg:postcode":"4621",
    "sg:province":"Danmark",
    "wof:name":"N\u00f8rrehus Maskinsnedkeri",
    "wof:placetype":"venue"
},
  "geometry": {"coordinates":[12.0971736908,55.5708274841],"type":"Point"}
}