{
  "type": "Feature",
  "properties": {
    "iso:country":"DK",
    "sg:address":"Randlevvej 2 P",
    "sg:city":"Odder",
    "sg:orig_category":"Jordemodercentre",
    "sg:phone":"+45 86 56 11 73",
    "sg:postcode":"8300",
    "sg:province":"Danmark",
    "wof:name":"Jordemoderkonsultationen",
    "wof:placetype":"venue"
},
  "geometry": {"coordinates":[10.1497612,55.9733161926],"type":"Point"}
}