{
  "type": "Feature",
  "properties": {
    "addr:full":"Esbjerg Lufthavn, John Tranums Vej 20 Esbjerg \u00d8 Danmark 6705",
    "addr:housenumber":"20",
    "addr:postcode":"6705",
    "addr:street":"John Tranums Vej;Danmark",
    "iso:country":"DK",
    "sg:address":"Esbjerg Lufthavn, John Tranums Vej 20",
    "sg:city":"Esbjerg \u00d8",
    "sg:orig_category":"Autoudlejning",
    "sg:phone":"+45 75 16 04 07",
    "sg:postcode":"6705",
    "sg:province":"Danmark",
    "sg:website":"www.hertzdk.dk",
    "wof:name":"Hertz Biludlejning A/S",
    "wof:placetype":"venue"
},
  "geometry": {"coordinates":[8.5338830948,55.5006523132],"type":"Point"}
}