{
  "type": "Feature",
  "properties": {
    "addr:full":"\u00c6rtebjergvej 56 A Hvidovre Danmark 2650",
    "addr:housenumber":"56 a",
    "addr:postcode":"2650",
    "addr:street":"Aertebjergvej",
    "iso:country":"DK",
    "sg:address":"\u00c6rtebjergvej 56 A",
    "sg:city":"Hvidovre",
    "sg:orig_category":"\u00c3\u02dcvrige foreninger",
    "sg:phone":"+45 36 77 80 41",
    "sg:postcode":"2650",
    "sg:province":"Danmark",
    "wof:name":"For\u00e6ldrer\u00e5det Vuggestuen \u00c6rtebjerg",
    "wof:placetype":"venue"
},
  "geometry": {"coordinates":[12.4627084732,55.6353378296],"type":"Point"}
}