{
  "type": "Feature",
  "properties": {
    "addr:full":"KamillianerGaarden, Kastetvej 3 Aalborg Danmark 9000",
    "addr:housenumber":"3",
    "addr:postcode":"9000",
    "addr:street":"Kastetvej",
    "iso:country":"DK",
    "sg:address":"KamillianerGaarden, Kastetvej 3",
    "sg:city":"Aalborg",
    "sg:classifiers":[
        {
            "category":"Social Services",
            "subcategory":"Child Care",
            "type":"Services"
        }
    ],
    "sg:phone":"+45 96 31 11 00",
    "sg:postcode":"9000",
    "sg:province":"Danmark",
    "sg:tags":[
        "hospice"
    ],
    "sg:website":"www.hospice-aalborg.dk",
    "wof:name":"Hospice",
    "wof:placetype":"venue"
},
  "geometry": {"coordinates":[9.9162902832,57.0493545532],"type":"Point"}
}