{
  "type": "Feature",
  "properties": {
    "addr:full":"Vinkelvej 4 Risskov Danmark 8240",
    "addr:housenumber":"4",
    "addr:postcode":"8240",
    "addr:street":"Vinkelvej",
    "iso:country":"DK",
    "sg:address":"Vinkelvej 4",
    "sg:city":"Risskov",
    "sg:orig_category":"Advokater",
    "sg:phone":"+45 86 17 40 00",
    "sg:postcode":"8240",
    "sg:province":"Danmark",
    "wof:name":"Nielsen, Bent",
    "wof:placetype":"venue"
},
  "geometry": {"coordinates":[10.2370939255,56.1898994446],"type":"Point"}
}