{
  "type": "Feature",
  "properties": {
    "iso:country":"DK",
    "sg:address":"\u00c5gade 1",
    "sg:city":"Hadsten",
    "sg:orig_category":"Supermarkeder",
    "sg:postcode":"8370",
    "sg:province":"Danmark",
    "wof:name":"Alta",
    "wof:placetype":"venue"
},
  "geometry": {"coordinates":[10.0426902771,56.3271827698],"type":"Point"}
}