{
  "type": "Feature",
  "properties": {
    "addr:full":"Hanne S\u00f8rensen, \u00d8stergade 32 Otterup Danmark 5450",
    "addr:housenumber":"32",
    "addr:postcode":"5450",
    "addr:street":"Hanne;Ostergade",
    "iso:country":"DK",
    "sg:address":"Hanne S\u00f8rensen, \u00d8stergade 32",
    "sg:city":"Otterup",
    "sg:orig_category":"Oplysningsforbund",
    "sg:phone":"+45 64 82 17 42",
    "sg:postcode":"5450",
    "sg:province":"Danmark",
    "wof:name":"AOF",
    "wof:placetype":"venue"
},
  "geometry": {"coordinates":[10.4545049667,55.5641746521],"type":"Point"}
}