{
  "type": "Feature",
  "properties": {
    "addr:full":"N\u00e6stvedvej 280 Vordingborg Danmark 4760",
    "addr:housenumber":"280",
    "addr:postcode":"4760",
    "addr:street":"Naestvedvej",
    "iso:country":"DK",
    "sg:address":"N\u00e6stvedvej 280",
    "sg:city":"Vordingborg",
    "sg:orig_category":"Gulvafslibning",
    "sg:phone":"+45 55 38 24 56",
    "sg:postcode":"4760",
    "sg:province":"Danmark",
    "wof:name":"S\u00f8rensen, Frank",
    "wof:placetype":"venue"
},
  "geometry": {"coordinates":[11.8553647995,55.0662651062],"type":"Point"}
}