{
  "type": "Feature",
  "properties": {
    "addr:full":"Dronn. Christines V 26 Aalborg Danmark 9000",
    "addr:housenumber":"26",
    "addr:postcode":"9000",
    "iso:country":"DK",
    "sg:address":"Dronn. Christines V 26",
    "sg:city":"Aalborg",
    "sg:orig_category":"INGENI\u00c3\u02dcRER",
    "sg:phone":"+45 98 12 30 44",
    "sg:postcode":"9000",
    "sg:province":"Danmark",
    "wof:name":"Frandsen & S\u00f8ndergaard",
    "wof:placetype":"venue"
},
  "geometry": {"coordinates":[9.905752182,57.0467338562],"type":"Point"}
}