{
  "type": "Feature",
  "properties": {
    "iso:country":"DK",
    "sg:address":"Knudsminde 2",
    "sg:city":"Odder",
    "sg:orig_category":"Maskinfabrikker",
    "sg:phone":"+45 87 80 31 30",
    "sg:postcode":"8300",
    "sg:province":"Danmark",
    "wof:name":"Lillnord A/S",
    "wof:placetype":"venue"
},
  "geometry": {"coordinates":[10.1534900665,55.9885253906],"type":"Point"}
}