{
  "type": "Feature",
  "properties": {
    "addr:full":"Gl. Landevej 153 Herning Danmark 7400",
    "addr:housenumber":"153",
    "addr:postcode":"7400",
    "addr:street":"Gl. Landevej",
    "iso:country":"DK",
    "sg:address":"Gl. Landevej 153",
    "sg:city":"Herning",
    "sg:orig_category":"Supermarkeder",
    "sg:phone":"+45 97 12 22 11",
    "sg:postcode":"7400",
    "sg:province":"Danmark",
    "wof:name":"Spar Super",
    "wof:placetype":"venue"
},
  "geometry": {"coordinates":[8.9596185684,56.1400260925],"type":"Point"}
}