{
  "type": "Feature",
  "properties": {
    "addr:full":"Br\u00f8deskovvej 3, Hammersholt Hiller\u00f8d Danmark 3400",
    "addr:housenumber":"3",
    "addr:postcode":"3400",
    "addr:street":"Brodeskovvej;Hammersholt Hillerod Danmark",
    "iso:country":"DK",
    "sg:address":"Br\u00f8deskovvej 3, Hammersholt",
    "sg:city":"Hiller\u00f8d",
    "sg:orig_category":"Private- og friskoler",
    "sg:phone":"+45 48 26 65 86",
    "sg:postcode":"3400",
    "sg:province":"Danmark",
    "wof:name":"Hiller\u00f8d Lille Skole",
    "wof:placetype":"venue"
},
  "geometry": {"coordinates":[12.3056097031,55.9288215637],"type":"Point"}
}