{
  "type": "Feature",
  "properties": {
    "addr:full":"Ambolten 18 Kolding Danmark 6000",
    "addr:housenumber":"18",
    "addr:postcode":"6000",
    "addr:street":"Ambolten",
    "iso:country":"DK",
    "sg:address":"Ambolten 18",
    "sg:city":"Kolding",
    "sg:classifiers":[
        {
            "category":"Autos & Motor Vehicles",
            "subcategory":"Automobile Sales",
            "type":"Retail Goods"
        }
    ],
    "sg:phone":"+45 75 52 18 77",
    "sg:postcode":"6000",
    "sg:province":"Danmark",
    "sg:tags":[
        "truck"
    ],
    "wof:name":"Walsted & S\u00f8n A/S, Th.",
    "wof:placetype":"venue"
},
  "geometry": {"coordinates":[9.4818649292,55.4653625488],"type":"Point"}
}