{
  "type": "Feature",
  "properties": {
    "addr:full":"S\u00f8ndertoften 9 Hobro Danmark 9500",
    "addr:housenumber":"9",
    "addr:postcode":"9500",
    "addr:street":"Sondertoften",
    "iso:country":"DK",
    "sg:address":"S\u00f8ndertoften 9",
    "sg:city":"Hobro",
    "sg:orig_category":"Fisk og vildt",
    "sg:phone":"+45 98 52 36 45",
    "sg:postcode":"9500",
    "sg:province":"Danmark",
    "wof:name":"Bredahl Fisk",
    "wof:placetype":"venue"
},
  "geometry": {"coordinates":[9.7995262146,56.6309776306],"type":"Point"}
}