{
  "type": "Feature",
  "properties": {
    "addr:full":"R\u00f8deg\u00e5rdsvej 45 Odense C Danmark 5000",
    "addr:housenumber":"45",
    "addr:postcode":"5000",
    "addr:street":"Rodegaardsvej",
    "iso:country":"DK",
    "sg:address":"R\u00f8deg\u00e5rdsvej 45",
    "sg:city":"Odense C",
    "sg:orig_category":"Bagere",
    "sg:phone":"+45 66 12 06 75",
    "sg:postcode":"5000",
    "sg:province":"Danmark",
    "wof:name":"Stjernebageriet",
    "wof:placetype":"venue"
},
  "geometry": {"coordinates":[10.390795,55.396172],"type":"Point"}
}