{
  "type": "Feature",
  "properties": {
    "iso:country":"DK",
    "sg:address":"Gyvelvej 41",
    "sg:city":"Thisted",
    "sg:orig_category":"Stilladser",
    "sg:phone":"+45 97 91 02 55",
    "sg:postcode":"7700",
    "sg:province":"Danmark",
    "wof:name":"Thy Stilladsudlejning ApS",
    "wof:placetype":"venue"
},
  "geometry": {"coordinates":[8.726477623,56.9555931091],"type":"Point"}
}