{
  "type": "Feature",
  "properties": {
    "addr:full":"Jagtvej 177 K\u00f8benhavn \u00d8 Danmark 2100",
    "addr:housenumber":"177",
    "addr:postcode":"2100",
    "addr:street":"Jagtvej",
    "iso:country":"DK",
    "sg:address":"Jagtvej 177",
    "sg:city":"K\u00f8benhavn \u00d8",
    "sg:classifiers":[
        {
            "category":"Restaurant",
            "type":"Food & Drink"
        }
    ],
    "sg:phone":"+45 39 18 49 69",
    "sg:postcode":"2100",
    "sg:province":"Danmark",
    "wof:name":"Sams\u00f8",
    "wof:placetype":"venue"
},
  "geometry": {"coordinates":[76.3241119385,31.6827793121],"type":"Point"}
}