{
  "type": "Feature",
  "properties": {
    "addr:full":"Mindet 2, Postboks 130 8100",
    "addr:housenumber":"2;130",
    "addr:postcode":"8100",
    "addr:street":"Mindet",
    "iso:country":"DK",
    "sg:address":"Mindet 2, Postboks 130",
    "sg:orig_category":"Havne",
    "sg:phone":"+45 86 13 32 66",
    "sg:postcode":"8100",
    "sg:website":"www.aarhushavn.dk",
    "wof:name":"\u00c5rhus Havn incl. \u00c5rhus Lystb\u00e5dehavn",
    "wof:placetype":"venue"
},
  "geometry": {"coordinates":[2.0778300762,49.1431007385],"type":"Point"}
}