{
  "type": "Feature",
  "properties": {
    "iso:country":"DK",
    "sg:address":"Vejenvej 4, Askov",
    "sg:city":"Vejen",
    "sg:orig_category":"Bodegaer",
    "sg:phone":"+45 75 36 73 75",
    "sg:postcode":"6600",
    "sg:province":"Danmark",
    "wof:name":"Askotten, Bodega",
    "wof:placetype":"venue"
},
  "geometry": {"coordinates":[9.1396121979,55.4778175354],"type":"Point"}
}