{
  "type": "Feature",
  "properties": {
    "iso:country":"DK",
    "sg:address":"Gerritsgade 18",
    "sg:city":"Svendborg",
    "sg:orig_category":"Sko",
    "sg:phone":"+45 62 21 44 13",
    "sg:postcode":"5700",
    "sg:province":"Danmark",
    "wof:name":"Bianco Footwear",
    "wof:placetype":"venue"
},
  "geometry": {"coordinates":[10.6088953018,55.0590591431],"type":"Point"}
}