{
  "type": "Feature",
  "properties": {
    "addr:full":"Amtssygehuset i Fakse, Pr\u00e6st\u00f8vej 76 Fakse Danmark 4640",
    "addr:housenumber":"76",
    "addr:postcode":"4640",
    "addr:street":"Praestovej",
    "iso:country":"DK",
    "sg:address":"Amtssygehuset i Fakse, Pr\u00e6st\u00f8vej 76",
    "sg:city":"Fakse",
    "sg:orig_category":"Jordemodercentre",
    "sg:phone":"+45 56 71 31 58",
    "sg:postcode":"4640",
    "sg:province":"Danmark",
    "wof:name":"Jordmoderkonsultationen",
    "wof:placetype":"venue"
},
  "geometry": {"coordinates":[12.1203422546,55.2574195862],"type":"Point"}
}