{
  "type": "Feature",
  "properties": {
    "addr:full":"T\u00f8nningsletvej 2 Ry Danmark 8680",
    "addr:housenumber":"2",
    "addr:postcode":"8680",
    "addr:street":"Tonningsletvej",
    "iso:country":"DK",
    "sg:address":"T\u00f8nningsletvej 2",
    "sg:city":"Ry",
    "sg:orig_category":"Skilte",
    "sg:phone":"+45 87 88 32 00",
    "sg:postcode":"8680",
    "sg:province":"Danmark",
    "wof:name":"Evald Pedersen, Skilte",
    "wof:placetype":"venue"
},
  "geometry": {"coordinates":[9.6450996399,56.0993347168],"type":"Point"}
}