{
  "type": "Feature",
  "properties": {
    "iso:country":"DK",
    "sg:address":"Klintebjergvej 15",
    "sg:city":"Otterup",
    "sg:orig_category":"Vaskemaskiner og service",
    "sg:phone":"+45 64 82 22 05",
    "sg:postcode":"5450",
    "sg:province":"Danmark",
    "wof:name":"Fyns Hvidevare Service",
    "wof:placetype":"venue"
},
  "geometry": {"coordinates":[10.4036550522,55.5109214783],"type":"Point"}
}