{
  "type": "Feature",
  "properties": {
    "addr:full":"R\u00f8dsp\u00e6ttevej 1 Strandby Danmark 9970",
    "addr:housenumber":"1",
    "addr:postcode":"9970",
    "addr:street":"Rodspaettevej",
    "iso:country":"DK",
    "sg:address":"R\u00f8dsp\u00e6ttevej 1",
    "sg:city":"Strandby",
    "sg:orig_category":"Fiskeriudstyr",
    "sg:phone":"+45 98 48 10 96",
    "sg:postcode":"9970",
    "sg:province":"Danmark",
    "wof:name":"Hermans Vod-Trawlbinderi ApS",
    "wof:placetype":"venue"
},
  "geometry": {"coordinates":[10.4970350266,57.4932899475],"type":"Point"}
}