{
  "type": "Feature",
  "properties": {
    "iso:country":"DK",
    "sg:address":"Vestergade 92",
    "sg:city":"Svendborg",
    "sg:orig_category":"Genbrugsbutikker",
    "sg:phone":"+45 62 80 01 51",
    "sg:postcode":"5700",
    "sg:province":"Danmark",
    "wof:name":"Genbrugs Kontakten",
    "wof:placetype":"venue"
},
  "geometry": {"coordinates":[10.5927972794,55.0638580322],"type":"Point"}
}