{
  "type": "Feature",
  "properties": {
    "iso:country":"DK",
    "sg:address":"Nordre Boulevard 325",
    "sg:city":"Varde",
    "sg:orig_category":"Autoreparation og -service",
    "sg:phone":"+45 75 22 25 36",
    "sg:postcode":"6800",
    "sg:province":"Danmark",
    "wof:name":"Poulsen, B.",
    "wof:placetype":"venue"
},
  "geometry": {"coordinates":[8.46052742,55.6229553223],"type":"Point"}
}