{
  "type": "Feature",
  "properties": {
    "addr:full":"Tj\u00f8rnevej 2, \u00d8. T\u00f8rslev Gjerlev Danmark 8983",
    "addr:housenumber":"2 o.",
    "addr:postcode":"8983",
    "addr:street":"Tjornevej;Torslev Gjerlev Danmark",
    "iso:country":"DK",
    "sg:address":"Tj\u00f8rnevej 2, \u00d8. T\u00f8rslev",
    "sg:city":"Gjerlev",
    "sg:orig_category":"Faglige organisationer og foreninger",
    "sg:phone":"+45 86 47 61 80",
    "sg:postcode":"8983",
    "sg:province":"Danmark",
    "wof:name":"SID",
    "wof:placetype":"venue"
},
  "geometry": {"coordinates":[10.1887750626,56.5788421631],"type":"Point"}
}