{
  "type": "Feature",
  "properties": {
    "addr:full":"Sct. Laurentii Vej 80 Skagen Danmark 9990",
    "addr:housenumber":"80",
    "addr:postcode":"9990",
    "addr:street":"Sct. Laurentii Vej",
    "iso:country":"DK",
    "sg:address":"Sct. Laurentii Vej 80",
    "sg:city":"Skagen",
    "sg:orig_category":"Gaveartikler",
    "sg:phone":"+45 98 45 08 80",
    "sg:postcode":"9990",
    "sg:province":"Danmark",
    "wof:name":"Moth Skagen",
    "wof:placetype":"venue"
},
  "geometry": {"coordinates":[10.5842475891,57.7201728821],"type":"Point"}
}