{
  "type": "Feature",
  "properties": {
    "addr:full":"St. Sct. Mikkels Gade 37 Viborg Danmark 8800",
    "addr:housenumber":"37",
    "addr:postcode":"8800",
    "addr:street":"Sct. Mikkels Gade",
    "iso:country":"DK",
    "sg:address":"St. Sct. Mikkels Gade 37",
    "sg:city":"Viborg",
    "sg:orig_category":"Garn",
    "sg:phone":"+45 86 61 50 22",
    "sg:postcode":"8800",
    "sg:province":"Danmark",
    "wof:name":"Mathilde",
    "wof:placetype":"venue"
},
  "geometry": {"coordinates":[9.4093065262,56.4505958557],"type":"Point"}
}