{
  "type": "Feature",
  "properties": {
    "addr:full":"Gr\u00f8nlundvej 81-83, Fasterholt Brande Danmark 7330",
    "addr:housenumber":"81-83",
    "addr:postcode":"7330",
    "addr:street":"Gronlundvej",
    "iso:country":"DK",
    "sg:address":"Gr\u00f8nlundvej 81-83, Fasterholt",
    "sg:city":"Brande",
    "sg:orig_category":"Galvanisering",
    "sg:phone":"+45 97 18 81 11",
    "sg:postcode":"7330",
    "sg:province":"Danmark",
    "wof:name":"Herning Galvanisering A/S",
    "wof:placetype":"venue"
},
  "geometry": {"coordinates":[9.1280345917,55.942779541],"type":"Point"}
}