{
  "type": "Feature",
  "properties": {
    "addr:full":"Billund Centret, Hans Jensens Vej 6 Billund Danmark 7190",
    "addr:housenumber":"6",
    "addr:postcode":"7190",
    "addr:street":"Hans Jensens Vej",
    "iso:country":"DK",
    "sg:address":"Billund Centret, Hans Jensens Vej 6",
    "sg:city":"Billund",
    "sg:orig_category":"Musikskoler, Kommunale",
    "sg:phone":"+45 72 13 15 25",
    "sg:postcode":"7190",
    "sg:province":"Danmark",
    "wof:name":"Den Musiske Skole, Billund",
    "wof:placetype":"venue"
},
  "geometry": {"coordinates":[9.1138372421,55.7316017151],"type":"Point"}
}