{
  "type": "Feature",
  "properties": {
    "addr:full":"N\u00f8rrev\u00e6nget 47  Silkeborg Danmark 8600",
    "addr:housenumber":"47",
    "addr:postcode":"8600",
    "addr:street":"Norrevaenget",
    "iso:country":"DK",
    "sg:address":"N\u00f8rrev\u00e6nget 47 ",
    "sg:city":"Silkeborg",
    "sg:classifiers":[
        {
            "category":"Manufacturing",
            "subcategory":"Lumber",
            "type":"Manufacturing & Wholesale Goods"
        }
    ],
    "sg:phone":"+45 86 82 06 88",
    "sg:postcode":"8600",
    "sg:province":"Danmark",
    "sg:tags":[
        "wood"
    ],
    "wof:name":"SILKEBORG PALLEFABRIK A/S",
    "wof:placetype":"venue"
},
  "geometry": {"coordinates":[9.5524425507,56.1693305969],"type":"Point"}
}