{
  "type": "Feature",
  "properties": {
    "iso:country":"DK",
    "sg:address":"Hj\u00f8rringgade 9",
    "sg:city":"Hirtshals",
    "sg:classifiers":[
        {
            "category":"Restaurant",
            "type":"Food & Drink"
        }
    ],
    "sg:phone":"+45 98 94 41 44",
    "sg:postcode":"9850",
    "sg:province":"Danmark",
    "wof:name":"Hirtshals Fiskerestaurant",
    "wof:placetype":"venue"
},
  "geometry": {"coordinates":[9.9549570084,57.590259552],"type":"Point"}
}