{
  "type": "Feature",
  "properties": {
    "addr:full":"Thorsvej 3 Ringsted Danmark 4100",
    "addr:housenumber":"3",
    "addr:postcode":"4100",
    "addr:street":"Thorsvej",
    "iso:country":"DK",
    "sg:address":"Thorsvej 3",
    "sg:city":"Ringsted",
    "sg:orig_category":"Snedkermestre",
    "sg:phone":"+45 57 61 09 70",
    "sg:postcode":"4100",
    "sg:province":"Danmark",
    "wof:name":"Barnkob Ringsted Aps",
    "wof:placetype":"venue"
},
  "geometry": {"coordinates":[11.7919273376,55.4334754944],"type":"Point"}
}