{
  "type": "Feature",
  "properties": {
    "iso:country":"DK",
    "sg:address":"v/ Jette Th\u00f8gersen, Br\u00e6ndmosevej 4, Karlstrup",
    "sg:city":"Karlslunde",
    "sg:orig_category":"\u00c3\u02dcvrige foreninger",
    "sg:phone":"+45 56 14 43 81",
    "sg:postcode":"2690",
    "sg:province":"Danmark",
    "wof:name":"Karlstrup Landsbylaug",
    "wof:placetype":"venue"
},
  "geometry": {"coordinates":[12.2294149399,55.5701599121],"type":"Point"}
}