{
  "type": "Feature",
  "properties": {
    "addr:full":"Ribevej 28, \u00d8dsted Vejle Danmark 7100",
    "addr:housenumber":"28",
    "addr:postcode":"7100",
    "addr:street":"Ribevej",
    "iso:country":"DK",
    "sg:address":"Ribevej 28, \u00d8dsted",
    "sg:city":"Vejle",
    "sg:orig_category":"Autoreparation og -service",
    "sg:phone":"+45 75 86 55 73",
    "sg:postcode":"7100",
    "sg:province":"Danmark",
    "wof:name":"\u00d8dsted Auto- & Traktorservice",
    "wof:placetype":"venue"
},
  "geometry": {"coordinates":[9.5368051529,55.7113952637],"type":"Point"}
}