{
  "type": "Feature",
  "properties": {
    "iso:country":"DK",
    "sg:address":"Struervej 111",
    "sg:city":"Holstebro",
    "sg:orig_category":"Blikkenslagere",
    "sg:phone":"+45 20 61 85 59",
    "sg:postcode":"7500",
    "sg:province":"Danmark",
    "wof:name":"Byens Blikkenslager",
    "wof:placetype":"venue"
},
  "geometry": {"coordinates":[8.615452,56.374004],"type":"Point"}
}