{
  "type": "Feature",
  "properties": {
    "iso:country":"DK",
    "sg:address":"Sogneg\u00e5rdsvej 103, Demstrup",
    "sg:city":"Kjellerup",
    "sg:orig_category":"Bagere",
    "sg:phone":"+45 86 66 70 47",
    "sg:postcode":"8620",
    "sg:province":"Danmark",
    "wof:name":"Demstrup Bageri",
    "wof:placetype":"venue"
},
  "geometry": {"coordinates":[9.430935,56.287766],"type":"Point"}
}