{
  "type": "Feature",
  "properties": {
    "addr:full":"Isefjordsvej 3 Esbjerg N Danmark 6715",
    "addr:housenumber":"3",
    "addr:postcode":"6715",
    "addr:street":"Isefjordsvej",
    "iso:country":"DK",
    "sg:address":"Isefjordsvej 3",
    "sg:city":"Esbjerg N",
    "sg:orig_category":"Cykler en gros",
    "sg:phone":"+45 75 47 00 00",
    "sg:postcode":"6715",
    "sg:province":"Danmark",
    "wof:name":"Bojsen's Eftf., Br\u00f8drene",
    "wof:placetype":"venue"
},
  "geometry": {"coordinates":[8.4701013565,55.510559082],"type":"Point"}
}