{
  "type": "Feature",
  "properties": {
    "addr:full":"Lyngbygade 19 Silkeborg Danmark 8600",
    "addr:housenumber":"19",
    "addr:postcode":"8600",
    "addr:street":"Lyngbygade",
    "iso:country":"DK",
    "sg:address":"Lyngbygade 19",
    "sg:city":"Silkeborg",
    "sg:orig_category":"Bodegaer",
    "sg:phone":"+45 86 82 00 79",
    "sg:postcode":"8600",
    "sg:province":"Danmark",
    "wof:name":"Hj\u00f8rnet",
    "wof:placetype":"venue"
},
  "geometry": {"coordinates":[9.5484170914,56.1626052856],"type":"Point"}
}