{
  "type": "Feature",
  "properties": {
    "iso:country":"DK",
    "sg:address":"Karen Jeppes Vej 1",
    "sg:city":"Karise",
    "sg:classifiers":[
        {
            "category":"Taxi",
            "type":"Transportation"
        }
    ],
    "sg:phone":"+45 56 78 73 00",
    "sg:postcode":"4653",
    "sg:province":"Danmark",
    "wof:name":"Karise Taxi",
    "wof:placetype":"venue"
},
  "geometry": {"coordinates":[12.2023696899,55.312412262],"type":"Point"}
}