{
  "type": "Feature",
  "properties": {
    "iso:country":"DK",
    "sg:address":"Fmd.: Ole Vesterg\u00e5rd, \u00c5havevej 71",
    "sg:city":"Silkeborg",
    "sg:orig_category":"Hobbybetonede foreninger",
    "sg:phone":"+45 86 80 16 76",
    "sg:postcode":"8600",
    "sg:province":"Danmark",
    "wof:name":"Silkeborg Skyttelaug Af 1857",
    "wof:placetype":"venue"
},
  "geometry": {"coordinates":[9.5524425507,56.1693305969],"type":"Point"}
}