{
  "type": "Feature",
  "properties": {
    "iso:country":"DK",
    "sg:address":"M\u00f8llevej 21",
    "sg:city":"Haarby",
    "sg:orig_category":"Tekstiler",
    "sg:phone":"+45 64 73 20 10",
    "sg:postcode":"5683",
    "sg:province":"Danmark",
    "wof:name":"Malou Textiler",
    "wof:placetype":"venue"
},
  "geometry": {"coordinates":[10.1170320511,55.2201805115],"type":"Point"}
}