{
  "type": "Feature",
  "properties": {
    "addr:full":"Nr. Bjertvej 88 Kolding Danmark 6000",
    "addr:housenumber":"88",
    "addr:postcode":"6000",
    "addr:street":"Nr. Bjertvej",
    "iso:country":"DK",
    "sg:address":"Nr. Bjertvej 88",
    "sg:city":"Kolding",
    "sg:orig_category":"Riste",
    "sg:phone":"+45 70 13 77 13",
    "sg:postcode":"6000",
    "sg:province":"Danmark",
    "sg:website":"www.fiberline.com",
    "wof:name":"Fiberline Composites A/S",
    "wof:placetype":"venue"
},
  "geometry": {"coordinates":[9.5386333466,55.5166435242],"type":"Point"}
}