{
  "type": "Feature",
  "properties": {
    "addr:full":"Kornvangen 20, Boeslum Ebeltoft Danmark 8400",
    "addr:housenumber":"20",
    "addr:postcode":"8400",
    "addr:street":"Kornvangen",
    "iso:country":"DK",
    "sg:address":"Kornvangen 20, Boeslum",
    "sg:city":"Ebeltoft",
    "sg:orig_category":"Musik- og sangundervisning",
    "sg:phone":"+45 86 34 32 08",
    "sg:postcode":"8400",
    "sg:province":"Danmark",
    "wof:name":"Fisker, Grete H.",
    "wof:placetype":"venue"
},
  "geometry": {"coordinates":[10.6778745651,56.199798584],"type":"Point"}
}