{
  "type": "Feature",
  "properties": {
    "iso:country":"DK",
    "sg:address":"M\u00f8lleengen 64",
    "sg:city":"Jyllinge",
    "sg:orig_category":"Boligselskaber",
    "sg:phone":"+45 46 73 02 53",
    "sg:postcode":"4040",
    "sg:province":"Danmark",
    "wof:name":"Ejendomskontoret",
    "wof:placetype":"venue"
},
  "geometry": {"coordinates":[12.1161260605,55.7511253357],"type":"Point"}
}