{
  "type": "Feature",
  "properties": {
    "addr:full":"Danmarksvej 25 Skanderborg Danmark 8660",
    "addr:housenumber":"25",
    "addr:postcode":"8660",
    "addr:street":"Danmarksvej",
    "iso:country":"DK",
    "sg:address":"Danmarksvej 25",
    "sg:city":"Skanderborg",
    "sg:orig_category":"Maskinfabrikker",
    "sg:phone":"+45 86 52 30 11",
    "sg:postcode":"8660",
    "sg:province":"Danmark",
    "wof:name":"AHCON Wheel Service Equipment ApS",
    "wof:placetype":"venue"
},
  "geometry": {"coordinates":[9.9505147934,56.0511894226],"type":"Point"}
}