{
  "type": "Feature",
  "properties": {
    "iso:country":"DK",
    "sg:address":"Fredensvej 67",
    "sg:city":"Charlottenlund",
    "sg:orig_category":"Vinduer",
    "sg:phone":"+45 39 63 25 40",
    "sg:postcode":"2920",
    "sg:province":"Danmark",
    "sg:website":"www.danishwoodworks.com",
    "wof:name":"Meinertz Vinduer",
    "wof:placetype":"venue"
},
  "geometry": {"coordinates":[12.5742378235,55.76039505],"type":"Point"}
}