{
  "type": "Feature",
  "properties": {
    "iso:country":"DK",
    "sg:address":"Vestergade 32",
    "sg:city":"Nyborg",
    "sg:orig_category":"Bowlingcentre",
    "sg:phone":"+45 65 31 01 22",
    "sg:postcode":"5800",
    "sg:province":"Danmark",
    "sg:website":"www.citybowling.dk",
    "wof:name":"Nyborg Bowling Center",
    "wof:placetype":"venue"
},
  "geometry": {"coordinates":[10.7889671326,55.3174438477],"type":"Point"}
}