{
  "type": "Feature",
  "properties": {
    "addr:full":"Enghavevej 9 D, 1. Vejle Danmark 7100",
    "addr:housenumber":"9 d 1",
    "addr:postcode":"7100",
    "addr:street":"Enghavevej",
    "iso:country":"DK",
    "sg:address":"Enghavevej 9 D, 1.",
    "sg:city":"Vejle",
    "sg:orig_category":"Revisorer",
    "sg:phone":"+45 75 82 10 99",
    "sg:postcode":"7100",
    "sg:province":"Danmark",
    "wof:name":"Ebsen, Paulsen & Rub\u00e6k Reg. Revisionsanpartsselskab",
    "wof:placetype":"venue"
},
  "geometry": {"coordinates":[9.5289201736,55.7062759399],"type":"Point"}
}