{
  "type": "Feature",
  "properties": {
    "addr:full":"Degnehusene 117 Albertslund Danmark 2620",
    "addr:housenumber":"117",
    "addr:postcode":"2620",
    "addr:street":"Degnehusene",
    "iso:country":"DK",
    "sg:address":"Degnehusene 117",
    "sg:city":"Albertslund",
    "sg:orig_category":"Distriktspsykiatri",
    "sg:phone":"+45 43 45 46 72",
    "sg:postcode":"2620",
    "sg:province":"Danmark",
    "sg:website":"www.sitecenter.dk/klubalbert",
    "wof:name":"Klub Albert",
    "wof:placetype":"venue"
},
  "geometry": {"coordinates":[12.3650760651,55.6703872681],"type":"Point"}
}