{
  "type": "Feature",
  "properties": {
    "addr:full":"Herningvej 31, K\u00f8lvr\u00e5 Karup Danmark 7470",
    "addr:housenumber":"31",
    "addr:postcode":"7470",
    "addr:street":"Herningvej;Kolvraa Karup Danmark",
    "iso:country":"DK",
    "sg:address":"Herningvej 31, K\u00f8lvr\u00e5",
    "sg:city":"Karup",
    "sg:orig_category":"Soldaterhjem",
    "sg:phone":"+45 97 10 10 65",
    "sg:postcode":"7470",
    "sg:province":"Danmark",
    "sg:website":"www.jiffy.dk/soldaterhjem",
    "wof:name":"KFUM Soldaterhjem",
    "wof:placetype":"venue"
},
  "geometry": {"coordinates":[9.2525548935,56.3398017883],"type":"Point"}
}