{
  "type": "Feature",
  "properties": {
    "addr:full":"Torvet 11 Grenaa Danmark 8500",
    "addr:housenumber":"11",
    "addr:postcode":"8500",
    "addr:street":"Torvet",
    "iso:country":"DK",
    "sg:address":"Torvet 11",
    "sg:city":"Grenaa",
    "sg:orig_category":"Diskoteker",
    "sg:phone":"+45 86 32 66 60",
    "sg:postcode":"8500",
    "sg:province":"Danmark",
    "wof:name":"Diskotek Rembrandt",
    "wof:placetype":"venue"
},
  "geometry": {"coordinates":[10.8765506744,56.4133834839],"type":"Point"}
}