{
  "type": "Feature",
  "properties": {
    "addr:full":"Tallerupvej 5, Tommerup St Tommerup Danmark 5690",
    "addr:housenumber":"5",
    "addr:postcode":"5690",
    "addr:street":"Tallerupvej;St",
    "iso:country":"DK",
    "sg:address":"Tallerupvej 5, Tommerup St",
    "sg:city":"Tommerup",
    "sg:orig_category":"Non-Classified Establishments",
    "sg:phone":"+45 64 76 17 10",
    "sg:postcode":"5690",
    "sg:province":"Danmark",
    "wof:name":"Hansen, Carl",
    "wof:placetype":"venue"
},
  "geometry": {"coordinates":[10.2489509583,55.3236503601],"type":"Point"}
}