{
  "type": "Feature",
  "properties": {
    "addr:full":"Fmd.: Erik Krag, \u00c5s\u00f8 Mosevej 5, \u00c5s\u00f8 Glums\u00f8 Danmark 4171",
    "addr:housenumber":"5",
    "addr:postcode":"4171",
    "addr:street":"Erik;Aaso Mosevej",
    "iso:country":"DK",
    "sg:address":"Fmd.: Erik Krag, \u00c5s\u00f8 Mosevej 5, \u00c5s\u00f8",
    "sg:city":"Glums\u00f8",
    "sg:orig_category":"Kulturelle foreninger",
    "sg:phone":"+45 57 64 62 97",
    "sg:postcode":"4171",
    "sg:province":"Danmark",
    "wof:name":"Sus\u00e5 Egnshistoriske Forening",
    "wof:placetype":"venue"
},
  "geometry": {"coordinates":[11.6862697601,55.3553962708],"type":"Point"}
}