{
  "type": "Feature",
  "properties": {
    "iso:country":"DK",
    "sg:address":"Bredgade 35, Feldborg",
    "sg:city":"Haderup",
    "sg:orig_category":"Maskinstationer",
    "sg:phone":"+45 97 45 40 88",
    "sg:postcode":"7540",
    "sg:province":"Danmark",
    "wof:name":"Nielsens Maskinstation, Brdr.",
    "wof:placetype":"venue"
},
  "geometry": {"coordinates":[8.9933700562,56.3879814148],"type":"Point"}
}