{
  "type": "Feature",
  "properties": {
    "addr:full":"Capellas Alle 29 Kastrup Danmark 2770",
    "addr:housenumber":"29",
    "addr:postcode":"2770",
    "addr:street":"Capellas Alle",
    "iso:country":"DK",
    "sg:address":"Capellas Alle 29",
    "sg:city":"Kastrup",
    "sg:orig_category":"Malermestre",
    "sg:phone":"+45 32 50 45 70",
    "sg:postcode":"2770",
    "sg:province":"Danmark",
    "wof:name":"Leth, John",
    "wof:placetype":"venue"
},
  "geometry": {"coordinates":[12.6204624176,55.625202179],"type":"Point"}
}