{
  "type": "Feature",
  "properties": {
    "addr:full":"Knudevejen 20 Vejen Danmark 6600",
    "addr:housenumber":"20",
    "addr:postcode":"6600",
    "addr:street":"Knudevejen",
    "iso:country":"DK",
    "sg:address":"Knudevejen 20",
    "sg:city":"Vejen",
    "sg:orig_category":"Autolakering",
    "sg:phone":"+45 75 36 15 40",
    "sg:postcode":"6600",
    "sg:province":"Danmark",
    "wof:name":"Knudevejens Autolakering",
    "wof:placetype":"venue"
},
  "geometry": {"coordinates":[9.14494133,55.4679069519],"type":"Point"}
}