{
  "type": "Feature",
  "properties": {
    "addr:full":"R\u00f8jlemosevej 22, Strib Middelfart Danmark 5500",
    "addr:housenumber":"22",
    "addr:postcode":"5500",
    "addr:street":"Rojlemosevej;Strib",
    "iso:country":"DK",
    "sg:address":"R\u00f8jlemosevej 22, Strib",
    "sg:city":"Middelfart",
    "sg:orig_category":"Trykkerier",
    "sg:phone":"+45 64 40 28 13",
    "sg:postcode":"5500",
    "sg:province":"Danmark",
    "wof:name":"Stentoft Serigrafi",
    "wof:placetype":"venue"
},
  "geometry": {"coordinates":[9.7417497635,55.5030250549],"type":"Point"}
}