{
  "type": "Feature",
  "properties": {
    "addr:full":"Jessensgade 4 Horsens Danmark 8700",
    "addr:housenumber":"4",
    "addr:postcode":"8700",
    "addr:street":"Jessensgade",
    "iso:country":"DK",
    "sg:address":"Jessensgade 4",
    "sg:city":"Horsens",
    "sg:orig_category":"Bagere",
    "sg:phone":"+45 75 62 54 83",
    "sg:postcode":"8700",
    "sg:province":"Danmark",
    "wof:name":"Stjernebageriet",
    "wof:placetype":"venue"
},
  "geometry": {"coordinates":[9.844053,55.861889],"type":"Point"}
}