{
  "type": "Feature",
  "properties": {
    "iso:country":"DK",
    "sg:address":"R\u00e5dhusparken 2",
    "sg:city":"Glostrup",
    "sg:orig_category":"Sundhedspleje",
    "sg:phone":"+45 43 23 64 65",
    "sg:postcode":"2600",
    "sg:province":"Danmark",
    "wof:name":"M\u00f8lg\u00e5rd, Lone",
    "wof:placetype":"venue"
},
  "geometry": {"coordinates":[12.394112587,55.6647491455],"type":"Point"}
}