{
  "type": "Feature",
  "properties": {
    "addr:full":"Birkmosevej 24, Timring Vildbjerg Danmark 7480",
    "addr:housenumber":"24",
    "addr:postcode":"7480",
    "addr:street":"Birkmosevej",
    "iso:country":"DK",
    "sg:address":"Birkmosevej 24, Timring",
    "sg:city":"Vildbjerg",
    "sg:orig_category":"Skolefritidsordninger",
    "sg:phone":"+45 97 13 31 99",
    "sg:postcode":"7480",
    "sg:province":"Danmark",
    "wof:name":"Myretuen Skolefritidsordning",
    "wof:placetype":"venue"
},
  "geometry": {"coordinates":[8.7678747177,56.1993865967],"type":"Point"}
}