{
  "type": "Feature",
  "properties": {
    "addr:full":"Taarsvej 92 Nakskov Danmark 4900",
    "addr:housenumber":"92",
    "addr:postcode":"4900",
    "addr:street":"Taarsvej",
    "iso:country":"DK",
    "sg:address":"Taarsvej 92",
    "sg:city":"Nakskov",
    "sg:orig_category":"Kiosker",
    "sg:phone":"+45 54 95 01 97",
    "sg:postcode":"4900",
    "sg:province":"Danmark",
    "wof:name":"T\u00e5rsvej D\u00f8gnkiosk",
    "wof:placetype":"venue"
},
  "geometry": {"coordinates":[11.1255617142,54.8382720947],"type":"Point"}
}