{
  "type": "Feature",
  "properties": {
    "addr:full":"Christian X's Vej 253 Tranbjerg Danmark 8310",
    "addr:housenumber":"253",
    "addr:postcode":"8310",
    "addr:street":"Christian X'S Vej",
    "iso:country":"DK",
    "sg:address":"Christian X's Vej 253",
    "sg:city":"Tranbjerg",
    "sg:orig_category":"Servicestationer",
    "sg:phone":"+45 86 29 02 09",
    "sg:postcode":"8310",
    "sg:province":"Danmark",
    "wof:name":"Statoil Servicenter",
    "wof:placetype":"venue"
},
  "geometry": {"coordinates":[10.1431903839,56.1030807495],"type":"Point"}
}