{
  "type": "Feature",
  "properties": {
    "addr:full":"K\u00e5strupvej 26, V. Lyby Skive Danmark 7800",
    "addr:housenumber":"26",
    "addr:postcode":"7800",
    "addr:street":"Kaastrupvej;Lyby",
    "iso:country":"DK",
    "sg:address":"K\u00e5strupvej 26, V. Lyby",
    "sg:city":"Skive",
    "sg:orig_category":"Cafeterier",
    "sg:phone":"+45 97 58 58 59",
    "sg:postcode":"7800",
    "sg:province":"Danmark",
    "wof:name":"DK Cafeteria",
    "wof:placetype":"venue"
},
  "geometry": {"coordinates":[9.0320358276,56.5666427612],"type":"Point"}
}