{
  "type": "Feature",
  "properties": {
    "addr:full":"Langgade 24, Vivild Alling\u00e5bro Danmark 8961",
    "addr:housenumber":"24",
    "addr:postcode":"8961",
    "addr:street":"Langgade",
    "iso:country":"DK",
    "sg:address":"Langgade 24, Vivild",
    "sg:city":"Alling\u00e5bro",
    "sg:classifiers":[
        {
            "category":"Banks & Credit Unions",
            "subcategory":"Bank",
            "type":"Services"
        }
    ],
    "sg:phone":"+45 86 48 60 46",
    "sg:postcode":"8961",
    "sg:province":"Danmark",
    "sg:tags":[
        "banker"
    ],
    "sg:website":"www.djurslandsbank.dk",
    "wof:name":"Djurslands Bank A/S",
    "wof:placetype":"venue"
},
  "geometry": {"coordinates":[10.3230552673,56.4639511108],"type":"Point"}
}