{
  "type": "Feature",
  "properties": {
    "addr:full":"Trelde N\u00e6svej 3, Trelde Fredericia Danmark 7000",
    "addr:housenumber":"3",
    "addr:postcode":"7000",
    "addr:street":"Trelde Naesvej",
    "iso:country":"DK",
    "sg:address":"Trelde N\u00e6svej 3, Trelde",
    "sg:city":"Fredericia",
    "sg:orig_category":"Murermestre",
    "sg:phone":"+45 75 95 74 60",
    "sg:postcode":"7000",
    "sg:province":"Danmark",
    "wof:name":"Hansen TH-Byg, Torben",
    "wof:placetype":"venue"
},
  "geometry": {"coordinates":[9.7591047287,55.566368103],"type":"Point"}
}