{
  "type": "Feature",
  "properties": {
    "addr:full":"Allervej 130, Aller Christiansfeld Danmark 6070",
    "addr:housenumber":"130",
    "addr:postcode":"6070",
    "addr:street":"Allervej",
    "iso:country":"DK",
    "sg:address":"Allervej 130, Aller",
    "sg:city":"Christiansfeld",
    "sg:orig_category":"Korn og foderstoffer",
    "sg:phone":"+45 74 56 12 10",
    "sg:postcode":"6070",
    "sg:province":"Danmark",
    "wof:name":"Aller M\u00f8lle A/S",
    "wof:placetype":"venue"
},
  "geometry": {"coordinates":[9.4834346771,55.3550567627],"type":"Point"}
}