{
  "type": "Feature",
  "properties": {
    "addr:full":"Urupvej 10 Horsens Danmark 8700",
    "addr:housenumber":"10",
    "addr:postcode":"8700",
    "addr:street":"Urupvej",
    "iso:country":"DK",
    "sg:address":"Urupvej 10",
    "sg:city":"Horsens",
    "sg:orig_category":"Kirker",
    "sg:postcode":"8700",
    "sg:province":"Danmark",
    "wof:name":"Lundum Kirke",
    "wof:placetype":"venue"
},
  "geometry": {"coordinates":[9.7742271423,55.9305458069],"type":"Point"}
}