{
  "type": "Feature",
  "properties": {
    "addr:full":"Sandbakkevej 49 Grenaa Danmark 8500",
    "addr:housenumber":"49",
    "addr:postcode":"8500",
    "addr:street":"Sandbakkevej",
    "iso:country":"DK",
    "sg:address":"Sandbakkevej 49",
    "sg:city":"Grenaa",
    "sg:orig_category":"Fisk og vildt",
    "sg:phone":"+45 86 32 06 26",
    "sg:postcode":"8500",
    "sg:province":"Danmark",
    "wof:name":"Deres Fiskehandler",
    "wof:placetype":"venue"
},
  "geometry": {"coordinates":[10.9076976776,56.4155197144],"type":"Point"}
}