{
  "type": "Feature",
  "properties": {
    "addr:full":"Lik\u00f8rstr\u00e6de 3 Kongens Lyngby Danmark 2800",
    "addr:housenumber":"3",
    "addr:postcode":"2800",
    "addr:street":"Likorstraede",
    "iso:country":"DK",
    "sg:address":"Lik\u00f8rstr\u00e6de 3",
    "sg:city":"Kongens Lyngby",
    "sg:orig_category":"Parfumerier",
    "sg:phone":"+45 45 93 38 30",
    "sg:postcode":"2800",
    "sg:province":"Danmark",
    "wof:name":"The Body Shop",
    "wof:placetype":"venue"
},
  "geometry": {"coordinates":[12.5368299484,55.7949905396],"type":"Point"}
}