{
  "type": "Feature",
  "properties": {
    "iso:country":"DK",
    "sg:address":"Fmd.: Rolf Diderichsen, Lysenvej 20, Hjerk",
    "sg:city":"Roslev",
    "sg:orig_category":"Hobbybetonede foreninger",
    "sg:phone":"+45 97 57 90 34",
    "sg:postcode":"7870",
    "sg:province":"Danmark",
    "wof:name":"Nord-\u00d8stsalling Skakklub",
    "wof:placetype":"venue"
},
  "geometry": {"coordinates":[8.8715353012,56.7570304871],"type":"Point"}
}