{
  "type": "Feature",
  "properties": {
    "iso:country":"DK",
    "sg:address":"Hovvej 5",
    "sg:city":"Nibe",
    "sg:orig_category":"Boligselskaber",
    "sg:phone":"+45 98 35 18 16",
    "sg:postcode":"9240",
    "sg:province":"Danmark",
    "wof:name":"Boligforeningen Enggaarden",
    "wof:placetype":"venue"
},
  "geometry": {"coordinates":[9.6379060745,56.9814529419],"type":"Point"}
}