{
  "type": "Feature",
  "properties": {
    "addr:full":"Slotsgade 33 Dronninglund Danmark 9330",
    "addr:housenumber":"33",
    "addr:postcode":"9330",
    "addr:street":"Slotsgade",
    "iso:country":"DK",
    "sg:address":"Slotsgade 33",
    "sg:city":"Dronninglund",
    "sg:orig_category":"Import-eksport",
    "sg:phone":"+45 98 84 30 70",
    "sg:postcode":"9330",
    "sg:province":"Danmark",
    "wof:name":"Rosenkrantz A/S",
    "wof:placetype":"venue"
},
  "geometry": {"coordinates":[10.2880325317,57.159488678],"type":"Point"}
}