{
  "type": "Feature",
  "properties": {
    "addr:full":"Hammerg\u00e5rdsvej 2 B, Gjerlev Gjerlev Danmark 8983",
    "addr:housenumber":"2 b",
    "addr:postcode":"8983",
    "addr:street":"Hammergaardsvej;Gjerlev Gjerlev Danmark",
    "iso:country":"DK",
    "sg:address":"Hammerg\u00e5rdsvej 2 B, Gjerlev",
    "sg:city":"Gjerlev",
    "sg:classifiers":[
        {
            "category":"Banks & Credit Unions",
            "subcategory":"Bank",
            "type":"Services"
        }
    ],
    "sg:phone":"+45 86 47 48 55",
    "sg:postcode":"8983",
    "sg:province":"Danmark",
    "sg:tags":[
        "banker"
    ],
    "sg:website":"www.oestjydskbank.dk",
    "wof:name":"\u00d8stjydsk Bank A/S",
    "wof:placetype":"venue"
},
  "geometry": {"coordinates":[10.188775,56.578842],"type":"Point"}
}