{
  "type": "Feature",
  "properties": {
    "addr:full":"Brogade 13 Svendborg Danmark 5700",
    "addr:housenumber":"13",
    "addr:postcode":"5700",
    "addr:street":"Brogade",
    "iso:country":"DK",
    "sg:address":"Brogade 13",
    "sg:city":"Svendborg",
    "sg:classifiers":[
        {
            "category":"Restaurant",
            "type":"Food & Drink"
        }
    ],
    "sg:phone":"+45 62 22 07 95",
    "sg:postcode":"5700",
    "sg:province":"Danmark",
    "wof:name":"Restaurant No. 13",
    "wof:placetype":"venue"
},
  "geometry": {"coordinates":[10.6129379272,55.0579986572],"type":"Point"}
}