{
  "type": "Feature",
  "properties": {
    "addr:full":"Hovedgaden 12 R\u00f8dvig Stevns Danmark 4673",
    "addr:housenumber":"12",
    "addr:postcode":"4673",
    "addr:street":"Hovedgaden",
    "iso:country":"DK",
    "sg:address":"Hovedgaden 12",
    "sg:city":"R\u00f8dvig Stevns",
    "sg:orig_category":"Slagter og viktualie",
    "sg:phone":"+45 56 50 60 89",
    "sg:postcode":"4673",
    "sg:province":"Danmark",
    "wof:name":"R\u00f8dvig Slagterforretning",
    "wof:placetype":"venue"
},
  "geometry": {"coordinates":[12.3765974045,55.2561035156],"type":"Point"}
}