{
  "type": "Feature",
  "properties": {
    "addr:full":"K\u00f8lbakken 9, Basballe Ebeltoft Danmark 8400",
    "addr:housenumber":"9",
    "addr:postcode":"8400",
    "addr:street":"Kolbakken",
    "iso:country":"DK",
    "sg:address":"K\u00f8lbakken 9, Basballe",
    "sg:city":"Ebeltoft",
    "sg:orig_category":"Motorcykler",
    "sg:phone":"+45 86 36 53 64",
    "sg:postcode":"8400",
    "sg:province":"Danmark",
    "sg:website":"www.bccdk.dk",
    "wof:name":"Basballe Cross Center",
    "wof:placetype":"venue"
},
  "geometry": {"coordinates":[10.6778745651,56.199798584],"type":"Point"}
}