{
  "type": "Feature",
  "properties": {
    "addr:full":"Sct. Mathias Gade 45 A Viborg Danmark 8800",
    "addr:housenumber":"45 a",
    "addr:postcode":"8800",
    "addr:street":"Sct. Mathias Gade",
    "iso:country":"DK",
    "sg:address":"Sct. Mathias Gade 45 A",
    "sg:city":"Viborg",
    "sg:orig_category":"Blomsterhandlere",
    "sg:phone":"+45 86 62 00 14",
    "sg:postcode":"8800",
    "sg:province":"Danmark",
    "wof:name":"Sm\u00f8rblomsten",
    "wof:placetype":"venue"
},
  "geometry": {"coordinates":[9.4099407196,56.4501190186],"type":"Point"}
}