{
  "type": "Feature",
  "properties": {
    "addr:full":"Klintevej 2 Haderslev Danmark 6100",
    "addr:housenumber":"2",
    "addr:postcode":"6100",
    "addr:street":"Klintevej",
    "iso:country":"DK",
    "sg:address":"Klintevej 2",
    "sg:city":"Haderslev",
    "sg:orig_category":"Snedkermestre",
    "sg:phone":"+45 74 52 77 44",
    "sg:postcode":"6100",
    "sg:province":"Danmark",
    "sg:website":"www.klintevejsbyg.dk",
    "wof:name":"Klintevejs Bygnings Snedkeri ApS",
    "wof:placetype":"venue"
},
  "geometry": {"coordinates":[9.5024900436,55.2366981506],"type":"Point"}
}