{
  "type": "Feature",
  "properties": {
    "iso:country":"DK",
    "sg:address":"v/ Richard Olsen, Udsigten 15",
    "sg:city":"Middelfart",
    "sg:orig_category":"Hobbybetonede foreninger",
    "sg:phone":"+45 64 41 46 19",
    "sg:postcode":"5500",
    "sg:province":"Danmark",
    "wof:name":"Danmarks civile Hundef\u00f8rer- forening afd. Vest Fyn",
    "wof:placetype":"venue"
},
  "geometry": {"coordinates":[9.7417497635,55.5030250549],"type":"Point"}
}