{
  "type": "Feature",
  "properties": {
    "addr:full":"Stationsvej 55 Holmegaard Danmark 4684",
    "addr:housenumber":"55",
    "addr:postcode":"4684",
    "addr:street":"Stationsvej",
    "iso:country":"DK",
    "sg:address":"Stationsvej 55",
    "sg:city":"Holmegaard",
    "sg:orig_category":"Forsamlingshuse",
    "sg:phone":"+45 55 56 25 33",
    "sg:postcode":"4684",
    "sg:province":"Danmark",
    "wof:name":"Holme-Olstrup Forsamlingshus",
    "wof:placetype":"venue"
},
  "geometry": {"coordinates":[11.8410692215,55.2521934509],"type":"Point"}
}