{
  "type": "Feature",
  "properties": {
    "addr:full":"v/ Frede Salling Pedersen, Nibstrupvej 174 Br\u00f8nderslev Danmark 9700",
    "addr:housenumber":"174",
    "addr:postcode":"9700",
    "addr:street":"Nibstrupvej",
    "iso:country":"DK",
    "sg:address":"v/ Frede Salling Pedersen, Nibstrupvej 174",
    "sg:city":"Br\u00f8nderslev",
    "sg:orig_category":"Musik og sang",
    "sg:phone":"+45 98 81 12 90",
    "sg:postcode":"9700",
    "sg:province":"Danmark",
    "wof:name":"Nordjysk Pigekor",
    "wof:placetype":"venue"
},
  "geometry": {"coordinates":[9.7584476471,57.2860298157],"type":"Point"}
}