{
  "type": "Feature",
  "properties": {
    "addr:full":"Herningvej 60 Brande Danmark 7330",
    "addr:housenumber":"60",
    "addr:postcode":"7330",
    "addr:street":"Herningvej",
    "iso:country":"DK",
    "sg:address":"Herningvej 60",
    "sg:city":"Brande",
    "sg:orig_category":"Kartofler",
    "sg:phone":"+45 96 42 55 55",
    "sg:postcode":"7330",
    "sg:province":"Danmark",
    "sg:website":"www.kmc.dk",
    "wof:name":"KMC Kartoffelmelcentralen amba",
    "wof:placetype":"venue"
},
  "geometry": {"coordinates":[9.1173295975,55.9506988525],"type":"Point"}
}