{
  "type": "Feature",
  "properties": {
    "iso:country":"DK",
    "sg:address":"Skolegade 12",
    "sg:city":"Vemb",
    "sg:orig_category":"Ungdomsklubber",
    "sg:phone":"+45 97 48 15 00",
    "sg:postcode":"7570",
    "sg:province":"Danmark",
    "wof:name":"Vemb Ungdomsklub",
    "wof:placetype":"venue"
},
  "geometry": {"coordinates":[8.3480348587,56.342086792],"type":"Point"}
}