{
  "type": "Feature",
  "properties": {
    "addr:full":"Borgergade 62 Glejbjerg Danmark 6752",
    "addr:housenumber":"62",
    "addr:postcode":"6752",
    "addr:street":"Borgergade",
    "iso:country":"DK",
    "sg:address":"Borgergade 62",
    "sg:city":"Glejbjerg",
    "sg:classifiers":[
        {
            "category":"Taxi",
            "type":"Transportation"
        }
    ],
    "sg:phone":"+45 75 19 83 83",
    "sg:postcode":"6752",
    "sg:province":"Danmark",
    "wof:name":"Glejbjerg Taxi",
    "wof:placetype":"venue"
},
  "geometry": {"coordinates":[8.8248271942,55.5580177307],"type":"Point"}
}