{
  "type": "Feature",
  "properties": {
    "iso:country":"DK",
    "sg:address":"v/ Tony Vejslev, R\u00e5bjergvej 42",
    "sg:city":"Helsinge",
    "sg:orig_category":"Borger- og beboerforeninger",
    "sg:phone":"+45 48 79 47 14",
    "sg:postcode":"3200",
    "sg:province":"Danmark",
    "wof:name":"M\u00e5rum-Kagerup Lokalr\u00e5d",
    "wof:placetype":"venue"
},
  "geometry": {"coordinates":[12.196846962,56.0224456787],"type":"Point"}
}