{
  "type": "Feature",
  "properties": {
    "addr:full":"Niels Brocks Gade 18 Randers Danmark 8900",
    "addr:housenumber":"18",
    "addr:postcode":"8900",
    "addr:street":"Niels Brocks Gade",
    "iso:country":"DK",
    "sg:address":"Niels Brocks Gade 18",
    "sg:city":"Randers",
    "sg:orig_category":"Reklamebureauer",
    "sg:phone":"+45 87 10 67 67",
    "sg:postcode":"8900",
    "sg:province":"Danmark",
    "wof:name":"B 10 Marketing A/S",
    "wof:placetype":"venue"
},
  "geometry": {"coordinates":[10.0454139709,56.4621086121],"type":"Point"}
}