{
  "type": "Feature",
  "properties": {
    "addr:full":"v/ Kenneth Jensen, Klakkeh\u00f8j 82 Ballerup Danmark 2750",
    "addr:housenumber":"82",
    "addr:postcode":"2750",
    "iso:country":"DK",
    "sg:address":"v/ Kenneth Jensen, Klakkeh\u00f8j 82",
    "sg:city":"Ballerup",
    "sg:orig_category":"Boligselskaber",
    "sg:phone":"+45 44 68 28 68",
    "sg:postcode":"2750",
    "sg:province":"Danmark",
    "wof:name":"A/B Bjergtaget",
    "wof:placetype":"venue"
},
  "geometry": {"coordinates":[12.361000061,55.7301216125],"type":"Point"}
}