{
  "type": "Feature",
  "properties": {
    "addr:full":"Ravnsbjergvej 23 Vig Danmark 4560",
    "addr:housenumber":"23",
    "addr:postcode":"4560",
    "addr:street":"Ravnsbjergvej",
    "iso:country":"DK",
    "sg:address":"Ravnsbjergvej 23",
    "sg:city":"Vig",
    "sg:orig_category":"Skolefritidsordninger",
    "sg:phone":"+45 59 31 64 66",
    "sg:postcode":"4560",
    "sg:province":"Danmark",
    "wof:name":"Vig Skolefritidsordning",
    "wof:placetype":"venue"
},
  "geometry": {"coordinates":[-82.79159545900001,39.2505378723],"type":"Point"}
}