{
  "type": "Feature",
  "properties": {
    "addr:full":"Stubberupvej 17 Nysted Danmark 4880",
    "addr:housenumber":"17",
    "addr:postcode":"4880",
    "addr:street":"Stubberupvej",
    "iso:country":"DK",
    "sg:address":"Stubberupvej 17",
    "sg:city":"Nysted",
    "sg:classifiers":[
        {
            "category":"Restaurant",
            "type":"Food & Drink"
        }
    ],
    "sg:phone":"+45 54 87 15 50",
    "sg:postcode":"4880",
    "sg:province":"Danmark",
    "wof:name":"Gamle G\u00e5rd Hapimag, Den",
    "wof:placetype":"venue"
},
  "geometry": {"coordinates":[11.692232132,54.6692047119],"type":"Point"}
}