{
  "type": "Feature",
  "properties": {
    "iso:country":"DK",
    "sg:address":"N\u00f8rregade 6 - 8",
    "sg:city":"Otterup",
    "sg:orig_category":"Ejendomshandel",
    "sg:phone":"+45 64 82 42 00",
    "sg:postcode":"5450",
    "sg:province":"Danmark",
    "wof:name":"Olesen, Ejendomsfirmaet Egil",
    "wof:placetype":"venue"
},
  "geometry": {"coordinates":[10.3985557556,55.5159568787],"type":"Point"}
}