{
  "type": "Feature",
  "properties": {
    "iso:country":"DK",
    "sg:address":"Valbyg\u00e5rdsvej 70",
    "sg:city":"Valby",
    "sg:orig_category":"Bogbinderier",
    "sg:phone":"+45 36 46 00 93",
    "sg:postcode":"2500",
    "sg:province":"Danmark",
    "wof:name":"Nielsen, A C",
    "wof:placetype":"venue"
},
  "geometry": {"coordinates":[12.5237102509,55.656993866],"type":"Point"}
}