{
  "type": "Feature",
  "properties": {
    "iso:country":"DK",
    "sg:address":"v/ Flemming Stougaard, R\u00e5dhusgade 20",
    "sg:city":"Odder",
    "sg:classifiers":[
        {
            "category":"Communications",
            "type":"Services"
        }
    ],
    "sg:phone":"+45 86 56 02 33",
    "sg:postcode":"8300",
    "sg:province":"Danmark",
    "sg:tags":[
        "radio-",
        "og",
        "tv-stationer"
    ],
    "wof:name":"Lokalradio Odder",
    "wof:placetype":"venue"
},
  "geometry": {"coordinates":[10.1497612,55.9733161926],"type":"Point"}
}