{
  "type": "Feature",
  "properties": {
    "addr:full":"Vinhaven 2-4 Valby Danmark 2500",
    "addr:housenumber":"2-4",
    "addr:postcode":"2500",
    "addr:street":"Vinhaven",
    "iso:country":"DK",
    "sg:address":"Vinhaven 2-4",
    "sg:city":"Valby",
    "sg:orig_category":"Ungdomsklubber",
    "sg:phone":"+45 36 30 16 46",
    "sg:postcode":"2500",
    "sg:province":"Danmark",
    "wof:name":"F/U Klubben Folehaven",
    "wof:placetype":"venue"
},
  "geometry": {"coordinates":[12.5009727478,55.6478843689],"type":"Point"}
}