{
  "type": "Feature",
  "properties": {
    "addr:full":"N\u00e6stvedvej 0 Fuglebjerg Danmark 4250",
    "addr:housenumber":"0",
    "addr:postcode":"4250",
    "addr:street":"Naestvedvej",
    "iso:country":"DK",
    "sg:address":"N\u00e6stvedvej 0",
    "sg:city":"Fuglebjerg",
    "sg:orig_category":"Kirker",
    "sg:postcode":"4250",
    "sg:province":"Danmark",
    "wof:name":"Fuglebjerg Kirke",
    "wof:placetype":"venue"
},
  "geometry": {"coordinates":[11.5493364334,55.3058166504],"type":"Point"}
}