{
  "type": "Feature",
  "properties": {
    "addr:full":"Vestergade 37 Vojens Danmark 6500",
    "addr:housenumber":"37",
    "addr:postcode":"6500",
    "addr:street":"Vestergade",
    "iso:country":"DK",
    "sg:address":"Vestergade 37",
    "sg:city":"Vojens",
    "sg:orig_category":"Begravelsesforretninger",
    "sg:phone":"+45 74 54 13 07",
    "sg:postcode":"6500",
    "sg:province":"Danmark",
    "sg:website":"www.vojens-begravelsesforretning.dk",
    "wof:name":"Vojens Begravelsesforretning",
    "wof:placetype":"venue"
},
  "geometry": {"coordinates":[9.298254,55.245522],"type":"Point"}
}