{
  "type": "Feature",
  "properties": {
    "addr:full":"v/ Trine Lykke Nielsen, Hovedvejen 10, Avernak\u00f8 Faaborg Danmark 5600",
    "addr:housenumber":"10",
    "addr:postcode":"5600",
    "addr:street":"Hovedvejen;Avernako",
    "iso:country":"DK",
    "sg:address":"v/ Trine Lykke Nielsen, Hovedvejen 10, Avernak\u00f8",
    "sg:city":"Faaborg",
    "sg:orig_category":"\u00c3\u2020ldreorganisationer og klubber",
    "sg:phone":"+45 62 61 76 98",
    "sg:postcode":"5600",
    "sg:province":"Danmark",
    "wof:name":"Avernak\u00f8 \u00c6ldreklub",
    "wof:placetype":"venue"
},
  "geometry": {"coordinates":[10.2400531769,55.0950622559],"type":"Point"}
}