{
  "type": "Feature",
  "properties": {
    "addr:full":"Torstensvej 55 Hvidovre Danmark 2650",
    "addr:housenumber":"55",
    "addr:postcode":"2650",
    "addr:street":"Torstensvej",
    "iso:country":"DK",
    "sg:address":"Torstensvej 55",
    "sg:city":"Hvidovre",
    "sg:orig_category":"Musikere",
    "sg:phone":"+45 36 34 14 02",
    "sg:postcode":"2650",
    "sg:province":"Danmark",
    "sg:website":"www.crazyheart.dk",
    "wof:name":"Crazy Heart",
    "wof:placetype":"venue"
},
  "geometry": {"coordinates":[12.4866695404,55.6469917297],"type":"Point"}
}