{
  "type": "Feature",
  "properties": {
    "addr:full":"Peder Skrams Gade 20 Esbjerg Danmark 6700",
    "addr:housenumber":"20",
    "addr:postcode":"6700",
    "addr:street":"Peder Skrams Gade",
    "iso:country":"DK",
    "sg:address":"Peder Skrams Gade 20",
    "sg:city":"Esbjerg",
    "sg:orig_category":"Psykologer, praktiserende",
    "sg:phone":"+45 75 45 29 95",
    "sg:postcode":"6700",
    "sg:province":"Danmark",
    "wof:name":"Nielsen, B\u00f8rge Johan",
    "wof:placetype":"venue"
},
  "geometry": {"coordinates":[8.456905365,55.465221405],"type":"Point"}
}