{
  "type": "Feature",
  "properties": {
    "addr:full":"Br\u00e6ndg\u00e5rdvej 12 - 16 Herning Danmark 7400",
    "addr:housenumber":"12 16",
    "addr:postcode":"7400",
    "addr:street":"Braendgaardvej",
    "iso:country":"DK",
    "sg:address":"Br\u00e6ndg\u00e5rdvej 12 - 16",
    "sg:city":"Herning",
    "sg:orig_category":"Ungdomsklubber",
    "sg:phone":"+45 97 22 11 03",
    "sg:postcode":"7400",
    "sg:province":"Danmark",
    "wof:name":"Ungdomsklubben Br\u00e6ndg\u00e5rd",
    "wof:placetype":"venue"
},
  "geometry": {"coordinates":[8.9768896103,56.1374168396],"type":"Point"}
}