{
  "type": "Feature",
  "properties": {
    "addr:full":"K\u00e6rhusvej 3, Brejning Kirkeby Spjald Danmark 6971",
    "addr:housenumber":"3",
    "addr:postcode":"6971",
    "addr:street":"Kaerhusvej;Brejning Kirkeby",
    "iso:country":"DK",
    "sg:address":"K\u00e6rhusvej 3, Brejning Kirkeby",
    "sg:city":"Spjald",
    "sg:orig_category":"Kirker",
    "sg:postcode":"6971",
    "sg:province":"Danmark",
    "wof:name":"Brejning Kirke",
    "wof:placetype":"venue"
},
  "geometry": {"coordinates":[8.5089349747,56.1276893616],"type":"Point"}
}