{
  "type": "Feature",
  "properties": {
    "addr:full":"Vejlegade 10 Nakskov Danmark 4900",
    "addr:housenumber":"10",
    "addr:postcode":"4900",
    "addr:street":"Vejlegade",
    "iso:country":"DK",
    "sg:address":"Vejlegade 10",
    "sg:city":"Nakskov",
    "sg:orig_category":"Zoneterapeuter",
    "sg:phone":"+45 54 92 13 96",
    "sg:postcode":"4900",
    "sg:province":"Danmark",
    "wof:name":"Tronier, Hanne",
    "wof:placetype":"venue"
},
  "geometry": {"coordinates":[11.1340141296,54.8309020996],"type":"Point"}
}