{
  "type": "Feature",
  "properties": {
    "iso:country":"DK",
    "sg:address":"Torvet 6",
    "sg:city":"Varde",
    "sg:orig_category":"Supermarkeder",
    "sg:phone":"+45 75 22 28 11",
    "sg:postcode":"6800",
    "sg:province":"Danmark",
    "wof:name":"Rema 1000",
    "wof:placetype":"venue"
},
  "geometry": {"coordinates":[8.4804363251,55.6203842163],"type":"Point"}
}