{
  "type": "Feature",
  "properties": {
    "addr:full":"Holb\u00e6kvej 144 Ringsted Danmark 4100",
    "addr:housenumber":"144",
    "addr:postcode":"4100",
    "addr:street":"Holbaekvej",
    "iso:country":"DK",
    "sg:address":"Holb\u00e6kvej 144",
    "sg:city":"Ringsted",
    "sg:classifiers":[
        {
            "category":"Restaurant",
            "type":"Food & Drink"
        }
    ],
    "sg:phone":"+45 57 60 00 47",
    "sg:postcode":"4100",
    "sg:province":"Danmark",
    "sg:website":"www.haraldsted-soe.dk",
    "wof:name":"Haraldsted Kro/Haraldsted S\u00f8",
    "wof:placetype":"venue"
},
  "geometry": {"coordinates":[11.7388811111,55.4804763794],"type":"Point"}
}