{
  "type": "Feature",
  "properties": {
    "iso:country":"DK",
    "sg:address":"Fmd.: Maja Andersen, G\u00f8gevej 4",
    "sg:city":"Brovst",
    "sg:orig_category":"\u00c3\u2020ldreorganisationer og klubber",
    "sg:phone":"+45 98 23 58 37",
    "sg:postcode":"9460",
    "sg:province":"Danmark",
    "wof:name":"Tranum pensionistforening",
    "wof:placetype":"venue"
},
  "geometry": {"coordinates":[9.5220241547,57.097366333],"type":"Point"}
}