{
  "type": "Feature",
  "properties": {
    "iso:country":"DK",
    "sg:address":"Industriparken 1, \u00d8. Toreby",
    "sg:city":"Nyk\u00f8bing",
    "sg:orig_category":"Vinduespolering",
    "sg:phone":"+45 54 86 03 38",
    "sg:postcode":"4800",
    "sg:province":"Danmark",
    "wof:name":"N.B.S. Vinduespolering",
    "wof:placetype":"venue"
},
  "geometry": {"coordinates":[11.8678541183,54.769241333],"type":"Point"}
}