{
  "type": "Feature",
  "properties": {
    "addr:full":"Chr. 8. Vej 32 Silkeborg Danmark 8600",
    "addr:housenumber":"32",
    "addr:postcode":"8600",
    "addr:street":"Chr. 8 Vej",
    "iso:country":"DK",
    "sg:address":"Chr. 8. Vej 32",
    "sg:city":"Silkeborg",
    "sg:orig_category":"Ejendomshandel",
    "sg:phone":"+45 86 82 09 35",
    "sg:postcode":"8600",
    "sg:province":"Danmark",
    "wof:name":"Bolig- & Erhvervscenter Ejendomsm\u00e6glerhuset",
    "wof:placetype":"venue"
},
  "geometry": {"coordinates":[9.5524425507,56.1693305969],"type":"Point"}
}