{
  "type": "Feature",
  "properties": {
    "addr:full":"Soldalen 19 Vildbjerg Danmark 7480",
    "addr:housenumber":"19",
    "addr:postcode":"7480",
    "addr:street":"Soldalen",
    "iso:country":"DK",
    "sg:address":"Soldalen 19",
    "sg:city":"Vildbjerg",
    "sg:orig_category":"Faglige organisationer og foreninger",
    "sg:phone":"+45 23 60 53 88",
    "sg:postcode":"7480",
    "sg:province":"Danmark",
    "wof:name":"LO i Treh\u00f8je",
    "wof:placetype":"venue"
},
  "geometry": {"coordinates":[8.7757987976,56.1962661743],"type":"Point"}
}