{
  "type": "Feature",
  "properties": {
    "addr:full":"Sennepsmarken 1 Virum Danmark 2830",
    "addr:housenumber":"1",
    "addr:postcode":"2830",
    "addr:street":"Sennepsmarken",
    "iso:country":"DK",
    "sg:address":"Sennepsmarken 1",
    "sg:city":"Virum",
    "sg:orig_category":"Fodterapeuter",
    "sg:phone":"+45 45 85 52 85",
    "sg:postcode":"2830",
    "sg:province":"Danmark",
    "wof:name":"Klinik for Fodterapi - Virumg\u00e5rd",
    "wof:placetype":"venue"
},
  "geometry": {"coordinates":[12.4845752716,55.7838745117],"type":"Point"}
}