{
  "type": "Feature",
  "properties": {
    "addr:full":"v/ Kurt B. Paulsen, Drosselvej 14 Aarup Danmark 5560",
    "addr:housenumber":"14",
    "addr:postcode":"5560",
    "addr:street":"Drosselvej",
    "iso:country":"DK",
    "sg:address":"v/ Kurt B. Paulsen, Drosselvej 14",
    "sg:city":"Aarup",
    "sg:orig_category":"Hobbybetonede foreninger",
    "sg:phone":"+45 64 43 19 60",
    "sg:postcode":"5560",
    "sg:province":"Danmark",
    "wof:name":"Vissenbjerg - Aarup Bridgeklub",
    "wof:placetype":"venue"
},
  "geometry": {"coordinates":[10.0490245819,55.3808059692],"type":"Point"}
}