{
  "type": "Feature",
  "properties": {
    "addr:full":"Gr\u00f8nvej 11 Langeskov Danmark 5550",
    "addr:housenumber":"11",
    "addr:postcode":"5550",
    "addr:street":"Gronvej",
    "iso:country":"DK",
    "sg:address":"Gr\u00f8nvej 11",
    "sg:city":"Langeskov",
    "sg:orig_category":"Dagplejeformidling",
    "sg:phone":"+45 63 38 28 38",
    "sg:postcode":"5550",
    "sg:province":"Danmark",
    "wof:name":"Dagplejeformidlingen i Langeskov Kommune",
    "wof:placetype":"venue"
},
  "geometry": {"coordinates":[10.5867357254,55.3599205017],"type":"Point"}
}