{
  "type": "Feature",
  "properties": {
    "addr:full":"Fmd.: Ejnar Krogh, Poppelvej 7 Thisted Danmark 7700",
    "addr:housenumber":"7",
    "addr:postcode":"7700",
    "addr:street":"Poppelvej",
    "iso:country":"DK",
    "sg:address":"Fmd.: Ejnar Krogh, Poppelvej 7",
    "sg:city":"Thisted",
    "sg:orig_category":"Soldaterforeninger",
    "sg:phone":"+45 97 92 50 80",
    "sg:postcode":"7700",
    "sg:province":"Danmark",
    "wof:name":"Danske Forsvarsbr\u00f8dre, De",
    "wof:placetype":"venue"
},
  "geometry": {"coordinates":[8.6919784546,56.9556121826],"type":"Point"}
}