{
  "type": "Feature",
  "properties": {
    "addr:full":"Nordlundvej 42 Brande Danmark 7330",
    "addr:housenumber":"42",
    "addr:postcode":"7330",
    "addr:street":"Nordlundvej",
    "iso:country":"DK",
    "sg:address":"Nordlundvej 42",
    "sg:city":"Brande",
    "sg:orig_category":"Malermestre",
    "sg:phone":"+45 97 18 38 23",
    "sg:postcode":"7330",
    "sg:province":"Danmark",
    "sg:website":"www.bonne-stylow.dk",
    "wof:name":"Bonne-Stylow",
    "wof:placetype":"venue"
},
  "geometry": {"coordinates":[9.112080574,55.9433631897],"type":"Point"}
}