{
  "type": "Feature",
  "properties": {
    "addr:full":"Yderholmvej 37, Jersie Solr\u00f8d Strand Danmark 2680",
    "addr:housenumber":"37",
    "addr:postcode":"2680",
    "addr:street":"Yderholmvej;Jersie Solrod Strand Danmark",
    "iso:country":"DK",
    "sg:address":"Yderholmvej 37, Jersie",
    "sg:city":"Solr\u00f8d Strand",
    "sg:orig_category":"Autolakering",
    "sg:phone":"+45 56 16 97 75",
    "sg:postcode":"2680",
    "sg:province":"Danmark",
    "wof:name":"Lyksagerg\u00e5rd Autolakering",
    "wof:placetype":"venue"
},
  "geometry": {"coordinates":[-122.35903167719999,48.9091377258],"type":"Point"}
}