{
  "type": "Feature",
  "properties": {
    "iso:country":"DK",
    "sg:address":"Svogerslev Hovedgade 48 ",
    "sg:city":"Roskilde",
    "sg:classifiers":[
        {
            "category":"Wholesale",
            "subcategory":"Machinery & Supplies",
            "type":"Manufacturing & Wholesale Goods"
        }
    ],
    "sg:phone":"+45 46 38 30 36",
    "sg:postcode":"4000",
    "sg:province":"Danmark",
    "sg:tags":[
        "-",
        "agriculture",
        "equipment"
    ],
    "wof:name":"SVOGERSLEV MASKINCENTER A/S",
    "wof:placetype":"venue"
},
  "geometry": {"coordinates":[12.0096817017,55.6336212158],"type":"Point"}
}