{
  "type": "Feature",
  "properties": {
    "addr:full":"Fmd.: Inger Jensen, Markedsgade 7 Vr\u00e5 Danmark 9760",
    "addr:housenumber":"7",
    "addr:postcode":"9760",
    "addr:street":"Markedsgade",
    "iso:country":"DK",
    "sg:address":"Fmd.: Inger Jensen, Markedsgade 7",
    "sg:city":"Vr\u00e5",
    "sg:orig_category":"\u00c3\u2020ldreorganisationer og klubber",
    "sg:phone":"+45 98 98 14 09",
    "sg:postcode":"9760",
    "sg:province":"Danmark",
    "wof:name":"Veteranklubben",
    "wof:placetype":"venue"
},
  "geometry": {"coordinates":[9.9477567673,57.3534927368],"type":"Point"}
}