{
  "type": "Feature",
  "properties": {
    "addr:full":"Karlavej 2 B, N\u00e6sby Odense N Danmark 5270",
    "addr:housenumber":"2 b",
    "addr:postcode":"5270",
    "addr:street":"Karlavej;Naesby",
    "iso:country":"DK",
    "sg:address":"Karlavej 2 B, N\u00e6sby",
    "sg:city":"Odense N",
    "sg:orig_category":"Supermarkeder",
    "sg:phone":"+45 66 18 00 76",
    "sg:postcode":"5270",
    "sg:province":"Danmark",
    "wof:name":"KC Stork\u00f8b, N\u00e6sby A/S",
    "wof:placetype":"venue"
},
  "geometry": {"coordinates":[10.3306798935,55.4711418152],"type":"Point"}
}