{
  "type": "Feature",
  "properties": {
    "addr:full":"M\u00f8llegade 31 H Broager Danmark 6310",
    "addr:housenumber":"31 h",
    "addr:postcode":"6310",
    "addr:street":"Mollegade",
    "iso:country":"DK",
    "sg:address":"M\u00f8llegade 31 H",
    "sg:city":"Broager",
    "sg:orig_category":"Grillbarer",
    "sg:phone":"+45 74 44 21 55",
    "sg:postcode":"6310",
    "sg:province":"Danmark",
    "wof:name":"City Grill Caf\u00e9",
    "wof:placetype":"venue"
},
  "geometry": {"coordinates":[9.6673240662,54.8893623352],"type":"Point"}
}