{
  "type": "Feature",
  "properties": {
    "addr:full":"Ridder Stigs Vej 12 Vejle Danmark 7100",
    "addr:housenumber":"12",
    "addr:postcode":"7100",
    "addr:street":"Ridder Stigs Vej",
    "iso:country":"DK",
    "sg:address":"Ridder Stigs Vej 12",
    "sg:city":"Vejle",
    "sg:orig_category":"Automater",
    "sg:phone":"+45 75 83 36 54",
    "sg:postcode":"7100",
    "sg:province":"Danmark",
    "wof:name":"B.M. Automater",
    "wof:placetype":"venue"
},
  "geometry": {"coordinates":[9.5455188751,55.6788825989],"type":"Point"}
}