{
  "type": "Feature",
  "properties": {
    "addr:full":"J\u00e6gersborgvej 64, 2. Kongens Lyngby Danmark 2800",
    "addr:housenumber":"64 2",
    "addr:postcode":"2800",
    "addr:street":"Jaegersborgvej",
    "iso:country":"DK",
    "sg:address":"J\u00e6gersborgvej 64, 2.",
    "sg:city":"Kongens Lyngby",
    "sg:orig_category":"Motionscentre",
    "sg:phone":"+45 45 88 59 57",
    "sg:postcode":"2800",
    "sg:province":"Danmark",
    "sg:website":"www.lyngbyfitness.dk",
    "wof:name":"Lyngby Fitness",
    "wof:placetype":"venue"
},
  "geometry": {"coordinates":[12.5193386078,55.764831543],"type":"Point"}
}