{
  "type": "Feature",
  "properties": {
    "addr:full":"Hvidsv\u00e6rmervej 135 R\u00f8dovre Danmark 2610",
    "addr:housenumber":"135",
    "addr:postcode":"2610",
    "addr:street":"Hvidsvaermervej",
    "iso:country":"DK",
    "sg:address":"Hvidsv\u00e6rmervej 135",
    "sg:city":"R\u00f8dovre",
    "sg:orig_category":"Maskinfabrikker",
    "sg:phone":"+45 44 53 45 46",
    "sg:postcode":"2610",
    "sg:province":"Danmark",
    "wof:name":"Accurate Products Manufacturing",
    "wof:placetype":"venue"
},
  "geometry": {"coordinates":[10.6992139816,61.1027755737],"type":"Point"}
}