{
  "type": "Feature",
  "properties": {
    "iso:country":"DK",
    "sg:address":"Risb\u00f8ge 55, Ferup",
    "sg:city":"Lunderskov",
    "sg:orig_category":"Konsulentvirksomheder",
    "sg:phone":"+45 75 55 91 91",
    "sg:postcode":"6640",
    "sg:province":"Danmark",
    "sg:website":"www.ita.suite.dk",
    "wof:name":"IT Assistance",
    "wof:placetype":"venue"
},
  "geometry": {"coordinates":[9.2983627319,55.4793586731],"type":"Point"}
}