{
  "type": "Feature",
  "properties": {
    "addr:full":"Jernbanegade 48 A Haslev Danmark 4690",
    "addr:housenumber":"48 a",
    "addr:postcode":"4690",
    "addr:street":"Jernbanegade",
    "iso:country":"DK",
    "sg:address":"Jernbanegade 48 A",
    "sg:city":"Haslev",
    "sg:orig_category":"Genbrugsbutikker",
    "sg:phone":"+45 56 31 70 78",
    "sg:postcode":"4690",
    "sg:province":"Danmark",
    "wof:name":"Billigboden",
    "wof:placetype":"venue"
},
  "geometry": {"coordinates":[11.9635124207,55.3260307312],"type":"Point"}
}