{
  "type": "Feature",
  "properties": {
    "iso:country":"DK",
    "sg:address":"Strandgade 75",
    "sg:city":"Helsing\u00f8r",
    "sg:classifiers":[
        {
            "category":"Food & Beverages",
            "subcategory":"Liquor & Beverages",
            "type":"Retail Goods"
        }
    ],
    "sg:phone":"+45 49 21 00 33",
    "sg:postcode":"3000",
    "sg:province":"Danmark",
    "sg:tags":[
        "vin"
    ],
    "wof:name":"Unna Helsing\u00f8r ApS, Simon",
    "wof:placetype":"venue"
},
  "geometry": {"coordinates":[12.6138763428,56.0343055725],"type":"Point"}
}