{
  "type": "Feature",
  "properties": {
    "addr:full":"Dragstrupvej 119, Dragstrup Erslev Danmark 7950",
    "addr:housenumber":"119",
    "addr:postcode":"7950",
    "addr:street":"Dragstrupvej;Dragstrup",
    "iso:country":"DK",
    "sg:address":"Dragstrupvej 119, Dragstrup",
    "sg:city":"Erslev",
    "sg:orig_category":"Fabrikker",
    "sg:phone":"+45 97 74 18 77",
    "sg:postcode":"7950",
    "sg:province":"Danmark",
    "wof:name":"KPK D\u00f8re & Vinduer A/S",
    "wof:placetype":"venue"
},
  "geometry": {"coordinates":[8.7200698853,56.8354682922],"type":"Point"}
}