{
  "type": "Feature",
  "properties": {
    "addr:full":"Baldersv\u00e6nget 4 Assens Danmark 5610",
    "addr:housenumber":"4",
    "addr:postcode":"5610",
    "addr:street":"Baldersvaenget",
    "iso:country":"DK",
    "sg:address":"Baldersv\u00e6nget 4",
    "sg:city":"Assens",
    "sg:orig_category":"Musik- og solistbureauer",
    "sg:phone":"+45 64 71 37 37",
    "sg:postcode":"5610",
    "sg:province":"Danmark",
    "wof:name":"Nederby, Henrik",
    "wof:placetype":"venue"
},
  "geometry": {"coordinates":[9.8998937607,55.2702522278],"type":"Point"}
}