{
  "type": "Feature",
  "properties": {
    "addr:full":"v/ Helle Jacobsen, Terslev M\u00f8llevej 48 Haslev Danmark 4690",
    "addr:housenumber":"48",
    "addr:postcode":"4690",
    "addr:street":"Mollevej",
    "iso:country":"DK",
    "sg:address":"v/ Helle Jacobsen, Terslev M\u00f8llevej 48",
    "sg:city":"Haslev",
    "sg:orig_category":"Grundejerforeninger",
    "sg:phone":"+45 56 38 19 97",
    "sg:postcode":"4690",
    "sg:province":"Danmark",
    "wof:name":"Grundejerforeningen Terslev Nord",
    "wof:placetype":"venue"
},
  "geometry": {"coordinates":[11.9678049088,55.3230895996],"type":"Point"}
}