{
  "type": "Feature",
  "properties": {
    "addr:full":"Mejsev\u00e6nget 2 N\u00e6stved Danmark 4700",
    "addr:housenumber":"2",
    "addr:postcode":"4700",
    "addr:street":"Mejsevaenget",
    "iso:country":"DK",
    "sg:address":"Mejsev\u00e6nget 2",
    "sg:city":"N\u00e6stved",
    "sg:orig_category":"Autoforhandlere",
    "sg:phone":"+45 55 73 47 87",
    "sg:postcode":"4700",
    "sg:province":"Danmark",
    "wof:name":"E. Olsen-Auto",
    "wof:placetype":"venue"
},
  "geometry": {"coordinates":[-73.5254440308,41.9771537781],"type":"Point"}
}