{
  "type": "Feature",
  "properties": {
    "iso:country":"DK",
    "sg:address":"Kirseb\u00e6rhaven 23-25",
    "sg:city":"Valby",
    "sg:orig_category":"Skoler",
    "sg:phone":"+45 36 30 35 82",
    "sg:postcode":"2500",
    "sg:province":"Danmark",
    "wof:name":"Kirseb\u00e6rhavens Skole",
    "wof:placetype":"venue"
},
  "geometry": {"coordinates":[12.5039663315,55.6493034363],"type":"Point"}
}