{
  "type": "Feature",
  "properties": {
    "addr:full":"Skolegade 3 Stoholm Danmark 7850",
    "addr:housenumber":"3",
    "addr:postcode":"7850",
    "addr:street":"Skolegade",
    "iso:country":"DK",
    "sg:address":"Skolegade 3",
    "sg:city":"Stoholm",
    "sg:orig_category":"Varmeforsyning",
    "sg:phone":"+45 97 54 15 63",
    "sg:postcode":"7850",
    "sg:province":"Danmark",
    "wof:name":"Stoholm Fjernvarmev\u00e6rk A.m.b.A.",
    "wof:placetype":"venue"
},
  "geometry": {"coordinates":[9.1492290497,56.4846763611],"type":"Point"}
}