{
  "type": "Feature",
  "properties": {
    "iso:country":"DK",
    "sg:address":"\u00d8stergade 29",
    "sg:city":"Skive",
    "sg:orig_category":"Daginstitutioner i Skive Kommune",
    "sg:phone":"+45 99 15 10 00",
    "sg:postcode":"7800",
    "sg:province":"Danmark",
    "wof:name":"Dagpleje, Den kommunale",
    "wof:placetype":"venue"
},
  "geometry": {"coordinates":[9.0302095413,56.566192627],"type":"Point"}
}