{
  "type": "Feature",
  "properties": {
    "addr:full":"Rytterv\u00e6nget 7 Lynge Danmark 3540",
    "addr:housenumber":"7",
    "addr:postcode":"3540",
    "addr:street":"Ryttervaenget",
    "iso:country":"DK",
    "sg:address":"Rytterv\u00e6nget 7",
    "sg:city":"Lynge",
    "sg:orig_category":"INGENI\u00c3\u02dcRER",
    "sg:phone":"+45 48 18 80 04",
    "sg:postcode":"3540",
    "sg:province":"Danmark",
    "wof:name":"Quality Consult",
    "wof:placetype":"venue"
},
  "geometry": {"coordinates":[12.2734966278,55.834186554],"type":"Point"}
}