{
  "type": "Feature",
  "properties": {
    "iso:country":"DK",
    "sg:address":"Torvegade 24",
    "sg:city":"K\u00f8benhavn",
    "sg:orig_category":"Skomagere",
    "sg:phone":"+45 32 57 58 45",
    "sg:postcode":"1400",
    "sg:province":"Danmark",
    "wof:name":"Christianshavns H\u00e6le & N\u00f8glebar",
    "wof:placetype":"venue"
},
  "geometry": {"coordinates":[12.5975999832,55.6689987183],"type":"Point"}
}