{
  "type": "Feature",
  "properties": {
    "addr:full":"Godth\u00e5bsvej 5 Vejle Danmark 7100",
    "addr:housenumber":"5",
    "addr:postcode":"7100",
    "addr:street":"Godthaabsvej",
    "iso:country":"DK",
    "sg:address":"Godth\u00e5bsvej 5",
    "sg:city":"Vejle",
    "sg:orig_category":"Fabrikker",
    "sg:phone":"+45 75 72 04 00",
    "sg:postcode":"7100",
    "sg:province":"Danmark",
    "wof:name":"De Forenede Trailerfabrikker",
    "wof:placetype":"venue"
},
  "geometry": {"coordinates":[9.5482120514,55.6713256836],"type":"Point"}
}