{
  "type": "Feature",
  "properties": {
    "addr:full":"Svallerup Bygade 26, Svallerup Kalundborg Danmark 4400",
    "addr:housenumber":"26",
    "addr:postcode":"4400",
    "addr:street":"Svallerup Bygade;Svallerup",
    "iso:country":"DK",
    "sg:address":"Svallerup Bygade 26, Svallerup",
    "sg:city":"Kalundborg",
    "sg:orig_category":"Diners transportables",
    "sg:phone":"+45 59 59 90 24",
    "sg:postcode":"4400",
    "sg:province":"Danmark",
    "wof:name":"ALG`s Diners Transportable",
    "wof:placetype":"venue"
},
  "geometry": {"coordinates":[11.0934085846,55.6797485352],"type":"Point"}
}