{
  "type": "Feature",
  "properties": {
    "iso:country":"DK",
    "sg:address":"Brandts Passage 37",
    "sg:city":"Odense C",
    "sg:orig_category":"Boghandlere",
    "sg:phone":"+45 66 14 53 76",
    "sg:postcode":"5000",
    "sg:province":"Danmark",
    "wof:name":"Kunst Boghandel Brandts Kl\u00e6defabrik",
    "wof:placetype":"venue"
},
  "geometry": {"coordinates":[10.3813066483,55.3956222534],"type":"Point"}
}