{
  "type": "Feature",
  "properties": {
    "iso:country":"DK",
    "sg:address":"All\u00e9gade 1",
    "sg:city":"Odense C",
    "sg:orig_category":"Boghandlere",
    "sg:phone":"+45 66 12 27 07",
    "sg:postcode":"5000",
    "sg:province":"Danmark",
    "wof:name":"Toustrups Boghandel",
    "wof:placetype":"venue"
},
  "geometry": {"coordinates":[10.3963108063,55.3910942078],"type":"Point"}
}