{
  "type": "Feature",
  "properties": {
    "iso:country":"DK",
    "sg:address":"Blommevej 22",
    "sg:city":"Randers",
    "sg:orig_category":"Landbrugsmaskiner",
    "sg:phone":"+45 86 41 75 22",
    "sg:postcode":"8900",
    "sg:province":"Danmark",
    "wof:name":"Feld & Jacobsen I/S",
    "wof:placetype":"venue"
},
  "geometry": {"coordinates":[10.0542993546,56.4841690063],"type":"Point"}
}