{
  "type": "Feature",
  "properties": {
    "addr:full":"Hovedgaden 26 B Billund Danmark 7190",
    "addr:housenumber":"26 b",
    "addr:postcode":"7190",
    "addr:street":"Hovedgaden",
    "iso:country":"DK",
    "sg:address":"Hovedgaden 26 B",
    "sg:city":"Billund",
    "sg:orig_category":"Sportsartikler",
    "sg:phone":"+45 75 33 81 79",
    "sg:postcode":"7190",
    "sg:province":"Danmark",
    "sg:website":"www.sportmaster.dk",
    "wof:name":"Sportmaster",
    "wof:placetype":"venue"
},
  "geometry": {"coordinates":[9.1122322083,55.7325019836],"type":"Point"}
}