{
  "type": "Feature",
  "properties": {
    "addr:full":"Gels\u00e5vej 7, Over Jerstal Vojens Danmark 6500",
    "addr:housenumber":"7",
    "addr:postcode":"6500",
    "addr:street":"Gelsaavej;Over Jerstal",
    "iso:country":"DK",
    "sg:address":"Gels\u00e5vej 7, Over Jerstal",
    "sg:city":"Vojens",
    "sg:orig_category":"Kartofler",
    "sg:phone":"+45 74 54 78 77",
    "sg:postcode":"6500",
    "sg:province":"Danmark",
    "wof:name":"Kartoffelhuset",
    "wof:placetype":"venue"
},
  "geometry": {"coordinates":[9.2987146378,55.2457237244],"type":"Point"}
}