{
  "type": "Feature",
  "properties": {
    "addr:full":"\u00c5gade 10 Kolding Danmark 6000",
    "addr:housenumber":"10",
    "addr:postcode":"6000",
    "addr:street":"Aagade",
    "iso:country":"DK",
    "sg:address":"\u00c5gade 10",
    "sg:city":"Kolding",
    "sg:orig_category":"\u00c3\u02dcvrige skoler",
    "sg:phone":"+45 76 30 11 00",
    "sg:postcode":"6000",
    "sg:province":"Danmark",
    "wof:name":"Designskolen Kolding",
    "wof:placetype":"venue"
},
  "geometry": {"coordinates":[9.4807472229,55.4862556458],"type":"Point"}
}