{
  "type": "Feature",
  "properties": {
    "addr:full":"Afd.fmd.: Thorvald Jakobsen, Hjejlevej 19, st. tv. Silkeborg Danmark 8600",
    "addr:housenumber":"19 st. tv.",
    "addr:postcode":"8600",
    "addr:street":"Thorvald;Hjejlevej",
    "iso:country":"DK",
    "sg:address":"Afd.fmd.: Thorvald Jakobsen, Hjejlevej 19, st. tv.",
    "sg:city":"Silkeborg",
    "sg:orig_category":"Kolonihaveforeninger",
    "sg:phone":"+45 86 81 39 02",
    "sg:postcode":"8600",
    "sg:province":"Danmark",
    "wof:name":"Haveforeningen Frydensbjerg",
    "wof:placetype":"venue"
},
  "geometry": {"coordinates":[9.5524425507,56.1693305969],"type":"Point"}
}