{
  "type": "Feature",
  "properties": {
    "addr:full":"Ribevej 46 Varde Danmark 6800",
    "addr:housenumber":"46",
    "addr:postcode":"6800",
    "addr:street":"Ribevej",
    "iso:country":"DK",
    "sg:address":"Ribevej 46",
    "sg:city":"Varde",
    "sg:orig_category":"Boligselskaber",
    "sg:phone":"+45 75 22 30 68",
    "sg:postcode":"6800",
    "sg:province":"Danmark",
    "wof:name":"Columbus, Boligforeningen",
    "wof:placetype":"venue"
},
  "geometry": {"coordinates":[8.4925851822,55.6107978821],"type":"Point"}
}