{
  "type": "Feature",
  "properties": {
    "addr:full":"Gl. Viborgvej 1, Hvam Aalestrup Danmark 9620",
    "addr:housenumber":"1",
    "addr:postcode":"9620",
    "addr:street":"Gl. Viborgvej",
    "iso:country":"DK",
    "sg:address":"Gl. Viborgvej 1, Hvam",
    "sg:city":"Aalestrup",
    "sg:orig_category":"Ejendomshandel",
    "sg:phone":"+45 98 64 80 70",
    "sg:postcode":"9620",
    "sg:province":"Danmark",
    "wof:name":"H\u00f8gh Ejendomshandel, Tage",
    "wof:placetype":"venue"
},
  "geometry": {"coordinates":[9.4901504517,56.6938285828],"type":"Point"}
}