{
  "type": "Feature",
  "properties": {
    "iso:country":"DK",
    "sg:address":"Tordenskjoldsgade 3",
    "sg:city":"\u00c5rhus N",
    "sg:classifiers":[
        {
            "category":"Food & Beverages",
            "subcategory":"Liquor & Beverages",
            "type":"Retail Goods"
        }
    ],
    "sg:phone":"+45 86 16 78 79",
    "sg:postcode":"8200",
    "sg:province":"Danmark",
    "sg:tags":[
        "vin"
    ],
    "wof:name":"Kj\u00e6r & Sommerfeldt A/S",
    "wof:placetype":"venue"
},
  "geometry": {"coordinates":[10.2154083252,56.1695976257],"type":"Point"}
}