{
  "type": "Feature",
  "properties": {
    "iso:country":"DK",
    "sg:address":"Roslevvej 41, Nannerup",
    "sg:city":"Roslev",
    "sg:orig_category":"Autoreparation og -service",
    "sg:phone":"+45 97 57 47 89",
    "sg:postcode":"7870",
    "sg:province":"Danmark",
    "wof:name":"Kims Auto",
    "wof:placetype":"venue"
},
  "geometry": {"coordinates":[8.8715353012,56.7570304871],"type":"Point"}
}