{
  "type": "Feature",
  "properties": {
    "addr:full":"Skyttevej 7 Hammel Danmark 8450",
    "addr:housenumber":"7",
    "addr:postcode":"8450",
    "addr:street":"Skyttevej",
    "iso:country":"DK",
    "sg:address":"Skyttevej 7",
    "sg:city":"Hammel",
    "sg:orig_category":"Haveservice",
    "sg:phone":"+45 86 96 33 56",
    "sg:postcode":"8450",
    "sg:province":"Danmark",
    "wof:name":"Kristensen, Villy Hornb\u00e6k",
    "wof:placetype":"venue"
},
  "geometry": {"coordinates":[9.8715085983,56.2523803711],"type":"Point"}
}