{
  "type": "Feature",
  "properties": {
    "addr:full":"L\u00f8geskov 50 Stenstrup Danmark 5771",
    "addr:housenumber":"50",
    "addr:postcode":"5771",
    "addr:street":"Logeskov",
    "iso:country":"DK",
    "sg:address":"L\u00f8geskov 50",
    "sg:city":"Stenstrup",
    "sg:orig_category":"Autoreparation og -service",
    "sg:phone":"+45 62 26 31 31",
    "sg:postcode":"5771",
    "sg:province":"Danmark",
    "wof:name":"L\u00f8geskov Auto",
    "wof:placetype":"venue"
},
  "geometry": {"coordinates":[10.4700088501,55.1465415955],"type":"Point"}
}