{
  "type": "Feature",
  "properties": {
    "addr:full":"N\u00f8rregade 57 Vemb Danmark 7570",
    "addr:housenumber":"57",
    "addr:postcode":"7570",
    "addr:street":"Norregade",
    "iso:country":"DK",
    "sg:address":"N\u00f8rregade 57",
    "sg:city":"Vemb",
    "sg:orig_category":"Autoreparation og -service",
    "sg:phone":"+45 97 48 17 00",
    "sg:postcode":"7570",
    "sg:province":"Danmark",
    "wof:name":"DK - Benzin Vemb",
    "wof:placetype":"venue"
},
  "geometry": {"coordinates":[8.3416585922,56.3467559814],"type":"Point"}
}