{
  "type": "Feature",
  "properties": {
    "addr:full":"Fmd.: Leif Thorup, Vestbyen 1, Vestby N\u00f8rager Danmark 9610",
    "addr:housenumber":"1",
    "addr:postcode":"9610",
    "addr:street":"Vestbyen",
    "iso:country":"DK",
    "sg:address":"Fmd.: Leif Thorup, Vestbyen 1, Vestby",
    "sg:city":"N\u00f8rager",
    "sg:orig_category":"Borger- og beboerforeninger",
    "sg:phone":"+45 98 65 41 72",
    "sg:postcode":"9610",
    "sg:province":"Danmark",
    "wof:name":"Haverslev Borgerforening",
    "wof:placetype":"venue"
},
  "geometry": {"coordinates":[23.6780910492,70.63595581049999],"type":"Point"}
}