{
  "type": "Feature",
  "properties": {
    "addr:full":"Sankelmarksvej 10 Silkeborg Danmark 8600",
    "addr:housenumber":"10",
    "addr:postcode":"8600",
    "addr:street":"Sankelmarksvej",
    "iso:country":"DK",
    "sg:address":"Sankelmarksvej 10",
    "sg:city":"Silkeborg",
    "sg:orig_category":"Murermestre",
    "sg:phone":"+45 86 82 85 99",
    "sg:postcode":"8600",
    "sg:province":"Danmark",
    "wof:name":"S\u00f8gaard, Ulf",
    "wof:placetype":"venue"
},
  "geometry": {"coordinates":[9.521733284,56.1740684509],"type":"Point"}
}