{
  "type": "Feature",
  "properties": {
    "addr:full":"Skjoldh\u00f8j All\u00e9 3 Charlottenlund Danmark 2920",
    "addr:housenumber":"3",
    "addr:postcode":"2920",
    "addr:street":"Skjoldhoj Alle\u0301",
    "iso:country":"DK",
    "sg:address":"Skjoldh\u00f8j All\u00e9 3",
    "sg:city":"Charlottenlund",
    "sg:orig_category":"Faglige organisationer og foreninger",
    "sg:phone":"+45 39 96 02 02",
    "sg:postcode":"2920",
    "sg:province":"Danmark",
    "wof:name":"Det Danske Travselskab",
    "wof:placetype":"venue"
},
  "geometry": {"coordinates":[12.5721197128,55.7532615662],"type":"Point"}
}