{
  "type": "Feature",
  "properties": {
    "addr:full":"Skolegade 3 Aulum Danmark 7490",
    "addr:housenumber":"3",
    "addr:postcode":"7490",
    "addr:street":"Skolegade",
    "iso:country":"DK",
    "sg:address":"Skolegade 3",
    "sg:city":"Aulum",
    "sg:orig_category":"Tandklinikker, Kommunale",
    "sg:phone":"+45 97 47 27 38",
    "sg:postcode":"7490",
    "sg:province":"Danmark",
    "wof:name":"Kommunale Tandpleje, Den",
    "wof:placetype":"venue"
},
  "geometry": {"coordinates":[8.7973117828,56.2652130127],"type":"Point"}
}