{
  "type": "Feature",
  "properties": {
    "addr:full":"Gersonsvej 23 Hellerup Danmark 2900",
    "addr:housenumber":"23",
    "addr:postcode":"2900",
    "addr:street":"Gersonsvej",
    "iso:country":"DK",
    "sg:address":"Gersonsvej 23",
    "sg:city":"Hellerup",
    "sg:orig_category":"INGENI\u00c3\u02dcRER",
    "sg:phone":"+45 39 62 17 02",
    "sg:postcode":"2900",
    "sg:province":"Danmark",
    "wof:name":"Krarup-Hansen, H.",
    "wof:placetype":"venue"
},
  "geometry": {"coordinates":[12.5671043396,55.734664917],"type":"Point"}
}