{
  "type": "Feature",
  "properties": {
    "addr:full":"Skoleleder: Gitte H\u00f8jsgaard, Sverigesvej 37 Dianalund Danmark 4293",
    "addr:housenumber":"37",
    "addr:postcode":"4293",
    "addr:street":"Sverigesvej",
    "iso:country":"DK",
    "sg:address":"Skoleleder: Gitte H\u00f8jsgaard, Sverigesvej 37",
    "sg:city":"Dianalund",
    "sg:orig_category":"Oplysningsforbund",
    "sg:phone":"+45 58 24 11 22",
    "sg:postcode":"4293",
    "sg:province":"Danmark",
    "wof:name":"Dianalund Oplysningsforbund DOF",
    "wof:placetype":"venue"
},
  "geometry": {"coordinates":[11.4945745468,55.5332489014],"type":"Point"}
}