{
  "type": "Feature",
  "properties": {
    "iso:country":"DK",
    "sg:address":"Pilealle 2",
    "sg:city":"Frederikssund",
    "sg:orig_category":"Boligselskaber",
    "sg:phone":"+45 47 38 42 58",
    "sg:postcode":"3600",
    "sg:province":"Danmark",
    "wof:name":"Frederikssund Boligselskab",
    "wof:placetype":"venue"
},
  "geometry": {"coordinates":[12.0736303329,55.8321495056],"type":"Point"}
}