{
  "type": "Feature",
  "properties": {
    "addr:full":"Volderslevvej 61, Hjallese Odense S Danmark 5260",
    "addr:housenumber":"61",
    "addr:postcode":"5260",
    "addr:street":"Volderslevvej",
    "iso:country":"DK",
    "sg:address":"Volderslevvej 61, Hjallese",
    "sg:city":"Odense S",
    "sg:orig_category":"Autoreparation og -service",
    "sg:phone":"+45 65 92 03 92",
    "sg:postcode":"5260",
    "sg:province":"Danmark",
    "wof:name":"Odense Bilpleje",
    "wof:placetype":"venue"
},
  "geometry": {"coordinates":[10.3157806396,55.3122825623],"type":"Point"}
}