{
  "type": "Feature",
  "properties": {
    "addr:full":"\u00d8rstedsvej 18 Ribe Danmark 6760",
    "addr:housenumber":"18",
    "addr:postcode":"6760",
    "addr:street":"Orstedsvej",
    "iso:country":"DK",
    "sg:address":"\u00d8rstedsvej 18",
    "sg:city":"Ribe",
    "sg:classifiers":[
        {
            "category":"Utilities",
            "subcategory":"Refuse",
            "type":"Services"
        }
    ],
    "sg:phone":"+45 75 42 18 33",
    "sg:postcode":"6760",
    "sg:province":"Danmark",
    "sg:tags":[
        "catering"
    ],
    "sg:website":"www.jogros.dk",
    "wof:name":"Jogros Catering",
    "wof:placetype":"venue"
},
  "geometry": {"coordinates":[8.772397995,55.351436615],"type":"Point"}
}