{
  "type": "Feature",
  "properties": {
    "addr:full":"Tingskoven 8 Tranbjerg Danmark 8310",
    "addr:housenumber":"8",
    "addr:postcode":"8310",
    "addr:street":"Tingskoven",
    "iso:country":"DK",
    "sg:address":"Tingskoven 8",
    "sg:city":"Tranbjerg",
    "sg:orig_category":"Hunde",
    "sg:phone":"+45 86 29 02 06",
    "sg:postcode":"8310",
    "sg:province":"Danmark",
    "wof:name":"Runeh\u00f8j, Kennel",
    "wof:placetype":"venue"
},
  "geometry": {"coordinates":[10.1103162766,56.0746612549],"type":"Point"}
}