{
  "type": "Feature",
  "properties": {
    "addr:full":"Skolegade 5 Aulum Danmark 7490",
    "addr:housenumber":"5",
    "addr:postcode":"7490",
    "addr:street":"Skolegade",
    "iso:country":"DK",
    "sg:address":"Skolegade 5",
    "sg:city":"Aulum",
    "sg:orig_category":"Legestuer",
    "sg:postcode":"7490",
    "sg:province":"Danmark",
    "wof:name":"Aulum Legestue",
    "wof:placetype":"venue"
},
  "geometry": {"coordinates":[8.7970714569,56.2645988464],"type":"Point"}
}