{
  "type": "Feature",
  "properties": {
    "addr:full":"Centerpladsen 7 A Tinglev Danmark 6360",
    "addr:housenumber":"7 a",
    "addr:postcode":"6360",
    "addr:street":"Centerpladsen",
    "iso:country":"DK",
    "sg:address":"Centerpladsen 7 A",
    "sg:city":"Tinglev",
    "sg:orig_category":"Revisorer",
    "sg:phone":"+45 74 64 24 24",
    "sg:postcode":"6360",
    "sg:province":"Danmark",
    "wof:name":"Revisionscentret a/s",
    "wof:placetype":"venue"
},
  "geometry": {"coordinates":[9.254693985,54.9367980957],"type":"Point"}
}