{
  "type": "Feature",
  "properties": {
    "iso:country":"DK",
    "sg:address":"Hedelyngen 115",
    "sg:city":"Herlev",
    "sg:orig_category":"Video- og TV-produktion",
    "sg:phone":"+45 44 84 05 26",
    "sg:postcode":"2730",
    "sg:province":"Danmark",
    "wof:name":"Storyline",
    "wof:placetype":"venue"
},
  "geometry": {"coordinates":[12.4216451645,55.7288246155],"type":"Point"}
}