{
  "type": "Feature",
  "properties": {
    "iso:country":"DK",
    "sg:address":"R\u00e5dhuset, Them-Centret 12",
    "sg:city":"Them",
    "sg:orig_category":"Kommunen",
    "sg:phone":"+45 87 97 33 33",
    "sg:postcode":"8653",
    "sg:province":"Danmark",
    "wof:name":"Them Kommune",
    "wof:placetype":"venue"
},
  "geometry": {"coordinates":[9.5470619202,56.0934791565],"type":"Point"}
}