{
  "type": "Feature",
  "properties": {
    "addr:full":"Ordrupvej 54 - 56 Charlottenlund Danmark 2920",
    "addr:housenumber":"54 56",
    "addr:postcode":"2920",
    "addr:street":"Ordrupvej",
    "iso:country":"DK",
    "sg:address":"Ordrupvej 54 - 56",
    "sg:city":"Charlottenlund",
    "sg:orig_category":"Ure og urmagere",
    "sg:phone":"+45 39 63 68 61",
    "sg:postcode":"2920",
    "sg:province":"Danmark",
    "sg:website":"www.lynggaard-guld-soelv.dk",
    "wof:name":"Lynggaard, H. Guld S\u00f8lv A/S",
    "wof:placetype":"venue"
},
  "geometry": {"coordinates":[12.5819635391,55.7662239075],"type":"Point"}
}