{
  "type": "Feature",
  "properties": {
    "iso:country":"DK",
    "sg:address":"N\u00e6stvedvej 40, Baarse",
    "sg:city":"Pr\u00e6st\u00f8",
    "sg:orig_category":"Bagere",
    "sg:phone":"+45 55 99 00 31",
    "sg:postcode":"4720",
    "sg:province":"Danmark",
    "wof:name":"Baarse Bageri",
    "wof:placetype":"venue"
},
  "geometry": {"coordinates":[12.161105,55.099545],"type":"Point"}
}