{
  "type": "Feature",
  "properties": {
    "addr:full":"Nordh\u00f8jvej 25 Gilleleje Danmark 3250",
    "addr:housenumber":"25",
    "addr:postcode":"3250",
    "addr:street":"Nordhojvej",
    "iso:country":"DK",
    "sg:address":"Nordh\u00f8jvej 25",
    "sg:city":"Gilleleje",
    "sg:orig_category":"Murermestre",
    "sg:phone":"+45 48 30 25 53",
    "sg:postcode":"3250",
    "sg:province":"Danmark",
    "wof:name":"Form & Byg",
    "wof:placetype":"venue"
},
  "geometry": {"coordinates":[12.2887840271,56.1273078918],"type":"Point"}
}