{
  "type": "Feature",
  "properties": {
    "addr:full":"Kirstinelundsvej 12 Ballerup Danmark 2750",
    "addr:housenumber":"12",
    "addr:postcode":"2750",
    "addr:street":"Kirstinelundsvej",
    "iso:country":"DK",
    "sg:address":"Kirstinelundsvej 12",
    "sg:city":"Ballerup",
    "sg:orig_category":"Plejehjem",
    "sg:phone":"+45 44 77 36 60",
    "sg:postcode":"2750",
    "sg:province":"Danmark",
    "wof:name":"Kirstinehaven Plejehjem",
    "wof:placetype":"venue"
},
  "geometry": {"coordinates":[12.361456871,55.7277412415],"type":"Point"}
}