{
  "type": "Feature",
  "properties": {
    "addr:full":"Nordhavnskaj 3 Hvide Sande Danmark 6960",
    "addr:housenumber":"3",
    "addr:postcode":"6960",
    "addr:street":"Nordhavnskaj",
    "iso:country":"DK",
    "sg:address":"Nordhavnskaj 3",
    "sg:city":"Hvide Sande",
    "sg:orig_category":"Vodbinderier",
    "sg:phone":"+45 97 31 29 44",
    "sg:postcode":"6960",
    "sg:province":"Danmark",
    "sg:website":"www.nordsotrawl.dk",
    "wof:name":"Nords\u00f8 Trawl",
    "wof:placetype":"venue"
},
  "geometry": {"coordinates":[8.124168396,56.0049057007],"type":"Point"}
}