{
  "type": "Feature",
  "properties": {
    "iso:country":"DK",
    "sg:address":"Byleddet 22 B",
    "sg:city":"Brabrand",
    "sg:orig_category":"Integrerede institutioner",
    "sg:phone":"+45 86 26 07 09",
    "sg:postcode":"8220",
    "sg:province":"Danmark",
    "wof:name":"S\u00f8stjernen, Integreret Inst.",
    "wof:placetype":"venue"
},
  "geometry": {"coordinates":[10.0897655487,56.1506462097],"type":"Point"}
}