{
  "type": "Feature",
  "properties": {
    "addr:full":"Smedegade 8 Kolding Danmark 6000",
    "addr:housenumber":"8",
    "addr:postcode":"6000",
    "addr:street":"Smedegade",
    "iso:country":"DK",
    "sg:address":"Smedegade 8",
    "sg:city":"Kolding",
    "sg:orig_category":"Bilpleje",
    "sg:phone":"+45 75 50 39 11",
    "sg:postcode":"6000",
    "sg:province":"Danmark",
    "wof:name":"dankemi Bilplejemidler ApS",
    "wof:placetype":"venue"
},
  "geometry": {"coordinates":[9.48185,55.469814],"type":"Point"}
}