{
  "type": "Feature",
  "properties": {
    "addr:full":"Hammelvej 145, Jebjerg Lang\u00e5 Danmark 8870",
    "addr:housenumber":"145",
    "addr:postcode":"8870",
    "addr:street":"Hammelvej;Jebjerg Langaa Danmark",
    "iso:country":"DK",
    "sg:address":"Hammelvej 145, Jebjerg",
    "sg:city":"Lang\u00e5",
    "sg:classifiers":[
        {
            "category":"Food & Beverages",
            "subcategory":"Liquor & Beverages",
            "type":"Retail Goods"
        }
    ],
    "sg:phone":"+45 86 44 50 69",
    "sg:postcode":"8870",
    "sg:province":"Danmark",
    "sg:tags":[
        "vin"
    ],
    "wof:name":"Lundgaard Vine",
    "wof:placetype":"venue"
},
  "geometry": {"coordinates":[9.8955049515,56.3900756836],"type":"Point"}
}