{
  "type": "Feature",
  "properties": {
    "iso:country":"DK",
    "sg:address":"Skovforten 4, Lysabildskov",
    "sg:city":"Sydals",
    "sg:orig_category":"Campingpladser",
    "sg:phone":"+45 74 40 43 98",
    "sg:postcode":"6470",
    "sg:province":"Danmark",
    "sg:website":"www.dk.camp.dk/lysabildskov",
    "wof:name":"Lysabildskov Camping & Feriecenter",
    "wof:placetype":"venue"
},
  "geometry": {"coordinates":[9.8924627304,54.9105377197],"type":"Point"}
}