{
  "type": "Feature",
  "properties": {
    "iso:country":"DK",
    "sg:address":"Buntmagervej 1",
    "sg:city":"Randers",
    "sg:orig_category":"Eksport",
    "sg:phone":"+45 86 40 14 50",
    "sg:postcode":"8900",
    "sg:province":"Danmark",
    "wof:name":"Danalco International",
    "wof:placetype":"venue"
},
  "geometry": {"coordinates":[10.0011587143,56.4749641418],"type":"Point"}
}