{
  "type": "Feature",
  "properties": {
    "iso:country":"DK",
    "sg:address":"N\u00f8rregade 1 A",
    "sg:city":"H\u00f8jer",
    "sg:orig_category":"Servicestationer",
    "sg:phone":"+45 74 78 26 35",
    "sg:postcode":"6280",
    "sg:province":"Danmark",
    "wof:name":"H\u00f8jer Shell Service",
    "wof:placetype":"venue"
},
  "geometry": {"coordinates":[-2.1972899437,49.2049789429],"type":"Point"}
}