{
  "type": "Feature",
  "properties": {
    "iso:country":"DK",
    "sg:address":"Jyllandsvej 15",
    "sg:city":"Hobro",
    "sg:orig_category":"Bowlingcentre",
    "sg:phone":"+45 98 51 25 00",
    "sg:postcode":"9500",
    "sg:province":"Danmark",
    "wof:name":"Bowl'n Fun Centret",
    "wof:placetype":"venue"
},
  "geometry": {"coordinates":[9.8174953461,56.6296424866],"type":"Point"}
}