{
  "type": "Feature",
  "properties": {
    "addr:full":"N\u00f8rremarksvej 56 Klarup Danmark 9270",
    "addr:housenumber":"56",
    "addr:postcode":"9270",
    "addr:street":"Norremarksvej",
    "iso:country":"DK",
    "sg:address":"N\u00f8rremarksvej 56",
    "sg:city":"Klarup",
    "sg:orig_category":"Autoforhandlere",
    "sg:phone":"+45 98 14 03 41",
    "sg:postcode":"9270",
    "sg:province":"Danmark",
    "wof:name":"R J Biler",
    "wof:placetype":"venue"
},
  "geometry": {"coordinates":[10.0557632446,57.0165481567],"type":"Point"}
}