{
  "type": "Feature",
  "properties": {
    "addr:full":"Vestergade 17 Fjerritslev Danmark 9690",
    "addr:housenumber":"17",
    "addr:postcode":"9690",
    "addr:street":"Vestergade",
    "iso:country":"DK",
    "sg:address":"Vestergade 17",
    "sg:city":"Fjerritslev",
    "sg:orig_category":"Forsikringer",
    "sg:phone":"+45 98 21 34 22",
    "sg:postcode":"9690",
    "sg:province":"Danmark",
    "wof:name":"Alm. Brand",
    "wof:placetype":"venue"
},
  "geometry": {"coordinates":[9.2630681992,57.0882072449],"type":"Point"}
}