{
  "type": "Feature",
  "properties": {
    "addr:full":"Bymosevej 17 Helsinge Danmark 3200",
    "addr:housenumber":"17",
    "addr:postcode":"3200",
    "addr:street":"Bymosevej",
    "iso:country":"DK",
    "sg:address":"Bymosevej 17",
    "sg:city":"Helsinge",
    "sg:orig_category":"Fabrikker",
    "sg:phone":"+45 48 79 55 21",
    "sg:postcode":"3200",
    "sg:province":"Danmark",
    "wof:name":"T\u00f8pholm & Westermann ApS",
    "wof:placetype":"venue"
},
  "geometry": {"coordinates":[12.1962051392,56.0157089233],"type":"Point"}
}