{
  "type": "Feature",
  "properties": {
    "iso:country":"DK",
    "sg:address":"Spanien 1",
    "sg:city":"\u00c5rhus C",
    "sg:orig_category":"Kiosker",
    "sg:phone":"+45 86 12 52 17",
    "sg:postcode":"8000",
    "sg:province":"Danmark",
    "wof:name":"Sv\u00f8mmehallens Vin & Tobak",
    "wof:placetype":"venue"
},
  "geometry": {"coordinates":[-2.9886798859,39.8950195312],"type":"Point"}
}