{
  "type": "Feature",
  "properties": {
    "addr:full":"Prags Boulevard 55 K\u00f8benhavn S Danmark 2300",
    "addr:housenumber":"55",
    "addr:postcode":"2300",
    "addr:street":"Prags Boulevard;Kobenhavn S Danmark",
    "iso:country":"DK",
    "sg:address":"Prags Boulevard 55",
    "sg:city":"K\u00f8benhavn S",
    "sg:orig_category":"Non-Classified Establishments",
    "sg:phone":"+45 32 95 29 23",
    "sg:postcode":"2300",
    "sg:province":"Danmark",
    "sg:website":"www.it-univers.com",
    "wof:name":"IT Univers ApS",
    "wof:placetype":"venue"
},
  "geometry": {"coordinates":[12.1321201324,46.7195549011],"type":"Point"}
}