{
  "type": "Feature",
  "properties": {
    "addr:full":"Badevej 1, S\u00f8ndervig Ringk\u00f8bing Danmark 6950",
    "addr:housenumber":"1",
    "addr:postcode":"6950",
    "addr:street":"Badevej",
    "iso:country":"DK",
    "sg:address":"Badevej 1, S\u00f8ndervig",
    "sg:city":"Ringk\u00f8bing",
    "sg:orig_category":"Sportsartikler",
    "sg:phone":"+45 97 33 88 11",
    "sg:postcode":"6950",
    "sg:province":"Danmark",
    "wof:name":"West Wind Sport & Mode ApS",
    "wof:placetype":"venue"
},
  "geometry": {"coordinates":[-114.0767440796,46.4432487488],"type":"Point"}
}