{
  "type": "Feature",
  "properties": {
    "addr:full":"Naurbjergvej 22 Lille Skensved Danmark 4623",
    "addr:housenumber":"22",
    "addr:postcode":"4623",
    "addr:street":"Naurbjergvej",
    "iso:country":"DK",
    "sg:address":"Naurbjergvej 22",
    "sg:city":"Lille Skensved",
    "sg:orig_category":"Dataservice",
    "sg:phone":"+45 56 16 73 52",
    "sg:postcode":"4623",
    "sg:province":"Danmark",
    "wof:name":"Jama Data",
    "wof:placetype":"venue"
},
  "geometry": {"coordinates":[12.1434640884,55.5174217224],"type":"Point"}
}