{
  "type": "Feature",
  "properties": {
    "addr:full":"Nejstdalen 2 Hirtshals Danmark 9850",
    "addr:housenumber":"2",
    "addr:postcode":"9850",
    "addr:street":"Nejstdalen",
    "iso:country":"DK",
    "sg:address":"Nejstdalen 2",
    "sg:city":"Hirtshals",
    "sg:orig_category":"Supermarkeder",
    "sg:phone":"+45 98 94 40 94",
    "sg:postcode":"9850",
    "sg:province":"Danmark",
    "wof:name":"Aktiv Super",
    "wof:placetype":"venue"
},
  "geometry": {"coordinates":[9.968378067,57.5807876587],"type":"Point"}
}