{
  "type": "Feature",
  "properties": {
    "addr:full":"\u00d8stergade 21 A Vorbasse Danmark 6623",
    "addr:housenumber":"21 a",
    "addr:postcode":"6623",
    "addr:street":"Ostergade",
    "iso:country":"DK",
    "sg:address":"\u00d8stergade 21 A",
    "sg:city":"Vorbasse",
    "sg:orig_category":"Autoreparation og -service",
    "sg:phone":"+45 75 33 38 40",
    "sg:postcode":"6623",
    "sg:province":"Danmark",
    "wof:name":"Autocentralen",
    "wof:placetype":"venue"
},
  "geometry": {"coordinates":[9.0848665237,55.6295661926],"type":"Point"}
}