{
  "type": "Feature",
  "properties": {
    "addr:full":"Industrivej 73 Bramming Danmark 6740",
    "addr:housenumber":"73",
    "addr:postcode":"6740",
    "addr:street":"Industrivej",
    "iso:country":"DK",
    "sg:address":"Industrivej 73",
    "sg:city":"Bramming",
    "sg:orig_category":"Inventar",
    "sg:phone":"+45 75 17 25 22",
    "sg:postcode":"6740",
    "sg:province":"Danmark",
    "wof:name":"Jens B\u00f8geskov ApS",
    "wof:placetype":"venue"
},
  "geometry": {"coordinates":[8.6681489944,55.4686393738],"type":"Point"}
}