{
  "type": "Feature",
  "properties": {
    "addr:full":"Torvet 4 Ringsted Danmark 4100",
    "addr:housenumber":"4",
    "addr:postcode":"4100",
    "addr:street":"Torvet",
    "iso:country":"DK",
    "sg:address":"Torvet 4",
    "sg:city":"Ringsted",
    "sg:orig_category":"Ejendomshandel",
    "sg:phone":"+45 57 67 46 00",
    "sg:postcode":"4100",
    "sg:province":"Danmark",
    "sg:website":"www.home.dk",
    "wof:name":"S\u00f8ren Bak",
    "wof:placetype":"venue"
},
  "geometry": {"coordinates":[11.7887220383,55.4453849792],"type":"Point"}
}