{
  "type": "Feature",
  "properties": {
    "addr:full":"Bredgade 6 Thybor\u00f8n Danmark 7680",
    "addr:housenumber":"6",
    "addr:postcode":"7680",
    "addr:street":"Bredgade",
    "iso:country":"DK",
    "sg:address":"Bredgade 6",
    "sg:city":"Thybor\u00f8n",
    "sg:orig_category":"Apoteker og -udsalg",
    "sg:phone":"+45 97 83 10 24",
    "sg:postcode":"7680",
    "sg:province":"Danmark",
    "wof:name":"Thybor\u00f8n Apoteksudsalg",
    "wof:placetype":"venue"
},
  "geometry": {"coordinates":[-76.5446014404,38.7092857361],"type":"Point"}
}