{
  "type": "Feature",
  "properties": {
    "addr:full":"Vesterr\u00f8n 22 Svendborg Danmark 5700",
    "addr:housenumber":"22",
    "addr:postcode":"5700",
    "addr:street":"Vesterron",
    "iso:country":"DK",
    "sg:address":"Vesterr\u00f8n 22",
    "sg:city":"Svendborg",
    "sg:orig_category":"Psykoterapi",
    "sg:phone":"+45 62 20 88 28",
    "sg:postcode":"5700",
    "sg:province":"Danmark",
    "wof:name":"Skov, Lene Brund",
    "wof:placetype":"venue"
},
  "geometry": {"coordinates":[10.6040811539,55.0596923828],"type":"Point"}
}