{
  "type": "Feature",
  "properties": {
    "iso:country":"DK",
    "sg:address":"S\u00f8ndergade 5, Hvidbjerg",
    "sg:city":"Thyholm",
    "sg:orig_category":"Genbrugsbutikker",
    "sg:phone":"+45 97 87 11 33",
    "sg:postcode":"7790",
    "sg:province":"Danmark",
    "wof:name":"Genbrugsbutikken",
    "wof:placetype":"venue"
},
  "geometry": {"coordinates":[8.525765419,56.6507072449],"type":"Point"}
}