{
  "type": "Feature",
  "properties": {
    "addr:full":"Troldemosevej 38, Kors\u00f8 Aalestrup Danmark 9620",
    "addr:housenumber":"38",
    "addr:postcode":"9620",
    "addr:street":"Troldemosevej",
    "iso:country":"DK",
    "sg:address":"Troldemosevej 38, Kors\u00f8",
    "sg:city":"Aalestrup",
    "sg:orig_category":"Stoffer",
    "sg:phone":"+45 98 64 81 21",
    "sg:postcode":"9620",
    "sg:province":"Danmark",
    "wof:name":"Marlis Stofbutik",
    "wof:placetype":"venue"
},
  "geometry": {"coordinates":[9.4901504517,56.6938285828],"type":"Point"}
}