{
  "type": "Feature",
  "properties": {
    "addr:full":"Jernbanegade 1 Viborg Danmark 8800",
    "addr:housenumber":"1",
    "addr:postcode":"8800",
    "addr:street":"Jernbanegade",
    "iso:country":"DK",
    "sg:address":"Jernbanegade 1",
    "sg:city":"Viborg",
    "sg:orig_category":"Akupunktur",
    "sg:phone":"+45 86 60 09 89",
    "sg:postcode":"8800",
    "sg:province":"Danmark",
    "sg:website":"www.kropoghelse.dk",
    "wof:name":"Krop & Helse",
    "wof:placetype":"venue"
},
  "geometry": {"coordinates":[9.3993854523,56.4481048584],"type":"Point"}
}