{
  "type": "Feature",
  "properties": {
    "addr:full":"Kobjergvej 3 Billund Danmark 7190",
    "addr:housenumber":"3",
    "addr:postcode":"7190",
    "addr:street":"Kobjergvej",
    "iso:country":"DK",
    "sg:address":"Kobjergvej 3",
    "sg:city":"Billund",
    "sg:orig_category":"Cykler",
    "sg:phone":"+45 75 35 39 03",
    "sg:postcode":"7190",
    "sg:province":"Danmark",
    "wof:name":"Pekuka I/S",
    "wof:placetype":"venue"
},
  "geometry": {"coordinates":[9.0926914215,55.7561798096],"type":"Point"}
}