{
  "type": "Feature",
  "properties": {
    "addr:full":"Sct. Mathias Gade 78 Viborg Danmark 8800",
    "addr:housenumber":"78",
    "addr:postcode":"8800",
    "addr:street":"Sct. Mathias Gade",
    "iso:country":"DK",
    "sg:address":"Sct. Mathias Gade 78",
    "sg:city":"Viborg",
    "sg:classifiers":[
        {
            "category":"Restaurant",
            "type":"Food & Drink"
        }
    ],
    "sg:phone":"+45 86 62 08 81",
    "sg:postcode":"8800",
    "sg:province":"Danmark",
    "wof:name":"Latinerly",
    "wof:placetype":"venue"
},
  "geometry": {"coordinates":[9.4107370377,56.4499397278],"type":"Point"}
}