{
  "type": "Feature",
  "properties": {
    "iso:country":"DK",
    "sg:address":"Godsbanegade 20, 2.",
    "sg:city":"Br\u00f8nderslev",
    "sg:orig_category":"INGENI\u00c3\u02dcRER",
    "sg:phone":"+45 98 80 12 80",
    "sg:postcode":"9700",
    "sg:province":"Danmark",
    "sg:website":"www.teko-aps.dk",
    "wof:name":"Teko - Maskinteknisk Tegne- og Konsulentbistand",
    "wof:placetype":"venue"
},
  "geometry": {"coordinates":[9.9428195953,57.2719917297],"type":"Point"}
}