{
  "type": "Feature",
  "properties": {
    "iso:country":"DK",
    "sg:address":"Hospitalsgade 7",
    "sg:city":"Give",
    "sg:orig_category":"\u00c3\u2020ldrecentre",
    "sg:phone":"+45 75 73 12 70",
    "sg:postcode":"7323",
    "sg:province":"Danmark",
    "wof:name":"Distrikt Solh\u00f8j - \u00c6ldrecenter Solh\u00f8j",
    "wof:placetype":"venue"
},
  "geometry": {"coordinates":[9.241651535,55.8463973999],"type":"Point"}
}