{
  "type": "Feature",
  "properties": {
    "addr:full":"Steng\u00e5rds Plads 2 \u00d8lstykke Danmark 3650",
    "addr:housenumber":"2",
    "addr:postcode":"3650",
    "addr:street":"Stengaards Plads",
    "iso:country":"DK",
    "sg:address":"Steng\u00e5rds Plads 2",
    "sg:city":"\u00d8lstykke",
    "sg:orig_category":"Tandklinikker, Kommunale",
    "sg:phone":"+45 47 17 93 27",
    "sg:postcode":"3650",
    "sg:province":"Danmark",
    "wof:name":"Steng\u00e5rdsskolens Tandklinik",
    "wof:placetype":"venue"
},
  "geometry": {"coordinates":[-68.9096984863,-37.3805999756],"type":"Point"}
}