{
  "type": "Feature",
  "properties": {
    "addr:full":"Gudmevej 4 Hesselager Danmark 5874",
    "addr:housenumber":"4",
    "addr:postcode":"5874",
    "addr:street":"Gudmevej",
    "iso:country":"DK",
    "sg:address":"Gudmevej 4",
    "sg:city":"Hesselager",
    "sg:orig_category":"Tagrenovering",
    "sg:phone":"+45 62 25 22 17",
    "sg:postcode":"5874",
    "sg:province":"Danmark",
    "sg:website":"www.ht-hesselager.dk",
    "wof:name":"Hesselager T\u00f8mrerforretning ApS",
    "wof:placetype":"venue"
},
  "geometry": {"coordinates":[10.7334756851,55.1686286926],"type":"Point"}
}