{
  "type": "Feature",
  "properties": {
    "addr:full":"Storegade 64 Varde Danmark 6800",
    "addr:housenumber":"64",
    "addr:postcode":"6800",
    "addr:street":"Storegade",
    "iso:country":"DK",
    "sg:address":"Storegade 64",
    "sg:city":"Varde",
    "sg:orig_category":"Kirkelige foreninger",
    "sg:phone":"+45 75 22 39 03",
    "sg:postcode":"6800",
    "sg:province":"Danmark",
    "wof:name":"KFUM og KFUK",
    "wof:placetype":"venue"
},
  "geometry": {"coordinates":[8.4817171097,55.6236000061],"type":"Point"}
}