{
  "type": "Feature",
  "properties": {
    "iso:country":"DK",
    "sg:address":"Baneg\u00e5rdsgade 8",
    "sg:city":"Odder",
    "sg:classifiers":[
        {
            "category":"Banks & Credit Unions",
            "subcategory":"Bank",
            "type":"Services"
        }
    ],
    "sg:phone":"+45 87 80 30 70",
    "sg:postcode":"8300",
    "sg:province":"Danmark",
    "sg:tags":[
        "banker"
    ],
    "sg:website":"www.danskebank.dk",
    "wof:name":"Danske Bank",
    "wof:placetype":"venue"
},
  "geometry": {"coordinates":[10.149393,55.972031],"type":"Point"}
}