{
  "type": "Feature",
  "properties": {
    "addr:full":"N\u00f8rrebrogade 59 Esbjerg Danmark 6700",
    "addr:housenumber":"59",
    "addr:postcode":"6700",
    "addr:street":"Norrebrogade",
    "iso:country":"DK",
    "sg:address":"N\u00f8rrebrogade 59",
    "sg:city":"Esbjerg",
    "sg:orig_category":"Fiskeeksport",
    "sg:phone":"+45 75 13 63 88",
    "sg:postcode":"6700",
    "sg:province":"Danmark",
    "wof:name":"Esbjerg Muslinge Kompagni ApS",
    "wof:placetype":"venue"
},
  "geometry": {"coordinates":[8.4611244202,55.4783401489],"type":"Point"}
}