{
  "type": "Feature",
  "properties": {
    "addr:full":"Tiendeladen 7 Aalborg Danmark 9000",
    "addr:housenumber":"7",
    "addr:postcode":"9000",
    "addr:street":"Tiendeladen",
    "iso:country":"DK",
    "sg:address":"Tiendeladen 7",
    "sg:city":"Aalborg",
    "sg:orig_category":"Advokater",
    "sg:phone":"+45 98 10 20 15",
    "sg:postcode":"9000",
    "sg:province":"Danmark",
    "wof:name":"Staal, Leif",
    "wof:placetype":"venue"
},
  "geometry": {"coordinates":[9.9162902832,57.0493545532],"type":"Point"}
}