{
  "type": "Feature",
  "properties": {
    "addr:full":"Selsmosestr\u00e6de 2 Taastrup Danmark 2630",
    "addr:housenumber":"2",
    "addr:postcode":"2630",
    "addr:street":"Selsmosestraede",
    "iso:country":"DK",
    "sg:address":"Selsmosestr\u00e6de 2",
    "sg:city":"Taastrup",
    "sg:orig_category":"Ungdomsboliger og -hybler",
    "sg:postcode":"2630",
    "sg:province":"Danmark",
    "wof:name":"H\u00f8je-Taastrup Ungdomsboliger, Den Selvejende Institution",
    "wof:placetype":"venue"
},
  "geometry": {"coordinates":[12.2961206436,55.6556129456],"type":"Point"}
}