{
  "type": "Feature",
  "properties": {
    "addr:full":"Baungaardsvej 1 B Vejen Danmark 6600",
    "addr:housenumber":"1 b",
    "addr:postcode":"6600",
    "addr:street":"Baungaardsvej",
    "iso:country":"DK",
    "sg:address":"Baungaardsvej 1 B",
    "sg:city":"Vejen",
    "sg:orig_category":"Faglige organisationer og foreninger",
    "sg:phone":"+45 75 36 06 66",
    "sg:postcode":"6600",
    "sg:province":"Danmark",
    "sg:website":"www.tib.dk",
    "wof:name":"Forbundet Tr\u00e6-Industri-Byg",
    "wof:placetype":"venue"
},
  "geometry": {"coordinates":[9.1396684647,55.4832229614],"type":"Point"}
}