{
  "type": "Feature",
  "properties": {
    "addr:full":"Himmerlandsgade 8 Aars Danmark 9600",
    "addr:housenumber":"8",
    "addr:postcode":"9600",
    "addr:street":"Himmerlandsgade",
    "iso:country":"DK",
    "sg:address":"Himmerlandsgade 8",
    "sg:city":"Aars",
    "sg:orig_category":"Malermestre",
    "sg:phone":"+45 98 62 16 26",
    "sg:postcode":"9600",
    "sg:province":"Danmark",
    "wof:name":"Laursen, Benny Thinggaard",
    "wof:placetype":"venue"
},
  "geometry": {"coordinates":[9.5272464752,56.8024635315],"type":"Point"}
}