{
  "type": "Feature",
  "properties": {
    "addr:full":"Assensvej 446 Millinge Danmark 5642",
    "addr:housenumber":"446",
    "addr:postcode":"5642",
    "addr:street":"Assensvej",
    "iso:country":"DK",
    "sg:address":"Assensvej 446",
    "sg:city":"Millinge",
    "sg:orig_category":"Plejecentre",
    "sg:phone":"+45 62 68 12 08",
    "sg:postcode":"5642",
    "sg:province":"Danmark",
    "wof:name":"Steensvang \u00c6ldrecenter",
    "wof:placetype":"venue"
},
  "geometry": {"coordinates":[10.1568307877,55.1456604004],"type":"Point"}
}