{
  "type": "Feature",
  "properties": {
    "addr:full":"Carl Bernhards Vej 26 Odense M Danmark 5230",
    "addr:housenumber":"26",
    "addr:postcode":"5230",
    "addr:street":"Carl Bernhards Vej",
    "iso:country":"DK",
    "sg:address":"Carl Bernhards Vej 26",
    "sg:city":"Odense M",
    "sg:orig_category":"Reklame",
    "sg:phone":"+45 66 12 80 42",
    "sg:postcode":"5230",
    "sg:province":"Danmark",
    "wof:name":"Sky Vision Fyns Flyvecenter",
    "wof:placetype":"venue"
},
  "geometry": {"coordinates":[10.3924455643,55.377571106],"type":"Point"}
}