{
  "type": "Feature",
  "properties": {
    "iso:country":"DK",
    "sg:address":"Birkedalsvej 2, \u00c5leb\u00e6k",
    "sg:city":"Borre",
    "sg:orig_category":"\u00c3\u02dckologiske produkter",
    "sg:phone":"+45 55 81 21 02",
    "sg:postcode":"4791",
    "sg:province":"Danmark",
    "wof:name":"Danas Have",
    "wof:placetype":"venue"
},
  "geometry": {"coordinates":[12.4392347336,54.9952545166],"type":"Point"}
}