{
  "type": "Feature",
  "properties": {
    "iso:country":"DK",
    "sg:address":"Storegade 31",
    "sg:city":"Aabenraa",
    "sg:classifiers":[
        {
            "category":"Banks & Credit Unions",
            "subcategory":"Bank",
            "type":"Services"
        }
    ],
    "sg:phone":"+45 74 62 15 00",
    "sg:postcode":"6200",
    "sg:province":"Danmark",
    "sg:tags":[
        "banker"
    ],
    "sg:website":"www.unibank.dk",
    "wof:name":"Nordea",
    "wof:placetype":"venue"
},
  "geometry": {"coordinates":[9.418879,55.043129],"type":"Point"}
}