{
  "type": "Feature",
  "properties": {
    "addr:full":"Sankt J\u00f8rgens Gade 3 Aalborg Danmark 9000",
    "addr:housenumber":"3",
    "addr:postcode":"9000",
    "addr:street":"Jorgens Gade",
    "iso:country":"DK",
    "sg:address":"Sankt J\u00f8rgens Gade 3",
    "sg:city":"Aalborg",
    "sg:orig_category":"Plejehjemsboliger",
    "sg:phone":"+45 98 12 54 89",
    "sg:postcode":"9000",
    "sg:province":"Danmark",
    "wof:name":"Sct. J\u00f8rgens Stiftelse",
    "wof:placetype":"venue"
},
  "geometry": {"coordinates":[9.9120473862,57.047000885],"type":"Point"}
}