{
  "type": "Feature",
  "properties": {
    "addr:full":"Vester Voldgade 91, st. K\u00f8benhavn Danmark 1552",
    "addr:housenumber":"91;1552",
    "addr:street":"Vester Voldgade",
    "iso:country":"DK",
    "sg:address":"Vester Voldgade 91, st.",
    "sg:city":"K\u00f8benhavn",
    "sg:orig_category":"Kulturelle organisationer og -foreninger",
    "sg:phone":"+45 33 11 13 91",
    "sg:postcode":"1552",
    "sg:province":"Danmark",
    "sg:website":"www.ksbf.dk",
    "wof:name":"Skolebiblioteksforening, Kommunernes",
    "wof:placetype":"venue"
},
  "geometry": {"coordinates":[12.570400238,55.6759986877],"type":"Point"}
}