{
  "type": "Feature",
  "properties": {
    "addr:full":"Frederikssundsvej 181 A Br\u00f8nsh\u00f8j Danmark 2700",
    "addr:housenumber":"181 a",
    "addr:postcode":"2700",
    "addr:street":"Frederikssundsvej",
    "iso:country":"DK",
    "sg:address":"Frederikssundsvej 181 A",
    "sg:city":"Br\u00f8nsh\u00f8j",
    "sg:orig_category":"Cykler",
    "sg:phone":"+45 38 28 06 34",
    "sg:postcode":"2700",
    "sg:province":"Danmark",
    "wof:name":"M.C.Cykler",
    "wof:placetype":"venue"
},
  "geometry": {"coordinates":[-65.6866531372,-23.1981296539],"type":"Point"}
}