{
  "type": "Feature",
  "properties": {
    "addr:full":"Tilst Skolevej 38 Tilst Danmark 8381",
    "addr:housenumber":"38",
    "addr:postcode":"8381",
    "addr:street":"Tilst Skolevej",
    "iso:country":"DK",
    "sg:address":"Tilst Skolevej 38",
    "sg:city":"Tilst",
    "sg:orig_category":"Autoreparation og -service",
    "sg:phone":"+45 86 24 12 44",
    "sg:postcode":"8381",
    "sg:province":"Danmark",
    "sg:website":"www.riisgaard-biler.dk",
    "wof:name":"Riisgaard Automobiler ApS, Brdr.",
    "wof:placetype":"venue"
},
  "geometry": {"coordinates":[10.103263855,56.1846008301],"type":"Point"}
}