{
  "type": "Feature",
  "properties": {
    "addr:full":"Lindevej 8, Dalum Odense SV Danmark 5250",
    "addr:housenumber":"8",
    "addr:postcode":"5250",
    "addr:street":"Lindevej;Dalum",
    "iso:country":"DK",
    "sg:address":"Lindevej 8, Dalum",
    "sg:city":"Odense SV",
    "sg:classifiers":[
        {
            "category":"Professional",
            "subcategory":"Computer Services",
            "type":"Services"
        }
    ],
    "sg:phone":"+45 66 14 63 17",
    "sg:postcode":"5250",
    "sg:province":"Danmark",
    "sg:tags":[
        "edb",
        "-",
        "software"
    ],
    "wof:name":"HBJ - Consult",
    "wof:placetype":"venue"
},
  "geometry": {"coordinates":[10.3153953552,55.3362998962],"type":"Point"}
}