{
  "type": "Feature",
  "properties": {
    "addr:full":"Langelinie 91 Odense M Danmark 5230",
    "addr:housenumber":"91",
    "addr:postcode":"5230",
    "addr:street":"Langelinie",
    "iso:country":"DK",
    "sg:address":"Langelinie 91",
    "sg:city":"Odense M",
    "sg:orig_category":"Finansiering",
    "sg:phone":"+45 65 91 65 35",
    "sg:postcode":"5230",
    "sg:province":"Danmark",
    "wof:name":"Ejlersen A/S, E Jul",
    "wof:placetype":"venue"
},
  "geometry": {"coordinates":[10.3766679764,55.3801994324],"type":"Point"}
}