{
  "type": "Feature",
  "properties": {
    "addr:full":"Fmd.: Frands A. Breindal Andersen, Varn\u00e6svej 759, Bovrup Aabenraa Danmark 6200",
    "addr:housenumber":"759",
    "addr:postcode":"6200",
    "addr:street":"Varnaesvej;Bovrup",
    "iso:country":"DK",
    "sg:address":"Fmd.: Frands A. Breindal Andersen, Varn\u00e6svej 759, Bovrup",
    "sg:city":"Aabenraa",
    "sg:orig_category":"Borger- og beboerforeninger",
    "sg:phone":"+45 74 68 00 80",
    "sg:postcode":"6200",
    "sg:province":"Danmark",
    "wof:name":"Bovrup Borgerforening",
    "wof:placetype":"venue"
},
  "geometry": {"coordinates":[9.4213867188,55.0449562073],"type":"Point"}
}