{
  "type": "Feature",
  "properties": {
    "addr:full":"Strandgade 6 K\u00f8benhavn Danmark 1401",
    "addr:housenumber":"6;1401",
    "addr:street":"Strandgade",
    "iso:country":"DK",
    "sg:address":"Strandgade 6",
    "sg:city":"K\u00f8benhavn",
    "sg:orig_category":"Faglige organisationer og -foreninger",
    "sg:phone":"+45 32 95 51 00",
    "sg:postcode":"1401",
    "sg:province":"Danmark",
    "sg:website":"www.danskforfatterforening.dk",
    "wof:name":"Forfatterforening, Dansk",
    "wof:placetype":"venue"
},
  "geometry": {"coordinates":[12.5947999954,55.6744003296],"type":"Point"}
}