{
  "type": "Feature",
  "properties": {
    "addr:full":"Fmd.: Chr. Lorentzen, Bregnevej 13 Nakskov Danmark 4900",
    "addr:housenumber":"13",
    "addr:postcode":"4900",
    "addr:street":"Chr.;Bregnevej",
    "iso:country":"DK",
    "sg:address":"Fmd.: Chr. Lorentzen, Bregnevej 13",
    "sg:city":"Nakskov",
    "sg:orig_category":"Grundejerforeninger",
    "sg:phone":"+45 54 92 65 82",
    "sg:postcode":"4900",
    "sg:province":"Danmark",
    "wof:name":"St\u00f8dby Strands Grundejerforening",
    "wof:placetype":"venue"
},
  "geometry": {"coordinates":[11.1359500885,54.8330116272],"type":"Point"}
}