{
  "type": "Feature",
  "properties": {
    "iso:country":"DK",
    "sg:address":"Haverslevvej 78, Aarestrup",
    "sg:city":"Sk\u00f8rping",
    "sg:orig_category":"Bogtrykkerier",
    "sg:phone":"+45 98 37 51 71",
    "sg:postcode":"9520",
    "sg:province":"Danmark",
    "wof:name":"\u00c5restrup Bogtrykkeri",
    "wof:placetype":"venue"
},
  "geometry": {"coordinates":[9.8477077484,56.8337860107],"type":"Point"}
}