{
  "type": "Feature",
  "properties": {
    "addr:full":"Vester\u00e5 14, 2 Aalborg Danmark 9000",
    "addr:housenumber":"14 2",
    "addr:postcode":"9000",
    "addr:street":"Vesteraa",
    "iso:country":"DK",
    "sg:address":"Vester\u00e5 14, 2",
    "sg:city":"Aalborg",
    "sg:orig_category":"Reklamebureauer",
    "sg:phone":"+45 98 12 12 42",
    "sg:postcode":"9000",
    "sg:province":"Danmark",
    "sg:website":"www.of.dk",
    "wof:name":"Okkel + Fedder A/S, Reklamebureauet",
    "wof:placetype":"venue"
},
  "geometry": {"coordinates":[9.9183568954,57.0503044128],"type":"Point"}
}