{
  "type": "Feature",
  "properties": {
    "addr:full":"Farvervej 23 B Viborg Danmark 8800",
    "addr:housenumber":"23 b",
    "addr:postcode":"8800",
    "addr:street":"Farvervej",
    "iso:country":"DK",
    "sg:address":"Farvervej 23 B",
    "sg:city":"Viborg",
    "sg:orig_category":"Foder",
    "sg:phone":"+45 87 25 44 50",
    "sg:postcode":"8800",
    "sg:province":"Danmark",
    "sg:website":"www.miljoefoder.dk",
    "wof:name":"Milj\u00f8foder",
    "wof:placetype":"venue"
},
  "geometry": {"coordinates":[9.3962135315,56.4662513733],"type":"Point"}
}