{
  "type": "Feature",
  "properties": {
    "iso:country":"DK",
    "sg:address":"Enghavevej 11, Lov",
    "sg:city":"N\u00e6stved",
    "sg:classifiers":[
        {
            "category":"Home & Garden",
            "subcategory":"Home Furnishings",
            "type":"Retail Goods"
        }
    ],
    "sg:phone":"+45 55 76 01 76",
    "sg:postcode":"4700",
    "sg:province":"Danmark",
    "sg:tags":[
        "gardiner"
    ],
    "wof:name":"Jack's Boligmontering",
    "wof:placetype":"venue"
},
  "geometry": {"coordinates":[11.7542486191,55.2315444946],"type":"Point"}
}