{
  "type": "Feature",
  "properties": {
    "addr:full":"Fyrremarksvej 5 B Risskov Danmark 8240",
    "addr:housenumber":"5 b",
    "addr:postcode":"8240",
    "addr:street":"Fyrremarksvej",
    "iso:country":"DK",
    "sg:address":"Fyrremarksvej 5 B",
    "sg:city":"Risskov",
    "sg:orig_category":"Psykologer, praktiserende",
    "sg:phone":"+45 86 17 50 25",
    "sg:postcode":"8240",
    "sg:province":"Danmark",
    "wof:name":"Langagergaard, Agnete",
    "wof:placetype":"venue"
},
  "geometry": {"coordinates":[10.2589387894,56.1976470947],"type":"Point"}
}