{
  "type": "Feature",
  "properties": {
    "addr:full":"K\u00e5strup Holmevej 9 Kalundborg Danmark 4400",
    "addr:housenumber":"9",
    "addr:postcode":"4400",
    "addr:street":"Holmevej",
    "iso:country":"DK",
    "sg:address":"K\u00e5strup Holmevej 9",
    "sg:city":"Kalundborg",
    "sg:orig_category":"Slamsugning",
    "sg:phone":"+45 59 50 70 33",
    "sg:postcode":"4400",
    "sg:province":"Danmark",
    "wof:name":"K\u00e5strup Maskinstation",
    "wof:placetype":"venue"
},
  "geometry": {"coordinates":[11.1339550018,55.7015419006],"type":"Point"}
}