{
  "type": "Feature",
  "properties": {
    "addr:full":"Himmerlandsgade 59 Aars Danmark 9600",
    "addr:housenumber":"59",
    "addr:postcode":"9600",
    "addr:street":"Himmerlandsgade",
    "iso:country":"DK",
    "sg:address":"Himmerlandsgade 59",
    "sg:city":"Aars",
    "sg:orig_category":"Ejendomshandel",
    "sg:phone":"+45 98 62 13 96",
    "sg:postcode":"9600",
    "sg:province":"Danmark",
    "wof:name":"Poulsen, Jens Laurits",
    "wof:placetype":"venue"
},
  "geometry": {"coordinates":[9.5190162659,56.8031768799],"type":"Point"}
}