{
  "type": "Feature",
  "properties": {
    "iso:country":"DK",
    "sg:address":"Hobrovej 792",
    "sg:city":"Svenstrup",
    "sg:orig_category":"Babyudstyr",
    "sg:phone":"+45 98 38 26 44",
    "sg:postcode":"9230",
    "sg:province":"Danmark",
    "sg:website":"www.babysam.dk",
    "wof:name":"BabySam Aalborg City-Svenstrup",
    "wof:placetype":"venue"
},
  "geometry": {"coordinates":[9.855048,56.968582],"type":"Point"}
}