{
  "type": "Feature",
  "properties": {
    "iso:country":"DK",
    "sg:address":"Diagonalvejen 86, Bregnhoved",
    "sg:city":"Give",
    "sg:orig_category":"Autoreparation og -service",
    "sg:phone":"+45 75 73 56 45",
    "sg:postcode":"7323",
    "sg:province":"Danmark",
    "wof:name":"Kruses Maskiner",
    "wof:placetype":"venue"
},
  "geometry": {"coordinates":[9.2362060547,55.845413208],"type":"Point"}
}