{
  "type": "Feature",
  "properties": {
    "addr:full":"M\u00f8llehaven 73 Karlslunde Danmark 2690",
    "addr:housenumber":"73",
    "addr:postcode":"2690",
    "addr:street":"Mollehaven",
    "iso:country":"DK",
    "sg:address":"M\u00f8llehaven 73",
    "sg:city":"Karlslunde",
    "sg:orig_category":"Vejledningscentre",
    "sg:phone":"+45 46 15 42 30",
    "sg:postcode":"2690",
    "sg:province":"Danmark",
    "wof:name":"Handelsfirmaet Frost",
    "wof:placetype":"venue"
},
  "geometry": {"coordinates":[12.2170982361,55.5735015869],"type":"Point"}
}