{
  "type": "Feature",
  "properties": {
    "addr:full":"Gr\u00f8nnemosevej 22 Svendborg Danmark 5700",
    "addr:housenumber":"22",
    "addr:postcode":"5700",
    "addr:street":"Gronnemosevej",
    "iso:country":"DK",
    "sg:address":"Gr\u00f8nnemosevej 22",
    "sg:city":"Svendborg",
    "sg:orig_category":"Autoforhandlere",
    "sg:phone":"+45 62 22 15 05",
    "sg:postcode":"5700",
    "sg:province":"Danmark",
    "sg:website":"www.nika.dk",
    "wof:name":"Nika - Biler A/S",
    "wof:placetype":"venue"
},
  "geometry": {"coordinates":[10.5883769989,55.0756225586],"type":"Point"}
}