{
  "type": "Feature",
  "properties": {
    "addr:full":"R\u00e5dhusholmen 10 Greve Danmark 2670",
    "addr:housenumber":"10",
    "addr:postcode":"2670",
    "addr:street":"Raadhusholmen",
    "iso:country":"DK",
    "sg:address":"R\u00e5dhusholmen 10",
    "sg:city":"Greve",
    "sg:orig_category":"Dagplejeformidling",
    "sg:phone":"+45 43 97 95 26",
    "sg:postcode":"2670",
    "sg:province":"Danmark",
    "wof:name":"Dagpleje, Den Kommunale",
    "wof:placetype":"venue"
},
  "geometry": {"coordinates":[12.2919883728,55.5827445984],"type":"Point"}
}