{
  "type": "Feature",
  "properties": {
    "addr:full":"Vr\u00f8ndingvej 88 Horsens Danmark 8700",
    "addr:housenumber":"88",
    "addr:postcode":"8700",
    "addr:street":"Vrondingvej",
    "iso:country":"DK",
    "sg:address":"Vr\u00f8ndingvej 88",
    "sg:city":"Horsens",
    "sg:orig_category":"Forsamlingshuse",
    "sg:phone":"+45 75 67 38 75",
    "sg:postcode":"8700",
    "sg:province":"Danmark",
    "wof:name":"Vr\u00f8nding Forsamlingshus",
    "wof:placetype":"venue"
},
  "geometry": {"coordinates":[9.7093381882,55.8756752014],"type":"Point"}
}