{
  "type": "Feature",
  "properties": {
    "addr:full":"N\u00f8rregade 16 Ringsted Danmark 4100",
    "addr:housenumber":"16",
    "addr:postcode":"4100",
    "addr:street":"Norregade",
    "iso:country":"DK",
    "sg:address":"N\u00f8rregade 16",
    "sg:city":"Ringsted",
    "sg:orig_category":"Skomagere",
    "sg:phone":"+45 57 61 02 49",
    "sg:postcode":"4100",
    "sg:province":"Danmark",
    "wof:name":"Ringstedskomageren",
    "wof:placetype":"venue"
},
  "geometry": {"coordinates":[11.7891778946,55.4471130371],"type":"Point"}
}