{
  "type": "Feature",
  "properties": {
    "addr:full":"Brundby Hovedgade 63 Sams\u00f8 Danmark 8305",
    "addr:housenumber":"63",
    "addr:postcode":"8305",
    "addr:street":"Brundby Hovedgade",
    "iso:country":"DK",
    "sg:address":"Brundby Hovedgade 63",
    "sg:city":"Sams\u00f8",
    "sg:orig_category":"HOTELS: OG MOTELLER",
    "sg:phone":"+45 86 59 00 11",
    "sg:postcode":"8305",
    "sg:province":"Danmark",
    "wof:name":"Brundby Hotel",
    "wof:placetype":"venue"
},
  "geometry": {"coordinates":[10.6033010483,55.8134765625],"type":"Point"}
}