{
  "type": "Feature",
  "properties": {
    "iso:country":"DK",
    "sg:address":"Dyrehavsbakken 10",
    "sg:city":"Klampenborg",
    "sg:orig_category":"Bijouterier",
    "sg:phone":"+45 39 62 51 63",
    "sg:postcode":"2930",
    "sg:province":"Danmark",
    "sg:website":"www.jouxli.com",
    "wof:name":"Jouxli",
    "wof:placetype":"venue"
},
  "geometry": {"coordinates":[12.578861,55.77486],"type":"Point"}
}