{
  "type": "Feature",
  "properties": {
    "addr:full":"Storegade 15 Tarm Danmark 6880",
    "addr:housenumber":"15",
    "addr:postcode":"6880",
    "addr:street":"Storegade",
    "iso:country":"DK",
    "sg:address":"Storegade 15",
    "sg:city":"Tarm",
    "sg:orig_category":"Sportsartikler",
    "sg:phone":"+45 97 37 13 77",
    "sg:postcode":"6880",
    "sg:province":"Danmark",
    "wof:name":"Alstrup Sport",
    "wof:placetype":"venue"
},
  "geometry": {"coordinates":[8.5215568542,55.9079208374],"type":"Point"}
}