{
  "type": "Feature",
  "properties": {
    "iso:country":"DK",
    "sg:address":"Boholtevej 85",
    "sg:city":"K\u00f8ge",
    "sg:orig_category":"Teatre",
    "sg:phone":"+45 56 65 96 86",
    "sg:postcode":"4600",
    "sg:province":"Danmark",
    "wof:name":"K\u00f8ge Scenen",
    "wof:placetype":"venue"
},
  "geometry": {"coordinates":[12.1630792618,55.4458808899],"type":"Point"}
}