{
  "type": "Feature",
  "properties": {
    "addr:full":"H\u00f8jerupvej 30  Store Heddinge Danmark 4660",
    "addr:housenumber":"30",
    "addr:postcode":"4660",
    "addr:street":"Hojerupvej",
    "iso:country":"DK",
    "sg:address":"H\u00f8jerupvej 30 ",
    "sg:city":"Store Heddinge",
    "sg:classifiers":[
        {
            "category":"Home & Garden",
            "subcategory":"Home Furnishings",
            "type":"Retail Goods"
        }
    ],
    "sg:phone":"+45 56 50 21 75",
    "sg:postcode":"4660",
    "sg:province":"Danmark",
    "sg:tags":[
        "household"
    ],
    "wof:name":"PJ FURNITURE A/S",
    "wof:placetype":"venue"
},
  "geometry": {"coordinates":[12.412733078,55.2987365723],"type":"Point"}
}