{
  "type": "Feature",
  "properties": {
    "addr:full":"Prinsensgade 35 kl. Aalborg Danmark 9000",
    "addr:housenumber":"35 kl.",
    "addr:postcode":"9000",
    "addr:street":"Prinsensgade",
    "iso:country":"DK",
    "sg:address":"Prinsensgade 35 kl.",
    "sg:city":"Aalborg",
    "sg:orig_category":"Stoffer",
    "sg:phone":"+45 98 13 98 98",
    "sg:postcode":"9000",
    "sg:province":"Danmark",
    "wof:name":"Lundbo Stof",
    "wof:placetype":"venue"
},
  "geometry": {"coordinates":[9.9162902832,57.0493545532],"type":"Point"}
}