{
  "type": "Feature",
  "properties": {
    "iso:country":"DK",
    "sg:address":"Fmd.: Lisbeth Schmidt, Erlevvej 72",
    "sg:city":"Haderslev",
    "sg:orig_category":"Kulturelle foreninger",
    "sg:phone":"+45 74 53 13 45",
    "sg:postcode":"6100",
    "sg:province":"Danmark",
    "wof:name":"Hertug Hans Brugerforening",
    "wof:placetype":"venue"
},
  "geometry": {"coordinates":[9.4879703522,55.2505493164],"type":"Point"}
}