{
  "type": "Feature",
  "properties": {
    "iso:country":"DK",
    "sg:address":"Fmd.: Hans Gydesen, Agertoften 7",
    "sg:city":"Tureby",
    "sg:orig_category":"Kirkelige foreninger",
    "sg:phone":"+45 56 28 35 38",
    "sg:postcode":"4682",
    "sg:province":"Danmark",
    "wof:name":"Sogneg\u00e5rden Algestrup",
    "wof:placetype":"venue"
},
  "geometry": {"coordinates":[12.0786523819,55.3774833679],"type":"Point"}
}