{
  "type": "Feature",
  "properties": {
    "addr:full":"J. M. Thieles Vej 6 Frederiksberg Danmark 1961",
    "addr:housenumber":"6;1961",
    "addr:street":"J. M. Thieles Vej",
    "iso:country":"DK",
    "sg:address":"J. M. Thieles Vej 6",
    "sg:city":"Frederiksberg",
    "sg:orig_category":"Psykologer, praktiserende",
    "sg:phone":"+45 35 35 06 90",
    "sg:postcode":"1961",
    "sg:province":"Danmark",
    "wof:name":"Busck, Ingrid",
    "wof:placetype":"venue"
},
  "geometry": {"coordinates":[12.5472078323,55.6812515259],"type":"Point"}
}