{
  "type": "Feature",
  "properties": {
    "iso:country":"DK",
    "sg:address":"Skotterupgade 16",
    "sg:city":"K\u00f8benhavn N",
    "sg:orig_category":"Glarmestre og glarmagere",
    "sg:phone":"+45 38 19 01 44",
    "sg:postcode":"2200",
    "sg:province":"Danmark",
    "wof:name":"B.M. & S\u00f8nner",
    "wof:placetype":"venue"
},
  "geometry": {"coordinates":[-94.2525939941,47.9151039124],"type":"Point"}
}