{
  "type": "Feature",
  "properties": {
    "addr:full":"Fmd.: Georg Henriksen, Skovbrynet 5, Pindstrup Ryomg\u00e5rd Danmark 8550",
    "addr:housenumber":"5",
    "addr:postcode":"8550",
    "addr:street":"Skovbrynet",
    "iso:country":"DK",
    "sg:address":"Fmd.: Georg Henriksen, Skovbrynet 5, Pindstrup",
    "sg:city":"Ryomg\u00e5rd",
    "sg:orig_category":"\u00c3\u2020ldreorganisationer og klubber",
    "sg:phone":"+45 86 39 67 70",
    "sg:postcode":"8550",
    "sg:province":"Danmark",
    "wof:name":"Pindstrup Og Omegns Pensionistforening",
    "wof:placetype":"venue"
},
  "geometry": {"coordinates":[10.5041999817,56.3809814453],"type":"Point"}
}