{
  "type": "Feature",
  "properties": {
    "addr:full":"Christian X's Vej 1 - 3 Haderslev Danmark 6100",
    "addr:housenumber":"1 3",
    "addr:postcode":"6100",
    "addr:street":"Christian X'S Vej",
    "iso:country":"DK",
    "sg:address":"Christian X's Vej 1 - 3",
    "sg:city":"Haderslev",
    "sg:orig_category":"Autoreparation og -service",
    "sg:phone":"+45 74 52 55 10",
    "sg:postcode":"6100",
    "sg:province":"Danmark",
    "wof:name":"Platz A/S, Brdr.",
    "wof:placetype":"venue"
},
  "geometry": {"coordinates":[9.5053548813,55.2536125183],"type":"Point"}
}