{
  "type": "Feature",
  "properties": {
    "addr:full":"Storegade 49 Hasle Danmark 3790",
    "addr:housenumber":"49",
    "addr:postcode":"3790",
    "addr:street":"Storegade",
    "iso:country":"DK",
    "sg:address":"Storegade 49",
    "sg:city":"Hasle",
    "sg:orig_category":"Sko",
    "sg:phone":"+45 56 96 40 57",
    "sg:postcode":"3790",
    "sg:province":"Danmark",
    "wof:name":"City Sko",
    "wof:placetype":"venue"
},
  "geometry": {"coordinates":[14.7058420181,55.1835136414],"type":"Point"}
}