{
  "type": "Feature",
  "properties": {
    "addr:full":"Sognepr\u00e6st: Iver Viftrup (K/B), Kongelysvej 11 Vestbjerg Danmark 9380",
    "addr:housenumber":"k / b;11",
    "addr:postcode":"9380",
    "addr:street":"Sognepraest Iver Viftrup;Kongelysvej",
    "iso:country":"DK",
    "sg:address":"Sognepr\u00e6st: Iver Viftrup (K/B), Kongelysvej 11",
    "sg:city":"Vestbjerg",
    "sg:orig_category":"Kirkesogne",
    "sg:phone":"+45 98 29 70 74",
    "sg:postcode":"9380",
    "sg:province":"Danmark",
    "wof:name":"Sulsted Sogn",
    "wof:placetype":"venue"
},
  "geometry": {"coordinates":[9.9697885513,57.1300506592],"type":"Point"}
}