{
  "type": "Feature",
  "properties": {
    "addr:full":"v/ Hans S\u00f8rensen, Toften 19, Voldby Grenaa Danmark 8500",
    "addr:housenumber":"19",
    "addr:postcode":"8500",
    "addr:street":"Sorensen Toften;Voldby",
    "iso:country":"DK",
    "sg:address":"v/ Hans S\u00f8rensen, Toften 19, Voldby",
    "sg:city":"Grenaa",
    "sg:orig_category":"Borger- og beboerforeninger",
    "sg:phone":"+45 86 33 26 58",
    "sg:postcode":"8500",
    "sg:province":"Danmark",
    "wof:name":"Voldby og Omegns Beboerfore. og Forsamlingshus",
    "wof:placetype":"venue"
},
  "geometry": {"coordinates":[10.8774929047,56.4126853943],"type":"Point"}
}