{
  "type": "Feature",
  "properties": {
    "addr:full":"Rahbeks Alle 19 Frederiksberg Danmark 1801",
    "addr:housenumber":"19;1801",
    "addr:street":"Rahbeks Alle",
    "iso:country":"DK",
    "sg:address":"Rahbeks Alle 19",
    "sg:city":"Frederiksberg",
    "sg:orig_category":"Sammensatte institutioner",
    "sg:phone":"+45 38 21 17 60",
    "sg:postcode":"1801",
    "sg:province":"Danmark",
    "wof:name":"Carlsvognen, Frederiksberg Kommunes B\u00f8rneinstitution",
    "wof:placetype":"venue"
},
  "geometry": {"coordinates":[12.5337867737,55.6689720154],"type":"Point"}
}