{
  "type": "Feature",
  "properties": {
    "iso:country":"DK",
    "sg:address":"(Kurt Bender Petersen), Bilds\u00f8vej 57, Kr. Stillinge",
    "sg:city":"Slagelse",
    "sg:orig_category":"Oliefyr og service",
    "sg:phone":"+45 58 54 77 22",
    "sg:postcode":"4200",
    "sg:province":"Danmark",
    "wof:name":"Kurt's Oliefyrservice",
    "wof:placetype":"venue"
},
  "geometry": {"coordinates":[11.3569850922,55.4050865173],"type":"Point"}
}