{
  "type": "Feature",
  "properties": {
    "iso:country":"DK",
    "sg:address":"Brob\u00e6ksgade 12",
    "sg:city":"Slangerup",
    "sg:classifiers":[
        {
            "category":"Banks & Credit Unions",
            "subcategory":"Bank",
            "type":"Services"
        }
    ],
    "sg:phone":"+45 47 33 40 26",
    "sg:postcode":"3550",
    "sg:province":"Danmark",
    "sg:tags":[
        "banker"
    ],
    "wof:name":"Nordea",
    "wof:placetype":"venue"
},
  "geometry": {"coordinates":[12.1721849442,55.8443145752],"type":"Point"}
}