{
  "type": "Feature",
  "properties": {
    "addr:full":"Silkeborg Kunstmuseum, Guden\u00e5vej 7 - 9 Silkeborg Danmark 8600",
    "addr:housenumber":"7 9",
    "addr:postcode":"8600",
    "addr:street":"Gudenaavej",
    "iso:country":"DK",
    "sg:address":"Silkeborg Kunstmuseum, Guden\u00e5vej 7 - 9",
    "sg:city":"Silkeborg",
    "sg:orig_category":"Museer",
    "sg:phone":"+45 86 82 53 88",
    "sg:postcode":"8600",
    "sg:province":"Danmark",
    "sg:website":"www.silkeborgkunstmuseum.dk",
    "wof:name":"Asger Jorns Samlinger",
    "wof:placetype":"venue"
},
  "geometry": {"coordinates":[9.5524425507,56.1693305969],"type":"Point"}
}