{
  "type": "Feature",
  "properties": {
    "iso:country":"DK",
    "sg:address":"Torvet 17",
    "sg:city":"K\u00f8ge",
    "sg:orig_category":"Biografer",
    "sg:phone":"+45 56 65 07 50",
    "sg:postcode":"4600",
    "sg:province":"Danmark",
    "sg:website":"www.koegebio.dk",
    "wof:name":"K\u00f8ge Bio",
    "wof:placetype":"venue"
},
  "geometry": {"coordinates":[10.69055,59.80946],"type":"Point"}
}