{
  "type": "Feature",
  "properties": {
    "addr:full":"Mejlstedvej 19 Vestbjerg Danmark 9380",
    "addr:housenumber":"19",
    "addr:postcode":"9380",
    "addr:street":"Mejlstedvej",
    "iso:country":"DK",
    "sg:address":"Mejlstedvej 19",
    "sg:city":"Vestbjerg",
    "sg:orig_category":"Ungdomsklubber",
    "sg:phone":"+45 98 29 69 88",
    "sg:postcode":"9380",
    "sg:province":"Danmark",
    "wof:name":"Vestbjerg Ungdomsklub",
    "wof:placetype":"venue"
},
  "geometry": {"coordinates":[9.9662446976,57.1276321411],"type":"Point"}
}