{
  "type": "Feature",
  "properties": {
    "iso:country":"DK",
    "sg:address":"S\u00f8parken 60, Hjallese",
    "sg:city":"Odense S",
    "sg:orig_category":"Alternativ behandling",
    "sg:phone":"+45 21 64 53 82",
    "sg:postcode":"5260",
    "sg:province":"Danmark",
    "wof:name":"Helheden, Zoneterapiklinik",
    "wof:placetype":"venue"
},
  "geometry": {"coordinates":[10.3157806396,55.3122825623],"type":"Point"}
}