{
  "type": "Feature",
  "properties": {
    "iso:country":"DK",
    "sg:address":"Str\u00f8get 67",
    "sg:city":"Ikast",
    "sg:orig_category":"Revisorer",
    "sg:phone":"+45 97 25 13 33",
    "sg:postcode":"7430",
    "sg:province":"Danmark",
    "wof:name":"Mercan Revision ApS",
    "wof:placetype":"venue"
},
  "geometry": {"coordinates":[9.1540393829,56.1443595886],"type":"Point"}
}