{
  "type": "Feature",
  "properties": {
    "addr:full":"Slotsparken 30 Bagsv\u00e6rd Danmark 2880",
    "addr:housenumber":"30",
    "addr:postcode":"2880",
    "addr:street":"Slotsparken",
    "iso:country":"DK",
    "sg:address":"Slotsparken 30",
    "sg:city":"Bagsv\u00e6rd",
    "sg:classifiers":[
        {
            "category":"Restaurant",
            "type":"Food & Drink"
        }
    ],
    "sg:phone":"+45 44 98 00 30",
    "sg:postcode":"2880",
    "sg:province":"Danmark",
    "wof:name":"Aldershvile Slotspavillon",
    "wof:placetype":"venue"
},
  "geometry": {"coordinates":[12.3929595947,55.9831085205],"type":"Point"}
}