{
  "type": "Feature",
  "properties": {
    "addr:full":"K\u00e6rlundsvej 30 Aalborg Danmark 9000",
    "addr:housenumber":"30",
    "addr:postcode":"9000",
    "addr:street":"Kaerlundsvej",
    "iso:country":"DK",
    "sg:address":"K\u00e6rlundsvej 30",
    "sg:city":"Aalborg",
    "sg:orig_category":"Reklame",
    "sg:phone":"+45 98 10 22 00",
    "sg:postcode":"9000",
    "sg:province":"Danmark",
    "wof:name":"Respons Marketing A/S",
    "wof:placetype":"venue"
},
  "geometry": {"coordinates":[9.9121847153,57.0385093689],"type":"Point"}
}