{
  "type": "Feature",
  "properties": {
    "addr:full":"Fmd.: Jes Jepsen, Vibev\u00e6nget 7 Tinglev Danmark 6360",
    "addr:housenumber":"7",
    "addr:postcode":"6360",
    "iso:country":"DK",
    "sg:address":"Fmd.: Jes Jepsen, Vibev\u00e6nget 7",
    "sg:city":"Tinglev",
    "sg:orig_category":"Kulturelle foreninger",
    "sg:phone":"+45 74 64 34 85",
    "sg:postcode":"6360",
    "sg:province":"Danmark",
    "wof:name":"Sofiedal Foredrags- og Idr\u00e6tsforening",
    "wof:placetype":"venue"
},
  "geometry": {"coordinates":[9.2476491928,54.9349365234],"type":"Point"}
}