{
  "type": "Feature",
  "properties": {
    "addr:full":"Vassinger\u00f8dvej 101 Lynge Danmark 3540",
    "addr:housenumber":"101",
    "addr:postcode":"3540",
    "addr:street":"Vassingerodvej",
    "iso:country":"DK",
    "sg:address":"Vassinger\u00f8dvej 101",
    "sg:city":"Lynge",
    "sg:orig_category":"Autoreparation og -service",
    "sg:phone":"+45 48 18 90 62",
    "sg:postcode":"3540",
    "sg:province":"Danmark",
    "wof:name":"TC Automobiler",
    "wof:placetype":"venue"
},
  "geometry": {"coordinates":[12.308514595,55.8289413452],"type":"Point"}
}