{
  "type": "Feature",
  "properties": {
    "addr:full":"Everdrupvej 20, Everdrup Tappern\u00f8je Danmark 4733",
    "addr:housenumber":"20",
    "addr:postcode":"4733",
    "addr:street":"Everdrupvej",
    "iso:country":"DK",
    "sg:address":"Everdrupvej 20, Everdrup",
    "sg:city":"Tappern\u00f8je",
    "sg:orig_category":"Forsamlingshuse",
    "sg:phone":"+45 55 56 40 55",
    "sg:postcode":"4733",
    "sg:province":"Danmark",
    "wof:name":"Everdrup Samlingshus",
    "wof:placetype":"venue"
},
  "geometry": {"coordinates":[11.9756202698,55.1781692505],"type":"Point"}
}