{
  "type": "Feature",
  "properties": {
    "addr:full":"v/\u00d8dsted Brugsen, Ribevej 31, \u00d8dsted Vejle Danmark 7100",
    "addr:housenumber":"31",
    "addr:postcode":"7100",
    "addr:street":"Ribevej",
    "iso:country":"DK",
    "sg:address":"v/\u00d8dsted Brugsen, Ribevej 31, \u00d8dsted",
    "sg:city":"Vejle",
    "sg:orig_category":"Apoteker og -udsalg",
    "sg:phone":"+45 75 86 50 11",
    "sg:postcode":"7100",
    "sg:province":"Danmark",
    "wof:name":"\u00d8dsted H\u00e5ndk\u00f8bsudsalg",
    "wof:placetype":"venue"
},
  "geometry": {"coordinates":[9.5368051529,55.7113952637],"type":"Point"}
}