{
  "type": "Feature",
  "properties": {
    "addr:full":"Assendl\u00f8sevejen 93 Viby Sj\u00e6lland Danmark 4130",
    "addr:housenumber":"93",
    "addr:postcode":"4130",
    "addr:street":"Assendlosevejen",
    "iso:country":"DK",
    "sg:address":"Assendl\u00f8sevejen 93",
    "sg:city":"Viby Sj\u00e6lland",
    "sg:orig_category":"Autoruder",
    "sg:phone":"+45 46 19 43 10",
    "sg:postcode":"4130",
    "sg:province":"Danmark",
    "wof:name":"D\u00e5strup Glas A/S",
    "wof:placetype":"venue"
},
  "geometry": {"coordinates":[12.0145998001,55.5553321838],"type":"Point"}
}