{
  "type": "Feature",
  "properties": {
    "addr:full":"Ladelundvej 25 Br\u00f8rup Danmark 6650",
    "addr:housenumber":"25",
    "addr:postcode":"6650",
    "addr:street":"Ladelundvej",
    "iso:country":"DK",
    "sg:address":"Ladelundvej 25",
    "sg:city":"Br\u00f8rup",
    "sg:orig_category":"Parykker",
    "sg:phone":"+45 75 38 19 09",
    "sg:postcode":"6650",
    "sg:province":"Danmark",
    "wof:name":"Else's Salon",
    "wof:placetype":"venue"
},
  "geometry": {"coordinates":[-93.1630935669,32.8507347107],"type":"Point"}
}