{
  "type": "Feature",
  "properties": {
    "addr:full":"v/ Evald Nielsen, Tornh\u00f8j 29, Sindbjerg Redsted Danmark 7970",
    "addr:housenumber":"29",
    "addr:postcode":"7970",
    "addr:street":"Sindbjerg Redsted Danmark",
    "iso:country":"DK",
    "sg:address":"v/ Evald Nielsen, Tornh\u00f8j 29, Sindbjerg",
    "sg:city":"Redsted",
    "sg:orig_category":"Kirkelige foreninger",
    "sg:phone":"+45 97 76 22 17",
    "sg:postcode":"7970",
    "sg:province":"Danmark",
    "wof:name":"Indre Mission, Redsted",
    "wof:placetype":"venue"
},
  "geometry": {"coordinates":[8.6130647659,56.7446250916],"type":"Point"}
}