{
  "type": "Feature",
  "properties": {
    "iso:country":"DK",
    "sg:address":"Industribakken 15, Johannesberg",
    "sg:city":"Lang\u00e5",
    "sg:orig_category":"Transportmateriel",
    "sg:phone":"+45 70 22 02 60",
    "sg:postcode":"8870",
    "sg:province":"Danmark",
    "sg:website":"www.bt-danmark.com",
    "wof:name":"BT Danmark",
    "wof:placetype":"venue"
},
  "geometry": {"coordinates":[9.8955049515,56.3900756836],"type":"Point"}
}