{
  "type": "Feature",
  "properties": {
    "addr:full":"Mosedeskolen, Lilleholm 58 Greve Danmark 2670",
    "addr:housenumber":"58",
    "addr:postcode":"2670",
    "addr:street":"Lilleholm",
    "iso:country":"DK",
    "sg:address":"Mosedeskolen, Lilleholm 58",
    "sg:city":"Greve",
    "sg:orig_category":"\u00c3\u02dcvrige foreninger",
    "sg:phone":"+45 43 90 39 98",
    "sg:postcode":"2670",
    "sg:province":"Danmark",
    "wof:name":"Foreningen af Tidl. Elever P\u00e5 Mosedeskolen",
    "wof:placetype":"venue"
},
  "geometry": {"coordinates":[12.2941808701,55.5844078064],"type":"Point"}
}