{
  "type": "Feature",
  "properties": {
    "iso:country":"DK",
    "sg:address":"Vestergade 13, st.th.",
    "sg:city":"Stubbek\u00f8bing",
    "sg:orig_category":"Teatre",
    "sg:phone":"+45 54 44 29 13",
    "sg:postcode":"4850",
    "sg:province":"Danmark",
    "wof:name":"Stubbek\u00f8bing Amat\u00f8rscene, M\u00e6lkeb\u00f8tten",
    "wof:placetype":"venue"
},
  "geometry": {"coordinates":[-114.0767440796,46.4432487488],"type":"Point"}
}