{
  "type": "Feature",
  "properties": {
    "iso:country":"DK",
    "sg:address":"Storegade 42",
    "sg:city":"Varde",
    "sg:orig_category":"Oplysningsforbund",
    "sg:phone":"+45 75 22 11 01",
    "sg:postcode":"6800",
    "sg:province":"Danmark",
    "sg:website":"www.varde.fof.mobilixnet.dk",
    "wof:name":"FOF",
    "wof:placetype":"venue"
},
  "geometry": {"coordinates":[8.4828147888,55.6222343445],"type":"Point"}
}