{
  "type": "Feature",
  "properties": {
    "addr:full":"Rosenkrantzgade 3 Thisted Danmark 7700",
    "addr:housenumber":"3",
    "addr:postcode":"7700",
    "addr:street":"Rosenkrantzgade",
    "iso:country":"DK",
    "sg:address":"Rosenkrantzgade 3",
    "sg:city":"Thisted",
    "sg:orig_category":"Supermarkeder",
    "sg:phone":"+45 97 92 64 28",
    "sg:postcode":"7700",
    "sg:province":"Danmark",
    "wof:name":"Rema 1000",
    "wof:placetype":"venue"
},
  "geometry": {"coordinates":[8.6871557236,56.9555702209],"type":"Point"}
}