{
  "type": "Feature",
  "properties": {
    "addr:full":"Maltvej 58, Askov Vejen Danmark 6600",
    "addr:housenumber":"58",
    "addr:postcode":"6600",
    "addr:street":"Maltvej",
    "iso:country":"DK",
    "sg:address":"Maltvej 58, Askov",
    "sg:city":"Vejen",
    "sg:orig_category":"Plejehjem",
    "sg:phone":"+45 75 36 09 30",
    "sg:postcode":"6600",
    "sg:province":"Danmark",
    "wof:name":"Birkely",
    "wof:placetype":"venue"
},
  "geometry": {"coordinates":[9.1396121979,55.4778175354],"type":"Point"}
}