{
  "type": "Feature",
  "properties": {
    "iso:country":"DK",
    "sg:address":"Drejergangen 1 B, 1. tv.",
    "sg:city":"Karlslunde",
    "sg:classifiers":[
        {
            "category":"Professional",
            "subcategory":"Computer Services",
            "type":"Services"
        }
    ],
    "sg:phone":"+45 46 15 44 64",
    "sg:postcode":"2690",
    "sg:province":"Danmark",
    "sg:tags":[
        "edb",
        "-",
        "software"
    ],
    "wof:name":"Dyrberg Trading I/S",
    "wof:placetype":"venue"
},
  "geometry": {"coordinates":[12.2294149399,55.5701599121],"type":"Point"}
}