{
  "type": "Feature",
  "properties": {
    "addr:full":"Algade 77 Middelfart Danmark 5500",
    "addr:housenumber":"77",
    "addr:postcode":"5500",
    "addr:street":"Algade",
    "iso:country":"DK",
    "sg:address":"Algade 77",
    "sg:city":"Middelfart",
    "sg:orig_category":"Pizzeriaer",
    "sg:phone":"+45 64 41 14 04",
    "sg:postcode":"5500",
    "sg:province":"Danmark",
    "wof:name":"Ritz Pizza",
    "wof:placetype":"venue"
},
  "geometry": {"coordinates":[9.7344617844,55.504825592],"type":"Point"}
}