{
  "type": "Feature",
  "properties": {
    "iso:country":"DK",
    "sg:address":"Gr\u00f8nnegade 3",
    "sg:city":"Pr\u00e6st\u00f8",
    "sg:orig_category":"Revisorer",
    "sg:phone":"+45 55 99 26 11",
    "sg:postcode":"4720",
    "sg:province":"Danmark",
    "wof:name":"E. J. Revision",
    "wof:placetype":"venue"
},
  "geometry": {"coordinates":[12.0418510437,55.1231994629],"type":"Point"}
}