{
  "type": "Feature",
  "properties": {
    "iso:country":"DK",
    "sg:address":"Nygade 9 - 11",
    "sg:city":"Silkeborg",
    "sg:orig_category":"Lingeri",
    "sg:phone":"+45 86 82 98 12",
    "sg:postcode":"8600",
    "sg:province":"Danmark",
    "wof:name":"Fleur",
    "wof:placetype":"venue"
},
  "geometry": {"coordinates":[9.5488986969,56.1675453186],"type":"Point"}
}