{
  "type": "Feature",
  "properties": {
    "addr:full":"Kappendrup 12 Otterup Danmark 5450",
    "addr:housenumber":"12",
    "addr:postcode":"5450",
    "addr:street":"Kappendrup",
    "iso:country":"DK",
    "sg:address":"Kappendrup 12",
    "sg:city":"Otterup",
    "sg:orig_category":"Slagter og viktualie",
    "sg:phone":"+45 64 85 11 05",
    "sg:postcode":"5450",
    "sg:province":"Danmark",
    "wof:name":"Kappendrup Slagterforretning",
    "wof:placetype":"venue"
},
  "geometry": {"coordinates":[10.3470420837,55.5385627747],"type":"Point"}
}