{
  "type": "Feature",
  "properties": {
    "addr:full":"Fmd.: Lise Hansen, K\u00e6rg\u00e5rdvej 8, Over Lerte Sommersted Danmark 6560",
    "addr:housenumber":"8",
    "addr:postcode":"6560",
    "addr:street":"Kaergaardvej;Over Lerte",
    "iso:country":"DK",
    "sg:address":"Fmd.: Lise Hansen, K\u00e6rg\u00e5rdvej 8, Over Lerte",
    "sg:city":"Sommersted",
    "sg:orig_category":"Spejderkorps",
    "sg:phone":"+45 74 50 43 49",
    "sg:postcode":"6560",
    "sg:province":"Danmark",
    "wof:name":"KFUM Sommersted",
    "wof:placetype":"venue"
},
  "geometry": {"coordinates":[9.2854347229,55.3127098083],"type":"Point"}
}