{
  "type": "Feature",
  "properties": {
    "addr:full":"Teglv\u00e6rksvej 1 A Bindslev Danmark 9881",
    "addr:housenumber":"1 a",
    "addr:postcode":"9881",
    "addr:street":"Teglvaerksvej",
    "iso:country":"DK",
    "sg:address":"Teglv\u00e6rksvej 1 A",
    "sg:city":"Bindslev",
    "sg:orig_category":"Murermestre",
    "sg:phone":"+45 98 93 86 35",
    "sg:postcode":"9881",
    "sg:province":"Danmark",
    "wof:name":"Bindslev Murerforretning",
    "wof:placetype":"venue"
},
  "geometry": {"coordinates":[10.2069530487,57.540184021],"type":"Point"}
}