{
  "type": "Feature",
  "properties": {
    "addr:full":"Solbjergvej 2 Frederiksberg Danmark 2000",
    "addr:housenumber":"2",
    "addr:postcode":"2000",
    "addr:street":"Solbjergvej",
    "iso:country":"DK",
    "sg:address":"Solbjergvej 2",
    "sg:city":"Frederiksberg",
    "sg:orig_category":"Dag- og distriktsblade",
    "sg:phone":"+45 38 11 97 00",
    "sg:postcode":"2000",
    "sg:province":"Danmark",
    "wof:name":"S\u00f8ndagsavisen/4",
    "wof:placetype":"venue"
},
  "geometry": {"coordinates":[12.5337409973,55.6811981201],"type":"Point"}
}