{
  "type": "Feature",
  "properties": {
    "addr:full":"\u00d8rhagevej 89, Klitm\u00f8ller Thisted Danmark 7700",
    "addr:housenumber":"89",
    "addr:postcode":"7700",
    "addr:street":"Orhagevej;Klitmoller",
    "iso:country":"DK",
    "sg:address":"\u00d8rhagevej 89, Klitm\u00f8ller",
    "sg:city":"Thisted",
    "sg:orig_category":"Bagere",
    "sg:phone":"+45 97 97 52 52",
    "sg:postcode":"7700",
    "sg:province":"Danmark",
    "wof:name":"Klitm\u00f8ller Bageri",
    "wof:placetype":"venue"
},
  "geometry": {"coordinates":[8.6919784546,56.9556121826],"type":"Point"}
}