{
  "type": "Feature",
  "properties": {
    "addr:full":"Industrivej 5 Langeskov Danmark 5550",
    "addr:housenumber":"5",
    "addr:postcode":"5550",
    "addr:street":"Industrivej",
    "iso:country":"DK",
    "sg:address":"Industrivej 5",
    "sg:city":"Langeskov",
    "sg:orig_category":"Autoreparation og -service",
    "sg:phone":"+45 65 38 37 36",
    "sg:postcode":"5550",
    "sg:province":"Danmark",
    "wof:name":"Sandholm Autov\u00e6rksted",
    "wof:placetype":"venue"
},
  "geometry": {"coordinates":[10.5799160004,55.3531227112],"type":"Point"}
}