{
  "type": "Feature",
  "properties": {
    "addr:full":"Willemoesvej 1 Hirtshals Danmark 9850",
    "addr:housenumber":"1",
    "addr:postcode":"9850",
    "addr:street":"Willemoesvej",
    "iso:country":"DK",
    "sg:address":"Willemoesvej 1",
    "sg:city":"Hirtshals",
    "sg:orig_category":"Museer",
    "sg:phone":"+45 98 94 48 19",
    "sg:postcode":"9850",
    "sg:province":"Danmark",
    "sg:website":"www.nordsoemuseet.dk",
    "wof:name":"Nords\u00f8museet Akvarium & Oceanarium",
    "wof:placetype":"venue"
},
  "geometry": {"coordinates":[9.9772520065,57.5864143372],"type":"Point"}
}