{
  "type": "Feature",
  "properties": {
    "addr:full":"K\u00e6rvejen 30 Uldum Danmark 7171",
    "addr:housenumber":"30",
    "addr:postcode":"7171",
    "addr:street":"Kaervejen",
    "iso:country":"DK",
    "sg:address":"K\u00e6rvejen 30",
    "sg:city":"Uldum",
    "sg:orig_category":"Skolefritidsordninger",
    "sg:phone":"+45 75 67 99 05",
    "sg:postcode":"7171",
    "sg:province":"Danmark",
    "wof:name":"Skolefritidsordningen - Uldum Skole",
    "wof:placetype":"venue"
},
  "geometry": {"coordinates":[9.5815200806,55.8521118164],"type":"Point"}
}