{
  "type": "Feature",
  "properties": {
    "addr:full":"Lykkesholms Alle 29 Frederiksberg Danmark 1902",
    "addr:housenumber":"29;1902",
    "addr:street":"Lykkesholms Alle",
    "iso:country":"DK",
    "sg:address":"Lykkesholms Alle 29",
    "sg:city":"Frederiksberg",
    "sg:orig_category":"Dykkere",
    "sg:phone":"+45 33 22 06 32",
    "sg:postcode":"1902",
    "sg:province":"Danmark",
    "sg:website":"www.scubadirect.dk",
    "wof:name":"Scuba Direct",
    "wof:placetype":"venue"
},
  "geometry": {"coordinates":[12.548781395,55.6787910461],"type":"Point"}
}