{
  "type": "Feature",
  "properties": {
    "addr:full":"Thorsvej 63 Holstebro Danmark 7500",
    "addr:housenumber":"63",
    "addr:postcode":"7500",
    "addr:street":"Thorsvej",
    "iso:country":"DK",
    "sg:address":"Thorsvej 63",
    "sg:city":"Holstebro",
    "sg:orig_category":"Daginstitution for voksne",
    "sg:phone":"+45 97 40 30 73",
    "sg:postcode":"7500",
    "sg:province":"Danmark",
    "wof:name":"Aktivitets- og Udviklingscentret",
    "wof:placetype":"venue"
},
  "geometry": {"coordinates":[8.6014299393,56.3658714294],"type":"Point"}
}