{
  "type": "Feature",
  "properties": {
    "addr:full":"Greve Strandvej 165 Greve Danmark 2670",
    "addr:housenumber":"165",
    "addr:postcode":"2670",
    "addr:street":"Greve Strandvej",
    "iso:country":"DK",
    "sg:address":"Greve Strandvej 165",
    "sg:city":"Greve",
    "sg:orig_category":"Dentallaboratorier",
    "sg:phone":"+45 43 69 11 33",
    "sg:postcode":"2670",
    "sg:province":"Danmark",
    "wof:name":"S\u00f8fort-J\u00f8rgensen ApS",
    "wof:placetype":"venue"
},
  "geometry": {"coordinates":[12.292052269,55.5735626221],"type":"Point"}
}