{
  "type": "Feature",
  "properties": {
    "addr:full":"Vestergade 7 Kjellerup Danmark 8620",
    "addr:housenumber":"7",
    "addr:postcode":"8620",
    "addr:street":"Vestergade",
    "iso:country":"DK",
    "sg:address":"Vestergade 7",
    "sg:city":"Kjellerup",
    "sg:orig_category":"Pizzeriaer",
    "sg:phone":"+45 86 88 30 80",
    "sg:postcode":"8620",
    "sg:province":"Danmark",
    "wof:name":"Pizza Turbo Express",
    "wof:placetype":"venue"
},
  "geometry": {"coordinates":[9.4292631149,56.2889518738],"type":"Point"}
}