{
  "type": "Feature",
  "properties": {
    "iso:country":"DK",
    "sg:address":"Industrivej 6",
    "sg:city":"Ribe",
    "sg:classifiers":[
        {
            "category":"Utilities",
            "subcategory":"Natural Gas",
            "type":"Services"
        }
    ],
    "sg:phone":"+45 75 42 32 88",
    "sg:postcode":"6760",
    "sg:province":"Danmark",
    "wof:name":"Special-Butikken Ribe A/S",
    "wof:placetype":"venue"
},
  "geometry": {"coordinates":[8.7750453949,55.3456420898],"type":"Point"}
}