{
  "type": "Feature",
  "properties": {
    "addr:full":"Parkvej 135 Taastrup Danmark 2630",
    "addr:housenumber":"135",
    "addr:postcode":"2630",
    "addr:street":"Parkvej",
    "iso:country":"DK",
    "sg:address":"Parkvej 135",
    "sg:city":"Taastrup",
    "sg:orig_category":"Fritidsklubber",
    "sg:phone":"+45 43 35 35 90",
    "sg:postcode":"2630",
    "sg:province":"Danmark",
    "wof:name":"Mix Fritidsklub",
    "wof:placetype":"venue"
},
  "geometry": {"coordinates":[12.3153381348,55.6524963379],"type":"Point"}
}