{
  "type": "Feature",
  "properties": {
    "addr:full":"Ruten 14 Br\u00f8nsh\u00f8j Danmark 2700",
    "addr:housenumber":"14",
    "addr:postcode":"2700",
    "addr:street":"Ruten",
    "iso:country":"DK",
    "sg:address":"Ruten 14",
    "sg:city":"Br\u00f8nsh\u00f8j",
    "sg:orig_category":"Kiosker",
    "sg:phone":"+45 38 60 70 56",
    "sg:postcode":"2700",
    "sg:province":"Danmark",
    "wof:name":"Kiosk 2000",
    "wof:placetype":"venue"
},
  "geometry": {"coordinates":[7.481180191,52.5436515808],"type":"Point"}
}