{
  "type": "Feature",
  "properties": {
    "iso:country":"DK",
    "sg:address":"Errits\u00f8 M\u00f8llebanke 36, Errits\u00f8",
    "sg:city":"Fredericia",
    "sg:classifiers":[
        {
            "category":"Food & Beverages",
            "subcategory":"Liquor & Beverages",
            "type":"Retail Goods"
        }
    ],
    "sg:phone":"+45 75 94 33 21",
    "sg:postcode":"7000",
    "sg:province":"Danmark",
    "sg:tags":[
        "vin"
    ],
    "wof:name":"Martens, Helge Huhl",
    "wof:placetype":"venue"
},
  "geometry": {"coordinates":[9.7591047287,55.566368103],"type":"Point"}
}