{
  "type": "Feature",
  "properties": {
    "addr:full":"Absalonsgade 2 Odense C Danmark 5000",
    "addr:housenumber":"2",
    "addr:postcode":"5000",
    "addr:street":"Absalonsgade",
    "iso:country":"DK",
    "sg:address":"Absalonsgade 2",
    "sg:city":"Odense C",
    "sg:classifiers":[
        {
            "category":"Restaurant",
            "type":"Food & Drink"
        }
    ],
    "sg:phone":"+45 66 14 96 85",
    "sg:postcode":"5000",
    "sg:province":"Danmark",
    "wof:name":"Ringmose, Erik",
    "wof:placetype":"venue"
},
  "geometry": {"coordinates":[10.3905792236,55.3924446106],"type":"Point"}
}