{
  "type": "Feature",
  "properties": {
    "addr:full":"v/ Lolland-Falsters Stiftsmuseum, Museumsgade 1 Maribo Danmark 4930",
    "addr:housenumber":"1",
    "addr:postcode":"4930",
    "addr:street":"Museumsgade",
    "iso:country":"DK",
    "sg:address":"v/ Lolland-Falsters Stiftsmuseum, Museumsgade 1",
    "sg:city":"Maribo",
    "sg:orig_category":"Kulturelle foreninger",
    "sg:phone":"+45 54 78 11 01",
    "sg:postcode":"4930",
    "sg:province":"Danmark",
    "wof:name":"Museumsforeningen Stiftsmuseets Venner",
    "wof:placetype":"venue"
},
  "geometry": {"coordinates":[11.502035141,54.7743835449],"type":"Point"}
}