{
  "type": "Feature",
  "properties": {
    "addr:full":"Tordenskjoldsgade 25 \u00c5rhus N Danmark 8200",
    "addr:housenumber":"25",
    "addr:postcode":"8200",
    "addr:street":"Tordenskjoldsgade",
    "iso:country":"DK",
    "sg:address":"Tordenskjoldsgade 25",
    "sg:city":"\u00c5rhus N",
    "sg:classifiers":[
        {
            "category":"Restaurant",
            "type":"Food & Drink"
        }
    ],
    "sg:phone":"+45 86 16 88 30",
    "sg:postcode":"8200",
    "sg:province":"Danmark",
    "wof:name":"Chez Tony ApS Gr\u00e6ske Specialiteter",
    "wof:placetype":"venue"
},
  "geometry": {"coordinates":[10.2158021927,56.170665741],"type":"Point"}
}