{
  "type": "Feature",
  "properties": {
    "iso:country":"DK",
    "sg:address":"v/ Gertrud Nissen, Svanevej 9, Assens",
    "sg:city":"Mariager",
    "sg:orig_category":"Boligselskaber",
    "sg:postcode":"9550",
    "sg:province":"Danmark",
    "wof:name":"Andelsboligforeningen Svanevej",
    "wof:placetype":"venue"
},
  "geometry": {"coordinates":[10.0618648529,56.676902771],"type":"Point"}
}