{
  "type": "Feature",
  "properties": {
    "iso:country":"DK",
    "sg:address":"Nyvej 18",
    "sg:city":"Gr\u00e6sted",
    "sg:orig_category":"Blikkenslagere",
    "sg:phone":"+45 48 39 21 01",
    "sg:postcode":"3230",
    "sg:province":"Danmark",
    "wof:name":"Hansen's VVS",
    "wof:placetype":"venue"
},
  "geometry": {"coordinates":[12.342648,56.0485],"type":"Point"}
}