{
  "type": "Feature",
  "properties": {
    "addr:full":"N\u00f8rregade 16 Bjerringbro Danmark 8850",
    "addr:housenumber":"16",
    "addr:postcode":"8850",
    "addr:street":"Norregade",
    "iso:country":"DK",
    "sg:address":"N\u00f8rregade 16",
    "sg:city":"Bjerringbro",
    "sg:orig_category":"Ejendomshandel",
    "sg:phone":"+45 86 68 48 44",
    "sg:postcode":"8850",
    "sg:province":"Danmark",
    "sg:website":"www.home.dk",
    "wof:name":"Home Bjerringbro",
    "wof:placetype":"venue"
},
  "geometry": {"coordinates":[9.6593112946,56.3759155273],"type":"Point"}
}