{
  "type": "Feature",
  "properties": {
    "iso:country":"DK",
    "sg:address":"Troelsvej 26, Flejsborg",
    "sg:city":"Fars\u00f8",
    "sg:orig_category":"Regnskabsassistance",
    "sg:phone":"+45 98 66 34 51",
    "sg:postcode":"9640",
    "sg:province":"Danmark",
    "wof:name":"Regnskab/EDB-assistance",
    "wof:placetype":"venue"
},
  "geometry": {"coordinates":[9.1937885284,56.6945037842],"type":"Point"}
}