{
  "type": "Feature",
  "properties": {
    "iso:country":"DK",
    "sg:address":"Akacievej 8",
    "sg:city":"Vemmelev",
    "sg:orig_category":"Integrerede institutioner",
    "sg:phone":"+45 58 36 35 00",
    "sg:postcode":"4241",
    "sg:province":"Danmark",
    "wof:name":"Akacieg\u00e5rdens B\u00f8rneinstitution",
    "wof:placetype":"venue"
},
  "geometry": {"coordinates":[11.2623262405,55.3634376526],"type":"Point"}
}