{
  "type": "Feature",
  "properties": {
    "addr:full":"S\u00f8nder Tranders Vej 39 A Aalborg S\u00d8 Danmark 9210",
    "addr:housenumber":"39 a",
    "addr:postcode":"9210",
    "addr:street":"Sonder Tranders Vej",
    "iso:country":"DK",
    "sg:address":"S\u00f8nder Tranders Vej 39 A",
    "sg:city":"Aalborg S\u00d8",
    "sg:orig_category":"Skolefritidsordninger",
    "sg:phone":"+45 98 14 66 37",
    "sg:postcode":"9210",
    "sg:province":"Danmark",
    "wof:name":"DUS Spor A-B-C - Gug Skole",
    "wof:placetype":"venue"
},
  "geometry": {"coordinates":[9.9332418442,57.0046005249],"type":"Point"}
}