{
  "type": "Feature",
  "properties": {
    "addr:full":"Borgdalsvej 15 - 17 Silkeborg Danmark 8600",
    "addr:housenumber":"15 17",
    "addr:postcode":"8600",
    "addr:street":"Borgdalsvej",
    "iso:country":"DK",
    "sg:address":"Borgdalsvej 15 - 17",
    "sg:city":"Silkeborg",
    "sg:orig_category":"Campingpladser",
    "sg:phone":"+45 86 84 63 83",
    "sg:postcode":"8600",
    "sg:province":"Danmark",
    "wof:name":"Sejs Bakker Camping",
    "wof:placetype":"venue"
},
  "geometry": {"coordinates":[9.6215839386,56.139831543],"type":"Point"}
}