{
  "type": "Feature",
  "properties": {
    "addr:full":"Edwin Rahrs Vej 28 Brabrand Danmark 8220",
    "addr:housenumber":"28",
    "addr:postcode":"8220",
    "addr:street":"Edwin Rahrs Vej",
    "iso:country":"DK",
    "sg:address":"Edwin Rahrs Vej 28",
    "sg:city":"Brabrand",
    "sg:orig_category":"Servicestationer",
    "sg:phone":"+45 86 25 27 94",
    "sg:postcode":"8220",
    "sg:province":"Danmark",
    "wof:name":"Shell",
    "wof:placetype":"venue"
},
  "geometry": {"coordinates":[10.1341161728,56.1625556946],"type":"Point"}
}