{
  "type": "Feature",
  "properties": {
    "iso:country":"DK",
    "sg:address":"H\u00f8eghsmindevej 32",
    "sg:city":"Gentofte",
    "sg:orig_category":"Ejendomshandel",
    "sg:phone":"+45 39 76 08 00",
    "sg:postcode":"2820",
    "sg:province":"Danmark",
    "wof:name":"Ramby & Partnere",
    "wof:placetype":"venue"
},
  "geometry": {"coordinates":[12.5513458252,55.7497215271],"type":"Point"}
}