{
  "type": "Feature",
  "properties": {
    "addr:full":"Glerupvej 13  R\u00f8dovre Danmark 2610",
    "addr:housenumber":"13",
    "addr:postcode":"2610",
    "addr:street":"Glerupvej",
    "iso:country":"DK",
    "sg:address":"Glerupvej 13 ",
    "sg:city":"R\u00f8dovre",
    "sg:classifiers":[
        {
            "category":"Real Estate",
            "subcategory":"Surveying",
            "type":"Services"
        }
    ],
    "sg:phone":"+45 44 94 41 25",
    "sg:postcode":"2610",
    "sg:province":"Danmark",
    "sg:tags":[
        "equipment",
        "material",
        "good",
        "-",
        "handling"
    ],
    "wof:name":"GYDE THOMSEN & CO A/S",
    "wof:placetype":"venue"
},
  "geometry": {"coordinates":[10.6992139816,61.1027755737],"type":"Point"}
}