{
  "type": "Feature",
  "properties": {
    "addr:full":"Flensborgvej 8-10 Krus\u00e5 Danmark 6340",
    "addr:housenumber":"8-10",
    "addr:postcode":"6340",
    "addr:street":"Flensborgvej",
    "iso:country":"DK",
    "sg:address":"Flensborgvej 8-10",
    "sg:city":"Krus\u00e5",
    "sg:orig_category":"Benzinstationer",
    "sg:phone":"+45 74 67 11 28",
    "sg:postcode":"6340",
    "sg:province":"Danmark",
    "wof:name":"Statoil Servicenter",
    "wof:placetype":"venue"
},
  "geometry": {"coordinates":[9.400601,54.844299],"type":"Point"}
}