{
  "type": "Feature",
  "properties": {
    "addr:full":"Vesterbro 23, Postboks 213 9100",
    "addr:housenumber":"23;213",
    "addr:postcode":"9100",
    "addr:street":"Vesterbro",
    "iso:country":"DK",
    "sg:address":"Vesterbro 23, Postboks 213",
    "sg:orig_category":"Boligselskaber",
    "sg:phone":"+45 98 12 37 44",
    "sg:postcode":"9100",
    "wof:name":"Boligselskabet \u00d8stparken",
    "wof:placetype":"venue"
},
  "geometry": {"coordinates":[9.9162597656,57.0493583679],"type":"Point"}
}