{
  "type": "Feature",
  "properties": {
    "addr:full":"Kontaktperson: Hejdi R\u00f8ygaard, Viaduktvej 13, Ring Lundby Danmark 4750",
    "addr:housenumber":"13",
    "addr:postcode":"4750",
    "addr:street":"Viaduktvej",
    "iso:country":"DK",
    "sg:address":"Kontaktperson: Hejdi R\u00f8ygaard, Viaduktvej 13, Ring",
    "sg:city":"Lundby",
    "sg:orig_category":"Legestuer",
    "sg:phone":"+45 55 76 73 21",
    "sg:postcode":"4750",
    "sg:province":"Danmark",
    "wof:name":"Lov Private Legestue",
    "wof:placetype":"venue"
},
  "geometry": {"coordinates":[11.8101682663,55.1197814941],"type":"Point"}
}