{
  "type": "Feature",
  "properties": {
    "iso:country":"DK",
    "sg:address":"Kv\u00e6rkebyvej 90",
    "sg:city":"Ringsted",
    "sg:orig_category":"Kirker",
    "sg:postcode":"4100",
    "sg:province":"Danmark",
    "wof:name":"Kv\u00e6rkeby Kirke",
    "wof:placetype":"venue"
},
  "geometry": {"coordinates":[11.8720798492,55.4528198242],"type":"Point"}
}