{
  "type": "Feature",
  "properties": {
    "addr:full":"Stationsvej 15 Holstebro Danmark 7500",
    "addr:housenumber":"15",
    "addr:postcode":"7500",
    "addr:street":"Stationsvej",
    "iso:country":"DK",
    "sg:address":"Stationsvej 15",
    "sg:city":"Holstebro",
    "sg:orig_category":"Rejsebureauer",
    "sg:phone":"+45 70 13 14 15",
    "sg:postcode":"7500",
    "sg:province":"Danmark",
    "wof:name":"DSB Rejsecenter",
    "wof:placetype":"venue"
},
  "geometry": {"coordinates":[8.62129879,56.3643226624],"type":"Point"}
}