{
  "type": "Feature",
  "properties": {
    "addr:full":"Lufthavnsvej 47, Postboks 6 Billund Danmark 7190",
    "addr:housenumber":"47;6",
    "addr:postcode":"7190",
    "addr:street":"Lufthavnsvej;Postboks",
    "iso:country":"DK",
    "sg:address":"Lufthavnsvej 47, Postboks 6",
    "sg:city":"Billund",
    "sg:orig_category":"Flyselskaber",
    "sg:phone":"+45 75 33 89 07",
    "sg:postcode":"7190",
    "sg:province":"Danmark",
    "sg:website":"www.billundaircenter.dk",
    "wof:name":"Billund Air Center",
    "wof:placetype":"venue"
},
  "geometry": {"coordinates":[9.1138372421,55.7316017151],"type":"Point"}
}