{
  "type": "Feature",
  "properties": {
    "addr:full":"Stormgade 69 Esbjerg Danmark 6700",
    "addr:housenumber":"69",
    "addr:postcode":"6700",
    "addr:street":"Stormgade",
    "iso:country":"DK",
    "sg:address":"Stormgade 69",
    "sg:city":"Esbjerg",
    "sg:orig_category":"Autoforhandlere",
    "sg:phone":"+45 75 13 52 22",
    "sg:postcode":"6700",
    "sg:province":"Danmark",
    "wof:name":"Auto-Hj\u00f8rnet",
    "wof:placetype":"venue"
},
  "geometry": {"coordinates":[8.4458370209,55.4730491638],"type":"Point"}
}