{
  "type": "Feature",
  "properties": {
    "addr:full":"Sognepr\u00e6st: Erik H. Bennetzen (K/B), Kirkebakken 1 Vils Danmark 7980",
    "addr:housenumber":"1",
    "addr:postcode":"7980",
    "addr:street":"Erik;Kirkebakken",
    "iso:country":"DK",
    "sg:address":"Sognepr\u00e6st: Erik H. Bennetzen (K/B), Kirkebakken 1",
    "sg:city":"Vils",
    "sg:orig_category":"Kirkesogne",
    "sg:phone":"+45 97 76 70 29",
    "sg:postcode":"7980",
    "sg:province":"Danmark",
    "wof:name":"Vejerslev-Lj\u00f8rslev-\u00d8rding Sogne",
    "wof:placetype":"venue"
},
  "geometry": {"coordinates":[8.7282047272,56.7638053894],"type":"Point"}
}