{
  "type": "Feature",
  "properties": {
    "addr:full":"\u00d8rb\u00e6kvej 12, Hoven Tarm Danmark 6880",
    "addr:housenumber":"12",
    "addr:postcode":"6880",
    "addr:street":"Orbaekvej",
    "iso:country":"DK",
    "sg:address":"\u00d8rb\u00e6kvej 12, Hoven",
    "sg:city":"Tarm",
    "sg:orig_category":"Dambrug",
    "sg:phone":"+45 75 34 30 98",
    "sg:postcode":"6880",
    "sg:province":"Danmark",
    "wof:name":"\u00d8rb\u00e6klunde Dambrug",
    "wof:placetype":"venue"
},
  "geometry": {"coordinates":[8.5200052261,55.9060554504],"type":"Point"}
}