{
  "type": "Feature",
  "properties": {
    "iso:country":"DK",
    "sg:address":"Bispemosevej 5 ",
    "sg:city":"Balle",
    "sg:classifiers":[
        {
            "category":"Professional",
            "subcategory":"Business Services",
            "type":"Services"
        }
    ],
    "sg:phone":"+45 86 33 74 55",
    "sg:postcode":"8444",
    "sg:province":"Danmark",
    "sg:tags":[
        "advice"
    ],
    "wof:name":"ROSMUS SKOLE",
    "wof:placetype":"venue"
},
  "geometry": {"coordinates":[10.8090896606,56.31640625],"type":"Point"}
}