{
  "type": "Feature",
  "properties": {
    "iso:country":"DK",
    "sg:address":"M\u00e5gevej 19",
    "sg:city":"Frederikssund",
    "sg:classifiers":[
        {
            "category":"Food & Beverages",
            "subcategory":"Liquor & Beverages",
            "type":"Retail Goods"
        }
    ],
    "sg:phone":"+45 47 38 51 52",
    "sg:postcode":"3600",
    "sg:province":"Danmark",
    "sg:tags":[
        "vin"
    ],
    "wof:name":"Frederikssund Vinlager",
    "wof:placetype":"venue"
},
  "geometry": {"coordinates":[12.0630149841,55.8373184204],"type":"Point"}
}