{
  "type": "Feature",
  "properties": {
    "addr:full":"Gilleleje Hovedgade 21 Gilleleje Danmark 3250",
    "addr:housenumber":"21",
    "addr:postcode":"3250",
    "addr:street":"Gilleleje Hovedgade",
    "iso:country":"DK",
    "sg:address":"Gilleleje Hovedgade 21",
    "sg:city":"Gilleleje",
    "sg:orig_category":"Antikviteter",
    "sg:phone":"+45 48 30 28 60",
    "sg:postcode":"3250",
    "sg:province":"Danmark",
    "wof:name":"Karin's Antik & Genbrug",
    "wof:placetype":"venue"
},
  "geometry": {"coordinates":[12.3086442947,56.1242675781],"type":"Point"}
}