{
  "type": "Feature",
  "properties": {
    "addr:full":"Nibe Sundhedscenter, Sygehusvej 14 Nibe Danmark 9240",
    "addr:housenumber":"14",
    "addr:postcode":"9240",
    "addr:street":"Sygehusvej",
    "iso:country":"DK",
    "sg:address":"Nibe Sundhedscenter, Sygehusvej 14",
    "sg:city":"Nibe",
    "sg:orig_category":"Tandteknikere, Kliniske",
    "sg:phone":"+45 98 35 38 40",
    "sg:postcode":"9240",
    "sg:province":"Danmark",
    "wof:name":"Kristensen, Lars Rye",
    "wof:placetype":"venue"
},
  "geometry": {"coordinates":[9.6393280029,56.982421875],"type":"Point"}
}