{
  "type": "Feature",
  "properties": {
    "addr:full":"Industrivej 5 Aabenraa Danmark 6200",
    "addr:housenumber":"5",
    "addr:postcode":"6200",
    "addr:street":"Industrivej",
    "iso:country":"DK",
    "sg:address":"Industrivej 5",
    "sg:city":"Aabenraa",
    "sg:orig_category":"Engros handel",
    "sg:phone":"+45 74 62 89 29",
    "sg:postcode":"6200",
    "sg:province":"Danmark",
    "wof:name":"Tristar A/S",
    "wof:placetype":"venue"
},
  "geometry": {"coordinates":[9.4025154114,55.047744751],"type":"Point"}
}