{
  "type": "Feature",
  "properties": {
    "addr:full":"Lindeg\u00e5rdsvej 10 B Herning Danmark 7400",
    "addr:housenumber":"10 b",
    "addr:postcode":"7400",
    "addr:street":"Lindegaardsvej",
    "iso:country":"DK",
    "sg:address":"Lindeg\u00e5rdsvej 10 B",
    "sg:city":"Herning",
    "sg:orig_category":"Socialpsykiatriske bosteder",
    "sg:phone":"+45 97 21 49 55",
    "sg:postcode":"7400",
    "sg:province":"Danmark",
    "wof:name":"Mosaikken, Bohuset",
    "wof:placetype":"venue"
},
  "geometry": {"coordinates":[8.9658718109,56.1317901611],"type":"Point"}
}