{
  "type": "Feature",
  "properties": {
    "addr:full":"H\u00f8jmevej 19, Dyrup Odense SV Danmark 5250",
    "addr:housenumber":"19",
    "addr:postcode":"5250",
    "addr:street":"Hojmevej;Dyrup",
    "iso:country":"DK",
    "sg:address":"H\u00f8jmevej 19, Dyrup",
    "sg:city":"Odense SV",
    "sg:orig_category":"Autoforhandlere",
    "sg:phone":"+45 66 17 17 01",
    "sg:postcode":"5250",
    "sg:province":"Danmark",
    "wof:name":"MAN Odense",
    "wof:placetype":"venue"
},
  "geometry": {"coordinates":[10.3153953552,55.3362998962],"type":"Point"}
}