{
  "type": "Feature",
  "properties": {
    "addr:full":"Gr\u00f8nlandsparken 80 A, st.th Esbjerg N Danmark 6715",
    "addr:housenumber":"80 a",
    "addr:postcode":"6715",
    "addr:street":"Gronlandsparken;St.Th",
    "iso:country":"DK",
    "sg:address":"Gr\u00f8nlandsparken 80 A, st.th",
    "sg:city":"Esbjerg N",
    "sg:orig_category":"Vinduespolering",
    "sg:phone":"+45 23 25 46 49",
    "sg:postcode":"6715",
    "sg:province":"Danmark",
    "wof:name":"Buch's Vinduespolering",
    "wof:placetype":"venue"
},
  "geometry": {"coordinates":[8.4780550003,55.535610199],"type":"Point"}
}