{
  "type": "Feature",
  "properties": {
    "addr:full":"Gyvelvej 16 Thisted Danmark 7700",
    "addr:housenumber":"16",
    "addr:postcode":"7700",
    "addr:street":"Gyvelvej",
    "iso:country":"DK",
    "sg:address":"Gyvelvej 16",
    "sg:city":"Thisted",
    "sg:orig_category":"Automater",
    "sg:phone":"+45 97 92 23 31",
    "sg:postcode":"7700",
    "sg:province":"Danmark",
    "wof:name":"Bega Automater ApS",
    "wof:placetype":"venue"
},
  "geometry": {"coordinates":[8.7287635803,56.9547767639],"type":"Point"}
}