{
  "type": "Feature",
  "properties": {
    "addr:full":"Fugleh\u00f8jen 48 Herlev Danmark 2730",
    "addr:housenumber":"48",
    "addr:postcode":"2730",
    "addr:street":"Fuglehojen",
    "iso:country":"DK",
    "sg:address":"Fugleh\u00f8jen 48",
    "sg:city":"Herlev",
    "sg:orig_category":"Malermestre",
    "sg:phone":"+45 44 94 85 50",
    "sg:postcode":"2730",
    "sg:province":"Danmark",
    "wof:name":"Nielsen, B Bog\u00f8",
    "wof:placetype":"venue"
},
  "geometry": {"coordinates":[12.417140007,55.7344589233],"type":"Point"}
}