{
  "type": "Feature",
  "properties": {
    "addr:full":"Sognepr\u00e6st: Morten Rydal (K/B), Br\u00f8ndumvej 34, Hem Skive Danmark 7800",
    "addr:housenumber":"34",
    "addr:postcode":"7800",
    "addr:street":"Morten;Brondumvej",
    "iso:country":"DK",
    "sg:address":"Sognepr\u00e6st: Morten Rydal (K/B), Br\u00f8ndumvej 34, Hem",
    "sg:city":"Skive",
    "sg:orig_category":"Kirkesogne",
    "sg:phone":"+45 97 53 10 35",
    "sg:postcode":"7800",
    "sg:province":"Danmark",
    "wof:name":"Hem/Hindborg og D\u00f8lby sogne",
    "wof:placetype":"venue"
},
  "geometry": {"coordinates":[9.0320358276,56.5666427612],"type":"Point"}
}