{
  "type": "Feature",
  "properties": {
    "addr:full":"Baldursgade 38 Esbjerg Danmark 6700",
    "addr:housenumber":"38",
    "addr:postcode":"6700",
    "addr:street":"Baldursgade",
    "iso:country":"DK",
    "sg:address":"Baldursgade 38",
    "sg:city":"Esbjerg",
    "sg:orig_category":"Murermestre",
    "sg:phone":"+45 75 45 11 36",
    "sg:postcode":"6700",
    "sg:province":"Danmark",
    "wof:name":"H P C Byg",
    "wof:placetype":"venue"
},
  "geometry": {"coordinates":[8.4559392929,55.4821014404],"type":"Point"}
}