{
  "type": "Feature",
  "properties": {
    "iso:country":"DK",
    "sg:address":"Snekkevej 53",
    "sg:city":"Jyllinge",
    "sg:orig_category":"Arkitekter",
    "sg:phone":"+45 46 78 87 66",
    "sg:postcode":"4040",
    "sg:province":"Danmark",
    "wof:name":"K\u00f8ppen, Svend Willy",
    "wof:placetype":"venue"
},
  "geometry": {"coordinates":[12.1069803238,55.7407608032],"type":"Point"}
}