{
  "type": "Feature",
  "properties": {
    "addr:full":"Rentemestervej 45-47 K\u00f8benhavn NV Danmark 2400",
    "addr:housenumber":"45-47",
    "addr:postcode":"2400",
    "addr:street":"Rentemestervej",
    "iso:country":"DK",
    "sg:address":"Rentemestervej 45-47",
    "sg:city":"K\u00f8benhavn NV",
    "sg:orig_category":"Fotolaboratorier",
    "sg:phone":"+45 38 88 32 88",
    "sg:postcode":"2400",
    "sg:province":"Danmark",
    "sg:website":"www.BilledService.dk",
    "wof:name":"BilledService A/S",
    "wof:placetype":"venue"
},
  "geometry": {"coordinates":[-117.02272033689999,38.5024604797],"type":"Point"}
}