{
  "type": "Feature",
  "properties": {
    "addr:full":"H\u00f8gevej 32, Heldum Lemvig Danmark 7620",
    "addr:housenumber":"32",
    "addr:postcode":"7620",
    "addr:street":"Hogevej",
    "iso:country":"DK",
    "sg:address":"H\u00f8gevej 32, Heldum",
    "sg:city":"Lemvig",
    "sg:orig_category":"Produktionsskoler",
    "sg:phone":"+45 96 63 01 08",
    "sg:postcode":"7620",
    "sg:province":"Danmark",
    "wof:name":"Lemvig Produktionsskole",
    "wof:placetype":"venue"
},
  "geometry": {"coordinates":[8.3073654175,56.5505104065],"type":"Point"}
}