{
  "type": "Feature",
  "properties": {
    "addr:full":"Torvegade 9 Fakse Danmark 4640",
    "addr:housenumber":"9",
    "addr:postcode":"4640",
    "addr:street":"Torvegade",
    "iso:country":"DK",
    "sg:address":"Torvegade 9",
    "sg:city":"Fakse",
    "sg:classifiers":[
        {
            "category":"Manufacturing",
            "subcategory":"Tobacco Products",
            "type":"Manufacturing & Wholesale Goods"
        }
    ],
    "sg:phone":"+45 56 71 45 04",
    "sg:postcode":"4640",
    "sg:province":"Danmark",
    "sg:tags":[
        "manufacturer"
    ],
    "wof:name":"Hansen, Erik",
    "wof:placetype":"venue"
},
  "geometry": {"coordinates":[12.1204843521,55.2569046021],"type":"Point"}
}