{
  "type": "Feature",
  "properties": {
    "addr:full":"Kjeld Abells Vej 3 Silkeborg Danmark 8600",
    "addr:housenumber":"3",
    "addr:postcode":"8600",
    "addr:street":"Kjeld Abells Vej",
    "iso:country":"DK",
    "sg:address":"Kjeld Abells Vej 3",
    "sg:city":"Silkeborg",
    "sg:orig_category":"Murermestre",
    "sg:phone":"+45 86 82 98 33",
    "sg:postcode":"8600",
    "sg:province":"Danmark",
    "wof:name":"Hansen ApS, Ove",
    "wof:placetype":"venue"
},
  "geometry": {"coordinates":[9.532576561,56.1867713928],"type":"Point"}
}