{
  "type": "Feature",
  "properties": {
    "addr:full":"Nordre Strandvej 51 Risskov Danmark 8240",
    "addr:housenumber":"51",
    "addr:postcode":"8240",
    "addr:street":"Nordre Strandvej",
    "iso:country":"DK",
    "sg:address":"Nordre Strandvej 51",
    "sg:city":"Risskov",
    "sg:orig_category":"Fotografer",
    "sg:phone":"+45 86 17 70 15",
    "sg:postcode":"8240",
    "sg:province":"Danmark",
    "sg:website":"www.risskovfotografi.dk",
    "wof:name":"Risskov Fotografi",
    "wof:placetype":"venue"
},
  "geometry": {"coordinates":[10.247795105,56.1954612732],"type":"Point"}
}