{
  "type": "Feature",
  "properties": {
    "addr:full":"\u00d8steralle 19 Ebeltoft Danmark 8400",
    "addr:housenumber":"19",
    "addr:postcode":"8400",
    "addr:street":"Osteralle",
    "iso:country":"DK",
    "sg:address":"\u00d8steralle 19",
    "sg:city":"Ebeltoft",
    "sg:orig_category":"Kommunale folkeskoler",
    "sg:phone":"+45 86 34 17 55",
    "sg:postcode":"8400",
    "sg:province":"Danmark",
    "wof:name":"Toftevangskolen",
    "wof:placetype":"venue"
},
  "geometry": {"coordinates":[10.6778745651,56.199798584],"type":"Point"}
}