{
  "type": "Feature",
  "properties": {
    "addr:full":"N\u00f8rremarksvej 3 Ribe Danmark 6760",
    "addr:housenumber":"3",
    "addr:postcode":"6760",
    "addr:street":"Norremarksvej",
    "iso:country":"DK",
    "sg:address":"N\u00f8rremarksvej 3",
    "sg:city":"Ribe",
    "sg:orig_category":"Arbejdsformidling",
    "sg:phone":"+45 75 42 08 44",
    "sg:postcode":"6760",
    "sg:province":"Danmark",
    "wof:name":"Arbejdsformidlingen, Ribe afd.",
    "wof:placetype":"venue"
},
  "geometry": {"coordinates":[8.7706108093,55.3316345215],"type":"Point"}
}