{
  "type": "Feature",
  "properties": {
    "addr:full":"Comedievognens Broscene, Griffenfeldsgade 7 A K\u00f8benhavn N Danmark 2200",
    "addr:housenumber":"7 a",
    "addr:postcode":"2200",
    "addr:street":"Griffenfeldsgade;Kobenhavn N Danmark",
    "iso:country":"DK",
    "sg:address":"Comedievognens Broscene, Griffenfeldsgade 7 A",
    "sg:city":"K\u00f8benhavn N",
    "sg:orig_category":"Teatre",
    "sg:phone":"+45 35 36 61 22",
    "sg:postcode":"2200",
    "sg:province":"Danmark",
    "sg:website":"www.comedievognen.aok.dk",
    "wof:name":"Comedievognen",
    "wof:placetype":"venue"
},
  "geometry": {"coordinates":[12.5554351807,55.6889572144],"type":"Point"}
}