{
  "type": "Feature",
  "properties": {
    "iso:country":"DK",
    "sg:address":"Skolegade 4, Kaas",
    "sg:city":"Pandrup",
    "sg:orig_category":"Kommunale folkeskoler",
    "sg:phone":"+45 98 24 51 39",
    "sg:postcode":"9490",
    "sg:province":"Danmark",
    "wof:name":"Jetsmark Centralskole",
    "wof:placetype":"venue"
},
  "geometry": {"coordinates":[9.6769151688,57.223815918],"type":"Point"}
}