{
  "type": "Feature",
  "properties": {
    "addr:full":"Brogade 6 Odense C Danmark 5000",
    "addr:housenumber":"6",
    "addr:postcode":"5000",
    "addr:street":"Brogade",
    "iso:country":"DK",
    "sg:address":"Brogade 6",
    "sg:city":"Odense C",
    "sg:classifiers":[
        {
            "category":"Restaurant",
            "type":"Food & Drink"
        }
    ],
    "sg:phone":"+45 66 14 40 97",
    "sg:postcode":"5000",
    "sg:province":"Danmark",
    "wof:name":"Spj\u00e6ldet",
    "wof:placetype":"venue"
},
  "geometry": {"coordinates":[10.3962850571,55.3967475891],"type":"Point"}
}