{
  "type": "Feature",
  "properties": {
    "addr:full":"Drechselsgade 1 K\u00f8benhavn S Danmark 2300",
    "addr:housenumber":"1",
    "addr:postcode":"2300",
    "addr:street":"Drechselsgade;S Danmark",
    "iso:country":"DK",
    "sg:address":"Drechselsgade 1",
    "sg:city":"K\u00f8benhavn S",
    "sg:orig_category":"Botilbud",
    "sg:phone":"+45 32 54 54 07",
    "sg:postcode":"2300",
    "sg:province":"Danmark",
    "wof:name":"K.F.U.M.'s Kollegium",
    "wof:placetype":"venue"
},
  "geometry": {"coordinates":[-82.55717468260001,38.4063796997],"type":"Point"}
}