{
  "type": "Feature",
  "properties": {
    "addr:full":"Paghs Alle 21 Herning Danmark 7400",
    "addr:housenumber":"21",
    "addr:postcode":"7400",
    "addr:street":"Paghs Alle",
    "iso:country":"DK",
    "sg:address":"Paghs Alle 21",
    "sg:city":"Herning",
    "sg:orig_category":"Autoreparation og -service",
    "sg:phone":"+45 97 22 22 84",
    "sg:postcode":"7400",
    "sg:province":"Danmark",
    "wof:name":"Midtbyens Auto- & Pladev\u00e6rksted",
    "wof:placetype":"venue"
},
  "geometry": {"coordinates":[8.9606304169,56.1378974915],"type":"Point"}
}