{
  "type": "Feature",
  "properties": {
    "iso:country":"DK",
    "sg:address":"Bygmarken 50",
    "sg:city":"Hanstholm",
    "sg:orig_category":"Arkitekter",
    "sg:phone":"+45 97 96 12 25",
    "sg:postcode":"7730",
    "sg:province":"Danmark",
    "wof:name":"Langhoff's Tegnestue",
    "wof:placetype":"venue"
},
  "geometry": {"coordinates":[8.6171703339,57.1100578308],"type":"Point"}
}