{
  "type": "Feature",
  "properties": {
    "addr:full":"L\u00f8vk\u00e6rparken 47, Tune Roskilde Danmark 4000",
    "addr:housenumber":"47",
    "addr:postcode":"4000",
    "addr:street":"Lovkaerparken",
    "iso:country":"DK",
    "sg:address":"L\u00f8vk\u00e6rparken 47, Tune",
    "sg:city":"Roskilde",
    "sg:orig_category":"Hospitalsudstyr",
    "sg:phone":"+45 46 13 61 40",
    "sg:postcode":"4000",
    "sg:province":"Danmark",
    "wof:name":"Medican",
    "wof:placetype":"venue"
},
  "geometry": {"coordinates":[12.0909376144,55.6404838562],"type":"Point"}
}