{
  "type": "Feature",
  "properties": {
    "addr:full":"Tingvejen 2, Skrydstrup Vojens Danmark 6500",
    "addr:housenumber":"2",
    "addr:postcode":"6500",
    "addr:street":"Tingvejen",
    "iso:country":"DK",
    "sg:address":"Tingvejen 2, Skrydstrup",
    "sg:city":"Vojens",
    "sg:orig_category":"Genvindingsindustri",
    "sg:phone":"+45 74 59 02 02",
    "sg:postcode":"6500",
    "sg:province":"Danmark",
    "sg:website":"www.replast.dk",
    "wof:name":"Replast A/S",
    "wof:placetype":"venue"
},
  "geometry": {"coordinates":[9.2987146378,55.2457237244],"type":"Point"}
}