{
  "type": "Feature",
  "properties": {
    "addr:full":"Fmd.: Per Frost S\u00f8rensen, Solv\u00e6nget 17, Biersted Aabybro Danmark 9440",
    "addr:housenumber":"17",
    "addr:postcode":"9440",
    "addr:street":"Biersted",
    "iso:country":"DK",
    "sg:address":"Fmd.: Per Frost S\u00f8rensen, Solv\u00e6nget 17, Biersted",
    "sg:city":"Aabybro",
    "sg:orig_category":"Hobbybetonede foreninger",
    "sg:phone":"+45 98 26 81 82",
    "sg:postcode":"9440",
    "sg:province":"Danmark",
    "wof:name":"Aalborg Bridgeklub",
    "wof:placetype":"venue"
},
  "geometry": {"coordinates":[9.7341356277,57.1588287354],"type":"Point"}
}