{
  "type": "Feature",
  "properties": {
    "addr:full":"B\u00f8gesangerv\u00e6nget 16 G, Snestrup Odense NV Danmark 5210",
    "addr:housenumber":"16 g",
    "addr:postcode":"5210",
    "addr:street":"Bogesangervaenget;Snestrup",
    "iso:country":"DK",
    "sg:address":"B\u00f8gesangerv\u00e6nget 16 G, Snestrup",
    "sg:city":"Odense NV",
    "sg:orig_category":"Homeparties",
    "sg:phone":"+45 66 16 21 20",
    "sg:postcode":"5210",
    "sg:province":"Danmark",
    "wof:name":"Schjermer, Birthe",
    "wof:placetype":"venue"
},
  "geometry": {"coordinates":[10.274764061,55.4303321838],"type":"Point"}
}