{
  "type": "Feature",
  "properties": {
    "addr:full":"Tomsg\u00e5rdsvej 15 K\u00f8benhavn NV Danmark 2400",
    "addr:housenumber":"15",
    "addr:postcode":"2400",
    "addr:street":"Tomsgaardsvej",
    "iso:country":"DK",
    "sg:address":"Tomsg\u00e5rdsvej 15",
    "sg:city":"K\u00f8benhavn NV",
    "sg:orig_category":"Fagblade og tidsskrifter",
    "sg:phone":"+45 70 25 35 00",
    "sg:postcode":"2400",
    "sg:province":"Danmark",
    "sg:website":"www.digital-design.dk",
    "wof:name":"Digital Design",
    "wof:placetype":"venue"
},
  "geometry": {"coordinates":[-117.02272033689999,38.5024604797],"type":"Point"}
}