{
  "type": "Feature",
  "properties": {
    "addr:full":"Haraldsborgvej 84, Himmelev Roskilde Danmark 4000",
    "addr:housenumber":"84",
    "addr:postcode":"4000",
    "addr:street":"Haraldsborgvej;Himmelev",
    "iso:country":"DK",
    "sg:address":"Haraldsborgvej 84, Himmelev",
    "sg:city":"Roskilde",
    "sg:orig_category":"Servicestationer",
    "sg:phone":"+45 46 36 21 77",
    "sg:postcode":"4000",
    "sg:province":"Danmark",
    "wof:name":"Statoil Servicecenter",
    "wof:placetype":"venue"
},
  "geometry": {"coordinates":[12.0909376144,55.6404838562],"type":"Point"}
}