{
  "type": "Feature",
  "properties": {
    "addr:full":"Tv\u00e6rvej 73 B Virum Danmark 2830",
    "addr:housenumber":"73 b",
    "addr:postcode":"2830",
    "addr:street":"Tvaervej",
    "iso:country":"DK",
    "sg:address":"Tv\u00e6rvej 73 B",
    "sg:city":"Virum",
    "sg:orig_category":"Fodplejere",
    "sg:phone":"+45 45 85 96 57",
    "sg:postcode":"2830",
    "sg:province":"Danmark",
    "wof:name":"Kromann, Ellen",
    "wof:placetype":"venue"
},
  "geometry": {"coordinates":[12.448559761,55.7956619263],"type":"Point"}
}