{
  "type": "Feature",
  "properties": {
    "addr:full":"Gl.Stenderupvej 9, Gl. Stenderup Broby Danmark 5672",
    "addr:housenumber":"9",
    "addr:postcode":"gl.;5672",
    "addr:street":"Gl.Stenderupvej",
    "iso:country":"DK",
    "sg:address":"Gl.Stenderupvej 9, Gl. Stenderup",
    "sg:city":"Broby",
    "sg:orig_category":"Skilte",
    "sg:phone":"+45 62 68 21 32",
    "sg:postcode":"5672",
    "sg:province":"Danmark",
    "wof:name":"Thorup Multi Skilte ApS",
    "wof:placetype":"venue"
},
  "geometry": {"coordinates":[10.3131303787,55.2695846558],"type":"Point"}
}