{
  "type": "Feature",
  "properties": {
    "addr:full":"Niels Lyhnes Vej 6 Vestbjerg Danmark 9380",
    "addr:housenumber":"6",
    "addr:postcode":"9380",
    "addr:street":"Niels Lyhnes Vej",
    "iso:country":"DK",
    "sg:address":"Niels Lyhnes Vej 6",
    "sg:city":"Vestbjerg",
    "sg:orig_category":"Lokalbiblioteker",
    "sg:phone":"+45 98 29 67 55",
    "sg:postcode":"9380",
    "sg:province":"Danmark",
    "wof:name":"Vestbjerg Bibliotek",
    "wof:placetype":"venue"
},
  "geometry": {"coordinates":[9.9664077759,57.1265792847],"type":"Point"}
}