{
  "type": "Feature",
  "properties": {
    "addr:full":"N\u00f8rregade 9 A Vorbasse Danmark 6623",
    "addr:housenumber":"9 a",
    "addr:postcode":"6623",
    "addr:street":"Norregade",
    "iso:country":"DK",
    "sg:address":"N\u00f8rregade 9 A",
    "sg:city":"Vorbasse",
    "sg:orig_category":"Cafeer",
    "sg:phone":"+45 75 33 39 79",
    "sg:postcode":"6623",
    "sg:province":"Danmark",
    "wof:name":"Stoppe-Stedet",
    "wof:placetype":"venue"
},
  "geometry": {"coordinates":[9.0798864365,55.6310501099],"type":"Point"}
}