{
  "type": "Feature",
  "properties": {
    "iso:country":"DK",
    "sg:address":"Esplanaden 48",
    "sg:city":"K\u00f8benhavn",
    "sg:orig_category":"Kort, Topografiske",
    "sg:phone":"+45 33 11 28 15",
    "sg:postcode":"1263",
    "sg:province":"Danmark",
    "wof:name":"Blankensteiners Eftf.",
    "wof:placetype":"venue"
},
  "geometry": {"coordinates":[12.5975999832,55.6869010925],"type":"Point"}
}