{
  "type": "Feature",
  "properties": {
    "iso:country":"DK",
    "sg:address":"Stationsvej 4",
    "sg:city":"Brovst",
    "sg:orig_category":"Kiosker",
    "sg:phone":"+45 98 23 30 50",
    "sg:postcode":"9460",
    "sg:province":"Danmark",
    "wof:name":"John's Vin & Tobak",
    "wof:placetype":"venue"
},
  "geometry": {"coordinates":[9.5196199417,57.0998764038],"type":"Point"}
}