{
  "type": "Feature",
  "properties": {
    "addr:full":"Mosestien 3 Fjenneslev Danmark 4173",
    "addr:housenumber":"3",
    "addr:postcode":"4173",
    "addr:street":"Mosestien",
    "iso:country":"DK",
    "sg:address":"Mosestien 3",
    "sg:city":"Fjenneslev",
    "sg:orig_category":"Fisk og vildt",
    "sg:phone":"+45 57 80 91 03",
    "sg:postcode":"4173",
    "sg:province":"Danmark",
    "wof:name":"Linda's Fiskevogn",
    "wof:placetype":"venue"
},
  "geometry": {"coordinates":[11.6512622833,55.44140625],"type":"Point"}
}