{
  "type": "Feature",
  "properties": {
    "addr:full":"Middelfartvej 9 Odense C Danmark 5000",
    "addr:housenumber":"9",
    "addr:postcode":"5000",
    "addr:street":"Middelfartvej",
    "iso:country":"DK",
    "sg:address":"Middelfartvej 9",
    "sg:city":"Odense C",
    "sg:orig_category":"Blomster en gros",
    "sg:phone":"+45 66 13 42 32",
    "sg:postcode":"5000",
    "sg:province":"Danmark",
    "wof:name":"Kuipers Danmark Aps",
    "wof:placetype":"venue"
},
  "geometry": {"coordinates":[10.36344,55.394402],"type":"Point"}
}