{
  "type": "Feature",
  "properties": {
    "iso:country":"DK",
    "sg:address":"Havnegade 1",
    "sg:city":"Odense C",
    "sg:orig_category":"Servicestationer",
    "sg:phone":"+45 66 19 00 81",
    "sg:postcode":"5000",
    "sg:province":"Danmark",
    "wof:name":"DK Benzin og N\u00e6rbutik",
    "wof:placetype":"venue"
},
  "geometry": {"coordinates":[10.384944,55.406422],"type":"Point"}
}