{
  "type": "Feature",
  "properties": {
    "addr:full":"Stationsvej 5 Stenlille Danmark 4295",
    "addr:housenumber":"5",
    "addr:postcode":"4295",
    "addr:street":"Stationsvej",
    "iso:country":"DK",
    "sg:address":"Stationsvej 5",
    "sg:city":"Stenlille",
    "sg:classifiers":[
        {
            "category":"Wholesale",
            "subcategory":"Chemicals & Plastics",
            "type":"Manufacturing & Wholesale Goods"
        }
    ],
    "sg:phone":"+45 57 89 48 00",
    "sg:postcode":"4295",
    "sg:province":"Danmark",
    "sg:website":"www.dbi.dk",
    "wof:name":"DBI Plastics A/S",
    "wof:placetype":"venue"
},
  "geometry": {"coordinates":[11.59516716,55.5386734009],"type":"Point"}
}