{
  "type": "Feature",
  "properties": {
    "iso:country":"DK",
    "sg:address":"Freerslev Bygade 14",
    "sg:city":"Haslev",
    "sg:orig_category":"Zoneterapeuter",
    "sg:phone":"+45 56 39 70 72",
    "sg:postcode":"4690",
    "sg:province":"Danmark",
    "wof:name":"Bach, Susi Q.",
    "wof:placetype":"venue"
},
  "geometry": {"coordinates":[12.0170602798,55.3289794922],"type":"Point"}
}