{
  "type": "Feature",
  "properties": {
    "iso:country":"DK",
    "sg:address":"Stefansgade 43",
    "sg:city":"K\u00f8benhavn N",
    "sg:orig_category":"Cykler",
    "sg:phone":"+45 35 85 07 95",
    "sg:postcode":"2200",
    "sg:province":"Danmark",
    "wof:name":"Stefan Cykler",
    "wof:placetype":"venue"
},
  "geometry": {"coordinates":[-87.5988616943,33.2456436157],"type":"Point"}
}