{
  "type": "Feature",
  "properties": {
    "iso:country":"DK",
    "sg:address":"Stationsvej 42",
    "sg:city":"Spentrup",
    "sg:orig_category":"Revisorer",
    "sg:phone":"+45 86 47 79 55",
    "sg:postcode":"8981",
    "sg:province":"Danmark",
    "sg:website":"www.chrkirk.dk",
    "wof:name":"Kirk I/S, Revisionsfirmaet Chr.",
    "wof:placetype":"venue"
},
  "geometry": {"coordinates":[10.0347032547,56.5400619507],"type":"Point"}
}