{
  "type": "Feature",
  "properties": {
    "addr:full":"Viborgvej 22 Silkeborg Danmark 8600",
    "addr:housenumber":"22",
    "addr:postcode":"8600",
    "addr:street":"Viborgvej",
    "iso:country":"DK",
    "sg:address":"Viborgvej 22",
    "sg:city":"Silkeborg",
    "sg:orig_category":"Engros handel",
    "sg:phone":"+45 87 20 47 60",
    "sg:postcode":"8600",
    "sg:province":"Danmark",
    "sg:website":"www.gate-one.dk",
    "wof:name":"Gate One",
    "wof:placetype":"venue"
},
  "geometry": {"coordinates":[9.5137119293,56.2034912109],"type":"Point"}
}