{
  "type": "Feature",
  "properties": {
    "addr:full":"Haraldsvej 21 Randers Danmark 8900",
    "addr:housenumber":"21",
    "addr:postcode":"8900",
    "addr:street":"Haraldsvej",
    "iso:country":"DK",
    "sg:address":"Haraldsvej 21",
    "sg:city":"Randers",
    "sg:orig_category":"Maskinfabrikker",
    "sg:phone":"+45 86 43 51 55",
    "sg:postcode":"8900",
    "sg:province":"Danmark",
    "wof:name":"Dan-List A/S",
    "wof:placetype":"venue"
},
  "geometry": {"coordinates":[10.0528650284,56.4392242432],"type":"Point"}
}