{
  "type": "Feature",
  "properties": {
    "iso:country":"DK",
    "sg:address":"Skolegade 32",
    "sg:city":"\u00c5rhus C",
    "sg:classifiers":[
        {
            "category":"Restaurant",
            "type":"Food & Drink"
        }
    ],
    "sg:phone":"+45 86 13 79 26",
    "sg:postcode":"8000",
    "sg:province":"Danmark",
    "wof:name":"F\u00e6rgekroen",
    "wof:placetype":"venue"
},
  "geometry": {"coordinates":[9.5235595703,55.7128295898],"type":"Point"}
}