{
  "type": "Feature",
  "properties": {
    "addr:full":"Svendsvej 7 Roskilde Danmark 4000",
    "addr:housenumber":"7",
    "addr:postcode":"4000",
    "addr:street":"Svendsvej",
    "iso:country":"DK",
    "sg:address":"Svendsvej 7",
    "sg:city":"Roskilde",
    "sg:orig_category":"Skorstensfejere",
    "sg:phone":"+45 46 36 52 63",
    "sg:postcode":"4000",
    "sg:province":"Danmark",
    "wof:name":"Jeppesen, Ole",
    "wof:placetype":"venue"
},
  "geometry": {"coordinates":[12.0862140656,55.6367073059],"type":"Point"}
}