{
  "type": "Feature",
  "properties": {
    "addr:full":"Annasvej 19 Hellerup Danmark 2900",
    "addr:housenumber":"19",
    "addr:postcode":"2900",
    "addr:street":"Annasvej",
    "iso:country":"DK",
    "sg:address":"Annasvej 19",
    "sg:city":"Hellerup",
    "sg:orig_category":"Grafiske tegnestuer",
    "sg:phone":"+45 39 62 38 08",
    "sg:postcode":"2900",
    "sg:province":"Danmark",
    "wof:name":"Gyldne Snit, Det",
    "wof:placetype":"venue"
},
  "geometry": {"coordinates":[12.5829162598,55.7401542664],"type":"Point"}
}