{
  "type": "Feature",
  "properties": {
    "iso:country":"DK",
    "sg:address":"Randlevvej 5",
    "sg:city":"Odder",
    "sg:orig_category":"Slagter og viktualie",
    "sg:phone":"+45 86 54 11 56",
    "sg:postcode":"8300",
    "sg:province":"Danmark",
    "wof:name":"Lindgaard, Slagter",
    "wof:placetype":"venue"
},
  "geometry": {"coordinates":[10.1538553238,55.9726753235],"type":"Point"}
}