{
  "type": "Feature",
  "properties": {
    "addr:full":"Industrivej Vest 2 Vejen Danmark 6600",
    "addr:housenumber":"2",
    "addr:postcode":"6600",
    "addr:street":"Industrivej Vest",
    "iso:country":"DK",
    "sg:address":"Industrivej Vest 2",
    "sg:city":"Vejen",
    "sg:orig_category":"Autoforhandlere",
    "sg:phone":"+45 75 36 54 00",
    "sg:postcode":"6600",
    "sg:province":"Danmark",
    "wof:name":"L\u00e6borg Autohandel",
    "wof:placetype":"venue"
},
  "geometry": {"coordinates":[9.1250915527,55.4903564453],"type":"Point"}
}