{
  "type": "Feature",
  "properties": {
    "addr:full":"Lindgreens Alle 20 K\u00f8benhavn S Danmark 2300",
    "addr:housenumber":"20",
    "addr:postcode":"2300",
    "addr:street":"Lindgreens Alle;S Danmark",
    "iso:country":"DK",
    "sg:address":"Lindgreens Alle 20",
    "sg:city":"K\u00f8benhavn S",
    "sg:orig_category":"Hobbybetonede foreninger",
    "sg:phone":"+45 32 57 20 20",
    "sg:postcode":"2300",
    "sg:province":"Danmark",
    "wof:name":"Amager Motorcykel klub af 1971",
    "wof:placetype":"venue"
},
  "geometry": {"coordinates":[-78.1299133301,36.7267417908],"type":"Point"}
}