{
  "type": "Feature",
  "properties": {
    "iso:country":"DK",
    "sg:address":"Peder Skrams Gade 12 - 14",
    "sg:city":"\u00c5rhus N",
    "sg:orig_category":"Blikkenslagere",
    "sg:phone":"+45 86 16 92 38",
    "sg:postcode":"8200",
    "sg:province":"Danmark",
    "wof:name":"R\u00f8hl A/S, C.",
    "wof:placetype":"venue"
},
  "geometry": {"coordinates":[99.925011,34.243011],"type":"Point"}
}