{
  "type": "Feature",
  "properties": {
    "addr:full":"Vesterbrogade 49, Humlum Struer Danmark 7600",
    "addr:housenumber":"49",
    "addr:postcode":"7600",
    "addr:street":"Vesterbrogade;Humlum",
    "iso:country":"DK",
    "sg:address":"Vesterbrogade 49, Humlum",
    "sg:city":"Struer",
    "sg:orig_category":"Grillbarer",
    "sg:phone":"+45 97 86 17 22",
    "sg:postcode":"7600",
    "sg:province":"Danmark",
    "wof:name":"Stjerne Grill",
    "wof:placetype":"venue"
},
  "geometry": {"coordinates":[8.5946903229,56.491191864],"type":"Point"}
}