{
  "type": "Feature",
  "properties": {
    "addr:full":"Dals\u00f8vej 56 Grindsted Danmark 7200",
    "addr:housenumber":"56",
    "addr:postcode":"7200",
    "addr:street":"Dalsovej",
    "iso:country":"DK",
    "sg:address":"Dals\u00f8vej 56",
    "sg:city":"Grindsted",
    "sg:orig_category":"Affald",
    "sg:phone":"+45 74 32 36 17",
    "sg:postcode":"7200",
    "sg:province":"Danmark",
    "wof:name":"Th\u00f8gersen, Aage",
    "wof:placetype":"venue"
},
  "geometry": {"coordinates":[8.9509773254,55.7559013367],"type":"Point"}
}