{
  "type": "Feature",
  "properties": {
    "iso:country":"DK",
    "sg:address":"Strandpromenaden 2 ",
    "sg:city":"Horsens",
    "sg:classifiers":[
        {
            "category":"Professional",
            "subcategory":"Computer Services",
            "type":"Services"
        }
    ],
    "sg:phone":"+45 75 62 87 11",
    "sg:postcode":"8700",
    "sg:province":"Danmark",
    "sg:tags":[
        "information",
        "technology"
    ],
    "wof:name":"INTEGRITY LOGO DATA APS",
    "wof:placetype":"venue"
},
  "geometry": {"coordinates":[9.8672065735,55.8599662781],"type":"Point"}
}