{
  "type": "Feature",
  "properties": {
    "addr:full":"Salbjergvej 42 Havdrup Danmark 4622",
    "addr:housenumber":"42",
    "addr:postcode":"4622",
    "addr:street":"Salbjergvej",
    "iso:country":"DK",
    "sg:address":"Salbjergvej 42",
    "sg:city":"Havdrup",
    "sg:orig_category":"Plastvarefabrikker",
    "sg:phone":"+45 46 18 55 66",
    "sg:postcode":"4622",
    "sg:province":"Danmark",
    "wof:name":"Dansk Poly Fabrik A/S",
    "wof:placetype":"venue"
},
  "geometry": {"coordinates":[12.1272611618,55.5511131287],"type":"Point"}
}