{
  "type": "Feature",
  "properties": {
    "addr:full":"Vognsbjergvej 7 Bagenkop Danmark 5935",
    "addr:housenumber":"7",
    "addr:postcode":"5935",
    "addr:street":"Vognsbjergvej",
    "iso:country":"DK",
    "sg:address":"Vognsbjergvej 7",
    "sg:city":"Bagenkop",
    "sg:orig_category":"Beslagsmede",
    "sg:phone":"+45 62 56 16 45",
    "sg:postcode":"5935",
    "sg:province":"Danmark",
    "wof:name":"Zawada, Keld",
    "wof:placetype":"venue"
},
  "geometry": {"coordinates":[10.718488,54.754177],"type":"Point"}
}