{
  "type": "Feature",
  "properties": {
    "iso:country":"DK",
    "sg:address":"Bakkedraget 1, Vognsild",
    "sg:city":"Aars",
    "sg:orig_category":"Reklamebureauer",
    "sg:phone":"+45 98 65 83 96",
    "sg:postcode":"9600",
    "sg:province":"Danmark",
    "sg:website":"www.viob.dk",
    "wof:name":"Vognsild Idr\u00e6ts-Boldklub",
    "wof:placetype":"venue"
},
  "geometry": {"coordinates":[9.5170412064,56.8031692505],"type":"Point"}
}