{
  "type": "Feature",
  "properties": {
    "addr:full":"Skibhusvej 150 Odense C Danmark 5000",
    "addr:housenumber":"150",
    "addr:postcode":"5000",
    "addr:street":"Skibhusvej",
    "iso:country":"DK",
    "sg:address":"Skibhusvej 150",
    "sg:city":"Odense C",
    "sg:orig_category":"Blomsterhandlere",
    "sg:phone":"+45 66 14 73 80",
    "sg:postcode":"5000",
    "sg:province":"Danmark",
    "wof:name":"Cora Blomster",
    "wof:placetype":"venue"
},
  "geometry": {"coordinates":[10.3946800232,55.4120635986],"type":"Point"}
}