{
  "type": "Feature",
  "properties": {
    "addr:full":"Hjermvej 6 Struer Danmark 7600",
    "addr:housenumber":"6",
    "addr:postcode":"7600",
    "addr:street":"Hjermvej",
    "iso:country":"DK",
    "sg:address":"Hjermvej 6",
    "sg:city":"Struer",
    "sg:orig_category":"Akupunktur",
    "sg:phone":"+45 97 85 22 07",
    "sg:postcode":"7600",
    "sg:province":"Danmark",
    "wof:name":"Brosb\u00f8lls Helseklinik",
    "wof:placetype":"venue"
},
  "geometry": {"coordinates":[8.606836319,56.4699554443],"type":"Point"}
}