{
  "type": "Feature",
  "properties": {
    "addr:full":"Skolegade 28 D Tarm Danmark 6880",
    "addr:housenumber":"28 d",
    "addr:postcode":"6880",
    "addr:street":"Skolegade",
    "iso:country":"DK",
    "sg:address":"Skolegade 28 D",
    "sg:city":"Tarm",
    "sg:orig_category":"Kulturelle foreninger",
    "sg:phone":"+45 97 37 11 10",
    "sg:postcode":"6880",
    "sg:province":"Danmark",
    "wof:name":"St\u00f8tteforeningen for Tarm Sygehus",
    "wof:placetype":"venue"
},
  "geometry": {"coordinates":[8.5237560272,55.9051132202],"type":"Point"}
}