{
  "type": "Feature",
  "properties": {
    "iso:country":"DK",
    "sg:address":"Kirkepladsen 2",
    "sg:city":"Ringe",
    "sg:orig_category":"Kontorartikler",
    "sg:phone":"+45 62 62 11 95",
    "sg:postcode":"5750",
    "sg:province":"Danmark",
    "wof:name":"Fjords Bog & Id\u00e9",
    "wof:placetype":"venue"
},
  "geometry": {"coordinates":[10.4786834717,55.2379875183],"type":"Point"}
}