{
  "type": "Feature",
  "properties": {
    "iso:country":"DK",
    "sg:address":"Bank-Mikkelsens Vej 15",
    "sg:city":"Gentofte",
    "sg:orig_category":"Handicap-daginstitutioner",
    "sg:phone":"+45 45 85 92 62",
    "sg:postcode":"2820",
    "sg:province":"Danmark",
    "wof:name":"Geelsg\u00e5rd B\u00f8rnehave",
    "wof:placetype":"venue"
},
  "geometry": {"coordinates":[12.5075483322,55.75233078],"type":"Point"}
}