{
  "type": "Feature",
  "properties": {
    "addr:full":"Fynbovej 11 Horslunde Danmark 4913",
    "addr:housenumber":"11",
    "addr:postcode":"4913",
    "addr:street":"Fynbovej",
    "iso:country":"DK",
    "sg:address":"Fynbovej 11",
    "sg:city":"Horslunde",
    "sg:orig_category":"Antikvariater",
    "sg:phone":"+45 54 93 53 23",
    "sg:postcode":"4913",
    "sg:province":"Danmark",
    "wof:name":"Bogladen",
    "wof:placetype":"venue"
},
  "geometry": {"coordinates":[11.2195978165,54.9280090332],"type":"Point"}
}