{
  "type": "Feature",
  "properties": {
    "iso:country":"DK",
    "sg:address":"Houmeden 21",
    "sg:city":"Randers",
    "sg:orig_category":"Glarmestre og glarmagere",
    "sg:phone":"+45 86 42 69 95",
    "sg:postcode":"8900",
    "sg:province":"Danmark",
    "wof:name":"Hougaard",
    "wof:placetype":"venue"
},
  "geometry": {"coordinates":[10.0341653824,56.460559845],"type":"Point"}
}