{
  "type": "Feature",
  "properties": {
    "addr:full":"Fmd.: Karl Hansen, Udlodgyden 33, Davinde Odense S\u00d8 Danmark 5220",
    "addr:housenumber":"33",
    "addr:postcode":"5220",
    "addr:street":"Udlodgyden",
    "iso:country":"DK",
    "sg:address":"Fmd.: Karl Hansen, Udlodgyden 33, Davinde",
    "sg:city":"Odense S\u00d8",
    "sg:orig_category":"Hobbybetonede foreninger",
    "sg:phone":"+45 65 97 27 86",
    "sg:postcode":"5220",
    "sg:province":"Danmark",
    "wof:name":"Langeskov-Ullerslev Fjerkr\u00e6klub",
    "wof:placetype":"venue"
},
  "geometry": {"coordinates":[10.4583454132,55.3316917419],"type":"Point"}
}