{
  "type": "Feature",
  "properties": {
    "addr:full":"Kongens Nytorv 22 K\u00f8benhavn Danmark 1050",
    "addr:housenumber":"22",
    "addr:postcode":"1050",
    "addr:street":"Kongens Nytorv",
    "iso:country":"DK",
    "sg:address":"Kongens Nytorv 22",
    "sg:city":"K\u00f8benhavn",
    "sg:orig_category":"Advokater",
    "sg:phone":"+45 33 14 32 36",
    "sg:postcode":"1050",
    "sg:province":"Danmark",
    "wof:name":"S\u00f8ltoft, Henriette R.",
    "wof:placetype":"venue"
},
  "geometry": {"coordinates":[12.5860204697,55.6806793213],"type":"Point"}
}