{
  "type": "Feature",
  "properties": {
    "iso:country":"DK",
    "sg:address":"Lille Bjerggade 11 A",
    "sg:city":"Vejle",
    "sg:orig_category":"Smykker",
    "sg:phone":"+45 75 72 80 94",
    "sg:postcode":"7100",
    "sg:province":"Danmark",
    "wof:name":"Smykke Galleriet",
    "wof:placetype":"venue"
},
  "geometry": {"coordinates":[9.5313863754,55.702331543],"type":"Point"}
}