{
  "type": "Feature",
  "properties": {
    "iso:country":"DK",
    "sg:address":"Vestre Strandvej 29",
    "sg:city":"Tj\u00e6reborg",
    "sg:orig_category":"Bagere",
    "sg:phone":"+45 75 17 50 17",
    "sg:postcode":"6731",
    "sg:province":"Danmark",
    "wof:name":"Tj\u00e6reborg Bageri",
    "wof:placetype":"venue"
},
  "geometry": {"coordinates":[6.87629,62.460281],"type":"Point"}
}