{
  "type": "Feature",
  "properties": {
    "addr:full":"Fmd.: Bodil Pedersen, N\u00f8rb\u00f8llingvej 6, N\u00f8rb\u00f8lling Br\u00f8rup Danmark 6650",
    "addr:housenumber":"6",
    "addr:postcode":"6650",
    "addr:street":"Norbollingvej",
    "iso:country":"DK",
    "sg:address":"Fmd.: Bodil Pedersen, N\u00f8rb\u00f8llingvej 6, N\u00f8rb\u00f8lling",
    "sg:city":"Br\u00f8rup",
    "sg:orig_category":"Folkedans",
    "sg:phone":"+45 75 38 24 86",
    "sg:postcode":"6650",
    "sg:province":"Danmark",
    "wof:name":"Folkedans for B\u00f8rn og Unge",
    "wof:placetype":"venue"
},
  "geometry": {"coordinates":[-93.1630935669,32.8507347107],"type":"Point"}
}