{
  "type": "Feature",
  "properties": {
    "addr:full":"Bisholt Strandvej 3, Bisholt Horsens Danmark 8700",
    "addr:housenumber":"3",
    "addr:postcode":"8700",
    "addr:street":"Bisholt Strandvej;Bisholt",
    "iso:country":"DK",
    "sg:address":"Bisholt Strandvej 3, Bisholt",
    "sg:city":"Horsens",
    "sg:orig_category":"Hobbybetonede foreninger",
    "sg:phone":"+45 75 64 45 17",
    "sg:postcode":"8700",
    "sg:province":"Danmark",
    "wof:name":"EDR - Radioamat\u00f8rforening Hornsyld Afd.",
    "wof:placetype":"venue"
},
  "geometry": {"coordinates":[9.8432445526,55.8621063232],"type":"Point"}
}