{
  "type": "Feature",
  "properties": {
    "addr:full":"Smedevangen 2 Lynge Danmark 3540",
    "addr:housenumber":"2",
    "addr:postcode":"3540",
    "addr:street":"Smedevangen",
    "iso:country":"DK",
    "sg:address":"Smedevangen 2",
    "sg:city":"Lynge",
    "sg:orig_category":"Kopiering",
    "sg:phone":"+45 48 19 28 48",
    "sg:postcode":"3540",
    "sg:province":"Danmark",
    "sg:website":"www.tobemo.dk",
    "wof:name":"Tobemo Offset A/S",
    "wof:placetype":"venue"
},
  "geometry": {"coordinates":[12.3070955276,55.8302688599],"type":"Point"}
}