{
  "type": "Feature",
  "properties": {
    "addr:full":"H\u00f8rsvinget 1-3, Klovtofte Taastrup Danmark 2630",
    "addr:housenumber":"1-3",
    "addr:postcode":"2630",
    "addr:street":"Horsvinget",
    "iso:country":"DK",
    "sg:address":"H\u00f8rsvinget 1-3, Klovtofte",
    "sg:city":"Taastrup",
    "sg:classifiers":[
        {
            "category":"Utilities",
            "subcategory":"Refuse",
            "type":"Services"
        }
    ],
    "sg:phone":"+45 43 58 91 40",
    "sg:postcode":"2630",
    "sg:province":"Danmark",
    "sg:tags":[
        "catering"
    ],
    "wof:name":"BC Catering T\u00e5strup A/S",
    "wof:placetype":"venue"
},
  "geometry": {"coordinates":[12.3020896912,55.6506767273],"type":"Point"}
}