{
  "type": "Feature",
  "properties": {
    "addr:full":"Vester Voldgade 90 K\u00f8benhavn Danmark 1552",
    "addr:housenumber":"90;1552",
    "addr:street":"Vester Voldgade",
    "iso:country":"DK",
    "sg:address":"Vester Voldgade 90",
    "sg:city":"K\u00f8benhavn",
    "sg:orig_category":"Advokater",
    "sg:phone":"+45 33 15 15 63",
    "sg:postcode":"1552",
    "sg:province":"Danmark",
    "sg:website":"www.ret-raad.dk",
    "wof:name":"Berg, Thomas",
    "wof:placetype":"venue"
},
  "geometry": {"coordinates":[12.570400238,55.6759986877],"type":"Point"}
}