{
  "type": "Feature",
  "properties": {
    "addr:full":"Borgergade 94 Silkeborg Danmark 8600",
    "addr:housenumber":"94",
    "addr:postcode":"8600",
    "addr:street":"Borgergade",
    "iso:country":"DK",
    "sg:address":"Borgergade 94",
    "sg:city":"Silkeborg",
    "sg:orig_category":"Kirker",
    "sg:phone":"+45 86 81 25 52",
    "sg:postcode":"8600",
    "sg:province":"Danmark",
    "wof:name":"Pinsekirken",
    "wof:placetype":"venue"
},
  "geometry": {"coordinates":[9.5474634171,56.1823959351],"type":"Point"}
}