{
  "type": "Feature",
  "properties": {
    "addr:full":"Jegind\u00f8vej 21  Viborg Danmark 8800",
    "addr:housenumber":"21",
    "addr:postcode":"8800",
    "addr:street":"Jegindovej",
    "iso:country":"DK",
    "sg:address":"Jegind\u00f8vej 21 ",
    "sg:city":"Viborg",
    "sg:classifiers":[
        {
            "category":"Sports & Exercise",
            "subcategory":"Playing Field",
            "type":"Entertainment"
        }
    ],
    "sg:phone":"+45 89 28 18 00",
    "sg:postcode":"8800",
    "sg:province":"Danmark",
    "sg:tags":[
        "game"
    ],
    "wof:name":"VESTERGAARD APS",
    "wof:placetype":"venue"
},
  "geometry": {"coordinates":[9.358001709,56.4513282776],"type":"Point"}
}