{
  "type": "Feature",
  "properties": {
    "iso:country":"DK",
    "sg:address":"Vimmelskaftet 5",
    "sg:city":"Give",
    "sg:orig_category":"Ejendomshandel",
    "sg:phone":"+45 75 73 99 00",
    "sg:postcode":"7323",
    "sg:province":"Danmark",
    "sg:website":"www.danbolig.dk",
    "wof:name":"DanBolig - Give",
    "wof:placetype":"venue"
},
  "geometry": {"coordinates":[9.2378759384,55.8440284729],"type":"Point"}
}