{
  "type": "Feature",
  "properties": {
    "addr:full":"Rosenv\u00e6nget 23 H\u00f8ng Danmark 4270",
    "addr:housenumber":"23",
    "addr:postcode":"4270",
    "addr:street":"Rosenvaenget;Hong Danmark",
    "iso:country":"DK",
    "sg:address":"Rosenv\u00e6nget 23",
    "sg:city":"H\u00f8ng",
    "sg:orig_category":"Selskabslokaler",
    "sg:phone":"+45 58 85 32 11",
    "sg:postcode":"4270",
    "sg:province":"Danmark",
    "wof:name":"Rosenv\u00e6ngets Selskabslokaler",
    "wof:placetype":"venue"
},
  "geometry": {"coordinates":[11.299076,55.509811],"type":"Point"}
}