{
  "type": "Feature",
  "properties": {
    "addr:full":"Benediktevej 18 Fuglebjerg Danmark 4250",
    "addr:housenumber":"18",
    "addr:postcode":"4250",
    "addr:street":"Benediktevej",
    "iso:country":"DK",
    "sg:address":"Benediktevej 18",
    "sg:city":"Fuglebjerg",
    "sg:orig_category":"Malermestre",
    "sg:phone":"+45 55 45 32 03",
    "sg:postcode":"4250",
    "sg:province":"Danmark",
    "wof:name":"Andersen, J\u00f8rgen",
    "wof:placetype":"venue"
},
  "geometry": {"coordinates":[11.5485076904,55.3029823303],"type":"Point"}
}