{
  "type": "Feature",
  "properties": {
    "addr:full":"Store Torvegade 98 R\u00f8nne Danmark 3700",
    "addr:housenumber":"98",
    "addr:postcode":"3700",
    "addr:street":"Store Torvegade",
    "iso:country":"DK",
    "sg:address":"Store Torvegade 98",
    "sg:city":"R\u00f8nne",
    "sg:orig_category":"Mobiltelefoner",
    "sg:phone":"+45 56 95 85 15",
    "sg:postcode":"3700",
    "sg:province":"Danmark",
    "wof:name":"Telecenter Bornholm ApS",
    "wof:placetype":"venue"
},
  "geometry": {"coordinates":[14.6975498199,55.0993003845],"type":"Point"}
}