{
  "type": "Feature",
  "properties": {
    "iso:country":"DK",
    "sg:address":"Fmd.: J\u00f8rn Bergmann, Skellet 25",
    "sg:city":"Vordingborg",
    "sg:orig_category":"\u00c3\u2020ldreorganisationer og klubber",
    "sg:phone":"+45 55 34 51 44",
    "sg:postcode":"4760",
    "sg:province":"Danmark",
    "wof:name":"Seniorklub 97 VKS",
    "wof:placetype":"venue"
},
  "geometry": {"coordinates":[11.9124183655,55.0085449219],"type":"Point"}
}