{
  "type": "Feature",
  "properties": {
    "addr:full":"Godth\u00e5bsvej 30 Frederiksberg Danmark 2000",
    "addr:housenumber":"30",
    "addr:postcode":"2000",
    "addr:street":"Godthaabsvej",
    "iso:country":"DK",
    "sg:address":"Godth\u00e5bsvej 30",
    "sg:city":"Frederiksberg",
    "sg:orig_category":"Antikviteter",
    "sg:phone":"+45 38 87 18 02",
    "sg:postcode":"2000",
    "sg:province":"Danmark",
    "wof:name":"J\u00f8rgensen & S\u00f8n Antik",
    "wof:placetype":"venue"
},
  "geometry": {"coordinates":[12.5337724686,55.686580658],"type":"Point"}
}