{
  "type": "Feature",
  "properties": {
    "addr:full":"Gl. F\u00e6rgevej 9 Esbjerg Danmark 6700",
    "addr:housenumber":"9",
    "addr:postcode":"6700",
    "addr:street":"Faergevej",
    "iso:country":"DK",
    "sg:address":"Gl. F\u00e6rgevej 9",
    "sg:city":"Esbjerg",
    "sg:orig_category":"Malermestre",
    "sg:phone":"+45 75 13 08 86",
    "sg:postcode":"6700",
    "sg:province":"Danmark",
    "sg:website":"www.jennys.dk",
    "wof:name":"Jenny's Skilte & Malerfirma",
    "wof:placetype":"venue"
},
  "geometry": {"coordinates":[8.456905365,55.465221405],"type":"Point"}
}