{
  "type": "Feature",
  "properties": {
    "addr:full":"Fmd.: Gustav Christensen, Syrenvej 12 Aalestrup Danmark 9620",
    "addr:housenumber":"12",
    "addr:postcode":"9620",
    "addr:street":"Syrenvej",
    "iso:country":"DK",
    "sg:address":"Fmd.: Gustav Christensen, Syrenvej 12",
    "sg:city":"Aalestrup",
    "sg:orig_category":"\u00c3\u2020ldreorganisationer og klubber",
    "sg:phone":"+45 98 64 29 13",
    "sg:postcode":"9620",
    "sg:province":"Danmark",
    "wof:name":"\u00c6ldre Sagen M\u00f8ldrup-Aalestrup",
    "wof:placetype":"venue"
},
  "geometry": {"coordinates":[9.4901504517,56.6938285828],"type":"Point"}
}