{
  "type": "Feature",
  "properties": {
    "addr:full":"Monasvej 10 Liseleje Danmark 3360",
    "addr:housenumber":"10",
    "addr:postcode":"3360",
    "addr:street":"Monasvej",
    "iso:country":"DK",
    "sg:address":"Monasvej 10",
    "sg:city":"Liseleje",
    "sg:orig_category":"Glarmestre og glarmagere",
    "sg:phone":"+45 47 74 60 79",
    "sg:postcode":"3360",
    "sg:province":"Danmark",
    "wof:name":"Kristensen, H J",
    "wof:placetype":"venue"
},
  "geometry": {"coordinates":[11.9808988571,56.0058364868],"type":"Point"}
}