{
  "type": "Feature",
  "properties": {
    "addr:full":"Hovedgaden 11 Billund Danmark 7190",
    "addr:housenumber":"11",
    "addr:postcode":"7190",
    "addr:street":"Hovedgaden",
    "iso:country":"DK",
    "sg:address":"Hovedgaden 11",
    "sg:city":"Billund",
    "sg:classifiers":[
        {
            "category":"Banks & Credit Unions",
            "subcategory":"Bank",
            "type":"Services"
        }
    ],
    "sg:phone":"+45 75 33 14 44",
    "sg:postcode":"7190",
    "sg:province":"Danmark",
    "sg:tags":[
        "banker"
    ],
    "wof:name":"Sydbank",
    "wof:placetype":"venue"
},
  "geometry": {"coordinates":[9.1137609482,55.7310905457],"type":"Point"}
}