{
  "type": "Feature",
  "properties": {
    "addr:full":"Stabrandvej 4, Krarup Kolind Danmark 8560",
    "addr:housenumber":"4",
    "addr:postcode":"8560",
    "addr:street":"Stabrandvej",
    "iso:country":"DK",
    "sg:address":"Stabrandvej 4, Krarup",
    "sg:city":"Kolind",
    "sg:orig_category":"Underholdning",
    "sg:phone":"+45 86 39 22 11",
    "sg:postcode":"8560",
    "sg:province":"Danmark",
    "wof:name":"Kolman, Sanne",
    "wof:placetype":"venue"
},
  "geometry": {"coordinates":[10.5873975754,56.3618812561],"type":"Point"}
}