{
  "type": "Feature",
  "properties": {
    "addr:full":"Jellingvej 34 Vejle Danmark 7100",
    "addr:housenumber":"34",
    "addr:postcode":"7100",
    "addr:street":"Jellingvej",
    "iso:country":"DK",
    "sg:address":"Jellingvej 34",
    "sg:city":"Vejle",
    "sg:orig_category":"Dentallaboratorier",
    "sg:phone":"+45 75 82 67 53",
    "sg:postcode":"7100",
    "sg:province":"Danmark",
    "wof:name":"Rasmussens Dental Laboratorium, Vagn",
    "wof:placetype":"venue"
},
  "geometry": {"coordinates":[9.5224323273,55.7202339172],"type":"Point"}
}