{
  "type": "Feature",
  "properties": {
    "addr:full":"Darumvej 115 Esbjerg Danmark 6700",
    "addr:housenumber":"115",
    "addr:postcode":"6700",
    "addr:street":"Darumvej",
    "iso:country":"DK",
    "sg:address":"Darumvej 115",
    "sg:city":"Esbjerg",
    "sg:orig_category":"Autoreparation og -service",
    "sg:phone":"+45 75 12 92 95",
    "sg:postcode":"6700",
    "sg:province":"Danmark",
    "wof:name":"Clemmensen's Autov\u00e6rksted, B\u00f8rge",
    "wof:placetype":"venue"
},
  "geometry": {"coordinates":[8.4863471985,55.4642601013],"type":"Point"}
}