{
  "type": "Feature",
  "properties": {
    "addr:full":"\u00d8rstedsvej 1 Hinnerup Danmark 8382",
    "addr:housenumber":"1",
    "addr:postcode":"8382",
    "addr:street":"Orstedsvej",
    "iso:country":"DK",
    "sg:address":"\u00d8rstedsvej 1",
    "sg:city":"Hinnerup",
    "sg:orig_category":"Bogtrykkerier",
    "sg:phone":"+45 86 98 56 66",
    "sg:postcode":"8382",
    "sg:province":"Danmark",
    "wof:name":"Hinnerup Bogtrykkeri ApS",
    "wof:placetype":"venue"
},
  "geometry": {"coordinates":[10.0594921112,56.2615242004],"type":"Point"}
}