{
  "type": "Feature",
  "properties": {
    "addr:full":"Stationsvej 21 Beder Danmark 8330",
    "addr:housenumber":"21",
    "addr:postcode":"8330",
    "addr:street":"Stationsvej",
    "iso:country":"DK",
    "sg:address":"Stationsvej 21",
    "sg:city":"Beder",
    "sg:orig_category":"Autoforhandlere",
    "sg:phone":"+45 86 93 63 99",
    "sg:postcode":"8330",
    "sg:province":"Danmark",
    "wof:name":"Pauls Automobiler, Klaus",
    "wof:placetype":"venue"
},
  "geometry": {"coordinates":[10.1988449097,56.056312561],"type":"Point"}
}