{
  "type": "Feature",
  "properties": {
    "addr:full":"Sj\u00e6llandsgade 38 Aalborg Danmark 9000",
    "addr:housenumber":"38",
    "addr:postcode":"9000",
    "addr:street":"Sjaellandsgade",
    "iso:country":"DK",
    "sg:address":"Sj\u00e6llandsgade 38",
    "sg:city":"Aalborg",
    "sg:orig_category":"Materialister",
    "sg:phone":"+45 98 12 26 65",
    "sg:postcode":"9000",
    "sg:province":"Danmark",
    "wof:name":"Matas",
    "wof:placetype":"venue"
},
  "geometry": {"coordinates":[9.9389810562,57.0412063599],"type":"Point"}
}