{
  "type": "Feature",
  "properties": {
    "addr:full":"v/ Niels J\u00f8rgen Hinrichsen, Dolmervej 24, Voldby Grenaa Danmark 8500",
    "addr:housenumber":"24",
    "addr:postcode":"8500",
    "addr:street":"Dolmervej;Voldby",
    "iso:country":"DK",
    "sg:address":"v/ Niels J\u00f8rgen Hinrichsen, Dolmervej 24, Voldby",
    "sg:city":"Grenaa",
    "sg:orig_category":"Faglige organisationer og foreninger",
    "sg:phone":"+45 86 33 24 75",
    "sg:postcode":"8500",
    "sg:province":"Danmark",
    "wof:name":"\u00d8stdjurs Familielandbrug",
    "wof:placetype":"venue"
},
  "geometry": {"coordinates":[10.8774929047,56.4126853943],"type":"Point"}
}