{
  "type": "Feature",
  "properties": {
    "addr:full":"Munkerup Strandvej 43 B Dronningm\u00f8lle Danmark 3120",
    "addr:housenumber":"43 b",
    "addr:postcode":"3120",
    "addr:street":"Munkerup Strandvej",
    "iso:country":"DK",
    "sg:address":"Munkerup Strandvej 43 B",
    "sg:city":"Dronningm\u00f8lle",
    "sg:orig_category":"Rejsebureauer",
    "sg:phone":"+45 49 71 72 42",
    "sg:postcode":"3120",
    "sg:province":"Danmark",
    "wof:name":"Karin's Turistrejser",
    "wof:placetype":"venue"
},
  "geometry": {"coordinates":[12.3698043823,56.1049613953],"type":"Point"}
}