{
  "type": "Feature",
  "properties": {
    "addr:full":"Algade 65 - 67 Vordingborg Danmark 4760",
    "addr:housenumber":"65 67",
    "addr:postcode":"4760",
    "addr:street":"Algade",
    "iso:country":"DK",
    "sg:address":"Algade 65 - 67",
    "sg:city":"Vordingborg",
    "sg:orig_category":"Sko",
    "sg:phone":"+45 55 37 01 69",
    "sg:postcode":"4760",
    "sg:province":"Danmark",
    "sg:website":"www.skonyt.dk",
    "wof:name":"Skot\u00f8jsMessen",
    "wof:placetype":"venue"
},
  "geometry": {"coordinates":[11.9070005417,55.0101394653],"type":"Point"}
}