{
  "type": "Feature",
  "properties": {
    "iso:country":"DK",
    "sg:address":"Vestre Lufthavnsvej 28",
    "sg:city":"Esbjerg \u00d8",
    "sg:orig_category":"Stutterier",
    "sg:phone":"+45 75 16 07 02",
    "sg:postcode":"6705",
    "sg:province":"Danmark",
    "wof:name":"Oksvanggaard Stutteri og Hestepension",
    "wof:placetype":"venue"
},
  "geometry": {"coordinates":[8.51496315,55.518081665],"type":"Point"}
}