{
  "type": "Feature",
  "properties": {
    "addr:full":"Sommerbuen 8 Ballerup Danmark 2750",
    "addr:housenumber":"8",
    "addr:postcode":"2750",
    "addr:street":"Sommerbuen",
    "iso:country":"DK",
    "sg:address":"Sommerbuen 8",
    "sg:city":"Ballerup",
    "sg:orig_category":"Murermestre",
    "sg:phone":"+45 44 65 80 11",
    "sg:postcode":"2750",
    "sg:province":"Danmark",
    "wof:name":"Christensen, J.C.",
    "wof:placetype":"venue"
},
  "geometry": {"coordinates":[12.3520317078,55.7152900696],"type":"Point"}
}