{
  "type": "Feature",
  "properties": {
    "addr:full":"Dosseringen 8 A Kerteminde Danmark 5300",
    "addr:housenumber":"8 a",
    "addr:postcode":"5300",
    "addr:street":"Dosseringen",
    "iso:country":"DK",
    "sg:address":"Dosseringen 8 A",
    "sg:city":"Kerteminde",
    "sg:classifiers":[
        {
            "category":"Restaurant",
            "type":"Food & Drink"
        }
    ],
    "sg:phone":"+45 65 32 34 30",
    "sg:postcode":"5300",
    "sg:province":"Danmark",
    "wof:name":"Varmestuen, Restaurant",
    "wof:placetype":"venue"
},
  "geometry": {"coordinates":[10.6596927643,55.4480667114],"type":"Point"}
}