{
  "type": "Feature",
  "properties": {
    "iso:country":"DK",
    "sg:address":"Sct. Olai Plads 2",
    "sg:city":"Hj\u00f8rring",
    "sg:classifiers":[
        {
            "category":"Banks & Credit Unions",
            "subcategory":"Bank",
            "type":"Services"
        }
    ],
    "sg:phone":"+45 98 92 92 77",
    "sg:postcode":"9800",
    "sg:province":"Danmark",
    "sg:tags":[
        "banker"
    ],
    "sg:website":"www.al-bank.dk",
    "wof:name":"Arbejdernes Landsbank",
    "wof:placetype":"venue"
},
  "geometry": {"coordinates":[-99.10262299999999,19.337889],"type":"Point"}
}