{
  "type": "Feature",
  "properties": {
    "addr:full":"City-Vest, Gudrunsvej 7 Brabrand Danmark 8220",
    "addr:housenumber":"7",
    "addr:postcode":"8220",
    "addr:street":"Gudrunsvej",
    "iso:country":"DK",
    "sg:address":"City-Vest, Gudrunsvej 7",
    "sg:city":"Brabrand",
    "sg:classifiers":[
        {
            "category":"Communications",
            "type":"Services"
        }
    ],
    "sg:phone":"+45 86 25 40 66",
    "sg:postcode":"8220",
    "sg:province":"Danmark",
    "sg:tags":[
        "og",
        "tv",
        "radio"
    ],
    "wof:name":"D:E:R",
    "wof:placetype":"venue"
},
  "geometry": {"coordinates":[10.1293649673,56.1601295471],"type":"Point"}
}