{
  "type": "Feature",
  "properties": {
    "iso:country":"DK",
    "sg:address":"Gr\u00f8ndalsvej 65",
    "sg:city":"Viby",
    "sg:orig_category":"Behandlingshjem",
    "sg:phone":"+45 86 28 16 66",
    "sg:postcode":"8260",
    "sg:province":"Danmark",
    "wof:name":"B\u00f8gholt Behandlingshjem",
    "wof:placetype":"venue"
},
  "geometry": {"coordinates":[10.135024,56.120239],"type":"Point"}
}