{
  "type": "Feature",
  "properties": {
    "iso:country":"DK",
    "sg:address":"Sydbanegade 9 - 11",
    "sg:city":"Kolding",
    "sg:orig_category":"Servicestationer",
    "sg:phone":"+45 75 52 24 17",
    "sg:postcode":"6000",
    "sg:province":"Danmark",
    "wof:name":"Shell Service",
    "wof:placetype":"venue"
},
  "geometry": {"coordinates":[9.4756793976,55.4863777161],"type":"Point"}
}