{
  "type": "Feature",
  "properties": {
    "addr:full":"Fmd.: Bjarne Jensen, Drogdensgade 11 K\u00f8benhavn S Danmark 2300",
    "addr:housenumber":"11",
    "addr:postcode":"2300",
    "addr:street":"Drogdensgade;S Danmark",
    "iso:country":"DK",
    "sg:address":"Fmd.: Bjarne Jensen, Drogdensgade 11",
    "sg:city":"K\u00f8benhavn S",
    "sg:orig_category":"Hobbybetonede foreninger",
    "sg:phone":"+45 32 59 79 04",
    "sg:postcode":"2300",
    "sg:province":"Danmark",
    "sg:website":"www.hjem.get2net.dk/oz2tg/edr_amager",
    "wof:name":"Eksperimenterende danske Radioamat\u00f8rer, EDR",
    "wof:placetype":"venue"
},
  "geometry": {"coordinates":[-78.1299133301,36.7267417908],"type":"Point"}
}