{
  "type": "Feature",
  "properties": {
    "iso:country":"DK",
    "sg:address":"\u00c5bovej 35",
    "sg:city":"Bylderup-Bov",
    "sg:classifiers":[
        {
            "category":"Taxi",
            "type":"Transportation"
        }
    ],
    "sg:phone":"+45 74 76 23 34",
    "sg:postcode":"6372",
    "sg:province":"Danmark",
    "wof:name":"Luddes Taxi & Mini Busser",
    "wof:placetype":"venue"
},
  "geometry": {"coordinates":[9.0886011124,54.9415626526],"type":"Point"}
}