{
  "type": "Feature",
  "properties": {
    "addr:full":"Fritidskrogen, Smedeparken 1 Sor\u00f8 Danmark 4180",
    "addr:housenumber":"1",
    "addr:postcode":"4180",
    "addr:street":"Smedeparken",
    "iso:country":"DK",
    "sg:address":"Fritidskrogen, Smedeparken 1",
    "sg:city":"Sor\u00f8",
    "sg:orig_category":"Skolefritidsordninger",
    "sg:phone":"+45 57 83 16 11",
    "sg:postcode":"4180",
    "sg:province":"Danmark",
    "wof:name":"Frederiksberg skolefritidsordning",
    "wof:placetype":"venue"
},
  "geometry": {"coordinates":[-102.94467926030001,45.4534721375],"type":"Point"}
}