{
  "type": "Feature",
  "properties": {
    "addr:full":"Oddesundvej 249 Hurup Danmark 7760",
    "addr:housenumber":"249",
    "addr:postcode":"7760",
    "addr:street":"Oddesundvej",
    "iso:country":"DK",
    "sg:address":"Oddesundvej 249",
    "sg:city":"Hurup",
    "sg:orig_category":"Plejehjem",
    "sg:phone":"+45 97 95 64 44",
    "sg:postcode":"7760",
    "sg:province":"Danmark",
    "wof:name":"Sct. Mortensgaard OMR\u00c5DE 1",
    "wof:placetype":"venue"
},
  "geometry": {"coordinates":[8.4134998322,56.7095756531],"type":"Point"}
}