{
  "type": "Feature",
  "properties": {
    "addr:full":"Agersigen 18 A, Vester\u00f8 Havn L\u00e6s\u00f8 Danmark 9940",
    "addr:housenumber":"18 a",
    "addr:postcode":"9940",
    "addr:street":"Agersigen;Vestero Havn;Danmark",
    "iso:country":"DK",
    "sg:address":"Agersigen 18 A, Vester\u00f8 Havn",
    "sg:city":"L\u00e6s\u00f8",
    "sg:orig_category":"Campingpladser",
    "sg:phone":"+45 98 49 94 95",
    "sg:postcode":"9940",
    "sg:province":"Danmark",
    "wof:name":"L\u00e6s\u00f8 Camping & Hytteby",
    "wof:placetype":"venue"
},
  "geometry": {"coordinates":[-82.57545471189999,38.4224014282],"type":"Point"}
}