{
  "type": "Feature",
  "properties": {
    "addr:full":"Stenstrupvej 16, Stenstrup Hobro Danmark 9500",
    "addr:housenumber":"16",
    "addr:postcode":"9500",
    "addr:street":"Stenstrupvej",
    "iso:country":"DK",
    "sg:address":"Stenstrupvej 16, Stenstrup",
    "sg:city":"Hobro",
    "sg:orig_category":"Autolakering",
    "sg:phone":"+45 98 56 61 02",
    "sg:postcode":"9500",
    "sg:province":"Danmark",
    "wof:name":"Korsholm Autolak",
    "wof:placetype":"venue"
},
  "geometry": {"coordinates":[9.7946596146,56.6382789612],"type":"Point"}
}