{
  "type": "Feature",
  "properties": {
    "addr:full":"Entrepren\u00f8rvej 1 A Fredericia Danmark 7000",
    "addr:housenumber":"1 a",
    "addr:postcode":"7000",
    "addr:street":"Entreprenorvej",
    "iso:country":"DK",
    "sg:address":"Entrepren\u00f8rvej 1 A",
    "sg:city":"Fredericia",
    "sg:orig_category":"Autoreparation og -service",
    "sg:phone":"+45 75 93 20 11",
    "sg:postcode":"7000",
    "sg:province":"Danmark",
    "wof:name":"Nordbyens Auto",
    "wof:placetype":"venue"
},
  "geometry": {"coordinates":[9.7623090744,55.5899543762],"type":"Point"}
}