{
  "type": "Feature",
  "properties": {
    "addr:full":"R\u00f8llikevej 5 Vodskov Danmark 9310",
    "addr:housenumber":"5",
    "addr:postcode":"9310",
    "addr:street":"Rollikevej",
    "iso:country":"DK",
    "sg:address":"R\u00f8llikevej 5",
    "sg:city":"Vodskov",
    "sg:orig_category":"Murermestre",
    "sg:phone":"+45 98 29 38 31",
    "sg:postcode":"9310",
    "sg:province":"Danmark",
    "wof:name":"Jensen, Per",
    "wof:placetype":"venue"
},
  "geometry": {"coordinates":[10.0266752243,57.1023864746],"type":"Point"}
}