{
  "type": "Feature",
  "properties": {
    "iso:country":"DK",
    "sg:address":"Vester Torv 8, Esperg\u00e6rde Centret",
    "sg:city":"Esperg\u00e6rde",
    "sg:orig_category":"Bagere",
    "sg:phone":"+45 49 17 05 33",
    "sg:postcode":"3060",
    "sg:province":"Danmark",
    "wof:name":"Bisgaard's Bageri",
    "wof:placetype":"venue"
},
  "geometry": {"coordinates":[11.65124,47.839062],"type":"Point"}
}