{
  "type": "Feature",
  "properties": {
    "iso:country":"DK",
    "sg:address":"\u00d8stergade 27",
    "sg:city":"Lemvig",
    "sg:classifiers":[
        {
            "category":"Home & Garden",
            "subcategory":"Home Furnishings",
            "type":"Retail Goods"
        }
    ],
    "sg:phone":"+45 97 82 06 24",
    "sg:postcode":"7620",
    "sg:province":"Danmark",
    "sg:tags":[
        "gardiner"
    ],
    "wof:name":"Garant - Sadolin Farveland",
    "wof:placetype":"venue"
},
  "geometry": {"coordinates":[8.3136529922,56.5504074097],"type":"Point"}
}