{
  "type": "Feature",
  "properties": {
    "addr:full":"Aved\u00f8reholmen 74 Hvidovre Danmark 2650",
    "addr:housenumber":"74",
    "addr:postcode":"2650",
    "addr:street":"Avedoreholmen",
    "iso:country":"DK",
    "sg:address":"Aved\u00f8reholmen 74",
    "sg:city":"Hvidovre",
    "sg:orig_category":"Lastvogne",
    "sg:phone":"+45 40 34 70 08",
    "sg:postcode":"2650",
    "sg:province":"Danmark",
    "wof:name":"Renault Lastbiler Danmark A/S",
    "wof:placetype":"venue"
},
  "geometry": {"coordinates":[12.4684743881,55.6114997864],"type":"Point"}
}