{
  "type": "Feature",
  "properties": {
    "addr:full":"Toldbodgade 40  Randers Danmark 8900",
    "addr:housenumber":"40",
    "addr:postcode":"8900",
    "addr:street":"Toldbodgade",
    "iso:country":"DK",
    "sg:address":"Toldbodgade 40 ",
    "sg:city":"Randers",
    "sg:classifiers":[
        {
            "category":"Manufacturing",
            "subcategory":"Lumber",
            "type":"Manufacturing & Wholesale Goods"
        }
    ],
    "sg:phone":"+45 86 41 44 44",
    "sg:postcode":"8900",
    "sg:province":"Danmark",
    "sg:tags":[
        "wood"
    ],
    "wof:name":"BYGMA HOLDGAARD OG AAQUIST A/S",
    "wof:placetype":"venue"
},
  "geometry": {"coordinates":[10.063627243,56.4663505554],"type":"Point"}
}