{
  "type": "Feature",
  "properties": {
    "addr:full":"H\u00f8jg\u00e5rdvej 20 Vejle Danmark 7100",
    "addr:housenumber":"20",
    "addr:postcode":"7100",
    "addr:street":"Hojgaardvej",
    "iso:country":"DK",
    "sg:address":"H\u00f8jg\u00e5rdvej 20",
    "sg:city":"Vejle",
    "sg:orig_category":"Musikere",
    "sg:phone":"+45 75 85 32 25",
    "sg:postcode":"7100",
    "sg:province":"Danmark",
    "wof:name":"NK Musik",
    "wof:placetype":"venue"
},
  "geometry": {"coordinates":[9.5368051529,55.7113952637],"type":"Point"}
}