{
  "type": "Feature",
  "properties": {
    "addr:full":"Krog\u00e5rdsvej 18 Greve Danmark 2670",
    "addr:housenumber":"18",
    "addr:postcode":"2670",
    "addr:street":"Krogaardsvej",
    "iso:country":"DK",
    "sg:address":"Krog\u00e5rdsvej 18",
    "sg:city":"Greve",
    "sg:orig_category":"Malermestre",
    "sg:phone":"+45 43 90 86 99",
    "sg:postcode":"2670",
    "sg:province":"Danmark",
    "wof:name":"Mogensen, Carlo",
    "wof:placetype":"venue"
},
  "geometry": {"coordinates":[12.3364019394,55.592918396],"type":"Point"}
}