{
  "type": "Feature",
  "properties": {
    "addr:full":"Skovvejen 35 Vejle Danmark 7100",
    "addr:housenumber":"35",
    "addr:postcode":"7100",
    "addr:street":"Skovvejen",
    "iso:country":"DK",
    "sg:address":"Skovvejen 35",
    "sg:city":"Vejle",
    "sg:orig_category":"Fugning",
    "sg:phone":"+45 75 82 87 93",
    "sg:postcode":"7100",
    "sg:province":"Danmark",
    "wof:name":"Nielsen, Alex",
    "wof:placetype":"venue"
},
  "geometry": {"coordinates":[9.5323896408,55.7207565308],"type":"Point"}
}