{
  "type": "Feature",
  "properties": {
    "addr:full":"Fmd.: Carsten Trinderup Pedersen, Trangb\u00e6kvej 6 Skals Danmark 8832",
    "addr:housenumber":"6",
    "addr:postcode":"8832",
    "addr:street":"Trangbaekvej",
    "iso:country":"DK",
    "sg:address":"Fmd.: Carsten Trinderup Pedersen, Trangb\u00e6kvej 6",
    "sg:city":"Skals",
    "sg:orig_category":"Grundejerforeninger",
    "sg:phone":"+45 86 69 50 72",
    "sg:postcode":"8832",
    "sg:province":"Danmark",
    "wof:name":"Grundejerforeningen Trangb\u00e6kvej",
    "wof:placetype":"venue"
},
  "geometry": {"coordinates":[9.4030599594,56.5558166504],"type":"Point"}
}