{
  "type": "Feature",
  "properties": {
    "iso:country":"DK",
    "sg:address":"Skodsborgvej 190",
    "sg:city":"N\u00e6rum",
    "sg:orig_category":"Hestetransport",
    "sg:phone":"+45 40 28 30 81",
    "sg:postcode":"2850",
    "sg:province":"Danmark",
    "sg:website":"www.hestetransporten.subnet.dk",
    "wof:name":"Hestetransporten",
    "wof:placetype":"venue"
},
  "geometry": {"coordinates":[-89.99810791020001,38.1321372986],"type":"Point"}
}