{
  "type": "Feature",
  "properties": {
    "addr:full":"Islevdalvej 138  R\u00f8dovre Danmark 2610",
    "addr:housenumber":"138",
    "addr:postcode":"2610",
    "addr:street":"Islevdalvej",
    "iso:country":"DK",
    "sg:address":"Islevdalvej 138 ",
    "sg:city":"R\u00f8dovre",
    "sg:classifiers":[
        {
            "category":"Professional",
            "subcategory":"Engineering",
            "type":"Services"
        }
    ],
    "sg:phone":"+45 44 94 33 79",
    "sg:postcode":"2610",
    "sg:province":"Danmark",
    "sg:tags":[
        "machine",
        "-",
        "mechanical"
    ],
    "wof:name":"BR\u00dcSCH MASKINFABRIK A/S",
    "wof:placetype":"venue"
},
  "geometry": {"coordinates":[10.6992139816,61.1027755737],"type":"Point"}
}