{
  "type": "Feature",
  "properties": {
    "addr:full":"v/ Peder Birkeb\u00e6k, Skibbildvej 25, Haunstrup Herning Danmark 7400",
    "addr:housenumber":"25",
    "addr:postcode":"7400",
    "addr:street":"Skibbildvej;Haunstrup",
    "iso:country":"DK",
    "sg:address":"v/ Peder Birkeb\u00e6k, Skibbildvej 25, Haunstrup",
    "sg:city":"Herning",
    "sg:orig_category":"Oplysningsforbund",
    "sg:phone":"+45 97 16 12 23",
    "sg:postcode":"7400",
    "sg:province":"Danmark",
    "wof:name":"Liberalt Oplysnings Forbund",
    "wof:placetype":"venue"
},
  "geometry": {"coordinates":[8.9768896103,56.1374168396],"type":"Point"}
}