{
  "type": "Feature",
  "properties": {
    "iso:country":"DK",
    "sg:address":"Algade 7",
    "sg:city":"Aalborg",
    "sg:orig_category":"Chokolade",
    "sg:phone":"+45 98 12 07 40",
    "sg:postcode":"9000",
    "sg:province":"Danmark",
    "wof:name":"Frellsen Konfekture, I. M.",
    "wof:placetype":"venue"
},
  "geometry": {"coordinates":[9.9226932526,57.0468940735],"type":"Point"}
}