{
  "type": "Feature",
  "properties": {
    "addr:full":"Kristensmindevej 2 Fuglebjerg Danmark 4250",
    "addr:housenumber":"2",
    "addr:postcode":"4250",
    "addr:street":"Kristensmindevej",
    "iso:country":"DK",
    "sg:address":"Kristensmindevej 2",
    "sg:city":"Fuglebjerg",
    "sg:orig_category":"El-forsyning",
    "sg:phone":"+45 54 45 40 11",
    "sg:postcode":"4250",
    "sg:province":"Danmark",
    "wof:name":"SEAS A/S",
    "wof:placetype":"venue"
},
  "geometry": {"coordinates":[11.5360212326,55.3058929443],"type":"Point"}
}