{
  "type": "Feature",
  "properties": {
    "addr:full":"Fmd.: Tove M. Sand, Hermodsvej 14 Spentrup Danmark 8981",
    "addr:housenumber":"14",
    "addr:postcode":"8981",
    "addr:street":"Tove M. Sand Hermodsvej",
    "iso:country":"DK",
    "sg:address":"Fmd.: Tove M. Sand, Hermodsvej 14",
    "sg:city":"Spentrup",
    "sg:orig_category":"Husflidsforeninger",
    "sg:phone":"+45 86 47 78 28",
    "sg:postcode":"8981",
    "sg:province":"Danmark",
    "wof:name":"Spentrup Husmoderforening",
    "wof:placetype":"venue"
},
  "geometry": {"coordinates":[10.0408000946,56.5371284485],"type":"Point"}
}