{
  "type": "Feature",
  "properties": {
    "iso:country":"DK",
    "sg:address":"Gammel K\u00f8ge Landevej 236 A",
    "sg:city":"Hvidovre",
    "sg:orig_category":"Bodegaer",
    "sg:phone":"+45 36 78 82 97",
    "sg:postcode":"2650",
    "sg:province":"Danmark",
    "wof:name":"La Strada Bodega",
    "wof:placetype":"venue"
},
  "geometry": {"coordinates":[12.4974508286,55.6393508911],"type":"Point"}
}