{
  "type": "Feature",
  "properties": {
    "addr:full":"Kirkegade 12 Aulum Danmark 7490",
    "addr:housenumber":"12",
    "addr:postcode":"7490",
    "addr:street":"Kirkegade",
    "iso:country":"DK",
    "sg:address":"Kirkegade 12",
    "sg:city":"Aulum",
    "sg:orig_category":"Bodegaer",
    "sg:phone":"+45 97 47 34 29",
    "sg:postcode":"7490",
    "sg:province":"Danmark",
    "wof:name":"Hammeren",
    "wof:placetype":"venue"
},
  "geometry": {"coordinates":[8.7978591919,56.2666511536],"type":"Point"}
}