{
  "type": "Feature",
  "properties": {
    "addr:full":"Einarsvej 12 Kongens Lyngby Danmark 2800",
    "addr:housenumber":"12",
    "addr:postcode":"2800",
    "addr:street":"Einarsvej",
    "iso:country":"DK",
    "sg:address":"Einarsvej 12",
    "sg:city":"Kongens Lyngby",
    "sg:orig_category":"Begravelsesforretninger",
    "sg:phone":"+45 44 98 89 06",
    "sg:postcode":"2800",
    "sg:province":"Danmark",
    "wof:name":"Anno 1977 Stengaard - Bagsv\u00e6rd Begravelses - og Ligkistemagasin",
    "wof:placetype":"venue"
},
  "geometry": {"coordinates":[12.4736614227,55.763217926],"type":"Point"}
}