{
  "type": "Feature",
  "properties": {
    "addr:full":"Chr. W\u00e6rums Gade 4 \u00c5rhus C Danmark 8000",
    "addr:housenumber":"4",
    "addr:postcode":"8000",
    "addr:street":"Waerums Gade",
    "iso:country":"DK",
    "sg:address":"Chr. W\u00e6rums Gade 4",
    "sg:city":"\u00c5rhus C",
    "sg:classifiers":[
        {
            "category":"Professional",
            "subcategory":"Computer Services",
            "type":"Services"
        }
    ],
    "sg:phone":"+45 86 19 09 66",
    "sg:postcode":"8000",
    "sg:province":"Danmark",
    "sg:tags":[
        "edb",
        "-",
        "software"
    ],
    "wof:name":"Webdesigners",
    "wof:placetype":"venue"
},
  "geometry": {"coordinates":[1.7223600149,46.8559417725],"type":"Point"}
}