{
  "type": "Feature",
  "properties": {
    "addr:full":"Vejlevej 334, Bramdrupdam Kolding Danmark 6000",
    "addr:housenumber":"334",
    "addr:postcode":"6000",
    "addr:street":"Vejlevej;Bramdrupdam",
    "iso:country":"DK",
    "sg:address":"Vejlevej 334, Bramdrupdam",
    "sg:city":"Kolding",
    "sg:orig_category":"Ejendomshandel",
    "sg:phone":"+45 75 56 99 00",
    "sg:postcode":"6000",
    "sg:province":"Danmark",
    "wof:name":"Nybolig - Kolding Nord",
    "wof:placetype":"venue"
},
  "geometry": {"coordinates":[9.4733953476,55.4863586426],"type":"Point"}
}