{
  "type": "Feature",
  "properties": {
    "addr:full":"Sn\u00e6rildvej 80 Odder Danmark 8300",
    "addr:housenumber":"80",
    "addr:postcode":"8300",
    "addr:street":"Snaerildvej",
    "iso:country":"DK",
    "sg:address":"Sn\u00e6rildvej 80",
    "sg:city":"Odder",
    "sg:orig_category":"Arkitekter",
    "sg:phone":"+45 86 54 07 67",
    "sg:postcode":"8300",
    "sg:province":"Danmark",
    "wof:name":"S\u00f8rensen, Ren\u00e9",
    "wof:placetype":"venue"
},
  "geometry": {"coordinates":[10.1275815964,55.9727554321],"type":"Point"}
}