{
  "type": "Feature",
  "properties": {
    "addr:full":"Hallenslevvej 5 H\u00f8ng Danmark 4270",
    "addr:housenumber":"5",
    "addr:postcode":"4270",
    "addr:street":"Hallenslevvej;Hong Danmark",
    "iso:country":"DK",
    "sg:address":"Hallenslevvej 5",
    "sg:city":"H\u00f8ng",
    "sg:orig_category":"INGENI\u00c3\u02dcRER",
    "sg:phone":"+45 58 85 31 54",
    "sg:postcode":"4270",
    "sg:province":"Danmark",
    "sg:website":"www.kkp-adviser.dk",
    "wof:name":"KKP Adviser Handels- og Ingeni\u00f8rr\u00e5dgivning A/S",
    "wof:placetype":"venue"
},
  "geometry": {"coordinates":[11.282160759,55.5191726685],"type":"Point"}
}