{
  "type": "Feature",
  "properties": {
    "addr:full":"Foldg\u00e5rdsvej 17, Vester Nebel Esbjerg N Danmark 6715",
    "addr:housenumber":"17",
    "addr:postcode":"6715",
    "addr:street":"Foldgaardsvej;Vester Nebel",
    "iso:country":"DK",
    "sg:address":"Foldg\u00e5rdsvej 17, Vester Nebel",
    "sg:city":"Esbjerg N",
    "sg:orig_category":"Tekstiltrykkerier",
    "sg:phone":"+45 75 16 90 22",
    "sg:postcode":"6715",
    "sg:province":"Danmark",
    "wof:name":"Alko Print",
    "wof:placetype":"venue"
},
  "geometry": {"coordinates":[8.4780550003,55.535610199],"type":"Point"}
}