{
  "type": "Feature",
  "properties": {
    "addr:full":"Klardam 27 Hvidovre Danmark 2650",
    "addr:housenumber":"27",
    "addr:postcode":"2650",
    "addr:street":"Klardam",
    "iso:country":"DK",
    "sg:address":"Klardam 27",
    "sg:city":"Hvidovre",
    "sg:orig_category":"Snedkermestre",
    "sg:phone":"+45 36 75 41 57",
    "sg:postcode":"2650",
    "sg:province":"Danmark",
    "wof:name":"Lund, Flemming",
    "wof:placetype":"venue"
},
  "geometry": {"coordinates":[12.4669294357,55.6514167786],"type":"Point"}
}