{
  "type": "Feature",
  "properties": {
    "addr:full":"Sognepr\u00e6st: J\u00f8rgen Kj\u00e6rgaard (K/B), Pr\u00e6steg\u00e5rdsvej 8, Tygstrup Vestervig Danmark 7770",
    "addr:housenumber":"8",
    "addr:postcode":"7770",
    "addr:street":"Praestegaardsvej",
    "iso:country":"DK",
    "sg:address":"Sognepr\u00e6st: J\u00f8rgen Kj\u00e6rgaard (K/B), Pr\u00e6steg\u00e5rdsvej 8, Tygstrup",
    "sg:city":"Vestervig",
    "sg:orig_category":"Kirkesogne",
    "sg:phone":"+45 97 94 11 12",
    "sg:postcode":"7770",
    "sg:province":"Danmark",
    "wof:name":"Vestervig og Agger Sogne",
    "wof:placetype":"venue"
},
  "geometry": {"coordinates":[8.2376403809,56.7811546326],"type":"Point"}
}