{
  "type": "Feature",
  "properties": {
    "addr:full":"Guldalderen 6, Fl\u00f8ng Hedehusene Danmark 2640",
    "addr:housenumber":"6",
    "addr:postcode":"2640",
    "addr:street":"Guldalderen;Flong",
    "iso:country":"DK",
    "sg:address":"Guldalderen 6, Fl\u00f8ng",
    "sg:city":"Hedehusene",
    "sg:orig_category":"Flytteforretninger",
    "sg:phone":"+45 46 59 30 30",
    "sg:postcode":"2640",
    "sg:province":"Danmark",
    "sg:website":"www.wht.dk",
    "wof:name":"WHT-Spedition A/S",
    "wof:placetype":"venue"
},
  "geometry": {"coordinates":[12.1993551254,55.6496009827],"type":"Point"}
}