{
  "type": "Feature",
  "properties": {
    "addr:full":"Kontaktpers.: Finn Mikkelsen, Elg\u00e5rdsminde 43 Hadsten Danmark 8370",
    "addr:housenumber":"43",
    "addr:postcode":"8370",
    "addr:street":"Elgaardsminde",
    "iso:country":"DK",
    "sg:address":"Kontaktpers.: Finn Mikkelsen, Elg\u00e5rdsminde 43",
    "sg:city":"Hadsten",
    "sg:orig_category":"Politiske foreninger, \u00c3\u02dcvrige",
    "sg:phone":"+45 86 98 13 75",
    "sg:postcode":"8370",
    "sg:province":"Danmark",
    "wof:name":"Folkebev\u00e6gelsen mod EU - Hadsten",
    "wof:placetype":"venue"
},
  "geometry": {"coordinates":[10.047659874,56.3287239075],"type":"Point"}
}