{
  "type": "Feature",
  "properties": {
    "addr:full":"Havnen 24 Nyk\u00f8bing Danmark 7900",
    "addr:housenumber":"24",
    "addr:postcode":"7900",
    "addr:street":"Havnen",
    "iso:country":"DK",
    "sg:address":"Havnen 24",
    "sg:city":"Nyk\u00f8bing",
    "sg:orig_category":"Faglige organisationer og foreninger",
    "sg:phone":"+45 97 72 09 77",
    "sg:postcode":"7900",
    "sg:province":"Danmark",
    "wof:name":"Kvindeligt Arbejderforbund",
    "wof:placetype":"venue"
},
  "geometry": {"coordinates":[8.8630752563,56.7945251465],"type":"Point"}
}