{
  "type": "Feature",
  "properties": {
    "addr:full":"Engvej 76 K\u00f8benhavn S Danmark 2300",
    "addr:housenumber":"76",
    "addr:postcode":"2300",
    "addr:street":"Engvej;Kobenhavn S Danmark",
    "iso:country":"DK",
    "sg:address":"Engvej 76",
    "sg:city":"K\u00f8benhavn S",
    "sg:orig_category":"Psykologer, praktiserende",
    "sg:phone":"+45 32 55 62 05",
    "sg:postcode":"2300",
    "sg:province":"Danmark",
    "wof:name":"Olsen, Flemming",
    "wof:placetype":"venue"
},
  "geometry": {"coordinates":[-78.1299133301,36.7267417908],"type":"Point"}
}