{
  "type": "Feature",
  "properties": {
    "addr:full":"Haslevvej 6 Ringsted Danmark 4100",
    "addr:housenumber":"6",
    "addr:postcode":"4100",
    "addr:street":"Haslevvej",
    "iso:country":"DK",
    "sg:address":"Haslevvej 6",
    "sg:city":"Ringsted",
    "sg:orig_category":"Maskinfabrikker",
    "sg:phone":"+45 57 67 60 00",
    "sg:postcode":"4100",
    "sg:province":"Danmark",
    "wof:name":"Rimatic ApS",
    "wof:placetype":"venue"
},
  "geometry": {"coordinates":[11.8007450104,55.4358329773],"type":"Point"}
}