{
  "type": "Feature",
  "properties": {
    "iso:country":"DK",
    "sg:address":"Dam Enge 5",
    "sg:city":"Stenl\u00f8se",
    "sg:orig_category":"Cykler en gros",
    "sg:phone":"+45 47 10 71 72",
    "sg:postcode":"3660",
    "sg:province":"Danmark",
    "wof:name":"Borandia ApS",
    "wof:placetype":"venue"
},
  "geometry": {"coordinates":[6.2413201332,51.4118499756],"type":"Point"}
}