{
  "type": "Feature",
  "properties": {
    "addr:full":"Dalv\u00e6nget 12 Assens Danmark 5610",
    "addr:housenumber":"12",
    "addr:postcode":"5610",
    "addr:street":"Dalvaenget",
    "iso:country":"DK",
    "sg:address":"Dalv\u00e6nget 12",
    "sg:city":"Assens",
    "sg:orig_category":"Cykler",
    "sg:phone":"+45 64 71 45 10",
    "sg:postcode":"5610",
    "sg:province":"Danmark",
    "wof:name":"Vestfyns Cykellager I/S",
    "wof:placetype":"venue"
},
  "geometry": {"coordinates":[9.8998937607,55.2702522278],"type":"Point"}
}