{
  "type": "Feature",
  "properties": {
    "addr:full":"Fmd.: C. Greve, Erstedskovvej 10, Stubberup Sk\u00f8rping Danmark 9520",
    "addr:housenumber":"10",
    "addr:postcode":"9520",
    "addr:street":"C.;Erstedskovvej",
    "iso:country":"DK",
    "sg:address":"Fmd.: C. Greve, Erstedskovvej 10, Stubberup",
    "sg:city":"Sk\u00f8rping",
    "sg:orig_category":"Kulturelle foreninger",
    "sg:phone":"+45 98 37 51 99",
    "sg:postcode":"9520",
    "sg:province":"Danmark",
    "wof:name":"\u00c5restrup - midt i Himmerland",
    "wof:placetype":"venue"
},
  "geometry": {"coordinates":[9.8477077484,56.8337860107],"type":"Point"}
}