{
  "type": "Feature",
  "properties": {
    "addr:full":"Vandv\u00e6rksvej 3, Farre Sporup Danmark 8472",
    "addr:housenumber":"3",
    "addr:postcode":"8472",
    "addr:street":"Vandvaerksvej",
    "iso:country":"DK",
    "sg:address":"Vandv\u00e6rksvej 3, Farre",
    "sg:city":"Sporup",
    "sg:orig_category":"Forsamlingshuse",
    "sg:phone":"+45 86 96 80 65",
    "sg:postcode":"8472",
    "sg:province":"Danmark",
    "wof:name":"Farre forsamlingshus",
    "wof:placetype":"venue"
},
  "geometry": {"coordinates":[9.8504247665,56.2205352783],"type":"Point"}
}