{
  "type": "Feature",
  "properties": {
    "addr:full":"H. C. \u00d8rsteds Vej 50 A Frederiksberg Danmark 1879",
    "addr:housenumber":"50 a",
    "addr:postcode":"1879",
    "addr:street":"H. C. Orsteds Vej",
    "iso:country":"DK",
    "sg:address":"H. C. \u00d8rsteds Vej 50 A",
    "sg:city":"Frederiksberg",
    "sg:orig_category":"Travbaner",
    "sg:phone":"+45 35 35 11 69",
    "sg:postcode":"1879",
    "sg:province":"Danmark",
    "wof:name":"\u00d8rsted Travbane",
    "wof:placetype":"venue"
},
  "geometry": {"coordinates":[12.5432500839,55.6777114868],"type":"Point"}
}