{
  "type": "Feature",
  "properties": {
    "addr:full":"H\u00f8rsholmsgade 18, kld. K\u00f8benhavn N Danmark 2200",
    "addr:housenumber":"18 kld. kobenhavn",
    "addr:postcode":"2200",
    "addr:street":"Horsholmsgade;N Danmark",
    "iso:country":"DK",
    "sg:address":"H\u00f8rsholmsgade 18, kld.",
    "sg:city":"K\u00f8benhavn N",
    "sg:orig_category":"Musikinstrumenter",
    "sg:phone":"+45 35 81 30 02",
    "sg:postcode":"2200",
    "sg:province":"Danmark",
    "sg:website":"www.ivannio.dk",
    "wof:name":"Nio Guitars",
    "wof:placetype":"venue"
},
  "geometry": {"coordinates":[-76.4168395996,37.452419281],"type":"Point"}
}