{
  "type": "Feature",
  "properties": {
    "iso:country":"DK",
    "sg:address":"Ingersvej 4 ",
    "sg:city":"Hedehusene",
    "sg:classifiers":[
        {
            "category":"Farming",
            "subcategory":"Livestock Farm",
            "type":"Manufacturing & Wholesale Goods"
        }
    ],
    "sg:phone":"+45 43 99 50 66",
    "sg:postcode":"2640",
    "sg:province":"Danmark",
    "sg:tags":[
        "agriculture"
    ],
    "wof:name":"JH PLANTER APS",
    "wof:placetype":"venue"
},
  "geometry": {"coordinates":[12.2167205811,55.6890068054],"type":"Point"}
}