{
  "type": "Feature",
  "properties": {
    "iso:country":"DK",
    "sg:address":"Trunderupvej 1 E",
    "sg:city":"Haarby",
    "sg:classifiers":[
        {
            "category":"Taxi",
            "type":"Transportation"
        }
    ],
    "sg:phone":"+45 64 73 16 14",
    "sg:postcode":"5683",
    "sg:province":"Danmark",
    "wof:name":"Haarby Taxi - Turist",
    "wof:placetype":"venue"
},
  "geometry": {"coordinates":[10.1234750748,55.2234535217],"type":"Point"}
}