{
  "type": "Feature",
  "properties": {
    "addr:full":"Bakken 3 Skanderborg Danmark 8660",
    "addr:housenumber":"3",
    "addr:postcode":"8660",
    "addr:street":"Bakken",
    "iso:country":"DK",
    "sg:address":"Bakken 3",
    "sg:city":"Skanderborg",
    "sg:classifiers":[
        {
            "category":"Food & Beverages",
            "subcategory":"Liquor & Beverages",
            "type":"Retail Goods"
        }
    ],
    "sg:phone":"+45 86 51 22 41",
    "sg:postcode":"8660",
    "sg:province":"Danmark",
    "sg:tags":[
        "vin"
    ],
    "wof:name":"Slotsimporten",
    "wof:placetype":"venue"
},
  "geometry": {"coordinates":[9.9366054535,56.0301017761],"type":"Point"}
}