{
  "type": "Feature",
  "properties": {
    "addr:full":"N\u00f8rreport 12 Aabenraa Danmark 6200",
    "addr:housenumber":"12",
    "addr:postcode":"6200",
    "addr:street":"Norreport",
    "iso:country":"DK",
    "sg:address":"N\u00f8rreport 12",
    "sg:city":"Aabenraa",
    "sg:classifiers":[
        {
            "category":"Restaurant",
            "type":"Food & Drink"
        }
    ],
    "sg:phone":"+45 74 62 20 49",
    "sg:postcode":"6200",
    "sg:province":"Danmark",
    "wof:name":"Hj\u00f8rnet, Restaurant",
    "wof:placetype":"venue"
},
  "geometry": {"coordinates":[9.419002533,55.0483665466],"type":"Point"}
}