{
  "type": "Feature",
  "properties": {
    "addr:full":"Gammel Havevej 4 Stege Danmark 4780",
    "addr:housenumber":"4",
    "addr:postcode":"4780",
    "addr:street":"Gammel Havevej",
    "iso:country":"DK",
    "sg:address":"Gammel Havevej 4",
    "sg:city":"Stege",
    "sg:orig_category":"Varmeforsyning",
    "sg:phone":"+45 55 81 50 88",
    "sg:postcode":"4780",
    "sg:province":"Danmark",
    "wof:name":"Stege Fjernvarme a.m.b.a.",
    "wof:placetype":"venue"
},
  "geometry": {"coordinates":[12.2861709595,54.9903564453],"type":"Point"}
}