{
  "type": "Feature",
  "properties": {
    "addr:full":"Frederikssundsvej 114 A Br\u00f8nsh\u00f8j Danmark 2700",
    "addr:housenumber":"114 a",
    "addr:postcode":"2700",
    "addr:street":"Frederikssundsvej",
    "iso:country":"DK",
    "sg:address":"Frederikssundsvej 114 A",
    "sg:city":"Br\u00f8nsh\u00f8j",
    "sg:classifiers":[
        {
            "category":"Communications",
            "type":"Services"
        }
    ],
    "sg:phone":"+45 38 60 15 66",
    "sg:postcode":"2700",
    "sg:province":"Danmark",
    "sg:tags":[
        "og",
        "tv",
        "radio"
    ],
    "wof:name":"Bella TV & Radio",
    "wof:placetype":"venue"
},
  "geometry": {"coordinates":[-65.6866531372,-23.1981296539],"type":"Point"}
}