{
  "type": "Feature",
  "properties": {
    "iso:country":"DK",
    "sg:address":"Naffet 4 D, Skrydstrup",
    "sg:city":"Vojens",
    "sg:orig_category":"Solcentre",
    "sg:phone":"+45 74 59 07 33",
    "sg:postcode":"6500",
    "sg:province":"Danmark",
    "wof:name":"Sun-In Solcenter",
    "wof:placetype":"venue"
},
  "geometry": {"coordinates":[9.2987146378,55.2457237244],"type":"Point"}
}