{
  "type": "Feature",
  "properties": {
    "addr:full":"Kalkhavesvej 1, Ballen Sams\u00f8 Danmark 8305",
    "addr:housenumber":"1",
    "addr:postcode":"8305",
    "addr:street":"Kalkhavesvej",
    "iso:country":"DK",
    "sg:address":"Kalkhavesvej 1, Ballen",
    "sg:city":"Sams\u00f8",
    "sg:orig_category":"Keramik",
    "sg:phone":"+45 86 59 32 32",
    "sg:postcode":"8305",
    "sg:province":"Danmark",
    "wof:name":"Rakuv\u00e6rkstedet",
    "wof:placetype":"venue"
},
  "geometry": {"coordinates":[10.5885000229,55.8320198059],"type":"Point"}
}