{
  "type": "Feature",
  "properties": {
    "addr:full":"Erhvervsvej 3  Varde Danmark 6800",
    "addr:housenumber":"3",
    "addr:postcode":"6800",
    "addr:street":"Erhvervsvej",
    "iso:country":"DK",
    "sg:address":"Erhvervsvej 3 ",
    "sg:city":"Varde",
    "sg:classifiers":[
        {
            "category":"Manufacturing",
            "subcategory":"Tools & Machinery",
            "type":"Manufacturing & Wholesale Goods"
        }
    ],
    "sg:phone":"+45 75 22 33 33",
    "sg:postcode":"6800",
    "sg:province":"Danmark",
    "sg:tags":[
        "environment",
        "equipment",
        "-"
    ],
    "wof:name":"SCANDI-AQUALINE A/S",
    "wof:placetype":"venue"
},
  "geometry": {"coordinates":[8.4529285431,55.6280212402],"type":"Point"}
}