{
  "type": "Feature",
  "properties": {
    "addr:full":"Jyllandsgade 5 Grindsted Danmark 7200",
    "addr:housenumber":"5",
    "addr:postcode":"7200",
    "addr:street":"Jyllandsgade",
    "iso:country":"DK",
    "sg:address":"Jyllandsgade 5",
    "sg:city":"Grindsted",
    "sg:classifiers":[
        {
            "category":"Professional",
            "subcategory":"Business Services",
            "type":"Services"
        }
    ],
    "sg:phone":"+45 75 32 35 22",
    "sg:postcode":"7200",
    "sg:province":"Danmark",
    "sg:tags":[
        "import",
        "vin"
    ],
    "wof:name":"Gemini Vinimport",
    "wof:placetype":"venue"
},
  "geometry": {"coordinates":[8.923874855,55.7598876953],"type":"Point"}
}