{
  "type": "Feature",
  "properties": {
    "iso:country":"DK",
    "sg:address":"\u00c5restrupsvej 1",
    "sg:city":"Aalborg",
    "sg:orig_category":"Handicap-daginstitutioner",
    "sg:phone":"+45 98 77 41 37",
    "sg:postcode":"9000",
    "sg:province":"Danmark",
    "wof:name":"Specialgruppen Ved BH. Bakkeg\u00e5rden",
    "wof:placetype":"venue"
},
  "geometry": {"coordinates":[9.967130661,57.0429878235],"type":"Point"}
}