{
  "type": "Feature",
  "properties": {
    "addr:full":"Kirkegade 13 Ebeltoft Danmark 8400",
    "addr:housenumber":"13",
    "addr:postcode":"8400",
    "addr:street":"Kirkegade",
    "iso:country":"DK",
    "sg:address":"Kirkegade 13",
    "sg:city":"Ebeltoft",
    "sg:orig_category":"Kirkesogne",
    "sg:phone":"+45 86 34 16 74",
    "sg:postcode":"8400",
    "sg:province":"Danmark",
    "wof:name":"Ebeltoft Kirkekontor",
    "wof:placetype":"venue"
},
  "geometry": {"coordinates":[10.6762781143,56.1949691772],"type":"Point"}
}