{
  "type": "Feature",
  "properties": {
    "iso:country":"DK",
    "sg:address":"Korsvangen 11 ",
    "sg:city":"Ringe",
    "sg:classifiers":[
        {
            "category":"Sports & Exercise",
            "subcategory":"Playing Field",
            "type":"Entertainment"
        }
    ],
    "sg:phone":"+45 63 62 12 50",
    "sg:postcode":"5750",
    "sg:province":"Danmark",
    "sg:tags":[
        "game"
    ],
    "wof:name":"KOMPAN A/S",
    "wof:placetype":"venue"
},
  "geometry": {"coordinates":[10.4818267822,55.2471199036],"type":"Point"}
}