{
  "type": "Feature",
  "properties": {
    "addr:full":"Artillerivej 48 K\u00f8benhavn S Danmark 2300",
    "addr:housenumber":"48",
    "addr:postcode":"2300",
    "addr:street":"Artillerivej;S Danmark",
    "iso:country":"DK",
    "sg:address":"Artillerivej 48",
    "sg:city":"K\u00f8benhavn S",
    "sg:classifiers":[
        {
            "category":"Restaurant",
            "type":"Food & Drink"
        }
    ],
    "sg:phone":"+45 32 54 62 71",
    "sg:postcode":"2300",
    "sg:province":"Danmark",
    "wof:name":"Artillericafeen",
    "wof:placetype":"venue"
},
  "geometry": {"coordinates":[-82.5001525879,38.4143486023],"type":"Point"}
}