{
  "type": "Feature",
  "properties": {
    "addr:full":"K\u00e6rsangervej 18 Lang\u00e5 Danmark 8870",
    "addr:housenumber":"18",
    "addr:postcode":"8870",
    "addr:street":"Kaersangervej",
    "iso:country":"DK",
    "sg:address":"K\u00e6rsangervej 18",
    "sg:city":"Lang\u00e5",
    "sg:orig_category":"Landbrugsmaskiner",
    "sg:phone":"+45 87 50 93 00",
    "sg:postcode":"8870",
    "sg:province":"Danmark",
    "wof:name":"Samson Agro A/S",
    "wof:placetype":"venue"
},
  "geometry": {"coordinates":[9.9008102417,56.3957901001],"type":"Point"}
}