{
  "type": "Feature",
  "properties": {
    "iso:country":"DK",
    "sg:address":"v/ Tinne Bredtoft, F\u00e6lledvej 8, Hald",
    "sg:city":"H\u00f8jslev",
    "sg:orig_category":"Spejderkorps",
    "sg:phone":"+45 97 53 87 60",
    "sg:postcode":"7840",
    "sg:province":"Danmark",
    "wof:name":"KFUM-spejderne Bruddalgruppe - H\u00f8jslev Kirkeby",
    "wof:placetype":"venue"
},
  "geometry": {"coordinates":[9.110039711,56.5504264832],"type":"Point"}
}