{
  "type": "Feature",
  "properties": {
    "iso:country":"DK",
    "sg:address":"Adelgade 1",
    "sg:city":"Bogense",
    "sg:orig_category":"Ejendomshandel",
    "sg:phone":"+45 64 81 30 30",
    "sg:postcode":"5400",
    "sg:province":"Danmark",
    "wof:name":"Balling, Anne",
    "wof:placetype":"venue"
},
  "geometry": {"coordinates":[10.0842256546,55.5663223267],"type":"Point"}
}