{
  "type": "Feature",
  "properties": {
    "addr:full":"Egebjergvej 136 Horsens Danmark 8700",
    "addr:housenumber":"136",
    "addr:postcode":"8700",
    "addr:street":"Egebjergvej",
    "iso:country":"DK",
    "sg:address":"Egebjergvej 136",
    "sg:city":"Horsens",
    "sg:orig_category":"Autoforhandlere",
    "sg:phone":"+45 75 65 66 77",
    "sg:postcode":"8700",
    "sg:province":"Danmark",
    "wof:name":"Egebjerg Auto",
    "wof:placetype":"venue"
},
  "geometry": {"coordinates":[9.839679718,55.8975105286],"type":"Point"}
}