{
  "type": "Feature",
  "properties": {
    "iso:country":"DK",
    "sg:address":"Store Torv 16",
    "sg:city":"\u00c5rhus C",
    "sg:orig_category":"INGENI\u00c3\u02dcRER",
    "sg:phone":"+45 86 13 82 11",
    "sg:postcode":"8000",
    "sg:province":"Danmark",
    "wof:name":"Melgaard, Torben A/S",
    "wof:placetype":"venue"
},
  "geometry": {"coordinates":[4.7165498734,49.7599182129],"type":"Point"}
}