{
  "type": "Feature",
  "properties": {
    "addr:full":"Fmd.: Hans Martinsen, Vodbindervej 11 Asaa Danmark 9340",
    "addr:housenumber":"11",
    "addr:postcode":"9340",
    "addr:street":"Vodbindervej",
    "iso:country":"DK",
    "sg:address":"Fmd.: Hans Martinsen, Vodbindervej 11",
    "sg:city":"Asaa",
    "sg:orig_category":"Kulturelle foreninger",
    "sg:phone":"+45 98 85 11 10",
    "sg:postcode":"9340",
    "sg:province":"Danmark",
    "wof:name":"Kristelig Lytter- og Fjernseer forening i Asaa",
    "wof:placetype":"venue"
},
  "geometry": {"coordinates":[10.4039297104,57.1481704712],"type":"Point"}
}