{
  "type": "Feature",
  "properties": {
    "addr:full":"v/ Kjeld Andersen, Krogenlundvej 5 Lynge Danmark 3540",
    "addr:housenumber":"5",
    "addr:postcode":"3540",
    "addr:street":"Krogenlundvej",
    "iso:country":"DK",
    "sg:address":"v/ Kjeld Andersen, Krogenlundvej 5",
    "sg:city":"Lynge",
    "sg:orig_category":"Musik og sang",
    "sg:phone":"+45 48 18 72 29",
    "sg:postcode":"3540",
    "sg:province":"Danmark",
    "wof:name":"Visens Venner i Aller\u00f8d",
    "wof:placetype":"venue"
},
  "geometry": {"coordinates":[12.2734966278,55.834186554],"type":"Point"}
}