{
  "type": "Feature",
  "properties": {
    "addr:full":"Holmegade 7 Ulfborg Danmark 6990",
    "addr:housenumber":"7",
    "addr:postcode":"6990",
    "addr:street":"Holmegade",
    "iso:country":"DK",
    "sg:address":"Holmegade 7",
    "sg:city":"Ulfborg",
    "sg:orig_category":"Ejendomshandel",
    "sg:phone":"+45 97 49 10 22",
    "sg:postcode":"6990",
    "sg:province":"Danmark",
    "wof:name":"Ulfborg Ejendomskontor",
    "wof:placetype":"venue"
},
  "geometry": {"coordinates":[8.3207740784,56.2728118896],"type":"Point"}
}