{
  "type": "Feature",
  "properties": {
    "addr:full":"Jens Juuls Vej 18 Viby Danmark 8260",
    "addr:housenumber":"18",
    "addr:postcode":"8260",
    "addr:street":"Jens Juuls Vej",
    "iso:country":"DK",
    "sg:address":"Jens Juuls Vej 18",
    "sg:city":"Viby",
    "sg:orig_category":"INGENI\u00c3\u02dcRER",
    "sg:phone":"+45 87 38 61 66",
    "sg:postcode":"8260",
    "sg:province":"Danmark",
    "wof:name":"Hedeselskabet Milj\u00f8 og Energi A/S",
    "wof:placetype":"venue"
},
  "geometry": {"coordinates":[10.1308107376,56.1125602722],"type":"Point"}
}