{
  "type": "Feature",
  "properties": {
    "iso:country":"DK",
    "sg:address":"Hvedevej 29",
    "sg:city":"Galten",
    "sg:orig_category":"Vinduespolering",
    "sg:phone":"+45 86 94 40 82",
    "sg:postcode":"8464",
    "sg:province":"Danmark",
    "wof:name":"B. S. Polering",
    "wof:placetype":"venue"
},
  "geometry": {"coordinates":[9.9246244431,56.1562232971],"type":"Point"}
}