{
  "type": "Feature",
  "properties": {
    "addr:full":"St. Sct. Mikkels Gade 20 Viborg Danmark 8800",
    "addr:housenumber":"20",
    "addr:postcode":"8800",
    "addr:street":"Sct. Mikkels Gade",
    "iso:country":"DK",
    "sg:address":"St. Sct. Mikkels Gade 20",
    "sg:city":"Viborg",
    "sg:orig_category":"Fisk og vildt",
    "sg:phone":"+45 86 62 01 11",
    "sg:postcode":"8800",
    "sg:province":"Danmark",
    "wof:name":"Mulbjerg Fisk",
    "wof:placetype":"venue"
},
  "geometry": {"coordinates":[9.4095716476,56.4504394531],"type":"Point"}
}