{
  "type": "Feature",
  "properties": {
    "addr:full":"Storgade 16 Sor\u00f8 Danmark 4180",
    "addr:housenumber":"16",
    "addr:postcode":"4180",
    "addr:street":"Storgade",
    "iso:country":"DK",
    "sg:address":"Storgade 16",
    "sg:city":"Sor\u00f8",
    "sg:orig_category":"Ure og urmagere",
    "sg:phone":"+45 57 83 00 82",
    "sg:postcode":"4180",
    "sg:province":"Danmark",
    "wof:name":"Jensen & S\u00f8n, Fred.",
    "wof:placetype":"venue"
},
  "geometry": {"coordinates":[-102.94467926030001,45.4534721375],"type":"Point"}
}