{
  "type": "Feature",
  "properties": {
    "addr:full":"Fmd.: Bjarne Andersen, Stammen 5 Gistrup Danmark 9260",
    "addr:housenumber":"5",
    "addr:postcode":"9260",
    "addr:street":"Stammen",
    "iso:country":"DK",
    "sg:address":"Fmd.: Bjarne Andersen, Stammen 5",
    "sg:city":"Gistrup",
    "sg:orig_category":"Hobbybetonede foreninger",
    "sg:phone":"+45 98 31 52 73",
    "sg:postcode":"9260",
    "sg:province":"Danmark",
    "wof:name":"Experimenterende Danske Radioamat\u00f8rer, Aalborg Afdeling",
    "wof:placetype":"venue"
},
  "geometry": {"coordinates":[9.9942445755,56.9978294373],"type":"Point"}
}