{
  "type": "Feature",
  "properties": {
    "addr:full":"Elvej 15 Saksk\u00f8bing Danmark 4990",
    "addr:housenumber":"15",
    "addr:postcode":"4990",
    "addr:street":"Elvej",
    "iso:country":"DK",
    "sg:address":"Elvej 15",
    "sg:city":"Saksk\u00f8bing",
    "sg:orig_category":"Frugt en gros",
    "sg:phone":"+45 54 70 45 34",
    "sg:postcode":"4990",
    "sg:province":"Danmark",
    "wof:name":"L.F.Frugt",
    "wof:placetype":"venue"
},
  "geometry": {"coordinates":[-89.24946594239999,39.2174491882],"type":"Point"}
}