{
  "type": "Feature",
  "properties": {
    "addr:full":"Buen 5 Frederiksberg Danmark 2000",
    "addr:housenumber":"5",
    "addr:postcode":"2000",
    "addr:street":"Buen",
    "iso:country":"DK",
    "sg:address":"Buen 5",
    "sg:city":"Frederiksberg",
    "sg:orig_category":"Forlag",
    "sg:phone":"+45 38 71 18 61",
    "sg:postcode":"2000",
    "sg:province":"Danmark",
    "wof:name":"Skolebogsforlaget",
    "wof:placetype":"venue"
},
  "geometry": {"coordinates":[12.4978675842,55.6833114624],"type":"Point"}
}