{
  "type": "Feature",
  "properties": {
    "addr:full":"Vestervej 3 Holeby Danmark 4960",
    "addr:housenumber":"3",
    "addr:postcode":"4960",
    "addr:street":"Vestervej",
    "iso:country":"DK",
    "sg:address":"Vestervej 3",
    "sg:city":"Holeby",
    "sg:orig_category":"Bagere",
    "sg:phone":"+45 54 60 66 88",
    "sg:postcode":"4960",
    "sg:province":"Danmark",
    "wof:name":"Holeby M\u00f8lle",
    "wof:placetype":"venue"
},
  "geometry": {"coordinates":[11.473228,54.70892],"type":"Point"}
}