{
  "type": "Feature",
  "properties": {
    "iso:country":"DK",
    "sg:address":"N\u00f8debovej 77 A, N\u00f8debo",
    "sg:city":"Fredensborg",
    "sg:orig_category":"Statslige direktorater og styrelser",
    "sg:phone":"+45 48 40 10 00",
    "sg:postcode":"3480",
    "sg:province":"Danmark",
    "sg:website":"www.sks.dk",
    "wof:name":"Skovskolen",
    "wof:placetype":"venue"
},
  "geometry": {"coordinates":[12.4020547867,55.9782943726],"type":"Point"}
}