{
  "type": "Feature",
  "properties": {
    "addr:full":"Gutenbergvej 1 Sindal Danmark 9870",
    "addr:housenumber":"1",
    "addr:postcode":"9870",
    "addr:street":"Gutenbergvej",
    "iso:country":"DK",
    "sg:address":"Gutenbergvej 1",
    "sg:city":"Sindal",
    "sg:orig_category":"Bogtrykkerier",
    "sg:phone":"+45 98 93 58 11",
    "sg:postcode":"9870",
    "sg:province":"Danmark",
    "wof:name":"Sindal Bogtrykkeri ComVision",
    "wof:placetype":"venue"
},
  "geometry": {"coordinates":[10.2012958527,57.485370636],"type":"Point"}
}