{
  "type": "Feature",
  "properties": {
    "iso:country":"DK",
    "sg:address":"Fortevej 98 a",
    "sg:city":"Risskov",
    "sg:orig_category":"Rejsebureauer",
    "sg:phone":"+45 86 18 45 77",
    "sg:postcode":"8240",
    "sg:province":"Danmark",
    "sg:website":"www.bbrejser.dk",
    "wof:name":"BB Rejser",
    "wof:placetype":"venue"
},
  "geometry": {"coordinates":[10.2442855835,56.1912918091],"type":"Point"}
}