{
  "type": "Feature",
  "properties": {
    "iso:country":"DK",
    "sg:address":"Tranumparken 3",
    "sg:city":"Aalborg \u00d8",
    "sg:orig_category":"Handicapboliger",
    "sg:phone":"+45 98 15 23 66",
    "sg:postcode":"9220",
    "sg:province":"Danmark",
    "wof:name":"Mobile Handicappede B\u00f8rn",
    "wof:placetype":"venue"
},
  "geometry": {"coordinates":[10.0038280487,57.0346412659],"type":"Point"}
}