{
  "type": "Feature",
  "properties": {
    "addr:full":"Fmd.: Eigil S\u00f8rensen, Toftbjerg 51, Snejbjerg Herning Danmark 7400",
    "addr:housenumber":"51",
    "addr:postcode":"7400",
    "addr:street":"Sorensen Toftbjerg;Snejbjerg",
    "iso:country":"DK",
    "sg:address":"Fmd.: Eigil S\u00f8rensen, Toftbjerg 51, Snejbjerg",
    "sg:city":"Herning",
    "sg:orig_category":"Borger- og beboerforeninger",
    "sg:phone":"+45 97 16 14 23",
    "sg:postcode":"7400",
    "sg:province":"Danmark",
    "wof:name":"Snejbjerg Borgerforening",
    "wof:placetype":"venue"
},
  "geometry": {"coordinates":[8.9768896103,56.1374168396],"type":"Point"}
}