{
  "type": "Feature",
  "properties": {
    "iso:country":"DK",
    "sg:address":"Egensevej 49, V. Kippinge",
    "sg:city":"N\u00f8rre Alslev",
    "sg:orig_category":"Handicapboliger",
    "sg:phone":"+45 54 43 11 80",
    "sg:postcode":"4840",
    "sg:province":"Danmark",
    "wof:name":"Vester Kippinge Plejehjem",
    "wof:placetype":"venue"
},
  "geometry": {"coordinates":[11.8542251587,54.9528236389],"type":"Point"}
}