{
  "type": "Feature",
  "properties": {
    "iso:country":"DK",
    "sg:address":"Engtoften 11 - 13",
    "sg:city":"Viby",
    "sg:classifiers":[
        {
            "category":"Building & Trades",
            "subcategory":"Construction",
            "type":"Services"
        }
    ],
    "sg:phone":"+45 86 14 15 17",
    "sg:postcode":"8260",
    "sg:province":"Danmark",
    "sg:tags":[
        "ventilation"
    ],
    "wof:name":"Rectus ApS",
    "wof:placetype":"venue"
},
  "geometry": {"coordinates":[10.1679878235,56.1237258911],"type":"Point"}
}