{
  "type": "Feature",
  "properties": {
    "addr:full":"Skovvej 105 Charlottenlund Danmark 2920",
    "addr:housenumber":"105",
    "addr:postcode":"2920",
    "addr:street":"Skovvej",
    "iso:country":"DK",
    "sg:address":"Skovvej 105",
    "sg:city":"Charlottenlund",
    "sg:orig_category":"Reklamebureauer",
    "sg:phone":"+45 39 63 55 61",
    "sg:postcode":"2920",
    "sg:province":"Danmark",
    "wof:name":"ReklameBiksen",
    "wof:placetype":"venue"
},
  "geometry": {"coordinates":[12.5535593033,55.7683143616],"type":"Point"}
}