{
  "type": "Feature",
  "properties": {
    "addr:full":"Teglg\u00e5rdsparken 17 Middelfart Danmark 5500",
    "addr:housenumber":"17",
    "addr:postcode":"5500",
    "addr:street":"Teglgaardsparken",
    "iso:country":"DK",
    "sg:address":"Teglg\u00e5rdsparken 17",
    "sg:city":"Middelfart",
    "sg:orig_category":"Misbrugscentre",
    "sg:phone":"+45 63 41 01 70",
    "sg:postcode":"5500",
    "sg:province":"Danmark",
    "wof:name":"Fyns Amts Alkoholbehandlingscenter.",
    "wof:placetype":"venue"
},
  "geometry": {"coordinates":[9.7268695831,55.4999084473],"type":"Point"}
}