{
  "type": "Feature",
  "properties": {
    "iso:country":"DK",
    "sg:address":"Elsenbakken 23 ",
    "sg:city":"Frederikssund",
    "sg:classifiers":[
        {
            "category":"Wholesale",
            "subcategory":"Drugs",
            "type":"Manufacturing & Wholesale Goods"
        }
    ],
    "sg:phone":"+45 47 38 47 00",
    "sg:postcode":"3600",
    "sg:province":"Danmark",
    "sg:tags":[
        "chemical",
        "pharmaceutical"
    ],
    "wof:name":"BRENNTAG BIOSECTOR A/S",
    "wof:placetype":"venue"
},
  "geometry": {"coordinates":[12.0654497147,55.8513374329],"type":"Point"}
}