{
  "type": "Feature",
  "properties": {
    "addr:full":"\u00d8stergade 6 Randers Danmark 8900",
    "addr:housenumber":"6",
    "addr:postcode":"8900",
    "addr:street":"Ostergade",
    "iso:country":"DK",
    "sg:address":"\u00d8stergade 6",
    "sg:city":"Randers",
    "sg:orig_category":"Kopiering",
    "sg:phone":"+45 86 40 10 33",
    "sg:postcode":"8900",
    "sg:province":"Danmark",
    "wof:name":"Kopiservice Kronjylland ApS",
    "wof:placetype":"venue"
},
  "geometry": {"coordinates":[10.0407590866,56.4617004395],"type":"Point"}
}