{
  "type": "Feature",
  "properties": {
    "addr:full":"Kollerupvej 25 Randers Danmark 8900",
    "addr:housenumber":"25",
    "addr:postcode":"8900",
    "addr:street":"Kollerupvej",
    "iso:country":"DK",
    "sg:address":"Kollerupvej 25",
    "sg:city":"Randers",
    "sg:orig_category":"Homeparties",
    "sg:phone":"+45 86 42 39 69",
    "sg:postcode":"8900",
    "sg:province":"Danmark",
    "wof:name":"Andersen I/S, Lene & Bo M\u00f8ller",
    "wof:placetype":"venue"
},
  "geometry": {"coordinates":[9.9287986755,56.5412139893],"type":"Point"}
}