{
  "type": "Feature",
  "properties": {
    "addr:full":"Nordvestvej 8 Aars Danmark 9600",
    "addr:housenumber":"8",
    "addr:postcode":"9600",
    "addr:street":"Nordvestvej",
    "iso:country":"DK",
    "sg:address":"Nordvestvej 8",
    "sg:city":"Aars",
    "sg:orig_category":"Isoleringsmateriel",
    "sg:phone":"+45 98 62 42 00",
    "sg:postcode":"9600",
    "sg:province":"Danmark",
    "wof:name":"Dc-System Insulation A/S",
    "wof:placetype":"venue"
},
  "geometry": {"coordinates":[9.4966106415,56.8173828125],"type":"Point"}
}