{
  "type": "Feature",
  "properties": {
    "addr:full":"Akkerupvej 50 Haarby Danmark 5683",
    "addr:housenumber":"50",
    "addr:postcode":"5683",
    "addr:street":"Akkerupvej",
    "iso:country":"DK",
    "sg:address":"Akkerupvej 50",
    "sg:city":"Haarby",
    "sg:orig_category":"Planteskoler",
    "sg:phone":"+45 64 73 10 58",
    "sg:postcode":"5683",
    "sg:province":"Danmark",
    "wof:name":"Akkerup Planteskole",
    "wof:placetype":"venue"
},
  "geometry": {"coordinates":[10.143163681,55.2304077148],"type":"Point"}
}