{
  "type": "Feature",
  "properties": {
    "addr:full":"Gammel Hejnsvigvej 12 Billund Danmark 7190",
    "addr:housenumber":"12",
    "addr:postcode":"7190",
    "addr:street":"Gammel Hejnsvigvej",
    "iso:country":"DK",
    "sg:address":"Gammel Hejnsvigvej 12",
    "sg:city":"Billund",
    "sg:orig_category":"Databehandling",
    "sg:phone":"+45 75 35 44 70",
    "sg:postcode":"7190",
    "sg:province":"Danmark",
    "wof:name":"Hornbak Internet Service",
    "wof:placetype":"venue"
},
  "geometry": {"coordinates":[9.1115894318,55.7299118042],"type":"Point"}
}