{
  "type": "Feature",
  "properties": {
    "addr:full":"Jeppe \u00c5kj\u00e6rs Vej 7 Aalborg SV Danmark 9200",
    "addr:housenumber":"7",
    "addr:postcode":"9200",
    "addr:street":"Jeppe Aakjaers Vej",
    "iso:country":"DK",
    "sg:address":"Jeppe \u00c5kj\u00e6rs Vej 7",
    "sg:city":"Aalborg SV",
    "sg:orig_category":"Handicapboliger",
    "sg:phone":"+45 98 18 92 46",
    "sg:postcode":"9200",
    "sg:province":"Danmark",
    "wof:name":"Boenheden",
    "wof:placetype":"venue"
},
  "geometry": {"coordinates":[9.8865880966,57.0114021301],"type":"Point"}
}