{
  "type": "Feature",
  "properties": {
    "iso:country":"DK",
    "sg:address":"Hjarupvej 14-16",
    "sg:city":"Lunderskov",
    "sg:orig_category":"Kommunale folkeskoler",
    "sg:phone":"+45 76 92 99 99",
    "sg:postcode":"6640",
    "sg:province":"Danmark",
    "sg:website":"come.to/forbundskolen",
    "wof:name":"Skanderup-Hjarup Forbundsskole",
    "wof:placetype":"venue"
},
  "geometry": {"coordinates":[9.3480825424,55.4636116028],"type":"Point"}
}