{
  "type": "Feature",
  "properties": {
    "addr:full":"Skibdalsvej 5, Sillerslev \u00d8ster Assels Danmark 7990",
    "addr:housenumber":"5",
    "addr:postcode":"7990",
    "addr:street":"Skibdalsvej;Oster",
    "iso:country":"DK",
    "sg:address":"Skibdalsvej 5, Sillerslev",
    "sg:city":"\u00d8ster Assels",
    "sg:orig_category":"Fisk og vildt",
    "sg:phone":"+45 97 76 48 03",
    "sg:postcode":"7990",
    "sg:province":"Danmark",
    "wof:name":"Krog & Co.",
    "wof:placetype":"venue"
},
  "geometry": {"coordinates":[8.7583551407,56.7187957764],"type":"Point"}
}