{
  "type": "Feature",
  "properties": {
    "addr:full":"Benediktevej 19, st. Fredensborg Danmark 3480",
    "addr:housenumber":"19",
    "addr:postcode":"3480",
    "addr:street":"Benediktevej",
    "iso:country":"DK",
    "sg:address":"Benediktevej 19, st.",
    "sg:city":"Fredensborg",
    "sg:orig_category":"Pressebureauer",
    "sg:phone":"+45 48 48 15 82",
    "sg:postcode":"3480",
    "sg:province":"Danmark",
    "wof:name":"Nordic Forecasts",
    "wof:placetype":"venue"
},
  "geometry": {"coordinates":[12.4020547867,55.9782943726],"type":"Point"}
}