{
  "type": "Feature",
  "properties": {
    "iso:country":"DK",
    "sg:address":"Frederiksgade 34",
    "sg:city":"\u00c5rhus C",
    "sg:orig_category":"Revisorer",
    "sg:phone":"+45 86 20 27 00",
    "sg:postcode":"8000",
    "sg:province":"Danmark",
    "wof:name":"Revisionsfirma Steen B. Hansen",
    "wof:placetype":"venue"
},
  "geometry": {"coordinates":[10.2051076889,56.1555328369],"type":"Point"}
}