{
  "type": "Feature",
  "properties": {
    "addr:full":"Ruten 20 Br\u00f8nsh\u00f8j Danmark 2700",
    "addr:housenumber":"20",
    "addr:postcode":"2700",
    "addr:street":"Ruten",
    "iso:country":"DK",
    "sg:address":"Ruten 20",
    "sg:city":"Br\u00f8nsh\u00f8j",
    "sg:orig_category":"Malermestre",
    "sg:phone":"+45 38 89 00 93",
    "sg:postcode":"2700",
    "sg:province":"Danmark",
    "wof:name":"Malerselskabet SBM A/S",
    "wof:placetype":"venue"
},
  "geometry": {"coordinates":[7.481180191,52.5436515808],"type":"Point"}
}