{
  "type": "Feature",
  "properties": {
    "addr:full":"Bredgade 129  L\u00f8gst\u00f8r Danmark 9670",
    "addr:housenumber":"129",
    "addr:postcode":"9670",
    "addr:street":"Bredgade",
    "iso:country":"DK",
    "sg:address":"Bredgade 129 ",
    "sg:city":"L\u00f8gst\u00f8r",
    "sg:classifiers":[
        {
            "category":"Wholesale",
            "subcategory":"Machinery & Supplies",
            "type":"Manufacturing & Wholesale Goods"
        }
    ],
    "sg:phone":"+45 98 67 10 33",
    "sg:postcode":"9670",
    "sg:province":"Danmark",
    "sg:tags":[
        "-",
        "agriculture",
        "equipment"
    ],
    "wof:name":"J HALDRUP A/S",
    "wof:placetype":"venue"
},
  "geometry": {"coordinates":[9.2115745544,56.8415603638],"type":"Point"}
}