{
  "type": "Feature",
  "properties": {
    "addr:full":"Fmd.: Ejnar Lajgaard, Tastumvej 52 B, Tastum Stoholm Danmark 7850",
    "addr:housenumber":"52 b",
    "addr:postcode":"7850",
    "addr:street":"Tastumvej;Tastum Stoholm Danmark",
    "iso:country":"DK",
    "sg:address":"Fmd.: Ejnar Lajgaard, Tastumvej 52 B, Tastum",
    "sg:city":"Stoholm",
    "sg:orig_category":"Hobbybetonede foreninger",
    "sg:phone":"+45 97 54 17 80",
    "sg:postcode":"7850",
    "sg:province":"Danmark",
    "wof:name":"Fugleforeningen for Skive, Salling og Fjends",
    "wof:placetype":"venue"
},
  "geometry": {"coordinates":[9.148730278,56.4856910706],"type":"Point"}
}