{
  "type": "Feature",
  "properties": {
    "addr:full":"Bakkeledet 9 K\u00f8ge Danmark 4600",
    "addr:housenumber":"9",
    "addr:postcode":"4600",
    "addr:street":"Bakkeledet",
    "iso:country":"DK",
    "sg:address":"Bakkeledet 9",
    "sg:city":"K\u00f8ge",
    "sg:orig_category":"Farvehandlere",
    "sg:phone":"+45 56 82 10 55",
    "sg:postcode":"4600",
    "sg:province":"Danmark",
    "wof:name":"HEA Byg ApS v/Malermester Hans E. Andersen",
    "wof:placetype":"venue"
},
  "geometry": {"coordinates":[12.1119480133,55.4697799683],"type":"Point"}
}