{
  "type": "Feature",
  "properties": {
    "addr:full":"Rytterholtsvej 22 A Silkeborg Danmark 8600",
    "addr:housenumber":"22 a",
    "addr:postcode":"8600",
    "addr:street":"Rytterholtsvej",
    "iso:country":"DK",
    "sg:address":"Rytterholtsvej 22 A",
    "sg:city":"Silkeborg",
    "sg:orig_category":"Psykologer, praktiserende",
    "sg:phone":"+45 86 84 42 00",
    "sg:postcode":"8600",
    "sg:province":"Danmark",
    "wof:name":"Bryld, Ejnar",
    "wof:placetype":"venue"
},
  "geometry": {"coordinates":[9.6346063614,56.1315574646],"type":"Point"}
}