{
  "type": "Feature",
  "properties": {
    "iso:country":"DK",
    "sg:address":"Billundvej 28, Ny N\u00f8rup",
    "sg:city":"Bredsten",
    "sg:orig_category":"Bagere",
    "sg:phone":"+45 75 88 37 11",
    "sg:postcode":"7182",
    "sg:province":"Danmark",
    "wof:name":"Ny N\u00f8rup Bageri",
    "wof:placetype":"venue"
},
  "geometry": {"coordinates":[9.380741,55.702332],"type":"Point"}
}