{
  "type": "Feature",
  "properties": {
    "addr:full":"Pennehave 7 Rungsted Kyst Danmark 2960",
    "addr:housenumber":"7",
    "addr:postcode":"2960",
    "addr:street":"Pennehave",
    "iso:country":"DK",
    "sg:address":"Pennehave 7",
    "sg:city":"Rungsted Kyst",
    "sg:classifiers":[
        {
            "category":"Communications",
            "type":"Services"
        }
    ],
    "sg:phone":"+45 45 57 15 51",
    "sg:postcode":"2960",
    "sg:province":"Danmark",
    "sg:tags":[
        "og",
        "tv",
        "radio"
    ],
    "wof:name":"Hi-fi Huset",
    "wof:placetype":"venue"
},
  "geometry": {"coordinates":[12.5231256485,55.8829421997],"type":"Point"}
}