{
  "type": "Feature",
  "properties": {
    "iso:country":"DK",
    "sg:address":"Produktionsvej 42 ",
    "sg:city":"Glostrup",
    "sg:classifiers":[
        {
            "category":"Wholesale",
            "subcategory":"Drugs",
            "type":"Manufacturing & Wholesale Goods"
        }
    ],
    "sg:phone":"+45 44 85 95 00",
    "sg:postcode":"2600",
    "sg:province":"Danmark",
    "sg:tags":[
        "chemical",
        "pharmaceutical"
    ],
    "wof:name":"DAKO CYTOMATION A/S",
    "wof:placetype":"venue"
},
  "geometry": {"coordinates":[12.42436409,55.7006340027],"type":"Point"}
}