{
  "type": "Feature",
  "properties": {
    "addr:full":"Hovedvejen 163, Osted Roskilde Danmark 4000",
    "addr:housenumber":"163",
    "addr:postcode":"4000",
    "addr:street":"Hovedvejen;Osted",
    "iso:country":"DK",
    "sg:address":"Hovedvejen 163, Osted",
    "sg:city":"Roskilde",
    "sg:orig_category":"Autoforhandlere",
    "sg:phone":"+45 46 49 82 81",
    "sg:postcode":"4000",
    "sg:province":"Danmark",
    "wof:name":"Stjerne Biler",
    "wof:placetype":"venue"
},
  "geometry": {"coordinates":[12.0909376144,55.6404838562],"type":"Point"}
}