{
  "type": "Feature",
  "properties": {
    "addr:full":"Birkevej 26 - 28 Vinderup Danmark 7830",
    "addr:housenumber":"26 28",
    "addr:postcode":"7830",
    "addr:street":"Birkevej",
    "iso:country":"DK",
    "sg:address":"Birkevej 26 - 28",
    "sg:city":"Vinderup",
    "sg:orig_category":"Non-Classified Establishments",
    "sg:phone":"+45 97 44 19 16",
    "sg:postcode":"7830",
    "sg:province":"Danmark",
    "wof:name":"Vinderup-V\u00e6rkstedet",
    "wof:placetype":"venue"
},
  "geometry": {"coordinates":[8.7712993622,56.4788818359],"type":"Point"}
}