{
  "type": "Feature",
  "properties": {
    "addr:full":"\u00d8stergade 52 Middelfart Danmark 5500",
    "addr:housenumber":"52",
    "addr:postcode":"5500",
    "addr:street":"Ostergade",
    "iso:country":"DK",
    "sg:address":"\u00d8stergade 52",
    "sg:city":"Middelfart",
    "sg:classifiers":[
        {
            "category":"Food & Beverages",
            "subcategory":"Liquor & Beverages",
            "type":"Retail Goods"
        }
    ],
    "sg:phone":"+45 64 41 22 06",
    "sg:postcode":"5500",
    "sg:province":"Danmark",
    "sg:tags":[
        "vin"
    ],
    "sg:website":"www.hjhansen.dk",
    "wof:name":"Vinspecialisten",
    "wof:placetype":"venue"
},
  "geometry": {"coordinates":[9.7417497635,55.5030250549],"type":"Point"}
}