{
  "type": "Feature",
  "properties": {
    "addr:full":"Ristingevej 9 Humble Danmark 5932",
    "addr:housenumber":"9",
    "addr:postcode":"5932",
    "addr:street":"Ristingevej",
    "iso:country":"DK",
    "sg:address":"Ristingevej 9",
    "sg:city":"Humble",
    "sg:classifiers":[
        {
            "category":"Banks & Credit Unions",
            "subcategory":"Bank",
            "type":"Services"
        }
    ],
    "sg:phone":"+45 62 57 12 13",
    "sg:postcode":"5932",
    "sg:province":"Danmark",
    "sg:tags":[
        "banker"
    ],
    "wof:name":"Nordea",
    "wof:placetype":"venue"
},
  "geometry": {"coordinates":[10.6974172592,54.8259735107],"type":"Point"}
}