{
  "type": "Feature",
  "properties": {
    "addr:full":"Hunderupvej 163 Odense M Danmark 5230",
    "addr:housenumber":"163",
    "addr:postcode":"5230",
    "addr:street":"Hunderupvej",
    "iso:country":"DK",
    "sg:address":"Hunderupvej 163",
    "sg:city":"Odense M",
    "sg:orig_category":"INGENI\u00c3\u02dcRER",
    "sg:phone":"+45 66 11 51 25",
    "sg:postcode":"5230",
    "sg:province":"Danmark",
    "wof:name":"Johansen, H.P. Hartz",
    "wof:placetype":"venue"
},
  "geometry": {"coordinates":[10.3878650665,55.3754577637],"type":"Point"}
}