{
  "type": "Feature",
  "properties": {
    "addr:full":"Fmd.: John Daugbjerg. Jensen, L\u00f8vsangervej 7, Kongsted R\u00f8nnede Danmark 4683",
    "addr:housenumber":"7",
    "addr:postcode":"4683",
    "addr:street":"Lovsangervej",
    "iso:country":"DK",
    "sg:address":"Fmd.: John Daugbjerg. Jensen, L\u00f8vsangervej 7, Kongsted",
    "sg:city":"R\u00f8nnede",
    "sg:orig_category":"Antenneforeninger",
    "sg:phone":"+45 56 71 21 14",
    "sg:postcode":"4683",
    "sg:province":"Danmark",
    "wof:name":"R\u00f8nnede-Kongsted Antenneforening",
    "wof:placetype":"venue"
},
  "geometry": {"coordinates":[12.040017128,55.2451210022],"type":"Point"}
}