{
  "type": "Feature",
  "properties": {
    "iso:country":"DK",
    "sg:address":"Rug\u00e5rdsvej 198, Skovsh\u00f8jrup",
    "sg:city":"Brenderup",
    "sg:orig_category":"Servicestationer",
    "sg:phone":"+45 64 44 21 21",
    "sg:postcode":"5464",
    "sg:province":"Danmark",
    "wof:name":"DK Benzin",
    "wof:placetype":"venue"
},
  "geometry": {"coordinates":[9.956905,55.51796],"type":"Point"}
}