{
  "type": "Feature",
  "properties": {
    "addr:full":"Petersmindevej 21 Odense C Danmark 5000",
    "addr:housenumber":"21",
    "addr:postcode":"5000",
    "addr:street":"Petersmindevej",
    "iso:country":"DK",
    "sg:address":"Petersmindevej 21",
    "sg:city":"Odense C",
    "sg:orig_category":"Autoreparation og -service",
    "sg:phone":"+45 65 91 54 46",
    "sg:postcode":"5000",
    "sg:province":"Danmark",
    "wof:name":"Auto Rep.",
    "wof:placetype":"venue"
},
  "geometry": {"coordinates":[10.4158754349,55.4025039673],"type":"Point"}
}