{
  "type": "Feature",
  "properties": {
    "addr:full":"Ceresvej 3 Frederiksberg Danmark 1863",
    "addr:housenumber":"3;1863",
    "addr:street":"Ceresvej",
    "iso:country":"DK",
    "sg:address":"Ceresvej 3",
    "sg:city":"Frederiksberg",
    "sg:orig_category":"Psykoterapi",
    "sg:phone":"+45 33 23 13 08",
    "sg:postcode":"1863",
    "sg:province":"Danmark",
    "wof:name":"Birte Glud",
    "wof:placetype":"venue"
},
  "geometry": {"coordinates":[12.5369758606,55.6792869568],"type":"Point"}
}