{
  "type": "Feature",
  "properties": {
    "addr:full":"Ajstrupvej 8 Malling Danmark 8340",
    "addr:housenumber":"8",
    "addr:postcode":"8340",
    "addr:street":"Ajstrupvej",
    "iso:country":"DK",
    "sg:address":"Ajstrupvej 8",
    "sg:city":"Malling",
    "sg:orig_category":"Servicestationer",
    "sg:phone":"+45 86 93 10 39",
    "sg:postcode":"8340",
    "sg:province":"Danmark",
    "wof:name":"Q8 Malling",
    "wof:placetype":"venue"
},
  "geometry": {"coordinates":[10.1930503845,56.0379524231],"type":"Point"}
}