{
  "type": "Feature",
  "properties": {
    "iso:country":"DK",
    "sg:address":"Daphnesvej 6",
    "sg:city":"Skagen",
    "sg:orig_category":"Genbrugsbutikker",
    "sg:phone":"+45 98 45 10 25",
    "sg:postcode":"9990",
    "sg:province":"Danmark",
    "wof:name":"Frelsens H\u00e6rs T\u00f8jmarked",
    "wof:placetype":"venue"
},
  "geometry": {"coordinates":[10.5982885361,57.7253875732],"type":"Point"}
}