{
  "type": "Feature",
  "properties": {
    "addr:full":"Ryetsvej 2, Kilden Frederikshavn Danmark 9900",
    "addr:housenumber":"2",
    "addr:postcode":"9900",
    "addr:street":"Ryetsvej;Kilden",
    "iso:country":"DK",
    "sg:address":"Ryetsvej 2, Kilden",
    "sg:city":"Frederikshavn",
    "sg:orig_category":"Zoneterapeuter",
    "sg:phone":"+45 98 43 56 55",
    "sg:postcode":"9900",
    "sg:province":"Danmark",
    "wof:name":"Christoffersen, Margith",
    "wof:placetype":"venue"
},
  "geometry": {"coordinates":[10.5362997055,57.4396400452],"type":"Point"}
}