{
  "type": "Feature",
  "properties": {
    "addr:full":"Karlslunde Strandvej 56 Karlslunde Danmark 2690",
    "addr:housenumber":"56",
    "addr:postcode":"2690",
    "addr:street":"Karlslunde Strandvej",
    "iso:country":"DK",
    "sg:address":"Karlslunde Strandvej 56",
    "sg:city":"Karlslunde",
    "sg:orig_category":"Vinduespolering",
    "sg:phone":"+45 46 15 37 16",
    "sg:postcode":"2690",
    "sg:province":"Danmark",
    "wof:name":"SPS Erhvervsreng\u00f8ring ApS",
    "wof:placetype":"venue"
},
  "geometry": {"coordinates":[12.2609081268,55.5598907471],"type":"Point"}
}