{
  "type": "Feature",
  "properties": {
    "addr:full":"Fj\u00e6llebrosvejen 79 A Faaborg Danmark 5600",
    "addr:housenumber":"79 a",
    "addr:postcode":"5600",
    "addr:street":"Fjaellebrosvejen",
    "iso:country":"DK",
    "sg:address":"Fj\u00e6llebrosvejen 79 A",
    "sg:city":"Faaborg",
    "sg:orig_category":"Havne",
    "sg:postcode":"5600",
    "sg:province":"Danmark",
    "wof:name":"Fjellebroen Havn A/S",
    "wof:placetype":"venue"
},
  "geometry": {"coordinates":[10.3824110031,55.0602722168],"type":"Point"}
}