{
  "type": "Feature",
  "properties": {
    "addr:full":"Fmd.: Vagn Angelo Christensen, Bygmarken 26 Kolind Danmark 8560",
    "addr:housenumber":"26",
    "addr:postcode":"8560",
    "addr:street":"Bygmarken",
    "iso:country":"DK",
    "sg:address":"Fmd.: Vagn Angelo Christensen, Bygmarken 26",
    "sg:city":"Kolind",
    "sg:orig_category":"\u00c3\u2020ldreorganisationer og klubber",
    "sg:phone":"+45 86 39 29 60",
    "sg:postcode":"8560",
    "sg:province":"Danmark",
    "wof:name":"\u00c6ldre Sagen",
    "wof:placetype":"venue"
},
  "geometry": {"coordinates":[10.5873975754,56.3618812561],"type":"Point"}
}