{
  "type": "Feature",
  "properties": {
    "addr:full":"H\u00e5rb\u00f8lle Bro 4, H\u00e5rb\u00f8lle Askeby Danmark 4792",
    "addr:housenumber":"4",
    "addr:postcode":"4792",
    "addr:street":"Haarbolle Bro",
    "iso:country":"DK",
    "sg:address":"H\u00e5rb\u00f8lle Bro 4, H\u00e5rb\u00f8lle",
    "sg:city":"Askeby",
    "sg:orig_category":"Zoneterapeuter",
    "sg:phone":"+45 55 81 76 95",
    "sg:postcode":"4792",
    "sg:province":"Danmark",
    "wof:name":"Larsen, Kirsten",
    "wof:placetype":"venue"
},
  "geometry": {"coordinates":[12.1452455521,54.8838500977],"type":"Point"}
}