{
  "type": "Feature",
  "properties": {
    "iso:country":"DK",
    "sg:address":"J\u00e6gersborg All\u00e9 31",
    "sg:city":"Charlottenlund",
    "sg:classifiers":[
        {
            "category":"Banks & Credit Unions",
            "subcategory":"Bank",
            "type":"Services"
        }
    ],
    "sg:phone":"+45 39 96 56 00",
    "sg:postcode":"2920",
    "sg:province":"Danmark",
    "sg:tags":[
        "banker"
    ],
    "sg:website":"www.danskebank.dk",
    "wof:name":"Danske Bank",
    "wof:placetype":"venue"
},
  "geometry": {"coordinates":[12.57212,55.753262],"type":"Point"}
}