{
  "type": "Feature",
  "properties": {
    "addr:full":"Fmd.: Lindy Kaiser, Vangevej 7, Soderup T\u00f8ll\u00f8se Danmark 4340",
    "addr:housenumber":"7",
    "addr:postcode":"4340",
    "addr:street":"Vangevej",
    "iso:country":"DK",
    "sg:address":"Fmd.: Lindy Kaiser, Vangevej 7, Soderup",
    "sg:city":"T\u00f8ll\u00f8se",
    "sg:orig_category":"Hobbybetonede foreninger",
    "sg:phone":"+45 59 18 58 78",
    "sg:postcode":"4340",
    "sg:province":"Danmark",
    "wof:name":"Selskabet De Danske Forsvarsbr\u00f8dre for T\u00f8ll\u00f8se og omegn",
    "wof:placetype":"venue"
},
  "geometry": {"coordinates":[11.5867519379,55.6034011841],"type":"Point"}
}