{
  "type": "Feature",
  "properties": {
    "addr:full":"Vestergade 14 Holsted Danmark 6670",
    "addr:housenumber":"14",
    "addr:postcode":"6670",
    "addr:street":"Vestergade",
    "iso:country":"DK",
    "sg:address":"Vestergade 14",
    "sg:city":"Holsted",
    "sg:orig_category":"Psykoterapi",
    "sg:phone":"+45 75 39 36 67",
    "sg:postcode":"6670",
    "sg:province":"Danmark",
    "wof:name":"Ziemelis, Lisbeth",
    "wof:placetype":"venue"
},
  "geometry": {"coordinates":[8.9151268005,55.5121002197],"type":"Point"}
}