{
  "type": "Feature",
  "properties": {
    "addr:full":"Hovborgvej 104, Hesselho Grindsted Danmark 7200",
    "addr:housenumber":"104",
    "addr:postcode":"7200",
    "addr:street":"Hovborgvej",
    "iso:country":"DK",
    "sg:address":"Hovborgvej 104, Hesselho",
    "sg:city":"Grindsted",
    "sg:orig_category":"Murermestre",
    "sg:phone":"+45 75 33 72 67",
    "sg:postcode":"7200",
    "sg:province":"Danmark",
    "wof:name":"BJ Murer",
    "wof:placetype":"venue"
},
  "geometry": {"coordinates":[8.9288702011,55.7560272217],"type":"Point"}
}