{
  "type": "Feature",
  "properties": {
    "addr:full":"S\u00f8ndergade 48 Vamdrup Danmark 6580",
    "addr:housenumber":"48",
    "addr:postcode":"6580",
    "addr:street":"Sondergade",
    "iso:country":"DK",
    "sg:address":"S\u00f8ndergade 48",
    "sg:city":"Vamdrup",
    "sg:orig_category":"Autoforhandlere",
    "sg:phone":"+45 75 58 11 46",
    "sg:postcode":"6580",
    "sg:province":"Danmark",
    "wof:name":"Vamdrup Autocenter",
    "wof:placetype":"venue"
},
  "geometry": {"coordinates":[9.2764081955,55.4220619202],"type":"Point"}
}