{
  "type": "Feature",
  "properties": {
    "addr:full":"v/Merethe Gejl, Skovvej 15 Jyllinge Danmark 4040",
    "addr:housenumber":"15",
    "addr:postcode":"4040",
    "addr:street":"Skovvej",
    "iso:country":"DK",
    "sg:address":"v/Merethe Gejl, Skovvej 15",
    "sg:city":"Jyllinge",
    "sg:orig_category":"Grundejerforeninger",
    "sg:phone":"+45 46 73 15 38",
    "sg:postcode":"4040",
    "sg:province":"Danmark",
    "wof:name":"Grundejerforeningen Jyllinge Skov",
    "wof:placetype":"venue"
},
  "geometry": {"coordinates":[12.1163625717,55.7643737793],"type":"Point"}
}