{
  "type": "Feature",
  "properties": {
    "addr:full":"Valby Langgade 235 Valby Danmark 2500",
    "addr:housenumber":"235",
    "addr:postcode":"2500",
    "addr:street":"Valby Langgade",
    "iso:country":"DK",
    "sg:address":"Valby Langgade 235",
    "sg:city":"Valby",
    "sg:orig_category":"Malermestre",
    "sg:phone":"+45 36 30 37 14",
    "sg:postcode":"2500",
    "sg:province":"Danmark",
    "wof:name":"M\u00f8ller, Torben V.",
    "wof:placetype":"venue"
},
  "geometry": {"coordinates":[12.4850616455,55.6713981628],"type":"Point"}
}