{
  "type": "Feature",
  "properties": {
    "addr:full":"Fmd.: Peter Koustrup, Lunbakkevej 14, \u00d8rup Balle Danmark 8444",
    "addr:housenumber":"14",
    "addr:postcode":"8444",
    "addr:street":"Lunbakkevej;Orup",
    "iso:country":"DK",
    "sg:address":"Fmd.: Peter Koustrup, Lunbakkevej 14, \u00d8rup",
    "sg:city":"Balle",
    "sg:orig_category":"Spejderkorps",
    "sg:phone":"+45 86 36 35 48",
    "sg:postcode":"8444",
    "sg:province":"Danmark",
    "wof:name":"KFUM-Spejderne, Tirstrup",
    "wof:placetype":"venue"
},
  "geometry": {"coordinates":[10.8090896606,56.31640625],"type":"Point"}
}