{
  "type": "Feature",
  "properties": {
    "addr:full":"Randersvej 21 Viborg Danmark 8800",
    "addr:housenumber":"21",
    "addr:postcode":"8800",
    "addr:street":"Randersvej",
    "iso:country":"DK",
    "sg:address":"Randersvej 21",
    "sg:city":"Viborg",
    "sg:orig_category":"Grillbarer",
    "sg:phone":"+45 86 67 57 55",
    "sg:postcode":"8800",
    "sg:province":"Danmark",
    "wof:name":"Chicken & Burger",
    "wof:placetype":"venue"
},
  "geometry": {"coordinates":[9.4204082489,56.4511528015],"type":"Point"}
}