{
  "type": "Feature",
  "properties": {
    "addr:full":"v/ Ruben Andersen, Pilev\u00e6nget 2 Odder Danmark 8300",
    "addr:housenumber":"2",
    "addr:postcode":"8300",
    "addr:street":"Pilevaenget",
    "iso:country":"DK",
    "sg:address":"v/ Ruben Andersen, Pilev\u00e6nget 2",
    "sg:city":"Odder",
    "sg:orig_category":"Kulturelle foreninger",
    "sg:phone":"+45 86 54 25 56",
    "sg:postcode":"8300",
    "sg:province":"Danmark",
    "wof:name":"Foreningen Norden",
    "wof:placetype":"venue"
},
  "geometry": {"coordinates":[10.1497612,55.9733161926],"type":"Point"}
}