{
  "type": "Feature",
  "properties": {
    "addr:full":"Sl\u00e5envej 47, Taulov Fredericia Danmark 7000",
    "addr:housenumber":"47",
    "addr:postcode":"7000",
    "addr:street":"Slaaenvej",
    "iso:country":"DK",
    "sg:address":"Sl\u00e5envej 47, Taulov",
    "sg:city":"Fredericia",
    "sg:orig_category":"Zoneterapeuter",
    "sg:phone":"+45 75 56 43 56",
    "sg:postcode":"7000",
    "sg:province":"Danmark",
    "wof:name":"Taulov Sol & Zoneterapi",
    "wof:placetype":"venue"
},
  "geometry": {"coordinates":[9.7591047287,55.566368103],"type":"Point"}
}