{
  "type": "Feature",
  "properties": {
    "iso:country":"DK",
    "sg:address":"Klingeberg 2 - 4",
    "sg:city":"Slagelse",
    "sg:orig_category":"Arbejdsformidling",
    "sg:phone":"+45 58 55 16 00",
    "sg:postcode":"4200",
    "sg:province":"Danmark",
    "wof:name":"AF-Vestsj\u00e6lland, Servicekontoret i Slagelse.",
    "wof:placetype":"venue"
},
  "geometry": {"coordinates":[11.3545179367,55.4022789001],"type":"Point"}
}