{
  "type": "Feature",
  "properties": {
    "addr:full":"Kuldyssen 16 Taastrup Danmark 2630",
    "addr:housenumber":"16",
    "addr:postcode":"2630",
    "addr:street":"Kuldyssen",
    "iso:country":"DK",
    "sg:address":"Kuldyssen 16",
    "sg:city":"Taastrup",
    "sg:orig_category":"Autoreservedele",
    "sg:phone":"+45 70 10 10 52",
    "sg:postcode":"2630",
    "sg:province":"Danmark",
    "sg:website":"www.hoyer-autodele.dk",
    "wof:name":"H\u00f8yer Autodele Taastrup ApS",
    "wof:placetype":"venue"
},
  "geometry": {"coordinates":[12.2875366211,55.6486091614],"type":"Point"}
}