{
  "type": "Feature",
  "properties": {
    "addr:full":"Vejlevej 5 Jelling Danmark 7300",
    "addr:housenumber":"5",
    "addr:postcode":"7300",
    "addr:street":"Vejlevej",
    "iso:country":"DK",
    "sg:address":"Vejlevej 5",
    "sg:city":"Jelling",
    "sg:orig_category":"Ejendomshandel",
    "sg:phone":"+45 70 25 01 05",
    "sg:postcode":"7300",
    "sg:province":"Danmark",
    "wof:name":"Boligbutikken Jelling",
    "wof:placetype":"venue"
},
  "geometry": {"coordinates":[9.4220380783,55.7562026978],"type":"Point"}
}