{
  "type": "Feature",
  "properties": {
    "iso:country":"DK",
    "sg:address":"Svendborgvej 50 - 54",
    "sg:city":"Ullerslev",
    "sg:orig_category":"Supermarkeder",
    "sg:phone":"+45 65 35 14 71",
    "sg:postcode":"5540",
    "sg:province":"Danmark",
    "wof:name":"Aktiv Super",
    "wof:placetype":"venue"
},
  "geometry": {"coordinates":[10.6684856415,55.3553161621],"type":"Point"}
}