{
  "type": "Feature",
  "properties": {
    "addr:full":"Vandv\u00e6rksvej 37 Greve Danmark 2670",
    "addr:housenumber":"37",
    "addr:postcode":"2670",
    "addr:street":"Vandvaerksvej",
    "iso:country":"DK",
    "sg:address":"Vandv\u00e6rksvej 37",
    "sg:city":"Greve",
    "sg:orig_category":"Feriekolonier",
    "sg:phone":"+45 43 97 79 90",
    "sg:postcode":"2670",
    "sg:province":"Danmark",
    "wof:name":"Lejrskolen Hulemoseg\u00e5rd",
    "wof:placetype":"venue"
},
  "geometry": {"coordinates":[12.3086805344,55.5871658325],"type":"Point"}
}