{
  "type": "Feature",
  "properties": {
    "addr:full":"Markvej 95 A Skagen Danmark 9990",
    "addr:housenumber":"95 a",
    "addr:postcode":"9990",
    "addr:street":"Markvej",
    "iso:country":"DK",
    "sg:address":"Markvej 95 A",
    "sg:city":"Skagen",
    "sg:orig_category":"Murermestre",
    "sg:phone":"+45 98 44 31 63",
    "sg:postcode":"9990",
    "sg:province":"Danmark",
    "wof:name":"Christensen ApS, Ib",
    "wof:placetype":"venue"
},
  "geometry": {"coordinates":[10.5810966492,57.7254066467],"type":"Point"}
}