{
  "type": "Feature",
  "properties": {
    "addr:full":"Solbjerg Have 4 B Frederiksberg Danmark 2000",
    "addr:housenumber":"4 b",
    "addr:postcode":"2000",
    "addr:street":"Solbjerg Have",
    "iso:country":"DK",
    "sg:address":"Solbjerg Have 4 B",
    "sg:city":"Frederiksberg",
    "sg:orig_category":"Sammensatte institutioner",
    "sg:phone":"+45 38 86 20 73",
    "sg:postcode":"2000",
    "sg:province":"Danmark",
    "wof:name":"Planeten, B\u00f8rnehuset",
    "wof:placetype":"venue"
},
  "geometry": {"coordinates":[12.5072841644,55.6821327209],"type":"Point"}
}