{
  "type": "Feature",
  "properties": {
    "addr:full":"Laasbyvej 32 Galten Danmark 8464",
    "addr:housenumber":"32",
    "addr:postcode":"8464",
    "addr:street":"Laasbyvej",
    "iso:country":"DK",
    "sg:address":"Laasbyvej 32",
    "sg:city":"Galten",
    "sg:orig_category":"Hundepensioner",
    "sg:phone":"+45 86 94 41 71",
    "sg:postcode":"8464",
    "sg:province":"Danmark",
    "wof:name":"Holiday, Pension",
    "wof:placetype":"venue"
},
  "geometry": {"coordinates":[9.8899059296,56.159828186],"type":"Point"}
}