{
  "type": "Feature",
  "properties": {
    "iso:country":"DK",
    "sg:address":"Borgergade 134",
    "sg:city":"K\u00f8benhavn",
    "sg:orig_category":"Grillbarer",
    "sg:phone":"+45 33 15 79 88",
    "sg:postcode":"1300",
    "sg:province":"Danmark",
    "wof:name":"King Tut Borgergade",
    "wof:placetype":"venue"
},
  "geometry": {"coordinates":[12.5867004395,55.6822013855],"type":"Point"}
}