{
  "type": "Feature",
  "properties": {
    "iso:country":"DK",
    "sg:address":"Havnevej 43",
    "sg:city":"Roskilde",
    "sg:classifiers":[
        {
            "category":"Restaurant",
            "type":"Food & Drink"
        }
    ],
    "sg:phone":"+45 46 32 50 45",
    "sg:postcode":"4000",
    "sg:province":"Danmark",
    "sg:website":"www.store-bors.dk",
    "wof:name":"Store B\u00f8rs",
    "wof:placetype":"venue"
},
  "geometry": {"coordinates":[12.0767726898,55.6496925354],"type":"Point"}
}