{
  "type": "Feature",
  "properties": {
    "iso:country":"DK",
    "sg:address":"\u00d8lsemaglevej 5",
    "sg:city":"K\u00f8ge",
    "sg:orig_category":"Tandteknikere, Kliniske",
    "sg:phone":"+45 56 65 42 16",
    "sg:postcode":"4600",
    "sg:province":"Danmark",
    "wof:name":"Brodersen ApS, Kirsten",
    "wof:placetype":"venue"
},
  "geometry": {"coordinates":[12.1894874573,55.492389679],"type":"Point"}
}