{
  "type": "Feature",
  "properties": {
    "addr:full":"Helgesvej 15 Frederiksberg Danmark 2000",
    "addr:housenumber":"15",
    "addr:postcode":"2000",
    "addr:street":"Helgesvej",
    "iso:country":"DK",
    "sg:address":"Helgesvej 15",
    "sg:city":"Frederiksberg",
    "sg:orig_category":"Lejerforeninger",
    "sg:phone":"+45 38 33 51 00",
    "sg:postcode":"2000",
    "sg:province":"Danmark",
    "wof:name":"Lejernes Landsorganisation, Distrikt Frederiksberg",
    "wof:placetype":"venue"
},
  "geometry": {"coordinates":[12.5347690582,55.6838760376],"type":"Point"}
}