{
  "type": "Feature",
  "properties": {
    "iso:country":"DK",
    "sg:address":"Jernbanegade 16",
    "sg:city":"Aalborg",
    "sg:orig_category":"Legestuer",
    "sg:phone":"+45 99 31 52 90",
    "sg:postcode":"9000",
    "sg:province":"Danmark",
    "wof:name":"Legestuen Solstr\u00e5len (Bethesda)",
    "wof:placetype":"venue"
},
  "geometry": {"coordinates":[9.9157876968,57.0466575623],"type":"Point"}
}