{
  "type": "Feature",
  "properties": {
    "addr:full":"Plastv\u00e6nget 6 Hadsund Danmark 9560",
    "addr:housenumber":"6",
    "addr:postcode":"9560",
    "addr:street":"Plastvaenget",
    "iso:country":"DK",
    "sg:address":"Plastv\u00e6nget 6",
    "sg:city":"Hadsund",
    "sg:orig_category":"Autoforhandlere",
    "sg:phone":"+45 98 57 16 77",
    "sg:postcode":"9560",
    "sg:province":"Danmark",
    "sg:website":"www.opel-hadsund.dk",
    "wof:name":"Hadsund Bilcenter A/S",
    "wof:placetype":"venue"
},
  "geometry": {"coordinates":[10.115904808,56.7150764465],"type":"Point"}
}