{
  "type": "Feature",
  "properties": {
    "iso:country":"DK",
    "sg:address":"Gentoftegade 39",
    "sg:city":"Gentofte",
    "sg:orig_category":"Biografer",
    "sg:phone":"+45 39 65 33 50",
    "sg:postcode":"2820",
    "sg:province":"Danmark",
    "wof:name":"Gentofte Kino",
    "wof:placetype":"venue"
},
  "geometry": {"coordinates":[12.541242,55.74715],"type":"Point"}
}