{
  "type": "Feature",
  "properties": {
    "addr:full":"Errits\u00f8 Bygade 1, Errits\u00f8 Fredericia Danmark 7000",
    "addr:housenumber":"1",
    "addr:postcode":"7000",
    "addr:street":"Erritso Bygade",
    "iso:country":"DK",
    "sg:address":"Errits\u00f8 Bygade 1, Errits\u00f8",
    "sg:city":"Fredericia",
    "sg:orig_category":"Kirker",
    "sg:postcode":"7000",
    "sg:province":"Danmark",
    "wof:name":"Errits\u00f8 Kirke",
    "wof:placetype":"venue"
},
  "geometry": {"coordinates":[9.7591047287,55.566368103],"type":"Point"}
}