{
  "type": "Feature",
  "properties": {
    "iso:country":"DK",
    "sg:address":"Rebslagervej 4",
    "sg:city":"Holb\u00e6k",
    "sg:classifiers":[
        {
            "category":"Utilities",
            "subcategory":"Refuse",
            "type":"Services"
        }
    ],
    "sg:phone":"+45 59 43 26 54",
    "sg:postcode":"4300",
    "sg:province":"Danmark",
    "sg:tags":[
        "catering"
    ],
    "wof:name":"Holgros Catering A/S",
    "wof:placetype":"venue"
},
  "geometry": {"coordinates":[76.3070983887,14.277130127],"type":"Point"}
}