{
  "type": "Feature",
  "properties": {
    "iso:country":"DK",
    "sg:address":"Gesagervej 68",
    "sg:city":"Hedensted",
    "sg:orig_category":"Solcentre",
    "sg:phone":"+45 75 89 29 00",
    "sg:postcode":"8722",
    "sg:province":"Danmark",
    "sg:website":"www.svom.dk",
    "wof:name":"Solcenter",
    "wof:placetype":"venue"
},
  "geometry": {"coordinates":[9.6906137466,55.781539917],"type":"Point"}
}