{
  "type": "Feature",
  "properties": {
    "iso:country":"DK",
    "sg:address":"G\u00f8rl\u00f8sevej 15, Uvelse",
    "sg:city":"Slangerup",
    "sg:orig_category":"Oliefyr og service",
    "sg:phone":"+45 48 27 72 72",
    "sg:postcode":"3550",
    "sg:province":"Danmark",
    "sg:website":"www.kbjoliefyr.dk",
    "wof:name":"J\u00f8rgensen Oliefyrsservice ApS, K.B.",
    "wof:placetype":"venue"
},
  "geometry": {"coordinates":[12.1717596054,55.8460769653],"type":"Point"}
}