{
  "type": "Feature",
  "properties": {
    "addr:full":"v/ Asta Simonsen, Rodelundvej 9 Them Danmark 8653",
    "addr:housenumber":"9",
    "addr:postcode":"8653",
    "addr:street":"Rodelundvej",
    "iso:country":"DK",
    "sg:address":"v/ Asta Simonsen, Rodelundvej 9",
    "sg:city":"Them",
    "sg:orig_category":"\u00c3\u2020ldreorganisationer og klubber",
    "sg:phone":"+45 86 84 70 24",
    "sg:postcode":"8653",
    "sg:province":"Danmark",
    "wof:name":"Them Pensionistklub",
    "wof:placetype":"venue"
},
  "geometry": {"coordinates":[9.5489425659,56.0950088501],"type":"Point"}
}