{
  "type": "Feature",
  "properties": {
    "addr:full":"Skellet 15 N\u00e6stved Danmark 4700",
    "addr:housenumber":"15",
    "addr:postcode":"4700",
    "addr:street":"Skellet",
    "iso:country":"DK",
    "sg:address":"Skellet 15",
    "sg:city":"N\u00e6stved",
    "sg:orig_category":"Sportsartikler",
    "sg:phone":"+45 55 77 34 33",
    "sg:postcode":"4700",
    "sg:province":"Danmark",
    "sg:website":"www.ski-sport.dk",
    "wof:name":"SkiSport",
    "wof:placetype":"venue"
},
  "geometry": {"coordinates":[11.7523651123,55.2282867432],"type":"Point"}
}