{
  "type": "Feature",
  "properties": {
    "addr:full":"Dyndetvej 11-13 Borup Danmark 4140",
    "addr:postcode":"11-13;4140",
    "addr:street":"Dyndetvej",
    "iso:country":"DK",
    "sg:address":"Dyndetvej 11-13",
    "sg:city":"Borup",
    "sg:orig_category":"Planteskoler",
    "sg:phone":"+45 57 52 62 11",
    "sg:postcode":"4140",
    "sg:province":"Danmark",
    "wof:name":"Treschows Planteskole",
    "wof:placetype":"venue"
},
  "geometry": {"coordinates":[11.9530382156,55.4752159119],"type":"Point"}
}