{
  "type": "Feature",
  "properties": {
    "addr:full":"Alsvej 5 Middelfart Danmark 5500",
    "addr:housenumber":"5",
    "addr:postcode":"5500",
    "addr:street":"Alsvej",
    "iso:country":"DK",
    "sg:address":"Alsvej 5",
    "sg:city":"Middelfart",
    "sg:orig_category":"Autoreparation og -service",
    "sg:phone":"+45 64 41 49 36",
    "sg:postcode":"5500",
    "sg:province":"Danmark",
    "wof:name":"Villy's Auto",
    "wof:placetype":"venue"
},
  "geometry": {"coordinates":[9.7617101669,55.5009307861],"type":"Point"}
}