{
  "type": "Feature",
  "properties": {
    "addr:full":"Christian Petersen, S\u00f8ndergade 7 Bredebro Danmark 6261",
    "addr:housenumber":"7",
    "addr:postcode":"6261",
    "addr:street":"Sondergade",
    "iso:country":"DK",
    "sg:address":"Christian Petersen, S\u00f8ndergade 7",
    "sg:city":"Bredebro",
    "sg:orig_category":"Hobbybetonede foreninger",
    "sg:phone":"+45 74 71 15 42",
    "sg:postcode":"6261",
    "sg:province":"Danmark",
    "wof:name":"Arbejdernes Radio- og Fjernsynsklub, T\u00f8nder afd.",
    "wof:placetype":"venue"
},
  "geometry": {"coordinates":[8.8284835815,55.0566978455],"type":"Point"}
}