{
  "type": "Feature",
  "properties": {
    "iso:country":"DK",
    "sg:address":"Vestergade 8",
    "sg:city":"Skanderborg",
    "sg:orig_category":"Begravelsesforretninger",
    "sg:phone":"+45 86 52 49 69",
    "sg:postcode":"8660",
    "sg:province":"Danmark",
    "wof:name":"Skanderborg Ligbr\u00e6ndings- og Begravelsesforretning",
    "wof:placetype":"venue"
},
  "geometry": {"coordinates":[9.930922,56.032421],"type":"Point"}
}