{
  "type": "Feature",
  "properties": {
    "addr:full":"Gotlandsvej 13 Horsens Danmark 8700",
    "addr:housenumber":"13",
    "addr:postcode":"8700",
    "addr:street":"Gotlandsvej",
    "iso:country":"DK",
    "sg:address":"Gotlandsvej 13",
    "sg:city":"Horsens",
    "sg:orig_category":"Malermestre",
    "sg:phone":"+45 75 64 22 11",
    "sg:postcode":"8700",
    "sg:province":"Danmark",
    "sg:website":"www.maler-horsens.dk",
    "wof:name":"malernes cooperative forretning a/s",
    "wof:placetype":"venue"
},
  "geometry": {"coordinates":[9.8093614578,55.8523979187],"type":"Point"}
}