{
  "type": "Feature",
  "properties": {
    "addr:full":"Alsvej 1 Nyborg Danmark 5800",
    "addr:housenumber":"1",
    "addr:postcode":"5800",
    "addr:street":"Alsvej",
    "iso:country":"DK",
    "sg:address":"Alsvej 1",
    "sg:city":"Nyborg",
    "sg:orig_category":"Autoreparation og -service",
    "sg:phone":"+45 65 31 08 81",
    "sg:postcode":"5800",
    "sg:province":"Danmark",
    "wof:name":"Vindinge Autov\u00e6rksted ApS",
    "wof:placetype":"venue"
},
  "geometry": {"coordinates":[10.750910759,55.3105506897],"type":"Point"}
}