{
  "type": "Feature",
  "properties": {
    "addr:full":"Vestergade 23 Svendborg Danmark 5700",
    "addr:housenumber":"23",
    "addr:postcode":"5700",
    "addr:street":"Vestergade",
    "iso:country":"DK",
    "sg:address":"Vestergade 23",
    "sg:city":"Svendborg",
    "sg:classifiers":[
        {
            "category":"Communications",
            "type":"Services"
        }
    ],
    "sg:phone":"+45 62 22 28 28",
    "sg:postcode":"5700",
    "sg:province":"Danmark",
    "sg:tags":[
        "radio-",
        "og",
        "tv-stationer"
    ],
    "sg:website":"www.radioaktiv.dk",
    "wof:name":"Radio Aktiv",
    "wof:placetype":"venue"
},
  "geometry": {"coordinates":[10.6040802002,55.0593719482],"type":"Point"}
}