{
  "type": "Feature",
  "properties": {
    "addr:full":"Rendeb\u00e6ksvej 8, Sm\u00f8rumnedre Sm\u00f8rum Danmark 2765",
    "addr:housenumber":"8",
    "addr:postcode":"2765",
    "addr:street":"Rendebaeksvej",
    "iso:country":"DK",
    "sg:address":"Rendeb\u00e6ksvej 8, Sm\u00f8rumnedre",
    "sg:city":"Sm\u00f8rum",
    "sg:orig_category":"Psykologer, praktiserende",
    "sg:phone":"+45 44 65 14 52",
    "sg:postcode":"2765",
    "sg:province":"Danmark",
    "wof:name":"Flindt, Tanja Gudbjerg",
    "wof:placetype":"venue"
},
  "geometry": {"coordinates":[-89.99810791020001,38.1321372986],"type":"Point"}
}