{
  "type": "Feature",
  "properties": {
    "addr:full":"v/Bettina Bech, Skt. Anna Gade 47, 1. th. \u00c5rhus C Danmark 8000",
    "addr:housenumber":"47 1 th.",
    "addr:postcode":"8000",
    "addr:street":"Skt. Anna Gade",
    "iso:country":"DK",
    "sg:address":"v/Bettina Bech, Skt. Anna Gade 47, 1. th.",
    "sg:city":"\u00c5rhus C",
    "sg:orig_category":"Spejderkorps",
    "sg:phone":"+45 86 76 02 78",
    "sg:postcode":"8000",
    "sg:province":"Danmark",
    "wof:name":"KFUM-Spejderne, Moesg\u00e5rd Division Sydlige \u00c5rhus",
    "wof:placetype":"venue"
},
  "geometry": {"coordinates":[16.7075405121,58.3486099243],"type":"Point"}
}