{
  "type": "Feature",
  "properties": {
    "addr:full":"v/ Kai Winckelmann, Tulipanvej 22 Roskilde Danmark 4000",
    "addr:housenumber":"22",
    "addr:postcode":"4000",
    "addr:street":"Tulipanvej",
    "iso:country":"DK",
    "sg:address":"v/ Kai Winckelmann, Tulipanvej 22",
    "sg:city":"Roskilde",
    "sg:orig_category":"Grundejerforeninger",
    "sg:phone":"+45 46 36 47 19",
    "sg:postcode":"4000",
    "sg:province":"Danmark",
    "wof:name":"Grundejerforeningen for Motel- og Tulipanvej",
    "wof:placetype":"venue"
},
  "geometry": {"coordinates":[12.0909376144,55.6404838562],"type":"Point"}
}