{
  "type": "Feature",
  "properties": {
    "addr:full":"Sportsvej 3 Holstebro Danmark 7500",
    "addr:housenumber":"3",
    "addr:postcode":"7500",
    "addr:street":"Sportsvej",
    "iso:country":"DK",
    "sg:address":"Sportsvej 3",
    "sg:city":"Holstebro",
    "sg:orig_category":"Ure og urmagere",
    "sg:phone":"+45 97 42 87 11",
    "sg:postcode":"7500",
    "sg:province":"Danmark",
    "wof:name":"Jensen, O. K.",
    "wof:placetype":"venue"
},
  "geometry": {"coordinates":[8.6264734268,56.3631057739],"type":"Point"}
}