{
  "type": "Feature",
  "properties": {
    "addr:full":"Rug\u00e5rdsvej 5 Odense C Danmark 5000",
    "addr:housenumber":"5",
    "addr:postcode":"5000",
    "addr:street":"Rugaardsvej",
    "iso:country":"DK",
    "sg:address":"Rug\u00e5rdsvej 5",
    "sg:city":"Odense C",
    "sg:orig_category":"Slagterier",
    "sg:phone":"+45 66 13 05 00",
    "sg:postcode":"5000",
    "sg:province":"Danmark",
    "wof:name":"Danish Crown",
    "wof:placetype":"venue"
},
  "geometry": {"coordinates":[10.3780384064,55.3993148804],"type":"Point"}
}