{
  "type": "Feature",
  "properties": {
    "addr:full":"Algade 18 Nyk\u00f8bing Danmark 4500",
    "addr:housenumber":"18",
    "addr:postcode":"4500",
    "addr:street":"Algade",
    "iso:country":"DK",
    "sg:address":"Algade 18",
    "sg:city":"Nyk\u00f8bing",
    "sg:orig_category":"Kiosker",
    "sg:phone":"+45 59 91 02 75",
    "sg:postcode":"4500",
    "sg:province":"Danmark",
    "wof:name":"O. K. Kiosken",
    "wof:placetype":"venue"
},
  "geometry": {"coordinates":[16.0969600677,78.3159866333],"type":"Point"}
}