{
  "type": "Feature",
  "properties": {
    "addr:full":"Fmd.: Ib Salling S\u00f8nder, Hovedgaden 23, Durup Roslev Danmark 7870",
    "addr:housenumber":"23",
    "addr:postcode":"7870",
    "addr:street":"Hovedgaden;Durup",
    "iso:country":"DK",
    "sg:address":"Fmd.: Ib Salling S\u00f8nder, Hovedgaden 23, Durup",
    "sg:city":"Roslev",
    "sg:orig_category":"Borger- og beboerforeninger",
    "sg:phone":"+45 97 59 20 84",
    "sg:postcode":"7870",
    "sg:province":"Danmark",
    "wof:name":"Durup Borger- og H\u00e5ndv\u00e6rkerforening",
    "wof:placetype":"venue"
},
  "geometry": {"coordinates":[8.8715353012,56.7570304871],"type":"Point"}
}