{
  "type": "Feature",
  "properties": {
    "iso:country":"DK",
    "sg:address":"Voldtoftevej 41, Fleml\u00f8se",
    "sg:city":"Glamsbjerg",
    "sg:orig_category":"Blikkenslagere",
    "sg:phone":"+45 40 52 19 31",
    "sg:postcode":"5620",
    "sg:province":"Danmark",
    "wof:name":"Voldtofte Blik",
    "wof:placetype":"venue"
},
  "geometry": {"coordinates":[10.10525,55.278332],"type":"Point"}
}