{
  "type": "Feature",
  "properties": {
    "addr:full":"S\u00f8ndergade 1 B, 1. Silkeborg Danmark 8600",
    "addr:housenumber":"1 b 1",
    "addr:postcode":"8600",
    "addr:street":"Sondergade",
    "iso:country":"DK",
    "sg:address":"S\u00f8ndergade 1 B, 1.",
    "sg:city":"Silkeborg",
    "sg:orig_category":"Zoneterapeuter",
    "sg:phone":"+45 86 81 30 15",
    "sg:postcode":"8600",
    "sg:province":"Danmark",
    "wof:name":"Elholm, Tove",
    "wof:placetype":"venue"
},
  "geometry": {"coordinates":[9.5495290756,56.1689910889],"type":"Point"}
}