{
  "type": "Feature",
  "properties": {
    "addr:full":"Ravnse Byvej 22 N\u00f8rre Alslev Danmark 4840",
    "addr:housenumber":"22",
    "addr:postcode":"4840",
    "addr:street":"Ravnse Byvej;Norre Alslev Danmark",
    "iso:country":"DK",
    "sg:address":"Ravnse Byvej 22",
    "sg:city":"N\u00f8rre Alslev",
    "sg:orig_category":"Porte",
    "sg:phone":"+45 54 40 06 26",
    "sg:postcode":"4840",
    "sg:province":"Danmark",
    "wof:name":"J E Montage I/S",
    "wof:placetype":"venue"
},
  "geometry": {"coordinates":[11.9028949738,54.901134491],"type":"Point"}
}