{
  "type": "Feature",
  "properties": {
    "addr:full":"S\u00f8gade 3 Fjerritslev Danmark 9690",
    "addr:housenumber":"3",
    "addr:postcode":"9690",
    "addr:street":"Sogade",
    "iso:country":"DK",
    "sg:address":"S\u00f8gade 3",
    "sg:city":"Fjerritslev",
    "sg:orig_category":"Garn",
    "sg:phone":"+45 98 21 30 56",
    "sg:postcode":"9690",
    "sg:province":"Danmark",
    "wof:name":"H\u00e5ndarbejdshuset",
    "wof:placetype":"venue"
},
  "geometry": {"coordinates":[9.2667350769,57.0882301331],"type":"Point"}
}