{
  "type": "Feature",
  "properties": {
    "iso:country":"DK",
    "sg:address":"Strandboulevarden 110",
    "sg:city":"K\u00f8benhavn \u00d8",
    "sg:orig_category":"Skomagere",
    "sg:phone":"+45 35 42 69 35",
    "sg:postcode":"2100",
    "sg:province":"Danmark",
    "wof:name":"Pedersen, Viggo Feldborg",
    "wof:placetype":"venue"
},
  "geometry": {"coordinates":[12.5865697861,55.7065696716],"type":"Point"}
}