{
  "type": "Feature",
  "properties": {
    "addr:full":"Margrethevej 5 Storvorde Danmark 9280",
    "addr:housenumber":"5",
    "addr:postcode":"9280",
    "addr:street":"Margrethevej",
    "iso:country":"DK",
    "sg:address":"Margrethevej 5",
    "sg:city":"Storvorde",
    "sg:orig_category":"Faglige organisationer og -foreninger",
    "sg:phone":"+45 98 31 70 20",
    "sg:postcode":"9280",
    "sg:province":"Danmark",
    "wof:name":"Gr\u00f8nlandske Tjenestemands Forening, Den",
    "wof:placetype":"venue"
},
  "geometry": {"coordinates":[10.0947265625,57.006565094],"type":"Point"}
}