{
  "type": "Feature",
  "properties": {
    "addr:full":"Seestvej 4, Seest Kolding Danmark 6000",
    "addr:housenumber":"4",
    "addr:postcode":"6000",
    "addr:street":"Seestvej;Seest",
    "iso:country":"DK",
    "sg:address":"Seestvej 4, Seest",
    "sg:city":"Kolding",
    "sg:orig_category":"Tandklinikker, Kommunale",
    "sg:phone":"+45 75 53 03 77",
    "sg:postcode":"6000",
    "sg:province":"Danmark",
    "wof:name":"Klinikken",
    "wof:placetype":"venue"
},
  "geometry": {"coordinates":[9.4733953476,55.4863586426],"type":"Point"}
}