{
  "type": "Feature",
  "properties": {
    "addr:full":"S\u00f8vej 13, Feldballe R\u00f8nde Danmark 8410",
    "addr:housenumber":"13",
    "addr:postcode":"8410",
    "addr:street":"Sovej",
    "iso:country":"DK",
    "sg:address":"S\u00f8vej 13, Feldballe",
    "sg:city":"R\u00f8nde",
    "sg:orig_category":"Skorstene",
    "sg:phone":"+45 86 36 79 70",
    "sg:postcode":"8410",
    "sg:province":"Danmark",
    "wof:name":"Murer- & entrepren\u00f8rfirmaet",
    "wof:placetype":"venue"
},
  "geometry": {"coordinates":[10.4288892746,56.295917511],"type":"Point"}
}