{
  "type": "Feature",
  "properties": {
    "addr:full":"Hovedgaden 11  Snedsted Danmark 7752",
    "addr:housenumber":"11",
    "addr:postcode":"7752",
    "addr:street":"Hovedgaden",
    "iso:country":"DK",
    "sg:address":"Hovedgaden 11 ",
    "sg:city":"Snedsted",
    "sg:classifiers":[
        {
            "category":"Shopping",
            "subcategory":"Clothing, Apparel, & Fashions",
            "type":"Retail Goods"
        }
    ],
    "sg:phone":"+45 97 93 44 00",
    "sg:postcode":"7752",
    "sg:province":"Danmark",
    "sg:tags":[
        "clothes"
    ],
    "wof:name":"A/S TH MALLE, SNEDSTED",
    "wof:placetype":"venue"
},
  "geometry": {"coordinates":[8.5319213867,56.892578125],"type":"Point"}
}