{
  "type": "Feature",
  "properties": {
    "iso:country":"DK",
    "sg:address":"Tangmosevej 88 - 90",
    "sg:city":"K\u00f8ge",
    "sg:orig_category":"Erhvervsskoler",
    "sg:phone":"+45 58 55 85 00",
    "sg:postcode":"4600",
    "sg:province":"Danmark",
    "wof:name":"AMU-Center Vest- og Sydsj\u00e6lland",
    "wof:placetype":"venue"
},
  "geometry": {"coordinates":[-85.78592681879999,36.9187889099],"type":"Point"}
}