{
  "type": "Feature",
  "properties": {
    "addr:full":"Birkevej 60 Thisted Danmark 7700",
    "addr:housenumber":"60",
    "addr:postcode":"7700",
    "addr:street":"Birkevej",
    "iso:country":"DK",
    "sg:address":"Birkevej 60",
    "sg:city":"Thisted",
    "sg:orig_category":"Psykologer, praktiserende",
    "sg:phone":"+45 97 92 16 89",
    "sg:postcode":"7700",
    "sg:province":"Danmark",
    "wof:name":"Nielsen, Hans J\u00f8rgen",
    "wof:placetype":"venue"
},
  "geometry": {"coordinates":[8.7181005478,56.9574623108],"type":"Point"}
}