{
  "type": "Feature",
  "properties": {
    "addr:full":"Margrethevej 14 Hirtshals Danmark 9850",
    "addr:housenumber":"14",
    "addr:postcode":"9850",
    "addr:street":"Margrethevej",
    "iso:country":"DK",
    "sg:address":"Margrethevej 14",
    "sg:city":"Hirtshals",
    "sg:orig_category":"Bagere",
    "sg:phone":"+45 98 94 16 92",
    "sg:postcode":"9850",
    "sg:province":"Danmark",
    "wof:name":"Butikstorvets Bageri",
    "wof:placetype":"venue"
},
  "geometry": {"coordinates":[9.965813,57.585793],"type":"Point"}
}