{
  "type": "Feature",
  "properties": {
    "iso:country":"DK",
    "sg:address":"H\u00f8jsagervej 52, Langer\u00f8d",
    "sg:city":"Fredensborg",
    "sg:orig_category":"Kattepensioner",
    "sg:phone":"+45 49 16 01 68",
    "sg:postcode":"3480",
    "sg:province":"Danmark",
    "wof:name":"Brokj\u00e6rgaard Katte og Hundepension",
    "wof:placetype":"venue"
},
  "geometry": {"coordinates":[12.4020547867,55.9782943726],"type":"Point"}
}