{
  "type": "Feature",
  "properties": {
    "addr:full":"Mettelundvej 8, Lindved Vejle Danmark 7100",
    "addr:housenumber":"8",
    "addr:postcode":"7100",
    "addr:street":"Mettelundvej",
    "iso:country":"DK",
    "sg:address":"Mettelundvej 8, Lindved",
    "sg:city":"Vejle",
    "sg:orig_category":"Murermestre",
    "sg:phone":"+45 76 90 30 31",
    "sg:postcode":"7100",
    "sg:province":"Danmark",
    "wof:name":"Jensen, Jimmy",
    "wof:placetype":"venue"
},
  "geometry": {"coordinates":[9.5368051529,55.7113952637],"type":"Point"}
}