{
  "type": "Feature",
  "properties": {
    "addr:full":"Bladstrupvej 5, Lumby Odense N Danmark 5270",
    "addr:housenumber":"5",
    "addr:postcode":"5270",
    "addr:street":"Bladstrupvej",
    "iso:country":"DK",
    "sg:address":"Bladstrupvej 5, Lumby",
    "sg:city":"Odense N",
    "sg:orig_category":"Gartnerier",
    "sg:phone":"+45 66 18 80 71",
    "sg:postcode":"5270",
    "sg:province":"Danmark",
    "wof:name":"Sandagerhus, Gartneriet",
    "wof:placetype":"venue"
},
  "geometry": {"coordinates":[10.3306798935,55.4711418152],"type":"Point"}
}