{
  "type": "Feature",
  "properties": {
    "addr:full":"Leder: Klaus Kierullf, S\u00f8nderbro 1 Grenaa Danmark 8500",
    "addr:housenumber":"1",
    "addr:postcode":"8500",
    "addr:street":"Sonderbro",
    "iso:country":"DK",
    "sg:address":"Leder: Klaus Kierullf, S\u00f8nderbro 1",
    "sg:city":"Grenaa",
    "sg:orig_category":"Oplysningsforbund",
    "sg:phone":"+45 86 32 43 11",
    "sg:postcode":"8500",
    "sg:province":"Danmark",
    "wof:name":"LOF",
    "wof:placetype":"venue"
},
  "geometry": {"coordinates":[10.8774929047,56.4126853943],"type":"Point"}
}