{
  "type": "Feature",
  "properties": {
    "addr:full":"Stillingvej 104 Sabro Danmark 8471",
    "addr:housenumber":"104",
    "addr:postcode":"8471",
    "addr:street":"Stillingvej",
    "iso:country":"DK",
    "sg:address":"Stillingvej 104",
    "sg:city":"Sabro",
    "sg:classifiers":[
        {
            "category":"Building & Trades",
            "subcategory":"Electrical",
            "type":"Services"
        }
    ],
    "sg:phone":"+45 86 94 81 81",
    "sg:postcode":"8471",
    "sg:province":"Danmark",
    "sg:tags":[
        "haller"
    ],
    "wof:name":"Haudrum-Haller Handels- & Projekteringsfirma",
    "wof:placetype":"venue"
},
  "geometry": {"coordinates":[10.0206823349,56.2105865479],"type":"Point"}
}