{
  "type": "Feature",
  "properties": {
    "addr:full":"Vilhelm Thomsens All\u00e9 9 Valby Danmark 2500",
    "addr:housenumber":"9",
    "addr:postcode":"2500",
    "addr:street":"Vilhelm Thomsens Alle\u0301",
    "iso:country":"DK",
    "sg:address":"Vilhelm Thomsens All\u00e9 9",
    "sg:city":"Valby",
    "sg:orig_category":"Aviser",
    "sg:phone":"+45 36 15 00 80",
    "sg:postcode":"2500",
    "sg:province":"Danmark",
    "wof:name":"Fagbladet Brandmanden",
    "wof:placetype":"venue"
},
  "geometry": {"coordinates":[12.5052728653,55.6602935791],"type":"Point"}
}