{
  "type": "Feature",
  "properties": {
    "addr:full":"Gr\u00f8nh\u00f8jvej 1 Harlev Danmark 8462",
    "addr:housenumber":"1",
    "addr:postcode":"8462",
    "addr:street":"Gronhojvej",
    "iso:country":"DK",
    "sg:address":"Gr\u00f8nh\u00f8jvej 1",
    "sg:city":"Harlev",
    "sg:orig_category":"Bogtrykkerier",
    "sg:phone":"+45 86 94 16 88",
    "sg:postcode":"8462",
    "sg:province":"Danmark",
    "wof:name":"Kj\u00e6rs Bogtryk & Forlag ApS, A. M.",
    "wof:placetype":"venue"
},
  "geometry": {"coordinates":[10.0093507767,56.1557807922],"type":"Point"}
}