{
  "type": "Feature",
  "properties": {
    "addr:full":"Byager 1, Nr. Hvals\u00f8 Kirke Hvals\u00f8 Danmark 4330",
    "addr:housenumber":"1",
    "addr:postcode":"4330",
    "addr:street":"Byager;Nr. Hvalso",
    "iso:country":"DK",
    "sg:address":"Byager 1, Nr. Hvals\u00f8",
    "sg:city":"Kirke Hvals\u00f8",
    "sg:orig_category":"Murermestre",
    "sg:phone":"+45 46 40 95 12",
    "sg:postcode":"4330",
    "sg:province":"Danmark",
    "wof:name":"S\u00f8gaard, Erik",
    "wof:placetype":"venue"
},
  "geometry": {"coordinates":[166.9221496582,-0.5282999873],"type":"Point"}
}