{
  "type": "Feature",
  "properties": {
    "addr:full":"Ahlefeldtsgade 20 K\u00f8benhavn Danmark 1359",
    "addr:housenumber":"20",
    "addr:postcode":"1359",
    "addr:street":"Ahlefeldtsgade",
    "iso:country":"DK",
    "sg:address":"Ahlefeldtsgade 20",
    "sg:city":"K\u00f8benhavn",
    "sg:orig_category":"Farvehandlere",
    "sg:phone":"+45 33 14 18 29",
    "sg:postcode":"1359",
    "sg:province":"Danmark",
    "wof:name":"Pallas Farve & Isenkram ApS",
    "wof:placetype":"venue"
},
  "geometry": {"coordinates":[12.5643501282,55.6834602356],"type":"Point"}
}