{
  "type": "Feature",
  "properties": {
    "addr:full":"Kragsbjergvej 72 Odense C Danmark 5000",
    "addr:housenumber":"72",
    "addr:postcode":"5000",
    "addr:street":"Kragsbjergvej",
    "iso:country":"DK",
    "sg:address":"Kragsbjergvej 72",
    "sg:city":"Odense C",
    "sg:orig_category":"Plejehjem",
    "sg:phone":"+45 66 14 25 25",
    "sg:postcode":"5000",
    "sg:province":"Danmark",
    "wof:name":"Kragsbjergl\u00f8kke plejehjem",
    "wof:placetype":"venue"
},
  "geometry": {"coordinates":[10.4044628143,55.3897895813],"type":"Point"}
}