{
  "type": "Feature",
  "properties": {
    "addr:full":"Danmarksgade 21 Esbjerg Danmark 6700",
    "addr:housenumber":"21",
    "addr:postcode":"6700",
    "addr:street":"Danmarksgade",
    "iso:country":"DK",
    "sg:address":"Danmarksgade 21",
    "sg:city":"Esbjerg",
    "sg:orig_category":"Vaskerier",
    "sg:phone":"+45 75 45 11 39",
    "sg:postcode":"6700",
    "sg:province":"Danmark",
    "wof:name":"Esbjerg M\u00f8ntvask I/S",
    "wof:placetype":"venue"
},
  "geometry": {"coordinates":[8.4548625946,55.4674606323],"type":"Point"}
}