{
  "type": "Feature",
  "properties": {
    "addr:full":"Hillerslev K\u00e6r Vej 5 Thisted Danmark 7700",
    "addr:housenumber":"5",
    "addr:postcode":"7700",
    "addr:street":"Kaer Vej",
    "iso:country":"DK",
    "sg:address":"Hillerslev K\u00e6r Vej 5",
    "sg:city":"Thisted",
    "sg:orig_category":"Skolefritidsordninger",
    "sg:phone":"+45 97 98 18 22",
    "sg:postcode":"7700",
    "sg:province":"Danmark",
    "wof:name":"Kridthuset Hillerslev skole",
    "wof:placetype":"venue"
},
  "geometry": {"coordinates":[8.7295150757,57.0133628845],"type":"Point"}
}