{
  "type": "Feature",
  "properties": {
    "addr:full":"Gr\u00f8nlandsparken 234 F Esbjerg N Danmark 6715",
    "addr:housenumber":"234 f",
    "addr:postcode":"6715",
    "addr:street":"Gronlandsparken",
    "iso:country":"DK",
    "sg:address":"Gr\u00f8nlandsparken 234 F",
    "sg:city":"Esbjerg N",
    "sg:orig_category":"Cafeterier",
    "sg:phone":"+45 75 15 36 05",
    "sg:postcode":"6715",
    "sg:province":"Danmark",
    "wof:name":"Spisekrogen",
    "wof:placetype":"venue"
},
  "geometry": {"coordinates":[8.4780550003,55.535610199],"type":"Point"}
}