{
  "type": "Feature",
  "properties": {
    "addr:full":"Hundige Alle 11 Greve Danmark 2670",
    "addr:housenumber":"11",
    "addr:postcode":"2670",
    "addr:street":"Hundige Alle",
    "iso:country":"DK",
    "sg:address":"Hundige Alle 11",
    "sg:city":"Greve",
    "sg:orig_category":"Tandklinikker, Kommunale",
    "sg:phone":"+45 43 90 77 70",
    "sg:postcode":"2670",
    "sg:province":"Danmark",
    "wof:name":"Hundige Klinik",
    "wof:placetype":"venue"
},
  "geometry": {"coordinates":[12.3308668137,55.6012001038],"type":"Point"}
}