{
  "type": "Feature",
  "properties": {
    "iso:country":"DK",
    "sg:address":"v/ Dagli'Brugsen, Kirkebyvej 8, Sdr. Nissum",
    "sg:city":"Ulfborg",
    "sg:orig_category":"Apoteker og -udsalg",
    "sg:phone":"+45 97 49 50 19",
    "sg:postcode":"6990",
    "sg:province":"Danmark",
    "wof:name":"H\u00e5ndk\u00f8bsudsalg",
    "wof:placetype":"venue"
},
  "geometry": {"coordinates":[8.1868152618,56.3060302734],"type":"Point"}
}