{
  "type": "Feature",
  "properties": {
    "addr:full":"Hejmdals Alle 25 Esbjerg \u00d8 Danmark 6705",
    "addr:housenumber":"25",
    "addr:postcode":"6705",
    "addr:street":"Hejmdals Alle;Danmark",
    "iso:country":"DK",
    "sg:address":"Hejmdals Alle 25",
    "sg:city":"Esbjerg \u00d8",
    "sg:orig_category":"Psykologer, praktiserende",
    "sg:phone":"+45 75 14 50 79",
    "sg:postcode":"6705",
    "sg:province":"Danmark",
    "wof:name":"Terapicenter, Esbjerg",
    "wof:placetype":"venue"
},
  "geometry": {"coordinates":[8.4750003815,55.4829101562],"type":"Point"}
}