{
  "type": "Feature",
  "properties": {
    "addr:full":"Fmd.: Henrik Lauritsen, Tingvej 30 B Haslev Danmark 4690",
    "addr:housenumber":"30 b",
    "addr:postcode":"4690",
    "addr:street":"Henrik Lauritsen Tingvej",
    "iso:country":"DK",
    "sg:address":"Fmd.: Henrik Lauritsen, Tingvej 30 B",
    "sg:city":"Haslev",
    "sg:orig_category":"Grundejerforeninger",
    "sg:phone":"+45 55 31 66 90",
    "sg:postcode":"4690",
    "sg:province":"Danmark",
    "wof:name":"Grundejerforeningen Skjoldbjerg Vellerup",
    "wof:placetype":"venue"
},
  "geometry": {"coordinates":[11.9678049088,55.3230895996],"type":"Point"}
}