{
  "type": "Feature",
  "properties": {
    "addr:full":"Langgade 49, Espe Ringe Danmark 5750",
    "addr:housenumber":"49",
    "addr:postcode":"5750",
    "addr:street":"Langgade",
    "iso:country":"DK",
    "sg:address":"Langgade 49, Espe",
    "sg:city":"Ringe",
    "sg:orig_category":"Gaffeltrucks",
    "sg:phone":"+45 62 66 16 66",
    "sg:postcode":"5750",
    "sg:province":"Danmark",
    "wof:name":"Espe Truckservice ApS",
    "wof:placetype":"venue"
},
  "geometry": {"coordinates":[10.4781074524,55.2356643677],"type":"Point"}
}