{
  "type": "Feature",
  "properties": {
    "addr:full":"Christoffersvej 5 Randers Danmark 8900",
    "addr:housenumber":"5",
    "addr:postcode":"8900",
    "addr:street":"Christoffersvej",
    "iso:country":"DK",
    "sg:address":"Christoffersvej 5",
    "sg:city":"Randers",
    "sg:orig_category":"Malermestre",
    "sg:phone":"+45 86 42 41 97",
    "sg:postcode":"8900",
    "sg:province":"Danmark",
    "wof:name":"Andersen A/S, Preben",
    "wof:placetype":"venue"
},
  "geometry": {"coordinates":[10.0687961578,56.4438056946],"type":"Point"}
}