{
  "type": "Feature",
  "properties": {
    "addr:full":"Vedelsgade 71-75 Vejle Danmark 7100",
    "addr:postcode":"71-75;7100",
    "addr:street":"Vedelsgade",
    "iso:country":"DK",
    "sg:address":"Vedelsgade 71-75",
    "sg:city":"Vejle",
    "sg:orig_category":"Antikvariater",
    "sg:phone":"+45 75 84 00 10",
    "sg:postcode":"7100",
    "sg:province":"Danmark",
    "wof:name":"Byttecentralen",
    "wof:placetype":"venue"
},
  "geometry": {"coordinates":[9.5326032639,55.7119026184],"type":"Point"}
}