{
  "type": "Feature",
  "properties": {
    "addr:full":"Nygade 35 F Silkeborg Danmark 8600",
    "addr:housenumber":"35 f",
    "addr:postcode":"8600",
    "addr:street":"Nygade",
    "iso:country":"DK",
    "sg:address":"Nygade 35 F",
    "sg:city":"Silkeborg",
    "sg:orig_category":"Pizzeriaer",
    "sg:phone":"+45 86 80 42 01",
    "sg:postcode":"8600",
    "sg:province":"Danmark",
    "wof:name":"Buffalo",
    "wof:placetype":"venue"
},
  "geometry": {"coordinates":[9.5524425507,56.1693305969],"type":"Point"}
}