{
  "type": "Feature",
  "properties": {
    "addr:full":"Robstrupvej 4, Voldby Grenaa Danmark 8500",
    "addr:housenumber":"4",
    "addr:postcode":"8500",
    "addr:street":"Robstrupvej;Voldby",
    "iso:country":"DK",
    "sg:address":"Robstrupvej 4, Voldby",
    "sg:city":"Grenaa",
    "sg:orig_category":"Murermestre",
    "sg:phone":"+45 86 33 25 40",
    "sg:postcode":"8500",
    "sg:province":"Danmark",
    "wof:name":"Hulvej, Johnny",
    "wof:placetype":"venue"
},
  "geometry": {"coordinates":[10.8774929047,56.4126853943],"type":"Point"}
}