{
  "type": "Feature",
  "properties": {
    "addr:full":"Klostergade 2 \u00c5rhus C Danmark 8000",
    "addr:housenumber":"2",
    "addr:postcode":"8000",
    "addr:street":"Klostergade",
    "iso:country":"DK",
    "sg:address":"Klostergade 2",
    "sg:city":"\u00c5rhus C",
    "sg:orig_category":"Helseprodukter",
    "sg:phone":"+45 86 12 54 15",
    "sg:postcode":"8000",
    "sg:province":"Danmark",
    "wof:name":"Ganefryd Helsekost",
    "wof:placetype":"venue"
},
  "geometry": {"coordinates":[4.717400074,49.7588005066],"type":"Point"}
}