{
  "type": "Feature",
  "properties": {
    "addr:full":"Kystvejen 79 A, \u00d8. Hurup Hadsund Danmark 9560",
    "addr:housenumber":"79 a o.",
    "addr:postcode":"9560",
    "addr:street":"Kystvejen",
    "iso:country":"DK",
    "sg:address":"Kystvejen 79 A, \u00d8. Hurup",
    "sg:city":"Hadsund",
    "sg:orig_category":"Konsulentvirksomheder",
    "sg:phone":"+45 98 58 88 89",
    "sg:postcode":"9560",
    "sg:province":"Danmark",
    "wof:name":"Protek Consulting",
    "wof:placetype":"venue"
},
  "geometry": {"coordinates":[10.115904808,56.7150764465],"type":"Point"}
}