{
  "type": "Feature",
  "properties": {
    "addr:full":"\u00c5rhusvej 1 A Auning Danmark 8963",
    "addr:housenumber":"1 a",
    "addr:postcode":"8963",
    "addr:street":"Aarhusvej",
    "iso:country":"DK",
    "sg:address":"\u00c5rhusvej 1 A",
    "sg:city":"Auning",
    "sg:orig_category":"Dag- og distriktsblade",
    "sg:phone":"+45 86 48 38 11",
    "sg:postcode":"8963",
    "sg:province":"Danmark",
    "wof:name":"Folkebladet Djursland",
    "wof:placetype":"venue"
},
  "geometry": {"coordinates":[10.3769283295,56.4284248352],"type":"Point"}
}