{
  "type": "Feature",
  "properties": {
    "addr:full":"K\u00f8benhavnsvej 1 Slangerup Danmark 3550",
    "addr:housenumber":"1",
    "addr:postcode":"3550",
    "addr:street":"Kobenhavnsvej",
    "iso:country":"DK",
    "sg:address":"K\u00f8benhavnsvej 1",
    "sg:city":"Slangerup",
    "sg:orig_category":"Industrimontage",
    "sg:phone":"+45 70 25 92 69",
    "sg:postcode":"3550",
    "sg:province":"Danmark",
    "sg:website":"www.nordiskmultiservice.dk",
    "wof:name":"Nordisk Multiservice af 1997 ApS",
    "wof:placetype":"venue"
},
  "geometry": {"coordinates":[12.1929740906,55.8358078003],"type":"Point"}
}