{
  "type": "Feature",
  "properties": {
    "addr:full":"Hadsundvej 43 Terndrup Danmark 9575",
    "addr:housenumber":"43",
    "addr:postcode":"9575",
    "addr:street":"Hadsundvej;Danmark",
    "iso:country":"DK",
    "sg:address":"Hadsundvej 43",
    "sg:city":"Terndrup",
    "sg:orig_category":"Autoreparation og -service",
    "sg:phone":"+45 98 33 52 31",
    "sg:postcode":"9575",
    "sg:province":"Danmark",
    "wof:name":"DK Benzin & Auto",
    "wof:placetype":"venue"
},
  "geometry": {"coordinates":[10.0570821762,56.8092422485],"type":"Point"}
}