{
  "type": "Feature",
  "properties": {
    "iso:country":"DK",
    "sg:address":"Langgade 10",
    "sg:city":"Nyk\u00f8bing",
    "sg:orig_category":"Realkreditinstitutter",
    "sg:phone":"+45 54 84 03 54",
    "sg:postcode":"4800",
    "sg:province":"Danmark",
    "sg:website":"www.nykredit.dk",
    "wof:name":"Nykredit A/S",
    "wof:placetype":"venue"
},
  "geometry": {"coordinates":[-114.0768203735,46.4432411194],"type":"Point"}
}