{
  "type": "Feature",
  "properties": {
    "addr:full":"Skavholmvej 3 Lystrup Danmark 8520",
    "addr:housenumber":"3",
    "addr:postcode":"8520",
    "addr:street":"Skavholmvej",
    "iso:country":"DK",
    "sg:address":"Skavholmvej 3",
    "sg:city":"Lystrup",
    "sg:orig_category":"Tyverisikring",
    "sg:phone":"+45 70 20 00 99",
    "sg:postcode":"8520",
    "sg:province":"Danmark",
    "sg:website":"www.absalarm.dk",
    "wof:name":"ABS Alarm & Sikkerhed A/S",
    "wof:placetype":"venue"
},
  "geometry": {"coordinates":[10.2398929596,56.2273025513],"type":"Point"}
}