{
  "type": "Feature",
  "properties": {
    "iso:country":"DK",
    "sg:address":"Nederg\u00e5rdsvej 8",
    "sg:city":"Brande",
    "sg:orig_category":"Strudsefarme",
    "sg:phone":"+45 97 18 04 51",
    "sg:postcode":"7330",
    "sg:province":"Danmark",
    "wof:name":"Tofth\u00f8jg\u00e5rd Strudseopdr\u00e6t",
    "wof:placetype":"venue"
},
  "geometry": {"coordinates":[9.1027603149,55.939956665],"type":"Point"}
}