{
  "type": "Feature",
  "properties": {
    "addr:full":"Windelsvej 138 Odense C Danmark 5000",
    "addr:housenumber":"138",
    "addr:postcode":"5000",
    "addr:street":"Windelsvej",
    "iso:country":"DK",
    "sg:address":"Windelsvej 138",
    "sg:city":"Odense C",
    "sg:orig_category":"Diners transportables",
    "sg:phone":"+45 65 90 40 00",
    "sg:postcode":"5000",
    "sg:province":"Danmark",
    "wof:name":"Marienlyst Odense ApS, Restaurant",
    "wof:placetype":"venue"
},
  "geometry": {"coordinates":[10.3964090347,55.4227333069],"type":"Point"}
}