{
  "type": "Feature",
  "properties": {
    "addr:full":"Ved Byskellet 31 A Randers Danmark 8900",
    "addr:housenumber":"31 a",
    "addr:postcode":"8900",
    "addr:street":"Ved Byskellet",
    "iso:country":"DK",
    "sg:address":"Ved Byskellet 31 A",
    "sg:city":"Randers",
    "sg:orig_category":"Vuggestuer",
    "sg:phone":"+45 86 43 32 46",
    "sg:postcode":"8900",
    "sg:province":"Danmark",
    "wof:name":"Solsikken, Vuggestuen",
    "wof:placetype":"venue"
},
  "geometry": {"coordinates":[10.0058965683,56.4799499512],"type":"Point"}
}