{
  "type": "Feature",
  "properties": {
    "addr:full":"Egetoftevej 5 H\u00f8jby Danmark 4573",
    "addr:housenumber":"5",
    "addr:postcode":"4573",
    "addr:street":"Egetoftevej",
    "iso:country":"DK",
    "sg:address":"Egetoftevej 5",
    "sg:city":"H\u00f8jby",
    "sg:orig_category":"Politi",
    "sg:phone":"+45 59 30 55 24",
    "sg:postcode":"4573",
    "sg:province":"Danmark",
    "wof:name":"Landpolitistationen i H\u00f8jby",
    "wof:placetype":"venue"
},
  "geometry": {"coordinates":[11.5892896652,55.9144744873],"type":"Point"}
}