{
  "type": "Feature",
  "properties": {
    "addr:full":"Finlandsvej 6 Skive Danmark 7800",
    "addr:housenumber":"6",
    "addr:postcode":"7800",
    "addr:street":"Finlandsvej",
    "iso:country":"DK",
    "sg:address":"Finlandsvej 6",
    "sg:city":"Skive",
    "sg:orig_category":"Forlag",
    "sg:phone":"+45 97 52 62 34",
    "sg:postcode":"7800",
    "sg:province":"Danmark",
    "wof:name":"B\u00e6ks Forlag-Skak, Bjarne",
    "wof:placetype":"venue"
},
  "geometry": {"coordinates":[9.0437450409,56.5620498657],"type":"Point"}
}