{
  "type": "Feature",
  "properties": {
    "iso:country":"DK",
    "sg:address":"Strandvejen 417",
    "sg:city":"Henne",
    "sg:orig_category":"Bagere",
    "sg:phone":"+45 75 25 58 00",
    "sg:postcode":"6854",
    "sg:province":"Danmark",
    "wof:name":"Bo, Bager",
    "wof:placetype":"venue"
},
  "geometry": {"coordinates":[8.180394,55.739212],"type":"Point"}
}