{
  "type": "Feature",
  "properties": {
    "iso:country":"DK",
    "sg:address":"Gravensgade 5",
    "sg:city":"Aalborg",
    "sg:orig_category":"Chokolade",
    "sg:phone":"+45 98 13 89 22",
    "sg:postcode":"9000",
    "sg:province":"Danmark",
    "wof:name":"Frellsen Chokolade",
    "wof:placetype":"venue"
},
  "geometry": {"coordinates":[9.9176435471,57.0489578247],"type":"Point"}
}