{
  "type": "Feature",
  "properties": {
    "addr:full":"Turistvej 2 Hundested Danmark 3390",
    "addr:housenumber":"2",
    "addr:postcode":"3390",
    "addr:street":"Turistvej",
    "iso:country":"DK",
    "sg:address":"Turistvej 2",
    "sg:city":"Hundested",
    "sg:orig_category":"Politiske foreninger, \u00c3\u02dcvrige",
    "sg:phone":"+45 47 93 83 99",
    "sg:postcode":"3390",
    "sg:province":"Danmark",
    "wof:name":"Folkebev\u00e6gelsen mod EU p\u00e5 Halsn\u00e6s",
    "wof:placetype":"venue"
},
  "geometry": {"coordinates":[11.8583240509,55.9537391663],"type":"Point"}
}