{
  "type": "Feature",
  "properties": {
    "addr:full":"Kabdrupvej 2, Bjerning Haderslev Danmark 6100",
    "addr:housenumber":"2",
    "addr:postcode":"6100",
    "addr:street":"Kabdrupvej;Bjerning",
    "iso:country":"DK",
    "sg:address":"Kabdrupvej 2, Bjerning",
    "sg:city":"Haderslev",
    "sg:orig_category":"Maskinfabrikker",
    "sg:phone":"+45 74 52 16 21",
    "sg:postcode":"6100",
    "sg:province":"Danmark",
    "wof:name":"Bema A/S, Maskinfabrikken",
    "wof:placetype":"venue"
},
  "geometry": {"coordinates":[9.4879703522,55.2505493164],"type":"Point"}
}