{
  "type": "Feature",
  "properties": {
    "addr:full":"Nybrovej 455 Kongens Lyngby Danmark 2800",
    "addr:housenumber":"455",
    "addr:postcode":"2800",
    "addr:street":"Nybrovej",
    "iso:country":"DK",
    "sg:address":"Nybrovej 455",
    "sg:city":"Kongens Lyngby",
    "sg:classifiers":[
        {
            "category":"Restaurant",
            "type":"Food & Drink"
        }
    ],
    "sg:phone":"+45 45 83 01 24",
    "sg:postcode":"2800",
    "sg:province":"Danmark",
    "wof:name":"Gamle Have, Den",
    "wof:placetype":"venue"
},
  "geometry": {"coordinates":[12.4461507797,55.7802696228],"type":"Point"}
}