{
  "type": "Feature",
  "properties": {
    "iso:country":"DK",
    "sg:address":"Helgolandsgade 35",
    "sg:city":"S\u00f8nderborg",
    "sg:orig_category":"Begravelsesforretninger",
    "sg:phone":"+45 74 43 45 40",
    "sg:postcode":"6400",
    "sg:province":"Danmark",
    "wof:name":"Als Begravelsesforretning",
    "wof:placetype":"venue"
},
  "geometry": {"coordinates":[9.7857618332,54.9140052795],"type":"Point"}
}