{
  "type": "Feature",
  "properties": {
    "addr:full":"Viborgvej 243, Svenstrup Hammel Danmark 8450",
    "addr:housenumber":"243",
    "addr:postcode":"8450",
    "addr:street":"Viborgvej;Svenstrup",
    "iso:country":"DK",
    "sg:address":"Viborgvej 243, Svenstrup",
    "sg:city":"Hammel",
    "sg:orig_category":"Forsamlingshuse",
    "sg:phone":"+45 86 96 24 20",
    "sg:postcode":"8450",
    "sg:province":"Danmark",
    "wof:name":"Svenstrup Forsamlingshus",
    "wof:placetype":"venue"
},
  "geometry": {"coordinates":[9.8615541458,56.2554588318],"type":"Point"}
}