{
  "type": "Feature",
  "properties": {
    "addr:full":"Fmd.: Helle Madsen, Hellekisten 39 Svenstrup Danmark 9230",
    "addr:housenumber":"39",
    "addr:postcode":"9230",
    "addr:street":"Helle Madsen Hellekisten",
    "iso:country":"DK",
    "sg:address":"Fmd.: Helle Madsen, Hellekisten 39",
    "sg:city":"Svenstrup",
    "sg:orig_category":"Kirkelige foreninger",
    "sg:phone":"+45 98 38 25 62",
    "sg:postcode":"9230",
    "sg:province":"Danmark",
    "wof:name":"KFUM Svenstrup",
    "wof:placetype":"venue"
},
  "geometry": {"coordinates":[9.8525295258,56.9723396301],"type":"Point"}
}