{
  "type": "Feature",
  "properties": {
    "addr:full":"Hobrovej 796 Svenstrup Danmark 9230",
    "addr:housenumber":"796",
    "addr:postcode":"9230",
    "addr:street":"Hobrovej",
    "iso:country":"DK",
    "sg:address":"Hobrovej 796",
    "sg:city":"Svenstrup",
    "sg:orig_category":"Autoudlejning",
    "sg:phone":"+45 98 38 13 33",
    "sg:postcode":"9230",
    "sg:province":"Danmark",
    "wof:name":"Aalborg Discount Biludlejning",
    "wof:placetype":"venue"
},
  "geometry": {"coordinates":[9.855134964,56.9680862427],"type":"Point"}
}