{
  "type": "Feature",
  "properties": {
    "addr:full":"N\u00e6ringen 100 Risskov Danmark 8240",
    "addr:housenumber":"100",
    "addr:postcode":"8240",
    "iso:country":"DK",
    "sg:address":"N\u00e6ringen 100",
    "sg:city":"Risskov",
    "sg:orig_category":"Private skoler",
    "sg:phone":"+45 86 78 30 55",
    "sg:postcode":"8240",
    "sg:province":"Danmark",
    "wof:name":"Jakobskolen",
    "wof:placetype":"venue"
},
  "geometry": {"coordinates":[10.1974506378,56.1955108643],"type":"Point"}
}