{
  "type": "Feature",
  "properties": {
    "addr:full":"Hornbjergvej 51 Hornslet Danmark 8543",
    "addr:housenumber":"51",
    "addr:postcode":"8543",
    "addr:street":"Hornbjergvej",
    "iso:country":"DK",
    "sg:address":"Hornbjergvej 51",
    "sg:city":"Hornslet",
    "sg:orig_category":"Bogtrykkerier",
    "sg:phone":"+45 87 85 11 11",
    "sg:postcode":"8543",
    "sg:province":"Danmark",
    "sg:website":"www.bke.dk",
    "wof:name":"BKE Graphic",
    "wof:placetype":"venue"
},
  "geometry": {"coordinates":[10.308836937,56.3029136658],"type":"Point"}
}