{
  "type": "Feature",
  "properties": {
    "iso:country":"DK",
    "sg:address":"Vesterled 18",
    "sg:city":"Ringk\u00f8bing",
    "sg:orig_category":"Reklame",
    "sg:phone":"+45 96 74 05 25",
    "sg:postcode":"6950",
    "sg:province":"Danmark",
    "wof:name":"Br\u00e4uner A/S",
    "wof:placetype":"venue"
},
  "geometry": {"coordinates":[-89.24946594239999,39.2174491882],"type":"Point"}
}