{
  "type": "Feature",
  "properties": {
    "iso:country":"DK",
    "sg:address":"Agertoften 1",
    "sg:city":"H\u00f8jer",
    "sg:orig_category":"Blikkenslagere",
    "sg:phone":"+45 74 78 27 94",
    "sg:postcode":"6280",
    "sg:province":"Danmark",
    "wof:name":"Marsk VVS",
    "wof:placetype":"venue"
},
  "geometry": {"coordinates":[-2.19729,49.204979],"type":"Point"}
}