{
  "type": "Feature",
  "properties": {
    "addr:full":"Vester\u00e5gade 47, Nr. Broby Broby Danmark 5672",
    "addr:housenumber":"47",
    "addr:postcode":"5672",
    "addr:street":"Vesteraagade",
    "iso:country":"DK",
    "sg:address":"Vester\u00e5gade 47, Nr. Broby",
    "sg:city":"Broby",
    "sg:orig_category":"Grillbarer",
    "sg:phone":"+45 62 63 22 11",
    "sg:postcode":"5672",
    "sg:province":"Danmark",
    "wof:name":"Kinesiske Grill, Den",
    "wof:placetype":"venue"
},
  "geometry": {"coordinates":[10.3131303787,55.2695846558],"type":"Point"}
}