{
  "type": "Feature",
  "properties": {
    "iso:country":"DK",
    "sg:address":"Pogevej 5",
    "sg:city":"Tylstrup",
    "sg:orig_category":"Skolefritidsordninger",
    "sg:phone":"+45 98 26 00 71",
    "sg:postcode":"9382",
    "sg:province":"Danmark",
    "wof:name":"DUS Spor A - Tylstrup Skole",
    "wof:placetype":"venue"
},
  "geometry": {"coordinates":[9.944940567,57.1958999634],"type":"Point"}
}