{
  "type": "Feature",
  "properties": {
    "iso:country":"DK",
    "sg:address":"Torpvej 30, Hjallese",
    "sg:city":"Odense S",
    "sg:orig_category":"Revisorer",
    "sg:phone":"+45 66 15 38 80",
    "sg:postcode":"5260",
    "sg:province":"Danmark",
    "wof:name":"B P Kontorhj\u00e6lp & EDB Bogf\u00f8ring",
    "wof:placetype":"venue"
},
  "geometry": {"coordinates":[10.3157806396,55.3122825623],"type":"Point"}
}