{
  "type": "Feature",
  "properties": {
    "addr:full":"Frederiks All\u00e9 134 \u00c5rhus C Danmark 8000",
    "addr:housenumber":"134",
    "addr:postcode":"8000",
    "addr:street":"Frederiks Alle\u0301",
    "iso:country":"DK",
    "sg:address":"Frederiks All\u00e9 134",
    "sg:city":"\u00c5rhus C",
    "sg:orig_category":"Rideudstyr",
    "sg:phone":"+45 86 18 49 47",
    "sg:postcode":"8000",
    "sg:province":"Danmark",
    "sg:website":"www.din-sadelmager.dk",
    "wof:name":"Sadelmager, Din",
    "wof:placetype":"venue"
},
  "geometry": {"coordinates":[10.1949110031,56.1471138],"type":"Point"}
}