{
  "type": "Feature",
  "properties": {
    "addr:full":"N\u00f8rregade 16, 4 Odense C Danmark 5000",
    "addr:housenumber":"16 4",
    "addr:postcode":"5000",
    "addr:street":"Norregade",
    "iso:country":"DK",
    "sg:address":"N\u00f8rregade 16, 4",
    "sg:city":"Odense C",
    "sg:orig_category":"Advokater",
    "sg:phone":"+45 66 11 80 00",
    "sg:postcode":"5000",
    "sg:province":"Danmark",
    "wof:name":"Bisgaard Larsen & Ole Maare Advokatfirmaet",
    "wof:placetype":"venue"
},
  "geometry": {"coordinates":[10.3885707855,55.3977546692],"type":"Point"}
}