{
  "type": "Feature",
  "properties": {
    "iso:country":"DK",
    "sg:address":"Gl. Landevej 5, Ejsing",
    "sg:city":"Vinderup",
    "sg:orig_category":"Naturgas install. og -service",
    "sg:phone":"+45 97 44 68 00",
    "sg:postcode":"7830",
    "sg:province":"Danmark",
    "wof:name":"Ejsing Smede- og VVS-forretning",
    "wof:placetype":"venue"
},
  "geometry": {"coordinates":[8.7796897888,56.482635498],"type":"Point"}
}