{
  "type": "Feature",
  "properties": {
    "addr:full":"Brogade 37 Bjerringbro Danmark 8850",
    "addr:housenumber":"37",
    "addr:postcode":"8850",
    "addr:street":"Brogade",
    "iso:country":"DK",
    "sg:address":"Brogade 37",
    "sg:city":"Bjerringbro",
    "sg:orig_category":"Kiosker",
    "sg:phone":"+45 86 68 45 90",
    "sg:postcode":"8850",
    "sg:province":"Danmark",
    "wof:name":"Centerkiosken",
    "wof:placetype":"venue"
},
  "geometry": {"coordinates":[9.6603755951,56.3705062866],"type":"Point"}
}