{
  "type": "Feature",
  "properties": {
    "addr:full":"Herningvej 76 Holstebro Danmark 7500",
    "addr:housenumber":"76",
    "addr:postcode":"7500",
    "addr:street":"Herningvej",
    "iso:country":"DK",
    "sg:address":"Herningvej 76",
    "sg:city":"Holstebro",
    "sg:orig_category":"Musikinstrumenter",
    "sg:phone":"+45 97 42 33 44",
    "sg:postcode":"7500",
    "sg:province":"Danmark",
    "sg:website":"www.alfred-christensen.dk",
    "wof:name":"Christensen Musikhandel A/S, Alfred",
    "wof:placetype":"venue"
},
  "geometry": {"coordinates":[8.6278295517,56.3480606079],"type":"Point"}
}