{
  "type": "Feature",
  "properties": {
    "addr:full":"Karsholtevej 26 Dianalund Danmark 4293",
    "addr:housenumber":"26",
    "addr:postcode":"4293",
    "addr:street":"Karsholtevej",
    "iso:country":"DK",
    "sg:address":"Karsholtevej 26",
    "sg:city":"Dianalund",
    "sg:orig_category":"Fodterapeuter",
    "sg:phone":"+45 58 26 49 43",
    "sg:postcode":"4293",
    "sg:province":"Danmark",
    "wof:name":"Jensen, Gudrun W.",
    "wof:placetype":"venue"
},
  "geometry": {"coordinates":[11.4851083755,55.5333175659],"type":"Point"}
}