{
  "type": "Feature",
  "properties": {
    "addr:full":"Godth\u00e5bsvej 37 Frederiksberg Danmark 2000",
    "addr:housenumber":"37",
    "addr:postcode":"2000",
    "addr:street":"Godthaabsvej",
    "iso:country":"DK",
    "sg:address":"Godth\u00e5bsvej 37",
    "sg:city":"Frederiksberg",
    "sg:orig_category":"Pizzeriaer",
    "sg:phone":"+45 38 87 12 45",
    "sg:postcode":"2000",
    "sg:province":"Danmark",
    "wof:name":"Latini Pizzabar",
    "wof:placetype":"venue"
},
  "geometry": {"coordinates":[12.532702446,55.6865463257],"type":"Point"}
}