{
  "type": "Feature",
  "properties": {
    "addr:full":"Oldermand: Frank Wagner, Drosselvej 5, Assens Mariager Danmark 9550",
    "addr:housenumber":"5",
    "addr:postcode":"9550",
    "addr:street":"Drosselvej",
    "iso:country":"DK",
    "sg:address":"Oldermand: Frank Wagner, Drosselvej 5, Assens",
    "sg:city":"Mariager",
    "sg:orig_category":"Faglige organisationer og foreninger",
    "sg:phone":"+45 98 58 37 40",
    "sg:postcode":"9550",
    "sg:province":"Danmark",
    "wof:name":"Randers Malerlaug",
    "wof:placetype":"venue"
},
  "geometry": {"coordinates":[10.0618648529,56.676902771],"type":"Point"}
}