{
  "type": "Feature",
  "properties": {
    "iso:country":"DK",
    "sg:address":"POSTBOKS 80",
    "sg:city":"Holb\u00e6k",
    "sg:classifiers":[
        {
            "category":"Banks & Credit Unions",
            "subcategory":"Financial Services",
            "type":"Services"
        }
    ],
    "sg:phone":"+45 59 48 82 00",
    "sg:postcode":"4300",
    "sg:province":"Danmark",
    "sg:tags":[
        "banking",
        "finance",
        "insurance"
    ],
    "wof:name":"DANSKE BANK A/S",
    "wof:placetype":"venue"
},
  "geometry": {"coordinates":[76.3070983887,14.277130127],"type":"Point"}
}