{
  "type": "Feature",
  "properties": {
    "iso:country":"DK",
    "sg:address":"Hirsevej 14",
    "sg:city":"Haderslev",
    "sg:orig_category":"Bilpleje",
    "sg:phone":"+45 74 53 53 29",
    "sg:postcode":"6100",
    "sg:province":"Danmark",
    "wof:name":"HBC System",
    "wof:placetype":"venue"
},
  "geometry": {"coordinates":[9.49932,55.23484],"type":"Point"}
}