{
  "type": "Feature",
  "properties": {
    "addr:full":"Vestre Boulevard 24 Aars Danmark 9600",
    "addr:housenumber":"24",
    "addr:postcode":"9600",
    "addr:street":"Vestre Boulevard",
    "iso:country":"DK",
    "sg:address":"Vestre Boulevard 24",
    "sg:city":"Aars",
    "sg:orig_category":"Kiropraktorer",
    "sg:phone":"+45 98 62 22 22",
    "sg:postcode":"9600",
    "sg:province":"Danmark",
    "wof:name":"Kiropraktisk Klinik ApS",
    "wof:placetype":"venue"
},
  "geometry": {"coordinates":[9.5052404404,56.8027801514],"type":"Point"}
}