{
  "type": "Feature",
  "properties": {
    "addr:full":"Fmd.: Berit Fravn, Nordskr\u00e6nten 57 Kokkedal Danmark 2980",
    "addr:housenumber":"57",
    "addr:postcode":"2980",
    "addr:street":"Nordskraenten",
    "iso:country":"DK",
    "sg:address":"Fmd.: Berit Fravn, Nordskr\u00e6nten 57",
    "sg:city":"Kokkedal",
    "sg:orig_category":"Grundejerforeninger",
    "sg:phone":"+45 45 76 00 90",
    "sg:postcode":"2980",
    "sg:province":"Danmark",
    "wof:name":"Nordskr\u00e6nten Grundejerforening",
    "wof:placetype":"venue"
},
  "geometry": {"coordinates":[12.4769096375,55.9091339111],"type":"Point"}
}