{
  "type": "Feature",
  "properties": {
    "addr:full":"Abterpvej 13 Bredebro Danmark 6261",
    "addr:housenumber":"13",
    "addr:postcode":"6261",
    "addr:street":"Abterpvej",
    "iso:country":"DK",
    "sg:address":"Abterpvej 13",
    "sg:city":"Bredebro",
    "sg:orig_category":"Maskinstationer",
    "sg:phone":"+45 74 71 15 09",
    "sg:postcode":"6261",
    "sg:province":"Danmark",
    "wof:name":"Bredebro Maskinstation",
    "wof:placetype":"venue"
},
  "geometry": {"coordinates":[8.8108539581,55.0645866394],"type":"Point"}
}