{
  "type": "Feature",
  "properties": {
    "addr:full":"Fayesgade 7 Hobro Danmark 9500",
    "addr:housenumber":"7",
    "addr:postcode":"9500",
    "addr:street":"Fayesgade",
    "iso:country":"DK",
    "sg:address":"Fayesgade 7",
    "sg:city":"Hobro",
    "sg:orig_category":"Autoudlejning",
    "sg:phone":"+45 98 52 56 48",
    "sg:postcode":"9500",
    "sg:province":"Danmark",
    "wof:name":"SK Minibus-udlejning",
    "wof:placetype":"venue"
},
  "geometry": {"coordinates":[9.802687645,56.6357955933],"type":"Point"}
}