{
  "type": "Feature",
  "properties": {
    "addr:full":"Egev\u00e6nget 4, Gadevang Hiller\u00f8d Danmark 3400",
    "addr:housenumber":"4",
    "addr:postcode":"3400",
    "addr:street":"Egevaenget",
    "iso:country":"DK",
    "sg:address":"Egev\u00e6nget 4, Gadevang",
    "sg:city":"Hiller\u00f8d",
    "sg:orig_category":"Elektronik",
    "sg:phone":"+45 48 25 05 25",
    "sg:postcode":"3400",
    "sg:province":"Danmark",
    "wof:name":"Steens Eftf., Arne",
    "wof:placetype":"venue"
},
  "geometry": {"coordinates":[12.3056097031,55.9288215637],"type":"Point"}
}