{
  "type": "Feature",
  "properties": {
    "addr:full":"Storegade 52 Haderslev Danmark 6100",
    "addr:housenumber":"52",
    "addr:postcode":"6100",
    "addr:street":"Storegade",
    "iso:country":"DK",
    "sg:address":"Storegade 52",
    "sg:city":"Haderslev",
    "sg:orig_category":"Reklamebureauer",
    "sg:phone":"+45 74 53 26 09",
    "sg:postcode":"6100",
    "sg:province":"Danmark",
    "wof:name":"Tekst & Design",
    "wof:placetype":"venue"
},
  "geometry": {"coordinates":[9.4811286926,55.2523841858],"type":"Point"}
}