{
  "type": "Feature",
  "properties": {
    "addr:full":"Lynevej 7, Sdr. Vium Hemmet Danmark 6893",
    "addr:housenumber":"7",
    "addr:postcode":"6893",
    "addr:street":"Lynevej;Sdr. Vium",
    "iso:country":"DK",
    "sg:address":"Lynevej 7, Sdr. Vium",
    "sg:city":"Hemmet",
    "sg:orig_category":"Forsamlingshuse",
    "sg:phone":"+45 97 37 54 56",
    "sg:postcode":"6893",
    "sg:province":"Danmark",
    "wof:name":"Sdr. Vium Forsamlingshus",
    "wof:placetype":"venue"
},
  "geometry": {"coordinates":[8.2862300873,55.8409957886],"type":"Point"}
}