{
  "type": "Feature",
  "properties": {
    "addr:full":"Br\u00f8sbjergvej 12 Knebel Danmark 8420",
    "addr:housenumber":"12",
    "addr:postcode":"8420",
    "addr:street":"Brosbjergvej",
    "iso:country":"DK",
    "sg:address":"Br\u00f8sbjergvej 12",
    "sg:city":"Knebel",
    "sg:orig_category":"Kirker",
    "sg:postcode":"8420",
    "sg:province":"Danmark",
    "wof:name":"Helgen\u00e6s Kirke",
    "wof:placetype":"venue"
},
  "geometry": {"coordinates":[10.5106611252,56.1328659058],"type":"Point"}
}