{
  "type": "Feature",
  "properties": {
    "addr:full":"Industrivej 3 Broager Danmark 6310",
    "addr:housenumber":"3",
    "addr:postcode":"6310",
    "addr:street":"Industrivej",
    "iso:country":"DK",
    "sg:address":"Industrivej 3",
    "sg:city":"Broager",
    "sg:orig_category":"Arbejdsformidling",
    "sg:phone":"+45 74 44 07 20",
    "sg:postcode":"6310",
    "sg:province":"Danmark",
    "wof:name":"Serviceafdelingen",
    "wof:placetype":"venue"
},
  "geometry": {"coordinates":[9.6594352722,54.8946151733],"type":"Point"}
}