{
  "type": "Feature",
  "properties": {
    "addr:full":"Torvegade 2 D Auning Danmark 8963",
    "addr:housenumber":"2 d",
    "addr:postcode":"8963",
    "addr:street":"Torvegade",
    "iso:country":"DK",
    "sg:address":"Torvegade 2 D",
    "sg:city":"Auning",
    "sg:orig_category":"Revisorer",
    "sg:phone":"+45 86 48 46 00",
    "sg:postcode":"8963",
    "sg:province":"Danmark",
    "wof:name":"NationalRevision, Registrerede Revisorer A/S",
    "wof:placetype":"venue"
},
  "geometry": {"coordinates":[10.3764228821,56.430103302],"type":"Point"}
}