{
  "type": "Feature",
  "properties": {
    "addr:full":"Kongensgade 22 Esbjerg Danmark 6700",
    "addr:housenumber":"22",
    "addr:postcode":"6700",
    "addr:street":"Kongensgade",
    "iso:country":"DK",
    "sg:address":"Kongensgade 22",
    "sg:city":"Esbjerg",
    "sg:classifiers":[
        {
            "category":"Restaurant",
            "type":"Food & Drink"
        }
    ],
    "sg:phone":"+45 75 12 00 78",
    "sg:postcode":"6700",
    "sg:province":"Danmark",
    "wof:name":"Ingeborg, Hos",
    "wof:placetype":"venue"
},
  "geometry": {"coordinates":[8.4539222717,55.4656524658],"type":"Point"}
}