{
  "type": "Feature",
  "properties": {
    "iso:country":"DK",
    "sg:address":"Havnegade 22",
    "sg:city":"Hirtshals",
    "sg:orig_category":"Sejlmagere",
    "sg:phone":"+45 98 94 12 27",
    "sg:postcode":"9850",
    "sg:province":"Danmark",
    "wof:name":"Hirtshals Sejlmageri",
    "wof:placetype":"venue"
},
  "geometry": {"coordinates":[9.9636249542,57.59192276],"type":"Point"}
}