{
  "type": "Feature",
  "properties": {
    "addr:full":"S\u00f8ndergade 64 Frederikshavn Danmark 9900",
    "addr:housenumber":"64",
    "addr:postcode":"9900",
    "addr:street":"Sondergade",
    "iso:country":"DK",
    "sg:address":"S\u00f8ndergade 64",
    "sg:city":"Frederikshavn",
    "sg:orig_category":"Rejsebureauer",
    "sg:phone":"+45 98 42 21 00",
    "sg:postcode":"9900",
    "sg:province":"Danmark",
    "wof:name":"FDM travel",
    "wof:placetype":"venue"
},
  "geometry": {"coordinates":[10.5287828445,57.4336051941],"type":"Point"}
}