{
  "type": "Feature",
  "properties": {
    "addr:full":"Klublokale, Asylgade 1 B, st. th. Frederikshavn Danmark 9900",
    "addr:housenumber":"1",
    "addr:postcode":"9900",
    "addr:street":"Asylgade;B St. Th.",
    "iso:country":"DK",
    "sg:address":"Klublokale, Asylgade 1 B, st. th.",
    "sg:city":"Frederikshavn",
    "sg:orig_category":"Hobbybetonede foreninger",
    "sg:postcode":"9900",
    "sg:province":"Danmark",
    "wof:name":"Frederikshavn Fotoklub",
    "wof:placetype":"venue"
},
  "geometry": {"coordinates":[10.5362997055,57.4396400452],"type":"Point"}
}