{
  "type": "Feature",
  "properties": {
    "addr:full":"Vestergade 11 - 15 Skive Danmark 7800",
    "addr:housenumber":"11 15",
    "addr:postcode":"7800",
    "addr:street":"Vestergade",
    "iso:country":"DK",
    "sg:address":"Vestergade 11 - 15",
    "sg:city":"Skive",
    "sg:orig_category":"Musikinstrumenter",
    "sg:phone":"+45 97 52 25 50",
    "sg:postcode":"7800",
    "sg:province":"Danmark",
    "wof:name":"St\u00e6rk Musikhandel, Per",
    "wof:placetype":"venue"
},
  "geometry": {"coordinates":[9.0239706039,56.565536499],"type":"Point"}
}