{
  "type": "Feature",
  "properties": {
    "addr:full":"Jomfru Ane Gade 9 Aalborg Danmark 9000",
    "addr:housenumber":"9",
    "addr:postcode":"9000",
    "addr:street":"Jomfru Ane Gade",
    "iso:country":"DK",
    "sg:address":"Jomfru Ane Gade 9",
    "sg:city":"Aalborg",
    "sg:classifiers":[
        {
            "category":"Restaurant",
            "type":"Food & Drink"
        }
    ],
    "sg:phone":"+45 98 13 99 95",
    "sg:postcode":"9000",
    "sg:province":"Danmark",
    "wof:name":"Manhattan",
    "wof:placetype":"venue"
},
  "geometry": {"coordinates":[9.9184751511,57.0499000549],"type":"Point"}
}