{
  "type": "Feature",
  "properties": {
    "addr:full":"Danmarksgade 14 Lemvig Danmark 7620",
    "addr:housenumber":"14",
    "addr:postcode":"7620",
    "addr:street":"Danmarksgade",
    "iso:country":"DK",
    "sg:address":"Danmarksgade 14",
    "sg:city":"Lemvig",
    "sg:orig_category":"Faglige organisationer og foreninger",
    "sg:phone":"+45 97 82 04 93",
    "sg:postcode":"7620",
    "sg:province":"Danmark",
    "wof:name":"Dansk Metalarbejderforbund",
    "wof:placetype":"venue"
},
  "geometry": {"coordinates":[8.3016748428,56.5458450317],"type":"Point"}
}