{
  "type": "Feature",
  "properties": {
    "addr:full":"Gartnerparken 1 - 5 Trige Danmark 8380",
    "addr:housenumber":"1 5",
    "addr:postcode":"8380",
    "addr:street":"Gartnerparken",
    "iso:country":"DK",
    "sg:address":"Gartnerparken 1 - 5",
    "sg:city":"Trige",
    "sg:orig_category":"Lokalcentre",
    "sg:phone":"+45 86 23 20 11",
    "sg:postcode":"8380",
    "sg:province":"Danmark",
    "wof:name":"Lokalcentret Bj\u00f8rnsh\u00f8j",
    "wof:placetype":"venue"
},
  "geometry": {"coordinates":[10.1442975998,56.2523727417],"type":"Point"}
}