{
  "type": "Feature",
  "properties": {
    "addr:full":"Fmd.: Tom R. Jensen, Sj\u00e6llandsgade 20 Ringsted Danmark 4100",
    "addr:housenumber":"20",
    "addr:postcode":"4100",
    "addr:street":"Sjaellandsgade",
    "iso:country":"DK",
    "sg:address":"Fmd.: Tom R. Jensen, Sj\u00e6llandsgade 20",
    "sg:city":"Ringsted",
    "sg:orig_category":"Hobbybetonede foreninger",
    "sg:phone":"+45 57 61 41 09",
    "sg:postcode":"4100",
    "sg:province":"Danmark",
    "wof:name":"Ringsted og omegns M\u00f8ntklub",
    "wof:placetype":"venue"
},
  "geometry": {"coordinates":[11.7875862122,55.4458961487],"type":"Point"}
}