{
  "type": "Feature",
  "properties": {
    "addr:full":"Industrivej 41 Fjerritslev Danmark 9690",
    "addr:housenumber":"41",
    "addr:postcode":"9690",
    "addr:street":"Industrivej",
    "iso:country":"DK",
    "sg:address":"Industrivej 41",
    "sg:city":"Fjerritslev",
    "sg:orig_category":"Autoforhandlere",
    "sg:phone":"+45 98 21 16 66",
    "sg:postcode":"9690",
    "sg:province":"Danmark",
    "wof:name":"Autocentralen Fjerritslev ApS",
    "wof:placetype":"venue"
},
  "geometry": {"coordinates":[9.251449585,57.0869560242],"type":"Point"}
}