{
  "type": "Feature",
  "properties": {
    "iso:country":"DK",
    "sg:address":"Lygten 29",
    "sg:city":"K\u00f8benhavn NV",
    "sg:orig_category":"Cafeer",
    "sg:phone":"+45 35 81 88 90",
    "sg:postcode":"2400",
    "sg:province":"Danmark",
    "wof:name":"Cafe Lygten",
    "wof:placetype":"venue"
},
  "geometry": {"coordinates":[-117.02272033689999,38.5024604797],"type":"Point"}
}