{
  "type": "Feature",
  "properties": {
    "addr:full":"\u00d8stergade 4, Hvidbjerg Thyholm Danmark 7790",
    "addr:housenumber":"4",
    "addr:postcode":"7790",
    "addr:street":"Ostergade;Hvidbjerg",
    "iso:country":"DK",
    "sg:address":"\u00d8stergade 4, Hvidbjerg",
    "sg:city":"Thyholm",
    "sg:orig_category":"Faglige organisationer og foreninger",
    "sg:phone":"+45 97 87 15 50",
    "sg:postcode":"7790",
    "sg:province":"Danmark",
    "wof:name":"SID Thyholm afdeling",
    "wof:placetype":"venue"
},
  "geometry": {"coordinates":[8.525765419,56.6507072449],"type":"Point"}
}