{
  "type": "Feature",
  "properties": {
    "addr:full":"\u00d8sterbro 24 Aalborg Danmark 9000",
    "addr:housenumber":"24",
    "addr:postcode":"9000",
    "addr:street":"Osterbro",
    "iso:country":"DK",
    "sg:address":"\u00d8sterbro 24",
    "sg:city":"Aalborg",
    "sg:orig_category":"Autoforhandlere",
    "sg:phone":"+45 98 12 27 22",
    "sg:postcode":"9000",
    "sg:province":"Danmark",
    "wof:name":"Kubicki Automobiler",
    "wof:placetype":"venue"
},
  "geometry": {"coordinates":[9.9347333908,57.046005249],"type":"Point"}
}