{
  "type": "Feature",
  "properties": {
    "addr:full":"Smedev\u00e6nget 8 Aarup Danmark 5560",
    "addr:housenumber":"8",
    "addr:postcode":"5560",
    "addr:street":"Smedevaenget",
    "iso:country":"DK",
    "sg:address":"Smedev\u00e6nget 8",
    "sg:city":"Aarup",
    "sg:orig_category":"Fabrikker",
    "sg:phone":"+45 64 43 22 66",
    "sg:postcode":"5560",
    "sg:province":"Danmark",
    "wof:name":"Hjem-Is Depot",
    "wof:placetype":"venue"
},
  "geometry": {"coordinates":[10.0490245819,55.3808059692],"type":"Point"}
}