{
  "type": "Feature",
  "properties": {
    "iso:country":"DK",
    "sg:address":"Bytoften 19",
    "sg:city":"Jordrup",
    "sg:orig_category":"Blikkenslagere",
    "sg:phone":"+45 75 55 64 46",
    "sg:postcode":"6064",
    "sg:province":"Danmark",
    "wof:name":"J\u00f8rgensen, Carsten Reymond",
    "wof:placetype":"venue"
},
  "geometry": {"coordinates":[9.309961,55.555637],"type":"Point"}
}