{
  "type": "Feature",
  "properties": {
    "addr:full":"Vestervej 7 Grenaa Danmark 8500",
    "addr:housenumber":"7",
    "addr:postcode":"8500",
    "addr:street":"Vestervej",
    "iso:country":"DK",
    "sg:address":"Vestervej 7",
    "sg:city":"Grenaa",
    "sg:orig_category":"Skilte",
    "sg:phone":"+45 86 32 50 26",
    "sg:postcode":"8500",
    "sg:province":"Danmark",
    "wof:name":"Pr\u00e6stholm Skilte",
    "wof:placetype":"venue"
},
  "geometry": {"coordinates":[10.8687210083,56.4145126343],"type":"Point"}
}