{
  "type": "Feature",
  "properties": {
    "addr:full":"Fmd.: Carl Egon Andersen, Jydby 18 Otterup Danmark 5450",
    "addr:housenumber":"18",
    "addr:postcode":"5450",
    "addr:street":"Jydby",
    "iso:country":"DK",
    "sg:address":"Fmd.: Carl Egon Andersen, Jydby 18",
    "sg:city":"Otterup",
    "sg:orig_category":"Havne",
    "sg:phone":"+45 64 82 15 28",
    "sg:postcode":"5450",
    "sg:province":"Danmark",
    "wof:name":"Otterup Lystb\u00e5dehavn",
    "wof:placetype":"venue"
},
  "geometry": {"coordinates":[10.4545049667,55.5641746521],"type":"Point"}
}