{
  "type": "Feature",
  "properties": {
    "addr:full":"Hedemarksvej 46 Albertslund Danmark 2620",
    "addr:housenumber":"46",
    "addr:postcode":"2620",
    "addr:street":"Hedemarksvej",
    "iso:country":"DK",
    "sg:address":"Hedemarksvej 46",
    "sg:city":"Albertslund",
    "sg:orig_category":"Tagrenovering",
    "sg:phone":"+45 43 64 41 40",
    "sg:postcode":"2620",
    "sg:province":"Danmark",
    "wof:name":"C. J. Tagentreprise",
    "wof:placetype":"venue"
},
  "geometry": {"coordinates":[12.3373613358,55.6570510864],"type":"Point"}
}