{
  "type": "Feature",
  "properties": {
    "iso:country":"DK",
    "sg:address":"Hyldemorsvej 32",
    "sg:city":"Herlev",
    "sg:orig_category":"Bogbinderier",
    "sg:phone":"+45 44 94 33 31",
    "sg:postcode":"2730",
    "sg:province":"Danmark",
    "wof:name":"Thorsen, J\u00f8rgen",
    "wof:placetype":"venue"
},
  "geometry": {"coordinates":[12.4507389069,55.728061676],"type":"Point"}
}