{
  "type": "Feature",
  "properties": {
    "iso:country":"DK",
    "sg:address":"S\u00f8gade 1 A, kdl.",
    "sg:city":"Ringsted",
    "sg:orig_category":"Jagt- og fiskeudstyr",
    "sg:phone":"+45 57 61 82 82",
    "sg:postcode":"4100",
    "sg:province":"Danmark",
    "wof:name":"Grej K\u00e6lderen",
    "wof:placetype":"venue"
},
  "geometry": {"coordinates":[11.7875862122,55.4458961487],"type":"Point"}
}