{
  "type": "Feature",
  "properties": {
    "addr:full":"Kirkegade 9 Esbjerg Danmark 6700",
    "addr:housenumber":"9",
    "addr:postcode":"6700",
    "addr:street":"Kirkegade",
    "iso:country":"DK",
    "sg:address":"Kirkegade 9",
    "sg:city":"Esbjerg",
    "sg:orig_category":"Revisorer",
    "sg:phone":"+45 75 13 47 11",
    "sg:postcode":"6700",
    "sg:province":"Danmark",
    "wof:name":"Skov ApS Revisionsfirmaet, Svend Erik",
    "wof:placetype":"venue"
},
  "geometry": {"coordinates":[8.4788503647,55.477558136],"type":"Point"}
}