{
  "type": "Feature",
  "properties": {
    "addr:full":"Duelundvej 9 Kjellerup Danmark 8620",
    "addr:housenumber":"9",
    "addr:postcode":"8620",
    "addr:street":"Duelundvej",
    "iso:country":"DK",
    "sg:address":"Duelundvej 9",
    "sg:city":"Kjellerup",
    "sg:orig_category":"Malermestre",
    "sg:phone":"+45 86 88 21 15",
    "sg:postcode":"8620",
    "sg:province":"Danmark",
    "wof:name":"Steiniches Malerforretning, Erik",
    "wof:placetype":"venue"
},
  "geometry": {"coordinates":[9.4089727402,56.3044128418],"type":"Point"}
}