{
  "type": "Feature",
  "properties": {
    "addr:full":"Viby Centret, Viby Ringvej 10 Viby Danmark 8260",
    "addr:housenumber":"10",
    "addr:postcode":"8260",
    "addr:street":"Viby Centret Viby Ringvej",
    "iso:country":"DK",
    "sg:address":"Viby Centret, Viby Ringvej 10",
    "sg:city":"Viby",
    "sg:classifiers":[
        {
            "category":"Banks & Credit Unions",
            "subcategory":"Bank",
            "type":"Services"
        }
    ],
    "sg:phone":"+45 87 34 20 00",
    "sg:postcode":"8260",
    "sg:province":"Danmark",
    "sg:tags":[
        "banker"
    ],
    "sg:website":"www.danskebank.dk",
    "wof:name":"Danske Bank",
    "wof:placetype":"venue"
},
  "geometry": {"coordinates":[10.1164493561,56.1353530884],"type":"Point"}
}