{
  "type": "Feature",
  "properties": {
    "addr:full":"D\u00e6mningen 41, 1. Vejle Danmark 7100",
    "addr:housenumber":"41 1",
    "addr:postcode":"7100",
    "addr:street":"Daemningen",
    "iso:country":"DK",
    "sg:address":"D\u00e6mningen 41, 1.",
    "sg:city":"Vejle",
    "sg:orig_category":"Faglige organisationer og foreninger",
    "sg:phone":"+45 75 82 22 07",
    "sg:postcode":"7100",
    "sg:province":"Danmark",
    "wof:name":"LO Vejle",
    "wof:placetype":"venue"
},
  "geometry": {"coordinates":[9.5359258652,55.7101898193],"type":"Point"}
}