{
  "type": "Feature",
  "properties": {
    "iso:country":"DK",
    "sg:address":"Fmd.: Svend Nielsen, G\u00f8ttrupstrandvej 60, G\u00f8ttrup Strand",
    "sg:city":"Fjerritslev",
    "sg:orig_category":"Kirkelige foreninger",
    "sg:phone":"+45 98 22 32 32",
    "sg:postcode":"9690",
    "sg:province":"Danmark",
    "wof:name":"KFUM/K Kettrup-G\u00f8ttrup",
    "wof:placetype":"venue"
},
  "geometry": {"coordinates":[9.2667350769,57.0882301331],"type":"Point"}
}