{
  "type": "Feature",
  "properties": {
    "addr:full":"Sabro Skolevej 4 Sabro Danmark 8471",
    "addr:housenumber":"4",
    "addr:postcode":"8471",
    "addr:street":"Sabro Skolevej",
    "iso:country":"DK",
    "sg:address":"Sabro Skolevej 4",
    "sg:city":"Sabro",
    "sg:orig_category":"Kommunale folkeskoler",
    "sg:phone":"+45 87 48 64 11",
    "sg:postcode":"8471",
    "sg:province":"Danmark",
    "sg:website":"www.sabro-korsvejskolen.dk",
    "wof:name":"Sabro-Korsvejskolen",
    "wof:placetype":"venue"
},
  "geometry": {"coordinates":[10.0236091614,56.2120437622],"type":"Point"}
}