{
  "type": "Feature",
  "properties": {
    "addr:full":"Godth\u00e5bsvej 88 Frederiksberg Danmark 2000",
    "addr:housenumber":"88",
    "addr:postcode":"2000",
    "addr:street":"Godthaabsvej",
    "iso:country":"DK",
    "sg:address":"Godth\u00e5bsvej 88",
    "sg:city":"Frederiksberg",
    "sg:orig_category":"Cafeer",
    "sg:phone":"+45 38 88 80 46",
    "sg:postcode":"2000",
    "sg:province":"Danmark",
    "wof:name":"Hardi's Caf\u00e9",
    "wof:placetype":"venue"
},
  "geometry": {"coordinates":[12.5252771378,55.6885566711],"type":"Point"}
}