{
  "type": "Feature",
  "properties": {
    "iso:country":"DK",
    "sg:address":"Hyldeg\u00e5rdsvej 29",
    "sg:city":"Charlottenlund",
    "sg:orig_category":"Ejendomshandel",
    "sg:phone":"+45 39 64 35 00",
    "sg:postcode":"2920",
    "sg:province":"Danmark",
    "wof:name":"Kromann og Partnere, Ejendomscenteret",
    "wof:placetype":"venue"
},
  "geometry": {"coordinates":[12.5788955688,55.7606010437],"type":"Point"}
}