{
  "type": "Feature",
  "properties": {
    "addr:full":"Fmd.: Torben Brynildsen, Kongensgavevej 1 D Helsinge Danmark 3200",
    "addr:housenumber":"1 d",
    "addr:postcode":"3200",
    "addr:street":"Kongensgavevej",
    "iso:country":"DK",
    "sg:address":"Fmd.: Torben Brynildsen, Kongensgavevej 1 D",
    "sg:city":"Helsinge",
    "sg:orig_category":"Grundejerforeninger",
    "sg:postcode":"3200",
    "sg:province":"Danmark",
    "wof:name":"Kongensgavevej 1 A-7 H Grundejerforening",
    "wof:placetype":"venue"
},
  "geometry": {"coordinates":[12.196846962,56.0224456787],"type":"Point"}
}