{
  "type": "Feature",
  "properties": {
    "iso:country":"DK",
    "sg:address":"Fmd.: J\u00f8rgen Berthelsen, Strandv\u00e6nget 4",
    "sg:city":"Rungsted Kyst",
    "sg:orig_category":"Kulturelle foreninger",
    "sg:phone":"+45 45 86 36 09",
    "sg:postcode":"2960",
    "sg:province":"Danmark",
    "sg:website":"www.jgberthelsen.suite.dk",
    "wof:name":"H\u00f8rsholm Ark\u00e6ologiske Forening",
    "wof:placetype":"venue"
},
  "geometry": {"coordinates":[12.5300750732,55.883846283],"type":"Point"}
}