{
  "type": "Feature",
  "properties": {
    "iso:country":"DK",
    "sg:address":"Kredsf\u00f8rer: Thomas L. Pilgaard, M\u00f8llehusvej 10, st.mf.",
    "sg:city":"Roskilde",
    "sg:orig_category":"Spejderkorps",
    "sg:phone":"+45 46 36 34 56",
    "sg:postcode":"4000",
    "sg:province":"Danmark",
    "sg:website":"www.roskilde.dbs.dk",
    "wof:name":"Danske Baptisters Spejderkorps",
    "wof:placetype":"venue"
},
  "geometry": {"coordinates":[12.0909376144,55.6404838562],"type":"Point"}
}