{
  "type": "Feature",
  "properties": {
    "iso:country":"DK",
    "sg:address":"Farum Bytorv 13",
    "sg:city":"Farum",
    "sg:orig_category":"Blomsterhandlere",
    "sg:phone":"+45 44 95 48 00",
    "sg:postcode":"3520",
    "sg:province":"Danmark",
    "wof:name":"Plante-Hallen",
    "wof:placetype":"venue"
},
  "geometry": {"coordinates":[12.3809099197,55.8150367737],"type":"Point"}
}