{
  "type": "Feature",
  "properties": {
    "addr:full":"Niels Hemmingsens Gade 10 K\u00f8benhavn Danmark 1153",
    "addr:housenumber":"10;1153",
    "addr:street":"Niels Hemmingsens Gade",
    "iso:country":"DK",
    "sg:address":"Niels Hemmingsens Gade 10",
    "sg:city":"K\u00f8benhavn",
    "sg:orig_category":"Diskoteker",
    "sg:phone":"+45 33 15 26 00",
    "sg:postcode":"1153",
    "sg:province":"Danmark",
    "sg:website":"www.jazzhouse.dk",
    "wof:name":"Copenhagen Jazzhouse",
    "wof:placetype":"venue"
},
  "geometry": {"coordinates":[12.5790996552,55.6789016724],"type":"Point"}
}