{
  "type": "Feature",
  "properties": {
    "iso:country":"DK",
    "sg:address":"Lunavej 5",
    "sg:city":"Auning",
    "sg:orig_category":"Oliefyr og service",
    "sg:phone":"+45 86 48 39 27",
    "sg:postcode":"8963",
    "sg:province":"Danmark",
    "wof:name":"Auning VVS",
    "wof:placetype":"venue"
},
  "geometry": {"coordinates":[10.3803052902,56.4290847778],"type":"Point"}
}