{
  "type": "Feature",
  "properties": {
    "addr:full":"Baneg\u00e5rdspladsen 3 Maribo Danmark 4930",
    "addr:housenumber":"3",
    "addr:postcode":"4930",
    "addr:street":"Banegaardspladsen",
    "iso:country":"DK",
    "sg:address":"Baneg\u00e5rdspladsen 3",
    "sg:city":"Maribo",
    "sg:orig_category":"Faglige organisationer og foreninger",
    "sg:phone":"+45 54 78 03 93",
    "sg:postcode":"4930",
    "sg:province":"Danmark",
    "wof:name":"Murernes Fagforening SID",
    "wof:placetype":"venue"
},
  "geometry": {"coordinates":[11.5000228882,54.7760810852],"type":"Point"}
}