{
  "type": "Feature",
  "properties": {
    "iso:country":"DK",
    "sg:address":"Leder: Jane Kromann, Tvilum Kirkevej 21, Horn",
    "sg:city":"F\u00e5rvang",
    "sg:orig_category":"\u00c3\u02dcvrig fritidsundervisning",
    "sg:phone":"+45 86 87 16 19",
    "sg:postcode":"8882",
    "sg:province":"Danmark",
    "wof:name":"Gjern Aftenskole",
    "wof:placetype":"venue"
},
  "geometry": {"coordinates":[9.7311849594,56.2691383362],"type":"Point"}
}