{
  "type": "Feature",
  "properties": {
    "addr:full":"Fmd.: Dorte Sorkn\u00e6s, Bjarkesvej 14, Thur\u00f8 Svendborg Danmark 5700",
    "addr:housenumber":"14",
    "addr:postcode":"5700",
    "addr:street":"Bjarkesvej;Thuro",
    "iso:country":"DK",
    "sg:address":"Fmd.: Dorte Sorkn\u00e6s, Bjarkesvej 14, Thur\u00f8",
    "sg:city":"Svendborg",
    "sg:orig_category":"Musik og sang",
    "sg:phone":"+45 62 20 56 00",
    "sg:postcode":"5700",
    "sg:province":"Danmark",
    "wof:name":"Tved Sangkor",
    "wof:placetype":"venue"
},
  "geometry": {"coordinates":[10.6065101624,55.0595970154],"type":"Point"}
}