{
  "type": "Feature",
  "properties": {
    "addr:full":"Jernbanegade 11 Roskilde Danmark 4000",
    "addr:housenumber":"11",
    "addr:postcode":"4000",
    "addr:street":"Jernbanegade",
    "iso:country":"DK",
    "sg:address":"Jernbanegade 11",
    "sg:city":"Roskilde",
    "sg:orig_category":"Alternativ behandling",
    "sg:phone":"+45 46 36 76 40",
    "sg:postcode":"4000",
    "sg:province":"Danmark",
    "sg:website":"www.energipunktet.hjem.wanadoo.dk",
    "wof:name":"Energipunktet",
    "wof:placetype":"venue"
},
  "geometry": {"coordinates":[12.0823469162,55.6376724243],"type":"Point"}
}