{
  "type": "Feature",
  "properties": {
    "addr:full":"Erik Christiansen, \u00c5sbjerg 67 Give Danmark 7323",
    "addr:housenumber":"67",
    "addr:postcode":"7323",
    "addr:street":"Erik;Aasbjerg",
    "iso:country":"DK",
    "sg:address":"Erik Christiansen, \u00c5sbjerg 67",
    "sg:city":"Give",
    "sg:orig_category":"Skorstensfejere",
    "sg:phone":"+45 75 73 18 28",
    "sg:postcode":"7323",
    "sg:province":"Danmark",
    "wof:name":"Skorstensfejermester Give/Nr. Snede",
    "wof:placetype":"venue"
},
  "geometry": {"coordinates":[9.2362060547,55.845413208],"type":"Point"}
}