{
  "type": "Feature",
  "properties": {
    "addr:full":"Strandvejen 130 D Hellerup Danmark 2900",
    "addr:housenumber":"130 d",
    "addr:postcode":"2900",
    "addr:street":"Strandvejen",
    "iso:country":"DK",
    "sg:address":"Strandvejen 130 D",
    "sg:city":"Hellerup",
    "sg:orig_category":"Ejendomshandel",
    "sg:phone":"+45 39 62 95 25",
    "sg:postcode":"2900",
    "sg:province":"Danmark",
    "wof:name":"Hjort Hellerup EDC",
    "wof:placetype":"venue"
},
  "geometry": {"coordinates":[12.5772132874,55.7398452759],"type":"Point"}
}