{
  "type": "Feature",
  "properties": {
    "iso:country":"DK",
    "sg:address":"Sandn\u00e6svej 1",
    "sg:city":"Vejle",
    "sg:orig_category":"Grafiske tegnestuer",
    "sg:phone":"+45 75 72 01 27",
    "sg:postcode":"7100",
    "sg:province":"Danmark",
    "sg:website":"www.grafiskdesignstudio.dk",
    "wof:name":"Grafisk Design Studio",
    "wof:placetype":"venue"
},
  "geometry": {"coordinates":[9.5365915298,55.6758766174],"type":"Point"}
}