{
  "type": "Feature",
  "properties": {
    "addr:full":"Pastor: Frede Rasmussen, Mejl\u00f8v\u00e6nget 18, True Tilst Danmark 8381",
    "addr:housenumber":"rasmussen;18",
    "addr:postcode":"8381",
    "addr:street":"Pastor Frede;True",
    "iso:country":"DK",
    "sg:address":"Pastor: Frede Rasmussen, Mejl\u00f8v\u00e6nget 18, True",
    "sg:city":"Tilst",
    "sg:orig_category":"Trossamfund uden for folkekirken",
    "sg:phone":"+45 86 24 26 26",
    "sg:postcode":"8381",
    "sg:province":"Danmark",
    "sg:website":"www.pinsekirken-aarhus.dk",
    "wof:name":"Pinsekirken",
    "wof:placetype":"venue"
},
  "geometry": {"coordinates":[10.1078147888,56.1882019043],"type":"Point"}
}