{
  "type": "Feature",
  "properties": {
    "addr:full":"Voldgade 13 Svendborg Danmark 5700",
    "addr:housenumber":"13",
    "addr:postcode":"5700",
    "addr:street":"Voldgade",
    "iso:country":"DK",
    "sg:address":"Voldgade 13",
    "sg:city":"Svendborg",
    "sg:classifiers":[
        {
            "category":"Communications",
            "type":"Services"
        }
    ],
    "sg:phone":"+45 63 21 02 75",
    "sg:postcode":"5700",
    "sg:province":"Danmark",
    "sg:tags":[
        "radio-",
        "og",
        "tv-stationer"
    ],
    "sg:website":"www.radio3.dk",
    "wof:name":"Radio 3 Sydfyn",
    "wof:placetype":"venue"
},
  "geometry": {"coordinates":[10.6052074432,55.059211731],"type":"Point"}
}