{
  "type": "Feature",
  "properties": {
    "addr:full":"Sandefjordvej 5 Haderslev Danmark 6100",
    "addr:housenumber":"5",
    "addr:postcode":"6100",
    "addr:street":"Sandefjordvej",
    "iso:country":"DK",
    "sg:address":"Sandefjordvej 5",
    "sg:city":"Haderslev",
    "sg:orig_category":"Glarmestre og glarmagere",
    "sg:phone":"+45 74 53 29 96",
    "sg:postcode":"6100",
    "sg:province":"Danmark",
    "wof:name":"Glasmont\u00f8ren",
    "wof:placetype":"venue"
},
  "geometry": {"coordinates":[9.5000934601,55.261932373],"type":"Point"}
}