{
  "type": "Feature",
  "properties": {
    "addr:full":"Fmd.: Ernst M. Lauridsen, Kongevejen 80, Jegind\u00f8 Thyholm Danmark 7790",
    "addr:housenumber":"80",
    "addr:postcode":"7790",
    "addr:street":"Kongevejen",
    "iso:country":"DK",
    "sg:address":"Fmd.: Ernst M. Lauridsen, Kongevejen 80, Jegind\u00f8",
    "sg:city":"Thyholm",
    "sg:orig_category":"Kirkelige foreninger",
    "sg:phone":"+45 97 87 93 23",
    "sg:postcode":"7790",
    "sg:province":"Danmark",
    "wof:name":"Indre Mission, Jegind\u00f8",
    "wof:placetype":"venue"
},
  "geometry": {"coordinates":[8.525765419,56.6507072449],"type":"Point"}
}