{
  "type": "Feature",
  "properties": {
    "addr:full":"Kandestedvej 55, Hulsig Skagen Danmark 9990",
    "addr:housenumber":"55",
    "addr:postcode":"9990",
    "addr:street":"Kandestedvej",
    "iso:country":"DK",
    "sg:address":"Kandestedvej 55, Hulsig",
    "sg:city":"Skagen",
    "sg:orig_category":"Campingpladser",
    "sg:phone":"+45 98 48 75 00",
    "sg:postcode":"9990",
    "sg:province":"Danmark",
    "wof:name":"R\u00e5bjerg Mile Camping",
    "wof:placetype":"venue"
},
  "geometry": {"coordinates":[10.5958003998,57.7247200012],"type":"Point"}
}