{
  "type": "Feature",
  "properties": {
    "addr:full":"Fabrikvej 15, R\u00f8jle Middelfart Danmark 5500",
    "addr:housenumber":"15",
    "addr:postcode":"5500",
    "addr:street":"Fabrikvej",
    "iso:country":"DK",
    "sg:address":"Fabrikvej 15, R\u00f8jle",
    "sg:city":"Middelfart",
    "sg:orig_category":"Emballage",
    "sg:phone":"+45 64 40 16 10",
    "sg:postcode":"5500",
    "sg:province":"Danmark",
    "wof:name":"Fyens \u00c6skefabrik - Hepa A/S",
    "wof:placetype":"venue"
},
  "geometry": {"coordinates":[9.7417497635,55.5030250549],"type":"Point"}
}