{
  "type": "Feature",
  "properties": {
    "iso:country":"DK",
    "sg:address":"True M\u00f8llevej 2 ",
    "sg:city":"Tilst",
    "sg:classifiers":[
        {
            "category":"Wholesale",
            "subcategory":"Drugs",
            "type":"Manufacturing & Wholesale Goods"
        }
    ],
    "sg:phone":"+45 87 45 15 00",
    "sg:postcode":"8381",
    "sg:province":"Danmark",
    "sg:tags":[
        "chemical",
        "pharmaceutical"
    ],
    "wof:name":"NOMECO A/S",
    "wof:placetype":"venue"
},
  "geometry": {"coordinates":[10.0868415833,56.1850967407],"type":"Point"}
}