{
  "type": "Feature",
  "properties": {
    "addr:full":"Overgade 46 Odense C Danmark 5000",
    "addr:housenumber":"46",
    "addr:postcode":"5000",
    "addr:street":"Overgade",
    "iso:country":"DK",
    "sg:address":"Overgade 46",
    "sg:city":"Odense C",
    "sg:orig_category":"Boghandlere",
    "sg:phone":"+45 66 19 48 47",
    "sg:postcode":"5000",
    "sg:province":"Danmark",
    "wof:name":"Himmel og Jord",
    "wof:placetype":"venue"
},
  "geometry": {"coordinates":[10.3935213089,55.39793396],"type":"Point"}
}