{
  "type": "Feature",
  "properties": {
    "addr:full":"Rudmevej 83-85, Herringe Ringe Danmark 5750",
    "addr:housenumber":"83-85",
    "addr:postcode":"5750",
    "addr:street":"Rudmevej",
    "iso:country":"DK",
    "sg:address":"Rudmevej 83-85, Herringe",
    "sg:city":"Ringe",
    "sg:orig_category":"Fotolaboratorier",
    "sg:phone":"+45 62 62 14 17",
    "sg:postcode":"5750",
    "sg:province":"Danmark",
    "wof:name":"H B H Fotolaboratorium",
    "wof:placetype":"venue"
},
  "geometry": {"coordinates":[10.4781074524,55.2356643677],"type":"Point"}
}