{
  "type": "Feature",
  "properties": {
    "iso:country":"DK",
    "sg:address":"Grantoften 5",
    "sg:city":"Viby Sj\u00e6lland",
    "sg:orig_category":"Integrerede institutioner",
    "sg:phone":"+45 46 19 51 52",
    "sg:postcode":"4130",
    "sg:province":"Danmark",
    "wof:name":"N\u00f8ddebo",
    "wof:placetype":"venue"
},
  "geometry": {"coordinates":[12.0261983871,55.5461349487],"type":"Point"}
}