{
  "type": "Feature",
  "properties": {
    "addr:full":"Kildehusvej 8, Vinstrup Fuglebjerg Danmark 4250",
    "addr:housenumber":"8",
    "addr:postcode":"4250",
    "addr:street":"Kildehusvej",
    "iso:country":"DK",
    "sg:address":"Kildehusvej 8, Vinstrup",
    "sg:city":"Fuglebjerg",
    "sg:orig_category":"Arkitekter",
    "sg:phone":"+45 57 84 92 42",
    "sg:postcode":"4250",
    "sg:province":"Danmark",
    "wof:name":"van Deurs, Lone",
    "wof:placetype":"venue"
},
  "geometry": {"coordinates":[11.5452251434,55.3061332703],"type":"Point"}
}