{
  "type": "Feature",
  "properties": {
    "iso:country":"DK",
    "sg:address":"Asylvej 8 A",
    "sg:city":"Stubbek\u00f8bing",
    "sg:orig_category":"Varmeforsyning",
    "sg:phone":"+45 54 44 15 44",
    "sg:postcode":"4850",
    "sg:province":"Danmark",
    "wof:name":"Stubbek\u00f8bing Fjernvarmeselskab",
    "wof:placetype":"venue"
},
  "geometry": {"coordinates":[-114.0767440796,46.4432487488],"type":"Point"}
}