{
  "type": "Feature",
  "properties": {
    "addr:full":"Zentavej 1 A Gistrup Danmark 9260",
    "addr:housenumber":"1 a",
    "addr:postcode":"9260",
    "addr:street":"Zentavej",
    "iso:country":"DK",
    "sg:address":"Zentavej 1 A",
    "sg:city":"Gistrup",
    "sg:orig_category":"Kirker",
    "sg:postcode":"9260",
    "sg:province":"Danmark",
    "wof:name":"Gistrup Kirke",
    "wof:placetype":"venue"
},
  "geometry": {"coordinates":[9.9855537415,56.9933738708],"type":"Point"}
}