{
  "type": "Feature",
  "properties": {
    "addr:full":"Englandsvej 368 Kastrup Danmark 2770",
    "addr:housenumber":"368",
    "addr:postcode":"2770",
    "addr:street":"Englandsvej",
    "iso:country":"DK",
    "sg:address":"Englandsvej 368",
    "sg:city":"Kastrup",
    "sg:orig_category":"Dyrehandlere",
    "sg:phone":"+45 32 50 31 04",
    "sg:postcode":"2770",
    "sg:province":"Danmark",
    "sg:website":"www.baf.dk",
    "wof:name":"Dus med Dyrene",
    "wof:placetype":"venue"
},
  "geometry": {"coordinates":[12.6041250229,55.6243553162],"type":"Point"}
}