{
  "type": "Feature",
  "properties": {
    "iso:country":"DK",
    "sg:address":"Sletten 7",
    "sg:city":"Hornslet",
    "sg:orig_category":"Skorstensfejere",
    "sg:phone":"+45 86 99 46 24",
    "sg:postcode":"8543",
    "sg:province":"Danmark",
    "wof:name":"Eriksen, Poul-Otto",
    "wof:placetype":"venue"
},
  "geometry": {"coordinates":[10.3079805374,56.3050193787],"type":"Point"}
}