{
  "type": "Feature",
  "properties": {
    "addr:full":"Fmd.: E. S. Meldgaard, Kl\u00f8vermarksvej 29 Hj\u00f8rring Danmark 9800",
    "addr:housenumber":"29",
    "addr:postcode":"9800",
    "addr:street":"Klovermarksvej",
    "iso:country":"DK",
    "sg:address":"Fmd.: E. S. Meldgaard, Kl\u00f8vermarksvej 29",
    "sg:city":"Hj\u00f8rring",
    "sg:orig_category":"Andelsboligforeninger",
    "sg:phone":"+45 98 92 54 58",
    "sg:postcode":"9800",
    "sg:province":"Danmark",
    "wof:name":"Andelsboligforeningen Kl\u00f8vermarksvej",
    "wof:placetype":"venue"
},
  "geometry": {"coordinates":[-63.2513618469,-24.1957702637],"type":"Point"}
}