{
  "type": "Feature",
  "properties": {
    "addr:full":"Veks\u00f8 Bygade 15 Veks\u00f8 Sj\u00e6lland Danmark 3670",
    "addr:housenumber":"15",
    "addr:postcode":"3670",
    "addr:street":"Vekso Bygade",
    "iso:country":"DK",
    "sg:address":"Veks\u00f8 Bygade 15",
    "sg:city":"Veks\u00f8 Sj\u00e6lland",
    "sg:orig_category":"Integrerede institutioner",
    "sg:phone":"+45 47 17 32 10",
    "sg:postcode":"3670",
    "sg:province":"Danmark",
    "wof:name":"Daginstitutionen Skibstedg\u00e5rd",
    "wof:placetype":"venue"
},
  "geometry": {"coordinates":[-76.0886383057,38.7291030884],"type":"Point"}
}