{
  "type": "Feature",
  "properties": {
    "addr:full":"Frejasvej 1 D Spentrup Danmark 8981",
    "addr:housenumber":"1 d",
    "addr:postcode":"8981",
    "addr:street":"Frejasvej",
    "iso:country":"DK",
    "sg:address":"Frejasvej 1 D",
    "sg:city":"Spentrup",
    "sg:orig_category":"Pizzeriaer",
    "sg:phone":"+45 86 47 75 46",
    "sg:postcode":"8981",
    "sg:province":"Danmark",
    "wof:name":"Antalya, Pizza",
    "wof:placetype":"venue"
},
  "geometry": {"coordinates":[10.0384216309,56.5377922058],"type":"Point"}
}