{
  "type": "Feature",
  "properties": {
    "addr:full":"v/ Anna Overg\u00e5rd, Sundsvej 80, Nybo Herning Danmark 7400",
    "addr:housenumber":"80",
    "addr:postcode":"7400",
    "addr:street":"Sundsvej",
    "iso:country":"DK",
    "sg:address":"v/ Anna Overg\u00e5rd, Sundsvej 80, Nybo",
    "sg:city":"Herning",
    "sg:orig_category":"Kulturelle foreninger",
    "sg:phone":"+45 97 14 14 42",
    "sg:postcode":"7400",
    "sg:province":"Danmark",
    "wof:name":"H\u00f8jskolehjemmets Ungdomsforening",
    "wof:placetype":"venue"
},
  "geometry": {"coordinates":[8.9768896103,56.1374168396],"type":"Point"}
}