{
  "type": "Feature",
  "properties": {
    "iso:country":"DK",
    "sg:address":"Fmd.: Martin S\u00d8rensen, Torstilg\u00e5rdsvej 2, 1. th.",
    "sg:city":"Tilst",
    "sg:orig_category":"Kolonihaveforeninger",
    "sg:phone":"+45 86 24 54 04",
    "sg:postcode":"8381",
    "sg:province":"Danmark",
    "wof:name":"Haveforeningen Moselund",
    "wof:placetype":"venue"
},
  "geometry": {"coordinates":[10.1078147888,56.1882019043],"type":"Point"}
}