{
  "type": "Feature",
  "properties": {
    "addr:full":"M\u00f8lhavevej 20 Aabybro Danmark 9440",
    "addr:housenumber":"20",
    "addr:postcode":"9440",
    "addr:street":"Molhavevej",
    "iso:country":"DK",
    "sg:address":"M\u00f8lhavevej 20",
    "sg:city":"Aabybro",
    "sg:orig_category":"Fabrikker",
    "sg:phone":"+45 98 24 40 55",
    "sg:postcode":"9440",
    "sg:province":"Danmark",
    "wof:name":"Cubic-Modulsystem A/S",
    "wof:placetype":"venue"
},
  "geometry": {"coordinates":[9.7437324524,57.150554657],"type":"Point"}
}