{
  "type": "Feature",
  "properties": {
    "addr:full":"Kass.: Paul T. Andersen, P.N. Lagonis Vej 17 Vojens Danmark 6500",
    "addr:housenumber":"17",
    "addr:postcode":"6500",
    "addr:street":"Kass.;P.N. Lagonis Vej",
    "iso:country":"DK",
    "sg:address":"Kass.: Paul T. Andersen, P.N. Lagonis Vej 17",
    "sg:city":"Vojens",
    "sg:orig_category":"\u00c3\u2020ldreorganisationer og klubber",
    "sg:phone":"+45 74 54 17 08",
    "sg:postcode":"6500",
    "sg:province":"Danmark",
    "wof:name":"Stampersonelgruppens Senior og Pensionistklub",
    "wof:placetype":"venue"
},
  "geometry": {"coordinates":[9.2987146378,55.2457237244],"type":"Point"}
}