{
  "type": "Feature",
  "properties": {
    "addr:full":"Aalborgvej 29, Mou Storvorde Danmark 9280",
    "addr:housenumber":"29",
    "addr:postcode":"9280",
    "addr:street":"Aalborgvej",
    "iso:country":"DK",
    "sg:address":"Aalborgvej 29, Mou",
    "sg:city":"Storvorde",
    "sg:orig_category":"Malermestre",
    "sg:phone":"+45 98 31 00 85",
    "sg:postcode":"9280",
    "sg:province":"Danmark",
    "wof:name":"Bonne, Pia",
    "wof:placetype":"venue"
},
  "geometry": {"coordinates":[10.1014204025,57.0045547485],"type":"Point"}
}