{
  "type": "Feature",
  "properties": {
    "iso:country":"DK",
    "sg:address":"Geminivej 32, Postboks 180",
    "sg:city":"Greve",
    "sg:orig_category":"El-artikler",
    "sg:phone":"+45 43 95 95 95",
    "sg:postcode":"2670",
    "sg:province":"Danmark",
    "sg:website":"www.elpefa.dk",
    "wof:name":"Elpefa Handel-og Ingeni\u00f8rfirma A/S",
    "wof:placetype":"venue"
},
  "geometry": {"coordinates":[12.2941808701,55.5844078064],"type":"Point"}
}