{
  "type": "Feature",
  "properties": {
    "addr:full":"Fjordvej 59 Munkebo Danmark 5330",
    "addr:housenumber":"59",
    "addr:postcode":"5330",
    "addr:street":"Fjordvej",
    "iso:country":"DK",
    "sg:address":"Fjordvej 59",
    "sg:city":"Munkebo",
    "sg:orig_category":"Psykoterapi",
    "sg:phone":"+45 65 97 70 30",
    "sg:postcode":"5330",
    "sg:province":"Danmark",
    "wof:name":"Knudsen, Birthe",
    "wof:placetype":"venue"
},
  "geometry": {"coordinates":[10.5566625595,55.4560432434],"type":"Point"}
}