{
  "type": "Feature",
  "properties": {
    "addr:full":"Fmd.: Henning Schack, Rungstedvej 52 Rungsted Kyst Danmark 2960",
    "addr:housenumber":"52",
    "addr:postcode":"2960",
    "addr:street":"Rungstedvej",
    "iso:country":"DK",
    "sg:address":"Fmd.: Henning Schack, Rungstedvej 52",
    "sg:city":"Rungsted Kyst",
    "sg:orig_category":"Grundejerforeninger",
    "sg:phone":"+45 45 86 34 11",
    "sg:postcode":"2960",
    "sg:province":"Danmark",
    "wof:name":"Grundejer- og Kommunalforening for H\u00f8rsholm",
    "wof:placetype":"venue"
},
  "geometry": {"coordinates":[12.5300750732,55.883846283],"type":"Point"}
}