{
  "type": "Feature",
  "properties": {
    "addr:full":"Solbakken 7 Risskov Danmark 8240",
    "addr:housenumber":"7",
    "addr:postcode":"8240",
    "addr:street":"Solbakken",
    "iso:country":"DK",
    "sg:address":"Solbakken 7",
    "sg:city":"Risskov",
    "sg:orig_category":"Integrerede institutioner",
    "sg:phone":"+45 86 17 76 49",
    "sg:postcode":"8240",
    "sg:province":"Danmark",
    "wof:name":"Under B\u00f8gen, Integreret Inst.",
    "wof:placetype":"venue"
},
  "geometry": {"coordinates":[10.2344646454,56.187713623],"type":"Point"}
}