{
  "type": "Feature",
  "properties": {
    "addr:full":"Solvangen 12 Nyk\u00f8bing Danmark 7900",
    "addr:housenumber":"12",
    "addr:postcode":"7900",
    "addr:street":"Solvangen",
    "iso:country":"DK",
    "sg:address":"Solvangen 12",
    "sg:city":"Nyk\u00f8bing",
    "sg:orig_category":"Autoreparation og -service",
    "sg:phone":"+45 97 72 26 11",
    "sg:postcode":"7900",
    "sg:province":"Danmark",
    "wof:name":"B\u00fclow's Auto",
    "wof:placetype":"venue"
},
  "geometry": {"coordinates":[-114.0768203735,46.4432411194],"type":"Point"}
}