{
  "type": "Feature",
  "properties": {
    "addr:full":"Mosebakken 21 Virum Danmark 2830",
    "addr:housenumber":"21",
    "addr:postcode":"2830",
    "addr:street":"Mosebakken",
    "iso:country":"DK",
    "sg:address":"Mosebakken 21",
    "sg:city":"Virum",
    "sg:orig_category":"Fotografer",
    "sg:phone":"+45 45 85 79 92",
    "sg:postcode":"2830",
    "sg:province":"Danmark",
    "wof:name":"GT Foto",
    "wof:placetype":"venue"
},
  "geometry": {"coordinates":[12.4589853287,55.7967224121],"type":"Point"}
}