{
  "type": "Feature",
  "properties": {
    "addr:full":"Nyh\u00e5bsvej 16 Kolind Danmark 8560",
    "addr:housenumber":"16",
    "addr:postcode":"8560",
    "addr:street":"Nyhaabsvej",
    "iso:country":"DK",
    "sg:address":"Nyh\u00e5bsvej 16",
    "sg:city":"Kolind",
    "sg:orig_category":"Autoophug",
    "sg:phone":"+45 86 39 29 00",
    "sg:postcode":"8560",
    "sg:province":"Danmark",
    "wof:name":"Koed 3'er Ophug",
    "wof:placetype":"venue"
},
  "geometry": {"coordinates":[10.5725193024,56.3517913818],"type":"Point"}
}