{
  "type": "Feature",
  "properties": {
    "iso:country":"DK",
    "sg:address":"S\u00f8nder Lemvej 16, Sdr. Lem",
    "sg:city":"Sp\u00f8ttrup",
    "sg:orig_category":"Genbrugsbutikker",
    "sg:phone":"+45 97 56 82 73",
    "sg:postcode":"7860",
    "sg:province":"Danmark",
    "sg:website":"www.toj-toys.dk",
    "wof:name":"T\u00f8j & Toys",
    "wof:placetype":"venue"
},
  "geometry": {"coordinates":[8.7428588867,56.5733261108],"type":"Point"}
}