{
  "type": "Feature",
  "properties": {
    "addr:full":"Margrethesvej 7, Lind Herning Danmark 7400",
    "addr:housenumber":"7",
    "addr:postcode":"7400",
    "addr:street":"Margrethesvej",
    "iso:country":"DK",
    "sg:address":"Margrethesvej 7, Lind",
    "sg:city":"Herning",
    "sg:orig_category":"Plejehjem",
    "sg:phone":"+45 97 12 40 05",
    "sg:postcode":"7400",
    "sg:province":"Danmark",
    "wof:name":"Kildevang",
    "wof:placetype":"venue"
},
  "geometry": {"coordinates":[8.9768896103,56.1374168396],"type":"Point"}
}