{
  "type": "Feature",
  "properties": {
    "addr:full":"Nybrovej 333 Kongens Lyngby Danmark 2800",
    "addr:housenumber":"333",
    "addr:postcode":"2800",
    "addr:street":"Nybrovej",
    "iso:country":"DK",
    "sg:address":"Nybrovej 333",
    "sg:city":"Kongens Lyngby",
    "sg:orig_category":"Socialpsykiatriske bosteder",
    "sg:phone":"+45 45 87 70 25",
    "sg:postcode":"2800",
    "sg:province":"Danmark",
    "wof:name":"Nybrog\u00e5rd plejehjem",
    "wof:placetype":"venue"
},
  "geometry": {"coordinates":[12.472155571,55.7729606628],"type":"Point"}
}