{
  "type": "Feature",
  "properties": {
    "addr:full":"Smedevej 7 Ikast Danmark 7430",
    "addr:housenumber":"7",
    "addr:postcode":"7430",
    "addr:street":"Smedevej",
    "iso:country":"DK",
    "sg:address":"Smedevej 7",
    "sg:city":"Ikast",
    "sg:orig_category":"Elektro",
    "sg:phone":"+45 97 25 15 16",
    "sg:postcode":"7430",
    "sg:province":"Danmark",
    "wof:name":"JW Elektro A/S",
    "wof:placetype":"venue"
},
  "geometry": {"coordinates":[9.1788330078,56.128200531],"type":"Point"}
}