{
  "type": "Feature",
  "properties": {
    "addr:full":"Torslundevej 120, Torslunde Ish\u00f8j Danmark 2635",
    "addr:housenumber":"120",
    "addr:postcode":"2635",
    "addr:street":"Torslundevej;Torslunde Ishoj Danmark",
    "iso:country":"DK",
    "sg:address":"Torslundevej 120, Torslunde",
    "sg:city":"Ish\u00f8j",
    "sg:orig_category":"Non-Classified Establishments",
    "sg:phone":"+45 43 99 96 50",
    "sg:postcode":"2635",
    "sg:province":"Danmark",
    "sg:website":"www.lyngbyhegn.dk",
    "wof:name":"Lyngby Hegn",
    "wof:placetype":"venue"
},
  "geometry": {"coordinates":[12.2484397888,55.626411438],"type":"Point"}
}