{
  "type": "Feature",
  "properties": {
    "addr:full":"Nygade 20 Br\u00f8nderslev Danmark 9700",
    "addr:housenumber":"20",
    "addr:postcode":"9700",
    "addr:street":"Nygade",
    "iso:country":"DK",
    "sg:address":"Nygade 20",
    "sg:city":"Br\u00f8nderslev",
    "sg:classifiers":[
        {
            "category":"Home & Garden",
            "subcategory":"Home Furnishings",
            "type":"Retail Goods"
        }
    ],
    "sg:phone":"+45 98 82 15 50",
    "sg:postcode":"9700",
    "sg:province":"Danmark",
    "sg:tags":[
        "gardiner"
    ],
    "wof:name":"Botex Gardiner",
    "wof:placetype":"venue"
},
  "geometry": {"coordinates":[9.7584476471,57.2860298157],"type":"Point"}
}