{
  "type": "Feature",
  "properties": {
    "addr:full":"Hundslevvej 11, Hundslev Augustenborg Danmark 6440",
    "addr:housenumber":"11",
    "addr:postcode":"6440",
    "addr:street":"Hundslevvej;Hundslev",
    "iso:country":"DK",
    "sg:address":"Hundslevvej 11, Hundslev",
    "sg:city":"Augustenborg",
    "sg:orig_category":"Maskinstationer",
    "sg:phone":"+45 74 47 32 37",
    "sg:postcode":"6440",
    "sg:province":"Danmark",
    "wof:name":"Blom Maskinstation, Henry",
    "wof:placetype":"venue"
},
  "geometry": {"coordinates":[9.8727750778,54.9459037781],"type":"Point"}
}