{
  "type": "Feature",
  "properties": {
    "iso:country":"DK",
    "sg:address":"Vennelystvej 1",
    "sg:city":"Tarm",
    "sg:orig_category":"Kommunikation",
    "sg:phone":"+45 97 37 29 39",
    "sg:postcode":"6880",
    "sg:province":"Danmark",
    "sg:website":"www.telekaeden.dk",
    "wof:name":"Telek\u00e6den Tarm",
    "wof:placetype":"venue"
},
  "geometry": {"coordinates":[8.5248613358,55.9135055542],"type":"Point"}
}