{
  "type": "Feature",
  "properties": {
    "addr:full":"v/ Kirsten Vestergaard, Ramsherred 47 Rudk\u00f8bing Danmark 5900",
    "addr:housenumber":"47",
    "addr:postcode":"5900",
    "addr:street":"Ramsherred",
    "iso:country":"DK",
    "sg:address":"v/ Kirsten Vestergaard, Ramsherred 47",
    "sg:city":"Rudk\u00f8bing",
    "sg:orig_category":"Hobbybetonede foreninger",
    "sg:phone":"+45 62 51 17 63",
    "sg:postcode":"5900",
    "sg:province":"Danmark",
    "wof:name":"Langelands Bridgeklub",
    "wof:placetype":"venue"
},
  "geometry": {"coordinates":[-114.0767440796,46.4432487488],"type":"Point"}
}