{
  "type": "Feature",
  "properties": {
    "addr:full":"V\u00e6vervej 7 Viborg Danmark 8800",
    "addr:housenumber":"7",
    "addr:postcode":"8800",
    "addr:street":"Vaevervej",
    "iso:country":"DK",
    "sg:address":"V\u00e6vervej 7",
    "sg:city":"Viborg",
    "sg:orig_category":"INGENI\u00c3\u02dcRER",
    "sg:phone":"+45 87 25 61 00",
    "sg:postcode":"8800",
    "sg:province":"Danmark",
    "wof:name":"Carl Bro a/s",
    "wof:placetype":"venue"
},
  "geometry": {"coordinates":[9.3988313675,56.461555481],"type":"Point"}
}