{
  "type": "Feature",
  "properties": {
    "addr:full":"Stamholmen 91 Hvidovre Danmark 2650",
    "addr:housenumber":"91",
    "addr:postcode":"2650",
    "addr:street":"Stamholmen",
    "iso:country":"DK",
    "sg:address":"Stamholmen 91",
    "sg:city":"Hvidovre",
    "sg:orig_category":"Faglige organisationer og -foreninger",
    "sg:phone":"+45 36 78 08 22",
    "sg:postcode":"2650",
    "sg:province":"Danmark",
    "sg:website":"www.asfaltindustrien.dk",
    "wof:name":"Asfaltindustriens Arbejdsgiverforening",
    "wof:placetype":"venue"
},
  "geometry": {"coordinates":[12.4594316483,55.6133804321],"type":"Point"}
}