{
  "type": "Feature",
  "properties": {
    "addr:full":"Doktor Abildgaards All\u00e9 7, 3. tv. Frederiksberg Danmark 1955",
    "addr:housenumber":"7 3 tv.;1955",
    "addr:street":"Doktor Abildgaards Alle\u0301",
    "iso:country":"DK",
    "sg:address":"Doktor Abildgaards All\u00e9 7, 3. tv.",
    "sg:city":"Frederiksberg",
    "sg:orig_category":"Kunstmalere",
    "sg:phone":"+45 35 35 15 13",
    "sg:postcode":"1955",
    "sg:province":"Danmark",
    "wof:name":"Mallow, Lizzi",
    "wof:placetype":"venue"
},
  "geometry": {"coordinates":[12.5403156281,55.6835327148],"type":"Point"}
}