{
  "type": "Feature",
  "properties": {
    "iso:country":"DK",
    "sg:address":"Rosenv\u00e6nget 11",
    "sg:city":"Middelfart",
    "sg:classifiers":[
        {
            "category":"Professional",
            "subcategory":"Computer Services",
            "type":"Services"
        }
    ],
    "sg:phone":"+45 64 41 31 33",
    "sg:postcode":"5500",
    "sg:province":"Danmark",
    "sg:tags":[
        "edb",
        "-",
        "software"
    ],
    "sg:website":"www.kck-data.dk",
    "wof:name":"Kck-Data",
    "wof:placetype":"venue"
},
  "geometry": {"coordinates":[9.7417497635,55.5030250549],"type":"Point"}
}