{
  "type": "Feature",
  "properties": {
    "iso:country":"DK",
    "sg:address":"N\u00f8rremarken 5 ",
    "sg:city":"Ansager",
    "sg:classifiers":[
        {
            "category":"Manufacturing",
            "subcategory":"Lumber",
            "type":"Manufacturing & Wholesale Goods"
        }
    ],
    "sg:phone":"+45 75 29 21 84",
    "sg:postcode":"6823",
    "sg:province":"Danmark",
    "sg:tags":[
        "wood"
    ],
    "wof:name":"LIMAX A/S",
    "wof:placetype":"venue"
},
  "geometry": {"coordinates":[8.7075662613,55.7416381836],"type":"Point"}
}