{
  "type": "Feature",
  "properties": {
    "iso:country":"DK",
    "sg:address":"Oldermand: Paul Poulsen, Akseltorv 12, Gjerlev J",
    "sg:city":"Gjerlev",
    "sg:orig_category":"Erhvervs- og brancheforeninger",
    "sg:phone":"+45 86 47 42 37",
    "sg:postcode":"8983",
    "sg:province":"Danmark",
    "wof:name":"Gammel Estrup Smedelaug",
    "wof:placetype":"venue"
},
  "geometry": {"coordinates":[10.1887750626,56.5788421631],"type":"Point"}
}