{
  "type": "Feature",
  "properties": {
    "addr:full":"Fmd.: Thomas Iversen, H\u00f8jgade 34 R\u00f8dding Danmark 6630",
    "addr:housenumber":"34",
    "addr:postcode":"6630",
    "addr:street":"Hojgade",
    "iso:country":"DK",
    "sg:address":"Fmd.: Thomas Iversen, H\u00f8jgade 34",
    "sg:city":"R\u00f8dding",
    "sg:orig_category":"Kirkelige foreninger",
    "sg:phone":"+45 74 84 27 84",
    "sg:postcode":"6630",
    "sg:province":"Danmark",
    "wof:name":"Indre Mission, R\u00f8dding",
    "wof:placetype":"venue"
},
  "geometry": {"coordinates":[-83.92775726319999,30.8681793213],"type":"Point"}
}