{
  "type": "Feature",
  "properties": {
    "iso:country":"DK",
    "sg:address":"POSTBOKS 40",
    "sg:city":"Lemvig",
    "sg:classifiers":[
        {
            "category":"Banks & Credit Unions",
            "subcategory":"Financial Services",
            "type":"Services"
        }
    ],
    "sg:phone":"+45 96 63 07 50",
    "sg:postcode":"7620",
    "sg:province":"Danmark",
    "sg:tags":[
        "banking",
        "finance",
        "insurance"
    ],
    "wof:name":"A/S NORDVESTBANK",
    "wof:placetype":"venue"
},
  "geometry": {"coordinates":[8.3073654175,56.5505104065],"type":"Point"}
}