{
  "type": "Feature",
  "properties": {
    "addr:full":"Frederiksberg Alle 42 A Frederiksberg Danmark 1820",
    "addr:housenumber":"42 a",
    "addr:postcode":"1820",
    "addr:street":"Frederiksberg Alle",
    "iso:country":"DK",
    "sg:address":"Frederiksberg Alle 42 A",
    "sg:city":"Frederiksberg",
    "sg:orig_category":"Antikviteter",
    "sg:phone":"+45 33 22 16 68",
    "sg:postcode":"1820",
    "sg:province":"Danmark",
    "wof:name":"Mourier, Vibeke",
    "wof:placetype":"venue"
},
  "geometry": {"coordinates":[12.5436649323,55.6738777161],"type":"Point"}
}