{
  "type": "Feature",
  "properties": {
    "addr:full":"M\u00f8llemarken 31, Vall\u00f8by K\u00f8ge Danmark 4600",
    "addr:housenumber":"31",
    "addr:postcode":"4600",
    "addr:street":"Mollemarken",
    "iso:country":"DK",
    "sg:address":"M\u00f8llemarken 31, Vall\u00f8by",
    "sg:city":"K\u00f8ge",
    "sg:orig_category":"Musikstudier",
    "sg:phone":"+45 56 26 82 30",
    "sg:postcode":"4600",
    "sg:province":"Danmark",
    "wof:name":"Fair Play",
    "wof:placetype":"venue"
},
  "geometry": {"coordinates":[12.2424716949,55.3997497559],"type":"Point"}
}