{
  "type": "Feature",
  "properties": {
    "iso:country":"DK",
    "sg:address":"Store Krog 104",
    "sg:city":"K\u00f8benhavn S",
    "sg:orig_category":"Ungdomsklubber",
    "sg:phone":"+45 32 51 27 11",
    "sg:postcode":"2300",
    "sg:province":"Danmark",
    "wof:name":"K\u00f8benhavns Kommunes Integrerede Institution Gyldenrisparken",
    "wof:placetype":"venue"
},
  "geometry": {"coordinates":[-82.51401519780001,38.4315757751],"type":"Point"}
}