{
  "type": "Feature",
  "properties": {
    "addr:full":"S\u00f8ndervangs Alle 38 Viby Danmark 8260",
    "addr:housenumber":"38",
    "addr:postcode":"8260",
    "addr:street":"Sondervangs Alle",
    "iso:country":"DK",
    "sg:address":"S\u00f8ndervangs Alle 38",
    "sg:city":"Viby",
    "sg:orig_category":"Bagere",
    "sg:phone":"+45 86 29 15 20",
    "sg:postcode":"8260",
    "sg:province":"Danmark",
    "wof:name":"Rosenh\u00f8j Bageri",
    "wof:placetype":"venue"
},
  "geometry": {"coordinates":[10.150449,56.112873],"type":"Point"}
}