{
  "type": "Feature",
  "properties": {
    "iso:country":"DK",
    "sg:address":"S\u00f8ndergade 2, 1.",
    "sg:city":"Nakskov",
    "sg:orig_category":"Revisorer",
    "sg:phone":"+45 54 92 25 00",
    "sg:postcode":"4900",
    "sg:province":"Danmark",
    "sg:website":"www.ce.dk",
    "wof:name":"Christiansen & Engelbrechtsen, RSM",
    "wof:placetype":"venue"
},
  "geometry": {"coordinates":[11.1365118027,54.8300285339],"type":"Point"}
}