{
  "type": "Feature",
  "properties": {
    "addr:full":"Fmd.: Bent Skalleb\u00e6k, Vejlevej 80 A, Aadum Tarm Danmark 6880",
    "addr:housenumber":"80 a",
    "addr:postcode":"6880",
    "addr:street":"Vejlevej;Aadum",
    "iso:country":"DK",
    "sg:address":"Fmd.: Bent Skalleb\u00e6k, Vejlevej 80 A, Aadum",
    "sg:city":"Tarm",
    "sg:orig_category":"Kulturelle foreninger",
    "sg:phone":"+45 97 37 62 66",
    "sg:postcode":"6880",
    "sg:province":"Danmark",
    "wof:name":"\u00c5dum/Hoven L\u00e6plantningslaug",
    "wof:placetype":"venue"
},
  "geometry": {"coordinates":[8.5200052261,55.9060554504],"type":"Point"}
}