{
  "type": "Feature",
  "properties": {
    "iso:country":"DK",
    "sg:address":"Blomsterv\u00e6nget 52 ",
    "sg:city":"Kongens Lyngby",
    "sg:classifiers":[
        {
            "category":"Communications",
            "subcategory":"Newspaper",
            "type":"Services"
        }
    ],
    "sg:phone":"+45 45 87 27 00",
    "sg:postcode":"2800",
    "sg:province":"Danmark",
    "sg:tags":[
        "advertising"
    ],
    "wof:name":"MAGIC HOUR FILMS APS",
    "wof:placetype":"venue"
},
  "geometry": {"coordinates":[12.51060009,55.7810211182],"type":"Point"}
}