{
  "type": "Feature",
  "properties": {
    "addr:full":"v/ Jens Erik Jensen, Kirkevej 7 Hejnsvig Danmark 7250",
    "addr:housenumber":"7",
    "addr:postcode":"7250",
    "addr:street":"Kirkevej",
    "iso:country":"DK",
    "sg:address":"v/ Jens Erik Jensen, Kirkevej 7",
    "sg:city":"Hejnsvig",
    "sg:orig_category":"Borger- og beboerforeninger",
    "sg:phone":"+45 75 33 51 80",
    "sg:postcode":"7250",
    "sg:province":"Danmark",
    "wof:name":"Hejnsvig Borgerforening",
    "wof:placetype":"venue"
},
  "geometry": {"coordinates":[8.9966459274,55.6951141357],"type":"Point"}
}