{
  "type": "Feature",
  "properties": {
    "addr:full":"\u00c5bjergvej 12, Uhe Give Danmark 7323",
    "addr:housenumber":"12",
    "addr:postcode":"7323",
    "addr:street":"Aabjergvej;Uhe",
    "iso:country":"DK",
    "sg:address":"\u00c5bjergvej 12, Uhe",
    "sg:city":"Give",
    "sg:orig_category":"Oliefyr og service",
    "sg:phone":"+45 75 73 82 82",
    "sg:postcode":"7323",
    "sg:province":"Danmark",
    "wof:name":"Winther's Oliefyrsservice",
    "wof:placetype":"venue"
},
  "geometry": {"coordinates":[9.2362060547,55.845413208],"type":"Point"}
}