{
  "type": "Feature",
  "properties": {
    "addr:full":"Finlandsvej 23 Vejle Danmark 7100",
    "addr:housenumber":"23",
    "addr:postcode":"7100",
    "addr:street":"Finlandsvej",
    "iso:country":"DK",
    "sg:address":"Finlandsvej 23",
    "sg:city":"Vejle",
    "sg:orig_category":"Vuggestuer",
    "sg:phone":"+45 76 40 99 00",
    "sg:postcode":"7100",
    "sg:province":"Danmark",
    "wof:name":"Solstr\u00e5len",
    "wof:placetype":"venue"
},
  "geometry": {"coordinates":[9.5621910095,55.7209396362],"type":"Point"}
}