{
  "type": "Feature",
  "properties": {
    "addr:full":"C. F. Richs Vej 103 Frederiksberg Danmark 2000",
    "addr:housenumber":"103",
    "addr:postcode":"2000",
    "addr:street":"C.;Richs Vej",
    "iso:country":"DK",
    "sg:address":"C. F. Richs Vej 103",
    "sg:city":"Frederiksberg",
    "sg:orig_category":"Faglige organisationer og foreninger",
    "sg:phone":"+45 38 86 18 85",
    "sg:postcode":"2000",
    "sg:province":"Danmark",
    "wof:name":"FDS",
    "wof:placetype":"venue"
},
  "geometry": {"coordinates":[12.5040826797,55.6860389709],"type":"Point"}
}