{
  "type": "Feature",
  "properties": {
    "iso:country":"DK",
    "sg:address":"Gruppeleder: Lisbeth Gr\u00f8nbeck, Hallandsvej 56, Apperup",
    "sg:city":"\u00c5lsg\u00e5rde",
    "sg:orig_category":"Spejderkorps",
    "sg:phone":"+45 49 70 92 07",
    "sg:postcode":"3140",
    "sg:province":"Danmark",
    "wof:name":"DDS, Hammerm\u00f8lle Gruppe",
    "wof:placetype":"venue"
},
  "geometry": {"coordinates":[12.5406808853,56.0749893188],"type":"Point"}
}