{
  "type": "Feature",
  "properties": {
    "addr:full":"Hvissingevej 14 Glostrup Danmark 2600",
    "addr:housenumber":"14",
    "addr:postcode":"2600",
    "addr:street":"Hvissingevej",
    "iso:country":"DK",
    "sg:address":"Hvissingevej 14",
    "sg:city":"Glostrup",
    "sg:orig_category":"Asbestsanering",
    "sg:phone":"+45 43 45 00 54",
    "sg:postcode":"2600",
    "sg:province":"Danmark",
    "wof:name":"Popp ApS, Karl",
    "wof:placetype":"venue"
},
  "geometry": {"coordinates":[12.4162559509,55.6710548401],"type":"Point"}
}