{
  "type": "Feature",
  "properties": {
    "addr:full":"M\u00e6lkevejen 3, Oue Hobro Danmark 9500",
    "addr:housenumber":"3",
    "addr:postcode":"9500",
    "addr:street":"Maelkevejen;Oue",
    "iso:country":"DK",
    "sg:address":"M\u00e6lkevejen 3, Oue",
    "sg:city":"Hobro",
    "sg:classifiers":[
        {
            "category":"Banks & Credit Unions",
            "subcategory":"Bank",
            "type":"Services"
        }
    ],
    "sg:phone":"+45 98 55 82 86",
    "sg:postcode":"9500",
    "sg:province":"Danmark",
    "sg:tags":[
        "banker"
    ],
    "wof:name":"Oue Andelskasse",
    "wof:placetype":"venue"
},
  "geometry": {"coordinates":[9.7946596146,56.6382789612],"type":"Point"}
}