{
  "type": "Feature",
  "properties": {
    "iso:country":"DK",
    "sg:address":"Brinken 23, Keldstrup",
    "sg:city":"Slagelse",
    "sg:orig_category":"Biavlere",
    "sg:phone":"+45 58 54 93 75",
    "sg:postcode":"4200",
    "sg:province":"Danmark",
    "wof:name":"Kongsbak, Erik",
    "wof:placetype":"venue"
},
  "geometry": {"coordinates":[11.356985,55.405087],"type":"Point"}
}