{
  "type": "Feature",
  "properties": {
    "addr:full":"Egeskovvej 2 Bjerringbro Danmark 8850",
    "addr:housenumber":"2",
    "addr:postcode":"8850",
    "addr:street":"Egeskovvej",
    "iso:country":"DK",
    "sg:address":"Egeskovvej 2",
    "sg:city":"Bjerringbro",
    "sg:orig_category":"Boinstitution for voksne",
    "sg:phone":"+45 86 68 20 26",
    "sg:postcode":"8850",
    "sg:province":"Danmark",
    "wof:name":"Boenheden Egeh\u00f8j",
    "wof:placetype":"venue"
},
  "geometry": {"coordinates":[9.6448135376,56.3788986206],"type":"Point"}
}