{
  "type": "Feature",
  "properties": {
    "iso:country":"DK",
    "sg:address":"Bredgade 74",
    "sg:city":"Hurup",
    "sg:orig_category":"Tandteknikere, Kliniske",
    "sg:phone":"+45 97 95 27 00",
    "sg:postcode":"7760",
    "sg:province":"Danmark",
    "wof:name":"Bunch, Lars",
    "wof:placetype":"venue"
},
  "geometry": {"coordinates":[8.4241323471,56.7484703064],"type":"Point"}
}