{
  "type": "Feature",
  "properties": {
    "iso:country":"DK",
    "sg:address":"Bergmannsvej 6, Thur\u00f8",
    "sg:city":"Svendborg",
    "sg:orig_category":"Systuer",
    "sg:phone":"+45 62 20 62 32",
    "sg:postcode":"5700",
    "sg:province":"Danmark",
    "wof:name":"GitteS Bekl\u00e6dningsv\u00e6rksted v/ Gitte Schr\u00f8der",
    "wof:placetype":"venue"
},
  "geometry": {"coordinates":[10.6065101624,55.0595970154],"type":"Point"}
}