{
  "type": "Feature",
  "properties": {
    "addr:full":"Strandvejen 323 Charlottenlund Danmark 2920",
    "addr:housenumber":"323",
    "addr:postcode":"2920",
    "addr:street":"Strandvejen",
    "iso:country":"DK",
    "sg:address":"Strandvejen 323",
    "sg:city":"Charlottenlund",
    "sg:orig_category":"Pizzeriaer",
    "sg:phone":"+45 39 64 32 02",
    "sg:postcode":"2920",
    "sg:province":"Danmark",
    "wof:name":"Costa Smeralda, Pizzeria",
    "wof:placetype":"venue"
},
  "geometry": {"coordinates":[12.5970258713,55.7627487183],"type":"Point"}
}