{
  "type": "Feature",
  "properties": {
    "addr:full":"Toldbodgade 12 Copenhagen 1253",
    "addr:housenumber":"12",
    "addr:postcode":"1253",
    "addr:street":"Toldbodgade",
    "iso:country":"DK",
    "sg:address":"Toldbodgade 12",
    "sg:city":"Copenhagen",
    "sg:classifiers":[
        {
            "category":"Professional",
            "subcategory":"Computer Services",
            "type":"Services"
        }
    ],
    "sg:postcode":"1253",
    "sg:website":"http://www.mobilepeople.com",
    "wof:name":"mobilePeople",
    "wof:placetype":"venue"
},
  "geometry": {"coordinates":[12.5920937,55.6805388],"type":"Point"}
}