{
  "type": "Feature",
  "properties": {
    "iso:country":"DK",
    "sg:address":"Valby Langgade 72",
    "sg:city":"Valby",
    "sg:orig_category":"Bagere",
    "sg:phone":"+45 36 46 48 20",
    "sg:postcode":"2500",
    "sg:province":"Danmark",
    "wof:name":"gamle Konditori, Det",
    "wof:placetype":"venue"
},
  "geometry": {"coordinates":[12.5132417679,55.6661491394],"type":"Point"}
}