{
  "type": "Feature",
  "properties": {
    "addr:full":"N\u00f8rregade 4 Hvide Sande Danmark 6960",
    "addr:housenumber":"4",
    "addr:postcode":"6960",
    "addr:street":"Norregade",
    "iso:country":"DK",
    "sg:address":"N\u00f8rregade 4",
    "sg:city":"Hvide Sande",
    "sg:orig_category":"Malermestre",
    "sg:phone":"+45 97 31 31 22",
    "sg:postcode":"6960",
    "sg:province":"Danmark",
    "wof:name":"Kelds Malerforretning",
    "wof:placetype":"venue"
},
  "geometry": {"coordinates":[8.1301717758,56.0058364868],"type":"Point"}
}