{
  "type": "Feature",
  "properties": {
    "addr:full":"v/ Per Kildal Christensen, Havnevej 118 Grenaa Danmark 8500",
    "addr:housenumber":"118",
    "addr:postcode":"8500",
    "addr:street":"Havnevej",
    "iso:country":"DK",
    "sg:address":"v/ Per Kildal Christensen, Havnevej 118",
    "sg:city":"Grenaa",
    "sg:orig_category":"Hobbybetonede foreninger",
    "sg:phone":"+45 86 32 31 55",
    "sg:postcode":"8500",
    "sg:province":"Danmark",
    "wof:name":"Dansk Triumph Automobilklub",
    "wof:placetype":"venue"
},
  "geometry": {"coordinates":[10.8774929047,56.4126853943],"type":"Point"}
}