{
  "type": "Feature",
  "properties": {
    "addr:full":"Klausdalsbrovej 601  Ballerup Danmark 2750",
    "addr:housenumber":"601",
    "addr:postcode":"2750",
    "addr:street":"Klausdalsbrovej",
    "iso:country":"DK",
    "sg:address":"Klausdalsbrovej 601 ",
    "sg:city":"Ballerup",
    "sg:classifiers":[
        {
            "category":"Banks & Credit Unions",
            "subcategory":"Financial Services",
            "type":"Services"
        }
    ],
    "sg:phone":"+45 70 11 20 20",
    "sg:postcode":"2750",
    "sg:province":"Danmark",
    "sg:tags":[
        "banking",
        "finance",
        "insurance"
    ],
    "wof:name":"TRYG",
    "wof:placetype":"venue"
},
  "geometry": {"coordinates":[12.398385,55.740562],"type":"Point"}
}