{
  "type": "Feature",
  "properties": {
    "addr:full":"Strandparken 26 Vordingborg Danmark 4760",
    "addr:housenumber":"26",
    "addr:postcode":"4760",
    "addr:street":"Strandparken",
    "iso:country":"DK",
    "sg:address":"Strandparken 26",
    "sg:city":"Vordingborg",
    "sg:orig_category":"Forlag",
    "sg:phone":"+45 55 37 55 05",
    "sg:postcode":"4760",
    "sg:province":"Danmark",
    "wof:name":"Regnbueland, Forlaget",
    "wof:placetype":"venue"
},
  "geometry": {"coordinates":[11.8653030396,55.008228302],"type":"Point"}
}