{
  "type": "Feature",
  "properties": {
    "addr:full":"Skomagerbakken 82 Gistrup Danmark 9260",
    "addr:housenumber":"82",
    "addr:postcode":"9260",
    "addr:street":"Skomagerbakken",
    "iso:country":"DK",
    "sg:address":"Skomagerbakken 82",
    "sg:city":"Gistrup",
    "sg:orig_category":"Autoreparation og -service",
    "sg:phone":"+45 98 33 35 29",
    "sg:postcode":"9260",
    "sg:province":"Danmark",
    "wof:name":"Gunderup Autohandel",
    "wof:placetype":"venue"
},
  "geometry": {"coordinates":[10.0188999176,56.9405250549],"type":"Point"}
}