{
  "type": "Feature",
  "properties": {
    "addr:full":"v/ Bent Bruun, Guldagervej 17, Nr. Holsted Holsted Danmark 6670",
    "addr:housenumber":"17",
    "addr:postcode":"6670",
    "addr:street":"Guldagervej",
    "iso:country":"DK",
    "sg:address":"v/ Bent Bruun, Guldagervej 17, Nr. Holsted",
    "sg:city":"Holsted",
    "sg:orig_category":"Faglige organisationer og foreninger",
    "sg:phone":"+45 75 39 20 76",
    "sg:postcode":"6670",
    "sg:province":"Danmark",
    "wof:name":"F\u00f8vling-Holsted Husmandsforening",
    "wof:placetype":"venue"
},
  "geometry": {"coordinates":[8.9169273376,55.5111999512],"type":"Point"}
}