{
  "type": "Feature",
  "properties": {
    "iso:country":"DK",
    "sg:address":"Vognporten 7",
    "sg:city":"Albertslund",
    "sg:orig_category":"Sammensatte institutioner",
    "sg:phone":"+45 43 64 65 56",
    "sg:postcode":"2620",
    "sg:province":"Danmark",
    "wof:name":"Vognporten B\u00f8rnehus",
    "wof:placetype":"venue"
},
  "geometry": {"coordinates":[12.3507547379,55.657245636],"type":"Point"}
}