{
  "type": "Feature",
  "properties": {
    "addr:full":"Flegborg 5 A Vejle Danmark 7100",
    "addr:housenumber":"5 a",
    "addr:postcode":"7100",
    "addr:street":"Flegborg",
    "iso:country":"DK",
    "sg:address":"Flegborg 5 A",
    "sg:city":"Vejle",
    "sg:orig_category":"Konsulentvirksomheder",
    "sg:phone":"+45 75 72 13 00",
    "sg:postcode":"7100",
    "sg:province":"Danmark",
    "wof:name":"Toudal & Svender A/S",
    "wof:placetype":"venue"
},
  "geometry": {"coordinates":[9.5329742432,55.7097167969],"type":"Point"}
}