{
  "type": "Feature",
  "properties": {
    "addr:full":"Sdr. Landevej 217, H\u00f8ruphav Sydals Danmark 6470",
    "addr:housenumber":"217",
    "addr:postcode":"6470",
    "addr:street":"Sdr. Landevej;Horuphav",
    "iso:country":"DK",
    "sg:address":"Sdr. Landevej 217, H\u00f8ruphav",
    "sg:city":"Sydals",
    "sg:orig_category":"Cafeer",
    "sg:phone":"+45 74 41 60 69",
    "sg:postcode":"6470",
    "sg:province":"Danmark",
    "wof:name":"Tony, Caf\u00e9",
    "wof:placetype":"venue"
},
  "geometry": {"coordinates":[9.8924627304,54.9105377197],"type":"Point"}
}