{
  "type": "Feature",
  "properties": {
    "addr:full":"S\u00e6dding Strandvej 7 Esbjerg V Danmark 6710",
    "addr:housenumber":"7",
    "addr:postcode":"6710",
    "addr:street":"Saedding Strandvej",
    "iso:country":"DK",
    "sg:address":"S\u00e6dding Strandvej 7",
    "sg:city":"Esbjerg V",
    "sg:orig_category":"Psykologer, praktiserende",
    "sg:phone":"+45 75 15 17 10",
    "sg:postcode":"6710",
    "sg:province":"Danmark",
    "wof:name":"Krogsgaard, Maria",
    "wof:placetype":"venue"
},
  "geometry": {"coordinates":[8.4093360901,55.4894218445],"type":"Point"}
}