{
  "type": "Feature",
  "properties": {
    "addr:full":"Gellerupvej 45 Varde Danmark 6800",
    "addr:housenumber":"45",
    "addr:postcode":"6800",
    "addr:street":"Gellerupvej",
    "iso:country":"DK",
    "sg:address":"Gellerupvej 45",
    "sg:city":"Varde",
    "sg:orig_category":"Solvarme",
    "sg:phone":"+45 75 21 04 11",
    "sg:postcode":"6800",
    "sg:province":"Danmark",
    "wof:name":"Nielsen VVS ApS, John",
    "wof:placetype":"venue"
},
  "geometry": {"coordinates":[8.4942951202,55.6184463501],"type":"Point"}
}