{
  "type": "Feature",
  "properties": {
    "addr:full":"L. P. Houm\u00f8llers Vej 25 Frederikshavn Danmark 9900",
    "addr:housenumber":"25",
    "addr:postcode":"9900",
    "addr:street":"L.;Houmollers Vej",
    "iso:country":"DK",
    "sg:address":"L. P. Houm\u00f8llers Vej 25",
    "sg:city":"Frederikshavn",
    "sg:orig_category":"Fodplejere",
    "sg:phone":"+45 98 43 09 08",
    "sg:postcode":"9900",
    "sg:province":"Danmark",
    "wof:name":"Bangsbo, Fodklinikken",
    "wof:placetype":"venue"
},
  "geometry": {"coordinates":[10.5362997055,57.4396400452],"type":"Point"}
}