{
  "type": "Feature",
  "properties": {
    "addr:full":"Fristrupvej 17 Aabybro Danmark 9440",
    "addr:housenumber":"17",
    "addr:postcode":"9440",
    "addr:street":"Fristrupvej",
    "iso:country":"DK",
    "sg:address":"Fristrupvej 17",
    "sg:city":"Aabybro",
    "sg:orig_category":"Autoforhandlere",
    "sg:phone":"+45 98 24 40 00",
    "sg:postcode":"9440",
    "sg:province":"Danmark",
    "sg:website":"www.auto-nord.dk/mk-auto",
    "wof:name":"MK Auto",
    "wof:placetype":"venue"
},
  "geometry": {"coordinates":[9.7378664017,57.1507263184],"type":"Point"}
}