{
  "type": "Feature",
  "properties": {
    "addr:full":"Leder: Bernd S\u00f8ndergaard, Vibev\u00e6nget 26 Tinglev Danmark 6360",
    "addr:housenumber":"26",
    "addr:postcode":"6360",
    "addr:street":"Vibevaenget",
    "iso:country":"DK",
    "sg:address":"Leder: Bernd S\u00f8ndergaard, Vibev\u00e6nget 26",
    "sg:city":"Tinglev",
    "sg:orig_category":"Ungdomsklubber",
    "sg:phone":"+45 74 64 22 20",
    "sg:postcode":"6360",
    "sg:province":"Danmark",
    "wof:name":"Jugendclub Tingleff",
    "wof:placetype":"venue"
},
  "geometry": {"coordinates":[9.2476491928,54.9349365234],"type":"Point"}
}