{
  "type": "Feature",
  "properties": {
    "addr:full":"Reesens Vej 2 Varde Danmark 6800",
    "addr:housenumber":"2",
    "addr:postcode":"6800",
    "addr:street":"Reesens Vej",
    "iso:country":"DK",
    "sg:address":"Reesens Vej 2",
    "sg:city":"Varde",
    "sg:orig_category":"Revisorer",
    "sg:phone":"+45 75 22 15 77",
    "sg:postcode":"6800",
    "sg:province":"Danmark",
    "wof:name":"Martinsen Statsautoriseret Revisionsaktieselskab, H.",
    "wof:placetype":"venue"
},
  "geometry": {"coordinates":[8.4611759186,55.625667572],"type":"Point"}
}