{
  "type": "Feature",
  "properties": {
    "addr:full":"Fmd.: S\u00f8ren Anker S\u00f8rensen, Strandagervej 4, Karlby Grenaa Danmark 8500",
    "addr:housenumber":"4",
    "addr:postcode":"8500",
    "addr:street":"Sorensen Strandagervej;Karlby",
    "iso:country":"DK",
    "sg:address":"Fmd.: S\u00f8ren Anker S\u00f8rensen, Strandagervej 4, Karlby",
    "sg:city":"Grenaa",
    "sg:orig_category":"Kulturelle foreninger",
    "sg:phone":"+45 86 33 25 01",
    "sg:postcode":"8500",
    "sg:province":"Danmark",
    "wof:name":"Valmuen, N\u00f8rre Djurs Egnsspilforening",
    "wof:placetype":"venue"
},
  "geometry": {"coordinates":[10.8774929047,56.4126853943],"type":"Point"}
}