{
  "type": "Feature",
  "properties": {
    "iso:country":"DK",
    "sg:address":"Fmd.: Lone Nielsen, Hallundb\u00e6kvej 9, Hodsager",
    "sg:city":"Aulum",
    "sg:orig_category":"Hobbybetonede foreninger",
    "sg:phone":"+45 97 47 63 30",
    "sg:postcode":"7490",
    "sg:province":"Danmark",
    "wof:name":"Sch\u00e6ferhundeklubben Kreds 33 Holstebro",
    "wof:placetype":"venue"
},
  "geometry": {"coordinates":[8.7971401215,56.2653999329],"type":"Point"}
}