{
  "type": "Feature",
  "properties": {
    "iso:country":"DK",
    "sg:address":"\u00d8stergade 7",
    "sg:city":"Grenaa",
    "sg:orig_category":"Bodegaer",
    "sg:phone":"+45 86 32 01 28",
    "sg:postcode":"8500",
    "sg:province":"Danmark",
    "wof:name":"Old Games Pub",
    "wof:placetype":"venue"
},
  "geometry": {"coordinates":[10.8781099319,56.413520813],"type":"Point"}
}