{
  "type": "Feature",
  "properties": {
    "iso:country":"DK",
    "sg:address":"Vordingborgvej 57",
    "sg:city":"Stensved",
    "sg:orig_category":"Autoreparation og -service",
    "sg:phone":"+45 55 38 60 22",
    "sg:postcode":"4773",
    "sg:province":"Danmark",
    "wof:name":"Petersen, Leif",
    "wof:placetype":"venue"
},
  "geometry": {"coordinates":[12.028002739,54.9955329895],"type":"Point"}
}