{
  "type": "Feature",
  "properties": {
    "addr:full":"Engholmvej 1 B, G\u00f8rup Skals Danmark 8832",
    "addr:housenumber":"1 b",
    "addr:postcode":"8832",
    "addr:street":"Engholmvej;Gorup",
    "iso:country":"DK",
    "sg:address":"Engholmvej 1 B, G\u00f8rup",
    "sg:city":"Skals",
    "sg:orig_category":"Ferielejligheder",
    "sg:phone":"+45 86 69 72 82",
    "sg:postcode":"8832",
    "sg:province":"Danmark",
    "wof:name":"Studstrup's Hjorte Center",
    "wof:placetype":"venue"
},
  "geometry": {"coordinates":[9.4030599594,56.5558166504],"type":"Point"}
}