{
  "type": "Feature",
  "properties": {
    "iso:country":"DK",
    "sg:address":"Kostervej 2, Lendemarke",
    "sg:city":"Stege",
    "sg:orig_category":"Revisorer",
    "sg:phone":"+45 55 81 12 34",
    "sg:postcode":"4780",
    "sg:province":"Danmark",
    "sg:website":"www.revisor-frr.dk",
    "wof:name":"\u00d8ernes Revision A/S",
    "wof:placetype":"venue"
},
  "geometry": {"coordinates":[12.2875270844,54.9855155945],"type":"Point"}
}