{
  "type": "Feature",
  "properties": {
    "addr:full":"Jernbanegade 31 Otterup Danmark 5450",
    "addr:housenumber":"31",
    "addr:postcode":"5450",
    "addr:street":"Jernbanegade",
    "iso:country":"DK",
    "sg:address":"Jernbanegade 31",
    "sg:city":"Otterup",
    "sg:classifiers":[
        {
            "category":"Home & Garden",
            "subcategory":"Home Furnishings",
            "type":"Retail Goods"
        }
    ],
    "sg:phone":"+45 64 82 10 41",
    "sg:postcode":"5450",
    "sg:province":"Danmark",
    "sg:tags":[
        "gardiner"
    ],
    "wof:name":"Otterup Farve- T\u00e6ppe- og Gardinhandel",
    "wof:placetype":"venue"
},
  "geometry": {"coordinates":[10.3970041275,55.5134391785],"type":"Point"}
}