{
  "type": "Feature",
  "properties": {
    "addr:full":"Dannebrogsgade 2 C K\u00f8benhavn Danmark 1660",
    "addr:housenumber":"2 c;1660",
    "addr:street":"Dannebrogsgade",
    "iso:country":"DK",
    "sg:address":"Dannebrogsgade 2 C",
    "sg:city":"K\u00f8benhavn",
    "sg:orig_category":"Dentallaboratorier",
    "sg:phone":"+45 33 31 63 78",
    "sg:postcode":"1660",
    "sg:province":"Danmark",
    "wof:name":"K.M. Dentallaboratorium",
    "wof:placetype":"venue"
},
  "geometry": {"coordinates":[12.5543003082,55.6702003479],"type":"Point"}
}