{
  "type": "Feature",
  "properties": {
    "addr:full":"H\u00f8jbovej 8 Glostrup Danmark 2600",
    "addr:housenumber":"8",
    "addr:postcode":"2600",
    "addr:street":"Hojbovej",
    "iso:country":"DK",
    "sg:address":"H\u00f8jbovej 8",
    "sg:city":"Glostrup",
    "sg:orig_category":"Skorstensfejere",
    "sg:phone":"+45 43 96 02 82",
    "sg:postcode":"2600",
    "sg:province":"Danmark",
    "wof:name":"Johansen, B. Lund",
    "wof:placetype":"venue"
},
  "geometry": {"coordinates":[12.3993015289,55.6686553955],"type":"Point"}
}