{
  "type": "Feature",
  "properties": {
    "addr:full":"Gl. Aalborgvej 33 Viborg Danmark 8800",
    "addr:housenumber":"33",
    "addr:postcode":"8800",
    "addr:street":"Gl. Aalborgvej",
    "iso:country":"DK",
    "sg:address":"Gl. Aalborgvej 33",
    "sg:city":"Viborg",
    "sg:orig_category":"Yogaundervisning",
    "sg:phone":"+45 86 62 61 83",
    "sg:postcode":"8800",
    "sg:province":"Danmark",
    "wof:name":"Andersen, Aase",
    "wof:placetype":"venue"
},
  "geometry": {"coordinates":[9.4164762497,56.4606895447],"type":"Point"}
}