{
  "type": "Feature",
  "properties": {
    "addr:full":"Sturlasgade 12 D K\u00f8benhavn S Danmark 2300",
    "addr:housenumber":"12 d",
    "addr:postcode":"2300",
    "addr:street":"Sturlasgade;Kobenhavn S Danmark",
    "iso:country":"DK",
    "sg:address":"Sturlasgade 12 D",
    "sg:city":"K\u00f8benhavn S",
    "sg:orig_category":"Smede",
    "sg:phone":"+45 32 96 71 11",
    "sg:postcode":"2300",
    "sg:province":"Danmark",
    "wof:name":"Skibby ApS, Flemming Jensen",
    "wof:placetype":"venue"
},
  "geometry": {"coordinates":[-78.1299133301,36.7267417908],"type":"Point"}
}