{
  "type": "Feature",
  "properties": {
    "addr:full":"Industriparken 14 Bredsten Danmark 7182",
    "addr:housenumber":"14",
    "addr:postcode":"7182",
    "addr:street":"Industriparken",
    "iso:country":"DK",
    "sg:address":"Industriparken 14",
    "sg:city":"Bredsten",
    "sg:orig_category":"Autolakering",
    "sg:phone":"+45 75 88 20 02",
    "sg:postcode":"7182",
    "sg:province":"Danmark",
    "wof:name":"Bredsten Autolak",
    "wof:placetype":"venue"
},
  "geometry": {"coordinates":[9.375626564,55.7004623413],"type":"Point"}
}