{
  "type": "Feature",
  "properties": {
    "addr:full":"Kontaktpers.: Erik G. Andresen, Borgerskovskolen, Aula B, Hybenv\u00e6nget 9 Ullerslev Danmark 5540",
    "addr:housenumber":"9",
    "addr:postcode":"5540",
    "addr:street":"Erik G.;Hybenvaenget",
    "iso:country":"DK",
    "sg:address":"Kontaktpers.: Erik G. Andresen, Borgerskovskolen, Aula B, Hybenv\u00e6nget 9",
    "sg:city":"Ullerslev",
    "sg:orig_category":"Hobbybetonede foreninger",
    "sg:phone":"+45 65 35 10 08",
    "sg:postcode":"5540",
    "sg:province":"Danmark",
    "wof:name":"Nyborg Skakklub",
    "wof:placetype":"venue"
},
  "geometry": {"coordinates":[10.6675348282,55.3605728149],"type":"Point"}
}