{
  "type": "Feature",
  "properties": {
    "addr:full":"v/ Gr\u00e6sted-Gilleleje Kommunes Pladsanvisning, Birkevang 214 Gilleleje Danmark 3250",
    "addr:housenumber":"214",
    "addr:postcode":"3250",
    "addr:street":"Birkevang",
    "iso:country":"DK",
    "sg:address":"v/ Gr\u00e6sted-Gilleleje Kommunes Pladsanvisning, Birkevang 214",
    "sg:city":"Gilleleje",
    "sg:orig_category":"Legestuer",
    "sg:phone":"+45 48 38 83 00",
    "sg:postcode":"3250",
    "sg:province":"Danmark",
    "wof:name":"Gilleleje Private Legestue",
    "wof:placetype":"venue"
},
  "geometry": {"coordinates":[12.3087387085,56.123462677],"type":"Point"}
}