{
  "type": "Feature",
  "properties": {
    "iso:country":"DK",
    "sg:address":"Storegade 15, Assens",
    "sg:city":"Mariager",
    "sg:orig_category":"Brugsforeninger",
    "sg:phone":"+45 98 58 30 05",
    "sg:postcode":"9550",
    "sg:province":"Danmark",
    "wof:name":"DagliBrugsen",
    "wof:placetype":"venue"
},
  "geometry": {"coordinates":[10.0618648529,56.676902771],"type":"Point"}
}