{
  "type": "Feature",
  "properties": {
    "addr:full":"Herredsvejen 57, Lejrskov Lunderskov Danmark 6640",
    "addr:housenumber":"57",
    "addr:postcode":"6640",
    "addr:street":"Herredsvejen;Lejrskov",
    "iso:country":"DK",
    "sg:address":"Herredsvejen 57, Lejrskov",
    "sg:city":"Lunderskov",
    "sg:orig_category":"Kurerservice",
    "sg:phone":"+45 75 55 80 30",
    "sg:postcode":"6640",
    "sg:province":"Danmark",
    "wof:name":"Direct",
    "wof:placetype":"venue"
},
  "geometry": {"coordinates":[9.2983627319,55.4793586731],"type":"Point"}
}