{
  "type": "Feature",
  "properties": {
    "iso:country":"DK",
    "sg:address":"Dronning Margrethes Vej 81",
    "sg:city":"\u00c5rhus N",
    "sg:orig_category":"Brudekjoler",
    "sg:phone":"+45 86 16 67 77",
    "sg:postcode":"8200",
    "sg:province":"Danmark",
    "wof:name":"H\u00f8ilunds Brudesalon, Ellen",
    "wof:placetype":"venue"
},
  "geometry": {"coordinates":[4.9393601418,49.7092018127],"type":"Point"}
}