{
  "type": "Feature",
  "properties": {
    "addr:full":"P. Th. Bruuns Alle 10 Varde Danmark 6800",
    "addr:housenumber":"10",
    "addr:postcode":"6800",
    "addr:street":"P. Th. Bruuns Alle",
    "iso:country":"DK",
    "sg:address":"P. Th. Bruuns Alle 10",
    "sg:city":"Varde",
    "sg:orig_category":"Faglige organisationer og foreninger",
    "sg:phone":"+45 75 22 19 80",
    "sg:postcode":"6800",
    "sg:province":"Danmark",
    "wof:name":"Kommunale Arbejdsm\u00e6nds klub",
    "wof:placetype":"venue"
},
  "geometry": {"coordinates":[8.4667654037,55.6243896484],"type":"Point"}
}