{
  "type": "Feature",
  "properties": {
    "addr:full":"Sofiendalsvej 93 Aalborg SV Danmark 9200",
    "addr:housenumber":"93",
    "addr:postcode":"9200",
    "addr:street":"Sofiendalsvej",
    "iso:country":"DK",
    "sg:address":"Sofiendalsvej 93",
    "sg:city":"Aalborg SV",
    "sg:orig_category":"INGENI\u00c3\u02dcRER",
    "sg:phone":"+45 96 34 68 68",
    "sg:postcode":"9200",
    "sg:province":"Danmark",
    "wof:name":"Texas Instruments A/S, Denmark",
    "wof:placetype":"venue"
},
  "geometry": {"coordinates":[9.8789510727,57.017742157],"type":"Point"}
}