{
  "type": "Feature",
  "properties": {
    "addr:full":"Lyngg\u00e5rdsvej 11 Silkeborg Danmark 8600",
    "addr:housenumber":"11",
    "addr:postcode":"8600",
    "addr:street":"Lynggaardsvej",
    "iso:country":"DK",
    "sg:address":"Lyngg\u00e5rdsvej 11",
    "sg:city":"Silkeborg",
    "sg:orig_category":"INGENI\u00c3\u02dcRER",
    "sg:phone":"+45 86 84 61 20",
    "sg:postcode":"8600",
    "sg:province":"Danmark",
    "wof:name":"Partner Engineering",
    "wof:placetype":"venue"
},
  "geometry": {"coordinates":[9.6428804398,56.1379585266],"type":"Point"}
}