{
  "type": "Feature",
  "properties": {
    "addr:full":"Ravnholmvej 11 Kongens Lyngby Danmark 2800",
    "addr:housenumber":"11",
    "addr:postcode":"2800",
    "addr:street":"Ravnholmvej",
    "iso:country":"DK",
    "sg:address":"Ravnholmvej 11",
    "sg:city":"Kongens Lyngby",
    "sg:orig_category":"Cafeterier",
    "sg:phone":"+45 45 88 41 94",
    "sg:postcode":"2800",
    "sg:province":"Danmark",
    "wof:name":"Lundtoftehallens Cafeteria",
    "wof:placetype":"venue"
},
  "geometry": {"coordinates":[12.5247974396,55.798828125],"type":"Point"}
}