{
  "type": "Feature",
  "properties": {
    "addr:full":"Hovedgaden 57 Humble Danmark 5932",
    "addr:housenumber":"57",
    "addr:postcode":"5932",
    "addr:street":"Hovedgaden",
    "iso:country":"DK",
    "sg:address":"Hovedgaden 57",
    "sg:city":"Humble",
    "sg:orig_category":"Filialbiblioteker",
    "sg:phone":"+45 63 56 50 00",
    "sg:postcode":"5932",
    "sg:province":"Danmark",
    "wof:name":"Humble bibliotek",
    "wof:placetype":"venue"
},
  "geometry": {"coordinates":[10.7016401291,54.8329315186],"type":"Point"}
}