{
  "type": "Feature",
  "properties": {
    "addr:full":"Fmd.: Kurt S\u00f8rensen, Pilevej 41, Taulov Fredericia Danmark 7000",
    "addr:housenumber":"41",
    "addr:postcode":"7000",
    "addr:street":"Pilevej",
    "iso:country":"DK",
    "sg:address":"Fmd.: Kurt S\u00f8rensen, Pilevej 41, Taulov",
    "sg:city":"Fredericia",
    "sg:orig_category":"Antenneforeninger",
    "sg:phone":"+45 75 56 34 18",
    "sg:postcode":"7000",
    "sg:province":"Danmark",
    "wof:name":"Antenneforeningen, Taulov Syd",
    "wof:placetype":"venue"
},
  "geometry": {"coordinates":[9.7591047287,55.566368103],"type":"Point"}
}