{
  "type": "Feature",
  "properties": {
    "addr:full":"Brordrupvej 1 Gadstrup Danmark 4621",
    "addr:housenumber":"1",
    "addr:postcode":"4621",
    "addr:street":"Brordrupvej",
    "iso:country":"DK",
    "sg:address":"Brordrupvej 1",
    "sg:city":"Gadstrup",
    "sg:orig_category":"Glarmestre og glarmagere",
    "sg:phone":"+45 46 19 10 45",
    "sg:postcode":"4621",
    "sg:province":"Danmark",
    "wof:name":"Brordrupvejens Thermorudeudskiftning",
    "wof:placetype":"venue"
},
  "geometry": {"coordinates":[12.0971784592,55.5743942261],"type":"Point"}
}