{
  "type": "Feature",
  "properties": {
    "addr:full":"Kildegade 8 - 10 Horsens Danmark 8700",
    "addr:housenumber":"8 10",
    "addr:postcode":"8700",
    "addr:street":"Kildegade",
    "iso:country":"DK",
    "sg:address":"Kildegade 8 - 10",
    "sg:city":"Horsens",
    "sg:orig_category":"Diners transportables",
    "sg:phone":"+45 75 62 83 33",
    "sg:postcode":"8700",
    "sg:province":"Danmark",
    "wof:name":"Danesis Mad",
    "wof:placetype":"venue"
},
  "geometry": {"coordinates":[9.8494367599,55.8640289307],"type":"Point"}
}