{
  "type": "Feature",
  "properties": {
    "iso:country":"DK",
    "sg:address":"Amerikavej 1 ",
    "sg:city":"Esbjerg",
    "sg:classifiers":[
        {
            "category":"Banks & Credit Unions",
            "subcategory":"Investment Brokerage",
            "type":"Services"
        }
    ],
    "sg:phone":"+45 75 12 31 33",
    "sg:postcode":"6700",
    "sg:province":"Danmark",
    "sg:tags":[
        "-",
        "transport",
        "related"
    ],
    "wof:name":"A/S J LAURITZENS EFTF",
    "wof:placetype":"venue"
},
  "geometry": {"coordinates":[8.450381279,55.4570007324],"type":"Point"}
}