{
  "type": "Feature",
  "properties": {
    "addr:full":"Gammel Kongevej 36 N\u00f8rresundby Danmark 9400",
    "addr:housenumber":"36",
    "addr:postcode":"9400",
    "addr:street":"Gammel Kongevej",
    "iso:country":"DK",
    "sg:address":"Gammel Kongevej 36",
    "sg:city":"N\u00f8rresundby",
    "sg:orig_category":"Skolefritidsordninger",
    "sg:phone":"+45 98 17 41 60",
    "sg:postcode":"9400",
    "sg:province":"Danmark",
    "wof:name":"DUS Spor A-B - Nr. Uttrup Skole",
    "wof:placetype":"venue"
},
  "geometry": {"coordinates":[9.943359375,57.0653991699],"type":"Point"}
}