{
  "type": "Feature",
  "properties": {
    "iso:country":"DK",
    "sg:address":"Sognepr\u00e6st: Marianne N. Kristensen, Rorupvej 15, Rorup",
    "sg:city":"Lejre",
    "sg:orig_category":"Kirkesogne",
    "sg:phone":"+45 46 49 71 37",
    "sg:postcode":"4320",
    "sg:province":"Danmark",
    "wof:name":"Rorup og Glim Sogne",
    "wof:placetype":"venue"
},
  "geometry": {"coordinates":[11.9678316116,55.6005630493],"type":"Point"}
}