{
  "type": "Feature",
  "properties": {
    "addr:full":"Kirkebakken 33, Jernved Gredstedbro Danmark 6771",
    "addr:housenumber":"33",
    "addr:postcode":"6771",
    "addr:street":"Kirkebakken",
    "iso:country":"DK",
    "sg:address":"Kirkebakken 33, Jernved",
    "sg:city":"Gredstedbro",
    "sg:orig_category":"Skolefritidsordninger",
    "sg:phone":"+45 75 43 53 27",
    "sg:postcode":"6771",
    "sg:province":"Danmark",
    "wof:name":"B\u00f8rnehuset skolefritidsordning - Jernved Skole",
    "wof:placetype":"venue"
},
  "geometry": {"coordinates":[8.7442560196,55.3970336914],"type":"Point"}
}