{
  "type": "Feature",
  "properties": {
    "addr:full":"Fmd.: Arne Nielsen, Tapagervej 40, Knud Haderslev Danmark 6100",
    "addr:housenumber":"40",
    "addr:postcode":"6100",
    "addr:street":"Arne;Tapagervej;Knud",
    "iso:country":"DK",
    "sg:address":"Fmd.: Arne Nielsen, Tapagervej 40, Knud",
    "sg:city":"Haderslev",
    "sg:orig_category":"Faglige organisationer og foreninger",
    "sg:phone":"+45 74 56 63 60",
    "sg:postcode":"6100",
    "sg:province":"Danmark",
    "wof:name":"Haderslev \u00d8steramts Familielandbrug",
    "wof:placetype":"venue"
},
  "geometry": {"coordinates":[9.4879703522,55.2505493164],"type":"Point"}
}