{
  "type": "Feature",
  "properties": {
    "iso:country":"DK",
    "sg:address":"Varn\u00e6svej 329",
    "sg:city":"Aabenraa",
    "sg:classifiers":[
        {
            "category":"Military Area",
            "subcategory":"Air Force Base",
            "type":"Public Place"
        }
    ],
    "sg:phone":"+45 74 61 36 22",
    "sg:postcode":"6200",
    "sg:province":"Danmark",
    "sg:tags":[
        "breakfast",
        "bed"
    ],
    "sg:website":"www.loff.dk",
    "wof:name":"Loff Bondeg\u00e5rdsferie",
    "wof:placetype":"venue"
},
  "geometry": {"coordinates":[9.47529,55.015381],"type":"Point"}
}