{
  "type": "Feature",
  "properties": {
    "addr:full":"H\u00f8jvangen 29 Fredensborg Danmark 3480",
    "addr:housenumber":"29",
    "addr:postcode":"3480",
    "addr:street":"Hojvangen",
    "iso:country":"DK",
    "sg:address":"H\u00f8jvangen 29",
    "sg:city":"Fredensborg",
    "sg:orig_category":"Autoreservedele",
    "sg:phone":"+45 48 48 56 11",
    "sg:postcode":"3480",
    "sg:province":"Danmark",
    "sg:website":"www.fsa.dk",
    "wof:name":"Frederikssund Autodele A/S",
    "wof:placetype":"venue"
},
  "geometry": {"coordinates":[12.4020547867,55.9782943726],"type":"Point"}
}