{
  "type": "Feature",
  "properties": {
    "addr:full":"Fmd.: Leif Madsen, Parken 6, 1. tv. Fredensborg Danmark 3480",
    "addr:housenumber":"6 1 tv.",
    "addr:postcode":"3480",
    "addr:street":"Leif Madsen Parken",
    "iso:country":"DK",
    "sg:address":"Fmd.: Leif Madsen, Parken 6, 1. tv.",
    "sg:city":"Fredensborg",
    "sg:orig_category":"Folkedans",
    "sg:phone":"+45 48 48 29 63",
    "sg:postcode":"3480",
    "sg:province":"Danmark",
    "wof:name":"Fredensborg og Omegns Folkedanseforening",
    "wof:placetype":"venue"
},
  "geometry": {"coordinates":[12.4020547867,55.9782943726],"type":"Point"}
}