{
  "type": "Feature",
  "properties": {
    "iso:country":"DK",
    "sg:address":"v/ Ea Welsch Andersen, R\u00f8dtj\u00f8rnevej 4, Horneby",
    "sg:city":"Hornb\u00e6k",
    "sg:orig_category":"Spejderkorps",
    "sg:phone":"+45 49 70 30 09",
    "sg:postcode":"3100",
    "sg:province":"Danmark",
    "wof:name":"DDS, Hornb\u00e6k Gruppe Store Bj\u00f8rn",
    "wof:placetype":"venue"
},
  "geometry": {"coordinates":[12.4300451279,56.0916366577],"type":"Point"}
}