{
  "type": "Feature",
  "properties": {
    "addr:full":"Horsensvej 74 Vejle Danmark 7100",
    "addr:housenumber":"74",
    "addr:postcode":"7100",
    "addr:street":"Horsensvej",
    "iso:country":"DK",
    "sg:address":"Horsensvej 74",
    "sg:city":"Vejle",
    "sg:orig_category":"Karate og selvforsvar",
    "sg:phone":"+45 75 72 37 74",
    "sg:postcode":"7100",
    "sg:province":"Danmark",
    "wof:name":"Vejle Taekwondo",
    "wof:placetype":"venue"
},
  "geometry": {"coordinates":[9.5598745346,55.7186431885],"type":"Point"}
}