{
  "type": "Feature",
  "properties": {
    "addr:full":"Birk Centerpark 38 Herning Danmark 7400",
    "addr:housenumber":"38",
    "addr:postcode":"7400",
    "addr:street":"Birk Centerpark",
    "iso:country":"DK",
    "sg:address":"Birk Centerpark 38",
    "sg:city":"Herning",
    "sg:orig_category":"Faglige organisationer og foreninger",
    "sg:phone":"+45 97 11 72 00",
    "sg:postcode":"7400",
    "sg:province":"Danmark",
    "sg:website":"www.textile.dk",
    "wof:name":"Dansk Textil & Bekl\u00e6dning",
    "wof:placetype":"venue"
},
  "geometry": {"coordinates":[9.0303945541,56.1271438599],"type":"Point"}
}