{
  "type": "Feature",
  "properties": {
    "iso:country":"DK",
    "sg:address":"Vestergade 5",
    "sg:city":"Vissenbjerg",
    "sg:orig_category":"Bagere",
    "sg:phone":"+45 64 47 12 66",
    "sg:postcode":"5492",
    "sg:province":"Danmark",
    "wof:name":"Vissenbjerg Bageri",
    "wof:placetype":"venue"
},
  "geometry": {"coordinates":[10.131186,55.385551],"type":"Point"}
}