{
  "type": "Feature",
  "properties": {
    "iso:country":"DK",
    "sg:address":"Nordentoftsvej 7",
    "sg:city":"Brabrand",
    "sg:orig_category":"Legestuer",
    "sg:phone":"+45 86 26 19 66",
    "sg:postcode":"8220",
    "sg:province":"Danmark",
    "wof:name":"Legestuen R\u00f8nnebo",
    "wof:placetype":"venue"
},
  "geometry": {"coordinates":[10.0996961594,56.1526794434],"type":"Point"}
}