{
  "type": "Feature",
  "properties": {
    "addr:full":"Bredgade 20 Roskilde Danmark 4000",
    "addr:housenumber":"20",
    "addr:postcode":"4000",
    "addr:street":"Bredgade",
    "iso:country":"DK",
    "sg:address":"Bredgade 20",
    "sg:city":"Roskilde",
    "sg:orig_category":"Trossamfund uden for folkekirken",
    "sg:phone":"+45 46 35 21 43",
    "sg:postcode":"4000",
    "sg:province":"Danmark",
    "wof:name":"Frelsens H\u00e6r",
    "wof:placetype":"venue"
},
  "geometry": {"coordinates":[12.0784225464,55.6396141052],"type":"Point"}
}