{
  "type": "Feature",
  "properties": {
    "iso:country":"DK",
    "sg:address":"Kr\u00fcgersv\u00e6nget 27",
    "sg:city":"Bevtoft",
    "sg:orig_category":"Antikviteter",
    "sg:phone":"+45 74 51 42 41",
    "sg:postcode":"6541",
    "sg:province":"Danmark",
    "wof:name":"Kramboden",
    "wof:placetype":"venue"
},
  "geometry": {"coordinates":[9.2058296204,55.1994361877],"type":"Point"}
}