{
  "type": "Feature",
  "properties": {
    "addr:full":"Bederslev 7 Otterup Danmark 5450",
    "addr:housenumber":"7",
    "addr:postcode":"5450",
    "addr:street":"Bederslev",
    "iso:country":"DK",
    "sg:address":"Bederslev 7",
    "sg:city":"Otterup",
    "sg:orig_category":"Kirker",
    "sg:postcode":"5450",
    "sg:province":"Danmark",
    "wof:name":"Bederslev Kirke",
    "wof:placetype":"venue"
},
  "geometry": {"coordinates":[10.3445043564,55.5513038635],"type":"Point"}
}