{
  "type": "Feature",
  "properties": {
    "addr:full":"Kollundvej 5 Silkeborg Danmark 8600",
    "addr:housenumber":"5",
    "addr:postcode":"8600",
    "addr:street":"Kollundvej",
    "iso:country":"DK",
    "sg:address":"Kollundvej 5",
    "sg:city":"Silkeborg",
    "sg:orig_category":"INGENI\u00c3\u02dcRER",
    "sg:phone":"+45 87 20 60 40",
    "sg:postcode":"8600",
    "sg:province":"Danmark",
    "sg:website":"www.kolle.com",
    "wof:name":"Kolle, IT-Ingeni\u00f8rfirma",
    "wof:placetype":"venue"
},
  "geometry": {"coordinates":[9.5142345428,56.1760635376],"type":"Point"}
}