{
  "type": "Feature",
  "properties": {
    "iso:country":"DK",
    "sg:address":"\u00c5kandevej 2, Stilling",
    "sg:city":"Skanderborg",
    "sg:orig_category":"INGENI\u00c3\u02dcRER",
    "sg:phone":"+45 70 20 02 42",
    "sg:postcode":"8660",
    "sg:province":"Danmark",
    "wof:name":"CAD-Projekt",
    "wof:placetype":"venue"
},
  "geometry": {"coordinates":[9.929974556,56.0380249023],"type":"Point"}
}