{
  "type": "Feature",
  "properties": {
    "addr:full":"S\u00f8ndre Fasanvej 10 Frederiksberg Danmark 2000",
    "addr:housenumber":"10",
    "addr:postcode":"2000",
    "addr:street":"Sondre Fasanvej",
    "iso:country":"DK",
    "sg:address":"S\u00f8ndre Fasanvej 10",
    "sg:city":"Frederiksberg",
    "sg:orig_category":"Faglige organisationer og -foreninger",
    "sg:phone":"+45 38 87 69 10",
    "sg:postcode":"2000",
    "sg:province":"Danmark",
    "wof:name":"Keramisk Fagforening",
    "wof:placetype":"venue"
},
  "geometry": {"coordinates":[12.5206184387,55.6780471802],"type":"Point"}
}