{
  "type": "Feature",
  "properties": {
    "addr:full":"Kredsleder: Bente Pedersen, Rosendalen 815 Munkebo Danmark 5330",
    "addr:housenumber":"815",
    "addr:postcode":"5330",
    "addr:street":"Kredsleder Bente;Rosendalen",
    "iso:country":"DK",
    "sg:address":"Kredsleder: Bente Pedersen, Rosendalen 815",
    "sg:city":"Munkebo",
    "sg:orig_category":"Redningsberedskab",
    "sg:phone":"+45 65 97 47 56",
    "sg:postcode":"5330",
    "sg:province":"Danmark",
    "wof:name":"Beredskabs-Forbundet Kerteminde/Munkebo Kreds",
    "wof:placetype":"venue"
},
  "geometry": {"coordinates":[10.5594701767,55.4595069885],"type":"Point"}
}