{
  "type": "Feature",
  "properties": {
    "addr:full":"Flodvej 62, Sm\u00f8rumnedre Sm\u00f8rum Danmark 2765",
    "addr:housenumber":"62",
    "addr:postcode":"2765",
    "addr:street":"Flodvej",
    "iso:country":"DK",
    "sg:address":"Flodvej 62, Sm\u00f8rumnedre",
    "sg:city":"Sm\u00f8rum",
    "sg:classifiers":[
        {
            "category":"Restaurant",
            "type":"Food & Drink"
        }
    ],
    "sg:phone":"+45 44 97 96 90",
    "sg:postcode":"2765",
    "sg:province":"Danmark",
    "wof:name":"Led\u00f8je-Sm\u00f8rumhallens Cafeteria",
    "wof:placetype":"venue"
},
  "geometry": {"coordinates":[-89.99810791020001,38.1321372986],"type":"Point"}
}