{
  "type": "Feature",
  "properties": {
    "iso:country":"DK",
    "sg:address":"Kirkegade 18",
    "sg:city":"Aulum",
    "sg:orig_category":"Bagere",
    "sg:phone":"+45 97 47 20 50",
    "sg:postcode":"7490",
    "sg:province":"Danmark",
    "wof:name":"Thuesens Bageri",
    "wof:placetype":"venue"
},
  "geometry": {"coordinates":[8.798045,56.26704],"type":"Point"}
}