{
  "type": "Feature",
  "properties": {
    "addr:full":"Lollandsgade 15 - 19 Aalborg Danmark 9000",
    "addr:housenumber":"15 19",
    "addr:postcode":"9000",
    "addr:street":"Lollandsgade",
    "iso:country":"DK",
    "sg:address":"Lollandsgade 15 - 19",
    "sg:city":"Aalborg",
    "sg:orig_category":"Plejehjemsboliger",
    "sg:phone":"+45 98 13 82 15",
    "sg:postcode":"9000",
    "sg:province":"Danmark",
    "wof:name":"Lollandshus",
    "wof:placetype":"venue"
},
  "geometry": {"coordinates":[9.943605423,57.0425491333],"type":"Point"}
}