{
  "type": "Feature",
  "properties": {
    "addr:full":"Gormsgade 9 Jelling Danmark 7300",
    "addr:housenumber":"9",
    "addr:postcode":"7300",
    "addr:street":"Gormsgade",
    "iso:country":"DK",
    "sg:address":"Gormsgade 9",
    "sg:city":"Jelling",
    "sg:classifiers":[
        {
            "category":"Restaurant",
            "type":"Food & Drink"
        }
    ],
    "sg:phone":"+45 75 87 28 02",
    "sg:postcode":"7300",
    "sg:province":"Danmark",
    "wof:name":"H\u00f8jens Grill & Spisehus",
    "wof:placetype":"venue"
},
  "geometry": {"coordinates":[9.4186897278,55.7556381226],"type":"Point"}
}