{
  "type": "Feature",
  "properties": {
    "addr:full":"Stationsvej 21 Sunds Danmark 7451",
    "addr:housenumber":"21",
    "addr:postcode":"7451",
    "addr:street":"Stationsvej",
    "iso:country":"DK",
    "sg:address":"Stationsvej 21",
    "sg:city":"Sunds",
    "sg:orig_category":"Tekstilindustri",
    "sg:phone":"+45 97 14 11 99",
    "sg:postcode":"7451",
    "sg:province":"Danmark",
    "wof:name":"Elkj\u00e6r A/S, Brdr.",
    "wof:placetype":"venue"
},
  "geometry": {"coordinates":[9.0196533203,56.2011184692],"type":"Point"}
}