{
  "type": "Feature",
  "properties": {
    "addr:full":"v/Lis Joensen, Larsensvej 9 B Gr\u00e6sted Danmark 3230",
    "addr:housenumber":"9 b",
    "addr:postcode":"3230",
    "addr:street":"Joensen Larsensvej",
    "iso:country":"DK",
    "sg:address":"v/Lis Joensen, Larsensvej 9 B",
    "sg:city":"Gr\u00e6sted",
    "sg:orig_category":"Folkedans",
    "sg:phone":"+45 48 39 37 81",
    "sg:postcode":"3230",
    "sg:province":"Danmark",
    "wof:name":"Hiller\u00f8d og Omegns Folkedansere",
    "wof:placetype":"venue"
},
  "geometry": {"coordinates":[-78.6975326538,35.0151481628],"type":"Point"}
}