{
  "type": "Feature",
  "properties": {
    "addr:full":"Tinggade 3 Ringsted Danmark 4100",
    "addr:housenumber":"3",
    "addr:postcode":"4100",
    "addr:street":"Tinggade",
    "iso:country":"DK",
    "sg:address":"Tinggade 3",
    "sg:city":"Ringsted",
    "sg:orig_category":"Fotografer",
    "sg:phone":"+45 57 61 02 37",
    "sg:postcode":"4100",
    "sg:province":"Danmark",
    "wof:name":"Atelier Leila",
    "wof:placetype":"venue"
},
  "geometry": {"coordinates":[11.7898702621,55.4431610107],"type":"Point"}
}