{
  "type": "Feature",
  "properties": {
    "addr:full":"Sankt Knuds Vej 8 Frederiksberg Danmark 1903",
    "addr:housenumber":"8",
    "addr:postcode":"1903",
    "addr:street":"Sankt Knuds Vej",
    "iso:country":"DK",
    "sg:address":"Sankt Knuds Vej 8",
    "sg:city":"Frederiksberg",
    "sg:orig_category":"Tegnere og tegnestuer",
    "sg:phone":"+45 33 31 14 90",
    "sg:postcode":"1903",
    "sg:province":"Danmark",
    "wof:name":"Ovesen, John",
    "wof:placetype":"venue"
},
  "geometry": {"coordinates":[12.5486879349,55.6757507324],"type":"Point"}
}