{
  "type": "Feature",
  "properties": {
    "addr:full":"Fmd.: Niels Bille-Hansen, Lammestrupvej 37, Stubberup Borup Danmark 4140",
    "addr:housenumber":"37",
    "addr:postcode":"4140",
    "addr:street":"Lammestrupvej",
    "iso:country":"DK",
    "sg:address":"Fmd.: Niels Bille-Hansen, Lammestrupvej 37, Stubberup",
    "sg:city":"Borup",
    "sg:orig_category":"Grundejerforeninger",
    "sg:phone":"+45 46 49 65 89",
    "sg:postcode":"4140",
    "sg:province":"Danmark",
    "wof:name":"Stubberup Grundejerforening",
    "wof:placetype":"venue"
},
  "geometry": {"coordinates":[11.9749145508,55.4920845032],"type":"Point"}
}