{
  "type": "Feature",
  "properties": {
    "addr:full":"Sofiendalsvej 85, Postboks 7040 9100",
    "addr:housenumber":"85;7040",
    "addr:postcode":"9100",
    "addr:street":"Sofiendalsvej",
    "iso:country":"DK",
    "sg:address":"Sofiendalsvej 85, Postboks 7040",
    "sg:orig_category":"Revisorer",
    "sg:phone":"+45 98 18 33 44",
    "sg:postcode":"9100",
    "sg:website":"www.danskrevision.dk",
    "wof:name":"Dansk Revision Aalborg",
    "wof:placetype":"venue"
},
  "geometry": {"coordinates":[9.9162597656,57.0493583679],"type":"Point"}
}