{
  "type": "Feature",
  "properties": {
    "addr:full":"Nygade 70 Aabenraa Danmark 6200",
    "addr:housenumber":"70",
    "addr:postcode":"6200",
    "addr:street":"Nygade",
    "iso:country":"DK",
    "sg:address":"Nygade 70",
    "sg:city":"Aabenraa",
    "sg:orig_category":"Skomagere",
    "sg:phone":"+45 74 62 47 32",
    "sg:postcode":"6200",
    "sg:province":"Danmark",
    "wof:name":"Skomagerv\u00e6rkstedet",
    "wof:placetype":"venue"
},
  "geometry": {"coordinates":[9.4155378342,55.0427398682],"type":"Point"}
}