{
  "type": "Feature",
  "properties": {
    "addr:full":"Viby Centret 3 A, Viby Ringvej 10 Viby Danmark 8260",
    "addr:housenumber":"3 a;10",
    "addr:postcode":"8260",
    "addr:street":"Viby Centret;Viby Ringvej",
    "iso:country":"DK",
    "sg:address":"Viby Centret 3 A, Viby Ringvej 10",
    "sg:city":"Viby",
    "sg:orig_category":"Materialister",
    "sg:phone":"+45 86 14 03 88",
    "sg:postcode":"8260",
    "sg:province":"Danmark",
    "wof:name":"Matas",
    "wof:placetype":"venue"
},
  "geometry": {"coordinates":[10.1164493561,56.1353530884],"type":"Point"}
}