{
  "type": "Feature",
  "properties": {
    "addr:full":"Bredstedgade 4, 3 Tv Odense C Danmark 5000",
    "addr:housenumber":"4 3",
    "addr:postcode":"5000",
    "addr:street":"Bredstedgade;Tv",
    "iso:country":"DK",
    "sg:address":"Bredstedgade 4, 3 Tv",
    "sg:city":"Odense C",
    "sg:orig_category":"Reklamebureauer",
    "sg:phone":"+45 66 13 34 40",
    "sg:postcode":"5000",
    "sg:province":"Danmark",
    "wof:name":"Lexbo Design",
    "wof:placetype":"venue"
},
  "geometry": {"coordinates":[10.390794754,55.3961715698],"type":"Point"}
}