{
  "type": "Feature",
  "properties": {
    "iso:country":"DK",
    "sg:address":"Algade 50",
    "sg:city":"Nyk\u00f8bing",
    "sg:orig_category":"Bagere",
    "sg:phone":"+45 59 91 10 20",
    "sg:postcode":"4500",
    "sg:province":"Danmark",
    "wof:name":"Bager Sofus",
    "wof:placetype":"venue"
},
  "geometry": {"coordinates":[16.09696,78.31598700000001],"type":"Point"}
}