{
  "type": "Feature",
  "properties": {
    "addr:full":"Solbrinken 37 Vildbjerg Danmark 7480",
    "addr:housenumber":"37",
    "addr:postcode":"7480",
    "addr:street":"Solbrinken",
    "iso:country":"DK",
    "sg:address":"Solbrinken 37",
    "sg:city":"Vildbjerg",
    "sg:orig_category":"Videofotografer",
    "sg:phone":"+45 97 13 22 69",
    "sg:postcode":"7480",
    "sg:province":"Danmark",
    "wof:name":"Treh\u00f8je Video",
    "wof:placetype":"venue"
},
  "geometry": {"coordinates":[8.7754631042,56.1989326477],"type":"Point"}
}