{
  "type": "Feature",
  "properties": {
    "iso:country":"DK",
    "sg:address":"Bredgade 49",
    "sg:city":"Herning",
    "sg:orig_category":"Sko",
    "sg:phone":"+45 97 21 40 04",
    "sg:postcode":"7400",
    "sg:province":"Danmark",
    "wof:name":"Bianco Footwear",
    "wof:placetype":"venue"
},
  "geometry": {"coordinates":[8.9689922333,56.1361541748],"type":"Point"}
}