{
  "type": "Feature",
  "properties": {
    "addr:full":"Buddingevej 291 S\u00f8borg Danmark 2860",
    "addr:housenumber":"291",
    "addr:postcode":"2860",
    "addr:street":"Buddingevej",
    "iso:country":"DK",
    "sg:address":"Buddingevej 291",
    "sg:city":"S\u00f8borg",
    "sg:orig_category":"Cykler",
    "sg:phone":"+45 39 56 47 37",
    "sg:postcode":"2860",
    "sg:province":"Danmark",
    "wof:name":"J\u00f8rgensen, Per",
    "wof:placetype":"venue"
},
  "geometry": {"coordinates":[-101.39041900629999,35.6679611206],"type":"Point"}
}