{
  "type": "Feature",
  "properties": {
    "iso:country":"DK",
    "sg:address":"Markhaven 20, Bullerup",
    "sg:city":"Agedrup",
    "sg:orig_category":"Revisorer",
    "sg:phone":"+45 66 10 72 12",
    "sg:postcode":"5320",
    "sg:province":"Danmark",
    "wof:name":"J H L Revision",
    "wof:placetype":"venue"
},
  "geometry": {"coordinates":[10.4700860977,55.4257240295],"type":"Point"}
}