{
  "type": "Feature",
  "properties": {
    "addr:full":"H\u00f8rsholmsgade 20,3sal K\u00f8benhavn N Danmark 2200",
    "addr:housenumber":"20,3",
    "addr:postcode":"2200",
    "addr:street":"Horsholmsgade;Kobenhavn N Danmark",
    "iso:country":"DK",
    "sg:address":"H\u00f8rsholmsgade 20,3sal",
    "sg:city":"K\u00f8benhavn N",
    "sg:orig_category":"Teatre",
    "sg:phone":"+45 35 82 06 10",
    "sg:postcode":"2200",
    "sg:province":"Danmark",
    "wof:name":"\u00c5ben Dans Produktion",
    "wof:placetype":"venue"
},
  "geometry": {"coordinates":[-94.49351501460001,47.8772392273],"type":"Point"}
}