{
  "type": "Feature",
  "properties": {
    "iso:country":"DK",
    "sg:address":"Rubinvej 15 A, \u00d8sterild",
    "sg:city":"Thisted",
    "sg:orig_category":"\u00c3\u2020ldrecentre",
    "sg:phone":"+45 97 99 74 44",
    "sg:postcode":"7700",
    "sg:province":"Danmark",
    "wof:name":"Solhjem, \u00c6ldrecentret",
    "wof:placetype":"venue"
},
  "geometry": {"coordinates":[8.6919784546,56.9556121826],"type":"Point"}
}