{
  "type": "Feature",
  "properties": {
    "addr:full":"M\u00f8gelholtvej 55 Hadsund Danmark 9560",
    "addr:housenumber":"55",
    "addr:postcode":"9560",
    "addr:street":"Mogelholtvej",
    "iso:country":"DK",
    "sg:address":"M\u00f8gelholtvej 55",
    "sg:city":"Hadsund",
    "sg:orig_category":"Forsamlingshuse",
    "sg:phone":"+45 98 58 19 27",
    "sg:postcode":"9560",
    "sg:province":"Danmark",
    "wof:name":"Hedens Forsamlingshus",
    "wof:placetype":"venue"
},
  "geometry": {"coordinates":[10.2602930069,56.7693748474],"type":"Point"}
}