{
  "type": "Feature",
  "properties": {
    "iso:country":"DK",
    "sg:address":"Nyholmsvej 16 ",
    "sg:city":"Randers",
    "sg:classifiers":[
        {
            "category":"Food & Beverages",
            "subcategory":"Bakery",
            "type":"Retail Goods"
        }
    ],
    "sg:phone":"+45 86 42 06 88",
    "sg:postcode":"8900",
    "sg:province":"Danmark",
    "sg:tags":[
        "grain",
        "cereal"
    ],
    "wof:name":"CARL J NIELSEN & S\u00d8N A/S",
    "wof:placetype":"venue"
},
  "geometry": {"coordinates":[10.0827732086,56.4713401794],"type":"Point"}
}