{
  "type": "Feature",
  "properties": {
    "addr:full":"Ole Borchs Vej 38 Valby Danmark 2500",
    "addr:housenumber":"38",
    "addr:postcode":"2500",
    "addr:street":"Ole Borchs Vej",
    "iso:country":"DK",
    "sg:address":"Ole Borchs Vej 38",
    "sg:city":"Valby",
    "sg:orig_category":"Sko en gros",
    "sg:phone":"+45 33 23 84 80",
    "sg:postcode":"2500",
    "sg:province":"Danmark",
    "wof:name":"FZ-Shoes Import",
    "wof:placetype":"venue"
},
  "geometry": {"coordinates":[12.4949960709,55.6628456116],"type":"Point"}
}