{
  "type": "Feature",
  "properties": {
    "addr:full":"\u00d8resundsvej 55 A K\u00f8benhavn S Danmark 2300",
    "addr:housenumber":"55 a",
    "addr:postcode":"2300",
    "addr:street":"Oresundsvej;Kobenhavn S Danmark",
    "iso:country":"DK",
    "sg:address":"\u00d8resundsvej 55 A",
    "sg:city":"K\u00f8benhavn S",
    "sg:orig_category":"Stofmisbruger-institutioner",
    "sg:phone":"+45 33 17 86 00",
    "sg:postcode":"2300",
    "sg:province":"Danmark",
    "wof:name":"Ambulatoriet Dyveke",
    "wof:placetype":"venue"
},
  "geometry": {"coordinates":[-82.5175323486,38.5039634705],"type":"Point"}
}