{
  "type": "Feature",
  "properties": {
    "addr:full":"Fmd.: Per N\u00f8rb\u00e6k, Strandvejen 15 Ebeltoft Danmark 8400",
    "addr:housenumber":"15",
    "addr:postcode":"8400",
    "addr:street":"Strandvejen",
    "iso:country":"DK",
    "sg:address":"Fmd.: Per N\u00f8rb\u00e6k, Strandvejen 15",
    "sg:city":"Ebeltoft",
    "sg:orig_category":"Hobbybetonede foreninger",
    "sg:phone":"+45 86 34 36 11",
    "sg:postcode":"8400",
    "sg:province":"Danmark",
    "wof:name":"Ebeltoft Jagtselskab",
    "wof:placetype":"venue"
},
  "geometry": {"coordinates":[10.6778745651,56.199798584],"type":"Point"}
}