{
  "type": "Feature",
  "properties": {
    "addr:full":"Sommerfuglevej 2 A Kolding Danmark 6000",
    "addr:housenumber":"2 a",
    "addr:postcode":"6000",
    "addr:street":"Sommerfuglevej",
    "iso:country":"DK",
    "sg:address":"Sommerfuglevej 2 A",
    "sg:city":"Kolding",
    "sg:orig_category":"Servicestationer",
    "sg:phone":"+45 75 53 30 66",
    "sg:postcode":"6000",
    "sg:province":"Danmark",
    "wof:name":"OK N\u00e6rbutik",
    "wof:placetype":"venue"
},
  "geometry": {"coordinates":[9.5059738159,55.5066833496],"type":"Point"}
}