{
  "type": "Feature",
  "properties": {
    "addr:full":"Bredgade 25 Kolind Danmark 8560",
    "addr:housenumber":"25",
    "addr:postcode":"8560",
    "addr:street":"Bredgade",
    "iso:country":"DK",
    "sg:address":"Bredgade 25",
    "sg:city":"Kolind",
    "sg:orig_category":"Farve og tapet",
    "sg:phone":"+45 86 39 10 62",
    "sg:postcode":"8560",
    "sg:province":"Danmark",
    "wof:name":"Kolind Tapet- og Farvehandel",
    "wof:placetype":"venue"
},
  "geometry": {"coordinates":[10.5895385742,56.3615989685],"type":"Point"}
}