{
  "type": "Feature",
  "properties": {
    "iso:country":"DK",
    "sg:address":"Hovedgaden 8, Lov",
    "sg:city":"N\u00e6stved",
    "sg:orig_category":"Cykler",
    "sg:phone":"+45 55 76 16 28",
    "sg:postcode":"4700",
    "sg:province":"Danmark",
    "wof:name":"Lov Cykler",
    "wof:placetype":"venue"
},
  "geometry": {"coordinates":[9.2555503845,54.9375686646],"type":"Point"}
}