{
  "type": "Feature",
  "properties": {
    "iso:country":"DK",
    "sg:address":"Holstebrovej 21",
    "sg:city":"Herning",
    "sg:orig_category":"Servicestationer",
    "sg:phone":"+45 97 12 21 38",
    "sg:postcode":"7400",
    "sg:province":"Danmark",
    "wof:name":"Statoil Servicenter",
    "wof:placetype":"venue"
},
  "geometry": {"coordinates":[8.9475898743,56.1372528076],"type":"Point"}
}