{
  "type": "Feature",
  "properties": {
    "iso:country":"DK",
    "sg:address":"Klosterv\u00e6nget 28",
    "sg:city":"Skjern",
    "sg:orig_category":"Revisorer",
    "sg:phone":"+45 97 35 30 97",
    "sg:postcode":"6900",
    "sg:province":"Danmark",
    "wof:name":"Trip, Marius",
    "wof:placetype":"venue"
},
  "geometry": {"coordinates":[8.4800682068,55.9425354004],"type":"Point"}
}