{
  "type": "Feature",
  "properties": {
    "addr:full":"R\u00e5dhusstien 3 Vejen Danmark 6600",
    "addr:housenumber":"3",
    "addr:postcode":"6600",
    "addr:street":"Raadhusstien",
    "iso:country":"DK",
    "sg:address":"R\u00e5dhusstien 3",
    "sg:city":"Vejen",
    "sg:orig_category":"Boghandlere",
    "sg:phone":"+45 75 36 00 23",
    "sg:postcode":"6600",
    "sg:province":"Danmark",
    "wof:name":"Vejen Bog & id\u00e9",
    "wof:placetype":"venue"
},
  "geometry": {"coordinates":[9.1371841431,55.4776191711],"type":"Point"}
}