{
  "type": "Feature",
  "properties": {
    "addr:full":"Gilleballetofte 2 A \u00c6r\u00f8sk\u00f8bing Danmark 5970",
    "addr:housenumber":"2 a",
    "addr:postcode":"5970",
    "addr:street":"Gilleballetofte",
    "iso:country":"DK",
    "sg:address":"Gilleballetofte 2 A",
    "sg:city":"\u00c6r\u00f8sk\u00f8bing",
    "sg:classifiers":[
        {
            "category":"Restaurant",
            "type":"Food & Drink"
        }
    ],
    "sg:phone":"+45 62 52 40 02",
    "sg:postcode":"5970",
    "sg:province":"Danmark",
    "wof:name":"Lille Claus, Cafe",
    "wof:placetype":"venue"
},
  "geometry": {"coordinates":[-102.0896530151,42.0193557739],"type":"Point"}
}