{
  "type": "Feature",
  "properties": {
    "addr:full":"v/ Jacob Mikkelsen, Moltrupvej 30 Haderslev Danmark 6100",
    "addr:housenumber":"30",
    "addr:postcode":"6100",
    "addr:street":"Moltrupvej",
    "iso:country":"DK",
    "sg:address":"v/ Jacob Mikkelsen, Moltrupvej 30",
    "sg:city":"Haderslev",
    "sg:orig_category":"Politiske foreninger, \u00c3\u02dcvrige",
    "sg:phone":"+45 74 53 37 87",
    "sg:postcode":"6100",
    "sg:province":"Danmark",
    "wof:name":"Socialistisk Folkepartis Ungdom-Vojens/Haderslev",
    "wof:placetype":"venue"
},
  "geometry": {"coordinates":[9.4879703522,55.2505493164],"type":"Point"}
}