{
  "type": "Feature",
  "properties": {
    "addr:full":"Mellemvang 27 Holb\u00e6k Danmark 4300",
    "addr:housenumber":"27",
    "addr:postcode":"4300",
    "addr:street":"Mellemvang",
    "iso:country":"DK",
    "sg:address":"Mellemvang 27",
    "sg:city":"Holb\u00e6k",
    "sg:orig_category":"Supermarkeder",
    "sg:phone":"+45 59 43 17 40",
    "sg:postcode":"4300",
    "sg:province":"Danmark",
    "wof:name":"Fav\u00f8r Supermarked Mogens Jensen Holb\u00e6k ApS",
    "wof:placetype":"venue"
},
  "geometry": {"coordinates":[76.3070983887,14.277130127],"type":"Point"}
}