{
  "type": "Feature",
  "properties": {
    "addr:full":"Havrev\u00e6nget 9 Vadum Danmark 9430",
    "addr:housenumber":"9",
    "addr:postcode":"9430",
    "addr:street":"Havrevaenget",
    "iso:country":"DK",
    "sg:address":"Havrev\u00e6nget 9",
    "sg:city":"Vadum",
    "sg:classifiers":[
        {
            "category":"Communications",
            "type":"Services"
        }
    ],
    "sg:phone":"+45 98 27 16 87",
    "sg:postcode":"9430",
    "sg:province":"Danmark",
    "sg:tags":[
        "og",
        "tv",
        "radio"
    ],
    "wof:name":"Vadum Radio- & TV-Service",
    "wof:placetype":"venue"
},
  "geometry": {"coordinates":[9.8614330292,57.1187477112],"type":"Point"}
}