{
  "type": "Feature",
  "properties": {
    "iso:country":"DK",
    "sg:address":"L V Bircks Vej 13, Hammerum",
    "sg:city":"Herning",
    "sg:orig_category":"Integrerede institutioner",
    "sg:phone":"+45 96 26 85 80",
    "sg:postcode":"7400",
    "sg:province":"Danmark",
    "wof:name":"Daginstitutionen N\u00f8rg\u00e5rd",
    "wof:placetype":"venue"
},
  "geometry": {"coordinates":[9.0635175705,56.1360778809],"type":"Point"}
}