{
  "type": "Feature",
  "properties": {
    "iso:country":"DK",
    "sg:address":"Sct. Laurentii Vej 112",
    "sg:city":"Skagen",
    "sg:orig_category":"Bogtrykkerier",
    "sg:phone":"+45 98 44 35 11",
    "sg:postcode":"9990",
    "sg:province":"Danmark",
    "wof:name":"Sj\u00f8beck Grafisk",
    "wof:placetype":"venue"
},
  "geometry": {"coordinates":[10.5791978836,57.7186889648],"type":"Point"}
}