{
  "type": "Feature",
  "properties": {
    "addr:full":"Gr\u00f8nnevej 2, Gamst Vejen Danmark 6600",
    "addr:housenumber":"2",
    "addr:postcode":"6600",
    "addr:street":"Gronnevej",
    "iso:country":"DK",
    "sg:address":"Gr\u00f8nnevej 2, Gamst",
    "sg:city":"Vejen",
    "sg:orig_category":"Maskinstationer",
    "sg:phone":"+45 75 58 80 51",
    "sg:postcode":"6600",
    "sg:province":"Danmark",
    "wof:name":"Gamst Maskinstation",
    "wof:placetype":"venue"
},
  "geometry": {"coordinates":[9.1396121979,55.4778175354],"type":"Point"}
}