{
  "type": "Feature",
  "properties": {
    "addr:full":"Snoldelev Bygade 21 Gadstrup Danmark 4621",
    "addr:housenumber":"21",
    "addr:postcode":"4621",
    "addr:street":"Snoldelev Bygade",
    "iso:country":"DK",
    "sg:address":"Snoldelev Bygade 21",
    "sg:city":"Gadstrup",
    "sg:orig_category":"Distriktsbiblioteker",
    "sg:phone":"+45 46 19 01 27",
    "sg:postcode":"4621",
    "sg:province":"Danmark",
    "wof:name":"Snoldelev Bibliotek",
    "wof:placetype":"venue"
},
  "geometry": {"coordinates":[12.1277608871,55.5709533691],"type":"Point"}
}