{
  "type": "Feature",
  "properties": {
    "iso:country":"DK",
    "sg:address":"Langegade 18",
    "sg:city":"Kerteminde",
    "sg:orig_category":"Non-Classified Establishments",
    "sg:phone":"+45 65 32 12 16",
    "sg:postcode":"5300",
    "sg:province":"Danmark",
    "wof:name":"Ost & Vin",
    "wof:placetype":"venue"
},
  "geometry": {"coordinates":[10.6580247879,55.4502449036],"type":"Point"}
}