{
  "type": "Feature",
  "properties": {
    "addr:full":"Kampmannsgade 4 K\u00f8benhavn Danmark 1604",
    "addr:housenumber":"4",
    "addr:postcode":"1604",
    "addr:street":"Kampmannsgade",
    "iso:country":"DK",
    "sg:address":"Kampmannsgade 4",
    "sg:city":"K\u00f8benhavn",
    "sg:orig_category":"Aviser",
    "sg:phone":"+45 33 14 21 40",
    "sg:postcode":"1604",
    "sg:province":"Danmark",
    "sg:website":"www.sid.dk",
    "wof:name":"Fagbladet",
    "wof:placetype":"venue"
},
  "geometry": {"coordinates":[12.5608997345,55.6772994995],"type":"Point"}
}