{
  "type": "Feature",
  "properties": {
    "addr:full":"Slotsgade 35 Aalborg Danmark 9000",
    "addr:housenumber":"35",
    "addr:postcode":"9000",
    "addr:street":"Slotsgade",
    "iso:country":"DK",
    "sg:address":"Slotsgade 35",
    "sg:city":"Aalborg",
    "sg:classifiers":[
        {
            "category":"Restaurant",
            "type":"Food & Drink"
        }
    ],
    "sg:phone":"+45 98 12 15 89",
    "sg:postcode":"9000",
    "sg:province":"Danmark",
    "wof:name":"Slots Kroen",
    "wof:placetype":"venue"
},
  "geometry": {"coordinates":[9.9254655838,57.0490684509],"type":"Point"}
}