{
  "type": "Feature",
  "properties": {
    "addr:full":"Merringvej 125, Merring L\u00f8sning Danmark 8723",
    "addr:housenumber":"125",
    "addr:postcode":"8723",
    "addr:street":"Merringvej",
    "iso:country":"DK",
    "sg:address":"Merringvej 125, Merring",
    "sg:city":"L\u00f8sning",
    "sg:orig_category":"Avlscentre",
    "sg:phone":"+45 75 79 01 89",
    "sg:postcode":"8723",
    "sg:province":"Danmark",
    "wof:name":"Avlcentret Lille Merring G\u00e5rd",
    "wof:placetype":"venue"
},
  "geometry": {"coordinates":[9.7620611191,55.8105201721],"type":"Point"}
}