{
  "type": "Feature",
  "properties": {
    "addr:full":"Havnevej 5 Roskilde Danmark 4000",
    "addr:housenumber":"5",
    "addr:postcode":"4000",
    "addr:street":"Havnevej",
    "iso:country":"DK",
    "sg:address":"Havnevej 5",
    "sg:city":"Roskilde",
    "sg:orig_category":"Faglige organisationer og foreninger",
    "sg:phone":"+45 46 30 40 00",
    "sg:postcode":"4000",
    "sg:province":"Danmark",
    "wof:name":"Dansk Sygeplejer\u00e5d Roskilde Amt",
    "wof:placetype":"venue"
},
  "geometry": {"coordinates":[12.0761833191,55.6462020874],"type":"Point"}
}