{
  "type": "Feature",
  "properties": {
    "addr:full":"Herlev Bygade 39 Herlev Danmark 2730",
    "addr:housenumber":"39",
    "addr:postcode":"2730",
    "addr:street":"Herlev Bygade",
    "iso:country":"DK",
    "sg:address":"Herlev Bygade 39",
    "sg:city":"Herlev",
    "sg:orig_category":"Aviser",
    "sg:phone":"+45 44 94 10 10",
    "sg:postcode":"2730",
    "sg:province":"Danmark",
    "wof:name":"Herlev Bladet",
    "wof:placetype":"venue"
},
  "geometry": {"coordinates":[12.4358348846,55.7247695923],"type":"Point"}
}