{
  "type": "Feature",
  "properties": {
    "addr:full":"Klostervej 74, Kloster Ringk\u00f8bing Danmark 6950",
    "addr:housenumber":"74",
    "addr:postcode":"6950",
    "addr:street":"Klostervej",
    "iso:country":"DK",
    "sg:address":"Klostervej 74, Kloster",
    "sg:city":"Ringk\u00f8bing",
    "sg:orig_category":"Kirker",
    "sg:postcode":"6950",
    "sg:province":"Danmark",
    "wof:name":"Ny Sogn Kirke",
    "wof:placetype":"venue"
},
  "geometry": {"coordinates":[8.2507953644,56.0878334045],"type":"Point"}
}