{
  "type": "Feature",
  "properties": {
    "addr:full":"H\u00f8buen 7, Blistrup Gr\u00e6sted Danmark 3230",
    "addr:housenumber":"7",
    "addr:postcode":"3230",
    "addr:street":"Hobuen",
    "iso:country":"DK",
    "sg:address":"H\u00f8buen 7, Blistrup",
    "sg:city":"Gr\u00e6sted",
    "sg:orig_category":"Kontorservice",
    "sg:phone":"+45 48 71 41 11",
    "sg:postcode":"3230",
    "sg:province":"Danmark",
    "wof:name":"Hoppe Kontorservice & Grafisk Service (DTP)",
    "wof:placetype":"venue"
},
  "geometry": {"coordinates":[12.3426475525,56.048500061],"type":"Point"}
}