{
  "type": "Feature",
  "properties": {
    "iso:country":"DK",
    "sg:address":"Engdahlsvej 2, Birk",
    "sg:city":"Herning",
    "sg:orig_category":"Babyudstyr",
    "sg:phone":"+45 97 21 05 35",
    "sg:postcode":"7400",
    "sg:province":"Danmark",
    "wof:name":"BabySam",
    "wof:placetype":"venue"
},
  "geometry": {"coordinates":[8.97689,56.137417],"type":"Point"}
}