{
  "type": "Feature",
  "properties": {
    "addr:full":"Fmd.: Gunnar Johansen, Fynsvej 5 H\u00f8ng Danmark 4270",
    "addr:housenumber":"5",
    "addr:postcode":"4270",
    "addr:street":"Fynsvej;Hong Danmark",
    "iso:country":"DK",
    "sg:address":"Fmd.: Gunnar Johansen, Fynsvej 5",
    "sg:city":"H\u00f8ng",
    "sg:orig_category":"Folkedans",
    "sg:phone":"+45 58 85 01 62",
    "sg:postcode":"4270",
    "sg:province":"Danmark",
    "wof:name":"Folkedanserforeningen Maj 1986 H\u00f8ng",
    "wof:placetype":"venue"
},
  "geometry": {"coordinates":[-108.880859375,59.3879013062],"type":"Point"}
}