{
  "type": "Feature",
  "properties": {
    "iso:country":"DK",
    "sg:address":"Veggerbyvej 1",
    "sg:city":"Suldrup",
    "sg:orig_category":"Brugsforeninger",
    "sg:phone":"+45 98 37 80 05",
    "sg:postcode":"9541",
    "sg:province":"Danmark",
    "wof:name":"Dagli' Brugsen",
    "wof:placetype":"venue"
},
  "geometry": {"coordinates":[9.700469017,56.8484153748],"type":"Point"}
}