{
  "type": "Feature",
  "properties": {
    "addr:full":"Middelfartvej 6 Odense C Danmark 5000",
    "addr:housenumber":"6",
    "addr:postcode":"5000",
    "addr:street":"Middelfartvej",
    "iso:country":"DK",
    "sg:address":"Middelfartvej 6",
    "sg:city":"Odense C",
    "sg:orig_category":"Autoreparation og -service",
    "sg:phone":"+45 66 12 83 62",
    "sg:postcode":"5000",
    "sg:province":"Danmark",
    "wof:name":"Bilg\u00e5rden Odense ApS",
    "wof:placetype":"venue"
},
  "geometry": {"coordinates":[10.3640079498,55.3942871094],"type":"Point"}
}