{
  "type": "Feature",
  "properties": {
    "addr:full":"Industrivej 11 Lunderskov Danmark 6640",
    "addr:housenumber":"11",
    "addr:postcode":"6640",
    "addr:street":"Industrivej",
    "iso:country":"DK",
    "sg:address":"Industrivej 11",
    "sg:city":"Lunderskov",
    "sg:orig_category":"Import-eksport",
    "sg:phone":"+45 76 84 08 20",
    "sg:postcode":"6640",
    "sg:province":"Danmark",
    "sg:website":"www.camper.dk",
    "wof:name":"Intercamp A/S",
    "wof:placetype":"venue"
},
  "geometry": {"coordinates":[9.2975578308,55.4910240173],"type":"Point"}
}