{
  "type": "Feature",
  "properties": {
    "addr:full":"\u00d8stergade 15 Silkeborg Danmark 8600",
    "addr:housenumber":"15",
    "addr:postcode":"8600",
    "addr:street":"Ostergade",
    "iso:country":"DK",
    "sg:address":"\u00d8stergade 15",
    "sg:city":"Silkeborg",
    "sg:orig_category":"Videobutikker og -klubber",
    "sg:phone":"+45 86 80 67 69",
    "sg:postcode":"8600",
    "sg:province":"Danmark",
    "sg:website":"www.blockbuster.dk",
    "wof:name":"Blockbuster",
    "wof:placetype":"venue"
},
  "geometry": {"coordinates":[9.5525827408,56.1707038879],"type":"Point"}
}