{
  "type": "Feature",
  "properties": {
    "addr:full":"Torvestr\u00e6det 18 Skovlunde Danmark 2740",
    "addr:housenumber":"18",
    "addr:postcode":"2740",
    "addr:street":"Torvestraedet",
    "iso:country":"DK",
    "sg:address":"Torvestr\u00e6det 18",
    "sg:city":"Skovlunde",
    "sg:orig_category":"Fotohandlere",
    "sg:phone":"+45 44 91 03 78",
    "sg:postcode":"2740",
    "sg:province":"Danmark",
    "wof:name":"bb foto & papir",
    "wof:placetype":"venue"
},
  "geometry": {"coordinates":[12.4007949829,55.7209892273],"type":"Point"}
}