{
  "type": "Feature",
  "properties": {
    "addr:full":"Fmd.: Leif Druedahl, Gunds\u00f8lillevej 58, T\u00e5gerup Roskilde Danmark 4000",
    "addr:housenumber":"58",
    "addr:postcode":"4000",
    "addr:street":"Gundsolillevej",
    "iso:country":"DK",
    "sg:address":"Fmd.: Leif Druedahl, Gunds\u00f8lillevej 58, T\u00e5gerup",
    "sg:city":"Roskilde",
    "sg:orig_category":"Kulturelle foreninger",
    "sg:phone":"+45 46 78 60 30",
    "sg:postcode":"4000",
    "sg:province":"Danmark",
    "sg:website":"www.teater-musik.dk",
    "wof:name":"Gunds\u00f8 Teater- og Musikforening",
    "wof:placetype":"venue"
},
  "geometry": {"coordinates":[12.0909376144,55.6404838562],"type":"Point"}
}