{
  "type": "Feature",
  "properties": {
    "addr:full":"Gl. Skolevej 1 A, Valsted Nibe Danmark 9240",
    "addr:housenumber":"1 a",
    "addr:postcode":"9240",
    "addr:street":"Gl. Skolevej;Valsted",
    "iso:country":"DK",
    "sg:address":"Gl. Skolevej 1 A, Valsted",
    "sg:city":"Nibe",
    "sg:orig_category":"Kommunale folkeskoler",
    "sg:phone":"+45 98 35 54 62",
    "sg:postcode":"9240",
    "sg:province":"Danmark",
    "wof:name":"Sebber Skole",
    "wof:placetype":"venue"
},
  "geometry": {"coordinates":[9.6393280029,56.982421875],"type":"Point"}
}