{
  "type": "Feature",
  "properties": {
    "addr:full":"Industrivej 22 Skibby Danmark 4050",
    "addr:housenumber":"22",
    "addr:postcode":"4050",
    "addr:street":"Industrivej",
    "iso:country":"DK",
    "sg:address":"Industrivej 22",
    "sg:city":"Skibby",
    "sg:orig_category":"Rutebiler",
    "sg:phone":"+45 47 52 88 32",
    "sg:postcode":"4050",
    "sg:province":"Danmark",
    "wof:name":"Partnerbus A/S",
    "wof:placetype":"venue"
},
  "geometry": {"coordinates":[11.9556341171,55.7560691833],"type":"Point"}
}