{
  "type": "Feature",
  "properties": {
    "addr:full":"Gl. Skivevej 72 Viborg Danmark 8800",
    "addr:housenumber":"72",
    "addr:postcode":"8800",
    "addr:street":"Gl. Skivevej",
    "iso:country":"DK",
    "sg:address":"Gl. Skivevej 72",
    "sg:city":"Viborg",
    "sg:orig_category":"Gravstene",
    "sg:phone":"+45 86 62 10 28",
    "sg:postcode":"8800",
    "sg:province":"Danmark",
    "wof:name":"Stenhuggerg\u00e5rden",
    "wof:placetype":"venue"
},
  "geometry": {"coordinates":[9.401350975,56.4657020569],"type":"Point"}
}