{
  "type": "Feature",
  "properties": {
    "iso:country":"DK",
    "sg:address":"S\u00f8vejen 15, Stilling",
    "sg:city":"Skanderborg",
    "sg:orig_category":"Revisorer",
    "sg:phone":"+45 86 57 20 01",
    "sg:postcode":"8660",
    "sg:province":"Danmark",
    "wof:name":"V.R. Revision",
    "wof:placetype":"venue"
},
  "geometry": {"coordinates":[9.929974556,56.0380249023],"type":"Point"}
}