{
  "type": "Feature",
  "properties": {
    "iso:country":"DK",
    "sg:address":"herningCentret, Merkurvej 5",
    "sg:city":"Herning",
    "sg:orig_category":"Boghandlere",
    "sg:phone":"+45 97 21 75 77",
    "sg:postcode":"7400",
    "sg:province":"Danmark",
    "wof:name":"Bog & id\u00e9",
    "wof:placetype":"venue"
},
  "geometry": {"coordinates":[8.9768896103,56.1374168396],"type":"Point"}
}