{
  "type": "Feature",
  "properties": {
    "addr:full":"N\u00f8rreport, Jyllandsgade 1 A Skive Danmark 7800",
    "addr:housenumber":"1 a",
    "addr:postcode":"7800",
    "addr:street":"Jyllandsgade",
    "iso:country":"DK",
    "sg:address":"N\u00f8rreport, Jyllandsgade 1 A",
    "sg:city":"Skive",
    "sg:orig_category":"Fodterapeuter",
    "sg:phone":"+45 97 52 77 46",
    "sg:postcode":"7800",
    "sg:province":"Danmark",
    "wof:name":"Klinik for Fodterapi",
    "wof:placetype":"venue"
},
  "geometry": {"coordinates":[9.0320358276,56.5666427612],"type":"Point"}
}