{
  "type": "Feature",
  "properties": {
    "addr:full":"Hostrupvej 2, Jejsing T\u00f8nder Danmark 6270",
    "addr:housenumber":"2",
    "addr:postcode":"6270",
    "addr:street":"Hostrupvej",
    "iso:country":"DK",
    "sg:address":"Hostrupvej 2, Jejsing",
    "sg:city":"T\u00f8nder",
    "sg:orig_category":"Autoreparation og -service",
    "sg:phone":"+45 74 73 44 88",
    "sg:postcode":"6270",
    "sg:province":"Danmark",
    "wof:name":"Jejsing Auto",
    "wof:placetype":"venue"
},
  "geometry": {"coordinates":[8.9661502838,54.9350318909],"type":"Point"}
}