{
  "type": "Feature",
  "properties": {
    "addr:full":"Gennem Landet 76 Anholt Danmark 8592",
    "addr:housenumber":"76",
    "addr:postcode":"8592",
    "addr:street":"Gennem Landet",
    "iso:country":"DK",
    "sg:address":"Gennem Landet 76",
    "sg:city":"Anholt",
    "sg:orig_category":"Skibsproviantering",
    "sg:phone":"+45 86 31 90 10",
    "sg:postcode":"8592",
    "sg:province":"Danmark",
    "wof:name":"Wich, Anni og Carsten",
    "wof:placetype":"venue"
},
  "geometry": {"coordinates":[11.5159540176,56.7149009705],"type":"Point"}
}