{
  "type": "Feature",
  "properties": {
    "addr:full":"Vejlevej 341, Bramdrupdam Kolding Danmark 6000",
    "addr:housenumber":"341",
    "addr:postcode":"6000",
    "addr:street":"Vejlevej;Bramdrupdam",
    "iso:country":"DK",
    "sg:address":"Vejlevej 341, Bramdrupdam",
    "sg:city":"Kolding",
    "sg:orig_category":"Frugt en gros",
    "sg:phone":"+45 75 56 93 99",
    "sg:postcode":"6000",
    "sg:province":"Danmark",
    "wof:name":"Slice Fruit A/S",
    "wof:placetype":"venue"
},
  "geometry": {"coordinates":[9.4733953476,55.4863586426],"type":"Point"}
}