{
  "type": "Feature",
  "properties": {
    "addr:full":"Hovg\u00e5rdvej 8, Svenstrup Vinderup Danmark 7830",
    "addr:housenumber":"8",
    "addr:postcode":"7830",
    "addr:street":"Hovgaardvej;Svenstrup",
    "iso:country":"DK",
    "sg:address":"Hovg\u00e5rdvej 8, Svenstrup",
    "sg:city":"Vinderup",
    "sg:orig_category":"Antikviteter",
    "sg:phone":"+45 97 44 33 53",
    "sg:postcode":"7830",
    "sg:province":"Danmark",
    "wof:name":"Hougaard Antik og Museum",
    "wof:placetype":"venue"
},
  "geometry": {"coordinates":[8.7796897888,56.482635498],"type":"Point"}
}