{
  "type": "Feature",
  "properties": {
    "iso:country":"DK",
    "sg:address":"Velkomstcentret, Marielyst Strandpark 3",
    "sg:city":"V\u00e6ggerl\u00f8se",
    "sg:orig_category":"Sommerhusudlejning",
    "sg:phone":"+45 54 13 29 30",
    "sg:postcode":"4873",
    "sg:province":"Danmark",
    "wof:name":"Sol & Strand Feriehusudlejning",
    "wof:placetype":"venue"
},
  "geometry": {"coordinates":[11.9238767624,54.7119483948],"type":"Point"}
}