{
  "type": "Feature",
  "properties": {
    "iso:country":"DK",
    "sg:address":"Industriparken 31 ",
    "sg:city":"Ballerup",
    "sg:classifiers":[
        {
            "category":"Wholesale",
            "subcategory":"Drugs",
            "type":"Manufacturing & Wholesale Goods"
        }
    ],
    "sg:phone":"+45 43 55 50 50",
    "sg:postcode":"2750",
    "sg:province":"Danmark",
    "sg:tags":[
        "chemical",
        "pharmaceutical"
    ],
    "wof:name":"HEDE NIELSEN A/S",
    "wof:placetype":"venue"
},
  "geometry": {"coordinates":[12.3817472458,55.7279853821],"type":"Point"}
}