{
  "type": "Feature",
  "properties": {
    "addr:full":"Kredsleder.: Ellen Faber J\u00f8rgensen, Nybyvej 38, Nyby Eskilstrup Danmark 4863",
    "addr:housenumber":"38",
    "addr:postcode":"4863",
    "addr:street":"Nybyvej",
    "iso:country":"DK",
    "sg:address":"Kredsleder.: Ellen Faber J\u00f8rgensen, Nybyvej 38, Nyby",
    "sg:city":"Eskilstrup",
    "sg:orig_category":"Spejderkorps",
    "sg:phone":"+45 54 43 62 49",
    "sg:postcode":"4863",
    "sg:province":"Danmark",
    "wof:name":"FDF Eskilstrup",
    "wof:placetype":"venue"
},
  "geometry": {"coordinates":[11.8839511871,54.8547515869],"type":"Point"}
}