{
  "type": "Feature",
  "properties": {
    "addr:full":"Langelinie 4 Horsens Danmark 8700",
    "addr:housenumber":"4",
    "addr:postcode":"8700",
    "addr:street":"Langelinie",
    "iso:country":"DK",
    "sg:address":"Langelinie 4",
    "sg:city":"Horsens",
    "sg:orig_category":"Facader",
    "sg:phone":"+45 75 62 75 88",
    "sg:postcode":"8700",
    "sg:province":"Danmark",
    "wof:name":"Lundsby Alufacader",
    "wof:placetype":"venue"
},
  "geometry": {"coordinates":[9.8750152588,55.8604240417],"type":"Point"}
}