{
  "type": "Feature",
  "properties": {
    "addr:full":"Kokbjerg 28 Kolding Danmark 6000",
    "addr:housenumber":"28",
    "addr:postcode":"6000",
    "addr:street":"Kokbjerg",
    "iso:country":"DK",
    "sg:address":"Kokbjerg 28",
    "sg:city":"Kolding",
    "sg:classifiers":[
        {
            "category":"Utilities",
            "subcategory":"Refuse",
            "type":"Services"
        }
    ],
    "sg:phone":"+45 76 32 18 00",
    "sg:postcode":"6000",
    "sg:province":"Danmark",
    "sg:tags":[
        "catering"
    ],
    "wof:name":"BC-Catering",
    "wof:placetype":"venue"
},
  "geometry": {"coordinates":[9.4745635986,55.5365104675],"type":"Point"}
}