{
  "type": "Feature",
  "properties": {
    "addr:full":"Vejrupg\u00e5rdsvej 3 Marslev Danmark 5290",
    "addr:housenumber":"3",
    "addr:postcode":"5290",
    "addr:street":"Vejrupgaardsvej",
    "iso:country":"DK",
    "sg:address":"Vejrupg\u00e5rdsvej 3",
    "sg:city":"Marslev",
    "sg:orig_category":"Autoophug",
    "sg:phone":"+45 65 95 11 90",
    "sg:postcode":"5290",
    "sg:province":"Danmark",
    "wof:name":"Marslev Autolager",
    "wof:placetype":"venue"
},
  "geometry": {"coordinates":[10.5197706223,55.3766174316],"type":"Point"}
}