{
  "type": "Feature",
  "properties": {
    "addr:full":"Troldbjergvej 12, Simmelk\u00e6r Sunds Danmark 7451",
    "addr:housenumber":"12",
    "addr:postcode":"7451",
    "addr:street":"Troldbjergvej;Simmelkaer",
    "iso:country":"DK",
    "sg:address":"Troldbjergvej 12, Simmelk\u00e6r",
    "sg:city":"Sunds",
    "sg:orig_category":"Forsamlingshuse",
    "sg:phone":"+45 97 14 33 26",
    "sg:postcode":"7451",
    "sg:province":"Danmark",
    "wof:name":"Simmelk\u00e6rhus",
    "wof:placetype":"venue"
},
  "geometry": {"coordinates":[9.0151100159,56.2057800293],"type":"Point"}
}