{
  "type": "Feature",
  "properties": {
    "iso:country":"DK",
    "sg:address":"Fangelvej 20, Fangel",
    "sg:city":"Odense S",
    "sg:orig_category":"Gartnerier",
    "sg:phone":"+45 65 96 24 75",
    "sg:postcode":"5260",
    "sg:province":"Danmark",
    "wof:name":"Andersen, Poul E.",
    "wof:placetype":"venue"
},
  "geometry": {"coordinates":[10.3157806396,55.3122825623],"type":"Point"}
}