{
  "type": "Feature",
  "properties": {
    "addr:full":"Kocksvej 1 C Frederikssund Danmark 3600",
    "addr:housenumber":"1 c",
    "addr:postcode":"3600",
    "addr:street":"Kocksvej",
    "iso:country":"DK",
    "sg:address":"Kocksvej 1 C",
    "sg:city":"Frederikssund",
    "sg:orig_category":"Kirurgiske mave-tarm sygdomme Kirurgisk gastroenterologi, Kirurgi",
    "sg:phone":"+45 47 38 37 38",
    "sg:postcode":"3600",
    "sg:province":"Danmark",
    "wof:name":"Banke, Lars",
    "wof:placetype":"venue"
},
  "geometry": {"coordinates":[12.0614204407,55.8405647278],"type":"Point"}
}