{
  "type": "Feature",
  "properties": {
    "iso:country":"DK",
    "sg:address":"Bregentved All\u00e9 31",
    "sg:city":"Gentofte",
    "sg:orig_category":"Balletskoler",
    "sg:phone":"+45 39 65 46 47",
    "sg:postcode":"2820",
    "sg:province":"Danmark",
    "wof:name":"Muus Balletstudio, Jette",
    "wof:placetype":"venue"
},
  "geometry": {"coordinates":[12.551913,55.743805],"type":"Point"}
}