{
  "type": "Feature",
  "properties": {
    "addr:full":"Faurskovvej 23 Br\u00f8rup Danmark 6650",
    "addr:housenumber":"23",
    "addr:postcode":"6650",
    "addr:street":"Faurskovvej",
    "iso:country":"DK",
    "sg:address":"Faurskovvej 23",
    "sg:city":"Br\u00f8rup",
    "sg:orig_category":"\u00c3\u02dcvrige skoler",
    "sg:phone":"+45 75 38 82 66",
    "sg:postcode":"6650",
    "sg:province":"Danmark",
    "sg:website":"www.assersboelgaard.ribeamt.dk",
    "wof:name":"Asserb\u00f8lg\u00e5rd, Kostskolen",
    "wof:placetype":"venue"
},
  "geometry": {"coordinates":[-93.1630935669,32.8507347107],"type":"Point"}
}