{
  "type": "Feature",
  "properties": {
    "addr:full":"Brinck Seidelins Gade 25 Hj\u00f8rring Danmark 9800",
    "addr:housenumber":"25",
    "addr:postcode":"9800",
    "addr:street":"Brinck Seidelins Gade",
    "iso:country":"DK",
    "sg:address":"Brinck Seidelins Gade 25",
    "sg:city":"Hj\u00f8rring",
    "sg:orig_category":"Politi",
    "sg:phone":"+45 96 23 14 48",
    "sg:postcode":"9800",
    "sg:province":"Danmark",
    "wof:name":"Politig\u00e5rden i Hj\u00f8rring.",
    "wof:placetype":"venue"
},
  "geometry": {"coordinates":[99.92501068120001,34.2430114746],"type":"Point"}
}