{
  "type": "Feature",
  "properties": {
    "addr:full":"Fmd.: Fini Kirk, Nyk\u00f8bingvej 44 Stubbek\u00f8bing Danmark 4850",
    "addr:housenumber":"44",
    "addr:postcode":"4850",
    "addr:street":"Nykobingvej",
    "iso:country":"DK",
    "sg:address":"Fmd.: Fini Kirk, Nyk\u00f8bingvej 44",
    "sg:city":"Stubbek\u00f8bing",
    "sg:orig_category":"Hobbybetonede foreninger",
    "sg:phone":"+45 54 44 28 58",
    "sg:postcode":"4850",
    "sg:province":"Danmark",
    "wof:name":"Frim\u00e6rke Klubben Stubbek\u00f8bing",
    "wof:placetype":"venue"
},
  "geometry": {"coordinates":[-114.0767440796,46.4432487488],"type":"Point"}
}