{
  "type": "Feature",
  "properties": {
    "addr:full":"Mindeh\u00f8jvej 2, Havnelev Mark R\u00f8dvig Stevns Danmark 4673",
    "addr:housenumber":"2",
    "addr:postcode":"4673",
    "addr:street":"Mindehojvej;Havnelev Mark",
    "iso:country":"DK",
    "sg:address":"Mindeh\u00f8jvej 2, Havnelev Mark",
    "sg:city":"R\u00f8dvig Stevns",
    "sg:orig_category":"Forsamlingshuse",
    "sg:phone":"+45 56 50 69 57",
    "sg:postcode":"4673",
    "sg:province":"Danmark",
    "wof:name":"Havnelev Forsamlingshus",
    "wof:placetype":"venue"
},
  "geometry": {"coordinates":[12.3775653839,55.2558746338],"type":"Point"}
}