{
  "type": "Feature",
  "properties": {
    "iso:country":"DK",
    "sg:address":"Fmd.: Merete Christensen, Kvisten 36",
    "sg:city":"Gistrup",
    "sg:orig_category":"Spejderkorps",
    "sg:phone":"+45 98 31 53 77",
    "sg:postcode":"9260",
    "sg:province":"Danmark",
    "wof:name":"FDF Gistrup + Knasten",
    "wof:placetype":"venue"
},
  "geometry": {"coordinates":[9.9942445755,56.9978294373],"type":"Point"}
}