{
  "type": "Feature",
  "properties": {
    "addr:full":"Dr\u00f8sselbjergvej 4, Dr\u00f8sselbjerg Slagelse Danmark 4200",
    "addr:housenumber":"4",
    "addr:postcode":"4200",
    "addr:street":"Drosselbjergvej;Drosselbjerg",
    "iso:country":"DK",
    "sg:address":"Dr\u00f8sselbjergvej 4, Dr\u00f8sselbjerg",
    "sg:city":"Slagelse",
    "sg:orig_category":"Forsamlingshuse",
    "sg:phone":"+45 58 85 82 86",
    "sg:postcode":"4200",
    "sg:province":"Danmark",
    "wof:name":"Dr\u00f8sselbjerg Forsamlingshus",
    "wof:placetype":"venue"
},
  "geometry": {"coordinates":[11.3569850922,55.4050865173],"type":"Point"}
}