{
  "type": "Feature",
  "properties": {
    "addr:full":"Marathonvej 17 K\u00f8benhavn S Danmark 2300",
    "addr:housenumber":"17",
    "addr:postcode":"2300",
    "addr:street":"Marathonvej;S Danmark",
    "iso:country":"DK",
    "sg:address":"Marathonvej 17",
    "sg:city":"K\u00f8benhavn S",
    "sg:orig_category":"Forlag",
    "sg:phone":"+45 32 58 78 40",
    "sg:postcode":"2300",
    "sg:province":"Danmark",
    "wof:name":"Jarlsen & Jenskov",
    "wof:placetype":"venue"
},
  "geometry": {"coordinates":[-82.5307998657,38.4808311462],"type":"Point"}
}