{
  "type": "Feature",
  "properties": {
    "addr:full":"Lemvigvej 13, Heldum Lemvig Danmark 7620",
    "addr:housenumber":"13",
    "addr:postcode":"7620",
    "addr:street":"Lemvigvej;Heldum",
    "iso:country":"DK",
    "sg:address":"Lemvigvej 13, Heldum",
    "sg:city":"Lemvig",
    "sg:orig_category":"Maskinfabrikker",
    "sg:phone":"+45 97 82 05 82",
    "sg:postcode":"7620",
    "sg:province":"Danmark",
    "wof:name":"P. \u00d8gendahls Maskinfabrik",
    "wof:placetype":"venue"
},
  "geometry": {"coordinates":[8.3073654175,56.5505104065],"type":"Point"}
}