{
  "type": "Feature",
  "properties": {
    "addr:full":"Ejby skole, N\u00f8rregade 88, Ejby Ejby Danmark 5592",
    "addr:housenumber":"88",
    "addr:postcode":"5592",
    "addr:street":"Norregade",
    "iso:country":"DK",
    "sg:address":"Ejby skole, N\u00f8rregade 88, Ejby",
    "sg:city":"Ejby",
    "sg:orig_category":"Ungdomsklubber",
    "sg:phone":"+45 63 46 20 48",
    "sg:postcode":"5592",
    "sg:province":"Danmark",
    "wof:name":"Ejby kommunale Ungdomsskoles Ungdomsklub",
    "wof:placetype":"venue"
},
  "geometry": {"coordinates":[9.9277296066,55.4288444519],"type":"Point"}
}