{
  "type": "Feature",
  "properties": {
    "addr:full":"Hovedgaden 26 Bryrup Danmark 8654",
    "addr:housenumber":"26",
    "addr:postcode":"8654",
    "addr:street":"Hovedgaden",
    "iso:country":"DK",
    "sg:address":"Hovedgaden 26",
    "sg:city":"Bryrup",
    "sg:orig_category":"Oliefyr og service",
    "sg:phone":"+45 75 75 60 17",
    "sg:postcode":"8654",
    "sg:province":"Danmark",
    "wof:name":"Bryrup Smede- og VVS-forretning",
    "wof:placetype":"venue"
},
  "geometry": {"coordinates":[9.510974884,56.0245475769],"type":"Point"}
}