{
  "type": "Feature",
  "properties": {
    "addr:full":"Tulstrupvej 1 A, Tulstrup Malling Danmark 8340",
    "addr:housenumber":"1 a",
    "addr:postcode":"8340",
    "addr:street":"Tulstrupvej;Tulstrup",
    "iso:country":"DK",
    "sg:address":"Tulstrupvej 1 A, Tulstrup",
    "sg:city":"Malling",
    "sg:orig_category":"Kirker",
    "sg:postcode":"8340",
    "sg:province":"Danmark",
    "wof:name":"Tulstrup Kirke",
    "wof:placetype":"venue"
},
  "geometry": {"coordinates":[10.193353653,56.0378875732],"type":"Point"}
}