{
  "type": "Feature",
  "properties": {
    "addr:full":"Maglebjergvej 1 Kongens Lyngby Danmark 2800",
    "addr:housenumber":"1",
    "addr:postcode":"2800",
    "addr:street":"Maglebjergvej",
    "iso:country":"DK",
    "sg:address":"Maglebjergvej 1",
    "sg:city":"Kongens Lyngby",
    "sg:orig_category":"Geoteknik",
    "sg:phone":"+45 45 88 44 44",
    "sg:postcode":"2800",
    "sg:province":"Danmark",
    "wof:name":"GEO",
    "wof:placetype":"venue"
},
  "geometry": {"coordinates":[12.5186548233,55.8003768921],"type":"Point"}
}