{
  "type": "Feature",
  "properties": {
    "addr:full":"Dyssevej 28, D\u00f8jringe Sor\u00f8 Danmark 4180",
    "addr:housenumber":"28",
    "addr:postcode":"4180",
    "addr:street":"Dyssevej;Soro",
    "iso:country":"DK",
    "sg:address":"Dyssevej 28, D\u00f8jringe",
    "sg:city":"Sor\u00f8",
    "sg:orig_category":"Asfalt",
    "sg:phone":"+45 57 83 23 22",
    "sg:postcode":"4180",
    "sg:province":"Danmark",
    "wof:name":"Pankas Asfaltv\u00e6rk Sj\u00e6lland",
    "wof:placetype":"venue"
},
  "geometry": {"coordinates":[-102.94467926030001,45.4534721375],"type":"Point"}
}