{
  "type": "Feature",
  "properties": {
    "iso:country":"DK",
    "sg:address":"Pr\u00e6stbrovej 324, \u00d8ster J\u00f8lby",
    "sg:city":"Erslev",
    "sg:orig_category":"Sparekasser",
    "sg:phone":"+45 97 74 13 44",
    "sg:postcode":"7950",
    "sg:province":"Danmark",
    "sg:website":"www.morsoesparekasse.dk",
    "wof:name":"Mors\u00f8 Sparekasse",
    "wof:placetype":"venue"
},
  "geometry": {"coordinates":[8.7200698853,56.8354682922],"type":"Point"}
}