{
  "type": "Feature",
  "properties": {
    "iso:country":"DK",
    "sg:address":"S\u00f8nderhedevej 11",
    "sg:city":"Esbjerg V",
    "sg:classifiers":[
        {
            "category":"Sports & Exercise",
            "subcategory":"Sports Center",
            "type":"Entertainment"
        }
    ],
    "sg:phone":"+45 75 26 92 72",
    "sg:postcode":"6710",
    "sg:province":"Danmark",
    "sg:tags":[
        "golf"
    ],
    "wof:name":"Esbjerg Golfklub",
    "wof:placetype":"venue"
},
  "geometry": {"coordinates":[8.3403348923,55.5708732605],"type":"Point"}
}