{
  "type": "Feature",
  "properties": {
    "iso:country":"DK",
    "sg:address":"Orebyvej 210",
    "sg:city":"Saksk\u00f8bing",
    "sg:classifiers":[
        {
            "category":"Banks & Credit Unions",
            "subcategory":"Investment Brokerage",
            "type":"Services"
        }
    ],
    "sg:phone":"+45 54 70 40 92",
    "sg:postcode":"4990",
    "sg:province":"Danmark",
    "sg:tags":[
        "healing"
    ],
    "wof:name":"Hansen, Vagn",
    "wof:placetype":"venue"
},
  "geometry": {"coordinates":[-114.0767440796,46.4432487488],"type":"Point"}
}