{
  "type": "Feature",
  "properties": {
    "addr:full":"Gislumvej 16 Aars Danmark 9600",
    "addr:housenumber":"16",
    "addr:postcode":"9600",
    "addr:street":"Gislumvej",
    "iso:country":"DK",
    "sg:address":"Gislumvej 16",
    "sg:city":"Aars",
    "sg:orig_category":"Dyrehandlere",
    "sg:phone":"+45 98 62 32 33",
    "sg:postcode":"9600",
    "sg:province":"Danmark",
    "wof:name":"Tropek\u00e6lderen",
    "wof:placetype":"venue"
},
  "geometry": {"coordinates":[9.5133886337,56.8016242981],"type":"Point"}
}