{
  "type": "Feature",
  "properties": {
    "addr:full":"Arres\u00f8vej 19 Risskov Danmark 8240",
    "addr:housenumber":"19",
    "addr:postcode":"8240",
    "addr:street":"Arresovej",
    "iso:country":"DK",
    "sg:address":"Arres\u00f8vej 19",
    "sg:city":"Risskov",
    "sg:orig_category":"Autoreparation og -service",
    "sg:phone":"+45 86 17 64 11",
    "sg:postcode":"8240",
    "sg:province":"Danmark",
    "wof:name":"Rydberg & S\u00f8n",
    "wof:placetype":"venue"
},
  "geometry": {"coordinates":[10.2331380844,56.2022476196],"type":"Point"}
}