{
  "type": "Feature",
  "properties": {
    "addr:full":"Fmd.: John L. Christensen, Markv\u00e6nget 6, Dommerby Skive Danmark 7800",
    "addr:housenumber":"6",
    "addr:postcode":"7800",
    "addr:street":"Markvaenget;Dommerby",
    "iso:country":"DK",
    "sg:address":"Fmd.: John L. Christensen, Markv\u00e6nget 6, Dommerby",
    "sg:city":"Skive",
    "sg:orig_category":"Spejderkorps",
    "sg:phone":"+45 97 53 58 93",
    "sg:postcode":"7800",
    "sg:province":"Danmark",
    "wof:name":"KFUM-spejderne - H\u00f8jslev St. Gruppe",
    "wof:placetype":"venue"
},
  "geometry": {"coordinates":[9.0320358276,56.5666427612],"type":"Point"}
}