{
  "type": "Feature",
  "properties": {
    "addr:full":"Kostr\u00e6de Byvej 39 Lundby Danmark 4750",
    "addr:housenumber":"39",
    "addr:postcode":"4750",
    "addr:street":"Kostraede Byvej",
    "iso:country":"DK",
    "sg:address":"Kostr\u00e6de Byvej 39",
    "sg:city":"Lundby",
    "sg:orig_category":"Bogtrykkerier",
    "sg:phone":"+45 55 76 90 46",
    "sg:postcode":"4750",
    "sg:province":"Danmark",
    "wof:name":"Partner Print",
    "wof:placetype":"venue"
},
  "geometry": {"coordinates":[11.8101682663,55.1197814941],"type":"Point"}
}