{
  "type": "Feature",
  "properties": {
    "addr:full":"v/ Superbrugsen Gadstrup Brugsforening, Dysseg\u00e5rdsvej 30 Gadstrup Danmark 4621",
    "addr:housenumber":"30",
    "addr:postcode":"4621",
    "addr:street":"Gadstrup;Dyssegaardsvej",
    "iso:country":"DK",
    "sg:address":"v/ Superbrugsen Gadstrup Brugsforening, Dysseg\u00e5rdsvej 30",
    "sg:city":"Gadstrup",
    "sg:orig_category":"Apoteker og -udsalg",
    "sg:phone":"+45 46 19 00 03",
    "sg:postcode":"4621",
    "sg:province":"Danmark",
    "wof:name":"H\u00e5ndk\u00f8bsudsalg fra Havdrup Apotek",
    "wof:placetype":"venue"
},
  "geometry": {"coordinates":[12.0978450775,55.5737800598],"type":"Point"}
}