{
  "type": "Feature",
  "properties": {
    "addr:full":"\u00d8stre Ringvej 37 Ringe Danmark 5750",
    "addr:housenumber":"37",
    "addr:postcode":"5750",
    "addr:street":"Ostre Ringvej",
    "iso:country":"DK",
    "sg:address":"\u00d8stre Ringvej 37",
    "sg:city":"Ringe",
    "sg:orig_category":"Malervarer",
    "sg:phone":"+45 62 62 10 04",
    "sg:postcode":"5750",
    "sg:province":"Danmark",
    "wof:name":"Ringe K\u00f8bmandsgaard A/S",
    "wof:placetype":"venue"
},
  "geometry": {"coordinates":[10.4843606949,55.238910675],"type":"Point"}
}