{
  "type": "Feature",
  "properties": {
    "addr:full":"Vestergade 55 Odense C Danmark 5000",
    "addr:housenumber":"55",
    "addr:postcode":"5000",
    "addr:street":"Vestergade",
    "iso:country":"DK",
    "sg:address":"Vestergade 55",
    "sg:city":"Odense C",
    "sg:classifiers":[
        {
            "category":"Restaurant",
            "type":"Food & Drink"
        }
    ],
    "sg:phone":"+45 66 12 82 34",
    "sg:postcode":"5000",
    "sg:province":"Danmark",
    "wof:name":"Sunset Boulevard",
    "wof:placetype":"venue"
},
  "geometry": {"coordinates":[10.3841218948,55.3951072693],"type":"Point"}
}