{
  "type": "Feature",
  "properties": {
    "addr:full":"Virketvej 44, Virket Eskilstrup Danmark 4863",
    "addr:housenumber":"44",
    "addr:postcode":"4863",
    "addr:street":"Virketvej",
    "iso:country":"DK",
    "sg:address":"Virketvej 44, Virket",
    "sg:city":"Eskilstrup",
    "sg:classifiers":[
        {
            "category":"Sports & Exercise",
            "subcategory":"Sports Center",
            "type":"Entertainment"
        }
    ],
    "sg:phone":"+45 54 43 81 43",
    "sg:postcode":"4863",
    "sg:province":"Danmark",
    "sg:tags":[
        "golf"
    ],
    "wof:name":"Falster Golf Klub",
    "wof:placetype":"venue"
},
  "geometry": {"coordinates":[11.8839511871,54.8547515869],"type":"Point"}
}