{
  "type": "Feature",
  "properties": {
    "addr:full":"City 2 306, Plan 3 Taastrup Danmark 2630",
    "addr:housenumber":"306;3",
    "addr:postcode":"2630",
    "addr:street":"2;Plan",
    "iso:country":"DK",
    "sg:address":"City 2 306, Plan 3",
    "sg:city":"Taastrup",
    "sg:orig_category":"Pelsvarer",
    "sg:phone":"+45 43 52 47 12",
    "sg:postcode":"2630",
    "sg:province":"Danmark",
    "wof:name":"Grand International Skindfashion",
    "wof:placetype":"venue"
},
  "geometry": {"coordinates":[12.2743463516,55.6432151794],"type":"Point"}
}