{
  "type": "Feature",
  "properties": {
    "addr:full":"Skomagergade 8,1 Roskilde Danmark 4000",
    "addr:housenumber":"8,1",
    "addr:postcode":"4000",
    "addr:street":"Skomagergade",
    "iso:country":"DK",
    "sg:address":"Skomagergade 8,1",
    "sg:city":"Roskilde",
    "sg:orig_category":"Hobbyartikler",
    "sg:phone":"+45 46 35 69 62",
    "sg:postcode":"4000",
    "sg:province":"Danmark",
    "wof:name":"Alleh\u00e5nde Hobby",
    "wof:placetype":"venue"
},
  "geometry": {"coordinates":[12.0794286728,55.6410713196],"type":"Point"}
}