{
  "type": "Feature",
  "properties": {
    "addr:full":"S\u00f8ller\u00f8dvej 76, S\u00f8ller\u00f8d Holte Danmark 2840",
    "addr:housenumber":"76",
    "addr:postcode":"2840",
    "addr:street":"Sollerodvej",
    "iso:country":"DK",
    "sg:address":"S\u00f8ller\u00f8dvej 76, S\u00f8ller\u00f8d",
    "sg:city":"Holte",
    "sg:orig_category":"Kursussteder",
    "sg:phone":"+45 45 50 51 35",
    "sg:postcode":"2840",
    "sg:province":"Danmark",
    "sg:website":"www.wld.dk",
    "wof:name":"Wilson Learning Danmark",
    "wof:placetype":"venue"
},
  "geometry": {"coordinates":[12.4706554413,55.8122367859],"type":"Point"}
}