{
  "type": "Feature",
  "properties": {
    "addr:full":"Algade 28 Store Heddinge Danmark 4660",
    "addr:housenumber":"28",
    "addr:postcode":"4660",
    "addr:street":"Algade",
    "iso:country":"DK",
    "sg:address":"Algade 28",
    "sg:city":"Store Heddinge",
    "sg:classifiers":[
        {
            "category":"Food & Beverages",
            "subcategory":"Liquor & Beverages",
            "type":"Retail Goods"
        }
    ],
    "sg:phone":"+45 56 50 23 51",
    "sg:postcode":"4660",
    "sg:province":"Danmark",
    "sg:tags":[
        "vin"
    ],
    "wof:name":"Skjold Burne",
    "wof:placetype":"venue"
},
  "geometry": {"coordinates":[12.3898391724,55.3115310669],"type":"Point"}
}