{
  "type": "Feature",
  "properties": {
    "iso:country":"DK",
    "sg:address":"K\u00f8benhavnsvej 106 H",
    "sg:city":"Roskilde",
    "sg:orig_category":"Bedriftssundhedstjenester",
    "sg:phone":"+45 46 75 48 48",
    "sg:postcode":"4000",
    "sg:province":"Danmark",
    "sg:website":"www.bst-roskilde.dk",
    "wof:name":"BST Nord ApS",
    "wof:placetype":"venue"
},
  "geometry": {"coordinates":[12.090938,55.640484],"type":"Point"}
}