{
  "type": "Feature",
  "properties": {
    "addr:full":"Lunden 66, Bullerup Agedrup Danmark 5320",
    "addr:housenumber":"66",
    "addr:postcode":"5320",
    "addr:street":"Lunden",
    "iso:country":"DK",
    "sg:address":"Lunden 66, Bullerup",
    "sg:city":"Agedrup",
    "sg:orig_category":"Posthuse",
    "sg:phone":"+45 66 10 90 02",
    "sg:postcode":"5320",
    "sg:province":"Danmark",
    "wof:name":"Post Danmark, Bullerup Posthus",
    "wof:placetype":"venue"
},
  "geometry": {"coordinates":[10.4700860977,55.4257240295],"type":"Point"}
}