{
  "type": "Feature",
  "properties": {
    "iso:country":"DK",
    "sg:address":"Klim Strandvej 156, Klim Bjerg",
    "sg:city":"Fjerritslev",
    "sg:classifiers":[
        {
            "category":"Restaurant",
            "type":"Food & Drink"
        }
    ],
    "sg:phone":"+45 98 22 52 42",
    "sg:postcode":"9690",
    "sg:province":"Danmark",
    "sg:website":"www.klimbjerg.dk",
    "wof:name":"Klim Bjerg, Hotel og Restaurant",
    "wof:placetype":"venue"
},
  "geometry": {"coordinates":[9.2667350769,57.0882301331],"type":"Point"}
}