{
  "type": "Feature",
  "properties": {
    "iso:country":"DK",
    "sg:address":"Havnevej 17 ",
    "sg:city":"Allinge",
    "sg:classifiers":[
        {
            "category":"Autos & Motor Vehicles",
            "subcategory":"Boat Sales",
            "type":"Retail Goods"
        }
    ],
    "sg:phone":"+45 56 48 01 50",
    "sg:postcode":"3770",
    "sg:province":"Danmark",
    "wof:name":"BRDR MADSEN MOTOR APS",
    "wof:placetype":"venue"
},
  "geometry": {"coordinates":[14.831492424,55.2493972778],"type":"Point"}
}