{
  "type": "Feature",
  "properties": {
    "addr:full":"Ferskes\u00f8str\u00e6de 27 Nex\u00f8 Danmark 3730",
    "addr:housenumber":"27",
    "addr:postcode":"3730",
    "addr:street":"Ferskesostraede",
    "iso:country":"DK",
    "sg:address":"Ferskes\u00f8str\u00e6de 27",
    "sg:city":"Nex\u00f8",
    "sg:orig_category":"Psykologer, praktiserende",
    "sg:phone":"+45 56 49 20 70",
    "sg:postcode":"3730",
    "sg:province":"Danmark",
    "wof:name":"Palby, Annette",
    "wof:placetype":"venue"
},
  "geometry": {"coordinates":[15.1096076965,55.0267219543],"type":"Point"}
}