{
  "type": "Feature",
  "properties": {
    "addr:full":"Stabyvej 70, Staby Ulfborg Danmark 6990",
    "addr:housenumber":"70",
    "addr:postcode":"6990",
    "addr:street":"Stabyvej",
    "iso:country":"DK",
    "sg:address":"Stabyvej 70, Staby",
    "sg:city":"Ulfborg",
    "sg:orig_category":"Arkitekter",
    "sg:phone":"+45 97 49 15 33",
    "sg:postcode":"6990",
    "sg:province":"Danmark",
    "wof:name":"Schmidt-Christensen, Aage",
    "wof:placetype":"venue"
},
  "geometry": {"coordinates":[8.3210029602,56.2727661133],"type":"Point"}
}