{
  "type": "Feature",
  "properties": {
    "addr:full":"Lejrvejen 6 Padborg Danmark 6330",
    "addr:housenumber":"6",
    "addr:postcode":"6330",
    "addr:street":"Lejrvejen",
    "iso:country":"DK",
    "sg:address":"Lejrvejen 6",
    "sg:city":"Padborg",
    "sg:orig_category":"Autoforhandlere",
    "sg:phone":"+45 74 67 04 60",
    "sg:postcode":"6330",
    "sg:province":"Danmark",
    "wof:name":"D.T. Auto A/S",
    "wof:placetype":"venue"
},
  "geometry": {"coordinates":[9.3447465897,54.8319091797],"type":"Point"}
}