{
  "type": "Feature",
  "properties": {
    "addr:full":"Gammel Kirkevej 104 Kastrup Danmark 2770",
    "addr:housenumber":"104",
    "addr:postcode":"2770",
    "addr:street":"Gammel Kirkevej",
    "iso:country":"DK",
    "sg:address":"Gammel Kirkevej 104",
    "sg:city":"Kastrup",
    "sg:orig_category":"Autoreparation og -service",
    "sg:phone":"+45 32 51 81 91",
    "sg:postcode":"2770",
    "sg:province":"Danmark",
    "wof:name":"BK Auto",
    "wof:placetype":"venue"
},
  "geometry": {"coordinates":[12.6205377579,55.6311607361],"type":"Point"}
}