{
  "type": "Feature",
  "properties": {
    "addr:full":"Vardevej 12 Skjern Danmark 6900",
    "addr:housenumber":"12",
    "addr:postcode":"6900",
    "addr:street":"Vardevej",
    "iso:country":"DK",
    "sg:address":"Vardevej 12",
    "sg:city":"Skjern",
    "sg:orig_category":"Kirker",
    "sg:postcode":"6900",
    "sg:province":"Danmark",
    "wof:name":"Skjern Kirke",
    "wof:placetype":"venue"
},
  "geometry": {"coordinates":[8.4986066818,55.9428672791],"type":"Point"}
}