{
  "type": "Feature",
  "properties": {
    "iso:country":"DK",
    "sg:address":"Elmebjergvej 27 A",
    "sg:city":"Sor\u00f8",
    "sg:orig_category":"Blomsterhandlere",
    "sg:phone":"+45 57 82 06 00",
    "sg:postcode":"4180",
    "sg:province":"Danmark",
    "sg:website":"www.silkegroent.dk",
    "wof:name":"Silkegr\u00f8nt",
    "wof:placetype":"venue"
},
  "geometry": {"coordinates":[-102.94467926030001,45.4534721375],"type":"Point"}
}