{
  "type": "Feature",
  "properties": {
    "addr:full":"Herningvej 48 - 52 Holstebro Danmark 7500",
    "addr:housenumber":"48 52",
    "addr:postcode":"7500",
    "addr:street":"Herningvej",
    "iso:country":"DK",
    "sg:address":"Herningvej 48 - 52",
    "sg:city":"Holstebro",
    "sg:orig_category":"Autoforhandlere",
    "sg:phone":"+45 97 42 22 66",
    "sg:postcode":"7500",
    "sg:province":"Danmark",
    "wof:name":"Bilhuset",
    "wof:placetype":"venue"
},
  "geometry": {"coordinates":[8.6239147186,56.3503723145],"type":"Point"}
}