{
  "type": "Feature",
  "properties": {
    "iso:country":"DK",
    "sg:address":"Hersegade 26",
    "sg:city":"Roskilde",
    "sg:classifiers":[
        {
            "category":"Food & Beverages",
            "subcategory":"Liquor & Beverages",
            "type":"Retail Goods"
        }
    ],
    "sg:phone":"+45 46 37 37 45",
    "sg:postcode":"4000",
    "sg:province":"Danmark",
    "sg:tags":[
        "vin"
    ],
    "wof:name":"tyske Vinhus, Det",
    "wof:placetype":"venue"
},
  "geometry": {"coordinates":[12.0850105286,55.6390838623],"type":"Point"}
}