{
  "type": "Feature",
  "properties": {
    "addr:full":"Gravene 45 Viborg Danmark 8800",
    "addr:housenumber":"45",
    "addr:postcode":"8800",
    "addr:street":"Gravene",
    "iso:country":"DK",
    "sg:address":"Gravene 45",
    "sg:city":"Viborg",
    "sg:classifiers":[
        {
            "category":"Restaurant",
            "type":"Food & Drink"
        }
    ],
    "sg:phone":"+45 86 62 02 67",
    "sg:postcode":"8800",
    "sg:province":"Danmark",
    "wof:name":"Sidki",
    "wof:placetype":"venue"
},
  "geometry": {"coordinates":[9.4077548981,56.4524040222],"type":"Point"}
}