{
  "type": "Feature",
  "properties": {
    "addr:full":"\u00d8stergade 8 B Struer Danmark 7600",
    "addr:housenumber":"8 b",
    "addr:postcode":"7600",
    "addr:street":"Ostergade",
    "iso:country":"DK",
    "sg:address":"\u00d8stergade 8 B",
    "sg:city":"Struer",
    "sg:orig_category":"Pizzeriaer",
    "sg:phone":"+45 97 85 30 34",
    "sg:postcode":"7600",
    "sg:province":"Danmark",
    "wof:name":"Charlie's Pizza & Kekab House",
    "wof:placetype":"venue"
},
  "geometry": {"coordinates":[8.5928936005,56.4920120239],"type":"Point"}
}