{
  "type": "Feature",
  "properties": {
    "addr:full":"Langelandsvej 14 Middelfart Danmark 5500",
    "addr:housenumber":"14",
    "addr:postcode":"5500",
    "addr:street":"Langelandsvej",
    "iso:country":"DK",
    "sg:address":"Langelandsvej 14",
    "sg:city":"Middelfart",
    "sg:orig_category":"Fabrikker",
    "sg:phone":"+45 64 41 21 75",
    "sg:postcode":"5500",
    "sg:province":"Danmark",
    "wof:name":"Odreco Belysning",
    "wof:placetype":"venue"
},
  "geometry": {"coordinates":[9.7613382339,55.5044593811],"type":"Point"}
}