{
  "type": "Feature",
  "properties": {
    "addr:full":"R\u00e5dhusgade 8 Aabenraa Danmark 6200",
    "addr:housenumber":"8",
    "addr:postcode":"6200",
    "addr:street":"Raadhusgade",
    "iso:country":"DK",
    "sg:address":"R\u00e5dhusgade 8",
    "sg:city":"Aabenraa",
    "sg:orig_category":"Blomsterhandlere",
    "sg:phone":"+45 73 62 14 14",
    "sg:postcode":"6200",
    "sg:province":"Danmark",
    "wof:name":"Vivaldi",
    "wof:placetype":"venue"
},
  "geometry": {"coordinates":[9.4194602966,55.0431022644],"type":"Point"}
}