{
  "type": "Feature",
  "properties": {
    "addr:full":"Kirkedals Alle 17 Hobro Danmark 9500",
    "addr:housenumber":"17",
    "addr:postcode":"9500",
    "addr:street":"Kirkedals Alle",
    "iso:country":"DK",
    "sg:address":"Kirkedals Alle 17",
    "sg:city":"Hobro",
    "sg:orig_category":"Skorstensfejere",
    "sg:phone":"+45 98 52 25 71",
    "sg:postcode":"9500",
    "sg:province":"Danmark",
    "wof:name":"Askgaard, S\u00f8ren",
    "wof:placetype":"venue"
},
  "geometry": {"coordinates":[9.8190164566,56.6314811707],"type":"Point"}
}