{
  "type": "Feature",
  "properties": {
    "addr:full":"Bellevuevej 19 Varde Danmark 6800",
    "addr:housenumber":"19",
    "addr:postcode":"6800",
    "addr:street":"Bellevuevej",
    "iso:country":"DK",
    "sg:address":"Bellevuevej 19",
    "sg:city":"Varde",
    "sg:orig_category":"Murermestre",
    "sg:phone":"+45 75 21 26 28",
    "sg:postcode":"6800",
    "sg:province":"Danmark",
    "wof:name":"Varde Murerne ApS",
    "wof:placetype":"venue"
},
  "geometry": {"coordinates":[8.4983778,55.6289787292],"type":"Point"}
}