{
  "type": "Feature",
  "properties": {
    "iso:country":"DK",
    "sg:address":"Nordre Strandvej 2, Lums\u00e5s",
    "sg:city":"Nyk\u00f8bing",
    "sg:orig_category":"Virksomhedskonsulenter",
    "sg:phone":"+45 59 32 10 74",
    "sg:postcode":"4500",
    "sg:province":"Danmark",
    "wof:name":"DesignGruppe DSG",
    "wof:placetype":"venue"
},
  "geometry": {"coordinates":[16.0969600677,78.3159866333],"type":"Point"}
}