{
  "type": "Feature",
  "properties": {
    "addr:full":"Vester S\u00f8ttrup Vej 25, S\u00f8ttrup Aars Danmark 9600",
    "addr:housenumber":"25",
    "addr:postcode":"9600",
    "addr:street":"Vester Sottrup Vej;Sottrup",
    "iso:country":"DK",
    "sg:address":"Vester S\u00f8ttrup Vej 25, S\u00f8ttrup",
    "sg:city":"Aars",
    "sg:orig_category":"Slagterier",
    "sg:postcode":"9600",
    "sg:province":"Danmark",
    "wof:name":"Hjemmeslagtning",
    "wof:placetype":"venue"
},
  "geometry": {"coordinates":[9.5170412064,56.8031692505],"type":"Point"}
}