{
  "type": "Feature",
  "properties": {
    "addr:full":"V\u00e6rnedamsvej 1 Frederiksberg Danmark 1819",
    "addr:housenumber":"1;1819",
    "addr:street":"Vaernedamsvej",
    "iso:country":"DK",
    "sg:address":"V\u00e6rnedamsvej 1",
    "sg:city":"Frederiksberg",
    "sg:orig_category":"Fotohandlere",
    "sg:phone":"+45 33 24 51 12",
    "sg:postcode":"1819",
    "sg:province":"Danmark",
    "sg:website":"www.bingo-foto.dk",
    "wof:name":"Bingo-Foto",
    "wof:placetype":"venue"
},
  "geometry": {"coordinates":[12.549706459,55.6737060547],"type":"Point"}
}