{
  "type": "Feature",
  "properties": {
    "addr:full":"Jupitervej 22, Rom Lemvig Danmark 7620",
    "addr:housenumber":"22",
    "addr:postcode":"7620",
    "addr:street":"Jupitervej",
    "iso:country":"DK",
    "sg:address":"Jupitervej 22, Rom",
    "sg:city":"Lemvig",
    "sg:orig_category":"Maskinfabrikker",
    "sg:phone":"+45 97 82 36 66",
    "sg:postcode":"7620",
    "sg:province":"Danmark",
    "wof:name":"Heta A/S",
    "wof:placetype":"venue"
},
  "geometry": {"coordinates":[8.3073654175,56.5505104065],"type":"Point"}
}