{
  "type": "Feature",
  "properties": {
    "iso:country":"DK",
    "sg:address":"\u00d8stergade 12. 1",
    "sg:city":"Helsinge",
    "sg:orig_category":"Advokater",
    "sg:phone":"+45 48 79 40 45",
    "sg:postcode":"3200",
    "sg:province":"Danmark",
    "wof:name":"Petersen og Tine Jacobsen, Poul Erik",
    "wof:placetype":"venue"
},
  "geometry": {"coordinates":[12.2004261017,56.0224494934],"type":"Point"}
}