{
  "type": "Feature",
  "properties": {
    "addr:full":"Engdraget 5 Lem Danmark 6940",
    "addr:housenumber":"5",
    "addr:postcode":"6940",
    "addr:street":"Engdraget",
    "iso:country":"DK",
    "sg:address":"Engdraget 5",
    "sg:city":"Lem",
    "sg:orig_category":"Murermestre",
    "sg:phone":"+45 97 34 12 57",
    "sg:postcode":"6940",
    "sg:province":"Danmark",
    "wof:name":"Madsen ApS, Martin",
    "wof:placetype":"venue"
},
  "geometry": {"coordinates":[8.3852748871,56.0288276672],"type":"Point"}
}