{
  "type": "Feature",
  "properties": {
    "addr:full":"Stubbendrupvej 1, Havndrup Ringe Danmark 5750",
    "addr:housenumber":"1",
    "addr:postcode":"5750",
    "addr:street":"Stubbendrupvej",
    "iso:country":"DK",
    "sg:address":"Stubbendrupvej 1, Havndrup",
    "sg:city":"Ringe",
    "sg:orig_category":"Murermestre",
    "sg:phone":"+45 62 67 25 78",
    "sg:postcode":"5750",
    "sg:province":"Danmark",
    "wof:name":"Jensen, Flemming",
    "wof:placetype":"venue"
},
  "geometry": {"coordinates":[10.4781074524,55.2356643677],"type":"Point"}
}