{
  "type": "Feature",
  "properties": {
    "addr:full":"Kollund Byvej 75 B Herning Danmark 7400",
    "addr:housenumber":"75 b",
    "addr:postcode":"7400",
    "addr:street":"Kollund Byvej",
    "iso:country":"DK",
    "sg:address":"Kollund Byvej 75 B",
    "sg:city":"Herning",
    "sg:orig_category":"Kirker",
    "sg:postcode":"7400",
    "sg:province":"Danmark",
    "wof:name":"Kollund Kirke",
    "wof:placetype":"venue"
},
  "geometry": {"coordinates":[9.0266389847,56.0907821655],"type":"Point"}
}