{
  "type": "Feature",
  "properties": {
    "iso:country":"DK",
    "sg:address":"Fmd.: Anne Marie Hansen, Granvej 5, Frederiks",
    "sg:city":"Karup",
    "sg:orig_category":"Husflidsforeninger",
    "sg:phone":"+45 86 66 20 11",
    "sg:postcode":"7470",
    "sg:province":"Danmark",
    "wof:name":"Frederiks Husmoderforening",
    "wof:placetype":"venue"
},
  "geometry": {"coordinates":[9.2525548935,56.3398017883],"type":"Point"}
}