{
  "type": "Feature",
  "properties": {
    "addr:full":"Vesterbyvej 15 Skagen Danmark 9990",
    "addr:housenumber":"15",
    "addr:postcode":"9990",
    "addr:street":"Vesterbyvej",
    "iso:country":"DK",
    "sg:address":"Vesterbyvej 15",
    "sg:city":"Skagen",
    "sg:orig_category":"Zoneterapeuter",
    "sg:phone":"+45 96 79 06 66",
    "sg:postcode":"9990",
    "sg:province":"Danmark",
    "wof:name":"Skagen Zoneterapiklinik",
    "wof:placetype":"venue"
},
  "geometry": {"coordinates":[10.5805072784,57.7183303833],"type":"Point"}
}