{
  "type": "Feature",
  "properties": {
    "addr:full":"\u00d8stergade 25 Ikast Danmark 7430",
    "addr:housenumber":"25",
    "addr:postcode":"7430",
    "addr:street":"Ostergade",
    "iso:country":"DK",
    "sg:address":"\u00d8stergade 25",
    "sg:city":"Ikast",
    "sg:orig_category":"Diskoteker",
    "sg:phone":"+45 97 15 48 18",
    "sg:postcode":"7430",
    "sg:province":"Danmark",
    "wof:name":"Disco 2000",
    "wof:placetype":"venue"
},
  "geometry": {"coordinates":[9.1591615677,56.1398925781],"type":"Point"}
}