{
  "type": "Feature",
  "properties": {
    "iso:country":"DK",
    "sg:address":"Fabriksvej 7 ",
    "sg:city":"Fars\u00f8",
    "sg:classifiers":[
        {
            "category":"Home & Garden",
            "subcategory":"Home Furnishings",
            "type":"Retail Goods"
        }
    ],
    "sg:phone":"+45 98 63 29 44",
    "sg:postcode":"9640",
    "sg:province":"Danmark",
    "sg:tags":[
        "household"
    ],
    "wof:name":"UNO FORM",
    "wof:placetype":"venue"
},
  "geometry": {"coordinates":[-109.44831848139999,42.1062355042],"type":"Point"}
}