{
  "type": "Feature",
  "properties": {
    "iso:country":"DK",
    "sg:address":"Hovedgaden 54",
    "sg:city":"Havdrup",
    "sg:orig_category":"Servicestationer",
    "sg:phone":"+45 46 18 50 54",
    "sg:postcode":"4622",
    "sg:province":"Danmark",
    "wof:name":"DK Benzin",
    "wof:placetype":"venue"
},
  "geometry": {"coordinates":[12.117196,55.539135],"type":"Point"}
}