{
  "type": "Feature",
  "properties": {
    "iso:country":"DK",
    "sg:address":"N\u00f8rregade 13 ",
    "sg:city":"Sindal",
    "sg:classifiers":[
        {
            "category":"Bars & Pubs",
            "subcategory":"Nightclub",
            "type":"Food & Drink"
        }
    ],
    "sg:phone":"+45 98 93 50 45",
    "sg:postcode":"9870",
    "sg:province":"Danmark",
    "sg:tags":[
        "cake",
        "bread"
    ],
    "wof:name":"BAGERIET INGEBORG APS",
    "wof:placetype":"venue"
},
  "geometry": {"coordinates":[10.2019605637,57.4723052979],"type":"Point"}
}