{
  "type": "Feature",
  "properties": {
    "addr:full":"Kass.: Ejvind Friis Jensen, Agervej 2, Kvislemark Sandved Danmark 4262",
    "addr:housenumber":"2",
    "addr:postcode":"4262",
    "addr:street":"Agervej",
    "iso:country":"DK",
    "sg:address":"Kass.: Ejvind Friis Jensen, Agervej 2, Kvislemark",
    "sg:city":"Sandved",
    "sg:orig_category":"Soldaterforeninger",
    "sg:phone":"+45 55 44 41 00",
    "sg:postcode":"4262",
    "sg:province":"Danmark",
    "wof:name":"Sj\u00e6llandske Livsregiments Soldaterforening 4. regiment",
    "wof:placetype":"venue"
},
  "geometry": {"coordinates":[11.5230302811,55.2632255554],"type":"Point"}
}