{
  "type": "Feature",
  "properties": {
    "addr:full":"Carolinevej 3 B Hellerup Danmark 2900",
    "addr:housenumber":"3 b",
    "addr:postcode":"2900",
    "addr:street":"Carolinevej",
    "iso:country":"DK",
    "sg:address":"Carolinevej 3 B",
    "sg:city":"Hellerup",
    "sg:orig_category":"Reklamebureauer",
    "sg:phone":"+45 39 46 31 00",
    "sg:postcode":"2900",
    "sg:province":"Danmark",
    "sg:website":"www.glp.dk",
    "wof:name":"Larsen & Partners A/S, Gorm",
    "wof:placetype":"venue"
},
  "geometry": {"coordinates":[12.5772781372,55.7295608521],"type":"Point"}
}