{
  "type": "Feature",
  "properties": {
    "iso:country":"DK",
    "sg:address":"v/ Boligkontoret Danmark, Lundsgade 9",
    "sg:city":"K\u00f8benhavn \u00d8",
    "sg:orig_category":"Boligselskaber",
    "sg:phone":"+45 39 27 21 00",
    "sg:postcode":"2100",
    "sg:province":"Danmark",
    "wof:name":"Statsbanepersonalets Andels-Boligforening",
    "wof:placetype":"venue"
},
  "geometry": {"coordinates":[9.5166797638,56.2756996155],"type":"Point"}
}