{
  "type": "Feature",
  "properties": {
    "addr:full":"Buddinge Hovedgade 124 S\u00f8borg Danmark 2860",
    "addr:housenumber":"124",
    "addr:postcode":"2860",
    "addr:street":"Buddinge Hovedgade",
    "iso:country":"DK",
    "sg:address":"Buddinge Hovedgade 124",
    "sg:city":"S\u00f8borg",
    "sg:classifiers":[
        {
            "category":"Restaurant",
            "type":"Food & Drink"
        }
    ],
    "sg:phone":"+45 39 69 26 83",
    "sg:postcode":"2860",
    "sg:province":"Danmark",
    "wof:name":"Lasses Hj\u00f8rne",
    "wof:placetype":"venue"
},
  "geometry": {"coordinates":[12.4982404709,55.7419395447],"type":"Point"}
}