{
  "type": "Feature",
  "properties": {
    "iso:country":"DK",
    "sg:address":"Gammel Lyngvej 23 A",
    "sg:city":"K\u00f8ge",
    "sg:orig_category":"Sengeudstyr",
    "sg:phone":"+45 56 65 40 62",
    "sg:postcode":"4600",
    "sg:province":"Danmark",
    "wof:name":"Jysk Senget\u00f8jslager",
    "wof:placetype":"venue"
},
  "geometry": {"coordinates":[12.20436,48.51823],"type":"Point"}
}