{
  "type": "Feature",
  "properties": {
    "addr:full":"Rynkebjergg\u00e5rdsvej 1, H\u00f8jby Lejre Danmark 4320",
    "addr:housenumber":"1",
    "addr:postcode":"4320",
    "addr:street":"Rynkebjerggaardsvej;Hojby",
    "iso:country":"DK",
    "sg:address":"Rynkebjergg\u00e5rdsvej 1, H\u00f8jby",
    "sg:city":"Lejre",
    "sg:orig_category":"Vuggestuer",
    "sg:phone":"+45 46 48 01 77",
    "sg:postcode":"4320",
    "sg:province":"Danmark",
    "wof:name":"R\u00f8glebakkens Vuggestue",
    "wof:placetype":"venue"
},
  "geometry": {"coordinates":[11.9678316116,55.6005630493],"type":"Point"}
}