{
  "type": "Feature",
  "properties": {
    "addr:full":"\u00d8stergade 38 B Hj\u00f8rring Danmark 9800",
    "addr:housenumber":"38 b",
    "addr:postcode":"9800",
    "addr:street":"Ostergade",
    "iso:country":"DK",
    "sg:address":"\u00d8stergade 38 B",
    "sg:city":"Hj\u00f8rring",
    "sg:orig_category":"Skomagere",
    "sg:phone":"+45 98 92 83 70",
    "sg:postcode":"9800",
    "sg:province":"Danmark",
    "wof:name":"Simmelsgaard, Per",
    "wof:placetype":"venue"
},
  "geometry": {"coordinates":[77.2480392456,14.1354398727],"type":"Point"}
}