{
  "type": "Feature",
  "properties": {
    "addr:full":"Hvingelbyvej 20, Lomborg Lemvig Danmark 7620",
    "addr:housenumber":"20",
    "addr:postcode":"7620",
    "addr:street":"Hvingelbyvej",
    "iso:country":"DK",
    "sg:address":"Hvingelbyvej 20, Lomborg",
    "sg:city":"Lemvig",
    "sg:orig_category":"Autoforhandlere",
    "sg:phone":"+45 97 88 93 95",
    "sg:postcode":"7620",
    "sg:province":"Danmark",
    "wof:name":"Lomborg Autohandel",
    "wof:placetype":"venue"
},
  "geometry": {"coordinates":[8.3073654175,56.5505104065],"type":"Point"}
}