{
  "type": "Feature",
  "properties": {
    "addr:full":"Revslundvej 2, Roost Branderup Danmark 6535",
    "addr:housenumber":"2",
    "addr:postcode":"6535",
    "addr:street":"Revslundvej",
    "iso:country":"DK",
    "sg:address":"Revslundvej 2, Roost",
    "sg:city":"Branderup",
    "sg:orig_category":"Maskinstationer",
    "sg:phone":"+45 74 83 54 19",
    "sg:postcode":"6535",
    "sg:province":"Danmark",
    "wof:name":"Refslund Entrepren\u00f8r- & Maskinstation",
    "wof:placetype":"venue"
},
  "geometry": {"coordinates":[9.0691099167,55.1218643188],"type":"Point"}
}