{
  "type": "Feature",
  "properties": {
    "addr:full":"Storegade 14 F\u00e5rup Danmark 8990",
    "addr:housenumber":"14",
    "addr:postcode":"8990",
    "addr:street":"Storegade",
    "iso:country":"DK",
    "sg:address":"Storegade 14",
    "sg:city":"F\u00e5rup",
    "sg:orig_category":"Posthuse",
    "sg:phone":"+45 86 45 39 16",
    "sg:postcode":"8990",
    "sg:province":"Danmark",
    "wof:name":"Post Danmark, F\u00e5rup Postbutik",
    "wof:placetype":"venue"
},
  "geometry": {"coordinates":[-93.1630935669,32.8507347107],"type":"Point"}
}