{
  "type": "Feature",
  "properties": {
    "addr:full":"Helgesvej 7 Herlufmagle Danmark 4160",
    "addr:housenumber":"7",
    "addr:postcode":"4160",
    "addr:street":"Helgesvej",
    "iso:country":"DK",
    "sg:address":"Helgesvej 7",
    "sg:city":"Herlufmagle",
    "sg:orig_category":"Musikskoler, Kommunale",
    "sg:phone":"+45 57 69 03 55",
    "sg:postcode":"4160",
    "sg:province":"Danmark",
    "wof:name":"Sus\u00e5 musikskole",
    "wof:placetype":"venue"
},
  "geometry": {"coordinates":[11.7521982193,55.3170700073],"type":"Point"}
}