{
  "type": "Feature",
  "properties": {
    "addr:full":"Istedgade 27 \u00c5rhus C Danmark 8000",
    "addr:housenumber":"27",
    "addr:postcode":"8000",
    "addr:street":"Istedgade",
    "iso:country":"DK",
    "sg:address":"Istedgade 27",
    "sg:city":"\u00c5rhus C",
    "sg:orig_category":"Kunsthandlere",
    "sg:phone":"+45 86 19 67 65",
    "sg:postcode":"8000",
    "sg:province":"Danmark",
    "wof:name":"Himmel og Hav ApS",
    "wof:placetype":"venue"
},
  "geometry": {"coordinates":[10.1993360519,56.1484222412],"type":"Point"}
}