{
  "type": "Feature",
  "properties": {
    "addr:full":"Kirkesmedien, Fuglesangsvej 2, Rutsker Hasle Danmark 3790",
    "addr:housenumber":"2",
    "addr:postcode":"3790",
    "addr:street":"Fuglesangsvej",
    "iso:country":"DK",
    "sg:address":"Kirkesmedien, Fuglesangsvej 2, Rutsker",
    "sg:city":"Hasle",
    "sg:orig_category":"Konsulentvirksomheder",
    "sg:phone":"+45 70 20 01 78",
    "sg:postcode":"3790",
    "sg:province":"Danmark",
    "wof:name":"Riemer, Gina",
    "wof:placetype":"venue"
},
  "geometry": {"coordinates":[14.7065896988,55.1830863953],"type":"Point"}
}