{
  "type": "Feature",
  "properties": {
    "addr:full":"N\u00f8rregade 42, 1. tv. Skive Danmark 7800",
    "addr:housenumber":"42 1 tv.",
    "addr:postcode":"7800",
    "addr:street":"Norregade",
    "iso:country":"DK",
    "sg:address":"N\u00f8rregade 42, 1. tv.",
    "sg:city":"Skive",
    "sg:orig_category":"Faglige organisationer og foreninger",
    "sg:phone":"+45 97 52 47 22",
    "sg:postcode":"7800",
    "sg:province":"Danmark",
    "sg:website":"www.krifa.dk",
    "wof:name":"Kristelige Fagbev\u00e6gelse, Den",
    "wof:placetype":"venue"
},
  "geometry": {"coordinates":[9.0320358276,56.5666427612],"type":"Point"}
}