{
  "type": "Feature",
  "properties": {
    "iso:country":"DK",
    "sg:address":"Fmd.: Ejlif D. Schmidt, Svalevej 32",
    "sg:city":"Lunderskov",
    "sg:orig_category":"\u00c3\u2020ldreorganisationer og klubber",
    "sg:phone":"+45 75 58 56 57",
    "sg:postcode":"6640",
    "sg:province":"Danmark",
    "wof:name":"Lunderskov Pensionistforening",
    "wof:placetype":"venue"
},
  "geometry": {"coordinates":[9.2983627319,55.4793586731],"type":"Point"}
}