{
  "type": "Feature",
  "properties": {
    "addr:full":"Parkvej 5 Nibe Danmark 9240",
    "addr:housenumber":"5",
    "addr:postcode":"9240",
    "addr:street":"Parkvej",
    "iso:country":"DK",
    "sg:address":"Parkvej 5",
    "sg:city":"Nibe",
    "sg:orig_category":"Kirker",
    "sg:postcode":"9240",
    "sg:province":"Danmark",
    "wof:name":"Baptistkirken",
    "wof:placetype":"venue"
},
  "geometry": {"coordinates":[9.6498212814,56.9860343933],"type":"Point"}
}