{
  "type": "Feature",
  "properties": {
    "addr:full":"Grevevej 39, Tune Greve Danmark 2670",
    "addr:housenumber":"39",
    "addr:postcode":"2670",
    "addr:street":"Grevevej",
    "iso:country":"DK",
    "sg:address":"Grevevej 39, Tune",
    "sg:city":"Greve",
    "sg:orig_category":"Listefabrikker",
    "sg:phone":"+45 43 61 01 35",
    "sg:postcode":"2670",
    "sg:province":"Danmark",
    "sg:website":"www.logik.subnet.dk",
    "wof:name":"Tune Listefabrik",
    "wof:placetype":"venue"
},
  "geometry": {"coordinates":[12.2941808701,55.5844078064],"type":"Point"}
}