{
  "type": "Feature",
  "properties": {
    "addr:full":"Skovgade 6 Middelfart Danmark 5500",
    "addr:housenumber":"6",
    "addr:postcode":"5500",
    "addr:street":"Skovgade",
    "iso:country":"DK",
    "sg:address":"Skovgade 6",
    "sg:city":"Middelfart",
    "sg:orig_category":"Murermestre",
    "sg:phone":"+45 64 41 28 35",
    "sg:postcode":"5500",
    "sg:province":"Danmark",
    "wof:name":"Bay's Murerfirma, Erik",
    "wof:placetype":"venue"
},
  "geometry": {"coordinates":[9.7249383926,55.5052223206],"type":"Point"}
}