{
  "type": "Feature",
  "properties": {
    "addr:full":"Solbakkevej 5 Brovst Danmark 9460",
    "addr:housenumber":"5",
    "addr:postcode":"9460",
    "addr:street":"Solbakkevej",
    "iso:country":"DK",
    "sg:address":"Solbakkevej 5",
    "sg:city":"Brovst",
    "sg:orig_category":"Malermestre",
    "sg:phone":"+45 98 23 11 62",
    "sg:postcode":"9460",
    "sg:province":"Danmark",
    "wof:name":"Simonsen, Malerfirmaet",
    "wof:placetype":"venue"
},
  "geometry": {"coordinates":[9.520316124,57.0985336304],"type":"Point"}
}