{
  "type": "Feature",
  "properties": {
    "addr:full":"Centrumgaden 16 A Ballerup Danmark 2750",
    "addr:housenumber":"16 a",
    "addr:postcode":"2750",
    "addr:street":"Centrumgaden",
    "iso:country":"DK",
    "sg:address":"Centrumgaden 16 A",
    "sg:city":"Ballerup",
    "sg:orig_category":"Sportsartikler",
    "sg:phone":"+45 44 66 31 35",
    "sg:postcode":"2750",
    "sg:province":"Danmark",
    "wof:name":"Sport'n G\u00e5gaden",
    "wof:placetype":"venue"
},
  "geometry": {"coordinates":[12.360458374,55.7307815552],"type":"Point"}
}