{
  "type": "Feature",
  "properties": {
    "addr:full":"Gr\u00f8nneled 4 Albertslund Danmark 2620",
    "addr:housenumber":"4",
    "addr:postcode":"2620",
    "addr:street":"Gronneled",
    "iso:country":"DK",
    "sg:address":"Gr\u00f8nneled 4",
    "sg:city":"Albertslund",
    "sg:orig_category":"Legeredskaber",
    "sg:phone":"+45 43 62 13 44",
    "sg:postcode":"2620",
    "sg:province":"Danmark",
    "wof:name":"Lappset Legepladsudstyr",
    "wof:placetype":"venue"
},
  "geometry": {"coordinates":[12.353679657,55.6615753174],"type":"Point"}
}