{
  "type": "Feature",
  "properties": {
    "addr:full":"B\u00f8gevej 5-7, \u00d8rum Tjele Danmark 8830",
    "addr:housenumber":"5-7",
    "addr:postcode":"8830",
    "addr:street":"Bogevej",
    "iso:country":"DK",
    "sg:address":"B\u00f8gevej 5-7, \u00d8rum",
    "sg:city":"Tjele",
    "sg:orig_category":"Varmeforsyning",
    "sg:phone":"+45 86 65 25 20",
    "sg:postcode":"8830",
    "sg:province":"Danmark",
    "sg:website":"www.oerumvarme.dk",
    "wof:name":"\u00d8rum Fjernvarmev\u00e6rk",
    "wof:placetype":"venue"
},
  "geometry": {"coordinates":[9.6264801025,56.4818611145],"type":"Point"}
}