{
  "type": "Feature",
  "properties": {
    "addr:full":"Posthussm\u00f8gen 11 C \u00c5rhus C Danmark 8000",
    "addr:housenumber":"11 c",
    "addr:postcode":"8000",
    "addr:street":"Posthussmogen",
    "iso:country":"DK",
    "sg:address":"Posthussm\u00f8gen 11 C",
    "sg:city":"\u00c5rhus C",
    "sg:orig_category":"Trossamfund uden for folkekirken",
    "sg:phone":"+45 86 18 17 10",
    "sg:postcode":"8000",
    "sg:province":"Danmark",
    "wof:name":"Spiritualistisk Forening Lyset",
    "wof:placetype":"venue"
},
  "geometry": {"coordinates":[4.717400074,49.7588005066],"type":"Point"}
}