{
  "type": "Feature",
  "properties": {
    "addr:full":"Vestergade 8 Gudme Danmark 5884",
    "addr:housenumber":"8",
    "addr:postcode":"5884",
    "addr:street":"Vestergade",
    "iso:country":"DK",
    "sg:address":"Vestergade 8",
    "sg:city":"Gudme",
    "sg:orig_category":"Zoneterapeuter",
    "sg:phone":"+45 62 25 34 79",
    "sg:postcode":"5884",
    "sg:province":"Danmark",
    "wof:name":"Gudme Zoneterapi",
    "wof:placetype":"venue"
},
  "geometry": {"coordinates":[10.7040376663,55.1540489197],"type":"Point"}
}