{
  "type": "Feature",
  "properties": {
    "addr:full":"Fmd.: Jens Hansen, Barakvejen 14, Kulhuse J\u00e6gerspris Danmark 3630",
    "addr:housenumber":"14",
    "addr:postcode":"3630",
    "addr:street":"Barakvejen",
    "iso:country":"DK",
    "sg:address":"Fmd.: Jens Hansen, Barakvejen 14, Kulhuse",
    "sg:city":"J\u00e6gerspris",
    "sg:orig_category":"Grundejerforeninger",
    "sg:postcode":"3630",
    "sg:province":"Danmark",
    "wof:name":"Bakkebo Grundejerforening",
    "wof:placetype":"venue"
},
  "geometry": {"coordinates":[11.9136800766,55.9269866943],"type":"Point"}
}