{
  "type": "Feature",
  "properties": {
    "iso:country":"DK",
    "sg:address":"Ved Kanalen 3",
    "sg:city":"K\u00f8benhavn",
    "sg:orig_category":"Internettjenester",
    "sg:phone":"+45 35 26 00 17",
    "sg:postcode":"1413",
    "sg:province":"Danmark",
    "wof:name":"Eida Internet Service",
    "wof:placetype":"venue"
},
  "geometry": {"coordinates":[12.5892000198,55.6699981689],"type":"Point"}
}