{
  "type": "Feature",
  "properties": {
    "iso:country":"DK",
    "sg:address":"Leder: Tenna Lauritsen, Hasselparken 16",
    "sg:city":"Jyllinge",
    "sg:orig_category":"\u00c3\u02dcvrig fritidsundervisning",
    "sg:phone":"+45 46 78 80 66",
    "sg:postcode":"4040",
    "sg:province":"Danmark",
    "wof:name":"Jyllinge Squaredance Klub",
    "wof:placetype":"venue"
},
  "geometry": {"coordinates":[12.1163625717,55.7643737793],"type":"Point"}
}