{
  "type": "Feature",
  "properties": {
    "addr:full":"Strandfoged Johanne Clausen, S\u00f8bakken 15, P\u00f8l Nordborg Danmark 6430",
    "addr:housenumber":"15",
    "addr:postcode":"6430",
    "addr:street":"Johanne;Sobakken",
    "iso:country":"DK",
    "sg:address":"Strandfoged Johanne Clausen, S\u00f8bakken 15, P\u00f8l",
    "sg:city":"Nordborg",
    "sg:orig_category":"Strandfogeder",
    "sg:phone":"+45 74 49 08 63",
    "sg:postcode":"6430",
    "sg:province":"Danmark",
    "wof:name":"Holm Strand",
    "wof:placetype":"venue"
},
  "geometry": {"coordinates":[9.7496232986,55.0542755127],"type":"Point"}
}