{
  "type": "Feature",
  "properties": {
    "addr:full":"Svendg\u00e5rdsvej 3 Beder Danmark 8330",
    "addr:housenumber":"3",
    "addr:postcode":"8330",
    "addr:street":"Svendgaardsvej",
    "iso:country":"DK",
    "sg:address":"Svendg\u00e5rdsvej 3",
    "sg:city":"Beder",
    "sg:orig_category":"Finansiering",
    "sg:phone":"+45 87 47 52 00",
    "sg:postcode":"8330",
    "sg:province":"Danmark",
    "wof:name":"\u00d8stjysk Forvaltningsselskab A/S",
    "wof:placetype":"venue"
},
  "geometry": {"coordinates":[10.2137899399,56.059211731],"type":"Point"}
}