{
  "type": "Feature",
  "properties": {
    "iso:country":"DK",
    "sg:address":"Naverland 31",
    "sg:city":"Glostrup",
    "sg:classifiers":[
        {
            "category":"Communications",
            "type":"Services"
        }
    ],
    "sg:phone":"+45 43 46 80 00",
    "sg:postcode":"2600",
    "sg:province":"Danmark",
    "sg:tags":[
        "og",
        "tv",
        "radio"
    ],
    "sg:website":"www.elektronik-centret.dk",
    "wof:name":"Elektronik Centret",
    "wof:placetype":"venue"
},
  "geometry": {"coordinates":[12.3744287491,55.6788635254],"type":"Point"}
}