{
  "type": "Feature",
  "properties": {
    "addr:full":"Forskningscenter Flakkebjerg, Fors\u00f8gsvej 1, Flakkebjerg Slagelse Danmark 4200",
    "addr:housenumber":"1",
    "addr:postcode":"4200",
    "addr:street":"Forsogsvej;Flakkebjerg",
    "iso:country":"DK",
    "sg:address":"Forskningscenter Flakkebjerg, Fors\u00f8gsvej 1, Flakkebjerg",
    "sg:city":"Slagelse",
    "sg:orig_category":"Forskningscentre",
    "sg:phone":"+45 58 11 33 00",
    "sg:postcode":"4200",
    "sg:province":"Danmark",
    "wof:name":"Danmarks Jordbrugsforskning",
    "wof:placetype":"venue"
},
  "geometry": {"coordinates":[11.3569850922,55.4050865173],"type":"Point"}
}