{
  "type": "Feature",
  "properties": {
    "iso:country":"DK",
    "sg:address":"Adelgade 45",
    "sg:city":"Nysted",
    "sg:orig_category":"Dag- og distriktsblade",
    "sg:phone":"+45 54 87 12 15",
    "sg:postcode":"4880",
    "sg:province":"Danmark",
    "wof:name":"Nysted-Avis",
    "wof:placetype":"venue"
},
  "geometry": {"coordinates":[11.7288007736,54.667339325],"type":"Point"}
}