{
  "type": "Feature",
  "properties": {
    "addr:full":"Nordvejen 17 Solbjerg Danmark 8355",
    "addr:housenumber":"17",
    "addr:postcode":"8355",
    "addr:street":"Nordvejen",
    "iso:country":"DK",
    "sg:address":"Nordvejen 17",
    "sg:city":"Solbjerg",
    "sg:orig_category":"Kirker",
    "sg:postcode":"8355",
    "sg:province":"Danmark",
    "wof:name":"Hvilsted Kirke",
    "wof:placetype":"venue"
},
  "geometry": {"coordinates":[10.0556917191,56.007068634],"type":"Point"}
}