{
  "type": "Feature",
  "properties": {
    "addr:full":"Fan\u00f8 Bibliotek, Niels Engersvej 5 A, Nordby Fan\u00f8 Danmark 6720",
    "addr:housenumber":"5 a",
    "addr:postcode":"6720",
    "addr:street":"Niels Engersvej",
    "iso:country":"DK",
    "sg:address":"Fan\u00f8 Bibliotek, Niels Engersvej 5 A, Nordby",
    "sg:city":"Fan\u00f8",
    "sg:orig_category":"Kulturelle foreninger",
    "sg:phone":"+45 75 16 22 30",
    "sg:postcode":"6720",
    "sg:province":"Danmark",
    "wof:name":"Kulturelt Samr\u00e5d Sekretariat",
    "wof:placetype":"venue"
},
  "geometry": {"coordinates":[8.4069461823,55.4484786987],"type":"Point"}
}