{
  "type": "Feature",
  "properties": {
    "iso:country":"DK",
    "sg:address":"Graabjergvej 10",
    "sg:city":"Ryslinge",
    "sg:orig_category":"Kommunale folkeskoler",
    "sg:phone":"+45 62 67 13 96",
    "sg:postcode":"5856",
    "sg:province":"Danmark",
    "wof:name":"Ryslinge Sogneskole",
    "wof:placetype":"venue"
},
  "geometry": {"coordinates":[10.5312480927,55.2310256958],"type":"Point"}
}