{
  "type": "Feature",
  "properties": {
    "addr:full":"Brogade 17 Bjerringbro Danmark 8850",
    "addr:housenumber":"17",
    "addr:postcode":"8850",
    "addr:street":"Brogade",
    "iso:country":"DK",
    "sg:address":"Brogade 17",
    "sg:city":"Bjerringbro",
    "sg:orig_category":"Malermestre",
    "sg:phone":"+45 86 68 11 29",
    "sg:postcode":"8850",
    "sg:province":"Danmark",
    "wof:name":"Bjerringbro Malerforretning",
    "wof:placetype":"venue"
},
  "geometry": {"coordinates":[9.6581344604,56.3724822998],"type":"Point"}
}