{
  "type": "Feature",
  "properties": {
    "iso:country":"DK",
    "sg:address":"Hvidovre Stationscenter 30",
    "sg:city":"Hvidovre",
    "sg:orig_category":"Bagere",
    "sg:phone":"+45 36 75 48 20",
    "sg:postcode":"2650",
    "sg:province":"Danmark",
    "wof:name":"Centerbageren",
    "wof:placetype":"venue"
},
  "geometry": {"coordinates":[12.494396,55.625149],"type":"Point"}
}