{
  "type": "Feature",
  "properties": {
    "addr:full":"Torvet 9 Silkeborg Danmark 8600",
    "addr:housenumber":"9",
    "addr:postcode":"8600",
    "addr:street":"Torvet",
    "iso:country":"DK",
    "sg:address":"Torvet 9",
    "sg:city":"Silkeborg",
    "sg:classifiers":[
        {
            "category":"Communications",
            "type":"Services"
        }
    ],
    "sg:phone":"+45 86 81 44 55",
    "sg:postcode":"8600",
    "sg:province":"Danmark",
    "sg:tags":[
        "og",
        "tv",
        "radio"
    ],
    "wof:name":"D:E:R",
    "wof:placetype":"venue"
},
  "geometry": {"coordinates":[9.5524425507,56.1693305969],"type":"Point"}
}