{
  "type": "Feature",
  "properties": {
    "addr:full":"\u00d8stergade 6 Hammel Danmark 8450",
    "addr:housenumber":"6",
    "addr:postcode":"8450",
    "addr:street":"Ostergade",
    "iso:country":"DK",
    "sg:address":"\u00d8stergade 6",
    "sg:city":"Hammel",
    "sg:orig_category":"Optikere",
    "sg:phone":"+45 86 96 90 79",
    "sg:postcode":"8450",
    "sg:province":"Danmark",
    "sg:website":"www.nielsen-optik.dk",
    "wof:name":"Nielsen Optik",
    "wof:placetype":"venue"
},
  "geometry": {"coordinates":[9.865571022,56.2561340332],"type":"Point"}
}