{
  "type": "Feature",
  "properties": {
    "addr:full":"Gert Blume, Februarv\u00e6nget 42, Bramdrupdam Kolding Danmark 6000",
    "addr:housenumber":"42",
    "addr:postcode":"6000",
    "addr:street":"Bramdrupdam",
    "iso:country":"DK",
    "sg:address":"Gert Blume, Februarv\u00e6nget 42, Bramdrupdam",
    "sg:city":"Kolding",
    "sg:orig_category":"Fotografer",
    "sg:phone":"+45 75 51 83 45",
    "sg:postcode":"6000",
    "sg:province":"Danmark",
    "wof:name":"Free-Lance Foto",
    "wof:placetype":"venue"
},
  "geometry": {"coordinates":[9.4733953476,55.4863586426],"type":"Point"}
}