{
  "type": "Feature",
  "properties": {
    "iso:country":"DK",
    "sg:address":"Fmd.: Robin Jakobsen, D\u00f8llefjeldevej 3",
    "sg:city":"Saksk\u00f8bing",
    "sg:orig_category":"Hobbybetonede foreninger",
    "sg:phone":"+45 54 86 42 64",
    "sg:postcode":"4990",
    "sg:province":"Danmark",
    "wof:name":"Brydebjerg Skole Skak",
    "wof:placetype":"venue"
},
  "geometry": {"coordinates":[-114.0767440796,46.4432487488],"type":"Point"}
}