{
  "type": "Feature",
  "properties": {
    "addr:full":"Fmd.: Bjarne Ringgaard Jensen, Resedavej 1, st. th. Silkeborg Danmark 8600",
    "addr:housenumber":"1;th.",
    "addr:postcode":"8600",
    "addr:street":"Resedavej",
    "iso:country":"DK",
    "sg:address":"Fmd.: Bjarne Ringgaard Jensen, Resedavej 1, st. th.",
    "sg:city":"Silkeborg",
    "sg:orig_category":"Hobbybetonede foreninger",
    "sg:phone":"+45 86 81 57 79",
    "sg:postcode":"8600",
    "sg:province":"Danmark",
    "sg:website":"www.thinggaard.homepage.dk",
    "wof:name":"Fodslaw Silkeborg",
    "wof:placetype":"venue"
},
  "geometry": {"coordinates":[9.5524425507,56.1693305969],"type":"Point"}
}