{
  "type": "Feature",
  "properties": {
    "addr:full":"R\u00e5dhuspladsen 5 \u00c5rhus C Danmark 8000",
    "addr:housenumber":"5",
    "addr:postcode":"8000",
    "addr:street":"Raadhuspladsen",
    "iso:country":"DK",
    "sg:address":"R\u00e5dhuspladsen 5",
    "sg:city":"\u00c5rhus C",
    "sg:orig_category":"El-artikler",
    "sg:phone":"+45 86 12 02 12",
    "sg:postcode":"8000",
    "sg:province":"Danmark",
    "sg:website":"www.lysmesteren.dk",
    "wof:name":"Westh, Lysmesteren",
    "wof:placetype":"venue"
},
  "geometry": {"coordinates":[4.717400074,49.7588005066],"type":"Point"}
}