{
  "type": "Feature",
  "properties": {
    "addr:full":"Fmd.: Birte S\u00f8nderskov, B\u00f8geskovvejen 11, Nebsager Hornsyld Danmark 8783",
    "addr:housenumber":"11",
    "addr:postcode":"8783",
    "addr:street":"Bogeskovvejen",
    "iso:country":"DK",
    "sg:address":"Fmd.: Birte S\u00f8nderskov, B\u00f8geskovvejen 11, Nebsager",
    "sg:city":"Hornsyld",
    "sg:orig_category":"Husflidsforeninger",
    "sg:phone":"+45 75 68 72 97",
    "sg:postcode":"8783",
    "sg:province":"Danmark",
    "wof:name":"Hornsyld-Bjerre-Br\u00e5skov Husholdningsforening",
    "wof:placetype":"venue"
},
  "geometry": {"coordinates":[9.8611288071,55.7560806274],"type":"Point"}
}