{
  "type": "Feature",
  "properties": {
    "addr:full":"Klosterplads 11 Svendborg Danmark 5700",
    "addr:housenumber":"11",
    "addr:postcode":"5700",
    "addr:street":"Klosterplads",
    "iso:country":"DK",
    "sg:address":"Klosterplads 11",
    "sg:city":"Svendborg",
    "sg:orig_category":"Offentlige kontorer",
    "sg:phone":"+45 65 43 32 00",
    "sg:postcode":"5700",
    "sg:province":"Danmark",
    "wof:name":"Post Danmark, Svendborg Postkontor",
    "wof:placetype":"venue"
},
  "geometry": {"coordinates":[10.6120862961,55.0598106384],"type":"Point"}
}