{
  "type": "Feature",
  "properties": {
    "addr:full":"Vestergade 7 Grindsted Danmark 7200",
    "addr:housenumber":"7",
    "addr:postcode":"7200",
    "addr:street":"Vestergade",
    "iso:country":"DK",
    "sg:address":"Vestergade 7",
    "sg:city":"Grindsted",
    "sg:classifiers":[
        {
            "category":"Banks & Credit Unions",
            "subcategory":"Bank",
            "type":"Services"
        }
    ],
    "sg:phone":"+45 76 72 62 20",
    "sg:postcode":"7200",
    "sg:province":"Danmark",
    "sg:tags":[
        "banker"
    ],
    "sg:website":"www.danskebank.dk",
    "wof:name":"Danske Bank",
    "wof:placetype":"venue"
},
  "geometry": {"coordinates":[8.926155,55.757458],"type":"Point"}
}