{
  "type": "Feature",
  "properties": {
    "addr:full":"Emdrup Banke 162 K\u00f8benhavn \u00d8 Danmark 2100",
    "addr:housenumber":"162",
    "addr:postcode":"2100",
    "addr:street":"Emdrup Banke;O",
    "iso:country":"DK",
    "sg:address":"Emdrup Banke 162",
    "sg:city":"K\u00f8benhavn \u00d8",
    "sg:orig_category":"Vinduespolering",
    "sg:phone":"+45 23 23 49 35",
    "sg:postcode":"2100",
    "sg:province":"Danmark",
    "sg:website":"www.roeds.dk",
    "wof:name":"Roed Vinduespolering",
    "wof:placetype":"venue"
},
  "geometry": {"coordinates":[12.5500001907,55.7167015076],"type":"Point"}
}