{
  "type": "Feature",
  "properties": {
    "addr:full":"Rosenvej 16 Vemmelev Danmark 4241",
    "addr:housenumber":"16",
    "addr:postcode":"4241",
    "addr:street":"Rosenvej",
    "iso:country":"DK",
    "sg:address":"Rosenvej 16",
    "sg:city":"Vemmelev",
    "sg:orig_category":"Kinesiologi",
    "sg:phone":"+45 58 38 33 07",
    "sg:postcode":"4241",
    "sg:province":"Danmark",
    "wof:name":"Pluto, Klinik",
    "wof:placetype":"venue"
},
  "geometry": {"coordinates":[11.2647075653,55.365070343],"type":"Point"}
}