{
  "type": "Feature",
  "properties": {
    "addr:full":"Nordbakken 2  Ringe Danmark 5750",
    "addr:housenumber":"2",
    "addr:postcode":"5750",
    "addr:street":"Nordbakken",
    "iso:country":"DK",
    "sg:address":"Nordbakken 2 ",
    "sg:city":"Ringe",
    "sg:classifiers":[
        {
            "category":"Food & Beverages",
            "subcategory":"Dairy",
            "type":"Retail Goods"
        }
    ],
    "sg:phone":"+45 63 62 05 20",
    "sg:postcode":"5750",
    "sg:province":"Danmark",
    "sg:tags":[
        "product"
    ],
    "wof:name":"LACTOSAN A/S",
    "wof:placetype":"venue"
},
  "geometry": {"coordinates":[10.4815273285,55.2504997253],"type":"Point"}
}