{
  "type": "Feature",
  "properties": {
    "iso:country":"DK",
    "sg:address":"R\u00f8dovre Centrum 159",
    "sg:city":"R\u00f8dovre",
    "sg:classifiers":[
        {
            "category":"Banks & Credit Unions",
            "subcategory":"Bank",
            "type":"Services"
        }
    ],
    "sg:phone":"+45 36 73 75 50",
    "sg:postcode":"2610",
    "sg:province":"Danmark",
    "sg:tags":[
        "banker"
    ],
    "wof:name":"BG Bank",
    "wof:placetype":"venue"
},
  "geometry": {"coordinates":[10.699214,61.102776],"type":"Point"}
}