{
  "type": "Feature",
  "properties": {
    "iso:country":"DK",
    "sg:address":"Petersmindevej 14",
    "sg:city":"Kolding",
    "sg:orig_category":"Maskinfabrikker",
    "sg:phone":"+45 75 51 97 20",
    "sg:postcode":"6000",
    "sg:province":"Danmark",
    "wof:name":"Rool Maskinfabrik",
    "wof:placetype":"venue"
},
  "geometry": {"coordinates":[9.4861402512,55.5329704285],"type":"Point"}
}