{
  "type": "Feature",
  "properties": {
    "addr:full":"Svalevej 42 Kolding Danmark 6000",
    "addr:housenumber":"42",
    "addr:postcode":"6000",
    "addr:street":"Svalevej",
    "iso:country":"DK",
    "sg:address":"Svalevej 42",
    "sg:city":"Kolding",
    "sg:orig_category":"Skorstene",
    "sg:phone":"+45 75 52 38 85",
    "sg:postcode":"6000",
    "sg:province":"Danmark",
    "wof:name":"Villa & Ejendomsservice",
    "wof:placetype":"venue"
},
  "geometry": {"coordinates":[9.4736347198,55.5021476746],"type":"Point"}
}