{
  "type": "Feature",
  "properties": {
    "addr:full":"\u00d8lstvadbrovej 20 Randers Danmark 8900",
    "addr:housenumber":"20",
    "addr:postcode":"8900",
    "addr:street":"Olstvadbrovej",
    "iso:country":"DK",
    "sg:address":"\u00d8lstvadbrovej 20",
    "sg:city":"Randers",
    "sg:orig_category":"Kirker",
    "sg:postcode":"8900",
    "sg:province":"Danmark",
    "wof:name":"\u00d8lst Kirke",
    "wof:placetype":"venue"
},
  "geometry": {"coordinates":[10.0357952118,56.4593734741],"type":"Point"}
}