{
  "type": "Feature",
  "properties": {
    "iso:country":"DK",
    "sg:address":"Spobjergvej 5",
    "sg:city":"Brabrand",
    "sg:orig_category":"Brugsforeninger",
    "sg:phone":"+45 86 24 09 82",
    "sg:postcode":"8220",
    "sg:province":"Danmark",
    "wof:name":"Lokal Brugsen",
    "wof:placetype":"venue"
},
  "geometry": {"coordinates":[10.1172103882,56.1676712036],"type":"Point"}
}