{
  "type": "Feature",
  "properties": {
    "addr:full":"Vandv\u00e6rksvej 3 Ulfborg Danmark 6990",
    "addr:housenumber":"3",
    "addr:postcode":"6990",
    "addr:street":"Vandvaerksvej",
    "iso:country":"DK",
    "sg:address":"Vandv\u00e6rksvej 3",
    "sg:city":"Ulfborg",
    "sg:orig_category":"Keramik",
    "sg:phone":"+45 97 49 09 02",
    "sg:postcode":"6990",
    "sg:province":"Danmark",
    "wof:name":"Ulfborg Pottemageri",
    "wof:placetype":"venue"
},
  "geometry": {"coordinates":[8.3180532455,56.2713813782],"type":"Point"}
}