{
  "type": "Feature",
  "properties": {
    "addr:full":"N\u00f8rre Alle 26-28 Assens Danmark 5610",
    "addr:postcode":"26-28;5610",
    "addr:street":"Norre Alle",
    "iso:country":"DK",
    "sg:address":"N\u00f8rre Alle 26-28",
    "sg:city":"Assens",
    "sg:orig_category":"Armyvarer",
    "sg:phone":"+45 64 71 15 05",
    "sg:postcode":"5610",
    "sg:province":"Danmark",
    "wof:name":"Army-Varer",
    "wof:placetype":"venue"
},
  "geometry": {"coordinates":[9.9114074707,55.275894165],"type":"Point"}
}