{
  "type": "Feature",
  "properties": {
    "iso:country":"DK",
    "sg:address":"Sognevejen 213, Knudstrup",
    "sg:city":"Aalestrup",
    "sg:orig_category":"Maskinstationer",
    "sg:phone":"+45 98 64 55 22",
    "sg:postcode":"9620",
    "sg:province":"Danmark",
    "wof:name":"Vesterb\u00f8lle Maskinstation",
    "wof:placetype":"venue"
},
  "geometry": {"coordinates":[9.4901504517,56.6938285828],"type":"Point"}
}