{
  "type": "Feature",
  "properties": {
    "addr:full":"Brol\u00e6ggervej 2 Thisted Danmark 7700",
    "addr:housenumber":"2",
    "addr:postcode":"7700",
    "addr:street":"Brolaeggervej",
    "iso:country":"DK",
    "sg:address":"Brol\u00e6ggervej 2",
    "sg:city":"Thisted",
    "sg:orig_category":"Stenhuggere",
    "sg:phone":"+45 97 92 00 94",
    "sg:postcode":"7700",
    "sg:province":"Danmark",
    "wof:name":"Stenhuggeren Thisted ApS",
    "wof:placetype":"venue"
},
  "geometry": {"coordinates":[8.6453447342,56.938331604],"type":"Point"}
}