{
  "type": "Feature",
  "properties": {
    "addr:full":"Fmd.: Ivan Gudmandsen, Overdrevsvej 12 Hundested Danmark 3390",
    "addr:housenumber":"12",
    "addr:postcode":"3390",
    "addr:street":"Overdrevsvej",
    "iso:country":"DK",
    "sg:address":"Fmd.: Ivan Gudmandsen, Overdrevsvej 12",
    "sg:city":"Hundested",
    "sg:orig_category":"Hobbybetonede foreninger",
    "sg:phone":"+45 47 93 97 38",
    "sg:postcode":"3390",
    "sg:province":"Danmark",
    "wof:name":"Dansk Amat\u00f8rfiskerforening, Hundested afd.",
    "wof:placetype":"venue"
},
  "geometry": {"coordinates":[11.8530349731,55.958530426],"type":"Point"}
}