{
  "type": "Feature",
  "properties": {
    "iso:country":"DK",
    "sg:address":"Fmd.: Irma Vestergaard, Lundvej 42, B\u00f8vling",
    "sg:city":"B\u00f8vlingbjerg",
    "sg:orig_category":"Spejderkorps",
    "sg:phone":"+45 97 88 54 18",
    "sg:postcode":"7650",
    "sg:province":"Danmark",
    "wof:name":"FDF B\u00f8vling",
    "wof:placetype":"venue"
},
  "geometry": {"coordinates":[-89.66645050050001,45.351688385],"type":"Point"}
}