{
  "type": "Feature",
  "properties": {
    "addr:full":"Ladeg\u00e5rdsgade 6 Aalborg Danmark 9000",
    "addr:housenumber":"6",
    "addr:postcode":"9000",
    "addr:street":"Ladegaardsgade",
    "iso:country":"DK",
    "sg:address":"Ladeg\u00e5rdsgade 6",
    "sg:city":"Aalborg",
    "sg:orig_category":"Gallerier",
    "sg:phone":"+45 98 12 18 88",
    "sg:postcode":"9000",
    "sg:province":"Danmark",
    "wof:name":"Inuit, Galleri",
    "wof:placetype":"venue"
},
  "geometry": {"coordinates":[9.9146566391,57.0480766296],"type":"Point"}
}