{
  "type": "Feature",
  "properties": {
    "addr:full":"\u00c5sen 7, Postboks 25 Kirke Hvals\u00f8 Danmark 4330",
    "addr:housenumber":"7;25",
    "addr:postcode":"4330",
    "addr:street":"Aasen;Kirke Hvalso Danmark",
    "iso:country":"DK",
    "sg:address":"\u00c5sen 7, Postboks 25",
    "sg:city":"Kirke Hvals\u00f8",
    "sg:orig_category":"Skilte",
    "sg:phone":"+45 46 40 77 17",
    "sg:postcode":"4330",
    "sg:province":"Danmark",
    "sg:website":"www.agentskilte.dk",
    "wof:name":"Agent Skilte",
    "wof:placetype":"venue"
},
  "geometry": {"coordinates":[-14.4455499649,14.4994497299],"type":"Point"}
}