{
  "type": "Feature",
  "properties": {
    "addr:full":"Valby Langgade 96 Valby Danmark 2500",
    "addr:housenumber":"96",
    "addr:postcode":"2500",
    "addr:street":"Valby Langgade",
    "iso:country":"DK",
    "sg:address":"Valby Langgade 96",
    "sg:city":"Valby",
    "sg:orig_category":"Kiosker",
    "sg:phone":"+45 36 46 03 02",
    "sg:postcode":"2500",
    "sg:province":"Danmark",
    "wof:name":"Pedersen, Flemming",
    "wof:placetype":"venue"
},
  "geometry": {"coordinates":[12.5087242126,55.6660003662],"type":"Point"}
}