{
  "type": "Feature",
  "properties": {
    "addr:full":"Skolegade 43 Helsinge Danmark 3200",
    "addr:housenumber":"43",
    "addr:postcode":"3200",
    "addr:street":"Skolegade",
    "iso:country":"DK",
    "sg:address":"Skolegade 43",
    "sg:city":"Helsinge",
    "sg:orig_category":"Legestuer",
    "sg:phone":"+45 48 79 78 14",
    "sg:postcode":"3200",
    "sg:province":"Danmark",
    "wof:name":"Tumlingerne Legestue",
    "wof:placetype":"venue"
},
  "geometry": {"coordinates":[12.1922855377,56.0266647339],"type":"Point"}
}