{
  "type": "Feature",
  "properties": {
    "addr:full":"Hovedgaden 46 Billund Danmark 7190",
    "addr:housenumber":"46",
    "addr:postcode":"7190",
    "addr:street":"Hovedgaden",
    "iso:country":"DK",
    "sg:address":"Hovedgaden 46",
    "sg:city":"Billund",
    "sg:orig_category":"Godstransport",
    "sg:phone":"+45 75 33 12 11",
    "sg:postcode":"7190",
    "sg:province":"Danmark",
    "wof:name":"Thomsen ApS, Villy",
    "wof:placetype":"venue"
},
  "geometry": {"coordinates":[9.1090240479,55.7339324951],"type":"Point"}
}