{
  "type": "Feature",
  "properties": {
    "addr:full":"Vestervangsvej 14 Viborg Danmark 8800",
    "addr:housenumber":"14",
    "addr:postcode":"8800",
    "addr:street":"Vestervangsvej",
    "iso:country":"DK",
    "sg:address":"Vestervangsvej 14",
    "sg:city":"Viborg",
    "sg:classifiers":[
        {
            "category":"Banks & Credit Unions",
            "subcategory":"Bank",
            "type":"Services"
        }
    ],
    "sg:phone":"+45 86 62 65 00",
    "sg:postcode":"8800",
    "sg:province":"Danmark",
    "sg:tags":[
        "banker"
    ],
    "wof:name":"Nordea",
    "wof:placetype":"venue"
},
  "geometry": {"coordinates":[9.395319,56.461456],"type":"Point"}
}