{
  "type": "Feature",
  "properties": {
    "addr:full":"H\u00f8jby Rosenvej 10 H\u00f8jby Danmark 4573",
    "addr:housenumber":"10",
    "addr:postcode":"4573",
    "addr:street":"Hojby Rosenvej",
    "iso:country":"DK",
    "sg:address":"H\u00f8jby Rosenvej 10",
    "sg:city":"H\u00f8jby",
    "sg:orig_category":"Psykologer, praktiserende",
    "sg:phone":"+45 59 30 35 25",
    "sg:postcode":"4573",
    "sg:province":"Danmark",
    "wof:name":"Akh\u00f8j, Karen",
    "wof:placetype":"venue"
},
  "geometry": {"coordinates":[11.5936431885,55.9089546204],"type":"Point"}
}