{
  "type": "Feature",
  "properties": {
    "addr:full":"M\u00f8rupvej 23 Herning Danmark 7400",
    "addr:housenumber":"23",
    "addr:postcode":"7400",
    "addr:street":"Morupvej",
    "iso:country":"DK",
    "sg:address":"M\u00f8rupvej 23",
    "sg:city":"Herning",
    "sg:orig_category":"Teglelementer",
    "sg:phone":"+45 97 12 56 55",
    "sg:postcode":"7400",
    "sg:province":"Danmark",
    "wof:name":"SHT A/S",
    "wof:placetype":"venue"
},
  "geometry": {"coordinates":[8.9434757233,56.1265945435],"type":"Point"}
}