{
  "type": "Feature",
  "properties": {
    "addr:full":"Jomfrustien 23 Haderslev Danmark 6100",
    "addr:housenumber":"23",
    "addr:postcode":"6100",
    "addr:street":"Jomfrustien",
    "iso:country":"DK",
    "sg:address":"Jomfrustien 23",
    "sg:city":"Haderslev",
    "sg:orig_category":"Trailere",
    "sg:phone":"+45 74 52 55 94",
    "sg:postcode":"6100",
    "sg:province":"Danmark",
    "wof:name":"Skov's autov\u00e6rksted",
    "wof:placetype":"venue"
},
  "geometry": {"coordinates":[9.4926567078,55.251159668],"type":"Point"}
}