{
  "type": "Feature",
  "properties": {
    "addr:full":"Stokkildhovedvej 7, Kollund Herning Danmark 7400",
    "addr:housenumber":"7",
    "addr:postcode":"7400",
    "addr:street":"Stokkildhovedvej;Kollund",
    "iso:country":"DK",
    "sg:address":"Stokkildhovedvej 7, Kollund",
    "sg:city":"Herning",
    "sg:orig_category":"Hobbybetonede foreninger",
    "sg:phone":"+45 97 22 36 03",
    "sg:postcode":"7400",
    "sg:province":"Danmark",
    "wof:name":"Herning Strandjagtforening",
    "wof:placetype":"venue"
},
  "geometry": {"coordinates":[8.9768896103,56.1374168396],"type":"Point"}
}