{
  "type": "Feature",
  "properties": {
    "addr:full":"Solbakken 56 Holte Danmark 2840",
    "addr:housenumber":"56",
    "addr:postcode":"2840",
    "addr:street":"Solbakken",
    "iso:country":"DK",
    "sg:address":"Solbakken 56",
    "sg:city":"Holte",
    "sg:orig_category":"Kirker",
    "sg:postcode":"2840",
    "sg:province":"Danmark",
    "wof:name":"Ny Holte Kirke",
    "wof:placetype":"venue"
},
  "geometry": {"coordinates":[12.4632892609,55.8201217651],"type":"Point"}
}