{
  "type": "Feature",
  "properties": {
    "addr:full":"Huslodsvej 8 Fredericia Danmark 7000",
    "addr:housenumber":"8",
    "addr:postcode":"7000",
    "addr:street":"Huslodsvej",
    "iso:country":"DK",
    "sg:address":"Huslodsvej 8",
    "sg:city":"Fredericia",
    "sg:orig_category":"Vinduespolering",
    "sg:phone":"+45 75 92 66 44",
    "sg:postcode":"7000",
    "sg:province":"Danmark",
    "wof:name":"Nielsen, Vagn",
    "wof:placetype":"venue"
},
  "geometry": {"coordinates":[9.7545623779,55.5735931396],"type":"Point"}
}