{
  "type": "Feature",
  "properties": {
    "addr:full":"Bj\u00e6lkerupvej 35 Store Heddinge Danmark 4660",
    "addr:housenumber":"35",
    "addr:postcode":"4660",
    "addr:street":"Bjaelkerupvej",
    "iso:country":"DK",
    "sg:address":"Bj\u00e6lkerupvej 35",
    "sg:city":"Store Heddinge",
    "sg:orig_category":"Vaskerier",
    "sg:phone":"+45 56 50 24 80",
    "sg:postcode":"4660",
    "sg:province":"Danmark",
    "wof:name":"St. Heddinge Dampvaskeri A/S",
    "wof:placetype":"venue"
},
  "geometry": {"coordinates":[12.382979393,55.3176345825],"type":"Point"}
}