{
  "type": "Feature",
  "properties": {
    "addr:full":"Borrelyngvej 30 Allinge Danmark 3770",
    "addr:housenumber":"30",
    "addr:postcode":"3770",
    "addr:street":"Borrelyngvej",
    "iso:country":"DK",
    "sg:address":"Borrelyngvej 30",
    "sg:city":"Allinge",
    "sg:orig_category":"Ridning",
    "sg:phone":"+45 56 48 09 68",
    "sg:postcode":"3770",
    "sg:province":"Danmark",
    "sg:website":"www.sic-bornholm.dk",
    "wof:name":"Slotslyngens Islands Center",
    "wof:placetype":"venue"
},
  "geometry": {"coordinates":[14.7848939896,55.2665328979],"type":"Point"}
}