{
  "type": "Feature",
  "properties": {
    "iso:country":"DK",
    "sg:address":"Tvingsbakken 46, Annisse",
    "sg:city":"Helsinge",
    "sg:orig_category":"Reklamebureauer",
    "sg:phone":"+45 48 79 69 35",
    "sg:postcode":"3200",
    "sg:province":"Danmark",
    "wof:name":"Smith Reklame ApS, Henrik",
    "wof:placetype":"venue"
},
  "geometry": {"coordinates":[12.196846962,56.0224456787],"type":"Point"}
}