{
  "type": "Feature",
  "properties": {
    "addr:full":"Vp-Arkaden 8 og 9 Helsinge Danmark 3200",
    "addr:housenumber":"8 og 9",
    "addr:postcode":"3200",
    "addr:street":"Vp-Arkaden",
    "iso:country":"DK",
    "sg:address":"Vp-Arkaden 8 og 9",
    "sg:city":"Helsinge",
    "sg:orig_category":"Materialister",
    "sg:phone":"+45 48 79 62 55",
    "sg:postcode":"3200",
    "sg:province":"Danmark",
    "wof:name":"Matas",
    "wof:placetype":"venue"
},
  "geometry": {"coordinates":[12.196846962,56.0224456787],"type":"Point"}
}