{
  "type": "Feature",
  "properties": {
    "addr:full":"Appevej 70, M\u00f8llebj Hus Tommerup Danmark 5690",
    "addr:housenumber":"70",
    "addr:postcode":"5690",
    "addr:street":"Appevej",
    "iso:country":"DK",
    "sg:address":"Appevej 70, M\u00f8llebj Hus",
    "sg:city":"Tommerup",
    "sg:orig_category":"Hundetrimning",
    "sg:phone":"+45 64 76 14 09",
    "sg:postcode":"5690",
    "sg:province":"Danmark",
    "sg:website":"www.odense-hundesalon.dk",
    "wof:name":"Odense Hundesalon",
    "wof:placetype":"venue"
},
  "geometry": {"coordinates":[10.2489509583,55.3236503601],"type":"Point"}
}