{
  "type": "Feature",
  "properties": {
    "addr:full":"Rosensgade 15 Odder Danmark 8300",
    "addr:housenumber":"15",
    "addr:postcode":"8300",
    "addr:street":"Rosensgade",
    "iso:country":"DK",
    "sg:address":"Rosensgade 15",
    "sg:city":"Odder",
    "sg:orig_category":"Dag- og distriktsblade",
    "sg:phone":"+45 86 54 10 11",
    "sg:postcode":"8300",
    "sg:province":"Danmark",
    "sg:website":"www.internetavisen.dk/odder",
    "wof:name":"Odder Avis",
    "wof:placetype":"venue"
},
  "geometry": {"coordinates":[10.148352623,55.9723815918],"type":"Point"}
}