{
  "type": "Feature",
  "properties": {
    "iso:country":"DK",
    "sg:address":"\u00d8stergade 66",
    "sg:city":"Idestrup",
    "sg:orig_category":"Afsyring",
    "sg:phone":"+45 54 14 86 23",
    "sg:postcode":"4872",
    "sg:province":"Danmark",
    "wof:name":"Jensen, Eigil",
    "wof:placetype":"venue"
},
  "geometry": {"coordinates":[11.9628038406,54.7412567139],"type":"Point"}
}