{
  "type": "Feature",
  "properties": {
    "addr:full":"Langeskov Centret 27 Langeskov Danmark 5550",
    "addr:housenumber":"27",
    "addr:postcode":"5550",
    "addr:street":"Langeskov Centret",
    "iso:country":"DK",
    "sg:address":"Langeskov Centret 27",
    "sg:city":"Langeskov",
    "sg:orig_category":"Posthuse",
    "sg:phone":"+45 63 21 68 68",
    "sg:postcode":"5550",
    "sg:province":"Danmark",
    "wof:name":"Post Danmark, Langeskov Posthus",
    "wof:placetype":"venue"
},
  "geometry": {"coordinates":[10.5898895264,55.3605804443],"type":"Point"}
}