{
  "type": "Feature",
  "properties": {
    "iso:country":"DK",
    "sg:address":"Carit Etlars Vej 3",
    "sg:city":"Frederiksberg",
    "sg:orig_category":"Rejsebureauer",
    "sg:phone":"+45 33 31 71 77",
    "sg:postcode":"1814",
    "sg:province":"Danmark",
    "wof:name":"Robinson Scandinavia A/S",
    "wof:placetype":"venue"
},
  "geometry": {"coordinates":[12.5416288376,55.6734237671],"type":"Point"}
}