{
  "type": "Feature",
  "properties": {
    "iso:country":"DK",
    "sg:address":"Slotsbakken 1",
    "sg:city":"Gr\u00e5sten",
    "sg:orig_category":"Kirker",
    "sg:postcode":"6300",
    "sg:province":"Danmark",
    "wof:name":"Gr\u00e5sten Slotskirke",
    "wof:placetype":"venue"
},
  "geometry": {"coordinates":[25.3302497864,60.2151107788],"type":"Point"}
}