{
  "type": "Feature",
  "properties": {
    "iso:country":"DK",
    "sg:address":"\u00c5dalsparken 9",
    "sg:city":"Esbjerg V",
    "sg:orig_category":"Reproanstalter",
    "sg:phone":"+45 75 15 55 33",
    "sg:postcode":"6710",
    "sg:province":"Danmark",
    "sg:website":"www.tecnocolor.dk",
    "wof:name":"Tecno-Color A/S",
    "wof:placetype":"venue"
},
  "geometry": {"coordinates":[8.403345108,55.505027771],"type":"Point"}
}