{
  "type": "Feature",
  "properties": {
    "addr:full":"Kingosvej 2, Frederiks Karup Danmark 7470",
    "addr:housenumber":"2",
    "addr:postcode":"7470",
    "addr:street":"Kingosvej;Frederiks Karup Danmark",
    "iso:country":"DK",
    "sg:address":"Kingosvej 2, Frederiks",
    "sg:city":"Karup",
    "sg:orig_category":"Murermestre",
    "sg:phone":"+45 86 66 13 74",
    "sg:postcode":"7470",
    "sg:province":"Danmark",
    "wof:name":"D\u00fcrr, Poul Erik",
    "wof:placetype":"venue"
},
  "geometry": {"coordinates":[9.2525548935,56.3398017883],"type":"Point"}
}