{
  "type": "Feature",
  "properties": {
    "iso:country":"DK",
    "sg:address":"Pedersholmparken 4",
    "sg:city":"Frederikssund",
    "sg:orig_category":"Autoruder",
    "sg:phone":"+45 47 31 59 00",
    "sg:postcode":"3600",
    "sg:province":"Danmark",
    "wof:name":"S\u00f8ndergaard Biler ApS, S.",
    "wof:placetype":"venue"
},
  "geometry": {"coordinates":[12.091629982,55.8240013123],"type":"Point"}
}