{
  "type": "Feature",
  "properties": {
    "addr:full":"Skovskellet 21  Holte Danmark 2840",
    "addr:housenumber":"21",
    "addr:postcode":"2840",
    "addr:street":"Skovskellet",
    "iso:country":"DK",
    "sg:address":"Skovskellet 21 ",
    "sg:city":"Holte",
    "sg:classifiers":[
        {
            "category":"Shopping",
            "subcategory":"Clothing, Apparel, & Fashions",
            "type":"Retail Goods"
        }
    ],
    "sg:phone":"+45 35 26 85 85",
    "sg:postcode":"2840",
    "sg:province":"Danmark",
    "sg:tags":[
        "clothing",
        "accessory"
    ],
    "wof:name":"CREATIV TEXTIL COPENHAGEN APS",
    "wof:placetype":"venue"
},
  "geometry": {"coordinates":[12.4984054565,55.8094444275],"type":"Point"}
}