{
  "type": "Feature",
  "properties": {
    "iso:country":"DK",
    "sg:address":"Frederiksborgvej 17",
    "sg:city":"Helsinge",
    "sg:classifiers":[
        {
            "category":"Restaurant",
            "type":"Food & Drink"
        }
    ],
    "sg:phone":"+45 48 79 80 81",
    "sg:postcode":"3200",
    "sg:province":"Danmark",
    "wof:name":"Portofino",
    "wof:placetype":"venue"
},
  "geometry": {"coordinates":[12.1998529434,56.0209617615],"type":"Point"}
}