{
  "type": "Feature",
  "properties": {
    "addr:full":"Centervej 33, Postboks 88 Hanstholm Danmark 7730",
    "addr:housenumber":"33;88",
    "addr:postcode":"7730",
    "addr:street":"Centervej",
    "iso:country":"DK",
    "sg:address":"Centervej 33, Postboks 88",
    "sg:city":"Hanstholm",
    "sg:orig_category":"Boligselskaber",
    "sg:phone":"+45 97 96 25 94",
    "sg:postcode":"7730",
    "sg:province":"Danmark",
    "sg:website":"www.boligselskabet-hanstholm.dk",
    "wof:name":"Boligselskabet Hanstholm",
    "wof:placetype":"venue"
},
  "geometry": {"coordinates":[8.6066236496,57.115940094],"type":"Point"}
}