{
  "type": "Feature",
  "properties": {
    "iso:country":"DK",
    "sg:address":"Frisenvoldvej 3 B, Jebjerg",
    "sg:city":"Lang\u00e5",
    "sg:orig_category":"Kirker",
    "sg:postcode":"8870",
    "sg:province":"Danmark",
    "wof:name":"\u00d8rum Kirke",
    "wof:placetype":"venue"
},
  "geometry": {"coordinates":[9.8955049515,56.3900756836],"type":"Point"}
}