{
  "type": "Feature",
  "properties": {
    "iso:country":"DK",
    "sg:address":"Kirstensvej 1, Humlum",
    "sg:city":"Struer",
    "sg:classifiers":[
        {
            "category":"Banks & Credit Unions",
            "subcategory":"Bank",
            "type":"Services"
        }
    ],
    "sg:phone":"+45 97 86 11 66",
    "sg:postcode":"7600",
    "sg:province":"Danmark",
    "sg:tags":[
        "banker"
    ],
    "wof:name":"Hvidbjerg Bank",
    "wof:placetype":"venue"
},
  "geometry": {"coordinates":[8.5946903229,56.491191864],"type":"Point"}
}