{
  "type": "Feature",
  "properties": {
    "addr:full":"Hans Broges Gade 3 \u00c5rhus C Danmark 8000",
    "addr:housenumber":"3",
    "addr:postcode":"8000",
    "addr:street":"Hans Broges Gade",
    "iso:country":"DK",
    "sg:address":"Hans Broges Gade 3",
    "sg:city":"\u00c5rhus C",
    "sg:orig_category":"Fodplejere",
    "sg:phone":"+45 86 19 12 11",
    "sg:postcode":"8000",
    "sg:province":"Danmark",
    "wof:name":"Fodklinikken",
    "wof:placetype":"venue"
},
  "geometry": {"coordinates":[99.92501068120001,34.2430114746],"type":"Point"}
}