{
  "type": "Feature",
  "properties": {
    "iso:country":"DK",
    "sg:address":"Fmd.: Karl O. J\u00f8rgensen, Brendg\u00e5rdvej 5, Ydby",
    "sg:city":"Hurup",
    "sg:orig_category":"\u00c3\u2020ldreorganisationer og klubber",
    "sg:phone":"+45 97 95 61 80",
    "sg:postcode":"7760",
    "sg:province":"Danmark",
    "wof:name":"Ydby og Omegns Pensionistforening",
    "wof:placetype":"venue"
},
  "geometry": {"coordinates":[8.4233045578,56.7485847473],"type":"Point"}
}