{
  "type": "Feature",
  "properties": {
    "iso:country":"DK",
    "sg:address":"Kirkepladsen 10",
    "sg:city":"Haslev",
    "sg:orig_category":"Kirkesogne",
    "sg:phone":"+45 56 31 51 62",
    "sg:postcode":"4690",
    "sg:province":"Danmark",
    "wof:name":"Haslev og Frerslev sognes kordegnekontor",
    "wof:placetype":"venue"
},
  "geometry": {"coordinates":[11.9632501602,55.3233566284],"type":"Point"}
}