{
  "type": "Feature",
  "properties": {
    "iso:country":"DK",
    "sg:address":"Mullerup Hovvej 18",
    "sg:city":"Gudbjerg",
    "sg:orig_category":"Handicapboliger",
    "sg:phone":"+45 62 25 16 13",
    "sg:postcode":"5892",
    "sg:province":"Danmark",
    "wof:name":"Boinstitutionen Elleruphus",
    "wof:placetype":"venue"
},
  "geometry": {"coordinates":[10.65599823,55.1697006226],"type":"Point"}
}