{
  "type": "Feature",
  "properties": {
    "addr:full":"Savv\u00e6rksvej 2, Sj\u00f8rup Viborg Danmark 8800",
    "addr:housenumber":"2",
    "addr:postcode":"8800",
    "addr:street":"Savvaerksvej",
    "iso:country":"DK",
    "sg:address":"Savv\u00e6rksvej 2, Sj\u00f8rup",
    "sg:city":"Viborg",
    "sg:orig_category":"Landbrugsmaskiner",
    "sg:phone":"+45 97 54 83 00",
    "sg:postcode":"8800",
    "sg:province":"Danmark",
    "wof:name":"Sj\u00f8rup Traktor A/S",
    "wof:placetype":"venue"
},
  "geometry": {"coordinates":[9.4071502686,56.452671051],"type":"Point"}
}