{
  "type": "Feature",
  "properties": {
    "addr:full":"Thorsvej 13 A Kongens Lyngby Danmark 2800",
    "addr:housenumber":"13 a",
    "addr:postcode":"2800",
    "addr:street":"Thorsvej",
    "iso:country":"DK",
    "sg:address":"Thorsvej 13 A",
    "sg:city":"Kongens Lyngby",
    "sg:orig_category":"INGENI\u00c3\u02dcRER",
    "sg:phone":"+45 45 87 50 68",
    "sg:postcode":"2800",
    "sg:province":"Danmark",
    "wof:name":"HL Consult",
    "wof:placetype":"venue"
},
  "geometry": {"coordinates":[12.4947977066,55.7674369812],"type":"Point"}
}