{
  "type": "Feature",
  "properties": {
    "addr:full":"Flegmade 18 Vejle Danmark 7100",
    "addr:housenumber":"18",
    "addr:postcode":"7100",
    "addr:street":"Flegmade",
    "iso:country":"DK",
    "sg:address":"Flegmade 18",
    "sg:city":"Vejle",
    "sg:orig_category":"Autoforhandlere",
    "sg:phone":"+45 75 82 03 11",
    "sg:postcode":"7100",
    "sg:province":"Danmark",
    "wof:name":"Autohuset Vestergaard A/S",
    "wof:placetype":"venue"
},
  "geometry": {"coordinates":[9.5250444412,55.709903717],"type":"Point"}
}