{
  "type": "Feature",
  "properties": {
    "addr:full":"R\u00f8dvigvej 71 R\u00f8dvig Stevns Danmark 4673",
    "addr:housenumber":"71",
    "addr:postcode":"4673",
    "addr:street":"Rodvigvej",
    "iso:country":"DK",
    "sg:address":"R\u00f8dvigvej 71",
    "sg:city":"R\u00f8dvig Stevns",
    "sg:orig_category":"Skorstensfejere",
    "sg:phone":"+45 56 50 66 47",
    "sg:postcode":"4673",
    "sg:province":"Danmark",
    "wof:name":"Hansen, Leo Blicher",
    "wof:placetype":"venue"
},
  "geometry": {"coordinates":[12.3775653839,55.2558746338],"type":"Point"}
}