{
  "type": "Feature",
  "properties": {
    "iso:country":"DK",
    "sg:address":"N\u00f8rregade 10",
    "sg:city":"Dronninglund",
    "sg:orig_category":"Skomagere",
    "sg:phone":"+45 98 84 28 66",
    "sg:postcode":"9330",
    "sg:province":"Danmark",
    "wof:name":"Dahl, Tonny",
    "wof:placetype":"venue"
},
  "geometry": {"coordinates":[10.2895011902,57.1603088379],"type":"Point"}
}