{
  "type": "Feature",
  "properties": {
    "iso:country":"DK",
    "sg:address":"Vestergade 96",
    "sg:city":"Svendborg",
    "sg:orig_category":"Skilte",
    "sg:phone":"+45 62 22 47 40",
    "sg:postcode":"5700",
    "sg:province":"Danmark",
    "wof:name":"KA Skilte",
    "wof:placetype":"venue"
},
  "geometry": {"coordinates":[10.5922660828,55.0640106201],"type":"Point"}
}