{
  "type": "Feature",
  "properties": {
    "iso:country":"DK",
    "sg:address":"Bjerrevej 413, Klejs",
    "sg:city":"Juelsminde",
    "sg:orig_category":"Hunde",
    "sg:phone":"+45 75 68 54 31",
    "sg:postcode":"7130",
    "sg:province":"Danmark",
    "wof:name":"Kragborg Dressur og Pension",
    "wof:placetype":"venue"
},
  "geometry": {"coordinates":[10.0143985748,55.7135848999],"type":"Point"}
}