{
  "type": "Feature",
  "properties": {
    "addr:full":"Kongens Nytorv 21, 1. K\u00f8benhavn Danmark 1050",
    "addr:housenumber":"21 1",
    "addr:postcode":"1050",
    "addr:street":"Kongens Nytorv",
    "iso:country":"DK",
    "sg:address":"Kongens Nytorv 21, 1.",
    "sg:city":"K\u00f8benhavn",
    "sg:orig_category":"Rejsebureauer",
    "sg:phone":"+45 33 15 57 44",
    "sg:postcode":"1050",
    "sg:province":"Danmark",
    "sg:website":"www.travellife.dk",
    "wof:name":"Travel Life ApS",
    "wof:placetype":"venue"
},
  "geometry": {"coordinates":[12.5860204697,55.6806793213],"type":"Point"}
}