{
  "type": "Feature",
  "properties": {
    "addr:full":"Havnegade 17, Postboks 313 Vejle Danmark 7100",
    "addr:housenumber":"17;313",
    "addr:postcode":"7100",
    "addr:street":"Havnegade",
    "iso:country":"DK",
    "sg:address":"Havnegade 17, Postboks 313",
    "sg:city":"Vejle",
    "sg:orig_category":"Arkitekter",
    "sg:phone":"+45 70 27 88 55",
    "sg:postcode":"7100",
    "sg:province":"Danmark",
    "wof:name":"Tegnestuen PLAN",
    "wof:placetype":"venue"
},
  "geometry": {"coordinates":[9.5368051529,55.7113952637],"type":"Point"}
}