{
  "type": "Feature",
  "properties": {
    "iso:country":"DK",
    "sg:address":"Edwin Rahrs Vej 85",
    "sg:city":"Brabrand",
    "sg:orig_category":"Maskinfabrikker",
    "sg:phone":"+45 86 26 32 00",
    "sg:postcode":"8220",
    "sg:province":"Danmark",
    "sg:website":"www.richard-thomsen.dk",
    "wof:name":"Thomsen Maskinfabrik A/S, Richard",
    "wof:placetype":"venue"
},
  "geometry": {"coordinates":[10.102519989,56.1644248962],"type":"Point"}
}