{
  "type": "Feature",
  "properties": {
    "addr:full":"Islandsgade 12 Odense C Danmark 5000",
    "addr:housenumber":"12",
    "addr:postcode":"5000",
    "addr:street":"Islandsgade",
    "iso:country":"DK",
    "sg:address":"Islandsgade 12",
    "sg:city":"Odense C",
    "sg:orig_category":"Elektronik",
    "sg:phone":"+45 66 14 44 00",
    "sg:postcode":"5000",
    "sg:province":"Danmark",
    "wof:name":"TEXIT",
    "wof:placetype":"venue"
},
  "geometry": {"coordinates":[10.4046049118,55.4010353088],"type":"Point"}
}