{
  "type": "Feature",
  "properties": {
    "addr:full":"M\u00f8gelvej 20 Snedsted Danmark 7752",
    "addr:housenumber":"20",
    "addr:postcode":"7752",
    "addr:street":"Mogelvej",
    "iso:country":"DK",
    "sg:address":"M\u00f8gelvej 20",
    "sg:city":"Snedsted",
    "sg:orig_category":"Maskinstationer",
    "sg:phone":"+45 21 47 74 54",
    "sg:postcode":"7752",
    "sg:province":"Danmark",
    "wof:name":"Thy Wrap & Halmludning",
    "wof:placetype":"venue"
},
  "geometry": {"coordinates":[8.5852508545,56.8826332092],"type":"Point"}
}