{
  "type": "Feature",
  "properties": {
    "addr:full":"Sofus Francks V\u00e6nge 14 Frederiksberg Danmark 2000",
    "addr:housenumber":"14",
    "addr:postcode":"2000",
    "addr:street":"Sofus;Vaenge",
    "iso:country":"DK",
    "sg:address":"Sofus Francks V\u00e6nge 14",
    "sg:city":"Frederiksberg",
    "sg:orig_category":"Fritidshjem",
    "sg:phone":"+45 38 21 12 80",
    "sg:postcode":"2000",
    "sg:province":"Danmark",
    "wof:name":"Brohuset Fritidshjem",
    "wof:placetype":"venue"
},
  "geometry": {"coordinates":[12.5046157837,55.6715049744],"type":"Point"}
}