{
  "type": "Feature",
  "properties": {
    "addr:full":"Gerritsgade 40 Svendborg Danmark 5700",
    "addr:housenumber":"40",
    "addr:postcode":"5700",
    "addr:street":"Gerritsgade",
    "iso:country":"DK",
    "sg:address":"Gerritsgade 40",
    "sg:city":"Svendborg",
    "sg:orig_category":"Optikere",
    "sg:phone":"+45 62 21 13 20",
    "sg:postcode":"5700",
    "sg:province":"Danmark",
    "sg:website":"www.heiko-stumbeck.dk",
    "wof:name":"Stumbeck, Heikoo",
    "wof:placetype":"venue"
},
  "geometry": {"coordinates":[10.607216835,55.059009552],"type":"Point"}
}