{
  "type": "Feature",
  "properties": {
    "addr:full":"Tvedvej 200, Tved Svendborg Danmark 5700",
    "addr:housenumber":"200",
    "addr:postcode":"5700",
    "addr:street":"Tvedvej;Tved",
    "iso:country":"DK",
    "sg:address":"Tvedvej 200, Tved",
    "sg:city":"Svendborg",
    "sg:classifiers":[
        {
            "category":"Communications",
            "subcategory":"Film & Video Production",
            "type":"Services"
        }
    ],
    "sg:phone":"+45 62 21 28 47",
    "sg:postcode":"5700",
    "sg:province":"Danmark",
    "sg:tags":[
        "radio-",
        "og",
        "tv-service"
    ],
    "sg:website":"www.2tal.dk/svendborg",
    "wof:name":"TV Doktoren Salgs- og Service Center A/S",
    "wof:placetype":"venue"
},
  "geometry": {"coordinates":[10.6065101624,55.0595970154],"type":"Point"}
}