{
  "type": "Feature",
  "properties": {
    "addr:full":"Stationsvej 10 Vejby Danmark 3210",
    "addr:housenumber":"10",
    "addr:postcode":"3210",
    "addr:street":"Stationsvej",
    "iso:country":"DK",
    "sg:address":"Stationsvej 10",
    "sg:city":"Vejby",
    "sg:orig_category":"Solcentre",
    "sg:phone":"+45 48 70 56 67",
    "sg:postcode":"3210",
    "sg:province":"Danmark",
    "wof:name":"Vejby Solcenter",
    "wof:placetype":"venue"
},
  "geometry": {"coordinates":[12.138507843,56.0654258728],"type":"Point"}
}