{
  "type": "Feature",
  "properties": {
    "iso:country":"DK",
    "sg:address":"Foreningsbygningen, Rosenkrantzgade 6",
    "sg:city":"Thisted",
    "sg:orig_category":"Kirkelige foreninger",
    "sg:phone":"+45 97 92 07 28",
    "sg:postcode":"7700",
    "sg:province":"Danmark",
    "wof:name":"Thisted KFUM og KFUK",
    "wof:placetype":"venue"
},
  "geometry": {"coordinates":[8.6919784546,56.9556121826],"type":"Point"}
}