{
  "type": "Feature",
  "properties": {
    "addr:full":"Rughavevej 68 Viborg Danmark 8800",
    "addr:housenumber":"68",
    "addr:postcode":"8800",
    "addr:street":"Rughavevej",
    "iso:country":"DK",
    "sg:address":"Rughavevej 68",
    "sg:city":"Viborg",
    "sg:orig_category":"Dagcentre",
    "sg:phone":"+45 87 25 32 80",
    "sg:postcode":"8800",
    "sg:province":"Danmark",
    "wof:name":"St\u00f8ttecenter for sindslidende",
    "wof:placetype":"venue"
},
  "geometry": {"coordinates":[9.3835706711,56.4630661011],"type":"Point"}
}