{
  "type": "Feature",
  "properties": {
    "addr:full":"Kontakt: Henrik Hadberg, Solbakken 903 Munkebo Danmark 5330",
    "addr:housenumber":"903",
    "addr:postcode":"5330",
    "addr:street":"Henrik Hadberg Solbakken",
    "iso:country":"DK",
    "sg:address":"Kontakt: Henrik Hadberg, Solbakken 903",
    "sg:city":"Munkebo",
    "sg:orig_category":"Kirkelige foreninger",
    "sg:phone":"+45 65 97 61 12",
    "sg:postcode":"5330",
    "sg:province":"Danmark",
    "sg:website":"www.dlm.dk",
    "wof:name":"Luthersk Missionsforening Nord\u00f8stfyn",
    "wof:placetype":"venue"
},
  "geometry": {"coordinates":[10.5594701767,55.4595069885],"type":"Point"}
}