{
  "type": "Feature",
  "properties": {
    "addr:full":"Odinsvej 5 Grindsted Danmark 7200",
    "addr:housenumber":"5",
    "addr:postcode":"7200",
    "addr:street":"Odinsvej",
    "iso:country":"DK",
    "sg:address":"Odinsvej 5",
    "sg:city":"Grindsted",
    "sg:orig_category":"Engros handel",
    "sg:phone":"+45 75 32 52 22",
    "sg:postcode":"7200",
    "sg:province":"Danmark",
    "wof:name":"Scanregn A/S",
    "wof:placetype":"venue"
},
  "geometry": {"coordinates":[8.9603357315,55.7544517517],"type":"Point"}
}