{
  "type": "Feature",
  "properties": {
    "addr:full":"Slagelsevej 19 - 23 Kalundborg Danmark 4400",
    "addr:housenumber":"19 23",
    "addr:postcode":"4400",
    "addr:street":"Slagelsevej",
    "iso:country":"DK",
    "sg:address":"Slagelsevej 19 - 23",
    "sg:city":"Kalundborg",
    "sg:orig_category":"Autoforhandlere",
    "sg:phone":"+45 59 51 55 33",
    "sg:postcode":"4400",
    "sg:province":"Danmark",
    "sg:website":"www.lindorf.dk",
    "wof:name":"Lindorf Automobiler, Simon",
    "wof:placetype":"venue"
},
  "geometry": {"coordinates":[11.1049871445,55.6793212891],"type":"Point"}
}