{
  "type": "Feature",
  "properties": {
    "iso:country":"DK",
    "sg:address":"Frederiksberg Alle 64",
    "sg:city":"Frederiksberg",
    "sg:orig_category":"Chokolade",
    "sg:phone":"+45 33 22 36 35",
    "sg:postcode":"1820",
    "sg:province":"Danmark",
    "wof:name":"Frederiksberg Chokolade",
    "wof:placetype":"venue"
},
  "geometry": {"coordinates":[12.5386638641,55.6743736267],"type":"Point"}
}