{
  "type": "Feature",
  "properties": {
    "iso:country":"DK",
    "sg:address":"Orient Plads 1",
    "sg:city":"K\u00f8benhavn \u00d8",
    "sg:orig_category":"Transport",
    "sg:phone":"+45 39 15 90 00",
    "sg:postcode":"2100",
    "sg:province":"Danmark",
    "wof:name":"Nielsen & Co., Anders",
    "wof:placetype":"venue"
},
  "geometry": {"coordinates":[-118.20812988279999,48.8676795959],"type":"Point"}
}