{
  "type": "Feature",
  "properties": {
    "addr:full":"Bergthorasgade 12 K\u00f8benhavn S Danmark 2300",
    "addr:housenumber":"12",
    "addr:postcode":"2300",
    "addr:street":"Bergthorasgade;S Danmark",
    "iso:country":"DK",
    "sg:address":"Bergthorasgade 12",
    "sg:city":"K\u00f8benhavn S",
    "sg:orig_category":"Tobak",
    "sg:phone":"+45 32 54 22 60",
    "sg:postcode":"2300",
    "sg:province":"Danmark",
    "wof:name":"Vita Vin- & Tobakshuset",
    "wof:placetype":"venue"
},
  "geometry": {"coordinates":[-78.1299133301,36.7267417908],"type":"Point"}
}