{
  "type": "Feature",
  "properties": {
    "iso:country":"DK",
    "sg:address":"S\u00f8ndergade 24",
    "sg:city":"Struer",
    "sg:orig_category":"Kollegier",
    "sg:postcode":"7600",
    "sg:province":"Danmark",
    "wof:name":"Struer Ungdomskollegie",
    "wof:placetype":"venue"
},
  "geometry": {"coordinates":[8.5991754532,56.4899406433],"type":"Point"}
}