{
  "type": "Feature",
  "properties": {
    "addr:full":"Solagervej 11 Karise Danmark 4653",
    "addr:housenumber":"11",
    "addr:postcode":"4653",
    "addr:street":"Solagervej",
    "iso:country":"DK",
    "sg:address":"Solagervej 11",
    "sg:city":"Karise",
    "sg:orig_category":"Murermestre",
    "sg:phone":"+45 56 78 86 01",
    "sg:postcode":"4653",
    "sg:province":"Danmark",
    "wof:name":"K.T.D. Murerentreprise ApS",
    "wof:placetype":"venue"
},
  "geometry": {"coordinates":[12.1945285797,55.3041992188],"type":"Point"}
}