{
  "type": "Feature",
  "properties": {
    "addr:full":"Maskedal 39, D\u00f8rup Skanderborg Danmark 8660",
    "addr:housenumber":"39",
    "addr:postcode":"8660",
    "addr:street":"Maskedal",
    "iso:country":"DK",
    "sg:address":"Maskedal 39, D\u00f8rup",
    "sg:city":"Skanderborg",
    "sg:orig_category":"Konsulentvirksomheder",
    "sg:phone":"+45 75 78 21 13",
    "sg:postcode":"8660",
    "sg:province":"Danmark",
    "wof:name":"Christensen, Chrisconsult \u00c5ge",
    "wof:placetype":"venue"
},
  "geometry": {"coordinates":[9.929974556,56.0380249023],"type":"Point"}
}