{
  "type": "Feature",
  "properties": {
    "addr:full":"Bredgade 26 Karise Danmark 4653",
    "addr:housenumber":"26",
    "addr:postcode":"4653",
    "addr:street":"Bredgade",
    "iso:country":"DK",
    "sg:address":"Bredgade 26",
    "sg:city":"Karise",
    "sg:orig_category":"Apoteker og -udsalg",
    "sg:phone":"+45 56 78 81 95",
    "sg:postcode":"4653",
    "sg:province":"Danmark",
    "wof:name":"Karise Apotek",
    "wof:placetype":"venue"
},
  "geometry": {"coordinates":[12.2007894516,55.3071060181],"type":"Point"}
}