{
  "type": "Feature",
  "properties": {
    "addr:full":"Hasmark Gade 36 Otterup Danmark 5450",
    "addr:housenumber":"36",
    "addr:postcode":"5450",
    "addr:street":"Hasmark Gade",
    "iso:country":"DK",
    "sg:address":"Hasmark Gade 36",
    "sg:city":"Otterup",
    "sg:orig_category":"Akvarier",
    "sg:phone":"+45 64 82 15 15",
    "sg:postcode":"5450",
    "sg:province":"Danmark",
    "wof:name":"Akvaristen i Hasmark",
    "wof:placetype":"venue"
},
  "geometry": {"coordinates":[10.4505119324,55.5483932495],"type":"Point"}
}