{
  "type": "Feature",
  "properties": {
    "addr:full":"Fmd.: Jan Vogel, S\u00f8gade 9, Venslev Skibby Danmark 4050",
    "addr:housenumber":"9",
    "addr:postcode":"4050",
    "addr:street":"Sogade;Venslev",
    "iso:country":"DK",
    "sg:address":"Fmd.: Jan Vogel, S\u00f8gade 9, Venslev",
    "sg:city":"Skibby",
    "sg:orig_category":"Politiske foreninger, \u00c3\u02dcvrige",
    "sg:phone":"+45 47 52 94 84",
    "sg:postcode":"4050",
    "sg:province":"Danmark",
    "wof:name":"Folkebev\u00e6gelsen Mod EU - Frederikssund/Hornsherred",
    "wof:placetype":"venue"
},
  "geometry": {"coordinates":[11.9594116211,55.7502975464],"type":"Point"}
}