{
  "type": "Feature",
  "properties": {
    "addr:full":"Store Valby Vej 248 A, Gunds\u00f8lille Roskilde Danmark 4000",
    "addr:housenumber":"248 a",
    "addr:postcode":"4000",
    "addr:street":"Store Valby Vej;Gundsolille",
    "iso:country":"DK",
    "sg:address":"Store Valby Vej 248 A, Gunds\u00f8lille",
    "sg:city":"Roskilde",
    "sg:orig_category":"Selskabslokaler",
    "sg:phone":"+45 46 78 70 64",
    "sg:postcode":"4000",
    "sg:province":"Danmark",
    "sg:website":"www.gundsoelillehallen.dk",
    "wof:name":"Gunds\u00f8lillehallen a.m.b.a.",
    "wof:placetype":"venue"
},
  "geometry": {"coordinates":[12.0909376144,55.6404838562],"type":"Point"}
}