{
  "type": "Feature",
  "properties": {
    "addr:full":"Hedelandsvej 23 Herning Danmark 7400",
    "addr:housenumber":"23",
    "addr:postcode":"7400",
    "addr:street":"Hedelandsvej",
    "iso:country":"DK",
    "sg:address":"Hedelandsvej 23",
    "sg:city":"Herning",
    "sg:orig_category":"Autolakering",
    "sg:phone":"+45 97 22 28 55",
    "sg:postcode":"7400",
    "sg:province":"Danmark",
    "wof:name":"Martins Autolakering",
    "wof:placetype":"venue"
},
  "geometry": {"coordinates":[8.9367866516,56.1277770996],"type":"Point"}
}