{
  "type": "Feature",
  "properties": {
    "addr:full":"Vardevej 16 Vejle Danmark 7100",
    "addr:housenumber":"16",
    "addr:postcode":"7100",
    "addr:street":"Vardevej",
    "iso:country":"DK",
    "sg:address":"Vardevej 16",
    "sg:city":"Vejle",
    "sg:orig_category":"Blomsterhandlere",
    "sg:phone":"+45 75 83 80 60",
    "sg:postcode":"7100",
    "sg:province":"Danmark",
    "wof:name":"Kreative Blomster",
    "wof:placetype":"venue"
},
  "geometry": {"coordinates":[9.5254602432,55.7159843445],"type":"Point"}
}