{
  "type": "Feature",
  "properties": {
    "addr:full":"S\u00f8vej 23, S\u00f8ller\u00f8d Holte Danmark 2840",
    "addr:housenumber":"23",
    "addr:postcode":"2840",
    "addr:street":"Sovej",
    "iso:country":"DK",
    "sg:address":"S\u00f8vej 23, S\u00f8ller\u00f8d",
    "sg:city":"Holte",
    "sg:orig_category":"Reklamebureauer",
    "sg:phone":"+45 45 42 01 82",
    "sg:postcode":"2840",
    "sg:province":"Danmark",
    "wof:name":"PH",
    "wof:placetype":"venue"
},
  "geometry": {"coordinates":[12.4706554413,55.8122367859],"type":"Point"}
}