{
  "type": "Feature",
  "properties": {
    "addr:full":"S\u00f8nder Alle 5 \u00c5rhus C Danmark 8000",
    "addr:housenumber":"5",
    "addr:postcode":"8000",
    "addr:street":"Sonder Alle",
    "iso:country":"DK",
    "sg:address":"S\u00f8nder Alle 5",
    "sg:city":"\u00c5rhus C",
    "sg:orig_category":"Regnemaskiner",
    "sg:phone":"+45 86 12 77 20",
    "sg:postcode":"8000",
    "sg:province":"Danmark",
    "sg:website":"www.editor.dk",
    "wof:name":"Editor",
    "wof:placetype":"venue"
},
  "geometry": {"coordinates":[4.717400074,49.7588005066],"type":"Point"}
}