{
  "type": "Feature",
  "properties": {
    "addr:full":"Risk\u00e6r 11, Sm\u00f8rumnedre Sm\u00f8rum Danmark 2765",
    "addr:housenumber":"11",
    "addr:postcode":"2765",
    "addr:street":"Riskaer",
    "iso:country":"DK",
    "sg:address":"Risk\u00e6r 11, Sm\u00f8rumnedre",
    "sg:city":"Sm\u00f8rum",
    "sg:orig_category":"Haveredskaber",
    "sg:phone":"+45 44 97 27 58",
    "sg:postcode":"2765",
    "sg:province":"Danmark",
    "wof:name":"Kej Motor- og Maskinservice ApS",
    "wof:placetype":"venue"
},
  "geometry": {"coordinates":[-89.99810791020001,38.1321372986],"type":"Point"}
}