{
  "type": "Feature",
  "properties": {
    "addr:full":"Kroengen 5, Esrum Gr\u00e6sted Danmark 3230",
    "addr:housenumber":"5",
    "addr:postcode":"3230",
    "addr:street":"Kroengen",
    "iso:country":"DK",
    "sg:address":"Kroengen 5, Esrum",
    "sg:city":"Gr\u00e6sted",
    "sg:orig_category":"Psykologer, praktiserende",
    "sg:phone":"+45 48 39 09 56",
    "sg:postcode":"3230",
    "sg:province":"Danmark",
    "wof:name":"Rex, Lisbeth",
    "wof:placetype":"venue"
},
  "geometry": {"coordinates":[12.3426475525,56.048500061],"type":"Point"}
}