{
  "type": "Feature",
  "properties": {
    "addr:full":"Saturnvej 30, Odby Thyholm Danmark 7790",
    "addr:housenumber":"30",
    "addr:postcode":"7790",
    "addr:street":"Saturnvej",
    "iso:country":"DK",
    "sg:address":"Saturnvej 30, Odby",
    "sg:city":"Thyholm",
    "sg:orig_category":"Autoreparation og -service",
    "sg:phone":"+45 97 87 56 50",
    "sg:postcode":"7790",
    "sg:province":"Danmark",
    "wof:name":"MR Auto",
    "wof:placetype":"venue"
},
  "geometry": {"coordinates":[8.525765419,56.6507072449],"type":"Point"}
}