{
  "type": "Feature",
  "properties": {
    "addr:full":"\u00d8stergade 4 Middelfart Danmark 5500",
    "addr:housenumber":"4",
    "addr:postcode":"5500",
    "addr:street":"Ostergade",
    "iso:country":"DK",
    "sg:address":"\u00d8stergade 4",
    "sg:city":"Middelfart",
    "sg:classifiers":[
        {
            "category":"Communications",
            "type":"Services"
        }
    ],
    "sg:phone":"+45 64 41 80 80",
    "sg:postcode":"5500",
    "sg:province":"Danmark",
    "sg:tags":[
        "og",
        "tv",
        "radio"
    ],
    "sg:website":"www.expert.dk",
    "wof:name":"Expert Audio Line",
    "wof:placetype":"venue"
},
  "geometry": {"coordinates":[9.7720470428,55.510269165],"type":"Point"}
}