{
  "type": "Feature",
  "properties": {
    "iso:country":"DK",
    "sg:address":"Sygehusvej 4, Tranebjerg",
    "sg:city":"Sams\u00f8",
    "sg:orig_category":"Biografer",
    "sg:phone":"+45 86 59 14 44",
    "sg:postcode":"8305",
    "sg:province":"Danmark",
    "wof:name":"Biografen Sams\u00f8",
    "wof:placetype":"venue"
},
  "geometry": {"coordinates":[10.5885,55.83202],"type":"Point"}
}