{
  "type": "Feature",
  "properties": {
    "iso:country":"DK",
    "sg:address":"Havnegade 3",
    "sg:city":"Vejle",
    "sg:orig_category":"Sko",
    "sg:phone":"+45 75 83 97 32",
    "sg:postcode":"7100",
    "sg:province":"Danmark",
    "wof:name":"NaturSko",
    "wof:placetype":"venue"
},
  "geometry": {"coordinates":[9.5362148285,55.707611084],"type":"Point"}
}