{
  "type": "Feature",
  "properties": {
    "iso:country":"DK",
    "sg:address":"Helgesh\u00f8j All\u00e9 61 ",
    "sg:city":"Taastrup",
    "sg:classifiers":[
        {
            "category":"Banks & Credit Unions",
            "subcategory":"Bank",
            "type":"Services"
        }
    ],
    "sg:phone":"+45 43 58 88 88",
    "sg:postcode":"2630",
    "sg:province":"Danmark",
    "sg:tags":[
        "banking",
        "institution"
    ],
    "wof:name":"V\u00c6RDIPAPIRCENTRALEN A/S",
    "wof:placetype":"venue"
},
  "geometry": {"coordinates":[12.30209,55.650677],"type":"Point"}
}