{
  "type": "Feature",
  "properties": {
    "addr:full":"Willemoesgade 87 Esbjerg Danmark 6700",
    "addr:housenumber":"87",
    "addr:postcode":"6700",
    "addr:street":"Willemoesgade",
    "iso:country":"DK",
    "sg:address":"Willemoesgade 87",
    "sg:city":"Esbjerg",
    "sg:orig_category":"Malermestre",
    "sg:phone":"+45 75 12 24 56",
    "sg:postcode":"6700",
    "sg:province":"Danmark",
    "wof:name":"Skjoldborg, H.",
    "wof:placetype":"venue"
},
  "geometry": {"coordinates":[8.4358587265,55.472530365],"type":"Point"}
}