{
  "type": "Feature",
  "properties": {
    "addr:full":"Morb\u00e6rv\u00e6nget 18 Frederikssund Danmark 3600",
    "addr:housenumber":"18",
    "addr:postcode":"3600",
    "addr:street":"Morbaervaenget",
    "iso:country":"DK",
    "sg:address":"Morb\u00e6rv\u00e6nget 18",
    "sg:city":"Frederikssund",
    "sg:orig_category":"Sammensatte institutioner",
    "sg:phone":"+45 47 31 36 75",
    "sg:postcode":"3600",
    "sg:province":"Danmark",
    "wof:name":"Store R\u00f8rb\u00e6k Daginstitution",
    "wof:placetype":"venue"
},
  "geometry": {"coordinates":[12.0661621094,55.8370323181],"type":"Point"}
}