{
  "type": "Feature",
  "properties": {
    "addr:full":"v/Ruth Wegeberg, Jernaldervej 425 Brabrand Danmark 8220",
    "addr:housenumber":"425",
    "addr:postcode":"8220",
    "addr:street":"Jernaldervej",
    "iso:country":"DK",
    "sg:address":"v/Ruth Wegeberg, Jernaldervej 425",
    "sg:city":"Brabrand",
    "sg:orig_category":"\u00c3\u02dcvrig fritidsundervisning",
    "sg:phone":"+45 86 24 20 68",
    "sg:postcode":"8220",
    "sg:province":"Danmark",
    "wof:name":"H\u00f8jskoleformiddage/Skjoldh\u00f8j",
    "wof:placetype":"venue"
},
  "geometry": {"coordinates":[10.1293649673,56.1601295471],"type":"Point"}
}