{
  "type": "Feature",
  "properties": {
    "iso:country":"DK",
    "sg:address":"Malm\u00f8vej 47",
    "sg:city":"Silkeborg",
    "sg:orig_category":"Detektivbureauer",
    "sg:phone":"+45 86 81 79 09",
    "sg:postcode":"8600",
    "sg:province":"Danmark",
    "wof:name":"Philbert Defence Industry",
    "wof:placetype":"venue"
},
  "geometry": {"coordinates":[9.6060628891,56.1962471008],"type":"Point"}
}