{
  "type": "Feature",
  "properties": {
    "addr:full":"K\u00e6rvej 501 A Billund Danmark 7190",
    "addr:housenumber":"501 a",
    "addr:postcode":"7190",
    "addr:street":"Kaervej",
    "iso:country":"DK",
    "sg:address":"K\u00e6rvej 501 A",
    "sg:city":"Billund",
    "sg:orig_category":"Legestuer",
    "sg:phone":"+45 75 33 83 60",
    "sg:postcode":"7190",
    "sg:province":"Danmark",
    "wof:name":"Billund Legestue",
    "wof:placetype":"venue"
},
  "geometry": {"coordinates":[9.1048946381,55.72448349],"type":"Point"}
}