{
  "type": "Feature",
  "properties": {
    "addr:full":"Strandgade 2 Vejle Danmark 7100",
    "addr:housenumber":"2",
    "addr:postcode":"7100",
    "addr:street":"Strandgade",
    "iso:country":"DK",
    "sg:address":"Strandgade 2",
    "sg:city":"Vejle",
    "sg:orig_category":"Kommunale folkeskoler",
    "sg:phone":"+45 75 83 96 11",
    "sg:postcode":"7100",
    "sg:province":"Danmark",
    "sg:website":"www.langelinies-skole.dk",
    "wof:name":"Langelinies Skole",
    "wof:placetype":"venue"
},
  "geometry": {"coordinates":[9.5403699875,55.7095794678],"type":"Point"}
}