{
  "type": "Feature",
  "properties": {
    "addr:full":"Spangsbjerg Kirkevej 51 Esbjerg Danmark 6700",
    "addr:housenumber":"51",
    "addr:postcode":"6700",
    "addr:street":"Spangsbjerg Kirkevej",
    "iso:country":"DK",
    "sg:address":"Spangsbjerg Kirkevej 51",
    "sg:city":"Esbjerg",
    "sg:orig_category":"\u00c3\u2020ldrecentre",
    "sg:phone":"+45 75 13 36 33",
    "sg:postcode":"6700",
    "sg:province":"Danmark",
    "wof:name":"Omr\u00e5decentret H\u00f8jvang",
    "wof:placetype":"venue"
},
  "geometry": {"coordinates":[8.4528713226,55.4841308594],"type":"Point"}
}