{
  "type": "Feature",
  "properties": {
    "addr:full":"Fyrparken 66 Esbjerg V Danmark 6710",
    "addr:housenumber":"66",
    "addr:postcode":"6710",
    "addr:street":"Fyrparken",
    "iso:country":"DK",
    "sg:address":"Fyrparken 66",
    "sg:city":"Esbjerg V",
    "sg:orig_category":"Arkitekter",
    "sg:phone":"+45 75 15 62 20",
    "sg:postcode":"6710",
    "sg:province":"Danmark",
    "wof:name":"Tanvig Arkitektfirma, Lindy",
    "wof:placetype":"venue"
},
  "geometry": {"coordinates":[8.4015197754,55.5006942749],"type":"Point"}
}