{
  "type": "Feature",
  "properties": {
    "addr:full":"v/ Niels Skouby, Ravnsvej 15, Egsmark Ebeltoft Danmark 8400",
    "addr:housenumber":"15",
    "addr:postcode":"8400",
    "addr:street":"Ravnsvej;Egsmark",
    "iso:country":"DK",
    "sg:address":"v/ Niels Skouby, Ravnsvej 15, Egsmark",
    "sg:city":"Ebeltoft",
    "sg:orig_category":"Musik og sang",
    "sg:phone":"+45 86 34 41 44",
    "sg:postcode":"8400",
    "sg:province":"Danmark",
    "wof:name":"Visens Venner",
    "wof:placetype":"venue"
},
  "geometry": {"coordinates":[10.6778745651,56.199798584],"type":"Point"}
}