{
  "type": "Feature",
  "properties": {
    "addr:full":"v/ Obs i Esbjerg, Gl. Vardevej 230 Esbjerg N Danmark 6715",
    "addr:housenumber":"230",
    "addr:postcode":"6715",
    "addr:street":"Gl. Vardevej",
    "iso:country":"DK",
    "sg:address":"v/ Obs i Esbjerg, Gl. Vardevej 230",
    "sg:city":"Esbjerg N",
    "sg:orig_category":"Apoteker og -udsalg",
    "sg:phone":"+45 75 15 80 11",
    "sg:postcode":"6715",
    "sg:province":"Danmark",
    "wof:name":"H\u00e5ndk\u00f8bsudsalget",
    "wof:placetype":"venue"
},
  "geometry": {"coordinates":[8.4780550003,55.535610199],"type":"Point"}
}