{
  "type": "Feature",
  "properties": {
    "addr:full":"Energivej 2 Ballerup Danmark 2750",
    "addr:housenumber":"2",
    "addr:postcode":"2750",
    "addr:street":"Energivej",
    "iso:country":"DK",
    "sg:address":"Energivej 2",
    "sg:city":"Ballerup",
    "sg:orig_category":"Autoforhandlere",
    "sg:phone":"+45 44 97 06 34",
    "sg:postcode":"2750",
    "sg:province":"Danmark",
    "wof:name":"Br\u00f8ndum Automobiler A/S",
    "wof:placetype":"venue"
},
  "geometry": {"coordinates":[12.3834819794,55.7235336304],"type":"Point"}
}