{
  "type": "Feature",
  "properties": {
    "addr:full":"Klintevej 5, Klokkerholm Hjallerup Danmark 9320",
    "addr:housenumber":"5",
    "addr:postcode":"9320",
    "addr:street":"Klintevej;Klokkerholm",
    "iso:country":"DK",
    "sg:address":"Klintevej 5, Klokkerholm",
    "sg:city":"Hjallerup",
    "sg:orig_category":"Skomagere",
    "sg:phone":"+45 98 28 43 41",
    "sg:postcode":"9320",
    "sg:province":"Danmark",
    "wof:name":"Bengtzon, Gunnar",
    "wof:placetype":"venue"
},
  "geometry": {"coordinates":[10.1444702148,57.1677742004],"type":"Point"}
}