{
  "type": "Feature",
  "properties": {
    "addr:full":"Elmelundsvej 4, Bolbro Odense V Danmark 5200",
    "addr:housenumber":"4",
    "addr:postcode":"5200",
    "addr:street":"Elmelundsvej;Bolbro",
    "iso:country":"DK",
    "sg:address":"Elmelundsvej 4, Bolbro",
    "sg:city":"Odense V",
    "sg:orig_category":"Kollegier",
    "sg:phone":"+45 65 71 02 50",
    "sg:postcode":"5200",
    "sg:province":"Danmark",
    "wof:name":"Rasmus Rask Kollegiet",
    "wof:placetype":"venue"
},
  "geometry": {"coordinates":[10.2629547119,55.4070854187],"type":"Point"}
}