{
  "type": "Feature",
  "properties": {
    "addr:full":"Strandvejen 90 \u00c5rhus C Danmark 8000",
    "addr:housenumber":"90",
    "addr:postcode":"8000",
    "addr:street":"Strandvejen",
    "iso:country":"DK",
    "sg:address":"Strandvejen 90",
    "sg:city":"\u00c5rhus C",
    "sg:orig_category":"Fotolaboratorier",
    "sg:phone":"+45 86 14 12 22",
    "sg:postcode":"8000",
    "sg:province":"Danmark",
    "sg:website":"www.maicolor.dk",
    "wof:name":"Mai Color A/S",
    "wof:placetype":"venue"
},
  "geometry": {"coordinates":[4.717400074,49.7588005066],"type":"Point"}
}