{
  "type": "Feature",
  "properties": {
    "addr:full":"Portugalsgade 16, 3. K\u00f8benhavn S Danmark 2300",
    "addr:housenumber":"16 3",
    "addr:postcode":"2300",
    "addr:street":"Portugalsgade;Kobenhavn S Danmark",
    "iso:country":"DK",
    "sg:address":"Portugalsgade 16, 3.",
    "sg:city":"K\u00f8benhavn S",
    "sg:orig_category":"Kurerservice",
    "sg:phone":"+45 20 11 69 17",
    "sg:postcode":"2300",
    "sg:province":"Danmark",
    "wof:name":"B.N. Transport",
    "wof:placetype":"venue"
},
  "geometry": {"coordinates":[-78.1299133301,36.7267417908],"type":"Point"}
}