{
  "type": "Feature",
  "properties": {
    "addr:full":"Holkebjergvej 48, H\u00f8jme Odense SV Danmark 5250",
    "addr:housenumber":"48",
    "addr:postcode":"5250",
    "addr:street":"Holkebjergvej;Hojme",
    "iso:country":"DK",
    "sg:address":"Holkebjergvej 48, H\u00f8jme",
    "sg:city":"Odense SV",
    "sg:orig_category":"Virksomhedsadministration",
    "sg:phone":"+45 63 17 42 17",
    "sg:postcode":"5250",
    "sg:province":"Danmark",
    "wof:name":"Micro Matic Holding A/S",
    "wof:placetype":"venue"
},
  "geometry": {"coordinates":[10.3153953552,55.3362998962],"type":"Point"}
}