{
  "type": "Feature",
  "properties": {
    "iso:country":"DK",
    "sg:address":"Industrivej 30 ",
    "sg:city":"Bramming",
    "sg:classifiers":[
        {
            "category":"Manufacturing",
            "subcategory":"Lumber",
            "type":"Manufacturing & Wholesale Goods"
        }
    ],
    "sg:phone":"+45 75 17 39 00",
    "sg:postcode":"6740",
    "sg:province":"Danmark",
    "sg:tags":[
        "wood"
    ],
    "wof:name":"BRAMMING BYGGELAGER A/S",
    "wof:placetype":"venue"
},
  "geometry": {"coordinates":[8.6809577942,55.4663314819],"type":"Point"}
}