{
  "type": "Feature",
  "properties": {
    "addr:full":"Fmd.: Mille Kj\u00e6r Lund, Kl\u00e5byh\u00f8jvej 3, Vesterb\u00e6k Ribe Danmark 6760",
    "addr:housenumber":"3",
    "addr:postcode":"6760",
    "addr:street":"Klaabyhojvej",
    "iso:country":"DK",
    "sg:address":"Fmd.: Mille Kj\u00e6r Lund, Kl\u00e5byh\u00f8jvej 3, Vesterb\u00e6k",
    "sg:city":"Ribe",
    "sg:orig_category":"Husflidsforeninger",
    "sg:phone":"+45 75 44 31 78",
    "sg:postcode":"6760",
    "sg:province":"Danmark",
    "wof:name":"Familie Aktiviteter i Roager",
    "wof:placetype":"venue"
},
  "geometry": {"coordinates":[8.7656240463,55.3297042847],"type":"Point"}
}