{
  "type": "Feature",
  "properties": {
    "addr:full":"Ordrupvej 51, Ordrup F\u00e5revejle Danmark 4540",
    "addr:housenumber":"51",
    "addr:postcode":"4540",
    "addr:street":"Ordrupvej",
    "iso:country":"DK",
    "sg:address":"Ordrupvej 51, Ordrup",
    "sg:city":"F\u00e5revejle",
    "sg:classifiers":[
        {
            "category":"Restaurant",
            "type":"Food & Drink"
        }
    ],
    "sg:phone":"+45 59 62 24 62",
    "sg:postcode":"4540",
    "sg:province":"Danmark",
    "wof:name":"Caf\u00e9en i Ordrup",
    "wof:placetype":"venue"
},
  "geometry": {"coordinates":[11.4679298401,55.7857704163],"type":"Point"}
}