{
  "type": "Feature",
  "properties": {
    "addr:full":"M\u00f8lleg\u00e5rdsparken 12, Fastrup Solbjerg Danmark 8355",
    "addr:housenumber":"12",
    "addr:postcode":"8355",
    "addr:street":"Mollegaardsparken",
    "iso:country":"DK",
    "sg:address":"M\u00f8lleg\u00e5rdsparken 12, Fastrup",
    "sg:city":"Solbjerg",
    "sg:orig_category":"Alternativ energi",
    "sg:phone":"+45 86 92 62 44",
    "sg:postcode":"8355",
    "sg:province":"Danmark",
    "wof:name":"Milj\u00f8 Varme",
    "wof:placetype":"venue"
},
  "geometry": {"coordinates":[10.0810050964,56.0374946594],"type":"Point"}
}