{
  "type": "Feature",
  "properties": {
    "addr:full":"Visherredsvej 12 Padborg Danmark 6330",
    "addr:housenumber":"12",
    "addr:postcode":"6330",
    "addr:street":"Visherredsvej",
    "iso:country":"DK",
    "sg:address":"Visherredsvej 12",
    "sg:city":"Padborg",
    "sg:orig_category":"Slagterier",
    "sg:phone":"+45 74 67 30 25",
    "sg:postcode":"6330",
    "sg:province":"Danmark",
    "wof:name":"Padborg Fjerkr\u00e6sslagteri A/S",
    "wof:placetype":"venue"
},
  "geometry": {"coordinates":[9.3588352203,54.8324661255],"type":"Point"}
}