{
  "type": "Feature",
  "properties": {
    "addr:full":"Nyk\u00f8bingvej 266, Nr. \u00d8rslev Nyk\u00f8bing Danmark 4800",
    "addr:housenumber":"266",
    "addr:postcode":"4800",
    "addr:street":"Nykobingvej",
    "iso:country":"DK",
    "sg:address":"Nyk\u00f8bingvej 266, Nr. \u00d8rslev",
    "sg:city":"Nyk\u00f8bing",
    "sg:orig_category":"Efterskoler",
    "sg:phone":"+45 54 86 80 30",
    "sg:postcode":"4800",
    "sg:province":"Danmark",
    "sg:website":"www.noeu-efterskole.dk",
    "wof:name":"N\u00f8rre \u00d8rslev ungdomsskole",
    "wof:placetype":"venue"
},
  "geometry": {"coordinates":[166.9221496582,-0.5282999873],"type":"Point"}
}