{
  "type": "Feature",
  "properties": {
    "addr:full":"Willemoesgade 2 A Assens Danmark 5610",
    "addr:housenumber":"2 a",
    "addr:postcode":"5610",
    "addr:street":"Willemoesgade",
    "iso:country":"DK",
    "sg:address":"Willemoesgade 2 A",
    "sg:city":"Assens",
    "sg:orig_category":"Revisorer",
    "sg:phone":"+45 64 71 16 88",
    "sg:postcode":"5610",
    "sg:province":"Danmark",
    "wof:name":"Assens Revisionskontor",
    "wof:placetype":"venue"
},
  "geometry": {"coordinates":[9.8927097321,55.2700843811],"type":"Point"}
}