{
  "type": "Feature",
  "properties": {
    "iso:country":"DK",
    "sg:address":"Thorslundsvej 1",
    "sg:city":"Odense C",
    "sg:orig_category":"Autoforhandlere",
    "sg:phone":"+45 66 14 47 49",
    "sg:postcode":"5000",
    "sg:province":"Danmark",
    "wof:name":"Stage Olsen Automobiler A/S",
    "wof:placetype":"venue"
},
  "geometry": {"coordinates":[10.3677902222,55.4145469666],"type":"Point"}
}