{
  "type": "Feature",
  "properties": {
    "addr:full":"Bramsn\u00e6slund 10 Kirke Hyllinge Danmark 4070",
    "addr:housenumber":"10",
    "addr:postcode":"4070",
    "addr:street":"Bramsnaeslund",
    "iso:country":"DK",
    "sg:address":"Bramsn\u00e6slund 10",
    "sg:city":"Kirke Hyllinge",
    "sg:orig_category":"Ergoterapeuter",
    "sg:phone":"+45 46 41 45 02",
    "sg:postcode":"4070",
    "sg:province":"Danmark",
    "wof:name":"Ryberg, Anni",
    "wof:placetype":"venue"
},
  "geometry": {"coordinates":[11.8490962982,55.6942939758],"type":"Point"}
}