{
  "type": "Feature",
  "properties": {
    "addr:full":"L\u00f8venholmvej 33 A, Gjesing Auning Danmark 8963",
    "addr:housenumber":"33 a",
    "addr:postcode":"8963",
    "addr:street":"Lovenholmvej;Gjesing",
    "iso:country":"DK",
    "sg:address":"L\u00f8venholmvej 33 A, Gjesing",
    "sg:city":"Auning",
    "sg:orig_category":"Malermestre",
    "sg:phone":"+45 86 48 12 92",
    "sg:postcode":"8963",
    "sg:province":"Danmark",
    "wof:name":"Alling\u00e5bro Malerfirma",
    "wof:placetype":"venue"
},
  "geometry": {"coordinates":[10.3770084381,56.430065155],"type":"Point"}
}