{
  "type": "Feature",
  "properties": {
    "addr:full":"Langstedgyden 3, Barl\u00f8se Assens Danmark 5610",
    "addr:housenumber":"3",
    "addr:postcode":"5610",
    "addr:street":"Langstedgyden;Barlose",
    "iso:country":"DK",
    "sg:address":"Langstedgyden 3, Barl\u00f8se",
    "sg:city":"Assens",
    "sg:orig_category":"Kirker",
    "sg:postcode":"5610",
    "sg:province":"Danmark",
    "wof:name":"Barl\u00f8se Kirke",
    "wof:placetype":"venue"
},
  "geometry": {"coordinates":[9.8998937607,55.2702522278],"type":"Point"}
}