{
  "type": "Feature",
  "properties": {
    "addr:full":"Alsikevej 5 Randers Danmark 8900",
    "addr:housenumber":"5",
    "addr:postcode":"8900",
    "addr:street":"Alsikevej",
    "iso:country":"DK",
    "sg:address":"Alsikevej 5",
    "sg:city":"Randers",
    "sg:orig_category":"Autoreparation og -service",
    "sg:phone":"+45 86 42 89 24",
    "sg:postcode":"8900",
    "sg:province":"Danmark",
    "wof:name":"Jensen, Brdr. Dahl",
    "wof:placetype":"venue"
},
  "geometry": {"coordinates":[10.0217380524,56.4863357544],"type":"Point"}
}