{
  "type": "Feature",
  "properties": {
    "addr:full":"Holmbladsgade 95 K\u00f8benhavn S Danmark 2300",
    "addr:housenumber":"95",
    "addr:postcode":"2300",
    "addr:street":"Holmbladsgade;Kobenhavn S Danmark",
    "iso:country":"DK",
    "sg:address":"Holmbladsgade 95",
    "sg:city":"K\u00f8benhavn S",
    "sg:orig_category":"Kiosker",
    "sg:phone":"+45 32 54 78 70",
    "sg:postcode":"2300",
    "sg:province":"Danmark",
    "wof:name":"Kiosk 95",
    "wof:placetype":"venue"
},
  "geometry": {"coordinates":[12.6146497726,55.6666908264],"type":"Point"}
}