{
  "type": "Feature",
  "properties": {
    "addr:full":"v/ Ole Michael Jensen, Enghave 21 C Rungsted Kyst Danmark 2960",
    "addr:housenumber":"21 c",
    "addr:postcode":"2960",
    "addr:street":"Enghave",
    "iso:country":"DK",
    "sg:address":"v/ Ole Michael Jensen, Enghave 21 C",
    "sg:city":"Rungsted Kyst",
    "sg:orig_category":"Hobbybetonede foreninger",
    "sg:phone":"+45 45 57 16 59",
    "sg:postcode":"2960",
    "sg:province":"Danmark",
    "wof:name":"H\u00f8rsholm og Omegns Biavlerforening",
    "wof:placetype":"venue"
},
  "geometry": {"coordinates":[12.5300750732,55.883846283],"type":"Point"}
}