{
  "type": "Feature",
  "properties": {
    "iso:country":"DK",
    "sg:address":"Sundvej 32 C",
    "sg:city":"Horsens",
    "sg:orig_category":"Bandagister",
    "sg:phone":"+45 75 62 27 00",
    "sg:postcode":"8700",
    "sg:province":"Danmark",
    "sg:website":"www.bandagisten-as.dk",
    "wof:name":"Bandagisten Body Support A/S",
    "wof:placetype":"venue"
},
  "geometry": {"coordinates":[9.875086,55.86512],"type":"Point"}
}