{
  "type": "Feature",
  "properties": {
    "addr:full":"Karlsbergvej 52 Randers Danmark 8900",
    "addr:housenumber":"52",
    "addr:postcode":"8900",
    "addr:street":"Karlsbergvej",
    "iso:country":"DK",
    "sg:address":"Karlsbergvej 52",
    "sg:city":"Randers",
    "sg:orig_category":"Internet, software",
    "sg:phone":"+45 86 44 83 76",
    "sg:postcode":"8900",
    "sg:province":"Danmark",
    "sg:website":"www.jg-design.dk",
    "wof:name":"JG Design",
    "wof:placetype":"venue"
},
  "geometry": {"coordinates":[10.0697517395,56.3982543945],"type":"Point"}
}