{
  "type": "Feature",
  "properties": {
    "addr:full":"Danagade 9 Nakskov Danmark 4900",
    "addr:housenumber":"9",
    "addr:postcode":"4900",
    "addr:street":"Danagade",
    "iso:country":"DK",
    "sg:address":"Danagade 9",
    "sg:city":"Nakskov",
    "sg:orig_category":"Faglige organisationer og foreninger",
    "sg:phone":"+45 54 92 09 41",
    "sg:postcode":"4900",
    "sg:province":"Danmark",
    "wof:name":"Dansk Metalarbejderforbund",
    "wof:placetype":"venue"
},
  "geometry": {"coordinates":[11.1406574249,54.8320846558],"type":"Point"}
}