{
  "type": "Feature",
  "properties": {
    "addr:full":"Vassinger\u00f8dvej 9  Lynge Danmark 3540",
    "addr:housenumber":"9",
    "addr:postcode":"3540",
    "addr:street":"Vassingerodvej",
    "iso:country":"DK",
    "sg:address":"Vassinger\u00f8dvej 9 ",
    "sg:city":"Lynge",
    "sg:classifiers":[
        {
            "category":"Wholesale",
            "subcategory":"Drugs",
            "type":"Manufacturing & Wholesale Goods"
        }
    ],
    "sg:phone":"+45 48 16 32 00",
    "sg:postcode":"3540",
    "sg:province":"Danmark",
    "sg:tags":[
        "chemical",
        "pharmaceutical"
    ],
    "wof:name":"MISSIONPHARMA A/S",
    "wof:placetype":"venue"
},
  "geometry": {"coordinates":[12.3184604645,55.8368453979],"type":"Point"}
}