{
  "type": "Feature",
  "properties": {
    "addr:full":"Sct. Laurentii Vej 56 Skagen Danmark 9990",
    "addr:housenumber":"56",
    "addr:postcode":"9990",
    "addr:street":"Sct. Laurentii Vej",
    "iso:country":"DK",
    "sg:address":"Sct. Laurentii Vej 56",
    "sg:city":"Skagen",
    "sg:classifiers":[
        {
            "category":"Restaurant",
            "type":"Food & Drink"
        }
    ],
    "sg:phone":"+45 98 44 39 00",
    "sg:postcode":"9990",
    "sg:province":"Danmark",
    "sg:website":"www.jerrys.dk",
    "wof:name":"Jerry's",
    "wof:placetype":"venue"
},
  "geometry": {"coordinates":[10.5872802734,57.7219200134],"type":"Point"}
}