{
  "type": "Feature",
  "properties": {
    "iso:country":"DK",
    "sg:address":"Hobrovej 786",
    "sg:city":"Svenstrup",
    "sg:orig_category":"Blomsterhandlere",
    "sg:phone":"+45 98 38 14 02",
    "sg:postcode":"9230",
    "sg:province":"Danmark",
    "wof:name":"Solglimt, Blomsterforretningen",
    "wof:placetype":"venue"
},
  "geometry": {"coordinates":[9.8550462723,56.9695549011],"type":"Point"}
}