{
  "type": "Feature",
  "properties": {
    "addr:full":"Borresvej 4 Horslunde Danmark 4913",
    "addr:housenumber":"4",
    "addr:postcode":"4913",
    "addr:street":"Borresvej",
    "iso:country":"DK",
    "sg:address":"Borresvej 4",
    "sg:city":"Horslunde",
    "sg:orig_category":"Autoreparation og -service",
    "sg:phone":"+45 54 93 52 59",
    "sg:postcode":"4913",
    "sg:province":"Danmark",
    "wof:name":"Ankers Auto",
    "wof:placetype":"venue"
},
  "geometry": {"coordinates":[11.2183465958,54.9091835022],"type":"Point"}
}