{
  "type": "Feature",
  "properties": {
    "addr:full":"Gudmevej 42 Hesselager Danmark 5874",
    "addr:housenumber":"42",
    "addr:postcode":"5874",
    "addr:street":"Gudmevej",
    "iso:country":"DK",
    "sg:address":"Gudmevej 42",
    "sg:city":"Hesselager",
    "sg:orig_category":"Typehuse",
    "sg:phone":"+45 62 25 28 70",
    "sg:postcode":"5874",
    "sg:province":"Danmark",
    "sg:website":"www.teamboro.se",
    "wof:name":"Team Boro",
    "wof:placetype":"venue"
},
  "geometry": {"coordinates":[10.7260494232,55.165271759],"type":"Point"}
}