{
  "type": "Feature",
  "properties": {
    "iso:country":"DK",
    "sg:address":"Bysvinget 4, Dr\u00e5by",
    "sg:city":"Ebeltoft",
    "sg:orig_category":"Keramik",
    "sg:phone":"+45 86 34 09 04",
    "sg:postcode":"8400",
    "sg:province":"Danmark",
    "wof:name":"Engstr\u00f8m Keramik",
    "wof:placetype":"venue"
},
  "geometry": {"coordinates":[10.6778745651,56.199798584],"type":"Point"}
}