{
  "type": "Feature",
  "properties": {
    "addr:full":"Enghaven 2 Holstebro Danmark 7500",
    "addr:housenumber":"2",
    "addr:postcode":"7500",
    "addr:street":"Enghaven",
    "iso:country":"DK",
    "sg:address":"Enghaven 2",
    "sg:city":"Holstebro",
    "sg:orig_category":"INGENI\u00c3\u02dcRER",
    "sg:phone":"+45 97 41 02 22",
    "sg:postcode":"7500",
    "sg:province":"Danmark",
    "wof:name":"Zickert Milj\u00f8 AS Ingeni\u00f8r- og Handelsfirma",
    "wof:placetype":"venue"
},
  "geometry": {"coordinates":[8.7039852142,56.3207130432],"type":"Point"}
}