{
  "type": "Feature",
  "properties": {
    "addr:full":"Fmd.: Ole B\u00e6k, Egerup Byvej 4, Egerup Sk\u00e6lsk\u00f8r Danmark 4230",
    "addr:housenumber":"4",
    "addr:postcode":"4230",
    "addr:street":"Egerup Byvej",
    "iso:country":"DK",
    "sg:address":"Fmd.: Ole B\u00e6k, Egerup Byvej 4, Egerup",
    "sg:city":"Sk\u00e6lsk\u00f8r",
    "sg:orig_category":"Loger",
    "sg:phone":"+45 58 14 00 65",
    "sg:postcode":"4230",
    "sg:province":"Danmark",
    "wof:name":"De danske Forsvarsbr\u00f8dre for Sk\u00e6lsk\u00f8r og omegn",
    "wof:placetype":"venue"
},
  "geometry": {"coordinates":[11.1915035248,55.2119750977],"type":"Point"}
}