{
  "type": "Feature",
  "properties": {
    "iso:country":"DK",
    "sg:address":"Algade 35",
    "sg:city":"Aalborg",
    "sg:orig_category":"Sko",
    "sg:phone":"+45 98 13 98 93",
    "sg:postcode":"9000",
    "sg:province":"Danmark",
    "wof:name":"Ko'Ko'",
    "wof:placetype":"venue"
},
  "geometry": {"coordinates":[9.920083046,57.0475196838],"type":"Point"}
}