{
  "type": "Feature",
  "properties": {
    "addr:full":"Klode M\u00f8lle Vej 1 Engesvang Danmark 7442",
    "addr:housenumber":"1",
    "addr:postcode":"7442",
    "addr:street":"Klode Molle Vej",
    "iso:country":"DK",
    "sg:address":"Klode M\u00f8lle Vej 1",
    "sg:city":"Engesvang",
    "sg:orig_category":"Autoforhandlere",
    "sg:phone":"+45 86 86 55 58",
    "sg:postcode":"7442",
    "sg:province":"Danmark",
    "sg:website":"www.klodebiler.dk",
    "wof:name":"Klode M\u00f8lle Biler",
    "wof:placetype":"venue"
},
  "geometry": {"coordinates":[9.3173027039,56.1930465698],"type":"Point"}
}