{
  "type": "Feature",
  "properties": {
    "iso:country":"DK",
    "sg:address":"Skolebakken 153",
    "sg:city":"Esbjerg \u00d8",
    "sg:orig_category":"Blikkenslagere",
    "sg:phone":"+45 75 13 44 34",
    "sg:postcode":"6705",
    "sg:province":"Danmark",
    "wof:name":"J\u00f8rgensen, Tommy",
    "wof:placetype":"venue"
},
  "geometry": {"coordinates":[8.48376,55.48008],"type":"Point"}
}