{
  "type": "Feature",
  "properties": {
    "iso:country":"DK",
    "sg:address":"Vigerslevvej 74 B",
    "sg:city":"Valby",
    "sg:orig_category":"Malermestre",
    "sg:phone":"+45 36 30 22 03",
    "sg:postcode":"2500",
    "sg:province":"Danmark",
    "wof:name":"Aagren, Johs.",
    "wof:placetype":"venue"
},
  "geometry": {"coordinates":[12.4853725433,55.6664733887],"type":"Point"}
}