{
  "type": "Feature",
  "properties": {
    "addr:full":"S\u00f8ndertoften 116 Taastrup Danmark 2630",
    "addr:housenumber":"116",
    "addr:postcode":"2630",
    "addr:street":"Sondertoften",
    "iso:country":"DK",
    "sg:address":"S\u00f8ndertoften 116",
    "sg:city":"Taastrup",
    "sg:orig_category":"Kinesiologi",
    "sg:phone":"+45 43 99 11 73",
    "sg:postcode":"2630",
    "sg:province":"Danmark",
    "wof:name":"Dithmer, Ulla",
    "wof:placetype":"venue"
},
  "geometry": {"coordinates":[12.3108720779,55.6396827698],"type":"Point"}
}