{
  "type": "Feature",
  "properties": {
    "addr:full":"Herlev Hovedgade 115 Herlev Danmark 2730",
    "addr:housenumber":"115",
    "addr:postcode":"2730",
    "addr:street":"Herlev Hovedgade",
    "iso:country":"DK",
    "sg:address":"Herlev Hovedgade 115",
    "sg:city":"Herlev",
    "sg:orig_category":"Farvehandlere",
    "sg:phone":"+45 44 94 04 74",
    "sg:postcode":"2730",
    "sg:province":"Danmark",
    "sg:website":"www.sadolinfarveland.dk",
    "wof:name":"Sadolin Farveland",
    "wof:placetype":"venue"
},
  "geometry": {"coordinates":[12.441860199,55.7224578857],"type":"Point"}
}