{
  "type": "Feature",
  "properties": {
    "addr:full":"v/ IJan Ruby, K\u00e6rvej 49, B\u00f8vling B\u00f8vlingbjerg Danmark 7650",
    "addr:housenumber":"49",
    "addr:postcode":"7650",
    "addr:street":"Ruby Kaervej",
    "iso:country":"DK",
    "sg:address":"v/ IJan Ruby, K\u00e6rvej 49, B\u00f8vling",
    "sg:city":"B\u00f8vlingbjerg",
    "sg:orig_category":"Borger- og beboerforeninger",
    "sg:phone":"+45 97 88 51 46",
    "sg:postcode":"7650",
    "sg:province":"Danmark",
    "wof:name":"B\u00f8vling Borgerforening",
    "wof:placetype":"venue"
},
  "geometry": {"coordinates":[-155.48915100100001,64.73806762700001],"type":"Point"}
}