{
  "type": "Feature",
  "properties": {
    "iso:country":"DK",
    "sg:address":"Hiller\u00f8dvej 44 F",
    "sg:city":"Lynge",
    "sg:classifiers":[
        {
            "category":"Banks & Credit Unions",
            "subcategory":"Bank",
            "type":"Services"
        }
    ],
    "sg:phone":"+45 48 18 73 30",
    "sg:postcode":"3540",
    "sg:province":"Danmark",
    "sg:tags":[
        "banker"
    ],
    "wof:name":"Unibank",
    "wof:placetype":"venue"
},
  "geometry": {"coordinates":[12.273497,55.834187],"type":"Point"}
}