{
  "type": "Feature",
  "properties": {
    "addr:full":"Morup M\u00f8llevej 26 Bedsted Danmark 7755",
    "addr:housenumber":"26",
    "addr:postcode":"7755",
    "addr:street":"Mollevej",
    "iso:country":"DK",
    "sg:address":"Morup M\u00f8llevej 26",
    "sg:city":"Bedsted",
    "sg:orig_category":"Tagrenovering",
    "sg:phone":"+45 97 94 45 56",
    "sg:postcode":"7755",
    "sg:province":"Danmark",
    "sg:website":"www.nordvestejendomservice.dk",
    "wof:name":"Nordvest Ejendomsservice",
    "wof:placetype":"venue"
},
  "geometry": {"coordinates":[8.4016628265,56.811088562],"type":"Point"}
}