{
  "type": "Feature",
  "properties": {
    "iso:country":"DK",
    "sg:address":"Lufthavnsvej 100 Aalborg Lufthavn ",
    "sg:city":"N\u00f8rresundby",
    "sg:classifiers":[
        {
            "category":"Airport",
            "subcategory":"General Aviation",
            "type":"Transportation"
        }
    ],
    "sg:phone":"+45 96 32 29 00",
    "sg:postcode":"9400",
    "sg:province":"Danmark",
    "sg:tags":[
        "transport",
        "air"
    ],
    "wof:name":"NORTH FLYING A/S",
    "wof:placetype":"venue"
},
  "geometry": {"coordinates":[9.9049549103,57.0654602051],"type":"Point"}
}