{
  "type": "Feature",
  "properties": {
    "addr:full":"Benediktevej 4 Fredensborg Danmark 3480",
    "addr:housenumber":"4",
    "addr:postcode":"3480",
    "addr:street":"Benediktevej",
    "iso:country":"DK",
    "sg:address":"Benediktevej 4",
    "sg:city":"Fredensborg",
    "sg:orig_category":"Flytteforretninger",
    "sg:phone":"+45 48 48 28 83",
    "sg:postcode":"3480",
    "sg:province":"Danmark",
    "sg:website":"www.fredensborg.vognmandsforr.dk",
    "wof:name":"Fredensborg Vognmandsforretning ApS",
    "wof:placetype":"venue"
},
  "geometry": {"coordinates":[12.4042043686,55.9762001038],"type":"Point"}
}