{
  "type": "Feature",
  "properties": {
    "addr:full":"Sognepr\u00e6st: Ruth Jeppesen (K/B), Doveroddevej 17, Boddum Hurup Danmark 7760",
    "addr:housenumber":"17",
    "addr:postcode":"7760",
    "addr:street":"Doveroddevej;Boddum",
    "iso:country":"DK",
    "sg:address":"Sognepr\u00e6st: Ruth Jeppesen (K/B), Doveroddevej 17, Boddum",
    "sg:city":"Hurup",
    "sg:orig_category":"Kirkesogne",
    "sg:phone":"+45 97 95 90 09",
    "sg:postcode":"7760",
    "sg:province":"Danmark",
    "wof:name":"Boddum og Ydby Sogne",
    "wof:placetype":"venue"
},
  "geometry": {"coordinates":[8.4233045578,56.7485847473],"type":"Point"}
}