{
  "type": "Feature",
  "properties": {
    "iso:country":"DK",
    "sg:address":"Glentevej 2 A",
    "sg:city":"K\u00f8benhavn NV",
    "sg:orig_category":"Afsyring",
    "sg:phone":"+45 38 34 05 68",
    "sg:postcode":"2400",
    "sg:province":"Danmark",
    "wof:name":"Bondestuen",
    "wof:placetype":"venue"
},
  "geometry": {"coordinates":[-117.02272033689999,38.5024604797],"type":"Point"}
}