{
  "type": "Feature",
  "properties": {
    "addr:full":"Tvillingevej 4, Sm\u00f8rumvang Sm\u00f8rum Danmark 2765",
    "addr:housenumber":"4",
    "addr:postcode":"2765",
    "addr:street":"Tvillingevej",
    "iso:country":"DK",
    "sg:address":"Tvillingevej 4, Sm\u00f8rumvang",
    "sg:city":"Sm\u00f8rum",
    "sg:orig_category":"Kaffe en gros",
    "sg:phone":"+45 22 42 16 18",
    "sg:postcode":"2765",
    "sg:province":"Danmark",
    "wof:name":"Kaffekompagniet I/S",
    "wof:placetype":"venue"
},
  "geometry": {"coordinates":[-89.99810791020001,38.1321372986],"type":"Point"}
}