{
  "type": "Feature",
  "properties": {
    "addr:full":"Skovv\u00e6nget 16, Arrild Toftlund Danmark 6520",
    "addr:housenumber":"16",
    "addr:postcode":"6520",
    "addr:street":"Skovvaenget;Arrild",
    "iso:country":"DK",
    "sg:address":"Skovv\u00e6nget 16, Arrild",
    "sg:city":"Toftlund",
    "sg:orig_category":"Maskinstationer",
    "sg:phone":"+45 74 83 44 00",
    "sg:postcode":"6520",
    "sg:province":"Danmark",
    "wof:name":"Vesterg\u00e5rd Maskinstation",
    "wof:placetype":"venue"
},
  "geometry": {"coordinates":[9.0629367828,55.1926651001],"type":"Point"}
}