{
  "type": "Feature",
  "properties": {
    "addr:full":"Voerg\u00e5rdsvej 48 Dronninglund Danmark 9330",
    "addr:housenumber":"48",
    "addr:postcode":"9330",
    "addr:street":"Voergaardsvej",
    "iso:country":"DK",
    "sg:address":"Voerg\u00e5rdsvej 48",
    "sg:city":"Dronninglund",
    "sg:orig_category":"Haveservice",
    "sg:phone":"+45 98 86 70 01",
    "sg:postcode":"9330",
    "sg:province":"Danmark",
    "wof:name":"N\u00f8rbjerg, Jens",
    "wof:placetype":"venue"
},
  "geometry": {"coordinates":[10.3781728745,57.232749939],"type":"Point"}
}