{
  "type": "Feature",
  "properties": {
    "addr:full":"Kaj Munks Vej 4 Herning Danmark 7400",
    "addr:housenumber":"4",
    "addr:postcode":"7400",
    "addr:street":"Kaj Munks Vej",
    "iso:country":"DK",
    "sg:address":"Kaj Munks Vej 4",
    "sg:city":"Herning",
    "sg:orig_category":"Advokater",
    "sg:phone":"+45 96 26 40 00",
    "sg:postcode":"7400",
    "sg:province":"Danmark",
    "wof:name":"Thygesen, S\u00f8ren",
    "wof:placetype":"venue"
},
  "geometry": {"coordinates":[8.9932088852,56.135345459],"type":"Point"}
}