{
  "type": "Feature",
  "properties": {
    "iso:country":"DK",
    "sg:address":"Fayes Alle 18",
    "sg:city":"Thisted",
    "sg:orig_category":"Sundhedspleje",
    "sg:postcode":"7700",
    "sg:province":"Danmark",
    "wof:name":"Brogaard, Sundhedsplejerske Bente",
    "wof:placetype":"venue"
},
  "geometry": {"coordinates":[8.6835851669,56.9572067261],"type":"Point"}
}