{
  "type": "Feature",
  "properties": {
    "addr:full":"Hattingvej 10 Horsens Danmark 8700",
    "addr:housenumber":"10",
    "addr:postcode":"8700",
    "addr:street":"Hattingvej",
    "iso:country":"DK",
    "sg:address":"Hattingvej 10",
    "sg:city":"Horsens",
    "sg:orig_category":"Emballage",
    "sg:phone":"+45 70 13 14 00",
    "sg:postcode":"8700",
    "sg:province":"Danmark",
    "sg:website":"www.daniscoflexible.com",
    "wof:name":"Amcor Flexibles Europe",
    "wof:placetype":"venue"
},
  "geometry": {"coordinates":[9.8153934479,55.8621368408],"type":"Point"}
}