{
  "type": "Feature",
  "properties": {
    "addr:full":"Hovedgaden 27 Tinglev Danmark 6360",
    "addr:housenumber":"27",
    "addr:postcode":"6360",
    "addr:street":"Hovedgaden",
    "iso:country":"DK",
    "sg:address":"Hovedgaden 27",
    "sg:city":"Tinglev",
    "sg:classifiers":[
        {
            "category":"Communications",
            "type":"Services"
        }
    ],
    "sg:phone":"+45 74 64 42 12",
    "sg:postcode":"6360",
    "sg:province":"Danmark",
    "sg:tags":[
        "og",
        "tv",
        "radio"
    ],
    "wof:name":"Radio-S\u00f8rensen",
    "wof:placetype":"venue"
},
  "geometry": {"coordinates":[9.2538089752,54.9371566772],"type":"Point"}
}