{
  "type": "Feature",
  "properties": {
    "addr:full":"\u00c5benr\u00e5vej 115, Uge Tinglev Danmark 6360",
    "addr:housenumber":"115",
    "addr:postcode":"6360",
    "addr:street":"Aabenraavej;Uge",
    "iso:country":"DK",
    "sg:address":"\u00c5benr\u00e5vej 115, Uge",
    "sg:city":"Tinglev",
    "sg:orig_category":"Forsamlingshuse",
    "sg:phone":"+45 74 64 41 19",
    "sg:postcode":"6360",
    "sg:province":"Danmark",
    "wof:name":"Uge Forsamlingshus",
    "wof:placetype":"venue"
},
  "geometry": {"coordinates":[9.2476491928,54.9349365234],"type":"Point"}
}