{
  "type": "Feature",
  "properties": {
    "addr:full":"Kildevej 8 Spjald Danmark 6971",
    "addr:housenumber":"8",
    "addr:postcode":"6971",
    "addr:street":"Kildevej",
    "iso:country":"DK",
    "sg:address":"Kildevej 8",
    "sg:city":"Spjald",
    "sg:orig_category":"Blomsterhandlere",
    "sg:phone":"+45 97 38 16 42",
    "sg:postcode":"6971",
    "sg:province":"Danmark",
    "wof:name":"Kildevejens Blomster",
    "wof:placetype":"venue"
},
  "geometry": {"coordinates":[8.5077543259,56.1245193481],"type":"Point"}
}