{
  "type": "Feature",
  "properties": {
    "addr:full":"S\u00f8ndermarken 28 Give Danmark 7323",
    "addr:housenumber":"28",
    "addr:postcode":"7323",
    "addr:street":"Sondermarken",
    "iso:country":"DK",
    "sg:address":"S\u00f8ndermarken 28",
    "sg:city":"Give",
    "sg:orig_category":"\u00c3\u02dcvrige institutioner",
    "sg:phone":"+45 75 73 58 05",
    "sg:postcode":"7323",
    "sg:province":"Danmark",
    "wof:name":"Bof\u00e6llesskabet Skr\u00e6nten",
    "wof:placetype":"venue"
},
  "geometry": {"coordinates":[9.2357587814,55.8410072327],"type":"Point"}
}