{
  "type": "Feature",
  "properties": {
    "addr:full":"N\u00f8rregade 7 K\u00f8ge Danmark 4600",
    "addr:housenumber":"7",
    "addr:postcode":"4600",
    "addr:street":"Norregade",
    "iso:country":"DK",
    "sg:address":"N\u00f8rregade 7",
    "sg:city":"K\u00f8ge",
    "sg:orig_category":"Lingeri",
    "sg:phone":"+45 56 65 04 24",
    "sg:postcode":"4600",
    "sg:province":"Danmark",
    "wof:name":"Aase, G.",
    "wof:placetype":"venue"
},
  "geometry": {"coordinates":[12.1829051971,55.4572181702],"type":"Point"}
}