{
  "type": "Feature",
  "properties": {
    "addr:full":"H\u00f8jskolevej 9 Vejle Danmark 7100",
    "addr:housenumber":"9",
    "addr:postcode":"7100",
    "addr:street":"Hojskolevej",
    "iso:country":"DK",
    "sg:address":"H\u00f8jskolevej 9",
    "sg:city":"Vejle",
    "sg:orig_category":"\u00c3\u02dcvrige skoler",
    "sg:phone":"+45 75 85 80 12",
    "sg:postcode":"7100",
    "sg:province":"Danmark",
    "sg:website":"www.husholdningsskole.dk",
    "wof:name":"Vinding Husholdningsskole",
    "wof:placetype":"venue"
},
  "geometry": {"coordinates":[9.5368051529,55.7113952637],"type":"Point"}
}