{
  "type": "Feature",
  "properties": {
    "addr:full":"F\u00e6r\u00f8vej 3  Horsens Danmark 8700",
    "addr:housenumber":"3",
    "addr:postcode":"8700",
    "addr:street":"Faerovej",
    "iso:country":"DK",
    "sg:address":"F\u00e6r\u00f8vej 3 ",
    "sg:city":"Horsens",
    "sg:classifiers":[
        {
            "category":"Food & Beverages",
            "subcategory":"Groceries & Convenience Stores",
            "type":"Retail Goods"
        }
    ],
    "sg:phone":"+45 75 61 13 44",
    "sg:postcode":"8700",
    "sg:province":"Danmark",
    "sg:tags":[
        "drink"
    ],
    "wof:name":"BRDR HONUM A/S",
    "wof:placetype":"venue"
},
  "geometry": {"coordinates":[9.8432445526,55.8621063232],"type":"Point"}
}