{
  "type": "Feature",
  "properties": {
    "addr:full":"Lundager 13 Greve Danmark 2670",
    "addr:housenumber":"13",
    "addr:postcode":"2670",
    "addr:street":"Lundager",
    "iso:country":"DK",
    "sg:address":"Lundager 13",
    "sg:city":"Greve",
    "sg:orig_category":"Poser, en gros",
    "sg:phone":"+45 43 90 37 33",
    "sg:postcode":"2670",
    "sg:province":"Danmark",
    "sg:website":"www.birepo.dk",
    "wof:name":"Birepo System ApS",
    "wof:placetype":"venue"
},
  "geometry": {"coordinates":[12.3077125549,55.5916175842],"type":"Point"}
}