{
  "type": "Feature",
  "properties": {
    "iso:country":"DK",
    "sg:address":"Slotsgade 55",
    "sg:city":"Dronninglund",
    "sg:orig_category":"Undervognsbehandling",
    "sg:phone":"+45 98 84 44 40",
    "sg:postcode":"9330",
    "sg:province":"Danmark",
    "wof:name":"Asaa Auto- & Karosseriv\u00e6rksted",
    "wof:placetype":"venue"
},
  "geometry": {"coordinates":[10.2713804245,57.1546974182],"type":"Point"}
}