{
  "type": "Feature",
  "properties": {
    "addr:full":"Krimsvej 5 1. K\u00f8benhavn S Danmark 2300",
    "addr:housenumber":"5 1",
    "addr:postcode":"2300",
    "addr:street":"Krimsvej;Kobenhavn S Danmark",
    "iso:country":"DK",
    "sg:address":"Krimsvej 5 1.",
    "sg:city":"K\u00f8benhavn S",
    "sg:orig_category":"Skorstensfejere",
    "sg:phone":"+45 32 84 66 20",
    "sg:postcode":"2300",
    "sg:province":"Danmark",
    "wof:name":"Skorstensfejerv\u00e6rkstedet 10.distr.",
    "wof:placetype":"venue"
},
  "geometry": {"coordinates":[-78.1299133301,36.7267417908],"type":"Point"}
}