{
  "type": "Feature",
  "properties": {
    "addr:full":"H. F. Bj\u00f8rns Vej 19 Hj\u00f8rring Danmark 9800",
    "addr:housenumber":"19",
    "addr:postcode":"9800",
    "addr:street":"Bjorns Vej",
    "iso:country":"DK",
    "sg:address":"H. F. Bj\u00f8rns Vej 19",
    "sg:city":"Hj\u00f8rring",
    "sg:orig_category":"Integrerede institutioner",
    "sg:phone":"+45 98 91 07 88",
    "sg:postcode":"9800",
    "sg:province":"Danmark",
    "wof:name":"Bj\u00f8rnen",
    "wof:placetype":"venue"
},
  "geometry": {"coordinates":[0.9861310124,42.9093589783],"type":"Point"}
}