{
  "type": "Feature",
  "properties": {
    "iso:country":"DK",
    "sg:address":"Otto M\u00f8nsteds Vej 1",
    "sg:city":"Aalborg SV",
    "sg:orig_category":"Supermarkeder",
    "sg:phone":"+45 96 34 64 00",
    "sg:postcode":"9200",
    "sg:province":"Danmark",
    "wof:name":"Dreisler Stork\u00f8b",
    "wof:placetype":"venue"
},
  "geometry": {"coordinates":[9.8955850601,57.0145874023],"type":"Point"}
}