{
  "type": "Feature",
  "properties": {
    "addr:full":"Boulevarden 8 Aalborg Danmark 9000",
    "addr:housenumber":"8",
    "addr:postcode":"9000",
    "addr:street":"Boulevarden",
    "iso:country":"DK",
    "sg:address":"Boulevarden 8",
    "sg:city":"Aalborg",
    "sg:classifiers":[
        {
            "category":"Restaurant",
            "type":"Food & Drink"
        }
    ],
    "sg:phone":"+45 98 13 07 88",
    "sg:postcode":"9000",
    "sg:province":"Danmark",
    "wof:name":"City Bodega",
    "wof:placetype":"venue"
},
  "geometry": {"coordinates":[9.9198122025,57.0471229553],"type":"Point"}
}