{
  "type": "Feature",
  "properties": {
    "addr:full":"Jernbanegade 6 St\u00f8vring Danmark 9530",
    "addr:housenumber":"6",
    "addr:postcode":"9530",
    "addr:street":"Jernbanegade",
    "iso:country":"DK",
    "sg:address":"Jernbanegade 6",
    "sg:city":"St\u00f8vring",
    "sg:classifiers":[
        {
            "category":"Home & Garden",
            "subcategory":"Home Furnishings",
            "type":"Retail Goods"
        }
    ],
    "sg:phone":"+45 98 37 40 11",
    "sg:postcode":"9530",
    "sg:province":"Danmark",
    "sg:tags":[
        "gardiner"
    ],
    "wof:name":"Ide Gardiner ApS",
    "wof:placetype":"venue"
},
  "geometry": {"coordinates":[9.8387527466,56.8919181824],"type":"Point"}
}