{
  "type": "Feature",
  "properties": {
    "addr:full":"Kongevejs-Centret 6 H\u00f8rsholm Danmark 2970",
    "addr:housenumber":"6",
    "addr:postcode":"2970",
    "addr:street":"Kongevejs-Centret",
    "iso:country":"DK",
    "sg:address":"Kongevejs-Centret 6",
    "sg:city":"H\u00f8rsholm",
    "sg:orig_category":"Bodegaer",
    "sg:phone":"+45 45 86 55 73",
    "sg:postcode":"2970",
    "sg:province":"Danmark",
    "wof:name":"Pinocchio Bodega",
    "wof:placetype":"venue"
},
  "geometry": {"coordinates":[12.4976701736,55.8879013062],"type":"Point"}
}