{
  "type": "Feature",
  "properties": {
    "addr:full":"Stagetornsvej 5 Frederikssund Danmark 3600",
    "addr:housenumber":"5",
    "addr:postcode":"3600",
    "addr:street":"Stagetornsvej",
    "iso:country":"DK",
    "sg:address":"Stagetornsvej 5",
    "sg:city":"Frederikssund",
    "sg:orig_category":"Musikere",
    "sg:phone":"+45 47 31 06 02",
    "sg:postcode":"3600",
    "sg:province":"Danmark",
    "wof:name":"Thisted, Poul",
    "wof:placetype":"venue"
},
  "geometry": {"coordinates":[12.0804595947,55.8266792297],"type":"Point"}
}