{
  "type": "Feature",
  "properties": {
    "addr:full":"H\u00f8jskolevej 3 -13  Dronninglund Danmark 9330",
    "addr:housenumber":"3 -13",
    "addr:postcode":"9330",
    "addr:street":"Hojskolevej",
    "iso:country":"DK",
    "sg:address":"H\u00f8jskolevej 3 -13 ",
    "sg:city":"Dronninglund",
    "sg:classifiers":[
        {
            "category":"Professional",
            "subcategory":"Business Services",
            "type":"Services"
        }
    ],
    "sg:phone":"+45 98 84 19 33",
    "sg:postcode":"9330",
    "sg:province":"Danmark",
    "sg:tags":[
        "advice"
    ],
    "wof:name":"TRY LANDBRUGSSKOLE",
    "wof:placetype":"venue"
},
  "geometry": {"coordinates":[10.2228908539,57.1417312622],"type":"Point"}
}