{
  "type": "Feature",
  "properties": {
    "addr:full":"Rug\u00e5rdsvej 820, Stilleb\u00e6k Veflinge Danmark 5474",
    "addr:housenumber":"820",
    "addr:postcode":"5474",
    "addr:street":"Rugaardsvej;Stillebaek",
    "iso:country":"DK",
    "sg:address":"Rug\u00e5rdsvej 820, Stilleb\u00e6k",
    "sg:city":"Veflinge",
    "sg:orig_category":"Tryllekunstnere",
    "sg:phone":"+45 64 83 13 83",
    "sg:postcode":"5474",
    "sg:province":"Danmark",
    "wof:name":"Zanito",
    "wof:placetype":"venue"
},
  "geometry": {"coordinates":[10.1596345901,55.4755935669],"type":"Point"}
}