{
  "type": "Feature",
  "properties": {
    "iso:country":"DK",
    "sg:address":"Hvolbyvej 2",
    "sg:city":"Vemb",
    "sg:orig_category":"Maskinstationer",
    "sg:phone":"+45 97 48 11 99",
    "sg:postcode":"7570",
    "sg:province":"Danmark",
    "sg:website":"www.thingstrup-maskinstation.dk",
    "wof:name":"Thingstrup Maskinstation",
    "wof:placetype":"venue"
},
  "geometry": {"coordinates":[8.3830356598,56.3207168579],"type":"Point"}
}