{
  "type": "Feature",
  "properties": {
    "addr:full":"Svejsegangen 12 Karlslunde Danmark 2690",
    "addr:housenumber":"12",
    "addr:postcode":"2690",
    "addr:street":"Svejsegangen",
    "iso:country":"DK",
    "sg:address":"Svejsegangen 12",
    "sg:city":"Karlslunde",
    "sg:orig_category":"Plastposer",
    "sg:phone":"+45 46 15 14 00",
    "sg:postcode":"2690",
    "sg:province":"Danmark",
    "wof:name":"Norlip A/S",
    "wof:placetype":"venue"
},
  "geometry": {"coordinates":[12.2406797409,55.5721893311],"type":"Point"}
}