{
  "type": "Feature",
  "properties": {
    "addr:full":"M\u00f8rdrupvej 123 C, M\u00f8rdrup Esperg\u00e6rde Danmark 3060",
    "addr:housenumber":"123 c",
    "addr:postcode":"3060",
    "addr:street":"Mordrupvej",
    "iso:country":"DK",
    "sg:address":"M\u00f8rdrupvej 123 C, M\u00f8rdrup",
    "sg:city":"Esperg\u00e6rde",
    "sg:orig_category":"Internet, udbydere",
    "sg:phone":"+45 70 26 15 35",
    "sg:postcode":"3060",
    "sg:province":"Danmark",
    "sg:website":"www.micromedia.dk",
    "wof:name":"Micromedia ApS",
    "wof:placetype":"venue"
},
  "geometry": {"coordinates":[11.6512403488,47.8390617371],"type":"Point"}
}