{
  "type": "Feature",
  "properties": {
    "addr:full":"Ringparken 3 Roskilde Danmark 4000",
    "addr:housenumber":"3",
    "addr:postcode":"4000",
    "addr:street":"Ringparken",
    "iso:country":"DK",
    "sg:address":"Ringparken 3",
    "sg:city":"Roskilde",
    "sg:orig_category":"Integrerede institutioner",
    "sg:phone":"+45 46 31 46 98",
    "sg:postcode":"4000",
    "sg:province":"Danmark",
    "wof:name":"Ringparkens B\u00f8rnehus",
    "wof:placetype":"venue"
},
  "geometry": {"coordinates":[12.0897169113,55.6319160461],"type":"Point"}
}