{
  "type": "Feature",
  "properties": {
    "addr:full":"Gl. Kirkevej 2 Knebel Danmark 8420",
    "addr:housenumber":"2",
    "addr:postcode":"8420",
    "addr:street":"Gl. Kirkevej",
    "iso:country":"DK",
    "sg:address":"Gl. Kirkevej 2",
    "sg:city":"Knebel",
    "sg:orig_category":"Murermestre",
    "sg:phone":"+45 86 35 12 93",
    "sg:postcode":"8420",
    "sg:province":"Danmark",
    "wof:name":"Rasmussen, Carsten",
    "wof:placetype":"venue"
},
  "geometry": {"coordinates":[10.4924116135,56.2104225159],"type":"Point"}
}