{
  "type": "Feature",
  "properties": {
    "addr:full":"\u00d8stergade 38 A Maribo Danmark 4930",
    "addr:housenumber":"38 a",
    "addr:postcode":"4930",
    "addr:street":"Ostergade",
    "iso:country":"DK",
    "sg:address":"\u00d8stergade 38 A",
    "sg:city":"Maribo",
    "sg:orig_category":"Arkitekter",
    "sg:phone":"+45 54 78 29 69",
    "sg:postcode":"4930",
    "sg:province":"Danmark",
    "wof:name":"Arkitektg\u00e5rden ApS",
    "wof:placetype":"venue"
},
  "geometry": {"coordinates":[11.5064687729,54.7745246887],"type":"Point"}
}