{
  "type": "Feature",
  "properties": {
    "addr:full":"Lindenborgvej 107, Kornerup Roskilde Danmark 4000",
    "addr:housenumber":"107",
    "addr:postcode":"4000",
    "addr:street":"Lindenborgvej",
    "iso:country":"DK",
    "sg:address":"Lindenborgvej 107, Kornerup",
    "sg:city":"Roskilde",
    "sg:orig_category":"Murermestre",
    "sg:phone":"+45 46 40 22 91",
    "sg:postcode":"4000",
    "sg:province":"Danmark",
    "wof:name":"SD-Byg",
    "wof:placetype":"venue"
},
  "geometry": {"coordinates":[12.0909376144,55.6404838562],"type":"Point"}
}