{
  "type": "Feature",
  "properties": {
    "addr:full":"Bjergbygade 6 Slagelse Danmark 4200",
    "addr:housenumber":"6",
    "addr:postcode":"4200",
    "addr:street":"Bjergbygade",
    "iso:country":"DK",
    "sg:address":"Bjergbygade 6",
    "sg:city":"Slagelse",
    "sg:orig_category":"Reklamebureauer",
    "sg:phone":"+45 58 52 01 88",
    "sg:postcode":"4200",
    "sg:province":"Danmark",
    "sg:website":"www.identitet.dk",
    "wof:name":"www.identitet.dk",
    "wof:placetype":"venue"
},
  "geometry": {"coordinates":[11.3531808853,55.4014205933],"type":"Point"}
}