{
  "type": "Feature",
  "properties": {
    "addr:full":"Slotsgade 38 Dronninglund Danmark 9330",
    "addr:housenumber":"38",
    "addr:postcode":"9330",
    "addr:street":"Slotsgade",
    "iso:country":"DK",
    "sg:address":"Slotsgade 38",
    "sg:city":"Dronninglund",
    "sg:orig_category":"Redningskorps",
    "sg:phone":"+45 70 10 20 30",
    "sg:postcode":"9330",
    "sg:province":"Danmark",
    "wof:name":"Falcks Redningskorps A/S",
    "wof:placetype":"venue"
},
  "geometry": {"coordinates":[10.2848548889,57.1589012146],"type":"Point"}
}