{
  "type": "Feature",
  "properties": {
    "addr:full":"Hammelvej 7 Hadsten Danmark 8370",
    "addr:housenumber":"7",
    "addr:postcode":"8370",
    "addr:street":"Hammelvej",
    "iso:country":"DK",
    "sg:address":"Hammelvej 7",
    "sg:city":"Hadsten",
    "sg:orig_category":"Tandklinikker, Kommunale",
    "sg:phone":"+45 86 98 22 90",
    "sg:postcode":"8370",
    "sg:province":"Danmark",
    "wof:name":"Tandklinikken ved \u00d8stervangskolen",
    "wof:placetype":"venue"
},
  "geometry": {"coordinates":[10.0398263931,56.3213577271],"type":"Point"}
}