{
  "type": "Feature",
  "properties": {
    "addr:full":"Vestergade 56 Horsens Danmark 8700",
    "addr:housenumber":"56",
    "addr:postcode":"8700",
    "addr:street":"Vestergade",
    "iso:country":"DK",
    "sg:address":"Vestergade 56",
    "sg:city":"Horsens",
    "sg:orig_category":"Bagere",
    "sg:phone":"+45 75 62 10 46",
    "sg:postcode":"8700",
    "sg:province":"Danmark",
    "wof:name":"Dresdner Bageriet",
    "wof:placetype":"venue"
},
  "geometry": {"coordinates":[9.839354,55.870483],"type":"Point"}
}