{
  "type": "Feature",
  "properties": {
    "iso:country":"DK",
    "sg:address":"Br\u00f8dregade 7",
    "sg:city":"Randers",
    "sg:orig_category":"Materialister",
    "sg:phone":"+45 86 41 26 27",
    "sg:postcode":"8900",
    "sg:province":"Danmark",
    "wof:name":"Matas",
    "wof:placetype":"venue"
},
  "geometry": {"coordinates":[10.0380220413,56.4601173401],"type":"Point"}
}