{
  "type": "Feature",
  "properties": {
    "addr:full":"Barfredsvej 83 Frederikshavn Danmark 9900",
    "addr:housenumber":"83",
    "addr:postcode":"9900",
    "addr:street":"Barfredsvej",
    "iso:country":"DK",
    "sg:address":"Barfredsvej 83",
    "sg:city":"Frederikshavn",
    "sg:orig_category":"Offentlige sygehuse",
    "sg:phone":"+45 99 20 21 22",
    "sg:postcode":"9900",
    "sg:province":"Danmark",
    "sg:website":"www.frederikshavn-sygehus.dk",
    "wof:name":"Frederikshavn-Skagen Sygehus.",
    "wof:placetype":"venue"
},
  "geometry": {"coordinates":[10.5331373215,57.4463500977],"type":"Point"}
}