{
  "type": "Feature",
  "properties": {
    "iso:country":"DK",
    "sg:address":"Nordre Ringgade 1",
    "sg:city":"\u00c5rhus C",
    "sg:orig_category":"Universiteter",
    "sg:phone":"+45 89 42 11 11",
    "sg:postcode":"8000",
    "sg:province":"Danmark",
    "sg:website":"www.au.dk",
    "wof:name":"Aarhus Universitet",
    "wof:placetype":"venue"
},
  "geometry": {"coordinates":[12.035369873,60.8038711548],"type":"Point"}
}