{
  "type": "Feature",
  "properties": {
    "addr:full":"Jens Birkholmsvej 27 Faaborg Danmark 5600",
    "addr:housenumber":"27",
    "addr:postcode":"5600",
    "addr:street":"Jens Birkholmsvej",
    "iso:country":"DK",
    "sg:address":"Jens Birkholmsvej 27",
    "sg:city":"Faaborg",
    "sg:orig_category":"EDB - udstyr",
    "sg:phone":"+45 62 61 76 40",
    "sg:postcode":"5600",
    "sg:province":"Danmark",
    "wof:name":"F\u00e5borg Data",
    "wof:placetype":"venue"
},
  "geometry": {"coordinates":[10.2284202576,55.1054801941],"type":"Point"}
}