{
  "type": "Feature",
  "properties": {
    "addr:full":"Egevolden 148 Hvidovre Danmark 2650",
    "addr:housenumber":"148",
    "addr:postcode":"2650",
    "addr:street":"Egevolden",
    "iso:country":"DK",
    "sg:address":"Egevolden 148",
    "sg:city":"Hvidovre",
    "sg:orig_category":"Gulvafslibning",
    "sg:phone":"+45 23 44 87 89",
    "sg:postcode":"2650",
    "sg:province":"Danmark",
    "wof:name":"Clemme's Gulvservice",
    "wof:placetype":"venue"
},
  "geometry": {"coordinates":[12.4676971436,55.6261062622],"type":"Point"}
}