{
  "type": "Feature",
  "properties": {
    "addr:full":"v/ F. K. Marked, Hovedgaden 8, Tvis Holstebro Danmark 7500",
    "addr:housenumber":"8",
    "addr:postcode":"7500",
    "addr:street":"Hovedgaden;Tvis",
    "iso:country":"DK",
    "sg:address":"v/ F. K. Marked, Hovedgaden 8, Tvis",
    "sg:city":"Holstebro",
    "sg:orig_category":"Apoteker og -udsalg",
    "sg:phone":"+45 97 43 50 15",
    "sg:postcode":"7500",
    "sg:province":"Danmark",
    "wof:name":"H\u00e5ndk\u00f8bsudsalget i Tvis",
    "wof:placetype":"venue"
},
  "geometry": {"coordinates":[8.6202583313,56.3625221252],"type":"Point"}
}