{
  "type": "Feature",
  "properties": {
    "iso:country":"DK",
    "sg:address":"Plantagevej 9, D\u00f8jringe",
    "sg:city":"Sor\u00f8",
    "sg:orig_category":"Hundesaloner",
    "sg:phone":"+45 51 24 84 94",
    "sg:postcode":"4180",
    "sg:province":"Danmark",
    "wof:name":"Kitta's Hundetrim",
    "wof:placetype":"venue"
},
  "geometry": {"coordinates":[-102.94467926030001,45.4534721375],"type":"Point"}
}