{
  "type": "Feature",
  "properties": {
    "iso:country":"DK",
    "sg:address":"Vestergade 70",
    "sg:city":"Odense C",
    "sg:orig_category":"Ejendomshandel",
    "sg:phone":"+45 70 23 00 69",
    "sg:postcode":"5000",
    "sg:province":"Danmark",
    "sg:website":"www.colliershv.dk",
    "wof:name":"Vestergaard, Colliers Hans",
    "wof:placetype":"venue"
},
  "geometry": {"coordinates":[10.3830118179,55.39453125],"type":"Point"}
}