{
  "type": "Feature",
  "properties": {
    "addr:full":"Slotsgade 5 Slagelse Danmark 4200",
    "addr:housenumber":"5",
    "addr:postcode":"4200",
    "addr:street":"Slotsgade",
    "iso:country":"DK",
    "sg:address":"Slotsgade 5",
    "sg:city":"Slagelse",
    "sg:classifiers":[
        {
            "category":"Restaurant",
            "type":"Food & Drink"
        }
    ],
    "sg:phone":"+45 58 52 63 78",
    "sg:postcode":"4200",
    "sg:province":"Danmark",
    "wof:name":"Pussy Cat",
    "wof:placetype":"venue"
},
  "geometry": {"coordinates":[11.3547077179,55.4019966125],"type":"Point"}
}