{
  "type": "Feature",
  "properties": {
    "addr:full":"Fmd.: Anna-Elise Christoffersen, Hovedvejen 33, Kirkeby Stenstrup Danmark 5771",
    "addr:housenumber":"33",
    "addr:postcode":"5771",
    "addr:street":"Hovedvejen",
    "iso:country":"DK",
    "sg:address":"Fmd.: Anna-Elise Christoffersen, Hovedvejen 33, Kirkeby",
    "sg:city":"Stenstrup",
    "sg:orig_category":"\u00c3\u2020ldreorganisationer og klubber",
    "sg:phone":"+45 62 26 11 48",
    "sg:postcode":"5771",
    "sg:province":"Danmark",
    "wof:name":"Pensionistforening Stenstrup Lunde Kirkeby",
    "wof:placetype":"venue"
},
  "geometry": {"coordinates":[10.5054998398,55.1317520142],"type":"Point"}
}