{
  "type": "Feature",
  "properties": {
    "addr:full":"Industrivej 2, V. \u00c5by Faaborg Danmark 5600",
    "addr:housenumber":"2",
    "addr:postcode":"5600",
    "addr:street":"Industrivej;Aaby",
    "iso:country":"DK",
    "sg:address":"Industrivej 2, V. \u00c5by",
    "sg:city":"Faaborg",
    "sg:orig_category":"Maskinfabrikker",
    "sg:phone":"+45 63 61 82 00",
    "sg:postcode":"5600",
    "sg:province":"Danmark",
    "sg:website":"www.damas.com",
    "wof:name":"Damas A/S",
    "wof:placetype":"venue"
},
  "geometry": {"coordinates":[10.2400531769,55.0950622559],"type":"Point"}
}