{
  "type": "Feature",
  "properties": {
    "iso:country":"DK",
    "sg:address":"Sognepr\u00e6st: Eva G. Lauridsen, Pr\u00e6steg\u00e5rdsvej 20",
    "sg:city":"Vemb",
    "sg:orig_category":"Kirkesogne",
    "sg:phone":"+45 97 48 10 19",
    "sg:postcode":"7570",
    "sg:province":"Danmark",
    "wof:name":"G\u00f8rding, Vemb og Bur Sogne",
    "wof:placetype":"venue"
},
  "geometry": {"coordinates":[8.343793869,56.343082428],"type":"Point"}
}