{
  "type": "Feature",
  "properties": {
    "addr:full":"Vester Alle 1 Hobro Danmark 9500",
    "addr:housenumber":"1",
    "addr:postcode":"9500",
    "addr:street":"Vester Alle",
    "iso:country":"DK",
    "sg:address":"Vester Alle 1",
    "sg:city":"Hobro",
    "sg:classifiers":[
        {
            "category":"Communications",
            "subcategory":"Film & Video Production",
            "type":"Services"
        }
    ],
    "sg:phone":"+45 98 52 02 05",
    "sg:postcode":"9500",
    "sg:province":"Danmark",
    "sg:tags":[
        "radio-",
        "og",
        "tv-service"
    ],
    "wof:name":"Expert Service",
    "wof:placetype":"venue"
},
  "geometry": {"coordinates":[9.7927532196,56.6349105835],"type":"Point"}
}