{
  "type": "Feature",
  "properties": {
    "iso:country":"DK",
    "sg:address":"Smedelundsgade 22",
    "sg:city":"Holb\u00e6k",
    "sg:orig_category":"Sko",
    "sg:phone":"+45 59 44 37 08",
    "sg:postcode":"4300",
    "sg:province":"Danmark",
    "wof:name":"Kornsted Sko",
    "wof:placetype":"venue"
},
  "geometry": {"coordinates":[76.3070983887,14.277130127],"type":"Point"}
}