{
  "type": "Feature",
  "properties": {
    "addr:full":"Danmarksgade 16 Ikast Danmark 7430",
    "addr:housenumber":"16",
    "addr:postcode":"7430",
    "addr:street":"Danmarksgade",
    "iso:country":"DK",
    "sg:address":"Danmarksgade 16",
    "sg:city":"Ikast",
    "sg:orig_category":"Tekstilindustri",
    "sg:phone":"+45 97 25 21 99",
    "sg:postcode":"7430",
    "sg:province":"Danmark",
    "wof:name":"Capello di Roma",
    "wof:placetype":"venue"
},
  "geometry": {"coordinates":[9.1587667465,56.1377296448],"type":"Point"}
}