{
  "type": "Feature",
  "properties": {
    "addr:full":"Rytterstaldstr\u00e6de 5 Slagelse Danmark 4200",
    "addr:housenumber":"5",
    "addr:postcode":"4200",
    "addr:street":"Rytterstaldstraede",
    "iso:country":"DK",
    "sg:address":"Rytterstaldstr\u00e6de 5",
    "sg:city":"Slagelse",
    "sg:orig_category":"Diners transportables",
    "sg:phone":"+45 58 53 27 27",
    "sg:postcode":"4200",
    "sg:province":"Danmark",
    "sg:website":"www.vdt-sj.dk",
    "wof:name":"Vestsj\u00e6llands Diner Transportable",
    "wof:placetype":"venue"
},
  "geometry": {"coordinates":[11.3546028137,55.4006118774],"type":"Point"}
}