{
  "type": "Feature",
  "properties": {
    "iso:country":"DK",
    "sg:address":"Vodroffsvej 49",
    "sg:city":"Frederiksberg",
    "sg:orig_category":"Kiosker",
    "sg:phone":"+45 35 36 13 46",
    "sg:postcode":"1900",
    "sg:province":"Danmark",
    "wof:name":"Service Kiosken",
    "wof:placetype":"venue"
},
  "geometry": {"coordinates":[12.5546913147,55.679649353],"type":"Point"}
}