{
  "type": "Feature",
  "properties": {
    "iso:country":"DK",
    "sg:address":"Dianavej 3",
    "sg:city":"Vejle",
    "sg:orig_category":"Autoelektro",
    "sg:phone":"+45 75 82 55 22",
    "sg:postcode":"7100",
    "sg:province":"Danmark",
    "sg:website":"www.bosch-vejle.dk",
    "wof:name":"Vejle Bil Elektro",
    "wof:placetype":"venue"
},
  "geometry": {"coordinates":[9.5643949509,55.7194747925],"type":"Point"}
}