{
  "type": "Feature",
  "properties": {
    "addr:full":"Fabriksvej 2  Skamby Danmark 5485",
    "addr:housenumber":"2",
    "addr:postcode":"5485",
    "addr:street":"Fabriksvej",
    "iso:country":"DK",
    "sg:address":"Fabriksvej 2 ",
    "sg:city":"Skamby",
    "sg:classifiers":[
        {
            "category":"Home & Garden",
            "subcategory":"Home Furnishings",
            "type":"Retail Goods"
        }
    ],
    "sg:phone":"+45 64 85 10 08",
    "sg:postcode":"5485",
    "sg:province":"Danmark",
    "sg:tags":[
        "household"
    ],
    "wof:name":"N EILERSEN A/S",
    "wof:placetype":"venue"
},
  "geometry": {"coordinates":[10.2777843475,55.5250854492],"type":"Point"}
}