{
  "type": "Feature",
  "properties": {
    "addr:full":"Frederiksgade 7 Skive Danmark 7800",
    "addr:housenumber":"7",
    "addr:postcode":"7800",
    "addr:street":"Frederiksgade",
    "iso:country":"DK",
    "sg:address":"Frederiksgade 7",
    "sg:city":"Skive",
    "sg:orig_category":"Helseprodukter",
    "sg:phone":"+45 97 52 96 44",
    "sg:postcode":"7800",
    "sg:province":"Danmark",
    "wof:name":"Helseboden",
    "wof:placetype":"venue"
},
  "geometry": {"coordinates":[9.0250930786,56.567237854],"type":"Point"}
}