{
  "type": "Feature",
  "properties": {
    "addr:full":"\u00d8sterbro 3 Odense C Danmark 5000",
    "addr:housenumber":"3",
    "addr:postcode":"5000",
    "addr:street":"Osterbro",
    "iso:country":"DK",
    "sg:address":"\u00d8sterbro 3",
    "sg:city":"Odense C",
    "sg:orig_category":"Faglige organisationer og foreninger",
    "sg:phone":"+45 66 66 29 00",
    "sg:postcode":"5000",
    "sg:province":"Danmark",
    "wof:name":"TKF-Fyn",
    "wof:placetype":"venue"
},
  "geometry": {"coordinates":[10.4021720886,55.4020118713],"type":"Point"}
}