{
  "type": "Feature",
  "properties": {
    "iso:country":"DK",
    "sg:address":"Fmd.: Ivan Christensen, Finnsvej 62, 1.",
    "sg:city":"Frederikshavn",
    "sg:orig_category":"Soldaterforeninger",
    "sg:phone":"+45 98 42 08 63",
    "sg:postcode":"9900",
    "sg:province":"Danmark",
    "wof:name":"Forsvarsbr\u00f8dre, De Danske",
    "wof:placetype":"venue"
},
  "geometry": {"coordinates":[10.5362997055,57.4396400452],"type":"Point"}
}