{
  "type": "Feature",
  "properties": {
    "addr:full":"Sognepr\u00e6st: Stig Skat Andersen (K/B), \u00d8stergade 3 Egtved Danmark 6040",
    "addr:housenumber":"k / b;3",
    "addr:postcode":"6040",
    "addr:street":"Sognepraest Stig;Ostergade",
    "iso:country":"DK",
    "sg:address":"Sognepr\u00e6st: Stig Skat Andersen (K/B), \u00d8stergade 3",
    "sg:city":"Egtved",
    "sg:orig_category":"Kirkesogne",
    "sg:phone":"+45 75 55 13 40",
    "sg:postcode":"6040",
    "sg:province":"Danmark",
    "wof:name":"Egtved Sogn",
    "wof:placetype":"venue"
},
  "geometry": {"coordinates":[9.3087482452,55.6161613464],"type":"Point"}
}