{
  "type": "Feature",
  "properties": {
    "addr:full":"Boserupvej 100 Roskilde Danmark 4000",
    "addr:housenumber":"100",
    "addr:postcode":"4000",
    "addr:street":"Boserupvej",
    "iso:country":"DK",
    "sg:address":"Boserupvej 100",
    "sg:city":"Roskilde",
    "sg:orig_category":"Private skoler",
    "sg:phone":"+45 46 32 32 50",
    "sg:postcode":"4000",
    "sg:province":"Danmark",
    "wof:name":"Roskilde Friskole",
    "wof:placetype":"venue"
},
  "geometry": {"coordinates":[12.0323534012,55.6553611755],"type":"Point"}
}