{
  "type": "Feature",
  "properties": {
    "iso:country":"DK",
    "sg:address":"Ny \u00d8stergade 20",
    "sg:city":"K\u00f8benhavn",
    "sg:classifiers":[
        {
            "category":"Banks & Credit Unions",
            "subcategory":"Bank",
            "type":"Services"
        }
    ],
    "sg:phone":"+45 33 36 09 44",
    "sg:postcode":"1101",
    "sg:province":"Danmark",
    "sg:tags":[
        "banking",
        "institution"
    ],
    "wof:name":"JUHLER HOLDING A/S",
    "wof:placetype":"venue"
},
  "geometry": {"coordinates":[-76.501892,42.856319],"type":"Point"}
}