{
  "type": "Feature",
  "properties": {
    "addr:full":"Pedersholmparken 12 Frederikssund Danmark 3600",
    "addr:housenumber":"12",
    "addr:postcode":"3600",
    "addr:street":"Pedersholmparken",
    "iso:country":"DK",
    "sg:address":"Pedersholmparken 12",
    "sg:city":"Frederikssund",
    "sg:orig_category":"Autoreparation og -service",
    "sg:phone":"+45 47 31 46 20",
    "sg:postcode":"3600",
    "sg:province":"Danmark",
    "sg:website":"www.max-martin.dk",
    "wof:name":"Max & Martin A/S",
    "wof:placetype":"venue"
},
  "geometry": {"coordinates":[12.0920295715,55.8241500854],"type":"Point"}
}