{
  "type": "Feature",
  "properties": {
    "iso:country":"DK",
    "sg:address":"Hovedgaden 58",
    "sg:city":"Snedsted",
    "sg:orig_category":"Ejendomshandel",
    "sg:phone":"+45 97 93 49 00",
    "sg:postcode":"7752",
    "sg:province":"Danmark",
    "sg:website":"www.ejendomsringen.dk",
    "wof:name":"Ejendomsringen Thy",
    "wof:placetype":"venue"
},
  "geometry": {"coordinates":[8.5233078003,56.8927955627],"type":"Point"}
}