{
  "type": "Feature",
  "properties": {
    "addr:full":"Kochsgade 112 Odense C Danmark 5000",
    "addr:housenumber":"112",
    "addr:postcode":"5000",
    "addr:street":"Kochsgade",
    "iso:country":"DK",
    "sg:address":"Kochsgade 112",
    "sg:city":"Odense C",
    "sg:orig_category":"Farve og tapet",
    "sg:phone":"+45 66 12 58 34",
    "sg:postcode":"5000",
    "sg:province":"Danmark",
    "wof:name":"Kochsgades Farvehandel ApS",
    "wof:placetype":"venue"
},
  "geometry": {"coordinates":[10.4057350159,55.4092521667],"type":"Point"}
}