{
  "type": "Feature",
  "properties": {
    "iso:country":"DK",
    "sg:address":"Fmd. Tom Mortensen, Engdalen 2",
    "sg:city":"Grenaa",
    "sg:orig_category":"Boligselskaber",
    "sg:phone":"+45 87 58 10 00",
    "sg:postcode":"8500",
    "sg:province":"Danmark",
    "wof:name":"Vanf\u00f8res Boligselskab, De",
    "wof:placetype":"venue"
},
  "geometry": {"coordinates":[10.8774929047,56.4126853943],"type":"Point"}
}