{
  "type": "Feature",
  "properties": {
    "addr:full":"Gyvelstien 12, Thorupstrand Fjerritslev Danmark 9690",
    "addr:housenumber":"12",
    "addr:postcode":"9690",
    "addr:street":"Gyvelstien;Thorupstrand",
    "iso:country":"DK",
    "sg:address":"Gyvelstien 12, Thorupstrand",
    "sg:city":"Fjerritslev",
    "sg:orig_category":"Faglige organisationer og foreninger",
    "sg:phone":"+45 98 22 55 72",
    "sg:postcode":"9690",
    "sg:province":"Danmark",
    "wof:name":"Thorupstrand Fiskeriforening",
    "wof:placetype":"venue"
},
  "geometry": {"coordinates":[9.2667350769,57.0882301331],"type":"Point"}
}