{
  "type": "Feature",
  "properties": {
    "iso:country":"DK",
    "sg:address":"Sindalsvej 34 ",
    "sg:city":"Risskov",
    "sg:classifiers":[
        {
            "category":"Sports & Exercise",
            "subcategory":"Playing Field",
            "type":"Entertainment"
        }
    ],
    "sg:phone":"+45 87 42 70 00",
    "sg:postcode":"8240",
    "sg:province":"Danmark",
    "sg:tags":[
        "game"
    ],
    "wof:name":"T C ELECTRONIC A/S",
    "wof:placetype":"venue"
},
  "geometry": {"coordinates":[10.2126092911,56.2096366882],"type":"Point"}
}