{
  "type": "Feature",
  "properties": {
    "addr:full":"Kredsleder: Svend Engelund, L\u00f8nkildevej 7, Lindelse Rudk\u00f8bing Danmark 5900",
    "addr:housenumber":"7",
    "addr:postcode":"5900",
    "addr:street":"Lonkildevej",
    "iso:country":"DK",
    "sg:address":"Kredsleder: Svend Engelund, L\u00f8nkildevej 7, Lindelse",
    "sg:city":"Rudk\u00f8bing",
    "sg:orig_category":"Beredskabsforbund",
    "sg:phone":"+45 62 57 12 09",
    "sg:postcode":"5900",
    "sg:province":"Danmark",
    "wof:name":"Beredskabsforbundet",
    "wof:placetype":"venue"
},
  "geometry": {"coordinates":[10.716315,54.935261],"type":"Point"}
}