{
  "type": "Feature",
  "properties": {
    "addr:full":"Nordstrandsvej 89 Nyk\u00f8bing Danmark 4500",
    "addr:housenumber":"89",
    "addr:postcode":"4500",
    "addr:street":"Nordstrandsvej",
    "iso:country":"DK",
    "sg:address":"Nordstrandsvej 89",
    "sg:city":"Nyk\u00f8bing",
    "sg:orig_category":"Feriekolonier",
    "sg:phone":"+45 59 91 08 08",
    "sg:postcode":"4500",
    "sg:province":"Danmark",
    "wof:name":"Carlsbergg\u00e5rden Feriekoloni",
    "wof:placetype":"venue"
},
  "geometry": {"coordinates":[16.0969600677,78.3159866333],"type":"Point"}
}