{
  "type": "Feature",
  "properties": {
    "addr:full":"Kordilgade 17 Kalundborg Danmark 4400",
    "addr:housenumber":"17",
    "addr:postcode":"4400",
    "addr:street":"Kordilgade",
    "iso:country":"DK",
    "sg:address":"Kordilgade 17",
    "sg:city":"Kalundborg",
    "sg:orig_category":"Cafeer",
    "sg:phone":"+45 59 51 00 57",
    "sg:postcode":"4400",
    "sg:province":"Danmark",
    "sg:website":"www.cafe-bogart.dk",
    "wof:name":"Bogart, Caf\u00e9",
    "wof:placetype":"venue"
},
  "geometry": {"coordinates":[11.0888805389,55.6805686951],"type":"Point"}
}