{
  "type": "Feature",
  "properties": {
    "addr:full":"Dir.: S\u00f8ren B\u00f8nnerup Jensen, Nordborgvej 11 Silkeborg Danmark 8600",
    "addr:housenumber":"11",
    "addr:postcode":"8600",
    "addr:street":"Dir.;Nordborgvej",
    "iso:country":"DK",
    "sg:address":"Dir.: S\u00f8ren B\u00f8nnerup Jensen, Nordborgvej 11",
    "sg:city":"Silkeborg",
    "sg:orig_category":"Musik og sang",
    "sg:phone":"+45 86 81 27 42",
    "sg:postcode":"8600",
    "sg:province":"Danmark",
    "wof:name":"Sk\u00e6gk\u00e6r Skoleorkester",
    "wof:placetype":"venue"
},
  "geometry": {"coordinates":[9.5524425507,56.1693305969],"type":"Point"}
}