{
  "type": "Feature",
  "properties": {
    "addr:full":"v/Solveig Sonne Hornsh\u00f8j, Urlev Kirkevej 12 Hedensted Danmark 8722",
    "addr:housenumber":"12",
    "addr:postcode":"8722",
    "addr:street":"Hornshoj Urlev Kirkevej",
    "iso:country":"DK",
    "sg:address":"v/Solveig Sonne Hornsh\u00f8j, Urlev Kirkevej 12",
    "sg:city":"Hedensted",
    "sg:orig_category":"Oplysningsforbund",
    "sg:postcode":"8722",
    "sg:province":"Danmark",
    "wof:name":"D\u00f8ves og H\u00f8reh\u00e6mmedes Oplysningsforbund, afd. Fyn",
    "wof:placetype":"venue"
},
  "geometry": {"coordinates":[9.6973247528,55.7688903809],"type":"Point"}
}