{
  "type": "Feature",
  "properties": {
    "addr:full":"Kl\u00f8vervej 16 Billund Danmark 7190",
    "addr:housenumber":"16",
    "addr:postcode":"7190",
    "addr:street":"Klovervej",
    "iso:country":"DK",
    "sg:address":"Kl\u00f8vervej 16",
    "sg:city":"Billund",
    "sg:orig_category":"Web- og Internetdesign",
    "sg:phone":"+45 76 50 20 36",
    "sg:postcode":"7190",
    "sg:province":"Danmark",
    "sg:website":"www.creascop.dk",
    "wof:name":"CreaScop",
    "wof:placetype":"venue"
},
  "geometry": {"coordinates":[9.1218852997,55.7226371765],"type":"Point"}
}