{
  "type": "Feature",
  "properties": {
    "addr:full":"H\u00f8jvangens Torv 4 Skanderborg Danmark 8660",
    "addr:housenumber":"4",
    "addr:postcode":"8660",
    "addr:street":"Hojvangens Torv",
    "iso:country":"DK",
    "sg:address":"H\u00f8jvangens Torv 4",
    "sg:city":"Skanderborg",
    "sg:orig_category":"Kommunale folkeskoler",
    "sg:phone":"+45 86 52 20 66",
    "sg:postcode":"8660",
    "sg:province":"Danmark",
    "wof:name":"Niels Ebbesen Skolen",
    "wof:placetype":"venue"
},
  "geometry": {"coordinates":[9.9450016022,56.0452041626],"type":"Point"}
}