{
  "type": "Feature",
  "properties": {
    "addr:full":"M\u00f8llebakken 18 Tommerup Danmark 5690",
    "addr:housenumber":"18",
    "addr:postcode":"5690",
    "addr:street":"Mollebakken",
    "iso:country":"DK",
    "sg:address":"M\u00f8llebakken 18",
    "sg:city":"Tommerup",
    "sg:orig_category":"Motorcykler",
    "sg:phone":"+45 64 76 34 76",
    "sg:postcode":"5690",
    "sg:province":"Danmark",
    "wof:name":"Claus May Motorcykel Center",
    "wof:placetype":"venue"
},
  "geometry": {"coordinates":[10.2026767731,55.3241958618],"type":"Point"}
}