{
  "type": "Feature",
  "properties": {
    "addr:full":"Stolpedalsparken 110 Aalborg Danmark 9000",
    "addr:housenumber":"110",
    "addr:postcode":"9000",
    "addr:street":"Stolpedalsparken",
    "iso:country":"DK",
    "sg:address":"Stolpedalsparken 110",
    "sg:city":"Aalborg",
    "sg:orig_category":"Ejendomshandel",
    "sg:phone":"+45 98 18 82 12",
    "sg:postcode":"9000",
    "sg:province":"Danmark",
    "wof:name":"Knudsen, Leif",
    "wof:placetype":"venue"
},
  "geometry": {"coordinates":[9.8906822205,57.0362472534],"type":"Point"}
}