{
  "type": "Feature",
  "properties": {
    "addr:full":"v/ Okkels Birk, S\u00f8nderskovvej 11, Ilskov Sunds Danmark 7451",
    "addr:housenumber":"11",
    "addr:postcode":"7451",
    "addr:street":"Sonderskovvej;Ilskov",
    "iso:country":"DK",
    "sg:address":"v/ Okkels Birk, S\u00f8nderskovvej 11, Ilskov",
    "sg:city":"Sunds",
    "sg:orig_category":"Borger- og beboerforeninger",
    "sg:phone":"+45 97 14 50 31",
    "sg:postcode":"7451",
    "sg:province":"Danmark",
    "wof:name":"Ilskov Sogneforening",
    "wof:placetype":"venue"
},
  "geometry": {"coordinates":[9.0151100159,56.2057800293],"type":"Point"}
}