{
  "type": "Feature",
  "properties": {
    "addr:full":"Kastanievej 23 Frederiksv\u00e6rk Danmark 3300",
    "addr:housenumber":"23",
    "addr:postcode":"3300",
    "addr:street":"Kastanievej",
    "iso:country":"DK",
    "sg:address":"Kastanievej 23",
    "sg:city":"Frederiksv\u00e6rk",
    "sg:orig_category":"Ferielejligheder",
    "sg:phone":"+45 47 74 51 40",
    "sg:postcode":"3300",
    "sg:province":"Danmark",
    "sg:website":"www.asserbo.dk",
    "wof:name":"Asserbo Sommerhusudlejning ApS",
    "wof:placetype":"venue"
},
  "geometry": {"coordinates":[12.0214824677,55.9648513794],"type":"Point"}
}