{
  "type": "Feature",
  "properties": {
    "addr:full":"Borgergade 4 Kolding Danmark 6000",
    "addr:housenumber":"4",
    "addr:postcode":"6000",
    "addr:street":"Borgergade",
    "iso:country":"DK",
    "sg:address":"Borgergade 4",
    "sg:city":"Kolding",
    "sg:orig_category":"Skilte",
    "sg:phone":"+45 75 53 97 07",
    "sg:postcode":"6000",
    "sg:province":"Danmark",
    "wof:name":"Skilteg\u00e5rden ApS",
    "wof:placetype":"venue"
},
  "geometry": {"coordinates":[9.468708992,55.49168396],"type":"Point"}
}