{
  "type": "Feature",
  "properties": {
    "addr:full":"M\u00f8llegade 4 H\u00f8jer Danmark 6280",
    "addr:housenumber":"4",
    "addr:postcode":"6280",
    "addr:street":"Mollegade",
    "iso:country":"DK",
    "sg:address":"M\u00f8llegade 4",
    "sg:city":"H\u00f8jer",
    "sg:orig_category":"Gulvafslibning",
    "sg:phone":"+45 20 43 60 40",
    "sg:postcode":"6280",
    "sg:province":"Danmark",
    "wof:name":"Uter, Knut",
    "wof:placetype":"venue"
},
  "geometry": {"coordinates":[-2.1972899437,49.2049789429],"type":"Point"}
}