{
  "type": "Feature",
  "properties": {
    "iso:country":"DK",
    "sg:address":"Nordre Strandvej 341 B",
    "sg:city":"Hornb\u00e6k",
    "sg:orig_category":"Ejendomshandel",
    "sg:phone":"+45 49 70 45 05",
    "sg:postcode":"3100",
    "sg:province":"Danmark",
    "wof:name":"DanBolig - Hornb\u00e6k",
    "wof:placetype":"venue"
},
  "geometry": {"coordinates":[12.035369873,60.8038711548],"type":"Point"}
}