{
  "type": "Feature",
  "properties": {
    "addr:full":"J\u00e6gersborg All\u00e9 32 A Charlottenlund Danmark 2920",
    "addr:housenumber":"32 a",
    "addr:postcode":"2920",
    "addr:street":"Jaegersborg Alle\u0301",
    "iso:country":"DK",
    "sg:address":"J\u00e6gersborg All\u00e9 32 A",
    "sg:city":"Charlottenlund",
    "sg:orig_category":"Fotohandlere",
    "sg:phone":"+45 39 64 16 34",
    "sg:postcode":"2920",
    "sg:province":"Danmark",
    "wof:name":"J\u00e6gersborg Foto",
    "wof:placetype":"venue"
},
  "geometry": {"coordinates":[12.5721197128,55.7532615662],"type":"Point"}
}