{
  "type": "Feature",
  "properties": {
    "iso:country":"DK",
    "sg:address":"Fars\u00f8vej 163, Fredbjerg",
    "sg:city":"Fars\u00f8",
    "sg:orig_category":"Maskinstationer",
    "sg:phone":"+45 98 63 13 44",
    "sg:postcode":"9640",
    "sg:province":"Danmark",
    "wof:name":"Fars\u00f8 Markservice",
    "wof:placetype":"venue"
},
  "geometry": {"coordinates":[9.1937885284,56.6945037842],"type":"Point"}
}