{
  "type": "Feature",
  "properties": {
    "addr:full":"Viborgvej 164 Randers Danmark 8900",
    "addr:housenumber":"164",
    "addr:postcode":"8900",
    "addr:street":"Viborgvej",
    "iso:country":"DK",
    "sg:address":"Viborgvej 164",
    "sg:city":"Randers",
    "sg:orig_category":"Autoreparation og -service",
    "sg:phone":"+45 86 42 61 60",
    "sg:postcode":"8900",
    "sg:province":"Danmark",
    "wof:name":"Randers Autohandel's Autov\u00e6rksted",
    "wof:placetype":"venue"
},
  "geometry": {"coordinates":[9.9836378098,56.467880249],"type":"Point"}
}