{
  "type": "Feature",
  "properties": {
    "addr:full":"St\u00e6rk\u00e6rvej 50 Bjerringbro Danmark 8850",
    "addr:housenumber":"50",
    "addr:postcode":"8850",
    "addr:street":"Staerkaervej",
    "iso:country":"DK",
    "sg:address":"St\u00e6rk\u00e6rvej 50",
    "sg:city":"Bjerringbro",
    "sg:orig_category":"Stenhuggere",
    "sg:phone":"+45 87 50 03 40",
    "sg:postcode":"8850",
    "sg:province":"Danmark",
    "sg:website":"www.stenhuggeri-aps.dk",
    "wof:name":"Bjerringbro Stenhuggeri",
    "wof:placetype":"venue"
},
  "geometry": {"coordinates":[9.6546850204,56.3754692078],"type":"Point"}
}