{
  "type": "Feature",
  "properties": {
    "iso:country":"DK",
    "sg:address":"Skindergade 6",
    "sg:city":"K\u00f8benhavn",
    "sg:orig_category":"Skind",
    "sg:phone":"+45 33 13 88 31",
    "sg:postcode":"1159",
    "sg:province":"Danmark",
    "sg:website":"www.skindhuset.dk",
    "wof:name":"Skindhuset A/S",
    "wof:placetype":"venue"
},
  "geometry": {"coordinates":[12.5747699738,55.6798706055],"type":"Point"}
}