{
  "type": "Feature",
  "properties": {
    "addr:full":"Gammel Kongevej 86 Frederiksberg Danmark 1850",
    "addr:housenumber":"86",
    "addr:postcode":"1850",
    "addr:street":"Gammel Kongevej",
    "iso:country":"DK",
    "sg:address":"Gammel Kongevej 86",
    "sg:city":"Frederiksberg",
    "sg:orig_category":"Fotohandlere",
    "sg:phone":"+45 33 24 26 94",
    "sg:postcode":"1850",
    "sg:province":"Danmark",
    "wof:name":"Frederiksberg Foto",
    "wof:placetype":"venue"
},
  "geometry": {"coordinates":[12.5487308502,55.6749458313],"type":"Point"}
}