{
  "type": "Feature",
  "properties": {
    "iso:country":"DK",
    "sg:address":"Kolkevej 8 A",
    "sg:city":"Kettinge",
    "sg:orig_category":"Konsulentvirksomheder",
    "sg:phone":"+45 54 87 35 60",
    "sg:postcode":"4892",
    "sg:province":"Danmark",
    "wof:name":"Jensen Netv\u00e6rksm\u00e6gler, Anders Finn",
    "wof:placetype":"venue"
},
  "geometry": {"coordinates":[11.7274465561,54.6951217651],"type":"Point"}
}