{
  "type": "Feature",
  "properties": {
    "addr:full":"Slotsgade 21, 2. Odense C Danmark 5000",
    "addr:housenumber":"21 2",
    "addr:postcode":"5000",
    "addr:street":"Slotsgade",
    "iso:country":"DK",
    "sg:address":"Slotsgade 21, 2.",
    "sg:city":"Odense C",
    "sg:orig_category":"Advokater",
    "sg:phone":"+45 66 12 43 44",
    "sg:postcode":"5000",
    "sg:province":"Danmark",
    "wof:name":"Andersen, Poul M\u00f8ller",
    "wof:placetype":"venue"
},
  "geometry": {"coordinates":[10.3827066422,55.3966407776],"type":"Point"}
}