{
  "type": "Feature",
  "properties": {
    "addr:full":"Fmd.: M. Bjergegaard, Pilevangen 42 Br\u00f8ndby Strand Danmark 2660",
    "addr:housenumber":"42",
    "addr:postcode":"2660",
    "addr:street":"Pilevangen;Strand Danmark",
    "iso:country":"DK",
    "sg:address":"Fmd.: M. Bjergegaard, Pilevangen 42",
    "sg:city":"Br\u00f8ndby Strand",
    "sg:orig_category":"Grundejerforeninger",
    "sg:phone":"+45 43 73 02 92",
    "sg:postcode":"2660",
    "sg:province":"Danmark",
    "wof:name":"Pilevangen Vejlaug",
    "wof:placetype":"venue"
},
  "geometry": {"coordinates":[-122.35903167719999,48.9091377258],"type":"Point"}
}