{
  "type": "Feature",
  "properties": {
    "addr:full":"Igls\u00f8vej 61, Kjeldbjerg Skive Danmark 7800",
    "addr:housenumber":"61",
    "addr:postcode":"7800",
    "addr:street":"Iglsovej",
    "iso:country":"DK",
    "sg:address":"Igls\u00f8vej 61, Kjeldbjerg",
    "sg:city":"Skive",
    "sg:orig_category":"Rutebiler",
    "sg:phone":"+45 97 54 51 84",
    "sg:postcode":"7800",
    "sg:province":"Danmark",
    "wof:name":"S\u00f8rensen, Erik J.",
    "wof:placetype":"venue"
},
  "geometry": {"coordinates":[9.0320358276,56.5666427612],"type":"Point"}
}