{
  "type": "Feature",
  "properties": {
    "addr:full":"Villavej 58 Lang\u00e5 Danmark 8870",
    "addr:housenumber":"58",
    "addr:postcode":"8870",
    "addr:street":"Villavej",
    "iso:country":"DK",
    "sg:address":"Villavej 58",
    "sg:city":"Lang\u00e5",
    "sg:orig_category":"Arkitekter",
    "sg:phone":"+45 86 46 14 18",
    "sg:postcode":"8870",
    "sg:province":"Danmark",
    "wof:name":"Carlsen, J. Harding",
    "wof:placetype":"venue"
},
  "geometry": {"coordinates":[9.8895149231,56.3854560852],"type":"Point"}
}