{
  "type": "Feature",
  "properties": {
    "addr:full":"L\u00e6g\u00e5rdvej 12 G Holstebro Danmark 7500",
    "addr:housenumber":"12 g",
    "addr:postcode":"7500",
    "addr:street":"Laegaardvej",
    "iso:country":"DK",
    "sg:address":"L\u00e6g\u00e5rdvej 12 G",
    "sg:city":"Holstebro",
    "sg:orig_category":"\u00c3\u02dcvrige skoler",
    "sg:phone":"+45 97 40 60 66",
    "sg:postcode":"7500",
    "sg:province":"Danmark",
    "sg:website":"www.sygeplejeskole.dk",
    "wof:name":"Sygeplejeskolen i Holstebro",
    "wof:placetype":"venue"
},
  "geometry": {"coordinates":[8.6202583313,56.3625221252],"type":"Point"}
}