{
  "type": "Feature",
  "properties": {
    "iso:country":"DK",
    "sg:address":"Buddinge Hovedgade 179",
    "sg:city":"S\u00f8borg",
    "sg:classifiers":[
        {
            "category":"Banks & Credit Unions",
            "subcategory":"Bank",
            "type":"Services"
        }
    ],
    "sg:phone":"+45 39 55 90 00",
    "sg:postcode":"2860",
    "sg:province":"Danmark",
    "sg:tags":[
        "banker"
    ],
    "sg:website":"www.danskebank.dk",
    "wof:name":"Danske Bank",
    "wof:placetype":"venue"
},
  "geometry": {"coordinates":[12.49824,55.74194],"type":"Point"}
}