{
  "type": "Feature",
  "properties": {
    "addr:full":"\u00d8stergade 73 Hadsten Danmark 8370",
    "addr:housenumber":"73",
    "addr:postcode":"8370",
    "addr:street":"Ostergade",
    "iso:country":"DK",
    "sg:address":"\u00d8stergade 73",
    "sg:city":"Hadsten",
    "sg:orig_category":"Handicapboliger",
    "sg:phone":"+45 86 98 01 76",
    "sg:postcode":"8370",
    "sg:province":"Danmark",
    "wof:name":"Hadsten Bo- og Aktivitetscenter",
    "wof:placetype":"venue"
},
  "geometry": {"coordinates":[10.0590963364,56.3243408203],"type":"Point"}
}