{
  "type": "Feature",
  "properties": {
    "addr:full":"Sognevej 39 Gentofte Danmark 2820",
    "addr:housenumber":"39",
    "addr:postcode":"2820",
    "addr:street":"Sognevej",
    "iso:country":"DK",
    "sg:address":"Sognevej 39",
    "sg:city":"Gentofte",
    "sg:orig_category":"\u00c3\u2020ldreboliger",
    "sg:phone":"+45 39 65 12 60",
    "sg:postcode":"2820",
    "sg:province":"Danmark",
    "wof:name":"Nymosehave",
    "wof:placetype":"venue"
},
  "geometry": {"coordinates":[12.5109291077,55.7511062622],"type":"Point"}
}