{
  "type": "Feature",
  "properties": {
    "addr:full":"Falkoner Alle 15 Frederiksberg Danmark 2000",
    "addr:housenumber":"15",
    "addr:postcode":"2000",
    "addr:street":"Falkoner Alle",
    "iso:country":"DK",
    "sg:address":"Falkoner Alle 15",
    "sg:city":"Frederiksberg",
    "sg:orig_category":"Fotohandlere",
    "sg:phone":"+45 38 88 71 44",
    "sg:postcode":"2000",
    "sg:province":"Danmark",
    "sg:website":"www.japanphoto.dk",
    "wof:name":"Japan Photo",
    "wof:placetype":"venue"
},
  "geometry": {"coordinates":[12.5337247849,55.6805496216],"type":"Point"}
}