{
  "type": "Feature",
  "properties": {
    "iso:country":"DK",
    "sg:address":"Vejlevangen 5 POSTBOKS 20 ",
    "sg:city":"Kerteminde",
    "sg:classifiers":[
        {
            "category":"Parking",
            "subcategory":"Lot",
            "type":"Transportation"
        }
    ],
    "sg:phone":"+45 65 32 12 41",
    "sg:postcode":"5300",
    "sg:province":"Danmark",
    "sg:tags":[
        "transport",
        "road"
    ],
    "wof:name":"POUL ANDERSEN MASKINFABRIK A/S",
    "wof:placetype":"venue"
},
  "geometry": {"coordinates":[10.6600999832,55.4506492615],"type":"Point"}
}