{
  "type": "Feature",
  "properties": {
    "addr:full":"Adelgade 11 Nysted Danmark 4880",
    "addr:housenumber":"11",
    "addr:postcode":"4880",
    "addr:street":"Adelgade",
    "iso:country":"DK",
    "sg:address":"Adelgade 11",
    "sg:city":"Nysted",
    "sg:orig_category":"Biblioteker",
    "sg:phone":"+45 54 87 11 23",
    "sg:postcode":"4880",
    "sg:province":"Danmark",
    "wof:name":"Nysted bibliotek",
    "wof:placetype":"venue"
},
  "geometry": {"coordinates":[11.7289113998,54.6694221497],"type":"Point"}
}