{
  "type": "Feature",
  "properties": {
    "addr:full":"Venusvej 5 Nyk\u00f8bing Danmark 4500",
    "addr:housenumber":"5",
    "addr:postcode":"4500",
    "addr:street":"Venusvej",
    "iso:country":"DK",
    "sg:address":"Venusvej 5",
    "sg:city":"Nyk\u00f8bing",
    "sg:orig_category":"Bilinspektion",
    "sg:postcode":"4500",
    "sg:province":"Danmark",
    "sg:website":"www.bilsyn.dk",
    "wof:name":"Statens Bilinspektion",
    "wof:placetype":"venue"
},
  "geometry": {"coordinates":[16.09696,78.31598700000001],"type":"Point"}
}