{
  "type": "Feature",
  "properties": {
    "addr:full":"Mejlbyvej 701, Mejlby Hjortsh\u00f8j Danmark 8530",
    "addr:housenumber":"701",
    "addr:postcode":"8530",
    "addr:street":"Mejlbyvej;Mejlby Hjortshoj Danmark",
    "iso:country":"DK",
    "sg:address":"Mejlbyvej 701, Mejlby",
    "sg:city":"Hjortsh\u00f8j",
    "sg:orig_category":"Autoreparation og -service",
    "sg:phone":"+45 86 99 80 22",
    "sg:postcode":"8530",
    "sg:province":"Danmark",
    "wof:name":"Mejlby Autov\u00e6rksted",
    "wof:placetype":"venue"
},
  "geometry": {"coordinates":[10.1459388733,56.2984962463],"type":"Point"}
}