{
  "type": "Feature",
  "properties": {
    "iso:country":"DK",
    "sg:address":"R\u00f8dovrevej 5 - 7",
    "sg:city":"R\u00f8dovre",
    "sg:orig_category":"Begravelsesforretninger",
    "sg:phone":"+45 36 70 04 40",
    "sg:postcode":"2610",
    "sg:province":"Danmark",
    "sg:website":"www.roedovre-bedemand.dk",
    "wof:name":"R\u00f8dovre Bedemandsforretning og Ligkistemagasin",
    "wof:placetype":"venue"
},
  "geometry": {"coordinates":[10.699214,61.102776],"type":"Point"}
}