{
  "type": "Feature",
  "properties": {
    "addr:full":"Skodsborg Strandvej 85 Skodsborg Danmark 2942",
    "addr:housenumber":"85",
    "addr:postcode":"2942",
    "addr:street":"Skodsborg Strandvej",
    "iso:country":"DK",
    "sg:address":"Skodsborg Strandvej 85",
    "sg:city":"Skodsborg",
    "sg:orig_category":"Malermestre",
    "sg:phone":"+45 45 80 59 69",
    "sg:postcode":"2942",
    "sg:province":"Danmark",
    "wof:name":"Eriksen, Mogens",
    "wof:placetype":"venue"
},
  "geometry": {"coordinates":[12.5748262405,55.8151702881],"type":"Point"}
}