{
  "type": "Feature",
  "properties": {
    "addr:full":"Fugholm 12 Horsens Danmark 8700",
    "addr:housenumber":"12",
    "addr:postcode":"8700",
    "addr:street":"Fugholm",
    "iso:country":"DK",
    "sg:address":"Fugholm 12",
    "sg:city":"Horsens",
    "sg:classifiers":[
        {
            "category":"Restaurant",
            "type":"Food & Drink"
        }
    ],
    "sg:phone":"+45 75 62 09 19",
    "sg:postcode":"8700",
    "sg:province":"Danmark",
    "wof:name":"Italiano, Restaurant",
    "wof:placetype":"venue"
},
  "geometry": {"coordinates":[9.852268219,55.8611793518],"type":"Point"}
}