{
  "type": "Feature",
  "properties": {
    "iso:country":"DK",
    "sg:address":"Smedegade 15",
    "sg:city":"Horsens",
    "sg:orig_category":"EDB - udstyr",
    "sg:phone":"+45 75 61 73 66",
    "sg:postcode":"8700",
    "sg:province":"Danmark",
    "wof:name":"Centrum Computer",
    "wof:placetype":"venue"
},
  "geometry": {"coordinates":[9.8479671478,55.8637428284],"type":"Point"}
}