{
  "type": "Feature",
  "properties": {
    "addr:full":"Sm\u00f8rblomstvej 5 A, Klokkerholm Hjallerup Danmark 9320",
    "addr:housenumber":"5 a",
    "addr:postcode":"9320",
    "addr:street":"Smorblomstvej;Klokkerholm",
    "iso:country":"DK",
    "sg:address":"Sm\u00f8rblomstvej 5 A, Klokkerholm",
    "sg:city":"Hjallerup",
    "sg:orig_category":"Kommunale folkeskoler",
    "sg:phone":"+45 98 28 42 55",
    "sg:postcode":"9320",
    "sg:province":"Danmark",
    "wof:name":"Klokkerholm Skole",
    "wof:placetype":"venue"
},
  "geometry": {"coordinates":[10.1444702148,57.1677742004],"type":"Point"}
}