{
  "type": "Feature",
  "properties": {
    "iso:country":"DK",
    "sg:address":"Vennelundsvej 8",
    "sg:city":"Odder",
    "sg:orig_category":"Zoneterapeuter",
    "sg:phone":"+45 86 54 21 03",
    "sg:postcode":"8300",
    "sg:province":"Danmark",
    "wof:name":"Rolfsen, Kirsten",
    "wof:placetype":"venue"
},
  "geometry": {"coordinates":[10.1360387802,55.9734916687],"type":"Point"}
}