{
  "type": "Feature",
  "properties": {
    "addr:full":"Gungevej 13 Hvidovre Danmark 2650",
    "addr:housenumber":"13",
    "addr:postcode":"2650",
    "addr:street":"Gungevej",
    "iso:country":"DK",
    "sg:address":"Gungevej 13",
    "sg:city":"Hvidovre",
    "sg:orig_category":"Konservatorer",
    "sg:phone":"+45 36 49 70 49",
    "sg:postcode":"2650",
    "sg:province":"Danmark",
    "sg:website":"www.malerikonservering.dk",
    "wof:name":"Ritterband, Susan",
    "wof:placetype":"venue"
},
  "geometry": {"coordinates":[12.4665384293,55.6414985657],"type":"Point"}
}