{
  "type": "Feature",
  "properties": {
    "iso:country":"DK",
    "sg:address":"Vinderslevholmvej 58, Hingeballe",
    "sg:city":"Kjellerup",
    "sg:orig_category":"Blomsterhandlere",
    "sg:phone":"+45 86 88 60 71",
    "sg:postcode":"8620",
    "sg:province":"Danmark",
    "wof:name":"Frugt - Gr\u00f8nt & Blomster",
    "wof:placetype":"venue"
},
  "geometry": {"coordinates":[9.430934906,56.2877655029],"type":"Point"}
}