{
  "type": "Feature",
  "properties": {
    "addr:full":"Bakkedraget 37 Lem Danmark 6940",
    "addr:housenumber":"37",
    "addr:postcode":"6940",
    "addr:street":"Bakkedraget",
    "iso:country":"DK",
    "sg:address":"Bakkedraget 37",
    "sg:city":"Lem",
    "sg:orig_category":"Murermestre",
    "sg:phone":"+45 97 34 15 37",
    "sg:postcode":"6940",
    "sg:province":"Danmark",
    "wof:name":"Christensen, Murerfirmaet S. Tornvig",
    "wof:placetype":"venue"
},
  "geometry": {"coordinates":[8.3850927353,56.0342445374],"type":"Point"}
}