{
  "type": "Feature",
  "properties": {
    "addr:full":"Havnegade 64, 1. Odense C Danmark 5000",
    "addr:housenumber":"64 1",
    "addr:postcode":"5000",
    "addr:street":"Havnegade",
    "iso:country":"DK",
    "sg:address":"Havnegade 64, 1.",
    "sg:city":"Odense C",
    "sg:orig_category":"Elektro",
    "sg:phone":"+45 63 11 09 67",
    "sg:postcode":"5000",
    "sg:province":"Danmark",
    "wof:name":"Jensen El, Jacob",
    "wof:placetype":"venue"
},
  "geometry": {"coordinates":[10.3812255859,55.4204483032],"type":"Point"}
}