{
  "type": "Feature",
  "properties": {
    "addr:full":"Fmd.: Mette Dreier, Ballingvej 56, Hem Skive Danmark 7800",
    "addr:housenumber":"56",
    "addr:postcode":"7800",
    "addr:street":"Ballingvej",
    "iso:country":"DK",
    "sg:address":"Fmd.: Mette Dreier, Ballingvej 56, Hem",
    "sg:city":"Skive",
    "sg:orig_category":"Husflidsforeninger",
    "sg:phone":"+45 97 53 10 95",
    "sg:postcode":"7800",
    "sg:province":"Danmark",
    "wof:name":"Hem Husholdningsforening",
    "wof:placetype":"venue"
},
  "geometry": {"coordinates":[9.0320358276,56.5666427612],"type":"Point"}
}