{
  "type": "Feature",
  "properties": {
    "addr:full":"Kastaniehusene 27 Karlslunde Danmark 2690",
    "addr:housenumber":"27",
    "addr:postcode":"2690",
    "addr:street":"Kastaniehusene",
    "iso:country":"DK",
    "sg:address":"Kastaniehusene 27",
    "sg:city":"Karlslunde",
    "sg:orig_category":"Lotterikollektioner",
    "sg:phone":"+45 46 15 06 12",
    "sg:postcode":"2690",
    "sg:province":"Danmark",
    "wof:name":"Klasselotteriet i Karlslunde",
    "wof:placetype":"venue"
},
  "geometry": {"coordinates":[12.2484550476,55.5702362061],"type":"Point"}
}