{
  "type": "Feature",
  "properties": {
    "addr:full":"Jernbanegade 20 Fredensborg Danmark 3480",
    "addr:housenumber":"20",
    "addr:postcode":"3480",
    "addr:street":"Jernbanegade",
    "iso:country":"DK",
    "sg:address":"Jernbanegade 20",
    "sg:city":"Fredensborg",
    "sg:orig_category":"Bagere",
    "sg:phone":"+45 48 48 00 60",
    "sg:postcode":"3480",
    "sg:province":"Danmark",
    "wof:name":"Fredensborg Br\u00f8dhus & Caf\u00e9",
    "wof:placetype":"venue"
},
  "geometry": {"coordinates":[12.3991346359,55.9786643982],"type":"Point"}
}