{
  "type": "Feature",
  "properties": {
    "addr:full":"Kongegade 8 Nyborg Danmark 5800",
    "addr:housenumber":"8",
    "addr:postcode":"5800",
    "addr:street":"Kongegade",
    "iso:country":"DK",
    "sg:address":"Kongegade 8",
    "sg:city":"Nyborg",
    "sg:orig_category":"Apoteker og -udsalg",
    "sg:phone":"+45 65 31 22 33",
    "sg:postcode":"5800",
    "sg:province":"Danmark",
    "wof:name":"Nyborg Apotek",
    "wof:placetype":"venue"
},
  "geometry": {"coordinates":[10.7897033691,55.3114814758],"type":"Point"}
}