{
  "type": "Feature",
  "properties": {
    "addr:full":"Brunagervej 8 St\u00f8vring Danmark 9530",
    "addr:housenumber":"8",
    "addr:postcode":"9530",
    "addr:street":"Brunagervej",
    "iso:country":"DK",
    "sg:address":"Brunagervej 8",
    "sg:city":"St\u00f8vring",
    "sg:classifiers":[
        {
            "category":"Taxi",
            "type":"Transportation"
        }
    ],
    "sg:phone":"+45 98 37 33 61",
    "sg:postcode":"9530",
    "sg:province":"Danmark",
    "wof:name":"Niels J\u00f8rgens Taxi",
    "wof:placetype":"venue"
},
  "geometry": {"coordinates":[-103.44198608400001,34.3833312988],"type":"Point"}
}