{
  "type": "Feature",
  "properties": {
    "addr:full":"\u00d8reg\u00e5rds All\u00e9 25 Hellerup Danmark 2900",
    "addr:housenumber":"25",
    "addr:postcode":"2900",
    "addr:street":"Oregaards Alle\u0301",
    "iso:country":"DK",
    "sg:address":"\u00d8reg\u00e5rds All\u00e9 25",
    "sg:city":"Hellerup",
    "sg:orig_category":"Ambassader og konsulater",
    "sg:phone":"+45 39 61 98 89",
    "sg:postcode":"2900",
    "sg:province":"Danmark",
    "wof:name":"Kinesiske Folkerepubliks Ambassade, Den",
    "wof:placetype":"venue"
},
  "geometry": {"coordinates":[12.5788497925,55.7413787842],"type":"Point"}
}