{
  "type": "Feature",
  "properties": {
    "addr:full":"Smedetorvet 7 Horsens Danmark 8700",
    "addr:housenumber":"7",
    "addr:postcode":"8700",
    "addr:street":"Smedetorvet",
    "iso:country":"DK",
    "sg:address":"Smedetorvet 7",
    "sg:city":"Horsens",
    "sg:orig_category":"Faglige organisationer og foreninger",
    "sg:phone":"+45 75 62 17 88",
    "sg:postcode":"8700",
    "sg:province":"Danmark",
    "wof:name":"Dansk Metalarbejderforbund",
    "wof:placetype":"venue"
},
  "geometry": {"coordinates":[9.8458786011,55.8660736084],"type":"Point"}
}