{
  "type": "Feature",
  "properties": {
    "addr:full":"Skovs-H\u00f8jrup-Vej 36, Skovs H\u00f8jrup Odense N Danmark 5270",
    "addr:housenumber":"36",
    "addr:postcode":"5270",
    "addr:street":"Skovs-Hojrup-Vej;Hojrup",
    "iso:country":"DK",
    "sg:address":"Skovs-H\u00f8jrup-Vej 36, Skovs H\u00f8jrup",
    "sg:city":"Odense N",
    "sg:orig_category":"Keramik",
    "sg:phone":"+45 65 96 46 26",
    "sg:postcode":"5270",
    "sg:province":"Danmark",
    "wof:name":"Rasmussen,Lissie",
    "wof:placetype":"venue"
},
  "geometry": {"coordinates":[10.3306798935,55.4711418152],"type":"Point"}
}