{
  "type": "Feature",
  "properties": {
    "addr:full":"Violvej 49 Skive Danmark 7800",
    "addr:housenumber":"49",
    "addr:postcode":"7800",
    "addr:street":"Violvej",
    "iso:country":"DK",
    "sg:address":"Violvej 49",
    "sg:city":"Skive",
    "sg:orig_category":"Malermestre",
    "sg:phone":"+45 97 51 01 08",
    "sg:postcode":"7800",
    "sg:province":"Danmark",
    "wof:name":"W\u00fcrtz, Malerfirmaet",
    "wof:placetype":"venue"
},
  "geometry": {"coordinates":[9.0418987274,56.5793495178],"type":"Point"}
}