{
  "type": "Feature",
  "properties": {
    "addr:full":"Magleparken 3 Ballerup Danmark 2750",
    "addr:housenumber":"3",
    "addr:postcode":"2750",
    "addr:street":"Magleparken",
    "iso:country":"DK",
    "sg:address":"Magleparken 3",
    "sg:city":"Ballerup",
    "sg:orig_category":"Fritidshjem",
    "sg:phone":"+45 44 77 17 02",
    "sg:postcode":"2750",
    "sg:province":"Danmark",
    "wof:name":"Magleg\u00e5rden Fritidshjem",
    "wof:placetype":"venue"
},
  "geometry": {"coordinates":[12.3621788025,55.7201766968],"type":"Point"}
}