{
  "type": "Feature",
  "properties": {
    "addr:full":"Gulagervej 6 Fjenneslev Danmark 4173",
    "addr:housenumber":"6",
    "addr:postcode":"4173",
    "addr:street":"Gulagervej",
    "iso:country":"DK",
    "sg:address":"Gulagervej 6",
    "sg:city":"Fjenneslev",
    "sg:orig_category":"Psykologer, praktiserende",
    "sg:phone":"+45 57 60 88 88",
    "sg:postcode":"4173",
    "sg:province":"Danmark",
    "wof:name":"A - Z Klinik",
    "wof:placetype":"venue"
},
  "geometry": {"coordinates":[11.6176919937,55.4277153015],"type":"Point"}
}