{
  "type": "Feature",
  "properties": {
    "iso:country":"DK",
    "sg:address":"Lille Borgergade 13",
    "sg:city":"N\u00f8rresundby",
    "sg:orig_category":"RESTAURANTS: ART",
    "sg:phone":"+45 70 20 99 44",
    "sg:postcode":"9400",
    "sg:province":"Danmark",
    "wof:name":"Nimand A/S",
    "wof:placetype":"venue"
},
  "geometry": {"coordinates":[1.5905510187,42.8531799316],"type":"Point"}
}