{
  "type": "Feature",
  "properties": {
    "addr:full":"Thorsgade 4 Randers Danmark 8900",
    "addr:housenumber":"4",
    "addr:postcode":"8900",
    "addr:street":"Thorsgade",
    "iso:country":"DK",
    "sg:address":"Thorsgade 4",
    "sg:city":"Randers",
    "sg:orig_category":"Solcentre",
    "sg:phone":"+45 86 41 20 20",
    "sg:postcode":"8900",
    "sg:province":"Danmark",
    "wof:name":"Faktor 1 Sun",
    "wof:placetype":"venue"
},
  "geometry": {"coordinates":[10.039812088,56.4618835449],"type":"Point"}
}