{
  "type": "Feature",
  "properties": {
    "addr:full":"Ulvevej 90 Esbjerg N Danmark 6715",
    "addr:housenumber":"90",
    "addr:postcode":"6715",
    "addr:street":"Ulvevej",
    "iso:country":"DK",
    "sg:address":"Ulvevej 90",
    "sg:city":"Esbjerg N",
    "sg:orig_category":"Integrerede institutioner",
    "sg:phone":"+45 75 45 95 35",
    "sg:postcode":"6715",
    "sg:province":"Danmark",
    "wof:name":"Bakkeg\u00e5rden, Aldersintegreret",
    "wof:placetype":"venue"
},
  "geometry": {"coordinates":[8.446554184,55.5080680847],"type":"Point"}
}