{
  "type": "Feature",
  "properties": {
    "iso:country":"DK",
    "sg:address":"Ribe Landevej 6",
    "sg:city":"Haderslev",
    "sg:orig_category":"Billedkunst",
    "sg:phone":"+45 74 52 77 80",
    "sg:postcode":"6100",
    "sg:province":"Danmark",
    "wof:name":"Seide-Hartmann",
    "wof:placetype":"venue"
},
  "geometry": {"coordinates":[9.475043,55.25135],"type":"Point"}
}