{
  "type": "Feature",
  "properties": {
    "addr:full":"Hovedvejen 68 Glostrup Danmark 2600",
    "addr:housenumber":"68",
    "addr:postcode":"2600",
    "addr:street":"Hovedvejen",
    "iso:country":"DK",
    "sg:address":"Hovedvejen 68",
    "sg:city":"Glostrup",
    "sg:orig_category":"Pizzeriaer",
    "sg:phone":"+45 43 96 06 32",
    "sg:postcode":"2600",
    "sg:province":"Danmark",
    "wof:name":"Pizza & Shawarma Bar",
    "wof:placetype":"venue"
},
  "geometry": {"coordinates":[12.4064464569,55.6668510437],"type":"Point"}
}