{
  "type": "Feature",
  "properties": {
    "addr:full":"Dronningholmsvej 48 Svendborg Danmark 5700",
    "addr:housenumber":"48",
    "addr:postcode":"5700",
    "addr:street":"Dronningholmsvej",
    "iso:country":"DK",
    "sg:address":"Dronningholmsvej 48",
    "sg:city":"Svendborg",
    "sg:orig_category":"Garverier",
    "sg:phone":"+45 62 21 24 22",
    "sg:postcode":"5700",
    "sg:province":"Danmark",
    "wof:name":"Elmo Leather A/S",
    "wof:placetype":"venue"
},
  "geometry": {"coordinates":[10.6099300385,55.0651664734],"type":"Point"}
}