{
  "type": "Feature",
  "properties": {
    "addr:full":"Lervejdal 10 A, Addit Br\u00e6dstrup Danmark 8740",
    "addr:housenumber":"10 a",
    "addr:postcode":"8740",
    "addr:street":"Lervejdal;Addit Braedstrup Danmark",
    "iso:country":"DK",
    "sg:address":"Lervejdal 10 A, Addit",
    "sg:city":"Br\u00e6dstrup",
    "sg:orig_category":"Fabrikker",
    "sg:phone":"+45 75 75 43 88",
    "sg:postcode":"8740",
    "sg:province":"Danmark",
    "sg:website":"www.dansand.dk",
    "wof:name":"Dansand Silkeborg A/S",
    "wof:placetype":"venue"
},
  "geometry": {"coordinates":[9.6119251251,55.9734191895],"type":"Point"}
}