{
  "type": "Feature",
  "properties": {
    "addr:full":"Aved\u00f8reholmen 46  Hvidovre Danmark 2650",
    "addr:housenumber":"46",
    "addr:postcode":"2650",
    "addr:street":"Avedoreholmen",
    "iso:country":"DK",
    "sg:address":"Aved\u00f8reholmen 46 ",
    "sg:city":"Hvidovre",
    "sg:classifiers":[
        {
            "category":"Travel",
            "subcategory":"Travel Agent",
            "type":"Entertainment"
        }
    ],
    "sg:phone":"+45 36 77 96 66",
    "sg:postcode":"2650",
    "sg:province":"Danmark",
    "sg:tags":[
        "business"
    ],
    "wof:name":"DHL SOLUTION A/S",
    "wof:placetype":"venue"
},
  "geometry": {"coordinates":[12.4689598083,55.6115989685],"type":"Point"}
}