{
  "type": "Feature",
  "properties": {
    "iso:country":"DK",
    "sg:address":"Jernbanegade 39",
    "sg:city":"Fredericia",
    "sg:orig_category":"Reklamebureauer",
    "sg:phone":"+45 75 93 36 11",
    "sg:postcode":"7000",
    "sg:province":"Danmark",
    "wof:name":"Brodersen Reklamebureau, Egon",
    "wof:placetype":"venue"
},
  "geometry": {"coordinates":[9.7441911697,55.565864563],"type":"Point"}
}