{
  "type": "Feature",
  "properties": {
    "addr:full":"Sj\u00e6llandsgade 4 Esbjerg Danmark 6700",
    "addr:housenumber":"4",
    "addr:postcode":"6700",
    "addr:street":"Sjaellandsgade",
    "iso:country":"DK",
    "sg:address":"Sj\u00e6llandsgade 4",
    "sg:city":"Esbjerg",
    "sg:classifiers":[
        {
            "category":"Shopping",
            "subcategory":"Pharmacy",
            "type":"Retail Goods"
        }
    ],
    "sg:phone":"+45 75 18 04 92",
    "sg:postcode":"6700",
    "sg:province":"Danmark",
    "sg:tags":[
        "drugstore"
    ],
    "wof:name":"Annis Drug-Store",
    "wof:placetype":"venue"
},
  "geometry": {"coordinates":[8.439622879,55.4710464478],"type":"Point"}
}