{
  "type": "Feature",
  "properties": {
    "iso:country":"DK",
    "sg:address":"Hjulmagervej 38",
    "sg:city":"Aalborg",
    "sg:orig_category":"Radiotelefoner",
    "sg:phone":"+45 98 12 09 11",
    "sg:postcode":"9000",
    "sg:province":"Danmark",
    "wof:name":"Nordjysk Diesel-Elektro ApS",
    "wof:placetype":"venue"
},
  "geometry": {"coordinates":[9.9219923019,57.0394744873],"type":"Point"}
}