{
  "type": "Feature",
  "properties": {
    "iso:country":"DK",
    "sg:address":"Bredevej 56 - 58",
    "sg:city":"Virum",
    "sg:classifiers":[
        {
            "category":"Restaurant",
            "type":"Food & Drink"
        }
    ],
    "sg:phone":"+45 45 85 39 13",
    "sg:postcode":"2830",
    "sg:province":"Danmark",
    "wof:name":"Castello, Restaurant",
    "wof:placetype":"venue"
},
  "geometry": {"coordinates":[12.4936513901,55.7965202332],"type":"Point"}
}