{
  "type": "Feature",
  "properties": {
    "addr:full":"Jernbanegade 36 S\u00f8llested Danmark 4920",
    "addr:housenumber":"36",
    "addr:postcode":"4920",
    "addr:street":"Jernbanegade",
    "iso:country":"DK",
    "sg:address":"Jernbanegade 36",
    "sg:city":"S\u00f8llested",
    "sg:orig_category":"Autoreparation og -service",
    "sg:phone":"+45 54 94 14 39",
    "sg:postcode":"4920",
    "sg:province":"Danmark",
    "wof:name":"P. E. Auto",
    "wof:placetype":"venue"
},
  "geometry": {"coordinates":[11.2581243515,54.8128204346],"type":"Point"}
}