{
  "type": "Feature",
  "properties": {
    "addr:full":"Sankt Hans Gade 31 Roskilde Danmark 4000",
    "addr:housenumber":"31",
    "addr:postcode":"4000",
    "addr:street":"Sankt Hans Gade",
    "iso:country":"DK",
    "sg:address":"Sankt Hans Gade 31",
    "sg:city":"Roskilde",
    "sg:orig_category":"Bandagister",
    "sg:phone":"+45 36 72 13 72",
    "sg:postcode":"4000",
    "sg:province":"Danmark",
    "wof:name":"Roskilde Ortop\u00e6diske H\u00e5ndskomageri",
    "wof:placetype":"venue"
},
  "geometry": {"coordinates":[12.071589,55.646587],"type":"Point"}
}