{
  "type": "Feature",
  "properties": {
    "iso:country":"DK",
    "sg:address":"Industriv. 7 ",
    "sg:city":"Herning",
    "sg:classifiers":[
        {
            "category":"Manufacturing",
            "subcategory":"Lumber",
            "type":"Manufacturing & Wholesale Goods"
        }
    ],
    "sg:phone":"+45 97 22 28 44",
    "sg:postcode":"7400",
    "sg:province":"Danmark",
    "sg:tags":[
        "wood"
    ],
    "wof:name":"GARANT MIDTJYLLAND A/S",
    "wof:placetype":"venue"
},
  "geometry": {"coordinates":[8.9760742188,56.1108474731],"type":"Point"}
}