{
  "type": "Feature",
  "properties": {
    "addr:full":"Storegade 26 Varde Danmark 6800",
    "addr:housenumber":"26",
    "addr:postcode":"6800",
    "addr:street":"Storegade",
    "iso:country":"DK",
    "sg:address":"Storegade 26",
    "sg:city":"Varde",
    "sg:orig_category":"Farve og tapet",
    "sg:phone":"+45 75 22 31 99",
    "sg:postcode":"6800",
    "sg:province":"Danmark",
    "wof:name":"Fl\u00fcgger farver",
    "wof:placetype":"venue"
},
  "geometry": {"coordinates":[8.4832859039,55.6206932068],"type":"Point"}
}