{
  "type": "Feature",
  "properties": {
    "addr:full":"Thorvaldsensgade 1 \u00c5rhus C Danmark 8000",
    "addr:housenumber":"1",
    "addr:postcode":"8000",
    "addr:street":"Thorvaldsensgade",
    "iso:country":"DK",
    "sg:address":"Thorvaldsensgade 1",
    "sg:city":"\u00c5rhus C",
    "sg:orig_category":"Grillbarer",
    "sg:phone":"+45 86 12 70 47",
    "sg:postcode":"8000",
    "sg:province":"Danmark",
    "wof:name":"Byens Burger og Pizza",
    "wof:placetype":"venue"
},
  "geometry": {"coordinates":[4.717400074,49.7588005066],"type":"Point"}
}