{
  "type": "Feature",
  "properties": {
    "iso:country":"DK",
    "sg:address":"Brorsonsvej 4",
    "sg:city":"Herning",
    "sg:orig_category":"Tandklinikker, Kommunale",
    "sg:phone":"+45 97 12 38 93",
    "sg:postcode":"7400",
    "sg:province":"Danmark",
    "wof:name":"Br\u00e6ndg\u00e5rdskolens Reguleringsklinik",
    "wof:placetype":"venue"
},
  "geometry": {"coordinates":[8.9650030136,56.1438369751],"type":"Point"}
}