{
  "type": "Feature",
  "properties": {
    "addr:full":"Vejlevej 60 Horsens Danmark 8700",
    "addr:housenumber":"60",
    "addr:postcode":"8700",
    "addr:street":"Vejlevej",
    "iso:country":"DK",
    "sg:address":"Vejlevej 60",
    "sg:city":"Horsens",
    "sg:orig_category":"Moteller",
    "sg:phone":"+45 75 64 25 30",
    "sg:postcode":"8700",
    "sg:province":"Danmark",
    "wof:name":"Thorsvang, Motel",
    "wof:placetype":"venue"
},
  "geometry": {"coordinates":[9.8244342804,55.8458099365],"type":"Point"}
}