{
  "type": "Feature",
  "properties": {
    "addr:full":"\u00d8stergade 49 Ansager Danmark 6823",
    "addr:housenumber":"49",
    "addr:postcode":"6823",
    "addr:street":"Ostergade",
    "iso:country":"DK",
    "sg:address":"\u00d8stergade 49",
    "sg:city":"Ansager",
    "sg:orig_category":"Autoreparation og -service",
    "sg:phone":"+45 75 29 71 63",
    "sg:postcode":"6823",
    "sg:province":"Danmark",
    "wof:name":"Ansager Autoservice",
    "wof:placetype":"venue"
},
  "geometry": {"coordinates":[8.7643404007,55.7027359009],"type":"Point"}
}