{
  "type": "Feature",
  "properties": {
    "addr:full":"Tvedenvej 40 Vodskov Danmark 9310",
    "addr:housenumber":"40",
    "addr:postcode":"9310",
    "addr:street":"Tvedenvej",
    "iso:country":"DK",
    "sg:address":"Tvedenvej 40",
    "sg:city":"Vodskov",
    "sg:orig_category":"Murermestre",
    "sg:phone":"+45 98 25 70 77",
    "sg:postcode":"9310",
    "sg:province":"Danmark",
    "wof:name":"Pedersen ApS, Keld",
    "wof:placetype":"venue"
},
  "geometry": {"coordinates":[10.1342687607,57.1074295044],"type":"Point"}
}