{
  "type": "Feature",
  "properties": {
    "addr:full":"Buen 7 Hj\u00f8rring Danmark 9800",
    "addr:housenumber":"7",
    "addr:postcode":"9800",
    "addr:street":"Buen",
    "iso:country":"DK",
    "sg:address":"Buen 7",
    "sg:city":"Hj\u00f8rring",
    "sg:orig_category":"Varmeforsyning",
    "sg:phone":"+45 96 24 15 00",
    "sg:postcode":"9800",
    "sg:province":"Danmark",
    "sg:website":"www.hjvarme.dk",
    "wof:name":"Hj\u00f8rring Varmeforsyning",
    "wof:placetype":"venue"
},
  "geometry": {"coordinates":[-8.7835798264,42.3259315491],"type":"Point"}
}