{
  "type": "Feature",
  "properties": {
    "addr:full":"v/ Jens Chr. Hansen, L\u00f8seb\u00e6kgade 6 Allinge Danmark 3770",
    "addr:housenumber":"6",
    "addr:postcode":"3770",
    "addr:street":"Losebaekgade",
    "iso:country":"DK",
    "sg:address":"v/ Jens Chr. Hansen, L\u00f8seb\u00e6kgade 6",
    "sg:city":"Allinge",
    "sg:orig_category":"Kirkelige foreninger",
    "sg:phone":"+45 56 48 09 54",
    "sg:postcode":"3770",
    "sg:province":"Danmark",
    "wof:name":"Evangelisk Luthersk Missionsforening Allinge",
    "wof:placetype":"venue"
},
  "geometry": {"coordinates":[14.7998552322,55.2743835449],"type":"Point"}
}