{
  "type": "Feature",
  "properties": {
    "addr:full":"Stadion Alle 3 B F\u00e5rup Danmark 8990",
    "addr:housenumber":"3 b",
    "addr:postcode":"8990",
    "addr:street":"Stadion Alle",
    "iso:country":"DK",
    "sg:address":"Stadion Alle 3 B",
    "sg:city":"F\u00e5rup",
    "sg:orig_category":"Non-Classified Establishments",
    "sg:phone":"+45 86 45 30 66",
    "sg:postcode":"8990",
    "sg:province":"Danmark",
    "wof:name":"V\u00e6restedet",
    "wof:placetype":"venue"
},
  "geometry": {"coordinates":[-93.1630935669,32.8507347107],"type":"Point"}
}