{
  "type": "Feature",
  "properties": {
    "addr:full":"Bredgade 19 Skjern Danmark 6900",
    "addr:housenumber":"19",
    "addr:postcode":"6900",
    "addr:street":"Bredgade",
    "iso:country":"DK",
    "sg:address":"Bredgade 19",
    "sg:city":"Skjern",
    "sg:orig_category":"Farve og tapet",
    "sg:phone":"+45 97 35 03 06",
    "sg:postcode":"6900",
    "sg:province":"Danmark",
    "wof:name":"Fl\u00fcgger farver",
    "wof:placetype":"venue"
},
  "geometry": {"coordinates":[8.4953279495,55.9452438354],"type":"Point"}
}