{
  "type": "Feature",
  "properties": {
    "addr:full":"Over Viskumvej 9, O Viskum Tjele Danmark 8830",
    "addr:housenumber":"9 o",
    "addr:postcode":"8830",
    "addr:street":"Over Viskumvej;Viskum",
    "iso:country":"DK",
    "sg:address":"Over Viskumvej 9, O Viskum",
    "sg:city":"Tjele",
    "sg:orig_category":"Autoreparation og -service",
    "sg:phone":"+45 86 65 42 52",
    "sg:postcode":"8830",
    "sg:province":"Danmark",
    "wof:name":"G\u00e5rdens Auto",
    "wof:placetype":"venue"
},
  "geometry": {"coordinates":[9.6264801025,56.4818611145],"type":"Point"}
}