{
  "type": "Feature",
  "properties": {
    "addr:full":"Sundbyvester Plads 9 K\u00f8benhavn S Danmark 2300",
    "addr:housenumber":"9",
    "addr:postcode":"2300",
    "addr:street":"Sundbyvester Plads;S Danmark",
    "iso:country":"DK",
    "sg:address":"Sundbyvester Plads 9",
    "sg:city":"K\u00f8benhavn S",
    "sg:orig_category":"Renserier",
    "sg:phone":"+45 32 55 61 36",
    "sg:postcode":"2300",
    "sg:province":"Danmark",
    "wof:name":"Sundby Rens",
    "wof:placetype":"venue"
},
  "geometry": {"coordinates":[12.5982503891,55.6506996155],"type":"Point"}
}