{
  "type": "Feature",
  "properties": {
    "iso:country":"DK",
    "sg:address":"Eventyrhaven 7",
    "sg:city":"Nyk\u00f8bing",
    "sg:orig_category":"Solcentre",
    "sg:phone":"+45 59 91 25 76",
    "sg:postcode":"4500",
    "sg:province":"Danmark",
    "wof:name":"Petersen, Lola",
    "wof:placetype":"venue"
},
  "geometry": {"coordinates":[16.0969600677,78.3159866333],"type":"Point"}
}