{
  "type": "Feature",
  "properties": {
    "addr:full":"Horsensvej 21 Skanderborg Danmark 8660",
    "addr:housenumber":"21",
    "addr:postcode":"8660",
    "addr:street":"Horsensvej",
    "iso:country":"DK",
    "sg:address":"Horsensvej 21",
    "sg:city":"Skanderborg",
    "sg:orig_category":"Campingpladser",
    "sg:phone":"+45 86 51 13 11",
    "sg:postcode":"8660",
    "sg:province":"Danmark",
    "sg:website":"www.campingskanderborg.dk",
    "wof:name":"Skanderborg S\u00f8 Camping",
    "wof:placetype":"venue"
},
  "geometry": {"coordinates":[9.8917255402,56.0214996338],"type":"Point"}
}