{
  "type": "Feature",
  "properties": {
    "addr:full":"Andreas Steenbergs Plads 2 Horsens Danmark 8700",
    "addr:housenumber":"2",
    "addr:postcode":"8700",
    "addr:street":"Andreas Steenbergs Plads",
    "iso:country":"DK",
    "sg:address":"Andreas Steenbergs Plads 2",
    "sg:city":"Horsens",
    "sg:orig_category":"\u00c3\u2020ldreboliger",
    "sg:postcode":"8700",
    "sg:province":"Danmark",
    "wof:name":"\u00c6ldreboliger",
    "wof:placetype":"venue"
},
  "geometry": {"coordinates":[9.8378982544,55.8628349304],"type":"Point"}
}