{
  "type": "Feature",
  "properties": {
    "addr:full":"Lunde Bygade 100, \u00d8ster Lunde Otterup Danmark 5450",
    "addr:housenumber":"100",
    "addr:postcode":"5450",
    "addr:street":"Lunde Bygade",
    "iso:country":"DK",
    "sg:address":"Lunde Bygade 100, \u00d8ster Lunde",
    "sg:city":"Otterup",
    "sg:orig_category":"Gaffeltrucks",
    "sg:phone":"+45 65 95 58 58",
    "sg:postcode":"5450",
    "sg:province":"Danmark",
    "wof:name":"FTH Service",
    "wof:placetype":"venue"
},
  "geometry": {"coordinates":[10.4545049667,55.5641746521],"type":"Point"}
}