{
  "type": "Feature",
  "properties": {
    "addr:full":"Lauge Kochs Vej 10 Frederikshavn Danmark 9900",
    "addr:housenumber":"10",
    "addr:postcode":"9900",
    "addr:street":"Lauge Kochs Vej",
    "iso:country":"DK",
    "sg:address":"Lauge Kochs Vej 10",
    "sg:city":"Frederikshavn",
    "sg:classifiers":[
        {
            "category":"Building & Trades",
            "subcategory":"Construction",
            "type":"Services"
        }
    ],
    "sg:phone":"+45 98 42 68 55",
    "sg:postcode":"9900",
    "sg:province":"Danmark",
    "sg:tags":[
        "renovation"
    ],
    "wof:name":"S\u00f8rig Industrirenovation, Peter",
    "wof:placetype":"venue"
},
  "geometry": {"coordinates":[10.5034313202,57.4424057007],"type":"Point"}
}