{
  "type": "Feature",
  "properties": {
    "addr:full":"Storegade 11 Randers Danmark 8900",
    "addr:housenumber":"11",
    "addr:postcode":"8900",
    "addr:street":"Storegade",
    "iso:country":"DK",
    "sg:address":"Storegade 11",
    "sg:city":"Randers",
    "sg:orig_category":"Cafeer",
    "sg:phone":"+45 86 43 32 10",
    "sg:postcode":"8900",
    "sg:province":"Danmark",
    "wof:name":"Smagl\u00f8s, Caf\u00e9",
    "wof:placetype":"venue"
},
  "geometry": {"coordinates":[10.0383605957,56.4580421448],"type":"Point"}
}