{
  "type": "Feature",
  "properties": {
    "iso:country":"DK",
    "sg:address":"Rug\u00e5rdsvej 4, Rug\u00e5rd",
    "sg:city":"Ebeltoft",
    "sg:orig_category":"Campingpladser",
    "sg:phone":"+45 86 33 60 25",
    "sg:postcode":"8400",
    "sg:province":"Danmark",
    "wof:name":"Rug\u00e5rd Camping",
    "wof:placetype":"venue"
},
  "geometry": {"coordinates":[10.6778745651,56.199798584],"type":"Point"}
}