{
  "type": "Feature",
  "properties": {
    "addr:full":"Clausholmvej 23 Randers Danmark 8900",
    "addr:housenumber":"23",
    "addr:postcode":"8900",
    "addr:street":"Clausholmvej",
    "iso:country":"DK",
    "sg:address":"Clausholmvej 23",
    "sg:city":"Randers",
    "sg:orig_category":"Fabrikker",
    "sg:phone":"+45 87 10 05 00",
    "sg:postcode":"8900",
    "sg:province":"Danmark",
    "wof:name":"Bosal-Sekura Industries A/S",
    "wof:placetype":"venue"
},
  "geometry": {"coordinates":[10.0722541809,56.4396438599],"type":"Point"}
}