{
  "type": "Feature",
  "properties": {
    "addr:full":"Hedegade 32 Roskilde Danmark 4000",
    "addr:housenumber":"32",
    "addr:postcode":"4000",
    "addr:street":"Hedegade",
    "iso:country":"DK",
    "sg:address":"Hedegade 32",
    "sg:city":"Roskilde",
    "sg:orig_category":"Cykler",
    "sg:phone":"+45 46 36 63 00",
    "sg:postcode":"4000",
    "sg:province":"Danmark",
    "wof:name":"Fabin Sport",
    "wof:placetype":"venue"
},
  "geometry": {"coordinates":[12.0693531036,55.6441459656],"type":"Point"}
}