{
  "type": "Feature",
  "properties": {
    "addr:full":"v/ Vibeke Lassen, Damhusvej 46 Odense C Danmark 5000",
    "addr:housenumber":"46",
    "addr:postcode":"5000",
    "addr:street":"Damhusvej",
    "iso:country":"DK",
    "sg:address":"v/ Vibeke Lassen, Damhusvej 46",
    "sg:city":"Odense C",
    "sg:orig_category":"Kulturelle foreninger",
    "sg:phone":"+45 66 11 98 80",
    "sg:postcode":"5000",
    "sg:province":"Danmark",
    "wof:name":"Medie- og Kultur Alliancen",
    "wof:placetype":"venue"
},
  "geometry": {"coordinates":[10.390794754,55.3961715698],"type":"Point"}
}