{
  "type": "Feature",
  "properties": {
    "addr:full":"Engvej 5 Faaborg Danmark 5600",
    "addr:housenumber":"5",
    "addr:postcode":"5600",
    "addr:street":"Engvej",
    "iso:country":"DK",
    "sg:address":"Engvej 5",
    "sg:city":"Faaborg",
    "sg:classifiers":[
        {
            "category":"Taxi",
            "type":"Transportation"
        }
    ],
    "sg:phone":"+45 62 61 88 00",
    "sg:postcode":"5600",
    "sg:province":"Danmark",
    "wof:name":"Faaborg Taxa",
    "wof:placetype":"venue"
},
  "geometry": {"coordinates":[10.2366390228,55.0988616943],"type":"Point"}
}