{
  "type": "Feature",
  "properties": {
    "addr:full":"S\u00f8ndergade 31 Svaneke Danmark 3740",
    "addr:housenumber":"31",
    "addr:postcode":"3740",
    "addr:street":"Sondergade",
    "iso:country":"DK",
    "sg:address":"S\u00f8ndergade 31",
    "sg:city":"Svaneke",
    "sg:orig_category":"Integrerede institutioner",
    "sg:phone":"+45 56 49 71 15",
    "sg:postcode":"3740",
    "sg:province":"Danmark",
    "wof:name":"Sydg\u00e5rden",
    "wof:placetype":"venue"
},
  "geometry": {"coordinates":[15.1471214294,55.1303825378],"type":"Point"}
}