{
  "type": "Feature",
  "properties": {
    "iso:country":"DK",
    "sg:address":"Vejle Landevej 34, Brovad",
    "sg:city":"Fredericia",
    "sg:orig_category":"Hunde",
    "sg:phone":"+45 75 94 38 37",
    "sg:postcode":"7000",
    "sg:province":"Danmark",
    "wof:name":"Brovad Hundepension",
    "wof:placetype":"venue"
},
  "geometry": {"coordinates":[9.7591047287,55.566368103],"type":"Point"}
}