{
  "type": "Feature",
  "properties": {
    "iso:country":"DK",
    "sg:address":"Overgade 19",
    "sg:city":"Odense C",
    "sg:orig_category":"Rammer",
    "sg:phone":"+45 66 12 44 21",
    "sg:postcode":"5000",
    "sg:province":"Danmark",
    "wof:name":"Overgades Ny Indramning",
    "wof:placetype":"venue"
},
  "geometry": {"coordinates":[10.3911838531,55.3970603943],"type":"Point"}
}