{
  "type": "Feature",
  "properties": {
    "addr:full":"Lille Slagtergade 3 Haderslev Danmark 6100",
    "addr:housenumber":"3",
    "addr:postcode":"6100",
    "addr:street":"Lille Slagtergade",
    "iso:country":"DK",
    "sg:address":"Lille Slagtergade 3",
    "sg:city":"Haderslev",
    "sg:classifiers":[
        {
            "category":"Building & Trades",
            "subcategory":"Electrical",
            "type":"Services"
        }
    ],
    "sg:phone":"+45 74 52 88 00",
    "sg:postcode":"6100",
    "sg:province":"Danmark",
    "sg:tags":[
        "distributor"
    ],
    "wof:name":"HJ Distribution",
    "wof:placetype":"venue"
},
  "geometry": {"coordinates":[9.4818191528,55.2526321411],"type":"Point"}
}