{
  "type": "Feature",
  "properties": {
    "addr:full":"Hvorvarpvej 32, Hvorvarp Aars Danmark 9600",
    "addr:housenumber":"32",
    "addr:postcode":"9600",
    "addr:street":"Hvorvarpvej",
    "iso:country":"DK",
    "sg:address":"Hvorvarpvej 32, Hvorvarp",
    "sg:city":"Aars",
    "sg:orig_category":"Brudekjoler",
    "sg:phone":"+45 98 66 11 65",
    "sg:postcode":"9600",
    "sg:province":"Danmark",
    "wof:name":"Brudesalonen",
    "wof:placetype":"venue"
},
  "geometry": {"coordinates":[9.5170412064,56.8031692505],"type":"Point"}
}