{
  "type": "Feature",
  "properties": {
    "iso:country":"DK",
    "sg:address":"Fmd.: Karl Overgaard, Poppelvej 2",
    "sg:city":"Aalestrup",
    "sg:orig_category":"Kirkelige foreninger",
    "sg:phone":"+45 98 64 20 04",
    "sg:postcode":"9620",
    "sg:province":"Danmark",
    "wof:name":"KFUM's st\u00f8tteforening",
    "wof:placetype":"venue"
},
  "geometry": {"coordinates":[9.4901504517,56.6938285828],"type":"Point"}
}