{
  "type": "Feature",
  "properties": {
    "addr:full":"B\u00e6kvej 4 Gedved Danmark 8751",
    "addr:housenumber":"4",
    "addr:postcode":"8751",
    "addr:street":"Baekvej",
    "iso:country":"DK",
    "sg:address":"B\u00e6kvej 4",
    "sg:city":"Gedved",
    "sg:orig_category":"Hundekenneler",
    "sg:phone":"+45 75 66 52 87",
    "sg:postcode":"8751",
    "sg:province":"Danmark",
    "wof:name":"Riis, Kennel",
    "wof:placetype":"venue"
},
  "geometry": {"coordinates":[9.8441801071,55.9348068237],"type":"Point"}
}