{
  "type": "Feature",
  "properties": {
    "addr:full":"Slettens Landevej 102, Klinte Holme Bogense Danmark 5400",
    "addr:housenumber":"102",
    "addr:postcode":"5400",
    "addr:street":"Slettens Landevej;Klinte Holme",
    "iso:country":"DK",
    "sg:address":"Slettens Landevej 102, Klinte Holme",
    "sg:city":"Bogense",
    "sg:orig_category":"Maskinstationer",
    "sg:phone":"+45 64 86 12 64",
    "sg:postcode":"5400",
    "sg:province":"Danmark",
    "wof:name":"Knud's Maskinstation ApS",
    "wof:placetype":"venue"
},
  "geometry": {"coordinates":[10.0943098068,55.5637893677],"type":"Point"}
}