{
  "type": "Feature",
  "properties": {
    "iso:country":"DK",
    "sg:address":"Brydehusvej 12",
    "sg:city":"Ballerup",
    "sg:orig_category":"Stofmisbruger-institutioner",
    "sg:phone":"+45 44 77 37 37",
    "sg:postcode":"2750",
    "sg:province":"Danmark",
    "wof:name":"St\u00f8tte- og Aktivitetscentret",
    "wof:placetype":"venue"
},
  "geometry": {"coordinates":[12.3752555847,55.7299804688],"type":"Point"}
}