{
  "type": "Feature",
  "properties": {
    "addr:full":"N\u00f8rregade 33 K\u00f8ge Danmark 4600",
    "addr:housenumber":"33",
    "addr:postcode":"4600",
    "addr:street":"Norregade",
    "iso:country":"DK",
    "sg:address":"N\u00f8rregade 33",
    "sg:city":"K\u00f8ge",
    "sg:orig_category":"Pizzeriaer",
    "sg:phone":"+45 56 63 57 52",
    "sg:postcode":"4600",
    "sg:province":"Danmark",
    "wof:name":"Shawarma Hus",
    "wof:placetype":"venue"
},
  "geometry": {"coordinates":[12.1835823059,55.4590034485],"type":"Point"}
}