{
  "type": "Feature",
  "properties": {
    "addr:full":"Bybjergvej 1-3 Skovlunde Danmark 2740",
    "addr:housenumber":"1-3",
    "addr:postcode":"2740",
    "addr:street":"Bybjergvej",
    "iso:country":"DK",
    "sg:address":"Bybjergvej 1-3",
    "sg:city":"Skovlunde",
    "sg:orig_category":"Legesteder",
    "sg:phone":"+45 44 77 21 40",
    "sg:postcode":"2740",
    "sg:province":"Danmark",
    "wof:name":"Ellekilde Fritidscenter",
    "wof:placetype":"venue"
},
  "geometry": {"coordinates":[12.403711319,55.7188873291],"type":"Point"}
}