{
  "type": "Feature",
  "properties": {
    "addr:full":"Munkevej 3 Thisted Danmark 7700",
    "addr:housenumber":"3",
    "addr:postcode":"7700",
    "addr:street":"Munkevej",
    "iso:country":"DK",
    "sg:address":"Munkevej 3",
    "sg:city":"Thisted",
    "sg:orig_category":"Distriktspsykiatri",
    "sg:phone":"+45 97 91 08 22",
    "sg:postcode":"7700",
    "sg:province":"Danmark",
    "wof:name":"Daghuset Thisted - Distriktpsykiatri Nord",
    "wof:placetype":"venue"
},
  "geometry": {"coordinates":[8.6964616776,56.9560546875],"type":"Point"}
}