{
  "type": "Feature",
  "properties": {
    "addr:full":"Lauravej 30 Valby Danmark 2500",
    "addr:housenumber":"30",
    "addr:postcode":"2500",
    "addr:street":"Lauravej",
    "iso:country":"DK",
    "sg:address":"Lauravej 30",
    "sg:city":"Valby",
    "sg:orig_category":"Gulvbehandling",
    "sg:phone":"+45 36 44 00 54",
    "sg:postcode":"2500",
    "sg:province":"Danmark",
    "wof:name":"Cirkel Gulve",
    "wof:placetype":"venue"
},
  "geometry": {"coordinates":[12.5106620789,55.6689529419],"type":"Point"}
}