{
  "type": "Feature",
  "properties": {
    "iso:country":"DK",
    "sg:address":"Ahlmanns All\u00e9 6",
    "sg:city":"Hellerup",
    "sg:orig_category":"Biblioteker",
    "sg:phone":"+45 39 48 75 00",
    "sg:postcode":"2900",
    "sg:province":"Danmark",
    "sg:website":"www.gentofte.bibnet.dk",
    "wof:name":"Hovedbiblioteket Gentofte Kommune",
    "wof:placetype":"venue"
},
  "geometry": {"coordinates":[12.574419,55.737],"type":"Point"}
}