{
  "type": "Feature",
  "properties": {
    "addr:full":"Liv\u00f8vej 10 B Viborg Danmark 8800",
    "addr:housenumber":"10 b",
    "addr:postcode":"8800",
    "addr:street":"Livovej",
    "iso:country":"DK",
    "sg:address":"Liv\u00f8vej 10 B",
    "sg:city":"Viborg",
    "sg:orig_category":"Vinduer",
    "sg:phone":"+45 86 62 18 88",
    "sg:postcode":"8800",
    "sg:province":"Danmark",
    "sg:website":"www.unik.as",
    "wof:name":"Unik Vinduer & D\u00f8re A/S",
    "wof:placetype":"venue"
},
  "geometry": {"coordinates":[9.3681592941,56.4520301819],"type":"Point"}
}