{
  "type": "Feature",
  "properties": {
    "iso:country":"DK",
    "sg:address":"Fmd.: Knud Rosenkj\u00e6r, Symfonialle 62",
    "sg:city":"Horsens",
    "sg:orig_category":"Hobbybetonede foreninger",
    "sg:phone":"+45 75 64 79 64",
    "sg:postcode":"8700",
    "sg:province":"Danmark",
    "wof:name":"Horsens Stenforening",
    "wof:placetype":"venue"
},
  "geometry": {"coordinates":[9.8432445526,55.8621063232],"type":"Point"}
}