{
  "type": "Feature",
  "properties": {
    "iso:country":"DK",
    "sg:address":"Alstrupvej 16",
    "sg:city":"Holstebro",
    "sg:orig_category":"Vinduespolering",
    "sg:phone":"+45 97 42 75 92",
    "sg:postcode":"7500",
    "sg:province":"Danmark",
    "wof:name":"H H Modulservice",
    "wof:placetype":"venue"
},
  "geometry": {"coordinates":[8.5729589462,56.3931427002],"type":"Point"}
}