{
  "type": "Feature",
  "properties": {
    "addr:full":"Kornblomstvej 2 Aalborg Danmark 9000",
    "addr:housenumber":"2",
    "addr:postcode":"9000",
    "addr:street":"Kornblomstvej",
    "iso:country":"DK",
    "sg:address":"Kornblomstvej 2",
    "sg:city":"Aalborg",
    "sg:orig_category":"Hudpleje",
    "sg:phone":"+45 98 16 22 43",
    "sg:postcode":"9000",
    "sg:province":"Danmark",
    "wof:name":"Ici, Clinique",
    "wof:placetype":"venue"
},
  "geometry": {"coordinates":[9.9041318893,57.0345573425],"type":"Point"}
}