{
  "type": "Feature",
  "properties": {
    "addr:full":"Tj\u00f8rnevej 12 Svinninge Danmark 4520",
    "addr:housenumber":"12",
    "addr:postcode":"4520",
    "addr:street":"Tjornevej",
    "iso:country":"DK",
    "sg:address":"Tj\u00f8rnevej 12",
    "sg:city":"Svinninge",
    "sg:orig_category":"Zoneterapeuter",
    "sg:phone":"+45 59 26 52 42",
    "sg:postcode":"4520",
    "sg:province":"Danmark",
    "wof:name":"Harbo, Birgit",
    "wof:placetype":"venue"
},
  "geometry": {"coordinates":[11.4666109085,55.7175102234],"type":"Point"}
}