{
  "type": "Feature",
  "properties": {
    "iso:country":"DK",
    "sg:address":"Fiskerihavnsgade 13 B",
    "sg:city":"Esbjerg",
    "sg:orig_category":"Spedition",
    "sg:phone":"+45 75 12 77 11",
    "sg:postcode":"6700",
    "sg:province":"Danmark",
    "wof:name":"Transport Service A/S",
    "wof:placetype":"venue"
},
  "geometry": {"coordinates":[8.426410675,55.4745750427],"type":"Point"}
}