{
  "type": "Feature",
  "properties": {
    "addr:full":"Fmd.: Klara Reenberg, Badstuegade 5 Vordingborg Danmark 4760",
    "addr:housenumber":"5",
    "addr:postcode":"4760",
    "addr:street":"Badstuegade",
    "iso:country":"DK",
    "sg:address":"Fmd.: Klara Reenberg, Badstuegade 5",
    "sg:city":"Vordingborg",
    "sg:orig_category":"Musik og sang",
    "sg:phone":"+45 55 37 35 90",
    "sg:postcode":"4760",
    "sg:province":"Danmark",
    "wof:name":"Sangforeningen Stjernen",
    "wof:placetype":"venue"
},
  "geometry": {"coordinates":[11.9124183655,55.0085449219],"type":"Point"}
}