{
  "type": "Feature",
  "properties": {
    "addr:full":"Birkev\u00e6nget 64, Askov Vejen Danmark 6600",
    "addr:housenumber":"64",
    "addr:postcode":"6600",
    "addr:street":"Birkevaenget",
    "iso:country":"DK",
    "sg:address":"Birkev\u00e6nget 64, Askov",
    "sg:city":"Vejen",
    "sg:orig_category":"Fodplejere",
    "sg:phone":"+45 75 36 08 10",
    "sg:postcode":"6600",
    "sg:province":"Danmark",
    "wof:name":"Ellen's Fodpleje",
    "wof:placetype":"venue"
},
  "geometry": {"coordinates":[9.1396121979,55.4778175354],"type":"Point"}
}