{
  "type": "Feature",
  "properties": {
    "iso:country":"DK",
    "sg:address":"Danmarksgade 23",
    "sg:city":"Vejle",
    "sg:orig_category":"Vuggestuer",
    "sg:phone":"+45 75 82 09 59",
    "sg:postcode":"7100",
    "sg:province":"Danmark",
    "wof:name":"Sct. Georgshjemmets Vuggestue",
    "wof:placetype":"venue"
},
  "geometry": {"coordinates":[9.5376052856,55.7053527832],"type":"Point"}
}