{
  "type": "Feature",
  "properties": {
    "iso:country":"DK",
    "sg:address":"R\u00f8m\u00f8vej 2",
    "sg:city":"Frederikshavn",
    "sg:orig_category":"Bagere",
    "sg:phone":"+45 98 41 04 91",
    "sg:postcode":"9900",
    "sg:province":"Danmark",
    "wof:name":"Centerbageriet",
    "wof:placetype":"venue"
},
  "geometry": {"coordinates":[10.5363,57.43964],"type":"Point"}
}