{
  "type": "Feature",
  "properties": {
    "iso:country":"DK",
    "sg:address":"N\u00f8rregade 7",
    "sg:city":"Hundested",
    "sg:orig_category":"Lokalarkiver",
    "sg:phone":"+45 47 98 10 10",
    "sg:postcode":"3390",
    "sg:province":"Danmark",
    "wof:name":"Lokalhistorisk arkiv",
    "wof:placetype":"venue"
},
  "geometry": {"coordinates":[11.8499736786,55.9653549194],"type":"Point"}
}