{
  "type": "Feature",
  "properties": {
    "addr:full":"Fmd.: Ejler Ottov, Hesteskoen 9, Ingstrup L\u00f8kken Danmark 9480",
    "addr:housenumber":"9",
    "addr:postcode":"9480",
    "addr:street":"Hesteskoen",
    "iso:country":"DK",
    "sg:address":"Fmd.: Ejler Ottov, Hesteskoen 9, Ingstrup",
    "sg:city":"L\u00f8kken",
    "sg:orig_category":"\u00c3\u2020ldreorganisationer og klubber",
    "sg:phone":"+45 98 88 36 87",
    "sg:postcode":"9480",
    "sg:province":"Danmark",
    "wof:name":"Ingstrup pensionistklub",
    "wof:placetype":"venue"
},
  "geometry": {"coordinates":[9.715880394,57.3703308105],"type":"Point"}
}