{
  "type": "Feature",
  "properties": {
    "addr:full":"Dyreg\u00e5rdsvej 9-13 Skovlunde Danmark 2740",
    "addr:housenumber":"9-13",
    "addr:postcode":"2740",
    "addr:street":"Dyregaardsvej",
    "iso:country":"DK",
    "sg:address":"Dyreg\u00e5rdsvej 9-13",
    "sg:city":"Skovlunde",
    "sg:orig_category":"Private skoler",
    "sg:phone":"+45 44 66 01 66",
    "sg:postcode":"2740",
    "sg:province":"Danmark",
    "sg:website":"www.thomasskolen.dk",
    "wof:name":"Thomasskolen",
    "wof:placetype":"venue"
},
  "geometry": {"coordinates":[12.3998947144,55.7288818359],"type":"Point"}
}