{
  "type": "Feature",
  "properties": {
    "addr:full":"Gl. Torv 10 Slagelse Danmark 4200",
    "addr:housenumber":"10",
    "addr:postcode":"4200",
    "addr:street":"Gl. Torv",
    "iso:country":"DK",
    "sg:address":"Gl. Torv 10",
    "sg:city":"Slagelse",
    "sg:orig_category":"Tandteknikere, Kliniske",
    "sg:phone":"+45 58 52 13 75",
    "sg:postcode":"4200",
    "sg:province":"Danmark",
    "wof:name":"Eriksen, H. J.",
    "wof:placetype":"venue"
},
  "geometry": {"coordinates":[11.3569850922,55.4050865173],"type":"Point"}
}