{
  "type": "Feature",
  "properties": {
    "addr:full":"\u00d8rneh\u00f8jg\u00e5rdsvej 11 Vordingborg Danmark 4760",
    "addr:housenumber":"11",
    "addr:postcode":"4760",
    "addr:street":"Ornehojgaardsvej",
    "iso:country":"DK",
    "sg:address":"\u00d8rneh\u00f8jg\u00e5rdsvej 11",
    "sg:city":"Vordingborg",
    "sg:orig_category":"\u00c3\u02dcvrige skoler",
    "sg:phone":"+45 55 31 25 00",
    "sg:postcode":"4760",
    "sg:province":"Danmark",
    "sg:website":"www.ornehoj.dk",
    "wof:name":"\u00d8rneh\u00f8j, V\u00e6rkstedsskolen",
    "wof:placetype":"venue"
},
  "geometry": {"coordinates":[11.9124183655,55.0085449219],"type":"Point"}
}