{
  "type": "Feature",
  "properties": {
    "addr:full":"Torvegade 14 Brande Danmark 7330",
    "addr:housenumber":"14",
    "addr:postcode":"7330",
    "addr:street":"Torvegade",
    "iso:country":"DK",
    "sg:address":"Torvegade 14",
    "sg:city":"Brande",
    "sg:orig_category":"Bodegaer",
    "sg:phone":"+45 97 18 18 48",
    "sg:postcode":"7330",
    "sg:province":"Danmark",
    "wof:name":"Hosekr\u00e6mmeren",
    "wof:placetype":"venue"
},
  "geometry": {"coordinates":[9.1295900345,55.9428787231],"type":"Point"}
}