{
  "type": "Feature",
  "properties": {
    "iso:country":"DK",
    "sg:address":"J\u00f8rlunde Overdrev 7, J\u00f8rlunde",
    "sg:city":"Slangerup",
    "sg:orig_category":"Gartnerier",
    "sg:phone":"+45 47 38 17 76",
    "sg:postcode":"3550",
    "sg:province":"Danmark",
    "wof:name":"Bures\u00f8 Gr\u00f8ntsager I/S",
    "wof:placetype":"venue"
},
  "geometry": {"coordinates":[12.1717596054,55.8460769653],"type":"Point"}
}