{
  "type": "Feature",
  "properties": {
    "addr:full":"Bredstrupvej 42 Grenaa Danmark 8500",
    "addr:housenumber":"42",
    "addr:postcode":"8500",
    "addr:street":"Bredstrupvej",
    "iso:country":"DK",
    "sg:address":"Bredstrupvej 42",
    "sg:city":"Grenaa",
    "sg:orig_category":"Fabrikker",
    "sg:phone":"+45 87 58 44 33",
    "sg:postcode":"8500",
    "sg:province":"Danmark",
    "wof:name":"BASF Health & Nutrition A/S",
    "wof:placetype":"venue"
},
  "geometry": {"coordinates":[10.9089584351,56.4215393066],"type":"Point"}
}