{
  "type": "Feature",
  "properties": {
    "addr:full":"Vinkelvej 19 Marslev Danmark 5290",
    "addr:housenumber":"19",
    "addr:postcode":"5290",
    "addr:street":"Vinkelvej",
    "iso:country":"DK",
    "sg:address":"Vinkelvej 19",
    "sg:city":"Marslev",
    "sg:orig_category":"Autoopretning",
    "sg:phone":"+45 65 95 15 53",
    "sg:postcode":"5290",
    "sg:province":"Danmark",
    "wof:name":"Marslev Autoopretning",
    "wof:placetype":"venue"
},
  "geometry": {"coordinates":[10.5191411972,55.379901886],"type":"Point"}
}