{
  "type": "Feature",
  "properties": {
    "addr:full":"Kl\u00f8vermarken 33 Esperg\u00e6rde Danmark 3060",
    "addr:housenumber":"33",
    "addr:postcode":"3060",
    "addr:street":"Klovermarken",
    "iso:country":"DK",
    "sg:address":"Kl\u00f8vermarken 33",
    "sg:city":"Esperg\u00e6rde",
    "sg:orig_category":"INGENI\u00c3\u02dcRER",
    "sg:phone":"+45 49 13 64 36",
    "sg:postcode":"3060",
    "sg:province":"Danmark",
    "wof:name":"Wium, Niels Erik",
    "wof:placetype":"venue"
},
  "geometry": {"coordinates":[11.6512403488,47.8390617371],"type":"Point"}
}