{
  "type": "Feature",
  "properties": {
    "addr:full":"Torvev\u00e6nget 5 B Tranbjerg Danmark 8310",
    "addr:housenumber":"5 b",
    "addr:postcode":"8310",
    "addr:street":"Torvevaenget",
    "iso:country":"DK",
    "sg:address":"Torvev\u00e6nget 5 B",
    "sg:city":"Tranbjerg",
    "sg:orig_category":"Integrerede institutioner",
    "sg:phone":"+45 86 29 50 68",
    "sg:postcode":"8310",
    "sg:province":"Danmark",
    "wof:name":"Torvev\u00e6nget, Integreret Inst.",
    "wof:placetype":"venue"
},
  "geometry": {"coordinates":[10.1377973557,56.0914382935],"type":"Point"}
}