{
  "type": "Feature",
  "properties": {
    "addr:full":"Tv\u00e6rgade 3 Silkeborg Danmark 8600",
    "addr:housenumber":"3",
    "addr:postcode":"8600",
    "addr:street":"Tvaergade",
    "iso:country":"DK",
    "sg:address":"Tv\u00e6rgade 3",
    "sg:city":"Silkeborg",
    "sg:orig_category":"Forsikringer",
    "sg:phone":"+45 87 20 71 00",
    "sg:postcode":"8600",
    "sg:province":"Danmark",
    "wof:name":"Tryg-Baltica",
    "wof:placetype":"venue"
},
  "geometry": {"coordinates":[9.5475273132,56.1685676575],"type":"Point"}
}