{
  "type": "Feature",
  "properties": {
    "addr:full":"v/ Susanne Juul Andersen, R\u00f8dehusvej 31, Vive Hadsund Danmark 9560",
    "addr:housenumber":"31",
    "addr:postcode":"9560",
    "addr:street":"Rodehusvej;Vive",
    "iso:country":"DK",
    "sg:address":"v/ Susanne Juul Andersen, R\u00f8dehusvej 31, Vive",
    "sg:city":"Hadsund",
    "sg:orig_category":"Borger- og beboerforeninger",
    "sg:phone":"+45 98 57 39 89",
    "sg:postcode":"9560",
    "sg:province":"Danmark",
    "wof:name":"Vive sogns Beboerforening",
    "wof:placetype":"venue"
},
  "geometry": {"coordinates":[10.115904808,56.7150764465],"type":"Point"}
}