{
  "type": "Feature",
  "properties": {
    "addr:full":"Peter Fabers Gade 35 st tv K\u00f8benhavn N Danmark 2200",
    "addr:housenumber":"35 st",
    "addr:postcode":"2200",
    "addr:street":"Peter Fabers Gade;N Danmark",
    "iso:country":"DK",
    "sg:address":"Peter Fabers Gade 35 st tv",
    "sg:city":"K\u00f8benhavn N",
    "sg:orig_category":"Konsulentvirksomheder",
    "sg:phone":"+45 28 26 45 03",
    "sg:postcode":"2200",
    "sg:province":"Danmark",
    "wof:name":"Fat Cat Consult",
    "wof:placetype":"venue"
},
  "geometry": {"coordinates":[99.92501068120001,34.2430114746],"type":"Point"}
}