{
  "type": "Feature",
  "properties": {
    "addr:full":"Vejlegadebro 6 Nakskov Danmark 4900",
    "addr:housenumber":"6",
    "addr:postcode":"4900",
    "addr:street":"Vejlegadebro",
    "iso:country":"DK",
    "sg:address":"Vejlegadebro 6",
    "sg:city":"Nakskov",
    "sg:orig_category":"Glarmestre og glarmagere",
    "sg:phone":"+45 54 92 64 56",
    "sg:postcode":"4900",
    "sg:province":"Danmark",
    "wof:name":"JD Glas ApS",
    "wof:placetype":"venue"
},
  "geometry": {"coordinates":[11.1310281754,54.8337593079],"type":"Point"}
}