{
  "type": "Feature",
  "properties": {
    "addr:full":"Skovbjergvej 7, Arnborg Herning Danmark 7400",
    "addr:housenumber":"7",
    "addr:postcode":"7400",
    "addr:street":"Skovbjergvej;Arnborg",
    "iso:country":"DK",
    "sg:address":"Skovbjergvej 7, Arnborg",
    "sg:city":"Herning",
    "sg:orig_category":"Genbrugsbutikker",
    "sg:phone":"+45 97 14 97 70",
    "sg:postcode":"7400",
    "sg:province":"Danmark",
    "wof:name":"Skovbjerg, Lilian Kiel",
    "wof:placetype":"venue"
},
  "geometry": {"coordinates":[8.9768896103,56.1374168396],"type":"Point"}
}