{
  "type": "Feature",
  "properties": {
    "addr:full":"Kalundborgvej 6 Holb\u00e6k Danmark 4300",
    "addr:housenumber":"6",
    "addr:postcode":"4300",
    "addr:street":"Kalundborgvej",
    "iso:country":"DK",
    "sg:address":"Kalundborgvej 6",
    "sg:city":"Holb\u00e6k",
    "sg:orig_category":"INGENI\u00c3\u02dcRER",
    "sg:phone":"+45 59 43 76 00",
    "sg:postcode":"4300",
    "sg:province":"Danmark",
    "wof:name":"Schmidt ApS, Ingeni\u00f8rfirmaet Sv. E.",
    "wof:placetype":"venue"
},
  "geometry": {"coordinates":[76.3070983887,14.277130127],"type":"Point"}
}