{
  "type": "Feature",
  "properties": {
    "addr:full":"R\u00f8nnevangshusene 158 Taastrup Danmark 2630",
    "addr:housenumber":"158",
    "addr:postcode":"2630",
    "iso:country":"DK",
    "sg:address":"R\u00f8nnevangshusene 158",
    "sg:city":"Taastrup",
    "sg:orig_category":"Vagtbureauer",
    "sg:phone":"+45 43 96 68 64",
    "sg:postcode":"2630",
    "sg:province":"Danmark",
    "sg:website":"www.khvagt.dk",
    "wof:name":"K.H. Vagtservice",
    "wof:placetype":"venue"
},
  "geometry": {"coordinates":[12.284995079,55.6446723938],"type":"Point"}
}