{
  "type": "Feature",
  "properties": {
    "iso:country":"DK",
    "sg:address":"H\u00f8jgade 2",
    "sg:city":"Vojens",
    "sg:orig_category":"Keramik",
    "sg:phone":"+45 74 54 00 20",
    "sg:postcode":"6500",
    "sg:province":"Danmark",
    "sg:website":"www.moellekeramik.nu",
    "wof:name":"M\u00f8lle Keramik",
    "wof:placetype":"venue"
},
  "geometry": {"coordinates":[9.2987146378,55.2457237244],"type":"Point"}
}