{
  "type": "Feature",
  "properties": {
    "addr:full":"Plutovej 1 Hedensted Danmark 8722",
    "addr:housenumber":"1",
    "addr:postcode":"8722",
    "addr:street":"Plutovej",
    "iso:country":"DK",
    "sg:address":"Plutovej 1",
    "sg:city":"Hedensted",
    "sg:orig_category":"Dyreklinikker og -hospitaler",
    "sg:phone":"+45 75 89 08 66",
    "sg:postcode":"8722",
    "sg:province":"Danmark",
    "wof:name":"Dyreklinikken",
    "wof:placetype":"venue"
},
  "geometry": {"coordinates":[9.6969938278,55.7806739807],"type":"Point"}
}