{
  "type": "Feature",
  "properties": {
    "addr:full":"Glarmestervej 6 Silkeborg Danmark 8600",
    "addr:housenumber":"6",
    "addr:postcode":"8600",
    "addr:street":"Glarmestervej",
    "iso:country":"DK",
    "sg:address":"Glarmestervej 6",
    "sg:city":"Silkeborg",
    "sg:orig_category":"Databehandling",
    "sg:phone":"+45 87 22 44 22",
    "sg:postcode":"8600",
    "sg:province":"Danmark",
    "wof:name":"Flex-Data ApS",
    "wof:placetype":"venue"
},
  "geometry": {"coordinates":[9.5367488861,56.184513092],"type":"Point"}
}