{
  "type": "Feature",
  "properties": {
    "addr:full":"Magnoliavej 19, Fl\u00f8ng Hedehusene Danmark 2640",
    "addr:housenumber":"19",
    "addr:postcode":"2640",
    "addr:street":"Magnoliavej;Flong",
    "iso:country":"DK",
    "sg:address":"Magnoliavej 19, Fl\u00f8ng",
    "sg:city":"Hedehusene",
    "sg:orig_category":"Blomsterhandlere",
    "sg:phone":"+45 46 59 00 69",
    "sg:postcode":"2640",
    "sg:province":"Danmark",
    "wof:name":"Blomsterskuret",
    "wof:placetype":"venue"
},
  "geometry": {"coordinates":[12.1993551254,55.6496009827],"type":"Point"}
}