{
  "type": "Feature",
  "properties": {
    "addr:full":"Frederiksberggade 23, Postboks 255 Silkeborg Danmark 8600",
    "addr:housenumber":"23;255",
    "addr:postcode":"8600",
    "addr:street":"Frederiksberggade",
    "iso:country":"DK",
    "sg:address":"Frederiksberggade 23, Postboks 255",
    "sg:city":"Silkeborg",
    "sg:orig_category":"Musik- og solistbureauer",
    "sg:phone":"+45 87 20 68 00",
    "sg:postcode":"8600",
    "sg:province":"Danmark",
    "sg:website":"www.panagency.com",
    "wof:name":"Pan International Agency ApS",
    "wof:placetype":"venue"
},
  "geometry": {"coordinates":[9.5524425507,56.1693305969],"type":"Point"}
}