{
  "type": "Feature",
  "properties": {
    "addr:full":"Langegade 16 Kerteminde Danmark 5300",
    "addr:housenumber":"16",
    "addr:postcode":"5300",
    "addr:street":"Langegade",
    "iso:country":"DK",
    "sg:address":"Langegade 16",
    "sg:city":"Kerteminde",
    "sg:orig_category":"Metervarer",
    "sg:phone":"+45 65 32 21 05",
    "sg:postcode":"5300",
    "sg:province":"Danmark",
    "wof:name":"Refning Poulsen",
    "wof:placetype":"venue"
},
  "geometry": {"coordinates":[10.6580095291,55.4501647949],"type":"Point"}
}