{
  "type": "Feature",
  "properties": {
    "iso:country":"DK",
    "sg:address":"Mosesvinget 3",
    "sg:city":"K\u00f8benhavn NV",
    "sg:classifiers":[
        {
            "category":"Restaurant",
            "type":"Food & Drink"
        }
    ],
    "sg:phone":"+45 38 60 52 48",
    "sg:postcode":"2400",
    "sg:province":"Danmark",
    "wof:name":"Mosehuset, Restaurant",
    "wof:placetype":"venue"
},
  "geometry": {"coordinates":[-117.02272033689999,38.5024604797],"type":"Point"}
}