{
  "type": "Feature",
  "properties": {
    "addr:full":"R\u00e6vevej 12 Skive Danmark 7800",
    "addr:housenumber":"12",
    "addr:postcode":"7800",
    "addr:street":"Raevevej",
    "iso:country":"DK",
    "sg:address":"R\u00e6vevej 12",
    "sg:city":"Skive",
    "sg:orig_category":"Maskinfabrikker",
    "sg:phone":"+45 97 51 04 99",
    "sg:postcode":"7800",
    "sg:province":"Danmark",
    "sg:website":"www.dapeca.dk",
    "wof:name":"Maskinfabrikken Dapeca ApS",
    "wof:placetype":"venue"
},
  "geometry": {"coordinates":[9.0254192352,56.5386810303],"type":"Point"}
}