{
  "type": "Feature",
  "properties": {
    "iso:country":"DK",
    "sg:address":"v/ Henning J\u00f8rgensen, Lifstrup Hovedvej 54",
    "sg:city":"Esbjerg N",
    "sg:orig_category":"Lokalarkiver",
    "sg:phone":"+45 75 16 92 46",
    "sg:postcode":"6715",
    "sg:province":"Danmark",
    "wof:name":"Vester Nebel Sognearkiv",
    "wof:placetype":"venue"
},
  "geometry": {"coordinates":[8.4780550003,55.535610199],"type":"Point"}
}