{
  "type": "Feature",
  "properties": {
    "iso:country":"DK",
    "sg:address":"Sydbanegade 2 A",
    "sg:city":"Kolding",
    "sg:orig_category":"INGENI\u00c3\u02dcRER",
    "sg:phone":"+45 75 50 89 91",
    "sg:postcode":"6000",
    "sg:province":"Danmark",
    "wof:name":"Stender ApS, Ingeni\u00f8rfirmaet Carsten",
    "wof:placetype":"venue"
},
  "geometry": {"coordinates":[9.4733667374,55.4862251282],"type":"Point"}
}