{
  "type": "Feature",
  "properties": {
    "addr:full":"Niels Bohrs Vej 44 Aalborg \u00d8 Danmark 9220",
    "addr:housenumber":"44",
    "addr:postcode":"9220",
    "addr:street":"Niels Bohrs Vej;Danmark",
    "iso:country":"DK",
    "sg:address":"Niels Bohrs Vej 44",
    "sg:city":"Aalborg \u00d8",
    "sg:orig_category":"Supermarkeder",
    "sg:phone":"+45 96 35 60 00",
    "sg:postcode":"9220",
    "sg:province":"Danmark",
    "wof:name":"F\u00f8tex",
    "wof:placetype":"venue"
},
  "geometry": {"coordinates":[9.9861726761,57.018409729],"type":"Point"}
}