{
  "type": "Feature",
  "properties": {
    "addr:full":"S\u00f8nderby Torv 29 Taastrup Danmark 2630",
    "addr:housenumber":"29",
    "addr:postcode":"2630",
    "addr:street":"Sonderby Torv",
    "iso:country":"DK",
    "sg:address":"S\u00f8nderby Torv 29",
    "sg:city":"Taastrup",
    "sg:orig_category":"Integrerede institutioner",
    "sg:phone":"+45 43 35 32 35",
    "sg:postcode":"2630",
    "sg:province":"Danmark",
    "wof:name":"Oasen Daginstitution",
    "wof:placetype":"venue"
},
  "geometry": {"coordinates":[12.2748765945,55.636806488],"type":"Point"}
}