{
  "type": "Feature",
  "properties": {
    "iso:country":"DK",
    "sg:address":"Lille \u00d8stergade 8",
    "sg:city":"Holstebro",
    "sg:classifiers":[
        {
            "category":"Restaurant",
            "type":"Food & Drink"
        }
    ],
    "sg:phone":"+45 97 42 80 99",
    "sg:postcode":"7500",
    "sg:province":"Danmark",
    "wof:name":"Papatya, Restaurant",
    "wof:placetype":"venue"
},
  "geometry": {"coordinates":[8.6192827225,56.3576850891],"type":"Point"}
}