{
  "type": "Feature",
  "properties": {
    "addr:full":"\u00d8sterbro 39 Aalborg Danmark 9000",
    "addr:housenumber":"39",
    "addr:postcode":"9000",
    "addr:street":"Osterbro",
    "iso:country":"DK",
    "sg:address":"\u00d8sterbro 39",
    "sg:city":"Aalborg",
    "sg:orig_category":"Autoforhandlere",
    "sg:phone":"+45 98 16 25 33",
    "sg:postcode":"9000",
    "sg:province":"Danmark",
    "wof:name":"Hyundai Aalborg",
    "wof:placetype":"venue"
},
  "geometry": {"coordinates":[9.9384078979,57.0464401245],"type":"Point"}
}