{
  "type": "Feature",
  "properties": {
    "addr:full":"Sverigesvej 20 Skanderborg Danmark 8660",
    "addr:housenumber":"20",
    "addr:postcode":"8660",
    "addr:street":"Sverigesvej",
    "iso:country":"DK",
    "sg:address":"Sverigesvej 20",
    "sg:city":"Skanderborg",
    "sg:orig_category":"Flytteforretninger",
    "sg:phone":"+45 70 22 44 74",
    "sg:postcode":"8660",
    "sg:province":"Danmark",
    "wof:name":"Nielsen Transport, Finn",
    "wof:placetype":"venue"
},
  "geometry": {"coordinates":[9.9535322189,56.0533943176],"type":"Point"}
}