{
  "type": "Feature",
  "properties": {
    "addr:full":"Pjentedamsgade 16 B Odense C Danmark 5000",
    "addr:housenumber":"16 b",
    "addr:postcode":"5000",
    "addr:street":"Pjentedamsgade",
    "iso:country":"DK",
    "sg:address":"Pjentedamsgade 16 B",
    "sg:city":"Odense C",
    "sg:classifiers":[
        {
            "category":"Restaurant",
            "type":"Food & Drink"
        }
    ],
    "sg:phone":"+45 65 90 67 07",
    "sg:postcode":"5000",
    "sg:province":"Danmark",
    "wof:name":"Torvecafeen",
    "wof:placetype":"venue"
},
  "geometry": {"coordinates":[10.3936319351,55.4000053406],"type":"Point"}
}