{
  "type": "Feature",
  "properties": {
    "iso:country":"DK",
    "sg:address":"Vedb\u00e6kvej 15",
    "sg:city":"K\u00f8ge",
    "sg:orig_category":"Vinduespolering",
    "sg:phone":"+45 56 66 09 21",
    "sg:postcode":"4600",
    "sg:province":"Danmark",
    "wof:name":"K.D. Vinduespolering",
    "wof:placetype":"venue"
},
  "geometry": {"coordinates":[12.1888580322,55.4986839294],"type":"Point"}
}