{
  "type": "Feature",
  "properties": {
    "addr:full":"v/ Ejner Nielsen, Degnev\u00e6nget 12, N\u00e6sby Odense N Danmark 5270",
    "addr:housenumber":"12",
    "addr:postcode":"5270",
    "addr:street":"Naesby",
    "iso:country":"DK",
    "sg:address":"v/ Ejner Nielsen, Degnev\u00e6nget 12, N\u00e6sby",
    "sg:city":"Odense N",
    "sg:orig_category":"Hobbybetonede foreninger",
    "sg:phone":"+45 66 18 15 05",
    "sg:postcode":"5270",
    "sg:province":"Danmark",
    "wof:name":"Odense Video & Smalfilm Amat\u00f8r-Klub",
    "wof:placetype":"venue"
},
  "geometry": {"coordinates":[10.3306798935,55.4711418152],"type":"Point"}
}