{
  "type": "Feature",
  "properties": {
    "addr:full":"N\u00f8rregade 28 Hornsyld Danmark 8783",
    "addr:housenumber":"28",
    "addr:postcode":"8783",
    "addr:street":"Norregade",
    "iso:country":"DK",
    "sg:address":"N\u00f8rregade 28",
    "sg:city":"Hornsyld",
    "sg:orig_category":"Non-Classified Establishments",
    "sg:phone":"+45 75 68 73 00",
    "sg:postcode":"8783",
    "sg:province":"Danmark",
    "wof:name":"Hornsyld K\u00f8bmandsgaard A/S",
    "wof:placetype":"venue"
},
  "geometry": {"coordinates":[9.8644666672,55.7593269348],"type":"Point"}
}