{
  "type": "Feature",
  "properties": {
    "iso:country":"DK",
    "sg:address":"Rudolfg\u00e5rdsvej 17",
    "sg:city":"Viby",
    "sg:orig_category":"Snedkermestre",
    "sg:phone":"+45 86 28 28 88",
    "sg:postcode":"8260",
    "sg:province":"Danmark",
    "wof:name":"Inventarsnedkeriet, A/S",
    "wof:placetype":"venue"
},
  "geometry": {"coordinates":[10.1410722733,56.111492157],"type":"Point"}
}