{
  "type": "Feature",
  "properties": {
    "addr:full":"Fmd.: Tage Bech, Baldersv\u00e6nget 3, Thur\u00f8 Svendborg Danmark 5700",
    "addr:housenumber":"3",
    "addr:postcode":"5700",
    "addr:street":"Baldersvaenget;Thuro",
    "iso:country":"DK",
    "sg:address":"Fmd.: Tage Bech, Baldersv\u00e6nget 3, Thur\u00f8",
    "sg:city":"Svendborg",
    "sg:orig_category":"Faglige organisationer og foreninger",
    "sg:phone":"+45 62 20 59 03",
    "sg:postcode":"5700",
    "sg:province":"Danmark",
    "wof:name":"Ledernes Hovedorganisation",
    "wof:placetype":"venue"
},
  "geometry": {"coordinates":[10.6065101624,55.0595970154],"type":"Point"}
}