{
  "type": "Feature",
  "properties": {
    "addr:full":"Svendborgvej 1, Hjallese Odense S Danmark 5260",
    "addr:housenumber":"1",
    "addr:postcode":"5260",
    "addr:street":"Svendborgvej;Hjallese",
    "iso:country":"DK",
    "sg:address":"Svendborgvej 1, Hjallese",
    "sg:city":"Odense S",
    "sg:orig_category":"Servicestationer",
    "sg:phone":"+45 66 13 09 01",
    "sg:postcode":"5260",
    "sg:province":"Danmark",
    "wof:name":"Statoil Servicenter",
    "wof:placetype":"venue"
},
  "geometry": {"coordinates":[10.3157806396,55.3122825623],"type":"Point"}
}