{
  "type": "Feature",
  "properties": {
    "addr:full":"v/ Richard Nielsen, Hasselvej 7 Bjerringbro Danmark 8850",
    "addr:housenumber":"7",
    "addr:postcode":"8850",
    "addr:street":"Hasselvej",
    "iso:country":"DK",
    "sg:address":"v/ Richard Nielsen, Hasselvej 7",
    "sg:city":"Bjerringbro",
    "sg:orig_category":"Loger",
    "sg:phone":"+45 86 68 40 66",
    "sg:postcode":"8850",
    "sg:province":"Danmark",
    "wof:name":"Sct. Georgs Gilde Bjerringbro",
    "wof:placetype":"venue"
},
  "geometry": {"coordinates":[9.6546850204,56.3754692078],"type":"Point"}
}