{
  "type": "Feature",
  "properties": {
    "addr:full":"Chr. Hansensvej 3 Vejle Danmark 7100",
    "addr:housenumber":"3",
    "addr:postcode":"7100",
    "addr:street":"Chr. Hansensvej",
    "iso:country":"DK",
    "sg:address":"Chr. Hansensvej 3",
    "sg:city":"Vejle",
    "sg:orig_category":"Forlag",
    "sg:phone":"+45 75 82 39 00",
    "sg:postcode":"7100",
    "sg:province":"Danmark",
    "sg:website":"www.kroghsforlag.dk",
    "wof:name":"Thaning & Appels Forlag A/S",
    "wof:placetype":"venue"
},
  "geometry": {"coordinates":[9.5326309204,55.724937439],"type":"Point"}
}