{
  "type": "Feature",
  "properties": {
    "iso:country":"DK",
    "sg:address":"S\u00f8ller\u00f8dvej 111, S\u00f8ller\u00f8d",
    "sg:city":"N\u00e6rum",
    "sg:orig_category":"Arkitekter",
    "sg:phone":"+45 45 80 65 00",
    "sg:postcode":"2850",
    "sg:province":"Danmark",
    "wof:name":"Nielsen, Erik O.",
    "wof:placetype":"venue"
},
  "geometry": {"coordinates":[-89.99810791020001,38.1321372986],"type":"Point"}
}