{
  "type": "Feature",
  "properties": {
    "iso:country":"DK",
    "sg:address":"Lavhedevej 54",
    "sg:city":"Holstebro",
    "sg:orig_category":"Bogtrykkerier",
    "sg:phone":"+45 97 42 06 02",
    "sg:postcode":"7500",
    "sg:province":"Danmark",
    "wof:name":"Holm Lyntryk",
    "wof:placetype":"venue"
},
  "geometry": {"coordinates":[8.6166992188,56.3752937317],"type":"Point"}
}