{
  "type": "Feature",
  "properties": {
    "addr:full":"Egeg\u00e5rdsvej 15 R\u00f8dovre Danmark 2610",
    "addr:housenumber":"15",
    "addr:postcode":"2610",
    "addr:street":"Egegaardsvej",
    "iso:country":"DK",
    "sg:address":"Egeg\u00e5rdsvej 15",
    "sg:city":"R\u00f8dovre",
    "sg:orig_category":"Autoreparation og -service",
    "sg:phone":"+45 36 70 95 79",
    "sg:postcode":"2610",
    "sg:province":"Danmark",
    "wof:name":"Taarup's Autov\u00e6rksted",
    "wof:placetype":"venue"
},
  "geometry": {"coordinates":[10.6992139816,61.1027755737],"type":"Point"}
}