{
  "type": "Feature",
  "properties": {
    "iso:country":"DK",
    "sg:address":"Limburg Alle 7",
    "sg:city":"Drag\u00f8r",
    "sg:orig_category":"Skorstensfejere",
    "sg:phone":"+45 32 94 71 92",
    "sg:postcode":"2791",
    "sg:province":"Danmark",
    "wof:name":"Krantz, Tonny",
    "wof:placetype":"venue"
},
  "geometry": {"coordinates":[5.8965101242,51.2644691467],"type":"Point"}
}