{
  "type": "Feature",
  "properties": {
    "addr:full":"Danmarksgade 24 B Frederikshavn Danmark 9900",
    "addr:housenumber":"24 b",
    "addr:postcode":"9900",
    "addr:street":"Danmarksgade",
    "iso:country":"DK",
    "sg:address":"Danmarksgade 24 B",
    "sg:city":"Frederikshavn",
    "sg:classifiers":[
        {
            "category":"Home & Garden",
            "subcategory":"Home Furnishings",
            "type":"Retail Goods"
        }
    ],
    "sg:phone":"+45 98 41 09 44",
    "sg:postcode":"9900",
    "sg:province":"Danmark",
    "sg:tags":[
        "gardiner"
    ],
    "wof:name":"KR Gardiner",
    "wof:placetype":"venue"
},
  "geometry": {"coordinates":[10.538274765,57.4437255859],"type":"Point"}
}