{
  "type": "Feature",
  "properties": {
    "addr:full":"Overdammen 9 Ribe Danmark 6760",
    "addr:housenumber":"9",
    "addr:postcode":"6760",
    "addr:street":"Overdammen",
    "iso:country":"DK",
    "sg:address":"Overdammen 9",
    "sg:city":"Ribe",
    "sg:orig_category":"Optikere",
    "sg:phone":"+45 75 42 01 66",
    "sg:postcode":"6760",
    "sg:province":"Danmark",
    "sg:website":"www.pirchert.dk",
    "wof:name":"Pirchert Optik",
    "wof:placetype":"venue"
},
  "geometry": {"coordinates":[8.762963295,55.3289337158],"type":"Point"}
}