{
  "type": "Feature",
  "properties": {
    "addr:full":"Torvet 5 Silkeborg Danmark 8600",
    "addr:housenumber":"5",
    "addr:postcode":"8600",
    "addr:street":"Torvet",
    "iso:country":"DK",
    "sg:address":"Torvet 5",
    "sg:city":"Silkeborg",
    "sg:orig_category":"Sko",
    "sg:phone":"+45 86 80 24 14",
    "sg:postcode":"8600",
    "sg:province":"Danmark",
    "wof:name":"Gr\u00f8nne Skobutik, Din",
    "wof:placetype":"venue"
},
  "geometry": {"coordinates":[9.5495252609,56.1697120667],"type":"Point"}
}