{
  "type": "Feature",
  "properties": {
    "iso:country":"DK",
    "sg:address":"Nikkelvej 4",
    "sg:city":"Randers",
    "sg:orig_category":"Lampefabrikker",
    "sg:phone":"+45 86 44 80 65",
    "sg:postcode":"8900",
    "sg:province":"Danmark",
    "sg:website":"www.danalighr.dk",
    "wof:name":"Danalight A/S",
    "wof:placetype":"venue"
},
  "geometry": {"coordinates":[10.051981926,56.4281616211],"type":"Point"}
}