{
  "type": "Feature",
  "properties": {
    "iso:country":"DK",
    "sg:address":"N\u00f8rregade 8",
    "sg:city":"Vamdrup",
    "sg:orig_category":"Brugsforeninger",
    "sg:phone":"+45 75 58 13 22",
    "sg:postcode":"6580",
    "sg:province":"Danmark",
    "wof:name":"Super Brugsen Vamdrup",
    "wof:placetype":"venue"
},
  "geometry": {"coordinates":[9.2835607529,55.4277076721],"type":"Point"}
}