{
  "type": "Feature",
  "properties": {
    "addr:full":"S\u00f8nderholmsvej 18 Karlslunde Danmark 2690",
    "addr:housenumber":"18",
    "addr:postcode":"2690",
    "addr:street":"Sonderholmsvej",
    "iso:country":"DK",
    "sg:address":"S\u00f8nderholmsvej 18",
    "sg:city":"Karlslunde",
    "sg:orig_category":"Maskinservice",
    "sg:phone":"+45 46 15 09 67",
    "sg:postcode":"2690",
    "sg:province":"Danmark",
    "wof:name":"Vogeleys Maskinservice, Henning",
    "wof:placetype":"venue"
},
  "geometry": {"coordinates":[12.243976593,55.5621910095],"type":"Point"}
}