{
  "type": "Feature",
  "properties": {
    "addr:full":"Gothersgade 24 Fredericia Danmark 7000",
    "addr:housenumber":"24",
    "addr:postcode":"7000",
    "addr:street":"Gothersgade",
    "iso:country":"DK",
    "sg:address":"Gothersgade 24",
    "sg:city":"Fredericia",
    "sg:orig_category":"Boghandlere",
    "sg:phone":"+45 75 92 01 62",
    "sg:postcode":"7000",
    "sg:province":"Danmark",
    "wof:name":"Billunds Boghandel",
    "wof:placetype":"venue"
},
  "geometry": {"coordinates":[9.7563066483,55.5644645691],"type":"Point"}
}