{
  "type": "Feature",
  "properties": {
    "addr:full":"Dyrl\u00e6geg\u00e5rds Alle 37 Frederikssund Danmark 3600",
    "addr:housenumber":"37",
    "addr:postcode":"3600",
    "addr:street":"Dyrlaegegaards Alle",
    "iso:country":"DK",
    "sg:address":"Dyrl\u00e6geg\u00e5rds Alle 37",
    "sg:city":"Frederikssund",
    "sg:orig_category":"Trykkerier",
    "sg:phone":"+45 47 38 47 47",
    "sg:postcode":"3600",
    "sg:province":"Danmark",
    "wof:name":"Pa - Kopi",
    "wof:placetype":"venue"
},
  "geometry": {"coordinates":[12.0726413727,55.8217010498],"type":"Point"}
}