{
  "type": "Feature",
  "properties": {
    "addr:full":"v/ S\u00f8ren Duelund S\u00f8rensen, Svendborgvej 307, H\u00f8jby Odense S Danmark 5260",
    "addr:housenumber":"307",
    "addr:postcode":"5260",
    "addr:street":"Svendborgvej;Hojby",
    "iso:country":"DK",
    "sg:address":"v/ S\u00f8ren Duelund S\u00f8rensen, Svendborgvej 307, H\u00f8jby",
    "sg:city":"Odense S",
    "sg:orig_category":"Hobbybetonede foreninger",
    "sg:postcode":"5260",
    "sg:province":"Danmark",
    "wof:name":"BMW Classic",
    "wof:placetype":"venue"
},
  "geometry": {"coordinates":[10.3157806396,55.3122825623],"type":"Point"}
}