{
  "type": "Feature",
  "properties": {
    "addr:full":"Langelinie 40 Odense M Danmark 5230",
    "addr:housenumber":"40",
    "addr:postcode":"5230",
    "addr:street":"Langelinie",
    "iso:country":"DK",
    "sg:address":"Langelinie 40",
    "sg:city":"Odense M",
    "sg:orig_category":"Designere",
    "sg:phone":"+45 66 14 01 12",
    "sg:postcode":"5230",
    "sg:province":"Danmark",
    "wof:name":"Fisher, Sharon",
    "wof:placetype":"venue"
},
  "geometry": {"coordinates":[10.3783302307,55.3844184875],"type":"Point"}
}