{
  "type": "Feature",
  "properties": {
    "addr:full":"Japanvej 14 Slagelse Danmark 4200",
    "addr:housenumber":"14",
    "addr:postcode":"4200",
    "addr:street":"Japanvej",
    "iso:country":"DK",
    "sg:address":"Japanvej 14",
    "sg:city":"Slagelse",
    "sg:orig_category":"El-artikler",
    "sg:phone":"+45 58 53 47 00",
    "sg:postcode":"4200",
    "sg:province":"Danmark",
    "wof:name":"Louis Poulsen El-teknik A/S",
    "wof:placetype":"venue"
},
  "geometry": {"coordinates":[11.3253860474,55.38722229],"type":"Point"}
}