{
  "type": "Feature",
  "properties": {
    "addr:full":"Storegade 77 Nordborg Danmark 6430",
    "addr:housenumber":"77",
    "addr:postcode":"6430",
    "addr:street":"Storegade",
    "iso:country":"DK",
    "sg:address":"Storegade 77",
    "sg:city":"Nordborg",
    "sg:orig_category":"Apoteker og -udsalg",
    "sg:phone":"+45 74 45 14 05",
    "sg:postcode":"6430",
    "sg:province":"Danmark",
    "wof:name":"Nordborg Apotek",
    "wof:placetype":"venue"
},
  "geometry": {"coordinates":[9.7521257401,55.0569114685],"type":"Point"}
}