{
  "type": "Feature",
  "properties": {
    "addr:full":"Lembckesvej 3  Haderslev Danmark 6100",
    "addr:housenumber":"3",
    "addr:postcode":"6100",
    "addr:street":"Lembckesvej",
    "iso:country":"DK",
    "sg:address":"Lembckesvej 3 ",
    "sg:city":"Haderslev",
    "sg:classifiers":[
        {
            "category":"Professional",
            "subcategory":"Business Services",
            "type":"Services"
        }
    ],
    "sg:phone":"+45 74 52 69 77",
    "sg:postcode":"6100",
    "sg:province":"Danmark",
    "sg:tags":[
        "advice"
    ],
    "wof:name":"CVU S\u00d8NDERJYLLAND EFTER OG VIDERE UDDANNELSE",
    "wof:placetype":"venue"
},
  "geometry": {"coordinates":[9.4852304459,55.2547225952],"type":"Point"}
}