{
  "type": "Feature",
  "properties": {
    "addr:full":"Kontor: Colosseum, Danmarksgade 80 Frederikshavn Danmark 9900",
    "addr:housenumber":"80",
    "addr:postcode":"9900",
    "addr:street":"Danmarksgade",
    "iso:country":"DK",
    "sg:address":"Kontor: Colosseum, Danmarksgade 80",
    "sg:city":"Frederikshavn",
    "sg:orig_category":"Kulturelle foreninger",
    "sg:phone":"+45 96 22 56 24",
    "sg:postcode":"9900",
    "sg:province":"Danmark",
    "wof:name":"Frederikshavn Teaterforening",
    "wof:placetype":"venue"
},
  "geometry": {"coordinates":[10.5362997055,57.4396400452],"type":"Point"}
}