{
  "type": "Feature",
  "properties": {
    "addr:full":"Jernbanegade 7 S\u00f8nderborg Danmark 6400",
    "addr:housenumber":"7",
    "addr:postcode":"6400",
    "addr:street":"Jernbanegade",
    "iso:country":"DK",
    "sg:address":"Jernbanegade 7",
    "sg:city":"S\u00f8nderborg",
    "sg:orig_category":"Bedriftssundhedstjenester",
    "sg:phone":"+45 74 43 22 32",
    "sg:postcode":"6400",
    "sg:province":"Danmark",
    "wof:name":"BST Alssund",
    "wof:placetype":"venue"
},
  "geometry": {"coordinates":[9.7932577133,54.9102058411],"type":"Point"}
}