{
  "type": "Feature",
  "properties": {
    "iso:country":"DK",
    "sg:address":"Lille Istedgade 5, 5tv",
    "sg:city":"K\u00f8benhavn",
    "sg:orig_category":"Video- og TV-produktion",
    "sg:phone":"+45 33 21 97 30",
    "sg:postcode":"1706",
    "sg:province":"Danmark",
    "wof:name":"Local Eyes",
    "wof:placetype":"venue"
},
  "geometry": {"coordinates":[12.5614004135,55.6698989868],"type":"Point"}
}