{
  "type": "Feature",
  "properties": {
    "addr:full":"Lundevej 2 A Svendborg Danmark 5700",
    "addr:housenumber":"2 a",
    "addr:postcode":"5700",
    "addr:street":"Lundevej",
    "iso:country":"DK",
    "sg:address":"Lundevej 2 A",
    "sg:city":"Svendborg",
    "sg:orig_category":"Pizzeriaer",
    "sg:phone":"+45 62 20 21 39",
    "sg:postcode":"5700",
    "sg:province":"Danmark",
    "wof:name":"Osmons Pizza & Grill",
    "wof:placetype":"venue"
},
  "geometry": {"coordinates":[10.6064062119,55.0582237244],"type":"Point"}
}