{
  "type": "Feature",
  "properties": {
    "addr:full":"v/ Egon S\u00f8rensen, Tommesensvej 20 Hammel Danmark 8450",
    "addr:housenumber":"20",
    "addr:postcode":"8450",
    "addr:street":"Tommesensvej",
    "iso:country":"DK",
    "sg:address":"v/ Egon S\u00f8rensen, Tommesensvej 20",
    "sg:city":"Hammel",
    "sg:orig_category":"Hobbybetonede foreninger",
    "sg:phone":"+45 86 96 12 82",
    "sg:postcode":"8450",
    "sg:province":"Danmark",
    "wof:name":"Hammel Borgerlig Skydeselskab",
    "wof:placetype":"venue"
},
  "geometry": {"coordinates":[9.8615541458,56.2554588318],"type":"Point"}
}