{
  "type": "Feature",
  "properties": {
    "iso:country":"DK",
    "sg:address":"Strandk\u00e6rvej 87",
    "sg:city":"Horsens",
    "sg:orig_category":"Supermarkeder",
    "sg:postcode":"8700",
    "sg:province":"Danmark",
    "wof:name":"Aldi Marked",
    "wof:placetype":"venue"
},
  "geometry": {"coordinates":[9.8437623978,55.8429641724],"type":"Point"}
}