{
  "type": "Feature",
  "properties": {
    "iso:country":"DK",
    "sg:address":"Bredgade 4 ",
    "sg:city":"Kolding",
    "sg:classifiers":[
        {
            "category":"Bars & Pubs",
            "subcategory":"Nightclub",
            "type":"Food & Drink"
        }
    ],
    "sg:phone":"+45 75 53 19 00",
    "sg:postcode":"6000",
    "sg:province":"Danmark",
    "sg:tags":[
        "cake",
        "bread"
    ],
    "wof:name":"DEN GYLDNE OVN A/S",
    "wof:placetype":"venue"
},
  "geometry": {"coordinates":[9.4721565247,55.4894714355],"type":"Point"}
}