{
  "type": "Feature",
  "properties": {
    "addr:full":"Fmd.: Viggo Hjarsen Petersen, Reberbanen 2 Svendborg Danmark 5700",
    "addr:housenumber":"2",
    "addr:postcode":"5700",
    "addr:street":"Reberbanen",
    "iso:country":"DK",
    "sg:address":"Fmd.: Viggo Hjarsen Petersen, Reberbanen 2",
    "sg:city":"Svendborg",
    "sg:orig_category":"Soldaterforeninger",
    "sg:phone":"+45 62 20 15 93",
    "sg:postcode":"5700",
    "sg:province":"Danmark",
    "wof:name":"De Danske Forsvarsbr\u00f8dre p\u00e5 Langeland",
    "wof:placetype":"venue"
},
  "geometry": {"coordinates":[10.6065101624,55.0595970154],"type":"Point"}
}