{
  "type": "Feature",
  "properties": {
    "iso:country":"DK",
    "sg:address":"Odensevej 10",
    "sg:city":"Ringe",
    "sg:orig_category":"Begravelsesforretninger",
    "sg:phone":"+45 62 62 16 38",
    "sg:postcode":"5750",
    "sg:province":"Danmark",
    "wof:name":"Ringe/Midtfyns Begravelsesforretning",
    "wof:placetype":"venue"
},
  "geometry": {"coordinates":[10.477219,55.24073],"type":"Point"}
}