{
  "type": "Feature",
  "properties": {
    "iso:country":"DK",
    "sg:address":"Bogensevej 414, N\u00e6sbyh Broby",
    "sg:city":"Odense N",
    "sg:classifiers":[
        {
            "category":"Home & Garden",
            "subcategory":"Home Furnishings",
            "type":"Retail Goods"
        }
    ],
    "sg:phone":"+45 65 97 86 07",
    "sg:postcode":"5270",
    "sg:province":"Danmark",
    "sg:tags":[
        "gardiner"
    ],
    "wof:name":"Heinmann ApS, Hos",
    "wof:placetype":"venue"
},
  "geometry": {"coordinates":[10.3306798935,55.4711418152],"type":"Point"}
}