{
  "type": "Feature",
  "properties": {
    "addr:full":"Borgmesterbakken 26 Horsens Danmark 8700",
    "addr:housenumber":"26",
    "addr:postcode":"8700",
    "addr:street":"Borgmesterbakken",
    "iso:country":"DK",
    "sg:address":"Borgmesterbakken 26",
    "sg:city":"Horsens",
    "sg:orig_category":"Tandklinikker, Kommunale",
    "sg:phone":"+45 75 61 03 99",
    "sg:postcode":"8700",
    "sg:province":"Danmark",
    "wof:name":"Reguleringsklinikken",
    "wof:placetype":"venue"
},
  "geometry": {"coordinates":[9.8541889191,55.8650436401],"type":"Point"}
}