{
  "type": "Feature",
  "properties": {
    "addr:full":"M\u00f8llevejen 33 A Marstal Danmark 5960",
    "addr:housenumber":"33 a",
    "addr:postcode":"5960",
    "addr:street":"Mollevejen",
    "iso:country":"DK",
    "sg:address":"M\u00f8llevejen 33 A",
    "sg:city":"Marstal",
    "sg:orig_category":"Dag- og distriktsblade",
    "sg:phone":"+45 62 53 11 53",
    "sg:postcode":"5960",
    "sg:province":"Danmark",
    "wof:name":"\u00c6r\u00f8 Ugeavis",
    "wof:placetype":"venue"
},
  "geometry": {"coordinates":[10.5114421844,54.8553237915],"type":"Point"}
}