{
  "type": "Feature",
  "properties": {
    "addr:full":"Gartnerivej 45 Holstebro Danmark 7500",
    "addr:housenumber":"45",
    "addr:postcode":"7500",
    "addr:street":"Gartnerivej",
    "iso:country":"DK",
    "sg:address":"Gartnerivej 45",
    "sg:city":"Holstebro",
    "sg:orig_category":"Kasseapparater",
    "sg:phone":"+45 97 42 49 00",
    "sg:postcode":"7500",
    "sg:province":"Danmark",
    "sg:website":"www.jk-kasseapparater.dk",
    "wof:name":"Kristensen, J\u00f8rgen",
    "wof:placetype":"venue"
},
  "geometry": {"coordinates":[8.6115684509,56.3817558289],"type":"Point"}
}