{
  "type": "Feature",
  "properties": {
    "addr:full":"Gl. Landevej 90 Herning Danmark 7400",
    "addr:housenumber":"90",
    "addr:postcode":"7400",
    "addr:street":"Gl. Landevej",
    "iso:country":"DK",
    "sg:address":"Gl. Landevej 90",
    "sg:city":"Herning",
    "sg:orig_category":"Automater",
    "sg:phone":"+45 97 21 69 70",
    "sg:postcode":"7400",
    "sg:province":"Danmark",
    "wof:name":"J. A. Automater",
    "wof:placetype":"venue"
},
  "geometry": {"coordinates":[8.9696083069,56.1412162781],"type":"Point"}
}