{
  "type": "Feature",
  "properties": {
    "iso:country":"DK",
    "sg:address":"Skanderborgvej 182",
    "sg:city":"Viby",
    "sg:orig_category":"Ejendomshandel",
    "sg:phone":"+45 86 11 44 99",
    "sg:postcode":"8260",
    "sg:province":"Danmark",
    "wof:name":"home VIBY - Tage Refsgaard",
    "wof:placetype":"venue"
},
  "geometry": {"coordinates":[10.1638593674,56.1298103333],"type":"Point"}
}