{
  "type": "Feature",
  "properties": {
    "addr:full":"v/ Ingeborg Marqvard, Klakring Stationsvej 18, Klakring Juelsminde Danmark 7130",
    "addr:housenumber":"18",
    "addr:postcode":"7130",
    "addr:street":"Klakring Stationsvej;Klakring",
    "iso:country":"DK",
    "sg:address":"v/ Ingeborg Marqvard, Klakring Stationsvej 18, Klakring",
    "sg:city":"Juelsminde",
    "sg:orig_category":"Hobbybetonede foreninger",
    "sg:phone":"+45 75 69 36 04",
    "sg:postcode":"7130",
    "sg:province":"Danmark",
    "wof:name":"Urtica \u00d8kologisk Indk\u00f8bsforening",
    "wof:placetype":"venue"
},
  "geometry": {"coordinates":[10.0143985748,55.7135848999],"type":"Point"}
}