{
  "type": "Feature",
  "properties": {
    "addr:full":"Hortensiavej 11 Frederiksberg Danmark 1857",
    "addr:housenumber":"11;1857",
    "addr:street":"Hortensiavej",
    "iso:country":"DK",
    "sg:address":"Hortensiavej 11",
    "sg:city":"Frederiksberg",
    "sg:orig_category":"Sammensatte institutioner",
    "sg:phone":"+45 38 21 17 10",
    "sg:postcode":"1857",
    "sg:province":"Danmark",
    "wof:name":"Rosenhaven, Frederiksberg Kommunes B\u00f8rneinstitution",
    "wof:placetype":"venue"
},
  "geometry": {"coordinates":[12.5350580215,55.6770172119],"type":"Point"}
}