{
  "type": "Feature",
  "properties": {
    "addr:full":"Riddergade 17 Fredericia Danmark 7000",
    "addr:housenumber":"17",
    "addr:postcode":"7000",
    "addr:street":"Riddergade",
    "iso:country":"DK",
    "sg:address":"Riddergade 17",
    "sg:city":"Fredericia",
    "sg:classifiers":[
        {
            "category":"Restaurant",
            "type":"Food & Drink"
        }
    ],
    "sg:phone":"+45 75 92 00 85",
    "sg:postcode":"7000",
    "sg:province":"Danmark",
    "wof:name":"Bacchus",
    "wof:placetype":"venue"
},
  "geometry": {"coordinates":[9.7558517456,55.5676078796],"type":"Point"}
}