{
  "type": "Feature",
  "properties": {
    "addr:full":"Brogade 21, Hou Hals Danmark 9370",
    "addr:housenumber":"21",
    "addr:postcode":"9370",
    "addr:street":"Brogade;Hou",
    "iso:country":"DK",
    "sg:address":"Brogade 21, Hou",
    "sg:city":"Hals",
    "sg:classifiers":[
        {
            "category":"Professional",
            "subcategory":"Advertising",
            "type":"Services"
        }
    ],
    "sg:phone":"+45 98 25 38 38",
    "sg:postcode":"9370",
    "sg:province":"Danmark",
    "sg:tags":[
        "marketing"
    ],
    "sg:website":"www.albatros-print.dk",
    "wof:name":"Albatros Print",
    "wof:placetype":"venue"
},
  "geometry": {"coordinates":[10.3669347763,57.0597991943],"type":"Point"}
}