{
  "type": "Feature",
  "properties": {
    "addr:full":"Kasserer.: Lars Lundborg Hansen, Tofteg\u00e5rdsparken 3 Sulsted Danmark 9381",
    "addr:housenumber":"3",
    "addr:postcode":"9381",
    "addr:street":"Toftegaardsparken",
    "iso:country":"DK",
    "sg:address":"Kasserer.: Lars Lundborg Hansen, Tofteg\u00e5rdsparken 3",
    "sg:city":"Sulsted",
    "sg:orig_category":"Grundejerforeninger",
    "sg:phone":"+45 98 26 10 80",
    "sg:postcode":"9381",
    "sg:province":"Danmark",
    "wof:name":"Grundejerforeningen Ger\u00e5 Vest",
    "wof:placetype":"venue"
},
  "geometry": {"coordinates":[9.965262413,57.1585540771],"type":"Point"}
}