{
  "type": "Feature",
  "properties": {
    "addr:full":"Haraldsdalvej 11 B Padborg Danmark 6330",
    "addr:housenumber":"11 b",
    "addr:postcode":"6330",
    "addr:street":"Haraldsdalvej",
    "iso:country":"DK",
    "sg:address":"Haraldsdalvej 11 B",
    "sg:city":"Padborg",
    "sg:orig_category":"Varmeforsyning",
    "sg:phone":"+45 74 67 33 25",
    "sg:postcode":"6330",
    "sg:province":"Danmark",
    "wof:name":"Padborg Fjernvarme a.m.b.a.",
    "wof:placetype":"venue"
},
  "geometry": {"coordinates":[9.3614320755,54.8192939758],"type":"Point"}
}