{
  "type": "Feature",
  "properties": {
    "addr:full":"Enghaven 16, Pollerup Stege Danmark 4780",
    "addr:housenumber":"16",
    "addr:postcode":"4780",
    "addr:street":"Enghaven;Pollerup",
    "iso:country":"DK",
    "sg:address":"Enghaven 16, Pollerup",
    "sg:city":"Stege",
    "sg:orig_category":"Kunsthandlere og -udstillinger",
    "sg:phone":"+45 55 81 34 19",
    "sg:postcode":"4780",
    "sg:province":"Danmark",
    "wof:name":"Villa Aurora",
    "wof:placetype":"venue"
},
  "geometry": {"coordinates":[12.2875270844,54.9855155945],"type":"Point"}
}