{
  "type": "Feature",
  "properties": {
    "addr:full":"Hylkedalvej 1 - 3, Seest Kolding Danmark 6000",
    "addr:housenumber":"1 3",
    "addr:postcode":"6000",
    "addr:street":"Hylkedalvej;Seest",
    "iso:country":"DK",
    "sg:address":"Hylkedalvej 1 - 3, Seest",
    "sg:city":"Kolding",
    "sg:orig_category":"Autoforhandlere",
    "sg:phone":"+45 75 50 77 00",
    "sg:postcode":"6000",
    "sg:province":"Danmark",
    "wof:name":"Auto-Centralen Syd/Citr\u00f6en",
    "wof:placetype":"venue"
},
  "geometry": {"coordinates":[9.4733953476,55.4863586426],"type":"Point"}
}