{
  "type": "Feature",
  "properties": {
    "addr:full":"Turkisvej 1 C Herlev Danmark 2730",
    "addr:housenumber":"1 c",
    "addr:postcode":"2730",
    "addr:street":"Turkisvej",
    "iso:country":"DK",
    "sg:address":"Turkisvej 1 C",
    "sg:city":"Herlev",
    "sg:orig_category":"Elektronik",
    "sg:phone":"+45 44 53 14 70",
    "sg:postcode":"2730",
    "sg:province":"Danmark",
    "wof:name":"Thita Elektronik",
    "wof:placetype":"venue"
},
  "geometry": {"coordinates":[12.4381847382,55.7291564941],"type":"Point"}
}