{
  "type": "Feature",
  "properties": {
    "iso:country":"DK",
    "sg:address":"Skovvej 6",
    "sg:city":"Hobro",
    "sg:orig_category":"Ejendomshandel",
    "sg:phone":"+45 98 51 17 07",
    "sg:postcode":"9500",
    "sg:province":"Danmark",
    "sg:website":"www.dithus.dk/hobro",
    "wof:name":"Hobro M\u00e6gleren",
    "wof:placetype":"venue"
},
  "geometry": {"coordinates":[9.6288967133,56.5892105103],"type":"Point"}
}