{
  "type": "Feature",
  "properties": {
    "addr:full":"N\u00e6ssundvej 170 Vils Danmark 7980",
    "addr:housenumber":"170",
    "addr:postcode":"7980",
    "addr:street":"Naessundvej",
    "iso:country":"DK",
    "sg:address":"N\u00e6ssundvej 170",
    "sg:city":"Vils",
    "sg:orig_category":"Autoforhandlere",
    "sg:phone":"+45 97 76 70 10",
    "sg:postcode":"7980",
    "sg:province":"Danmark",
    "wof:name":"Auto Salg & Service",
    "wof:placetype":"venue"
},
  "geometry": {"coordinates":[8.7269458771,56.7638053894],"type":"Point"}
}