{
  "type": "Feature",
  "properties": {
    "addr:full":"Fabrikvej 22 Viborg Danmark 8800",
    "addr:housenumber":"22",
    "addr:postcode":"8800",
    "addr:street":"Fabrikvej",
    "iso:country":"DK",
    "sg:address":"Fabrikvej 22",
    "sg:city":"Viborg",
    "sg:orig_category":"Fabrikker",
    "sg:phone":"+45 86 64 50 11",
    "sg:postcode":"8800",
    "sg:province":"Danmark",
    "sg:website":"www.murbinder.dk",
    "wof:name":"Midtjydsk Murbinderfabrik A/S",
    "wof:placetype":"venue"
},
  "geometry": {"coordinates":[9.4064598083,56.469871521],"type":"Point"}
}