{
  "type": "Feature",
  "properties": {
    "addr:full":"Elbjergvej 33, Kattrup Hovedg\u00e5rd Danmark 8732",
    "addr:housenumber":"33",
    "addr:postcode":"8732",
    "addr:street":"Elbjergvej",
    "iso:country":"DK",
    "sg:address":"Elbjergvej 33, Kattrup",
    "sg:city":"Hovedg\u00e5rd",
    "sg:orig_category":"Autoreparation og -service",
    "sg:phone":"+45 75 66 15 72",
    "sg:postcode":"8732",
    "sg:province":"Danmark",
    "wof:name":"Kattrup Auto",
    "wof:placetype":"venue"
},
  "geometry": {"coordinates":[9.9604625702,55.9431648254],"type":"Point"}
}