{
  "type": "Feature",
  "properties": {
    "addr:full":"Sofiendalsvej 22 Haslev Danmark 4690",
    "addr:housenumber":"22",
    "addr:postcode":"4690",
    "addr:street":"Sofiendalsvej",
    "iso:country":"DK",
    "sg:address":"Sofiendalsvej 22",
    "sg:city":"Haslev",
    "sg:orig_category":"Forsikringer",
    "sg:phone":"+45 70 21 14 35",
    "sg:postcode":"4690",
    "sg:province":"Danmark",
    "sg:website":"www.kab.dk",
    "wof:name":"K\u00f8bst\u00e6dernes Forsikring",
    "wof:placetype":"venue"
},
  "geometry": {"coordinates":[11.9672689438,55.3296508789],"type":"Point"}
}