{
  "type": "Feature",
  "properties": {
    "addr:full":"Ny Carlsberg Vej 31 K\u00f8benhavn Danmark 1760",
    "addr:housenumber":"31;1760",
    "addr:street":"Carlsberg Vej",
    "iso:country":"DK",
    "sg:address":"Ny Carlsberg Vej 31",
    "sg:city":"K\u00f8benhavn",
    "sg:orig_category":"Integrerede institutioner",
    "sg:phone":"+45 33 22 01 53",
    "sg:postcode":"1760",
    "sg:province":"Danmark",
    "wof:name":"Vestervang, Integreret skoleinstitution",
    "wof:placetype":"venue"
},
  "geometry": {"coordinates":[-76.50189208979999,42.8563194275],"type":"Point"}
}