{
  "type": "Feature",
  "properties": {
    "addr:full":"Fmd.: Mette Helth Christiansen, Sofiegade 6-8 K\u00f8benhavn Danmark 1418",
    "addr:housenumber":"6-8;1418",
    "addr:street":"Sofiegade",
    "iso:country":"DK",
    "sg:address":"Fmd.: Mette Helth Christiansen, Sofiegade 6-8",
    "sg:city":"K\u00f8benhavn",
    "sg:orig_category":"Loger",
    "sg:phone":"+45 32 96 11 44",
    "sg:postcode":"1418",
    "sg:province":"Danmark",
    "wof:name":"Junior Chamber Amager",
    "wof:placetype":"venue"
},
  "geometry": {"coordinates":[12.5909500122,55.6709289551],"type":"Point"}
}