{
  "type": "Feature",
  "properties": {
    "addr:full":"V\u00e6nges\u00f8vej 3, Borup Knebel Danmark 8420",
    "addr:housenumber":"3",
    "addr:postcode":"8420",
    "addr:street":"Vaengesovej",
    "iso:country":"DK",
    "sg:address":"V\u00e6nges\u00f8vej 3, Borup",
    "sg:city":"Knebel",
    "sg:orig_category":"Efterskoler",
    "sg:phone":"+45 86 35 61 00",
    "sg:postcode":"8420",
    "sg:province":"Danmark",
    "wof:name":"Helgen\u00e6s Naturefterskole",
    "wof:placetype":"venue"
},
  "geometry": {"coordinates":[10.3770122528,56.1816596985],"type":"Point"}
}