{
  "type": "Feature",
  "properties": {
    "addr:full":"Slotsalleen 22 B Slagelse Danmark 4200",
    "addr:housenumber":"22 b",
    "addr:postcode":"4200",
    "addr:street":"Slotsalleen",
    "iso:country":"DK",
    "sg:address":"Slotsalleen 22 B",
    "sg:city":"Slagelse",
    "sg:orig_category":"Zoneterapeuter",
    "sg:phone":"+45 58 52 00 05",
    "sg:postcode":"4200",
    "sg:province":"Danmark",
    "wof:name":"Ulrich, Annie",
    "wof:placetype":"venue"
},
  "geometry": {"coordinates":[11.360247612,55.3969650269],"type":"Point"}
}