{
  "type": "Feature",
  "properties": {
    "addr:full":"Herningvej 1, Postboks 59 Karup Danmark 7470",
    "addr:housenumber":"1;59",
    "addr:postcode":"7470",
    "addr:street":"Herningvej;Karup Danmark",
    "iso:country":"DK",
    "sg:address":"Herningvej 1, Postboks 59",
    "sg:city":"Karup",
    "sg:orig_category":"Forsvaret",
    "sg:phone":"+45 99 62 49 70",
    "sg:postcode":"7470",
    "sg:province":"Danmark",
    "sg:website":"www.hok.dk",
    "wof:name":"H\u00e6rens Operative Komando",
    "wof:placetype":"venue"
},
  "geometry": {"coordinates":[9.2525548935,56.3398017883],"type":"Point"}
}