{
  "type": "Feature",
  "properties": {
    "addr:full":"Thygesensvej 2, Krogsb\u00f8lle Otterup Danmark 5450",
    "addr:housenumber":"2",
    "addr:postcode":"5450",
    "addr:street":"Thygesensvej",
    "iso:country":"DK",
    "sg:address":"Thygesensvej 2, Krogsb\u00f8lle",
    "sg:city":"Otterup",
    "sg:orig_category":"Revisorer",
    "sg:phone":"+45 64 87 14 89",
    "sg:postcode":"5450",
    "sg:province":"Danmark",
    "wof:name":"MS-Revision",
    "wof:placetype":"venue"
},
  "geometry": {"coordinates":[10.4545049667,55.5641746521],"type":"Point"}
}