{
  "type": "Feature",
  "properties": {
    "addr:full":"Ribegade 169 A Esbjerg Danmark 6700",
    "addr:housenumber":"169 a",
    "addr:postcode":"6700",
    "addr:street":"Ribegade",
    "iso:country":"DK",
    "sg:address":"Ribegade 169 A",
    "sg:city":"Esbjerg",
    "sg:orig_category":"\u00c3\u2020ldrecentre",
    "sg:phone":"+45 75 45 31 44",
    "sg:postcode":"6700",
    "sg:province":"Danmark",
    "wof:name":"\u00d8sterbycentret",
    "wof:placetype":"venue"
},
  "geometry": {"coordinates":[8.4837274551,55.466003418],"type":"Point"}
}