{
  "type": "Feature",
  "properties": {
    "addr:full":"Hovedgaden 101 Snedsted Danmark 7752",
    "addr:housenumber":"101",
    "addr:postcode":"7752",
    "addr:street":"Hovedgaden",
    "iso:country":"DK",
    "sg:address":"Hovedgaden 101",
    "sg:city":"Snedsted",
    "sg:orig_category":"Hobbyartikler",
    "sg:phone":"+45 97 93 48 27",
    "sg:postcode":"7752",
    "sg:province":"Danmark",
    "wof:name":"Hobbybiksen",
    "wof:placetype":"venue"
},
  "geometry": {"coordinates":[8.5176515579,56.8925247192],"type":"Point"}
}