{
  "type": "Feature",
  "properties": {
    "addr:full":"S\u00f8ndergade 26 Saltum Danmark 9493",
    "addr:housenumber":"26",
    "addr:postcode":"9493",
    "addr:street":"Sondergade",
    "iso:country":"DK",
    "sg:address":"S\u00f8ndergade 26",
    "sg:city":"Saltum",
    "sg:classifiers":[
        {
            "category":"Taxi",
            "type":"Transportation"
        }
    ],
    "sg:phone":"+45 98 88 10 76",
    "sg:postcode":"9493",
    "sg:province":"Danmark",
    "wof:name":"Saltum Taxi",
    "wof:placetype":"venue"
},
  "geometry": {"coordinates":[9.6970901489,57.2699813843],"type":"Point"}
}