{
  "type": "Feature",
  "properties": {
    "addr:full":"Gr\u00f8nh\u00f8j Strandvej 35, Ingstrup L\u00f8kken Danmark 9480",
    "addr:housenumber":"35",
    "addr:postcode":"9480",
    "addr:street":"Gronhoj Strandvej",
    "iso:country":"DK",
    "sg:address":"Gr\u00f8nh\u00f8j Strandvej 35, Ingstrup",
    "sg:city":"L\u00f8kken",
    "sg:orig_category":"Selskabslokaler",
    "sg:phone":"+45 98 88 30 36",
    "sg:postcode":"9480",
    "sg:province":"Danmark",
    "wof:name":"Rolighed Camping & Selskabslokaler",
    "wof:placetype":"venue"
},
  "geometry": {"coordinates":[9.715880394,57.3703308105],"type":"Point"}
}