{
  "type": "Feature",
  "properties": {
    "addr:full":"Stavangervej 7 Silkeborg Danmark 8600",
    "addr:housenumber":"7",
    "addr:postcode":"8600",
    "addr:street":"Stavangervej",
    "iso:country":"DK",
    "sg:address":"Stavangervej 7",
    "sg:city":"Silkeborg",
    "sg:orig_category":"Trossamfund uden for folkekirken",
    "sg:phone":"+45 86 82 63 61",
    "sg:postcode":"8600",
    "sg:province":"Danmark",
    "wof:name":"Jehovas Vidners Rigssal",
    "wof:placetype":"venue"
},
  "geometry": {"coordinates":[9.5928583145,56.1794242859],"type":"Point"}
}