{
  "type": "Feature",
  "properties": {
    "addr:full":"Jeppe \u00c5kj\u00e6rs Vej 26 Silkeborg Danmark 8600",
    "addr:housenumber":"26",
    "addr:postcode":"8600",
    "addr:street":"Jeppe Aakjaers Vej",
    "iso:country":"DK",
    "sg:address":"Jeppe \u00c5kj\u00e6rs Vej 26",
    "sg:city":"Silkeborg",
    "sg:orig_category":"Psykoterapi",
    "sg:phone":"+45 86 80 38 60",
    "sg:postcode":"8600",
    "sg:province":"Danmark",
    "wof:name":"Psykoterapeutisk V\u00e6rksted",
    "wof:placetype":"venue"
},
  "geometry": {"coordinates":[9.5262641907,56.1935501099],"type":"Point"}
}