{
  "type": "Feature",
  "properties": {
    "addr:full":"Rylevej 1 Silkeborg Danmark 8600",
    "addr:housenumber":"1",
    "addr:postcode":"8600",
    "addr:street":"Rylevej",
    "iso:country":"DK",
    "sg:address":"Rylevej 1",
    "sg:city":"Silkeborg",
    "sg:orig_category":"\u00c3\u02dcvrige skoler",
    "sg:phone":"+45 86 80 47 55",
    "sg:postcode":"8600",
    "sg:province":"Danmark",
    "sg:website":"www.sosusilkeborg.dk",
    "wof:name":"Social- Og Sundhedsskolen",
    "wof:placetype":"venue"
},
  "geometry": {"coordinates":[9.561340332,56.1678390503],"type":"Point"}
}