{
  "type": "Feature",
  "properties": {
    "addr:full":"R\u00f8nneb\u00e6rvej 2 Grindsted Danmark 7200",
    "addr:housenumber":"2",
    "addr:postcode":"7200",
    "addr:street":"Ronnebaervej",
    "iso:country":"DK",
    "sg:address":"R\u00f8nneb\u00e6rvej 2",
    "sg:city":"Grindsted",
    "sg:orig_category":"Keramik",
    "sg:phone":"+45 75 32 38 40",
    "sg:postcode":"7200",
    "sg:province":"Danmark",
    "wof:name":"Kira Keramik",
    "wof:placetype":"venue"
},
  "geometry": {"coordinates":[8.9288702011,55.7560272217],"type":"Point"}
}