{
  "type": "Feature",
  "properties": {
    "addr:full":"Fynsgade 2A Toftlund Danmark 6520",
    "addr:housenumber":"2a",
    "addr:postcode":"6520",
    "addr:street":"Fynsgade",
    "iso:country":"DK",
    "sg:address":"Fynsgade 2A",
    "sg:city":"Toftlund",
    "sg:orig_category":"Konfektionsfabrikker",
    "sg:phone":"+45 74 83 17 55",
    "sg:postcode":"6520",
    "sg:province":"Danmark",
    "wof:name":"Chris of Denmark A/S",
    "wof:placetype":"venue"
},
  "geometry": {"coordinates":[9.0740976334,55.1904411316],"type":"Point"}
}