{
  "type": "Feature",
  "properties": {
    "addr:full":"Gammeltorv 8 K\u00f8benhavn Danmark 1457",
    "addr:housenumber":"8;1457",
    "addr:street":"Gammeltorv",
    "iso:country":"DK",
    "sg:address":"Gammeltorv 8",
    "sg:city":"K\u00f8benhavn",
    "sg:classifiers":[
        {
            "category":"Organizations",
            "subcategory":"Community Association",
            "type":"Services"
        }
    ],
    "sg:phone":"+45 33 13 76 76",
    "sg:postcode":"1457",
    "sg:province":"Danmark",
    "sg:tags":[
        "relation",
        "public"
    ],
    "sg:website":"www.idkommunikation.com",
    "wof:name":"ID Kommunikation A/S",
    "wof:placetype":"venue"
},
  "geometry": {"coordinates":[12.5725603104,55.6781692505],"type":"Point"}
}