{
  "type": "Feature",
  "properties": {
    "addr:full":"Vagtelvej 35 Frederiksberg Danmark 2000",
    "addr:housenumber":"35",
    "addr:postcode":"2000",
    "addr:street":"Vagtelvej",
    "iso:country":"DK",
    "sg:address":"Vagtelvej 35",
    "sg:city":"Frederiksberg",
    "sg:orig_category":"Tegnere og tegnestuer",
    "sg:phone":"+45 38 34 23 46",
    "sg:postcode":"2000",
    "sg:province":"Danmark",
    "wof:name":"Hauer, Hanne",
    "wof:placetype":"venue"
},
  "geometry": {"coordinates":[12.5223321915,55.6924247742],"type":"Point"}
}