{
  "type": "Feature",
  "properties": {
    "iso:country":"DK",
    "sg:address":"Wesselsvej 37",
    "sg:city":"Vordingborg",
    "sg:orig_category":"Sommerhusudlejning",
    "sg:phone":"+45 55 34 35 16",
    "sg:postcode":"4760",
    "sg:province":"Danmark",
    "wof:name":"Dehnshytten",
    "wof:placetype":"venue"
},
  "geometry": {"coordinates":[11.9286212921,55.0082588196],"type":"Point"}
}