{
  "type": "Feature",
  "properties": {
    "iso:country":"DK",
    "sg:address":"N\u00f8rregade 2",
    "sg:city":"Grindsted",
    "sg:orig_category":"Kiosker",
    "sg:phone":"+45 75 32 13 89",
    "sg:postcode":"7200",
    "sg:province":"Danmark",
    "wof:name":"Byens kiosk",
    "wof:placetype":"venue"
},
  "geometry": {"coordinates":[8.9272603989,55.7573699951],"type":"Point"}
}