{
  "type": "Feature",
  "properties": {
    "iso:country":"DK",
    "sg:address":"\u00d8stergade 10",
    "sg:city":"Ejstrupholm",
    "sg:orig_category":"Bagere",
    "sg:phone":"+45 75 77 27 49",
    "sg:postcode":"7361",
    "sg:province":"Danmark",
    "wof:name":"I. H. Br\u00f8d",
    "wof:placetype":"venue"
},
  "geometry": {"coordinates":[9.291062355,55.9836235046],"type":"Point"}
}