{
  "type": "Feature",
  "properties": {
    "iso:country":"DK",
    "sg:address":"v/ Birgitte S\u00f8rensen, Bringebakken 54, Jonstrup",
    "sg:city":"V\u00e6rl\u00f8se",
    "sg:orig_category":"Kulturelle foreninger",
    "sg:phone":"+45 44 66 00 35",
    "sg:postcode":"3500",
    "sg:province":"Danmark",
    "wof:name":"Tema's B\u00f8rneteater i Baltoppten/Baghuset",
    "wof:placetype":"venue"
},
  "geometry": {"coordinates":[12.4117698669,55.754650116],"type":"Point"}
}