{
  "type": "Feature",
  "properties": {
    "addr:full":"Sydvestvej 110 Glostrup Danmark 2600",
    "addr:housenumber":"110",
    "addr:postcode":"2600",
    "addr:street":"Sydvestvej",
    "iso:country":"DK",
    "sg:address":"Sydvestvej 110",
    "sg:city":"Glostrup",
    "sg:orig_category":"Dag- og distriktsblade",
    "sg:phone":"+45 43 29 21 00",
    "sg:postcode":"2600",
    "sg:province":"Danmark",
    "sg:website":"www.dansk-avistryk.dk",
    "wof:name":"Dansk AvisTryk A/S",
    "wof:placetype":"venue"
},
  "geometry": {"coordinates":[12.3759746552,55.6616134644],"type":"Point"}
}