{
  "type": "Feature",
  "properties": {
    "addr:full":"Kanalgaden 4 Albertslund Danmark 2620",
    "addr:housenumber":"4",
    "addr:postcode":"2620",
    "addr:street":"Kanalgaden",
    "iso:country":"DK",
    "sg:address":"Kanalgaden 4",
    "sg:city":"Albertslund",
    "sg:orig_category":"Tandteknikere, Kliniske",
    "sg:phone":"+45 43 64 61 01",
    "sg:postcode":"2620",
    "sg:province":"Danmark",
    "wof:name":"Utzon, Connie Hejner",
    "wof:placetype":"venue"
},
  "geometry": {"coordinates":[12.3544502258,55.6553878784],"type":"Point"}
}