{
  "type": "Feature",
  "properties": {
    "addr:full":"\u00d8stervej 17 Fakse Danmark 4640",
    "addr:housenumber":"17",
    "addr:postcode":"4640",
    "addr:street":"Ostervej",
    "iso:country":"DK",
    "sg:address":"\u00d8stervej 17",
    "sg:city":"Fakse",
    "sg:orig_category":"Boligselskaber",
    "sg:phone":"+45 56 71 32 30",
    "sg:postcode":"4640",
    "sg:province":"Danmark",
    "wof:name":"Faxe og Hylleholt Boligforening",
    "wof:placetype":"venue"
},
  "geometry": {"coordinates":[12.1203422546,55.2574195862],"type":"Point"}
}