{
  "type": "Feature",
  "properties": {
    "addr:full":"R\u00f8rsangervej 4, Hadbjerg Hadsten Danmark 8370",
    "addr:housenumber":"4",
    "addr:postcode":"8370",
    "addr:street":"Rorsangervej",
    "iso:country":"DK",
    "sg:address":"R\u00f8rsangervej 4, Hadbjerg",
    "sg:city":"Hadsten",
    "sg:orig_category":"Filmproduktion",
    "sg:phone":"+45 86 91 44 77",
    "sg:postcode":"8370",
    "sg:province":"Danmark",
    "wof:name":"Dansk Erhvervs TV",
    "wof:placetype":"venue"
},
  "geometry": {"coordinates":[10.047659874,56.3287239075],"type":"Point"}
}