{
  "type": "Feature",
  "properties": {
    "iso:country":"DK",
    "sg:address":"Amagerbrogade 111",
    "sg:city":"K\u00f8benhavn S",
    "sg:classifiers":[
        {
            "category":"Restaurant",
            "type":"Food & Drink"
        }
    ],
    "sg:phone":"+45 32 55 55 70",
    "sg:postcode":"2300",
    "sg:province":"Danmark",
    "wof:name":"Pizzeria Italiana Paninoteca",
    "wof:placetype":"venue"
},
  "geometry": {"coordinates":[-78.1299133301,36.7267417908],"type":"Point"}
}