{
  "type": "Feature",
  "properties": {
    "iso:country":"DK",
    "sg:address":"Fmd.: Ejnar Christensen, Katrinelundsvej 6",
    "sg:city":"Hovedg\u00e5rd",
    "sg:orig_category":"\u00c3\u2020ldreorganisationer og klubber",
    "sg:phone":"+45 75 66 17 90",
    "sg:postcode":"8732",
    "sg:province":"Danmark",
    "wof:name":"Pensionistforeningen i Hovedg\u00e5rd",
    "wof:placetype":"venue"
},
  "geometry": {"coordinates":[-120.56749725340001,41.2807998657],"type":"Point"}
}