{
  "type": "Feature",
  "properties": {
    "iso:country":"DK",
    "sg:address":"Ravnevej 2",
    "sg:city":"Esbjerg \u00d8",
    "sg:orig_category":"Genbrugsbutikker",
    "sg:phone":"+45 75 14 24 22",
    "sg:postcode":"6705",
    "sg:province":"Danmark",
    "wof:name":"Frelsens H\u00e6rs Genbrugscenter",
    "wof:placetype":"venue"
},
  "geometry": {"coordinates":[8.4792728424,55.4873542786],"type":"Point"}
}