{
  "type": "Feature",
  "properties": {
    "addr:full":"Vestergade 26 K\u00f8ge Danmark 4600",
    "addr:housenumber":"26",
    "addr:postcode":"4600",
    "addr:street":"Vestergade",
    "iso:country":"DK",
    "sg:address":"Vestergade 26",
    "sg:city":"K\u00f8ge",
    "sg:orig_category":"Erhvervsskoler",
    "sg:phone":"+45 56 64 08 50",
    "sg:postcode":"4600",
    "sg:province":"Danmark",
    "sg:website":"www.muhus.dk",
    "wof:name":"Mulighedernes Hus",
    "wof:placetype":"venue"
},
  "geometry": {"coordinates":[9.5455904007,56.1682090759],"type":"Point"}
}