{
  "type": "Feature",
  "properties": {
    "iso:country":"DK",
    "sg:address":"Gentoftegade 27 C",
    "sg:city":"Gentofte",
    "sg:orig_category":"Stoffer",
    "sg:phone":"+45 39 68 30 11",
    "sg:postcode":"2820",
    "sg:province":"Danmark",
    "wof:name":"Gentofte Modestoffer Aps",
    "wof:placetype":"venue"
},
  "geometry": {"coordinates":[12.5412111282,55.7485923767],"type":"Point"}
}