{
  "type": "Feature",
  "properties": {
    "iso:country":"DK",
    "sg:address":"M. P. Bruuns Gade 36",
    "sg:city":"\u00c5rhus C",
    "sg:classifiers":[
        {
            "category":"Banks & Credit Unions",
            "subcategory":"Bank",
            "type":"Services"
        }
    ],
    "sg:phone":"+45 87 32 90 50",
    "sg:postcode":"8000",
    "sg:province":"Danmark",
    "sg:tags":[
        "banker"
    ],
    "sg:website":"www.danskebank.dk",
    "wof:name":"Danske Bank",
    "wof:placetype":"venue"
},
  "geometry": {"coordinates":[99.925011,34.243011],"type":"Point"}
}