{
  "type": "Feature",
  "properties": {
    "addr:full":"Jens Kofods Gade 1, 3. tv. K\u00f8benhavn Danmark 1268",
    "addr:housenumber":"1 3 tv.;1268",
    "addr:street":"Jens Kofods Gade",
    "iso:country":"DK",
    "sg:address":"Jens Kofods Gade 1, 3. tv.",
    "sg:city":"K\u00f8benhavn",
    "sg:orig_category":"Statslige direktorater og styrelser",
    "sg:phone":"+45 33 30 73 50",
    "sg:postcode":"1268",
    "sg:province":"Danmark",
    "wof:name":"Statsadvokaten for Fyn, Syd\u00f8stsj\u00e6lland, Lolland, Falster og Bornholm",
    "wof:placetype":"venue"
},
  "geometry": {"coordinates":[12.593000412,55.6884994507],"type":"Point"}
}