{
  "type": "Feature",
  "properties": {
    "addr:full":"H. P. Folkmanns Vej 6 Jyderup Danmark 4450",
    "addr:housenumber":"6",
    "addr:postcode":"4450",
    "addr:street":"H. P. Folkmanns Vej",
    "iso:country":"DK",
    "sg:address":"H. P. Folkmanns Vej 6",
    "sg:city":"Jyderup",
    "sg:orig_category":"Bodegaer",
    "sg:phone":"+45 59 27 71 61",
    "sg:postcode":"4450",
    "sg:province":"Danmark",
    "wof:name":"Centerpubben",
    "wof:placetype":"venue"
},
  "geometry": {"coordinates":[11.3971138,55.6600341797],"type":"Point"}
}