{
  "type": "Feature",
  "properties": {
    "addr:full":"Kongsvang Alle 35 \u00c5rhus C Danmark 8000",
    "addr:housenumber":"35",
    "addr:postcode":"8000",
    "addr:street":"Kongsvang Alle",
    "iso:country":"DK",
    "sg:address":"Kongsvang Alle 35",
    "sg:city":"\u00c5rhus C",
    "sg:orig_category":"\u00c3\u02dcvrige skoler",
    "sg:phone":"+45 86 11 81 55",
    "sg:postcode":"8000",
    "sg:province":"Danmark",
    "wof:name":"Danmarks Erhvervsp\u00e6dagogiske L\u00e6reruddannelse",
    "wof:placetype":"venue"
},
  "geometry": {"coordinates":[4.717400074,49.7588005066],"type":"Point"}
}