{
  "type": "Feature",
  "properties": {
    "addr:full":"Poppelstr\u00e6det 6, Ferslev Skibby Danmark 4050",
    "addr:housenumber":"6",
    "addr:postcode":"4050",
    "addr:street":"Poppelstraedet;Ferslev",
    "iso:country":"DK",
    "sg:address":"Poppelstr\u00e6det 6, Ferslev",
    "sg:city":"Skibby",
    "sg:orig_category":"Revisorer",
    "sg:phone":"+45 47 52 98 45",
    "sg:postcode":"4050",
    "sg:province":"Danmark",
    "sg:website":"www.nordskov.dkt",
    "wof:name":"Nordskov Revision",
    "wof:placetype":"venue"
},
  "geometry": {"coordinates":[11.9594116211,55.7502975464],"type":"Point"}
}