{
  "type": "Feature",
  "properties": {
    "iso:country":"DK",
    "sg:address":"Smedeland 7 ",
    "sg:city":"Glostrup",
    "sg:classifiers":[
        {
            "category":"Wholesale",
            "subcategory":"Drugs",
            "type":"Manufacturing & Wholesale Goods"
        }
    ],
    "sg:phone":"+45 43 45 15 38",
    "sg:postcode":"2600",
    "sg:province":"Danmark",
    "sg:tags":[
        "chemical",
        "pharmaceutical"
    ],
    "wof:name":"DYNO NOBEL DANMARK A/S",
    "wof:placetype":"venue"
},
  "geometry": {"coordinates":[12.39016819,55.6838989258],"type":"Point"}
}