{
  "type": "Feature",
  "properties": {
    "addr:full":"Tarphagevej 19 Esbjerg V Danmark 6710",
    "addr:housenumber":"19",
    "addr:postcode":"6710",
    "addr:street":"Tarphagevej",
    "iso:country":"DK",
    "sg:address":"Tarphagevej 19",
    "sg:city":"Esbjerg V",
    "sg:orig_category":"Pizzeriaer",
    "sg:phone":"+45 75 46 82 88",
    "sg:postcode":"6710",
    "sg:province":"Danmark",
    "wof:name":"Istanbul",
    "wof:placetype":"venue"
},
  "geometry": {"coordinates":[8.4100351334,55.4942474365],"type":"Point"}
}