{
  "type": "Feature",
  "properties": {
    "addr:full":"Nr. Lindvej 30, Lind Herning Danmark 7400",
    "addr:housenumber":"30",
    "addr:postcode":"7400",
    "addr:street":"Nr. Lindvej",
    "iso:country":"DK",
    "sg:address":"Nr. Lindvej 30, Lind",
    "sg:city":"Herning",
    "sg:orig_category":"Landbrugsartikler",
    "sg:phone":"+45 96 26 18 00",
    "sg:postcode":"7400",
    "sg:province":"Danmark",
    "wof:name":"Skiold datamix a/s",
    "wof:placetype":"venue"
},
  "geometry": {"coordinates":[8.9768896103,56.1374168396],"type":"Point"}
}