{
  "type": "Feature",
  "properties": {
    "addr:full":"Borgergade 12, Magleby Klippinge Danmark 4672",
    "addr:housenumber":"12",
    "addr:postcode":"4672",
    "addr:street":"Borgergade",
    "iso:country":"DK",
    "sg:address":"Borgergade 12, Magleby",
    "sg:city":"Klippinge",
    "sg:orig_category":"Murermestre",
    "sg:phone":"+45 56 57 84 18",
    "sg:postcode":"4672",
    "sg:province":"Danmark",
    "sg:website":"www.jjsas.dk",
    "wof:name":"Jacobsen & S\u00f8nner A/S, Jens",
    "wof:placetype":"venue"
},
  "geometry": {"coordinates":[12.3291807175,55.3516769409],"type":"Point"}
}