{
  "type": "Feature",
  "properties": {
    "addr:full":"Assendl\u00f8sevejen 80 Viby Sj\u00e6lland Danmark 4130",
    "addr:housenumber":"80",
    "addr:postcode":"4130",
    "addr:street":"Assendlosevejen",
    "iso:country":"DK",
    "sg:address":"Assendl\u00f8sevejen 80",
    "sg:city":"Viby Sj\u00e6lland",
    "sg:orig_category":"Autoreparation og -service",
    "sg:phone":"+45 46 19 56 02",
    "sg:postcode":"4130",
    "sg:province":"Danmark",
    "wof:name":"D\u00e5strup Auto",
    "wof:placetype":"venue"
},
  "geometry": {"coordinates":[12.0152931213,55.5544242859],"type":"Point"}
}