{
  "type": "Feature",
  "properties": {
    "addr:full":"Vejringevej 26 Herlev Danmark 2730",
    "addr:housenumber":"26",
    "addr:postcode":"2730",
    "addr:street":"Vejringevej",
    "iso:country":"DK",
    "sg:address":"Vejringevej 26",
    "sg:city":"Herlev",
    "sg:orig_category":"Musikere",
    "sg:phone":"+45 44 91 23 71",
    "sg:postcode":"2730",
    "sg:province":"Danmark",
    "wof:name":"Hansen, John",
    "wof:placetype":"venue"
},
  "geometry": {"coordinates":[12.4242620468,55.7459182739],"type":"Point"}
}