{
  "type": "Feature",
  "properties": {
    "iso:country":"DK",
    "sg:address":"Troelsevej 96, Troelse",
    "sg:city":"Blommenslyst",
    "sg:orig_category":"Stutterier",
    "sg:phone":"+45 65 96 70 69",
    "sg:postcode":"5491",
    "sg:province":"Danmark",
    "wof:name":"Ll Korsebjerg",
    "wof:placetype":"venue"
},
  "geometry": {"coordinates":[10.2299203873,55.3889007568],"type":"Point"}
}