{
  "type": "Feature",
  "properties": {
    "addr:full":"Jacob Gades Alle 7 Vejen Danmark 6600",
    "addr:housenumber":"7",
    "addr:postcode":"6600",
    "addr:street":"Jacob Gades Alle",
    "iso:country":"DK",
    "sg:address":"Jacob Gades Alle 7",
    "sg:city":"Vejen",
    "sg:orig_category":"Kiropraktorer",
    "sg:phone":"+45 75 36 40 44",
    "sg:postcode":"6600",
    "sg:province":"Danmark",
    "wof:name":"Kiropraktisk Klinik",
    "wof:placetype":"venue"
},
  "geometry": {"coordinates":[9.1256637573,55.4731254578],"type":"Point"}
}