{
  "type": "Feature",
  "properties": {
    "addr:full":"Mejlgade 41 \u00c5rhus C Danmark 8000",
    "addr:housenumber":"41",
    "addr:postcode":"8000",
    "addr:street":"Mejlgade",
    "iso:country":"DK",
    "sg:address":"Mejlgade 41",
    "sg:city":"\u00c5rhus C",
    "sg:orig_category":"Cykler",
    "sg:phone":"+45 86 19 29 27",
    "sg:postcode":"8000",
    "sg:province":"Danmark",
    "wof:name":"MM Cykelv\u00e6rksted",
    "wof:placetype":"venue"
},
  "geometry": {"coordinates":[4.717400074,49.7588005066],"type":"Point"}
}