{
  "type": "Feature",
  "properties": {
    "addr:full":"Pastor: Annette V. Hedensted, Lerg\u00e5rd 6 Aabenraa Danmark 6200",
    "addr:housenumber":"6",
    "addr:postcode":"6200",
    "addr:street":"Pastor Annette V. Hedensted Lergaard",
    "iso:country":"DK",
    "sg:address":"Pastor: Annette V. Hedensted, Lerg\u00e5rd 6",
    "sg:city":"Aabenraa",
    "sg:orig_category":"Kirkesogne",
    "sg:phone":"+45 74 62 97 17",
    "sg:postcode":"6200",
    "sg:province":"Danmark",
    "wof:name":"Aabenraa Sogn",
    "wof:placetype":"venue"
},
  "geometry": {"coordinates":[9.4213867188,55.0449562073],"type":"Point"}
}