{
  "type": "Feature",
  "properties": {
    "addr:full":"Psykologhuset Svanen, \u00d8sterbrogade 115 K\u00f8benhavn \u00d8 Danmark 2100",
    "addr:housenumber":"115",
    "addr:postcode":"2100",
    "addr:street":"Osterbrogade;O",
    "iso:country":"DK",
    "sg:address":"Psykologhuset Svanen, \u00d8sterbrogade 115",
    "sg:city":"K\u00f8benhavn \u00d8",
    "sg:orig_category":"Psykologer, praktiserende",
    "sg:phone":"+45 39 27 27 06",
    "sg:postcode":"2100",
    "sg:province":"Danmark",
    "wof:name":"Melgaard, Grethe",
    "wof:placetype":"venue"
},
  "geometry": {"coordinates":[22.7311306,63.7053794861],"type":"Point"}
}