{
  "type": "Feature",
  "properties": {
    "addr:full":"Naverland 34 Glostrup Danmark 2600",
    "addr:housenumber":"34",
    "addr:postcode":"2600",
    "addr:street":"Naverland",
    "iso:country":"DK",
    "sg:address":"Naverland 34",
    "sg:city":"Glostrup",
    "sg:orig_category":"Faglige organisationer og -foreninger",
    "sg:phone":"+45 43 43 46 46",
    "sg:postcode":"2600",
    "sg:province":"Danmark",
    "wof:name":"FEHA, Fabrik. og import\u00f8rer, Foreningen af",
    "wof:placetype":"venue"
},
  "geometry": {"coordinates":[12.3741168976,55.6791191101],"type":"Point"}
}