{
  "type": "Feature",
  "properties": {
    "addr:full":"H\u00f8jvangvej 1, Estvadg Mark Skive Danmark 7800",
    "addr:housenumber":"1",
    "addr:postcode":"7800",
    "addr:street":"Hojvangvej;Mark",
    "iso:country":"DK",
    "sg:address":"H\u00f8jvangvej 1, Estvadg Mark",
    "sg:city":"Skive",
    "sg:orig_category":"Flytteforretninger",
    "sg:phone":"+45 97 52 19 43",
    "sg:postcode":"7800",
    "sg:province":"Danmark",
    "wof:name":"Skive Flytte- og budcentral I/S",
    "wof:placetype":"venue"
},
  "geometry": {"coordinates":[9.0320358276,56.5666427612],"type":"Point"}
}