{
  "type": "Feature",
  "properties": {
    "addr:full":"Konst. insp. J\u00f8rn Larsen, Kirkealle 1 R\u00f8dby Danmark 4970",
    "addr:housenumber":"1",
    "addr:postcode":"4970",
    "addr:street":"Kirkealle",
    "iso:country":"DK",
    "sg:address":"Konst. insp. J\u00f8rn Larsen, Kirkealle 1",
    "sg:city":"R\u00f8dby",
    "sg:orig_category":"Kommunale ungdomsskoler",
    "sg:phone":"+45 54 60 20 80",
    "sg:postcode":"4970",
    "sg:province":"Danmark",
    "wof:name":"Ungdomsskolen",
    "wof:placetype":"venue"
},
  "geometry": {"coordinates":[-36.775188446,-5.9064798355],"type":"Point"}
}