{
  "type": "Feature",
  "properties": {
    "iso:country":"DK",
    "sg:address":"Kongebakken 19-21",
    "sg:city":"Roskilde",
    "sg:orig_category":"Tandklinikker, Kommunale",
    "sg:phone":"+45 46 35 58 65",
    "sg:postcode":"4000",
    "sg:province":"Danmark",
    "wof:name":"Tandplejen ved Klostermarksskolen",
    "wof:placetype":"venue"
},
  "geometry": {"coordinates":[12.0933179855,55.6498908997],"type":"Point"}
}