{
  "type": "Feature",
  "properties": {
    "addr:full":"Novovej 2 A, \u00d8. Hurup Hadsund Danmark 9560",
    "addr:housenumber":"2 a o.",
    "addr:postcode":"9560",
    "addr:street":"Novovej",
    "iso:country":"DK",
    "sg:address":"Novovej 2 A, \u00d8. Hurup",
    "sg:city":"Hadsund",
    "sg:orig_category":"Ejendomshandel",
    "sg:phone":"+45 98 58 86 55",
    "sg:postcode":"9560",
    "sg:province":"Danmark",
    "wof:name":"Steve, EDC Ejendomsm\u00e6glerfirmaet J\u00f8rgen",
    "wof:placetype":"venue"
},
  "geometry": {"coordinates":[10.115904808,56.7150764465],"type":"Point"}
}