{
  "type": "Feature",
  "properties": {
    "addr:full":"H\u00e5ndv\u00e6rkerbyen 21 Greve Danmark 2670",
    "addr:housenumber":"21",
    "addr:postcode":"2670",
    "addr:street":"Haandvaerkerbyen",
    "iso:country":"DK",
    "sg:address":"H\u00e5ndv\u00e6rkerbyen 21",
    "sg:city":"Greve",
    "sg:orig_category":"Posthuse",
    "sg:phone":"+45 43 90 25 11",
    "sg:postcode":"2670",
    "sg:province":"Danmark",
    "wof:name":"Greve Postkontor",
    "wof:placetype":"venue"
},
  "geometry": {"coordinates":[12.2941808701,55.5844078064],"type":"Point"}
}