{
  "type": "Feature",
  "properties": {
    "addr:full":"Egeg\u00e5rdsvej 69 R\u00f8dovre Danmark 2610",
    "addr:housenumber":"69",
    "addr:postcode":"2610",
    "addr:street":"Egegaardsvej",
    "iso:country":"DK",
    "sg:address":"Egeg\u00e5rdsvej 69",
    "sg:city":"R\u00f8dovre",
    "sg:orig_category":"Integrerede institutioner",
    "sg:phone":"+45 36 41 00 31",
    "sg:postcode":"2610",
    "sg:province":"Danmark",
    "wof:name":"B\u00f8rneinstitutionen Solen",
    "wof:placetype":"venue"
},
  "geometry": {"coordinates":[10.6992139816,61.1027755737],"type":"Point"}
}