{
  "type": "Feature",
  "properties": {
    "iso:country":"DK",
    "sg:address":"B\u00e5dehavnen 2",
    "sg:city":"K\u00f8ge",
    "sg:orig_category":"Havne",
    "sg:phone":"+45 56 66 16 89",
    "sg:postcode":"4600",
    "sg:province":"Danmark",
    "wof:name":"Lystb\u00e5dehavnen",
    "wof:placetype":"venue"
},
  "geometry": {"coordinates":[12.1943130493,55.4703674316],"type":"Point"}
}