{
  "type": "Feature",
  "properties": {
    "addr:full":"Bredgade 5 Lem Danmark 6940",
    "addr:housenumber":"5",
    "addr:postcode":"6940",
    "addr:street":"Bredgade",
    "iso:country":"DK",
    "sg:address":"Bredgade 5",
    "sg:city":"Lem",
    "sg:orig_category":"Korn og foderstoffer",
    "sg:phone":"+45 97 34 10 06",
    "sg:postcode":"6940",
    "sg:province":"Danmark",
    "wof:name":"DLG Midtvest",
    "wof:placetype":"venue"
},
  "geometry": {"coordinates":[8.3729610443,56.0261764526],"type":"Point"}
}