{
  "type": "Feature",
  "properties": {
    "addr:full":"Ordrupvej 55 A Charlottenlund Danmark 2920",
    "addr:housenumber":"55 a",
    "addr:postcode":"2920",
    "addr:street":"Ordrupvej",
    "iso:country":"DK",
    "sg:address":"Ordrupvej 55 A",
    "sg:city":"Charlottenlund",
    "sg:orig_category":"Ejendomshandel",
    "sg:phone":"+45 70 20 10 19",
    "sg:postcode":"2920",
    "sg:province":"Danmark",
    "sg:website":"www.nybolig.dk",
    "wof:name":"Nybolig",
    "wof:placetype":"venue"
},
  "geometry": {"coordinates":[12.5801391602,55.7640380859],"type":"Point"}
}