{
  "type": "Feature",
  "properties": {
    "addr:full":"\u00c5geslundvej 24 Grindsted Danmark 7200",
    "addr:housenumber":"24",
    "addr:postcode":"7200",
    "addr:street":"Aageslundvej",
    "iso:country":"DK",
    "sg:address":"\u00c5geslundvej 24",
    "sg:city":"Grindsted",
    "sg:orig_category":"Fritidsklubber",
    "sg:phone":"+45 75 32 23 94",
    "sg:postcode":"7200",
    "sg:province":"Danmark",
    "wof:name":"Grindsted Teaterforening",
    "wof:placetype":"venue"
},
  "geometry": {"coordinates":[8.9126853943,55.772769928],"type":"Point"}
}