{
  "type": "Feature",
  "properties": {
    "addr:full":"N\u00f8rreg\u00e5rdsvej 7, Dongsh\u00f8jrup Stenstrup Danmark 5771",
    "addr:housenumber":"7",
    "addr:postcode":"5771",
    "addr:street":"Norregaardsvej",
    "iso:country":"DK",
    "sg:address":"N\u00f8rreg\u00e5rdsvej 7, Dongsh\u00f8jrup",
    "sg:city":"Stenstrup",
    "sg:orig_category":"Keramik",
    "sg:phone":"+45 62 26 10 89",
    "sg:postcode":"5771",
    "sg:province":"Danmark",
    "wof:name":"Green, Pia",
    "wof:placetype":"venue"
},
  "geometry": {"coordinates":[10.5054998398,55.1317520142],"type":"Point"}
}