{
  "type": "Feature",
  "properties": {
    "addr:full":"Fmd.: Bent Ravn, Ravnebjerg 8 Faaborg Danmark 5600",
    "addr:housenumber":"8",
    "addr:postcode":"5600",
    "addr:street":"Ravnebjerg",
    "iso:country":"DK",
    "sg:address":"Fmd.: Bent Ravn, Ravnebjerg 8",
    "sg:city":"Faaborg",
    "sg:orig_category":"Hobbybetonede foreninger",
    "sg:phone":"+45 62 61 06 26",
    "sg:postcode":"5600",
    "sg:province":"Danmark",
    "wof:name":"Faaborg og Omegns Biavlerforening",
    "wof:placetype":"venue"
},
  "geometry": {"coordinates":[10.2400531769,55.0950622559],"type":"Point"}
}