{
  "type": "Feature",
  "properties": {
    "addr:full":"Vibevej 8 Silkeborg Danmark 8600",
    "addr:housenumber":"8",
    "addr:postcode":"8600",
    "addr:street":"Vibevej",
    "iso:country":"DK",
    "sg:address":"Vibevej 8",
    "sg:city":"Silkeborg",
    "sg:orig_category":"Jordemodercentre",
    "sg:phone":"+45 86 82 59 15",
    "sg:postcode":"8600",
    "sg:province":"Danmark",
    "wof:name":"Silkeborg Jordemodercenter",
    "wof:placetype":"venue"
},
  "geometry": {"coordinates":[9.5602645874,56.1690177917],"type":"Point"}
}