{
  "type": "Feature",
  "properties": {
    "addr:full":"Apotekerbakken 23 Hornsyld Danmark 8783",
    "addr:housenumber":"23",
    "addr:postcode":"8783",
    "addr:street":"Apotekerbakken",
    "iso:country":"DK",
    "sg:address":"Apotekerbakken 23",
    "sg:city":"Hornsyld",
    "sg:orig_category":"Apoteker og -udsalg",
    "sg:phone":"+45 75 68 73 44",
    "sg:postcode":"8783",
    "sg:province":"Danmark",
    "wof:name":"Hornsyld Apotek",
    "wof:placetype":"venue"
},
  "geometry": {"coordinates":[9.8521528244,55.7539558411],"type":"Point"}
}