{
  "type": "Feature",
  "properties": {
    "addr:full":"Industrivej 6 Brovst Danmark 9460",
    "addr:housenumber":"6",
    "addr:postcode":"9460",
    "addr:street":"Industrivej",
    "iso:country":"DK",
    "sg:address":"Industrivej 6",
    "sg:city":"Brovst",
    "sg:orig_category":"Undervognsbehandling",
    "sg:phone":"+45 98 23 30 22",
    "sg:postcode":"9460",
    "sg:province":"Danmark",
    "wof:name":"Ford i Brovst",
    "wof:placetype":"venue"
},
  "geometry": {"coordinates":[9.5392160416,57.0996704102],"type":"Point"}
}