{
  "type": "Feature",
  "properties": {
    "addr:full":"Annebergvej 6 - 8 Aalborg Danmark 9000",
    "addr:housenumber":"6 8",
    "addr:postcode":"9000",
    "addr:street":"Annebergvej",
    "iso:country":"DK",
    "sg:address":"Annebergvej 6 - 8",
    "sg:city":"Aalborg",
    "sg:orig_category":"Plejehjemsboliger",
    "sg:phone":"+45 98 13 54 77",
    "sg:postcode":"9000",
    "sg:province":"Danmark",
    "wof:name":"Annebergcentret",
    "wof:placetype":"venue"
},
  "geometry": {"coordinates":[9.9048299789,57.0499153137],"type":"Point"}
}