{
  "type": "Feature",
  "properties": {
    "addr:full":"Fmd.: Niels J\u00f8rn Rahbek, Dronningborg Industries A/S, Udbyh\u00f8jvej 113 Randers Danmark 8900",
    "addr:housenumber":"113",
    "addr:postcode":"8900",
    "addr:street":"Udbyhojvej",
    "iso:country":"DK",
    "sg:address":"Fmd.: Niels J\u00f8rn Rahbek, Dronningborg Industries A/S, Udbyh\u00f8jvej 113",
    "sg:city":"Randers",
    "sg:orig_category":"Faglige organisationer og foreninger",
    "sg:phone":"+45 89 10 89 10",
    "sg:postcode":"8900",
    "sg:province":"Danmark",
    "wof:name":"Dansk Arbejdsgiverforening i Randers",
    "wof:placetype":"venue"
},
  "geometry": {"coordinates":[10.0357952118,56.4593734741],"type":"Point"}
}