{
  "type": "Feature",
  "properties": {
    "addr:full":"Centrumgaden 3, 2., Postboks 12 Ballerup Danmark 2750",
    "addr:housenumber":"3 2;12",
    "addr:postcode":"2750",
    "addr:street":"Centrumgaden;Postboks",
    "iso:country":"DK",
    "sg:address":"Centrumgaden 3, 2., Postboks 12",
    "sg:city":"Ballerup",
    "sg:orig_category":"Revisorer",
    "sg:phone":"+45 44 65 07 15",
    "sg:postcode":"2750",
    "sg:province":"Danmark",
    "sg:website":"www.multirevision.dk",
    "wof:name":"Nielsen Revisionsanpartsselskab, Knud Gravers",
    "wof:placetype":"venue"
},
  "geometry": {"coordinates":[12.361000061,55.7301216125],"type":"Point"}
}