{
  "type": "Feature",
  "properties": {
    "addr:full":"Pr\u00e6sident: Edvard Nielsen, M\u00f8lleparken 49 Lunderskov Danmark 6640",
    "addr:housenumber":"49",
    "addr:postcode":"6640",
    "addr:street":"Edvard Nielsen Molleparken",
    "iso:country":"DK",
    "sg:address":"Pr\u00e6sident: Edvard Nielsen, M\u00f8lleparken 49",
    "sg:city":"Lunderskov",
    "sg:orig_category":"Loger",
    "sg:phone":"+45 75 58 57 34",
    "sg:postcode":"6640",
    "sg:province":"Danmark",
    "wof:name":"Lunderskov Y's Men's Club",
    "wof:placetype":"venue"
},
  "geometry": {"coordinates":[9.2983627319,55.4793586731],"type":"Point"}
}