{
  "type": "Feature",
  "properties": {
    "iso:country":"DK",
    "sg:address":"Fmd.: Hannah Buhl, Pugg\u00e5rdsvej 72, Jernvedlund",
    "sg:city":"Gredstedbro",
    "sg:orig_category":"Spejderkorps",
    "sg:phone":"+45 75 43 51 20",
    "sg:postcode":"6771",
    "sg:province":"Danmark",
    "wof:name":"FDF Gredstedbro",
    "wof:placetype":"venue"
},
  "geometry": {"coordinates":[8.7442560196,55.3970336914],"type":"Point"}
}