{
  "type": "Feature",
  "properties": {
    "addr:full":"Tiufk\u00e6rvej 3, Smidstrup Fredericia Danmark 7000",
    "addr:housenumber":"3",
    "addr:postcode":"7000",
    "addr:street":"Tiufkaervej;Smidstrup",
    "iso:country":"DK",
    "sg:address":"Tiufk\u00e6rvej 3, Smidstrup",
    "sg:city":"Fredericia",
    "sg:orig_category":"Lokalbiblioteker",
    "sg:phone":"+45 75 86 00 87",
    "sg:postcode":"7000",
    "sg:province":"Danmark",
    "wof:name":"Smidstrup Bibliotek",
    "wof:placetype":"venue"
},
  "geometry": {"coordinates":[9.7591047287,55.566368103],"type":"Point"}
}