{
  "type": "Feature",
  "properties": {
    "addr:full":"Gl. Landevej 61 Herning Danmark 7400",
    "addr:housenumber":"61",
    "addr:postcode":"7400",
    "addr:street":"Gl. Landevej",
    "iso:country":"DK",
    "sg:address":"Gl. Landevej 61",
    "sg:city":"Herning",
    "sg:orig_category":"Offentlige sygehuse",
    "sg:phone":"+45 99 27 27 27",
    "sg:postcode":"7400",
    "sg:province":"Danmark",
    "sg:website":"www.herningcentralsygehus.dk",
    "wof:name":"Herning Centralsygehus.",
    "wof:placetype":"venue"
},
  "geometry": {"coordinates":[8.9717035294,56.1404457092],"type":"Point"}
}