{
  "type": "Feature",
  "properties": {
    "addr:full":"Strandeg\u00e5rdsvej 29 Hvidovre Danmark 2650",
    "addr:housenumber":"29",
    "addr:postcode":"2650",
    "addr:street":"Strandegaardsvej",
    "iso:country":"DK",
    "sg:address":"Strandeg\u00e5rdsvej 29",
    "sg:city":"Hvidovre",
    "sg:orig_category":"Revisorer",
    "sg:phone":"+45 36 49 14 32",
    "sg:postcode":"2650",
    "sg:province":"Danmark",
    "wof:name":"Becker, Lene E.",
    "wof:placetype":"venue"
},
  "geometry": {"coordinates":[12.4946403503,55.6295013428],"type":"Point"}
}