{
  "type": "Feature",
  "properties": {
    "addr:full":"Frederiksgade 24 \u00c5rhus C Danmark 8000",
    "addr:housenumber":"24",
    "addr:postcode":"8000",
    "addr:street":"Frederiksgade",
    "iso:country":"DK",
    "sg:address":"Frederiksgade 24",
    "sg:city":"\u00c5rhus C",
    "sg:orig_category":"Chokolade",
    "sg:phone":"+45 86 13 00 01",
    "sg:postcode":"8000",
    "sg:province":"Danmark",
    "wof:name":"Eliza",
    "wof:placetype":"venue"
},
  "geometry": {"coordinates":[10.2055578232,56.1557540894],"type":"Point"}
}