{
  "type": "Feature",
  "properties": {
    "addr:full":"\u00d8stre Stationsvej 6 Odense C Danmark 5000",
    "addr:housenumber":"6",
    "addr:postcode":"5000",
    "addr:street":"Ostre Stationsvej",
    "iso:country":"DK",
    "sg:address":"\u00d8stre Stationsvej 6",
    "sg:city":"Odense C",
    "sg:orig_category":"Telemateriel",
    "sg:phone":"+45 66 14 87 30",
    "sg:postcode":"5000",
    "sg:province":"Danmark",
    "wof:name":"Citymobil",
    "wof:placetype":"venue"
},
  "geometry": {"coordinates":[10.3844690323,55.4006767273],"type":"Point"}
}