{
  "type": "Feature",
  "properties": {
    "addr:full":"Gruppeleder: Verner Ibsen, Solbakken 10 Holstebro Danmark 7500",
    "addr:housenumber":"10",
    "addr:postcode":"7500",
    "addr:street":"Gruppeleder Verner Ibsen Solbakken",
    "iso:country":"DK",
    "sg:address":"Gruppeleder: Verner Ibsen, Solbakken 10",
    "sg:city":"Holstebro",
    "sg:orig_category":"Spejderkorps",
    "sg:phone":"+45 97 41 23 40",
    "sg:postcode":"7500",
    "sg:province":"Danmark",
    "wof:name":"KFUM-spejderne, 1. Prins Buris gruppe",
    "wof:placetype":"venue"
},
  "geometry": {"coordinates":[8.6202583313,56.3625221252],"type":"Point"}
}