{
  "type": "Feature",
  "properties": {
    "addr:full":"Kornmarken 6, M\u00f8rdrup Esperg\u00e6rde Danmark 3060",
    "addr:housenumber":"6",
    "addr:postcode":"3060",
    "addr:street":"Kornmarken",
    "iso:country":"DK",
    "sg:address":"Kornmarken 6, M\u00f8rdrup",
    "sg:city":"Esperg\u00e6rde",
    "sg:orig_category":"Arkitekter",
    "sg:phone":"+45 49 13 11 47",
    "sg:postcode":"3060",
    "sg:province":"Danmark",
    "wof:name":"Christiansen, Per",
    "wof:placetype":"venue"
},
  "geometry": {"coordinates":[11.6512403488,47.8390617371],"type":"Point"}
}