{
  "type": "Feature",
  "properties": {
    "addr:full":"Digtervejen 6 Aalborg SV Danmark 9200",
    "addr:housenumber":"6",
    "addr:postcode":"9200",
    "addr:street":"Digtervejen",
    "iso:country":"DK",
    "sg:address":"Digtervejen 6",
    "sg:city":"Aalborg SV",
    "sg:orig_category":"Kirker",
    "sg:postcode":"9200",
    "sg:province":"Danmark",
    "wof:name":"Skalborg Kirke",
    "wof:placetype":"venue"
},
  "geometry": {"coordinates":[9.8870306015,57.0141906738],"type":"Point"}
}