{
  "type": "Feature",
  "properties": {
    "iso:country":"DK",
    "sg:address":"H\u00f8stenvej 15, H\u00f8sten",
    "sg:city":"Haslev",
    "sg:orig_category":"Maskinfabrikker",
    "sg:phone":"+45 56 39 80 14",
    "sg:postcode":"4690",
    "sg:province":"Danmark",
    "wof:name":"Cosmo R\u00f8rbukkemaskiner",
    "wof:placetype":"venue"
},
  "geometry": {"coordinates":[11.9678049088,55.3230895996],"type":"Point"}
}