{
  "type": "Feature",
  "properties": {
    "iso:country":"DK",
    "sg:address":"Springvandspladsen 2, V. Hassing",
    "sg:city":"Vodskov",
    "sg:orig_category":"Brugsforeninger",
    "sg:phone":"+45 98 25 60 10",
    "sg:postcode":"9310",
    "sg:province":"Danmark",
    "wof:name":"Dagli' Brugsen V. Hassing",
    "wof:placetype":"venue"
},
  "geometry": {"coordinates":[10.0289011002,57.1044425964],"type":"Point"}
}