{
  "type": "Feature",
  "properties": {
    "iso:country":"DK",
    "sg:address":"Nytorv 19",
    "sg:city":"Slagelse",
    "sg:orig_category":"Realkreditinstitutter",
    "sg:phone":"+45 58 55 59 70",
    "sg:postcode":"4200",
    "sg:province":"Danmark",
    "sg:website":"www.rd.dk",
    "wof:name":"Realkredit Danmark",
    "wof:placetype":"venue"
},
  "geometry": {"coordinates":[11.3494033813,55.4108276367],"type":"Point"}
}