{
  "type": "Feature",
  "properties": {
    "addr:full":"Havnegade 38 Allinge Danmark 3770",
    "addr:housenumber":"38",
    "addr:postcode":"3770",
    "addr:street":"Havnegade",
    "iso:country":"DK",
    "sg:address":"Havnegade 38",
    "sg:city":"Allinge",
    "sg:orig_category":"Pensionater",
    "sg:phone":"+45 56 48 22 18",
    "sg:postcode":"3770",
    "sg:province":"Danmark",
    "wof:name":"Danchel Hus",
    "wof:placetype":"venue"
},
  "geometry": {"coordinates":[14.7961835861,55.2807312012],"type":"Point"}
}