{
  "type": "Feature",
  "properties": {
    "addr:full":"Frederiksdalvej 51 Kjellerup Danmark 8620",
    "addr:housenumber":"51",
    "addr:postcode":"8620",
    "addr:street":"Frederiksdalvej",
    "iso:country":"DK",
    "sg:address":"Frederiksdalvej 51",
    "sg:city":"Kjellerup",
    "sg:orig_category":"Antikviteter",
    "sg:phone":"+45 86 86 71 38",
    "sg:postcode":"8620",
    "sg:province":"Danmark",
    "wof:name":"A. K. Antik & Gammelt",
    "wof:placetype":"venue"
},
  "geometry": {"coordinates":[9.382686615,56.2233467102],"type":"Point"}
}