{
  "type": "Feature",
  "properties": {
    "addr:full":"Vandv\u00e6rksvej 31 Kjellerup Danmark 8620",
    "addr:housenumber":"31",
    "addr:postcode":"8620",
    "addr:street":"Vandvaerksvej",
    "iso:country":"DK",
    "sg:address":"Vandv\u00e6rksvej 31",
    "sg:city":"Kjellerup",
    "sg:orig_category":"Autoreparation og -service",
    "sg:phone":"+45 86 88 34 11",
    "sg:postcode":"8620",
    "sg:province":"Danmark",
    "wof:name":"B. T. Auto",
    "wof:placetype":"venue"
},
  "geometry": {"coordinates":[9.4410257339,56.2714042664],"type":"Point"}
}