{
  "type": "Feature",
  "properties": {
    "addr:full":"Landsgravvej 42 Slagelse Danmark 4200",
    "addr:housenumber":"42",
    "addr:postcode":"4200",
    "addr:street":"Landsgravvej",
    "iso:country":"DK",
    "sg:address":"Landsgravvej 42",
    "sg:city":"Slagelse",
    "sg:orig_category":"Gasfyr og service",
    "sg:phone":"+45 58 53 32 15",
    "sg:postcode":"4200",
    "sg:province":"Danmark",
    "wof:name":"Per's Gas- & Oliefyrsservice",
    "wof:placetype":"venue"
},
  "geometry": {"coordinates":[11.3308458328,55.3972511292],"type":"Point"}
}