{
  "type": "Feature",
  "properties": {
    "addr:full":"Frederikssund Sygehus, Frederikssundsvej 30 Frederikssund Danmark 3600",
    "addr:housenumber":"30",
    "addr:postcode":"3600",
    "addr:street":"Frederikssundsvej",
    "iso:country":"DK",
    "sg:address":"Frederikssund Sygehus, Frederikssundsvej 30",
    "sg:city":"Frederikssund",
    "sg:orig_category":"Blodbank",
    "sg:phone":"+45 48 29 53 96",
    "sg:postcode":"3600",
    "sg:province":"Danmark",
    "wof:name":"Blodbanken",
    "wof:placetype":"venue"
},
  "geometry": {"coordinates":[12.066162,55.837032],"type":"Point"}
}