{
  "type": "Feature",
  "properties": {
    "addr:full":"R\u00f8dbyvej 81 Maribo Danmark 4930",
    "addr:housenumber":"81",
    "addr:postcode":"4930",
    "addr:street":"Rodbyvej",
    "iso:country":"DK",
    "sg:address":"R\u00f8dbyvej 81",
    "sg:city":"Maribo",
    "sg:orig_category":"Kirker",
    "sg:postcode":"4930",
    "sg:province":"Danmark",
    "wof:name":"Hillested Kirke",
    "wof:placetype":"venue"
},
  "geometry": {"coordinates":[11.502035141,54.7743835449],"type":"Point"}
}