{
  "type": "Feature",
  "properties": {
    "iso:country":"DK",
    "sg:address":"R\u00e5dhuset, R\u00e5dhus Alle 100",
    "sg:city":"Frederikshavn",
    "sg:orig_category":"Kommunen",
    "sg:phone":"+45 96 22 50 00",
    "sg:postcode":"9900",
    "sg:province":"Danmark",
    "wof:name":"Frederikshavn Kommune",
    "wof:placetype":"venue"
},
  "geometry": {"coordinates":[10.5324773788,57.4413642883],"type":"Point"}
}