{
  "type": "Feature",
  "properties": {
    "iso:country":"DK",
    "sg:address":"Sognepr\u00e6st: Georg Klinting (K/B), Krogsb\u00f8lle Bygade 64",
    "sg:city":"Otterup",
    "sg:orig_category":"Kirkesogne",
    "sg:phone":"+45 64 87 11 01",
    "sg:postcode":"5450",
    "sg:province":"Danmark",
    "wof:name":"Krogsb\u00f8lle og Norup sogn (herunder Hasmark kirke)",
    "wof:placetype":"venue"
},
  "geometry": {"coordinates":[10.4545049667,55.5641746521],"type":"Point"}
}