{
  "type": "Feature",
  "properties": {
    "addr:full":"Smedebakken 44, N\u00e6sby Odense N Danmark 5270",
    "addr:housenumber":"44",
    "addr:postcode":"5270",
    "addr:street":"Smedebakken;Naesby",
    "iso:country":"DK",
    "sg:address":"Smedebakken 44, N\u00e6sby",
    "sg:city":"Odense N",
    "sg:orig_category":"Autolakering",
    "sg:phone":"+45 66 18 94 91",
    "sg:postcode":"5270",
    "sg:province":"Danmark",
    "wof:name":"John's Autolakering",
    "wof:placetype":"venue"
},
  "geometry": {"coordinates":[10.3306798935,55.4711418152],"type":"Point"}
}