{
  "type": "Feature",
  "properties": {
    "addr:full":"Holsted Alle 30 N\u00e6stved Danmark 4700",
    "addr:housenumber":"30",
    "addr:postcode":"4700",
    "addr:street":"Holsted Alle",
    "iso:country":"DK",
    "sg:address":"Holsted Alle 30",
    "sg:city":"N\u00e6stved",
    "sg:orig_category":"Skolefritidsordninger",
    "sg:phone":"+45 55 78 52 06",
    "sg:postcode":"4700",
    "sg:province":"Danmark",
    "wof:name":"Holsted Skole, SFO",
    "wof:placetype":"venue"
},
  "geometry": {"coordinates":[11.7628364563,55.2452812195],"type":"Point"}
}