{
  "type": "Feature",
  "properties": {
    "addr:full":"Kyhnsvej 7 Ry Danmark 8680",
    "addr:housenumber":"7",
    "addr:postcode":"8680",
    "addr:street":"Kyhnsvej",
    "iso:country":"DK",
    "sg:address":"Kyhnsvej 7",
    "sg:city":"Ry",
    "sg:orig_category":"Ejendomshandel",
    "sg:phone":"+45 86 89 14 66",
    "sg:postcode":"8680",
    "sg:province":"Danmark",
    "sg:website":"www.edc.dk",
    "wof:name":"EDC M\u00e6glerne Ry",
    "wof:placetype":"venue"
},
  "geometry": {"coordinates":[9.7567453384,56.0923614502],"type":"Point"}
}