{
  "type": "Feature",
  "properties": {
    "addr:full":"Skr\u00e5hedevej 6, St. Torup Skals Danmark 8832",
    "addr:housenumber":"6",
    "addr:postcode":"8832",
    "addr:street":"Skraahedevej",
    "iso:country":"DK",
    "sg:address":"Skr\u00e5hedevej 6, St. Torup",
    "sg:city":"Skals",
    "sg:orig_category":"Campingpladser",
    "sg:phone":"+45 86 69 70 93",
    "sg:postcode":"8832",
    "sg:province":"Danmark",
    "sg:website":"www.dk-camp.dk/ulbjerg",
    "wof:name":"Camping Ulbjerg",
    "wof:placetype":"venue"
},
  "geometry": {"coordinates":[9.4030599594,56.5558166504],"type":"Point"}
}