{
  "type": "Feature",
  "properties": {
    "iso:country":"DK",
    "sg:address":"Fmd.: Karen Pedersen, Byledet 4, Lellinge",
    "sg:city":"K\u00f8ge",
    "sg:orig_category":"Borger- og beboerforeninger",
    "sg:phone":"+45 56 82 03 06",
    "sg:postcode":"4600",
    "sg:province":"Danmark",
    "wof:name":"Lellinge Beboerforening",
    "wof:placetype":"venue"
},
  "geometry": {"coordinates":[12.2430353165,55.4170417786],"type":"Point"}
}