{
  "type": "Feature",
  "properties": {
    "addr:full":"Kongensgade 62 Odense C Danmark 5000",
    "addr:housenumber":"62",
    "addr:postcode":"5000",
    "addr:street":"Kongensgade",
    "iso:country":"DK",
    "sg:address":"Kongensgade 62",
    "sg:city":"Odense C",
    "sg:orig_category":"Cafeterier",
    "sg:phone":"+45 66 14 69 18",
    "sg:postcode":"5000",
    "sg:province":"Danmark",
    "wof:name":"Thi Tam Tang & Van Hai Em Nguyen",
    "wof:placetype":"venue"
},
  "geometry": {"coordinates":[10.3801174164,55.3978500366],"type":"Point"}
}