{
  "type": "Feature",
  "properties": {
    "addr:full":"Th. Olesen L\u00f8kkens Vej 6 Aalborg SV Danmark 9200",
    "addr:housenumber":"6",
    "addr:postcode":"9200",
    "addr:street":"Th.;Lokkens Vej",
    "iso:country":"DK",
    "sg:address":"Th. Olesen L\u00f8kkens Vej 6",
    "sg:city":"Aalborg SV",
    "sg:orig_category":"Autoreparation og -service",
    "sg:phone":"+45 98 18 11 88",
    "sg:postcode":"9200",
    "sg:province":"Danmark",
    "wof:name":"Christiansen's Autov\u00e6rksted, Vilhelm",
    "wof:placetype":"venue"
},
  "geometry": {"coordinates":[9.8851928711,57.0102844238],"type":"Point"}
}