{
  "type": "Feature",
  "properties": {
    "iso:country":"DK",
    "sg:address":"Teglmarken 65",
    "sg:city":"Viborg",
    "sg:orig_category":"Hobbybetonede foreninger",
    "sg:phone":"+45 86 61 59 51",
    "sg:postcode":"8800",
    "sg:province":"Danmark",
    "wof:name":"Viborg Radiostyrings Klub",
    "wof:placetype":"venue"
},
  "geometry": {"coordinates":[9.3945140839,56.4292488098],"type":"Point"}
}