{
  "type": "Feature",
  "properties": {
    "iso:country":"DK",
    "sg:address":"Risbjergvej 5",
    "sg:city":"Brande",
    "sg:classifiers":[
        {
            "category":"Building & Trades",
            "subcategory":"Construction",
            "type":"Services"
        }
    ],
    "sg:phone":"+45 97 18 19 00",
    "sg:postcode":"7330",
    "sg:province":"Danmark",
    "sg:tags":[
        "renovation"
    ],
    "wof:name":"Eriksen, S\u00f8ren",
    "wof:placetype":"venue"
},
  "geometry": {"coordinates":[9.1010980606,55.9301681519],"type":"Point"}
}