{
  "type": "Feature",
  "properties": {
    "addr:full":"Italiensvej 50 K\u00f8benhavn S Danmark 2300",
    "addr:housenumber":"50",
    "addr:postcode":"2300",
    "addr:street":"Italiensvej;S Danmark",
    "iso:country":"DK",
    "sg:address":"Italiensvej 50",
    "sg:city":"K\u00f8benhavn S",
    "sg:orig_category":"Revisorer",
    "sg:phone":"+45 32 58 33 32",
    "sg:postcode":"2300",
    "sg:province":"Danmark",
    "wof:name":"R\u00fctzou, Finn",
    "wof:placetype":"venue"
},
  "geometry": {"coordinates":[-98.62767028810001,48.1367988586],"type":"Point"}
}