{
  "type": "Feature",
  "properties": {
    "addr:full":"\u00d8stervold 40 Randers Danmark 8900",
    "addr:housenumber":"40",
    "addr:postcode":"8900",
    "addr:street":"Ostervold",
    "iso:country":"DK",
    "sg:address":"\u00d8stervold 40",
    "sg:city":"Randers",
    "sg:orig_category":"Kiropraktorer",
    "sg:phone":"+45 86 43 83 00",
    "sg:postcode":"8900",
    "sg:province":"Danmark",
    "wof:name":"Lund, Erling",
    "wof:placetype":"venue"
},
  "geometry": {"coordinates":[10.0406990051,56.4590988159],"type":"Point"}
}