{
  "type": "Feature",
  "properties": {
    "addr:full":"Konsul Beyers All\u00e9 1 Holb\u00e6k Danmark 4300",
    "addr:housenumber":"1",
    "addr:postcode":"4300",
    "addr:street":"Konsul Beyers Alle\u0301",
    "iso:country":"DK",
    "sg:address":"Konsul Beyers All\u00e9 1",
    "sg:city":"Holb\u00e6k",
    "sg:orig_category":"Integrerede institutioner",
    "sg:phone":"+45 59 44 12 66",
    "sg:postcode":"4300",
    "sg:province":"Danmark",
    "wof:name":"B\u00f8rnehuset Villa Kulla",
    "wof:placetype":"venue"
},
  "geometry": {"coordinates":[76.3070983887,14.277130127],"type":"Point"}
}