{
  "type": "Feature",
  "properties": {
    "addr:full":"Hulvejen 31, Ny Hammersholt Hiller\u00f8d Danmark 3400",
    "addr:housenumber":"31",
    "addr:postcode":"3400",
    "addr:street":"Hulvejen;Hammersholt;Danmark",
    "iso:country":"DK",
    "sg:address":"Hulvejen 31, Ny Hammersholt",
    "sg:city":"Hiller\u00f8d",
    "sg:orig_category":"Fritidsklubber",
    "sg:phone":"+45 48 24 18 40",
    "sg:postcode":"3400",
    "sg:province":"Danmark",
    "wof:name":"Petras Hus",
    "wof:placetype":"venue"
},
  "geometry": {"coordinates":[12.3056097031,55.9288215637],"type":"Point"}
}