{
  "type": "Feature",
  "properties": {
    "addr:full":"Langelandsvej 32 A Frederiksberg Danmark 2000",
    "addr:housenumber":"32 a",
    "addr:postcode":"2000",
    "addr:street":"Langelandsvej",
    "iso:country":"DK",
    "sg:address":"Langelandsvej 32 A",
    "sg:city":"Frederiksberg",
    "sg:orig_category":"Musikere",
    "sg:phone":"+45 38 34 42 29",
    "sg:postcode":"2000",
    "sg:province":"Danmark",
    "wof:name":"Pedersen, Fritz",
    "wof:placetype":"venue"
},
  "geometry": {"coordinates":[12.5308856964,55.6856040955],"type":"Point"}
}