{
  "type": "Feature",
  "properties": {
    "addr:full":"Holmstrupg\u00e5rdvej 20 A Brabrand Danmark 8220",
    "addr:housenumber":"20 a",
    "addr:postcode":"8220",
    "addr:street":"Holmstrupgaardvej",
    "iso:country":"DK",
    "sg:address":"Holmstrupg\u00e5rdvej 20 A",
    "sg:city":"Brabrand",
    "sg:orig_category":"INGENI\u00c3\u02dcRER",
    "sg:phone":"+45 86 24 50 66",
    "sg:postcode":"8220",
    "sg:province":"Danmark",
    "wof:name":"William Hansen & Co. R\u00e5dgivende Ingeni\u00f8rer F.R.I A/S",
    "wof:placetype":"venue"
},
  "geometry": {"coordinates":[10.1212882996,56.166229248],"type":"Point"}
}