{
  "type": "Feature",
  "properties": {
    "addr:full":"Kald\u00e6avej 14 K\u00f8benhavn S Danmark 2300",
    "addr:housenumber":"14",
    "addr:postcode":"2300",
    "addr:street":"Kaldaeavej;S Danmark",
    "iso:country":"DK",
    "sg:address":"Kald\u00e6avej 14",
    "sg:city":"K\u00f8benhavn S",
    "sg:orig_category":"Ungdomsklubber",
    "sg:phone":"+45 32 55 00 14",
    "sg:postcode":"2300",
    "sg:province":"Danmark",
    "wof:name":"Skoleinstitutionen p\u00e5 skolen ved Sundet",
    "wof:placetype":"venue"
},
  "geometry": {"coordinates":[49.2181816101,35.5731506348],"type":"Point"}
}