{
  "type": "Feature",
  "properties": {
    "addr:full":"Flintbakken 12, Rostved R\u00f8nde Danmark 8410",
    "addr:housenumber":"12",
    "addr:postcode":"8410",
    "addr:street":"Flintbakken;Ronde Danmark",
    "iso:country":"DK",
    "sg:address":"Flintbakken 12, Rostved",
    "sg:city":"R\u00f8nde",
    "sg:orig_category":"Sommerhusudlejning",
    "sg:phone":"+45 86 37 37 09",
    "sg:postcode":"8410",
    "sg:province":"Danmark",
    "wof:name":"Nauh\u00f8j",
    "wof:placetype":"venue"
},
  "geometry": {"coordinates":[10.4288892746,56.295917511],"type":"Point"}
}