{
  "type": "Feature",
  "properties": {
    "addr:full":"Holmegade 10 Ulfborg Danmark 6990",
    "addr:housenumber":"10",
    "addr:postcode":"6990",
    "addr:street":"Holmegade",
    "iso:country":"DK",
    "sg:address":"Holmegade 10",
    "sg:city":"Ulfborg",
    "sg:orig_category":"Glarmestre og glarmagere",
    "sg:phone":"+45 97 49 17 17",
    "sg:postcode":"6990",
    "sg:province":"Danmark",
    "wof:name":"Ulfborg Glarmesterforretning",
    "wof:placetype":"venue"
},
  "geometry": {"coordinates":[8.3212995529,56.2728233337],"type":"Point"}
}