{
  "type": "Feature",
  "properties": {
    "addr:full":"N. W. Gades Vej 1 Fredensborg Danmark 3480",
    "addr:housenumber":"1",
    "addr:postcode":"3480",
    "addr:street":"N. W. Gades Vej",
    "iso:country":"DK",
    "sg:address":"N. W. Gades Vej 1",
    "sg:city":"Fredensborg",
    "sg:orig_category":"Fritidshjem",
    "sg:phone":"+45 48 48 02 41",
    "sg:postcode":"3480",
    "sg:province":"Danmark",
    "wof:name":"Fredensborg fritidshjem",
    "wof:placetype":"venue"
},
  "geometry": {"coordinates":[12.4001522064,55.975112915],"type":"Point"}
}