{
  "type": "Feature",
  "properties": {
    "addr:full":"Hjarn\u00f8gade 1 \u00c5rhus C Danmark 8000",
    "addr:housenumber":"1",
    "addr:postcode":"8000",
    "addr:street":"Hjarnogade",
    "iso:country":"DK",
    "sg:address":"Hjarn\u00f8gade 1",
    "sg:city":"\u00c5rhus C",
    "sg:orig_category":"Kirker",
    "sg:postcode":"8000",
    "sg:province":"Danmark",
    "wof:name":"Betlehemskirken, Metodistkirken i \u00c5rhus",
    "wof:placetype":"venue"
},
  "geometry": {"coordinates":[99.92501068120001,34.2430114746],"type":"Point"}
}