{
  "type": "Feature",
  "properties": {
    "addr:full":"Amtsvejen 325 Hundested Danmark 3390",
    "addr:housenumber":"325",
    "addr:postcode":"3390",
    "addr:street":"Amtsvejen",
    "iso:country":"DK",
    "sg:address":"Amtsvejen 325",
    "sg:city":"Hundested",
    "sg:orig_category":"Haveservice",
    "sg:phone":"+45 47 98 76 98",
    "sg:postcode":"3390",
    "sg:province":"Danmark",
    "wof:name":"Top Service",
    "wof:placetype":"venue"
},
  "geometry": {"coordinates":[11.9528808594,55.9644737244],"type":"Point"}
}