{
  "type": "Feature",
  "properties": {
    "addr:full":"Helseholmen 1 Hvidovre Danmark 2650",
    "addr:housenumber":"1",
    "addr:postcode":"2650",
    "addr:street":"Helseholmen",
    "iso:country":"DK",
    "sg:address":"Helseholmen 1",
    "sg:city":"Hvidovre",
    "sg:orig_category":"INGENI\u00c3\u02dcRER",
    "sg:phone":"+45 36 34 33 66",
    "sg:postcode":"2650",
    "sg:province":"Danmark",
    "sg:website":"www.mthojgaard.dk",
    "wof:name":"MT H\u00f8jgaard a/s",
    "wof:placetype":"venue"
},
  "geometry": {"coordinates":[12.4604549408,55.6123847961],"type":"Point"}
}