{
  "type": "Feature",
  "properties": {
    "addr:full":"Fmd.: Kristian Damgaard Andersen, M\u00f8llebakken 5 B Saltum Danmark 9493",
    "addr:housenumber":"5 b",
    "addr:postcode":"9493",
    "addr:street":"Mollebakken",
    "iso:country":"DK",
    "sg:address":"Fmd.: Kristian Damgaard Andersen, M\u00f8llebakken 5 B",
    "sg:city":"Saltum",
    "sg:orig_category":"\u00c3\u2020ldreorganisationer og klubber",
    "sg:phone":"+45 98 88 11 72",
    "sg:postcode":"9493",
    "sg:province":"Danmark",
    "wof:name":"Saltum pensionistforening",
    "wof:placetype":"venue"
},
  "geometry": {"coordinates":[9.6585969925,57.2849464417],"type":"Point"}
}