{
  "type": "Feature",
  "properties": {
    "addr:full":"Gasv\u00e6rksvej 6 Marstal Danmark 5960",
    "addr:housenumber":"6",
    "addr:postcode":"5960",
    "addr:street":"Gasvaerksvej",
    "iso:country":"DK",
    "sg:address":"Gasv\u00e6rksvej 6",
    "sg:city":"Marstal",
    "sg:orig_category":"Handicapboliger",
    "sg:phone":"+45 63 52 63 89",
    "sg:postcode":"5960",
    "sg:province":"Danmark",
    "wof:name":"Bof\u00e6llesskabet",
    "wof:placetype":"venue"
},
  "geometry": {"coordinates":[10.5191106796,54.8500595093],"type":"Point"}
}