{
  "type": "Feature",
  "properties": {
    "addr:full":"Greve Strandvej 16 Greve Danmark 2670",
    "addr:housenumber":"16",
    "addr:postcode":"2670",
    "addr:street":"Greve Strandvej",
    "iso:country":"DK",
    "sg:address":"Greve Strandvej 16",
    "sg:city":"Greve",
    "sg:orig_category":"Advokater",
    "sg:phone":"+45 70 20 70 83",
    "sg:postcode":"2670",
    "sg:province":"Danmark",
    "sg:website":"www.ret-raad.dk",
    "wof:name":"Ret & Raad Sydkysten A/S",
    "wof:placetype":"venue"
},
  "geometry": {"coordinates":[12.3105564117,55.5822753906],"type":"Point"}
}