{
  "type": "Feature",
  "properties": {
    "addr:full":"Systofte Bygade 2 Nyk\u00f8bing Danmark 4800",
    "addr:housenumber":"2",
    "addr:postcode":"4800",
    "addr:street":"Systofte Bygade",
    "iso:country":"DK",
    "sg:address":"Systofte Bygade 2",
    "sg:city":"Nyk\u00f8bing",
    "sg:orig_category":"Sten og grus",
    "sg:phone":"+45 54 86 80 87",
    "sg:postcode":"4800",
    "sg:province":"Danmark",
    "wof:name":"Bj\u00f8rup Grusgrav",
    "wof:placetype":"venue"
},
  "geometry": {"coordinates":[11.8678541183,54.769241333],"type":"Point"}
}