{
  "type": "Feature",
  "properties": {
    "addr:full":"Porskj\u00e6rvej 18 A Galten Danmark 8464",
    "addr:housenumber":"18 a",
    "addr:postcode":"8464",
    "addr:street":"Porskjaervej",
    "iso:country":"DK",
    "sg:address":"Porskj\u00e6rvej 18 A",
    "sg:city":"Galten",
    "sg:orig_category":"\u00c3\u2020ldreorganisationer og klubber",
    "sg:phone":"+45 87 54 53 40",
    "sg:postcode":"8464",
    "sg:province":"Danmark",
    "wof:name":"Galten Efterl\u00f8nsklub",
    "wof:placetype":"venue"
},
  "geometry": {"coordinates":[9.9075860977,56.1529197693],"type":"Point"}
}