{
  "type": "Feature",
  "properties": {
    "addr:full":"Gr\u00f8nnevej 77, 1. th. Virum Danmark 2830",
    "addr:housenumber":"77 1 th.",
    "addr:postcode":"2830",
    "addr:street":"Gronnevej",
    "iso:country":"DK",
    "sg:address":"Gr\u00f8nnevej 77, 1. th.",
    "sg:city":"Virum",
    "sg:orig_category":"Malermestre",
    "sg:phone":"+45 45 85 52 37",
    "sg:postcode":"2830",
    "sg:province":"Danmark",
    "wof:name":"Basse, Allan",
    "wof:placetype":"venue"
},
  "geometry": {"coordinates":[12.4732246399,55.7885513306],"type":"Point"}
}