{
  "type": "Feature",
  "properties": {
    "addr:full":"Kongensgade 66  Esbjerg Danmark 6700",
    "addr:housenumber":"66",
    "addr:postcode":"6700",
    "addr:street":"Kongensgade",
    "iso:country":"DK",
    "sg:address":"Kongensgade 66 ",
    "sg:city":"Esbjerg",
    "sg:classifiers":[
        {
            "category":"Communications",
            "subcategory":"Television Station",
            "type":"Services"
        }
    ],
    "sg:phone":"+45 75 12 11 22",
    "sg:postcode":"6700",
    "sg:province":"Danmark",
    "sg:tags":[
        "audio-visual"
    ],
    "wof:name":"JASPERS RADIO A/S",
    "wof:placetype":"venue"
},
  "geometry": {"coordinates":[8.4492635727,55.4661407471],"type":"Point"}
}