{
  "type": "Feature",
  "properties": {
    "addr:full":"Borgergade 72 Silkeborg Danmark 8600",
    "addr:housenumber":"72",
    "addr:postcode":"8600",
    "addr:street":"Borgergade",
    "iso:country":"DK",
    "sg:address":"Borgergade 72",
    "sg:city":"Silkeborg",
    "sg:orig_category":"Mobiltelefoner",
    "sg:phone":"+45 87 20 00 73",
    "sg:postcode":"8600",
    "sg:province":"Danmark",
    "wof:name":"Unitalk",
    "wof:placetype":"venue"
},
  "geometry": {"coordinates":[9.5486421585,56.1815185547],"type":"Point"}
}