{
  "type": "Feature",
  "properties": {
    "addr:full":"Vestergade 67 Grindsted Danmark 7200",
    "addr:housenumber":"67",
    "addr:postcode":"7200",
    "addr:street":"Vestergade",
    "iso:country":"DK",
    "sg:address":"Vestergade 67",
    "sg:city":"Grindsted",
    "sg:orig_category":"Brandslukning",
    "sg:phone":"+45 70 10 20 30",
    "sg:postcode":"7200",
    "sg:province":"Danmark",
    "wof:name":"Falcks Redningskorps",
    "wof:placetype":"venue"
},
  "geometry": {"coordinates":[8.9159946442,55.7600784302],"type":"Point"}
}