{
  "type": "Feature",
  "properties": {
    "iso:country":"DK",
    "sg:address":"Essen 22",
    "sg:city":"Kolding",
    "sg:orig_category":"Bogtrykkerier",
    "sg:phone":"+45 75 56 68 22",
    "sg:postcode":"6000",
    "sg:province":"Danmark",
    "wof:name":"Thomsen Offset A/S, J\u00f8rn",
    "wof:placetype":"venue"
},
  "geometry": {"coordinates":[9.4772472382,55.4621505737],"type":"Point"}
}