{
  "type": "Feature",
  "properties": {
    "addr:full":"Marsvej 29 Thors\u00f8 Danmark 8881",
    "addr:housenumber":"29",
    "addr:postcode":"8881",
    "addr:street":"Marsvej",
    "iso:country":"DK",
    "sg:address":"Marsvej 29",
    "sg:city":"Thors\u00f8",
    "sg:orig_category":"Murermestre",
    "sg:phone":"+45 86 96 62 77",
    "sg:postcode":"8881",
    "sg:province":"Danmark",
    "wof:name":"Gertsen's Murerfirma ApS",
    "wof:placetype":"venue"
},
  "geometry": {"coordinates":[9.7927570343,56.302028656],"type":"Point"}
}