{
  "type": "Feature",
  "properties": {
    "addr:full":"Golfvangen 20 Esbjerg N Danmark 6715",
    "addr:housenumber":"20",
    "addr:postcode":"6715",
    "addr:street":"Golfvangen",
    "iso:country":"DK",
    "sg:address":"Golfvangen 20",
    "sg:city":"Esbjerg N",
    "sg:orig_category":"Faglige organisationer og foreninger",
    "sg:phone":"+45 75 18 15 51",
    "sg:postcode":"6715",
    "sg:province":"Danmark",
    "wof:name":"Maskinmesternes Forening Sydvestjydsk Kreds",
    "wof:placetype":"venue"
},
  "geometry": {"coordinates":[8.4399013519,55.5012626648],"type":"Point"}
}