{
  "type": "Feature",
  "properties": {
    "addr:full":"Hovedgaden 22 Havdrup Danmark 4622",
    "addr:housenumber":"22",
    "addr:postcode":"4622",
    "addr:street":"Hovedgaden",
    "iso:country":"DK",
    "sg:address":"Hovedgaden 22",
    "sg:city":"Havdrup",
    "sg:orig_category":"Pizzeriaer",
    "sg:phone":"+45 46 18 69 83",
    "sg:postcode":"4622",
    "sg:province":"Danmark",
    "wof:name":"Sema Pizza Bar",
    "wof:placetype":"venue"
},
  "geometry": {"coordinates":[12.116027832,55.5426521301],"type":"Point"}
}