{
  "type": "Feature",
  "properties": {
    "addr:full":"J. P. Larsens Vej 1 Brabrand Danmark 8220",
    "addr:housenumber":"1",
    "addr:postcode":"8220",
    "addr:street":"J. P. Larsens Vej",
    "iso:country":"DK",
    "sg:address":"J. P. Larsens Vej 1",
    "sg:city":"Brabrand",
    "sg:orig_category":"Graffitifjerner",
    "sg:phone":"+45 70 20 00 92",
    "sg:postcode":"8220",
    "sg:province":"Danmark",
    "wof:name":"Graffiti Patruljen ApS",
    "wof:placetype":"venue"
},
  "geometry": {"coordinates":[10.1167154312,56.1536941528],"type":"Point"}
}