{
  "type": "Feature",
  "properties": {
    "iso:country":"DK",
    "sg:address":"Langbjergvej 8",
    "sg:city":"Gesten",
    "sg:orig_category":"Hundepensioner",
    "sg:phone":"+45 75 55 70 21",
    "sg:postcode":"6621",
    "sg:province":"Danmark",
    "wof:name":"Langbjerg Hundepension",
    "wof:placetype":"venue"
},
  "geometry": {"coordinates":[9.1871995926,55.5302734375],"type":"Point"}
}