{
  "type": "Feature",
  "properties": {
    "addr:full":"Borrisvej 2, Spark\u00e6r Viborg Danmark 8800",
    "addr:housenumber":"2",
    "addr:postcode":"8800",
    "addr:street":"Borrisvej",
    "iso:country":"DK",
    "sg:address":"Borrisvej 2, Spark\u00e6r",
    "sg:city":"Viborg",
    "sg:orig_category":"\u00c3\u2020ldrecentre",
    "sg:phone":"+45 86 64 52 22",
    "sg:postcode":"8800",
    "sg:province":"Danmark",
    "wof:name":"Nordstjernen \u00c6ldrecenter \u00d8st",
    "wof:placetype":"venue"
},
  "geometry": {"coordinates":[9.4071502686,56.452671051],"type":"Point"}
}