{
  "type": "Feature",
  "properties": {
    "iso:country":"DK",
    "sg:address":"Banesvinget 5",
    "sg:city":"St\u00f8vring",
    "sg:orig_category":"Glasfiberindustri",
    "sg:phone":"+45 98 37 27 44",
    "sg:postcode":"9530",
    "sg:province":"Danmark",
    "wof:name":"TuboTec glasfiber A/S",
    "wof:placetype":"venue"
},
  "geometry": {"coordinates":[-103.3109588623,34.3324546814],"type":"Point"}
}