{
  "type": "Feature",
  "properties": {
    "addr:full":"Engelstrupvej 22, Engelstrup Tappern\u00f8je Danmark 4733",
    "addr:housenumber":"22",
    "addr:postcode":"4733",
    "addr:street":"Engelstrupvej",
    "iso:country":"DK",
    "sg:address":"Engelstrupvej 22, Engelstrup",
    "sg:city":"Tappern\u00f8je",
    "sg:orig_category":"Regnskabsassistance",
    "sg:phone":"+45 55 56 44 90",
    "sg:postcode":"4733",
    "sg:province":"Danmark",
    "wof:name":"Posterings-Linien",
    "wof:placetype":"venue"
},
  "geometry": {"coordinates":[11.9756202698,55.1781692505],"type":"Point"}
}