{
  "type": "Feature",
  "properties": {
    "addr:full":"v/ J\u00f8rgen Esbjerg, \u00d8rvigvej 48 Egtved Danmark 6040",
    "addr:housenumber":"48",
    "addr:postcode":"6040",
    "addr:street":"Orvigvej",
    "iso:country":"DK",
    "sg:address":"v/ J\u00f8rgen Esbjerg, \u00d8rvigvej 48",
    "sg:city":"Egtved",
    "sg:orig_category":"Loger",
    "sg:phone":"+45 75 55 19 38",
    "sg:postcode":"6040",
    "sg:province":"Danmark",
    "wof:name":"Lions Club Egtved",
    "wof:placetype":"venue"
},
  "geometry": {"coordinates":[9.3087482452,55.6161613464],"type":"Point"}
}