{
  "type": "Feature",
  "properties": {
    "addr:full":"Gr\u00e5sig 10 Ans Danmark 8643",
    "addr:housenumber":"10",
    "addr:postcode":"8643",
    "addr:street":"Graasig",
    "iso:country":"DK",
    "sg:address":"Gr\u00e5sig 10",
    "sg:city":"Ans",
    "sg:orig_category":"Malermestre",
    "sg:phone":"+45 86 87 04 66",
    "sg:postcode":"8643",
    "sg:province":"Danmark",
    "wof:name":"Frede's Malerforretning",
    "wof:placetype":"venue"
},
  "geometry": {"coordinates":[9.5970220566,56.3055915833],"type":"Point"}
}