{
  "type": "Feature",
  "properties": {
    "iso:country":"DK",
    "sg:address":"Nygade 6",
    "sg:city":"K\u00f8benhavn",
    "sg:orig_category":"Advokater",
    "sg:phone":"+45 33 32 86 80",
    "sg:postcode":"1164",
    "sg:province":"Danmark",
    "wof:name":"Popp-Madsen, Mogens",
    "wof:placetype":"venue"
},
  "geometry": {"coordinates":[12.5732603073,55.6782798767],"type":"Point"}
}