{
  "type": "Feature",
  "properties": {
    "addr:full":"Egensevej 25  Kastrup Danmark 2770",
    "addr:housenumber":"25",
    "addr:postcode":"2770",
    "addr:street":"Egensevej",
    "iso:country":"DK",
    "sg:address":"Egensevej 25 ",
    "sg:city":"Kastrup",
    "sg:classifiers":[
        {
            "category":"Airport",
            "subcategory":"General Aviation",
            "type":"Transportation"
        }
    ],
    "sg:phone":"+45 32 52 61 00",
    "sg:postcode":"2770",
    "sg:province":"Danmark",
    "sg:tags":[
        "transport",
        "air"
    ],
    "wof:name":"TRANS-AIR DANMARK A/S",
    "wof:placetype":"venue"
},
  "geometry": {"coordinates":[12.5967912674,55.6252708435],"type":"Point"}
}