{
  "type": "Feature",
  "properties": {
    "addr:full":"v/Poul Breth Madsen, Borgergade 9, Brejning B\u00f8rkop Danmark 7080",
    "addr:housenumber":"9",
    "addr:postcode":"7080",
    "addr:street":"Breth;Borgergade",
    "iso:country":"DK",
    "sg:address":"v/Poul Breth Madsen, Borgergade 9, Brejning",
    "sg:city":"B\u00f8rkop",
    "sg:orig_category":"Loger",
    "sg:phone":"+45 75 86 16 05",
    "sg:postcode":"7080",
    "sg:province":"Danmark",
    "wof:name":"Lions Club, B\u00f8rkop",
    "wof:placetype":"venue"
},
  "geometry": {"coordinates":[9.739865303,55.6495666504],"type":"Point"}
}