{
  "type": "Feature",
  "properties": {
    "addr:full":"Christianshavn, Wilders Plads 1, Bygning G K\u00f8benhavn Danmark 1403",
    "addr:housenumber":"1 bygning g;1403",
    "addr:street":"Wilders Plads",
    "iso:country":"DK",
    "sg:address":"Christianshavn, Wilders Plads 1, Bygning G",
    "sg:city":"K\u00f8benhavn",
    "sg:orig_category":"Strikvarer",
    "sg:phone":"+45 32 54 42 24",
    "sg:postcode":"1403",
    "sg:province":"Danmark",
    "wof:name":"Hanne Holm Strikkeri",
    "wof:placetype":"venue"
},
  "geometry": {"coordinates":[12.5967998505,55.6748008728],"type":"Point"}
}