{
  "type": "Feature",
  "properties": {
    "addr:full":"Storegade 86 Stege Danmark 4780",
    "addr:housenumber":"86",
    "addr:postcode":"4780",
    "addr:street":"Storegade",
    "iso:country":"DK",
    "sg:address":"Storegade 86",
    "sg:city":"Stege",
    "sg:orig_category":"Vaskerier",
    "sg:phone":"+45 55 81 44 16",
    "sg:postcode":"4780",
    "sg:province":"Danmark",
    "wof:name":"Chic, Vaskeriet",
    "wof:placetype":"venue"
},
  "geometry": {"coordinates":[12.2891454697,54.9868545532],"type":"Point"}
}