{
  "type": "Feature",
  "properties": {
    "addr:full":"Engtoften 14, Agedrup Agedrup Danmark 5320",
    "addr:housenumber":"14",
    "addr:postcode":"5320",
    "addr:street":"Engtoften",
    "iso:country":"DK",
    "sg:address":"Engtoften 14, Agedrup",
    "sg:city":"Agedrup",
    "sg:orig_category":"Ost en gros",
    "sg:phone":"+45 66 10 88 33",
    "sg:postcode":"5320",
    "sg:province":"Danmark",
    "wof:name":"Frederiksen, Freddy",
    "wof:placetype":"venue"
},
  "geometry": {"coordinates":[10.4700860977,55.4257240295],"type":"Point"}
}