{
  "type": "Feature",
  "properties": {
    "addr:full":"Helligkorsvej 8 Roskilde Danmark 4000",
    "addr:housenumber":"8",
    "addr:postcode":"4000",
    "addr:street":"Helligkorsvej",
    "iso:country":"DK",
    "sg:address":"Helligkorsvej 8",
    "sg:city":"Roskilde",
    "sg:orig_category":"Loger",
    "sg:phone":"+45 46 35 18 49",
    "sg:postcode":"4000",
    "sg:province":"Danmark",
    "wof:name":"Dansk Broder Orden",
    "wof:placetype":"venue"
},
  "geometry": {"coordinates":[12.0699701309,55.6392631531],"type":"Point"}
}