{
  "type": "Feature",
  "properties": {
    "addr:full":"Kirkeplads 8 C Aabenraa Danmark 6200",
    "addr:housenumber":"8 c",
    "addr:postcode":"6200",
    "addr:street":"Kirkeplads",
    "iso:country":"DK",
    "sg:address":"Kirkeplads 8 C",
    "sg:city":"Aabenraa",
    "sg:orig_category":"Arkitekter",
    "sg:phone":"+45 74 62 79 78",
    "sg:postcode":"6200",
    "sg:province":"Danmark",
    "wof:name":"Mathiesen, Fleming",
    "wof:placetype":"venue"
},
  "geometry": {"coordinates":[9.4177236557,55.044342041],"type":"Point"}
}