{
  "type": "Feature",
  "properties": {
    "addr:full":"Petersbjergg\u00e5rd 10 Kolding Danmark 6000",
    "addr:housenumber":"10",
    "addr:postcode":"6000",
    "iso:country":"DK",
    "sg:address":"Petersbjergg\u00e5rd 10",
    "sg:city":"Kolding",
    "sg:orig_category":"Forsikringer",
    "sg:phone":"+45 75 52 26 22",
    "sg:postcode":"6000",
    "sg:province":"Danmark",
    "wof:name":"PFA Pension",
    "wof:placetype":"venue"
},
  "geometry": {"coordinates":[9.502779007,55.5015411377],"type":"Point"}
}