{
  "type": "Feature",
  "properties": {
    "addr:full":"Kong Christians Alle 6 Aalborg Danmark 9000",
    "addr:housenumber":"6",
    "addr:postcode":"9000",
    "addr:street":"Kong Christians Alle",
    "iso:country":"DK",
    "sg:address":"Kong Christians Alle 6",
    "sg:city":"Aalborg",
    "sg:orig_category":"Reklamebureauer",
    "sg:phone":"+45 98 16 66 00",
    "sg:postcode":"9000",
    "sg:province":"Danmark",
    "wof:name":"Jensen Marketing A/S, Poul Erik",
    "wof:placetype":"venue"
},
  "geometry": {"coordinates":[9.9031953812,57.0492706299],"type":"Point"}
}