{
  "type": "Feature",
  "properties": {
    "addr:full":"S\u00f8ndbjerg Strandvej 4, S\u00f8ndbjerg Thyholm Danmark 7790",
    "addr:housenumber":"4",
    "addr:postcode":"7790",
    "addr:street":"Sondbjerg Strandvej",
    "iso:country":"DK",
    "sg:address":"S\u00f8ndbjerg Strandvej 4, S\u00f8ndbjerg",
    "sg:city":"Thyholm",
    "sg:orig_category":"EDB - konsulenter",
    "sg:phone":"+45 70 20 59 95",
    "sg:postcode":"7790",
    "sg:province":"Danmark",
    "sg:website":"www.svalgaard.com",
    "wof:name":"Svalgaard IT-service",
    "wof:placetype":"venue"
},
  "geometry": {"coordinates":[8.525765419,56.6507072449],"type":"Point"}
}