{
  "type": "Feature",
  "properties": {
    "addr:full":"M\u00f8llergade 64 D Svendborg Danmark 5700",
    "addr:housenumber":"64 d",
    "addr:postcode":"5700",
    "addr:street":"Mollergade",
    "iso:country":"DK",
    "sg:address":"M\u00f8llergade 64 D",
    "sg:city":"Svendborg",
    "sg:orig_category":"Bandagister",
    "sg:phone":"+45 62 20 14 84",
    "sg:postcode":"5700",
    "sg:province":"Danmark",
    "sg:website":"www.fynsbandageri.dk",
    "wof:name":"Fyns Bandageri A/S",
    "wof:placetype":"venue"
},
  "geometry": {"coordinates":[10.611094,55.061996],"type":"Point"}
}