{
  "type": "Feature",
  "properties": {
    "addr:full":"Pr\u00e6stev\u00e6nget 2 A Vildbjerg Danmark 7480",
    "addr:housenumber":"2 a",
    "addr:postcode":"7480",
    "addr:street":"Praestevaenget",
    "iso:country":"DK",
    "sg:address":"Pr\u00e6stev\u00e6nget 2 A",
    "sg:city":"Vildbjerg",
    "sg:orig_category":"Malermestre",
    "sg:phone":"+45 97 13 36 22",
    "sg:postcode":"7480",
    "sg:province":"Danmark",
    "wof:name":"K\u00f8hler, Malerfirmaet John",
    "wof:placetype":"venue"
},
  "geometry": {"coordinates":[8.7678747177,56.1993865967],"type":"Point"}
}