{
  "type": "Feature",
  "properties": {
    "addr:full":"Overgade 31 Odense C Danmark 5000",
    "addr:housenumber":"31",
    "addr:postcode":"5000",
    "addr:street":"Overgade",
    "iso:country":"DK",
    "sg:address":"Overgade 31",
    "sg:city":"Odense C",
    "sg:orig_category":"Gaveartikler",
    "sg:phone":"+45 66 13 72 18",
    "sg:postcode":"5000",
    "sg:province":"Danmark",
    "wof:name":"India, Boutique",
    "wof:placetype":"venue"
},
  "geometry": {"coordinates":[10.3923397064,55.3973731995],"type":"Point"}
}