{
  "type": "Feature",
  "properties": {
    "iso:country":"DK",
    "sg:address":"Hiller\u00f8dgade 30 A",
    "sg:city":"K\u00f8benhavn N",
    "sg:orig_category":"Arkitekter",
    "sg:phone":"+45 35 85 12 72",
    "sg:postcode":"2200",
    "sg:province":"Danmark",
    "wof:name":"3D arkitekter maa",
    "wof:placetype":"venue"
},
  "geometry": {"coordinates":[-94.46161651609999,47.8553733826],"type":"Point"}
}