{
  "type": "Feature",
  "properties": {
    "addr:full":"Nordre Strandvej 15 Risskov Danmark 8240",
    "addr:housenumber":"15",
    "addr:postcode":"8240",
    "addr:street":"Nordre Strandvej",
    "iso:country":"DK",
    "sg:address":"Nordre Strandvej 15",
    "sg:city":"Risskov",
    "sg:orig_category":"Farve og tapet",
    "sg:phone":"+45 86 17 99 22",
    "sg:postcode":"8240",
    "sg:province":"Danmark",
    "wof:name":"Risskov Tapet & Farve",
    "wof:placetype":"venue"
},
  "geometry": {"coordinates":[10.2415046692,56.1922874451],"type":"Point"}
}