{
  "type": "Feature",
  "properties": {
    "addr:full":"Lundevangsvej 15 Hellerup Danmark 2900",
    "addr:housenumber":"15",
    "addr:postcode":"2900",
    "addr:street":"Lundevangsvej",
    "iso:country":"DK",
    "sg:address":"Lundevangsvej 15",
    "sg:city":"Hellerup",
    "sg:orig_category":"INGENI\u00c3\u02dcRER",
    "sg:phone":"+45 39 62 89 69",
    "sg:postcode":"2900",
    "sg:province":"Danmark",
    "wof:name":"Guntofte & Bech ApS",
    "wof:placetype":"venue"
},
  "geometry": {"coordinates":[12.5788497925,55.7413787842],"type":"Point"}
}