{
  "type": "Feature",
  "properties": {
    "addr:full":"Hulvej 35 Horsens Danmark 8700",
    "addr:housenumber":"35",
    "addr:postcode":"8700",
    "addr:street":"Hulvej",
    "iso:country":"DK",
    "sg:address":"Hulvej 35",
    "sg:city":"Horsens",
    "sg:classifiers":[
        {
            "category":"Personal",
            "subcategory":"Massage",
            "type":"Services"
        }
    ],
    "sg:phone":"+45 75 61 76 17",
    "sg:postcode":"8700",
    "sg:province":"Danmark",
    "wof:name":"Johansen, Hanna",
    "wof:placetype":"venue"
},
  "geometry": {"coordinates":[9.8580131531,55.8650779724],"type":"Point"}
}