{
  "type": "Feature",
  "properties": {
    "addr:full":"Fmd.: Hans Bjerrum, \u00d8. Lundg\u00e5rdvej 24, Nr. Nissum Lemvig Danmark 7620",
    "addr:housenumber":"24",
    "addr:postcode":"7620",
    "addr:street":"Lundgaardvej",
    "iso:country":"DK",
    "sg:address":"Fmd.: Hans Bjerrum, \u00d8. Lundg\u00e5rdvej 24, Nr. Nissum",
    "sg:city":"Lemvig",
    "sg:orig_category":"Hobbybetonede foreninger",
    "sg:phone":"+45 97 89 11 65",
    "sg:postcode":"7620",
    "sg:province":"Danmark",
    "wof:name":"Lemvig og Omegns Biavlerforening",
    "wof:placetype":"venue"
},
  "geometry": {"coordinates":[8.3073654175,56.5505104065],"type":"Point"}
}