{
  "type": "Feature",
  "properties": {
    "addr:full":"Fmd.: Kirsten Christiansen, Fyrrevangen 29 Esbjerg N Danmark 6715",
    "addr:housenumber":"29",
    "addr:postcode":"6715",
    "addr:street":"Fyrrevangen",
    "iso:country":"DK",
    "sg:address":"Fmd.: Kirsten Christiansen, Fyrrevangen 29",
    "sg:city":"Esbjerg N",
    "sg:orig_category":"Husflidsforeninger",
    "sg:phone":"+45 75 12 60 23",
    "sg:postcode":"6715",
    "sg:province":"Danmark",
    "wof:name":"Aktive Piger",
    "wof:placetype":"venue"
},
  "geometry": {"coordinates":[8.4780550003,55.535610199],"type":"Point"}
}