{
  "type": "Feature",
  "properties": {
    "iso:country":"DK",
    "sg:address":"\u00d8ster Hedevej 161",
    "sg:city":"Hj\u00f8rring",
    "sg:orig_category":"Vinduespolering",
    "sg:phone":"+45 98 90 01 85",
    "sg:postcode":"9800",
    "sg:province":"Danmark",
    "wof:name":"Kerns Vinduespolering",
    "wof:placetype":"venue"
},
  "geometry": {"coordinates":[3.530174017,50.9863166809],"type":"Point"}
}