{
  "type": "Feature",
  "properties": {
    "addr:full":"Birkev\u00e6nget 3 Varde Danmark 6800",
    "addr:housenumber":"3",
    "addr:postcode":"6800",
    "addr:street":"Birkevaenget",
    "iso:country":"DK",
    "sg:address":"Birkev\u00e6nget 3",
    "sg:city":"Varde",
    "sg:orig_category":"Vinduespolering",
    "sg:phone":"+45 75 21 02 71",
    "sg:postcode":"6800",
    "sg:province":"Danmark",
    "wof:name":"LS Vinduespolering & T\u00e6pperens",
    "wof:placetype":"venue"
},
  "geometry": {"coordinates":[8.482629776,55.6220741272],"type":"Point"}
}