{
  "type": "Feature",
  "properties": {
    "addr:full":"Munkholmvej 17 Holb\u00e6k Danmark 4300",
    "addr:housenumber":"17",
    "addr:postcode":"4300",
    "addr:street":"Munkholmvej",
    "iso:country":"DK",
    "sg:address":"Munkholmvej 17",
    "sg:city":"Holb\u00e6k",
    "sg:orig_category":"Faglige organisationer og foreninger",
    "sg:phone":"+45 59 45 80 00",
    "sg:postcode":"4300",
    "sg:province":"Danmark",
    "wof:name":"Handels- og Kontorfunktion\u00e6rernes Forbund",
    "wof:placetype":"venue"
},
  "geometry": {"coordinates":[76.3070983887,14.277130127],"type":"Point"}
}