{
  "type": "Feature",
  "properties": {
    "addr:full":"Regnbuen, Skolegade 23, Herrup Vinderup Danmark 7830",
    "addr:housenumber":"23",
    "addr:postcode":"7830",
    "addr:street":"Regnbuen Skolegade;Herrup",
    "iso:country":"DK",
    "sg:address":"Regnbuen, Skolegade 23, Herrup",
    "sg:city":"Vinderup",
    "sg:orig_category":"Skolefritidsordninger",
    "sg:phone":"+45 97 45 27 12",
    "sg:postcode":"7830",
    "sg:province":"Danmark",
    "wof:name":"Skolefritidsordningen ved Herrup Skole",
    "wof:placetype":"venue"
},
  "geometry": {"coordinates":[8.7796897888,56.482635498],"type":"Point"}
}