{
  "type": "Feature",
  "properties": {
    "addr:full":"Degnehusene 113 Albertslund Danmark 2620",
    "addr:housenumber":"113",
    "addr:postcode":"2620",
    "addr:street":"Degnehusene",
    "iso:country":"DK",
    "sg:address":"Degnehusene 113",
    "sg:city":"Albertslund",
    "sg:orig_category":"Sammensatte institutioner",
    "sg:phone":"+45 43 45 21 24",
    "sg:postcode":"2620",
    "sg:province":"Danmark",
    "wof:name":"Vejrm\u00f8llen B\u00f8rnehus",
    "wof:placetype":"venue"
},
  "geometry": {"coordinates":[12.3649406433,55.6703491211],"type":"Point"}
}