{
  "type": "Feature",
  "properties": {
    "addr:full":"Paludan-M\u00fcllers Vej 92 \u00c5rhus N Danmark 8200",
    "addr:housenumber":"92",
    "addr:postcode":"8200",
    "addr:street":"Paludan-Muellers Vej",
    "iso:country":"DK",
    "sg:address":"Paludan-M\u00fcllers Vej 92",
    "sg:city":"\u00c5rhus N",
    "sg:orig_category":"Fritidshjem",
    "sg:phone":"+45 86 16 46 70",
    "sg:postcode":"8200",
    "sg:province":"Danmark",
    "wof:name":"Ovenp\u00e5, Fritidshjem",
    "wof:placetype":"venue"
},
  "geometry": {"coordinates":[4.9393601418,49.7092018127],"type":"Point"}
}