{
  "type": "Feature",
  "properties": {
    "addr:full":"Spang 11 S\u00f8nderborg Danmark 6400",
    "addr:housenumber":"11",
    "addr:postcode":"6400",
    "addr:street":"Spang",
    "iso:country":"DK",
    "sg:address":"Spang 11",
    "sg:city":"S\u00f8nderborg",
    "sg:orig_category":"Isolering",
    "sg:phone":"+45 74 42 14 72",
    "sg:postcode":"6400",
    "sg:province":"Danmark",
    "wof:name":"S\u00f8nderborg Isoleringsforretning",
    "wof:placetype":"venue"
},
  "geometry": {"coordinates":[9.6049203873,54.7732696533],"type":"Point"}
}