{
  "type": "Feature",
  "properties": {
    "addr:full":"Gruppeleder: Erik Jensen, Dunhammerv\u00e6nget 19 Otterup Danmark 5450",
    "addr:housenumber":"19",
    "addr:postcode":"5450",
    "addr:street":"Erik",
    "iso:country":"DK",
    "sg:address":"Gruppeleder: Erik Jensen, Dunhammerv\u00e6nget 19",
    "sg:city":"Otterup",
    "sg:orig_category":"Spejderkorps",
    "sg:phone":"+45 64 82 24 02",
    "sg:postcode":"5450",
    "sg:province":"Danmark",
    "wof:name":"KFUM spejderne, Otterup",
    "wof:placetype":"venue"
},
  "geometry": {"coordinates":[10.4545049667,55.5641746521],"type":"Point"}
}