{
  "type": "Feature",
  "properties": {
    "addr:full":"Trong\u00e5rdsvej 44 Kongens Lyngby Danmark 2800",
    "addr:housenumber":"44",
    "addr:postcode":"2800",
    "addr:street":"Trongaardsvej",
    "iso:country":"DK",
    "sg:address":"Trong\u00e5rdsvej 44",
    "sg:city":"Kongens Lyngby",
    "sg:orig_category":"Erhvervsskoler",
    "sg:phone":"+45 45 98 96 00",
    "sg:postcode":"2800",
    "sg:province":"Danmark",
    "sg:website":"www.lyngby.nu",
    "wof:name":"Lyngby Business Consult",
    "wof:placetype":"venue"
},
  "geometry": {"coordinates":[12.5350542068,55.77734375],"type":"Point"}
}