{
  "type": "Feature",
  "properties": {
    "addr:full":"Vestergade 18 Bogense Danmark 5400",
    "addr:housenumber":"18",
    "addr:postcode":"5400",
    "addr:street":"Vestergade",
    "iso:country":"DK",
    "sg:address":"Vestergade 18",
    "sg:city":"Bogense",
    "sg:orig_category":"Posthuse",
    "sg:phone":"+45 65 43 32 00",
    "sg:postcode":"5400",
    "sg:province":"Danmark",
    "wof:name":"Post Danmark, Bogense Posthus",
    "wof:placetype":"venue"
},
  "geometry": {"coordinates":[10.0871295929,55.5646057129],"type":"Point"}
}