{
  "type": "Feature",
  "properties": {
    "addr:full":"Bavnevangen 32 Aalborg S\u00d8 Danmark 9210",
    "addr:housenumber":"32",
    "addr:postcode":"9210",
    "addr:street":"Bavnevangen",
    "iso:country":"DK",
    "sg:address":"Bavnevangen 32",
    "sg:city":"Aalborg S\u00d8",
    "sg:classifiers":[
        {
            "category":"Retail",
            "subcategory":"Storage",
            "type":"Services"
        }
    ],
    "sg:phone":"+45 98 14 96 09",
    "sg:postcode":"9210",
    "sg:province":"Danmark",
    "sg:tags":[
        "edb",
        "hardware",
        "-"
    ],
    "wof:name":"Bavne Data",
    "wof:placetype":"venue"
},
  "geometry": {"coordinates":[9.9440040588,57.0149078369],"type":"Point"}
}