{
  "type": "Feature",
  "properties": {
    "addr:full":"Egev\u00e6nget 9 Hanstholm Danmark 7730",
    "addr:housenumber":"9",
    "addr:postcode":"7730",
    "addr:street":"Egevaenget",
    "iso:country":"DK",
    "sg:address":"Egev\u00e6nget 9",
    "sg:city":"Hanstholm",
    "sg:orig_category":"Revisorer",
    "sg:phone":"+45 97 96 10 18",
    "sg:postcode":"7730",
    "sg:province":"Danmark",
    "wof:name":"Hanstholm Regnskabskontor",
    "wof:placetype":"venue"
},
  "geometry": {"coordinates":[8.6066236496,57.115940094],"type":"Point"}
}