{
  "type": "Feature",
  "properties": {
    "addr:full":"Enghavevej 7 Hj\u00f8rring Danmark 9800",
    "addr:housenumber":"7",
    "addr:postcode":"9800",
    "addr:street":"Enghavevej",
    "iso:country":"DK",
    "sg:address":"Enghavevej 7",
    "sg:city":"Hj\u00f8rring",
    "sg:orig_category":"Murermestre",
    "sg:phone":"+45 98 90 26 50",
    "sg:postcode":"9800",
    "sg:province":"Danmark",
    "wof:name":"Andersen, Byggefirmaet Kim",
    "wof:placetype":"venue"
},
  "geometry": {"coordinates":[9.9831857681,57.4532241821],"type":"Point"}
}