{
  "type": "Feature",
  "properties": {
    "addr:full":"S\u00f8kildevej 69 Ry Danmark 8680",
    "addr:housenumber":"69",
    "addr:postcode":"8680",
    "addr:street":"Sokildevej",
    "iso:country":"DK",
    "sg:address":"S\u00f8kildevej 69",
    "sg:city":"Ry",
    "sg:classifiers":[
        {
            "category":"Restaurant",
            "type":"Food & Drink"
        }
    ],
    "sg:phone":"+45 86 89 18 66",
    "sg:postcode":"8680",
    "sg:province":"Danmark",
    "wof:name":"S\u00f8nder Ege, Restaurant",
    "wof:placetype":"venue"
},
  "geometry": {"coordinates":[9.7593002319,56.0920562744],"type":"Point"}
}