{
  "type": "Feature",
  "properties": {
    "iso:country":"DK",
    "sg:address":"Bredgade 151",
    "sg:city":"Hurup",
    "sg:classifiers":[
        {
            "category":"Restaurant",
            "type":"Food & Drink"
        }
    ],
    "sg:phone":"+45 97 95 27 77",
    "sg:postcode":"7760",
    "sg:province":"Danmark",
    "wof:name":"Botan Restaurant",
    "wof:placetype":"venue"
},
  "geometry": {"coordinates":[8.4182500839,56.7501792908],"type":"Point"}
}