{
  "type": "Feature",
  "properties": {
    "addr:full":"Vantingevej 7  Ringe Danmark 5750",
    "addr:housenumber":"7",
    "addr:postcode":"5750",
    "addr:street":"Vantingevej",
    "iso:country":"DK",
    "sg:address":"Vantingevej 7 ",
    "sg:city":"Ringe",
    "sg:classifiers":[
        {
            "category":"Home & Garden",
            "subcategory":"Home Furnishings",
            "type":"Retail Goods"
        }
    ],
    "sg:phone":"+45 62 66 10 88",
    "sg:postcode":"5750",
    "sg:province":"Danmark",
    "sg:tags":[
        "household"
    ],
    "wof:name":"VANTINGE M\u00d8BELINDUSTRI A/S",
    "wof:placetype":"venue"
},
  "geometry": {"coordinates":[10.3894643784,55.2363700867],"type":"Point"}
}