{
  "type": "Feature",
  "properties": {
    "addr:full":"Lundg\u00e5rdcentret, Gavn\u00f8vej 4, Tj\u00f8rring Herning Danmark 7400",
    "addr:housenumber":"4",
    "addr:postcode":"7400",
    "addr:street":"Gavnovej;Tjorring",
    "iso:country":"DK",
    "sg:address":"Lundg\u00e5rdcentret, Gavn\u00f8vej 4, Tj\u00f8rring",
    "sg:city":"Herning",
    "sg:classifiers":[
        {
            "category":"Restaurant",
            "type":"Food & Drink"
        }
    ],
    "sg:phone":"+45 97 26 86 70",
    "sg:postcode":"7400",
    "sg:province":"Danmark",
    "wof:name":"Bakkens Bodega",
    "wof:placetype":"venue"
},
  "geometry": {"coordinates":[8.9768896103,56.1374168396],"type":"Point"}
}