{
  "type": "Feature",
  "properties": {
    "addr:full":"Nylandsvej 115 K\u00f8ge Danmark 4600",
    "addr:housenumber":"115",
    "addr:postcode":"4600",
    "addr:street":"Nylandsvej",
    "iso:country":"DK",
    "sg:address":"Nylandsvej 115",
    "sg:city":"K\u00f8ge",
    "sg:orig_category":"Vuggestuer",
    "sg:phone":"+45 56 65 39 26",
    "sg:postcode":"4600",
    "sg:province":"Danmark",
    "wof:name":"Lejerbo Vuggestue",
    "wof:placetype":"venue"
},
  "geometry": {"coordinates":[121.6054229736,25.0393390656],"type":"Point"}
}