{
  "type": "Feature",
  "properties": {
    "addr:full":"G\u00e5sdalsvej 12, Troldhede Videb\u00e6k Danmark 6920",
    "addr:housenumber":"12",
    "addr:postcode":"6920",
    "addr:street":"Gaasdalsvej",
    "iso:country":"DK",
    "sg:address":"G\u00e5sdalsvej 12, Troldhede",
    "sg:city":"Videb\u00e6k",
    "sg:orig_category":"El-automatik",
    "sg:phone":"+45 97 19 44 66",
    "sg:postcode":"6920",
    "sg:province":"Danmark",
    "sg:website":"www.tiautomation.dk",
    "wof:name":"T I Automation",
    "wof:placetype":"venue"
},
  "geometry": {"coordinates":[8.7436800003,55.9904136658],"type":"Point"}
}