{
  "type": "Feature",
  "properties": {
    "addr:full":"Vesterled 26 A Janderup Danmark 6851",
    "addr:housenumber":"26 a",
    "addr:postcode":"6851",
    "addr:street":"Vesterled",
    "iso:country":"DK",
    "sg:address":"Vesterled 26 A",
    "sg:city":"Janderup",
    "sg:orig_category":"Landbrug",
    "sg:phone":"+45 75 25 81 62",
    "sg:postcode":"6851",
    "sg:province":"Danmark",
    "wof:name":"Petersen, Klemmen",
    "wof:placetype":"venue"
},
  "geometry": {"coordinates":[8.3728504181,55.6240577698],"type":"Point"}
}