{
  "type": "Feature",
  "properties": {
    "iso:country":"DK",
    "sg:address":"Poststr\u00e6det 7, Skovsgaard",
    "sg:city":"Brovst",
    "sg:orig_category":"Brugsforeninger",
    "sg:phone":"+45 98 23 14 43",
    "sg:postcode":"9460",
    "sg:province":"Danmark",
    "wof:name":"Dagli'Brugsen",
    "wof:placetype":"venue"
},
  "geometry": {"coordinates":[9.5220241547,57.097366333],"type":"Point"}
}