{
  "type": "Feature",
  "properties": {
    "addr:full":"Amager Landevej 54 Kastrup Danmark 2770",
    "addr:housenumber":"54",
    "addr:postcode":"2770",
    "addr:street":"Amager Landevej",
    "iso:country":"DK",
    "sg:address":"Amager Landevej 54",
    "sg:city":"Kastrup",
    "sg:orig_category":"Advokater",
    "sg:phone":"+45 32 50 55 60",
    "sg:postcode":"2770",
    "sg:province":"Danmark",
    "sg:website":"www.ejendomsadvokaterne.dk",
    "wof:name":"M\u00f8lck, Anders Larsen & Ditlev Nielsen, Chr.",
    "wof:placetype":"venue"
},
  "geometry": {"coordinates":[12.6191072464,55.6357955933],"type":"Point"}
}