{
  "type": "Feature",
  "properties": {
    "addr:full":"Bycentret 208 Munkebo Danmark 5330",
    "addr:housenumber":"208",
    "addr:postcode":"5330",
    "addr:street":"Bycentret",
    "iso:country":"DK",
    "sg:address":"Bycentret 208",
    "sg:city":"Munkebo",
    "sg:orig_category":"Apoteker og -udsalg",
    "sg:phone":"+45 65 97 49 20",
    "sg:postcode":"5330",
    "sg:province":"Danmark",
    "wof:name":"Munkebo Apoteksudsalg",
    "wof:placetype":"venue"
},
  "geometry": {"coordinates":[10.5609579086,55.4601631165],"type":"Point"}
}