{
  "type": "Feature",
  "properties": {
    "addr:full":"Hammershusvej 16 Herning Danmark 7400",
    "addr:housenumber":"16",
    "addr:postcode":"7400",
    "addr:street":"Hammershusvej",
    "iso:country":"DK",
    "sg:address":"Hammershusvej 16",
    "sg:city":"Herning",
    "sg:orig_category":"Forlag",
    "sg:phone":"+45 97 12 84 33",
    "sg:postcode":"7400",
    "sg:province":"Danmark",
    "wof:name":"Special- P\u00e6dagogisk Forlag A/S",
    "wof:placetype":"venue"
},
  "geometry": {"coordinates":[8.9712648392,56.1552581787],"type":"Point"}
}