{
  "type": "Feature",
  "properties": {
    "addr:full":"Skovbov\u00e6nget 124 Ballerup Danmark 2750",
    "addr:housenumber":"124",
    "addr:postcode":"2750",
    "iso:country":"DK",
    "sg:address":"Skovbov\u00e6nget 124",
    "sg:city":"Ballerup",
    "sg:orig_category":"Private skoler",
    "sg:phone":"+45 44 98 82 10",
    "sg:postcode":"2750",
    "sg:province":"Danmark",
    "wof:name":"Hareskovens Lilleskole",
    "wof:placetype":"venue"
},
  "geometry": {"coordinates":[12.3880777359,55.7557106018],"type":"Point"}
}