{
  "type": "Feature",
  "properties": {
    "addr:full":"Klosterbanken 60 Slagelse Danmark 4200",
    "addr:housenumber":"60",
    "addr:postcode":"4200",
    "addr:street":"Klosterbanken",
    "iso:country":"DK",
    "sg:address":"Klosterbanken 60",
    "sg:city":"Slagelse",
    "sg:orig_category":"Advokater",
    "sg:phone":"+45 58 50 26 02",
    "sg:postcode":"4200",
    "sg:province":"Danmark",
    "sg:website":"www.net-advokaten.dk",
    "wof:name":"Nielsen, Advokat Jens Peter",
    "wof:placetype":"venue"
},
  "geometry": {"coordinates":[11.379529953,55.40442276],"type":"Point"}
}