{
  "type": "Feature",
  "properties": {
    "addr:full":"Skolevej 13, Nordby Fan\u00f8 Danmark 6720",
    "addr:housenumber":"13",
    "addr:postcode":"6720",
    "addr:street":"Skolevej",
    "iso:country":"DK",
    "sg:address":"Skolevej 13, Nordby",
    "sg:city":"Fan\u00f8",
    "sg:orig_category":"Murermestre",
    "sg:phone":"+45 75 16 21 70",
    "sg:postcode":"6720",
    "sg:province":"Danmark",
    "wof:name":"Schmidt, Brdr.",
    "wof:placetype":"venue"
},
  "geometry": {"coordinates":[8.4069461823,55.4484786987],"type":"Point"}
}