{
  "type": "Feature",
  "properties": {
    "iso:country":"DK",
    "sg:address":"Drej\u00f8gade 4",
    "sg:city":"K\u00f8benhavn \u00d8",
    "sg:orig_category":"Malermestre",
    "sg:phone":"+45 39 29 47 03",
    "sg:postcode":"2100",
    "sg:province":"Danmark",
    "wof:name":"M\u00f8ller, J\u00f8rgen",
    "wof:placetype":"venue"
},
  "geometry": {"coordinates":[99.92501068120001,34.2430114746],"type":"Point"}
}