{
  "type": "Feature",
  "properties": {
    "addr:full":"Olaf Ryes Gade 4 - 6 Kolding Danmark 6000",
    "addr:housenumber":"4 6",
    "addr:postcode":"6000",
    "addr:street":"Olaf Ryes Gade",
    "iso:country":"DK",
    "sg:address":"Olaf Ryes Gade 4 - 6",
    "sg:city":"Kolding",
    "sg:orig_category":"Autolakering",
    "sg:phone":"+45 75 52 73 52",
    "sg:postcode":"6000",
    "sg:province":"Danmark",
    "wof:name":"Termolak",
    "wof:placetype":"venue"
},
  "geometry": {"coordinates":[9.4633150101,55.4870147705],"type":"Point"}
}