{
  "type": "Feature",
  "properties": {
    "addr:full":"Jernbanegade 13 Kolding Danmark 6000",
    "addr:housenumber":"13",
    "addr:postcode":"6000",
    "addr:street":"Jernbanegade",
    "iso:country":"DK",
    "sg:address":"Jernbanegade 13",
    "sg:city":"Kolding",
    "sg:orig_category":"Diskoteker",
    "sg:phone":"+45 75 54 16 88",
    "sg:postcode":"6000",
    "sg:province":"Danmark",
    "wof:name":"Crazy Daisy Kolding ApS",
    "wof:placetype":"venue"
},
  "geometry": {"coordinates":[9.4759063721,55.4902496338],"type":"Point"}
}