{
  "type": "Feature",
  "properties": {
    "iso:country":"DK",
    "sg:address":"Reberbansgade 12 B",
    "sg:city":"Aalborg",
    "sg:orig_category":"Blomsterhandlere",
    "sg:phone":"+45 98 16 45 10",
    "sg:postcode":"9000",
    "sg:province":"Danmark",
    "wof:name":"Blomster Snedkeren",
    "wof:placetype":"venue"
},
  "geometry": {"coordinates":[9.913684845,57.0495300293],"type":"Point"}
}