{
  "type": "Feature",
  "properties": {
    "iso:country":"DK",
    "sg:address":"Amager Landevej 61, 1.",
    "sg:city":"Kastrup",
    "sg:orig_category":"Distriktspsykiatri",
    "sg:phone":"+45 32 52 20 33",
    "sg:postcode":"2770",
    "sg:province":"Danmark",
    "wof:name":"Distrikspsykiatrisk Team",
    "wof:placetype":"venue"
},
  "geometry": {"coordinates":[12.6203079224,55.6344718933],"type":"Point"}
}