{
  "type": "Feature",
  "properties": {
    "addr:full":"Resenvej 79 Skive Danmark 7800",
    "addr:housenumber":"79",
    "addr:postcode":"7800",
    "addr:street":"Resenvej",
    "iso:country":"DK",
    "sg:address":"Resenvej 79",
    "sg:city":"Skive",
    "sg:orig_category":"Revisorer",
    "sg:phone":"+45 97 52 54 11",
    "sg:postcode":"7800",
    "sg:province":"Danmark",
    "wof:name":"Dansk Revision Skive",
    "wof:placetype":"venue"
},
  "geometry": {"coordinates":[9.0283975601,56.5793647766],"type":"Point"}
}