{
  "type": "Feature",
  "properties": {
    "addr:full":"Godth\u00e5bsvej 8 A Frederiksberg Danmark 2000",
    "addr:housenumber":"8 a",
    "addr:postcode":"2000",
    "addr:street":"Godthaabsvej",
    "iso:country":"DK",
    "sg:address":"Godth\u00e5bsvej 8 A",
    "sg:city":"Frederiksberg",
    "sg:orig_category":"Skomagere",
    "sg:phone":"+45 38 86 64 98",
    "sg:postcode":"2000",
    "sg:province":"Danmark",
    "wof:name":"Sko N\u00f8gle Service",
    "wof:placetype":"venue"
},
  "geometry": {"coordinates":[12.5373821259,55.6857414246],"type":"Point"}
}