{
  "type": "Feature",
  "properties": {
    "addr:full":"Ydingvej 27, Yding \u00d8stbirk Danmark 8752",
    "addr:housenumber":"27",
    "addr:postcode":"8752",
    "addr:street":"Ydingvej",
    "iso:country":"DK",
    "sg:address":"Ydingvej 27, Yding",
    "sg:city":"\u00d8stbirk",
    "sg:orig_category":"Autoreparation og -service",
    "sg:phone":"+45 75 78 22 97",
    "sg:postcode":"8752",
    "sg:province":"Danmark",
    "wof:name":"H\u00f8jg\u00e5rdens Auto",
    "wof:placetype":"venue"
},
  "geometry": {"coordinates":[9.7709598541,56.0007743835],"type":"Point"}
}