{
  "type": "Feature",
  "properties": {
    "addr:full":"Skanderborgvej 11 Ry Danmark 8680",
    "addr:housenumber":"11",
    "addr:postcode":"8680",
    "addr:street":"Skanderborgvej",
    "iso:country":"DK",
    "sg:address":"Skanderborgvej 11",
    "sg:city":"Ry",
    "sg:orig_category":"Apoteker og -udsalg",
    "sg:phone":"+45 86 89 30 88",
    "sg:postcode":"8680",
    "sg:province":"Danmark",
    "wof:name":"Ry Apoteksudsalg",
    "wof:placetype":"venue"
},
  "geometry": {"coordinates":[9.7596645355,56.0921325684],"type":"Point"}
}