{
  "type": "Feature",
  "properties": {
    "addr:full":"Middelfartvej 131, Bolbro Odense V Danmark 5200",
    "addr:housenumber":"131",
    "addr:postcode":"5200",
    "addr:street":"Middelfartvej;Bolbro",
    "iso:country":"DK",
    "sg:address":"Middelfartvej 131, Bolbro",
    "sg:city":"Odense V",
    "sg:orig_category":"Autoforhandlere",
    "sg:phone":"+45 66 16 60 00",
    "sg:postcode":"5200",
    "sg:province":"Danmark",
    "wof:name":"Fehr & Co. A/S",
    "wof:placetype":"venue"
},
  "geometry": {"coordinates":[10.2629547119,55.4070854187],"type":"Point"}
}