{
  "type": "Feature",
  "properties": {
    "addr:full":"Havnevejen 1 S\u00f8by Danmark 5985",
    "addr:housenumber":"1",
    "addr:postcode":"5985",
    "addr:street":"Havnevejen",
    "iso:country":"DK",
    "sg:address":"Havnevejen 1",
    "sg:city":"S\u00f8by",
    "sg:orig_category":"Sparekasser",
    "sg:phone":"+45 62 58 10 08",
    "sg:postcode":"5985",
    "sg:province":"Danmark",
    "wof:name":"Amtssparekassen",
    "wof:placetype":"venue"
},
  "geometry": {"coordinates":[-78.0637512207,43.0498466492],"type":"Point"}
}