{
  "type": "Feature",
  "properties": {
    "addr:full":"Lilleg\u00e5rds Alle 13 Herlev Danmark 2730",
    "addr:housenumber":"13",
    "addr:postcode":"2730",
    "addr:street":"Lillegaards Alle",
    "iso:country":"DK",
    "sg:address":"Lilleg\u00e5rds Alle 13",
    "sg:city":"Herlev",
    "sg:orig_category":"Elektro",
    "sg:phone":"+45 44 84 27 78",
    "sg:postcode":"2730",
    "sg:province":"Danmark",
    "wof:name":"J. N. E.",
    "wof:placetype":"venue"
},
  "geometry": {"coordinates":[12.4702415466,55.7210731506],"type":"Point"}
}