{
  "type": "Feature",
  "properties": {
    "addr:full":"B\u00f8gevej 1, Taulov Fredericia Danmark 7000",
    "addr:housenumber":"1",
    "addr:postcode":"7000",
    "addr:street":"Bogevej;Taulov",
    "iso:country":"DK",
    "sg:address":"B\u00f8gevej 1, Taulov",
    "sg:city":"Fredericia",
    "sg:classifiers":[
        {
            "category":"Banks & Credit Unions",
            "subcategory":"Bank",
            "type":"Services"
        }
    ],
    "sg:phone":"+45 76 24 53 00",
    "sg:postcode":"7000",
    "sg:province":"Danmark",
    "sg:tags":[
        "banker"
    ],
    "wof:name":"BG Bank",
    "wof:placetype":"venue"
},
  "geometry": {"coordinates":[9.7591047287,55.566368103],"type":"Point"}
}