{
  "type": "Feature",
  "properties": {
    "addr:full":"Toldbodvej 9 Vejle Danmark 7100",
    "addr:housenumber":"9",
    "addr:postcode":"7100",
    "addr:street":"Toldbodvej",
    "iso:country":"DK",
    "sg:address":"Toldbodvej 9",
    "sg:city":"Vejle",
    "sg:orig_category":"Jernhandel",
    "sg:phone":"+45 75 83 44 22",
    "sg:postcode":"7100",
    "sg:province":"Danmark",
    "sg:website":"www.palleiversen.dk",
    "wof:name":"Iversen, Palle A/S",
    "wof:placetype":"venue"
},
  "geometry": {"coordinates":[9.5434894562,55.704624176],"type":"Point"}
}