{
  "type": "Feature",
  "properties": {
    "iso:country":"DK",
    "sg:address":"Skarrids\u00f8gade 40",
    "sg:city":"Jyderup",
    "sg:orig_category":"Jernbaner",
    "sg:phone":"+45 59 27 60 50",
    "sg:postcode":"4450",
    "sg:province":"Danmark",
    "wof:name":"DSB, Jyderup Station",
    "wof:placetype":"venue"
},
  "geometry": {"coordinates":[11.3990087509,55.6600151062],"type":"Point"}
}