{
  "type": "Feature",
  "properties": {
    "addr:full":"Nedergade 4 Ebeltoft Danmark 8400",
    "addr:housenumber":"4",
    "addr:postcode":"8400",
    "addr:street":"Nedergade",
    "iso:country":"DK",
    "sg:address":"Nedergade 4",
    "sg:city":"Ebeltoft",
    "sg:orig_category":"Glaskunstnere",
    "sg:phone":"+45 86 34 08 44",
    "sg:postcode":"8400",
    "sg:province":"Danmark",
    "wof:name":"Rosleff Glas",
    "wof:placetype":"venue"
},
  "geometry": {"coordinates":[10.6752157211,56.1969604492],"type":"Point"}
}