{
  "type": "Feature",
  "properties": {
    "addr:full":"Lin\u00e5vej 9 Silkeborg Danmark 8600",
    "addr:housenumber":"9",
    "addr:postcode":"8600",
    "addr:street":"Linaavej",
    "iso:country":"DK",
    "sg:address":"Lin\u00e5vej 9",
    "sg:city":"Silkeborg",
    "sg:orig_category":"Non-Classified Establishments",
    "sg:phone":"+45 86 84 56 99",
    "sg:postcode":"8600",
    "sg:province":"Danmark",
    "sg:website":"www.mia.dk",
    "wof:name":"Music Industri & Audio ApS",
    "wof:placetype":"venue"
},
  "geometry": {"coordinates":[9.6348247528,56.1559524536],"type":"Point"}
}