{
  "type": "Feature",
  "properties": {
    "addr:full":"V\u00f8lundsvej 2 Frederikssund Danmark 3600",
    "addr:housenumber":"2",
    "addr:postcode":"3600",
    "addr:street":"Volundsvej",
    "iso:country":"DK",
    "sg:address":"V\u00f8lundsvej 2",
    "sg:city":"Frederikssund",
    "sg:orig_category":"Autoforhandlere",
    "sg:phone":"+45 47 31 13 64",
    "sg:postcode":"3600",
    "sg:province":"Danmark",
    "sg:website":"www.fiat-frederikssund.dk",
    "wof:name":"Nielsens Automobiler, Gert",
    "wof:placetype":"venue"
},
  "geometry": {"coordinates":[12.0609207153,55.8493118286],"type":"Point"}
}