{
  "type": "Feature",
  "properties": {
    "addr:full":"Hestedamsgade 3 Horsens Danmark 8700",
    "addr:housenumber":"3",
    "addr:postcode":"8700",
    "addr:street":"Hestedamsgade",
    "iso:country":"DK",
    "sg:address":"Hestedamsgade 3",
    "sg:city":"Horsens",
    "sg:orig_category":"Materialister",
    "sg:phone":"+45 76 25 37 38",
    "sg:postcode":"8700",
    "sg:province":"Danmark",
    "wof:name":"Matas",
    "wof:placetype":"venue"
},
  "geometry": {"coordinates":[9.8452072144,55.8621406555],"type":"Point"}
}