{
  "type": "Feature",
  "properties": {
    "iso:country":"DK",
    "sg:address":"Skelb\u00e6k 12 ",
    "sg:city":"Snertinge",
    "sg:classifiers":[
        {
            "category":"Wholesale",
            "subcategory":"Machinery & Supplies",
            "type":"Manufacturing & Wholesale Goods"
        }
    ],
    "sg:phone":"+45 59 26 80 04",
    "sg:postcode":"4460",
    "sg:province":"Danmark",
    "sg:tags":[
        "-",
        "agriculture",
        "equipment"
    ],
    "wof:name":"SNERTINGE MASKINFORRETNING A/S",
    "wof:placetype":"venue"
},
  "geometry": {"coordinates":[11.412979126,55.7149047852],"type":"Point"}
}