{
  "type": "Feature",
  "properties": {
    "iso:country":"DK",
    "sg:address":"Holb\u00e6kvej 5",
    "sg:city":"Jyderup",
    "sg:orig_category":"Bagere",
    "sg:phone":"+45 59 27 60 80",
    "sg:postcode":"4450",
    "sg:province":"Danmark",
    "wof:name":"Guldbageren",
    "wof:placetype":"venue"
},
  "geometry": {"coordinates":[11.402683,55.66029],"type":"Point"}
}