{
  "type": "Feature",
  "properties": {
    "addr:full":"Frederiksgade 74 \u00c5rhus C Danmark 8000",
    "addr:housenumber":"74",
    "addr:postcode":"8000",
    "addr:street":"Frederiksgade",
    "iso:country":"DK",
    "sg:address":"Frederiksgade 74",
    "sg:city":"\u00c5rhus C",
    "sg:orig_category":"Fotokopiering",
    "sg:phone":"+45 86 18 35 55",
    "sg:postcode":"8000",
    "sg:province":"Danmark",
    "wof:name":"With Kopicenter ApS",
    "wof:placetype":"venue"
},
  "geometry": {"coordinates":[10.203373909,56.1542167664],"type":"Point"}
}