{
  "type": "Feature",
  "properties": {
    "addr:full":"Rosenv\u00e6nget 3 Horsens Danmark 8700",
    "addr:housenumber":"3",
    "addr:postcode":"8700",
    "addr:street":"Rosenvaenget",
    "iso:country":"DK",
    "sg:address":"Rosenv\u00e6nget 3",
    "sg:city":"Horsens",
    "sg:orig_category":"Malermestre",
    "sg:phone":"+45 75 64 68 61",
    "sg:postcode":"8700",
    "sg:province":"Danmark",
    "wof:name":"Pedersen, Malerfirma Charles",
    "wof:placetype":"venue"
},
  "geometry": {"coordinates":[9.8432445526,55.8621063232],"type":"Point"}
}