{
  "type": "Feature",
  "properties": {
    "addr:full":"Assensvej 249 Millinge Danmark 5642",
    "addr:housenumber":"249",
    "addr:postcode":"5642",
    "addr:street":"Assensvej",
    "iso:country":"DK",
    "sg:address":"Assensvej 249",
    "sg:city":"Millinge",
    "sg:orig_category":"Brugsforeninger",
    "sg:phone":"+45 62 61 94 94",
    "sg:postcode":"5642",
    "sg:province":"Danmark",
    "wof:name":"Dagli' Brugsen",
    "wof:placetype":"venue"
},
  "geometry": {"coordinates":[10.2102451324,55.1308174133],"type":"Point"}
}