{
  "type": "Feature",
  "properties": {
    "addr:full":"Paludan-M\u00fcllers Vej 227 \u00c5rhus N Danmark 8200",
    "addr:housenumber":"227",
    "addr:postcode":"8200",
    "addr:street":"Paludan-Muellers Vej",
    "iso:country":"DK",
    "sg:address":"Paludan-M\u00fcllers Vej 227",
    "sg:city":"\u00c5rhus N",
    "sg:orig_category":"Faglige organisationer og foreninger",
    "sg:phone":"+45 87 39 20 40",
    "sg:postcode":"8200",
    "sg:province":"Danmark",
    "wof:name":"\u00c5rhus 1601 NNF Slagterigruppen",
    "wof:placetype":"venue"
},
  "geometry": {"coordinates":[4.9393601418,49.7092018127],"type":"Point"}
}