{
  "type": "Feature",
  "properties": {
    "addr:full":"Kongens Nytorv 34 K\u00f8benhavn Danmark 1050",
    "addr:housenumber":"34",
    "addr:postcode":"1050",
    "addr:street":"Kongens Nytorv",
    "iso:country":"DK",
    "sg:address":"Kongens Nytorv 34",
    "sg:city":"K\u00f8benhavn",
    "sg:classifiers":[
        {
            "category":"Restaurant",
            "type":"Food & Drink"
        }
    ],
    "sg:phone":"+45 33 37 06 45",
    "sg:postcode":"1050",
    "sg:province":"Danmark",
    "sg:website":"www.remmen.dk",
    "wof:name":"Restaurant Wiinblad",
    "wof:placetype":"venue"
},
  "geometry": {"coordinates":[12.5860204697,55.6806793213],"type":"Point"}
}