{
  "type": "Feature",
  "properties": {
    "addr:full":"Bakkensbro 6, Ullerup S\u00f8nderborg Danmark 6400",
    "addr:housenumber":"6",
    "addr:postcode":"6400",
    "addr:street":"Bakkensbro",
    "iso:country":"DK",
    "sg:address":"Bakkensbro 6, Ullerup",
    "sg:city":"S\u00f8nderborg",
    "sg:orig_category":"Kommunale folkeskoler",
    "sg:phone":"+45 74 46 12 03",
    "sg:postcode":"6400",
    "sg:province":"Danmark",
    "sg:website":"www.bakkensbro-skole.dk",
    "wof:name":"Bakkensbro Skole",
    "wof:placetype":"venue"
},
  "geometry": {"coordinates":[9.7899465561,54.9100151062],"type":"Point"}
}