{
  "type": "Feature",
  "properties": {
    "iso:country":"DK",
    "sg:address":"v/ Hanne Andersen, Toftev\u00e6nget 16, H\u00f8jby",
    "sg:city":"Odense S",
    "sg:orig_category":"\u00c3\u02dcvrig fritidsundervisning",
    "sg:phone":"+45 65 95 89 72",
    "sg:postcode":"5260",
    "sg:province":"Danmark",
    "wof:name":"3V-Skolen",
    "wof:placetype":"venue"
},
  "geometry": {"coordinates":[10.3157806396,55.3122825623],"type":"Point"}
}