{
  "type": "Feature",
  "properties": {
    "addr:full":"Sct. Laurentii Vej 70 Skagen Danmark 9990",
    "addr:housenumber":"70",
    "addr:postcode":"9990",
    "addr:street":"Sct. Laurentii Vej",
    "iso:country":"DK",
    "sg:address":"Sct. Laurentii Vej 70",
    "sg:city":"Skagen",
    "sg:orig_category":"Tandteknikere, Kliniske",
    "sg:phone":"+45 98 44 62 28",
    "sg:postcode":"9990",
    "sg:province":"Danmark",
    "wof:name":"Dall, Jytte",
    "wof:placetype":"venue"
},
  "geometry": {"coordinates":[10.5855722427,57.7211647034],"type":"Point"}
}