{
  "type": "Feature",
  "properties": {
    "addr:full":"Vesthavnsvej 21 Fredericia Danmark 7000",
    "addr:housenumber":"21",
    "addr:postcode":"7000",
    "addr:street":"Vesthavnsvej",
    "iso:country":"DK",
    "sg:address":"Vesthavnsvej 21",
    "sg:city":"Fredericia",
    "sg:orig_category":"Pakhuse",
    "sg:phone":"+45 76 20 50 20",
    "sg:postcode":"7000",
    "sg:province":"Danmark",
    "sg:website":"www.jms.dk",
    "wof:name":"Fredericia Havnelager",
    "wof:placetype":"venue"
},
  "geometry": {"coordinates":[9.7456111908,55.5601921082],"type":"Point"}
}