{
  "type": "Feature",
  "properties": {
    "addr:full":"Skovballevej 62, T\u00e5singe Svendborg Danmark 5700",
    "addr:housenumber":"62",
    "addr:postcode":"5700",
    "addr:street":"Skovballevej;Taasinge",
    "iso:country":"DK",
    "sg:address":"Skovballevej 62, T\u00e5singe",
    "sg:city":"Svendborg",
    "sg:orig_category":"Autoreparation og -service",
    "sg:phone":"+45 62 54 10 73",
    "sg:postcode":"5700",
    "sg:province":"Danmark",
    "wof:name":"Pytlick, Per",
    "wof:placetype":"venue"
},
  "geometry": {"coordinates":[10.6065101624,55.0595970154],"type":"Point"}
}