{
  "type": "Feature",
  "properties": {
    "addr:full":"Adelgade 26 A Nysted Danmark 4880",
    "addr:housenumber":"26 a",
    "addr:postcode":"4880",
    "addr:street":"Adelgade",
    "iso:country":"DK",
    "sg:address":"Adelgade 26 A",
    "sg:city":"Nysted",
    "sg:orig_category":"Optikere",
    "sg:phone":"+45 54 87 23 16",
    "sg:postcode":"4880",
    "sg:province":"Danmark",
    "wof:name":"S\u00f8rens Briller",
    "wof:placetype":"venue"
},
  "geometry": {"coordinates":[11.7284231186,54.6686248779],"type":"Point"}
}