{
  "type": "Feature",
  "properties": {
    "addr:full":"Christiansvej 38 Hjallerup Danmark 9320",
    "addr:housenumber":"38",
    "addr:postcode":"9320",
    "addr:street":"Christiansvej",
    "iso:country":"DK",
    "sg:address":"Christiansvej 38",
    "sg:city":"Hjallerup",
    "sg:classifiers":[
        {
            "category":"Taxi",
            "type":"Transportation"
        }
    ],
    "sg:phone":"+45 98 28 10 73",
    "sg:postcode":"9320",
    "sg:province":"Danmark",
    "wof:name":"\u00d8stergaards Biler",
    "wof:placetype":"venue"
},
  "geometry": {"coordinates":[10.1413221359,57.1639671326],"type":"Point"}
}