{
  "type": "Feature",
  "properties": {
    "addr:full":"Sognepr\u00e6st: Jens Jakobsen (K/B), Teglg\u00e5rdsvej 3 Bogense Danmark 5400",
    "addr:housenumber":"3",
    "addr:postcode":"5400",
    "addr:street":"Teglgaardsvej",
    "iso:country":"DK",
    "sg:address":"Sognepr\u00e6st: Jens Jakobsen (K/B), Teglg\u00e5rdsvej 3",
    "sg:city":"Bogense",
    "sg:orig_category":"Kirkesogne",
    "sg:phone":"+45 64 81 10 21",
    "sg:postcode":"5400",
    "sg:province":"Danmark",
    "wof:name":"Bogense sogn",
    "wof:placetype":"venue"
},
  "geometry": {"coordinates":[10.0943098068,55.5637893677],"type":"Point"}
}