{
  "type": "Feature",
  "properties": {
    "addr:full":"Bog\u00f8v\u00e6nget 26, True Tilst Danmark 8381",
    "addr:housenumber":"26",
    "addr:postcode":"8381",
    "addr:street":"Bogovaenget;True",
    "iso:country":"DK",
    "sg:address":"Bog\u00f8v\u00e6nget 26, True",
    "sg:city":"Tilst",
    "sg:orig_category":"Pressebureauer",
    "sg:phone":"+45 86 24 77 17",
    "sg:postcode":"8381",
    "sg:province":"Danmark",
    "wof:name":"Science Contact",
    "wof:placetype":"venue"
},
  "geometry": {"coordinates":[10.1078147888,56.1882019043],"type":"Point"}
}