{
  "type": "Feature",
  "properties": {
    "addr:full":"Refshalevej 49 Maribo Danmark 4930",
    "addr:housenumber":"49",
    "addr:postcode":"4930",
    "addr:street":"Refshalevej",
    "iso:country":"DK",
    "sg:address":"Refshalevej 49",
    "sg:city":"Maribo",
    "sg:orig_category":"Diners transportables",
    "sg:phone":"+45 54 78 07 62",
    "sg:postcode":"4930",
    "sg:province":"Danmark",
    "wof:name":"Jensen, Skjold",
    "wof:placetype":"venue"
},
  "geometry": {"coordinates":[11.5097131729,54.770652771],"type":"Point"}
}