{
  "type": "Feature",
  "properties": {
    "addr:full":"St\u00f8berivej 5 - 7, Ulstrup G\u00f8rlev Danmark 4281",
    "addr:housenumber":"5 7",
    "addr:postcode":"4281",
    "addr:street":"Stoberivej",
    "iso:country":"DK",
    "sg:address":"St\u00f8berivej 5 - 7, Ulstrup",
    "sg:city":"G\u00f8rlev",
    "sg:orig_category":"Fliser",
    "sg:phone":"+45 58 85 65 01",
    "sg:postcode":"4281",
    "sg:province":"Danmark",
    "sg:website":"www.bergs-beton.dk",
    "wof:name":"Berg's Betonvarer",
    "wof:placetype":"venue"
},
  "geometry": {"coordinates":[11.1143903732,55.5207710266],"type":"Point"}
}