{
  "type": "Feature",
  "properties": {
    "addr:full":"Skolevej 9-11 Aakirkeby Danmark 3720",
    "addr:housenumber":"9-11",
    "addr:postcode":"3720",
    "addr:street":"Skolevej",
    "iso:country":"DK",
    "sg:address":"Skolevej 9-11",
    "sg:city":"Aakirkeby",
    "sg:orig_category":"Integrerede institutioner",
    "sg:phone":"+45 56 97 49 40",
    "sg:postcode":"3720",
    "sg:province":"Danmark",
    "wof:name":"Legestedet",
    "wof:placetype":"venue"
},
  "geometry": {"coordinates":[14.9158096313,55.072719574],"type":"Point"}
}