{
  "type": "Feature",
  "properties": {
    "addr:full":"Carstensgade 95 T\u00f8nder Danmark 6270",
    "addr:housenumber":"95",
    "addr:postcode":"6270",
    "addr:street":"Carstensgade",
    "iso:country":"DK",
    "sg:address":"Carstensgade 95",
    "sg:city":"T\u00f8nder",
    "sg:orig_category":"Begravelsesforretninger",
    "sg:phone":"+45 74 72 41 42",
    "sg:postcode":"6270",
    "sg:province":"Danmark",
    "wof:name":"T\u00f8nder/H\u00f8jer Begravelsesforretning",
    "wof:placetype":"venue"
},
  "geometry": {"coordinates":[8.8797273636,54.9475593567],"type":"Point"}
}