{
  "type": "Feature",
  "properties": {
    "addr:full":"Falkevej 3 Silkeborg Danmark 8600",
    "addr:housenumber":"3",
    "addr:postcode":"8600",
    "addr:street":"Falkevej",
    "iso:country":"DK",
    "sg:address":"Falkevej 3",
    "sg:city":"Silkeborg",
    "sg:orig_category":"Kiosker",
    "sg:phone":"+45 86 82 37 48",
    "sg:postcode":"8600",
    "sg:province":"Danmark",
    "wof:name":"Sygehuskiosken",
    "wof:placetype":"venue"
},
  "geometry": {"coordinates":[9.5596313477,56.1698989868],"type":"Point"}
}