{
  "type": "Feature",
  "properties": {
    "addr:full":"Lundevej 36 Kalundborg Danmark 4400",
    "addr:housenumber":"36",
    "addr:postcode":"4400",
    "addr:street":"Lundevej",
    "iso:country":"DK",
    "sg:address":"Lundevej 36",
    "sg:city":"Kalundborg",
    "sg:orig_category":"Plejecentre",
    "sg:phone":"+45 59 55 09 20",
    "sg:postcode":"4400",
    "sg:province":"Danmark",
    "wof:name":"Plejecenter Solg\u00e5rden",
    "wof:placetype":"venue"
},
  "geometry": {"coordinates":[11.0732488632,55.6814689636],"type":"Point"}
}