{
  "type": "Feature",
  "properties": {
    "addr:full":"Sct. Laurentii Vej 41 Skagen Danmark 9990",
    "addr:housenumber":"41",
    "addr:postcode":"9990",
    "addr:street":"Sct. Laurentii Vej",
    "iso:country":"DK",
    "sg:address":"Sct. Laurentii Vej 41",
    "sg:city":"Skagen",
    "sg:orig_category":"Musik og sang",
    "sg:phone":"+45 98 44 13 06",
    "sg:postcode":"9990",
    "sg:province":"Danmark",
    "sg:website":"www.skaw.dk/foldens-hotel",
    "wof:name":"Visev\u00e6rtshuset",
    "wof:placetype":"venue"
},
  "geometry": {"coordinates":[10.5916566849,57.7231025696],"type":"Point"}
}