{
  "type": "Feature",
  "properties": {
    "iso:country":"DK",
    "sg:address":"\u00d8stergade 136",
    "sg:city":"Horsens",
    "sg:orig_category":"Reklamebureauer",
    "sg:phone":"+45 75 60 21 60",
    "sg:postcode":"8700",
    "sg:province":"Danmark",
    "wof:name":"La Cour Pr.",
    "wof:placetype":"venue"
},
  "geometry": {"coordinates":[9.8675098419,55.8663711548],"type":"Point"}
}