{
  "type": "Feature",
  "properties": {
    "addr:full":"v/ Alfred Christensen, Bovrup Kirkevej 8, Bovrup Aabenraa Danmark 6200",
    "addr:housenumber":"8",
    "addr:postcode":"6200",
    "addr:street":"Bovrup Kirkevej;Bovrup",
    "iso:country":"DK",
    "sg:address":"v/ Alfred Christensen, Bovrup Kirkevej 8, Bovrup",
    "sg:city":"Aabenraa",
    "sg:orig_category":"Teatre",
    "sg:phone":"+45 74 68 05 09",
    "sg:postcode":"6200",
    "sg:province":"Danmark",
    "wof:name":"Bovrup Seniorteater",
    "wof:placetype":"venue"
},
  "geometry": {"coordinates":[9.4213867188,55.0449562073],"type":"Point"}
}