{
  "type": "Feature",
  "properties": {
    "addr:full":"Skodsborg Strandvej 117 A Skodsborg Danmark 2942",
    "addr:housenumber":"117 a",
    "addr:postcode":"2942",
    "addr:street":"Skodsborg Strandvej",
    "iso:country":"DK",
    "sg:address":"Skodsborg Strandvej 117 A",
    "sg:city":"Skodsborg",
    "sg:orig_category":"Filmproduktion",
    "sg:phone":"+45 45 80 22 57",
    "sg:postcode":"2942",
    "sg:province":"Danmark",
    "wof:name":"Bjerring, Mette",
    "wof:placetype":"venue"
},
  "geometry": {"coordinates":[12.57401371,55.8181610107],"type":"Point"}
}