{
  "type": "Feature",
  "properties": {
    "addr:full":"Aastoften 26, Svogerslev Roskilde Danmark 4000",
    "addr:housenumber":"26",
    "addr:postcode":"4000",
    "addr:street":"Aastoften;Svogerslev",
    "iso:country":"DK",
    "sg:address":"Aastoften 26, Svogerslev",
    "sg:city":"Roskilde",
    "sg:orig_category":"Revisorer",
    "sg:phone":"+45 46 38 38 18",
    "sg:postcode":"4000",
    "sg:province":"Danmark",
    "wof:name":"Mogensen, Jette",
    "wof:placetype":"venue"
},
  "geometry": {"coordinates":[12.0909376144,55.6404838562],"type":"Point"}
}