{
  "type": "Feature",
  "properties": {
    "addr:full":"Klosterparkvej 16 Kalundborg Danmark 4400",
    "addr:housenumber":"16",
    "addr:postcode":"4400",
    "addr:street":"Klosterparkvej",
    "iso:country":"DK",
    "sg:address":"Klosterparkvej 16",
    "sg:city":"Kalundborg",
    "sg:orig_category":"Kirkesogne",
    "sg:phone":"+45 59 51 04 01",
    "sg:postcode":"4400",
    "sg:province":"Danmark",
    "wof:name":"Vor Frue Sogns Kirkekontor",
    "wof:placetype":"venue"
},
  "geometry": {"coordinates":[11.0866851807,55.6833496094],"type":"Point"}
}