{
  "type": "Feature",
  "properties": {
    "addr:full":"\u00d8stergade 5 Ejstrupholm Danmark 7361",
    "addr:housenumber":"5",
    "addr:postcode":"7361",
    "addr:street":"Ostergade",
    "iso:country":"DK",
    "sg:address":"\u00d8stergade 5",
    "sg:city":"Ejstrupholm",
    "sg:orig_category":"Sko",
    "sg:phone":"+45 75 77 20 05",
    "sg:postcode":"7361",
    "sg:province":"Danmark",
    "wof:name":"Orup Sko",
    "wof:placetype":"venue"
},
  "geometry": {"coordinates":[9.2909784317,55.983921051],"type":"Point"}
}