{
  "type": "Feature",
  "properties": {
    "addr:full":"\u00d8sterh\u00f8j Bygade 123 B Ballerup Danmark 2750",
    "addr:housenumber":"123 b",
    "addr:postcode":"2750",
    "addr:street":"Osterhoj Bygade",
    "iso:country":"DK",
    "sg:address":"\u00d8sterh\u00f8j Bygade 123 B",
    "sg:city":"Ballerup",
    "sg:orig_category":"Pizzeriaer",
    "sg:phone":"+45 44 66 13 73",
    "sg:postcode":"2750",
    "sg:province":"Danmark",
    "wof:name":"Lady-Vagabonden",
    "wof:placetype":"venue"
},
  "geometry": {"coordinates":[12.361000061,55.7301216125],"type":"Point"}
}