{
  "type": "Feature",
  "properties": {
    "addr:full":"Fmd.: Lars Aage Jensen, Langebjerg 10, 3. th N\u00e6rum Danmark 2850",
    "addr:housenumber":"10 3 th",
    "addr:postcode":"2850",
    "addr:street":"Aage;Langebjerg;Danmark",
    "iso:country":"DK",
    "sg:address":"Fmd.: Lars Aage Jensen, Langebjerg 10, 3. th",
    "sg:city":"N\u00e6rum",
    "sg:orig_category":"Grundejerforeninger",
    "sg:phone":"+45 45 80 14 98",
    "sg:postcode":"2850",
    "sg:province":"Danmark",
    "wof:name":"Egevang Syd Ejerforening",
    "wof:placetype":"venue"
},
  "geometry": {"coordinates":[11.5263500214,55.3640594482],"type":"Point"}
}