{
  "type": "Feature",
  "properties": {
    "addr:full":"Rye Gade 14, Rye Kirke S\u00e5by Danmark 4060",
    "addr:housenumber":"14",
    "addr:postcode":"4060",
    "addr:street":"Rye Gade;Rye",
    "iso:country":"DK",
    "sg:address":"Rye Gade 14, Rye",
    "sg:city":"Kirke S\u00e5by",
    "sg:classifiers":[
        {
            "category":"Home & Garden",
            "subcategory":"Home Furnishings",
            "type":"Retail Goods"
        }
    ],
    "sg:phone":"+45 28 44 25 46",
    "sg:postcode":"4060",
    "sg:province":"Danmark",
    "sg:tags":[
        "gardiner"
    ],
    "wof:name":"Gardin Ringen",
    "wof:placetype":"venue"
},
  "geometry": {"coordinates":[-70.7727432251,43.0119018555],"type":"Point"}
}