{
  "type": "Feature",
  "properties": {
    "iso:country":"DK",
    "sg:address":"S\u00f8borg Hovedgade 119",
    "sg:city":"S\u00f8borg",
    "sg:orig_category":"Boghandlere",
    "sg:phone":"+45 39 56 04 56",
    "sg:postcode":"2860",
    "sg:province":"Danmark",
    "sg:website":"www.soeborghovedgade.dk/kristensen",
    "wof:name":"Kristensen, Klaus",
    "wof:placetype":"venue"
},
  "geometry": {"coordinates":[-101.37712097169999,35.6836738586],"type":"Point"}
}