{
  "type": "Feature",
  "properties": {
    "iso:country":"DK",
    "sg:address":"Hasseris Bymidte 17",
    "sg:city":"Aalborg",
    "sg:orig_category":"Briller",
    "sg:phone":"+45 96 34 00 88",
    "sg:postcode":"9000",
    "sg:province":"Danmark",
    "wof:name":"Hasseris Optik",
    "wof:placetype":"venue"
},
  "geometry": {"coordinates":[9.8830623627,57.0365180969],"type":"Point"}
}