{
  "type": "Feature",
  "properties": {
    "addr:full":"Kulturforvaltningen, Torvegade 24, 3. Slagelse Danmark 4200",
    "addr:housenumber":"24 3",
    "addr:postcode":"4200",
    "addr:street":"Kulturforvaltningen Torvegade",
    "iso:country":"DK",
    "sg:address":"Kulturforvaltningen, Torvegade 24, 3.",
    "sg:city":"Slagelse",
    "sg:orig_category":"Dagplejeformidling",
    "sg:phone":"+45 58 52 36 00",
    "sg:postcode":"4200",
    "sg:province":"Danmark",
    "wof:name":"Dagplejeformidlingen",
    "wof:placetype":"venue"
},
  "geometry": {"coordinates":[11.3569850922,55.4050865173],"type":"Point"}
}