{
  "type": "Feature",
  "properties": {
    "iso:country":"DK",
    "sg:address":"Nibevej 40",
    "sg:city":"Aalborg SV",
    "sg:orig_category":"Isolering",
    "sg:phone":"+45 70 12 11 66",
    "sg:postcode":"9200",
    "sg:province":"Danmark",
    "sg:website":"www.sw.aalborg.rockwool.dk",
    "wof:name":"Simonsen & Wendt A/S",
    "wof:placetype":"venue"
},
  "geometry": {"coordinates":[9.8756542206,57.0069885254],"type":"Point"}
}