{
  "type": "Feature",
  "properties": {
    "iso:country":"DK",
    "sg:address":"v/ Rene Simonsen, Hold-An Vej 178",
    "sg:city":"Ballerup",
    "sg:orig_category":"Hobbybetonede foreninger",
    "sg:phone":"+45 44 47 05 44",
    "sg:postcode":"2750",
    "sg:province":"Danmark",
    "sg:website":"www.volvo-pv.dk",
    "wof:name":"Dansk Volvo PV-Klub",
    "wof:placetype":"venue"
},
  "geometry": {"coordinates":[12.361000061,55.7301216125],"type":"Point"}
}