{
  "type": "Feature",
  "properties": {
    "addr:full":"K\u00f8gevej 7 Klippinge Danmark 4672",
    "addr:housenumber":"7",
    "addr:postcode":"4672",
    "addr:street":"Kogevej",
    "iso:country":"DK",
    "sg:address":"K\u00f8gevej 7",
    "sg:city":"Klippinge",
    "sg:orig_category":"Antikviteter",
    "sg:phone":"+45 56 57 80 80",
    "sg:postcode":"4672",
    "sg:province":"Danmark",
    "wof:name":"Antikg\u00e5rden",
    "wof:placetype":"venue"
},
  "geometry": {"coordinates":[12.3271865845,55.3490257263],"type":"Point"}
}