{
  "type": "Feature",
  "properties": {
    "addr:full":"Herredsvejen 22 Sorring Danmark 8641",
    "addr:housenumber":"22",
    "addr:postcode":"8641",
    "addr:street":"Herredsvejen",
    "iso:country":"DK",
    "sg:address":"Herredsvejen 22",
    "sg:city":"Sorring",
    "sg:orig_category":"Autoreparation og -service",
    "sg:phone":"+45 86 95 75 63",
    "sg:postcode":"8641",
    "sg:province":"Danmark",
    "wof:name":"Sorring Autotrim",
    "wof:placetype":"venue"
},
  "geometry": {"coordinates":[9.7624292374,56.1933631897],"type":"Point"}
}