{
  "type": "Feature",
  "properties": {
    "addr:full":"Eskildsgade 13-15 K\u00f8benhavn Danmark 1657",
    "addr:housenumber":"13-15",
    "addr:postcode":"1657",
    "addr:street":"Eskildsgade",
    "iso:country":"DK",
    "sg:address":"Eskildsgade 13-15",
    "sg:city":"K\u00f8benhavn",
    "sg:classifiers":[
        {
            "category":"Restaurant",
            "type":"Food & Drink"
        }
    ],
    "sg:phone":"+45 33 31 04 14",
    "sg:postcode":"1657",
    "sg:province":"Danmark",
    "wof:name":"Restaurant Afrodit",
    "wof:placetype":"venue"
},
  "geometry": {"coordinates":[12.557100296,55.670501709],"type":"Point"}
}