{
  "type": "Feature",
  "properties": {
    "addr:full":"Niels Jernes Vej 2 - 4 Aalborg \u00d8 Danmark 9220",
    "addr:housenumber":"2 4",
    "addr:postcode":"9220",
    "addr:street":"Niels Jernes Vej;Danmark",
    "iso:country":"DK",
    "sg:address":"Niels Jernes Vej 2 - 4",
    "sg:city":"Aalborg \u00d8",
    "sg:orig_category":"INGENI\u00c3\u02dcRER",
    "sg:phone":"+45 96 35 08 00",
    "sg:postcode":"9220",
    "sg:province":"Danmark",
    "sg:website":"www.force.dk",
    "wof:name":"Force Instituttet",
    "wof:placetype":"venue"
},
  "geometry": {"coordinates":[9.9880418777,57.0130081177],"type":"Point"}
}