{
  "type": "Feature",
  "properties": {
    "addr:full":"Tiendeladen 7, Postboks 1363 9100",
    "addr:housenumber":"7;1363",
    "addr:postcode":"9100",
    "addr:street":"Tiendeladen",
    "iso:country":"DK",
    "sg:address":"Tiendeladen 7, Postboks 1363",
    "sg:orig_category":"Advokater",
    "sg:phone":"+45 98 10 20 15",
    "sg:postcode":"9100",
    "wof:name":"Madsen, Kristian H\u00f8jgaard",
    "wof:placetype":"venue"
},
  "geometry": {"coordinates":[9.9162597656,57.0493583679],"type":"Point"}
}