{
  "type": "Feature",
  "properties": {
    "addr:full":"Si\u00f8v\u00e6nget 9, Sk\u00e6rb\u00e6k Fredericia Danmark 7000",
    "addr:housenumber":"9",
    "addr:postcode":"7000",
    "addr:street":"Siovaenget",
    "iso:country":"DK",
    "sg:address":"Si\u00f8v\u00e6nget 9, Sk\u00e6rb\u00e6k",
    "sg:city":"Fredericia",
    "sg:orig_category":"Fodplejere",
    "sg:phone":"+45 75 56 25 30",
    "sg:postcode":"7000",
    "sg:province":"Danmark",
    "wof:name":"Petersen, Margit",
    "wof:placetype":"venue"
},
  "geometry": {"coordinates":[9.7591047287,55.566368103],"type":"Point"}
}