{
  "type": "Feature",
  "properties": {
    "addr:full":"Fmd.: J\u00f8rgen Rasmussen, Tambosundvej 6 Aalborg \u00d8 Danmark 9220",
    "addr:housenumber":"6",
    "addr:postcode":"9220",
    "addr:street":"Tambosundvej;Danmark",
    "iso:country":"DK",
    "sg:address":"Fmd.: J\u00f8rgen Rasmussen, Tambosundvej 6",
    "sg:city":"Aalborg \u00d8",
    "sg:orig_category":"Borger- og beboerforeninger",
    "sg:postcode":"9220",
    "sg:province":"Danmark",
    "wof:name":"Himmerland afd. 22",
    "wof:placetype":"venue"
},
  "geometry": {"coordinates":[10.0031700134,57.0515899658],"type":"Point"}
}