{
  "type": "Feature",
  "properties": {
    "addr:full":"B\u00f8geparken 80, 4. tv. Odense N\u00d8 Danmark 5240",
    "addr:housenumber":"80 4 tv.",
    "addr:postcode":"5240",
    "addr:street":"Bogeparken",
    "iso:country":"DK",
    "sg:address":"B\u00f8geparken 80, 4. tv.",
    "sg:city":"Odense N\u00d8",
    "sg:orig_category":"Gaveartikler",
    "sg:phone":"+45 66 10 42 46",
    "sg:postcode":"5240",
    "sg:province":"Danmark",
    "wof:name":"\u00d8stens Have",
    "wof:placetype":"venue"
},
  "geometry": {"coordinates":[10.444185257,55.4261131287],"type":"Point"}
}