{
  "type": "Feature",
  "properties": {
    "iso:country":"DK",
    "sg:address":"Vester\u00e5 9",
    "sg:city":"Aalborg",
    "sg:orig_category":"Antikviteter",
    "sg:phone":"+45 98 11 58 07",
    "sg:postcode":"9000",
    "sg:province":"Danmark",
    "wof:name":"Larsen, Ole Buus",
    "wof:placetype":"venue"
},
  "geometry": {"coordinates":[9.9178647995,57.0503463745],"type":"Point"}
}