{
  "type": "Feature",
  "properties": {
    "addr:full":"Strandmarksvej 10 Hvidovre Danmark 2650",
    "addr:housenumber":"10",
    "addr:postcode":"2650",
    "addr:street":"Strandmarksvej",
    "iso:country":"DK",
    "sg:address":"Strandmarksvej 10",
    "sg:city":"Hvidovre",
    "sg:orig_category":"Autoforhandlere",
    "sg:phone":"+45 36 49 65 23",
    "sg:postcode":"2650",
    "sg:province":"Danmark",
    "wof:name":"Pedersen, Bent",
    "wof:placetype":"venue"
},
  "geometry": {"coordinates":[12.4838466644,55.6276016235],"type":"Point"}
}