{
  "type": "Feature",
  "properties": {
    "iso:country":"DK",
    "sg:address":"Abterpvej 15",
    "sg:city":"Bredebro",
    "sg:orig_category":"Korn og foderstoffer",
    "sg:phone":"+45 74 71 16 33",
    "sg:postcode":"6261",
    "sg:province":"Danmark",
    "wof:name":"S\u00f8nniksen A/S, Hans",
    "wof:placetype":"venue"
},
  "geometry": {"coordinates":[8.8064088821,55.0685997009],"type":"Point"}
}