{
  "type": "Feature",
  "properties": {
    "addr:full":"Lucernemarken 14 A, Resen Struer Danmark 7600",
    "addr:housenumber":"14 a",
    "addr:postcode":"7600",
    "addr:street":"Lucernemarken",
    "iso:country":"DK",
    "sg:address":"Lucernemarken 14 A, Resen",
    "sg:city":"Struer",
    "sg:orig_category":"Private- og friskoler",
    "sg:phone":"+45 97 86 18 24",
    "sg:postcode":"7600",
    "sg:province":"Danmark",
    "wof:name":"Resen Friskole",
    "wof:placetype":"venue"
},
  "geometry": {"coordinates":[8.5946903229,56.491191864],"type":"Point"}
}