{
  "type": "Feature",
  "properties": {
    "addr:full":"Servicebutikken, R\u00e5dhuset, Klostergade 20 A Nakskov Danmark 4900",
    "addr:housenumber":"20 a",
    "addr:postcode":"4900",
    "addr:street":"Klostergade",
    "iso:country":"DK",
    "sg:address":"Servicebutikken, R\u00e5dhuset, Klostergade 20 A",
    "sg:city":"Nakskov",
    "sg:orig_category":"Dagplejeformidling",
    "sg:phone":"+45 54 97 02 00",
    "sg:postcode":"4900",
    "sg:province":"Danmark",
    "wof:name":"Dagplejeformidlingen",
    "wof:placetype":"venue"
},
  "geometry": {"coordinates":[11.1359500885,54.8330116272],"type":"Point"}
}