{
  "type": "Feature",
  "properties": {
    "addr:full":"Vestergade 20 R\u00f8dekro Danmark 6230",
    "addr:housenumber":"20",
    "addr:postcode":"6230",
    "addr:street":"Vestergade",
    "iso:country":"DK",
    "sg:address":"Vestergade 20",
    "sg:city":"R\u00f8dekro",
    "sg:orig_category":"Biblioteker",
    "sg:phone":"+45 74 66 26 23",
    "sg:postcode":"6230",
    "sg:province":"Danmark",
    "sg:website":"www.roedekrobib.dk",
    "wof:name":"R\u00f8dekro Bibliotek",
    "wof:placetype":"venue"
},
  "geometry": {"coordinates":[9.5455904007,56.1682090759],"type":"Point"}
}