{
  "type": "Feature",
  "properties": {
    "addr:full":"Palnatokesvej 2 Odense C Danmark 5000",
    "addr:housenumber":"2",
    "addr:postcode":"5000",
    "addr:street":"Palnatokesvej",
    "iso:country":"DK",
    "sg:address":"Palnatokesvej 2",
    "sg:city":"Odense C",
    "sg:orig_category":"Pizzeriaer",
    "sg:phone":"+45 66 13 90 06",
    "sg:postcode":"5000",
    "sg:province":"Danmark",
    "wof:name":"Dino, Pizza",
    "wof:placetype":"venue"
},
  "geometry": {"coordinates":[10.4053249359,55.3988838196],"type":"Point"}
}