{
  "type": "Feature",
  "properties": {
    "iso:country":"DK",
    "sg:address":"Vinbjergvej 15",
    "sg:city":"Vejle \u00d8",
    "sg:orig_category":"Zoneterapeuter",
    "sg:phone":"+45 75 71 16 46",
    "sg:postcode":"7120",
    "sg:province":"Danmark",
    "wof:name":"Jettes Klinik",
    "wof:placetype":"venue"
},
  "geometry": {"coordinates":[9.6118173599,55.7115058899],"type":"Point"}
}