{
  "type": "Feature",
  "properties": {
    "addr:full":"Vestvejen 165 Aabenraa Danmark 6200",
    "addr:housenumber":"165",
    "addr:postcode":"6200",
    "addr:street":"Vestvejen",
    "iso:country":"DK",
    "sg:address":"Vestvejen 165",
    "sg:city":"Aabenraa",
    "sg:orig_category":"Flytteforretninger",
    "sg:phone":"+45 74 62 54 54",
    "sg:postcode":"6200",
    "sg:province":"Danmark",
    "sg:website":"www.aabmobeltrans.dk",
    "wof:name":"Aabenraa M\u00f8beltransport",
    "wof:placetype":"venue"
},
  "geometry": {"coordinates":[9.403837204,55.0502815247],"type":"Point"}
}