{
  "type": "Feature",
  "properties": {
    "addr:full":"Torvet 20 Esbjerg Danmark 6700",
    "addr:housenumber":"20",
    "addr:postcode":"6700",
    "addr:street":"Torvet",
    "iso:country":"DK",
    "sg:address":"Torvet 20",
    "sg:city":"Esbjerg",
    "sg:orig_category":"Posthuse",
    "sg:phone":"+45 79 12 12 12",
    "sg:postcode":"6700",
    "sg:province":"Danmark",
    "wof:name":"Post Danmark, Esbjerg Postkontor",
    "wof:placetype":"venue"
},
  "geometry": {"coordinates":[8.4517450333,55.4665679932],"type":"Point"}
}