{
  "type": "Feature",
  "properties": {
    "iso:country":"DK",
    "sg:address":"Kulturhuset, Nygade 22, 1.",
    "sg:city":"Holstebro",
    "sg:orig_category":"Kulturelle foreninger",
    "sg:phone":"+45 97 41 18 41",
    "sg:postcode":"7500",
    "sg:province":"Danmark",
    "wof:name":"Integrationsforeningen Sammen",
    "wof:placetype":"venue"
},
  "geometry": {"coordinates":[8.6202583313,56.3625221252],"type":"Point"}
}