{
  "type": "Feature",
  "properties": {
    "addr:full":"N\u00f8rregade 14, Sh Lyndelse Broby Danmark 5672",
    "addr:housenumber":"14",
    "addr:postcode":"5672",
    "addr:street":"Norregade;Lyndelse",
    "iso:country":"DK",
    "sg:address":"N\u00f8rregade 14, Sh Lyndelse",
    "sg:city":"Broby",
    "sg:orig_category":"Web- og Internetdesign",
    "sg:phone":"+45 62 64 16 20",
    "sg:postcode":"5672",
    "sg:province":"Danmark",
    "sg:website":"www.svejdaldata.dk",
    "wof:name":"Svejdal Data",
    "wof:placetype":"venue"
},
  "geometry": {"coordinates":[10.3131303787,55.2695846558],"type":"Point"}
}