{
  "type": "Feature",
  "properties": {
    "addr:full":"Adelgade 33 Hobro Danmark 9500",
    "addr:housenumber":"33",
    "addr:postcode":"9500",
    "addr:street":"Adelgade",
    "iso:country":"DK",
    "sg:address":"Adelgade 33",
    "sg:city":"Hobro",
    "sg:orig_category":"Boghandlere",
    "sg:phone":"+45 98 52 00 78",
    "sg:postcode":"9500",
    "sg:province":"Danmark",
    "wof:name":"Haarsl\u00f8vs Boghandel",
    "wof:placetype":"venue"
},
  "geometry": {"coordinates":[9.7945413589,56.6379051208],"type":"Point"}
}