{
  "type": "Feature",
  "properties": {
    "addr:full":"Ll. Dalbyvej 14 Borup Danmark 4140",
    "addr:housenumber":"14",
    "addr:postcode":"4140",
    "addr:street":"Ll. Dalbyvej",
    "iso:country":"DK",
    "sg:address":"Ll. Dalbyvej 14",
    "sg:city":"Borup",
    "sg:orig_category":"Murermestre",
    "sg:phone":"+45 57 52 65 14",
    "sg:postcode":"4140",
    "sg:province":"Danmark",
    "wof:name":"Kjeldal, Per",
    "wof:placetype":"venue"
},
  "geometry": {"coordinates":[11.9934864044,55.4651031494],"type":"Point"}
}