{
  "type": "Feature",
  "properties": {
    "addr:full":"Klostertorvet 2 \u00c5rhus C Danmark 8000",
    "addr:housenumber":"2",
    "addr:postcode":"8000",
    "addr:street":"Klostertorvet",
    "iso:country":"DK",
    "sg:address":"Klostertorvet 2",
    "sg:city":"\u00c5rhus C",
    "sg:classifiers":[
        {
            "category":"Restaurant",
            "type":"Food & Drink"
        }
    ],
    "sg:phone":"+45 86 13 20 55",
    "sg:postcode":"8000",
    "sg:province":"Danmark",
    "wof:name":"Pizza Hot",
    "wof:placetype":"venue"
},
  "geometry": {"coordinates":[4.717400074,49.7588005066],"type":"Point"}
}