{
  "type": "Feature",
  "properties": {
    "addr:full":"Store Kongensgade 110 C K\u00f8benhavn Danmark 1264",
    "addr:housenumber":"110 c;1264",
    "addr:street":"Store Kongensgade",
    "iso:country":"DK",
    "sg:address":"Store Kongensgade 110 C",
    "sg:city":"K\u00f8benhavn",
    "sg:orig_category":"Keramik",
    "sg:phone":"+45 33 14 41 13",
    "sg:postcode":"1264",
    "sg:province":"Danmark",
    "wof:name":"Packness, Jesper",
    "wof:placetype":"venue"
},
  "geometry": {"coordinates":[12.5923995972,55.6865005493],"type":"Point"}
}