{
  "type": "Feature",
  "properties": {
    "iso:country":"DK",
    "sg:address":"Flinterupvej 52",
    "sg:city":"Store Fuglede",
    "sg:orig_category":"Blikkenslagere",
    "sg:phone":"+45 59 59 82 82",
    "sg:postcode":"4480",
    "sg:province":"Danmark",
    "wof:name":"SP St\u00e5l",
    "wof:placetype":"venue"
},
  "geometry": {"coordinates":[11.217483,55.586914],"type":"Point"}
}