{
  "type": "Feature",
  "properties": {
    "addr:full":"Frederiksgade 9 Svendborg Danmark 5700",
    "addr:housenumber":"9",
    "addr:postcode":"5700",
    "addr:street":"Frederiksgade",
    "iso:country":"DK",
    "sg:address":"Frederiksgade 9",
    "sg:city":"Svendborg",
    "sg:orig_category":"Pizzeriaer",
    "sg:phone":"+45 62 22 21 61",
    "sg:postcode":"5700",
    "sg:province":"Danmark",
    "wof:name":"Valentino, Pizzaria",
    "wof:placetype":"venue"
},
  "geometry": {"coordinates":[10.6128377914,55.0589828491],"type":"Point"}
}