{
  "type": "Feature",
  "properties": {
    "iso:country":"DK",
    "sg:address":"Gartnergade 15",
    "sg:city":"K\u00f8benhavn N",
    "sg:orig_category":"Ungdomsklubber",
    "sg:phone":"+45 35 37 65 36",
    "sg:postcode":"2200",
    "sg:province":"Danmark",
    "wof:name":"Kvisten",
    "wof:placetype":"venue"
},
  "geometry": {"coordinates":[-94.2897186279,47.8772926331],"type":"Point"}
}