{
  "type": "Feature",
  "properties": {
    "addr:full":"Klosterg\u00e5rden, Klostergade 16 Kolding Danmark 6000",
    "addr:housenumber":"16",
    "addr:postcode":"6000",
    "addr:street":"Klostergade",
    "iso:country":"DK",
    "sg:address":"Klosterg\u00e5rden, Klostergade 16",
    "sg:city":"Kolding",
    "sg:orig_category":"Kulturelle foreninger",
    "sg:phone":"+45 75 52 63 00",
    "sg:postcode":"6000",
    "sg:province":"Danmark",
    "sg:website":"www.kolding.fof.dk",
    "wof:name":"FOF",
    "wof:placetype":"venue"
},
  "geometry": {"coordinates":[9.4733953476,55.4863586426],"type":"Point"}
}