{
  "type": "Feature",
  "properties": {
    "addr:full":"Boulevarden 26 Aalborg Danmark 9000",
    "addr:housenumber":"26",
    "addr:postcode":"9000",
    "addr:street":"Boulevarden",
    "iso:country":"DK",
    "sg:address":"Boulevarden 26",
    "sg:city":"Aalborg",
    "sg:orig_category":"Antikviteter",
    "sg:phone":"+45 98 11 38 44",
    "sg:postcode":"9000",
    "sg:province":"Danmark",
    "wof:name":"Almuen",
    "wof:placetype":"venue"
},
  "geometry": {"coordinates":[9.9179916382,57.0453071594],"type":"Point"}
}