{
  "type": "Feature",
  "properties": {
    "iso:country":"DK",
    "sg:address":"Industrivej 10",
    "sg:city":"Slangerup",
    "sg:orig_category":"Kosmetik",
    "sg:phone":"+45 70 27 04 04",
    "sg:postcode":"3550",
    "sg:province":"Danmark",
    "sg:website":"www.oriflame.dk",
    "wof:name":"Oriflame Kosmetik Klub",
    "wof:placetype":"venue"
},
  "geometry": {"coordinates":[12.1909198761,55.8467788696],"type":"Point"}
}