{
  "type": "Feature",
  "properties": {
    "addr:full":"Nygade 3 Gr\u00e5sten Danmark 6300",
    "addr:housenumber":"3",
    "addr:postcode":"6300",
    "addr:street":"Nygade",
    "iso:country":"DK",
    "sg:address":"Nygade 3",
    "sg:city":"Gr\u00e5sten",
    "sg:orig_category":"Ejendomshandel",
    "sg:phone":"+45 74 65 04 07",
    "sg:postcode":"6300",
    "sg:province":"Danmark",
    "sg:website":"www.ejendomsnet.dk",
    "wof:name":"Gr\u00e5sten Bolighandel",
    "wof:placetype":"venue"
},
  "geometry": {"coordinates":[9.5949192047,54.9218902588],"type":"Point"}
}