{
  "type": "Feature",
  "properties": {
    "addr:full":"Hejrevej 43 Roskilde Danmark 4000",
    "addr:housenumber":"43",
    "addr:postcode":"4000",
    "addr:street":"Hejrevej",
    "iso:country":"DK",
    "sg:address":"Hejrevej 43",
    "sg:city":"Roskilde",
    "sg:orig_category":"Finmekanikere",
    "sg:phone":"+45 46 75 73 94",
    "sg:postcode":"4000",
    "sg:province":"Danmark",
    "wof:name":"Hansen, Bjarne",
    "wof:placetype":"venue"
},
  "geometry": {"coordinates":[12.114405632,55.6503562927],"type":"Point"}
}