{
  "type": "Feature",
  "properties": {
    "addr:full":"Kratbjerg 332  Fredensborg Danmark 3480",
    "addr:housenumber":"332",
    "addr:postcode":"3480",
    "addr:street":"Kratbjerg",
    "iso:country":"DK",
    "sg:address":"Kratbjerg 332 ",
    "sg:city":"Fredensborg",
    "sg:classifiers":[
        {
            "category":"Farming",
            "subcategory":"Livestock Farm",
            "type":"Manufacturing & Wholesale Goods"
        }
    ],
    "sg:phone":"+45 48 48 30 28",
    "sg:postcode":"3480",
    "sg:province":"Danmark",
    "sg:tags":[
        "agriculture"
    ],
    "wof:name":"POULSEN ROSER APS",
    "wof:placetype":"venue"
},
  "geometry": {"coordinates":[12.3901700974,55.9661712646],"type":"Point"}
}