{
  "type": "Feature",
  "properties": {
    "addr:full":"Hasseris Bymidte 29 Aalborg Danmark 9000",
    "addr:housenumber":"29",
    "addr:postcode":"9000",
    "addr:street":"Hasseris Bymidte",
    "iso:country":"DK",
    "sg:address":"Hasseris Bymidte 29",
    "sg:city":"Aalborg",
    "sg:orig_category":"Supermarkeder",
    "sg:phone":"+45 98 18 25 55",
    "sg:postcode":"9000",
    "sg:province":"Danmark",
    "wof:name":"Super Best",
    "wof:placetype":"venue"
},
  "geometry": {"coordinates":[9.8827314377,57.035900116],"type":"Point"}
}