{
  "type": "Feature",
  "properties": {
    "iso:country":"DK",
    "sg:address":"\u00c5l\u00f8kkevej 3",
    "sg:city":"Aarup",
    "sg:orig_category":"Malermestre",
    "sg:phone":"+45 64 43 37 64",
    "sg:postcode":"5560",
    "sg:province":"Danmark",
    "wof:name":"Andersen, Claus",
    "wof:placetype":"venue"
},
  "geometry": {"coordinates":[10.0490245819,55.3808059692],"type":"Point"}
}