{
  "type": "Feature",
  "properties": {
    "addr:full":"Sm\u00f8gen 2 Hvidovre Danmark 2650",
    "addr:housenumber":"2",
    "addr:postcode":"2650",
    "addr:street":"Smogen",
    "iso:country":"DK",
    "sg:address":"Sm\u00f8gen 2",
    "sg:city":"Hvidovre",
    "sg:orig_category":"Revisorer",
    "sg:phone":"+45 36 78 97 66",
    "sg:postcode":"2650",
    "sg:province":"Danmark",
    "wof:name":"Aved\u00f8re Revisionskontor",
    "wof:placetype":"venue"
},
  "geometry": {"coordinates":[12.4440603256,55.6410751343],"type":"Point"}
}