{
  "type": "Feature",
  "properties": {
    "addr:full":"Fmd.: Finn Olsen, Strandvejen 227 A Charlottenlund Danmark 2920",
    "addr:housenumber":"227 a",
    "addr:postcode":"2920",
    "addr:street":"Strandvejen",
    "iso:country":"DK",
    "sg:address":"Fmd.: Finn Olsen, Strandvejen 227 A",
    "sg:city":"Charlottenlund",
    "sg:orig_category":"Grundejerforeninger",
    "sg:phone":"+45 39 62 41 40",
    "sg:postcode":"2920",
    "sg:province":"Danmark",
    "wof:name":"Grundejerforening v. Asserbo Plantage",
    "wof:placetype":"venue"
},
  "geometry": {"coordinates":[12.5721197128,55.7532615662],"type":"Point"}
}