{
  "type": "Feature",
  "properties": {
    "addr:full":"Slotshaven 5 Holb\u00e6k Danmark 4300",
    "addr:housenumber":"5",
    "addr:postcode":"4300",
    "addr:street":"Slotshaven",
    "iso:country":"DK",
    "sg:address":"Slotshaven 5",
    "sg:city":"Holb\u00e6k",
    "sg:orig_category":"Voksenuddannelsescentre",
    "sg:phone":"+45 59 48 03 48",
    "sg:postcode":"4300",
    "sg:province":"Danmark",
    "sg:website":"www.nordvestsjaelland-vuc.dk",
    "wof:name":"VUC Nordvestsj\u00e6lland",
    "wof:placetype":"venue"
},
  "geometry": {"coordinates":[12.505399704,55.8709983826],"type":"Point"}
}