{
  "type": "Feature",
  "properties": {
    "addr:full":"Lilleskovvej 3, Tommerup St Tommerup Danmark 5690",
    "addr:housenumber":"3",
    "addr:postcode":"5690",
    "addr:street":"Lilleskovvej;St",
    "iso:country":"DK",
    "sg:address":"Lilleskovvej 3, Tommerup St",
    "sg:city":"Tommerup",
    "sg:orig_category":"Filialbiblioteker",
    "sg:phone":"+45 64 76 24 32",
    "sg:postcode":"5690",
    "sg:province":"Danmark",
    "wof:name":"Tommerup St. Bibliotek",
    "wof:placetype":"venue"
},
  "geometry": {"coordinates":[10.2489509583,55.3236503601],"type":"Point"}
}