{
  "type": "Feature",
  "properties": {
    "addr:full":"Kongensgade 1 Marstal Danmark 5960",
    "addr:housenumber":"1",
    "addr:postcode":"5960",
    "addr:street":"Kongensgade",
    "iso:country":"DK",
    "sg:address":"Kongensgade 1",
    "sg:city":"Marstal",
    "sg:orig_category":"Rederier",
    "sg:phone":"+45 62 53 10 48",
    "sg:postcode":"5960",
    "sg:province":"Danmark",
    "wof:name":"Kromann I/S, Rederiet Erik B.",
    "wof:placetype":"venue"
},
  "geometry": {"coordinates":[10.5202217102,54.8555641174],"type":"Point"}
}