{
  "type": "Feature",
  "properties": {
    "addr:full":"Englandsvej 5-7, Tved Svendborg Danmark 5700",
    "addr:housenumber":"5-7",
    "addr:postcode":"5700",
    "addr:street":"Englandsvej;Tved",
    "iso:country":"DK",
    "sg:address":"Englandsvej 5-7, Tved",
    "sg:city":"Svendborg",
    "sg:orig_category":"Maskinfabrikker",
    "sg:phone":"+45 62 22 30 95",
    "sg:postcode":"5700",
    "sg:province":"Danmark",
    "wof:name":"Medeq I/S",
    "wof:placetype":"venue"
},
  "geometry": {"coordinates":[10.6065101624,55.0595970154],"type":"Point"}
}