{
  "type": "Feature",
  "properties": {
    "iso:country":"DK",
    "sg:address":"Falen 11",
    "sg:city":"Odense C",
    "sg:orig_category":"Non-Classified Establishments",
    "sg:phone":"+45 66 14 86 07",
    "sg:postcode":"5000",
    "sg:province":"Danmark",
    "wof:name":"Papirg\u00e5rden A/S",
    "wof:placetype":"venue"
},
  "geometry": {"coordinates":[10.3760480881,55.3931694031],"type":"Point"}
}