{
  "type": "Feature",
  "properties": {
    "addr:full":"v/ Birgit Reimann, Englerup Gade 24, Englerup Kirke S\u00e5by Danmark 4060",
    "addr:housenumber":"24",
    "addr:postcode":"4060",
    "addr:street":"Englerup Gade;Englerup Kirke",
    "iso:country":"DK",
    "sg:address":"v/ Birgit Reimann, Englerup Gade 24, Englerup",
    "sg:city":"Kirke S\u00e5by",
    "sg:orig_category":"Borger- og beboerforeninger",
    "sg:phone":"+45 46 49 91 14",
    "sg:postcode":"4060",
    "sg:province":"Danmark",
    "wof:name":"Englerup Bylaug",
    "wof:placetype":"venue"
},
  "geometry": {"coordinates":[11.8739786148,55.6341285706],"type":"Point"}
}