{
  "type": "Feature",
  "properties": {
    "addr:full":"Fl\u00f8jstrupvej 88 Malling Danmark 8340",
    "addr:housenumber":"88",
    "addr:postcode":"8340",
    "addr:street":"Flojstrupvej",
    "iso:country":"DK",
    "sg:address":"Fl\u00f8jstrupvej 88",
    "sg:city":"Malling",
    "sg:orig_category":"Maskinstationer",
    "sg:phone":"+45 86 93 03 03",
    "sg:postcode":"8340",
    "sg:province":"Danmark",
    "wof:name":"Malling Maskinstation ApS",
    "wof:placetype":"venue"
},
  "geometry": {"coordinates":[10.2126121521,56.0445709229],"type":"Point"}
}