{
  "type": "Feature",
  "properties": {
    "addr:full":"\u00d8stergade 3 Skjern Danmark 6900",
    "addr:housenumber":"3",
    "addr:postcode":"6900",
    "addr:street":"Ostergade",
    "iso:country":"DK",
    "sg:address":"\u00d8stergade 3",
    "sg:city":"Skjern",
    "sg:orig_category":"Bodegaer",
    "sg:phone":"+45 97 35 12 13",
    "sg:postcode":"6900",
    "sg:province":"Danmark",
    "wof:name":"Hannes Bar",
    "wof:placetype":"venue"
},
  "geometry": {"coordinates":[8.4925527573,55.9486351013],"type":"Point"}
}