{
  "type": "Feature",
  "properties": {
    "addr:full":"Jernbanegade 23 Roskilde Danmark 4000",
    "addr:housenumber":"23",
    "addr:postcode":"4000",
    "addr:street":"Jernbanegade",
    "iso:country":"DK",
    "sg:address":"Jernbanegade 23",
    "sg:city":"Roskilde",
    "sg:orig_category":"Ejendomshandel",
    "sg:phone":"+45 46 36 38 37",
    "sg:postcode":"4000",
    "sg:province":"Danmark",
    "sg:website":"www.ejendomsringen.net",
    "wof:name":"EjendomsRingen",
    "wof:placetype":"venue"
},
  "geometry": {"coordinates":[12.0791053772,55.6376686096],"type":"Point"}
}