{
  "type": "Feature",
  "properties": {
    "addr:full":"Holbergsvej 10 Kolding Danmark 6000",
    "addr:housenumber":"10",
    "addr:postcode":"6000",
    "addr:street":"Holbergsvej",
    "iso:country":"DK",
    "sg:address":"Holbergsvej 10",
    "sg:city":"Kolding",
    "sg:orig_category":"Laboratorier",
    "sg:phone":"+45 75 52 04 33",
    "sg:postcode":"6000",
    "sg:province":"Danmark",
    "wof:name":"Bioteknologisk Institut",
    "wof:placetype":"venue"
},
  "geometry": {"coordinates":[9.4482946396,55.4845199585],"type":"Point"}
}