{
  "type": "Feature",
  "properties": {
    "addr:full":"Hadsundvej 2 Hobro Danmark 9500",
    "addr:housenumber":"2",
    "addr:postcode":"9500",
    "addr:street":"Hadsundvej",
    "iso:country":"DK",
    "sg:address":"Hadsundvej 2",
    "sg:city":"Hobro",
    "sg:orig_category":"Murermestre",
    "sg:phone":"+45 98 52 27 11",
    "sg:postcode":"9500",
    "sg:province":"Danmark",
    "wof:name":"K. H. S. Byggeindustri ApS",
    "wof:placetype":"venue"
},
  "geometry": {"coordinates":[9.7944869995,56.649433136],"type":"Point"}
}