{
  "type": "Feature",
  "properties": {
    "addr:full":"Rantzausmindevej 9 Svendborg Danmark 5700",
    "addr:housenumber":"9",
    "addr:postcode":"5700",
    "addr:street":"Rantzausmindevej",
    "iso:country":"DK",
    "sg:address":"Rantzausmindevej 9",
    "sg:city":"Svendborg",
    "sg:orig_category":"Alternativ behandling",
    "sg:postcode":"5700",
    "sg:province":"Danmark",
    "wof:name":"Aurelius, Morten",
    "wof:placetype":"venue"
},
  "geometry": {"coordinates":[10.5276002884,55.0327796936],"type":"Point"}
}