{
  "type": "Feature",
  "properties": {
    "addr:full":"Pr\u00e6st\u00f8vej 11 Fakse Danmark 4640",
    "addr:housenumber":"11",
    "addr:postcode":"4640",
    "addr:street":"Praestovej",
    "iso:country":"DK",
    "sg:address":"Pr\u00e6st\u00f8vej 11",
    "sg:city":"Fakse",
    "sg:orig_category":"\u00c3\u02dcvrige institutioner",
    "sg:phone":"+45 56 73 08 75",
    "sg:postcode":"4640",
    "sg:province":"Danmark",
    "wof:name":"Rosenh\u00f8j V\u00e6rested",
    "wof:placetype":"venue"
},
  "geometry": {"coordinates":[12.1180057526,55.2540359497],"type":"Point"}
}