{
  "type": "Feature",
  "properties": {
    "iso:country":"DK",
    "sg:address":"Sandmarken 37, Askov",
    "sg:city":"Vejen",
    "sg:orig_category":"Zoneterapeuter",
    "sg:phone":"+45 75 36 04 77",
    "sg:postcode":"6600",
    "sg:province":"Danmark",
    "wof:name":"Body-Mind, Zoneterapiklinikken",
    "wof:placetype":"venue"
},
  "geometry": {"coordinates":[9.1396121979,55.4778175354],"type":"Point"}
}