{
  "type": "Feature",
  "properties": {
    "addr:full":"v/ Tine Asmussen, Svinget 37 Hinnerup Danmark 8382",
    "addr:housenumber":"37",
    "addr:postcode":"8382",
    "addr:street":"Asmussen Svinget",
    "iso:country":"DK",
    "sg:address":"v/ Tine Asmussen, Svinget 37",
    "sg:city":"Hinnerup",
    "sg:orig_category":"Kulturelle foreninger",
    "sg:phone":"+45 86 91 13 35",
    "sg:postcode":"8382",
    "sg:province":"Danmark",
    "wof:name":"HAT - Hinnerup Amat\u00f8r-Teater",
    "wof:placetype":"venue"
},
  "geometry": {"coordinates":[10.0614156723,56.2650604248],"type":"Point"}
}