{
  "type": "Feature",
  "properties": {
    "addr:full":"Algade 104 Vordingborg Danmark 4760",
    "addr:housenumber":"104",
    "addr:postcode":"4760",
    "addr:street":"Algade",
    "iso:country":"DK",
    "sg:address":"Algade 104",
    "sg:city":"Vordingborg",
    "sg:orig_category":"Beskyttede boliger",
    "sg:phone":"+45 55 35 36 64",
    "sg:postcode":"4760",
    "sg:province":"Danmark",
    "wof:name":"Br\u00e6nderig\u00e5rden beskyttede boliger",
    "wof:placetype":"venue"
},
  "geometry": {"coordinates":[11.9148321152,55.0071296692],"type":"Point"}
}