{
  "type": "Feature",
  "properties": {
    "addr:full":"Vejlevej 4 Viborg Danmark 8800",
    "addr:housenumber":"4",
    "addr:postcode":"8800",
    "addr:street":"Vejlevej",
    "iso:country":"DK",
    "sg:address":"Vejlevej 4",
    "sg:city":"Viborg",
    "sg:orig_category":"Hundefoder",
    "sg:phone":"+45 86 63 84 08",
    "sg:postcode":"8800",
    "sg:province":"Danmark",
    "wof:name":"Ropo-Dog Hundefoder",
    "wof:placetype":"venue"
},
  "geometry": {"coordinates":[9.3754472733,56.4117965698],"type":"Point"}
}