{
  "type": "Feature",
  "properties": {
    "addr:full":"V\u00e6selvej 62 Skive Danmark 7800",
    "addr:housenumber":"62",
    "addr:postcode":"7800",
    "addr:street":"Vaeselvej",
    "iso:country":"DK",
    "sg:address":"V\u00e6selvej 62",
    "sg:city":"Skive",
    "sg:orig_category":"Boligindretning",
    "sg:phone":"+45 97 51 21 11",
    "sg:postcode":"7800",
    "sg:province":"Danmark",
    "wof:name":"Poulsen, Irene",
    "wof:placetype":"venue"
},
  "geometry": {"coordinates":[9.0190534592,56.5388832092],"type":"Point"}
}