{
  "type": "Feature",
  "properties": {
    "addr:full":"Kultorvet 11 K\u00f8benhavn Danmark 1175",
    "addr:housenumber":"11;1175",
    "addr:street":"Kultorvet",
    "iso:country":"DK",
    "sg:address":"Kultorvet 11",
    "sg:city":"K\u00f8benhavn",
    "sg:classifiers":[
        {
            "category":"Restaurant",
            "type":"Food & Drink"
        }
    ],
    "sg:phone":"+45 33 13 31 48",
    "sg:postcode":"1175",
    "sg:province":"Danmark",
    "wof:name":"Klaptr\u00e6et",
    "wof:placetype":"venue"
},
  "geometry": {"coordinates":[12.5739498138,55.6827392578],"type":"Point"}
}