{
  "type": "Feature",
  "properties": {
    "iso:country":"DK",
    "sg:address":"Morup M\u00f8llevej 16",
    "sg:city":"Bedsted",
    "sg:classifiers":[
        {
            "category":"Taxi",
            "type":"Transportation"
        }
    ],
    "sg:phone":"+45 97 94 52 51",
    "sg:postcode":"7755",
    "sg:province":"Danmark",
    "wof:name":"Koldby Taxi",
    "wof:placetype":"venue"
},
  "geometry": {"coordinates":[8.4032526016,56.8101196289],"type":"Point"}
}