{
  "type": "Feature",
  "properties": {
    "addr:full":"Bonder\u00f8dvej 28, Bonder\u00f8d Fakse Danmark 4640",
    "addr:housenumber":"28",
    "addr:postcode":"4640",
    "addr:street":"Bonderodvej",
    "iso:country":"DK",
    "sg:address":"Bonder\u00f8dvej 28, Bonder\u00f8d",
    "sg:city":"Fakse",
    "sg:orig_category":"Autoreparation og -service",
    "sg:phone":"+45 56 71 01 45",
    "sg:postcode":"4640",
    "sg:province":"Danmark",
    "wof:name":"Bonder\u00f8d Auto- & Traktorv\u00e6rksted",
    "wof:placetype":"venue"
},
  "geometry": {"coordinates":[12.1203422546,55.2574195862],"type":"Point"}
}