{
  "type": "Feature",
  "properties": {
    "iso:country":"DK",
    "sg:address":"Tagt\u00e6kkervej 13",
    "sg:city":"Viborg",
    "sg:orig_category":"Skilte",
    "sg:phone":"+45 86 62 37 39",
    "sg:postcode":"8800",
    "sg:province":"Danmark",
    "wof:name":"PJ Skilte",
    "wof:placetype":"venue"
},
  "geometry": {"coordinates":[9.403676033,56.4716682434],"type":"Point"}
}