{
  "type": "Feature",
  "properties": {
    "addr:full":"Marielystvej 9 A Frederiksberg Danmark 2000",
    "addr:housenumber":"9 a",
    "addr:postcode":"2000",
    "addr:street":"Marielystvej",
    "iso:country":"DK",
    "sg:address":"Marielystvej 9 A",
    "sg:city":"Frederiksberg",
    "sg:orig_category":"Alexanderteknik",
    "sg:phone":"+45 38 74 74 15",
    "sg:postcode":"2000",
    "sg:province":"Danmark",
    "wof:name":"Harder, Lise",
    "wof:placetype":"venue"
},
  "geometry": {"coordinates":[12.5005512238,55.677570343],"type":"Point"}
}