{
  "type": "Feature",
  "properties": {
    "addr:full":"Ane Staunings Vej 5 Horsens Danmark 8700",
    "addr:housenumber":"5",
    "addr:postcode":"8700",
    "addr:street":"Ane Staunings Vej",
    "iso:country":"DK",
    "sg:address":"Ane Staunings Vej 5",
    "sg:city":"Horsens",
    "sg:orig_category":"Autoreparation og -service",
    "sg:phone":"+45 75 61 52 27",
    "sg:postcode":"8700",
    "sg:province":"Danmark",
    "wof:name":"L. \u00c5. C. Autov\u00e6rksted",
    "wof:placetype":"venue"
},
  "geometry": {"coordinates":[9.8523054123,55.8694038391],"type":"Point"}
}