{
  "type": "Feature",
  "properties": {
    "iso:country":"DK",
    "sg:address":"Jels S\u00f8ndergade 8",
    "sg:city":"R\u00f8dding",
    "sg:classifiers":[
        {
            "category":"Restaurant",
            "type":"Food & Drink"
        }
    ],
    "sg:phone":"+45 74 55 25 41",
    "sg:postcode":"6630",
    "sg:province":"Danmark",
    "wof:name":"Jels G\u00e6stgiverg\u00e5rd",
    "wof:placetype":"venue"
},
  "geometry": {"coordinates":[9.2026863098,55.3560791016],"type":"Point"}
}