{
  "type": "Feature",
  "properties": {
    "addr:full":"Orebyg\u00e5rdsvej 3 - 5  Herning Danmark 7400",
    "addr:housenumber":"3 5",
    "addr:postcode":"7400",
    "addr:street":"Orebygaardsvej",
    "iso:country":"DK",
    "sg:address":"Orebyg\u00e5rdsvej 3 - 5 ",
    "sg:city":"Herning",
    "sg:classifiers":[
        {
            "category":"Shopping",
            "subcategory":"Clothing, Apparel, & Fashions",
            "type":"Retail Goods"
        }
    ],
    "sg:phone":"+45 97 26 88 00",
    "sg:postcode":"7400",
    "sg:province":"Danmark",
    "sg:tags":[
        "clothes"
    ],
    "wof:name":"JENSEN WOMEN A/S",
    "wof:placetype":"venue"
},
  "geometry": {"coordinates":[8.9323148727,56.1550788879],"type":"Point"}
}