{
  "type": "Feature",
  "properties": {
    "addr:full":"v/ OK Trustup, \u00c5rhusvej 192, Trustrup Trustrup Danmark 8570",
    "addr:housenumber":"192",
    "addr:postcode":"8570",
    "addr:street":"Aarhusvej",
    "iso:country":"DK",
    "sg:address":"v/ OK Trustup, \u00c5rhusvej 192, Trustrup",
    "sg:city":"Trustrup",
    "sg:orig_category":"Apoteker og -udsalg",
    "sg:phone":"+45 86 33 40 47",
    "sg:postcode":"8570",
    "sg:province":"Danmark",
    "wof:name":"H\u00e5ndk\u00f8bsudsalget",
    "wof:placetype":"venue"
},
  "geometry": {"coordinates":[10.7718954086,56.3482666016],"type":"Point"}
}