{
  "type": "Feature",
  "properties": {
    "addr:full":"Falkoner Alle 41 Frederiksberg Danmark 2000",
    "addr:housenumber":"41",
    "addr:postcode":"2000",
    "addr:street":"Falkoner Alle",
    "iso:country":"DK",
    "sg:address":"Falkoner Alle 41",
    "sg:city":"Frederiksberg",
    "sg:orig_category":"Ejendomshandel",
    "sg:phone":"+45 38 32 50 00",
    "sg:postcode":"2000",
    "sg:province":"Danmark",
    "wof:name":"Skovgaard, Bent",
    "wof:placetype":"venue"
},
  "geometry": {"coordinates":[12.5366287231,55.6837692261],"type":"Point"}
}