{
  "type": "Feature",
  "properties": {
    "iso:country":"DK",
    "sg:address":"Ahlgade 47",
    "sg:city":"Holb\u00e6k",
    "sg:orig_category":"Sko",
    "sg:phone":"+45 59 43 80 63",
    "sg:postcode":"4300",
    "sg:province":"Danmark",
    "wof:name":"Bianco Footwear",
    "wof:placetype":"venue"
},
  "geometry": {"coordinates":[76.3070983887,14.277130127],"type":"Point"}
}