{
  "type": "Feature",
  "properties": {
    "addr:full":"v/ Hanne Thomsen, Nords\u00f8vej 12, Vorup\u00f8r Thisted Danmark 7700",
    "addr:housenumber":"12",
    "addr:postcode":"7700",
    "addr:street":"Nordsovej;Vorupor",
    "iso:country":"DK",
    "sg:address":"v/ Hanne Thomsen, Nords\u00f8vej 12, Vorup\u00f8r",
    "sg:city":"Thisted",
    "sg:orig_category":"Borger- og beboerforeninger",
    "sg:phone":"+45 97 93 84 30",
    "sg:postcode":"7700",
    "sg:province":"Danmark",
    "wof:name":"Vorup\u00f8r Borgerforening",
    "wof:placetype":"venue"
},
  "geometry": {"coordinates":[8.6919784546,56.9556121826],"type":"Point"}
}