{
  "type": "Feature",
  "properties": {
    "iso:country":"DK",
    "sg:address":"Esthersvej 34",
    "sg:city":"Hellerup",
    "sg:orig_category":"Bagere",
    "sg:phone":"+45 39 62 03 12",
    "sg:postcode":"2900",
    "sg:province":"Danmark",
    "wof:name":"Petersen Bageriet, Teddy",
    "wof:placetype":"venue"
},
  "geometry": {"coordinates":[12.565825,55.730927],"type":"Point"}
}