{
  "type": "Feature",
  "properties": {
    "addr:full":"Tilst Skolevej 23 Tilst Danmark 8381",
    "addr:housenumber":"23",
    "addr:postcode":"8381",
    "addr:street":"Tilst Skolevej",
    "iso:country":"DK",
    "sg:address":"Tilst Skolevej 23",
    "sg:city":"Tilst",
    "sg:orig_category":"Ejendomshandel",
    "sg:phone":"+45 86 24 51 00",
    "sg:postcode":"8381",
    "sg:province":"Danmark",
    "sg:website":"www.danbolig.dk",
    "wof:name":"Skj\u00f8dt's Ejendomskontor",
    "wof:placetype":"venue"
},
  "geometry": {"coordinates":[10.1037273407,56.1845169067],"type":"Point"}
}