{
  "type": "Feature",
  "properties": {
    "addr:full":"Engvej 35 Odense M Danmark 5230",
    "addr:housenumber":"35",
    "addr:postcode":"5230",
    "addr:street":"Engvej",
    "iso:country":"DK",
    "sg:address":"Engvej 35",
    "sg:city":"Odense M",
    "sg:classifiers":[
        {
            "category":"Professional",
            "subcategory":"Computer Services",
            "type":"Services"
        }
    ],
    "sg:phone":"+45 66 19 33 95",
    "sg:postcode":"5230",
    "sg:province":"Danmark",
    "sg:tags":[
        "edb",
        "-",
        "software"
    ],
    "wof:name":"Lighthouse Data",
    "wof:placetype":"venue"
},
  "geometry": {"coordinates":[10.3817434311,55.378452301],"type":"Point"}
}