{
  "type": "Feature",
  "properties": {
    "addr:full":"Gammel Kulhusvej 149, Kulhuse J\u00e6gerspris Danmark 3630",
    "addr:housenumber":"149",
    "addr:postcode":"3630",
    "addr:street":"Gammel Kulhusvej",
    "iso:country":"DK",
    "sg:address":"Gammel Kulhusvej 149, Kulhuse",
    "sg:city":"J\u00e6gerspris",
    "sg:orig_category":"Distriktsbiblioteker",
    "sg:phone":"+45 47 53 69 87",
    "sg:postcode":"3630",
    "sg:province":"Danmark",
    "wof:name":"Skoven Bibliotek",
    "wof:placetype":"venue"
},
  "geometry": {"coordinates":[11.9136800766,55.9269866943],"type":"Point"}
}