{
  "type": "Feature",
  "properties": {
    "addr:full":"Nordstjernevej 8 Aabybro Danmark 9440",
    "addr:housenumber":"8",
    "addr:postcode":"9440",
    "addr:street":"Nordstjernevej",
    "iso:country":"DK",
    "sg:address":"Nordstjernevej 8",
    "sg:city":"Aabybro",
    "sg:classifiers":[
        {
            "category":"Restaurant",
            "type":"Food & Drink"
        }
    ],
    "sg:phone":"+45 98 24 13 27",
    "sg:postcode":"9440",
    "sg:province":"Danmark",
    "wof:name":"Mc Donalds Familierestaurant",
    "wof:placetype":"venue"
},
  "geometry": {"coordinates":[9.7517127991,57.1497802734],"type":"Point"}
}