{
  "type": "Feature",
  "properties": {
    "addr:full":"Borrehusvej 7 Kolding Danmark 6000",
    "addr:housenumber":"7",
    "addr:postcode":"6000",
    "addr:street":"Borrehusvej",
    "iso:country":"DK",
    "sg:address":"Borrehusvej 7",
    "sg:city":"Kolding",
    "sg:orig_category":"Konsulentvirksomheder",
    "sg:phone":"+45 75 53 12 06",
    "sg:postcode":"6000",
    "sg:province":"Danmark",
    "wof:name":"Thisgaard, Ole",
    "wof:placetype":"venue"
},
  "geometry": {"coordinates":[9.4918088913,55.4984321594],"type":"Point"}
}