{
  "type": "Feature",
  "properties": {
    "addr:full":"Dronn. Christines V 6 Aalborg Danmark 9000",
    "addr:housenumber":"6",
    "addr:postcode":"9000",
    "iso:country":"DK",
    "sg:address":"Dronn. Christines V 6",
    "sg:city":"Aalborg",
    "sg:orig_category":"Private skoler",
    "sg:phone":"+45 96 31 18 18",
    "sg:postcode":"9000",
    "sg:province":"Danmark",
    "wof:name":"Klostermarksskolen",
    "wof:placetype":"venue"
},
  "geometry": {"coordinates":[9.9064617157,57.0489616394],"type":"Point"}
}