{
  "type": "Feature",
  "properties": {
    "iso:country":"DK",
    "sg:address":"Fmd.: Kurt Pedersen, \u00d8ster Vedsted Vej 54",
    "sg:city":"Ribe",
    "sg:orig_category":"Spejderkorps",
    "sg:phone":"+45 75 41 03 35",
    "sg:postcode":"6760",
    "sg:province":"Danmark",
    "wof:name":"FDF, \u00d8ster Vedsted",
    "wof:placetype":"venue"
},
  "geometry": {"coordinates":[8.7656240463,55.3297042847],"type":"Point"}
}