{
  "type": "Feature",
  "properties": {
    "iso:country":"DK",
    "sg:address":"Thomas B.Thriges Gd. 24",
    "sg:city":"Odense C",
    "sg:orig_category":"Boligselskaber",
    "sg:phone":"+45 63 13 31 33",
    "sg:postcode":"5000",
    "sg:province":"Danmark",
    "wof:name":"Odense Andelsboligforening",
    "wof:placetype":"venue"
},
  "geometry": {"coordinates":[10.3893060684,55.399181366],"type":"Point"}
}