{
  "type": "Feature",
  "properties": {
    "addr:full":"Smedeholm 18 Herlev Danmark 2730",
    "addr:housenumber":"18",
    "addr:postcode":"2730",
    "addr:street":"Smedeholm",
    "iso:country":"DK",
    "sg:address":"Smedeholm 18",
    "sg:city":"Herlev",
    "sg:orig_category":"Kontorindretning og -systemer",
    "sg:phone":"+45 44 84 96 67",
    "sg:postcode":"2730",
    "sg:province":"Danmark",
    "wof:name":"Herlev Snedkeri ApS",
    "wof:placetype":"venue"
},
  "geometry": {"coordinates":[12.4205465317,55.7228813171],"type":"Point"}
}