{
  "type": "Feature",
  "properties": {
    "addr:full":"Rebildparken 33 Aalborg \u00d8 Danmark 9220",
    "addr:housenumber":"33",
    "addr:postcode":"9220",
    "addr:street":"Rebildparken;Danmark",
    "iso:country":"DK",
    "sg:address":"Rebildparken 33",
    "sg:city":"Aalborg \u00d8",
    "sg:orig_category":"Cykler",
    "sg:phone":"+45 98 15 19 19",
    "sg:postcode":"9220",
    "sg:province":"Danmark",
    "wof:name":"Cykelbiksen",
    "wof:placetype":"venue"
},
  "geometry": {"coordinates":[10.0076551437,57.0295753479],"type":"Point"}
}