{
  "type": "Feature",
  "properties": {
    "addr:full":"Bysmedevej 57, Tilst Tilst Danmark 8381",
    "addr:housenumber":"57",
    "addr:postcode":"8381",
    "addr:street":"Bysmedevej",
    "iso:country":"DK",
    "sg:address":"Bysmedevej 57, Tilst",
    "sg:city":"Tilst",
    "sg:orig_category":"Kirker",
    "sg:postcode":"8381",
    "sg:province":"Danmark",
    "wof:name":"Tilst Kirke",
    "wof:placetype":"venue"
},
  "geometry": {"coordinates":[10.1078147888,56.1882019043],"type":"Point"}
}