{
  "type": "Feature",
  "properties": {
    "addr:full":"Sinding Kirkevej 3 B Herning Danmark 7400",
    "addr:housenumber":"3 b",
    "addr:postcode":"7400",
    "addr:street":"Sinding Kirkevej",
    "iso:country":"DK",
    "sg:address":"Sinding Kirkevej 3 B",
    "sg:city":"Herning",
    "sg:orig_category":"Kirker",
    "sg:postcode":"7400",
    "sg:province":"Danmark",
    "wof:name":"Sinding Kirke",
    "wof:placetype":"venue"
},
  "geometry": {"coordinates":[8.8642959595,56.2071762085],"type":"Point"}
}