{
  "type": "Feature",
  "properties": {
    "addr:full":"T\u00e5strup M\u00f8llevej 14 Holb\u00e6k Danmark 4300",
    "addr:housenumber":"14",
    "addr:postcode":"4300",
    "addr:street":"Mollevej",
    "iso:country":"DK",
    "sg:address":"T\u00e5strup M\u00f8llevej 14",
    "sg:city":"Holb\u00e6k",
    "sg:orig_category":"Tekstiler",
    "sg:phone":"+45 59 44 37 13",
    "sg:postcode":"4300",
    "sg:province":"Danmark",
    "sg:website":"www.contrasttextil.dk",
    "wof:name":"Contrast Boligtextiler",
    "wof:placetype":"venue"
},
  "geometry": {"coordinates":[76.3070983887,14.277130127],"type":"Point"}
}