{
  "type": "Feature",
  "properties": {
    "addr:full":"Marsvej 43 Randers Danmark 8900",
    "addr:housenumber":"43",
    "addr:postcode":"8900",
    "addr:street":"Marsvej",
    "iso:country":"DK",
    "sg:address":"Marsvej 43",
    "sg:city":"Randers",
    "sg:orig_category":"Slagterier",
    "sg:phone":"+45 89 19 19 19",
    "sg:postcode":"8900",
    "sg:province":"Danmark",
    "sg:website":"www.danischcrown.dk",
    "wof:name":"Danish Crown",
    "wof:placetype":"venue"
},
  "geometry": {"coordinates":[10.0588769913,56.4291954041],"type":"Point"}
}