{
  "type": "Feature",
  "properties": {
    "addr:full":"Bavnevej 40 Vamdrup Danmark 6580",
    "addr:housenumber":"40",
    "addr:postcode":"6580",
    "addr:street":"Bavnevej",
    "iso:country":"DK",
    "sg:address":"Bavnevej 40",
    "sg:city":"Vamdrup",
    "sg:orig_category":"Galvanisering",
    "sg:phone":"+45 75 58 38 88",
    "sg:postcode":"6580",
    "sg:province":"Danmark",
    "wof:name":"Sydjydsk El-Galvanisering",
    "wof:placetype":"venue"
},
  "geometry": {"coordinates":[9.3007736206,55.4239234924],"type":"Point"}
}