{
  "type": "Feature",
  "properties": {
    "addr:full":"Fmd.: Poul Randa Jensen, Nedre Strandvej 59 Hobro Danmark 9500",
    "addr:housenumber":"59",
    "addr:postcode":"9500",
    "addr:street":"Poul Randa Jensen Nedre Strandvej",
    "iso:country":"DK",
    "sg:address":"Fmd.: Poul Randa Jensen, Nedre Strandvej 59",
    "sg:city":"Hobro",
    "sg:orig_category":"Havne",
    "sg:phone":"+45 98 51 28 68",
    "sg:postcode":"9500",
    "sg:province":"Danmark",
    "wof:name":"Lystb\u00e5dehavnen",
    "wof:placetype":"venue"
},
  "geometry": {"coordinates":[9.7946596146,56.6382789612],"type":"Point"}
}