{
  "type": "Feature",
  "properties": {
    "addr:full":"Vusk\u00e6rvej 1, Tilsted Thisted Danmark 7700",
    "addr:housenumber":"1",
    "addr:postcode":"7700",
    "addr:street":"Vuskaervej;Tilsted",
    "iso:country":"DK",
    "sg:address":"Vusk\u00e6rvej 1, Tilsted",
    "sg:city":"Thisted",
    "sg:orig_category":"Kirker",
    "sg:postcode":"7700",
    "sg:province":"Danmark",
    "wof:name":"Tilsted Kirke",
    "wof:placetype":"venue"
},
  "geometry": {"coordinates":[8.6919784546,56.9556121826],"type":"Point"}
}