{
  "type": "Feature",
  "properties": {
    "addr:full":"Langebakken 1 Rungsted Kyst Danmark 2960",
    "addr:housenumber":"1",
    "addr:postcode":"2960",
    "addr:street":"Langebakken",
    "iso:country":"DK",
    "sg:address":"Langebakken 1",
    "sg:city":"Rungsted Kyst",
    "sg:orig_category":"INGENI\u00c3\u02dcRER",
    "sg:phone":"+45 45 76 05 03",
    "sg:postcode":"2960",
    "sg:province":"Danmark",
    "wof:name":"Weartec",
    "wof:placetype":"venue"
},
  "geometry": {"coordinates":[12.5506210327,55.8729133606],"type":"Point"}
}