{
  "type": "Feature",
  "properties": {
    "iso:country":"DK",
    "sg:address":"Fmd.: Peter Klemmensen, S\u00f8ndervangsvej 3, Bejstrup",
    "sg:city":"Fjerritslev",
    "sg:orig_category":"Havne",
    "sg:phone":"+45 98 21 59 31",
    "sg:postcode":"9690",
    "sg:province":"Danmark",
    "wof:name":"Haverslev Havn",
    "wof:placetype":"venue"
},
  "geometry": {"coordinates":[9.2667350769,57.0882301331],"type":"Point"}
}