{
  "type": "Feature",
  "properties": {
    "addr:full":"Lindbjergvej 22 A Ballerup Danmark 2750",
    "addr:housenumber":"22 a",
    "addr:postcode":"2750",
    "addr:street":"Lindbjergvej",
    "iso:country":"DK",
    "sg:address":"Lindbjergvej 22 A",
    "sg:city":"Ballerup",
    "sg:orig_category":"Murermestre",
    "sg:phone":"+45 44 97 51 58",
    "sg:postcode":"2750",
    "sg:province":"Danmark",
    "wof:name":"Mortensen, Flemming Juul",
    "wof:placetype":"venue"
},
  "geometry": {"coordinates":[12.3443613052,55.7383766174],"type":"Point"}
}