{
  "type": "Feature",
  "properties": {
    "iso:country":"DK",
    "sg:address":"\u00d8mosevej 4, Skovby",
    "sg:city":"Bogense",
    "sg:orig_category":"Brugsforeninger",
    "sg:phone":"+45 64 81 14 12",
    "sg:postcode":"5400",
    "sg:province":"Danmark",
    "wof:name":"Brugsen, Skovby",
    "wof:placetype":"venue"
},
  "geometry": {"coordinates":[10.0943098068,55.5637893677],"type":"Point"}
}