{
  "type": "Feature",
  "properties": {
    "addr:full":"Atterup V\u00e6nge 7 Dianalund Danmark 4293",
    "addr:housenumber":"7",
    "addr:postcode":"4293",
    "addr:street":"Vaenge",
    "iso:country":"DK",
    "sg:address":"Atterup V\u00e6nge 7",
    "sg:city":"Dianalund",
    "sg:orig_category":"Blikkenslagere",
    "sg:phone":"+45 58 26 43 32",
    "sg:postcode":"4293",
    "sg:province":"Danmark",
    "wof:name":"Anders' Gas - Vand",
    "wof:placetype":"venue"
},
  "geometry": {"coordinates":[11.517846,55.524754],"type":"Point"}
}