{
  "type": "Feature",
  "properties": {
    "addr:full":"v/ Eyvind Lindegaard Andersen, Callisensvej 13 Hellerup Danmark 2900",
    "addr:housenumber":"13",
    "addr:postcode":"2900",
    "addr:street":"Callisensvej",
    "iso:country":"DK",
    "sg:address":"v/ Eyvind Lindegaard Andersen, Callisensvej 13",
    "sg:city":"Hellerup",
    "sg:orig_category":"Grundejerforeninger",
    "sg:phone":"+45 39 62 22 77",
    "sg:postcode":"2900",
    "sg:province":"Danmark",
    "wof:name":"Hellerup-Maglegaard Sogne Grundejerforening",
    "wof:placetype":"venue"
},
  "geometry": {"coordinates":[12.5788497925,55.7413787842],"type":"Point"}
}