{
  "type": "Feature",
  "properties": {
    "addr:full":"v/ Vognmand Thorkild Jensen, L\u00f8kkensvej 664, Hundelev L\u00f8kken Danmark 9480",
    "addr:housenumber":"664",
    "addr:postcode":"9480",
    "addr:street":"Lokkensvej;Lokken",
    "iso:country":"DK",
    "sg:address":"v/ Vognmand Thorkild Jensen, L\u00f8kkensvej 664, Hundelev",
    "sg:city":"L\u00f8kken",
    "sg:orig_category":"Faglige organisationer og foreninger",
    "sg:phone":"+45 98 99 90 44",
    "sg:postcode":"9480",
    "sg:province":"Danmark",
    "wof:name":"Vognmandsforeningen Vendsyssel",
    "wof:placetype":"venue"
},
  "geometry": {"coordinates":[9.715880394,57.3703308105],"type":"Point"}
}