{
  "type": "Feature",
  "properties": {
    "addr:full":"Vinkelvej 0 Nimtofte Danmark 8581",
    "addr:housenumber":"0",
    "addr:postcode":"8581",
    "addr:street":"Vinkelvej",
    "iso:country":"DK",
    "sg:address":"Vinkelvej 0",
    "sg:city":"Nimtofte",
    "sg:orig_category":"Kirker",
    "sg:postcode":"8581",
    "sg:province":"Danmark",
    "wof:name":"Nimtofte Kirke",
    "wof:placetype":"venue"
},
  "geometry": {"coordinates":[10.5652008057,56.4089393616],"type":"Point"}
}