{
  "type": "Feature",
  "properties": {
    "addr:full":"Strandvejen 396 Asaa Danmark 9340",
    "addr:housenumber":"396",
    "addr:postcode":"9340",
    "addr:street":"Strandvejen",
    "iso:country":"DK",
    "sg:address":"Strandvejen 396",
    "sg:city":"Asaa",
    "sg:orig_category":"Autoreparation og -service",
    "sg:phone":"+45 98 85 11 27",
    "sg:postcode":"9340",
    "sg:province":"Danmark",
    "wof:name":"Strandvejens Auto Service",
    "wof:placetype":"venue"
},
  "geometry": {"coordinates":[10.4010772705,57.1460494995],"type":"Point"}
}