{
  "type": "Feature",
  "properties": {
    "iso:country":"DK",
    "sg:address":"Wilders Plads 1",
    "sg:city":"K\u00f8benhavn",
    "sg:orig_category":"Designere",
    "sg:phone":"+45 32 95 94 10",
    "sg:postcode":"1403",
    "sg:province":"Danmark",
    "wof:name":"B.O.B.L.E. Design",
    "wof:placetype":"venue"
},
  "geometry": {"coordinates":[12.5941696167,55.6755905151],"type":"Point"}
}