{
  "type": "Feature",
  "properties": {
    "iso:country":"DK",
    "sg:address":"M. P. Bruuns Gade 56",
    "sg:city":"\u00c5rhus C",
    "sg:orig_category":"Bagere",
    "sg:phone":"+45 86 12 34 47",
    "sg:postcode":"8000",
    "sg:province":"Danmark",
    "wof:name":"Schweizer Bageriet",
    "wof:placetype":"venue"
},
  "geometry": {"coordinates":[99.925011,34.243011],"type":"Point"}
}