{
  "type": "Feature",
  "properties": {
    "addr:full":"L\u00f8rupvej 19 Ringe Danmark 5750",
    "addr:housenumber":"19",
    "addr:postcode":"5750",
    "addr:street":"Lorupvej",
    "iso:country":"DK",
    "sg:address":"L\u00f8rupvej 19",
    "sg:city":"Ringe",
    "sg:orig_category":"Malervarer",
    "sg:phone":"+45 62 67 10 58",
    "sg:postcode":"5750",
    "sg:province":"Danmark",
    "wof:name":"L\u00f8rup Malervarer",
    "wof:placetype":"venue"
},
  "geometry": {"coordinates":[10.5142946243,55.2207221985],"type":"Point"}
}