{
  "type": "Feature",
  "properties": {
    "addr:full":"Frederiksv\u00e6rkvej 21 Helsinge Danmark 3200",
    "addr:housenumber":"21",
    "addr:postcode":"3200",
    "addr:street":"Frederiksvaerkvej",
    "iso:country":"DK",
    "sg:address":"Frederiksv\u00e6rkvej 21",
    "sg:city":"Helsinge",
    "sg:orig_category":"Keramik",
    "sg:phone":"+45 48 79 48 70",
    "sg:postcode":"3200",
    "sg:province":"Danmark",
    "wof:name":"Bertelsen, Chr. Ulrik",
    "wof:placetype":"venue"
},
  "geometry": {"coordinates":[12.1722803116,56.0179862976],"type":"Point"}
}