{
  "type": "Feature",
  "properties": {
    "addr:full":"Kirkekontoret, O. Vestergaard-Poulsens Vej 1 Ikast Danmark 7430",
    "addr:housenumber":"1",
    "addr:postcode":"7430",
    "addr:street":"Vestergaard-Poulsens Vej",
    "iso:country":"DK",
    "sg:address":"Kirkekontoret, O. Vestergaard-Poulsens Vej 1",
    "sg:city":"Ikast",
    "sg:orig_category":"Kirkesogne",
    "sg:phone":"+45 97 25 27 81",
    "sg:postcode":"7430",
    "sg:province":"Danmark",
    "wof:name":"Fonnesb\u00e6k Sogn",
    "wof:placetype":"venue"
},
  "geometry": {"coordinates":[9.1434116364,56.1274299622],"type":"Point"}
}