{
  "type": "Feature",
  "properties": {
    "iso:country":"DK",
    "sg:address":"Kornv\u00e6nget 3",
    "sg:city":"Ballerup",
    "sg:orig_category":"Autoforhandlere",
    "sg:phone":"+45 44 65 94 64",
    "sg:postcode":"2750",
    "sg:province":"Danmark",
    "wof:name":"L.H. Biler",
    "wof:placetype":"venue"
},
  "geometry": {"coordinates":[12.361000061,55.7301216125],"type":"Point"}
}