{
  "type": "Feature",
  "properties": {
    "addr:full":"H\u00f8jtoften 20 Skibby Danmark 4050",
    "addr:housenumber":"20",
    "addr:postcode":"4050",
    "addr:street":"Hojtoften",
    "iso:country":"DK",
    "sg:address":"H\u00f8jtoften 20",
    "sg:city":"Skibby",
    "sg:orig_category":"Revisorer",
    "sg:phone":"+45 47 51 24 12",
    "sg:postcode":"4050",
    "sg:province":"Danmark",
    "wof:name":"Birk, Kjeld",
    "wof:placetype":"venue"
},
  "geometry": {"coordinates":[11.9594116211,55.7502975464],"type":"Point"}
}