{
  "type": "Feature",
  "properties": {
    "addr:full":"Villadsgyde 8 Ebeltoft Danmark 8400",
    "addr:housenumber":"8",
    "addr:postcode":"8400",
    "addr:street":"Villadsgyde",
    "iso:country":"DK",
    "sg:address":"Villadsgyde 8",
    "sg:city":"Ebeltoft",
    "sg:orig_category":"Billedkunstnere",
    "sg:phone":"+45 86 34 63 31",
    "sg:postcode":"8400",
    "sg:province":"Danmark",
    "wof:name":"Popp, Charlotte",
    "wof:placetype":"venue"
},
  "geometry": {"coordinates":[10.676589,56.196404],"type":"Point"}
}