{
  "type": "Feature",
  "properties": {
    "addr:full":"Bag Fortet 8 Herlev Danmark 2730",
    "addr:housenumber":"8",
    "addr:postcode":"2730",
    "addr:street":"Fortet",
    "iso:country":"DK",
    "sg:address":"Bag Fortet 8",
    "sg:city":"Herlev",
    "sg:orig_category":"Revisorer",
    "sg:phone":"+45 44 94 76 40",
    "sg:postcode":"2730",
    "sg:province":"Danmark",
    "wof:name":"Egede Revision",
    "wof:placetype":"venue"
},
  "geometry": {"coordinates":[12.4520425797,55.7397956848],"type":"Point"}
}