{
  "type": "Feature",
  "properties": {
    "iso:country":"DK",
    "sg:address":"v/ S\u00f8ren Pedersen, Granh\u00f8jvej 15",
    "sg:city":"Hundested",
    "sg:orig_category":"Grundejerforeninger",
    "sg:phone":"+45 47 94 09 12",
    "sg:postcode":"3390",
    "sg:province":"Danmark",
    "wof:name":"Grundejerforeningen Sommerhusg\u00e5rden",
    "wof:placetype":"venue"
},
  "geometry": {"coordinates":[11.8530349731,55.958530426],"type":"Point"}
}