{
  "type": "Feature",
  "properties": {
    "iso:country":"DK",
    "sg:address":"Pr\u00e6steg\u00e5rds Alle 5",
    "sg:city":"Br\u00f8nsh\u00f8j",
    "sg:orig_category":"Kirkesogne",
    "sg:phone":"+45 38 28 25 05",
    "sg:postcode":"2700",
    "sg:province":"Danmark",
    "wof:name":"Br\u00f8nsh\u00f8j sogns kirkekontor",
    "wof:placetype":"venue"
},
  "geometry": {"coordinates":[-65.6866531372,-23.1981296539],"type":"Point"}
}