{
  "type": "Feature",
  "properties": {
    "addr:full":"K\u00f8benhavnsvej 228 K\u00f8ge Danmark 4600",
    "addr:housenumber":"228",
    "addr:postcode":"4600",
    "addr:street":"Kobenhavnsvej",
    "iso:country":"DK",
    "sg:address":"K\u00f8benhavnsvej 228",
    "sg:city":"K\u00f8ge",
    "sg:orig_category":"Revisorer",
    "sg:phone":"+45 56 63 37 37",
    "sg:postcode":"4600",
    "sg:province":"Danmark",
    "wof:name":"K\u00f8ge Nord Revision",
    "wof:placetype":"venue"
},
  "geometry": {"coordinates":[121.9146499634,25.0305194855],"type":"Point"}
}