{
  "type": "Feature",
  "properties": {
    "addr:full":"Fmd.: Knud G. S\u00f8rensen, Danasvej 5 Aalestrup Danmark 9620",
    "addr:housenumber":"5",
    "addr:postcode":"9620",
    "addr:street":"Knud G. Sorensen Danasvej",
    "iso:country":"DK",
    "sg:address":"Fmd.: Knud G. S\u00f8rensen, Danasvej 5",
    "sg:city":"Aalestrup",
    "sg:orig_category":"Musik og sang",
    "sg:phone":"+45 98 64 17 21",
    "sg:postcode":"9620",
    "sg:province":"Danmark",
    "wof:name":"Gedsted-Aalestrup Sangkor",
    "wof:placetype":"venue"
},
  "geometry": {"coordinates":[9.4901504517,56.6938285828],"type":"Point"}
}