{
  "type": "Feature",
  "properties": {
    "iso:country":"DK",
    "sg:address":"Slettebjerget 33, Ny Hammersholt",
    "sg:city":"Hiller\u00f8d",
    "sg:classifiers":[
        {
            "category":"Food & Beverages",
            "subcategory":"Liquor & Beverages",
            "type":"Retail Goods"
        }
    ],
    "sg:phone":"+45 48 24 31 04",
    "sg:postcode":"3400",
    "sg:province":"Danmark",
    "sg:tags":[
        "vin"
    ],
    "sg:website":"www.vincru.dk",
    "wof:name":"Vin Cru",
    "wof:placetype":"venue"
},
  "geometry": {"coordinates":[12.3056097031,55.9288215637],"type":"Point"}
}