{
  "type": "Feature",
  "properties": {
    "addr:full":"Algade 66 Middelfart Danmark 5500",
    "addr:housenumber":"66",
    "addr:postcode":"5500",
    "addr:street":"Algade",
    "iso:country":"DK",
    "sg:address":"Algade 66",
    "sg:city":"Middelfart",
    "sg:orig_category":"Glarmestre og glarmagere",
    "sg:phone":"+45 64 41 01 00",
    "sg:postcode":"5500",
    "sg:province":"Danmark",
    "wof:name":"Spring, Otto",
    "wof:placetype":"venue"
},
  "geometry": {"coordinates":[9.7342453003,55.5045852661],"type":"Point"}
}