{
  "type": "Feature",
  "properties": {
    "iso:country":"DK",
    "sg:address":"Havnevej 6",
    "sg:city":"Skagen",
    "sg:orig_category":"Grillbarer",
    "sg:phone":"+45 98 45 07 11",
    "sg:postcode":"9990",
    "sg:province":"Danmark",
    "wof:name":"Blue Burger",
    "wof:placetype":"venue"
},
  "geometry": {"coordinates":[10.5888118744,57.7217559814],"type":"Point"}
}