{
  "type": "Feature",
  "properties": {
    "addr:full":"Vesterbro 9 Odense C Danmark 5000",
    "addr:housenumber":"9",
    "addr:postcode":"5000",
    "addr:street":"Vesterbro",
    "iso:country":"DK",
    "sg:address":"Vesterbro 9",
    "sg:city":"Odense C",
    "sg:orig_category":"Glarmestre og glarmagere",
    "sg:phone":"+45 66 12 06 04",
    "sg:postcode":"5000",
    "sg:province":"Danmark",
    "wof:name":"Nielsens Eftf., C. A.",
    "wof:placetype":"venue"
},
  "geometry": {"coordinates":[10.3789167404,55.3938179016],"type":"Point"}
}