{
  "type": "Feature",
  "properties": {
    "addr:full":"Mosevej 22 Ribe Danmark 6760",
    "addr:housenumber":"22",
    "addr:postcode":"6760",
    "addr:street":"Mosevej",
    "iso:country":"DK",
    "sg:address":"Mosevej 22",
    "sg:city":"Ribe",
    "sg:classifiers":[
        {
            "category":"Communications",
            "type":"Services"
        }
    ],
    "sg:phone":"+45 75 41 13 12",
    "sg:postcode":"6760",
    "sg:province":"Danmark",
    "sg:tags":[
        "og",
        "tv",
        "radio"
    ],
    "wof:name":"2tal Radio Graff",
    "wof:placetype":"venue"
},
  "geometry": {"coordinates":[8.7830753326,55.3431777954],"type":"Point"}
}