{
  "type": "Feature",
  "properties": {
    "iso:country":"DK",
    "sg:address":"R\u00e5dmandsgade 52",
    "sg:city":"K\u00f8benhavn N",
    "sg:orig_category":"Tyverisikring",
    "sg:phone":"+45 70 22 75 75",
    "sg:postcode":"2200",
    "sg:province":"Danmark",
    "sg:website":"www.stop-tyven.dk",
    "wof:name":"GitterGruppen A/S",
    "wof:placetype":"venue"
},
  "geometry": {"coordinates":[-96.8056793213,46.9482307434],"type":"Point"}
}