{
  "type": "Feature",
  "properties": {
    "addr:full":"Bredgade 21, M\u00f8nsted Viborg Danmark 8800",
    "addr:housenumber":"21",
    "addr:postcode":"8800",
    "addr:street":"Bredgade",
    "iso:country":"DK",
    "sg:address":"Bredgade 21, M\u00f8nsted",
    "sg:city":"Viborg",
    "sg:classifiers":[
        {
            "category":"Communications",
            "type":"Services"
        }
    ],
    "sg:phone":"+45 86 64 66 46",
    "sg:postcode":"8800",
    "sg:province":"Danmark",
    "sg:tags":[
        "og",
        "tv",
        "radio"
    ],
    "wof:name":"M\u00f8nsted Radio/TV",
    "wof:placetype":"venue"
},
  "geometry": {"coordinates":[9.4071502686,56.452671051],"type":"Point"}
}