{
  "type": "Feature",
  "properties": {
    "addr:full":"Kongebrogade 46 Kolding Danmark 6000",
    "addr:housenumber":"46",
    "addr:postcode":"6000",
    "addr:street":"Kongebrogade",
    "iso:country":"DK",
    "sg:address":"Kongebrogade 46",
    "sg:city":"Kolding",
    "sg:orig_category":"Forsikringer",
    "sg:phone":"+45 76 30 01 04",
    "sg:postcode":"6000",
    "sg:province":"Danmark",
    "wof:name":"Provinzial Danmark A/S",
    "wof:placetype":"venue"
},
  "geometry": {"coordinates":[9.4772157669,55.4853096008],"type":"Point"}
}