{
  "type": "Feature",
  "properties": {
    "addr:full":"Jernbanegade 28 A S\u00f8nderborg Danmark 6400",
    "addr:housenumber":"28 a",
    "addr:postcode":"6400",
    "addr:street":"Jernbanegade",
    "iso:country":"DK",
    "sg:address":"Jernbanegade 28 A",
    "sg:city":"S\u00f8nderborg",
    "sg:orig_category":"Arbejdsformidling",
    "sg:phone":"+45 74 42 33 41",
    "sg:postcode":"6400",
    "sg:province":"Danmark",
    "wof:name":"Arbejdsmarkeds Center S\u00f8nderborg.",
    "wof:placetype":"venue"
},
  "geometry": {"coordinates":[9.7914600372,54.9104385376],"type":"Point"}
}