{
  "type": "Feature",
  "properties": {
    "addr:full":"S\u00f8ndergade 26 Toftlund Danmark 6520",
    "addr:housenumber":"26",
    "addr:postcode":"6520",
    "addr:street":"Sondergade",
    "iso:country":"DK",
    "sg:address":"S\u00f8ndergade 26",
    "sg:city":"Toftlund",
    "sg:classifiers":[
        {
            "category":"Manufacturing",
            "subcategory":"Tobacco Products",
            "type":"Manufacturing & Wholesale Goods"
        }
    ],
    "sg:phone":"+45 74 83 11 16",
    "sg:postcode":"6520",
    "sg:province":"Danmark",
    "sg:tags":[
        "manufacturer"
    ],
    "wof:name":"Thea - Lautrup's Eftf.",
    "wof:placetype":"venue"
},
  "geometry": {"coordinates":[9.0641384125,55.1906661987],"type":"Point"}
}