{
  "type": "Feature",
  "properties": {
    "addr:full":"Jessens Mole 9 A Svendborg Danmark 5700",
    "addr:housenumber":"9 a",
    "addr:postcode":"5700",
    "addr:street":"Jessens Mole",
    "iso:country":"DK",
    "sg:address":"Jessens Mole 9 A",
    "sg:city":"Svendborg",
    "sg:orig_category":"Spedition",
    "sg:phone":"+45 62 21 26 00",
    "sg:postcode":"5700",
    "sg:province":"Danmark",
    "sg:website":"www.bjerrum-jensen.dk",
    "wof:name":"Bjerrum & Jensen ApS",
    "wof:placetype":"venue"
},
  "geometry": {"coordinates":[10.6138715744,55.0602493286],"type":"Point"}
}