{
  "type": "Feature",
  "properties": {
    "addr:full":"Ribevej 11 Randers Danmark 8900",
    "addr:housenumber":"11",
    "addr:postcode":"8900",
    "addr:street":"Ribevej",
    "iso:country":"DK",
    "sg:address":"Ribevej 11",
    "sg:city":"Randers",
    "sg:orig_category":"Autoforhandlere",
    "sg:phone":"+45 87 11 35 81",
    "sg:postcode":"8900",
    "sg:province":"Danmark",
    "wof:name":"Kronjyllands Bilcenter APS",
    "wof:placetype":"venue"
},
  "geometry": {"coordinates":[10.0514593124,56.4346466064],"type":"Point"}
}