{
  "type": "Feature",
  "properties": {
    "addr:full":"Kong Georgs Vej 114, 4. tv. Frederiksberg Danmark 2000",
    "addr:housenumber":"114 4 tv.",
    "addr:postcode":"2000",
    "addr:street":"Kong Georgs Vej",
    "iso:country":"DK",
    "sg:address":"Kong Georgs Vej 114, 4. tv.",
    "sg:city":"Frederiksberg",
    "sg:orig_category":"Alternativ behandling",
    "sg:phone":"+45 38 10 56 50",
    "sg:postcode":"2000",
    "sg:province":"Danmark",
    "wof:name":"Harder, Emely",
    "wof:placetype":"venue"
},
  "geometry": {"coordinates":[12.5299301147,55.6787872314],"type":"Point"}
}