{
  "type": "Feature",
  "properties": {
    "addr:full":"Fmd.: Ove Nielsen, \u00c5bakkevej 48, Bro Brenderup Danmark 5464",
    "addr:housenumber":"48",
    "addr:postcode":"5464",
    "addr:street":"Ove;Aabakkevej",
    "iso:country":"DK",
    "sg:address":"Fmd.: Ove Nielsen, \u00c5bakkevej 48, Bro",
    "sg:city":"Brenderup",
    "sg:orig_category":"Borger- og beboerforeninger",
    "sg:phone":"+45 64 44 20 41",
    "sg:postcode":"5464",
    "sg:province":"Danmark",
    "wof:name":"Brenderup Borgerforening",
    "wof:placetype":"venue"
},
  "geometry": {"coordinates":[9.956905365,55.5179595947],"type":"Point"}
}