{
  "type": "Feature",
  "properties": {
    "addr:full":"Fmd.: Jeanette Nielsen, Villemoesvej 2, Vejrum Hjerm Danmark 7560",
    "addr:housenumber":"2",
    "addr:postcode":"7560",
    "addr:street":"Villemoesvej",
    "iso:country":"DK",
    "sg:address":"Fmd.: Jeanette Nielsen, Villemoesvej 2, Vejrum",
    "sg:city":"Hjerm",
    "sg:orig_category":"Hobbybetonede foreninger",
    "sg:phone":"+45 97 46 43 17",
    "sg:postcode":"7560",
    "sg:province":"Danmark",
    "wof:name":"Hjerm Havekreds",
    "wof:placetype":"venue"
},
  "geometry": {"coordinates":[8.6395950317,56.4384765625],"type":"Point"}
}