{
  "type": "Feature",
  "properties": {
    "iso:country":"DK",
    "sg:address":"Adelgade 11",
    "sg:city":"Kolding",
    "sg:classifiers":[
        {
            "category":"Banks & Credit Unions",
            "subcategory":"Investment Brokerage",
            "type":"Services"
        }
    ],
    "sg:phone":"+45 75 50 95 71",
    "sg:postcode":"6000",
    "sg:province":"Danmark",
    "sg:tags":[
        "healing"
    ],
    "wof:name":"Center for healig og terapi",
    "wof:placetype":"venue"
},
  "geometry": {"coordinates":[9.4722042084,55.4909324646],"type":"Point"}
}