{
  "type": "Feature",
  "properties": {
    "addr:full":"Valdemarsgade 34 K\u00f8benhavn Danmark 1665",
    "addr:housenumber":"34",
    "addr:postcode":"1665",
    "addr:street":"Valdemarsgade",
    "iso:country":"DK",
    "sg:address":"Valdemarsgade 34",
    "sg:city":"K\u00f8benhavn",
    "sg:orig_category":"Gaveartikler",
    "sg:phone":"+45 33 79 30 29",
    "sg:postcode":"1665",
    "sg:province":"Danmark",
    "wof:name":"Antikvit",
    "wof:placetype":"venue"
},
  "geometry": {"coordinates":[12.548740387,55.671081543],"type":"Point"}
}