{
  "type": "Feature",
  "properties": {
    "addr:full":"Skovby Bygade 12 Vojens Danmark 6500",
    "addr:housenumber":"12",
    "addr:postcode":"6500",
    "addr:street":"Skovby Bygade",
    "iso:country":"DK",
    "sg:address":"Skovby Bygade 12",
    "sg:city":"Vojens",
    "sg:orig_category":"Forsamlingshuse",
    "sg:postcode":"6500",
    "sg:province":"Danmark",
    "wof:name":"Skovby Forsamlingshus",
    "wof:placetype":"venue"
},
  "geometry": {"coordinates":[9.3823003769,55.1691055298],"type":"Point"}
}