{
  "type": "Feature",
  "properties": {
    "addr:full":"R\u00f8nnevej 1  Herning Danmark 7400",
    "addr:housenumber":"1",
    "addr:postcode":"7400",
    "addr:street":"Ronnevej",
    "iso:country":"DK",
    "sg:address":"R\u00f8nnevej 1 ",
    "sg:city":"Herning",
    "sg:classifiers":[
        {
            "category":"Shopping",
            "subcategory":"Clothing, Apparel, & Fashions",
            "type":"Retail Goods"
        }
    ],
    "sg:phone":"+45 97 21 64 66",
    "sg:postcode":"7400",
    "sg:province":"Danmark",
    "sg:tags":[
        "clothes"
    ],
    "wof:name":"KA BOO KI A/S",
    "wof:placetype":"venue"
},
  "geometry": {"coordinates":[8.9940853119,56.150604248],"type":"Point"}
}