{
  "type": "Feature",
  "properties": {
    "addr:full":"Kystvej 15 Gr\u00e5sten Danmark 6300",
    "addr:housenumber":"15",
    "addr:postcode":"6300",
    "addr:street":"Kystvej",
    "iso:country":"DK",
    "sg:address":"Kystvej 15",
    "sg:city":"Gr\u00e5sten",
    "sg:orig_category":"Kulturelle foreninger",
    "sg:phone":"+45 74 65 05 39",
    "sg:postcode":"6300",
    "sg:province":"Danmark",
    "wof:name":"Deutscher Ruderverein Gravenstein",
    "wof:placetype":"venue"
},
  "geometry": {"coordinates":[25.3302497864,60.2151107788],"type":"Point"}
}