{
  "type": "Feature",
  "properties": {
    "iso:country":"DK",
    "sg:address":"\u00d8stergade 7",
    "sg:city":"Silkeborg",
    "sg:orig_category":"Cykler",
    "sg:phone":"+45 86 82 18 41",
    "sg:postcode":"8600",
    "sg:province":"Danmark",
    "wof:name":"Fri Cykler",
    "wof:placetype":"venue"
},
  "geometry": {"coordinates":[9.5509662628,56.1704368591],"type":"Point"}
}