{
  "type": "Feature",
  "properties": {
    "addr:full":"K\u00e6rvej 20 Roslev Danmark 7870",
    "addr:housenumber":"20",
    "addr:postcode":"7870",
    "addr:street":"Kaervej",
    "iso:country":"DK",
    "sg:address":"K\u00e6rvej 20",
    "sg:city":"Roslev",
    "sg:orig_category":"Trossamfund uden for folkekirken",
    "sg:phone":"+45 97 57 21 71",
    "sg:postcode":"7870",
    "sg:province":"Danmark",
    "wof:name":"Jehovas Vidner Rigssal",
    "wof:placetype":"venue"
},
  "geometry": {"coordinates":[8.9858865738,56.7079353333],"type":"Point"}
}