{
  "type": "Feature",
  "properties": {
    "addr:full":"M\u00f8lleg\u00e5rdsvej 1, N\u00e6sby Odense N Danmark 5270",
    "addr:housenumber":"1",
    "addr:postcode":"5270",
    "addr:street":"Mollegaardsvej;Naesby",
    "iso:country":"DK",
    "sg:address":"M\u00f8lleg\u00e5rdsvej 1, N\u00e6sby",
    "sg:city":"Odense N",
    "sg:orig_category":"Malerforretninger",
    "sg:phone":"+45 66 18 35 66",
    "sg:postcode":"5270",
    "sg:province":"Danmark",
    "wof:name":"Henriksen, Niels Ringsing",
    "wof:placetype":"venue"
},
  "geometry": {"coordinates":[10.3306798935,55.4711418152],"type":"Point"}
}