{
  "type": "Feature",
  "properties": {
    "addr:full":"Danmarksgade 2 Aulum Danmark 7490",
    "addr:housenumber":"2",
    "addr:postcode":"7490",
    "addr:street":"Danmarksgade",
    "iso:country":"DK",
    "sg:address":"Danmarksgade 2",
    "sg:city":"Aulum",
    "sg:orig_category":"Grillbarer",
    "sg:phone":"+45 97 47 17 89",
    "sg:postcode":"7490",
    "sg:province":"Danmark",
    "wof:name":"China Grill & Cafe",
    "wof:placetype":"venue"
},
  "geometry": {"coordinates":[8.7971544266,56.266040802],"type":"Point"}
}