{
  "type": "Feature",
  "properties": {
    "iso:country":"DK",
    "sg:address":"Errindlevvej 0",
    "sg:city":"Errindlev",
    "sg:orig_category":"Kirker",
    "sg:postcode":"4895",
    "sg:province":"Danmark",
    "wof:name":"Errindlev Kirke",
    "wof:placetype":"venue"
},
  "geometry": {"coordinates":[11.4945898056,54.6736488342],"type":"Point"}
}