{
  "type": "Feature",
  "properties": {
    "iso:country":"DK",
    "sg:address":"Jernholmen 38",
    "sg:city":"Hvidovre",
    "sg:orig_category":"INGENI\u00c3\u02dcRER",
    "sg:phone":"+45 36 34 43 00",
    "sg:postcode":"2650",
    "sg:province":"Danmark",
    "wof:name":"Larsen & Frederiksen Elberegning ApS",
    "wof:placetype":"venue"
},
  "geometry": {"coordinates":[12.4890670776,55.607219696],"type":"Point"}
}