{
  "type": "Feature",
  "properties": {
    "iso:country":"DK",
    "sg:address":"Lindevangs Alle 6-12",
    "sg:city":"Frederiksberg",
    "sg:orig_category":"\u00c3\u02dcvrige skoler",
    "sg:phone":"+45 38 14 52 00",
    "sg:postcode":"2000",
    "sg:province":"Danmark",
    "sg:website":"www.dfhnet.dk",
    "wof:name":"Danmarks Forvaltningsh\u00f8jskole",
    "wof:placetype":"venue"
},
  "geometry": {"coordinates":[12.5178394318,55.6798973083],"type":"Point"}
}