{
  "type": "Feature",
  "properties": {
    "addr:full":"L\u00e6ss\u00f8egade 41 Kolding Danmark 6000",
    "addr:housenumber":"41",
    "addr:postcode":"6000",
    "addr:street":"Laessoegade",
    "iso:country":"DK",
    "sg:address":"L\u00e6ss\u00f8egade 41",
    "sg:city":"Kolding",
    "sg:orig_category":"Tagrensning",
    "sg:phone":"+45 75 54 15 36",
    "sg:postcode":"6000",
    "sg:province":"Danmark",
    "wof:name":"GR Tagrens",
    "wof:placetype":"venue"
},
  "geometry": {"coordinates":[9.4733953476,55.4863586426],"type":"Point"}
}