{
  "type": "Feature",
  "properties": {
    "addr:full":"Bavnevej 38 Vamdrup Danmark 6580",
    "addr:housenumber":"38",
    "addr:postcode":"6580",
    "addr:street":"Bavnevej",
    "iso:country":"DK",
    "sg:address":"Bavnevej 38",
    "sg:city":"Vamdrup",
    "sg:orig_category":"Autoforhandlere",
    "sg:phone":"+45 75 58 33 46",
    "sg:postcode":"6580",
    "sg:province":"Danmark",
    "wof:name":"Bechs Auto Vamdrup ApS",
    "wof:placetype":"venue"
},
  "geometry": {"coordinates":[9.2981443405,55.4250335693],"type":"Point"}
}