{
  "type": "Feature",
  "properties": {
    "iso:country":"DK",
    "sg:address":"Sognepr\u00e6st: Kirsten Clement (K/B), Bredgade 40",
    "sg:city":"Skamby",
    "sg:orig_category":"Kirkesogne",
    "sg:phone":"+45 64 85 11 79",
    "sg:postcode":"5485",
    "sg:province":"Danmark",
    "sg:website":"www.skambykirke.dk",
    "wof:name":"Skamby sogn",
    "wof:placetype":"venue"
},
  "geometry": {"coordinates":[10.2746753693,55.5210037231],"type":"Point"}
}