{
  "type": "Feature",
  "properties": {
    "iso:country":"DK",
    "sg:address":"Graven 6",
    "sg:city":"Horsens",
    "sg:orig_category":"Genbrugscentre",
    "sg:phone":"+45 75 61 62 63",
    "sg:postcode":"8700",
    "sg:province":"Danmark",
    "wof:name":"Kirkens Korsh\u00e6r Second Hand Shop",
    "wof:placetype":"venue"
},
  "geometry": {"coordinates":[9.8482513428,55.862575531],"type":"Point"}
}