{
  "type": "Feature",
  "properties": {
    "iso:country":"DK",
    "sg:address":"Bredahlsgade 1 ",
    "sg:city":"Slagelse",
    "sg:classifiers":[
        {
            "category":"Professional",
            "subcategory":"Business Services",
            "type":"Services"
        }
    ],
    "sg:phone":"+45 58 56 70 00",
    "sg:postcode":"4200",
    "sg:province":"Danmark",
    "sg:tags":[
        "advice"
    ],
    "wof:name":"SELANDIA CENTER FOR ERHVERVSUDDANNELSE",
    "wof:placetype":"venue"
},
  "geometry": {"coordinates":[11.3363046646,55.403678894],"type":"Point"}
}