{
  "type": "Feature",
  "properties": {
    "addr:full":"Jens Bangs Gade 4 Aalborg Danmark 9000",
    "addr:housenumber":"4",
    "addr:postcode":"9000",
    "addr:street":"Jens Bangs Gade",
    "iso:country":"DK",
    "sg:address":"Jens Bangs Gade 4",
    "sg:city":"Aalborg",
    "sg:orig_category":"Smykker",
    "sg:phone":"+45 98 16 66 55",
    "sg:postcode":"9000",
    "sg:province":"Danmark",
    "wof:name":"N\u00f8ddebo, Vibeke",
    "wof:placetype":"venue"
},
  "geometry": {"coordinates":[9.9156904221,57.0491523743],"type":"Point"}
}