{
  "type": "Feature",
  "properties": {
    "addr:full":"R\u00e5dhuset, Adelgade 61 Nysted Danmark 4880",
    "addr:housenumber":"61",
    "addr:postcode":"4880",
    "addr:street":"Adelgade",
    "iso:country":"DK",
    "sg:address":"R\u00e5dhuset, Adelgade 61",
    "sg:city":"Nysted",
    "sg:orig_category":"Kommunen",
    "sg:phone":"+45 54 87 12 22",
    "sg:postcode":"4880",
    "sg:province":"Danmark",
    "sg:website":"www.nysted.dk",
    "wof:name":"Nysted Kommune",
    "wof:placetype":"venue"
},
  "geometry": {"coordinates":[11.7297554016,54.6671638489],"type":"Point"}
}