{
  "type": "Feature",
  "properties": {
    "iso:country":"DK",
    "sg:address":"Langgade 16",
    "sg:city":"Nyk\u00f8bing",
    "sg:orig_category":"Blomsterhandlere",
    "sg:phone":"+45 54 85 09 59",
    "sg:postcode":"4800",
    "sg:province":"Danmark",
    "wof:name":"la France",
    "wof:placetype":"venue"
},
  "geometry": {"coordinates":[-114.0768203735,46.4432411194],"type":"Point"}
}