{
  "type": "Feature",
  "properties": {
    "addr:full":"Griffenfeldsgade 6 K\u00f8benhavn N Danmark 2200",
    "addr:housenumber":"6",
    "addr:postcode":"2200",
    "addr:street":"Griffenfeldsgade;N Danmark",
    "iso:country":"DK",
    "sg:address":"Griffenfeldsgade 6",
    "sg:city":"K\u00f8benhavn N",
    "sg:orig_category":"Bodegaer",
    "sg:phone":"+45 35 39 23 80",
    "sg:postcode":"2200",
    "sg:province":"Danmark",
    "wof:name":"N\u00f8rrehus Cafe",
    "wof:placetype":"venue"
},
  "geometry": {"coordinates":[12.555434227,55.6895027161],"type":"Point"}
}