{
  "type": "Feature",
  "properties": {
    "iso:country":"DK",
    "sg:address":"Vesterhavsgade 54, Vorup\u00f8r",
    "sg:city":"Thisted",
    "sg:orig_category":"Bagere",
    "sg:phone":"+45 97 93 80 21",
    "sg:postcode":"7700",
    "sg:province":"Danmark",
    "wof:name":"Andersens Bageri, Brdr.",
    "wof:placetype":"venue"
},
  "geometry": {"coordinates":[8.691978,56.955612],"type":"Point"}
}