{
  "type": "Feature",
  "properties": {
    "addr:full":"Sognepr\u00e6st: Frederik Birkler (K/B), Teglg\u00e5rdvej 30, Hersom Hobro Danmark 9500",
    "addr:housenumber":"k / b;30",
    "addr:postcode":"9500",
    "addr:street":"Frederik Birkler;Teglgaardvej",
    "iso:country":"DK",
    "sg:address":"Sognepr\u00e6st: Frederik Birkler (K/B), Teglg\u00e5rdvej 30, Hersom",
    "sg:city":"Hobro",
    "sg:orig_category":"Kirkesogne",
    "sg:phone":"+45 86 69 00 09",
    "sg:postcode":"9500",
    "sg:province":"Danmark",
    "wof:name":"Hersom, Klejtrup og V. Bjerregrav Sogne",
    "wof:placetype":"venue"
},
  "geometry": {"coordinates":[9.7946596146,56.6382789612],"type":"Point"}
}