{
  "type": "Feature",
  "properties": {
    "addr:full":"Fmd.: Finn Galatius, Strandstr\u00e6de 43 Marstal Danmark 5960",
    "addr:housenumber":"43",
    "addr:postcode":"5960",
    "addr:street":"Strandstraede",
    "iso:country":"DK",
    "sg:address":"Fmd.: Finn Galatius, Strandstr\u00e6de 43",
    "sg:city":"Marstal",
    "sg:orig_category":"Faglige organisationer og foreninger",
    "sg:phone":"+45 62 53 28 17",
    "sg:postcode":"5960",
    "sg:province":"Danmark",
    "wof:name":"Dansk Arbejdsgiverforening",
    "wof:placetype":"venue"
},
  "geometry": {"coordinates":[10.5212097168,54.8543815613],"type":"Point"}
}