{
  "type": "Feature",
  "properties": {
    "iso:country":"DK",
    "sg:address":"Kongelysvej 23",
    "sg:city":"Gentofte",
    "sg:orig_category":"Gulvafslibning",
    "sg:phone":"+45 39 68 00 60",
    "sg:postcode":"2820",
    "sg:province":"Danmark",
    "sg:website":"www.vistis-gulvservice.dk",
    "wof:name":"Visti's Gulvservice A/S",
    "wof:placetype":"venue"
},
  "geometry": {"coordinates":[12.53632164,55.7381134033],"type":"Point"}
}