{
  "type": "Feature",
  "properties": {
    "addr:full":"Bakkedraget 13 Lem Danmark 6940",
    "addr:housenumber":"13",
    "addr:postcode":"6940",
    "addr:street":"Bakkedraget",
    "iso:country":"DK",
    "sg:address":"Bakkedraget 13",
    "sg:city":"Lem",
    "sg:orig_category":"Investering",
    "sg:phone":"+45 97 34 13 06",
    "sg:postcode":"6940",
    "sg:province":"Danmark",
    "wof:name":"BKN-Invest ApS",
    "wof:placetype":"venue"
},
  "geometry": {"coordinates":[8.387793541,56.0333824158],"type":"Point"}
}