{
  "type": "Feature",
  "properties": {
    "iso:country":"DK",
    "sg:address":"Smedevej 14 ",
    "sg:city":"Ikast",
    "sg:classifiers":[
        {
            "category":"Home & Garden",
            "subcategory":"Home Furnishings",
            "type":"Retail Goods"
        }
    ],
    "sg:phone":"+45 97 15 35 44",
    "sg:postcode":"7430",
    "sg:province":"Danmark",
    "sg:tags":[
        "household"
    ],
    "wof:name":"LAURIDS PEDERSEN, IKAST A/S",
    "wof:placetype":"venue"
},
  "geometry": {"coordinates":[9.1766386032,56.1278533936],"type":"Point"}
}