{
  "type": "Feature",
  "properties": {
    "iso:country":"DK",
    "sg:address":"S\u00f8vej 1",
    "sg:city":"Borup",
    "sg:orig_category":"Dag- og distriktsblade",
    "sg:phone":"+45 57 52 22 88",
    "sg:postcode":"4140",
    "sg:province":"Danmark",
    "wof:name":"Lokalavisen Heden/Midtsj\u00e6llands Avis",
    "wof:placetype":"venue"
},
  "geometry": {"coordinates":[11.9749145508,55.4920845032],"type":"Point"}
}