{
  "type": "Feature",
  "properties": {
    "addr:full":"v/ Vivi Guldager, Bisserup Havnevej 60, Bisserup Rude Danmark 4243",
    "addr:housenumber":"60",
    "addr:postcode":"4243",
    "addr:street":"Bisserup Havnevej;Bisserup",
    "iso:country":"DK",
    "sg:address":"v/ Vivi Guldager, Bisserup Havnevej 60, Bisserup",
    "sg:city":"Rude",
    "sg:orig_category":"Forsamlingshuse",
    "sg:phone":"+45 55 45 93 60",
    "sg:postcode":"4243",
    "sg:province":"Danmark",
    "wof:name":"Bisserup Forsamlingshus",
    "wof:placetype":"venue"
},
  "geometry": {"coordinates":[11.4970302582,55.2066993713],"type":"Point"}
}