{
  "type": "Feature",
  "properties": {
    "addr:full":"Gentoftegade 16 Gentofte Danmark 2820",
    "addr:housenumber":"16",
    "addr:postcode":"2820",
    "addr:street":"Gentoftegade",
    "iso:country":"DK",
    "sg:address":"Gentoftegade 16",
    "sg:city":"Gentofte",
    "sg:orig_category":"Helsekost",
    "sg:phone":"+45 39 65 66 49",
    "sg:postcode":"2820",
    "sg:province":"Danmark",
    "wof:name":"Charonn Consult",
    "wof:placetype":"venue"
},
  "geometry": {"coordinates":[12.5414228439,55.7507171631],"type":"Point"}
}