{
  "type": "Feature",
  "properties": {
    "addr:full":"Absalonsvej 2 Herning Danmark 7400",
    "addr:housenumber":"2",
    "addr:postcode":"7400",
    "addr:street":"Absalonsvej",
    "iso:country":"DK",
    "sg:address":"Absalonsvej 2",
    "sg:city":"Herning",
    "sg:orig_category":"Databehandling",
    "sg:phone":"+45 96 26 67 00",
    "sg:postcode":"7400",
    "sg:province":"Danmark",
    "wof:name":"Bankernes EDB Central",
    "wof:placetype":"venue"
},
  "geometry": {"coordinates":[9.0004301071,56.1341400146],"type":"Point"}
}