{
  "type": "Feature",
  "properties": {
    "addr:full":"Hedager 1 Greve Danmark 2670",
    "addr:housenumber":"1",
    "addr:postcode":"2670",
    "addr:street":"Hedager",
    "iso:country":"DK",
    "sg:address":"Hedager 1",
    "sg:city":"Greve",
    "sg:orig_category":"Farve- og stilanalyse",
    "sg:phone":"+45 43 90 89 98",
    "sg:postcode":"2670",
    "sg:province":"Danmark",
    "wof:name":"Beauty For All Seasons",
    "wof:placetype":"venue"
},
  "geometry": {"coordinates":[12.2925548553,55.5886383057],"type":"Point"}
}