{
  "type": "Feature",
  "properties": {
    "iso:country":"DK",
    "sg:address":"Fmd.: Peder Ottesen, M\u00e5gestien 8, Mullerup",
    "sg:city":"Slagelse",
    "sg:orig_category":"Hobbybetonede foreninger",
    "sg:phone":"+45 58 85 80 85",
    "sg:postcode":"4200",
    "sg:province":"Danmark",
    "wof:name":"Nord-Vestsj\u00e6llands Flyveklub",
    "wof:placetype":"venue"
},
  "geometry": {"coordinates":[11.3569850922,55.4050865173],"type":"Point"}
}