{
  "type": "Feature",
  "properties": {
    "addr:full":"Industrivej 14 Christiansfeld Danmark 6070",
    "addr:housenumber":"14",
    "addr:postcode":"6070",
    "addr:street":"Industrivej",
    "iso:country":"DK",
    "sg:address":"Industrivej 14",
    "sg:city":"Christiansfeld",
    "sg:orig_category":"Autosadelmagere",
    "sg:phone":"+45 74 56 29 97",
    "sg:postcode":"6070",
    "sg:province":"Danmark",
    "wof:name":"Christiansfeld Autopolstring",
    "wof:placetype":"venue"
},
  "geometry": {"coordinates":[9.4854078293,55.3621635437],"type":"Point"}
}