{
  "type": "Feature",
  "properties": {
    "addr:full":"Merkurv\u00e6nget 2 Fredericia Danmark 7000",
    "addr:housenumber":"2",
    "addr:postcode":"7000",
    "addr:street":"Merkurvaenget",
    "iso:country":"DK",
    "sg:address":"Merkurv\u00e6nget 2",
    "sg:city":"Fredericia",
    "sg:orig_category":"Specialskoler for handicappede",
    "sg:phone":"+45 76 20 11 00",
    "sg:postcode":"7000",
    "sg:province":"Danmark",
    "wof:name":"Fredericiaskolen",
    "wof:placetype":"venue"
},
  "geometry": {"coordinates":[9.7591047287,55.566368103],"type":"Point"}
}