{
  "type": "Feature",
  "properties": {
    "addr:full":"Sydvestvej 29 Horsens Danmark 8700",
    "addr:housenumber":"29",
    "addr:postcode":"8700",
    "addr:street":"Sydvestvej",
    "iso:country":"DK",
    "sg:address":"Sydvestvej 29",
    "sg:city":"Horsens",
    "sg:orig_category":"Danseundervisning",
    "sg:phone":"+45 75 63 07 06",
    "sg:postcode":"8700",
    "sg:province":"Danmark",
    "wof:name":"Sappy Dance Team",
    "wof:placetype":"venue"
},
  "geometry": {"coordinates":[9.8494682312,55.8276863098],"type":"Point"}
}