{
  "type": "Feature",
  "properties": {
    "addr:full":"Karisevej 66, Dalby Haslev Danmark 4690",
    "addr:housenumber":"66",
    "addr:postcode":"4690",
    "addr:street":"Karisevej",
    "iso:country":"DK",
    "sg:address":"Karisevej 66, Dalby",
    "sg:city":"Haslev",
    "sg:orig_category":"Forsamlingshuse",
    "sg:phone":"+45 56 39 83 23",
    "sg:postcode":"4690",
    "sg:province":"Danmark",
    "wof:name":"Dalby Forsamlingshus, I/S",
    "wof:placetype":"venue"
},
  "geometry": {"coordinates":[11.9678049088,55.3230895996],"type":"Point"}
}