{
  "type": "Feature",
  "properties": {
    "addr:full":"Egelundsvej 8, Rostrup Arden Danmark 9510",
    "addr:housenumber":"8",
    "addr:postcode":"9510",
    "addr:street":"Egelundsvej",
    "iso:country":"DK",
    "sg:address":"Egelundsvej 8, Rostrup",
    "sg:city":"Arden",
    "sg:orig_category":"Fodterapeuter",
    "sg:phone":"+45 98 56 63 20",
    "sg:postcode":"9510",
    "sg:province":"Danmark",
    "wof:name":"Klinik For Fodterapi",
    "wof:placetype":"venue"
},
  "geometry": {"coordinates":[9.8580989838,56.7683296204],"type":"Point"}
}