{
  "type": "Feature",
  "properties": {
    "addr:full":"Vigerslevvej 44 Valby Danmark 2500",
    "addr:housenumber":"44",
    "addr:postcode":"2500",
    "addr:street":"Vigerslevvej",
    "iso:country":"DK",
    "sg:address":"Vigerslevvej 44",
    "sg:city":"Valby",
    "sg:orig_category":"Import-eksport",
    "sg:phone":"+45 36 30 58 90",
    "sg:postcode":"2500",
    "sg:province":"Danmark",
    "wof:name":"Scan East Import & Eksport",
    "wof:placetype":"venue"
},
  "geometry": {"coordinates":[12.4876747131,55.6681785583],"type":"Point"}
}