{
  "type": "Feature",
  "properties": {
    "addr:full":"Torvet 2, Kliplev Aabenraa Danmark 6200",
    "addr:housenumber":"2",
    "addr:postcode":"6200",
    "addr:street":"Torvet;Kliplev",
    "iso:country":"DK",
    "sg:address":"Torvet 2, Kliplev",
    "sg:city":"Aabenraa",
    "sg:orig_category":"Forsamlingshuse",
    "sg:phone":"+45 74 68 76 18",
    "sg:postcode":"6200",
    "sg:province":"Danmark",
    "wof:name":"I. M\u00f8rks Kro",
    "wof:placetype":"venue"
},
  "geometry": {"coordinates":[9.4213867188,55.0449562073],"type":"Point"}
}