{
  "type": "Feature",
  "properties": {
    "iso:country":"DK",
    "sg:address":"Krohaven 20",
    "sg:city":"Greve",
    "sg:orig_category":"Vinduespolering",
    "sg:phone":"+45 43 61 11 46",
    "sg:postcode":"2670",
    "sg:province":"Danmark",
    "wof:name":"G.S. Service",
    "wof:placetype":"venue"
},
  "geometry": {"coordinates":[12.2631225586,55.6088142395],"type":"Point"}
}