{
  "type": "Feature",
  "properties": {
    "addr:full":"Herningvej 37 Aalborg \u00d8 Danmark 9220",
    "addr:housenumber":"37",
    "addr:postcode":"9220",
    "addr:street":"Herningvej;Danmark",
    "iso:country":"DK",
    "sg:address":"Herningvej 37",
    "sg:city":"Aalborg \u00d8",
    "sg:orig_category":"Fritidscentre",
    "sg:phone":"+45 98 15 65 68",
    "sg:postcode":"9220",
    "sg:province":"Danmark",
    "wof:name":"Fritidscentret Herningvej",
    "wof:placetype":"venue"
},
  "geometry": {"coordinates":[9.9842767715,57.0277557373],"type":"Point"}
}