{
  "type": "Feature",
  "properties": {
    "addr:full":"Jernbanegade 2 D Slagelse Danmark 4200",
    "addr:housenumber":"2 d",
    "addr:postcode":"4200",
    "addr:street":"Jernbanegade",
    "iso:country":"DK",
    "sg:address":"Jernbanegade 2 D",
    "sg:city":"Slagelse",
    "sg:orig_category":"Dyrehandlere",
    "sg:phone":"+45 58 50 32 03",
    "sg:postcode":"4200",
    "sg:province":"Danmark",
    "wof:name":"Slagelse Dyrecenter",
    "wof:placetype":"venue"
},
  "geometry": {"coordinates":[11.353471756,55.4050712585],"type":"Point"}
}