{
  "type": "Feature",
  "properties": {
    "addr:full":"Munkevej 7 C Thisted Danmark 7700",
    "addr:housenumber":"7 c",
    "addr:postcode":"7700",
    "addr:street":"Munkevej",
    "iso:country":"DK",
    "sg:address":"Munkevej 7 C",
    "sg:city":"Thisted",
    "sg:orig_category":"Advokater",
    "sg:phone":"+45 97 91 15 55",
    "sg:postcode":"7700",
    "sg:province":"Danmark",
    "wof:name":"Johnsen, Advokatfirmaet Jon",
    "wof:placetype":"venue"
},
  "geometry": {"coordinates":[8.6972856522,56.9559555054],"type":"Point"}
}