{
  "type": "Feature",
  "properties": {
    "addr:full":"Mortensgade 13 Aabybro Danmark 9440",
    "addr:housenumber":"13",
    "addr:postcode":"9440",
    "addr:street":"Mortensgade",
    "iso:country":"DK",
    "sg:address":"Mortensgade 13",
    "sg:city":"Aabybro",
    "sg:orig_category":"Indramning",
    "sg:phone":"+45 98 24 11 58",
    "sg:postcode":"9440",
    "sg:province":"Danmark",
    "wof:name":"Nielsen, Herdis",
    "wof:placetype":"venue"
},
  "geometry": {"coordinates":[9.7319612503,57.1643371582],"type":"Point"}
}