{
  "type": "Feature",
  "properties": {
    "addr:full":"Bredgade 29 Otterup Danmark 5450",
    "addr:housenumber":"29",
    "addr:postcode":"5450",
    "addr:street":"Bredgade",
    "iso:country":"DK",
    "sg:address":"Bredgade 29",
    "sg:city":"Otterup",
    "sg:orig_category":"Ejendomshandel",
    "sg:phone":"+45 64 82 16 34",
    "sg:postcode":"5450",
    "sg:province":"Danmark",
    "wof:name":"Nybolig",
    "wof:placetype":"venue"
},
  "geometry": {"coordinates":[10.3983163834,55.5149993896],"type":"Point"}
}