{
  "type": "Feature",
  "properties": {
    "iso:country":"DK",
    "sg:address":"Billedsk\u00e6rervej 20",
    "sg:city":"Odense M",
    "sg:orig_category":"Vaskerier",
    "sg:phone":"+45 66 15 81 25",
    "sg:postcode":"5230",
    "sg:province":"Danmark",
    "wof:name":"Odense Kittel Service A/S",
    "wof:placetype":"venue"
},
  "geometry": {"coordinates":[10.4141263962,55.3777046204],"type":"Point"}
}