{
  "type": "Feature",
  "properties": {
    "addr:full":"Torvet 2 Stubbek\u00f8bing Danmark 4850",
    "addr:housenumber":"2",
    "addr:postcode":"4850",
    "addr:street":"Torvet",
    "iso:country":"DK",
    "sg:address":"Torvet 2",
    "sg:city":"Stubbek\u00f8bing",
    "sg:classifiers":[
        {
            "category":"Banks & Credit Unions",
            "subcategory":"Bank",
            "type":"Services"
        }
    ],
    "sg:phone":"+45 54 49 06 80",
    "sg:postcode":"4850",
    "sg:province":"Danmark",
    "sg:tags":[
        "banker"
    ],
    "sg:website":"www.danskebank.dk",
    "wof:name":"Danske Bank",
    "wof:placetype":"venue"
},
  "geometry": {"coordinates":[-102.0896530151,42.0193557739],"type":"Point"}
}