{
  "type": "Feature",
  "properties": {
    "iso:country":"DK",
    "sg:address":"Fmd.: Jens Martin Jakobsen, Rolighedsvej 17, Flauenskjold",
    "sg:city":"Dronninglund",
    "sg:orig_category":"Kirkelige foreninger",
    "sg:phone":"+45 98 86 19 80",
    "sg:postcode":"9330",
    "sg:province":"Danmark",
    "wof:name":"Indre Mission, Flauenskjold",
    "wof:placetype":"venue"
},
  "geometry": {"coordinates":[10.2918195724,57.1594543457],"type":"Point"}
}