{
  "type": "Feature",
  "properties": {
    "iso:country":"DK",
    "sg:address":"Fynsvej 7 ",
    "sg:city":"Brande",
    "sg:classifiers":[
        {
            "category":"Real Estate",
            "subcategory":"Surveying",
            "type":"Services"
        }
    ],
    "sg:phone":"+45 96 42 22 88",
    "sg:postcode":"7330",
    "sg:province":"Danmark",
    "sg:tags":[
        "equipment",
        "material",
        "good",
        "-",
        "handling"
    ],
    "wof:name":"GIVE KRANSERVICE A/S",
    "wof:placetype":"venue"
},
  "geometry": {"coordinates":[9.1531648636,55.9292602539],"type":"Point"}
}