{
  "type": "Feature",
  "properties": {
    "addr:full":"Tempovej 35 E Ballerup Danmark 2750",
    "addr:housenumber":"35",
    "addr:postcode":"2750",
    "addr:street":"Tempovej;E",
    "iso:country":"DK",
    "sg:address":"Tempovej 35 E",
    "sg:city":"Ballerup",
    "sg:orig_category":"Bowlingcentre",
    "sg:phone":"+45 44 66 83 10",
    "sg:postcode":"2750",
    "sg:province":"Danmark",
    "sg:website":"www.ballerup-bowling-center.dk",
    "wof:name":"Ballerup Bowling Center",
    "wof:placetype":"venue"
},
  "geometry": {"coordinates":[12.361000061,55.7301216125],"type":"Point"}
}