{
  "type": "Feature",
  "properties": {
    "iso:country":"DK",
    "sg:address":"Bjerring Hede 4",
    "sg:city":"Bjerringbro",
    "sg:orig_category":"Kogekoner",
    "sg:phone":"+45 86 68 29 64",
    "sg:postcode":"8850",
    "sg:province":"Danmark",
    "wof:name":"Koustrup, Mona",
    "wof:placetype":"venue"
},
  "geometry": {"coordinates":[9.6222667694,56.3818397522],"type":"Point"}
}