{
  "type": "Feature",
  "properties": {
    "addr:full":"Bredgade 55 Skjern Danmark 6900",
    "addr:housenumber":"55",
    "addr:postcode":"6900",
    "addr:street":"Bredgade",
    "iso:country":"DK",
    "sg:address":"Bredgade 55",
    "sg:city":"Skjern",
    "sg:orig_category":"Jernbaner",
    "sg:phone":"+45 97 35 00 46",
    "sg:postcode":"6900",
    "sg:province":"Danmark",
    "wof:name":"DSB, Skjern Station",
    "wof:placetype":"venue"
},
  "geometry": {"coordinates":[8.4927778244,55.9477348328],"type":"Point"}
}