{
  "type": "Feature",
  "properties": {
    "addr:full":"Tinghusgade 23 Svendborg Danmark 5700",
    "addr:housenumber":"23",
    "addr:postcode":"5700",
    "addr:street":"Tinghusgade",
    "iso:country":"DK",
    "sg:address":"Tinghusgade 23",
    "sg:city":"Svendborg",
    "sg:orig_category":"Gaveartikler",
    "sg:phone":"+45 62 20 20 72",
    "sg:postcode":"5700",
    "sg:province":"Danmark",
    "wof:name":"Tiger",
    "wof:placetype":"venue"
},
  "geometry": {"coordinates":[10.6040372849,55.0602416992],"type":"Point"}
}