{
  "type": "Feature",
  "properties": {
    "addr:full":"Strandpromenaden 3  Helsing\u00f8r Danmark 3000",
    "addr:housenumber":"3",
    "addr:postcode":"3000",
    "addr:street":"Strandpromenaden",
    "iso:country":"DK",
    "sg:address":"Strandpromenaden 3 ",
    "sg:city":"Helsing\u00f8r",
    "sg:classifiers":[
        {
            "category":"Wholesale",
            "subcategory":"Drugs",
            "type":"Manufacturing & Wholesale Goods"
        }
    ],
    "sg:phone":"+45 49 20 17 50",
    "sg:postcode":"3000",
    "sg:province":"Danmark",
    "sg:tags":[
        "chemical",
        "pharmaceutical"
    ],
    "wof:name":"AWL KEMI APS",
    "wof:placetype":"venue"
},
  "geometry": {"coordinates":[12.6128206253,56.0405273438],"type":"Point"}
}