{
  "type": "Feature",
  "properties": {
    "iso:country":"DK",
    "sg:address":"Haraldsborgvej 78",
    "sg:city":"Roskilde",
    "sg:orig_category":"Vuggestuer",
    "sg:phone":"+45 46 36 52 98",
    "sg:postcode":"4000",
    "sg:province":"Danmark",
    "wof:name":"Klostermarkens Vuggestue",
    "wof:placetype":"venue"
},
  "geometry": {"coordinates":[12.0927639008,55.6543426514],"type":"Point"}
}