{
  "type": "Feature",
  "properties": {
    "addr:full":"Gl. Torv 4, 1. Slagelse Danmark 4200",
    "addr:housenumber":"4 1",
    "addr:postcode":"4200",
    "addr:street":"Gl. Torv",
    "iso:country":"DK",
    "sg:address":"Gl. Torv 4, 1.",
    "sg:city":"Slagelse",
    "sg:orig_category":"Fagforbund og -foreninger",
    "sg:phone":"+45 58 56 52 30",
    "sg:postcode":"4200",
    "sg:province":"Danmark",
    "sg:website":"www.ase.dk",
    "wof:name":"Ase, Vestsj\u00e6llands Amt",
    "wof:placetype":"venue"
},
  "geometry": {"coordinates":[11.3569850922,55.4050865173],"type":"Point"}
}