{
  "type": "Feature",
  "properties": {
    "addr:full":"Broholms All\u00e9 19A Charlottenlund Danmark 2920",
    "addr:housenumber":"19a",
    "addr:postcode":"2920",
    "addr:street":"Broholms Alle\u0301",
    "iso:country":"DK",
    "sg:address":"Broholms All\u00e9 19A",
    "sg:city":"Charlottenlund",
    "sg:orig_category":"\u00c3\u2020ldreboliger",
    "sg:phone":"+45 39 64 46 56",
    "sg:postcode":"2920",
    "sg:province":"Danmark",
    "wof:name":"Pensionistboligerne",
    "wof:placetype":"venue"
},
  "geometry": {"coordinates":[12.5837841034,55.7616004944],"type":"Point"}
}