{
  "type": "Feature",
  "properties": {
    "addr:full":"Gj\u00f8rlingsvej 2 Hellerup Danmark 2900",
    "addr:housenumber":"2",
    "addr:postcode":"2900",
    "addr:street":"Gjorlingsvej",
    "iso:country":"DK",
    "sg:address":"Gj\u00f8rlingsvej 2",
    "sg:city":"Hellerup",
    "sg:orig_category":"Zoneterapeuter",
    "sg:phone":"+45 39 61 02 77",
    "sg:postcode":"2900",
    "sg:province":"Danmark",
    "wof:name":"Mortensen, Grethe Elgaard",
    "wof:placetype":"venue"
},
  "geometry": {"coordinates":[12.5589666367,55.7345123291],"type":"Point"}
}