{
  "type": "Feature",
  "properties": {
    "iso:country":"DK",
    "sg:address":"Fmd.: Ole Koefoed Nielsen, Jens Baggesens Vej 12",
    "sg:city":"Skanderborg",
    "sg:orig_category":"Kulturelle foreninger",
    "sg:phone":"+45 86 52 14 40",
    "sg:postcode":"8660",
    "sg:province":"Danmark",
    "wof:name":"Skanderborg Museumsforening",
    "wof:placetype":"venue"
},
  "geometry": {"coordinates":[9.929974556,56.0380249023],"type":"Point"}
}