{
  "type": "Feature",
  "properties": {
    "addr:full":"Elmesvinget 7 Aalborg S\u00d8 Danmark 9210",
    "addr:housenumber":"7",
    "addr:postcode":"9210",
    "addr:street":"Elmesvinget",
    "iso:country":"DK",
    "sg:address":"Elmesvinget 7",
    "sg:city":"Aalborg S\u00d8",
    "sg:orig_category":"Malermestre",
    "sg:phone":"+45 98 14 31 55",
    "sg:postcode":"9210",
    "sg:province":"Danmark",
    "wof:name":"S\u00f8rensen, Aabo",
    "wof:placetype":"venue"
},
  "geometry": {"coordinates":[9.937005043,57.0159797668],"type":"Point"}
}