{
  "type": "Feature",
  "properties": {
    "addr:full":"\u00d8stergade 45 Ikast Danmark 7430",
    "addr:housenumber":"45",
    "addr:postcode":"7430",
    "addr:street":"Ostergade",
    "iso:country":"DK",
    "sg:address":"\u00d8stergade 45",
    "sg:city":"Ikast",
    "sg:orig_category":"Pizzeriaer",
    "sg:phone":"+45 97 25 04 74",
    "sg:postcode":"7430",
    "sg:province":"Danmark",
    "wof:name":"Alanya Pizza",
    "wof:placetype":"venue"
},
  "geometry": {"coordinates":[9.1634902954,56.1401977539],"type":"Point"}
}