{
  "type": "Feature",
  "properties": {
    "iso:country":"DK",
    "sg:address":"Amager Landevej 147 B ",
    "sg:city":"Kastrup",
    "sg:classifiers":[
        {
            "category":"Manufacturing",
            "subcategory":"Aerospace",
            "type":"Manufacturing & Wholesale Goods"
        }
    ],
    "sg:phone":"+45 32 51 42 22",
    "sg:postcode":"2770",
    "sg:province":"Danmark",
    "sg:tags":[
        "aeronautic"
    ],
    "wof:name":"SCANAVIATION A/S",
    "wof:placetype":"venue"
},
  "geometry": {"coordinates":[12.6251659393,55.6277046204],"type":"Point"}
}