{
  "type": "Feature",
  "properties": {
    "addr:full":"Viborgvej 22 - 24 Silkeborg Danmark 8600",
    "addr:housenumber":"22 24",
    "addr:postcode":"8600",
    "addr:street":"Viborgvej",
    "iso:country":"DK",
    "sg:address":"Viborgvej 22 - 24",
    "sg:city":"Silkeborg",
    "sg:orig_category":"Erhvervsudvikling",
    "sg:phone":"+45 87 20 47 11",
    "sg:postcode":"8600",
    "sg:province":"Danmark",
    "wof:name":"ErhvervsUdviklingsCenter Silkeborg",
    "wof:placetype":"venue"
},
  "geometry": {"coordinates":[9.5137119293,56.2034912109],"type":"Point"}
}