{
  "type": "Feature",
  "properties": {
    "addr:full":"Storegade 2 Hadsund Danmark 9560",
    "addr:housenumber":"2",
    "addr:postcode":"9560",
    "addr:street":"Storegade",
    "iso:country":"DK",
    "sg:address":"Storegade 2",
    "sg:city":"Hadsund",
    "sg:orig_category":"Pizzeriaer",
    "sg:phone":"+45 98 57 53 01",
    "sg:postcode":"9560",
    "sg:province":"Danmark",
    "wof:name":"Sea Sweet Pizza",
    "wof:placetype":"venue"
},
  "geometry": {"coordinates":[10.1123113632,56.7149848938],"type":"Point"}
}