{
  "type": "Feature",
  "properties": {
    "addr:full":"\u00d8sterbyvej 13 Lemming Danmark 8632",
    "addr:housenumber":"13",
    "addr:postcode":"8632",
    "addr:street":"Osterbyvej",
    "iso:country":"DK",
    "sg:address":"\u00d8sterbyvej 13",
    "sg:city":"Lemming",
    "sg:orig_category":"Autoforhandlere",
    "sg:phone":"+45 86 85 91 96",
    "sg:postcode":"8632",
    "sg:province":"Danmark",
    "wof:name":"TR Biler Lemming",
    "wof:placetype":"venue"
},
  "geometry": {"coordinates":[9.5501670837,56.2412796021],"type":"Point"}
}