{
  "type": "Feature",
  "properties": {
    "addr:full":"Oddenvej 252, Overby Sj\u00e6llands Odde Danmark 4583",
    "addr:housenumber":"252",
    "addr:postcode":"4583",
    "addr:street":"Oddenvej;Sjaellands",
    "iso:country":"DK",
    "sg:address":"Oddenvej 252, Overby",
    "sg:city":"Sj\u00e6llands Odde",
    "sg:orig_category":"Gallerier",
    "sg:phone":"+45 59 32 62 31",
    "sg:postcode":"4583",
    "sg:province":"Danmark",
    "wof:name":"Galleri Strandgaarden",
    "wof:placetype":"venue"
},
  "geometry": {"coordinates":[11.3198680878,55.9799728394],"type":"Point"}
}