{
  "type": "Feature",
  "properties": {
    "addr:full":"Fmd.: Tonny Gjersen, S\u00f8ndergade 2, Nordenbro Humble Danmark 5932",
    "addr:housenumber":"2",
    "addr:postcode":"5932",
    "addr:street":"Sondergade;Nordenbro",
    "iso:country":"DK",
    "sg:address":"Fmd.: Tonny Gjersen, S\u00f8ndergade 2, Nordenbro",
    "sg:city":"Humble",
    "sg:orig_category":"Hobbybetonede foreninger",
    "sg:phone":"+45 62 56 18 84",
    "sg:postcode":"5932",
    "sg:province":"Danmark",
    "wof:name":"Magleby Dilettantforening",
    "wof:placetype":"venue"
},
  "geometry": {"coordinates":[10.6990814209,54.8273429871],"type":"Point"}
}