{
  "type": "Feature",
  "properties": {
    "addr:full":"H\u00f8jby Hovedgade 28 H\u00f8jby Danmark 4573",
    "addr:housenumber":"28",
    "addr:postcode":"4573",
    "addr:street":"Hojby Hovedgade",
    "iso:country":"DK",
    "sg:address":"H\u00f8jby Hovedgade 28",
    "sg:city":"H\u00f8jby",
    "sg:classifiers":[
        {
            "category":"Restaurant",
            "type":"Food & Drink"
        }
    ],
    "sg:phone":"+45 59 30 20 51",
    "sg:postcode":"4573",
    "sg:province":"Danmark",
    "sg:website":"www.hojbykro.dk",
    "wof:name":"H\u00f8jby Kro og Hotel",
    "wof:placetype":"venue"
},
  "geometry": {"coordinates":[11.6044721603,55.9117279053],"type":"Point"}
}