{
  "type": "Feature",
  "properties": {
    "addr:full":"Hammelvej 307, B\u00f8strup Lang\u00e5 Danmark 8870",
    "addr:housenumber":"307",
    "addr:postcode":"8870",
    "addr:street":"Hammelvej",
    "iso:country":"DK",
    "sg:address":"Hammelvej 307, B\u00f8strup",
    "sg:city":"Lang\u00e5",
    "sg:classifiers":[
        {
            "category":"Autos & Motor Vehicles",
            "subcategory":"Fuel & Gas Station",
            "type":"Retail Goods"
        }
    ],
    "sg:phone":"+45 86 96 40 69",
    "sg:postcode":"8870",
    "sg:province":"Danmark",
    "sg:tags":[
        "pumper"
    ],
    "wof:name":"J. H. Pumpe Service",
    "wof:placetype":"venue"
},
  "geometry": {"coordinates":[9.8955049515,56.3900756836],"type":"Point"}
}