{
  "type": "Feature",
  "properties": {
    "addr:full":"Vestervej 13 Taastrup Danmark 2630",
    "addr:housenumber":"13",
    "addr:postcode":"2630",
    "addr:street":"Vestervej",
    "iso:country":"DK",
    "sg:address":"Vestervej 13",
    "sg:city":"Taastrup",
    "sg:orig_category":"Alternativ behandling",
    "sg:phone":"+45 43 99 43 20",
    "sg:postcode":"2630",
    "sg:province":"Danmark",
    "sg:website":"www.radioni.dk",
    "wof:name":"Radionisk Analyse",
    "wof:placetype":"venue"
},
  "geometry": {"coordinates":[12.2981977463,55.6491889954],"type":"Point"}
}