{
  "type": "Feature",
  "properties": {
    "iso:country":"DK",
    "sg:address":"Hyllingebjergvej 11",
    "sg:city":"Liseleje",
    "sg:orig_category":"Indretningsarkitekter",
    "sg:phone":"+45 47 74 53 41",
    "sg:postcode":"3360",
    "sg:province":"Danmark",
    "wof:name":"Interieur Studio",
    "wof:placetype":"venue"
},
  "geometry": {"coordinates":[11.9604825974,56.0123901367],"type":"Point"}
}