{
  "type": "Feature",
  "properties": {
    "addr:full":"S\u00f8gade 3 Ringsted Danmark 4100",
    "addr:housenumber":"3",
    "addr:postcode":"4100",
    "addr:street":"Sogade",
    "iso:country":"DK",
    "sg:address":"S\u00f8gade 3",
    "sg:city":"Ringsted",
    "sg:orig_category":"Medborgerhuse",
    "sg:phone":"+45 57 62 70 60",
    "sg:postcode":"4100",
    "sg:province":"Danmark",
    "wof:name":"Medborgerhuset",
    "wof:placetype":"venue"
},
  "geometry": {"coordinates":[11.8879852295,55.3917617798],"type":"Point"}
}