{
  "type": "Feature",
  "properties": {
    "iso:country":"DK",
    "sg:address":"Suurkj\u00e6rvej 9, Flovlev",
    "sg:city":"Thyholm",
    "sg:orig_category":"Hydraulik",
    "sg:phone":"+45 97 87 19 00",
    "sg:postcode":"7790",
    "sg:province":"Danmark",
    "sg:website":"www.tmphydraulik.dk",
    "wof:name":"T.M.P. hydraulik",
    "wof:placetype":"venue"
},
  "geometry": {"coordinates":[8.525765419,56.6507072449],"type":"Point"}
}