{
  "type": "Feature",
  "properties": {
    "addr:full":"Sankt Hans Vej 6 A Svendborg Danmark 5700",
    "addr:housenumber":"6 a",
    "addr:postcode":"5700",
    "addr:street":"Sankt Hans Vej",
    "iso:country":"DK",
    "sg:address":"Sankt Hans Vej 6 A",
    "sg:city":"Svendborg",
    "sg:orig_category":"Vinduespolering",
    "sg:phone":"+45 40 92 94 77",
    "sg:postcode":"5700",
    "sg:province":"Danmark",
    "wof:name":"Sch\u00e6fer's Vinduespolering",
    "wof:placetype":"venue"
},
  "geometry": {"coordinates":[10.5974035263,55.0593261719],"type":"Point"}
}