{
  "type": "Feature",
  "properties": {
    "addr:full":"Lejrvejen 103, Fr\u00f8slev Padborg Danmark 6330",
    "addr:housenumber":"103",
    "addr:postcode":"6330",
    "addr:street":"Lejrvejen;Froslev",
    "iso:country":"DK",
    "sg:address":"Lejrvejen 103, Fr\u00f8slev",
    "sg:city":"Padborg",
    "sg:orig_category":"Museer",
    "sg:phone":"+45 74 67 68 87",
    "sg:postcode":"6330",
    "sg:province":"Danmark",
    "wof:name":"Beredskabs-Forbundets Informationsbarak H 1",
    "wof:placetype":"venue"
},
  "geometry": {"coordinates":[9.3618345261,54.8222312927],"type":"Point"}
}