{
  "type": "Feature",
  "properties": {
    "iso:country":"DK",
    "sg:address":"Fr\u00f8rup Byvej 34",
    "sg:city":"Fr\u00f8rup",
    "sg:classifiers":[
        {
            "category":"Taxi",
            "type":"Transportation"
        }
    ],
    "sg:phone":"+45 65 37 15 16",
    "sg:postcode":"5871",
    "sg:province":"Danmark",
    "wof:name":"Fr\u00f8rup Taxi",
    "wof:placetype":"venue"
},
  "geometry": {"coordinates":[-93.1630935669,32.8507347107],"type":"Point"}
}