{
  "type": "Feature",
  "properties": {
    "addr:full":"Garverg\u00e5rdsvej 86 Slagelse Danmark 4200",
    "addr:housenumber":"86",
    "addr:postcode":"4200",
    "addr:street":"Garvergaardsvej",
    "iso:country":"DK",
    "sg:address":"Garverg\u00e5rdsvej 86",
    "sg:city":"Slagelse",
    "sg:orig_category":"Vinduespolering",
    "sg:phone":"+45 58 52 24 95",
    "sg:postcode":"4200",
    "sg:province":"Danmark",
    "wof:name":"Mortensen & S\u00f8nner, A C",
    "wof:placetype":"venue"
},
  "geometry": {"coordinates":[11.3806467056,55.4065971375],"type":"Point"}
}