{
  "type": "Feature",
  "properties": {
    "addr:full":"Fmd.: S\u00f8ren Hoffmann Iversen, Skovbakken 4 Lemvig Danmark 7620",
    "addr:housenumber":"4",
    "addr:postcode":"7620",
    "addr:street":"Skovbakken",
    "iso:country":"DK",
    "sg:address":"Fmd.: S\u00f8ren Hoffmann Iversen, Skovbakken 4",
    "sg:city":"Lemvig",
    "sg:orig_category":"Kirkelige foreninger",
    "sg:phone":"+45 97 81 01 12",
    "sg:postcode":"7620",
    "sg:province":"Danmark",
    "wof:name":"Indre Missions Samfund",
    "wof:placetype":"venue"
},
  "geometry": {"coordinates":[8.3073654175,56.5505104065],"type":"Point"}
}