{
  "type": "Feature",
  "properties": {
    "iso:country":"DK",
    "sg:address":"Koldingvej 30, Vester Nebel",
    "sg:city":"Egtved",
    "sg:orig_category":"Bagere",
    "sg:phone":"+45 75 55 33 47",
    "sg:postcode":"6040",
    "sg:province":"Danmark",
    "sg:website":"www.guldbageren.dk",
    "wof:name":"Vester Nebel Bageri ApS",
    "wof:placetype":"venue"
},
  "geometry": {"coordinates":[9.308748,55.616161],"type":"Point"}
}