{
  "type": "Feature",
  "properties": {
    "addr:full":"Landbruget, Landtingvej 36, Landting Vinderup Danmark 7830",
    "addr:housenumber":"36",
    "addr:postcode":"7830",
    "addr:street":"Landtingvej",
    "iso:country":"DK",
    "sg:address":"Landbruget, Landtingvej 36, Landting",
    "sg:city":"Vinderup",
    "sg:orig_category":"Non-Classified Establishments",
    "sg:phone":"+45 97 44 64 22",
    "sg:postcode":"7830",
    "sg:province":"Danmark",
    "wof:name":"Psykiatrien i Ringkj\u00f8bing Amt, Garland afd.",
    "wof:placetype":"venue"
},
  "geometry": {"coordinates":[8.7796897888,56.482635498],"type":"Point"}
}