{
  "type": "Feature",
  "properties": {
    "addr:full":"Tofteb\u00e6ksvej 15 C Kongens Lyngby Danmark 2800",
    "addr:housenumber":"15 c",
    "addr:postcode":"2800",
    "addr:street":"Toftebaeksvej",
    "iso:country":"DK",
    "sg:address":"Tofteb\u00e6ksvej 15 C",
    "sg:city":"Kongens Lyngby",
    "sg:orig_category":"Cykler",
    "sg:phone":"+45 45 88 93 20",
    "sg:postcode":"2800",
    "sg:province":"Danmark",
    "wof:name":"LMC Lyngby",
    "wof:placetype":"venue"
},
  "geometry": {"coordinates":[12.50502491,55.7736549377],"type":"Point"}
}