{
  "type": "Feature",
  "properties": {
    "addr:full":"Smedegade 41 Struer Danmark 7600",
    "addr:housenumber":"41",
    "addr:postcode":"7600",
    "addr:street":"Smedegade",
    "iso:country":"DK",
    "sg:address":"Smedegade 41",
    "sg:city":"Struer",
    "sg:orig_category":"Grillbarer",
    "sg:phone":"+45 97 85 03 48",
    "sg:postcode":"7600",
    "sg:province":"Danmark",
    "wof:name":"Stjerne Grill",
    "wof:placetype":"venue"
},
  "geometry": {"coordinates":[8.5867824554,56.4910011292],"type":"Point"}
}