{
  "type": "Feature",
  "properties": {
    "addr:full":"Nordvej 4, Vangen Frederikshavn Danmark 9900",
    "addr:housenumber":"4",
    "addr:postcode":"9900",
    "addr:street":"Nordvej;Vangen",
    "iso:country":"DK",
    "sg:address":"Nordvej 4, Vangen",
    "sg:city":"Frederikshavn",
    "sg:orig_category":"Cafeterier",
    "sg:phone":"+45 98 47 90 16",
    "sg:postcode":"9900",
    "sg:province":"Danmark",
    "wof:name":"Nikolines Cafeteria",
    "wof:placetype":"venue"
},
  "geometry": {"coordinates":[10.5362997055,57.4396400452],"type":"Point"}
}