{
  "type": "Feature",
  "properties": {
    "addr:full":"Fmd.: Willy Richard Jensen, Toftevej 10 Slagelse Danmark 4200",
    "addr:housenumber":"10",
    "addr:postcode":"4200",
    "addr:street":"Toftevej",
    "iso:country":"DK",
    "sg:address":"Fmd.: Willy Richard Jensen, Toftevej 10",
    "sg:city":"Slagelse",
    "sg:orig_category":"Loger",
    "sg:phone":"+45 58 52 31 08",
    "sg:postcode":"4200",
    "sg:province":"Danmark",
    "wof:name":"Odd Fellow Logen - Hellig Anders",
    "wof:placetype":"venue"
},
  "geometry": {"coordinates":[11.3569850922,55.4050865173],"type":"Point"}
}