{
  "type": "Feature",
  "properties": {
    "iso:country":"DK",
    "sg:address":"Kvinderupvej 12, Kvinderup",
    "sg:city":"Slangerup",
    "sg:orig_category":"Helsekost",
    "sg:phone":"+45 48 27 71 10",
    "sg:postcode":"3550",
    "sg:province":"Danmark",
    "sg:website":"www.panacea.dk",
    "wof:name":"Panacea Helse",
    "wof:placetype":"venue"
},
  "geometry": {"coordinates":[12.1717596054,55.8460769653],"type":"Point"}
}