{
  "type": "Feature",
  "properties": {
    "addr:full":"Skjernvej 165 Holstebro Danmark 7500",
    "addr:housenumber":"165",
    "addr:postcode":"7500",
    "addr:street":"Skjernvej",
    "iso:country":"DK",
    "sg:address":"Skjernvej 165",
    "sg:city":"Holstebro",
    "sg:orig_category":"Maskinstationer",
    "sg:phone":"+45 97 42 40 75",
    "sg:postcode":"7500",
    "sg:province":"Danmark",
    "wof:name":"Nr. Felding Maskinstation I/S",
    "wof:placetype":"venue"
},
  "geometry": {"coordinates":[8.6041650772,56.3078956604],"type":"Point"}
}