{
  "type": "Feature",
  "properties": {
    "iso:country":"DK",
    "sg:address":"Amagertorv 29 A, 4",
    "sg:city":"K\u00f8benhavn",
    "sg:classifiers":[
        {
            "category":"Professional",
            "subcategory":"Advertising",
            "type":"Services"
        }
    ],
    "sg:phone":"+45 33 37 97 00",
    "sg:postcode":"1160",
    "sg:province":"Danmark",
    "sg:tags":[
        "telemarketing"
    ],
    "wof:name":"Recall Denmark A/S",
    "wof:placetype":"venue"
},
  "geometry": {"coordinates":[12.5804004669,55.6781005859],"type":"Point"}
}