{
  "type": "Feature",
  "properties": {
    "addr:full":"Sognepr\u00e6st: Niels J\u00f8rgen Kirketerp (K/B), Ugiltvej 529, Ugilt Hj\u00f8rring Danmark 9800",
    "addr:housenumber":"529",
    "addr:postcode":"9800",
    "addr:street":"Ugiltvej",
    "iso:country":"DK",
    "sg:address":"Sognepr\u00e6st: Niels J\u00f8rgen Kirketerp (K/B), Ugiltvej 529, Ugilt",
    "sg:city":"Hj\u00f8rring",
    "sg:orig_category":"Kirkesogne",
    "sg:phone":"+45 98 93 30 27",
    "sg:postcode":"9800",
    "sg:province":"Danmark",
    "wof:name":"Ugilt-Astrup Sogne",
    "wof:placetype":"venue"
},
  "geometry": {"coordinates":[9.9885387421,57.4594764709],"type":"Point"}
}