{
  "type": "Feature",
  "properties": {
    "addr:full":"Jagtvej 80 Odense C Danmark 5000",
    "addr:housenumber":"80",
    "addr:postcode":"5000",
    "addr:street":"Jagtvej",
    "iso:country":"DK",
    "sg:address":"Jagtvej 80",
    "sg:city":"Odense C",
    "sg:orig_category":"Handicap-daginstitutioner",
    "sg:phone":"+45 66 13 33 24",
    "sg:postcode":"5000",
    "sg:province":"Danmark",
    "wof:name":"Specialb\u00f8rnehaven",
    "wof:placetype":"venue"
},
  "geometry": {"coordinates":[10.3848161697,55.3894386292],"type":"Point"}
}