{
  "type": "Feature",
  "properties": {
    "addr:full":"Hennevej 22 Outrup Danmark 6855",
    "addr:housenumber":"22",
    "addr:postcode":"6855",
    "addr:street":"Hennevej",
    "iso:country":"DK",
    "sg:address":"Hennevej 22",
    "sg:city":"Outrup",
    "sg:orig_category":"Legestuer",
    "sg:phone":"+45 75 25 16 22",
    "sg:postcode":"6855",
    "sg:province":"Danmark",
    "wof:name":"Outrup Legestue",
    "wof:placetype":"venue"
},
  "geometry": {"coordinates":[8.3423709869,55.718460083],"type":"Point"}
}