{
  "type": "Feature",
  "properties": {
    "addr:full":"Skovhusevej 21, Tolstrup Mern Danmark 4735",
    "addr:housenumber":"21",
    "addr:postcode":"4735",
    "addr:street":"Skovhusevej",
    "iso:country":"DK",
    "sg:address":"Skovhusevej 21, Tolstrup",
    "sg:city":"Mern",
    "sg:orig_category":"Revisorer",
    "sg:phone":"+45 55 93 00 50",
    "sg:postcode":"4735",
    "sg:province":"Danmark",
    "wof:name":"Revisorgaarden ApS",
    "wof:placetype":"venue"
},
  "geometry": {"coordinates":[12.0578746796,55.049079895],"type":"Point"}
}