{
  "type": "Feature",
  "properties": {
    "addr:full":"Nr. Bjertvej 87 A Kolding Danmark 6000",
    "addr:housenumber":"87 a",
    "addr:postcode":"6000",
    "addr:street":"Nr. Bjertvej",
    "iso:country":"DK",
    "sg:address":"Nr. Bjertvej 87 A",
    "sg:city":"Kolding",
    "sg:orig_category":"Kirker",
    "sg:postcode":"6000",
    "sg:province":"Danmark",
    "wof:name":"Nr. Bj\u00e6rt Kirke",
    "wof:placetype":"venue"
},
  "geometry": {"coordinates":[9.536939621,55.5157585144],"type":"Point"}
}