{
  "type": "Feature",
  "properties": {
    "addr:full":"Br\u00f8ndumvej 3, Blenstrup Sk\u00f8rping Danmark 9520",
    "addr:housenumber":"3",
    "addr:postcode":"9520",
    "addr:street":"Brondumvej",
    "iso:country":"DK",
    "sg:address":"Br\u00f8ndumvej 3, Blenstrup",
    "sg:city":"Sk\u00f8rping",
    "sg:orig_category":"Kommunale folkeskoler",
    "sg:phone":"+45 99 82 84 55",
    "sg:postcode":"9520",
    "sg:province":"Danmark",
    "wof:name":"Blenstrup Skole",
    "wof:placetype":"venue"
},
  "geometry": {"coordinates":[9.8477077484,56.8337860107],"type":"Point"}
}