{
  "type": "Feature",
  "properties": {
    "addr:full":"Gedingvej 30 Tilst Danmark 8381",
    "addr:housenumber":"30",
    "addr:postcode":"8381",
    "addr:street":"Gedingvej",
    "iso:country":"DK",
    "sg:address":"Gedingvej 30",
    "sg:city":"Tilst",
    "sg:orig_category":"Rideskoler",
    "sg:phone":"+45 86 24 28 82",
    "sg:postcode":"8381",
    "sg:province":"Danmark",
    "wof:name":"Steng\u00e5rd, Ridecenter",
    "wof:placetype":"venue"
},
  "geometry": {"coordinates":[10.1051483154,56.1995544434],"type":"Point"}
}