{
  "type": "Feature",
  "properties": {
    "addr:full":"Violskr\u00e6nten 13 Grenaa Danmark 8500",
    "addr:housenumber":"13",
    "addr:postcode":"8500",
    "addr:street":"Violskraenten",
    "iso:country":"DK",
    "sg:address":"Violskr\u00e6nten 13",
    "sg:city":"Grenaa",
    "sg:orig_category":"Plejehjem",
    "sg:phone":"+45 86 32 60 00",
    "sg:postcode":"8500",
    "sg:province":"Danmark",
    "wof:name":"Plejehjemmet Violskr\u00e6nten",
    "wof:placetype":"venue"
},
  "geometry": {"coordinates":[10.8774929047,56.4126853943],"type":"Point"}
}