{
  "type": "Feature",
  "properties": {
    "addr:full":"Brendg\u00e5rdvej 3, Ydby Hurup Danmark 7760",
    "addr:housenumber":"3",
    "addr:postcode":"7760",
    "addr:street":"Brendgaardvej;Ydby",
    "iso:country":"DK",
    "sg:address":"Brendg\u00e5rdvej 3, Ydby",
    "sg:city":"Hurup",
    "sg:orig_category":"Web- og Internetdesign",
    "sg:phone":"+45 97 95 62 24",
    "sg:postcode":"7760",
    "sg:province":"Danmark",
    "sg:website":"www.sydthy-webdesign.dk",
    "wof:name":"Sydthy Webdesign",
    "wof:placetype":"venue"
},
  "geometry": {"coordinates":[8.4233045578,56.7485847473],"type":"Point"}
}