{
  "type": "Feature",
  "properties": {
    "addr:full":"Morsb\u00f8l Skolevej 19, Morsb\u00f8l Grindsted Danmark 7200",
    "addr:housenumber":"19",
    "addr:postcode":"7200",
    "addr:street":"Skolevej;Morsbol",
    "iso:country":"DK",
    "sg:address":"Morsb\u00f8l Skolevej 19, Morsb\u00f8l",
    "sg:city":"Grindsted",
    "sg:orig_category":"Autoreparation og -service",
    "sg:phone":"+45 75 32 23 45",
    "sg:postcode":"7200",
    "sg:province":"Danmark",
    "wof:name":"S\u00f8rensen, S\u00f8ren Chr.",
    "wof:placetype":"venue"
},
  "geometry": {"coordinates":[8.9288702011,55.7560272217],"type":"Point"}
}