{
  "type": "Feature",
  "properties": {
    "addr:full":"Ringk\u00f8bingvej 99-101 Herning Danmark 7400",
    "addr:housenumber":"99-101",
    "addr:postcode":"7400",
    "addr:street":"Ringkobingvej",
    "iso:country":"DK",
    "sg:address":"Ringk\u00f8bingvej 99-101",
    "sg:city":"Herning",
    "sg:orig_category":"Autoforhandlere",
    "sg:phone":"+45 96 27 63 33",
    "sg:postcode":"7400",
    "sg:province":"Danmark",
    "wof:name":"Herning Bilcenter ApS",
    "wof:placetype":"venue"
},
  "geometry": {"coordinates":[8.9323549271,56.1348991394],"type":"Point"}
}