{
  "type": "Feature",
  "properties": {
    "addr:full":"H\u00f8jen 1 Horsens Danmark 8700",
    "addr:housenumber":"1",
    "addr:postcode":"8700",
    "addr:street":"Hojen",
    "iso:country":"DK",
    "sg:address":"H\u00f8jen 1",
    "sg:city":"Horsens",
    "sg:orig_category":"Gymnasier og HF-kurser",
    "sg:phone":"+45 76 26 15 00",
    "sg:postcode":"8700",
    "sg:province":"Danmark",
    "wof:name":"Horsens Amtsgymnasium",
    "wof:placetype":"venue"
},
  "geometry": {"coordinates":[9.8305206299,55.8444290161],"type":"Point"}
}