{
  "type": "Feature",
  "properties": {
    "addr:full":"\u00d8sterbro 13 Havndal Danmark 8970",
    "addr:housenumber":"13",
    "addr:postcode":"8970",
    "addr:street":"Osterbro",
    "iso:country":"DK",
    "sg:address":"\u00d8sterbro 13",
    "sg:city":"Havndal",
    "sg:orig_category":"Gallerier",
    "sg:phone":"+45 86 47 08 75",
    "sg:postcode":"8970",
    "sg:province":"Danmark",
    "wof:name":"Kr\u00f8yer, Galleri",
    "wof:placetype":"venue"
},
  "geometry": {"coordinates":[10.1944665909,56.6535491943],"type":"Point"}
}