{
  "type": "Feature",
  "properties": {
    "addr:full":"Mosedraget 13 Herlev Danmark 2730",
    "addr:housenumber":"13",
    "addr:postcode":"2730",
    "addr:street":"Mosedraget",
    "iso:country":"DK",
    "sg:address":"Mosedraget 13",
    "sg:city":"Herlev",
    "sg:orig_category":"Musikere",
    "sg:phone":"+45 44 84 35 57",
    "sg:postcode":"2730",
    "sg:province":"Danmark",
    "wof:name":"Wamsahl, Bj\u00f8rn",
    "wof:placetype":"venue"
},
  "geometry": {"coordinates":[12.4104328156,55.7367095947],"type":"Point"}
}