{
  "type": "Feature",
  "properties": {
    "addr:full":"Br\u00f8nderslevvej 99, G\u00e6rum Frederikshavn Danmark 9900",
    "addr:housenumber":"99",
    "addr:postcode":"9900",
    "addr:street":"Bronderslevvej",
    "iso:country":"DK",
    "sg:address":"Br\u00f8nderslevvej 99, G\u00e6rum",
    "sg:city":"Frederikshavn",
    "sg:orig_category":"Integrerede institutioner",
    "sg:phone":"+45 98 48 63 35",
    "sg:postcode":"9900",
    "sg:province":"Danmark",
    "wof:name":"Kernehuset",
    "wof:placetype":"venue"
},
  "geometry": {"coordinates":[10.5362997055,57.4396400452],"type":"Point"}
}