{
  "type": "Feature",
  "properties": {
    "addr:full":"Fmd.: Leif Kunkel, Hundstrupvej 31, Krarup Ringe Danmark 5750",
    "addr:housenumber":"31",
    "addr:postcode":"5750",
    "addr:street":"Hundstrupvej;Krarup",
    "iso:country":"DK",
    "sg:address":"Fmd.: Leif Kunkel, Hundstrupvej 31, Krarup",
    "sg:city":"Ringe",
    "sg:orig_category":"Borger- og beboerforeninger",
    "sg:phone":"+45 62 26 34 54",
    "sg:postcode":"5750",
    "sg:province":"Danmark",
    "wof:name":"Krarup sogns Beboerforening",
    "wof:placetype":"venue"
},
  "geometry": {"coordinates":[10.4781074524,55.2356643677],"type":"Point"}
}