{
  "type": "Feature",
  "properties": {
    "addr:full":"Kv\u00e6rnen 11 Aalborg S\u00d8 Danmark 9210",
    "addr:housenumber":"11",
    "addr:postcode":"9210",
    "addr:street":"Kvaernen",
    "iso:country":"DK",
    "sg:address":"Kv\u00e6rnen 11",
    "sg:city":"Aalborg S\u00d8",
    "sg:orig_category":"Vagtbureauer",
    "sg:phone":"+45 98 14 82 66",
    "sg:postcode":"9210",
    "sg:province":"Danmark",
    "wof:name":"Jysk Vagt- og Overv\u00e5gning A/S",
    "wof:placetype":"venue"
},
  "geometry": {"coordinates":[9.9285211563,57.0116577148],"type":"Point"}
}