{
  "type": "Feature",
  "properties": {
    "iso:country":"DK",
    "sg:address":"Roldvej 36, Mosb\u00e6k",
    "sg:city":"Aars",
    "sg:orig_category":"Garn",
    "sg:phone":"+45 98 62 25 01",
    "sg:postcode":"9600",
    "sg:province":"Danmark",
    "wof:name":"Ret Og Vrang",
    "wof:placetype":"venue"
},
  "geometry": {"coordinates":[9.5170412064,56.8031692505],"type":"Point"}
}