{
  "type": "Feature",
  "properties": {
    "addr:full":"Islandsvej 14 A Kongens Lyngby Danmark 2800",
    "addr:housenumber":"14 a",
    "addr:postcode":"2800",
    "addr:street":"Islandsvej",
    "iso:country":"DK",
    "sg:address":"Islandsvej 14 A",
    "sg:city":"Kongens Lyngby",
    "sg:orig_category":"Zoneterapeuter",
    "sg:phone":"+45 45 88 92 37",
    "sg:postcode":"2800",
    "sg:province":"Danmark",
    "wof:name":"Sterner, Birgitta",
    "wof:placetype":"venue"
},
  "geometry": {"coordinates":[12.5079689026,55.7976608276],"type":"Point"}
}