{
  "type": "Feature",
  "properties": {
    "addr:full":"Storegade 37, Assentoft Randers Danmark 8900",
    "addr:housenumber":"37",
    "addr:postcode":"8900",
    "addr:street":"Storegade",
    "iso:country":"DK",
    "sg:address":"Storegade 37, Assentoft",
    "sg:city":"Randers",
    "sg:orig_category":"Ejendomshandel",
    "sg:phone":"+45 86 49 44 44",
    "sg:postcode":"8900",
    "sg:province":"Danmark",
    "wof:name":"EDC M\u00e6glerne - M\u00e6glergruppen",
    "wof:placetype":"venue"
},
  "geometry": {"coordinates":[10.0357952118,56.4593734741],"type":"Point"}
}