{
  "type": "Feature",
  "properties": {
    "addr:full":"(Fmd. Palle Hansen), Japanvej 3 Slagelse Danmark 4200",
    "addr:housenumber":"3",
    "addr:postcode":"4200",
    "addr:street":"Japanvej",
    "iso:country":"DK",
    "sg:address":"(Fmd. Palle Hansen), Japanvej 3",
    "sg:city":"Slagelse",
    "sg:orig_category":"Fagforbund og -foreninger",
    "sg:phone":"+45 58 56 52 10",
    "sg:postcode":"4200",
    "sg:province":"Danmark",
    "wof:name":"Teknisk Landsforbund Vestsj\u00e6llands afd.",
    "wof:placetype":"venue"
},
  "geometry": {"coordinates":[11.325633049,55.3882522583],"type":"Point"}
}