{
  "type": "Feature",
  "properties": {
    "iso:country":"DK",
    "sg:address":"Fmd.: Sv. E. Clemmensen, \u00c6rtevej 6, Dommerby",
    "sg:city":"H\u00f8jslev",
    "sg:orig_category":"Hobbybetonede foreninger",
    "sg:phone":"+45 97 53 51 73",
    "sg:postcode":"7840",
    "sg:province":"Danmark",
    "wof:name":"Skiveegnens husdyrauktion",
    "wof:placetype":"venue"
},
  "geometry": {"coordinates":[9.110039711,56.5504264832],"type":"Point"}
}