{
  "type": "Feature",
  "properties": {
    "addr:full":"Pilevej 11, Assens Mariager Danmark 9550",
    "addr:housenumber":"11",
    "addr:postcode":"9550",
    "addr:street":"Pilevej",
    "iso:country":"DK",
    "sg:address":"Pilevej 11, Assens",
    "sg:city":"Mariager",
    "sg:orig_category":"Murermestre",
    "sg:phone":"+45 98 58 33 75",
    "sg:postcode":"9550",
    "sg:province":"Danmark",
    "wof:name":"Hjeronymus, Henning",
    "wof:placetype":"venue"
},
  "geometry": {"coordinates":[10.0618648529,56.676902771],"type":"Point"}
}