{
  "type": "Feature",
  "properties": {
    "addr:full":"N\u00f8rregade 14 Bjerringbro Danmark 8850",
    "addr:housenumber":"14",
    "addr:postcode":"8850",
    "addr:street":"Norregade",
    "iso:country":"DK",
    "sg:address":"N\u00f8rregade 14",
    "sg:city":"Bjerringbro",
    "sg:orig_category":"Faglige organisationer og foreninger",
    "sg:phone":"+45 86 68 35 00",
    "sg:postcode":"8850",
    "sg:province":"Danmark",
    "sg:website":"www.kad.dk",
    "wof:name":"Kvindeligt Arbejderforbund I Danmark, Bjerringbro afd.",
    "wof:placetype":"venue"
},
  "geometry": {"coordinates":[9.6591882706,56.3757972717],"type":"Point"}
}