{
  "type": "Feature",
  "properties": {
    "addr:full":"Agtrupvej 196 Kolding Danmark 6000",
    "addr:housenumber":"196",
    "addr:postcode":"6000",
    "addr:street":"Agtrupvej",
    "iso:country":"DK",
    "sg:address":"Agtrupvej 196",
    "sg:city":"Kolding",
    "sg:orig_category":"Indretningsarkitekter",
    "sg:phone":"+45 75 53 02 25",
    "sg:postcode":"6000",
    "sg:province":"Danmark",
    "wof:name":"D-Sign Tegnestuen",
    "wof:placetype":"venue"
},
  "geometry": {"coordinates":[9.497376442,55.4778022766],"type":"Point"}
}