{
  "type": "Feature",
  "properties": {
    "addr:full":"\u00d8sterbrogade 15 Kolding Danmark 6000",
    "addr:housenumber":"15",
    "addr:postcode":"6000",
    "addr:street":"Osterbrogade",
    "iso:country":"DK",
    "sg:address":"\u00d8sterbrogade 15",
    "sg:city":"Kolding",
    "sg:orig_category":"Produkthandlere",
    "sg:phone":"+45 75 53 29 41",
    "sg:postcode":"6000",
    "sg:province":"Danmark",
    "wof:name":"K.T. Produkt",
    "wof:placetype":"venue"
},
  "geometry": {"coordinates":[9.4848823547,55.4848747253],"type":"Point"}
}