{
  "type": "Feature",
  "properties": {
    "iso:country":"DK",
    "sg:address":"Munkebakke 23, Esb\u00f8nderup",
    "sg:city":"Gr\u00e6sted",
    "sg:orig_category":"Skibskonsulenter",
    "sg:phone":"+45 48 39 08 21",
    "sg:postcode":"3230",
    "sg:province":"Danmark",
    "wof:name":"Borghegn Yachtdesign",
    "wof:placetype":"venue"
},
  "geometry": {"coordinates":[-78.6975326538,35.0151481628],"type":"Point"}
}