{
  "type": "Feature",
  "properties": {
    "addr:full":"v/ Flemming Reisz, Gyvelk\u00e6den 25 Greve Danmark 2670",
    "addr:housenumber":"25",
    "addr:postcode":"2670",
    "addr:street":"Gyvelkaeden",
    "iso:country":"DK",
    "sg:address":"v/ Flemming Reisz, Gyvelk\u00e6den 25",
    "sg:city":"Greve",
    "sg:orig_category":"Produktudvikling",
    "sg:phone":"+45 43 90 57 24",
    "sg:postcode":"2670",
    "sg:province":"Danmark",
    "wof:name":"International Management Consultans ApS",
    "wof:placetype":"venue"
},
  "geometry": {"coordinates":[12.2941808701,55.5844078064],"type":"Point"}
}