{
  "type": "Feature",
  "properties": {
    "addr:full":"Fmd.: J\u00f8rgen Christensen, Thur\u00f8gade 32, 1. Odense C Danmark 5000",
    "addr:housenumber":"32 1",
    "addr:postcode":"5000",
    "addr:street":"Thurogade",
    "iso:country":"DK",
    "sg:address":"Fmd.: J\u00f8rgen Christensen, Thur\u00f8gade 32, 1.",
    "sg:city":"Odense C",
    "sg:orig_category":"Faglige organisationer og foreninger",
    "sg:phone":"+45 65 90 50 02",
    "sg:postcode":"5000",
    "sg:province":"Danmark",
    "wof:name":"Ledernes Hovedorganisation",
    "wof:placetype":"venue"
},
  "geometry": {"coordinates":[10.390794754,55.3961715698],"type":"Point"}
}