{
  "type": "Feature",
  "properties": {
    "iso:country":"DK",
    "sg:address":"Bandholmvej 101",
    "sg:city":"Torrig",
    "sg:orig_category":"Integrerede institutioner",
    "sg:phone":"+45 54 93 74 84",
    "sg:postcode":"4943",
    "sg:province":"Danmark",
    "wof:name":"B\u00f8rnehuset i Birket",
    "wof:placetype":"venue"
},
  "geometry": {"coordinates":[11.3323154449,54.8991661072],"type":"Point"}
}