{
  "type": "Feature",
  "properties": {
    "addr:full":"Ny Esbjergvej 16 Pr\u00e6st\u00f8 Danmark 4720",
    "addr:housenumber":"16",
    "addr:postcode":"4720",
    "addr:street":"Esbjergvej",
    "iso:country":"DK",
    "sg:address":"Ny Esbjergvej 16",
    "sg:city":"Pr\u00e6st\u00f8",
    "sg:orig_category":"Cylinderservice",
    "sg:phone":"+45 55 99 37 37",
    "sg:postcode":"4720",
    "sg:province":"Danmark",
    "sg:website":"www.55993737.dk",
    "wof:name":"B\u00e5rse Maskinforretning og Cylinderservice",
    "wof:placetype":"venue"
},
  "geometry": {"coordinates":[-76.50189208979999,42.8563194275],"type":"Point"}
}