{
  "type": "Feature",
  "properties": {
    "addr:full":"Hadsundvej 115 Hadsund Danmark 9560",
    "addr:housenumber":"115",
    "addr:postcode":"9560",
    "addr:street":"Hadsundvej",
    "iso:country":"DK",
    "sg:address":"Hadsundvej 115",
    "sg:city":"Hadsund",
    "sg:orig_category":"Reklamebureauer",
    "sg:phone":"+45 70 20 99 11",
    "sg:postcode":"9560",
    "sg:province":"Danmark",
    "wof:name":"Andersen-Farmer Kommunikation",
    "wof:placetype":"venue"
},
  "geometry": {"coordinates":[10.262339592,56.7535552979],"type":"Point"}
}