{
  "type": "Feature",
  "properties": {
    "addr:full":"P. Ladefogeds Vej 3, Lyng\u00e5 Hadsten Danmark 8370",
    "addr:housenumber":"3",
    "addr:postcode":"8370",
    "addr:street":"P. Ladefogeds Vej",
    "iso:country":"DK",
    "sg:address":"P. Ladefogeds Vej 3, Lyng\u00e5",
    "sg:city":"Hadsten",
    "sg:orig_category":"Skorstensfejere",
    "sg:phone":"+45 86 91 59 30",
    "sg:postcode":"8370",
    "sg:province":"Danmark",
    "wof:name":"Christensen, Claus Bjarne",
    "wof:placetype":"venue"
},
  "geometry": {"coordinates":[10.047659874,56.3287239075],"type":"Point"}
}