{
  "type": "Feature",
  "properties": {
    "iso:country":"DK",
    "sg:address":"Vasen 5",
    "sg:city":"Lemvig",
    "sg:orig_category":"Bogtrykkerier",
    "sg:phone":"+45 97 82 15 00",
    "sg:postcode":"7620",
    "sg:province":"Danmark",
    "wof:name":"Grafisk Tryk",
    "wof:placetype":"venue"
},
  "geometry": {"coordinates":[8.3104963303,56.5494308472],"type":"Point"}
}