{
  "type": "Feature",
  "properties": {
    "addr:full":"Kongevejen 274, Nyrup Kvistg\u00e5rd Danmark 3490",
    "addr:housenumber":"274",
    "addr:postcode":"3490",
    "addr:street":"Kongevejen",
    "iso:country":"DK",
    "sg:address":"Kongevejen 274, Nyrup",
    "sg:city":"Kvistg\u00e5rd",
    "sg:orig_category":"Benzinstationer",
    "sg:phone":"+45 49 13 91 43",
    "sg:postcode":"3490",
    "sg:province":"Danmark",
    "wof:name":"Q8 Kvistg\u00e5rd",
    "wof:placetype":"venue"
},
  "geometry": {"coordinates":[12.5004415512,55.9893493652],"type":"Point"}
}