{
  "type": "Feature",
  "properties": {
    "addr:full":"Folden 6 Fr\u00f8rup Danmark 5871",
    "addr:housenumber":"6",
    "addr:postcode":"5871",
    "addr:street":"Folden",
    "iso:country":"DK",
    "sg:address":"Folden 6",
    "sg:city":"Fr\u00f8rup",
    "sg:orig_category":"EDB - undervisning",
    "sg:phone":"+45 65 37 16 07",
    "sg:postcode":"5871",
    "sg:province":"Danmark",
    "wof:name":"Bruno",
    "wof:placetype":"venue"
},
  "geometry": {"coordinates":[-93.1630935669,32.8507347107],"type":"Point"}
}