{
  "type": "Feature",
  "properties": {
    "addr:full":"Rylevej 41 Silkeborg Danmark 8600",
    "addr:housenumber":"41",
    "addr:postcode":"8600",
    "addr:street":"Rylevej",
    "iso:country":"DK",
    "sg:address":"Rylevej 41",
    "sg:city":"Silkeborg",
    "sg:orig_category":"Ungdomsklubber",
    "sg:phone":"+45 86 82 13 73",
    "sg:postcode":"8600",
    "sg:province":"Danmark",
    "wof:name":"Bakkeg\u00e5rdens Fritids- Og Ungdomsklub",
    "wof:placetype":"venue"
},
  "geometry": {"coordinates":[9.5651416779,56.1675796509],"type":"Point"}
}