{
  "type": "Feature",
  "properties": {
    "addr:full":"H\u00f8jvangsvej 12, Skjoldelev Sabro Danmark 8471",
    "addr:housenumber":"12",
    "addr:postcode":"8471",
    "addr:street":"Hojvangsvej",
    "iso:country":"DK",
    "sg:address":"H\u00f8jvangsvej 12, Skjoldelev",
    "sg:city":"Sabro",
    "sg:orig_category":"Gartnerier",
    "sg:phone":"+45 86 96 86 66",
    "sg:postcode":"8471",
    "sg:province":"Danmark",
    "wof:name":"Skjoldvang A/S",
    "wof:placetype":"venue"
},
  "geometry": {"coordinates":[10.0375204086,56.2109718323],"type":"Point"}
}