{
  "type": "Feature",
  "properties": {
    "addr:full":"Bel Colles Alle 7 Rungsted Kyst Danmark 2960",
    "addr:housenumber":"7",
    "addr:postcode":"2960",
    "addr:street":"Bel Colles Alle",
    "iso:country":"DK",
    "sg:address":"Bel Colles Alle 7",
    "sg:city":"Rungsted Kyst",
    "sg:orig_category":"Arkitekter",
    "sg:phone":"+45 45 86 49 92",
    "sg:postcode":"2960",
    "sg:province":"Danmark",
    "wof:name":"Studsgarth, Peter",
    "wof:placetype":"venue"
},
  "geometry": {"coordinates":[12.5178527832,55.8841934204],"type":"Point"}
}