{
  "type": "Feature",
  "properties": {
    "addr:full":"H\u00f8jlundvej 18 Harlev Danmark 8462",
    "addr:housenumber":"18",
    "addr:postcode":"8462",
    "addr:street":"Hojlundvej",
    "iso:country":"DK",
    "sg:address":"H\u00f8jlundvej 18",
    "sg:city":"Harlev",
    "sg:orig_category":"Bookingbureauer",
    "sg:phone":"+45 86 94 22 66",
    "sg:postcode":"8462",
    "sg:province":"Danmark",
    "wof:name":"Dansk Underholdning",
    "wof:placetype":"venue"
},
  "geometry": {"coordinates":[9.9944009781,56.1391944885],"type":"Point"}
}