{
  "type": "Feature",
  "properties": {
    "iso:country":"DK",
    "sg:address":"Yd\u00f8vej 2",
    "sg:city":"Nakskov",
    "sg:orig_category":"Snedkermestre",
    "sg:phone":"+45 54 94 83 30",
    "sg:postcode":"4900",
    "sg:province":"Danmark",
    "wof:name":"Wiuff, J\u00f8rgen",
    "wof:placetype":"venue"
},
  "geometry": {"coordinates":[11.0096082687,54.8005485535],"type":"Point"}
}