{
  "type": "Feature",
  "properties": {
    "addr:full":"Kulholmsvej 20 Randers Danmark 8900",
    "addr:housenumber":"20",
    "addr:postcode":"8900",
    "addr:street":"Kulholmsvej",
    "iso:country":"DK",
    "sg:address":"Kulholmsvej 20",
    "sg:city":"Randers",
    "sg:orig_category":"Asfalt",
    "sg:phone":"+45 86 42 14 88",
    "sg:postcode":"8900",
    "sg:province":"Danmark",
    "wof:name":"Lemmink\u00e4inen A/S",
    "wof:placetype":"venue"
},
  "geometry": {"coordinates":[10.0495290756,56.4593009949],"type":"Point"}
}