{
  "type": "Feature",
  "properties": {
    "addr:full":"Hesteh\u00f8jvej 155 A, H\u00f8jby Odense S Danmark 5260",
    "addr:housenumber":"155 a",
    "addr:postcode":"5260",
    "addr:street":"Hestehojvej;Hojby",
    "iso:country":"DK",
    "sg:address":"Hesteh\u00f8jvej 155 A, H\u00f8jby",
    "sg:city":"Odense S",
    "sg:orig_category":"Naturprodukter",
    "sg:phone":"+45 65 95 97 42",
    "sg:postcode":"5260",
    "sg:province":"Danmark",
    "wof:name":"Naturalia Direct Line",
    "wof:placetype":"venue"
},
  "geometry": {"coordinates":[10.3157806396,55.3122825623],"type":"Point"}
}