{
  "type": "Feature",
  "properties": {
    "addr:full":"\u00d8stmarken 4, 1 S\u00f8borg Danmark 2860",
    "addr:housenumber":"4 1",
    "addr:postcode":"2860",
    "addr:street":"Ostmarken",
    "iso:country":"DK",
    "sg:address":"\u00d8stmarken 4, 1",
    "sg:city":"S\u00f8borg",
    "sg:orig_category":"Forlag",
    "sg:phone":"+45 35 20 30 40",
    "sg:postcode":"2860",
    "sg:province":"Danmark",
    "wof:name":"DR Udvikling",
    "wof:placetype":"venue"
},
  "geometry": {"coordinates":[-101.38818359379999,35.6691398621],"type":"Point"}
}