{
  "type": "Feature",
  "properties": {
    "addr:full":"Nordre Farimagsvej 18 N\u00e6stved Danmark 4700",
    "addr:housenumber":"18",
    "addr:postcode":"4700",
    "addr:street":"Nordre Farimagsvej",
    "iso:country":"DK",
    "sg:address":"Nordre Farimagsvej 18",
    "sg:city":"N\u00e6stved",
    "sg:orig_category":"Bandagister",
    "sg:phone":"+45 55 73 92 04",
    "sg:postcode":"4700",
    "sg:province":"Danmark",
    "wof:name":"Sahva Bandageri og Skomageri",
    "wof:placetype":"venue"
},
  "geometry": {"coordinates":[12.035369873,60.8038711548],"type":"Point"}
}