{
  "type": "Feature",
  "properties": {
    "addr:full":"Lee Byvej 37A Bjerringbro Danmark 8850",
    "addr:housenumber":"37a",
    "addr:postcode":"8850",
    "addr:street":"Lee Byvej",
    "iso:country":"DK",
    "sg:address":"Lee Byvej 37A",
    "sg:city":"Bjerringbro",
    "sg:orig_category":"Kirker",
    "sg:postcode":"8850",
    "sg:province":"Danmark",
    "wof:name":"Lee Kirke",
    "wof:placetype":"venue"
},
  "geometry": {"coordinates":[9.6730833054,56.4249000549],"type":"Point"}
}