{
  "type": "Feature",
  "properties": {
    "addr:full":"S\u00f8ndergade 30 Galten Danmark 8464",
    "addr:housenumber":"30",
    "addr:postcode":"8464",
    "addr:street":"Sondergade",
    "iso:country":"DK",
    "sg:address":"S\u00f8ndergade 30",
    "sg:city":"Galten",
    "sg:orig_category":"Antikviteter",
    "sg:phone":"+45 86 94 30 13",
    "sg:postcode":"8464",
    "sg:province":"Danmark",
    "wof:name":"J\u00e6gerhuset",
    "wof:placetype":"venue"
},
  "geometry": {"coordinates":[9.9023742676,56.1515388489],"type":"Point"}
}