{
  "type": "Feature",
  "properties": {
    "addr:full":"Henv.: Kirsten Rud Svenning, Kissendrupvej 63, Langtved Ullerslev Danmark 5540",
    "addr:housenumber":"63",
    "addr:postcode":"5540",
    "addr:street":"Svenning Kissendrupvej",
    "iso:country":"DK",
    "sg:address":"Henv.: Kirsten Rud Svenning, Kissendrupvej 63, Langtved",
    "sg:city":"Ullerslev",
    "sg:orig_category":"\u00c3\u2020ldreorganisationer og klubber",
    "sg:phone":"+45 65 35 12 93",
    "sg:postcode":"5540",
    "sg:province":"Danmark",
    "wof:name":"\u00c6ldreklubben i Langtved",
    "wof:placetype":"venue"
},
  "geometry": {"coordinates":[10.6675348282,55.3605728149],"type":"Point"}
}