{
  "type": "Feature",
  "properties": {
    "addr:full":"Fmd.: Verner Dissing, Hybenvej 5 Terndrup Danmark 9575",
    "addr:housenumber":"5",
    "addr:postcode":"9575",
    "addr:street":"Fmd. Verner Dissing Hybenvej;Danmark",
    "iso:country":"DK",
    "sg:address":"Fmd.: Verner Dissing, Hybenvej 5",
    "sg:city":"Terndrup",
    "sg:orig_category":"Erhvervs- og brancheforeninger",
    "sg:phone":"+45 98 33 63 17",
    "sg:postcode":"9575",
    "sg:province":"Danmark",
    "wof:name":"Terndrup Erhvervsforening",
    "wof:placetype":"venue"
},
  "geometry": {"coordinates":[10.058382988,56.8162651062],"type":"Point"}
}