{
  "type": "Feature",
  "properties": {
    "iso:country":"DK",
    "sg:address":"N\u00f8rregade 108",
    "sg:city":"K\u00f8ge",
    "sg:orig_category":"Bagere",
    "sg:phone":"+45 56 65 08 58",
    "sg:postcode":"4600",
    "sg:province":"Danmark",
    "wof:name":"Nicolai's Bageri",
    "wof:placetype":"venue"
},
  "geometry": {"coordinates":[12.182728,55.456615],"type":"Point"}
}