{
  "type": "Feature",
  "properties": {
    "iso:country":"DK",
    "sg:address":"v/ Helmer Skov, Kolstrupvej 77, Dal",
    "sg:city":"Grindsted",
    "sg:orig_category":"Erhvervs- og brancheforeninger",
    "sg:phone":"+45 75 32 12 70",
    "sg:postcode":"7200",
    "sg:province":"Danmark",
    "wof:name":"Grindsted Husmandskredsforening",
    "wof:placetype":"venue"
},
  "geometry": {"coordinates":[8.9288702011,55.7560272217],"type":"Point"}
}