{
  "type": "Feature",
  "properties": {
    "iso:country":"DK",
    "sg:address":"Knud Den Stores Vej 33 A",
    "sg:city":"Roskilde",
    "sg:orig_category":"Revisorer",
    "sg:phone":"+45 46 36 43 48",
    "sg:postcode":"4000",
    "sg:province":"Danmark",
    "sg:website":"www.lmrevision.dk",
    "wof:name":"L.M. Revision",
    "wof:placetype":"venue"
},
  "geometry": {"coordinates":[12.0901660919,55.6482124329],"type":"Point"}
}