{
  "type": "Feature",
  "properties": {
    "addr:full":"\u00c5byskovvej 39 Sk\u00e5rup Danmark 5881",
    "addr:housenumber":"39",
    "addr:postcode":"5881",
    "addr:street":"Aabyskovvej",
    "iso:country":"DK",
    "sg:address":"\u00c5byskovvej 39",
    "sg:city":"Sk\u00e5rup",
    "sg:orig_category":"Forsamlingshuse",
    "sg:phone":"+45 62 23 17 38",
    "sg:postcode":"5881",
    "sg:province":"Danmark",
    "wof:name":"\u00c5byskov Forsamlingshus",
    "wof:placetype":"venue"
},
  "geometry": {"coordinates":[10.7258863449,55.0737991333],"type":"Point"}
}