{
  "type": "Feature",
  "properties": {
    "addr:full":"v/ Hans Rasmussen, S\u00f8ndergade 51 Hundested Danmark 3390",
    "addr:housenumber":"51",
    "addr:postcode":"3390",
    "addr:street":"Sondergade",
    "iso:country":"DK",
    "sg:address":"v/ Hans Rasmussen, S\u00f8ndergade 51",
    "sg:city":"Hundested",
    "sg:orig_category":"Erhvervs- og brancheforeninger",
    "sg:phone":"+45 47 93 72 95",
    "sg:postcode":"3390",
    "sg:province":"Danmark",
    "wof:name":"Lyn\u00e6s Fiskeriforening",
    "wof:placetype":"venue"
},
  "geometry": {"coordinates":[11.8530349731,55.958530426],"type":"Point"}
}