{
  "type": "Feature",
  "properties": {
    "addr:full":"Strandvejen 4 Kerteminde Danmark 5300",
    "addr:housenumber":"4",
    "addr:postcode":"5300",
    "addr:street":"Strandvejen",
    "iso:country":"DK",
    "sg:address":"Strandvejen 4",
    "sg:city":"Kerteminde",
    "sg:orig_category":"Posthuse",
    "sg:phone":"+45 65 43 32 00",
    "sg:postcode":"5300",
    "sg:province":"Danmark",
    "wof:name":"Post Danmark, Kerteminde Posthus",
    "wof:placetype":"venue"
},
  "geometry": {"coordinates":[10.6597633362,55.4498062134],"type":"Point"}
}