{
  "type": "Feature",
  "properties": {
    "addr:full":"Gammel Jernbanevej 28 Valby Danmark 2500",
    "addr:housenumber":"28",
    "addr:postcode":"2500",
    "addr:street":"Gammel Jernbanevej",
    "iso:country":"DK",
    "sg:address":"Gammel Jernbanevej 28",
    "sg:city":"Valby",
    "sg:orig_category":"Cykler",
    "sg:phone":"+45 36 46 37 88",
    "sg:postcode":"2500",
    "sg:province":"Danmark",
    "wof:name":"Troest, Jan",
    "wof:placetype":"venue"
},
  "geometry": {"coordinates":[12.5189342499,55.6645927429],"type":"Point"}
}