{
  "type": "Feature",
  "properties": {
    "addr:full":"v/ M. Mortensen, H\u00f8jlund 38, V. Sottrup S\u00f8nderborg Danmark 6400",
    "addr:housenumber":"38",
    "addr:postcode":"6400",
    "addr:street":"/ M. Mortensen Hojlund;Sottrup",
    "iso:country":"DK",
    "sg:address":"v/ M. Mortensen, H\u00f8jlund 38, V. Sottrup",
    "sg:city":"S\u00f8nderborg",
    "sg:orig_category":"Grundejerforeninger",
    "sg:phone":"+45 74 46 81 11",
    "sg:postcode":"6400",
    "sg:province":"Danmark",
    "wof:name":"Grundejerforeningen H\u00f8jlund",
    "wof:placetype":"venue"
},
  "geometry": {"coordinates":[9.7899465561,54.9100151062],"type":"Point"}
}