{
  "type": "Feature",
  "properties": {
    "addr:full":"Pr\u00e6stestr\u00e6de 36 Nyk\u00f8bing Danmark 4800",
    "addr:housenumber":"36",
    "addr:postcode":"4800",
    "addr:street":"Praestestraede",
    "iso:country":"DK",
    "sg:address":"Pr\u00e6stestr\u00e6de 36",
    "sg:city":"Nyk\u00f8bing",
    "sg:orig_category":"Haveservice",
    "sg:phone":"+45 54 17 40 29",
    "sg:postcode":"4800",
    "sg:province":"Danmark",
    "wof:name":"Sydfalster Gr\u00e6ssl\u00e5ningsservice",
    "wof:placetype":"venue"
},
  "geometry": {"coordinates":[-114.0768203735,46.4432411194],"type":"Point"}
}