{
  "type": "Feature",
  "properties": {
    "addr:full":"Melissehaven 3, 3 th. Herlev Danmark 2730",
    "addr:housenumber":"3 3 th.",
    "addr:postcode":"2730",
    "addr:street":"Melissehaven",
    "iso:country":"DK",
    "sg:address":"Melissehaven 3, 3 th.",
    "sg:city":"Herlev",
    "sg:orig_category":"Glarmestre og glarmagere",
    "sg:phone":"+45 44 94 36 17",
    "sg:postcode":"2730",
    "sg:province":"Danmark",
    "wof:name":"Craner, Henrik R",
    "wof:placetype":"venue"
},
  "geometry": {"coordinates":[12.4382095337,55.7250595093],"type":"Point"}
}