{
  "type": "Feature",
  "properties": {
    "addr:full":"Peter Bangs Vej 18 Frederiksberg Danmark 2000",
    "addr:housenumber":"18",
    "addr:postcode":"2000",
    "addr:street":"Peter Bangs Vej",
    "iso:country":"DK",
    "sg:address":"Peter Bangs Vej 18",
    "sg:city":"Frederiksberg",
    "sg:orig_category":"Akvarier",
    "sg:phone":"+45 38 88 66 05",
    "sg:postcode":"2000",
    "sg:province":"Danmark",
    "wof:name":"Akvarieudlejningen I/S",
    "wof:placetype":"venue"
},
  "geometry": {"coordinates":[12.5168199539,55.6791648865],"type":"Point"}
}