{
  "type": "Feature",
  "properties": {
    "addr:full":"Nejstvej 110 Tylstrup Danmark 9382",
    "addr:housenumber":"110",
    "addr:postcode":"9382",
    "addr:street":"Nejstvej",
    "iso:country":"DK",
    "sg:address":"Nejstvej 110",
    "sg:city":"Tylstrup",
    "sg:orig_category":"Autoforhandlere",
    "sg:phone":"+45 98 26 21 66",
    "sg:postcode":"9382",
    "sg:province":"Danmark",
    "wof:name":"Nejstvejens Biler",
    "wof:placetype":"venue"
},
  "geometry": {"coordinates":[9.9428501129,57.2186393738],"type":"Point"}
}