{
  "type": "Feature",
  "properties": {
    "addr:full":"Hudevad Byvej 32, Hudevad \u00c5rslev Danmark 5792",
    "addr:housenumber":"32",
    "addr:postcode":"5792",
    "addr:street":"Hudevad Byvej",
    "iso:country":"DK",
    "sg:address":"Hudevad Byvej 32, Hudevad",
    "sg:city":"\u00c5rslev",
    "sg:orig_category":"Borger- og beboerforeninger",
    "sg:postcode":"5792",
    "sg:province":"Danmark",
    "wof:name":"HD 89",
    "wof:placetype":"venue"
},
  "geometry": {"coordinates":[10.4862937927,55.3088531494],"type":"Point"}
}