{
  "type": "Feature",
  "properties": {
    "iso:country":"DK",
    "sg:address":"Borgergade 19, R\u00f8dding",
    "sg:city":"Sp\u00f8ttrup",
    "sg:orig_category":"Brugsforeninger",
    "sg:phone":"+45 97 56 10 10",
    "sg:postcode":"7860",
    "sg:province":"Danmark",
    "wof:name":"Dagli' Brugsen",
    "wof:placetype":"venue"
},
  "geometry": {"coordinates":[8.7428588867,56.5733261108],"type":"Point"}
}