{
  "type": "Feature",
  "properties": {
    "addr:full":"Fynslundvej 11, H\u00f8jrup Lunderskov Danmark 6640",
    "addr:housenumber":"11",
    "addr:postcode":"6640",
    "addr:street":"Fynslundvej;Hojrup",
    "iso:country":"DK",
    "sg:address":"Fynslundvej 11, H\u00f8jrup",
    "sg:city":"Lunderskov",
    "sg:orig_category":"Nedbrydning",
    "sg:phone":"+45 75 55 94 95",
    "sg:postcode":"6640",
    "sg:province":"Danmark",
    "wof:name":"Hasselstr\u00f8m & S\u00f8n",
    "wof:placetype":"venue"
},
  "geometry": {"coordinates":[9.2983627319,55.4793586731],"type":"Point"}
}