{
  "type": "Feature",
  "properties": {
    "addr:full":"Strandvejen 114 Hellerup Danmark 2900",
    "addr:housenumber":"114",
    "addr:postcode":"2900",
    "addr:street":"Strandvejen",
    "iso:country":"DK",
    "sg:address":"Strandvejen 114",
    "sg:city":"Hellerup",
    "sg:orig_category":"Ejendomshandel",
    "sg:phone":"+45 39 46 09 46",
    "sg:postcode":"2900",
    "sg:province":"Danmark",
    "wof:name":"DanBolig Kristensen & Mikkelsen",
    "wof:placetype":"venue"
},
  "geometry": {"coordinates":[12.5751533508,55.7346839905],"type":"Point"}
}