{
  "type": "Feature",
  "properties": {
    "addr:full":"Bjerggade 12 K\u00f8ge Danmark 4600",
    "addr:housenumber":"12",
    "addr:postcode":"4600",
    "addr:street":"Bjerggade",
    "iso:country":"DK",
    "sg:address":"Bjerggade 12",
    "sg:city":"K\u00f8ge",
    "sg:orig_category":"Psykologer, praktiserende",
    "sg:phone":"+45 56 28 80 78",
    "sg:postcode":"4600",
    "sg:province":"Danmark",
    "wof:name":"Ottesen, Ole",
    "wof:placetype":"venue"
},
  "geometry": {"coordinates":[12.1854028702,55.4595527649],"type":"Point"}
}