{
  "type": "Feature",
  "properties": {
    "iso:country":"DK",
    "sg:address":"Fmd.: Jacob Trzeciak, Torupvej 21",
    "sg:city":"Assens",
    "sg:orig_category":"Loger",
    "sg:phone":"+45 64 79 29 59",
    "sg:postcode":"5610",
    "sg:province":"Danmark",
    "wof:name":"Junior Chamber Vestfyn",
    "wof:placetype":"venue"
},
  "geometry": {"coordinates":[9.8998937607,55.2702522278],"type":"Point"}
}