{
  "type": "Feature",
  "properties": {
    "addr:full":"City 2 400 Taastrup Danmark 2630",
    "addr:housenumber":"400",
    "addr:postcode":"2630",
    "addr:street":"2",
    "iso:country":"DK",
    "sg:address":"City 2 400",
    "sg:city":"Taastrup",
    "sg:classifiers":[
        {
            "category":"Communications",
            "type":"Services"
        }
    ],
    "sg:phone":"+45 43 52 33 11",
    "sg:postcode":"2630",
    "sg:province":"Danmark",
    "sg:tags":[
        "radio-",
        "og",
        "tv-stationer"
    ],
    "wof:name":"POP FM",
    "wof:placetype":"venue"
},
  "geometry": {"coordinates":[12.2743463516,55.6432151794],"type":"Point"}
}