{
  "type": "Feature",
  "properties": {
    "addr:full":"Vindegade 67 Odense C Danmark 5000",
    "addr:housenumber":"67",
    "addr:postcode":"5000",
    "addr:street":"Vindegade",
    "iso:country":"DK",
    "sg:address":"Vindegade 67",
    "sg:city":"Odense C",
    "sg:classifiers":[
        {
            "category":"Restaurant",
            "type":"Food & Drink"
        }
    ],
    "sg:phone":"+45 66 19 16 28",
    "sg:postcode":"5000",
    "sg:province":"Danmark",
    "wof:name":"Caf\u00e9 Monsun",
    "wof:placetype":"venue"
},
  "geometry": {"coordinates":[10.3795690536,55.3975067139],"type":"Point"}
}