{
  "type": "Feature",
  "properties": {
    "addr:full":"Folkevej 25 Gentofte Danmark 2820",
    "addr:housenumber":"25",
    "addr:postcode":"2820",
    "addr:street":"Folkevej",
    "iso:country":"DK",
    "sg:address":"Folkevej 25",
    "sg:city":"Gentofte",
    "sg:orig_category":"Murermestre",
    "sg:phone":"+45 39 67 64 61",
    "sg:postcode":"2820",
    "sg:province":"Danmark",
    "wof:name":"BKT Murerservice",
    "wof:placetype":"venue"
},
  "geometry": {"coordinates":[12.5018110275,55.7482566833],"type":"Point"}
}