{
  "type": "Feature",
  "properties": {
    "addr:full":"v/ Jens J\u00f8rgensen, Blomsterv\u00e6nget 10, Rindum Ringk\u00f8bing Danmark 6950",
    "addr:housenumber":"10",
    "addr:postcode":"6950",
    "addr:street":"Rindum Ringkobing Danmark",
    "iso:country":"DK",
    "sg:address":"v/ Jens J\u00f8rgensen, Blomsterv\u00e6nget 10, Rindum",
    "sg:city":"Ringk\u00f8bing",
    "sg:orig_category":"Grundejerforeninger",
    "sg:phone":"+45 97 32 27 09",
    "sg:postcode":"6950",
    "sg:province":"Danmark",
    "wof:name":"Grundejerforeningen Blomsterv\u00e6nget",
    "wof:placetype":"venue"
},
  "geometry": {"coordinates":[-114.0767440796,46.4432487488],"type":"Point"}
}