{
  "type": "Feature",
  "properties": {
    "addr:full":"Holmedal 78, Voerladeg\u00e5rd Skanderborg Danmark 8660",
    "addr:housenumber":"78",
    "addr:postcode":"8660",
    "addr:street":"Holmedal",
    "iso:country":"DK",
    "sg:address":"Holmedal 78, Voerladeg\u00e5rd",
    "sg:city":"Skanderborg",
    "sg:orig_category":"Autoreparation og -service",
    "sg:phone":"+45 75 78 20 36",
    "sg:postcode":"8660",
    "sg:province":"Danmark",
    "wof:name":"Voerladeg\u00e5rd Autov\u00e6rksted",
    "wof:placetype":"venue"
},
  "geometry": {"coordinates":[9.929974556,56.0380249023],"type":"Point"}
}