{
  "type": "Feature",
  "properties": {
    "iso:country":"DK",
    "sg:address":"\u00d8stergade 10",
    "sg:city":"Nakskov",
    "sg:orig_category":"Begravelsesforretninger",
    "sg:phone":"+45 54 95 11 90",
    "sg:postcode":"4900",
    "sg:province":"Danmark",
    "wof:name":"Kurdahls Bedemandsforretning",
    "wof:placetype":"venue"
},
  "geometry": {"coordinates":[11.141043663,54.8310546875],"type":"Point"}
}