{
  "type": "Feature",
  "properties": {
    "addr:full":"Thomas B.Thriges Gd. 32, 2. Odense C Danmark 5000",
    "addr:housenumber":"2",
    "addr:postcode":"5000",
    "addr:street":"Gd. 32",
    "iso:country":"DK",
    "sg:address":"Thomas B.Thriges Gd. 32, 2.",
    "sg:city":"Odense C",
    "sg:classifiers":[
        {
            "category":"Restaurant",
            "type":"Food & Drink"
        }
    ],
    "sg:phone":"+45 63 11 33 10",
    "sg:postcode":"5000",
    "sg:province":"Danmark",
    "wof:name":"Wip Personalerestauranter A/S",
    "wof:placetype":"venue"
},
  "geometry": {"coordinates":[10.390162468,55.4004211426],"type":"Point"}
}