{
  "type": "Feature",
  "properties": {
    "addr:full":"Skolevej 21 Tommerup Danmark 5690",
    "addr:housenumber":"21",
    "addr:postcode":"5690",
    "addr:street":"Skolevej",
    "iso:country":"DK",
    "sg:address":"Skolevej 21",
    "sg:city":"Tommerup",
    "sg:orig_category":"Non-Classified Establishments",
    "sg:phone":"+45 64 76 13 94",
    "sg:postcode":"5690",
    "sg:province":"Danmark",
    "wof:name":"DK Benzin - Tommerup Auto ApS",
    "wof:placetype":"venue"
},
  "geometry": {"coordinates":[10.2023859024,55.3211631775],"type":"Point"}
}