{
  "type": "Feature",
  "properties": {
    "iso:country":"DK",
    "sg:address":"Haraldsvej 36",
    "sg:city":"Randers",
    "sg:orig_category":"Lastvogne",
    "sg:phone":"+45 87 11 04 25",
    "sg:postcode":"8900",
    "sg:province":"Danmark",
    "wof:name":"Viking Lastbil A/S",
    "wof:placetype":"venue"
},
  "geometry": {"coordinates":[10.0535831451,56.4378089905],"type":"Point"}
}