{
  "type": "Feature",
  "properties": {
    "iso:country":"DK",
    "sg:address":"Sverigesvej 3",
    "sg:city":"Hammel",
    "sg:orig_category":"Skorstensfejere",
    "sg:phone":"+45 86 96 12 39",
    "sg:postcode":"8450",
    "sg:province":"Danmark",
    "wof:name":"Nielsen, Bjarne Dahl",
    "wof:placetype":"venue"
},
  "geometry": {"coordinates":[9.8528652191,56.250667572],"type":"Point"}
}