{
  "type": "Feature",
  "properties": {
    "iso:country":"DK",
    "sg:address":"Vester Voldgade 17",
    "sg:city":"K\u00f8benhavn",
    "sg:orig_category":"Boligselskaber",
    "sg:phone":"+45 33 63 10 00",
    "sg:postcode":"1552",
    "sg:province":"Danmark",
    "sg:website":"www.kab-bolig.dk",
    "wof:name":"KAB - Bygge- og Boligadministration",
    "wof:placetype":"venue"
},
  "geometry": {"coordinates":[12.570400238,55.6759986877],"type":"Point"}
}