{
  "type": "Feature",
  "properties": {
    "addr:full":"Lyngvej 19 Jyderup Danmark 4450",
    "addr:housenumber":"19",
    "addr:postcode":"4450",
    "addr:street":"Lyngvej",
    "iso:country":"DK",
    "sg:address":"Lyngvej 19",
    "sg:city":"Jyderup",
    "sg:orig_category":"Trykkerier",
    "sg:phone":"+45 59 27 62 18",
    "sg:postcode":"4450",
    "sg:province":"Danmark",
    "sg:website":"www.jboffset.dk",
    "wof:name":"Jyderup Bogtryk/Offset ApS",
    "wof:placetype":"venue"
},
  "geometry": {"coordinates":[11.4087667465,55.6598777771],"type":"Point"}
}