{
  "type": "Feature",
  "properties": {
    "addr:full":"R\u00f8dovre Stationscenter 3 R\u00f8dovre Danmark 2610",
    "addr:housenumber":"3",
    "addr:postcode":"2610",
    "addr:street":"Rodovre Stationscenter",
    "iso:country":"DK",
    "sg:address":"R\u00f8dovre Stationscenter 3",
    "sg:city":"R\u00f8dovre",
    "sg:orig_category":"Apoteker og -udsalg",
    "sg:phone":"+45 36 72 13 25",
    "sg:postcode":"2610",
    "sg:province":"Danmark",
    "wof:name":"Apoteksudsalget fra Br\u00f8ndby\u00f8ster Apotek",
    "wof:placetype":"venue"
},
  "geometry": {"coordinates":[10.6992139816,61.1027755737],"type":"Point"}
}