{
  "type": "Feature",
  "properties": {
    "addr:full":"Besser Kirkevej 25 Sams\u00f8 Danmark 8305",
    "addr:housenumber":"25",
    "addr:postcode":"8305",
    "addr:street":"Besser Kirkevej",
    "iso:country":"DK",
    "sg:address":"Besser Kirkevej 25",
    "sg:city":"Sams\u00f8",
    "sg:orig_category":"Arkitekter",
    "sg:phone":"+45 86 59 23 90",
    "sg:postcode":"8305",
    "sg:province":"Danmark",
    "wof:name":"Fast, Karl Erik",
    "wof:placetype":"venue"
},
  "geometry": {"coordinates":[-86.09934997560001,31.2234687805],"type":"Point"}
}