{
  "type": "Feature",
  "properties": {
    "addr:full":"Fmd.: Thomas Salicath, Bredgade 49 st. K\u00f8benhavn Danmark 1260",
    "addr:housenumber":"49",
    "addr:postcode":"1260",
    "addr:street":"Bredgade",
    "iso:country":"DK",
    "sg:address":"Fmd.: Thomas Salicath, Bredgade 49 st.",
    "sg:city":"K\u00f8benhavn",
    "sg:orig_category":"Grundejerforeninger",
    "sg:phone":"+45 33 91 28 88",
    "sg:postcode":"1260",
    "sg:province":"Danmark",
    "wof:name":"Arrenakkelyng Grundejerforening",
    "wof:placetype":"venue"
},
  "geometry": {"coordinates":[12.5931997299,55.6845016479],"type":"Point"}
}