{
  "type": "Feature",
  "properties": {
    "addr:full":"v/ Bent Lassen, Odinsgaadsvej 5 Stakroge Danmark 7270",
    "addr:housenumber":"5",
    "addr:postcode":"7270",
    "addr:street":"Odinsgaadsvej",
    "iso:country":"DK",
    "sg:address":"v/ Bent Lassen, Odinsgaadsvej 5",
    "sg:city":"Stakroge",
    "sg:orig_category":"Borger- og beboerforeninger",
    "sg:phone":"+45 75 34 71 81",
    "sg:postcode":"7270",
    "sg:province":"Danmark",
    "wof:name":"Stakroge Borgerforening",
    "wof:placetype":"venue"
},
  "geometry": {"coordinates":[8.8480148315,55.8899345398],"type":"Point"}
}