{
  "type": "Feature",
  "properties": {
    "addr:full":"L\u00f8vegade 36 Slagelse Danmark 4200",
    "addr:housenumber":"36",
    "addr:postcode":"4200",
    "addr:street":"Lovegade",
    "iso:country":"DK",
    "sg:address":"L\u00f8vegade 36",
    "sg:city":"Slagelse",
    "sg:classifiers":[
        {
            "category":"Restaurant",
            "type":"Food & Drink"
        }
    ],
    "sg:phone":"+45 58 52 11 41",
    "sg:postcode":"4200",
    "sg:province":"Danmark",
    "wof:name":"Teater Cafeen",
    "wof:placetype":"venue"
},
  "geometry": {"coordinates":[11.3479452133,55.4044914246],"type":"Point"}
}