{
  "type": "Feature",
  "properties": {
    "addr:full":"Naffet 5 B, Skrydstrup Vojens Danmark 6500",
    "addr:housenumber":"5 b",
    "addr:postcode":"6500",
    "addr:street":"Naffet;Skrydstrup",
    "iso:country":"DK",
    "sg:address":"Naffet 5 B, Skrydstrup",
    "sg:city":"Vojens",
    "sg:orig_category":"Kirker",
    "sg:postcode":"6500",
    "sg:province":"Danmark",
    "wof:name":"Skrydstrup Kirke",
    "wof:placetype":"venue"
},
  "geometry": {"coordinates":[9.2987146378,55.2457237244],"type":"Point"}
}