{
  "type": "Feature",
  "properties": {
    "addr:full":"Maglekildevej 22 Roskilde Danmark 4000",
    "addr:housenumber":"22",
    "addr:postcode":"4000",
    "addr:street":"Maglekildevej",
    "iso:country":"DK",
    "sg:address":"Maglekildevej 22",
    "sg:city":"Roskilde",
    "sg:classifiers":[
        {
            "category":"Communications",
            "type":"Services"
        }
    ],
    "sg:phone":"+45 46 35 72 98",
    "sg:postcode":"4000",
    "sg:province":"Danmark",
    "sg:tags":[
        "og",
        "tv",
        "radio"
    ],
    "wof:name":"Maglekilde Radio",
    "wof:placetype":"venue"
},
  "geometry": {"coordinates":[12.0767726898,55.6445655823],"type":"Point"}
}