{
  "type": "Feature",
  "properties": {
    "addr:full":"Kontaktpers.: Egon Hylleberg, Klosterhaven 54, st. tv. Viborg Danmark 8800",
    "addr:housenumber":"54 st. tv.",
    "addr:postcode":"8800",
    "addr:street":"Klosterhaven",
    "iso:country":"DK",
    "sg:address":"Kontaktpers.: Egon Hylleberg, Klosterhaven 54, st. tv.",
    "sg:city":"Viborg",
    "sg:orig_category":"Afholdsforeninger",
    "sg:phone":"+45 86 62 23 15",
    "sg:postcode":"8800",
    "sg:province":"Danmark",
    "wof:name":"Viborg-Fjends Herreds Afholdskreds",
    "wof:placetype":"venue"
},
  "geometry": {"coordinates":[9.4071502686,56.452671051],"type":"Point"}
}