{
  "type": "Feature",
  "properties": {
    "addr:full":"Frederiksgade 25 \u00c5rhus C Danmark 8000",
    "addr:housenumber":"25",
    "addr:postcode":"8000",
    "addr:street":"Frederiksgade",
    "iso:country":"DK",
    "sg:address":"Frederiksgade 25",
    "sg:city":"\u00c5rhus C",
    "sg:orig_category":"Kiosker",
    "sg:phone":"+45 86 19 86 33",
    "sg:postcode":"8000",
    "sg:province":"Danmark",
    "wof:name":"C. C. Kiosken - Busgaden",
    "wof:placetype":"venue"
},
  "geometry": {"coordinates":[10.2061004639,56.1556396484],"type":"Point"}
}