{
  "type": "Feature",
  "properties": {
    "addr:full":"Birkevej 5 Kalundborg Danmark 4400",
    "addr:housenumber":"5",
    "addr:postcode":"4400",
    "addr:street":"Birkevej",
    "iso:country":"DK",
    "sg:address":"Birkevej 5",
    "sg:city":"Kalundborg",
    "sg:orig_category":"Vinduespolering",
    "sg:phone":"+45 59 50 82 20",
    "sg:postcode":"4400",
    "sg:province":"Danmark",
    "wof:name":"Jensen, Jens Brunholt",
    "wof:placetype":"venue"
},
  "geometry": {"coordinates":[11.0494356155,55.6939277649],"type":"Point"}
}