{
  "type": "Feature",
  "properties": {
    "iso:country":"DK",
    "sg:address":"Vesterbrogade 36",
    "sg:city":"Gilleleje",
    "sg:orig_category":"Skomagere",
    "sg:phone":"+45 48 30 16 08",
    "sg:postcode":"3250",
    "sg:province":"Danmark",
    "wof:name":"Skomageri & L\u00e5seservice",
    "wof:placetype":"venue"
},
  "geometry": {"coordinates":[12.300573349,56.1260528564],"type":"Point"}
}