{
  "type": "Feature",
  "properties": {
    "addr:full":"Engtoften 52 Storvorde Danmark 9280",
    "addr:housenumber":"52",
    "addr:postcode":"9280",
    "addr:street":"Engtoften",
    "iso:country":"DK",
    "sg:address":"Engtoften 52",
    "sg:city":"Storvorde",
    "sg:orig_category":"Murermestre",
    "sg:phone":"+45 98 31 83 91",
    "sg:postcode":"9280",
    "sg:province":"Danmark",
    "wof:name":"Hassing Storvorde ApS, Bent",
    "wof:placetype":"venue"
},
  "geometry": {"coordinates":[10.1055364609,57.0005874634],"type":"Point"}
}