{
  "type": "Feature",
  "properties": {
    "addr:full":"Stangevej 1, \u00d8sterlars Gudhjem Danmark 3760",
    "addr:housenumber":"1",
    "addr:postcode":"3760",
    "addr:street":"Stangevej;Osterlars",
    "iso:country":"DK",
    "sg:address":"Stangevej 1, \u00d8sterlars",
    "sg:city":"Gudhjem",
    "sg:orig_category":"Museer",
    "sg:phone":"+45 56 49 83 19",
    "sg:postcode":"3760",
    "sg:province":"Danmark",
    "sg:website":"www.bornmid.dk",
    "wof:name":"Bornholms Middelaldercenter",
    "wof:placetype":"venue"
},
  "geometry": {"coordinates":[15.1870470047,55.3205566406],"type":"Point"}
}