{
  "type": "Feature",
  "properties": {
    "addr:full":"Langelinie 9, Nordby Fan\u00f8 Danmark 6720",
    "addr:housenumber":"9",
    "addr:postcode":"6720",
    "addr:street":"Langelinie",
    "iso:country":"DK",
    "sg:address":"Langelinie 9, Nordby",
    "sg:city":"Fan\u00f8",
    "sg:orig_category":"Sommerhusudlejning",
    "sg:phone":"+45 75 16 21 22",
    "sg:postcode":"6720",
    "sg:province":"Danmark",
    "sg:website":"www.dancenter.com",
    "wof:name":"DanCenter Fan\u00f8",
    "wof:placetype":"venue"
},
  "geometry": {"coordinates":[8.4069461823,55.4484786987],"type":"Point"}
}