{
  "type": "Feature",
  "properties": {
    "addr:full":"Torupvej 1 Hedensted Danmark 8722",
    "addr:housenumber":"1",
    "addr:postcode":"8722",
    "addr:street":"Torupvej",
    "iso:country":"DK",
    "sg:address":"Torupvej 1",
    "sg:city":"Hedensted",
    "sg:orig_category":"Menighedshuse",
    "sg:phone":"+45 75 89 18 90",
    "sg:postcode":"8722",
    "sg:province":"Danmark",
    "wof:name":"Hedensted Missionshus",
    "wof:placetype":"venue"
},
  "geometry": {"coordinates":[9.702132225,55.7654953003],"type":"Point"}
}