{
  "type": "Feature",
  "properties": {
    "addr:full":"Fmd.: Palle Madsen, Skagen Landevej 398, Mygdal Hj\u00f8rring Danmark 9800",
    "addr:housenumber":"398",
    "addr:postcode":"9800",
    "addr:street":"Palle Madsen Skagen Landevej;Mygdal Hjorring Danmark",
    "iso:country":"DK",
    "sg:address":"Fmd.: Palle Madsen, Skagen Landevej 398, Mygdal",
    "sg:city":"Hj\u00f8rring",
    "sg:orig_category":"Folkedans",
    "sg:phone":"+45 98 97 15 02",
    "sg:postcode":"9800",
    "sg:province":"Danmark",
    "wof:name":"Bjergby-Mygdal Folkedanserforening",
    "wof:placetype":"venue"
},
  "geometry": {"coordinates":[9.9885387421,57.4594764709],"type":"Point"}
}