{
  "type": "Feature",
  "properties": {
    "addr:full":"Sangg\u00e5rdvej 2, Borbjerg Holstebro Danmark 7500",
    "addr:housenumber":"2",
    "addr:postcode":"7500",
    "addr:street":"Sanggaardvej;Borbjerg",
    "iso:country":"DK",
    "sg:address":"Sangg\u00e5rdvej 2, Borbjerg",
    "sg:city":"Holstebro",
    "sg:orig_category":"Maskinstationer",
    "sg:phone":"+45 97 44 00 13",
    "sg:postcode":"7500",
    "sg:province":"Danmark",
    "wof:name":"Sanggaard Maskinstation",
    "wof:placetype":"venue"
},
  "geometry": {"coordinates":[8.6202583313,56.3625221252],"type":"Point"}
}