{
  "type": "Feature",
  "properties": {
    "addr:full":"Horsensvej 581 Vejle \u00d8 Danmark 7120",
    "addr:housenumber":"581",
    "addr:postcode":"7120",
    "addr:street":"Horsensvej",
    "iso:country":"DK",
    "sg:address":"Horsensvej 581",
    "sg:city":"Vejle \u00d8",
    "sg:orig_category":"HOTELS: OG MOTELLER",
    "sg:phone":"+45 75 89 57 99",
    "sg:postcode":"7120",
    "sg:province":"Danmark",
    "wof:name":"Bredal Kro & Motel",
    "wof:placetype":"venue"
},
  "geometry": {"coordinates":[9.6419563293,55.7478904724],"type":"Point"}
}