{
  "type": "Feature",
  "properties": {
    "addr:full":"Baneg\u00e5rdsalleen 100 Nyborg Danmark 5800",
    "addr:housenumber":"100",
    "addr:postcode":"5800",
    "addr:street":"Banegaardsalleen",
    "iso:country":"DK",
    "sg:address":"Baneg\u00e5rdsalleen 100",
    "sg:city":"Nyborg",
    "sg:orig_category":"Jernbaner",
    "sg:phone":"+45 70 13 14 15",
    "sg:postcode":"5800",
    "sg:province":"Danmark",
    "sg:website":"www.dsb.dk",
    "wof:name":"Nyborg Station",
    "wof:placetype":"venue"
},
  "geometry": {"coordinates":[10.8045387268,55.3115158081],"type":"Point"}
}