{
  "type": "Feature",
  "properties": {
    "iso:country":"DK",
    "sg:address":"Sundevedsgade 38",
    "sg:city":"K\u00f8benhavn",
    "sg:orig_category":"Bodegaer",
    "sg:phone":"+45 33 31 18 22",
    "sg:postcode":"1751",
    "sg:province":"Danmark",
    "wof:name":"Lille R\u00e5dhus, Det",
    "wof:placetype":"venue"
},
  "geometry": {"coordinates":[12.5460996628,55.6698989868],"type":"Point"}
}