{
  "type": "Feature",
  "properties": {
    "iso:country":"DK",
    "sg:address":"Bannerupvej 3, Bannerup",
    "sg:city":"Eskilstrup",
    "sg:orig_category":"Rideskoler",
    "sg:phone":"+45 54 43 69 89",
    "sg:postcode":"4863",
    "sg:province":"Danmark",
    "wof:name":"N\u00f8rre Alslev Sportsrideklub",
    "wof:placetype":"venue"
},
  "geometry": {"coordinates":[11.8839511871,54.8547515869],"type":"Point"}
}