{
  "type": "Feature",
  "properties": {
    "addr:full":"S\u00f8gade 1 Frederikshavn Danmark 9900",
    "addr:housenumber":"1",
    "addr:postcode":"9900",
    "addr:street":"Sogade",
    "iso:country":"DK",
    "sg:address":"S\u00f8gade 1",
    "sg:city":"Frederikshavn",
    "sg:orig_category":"Psykologer, praktiserende",
    "sg:phone":"+45 98 42 25 22",
    "sg:postcode":"9900",
    "sg:province":"Danmark",
    "wof:name":"Pontoppidan, Anne",
    "wof:placetype":"venue"
},
  "geometry": {"coordinates":[10.5287399292,57.4326667786],"type":"Point"}
}