{
  "type": "Feature",
  "properties": {
    "addr:full":"Skovvangsvej 129 \u00c5rhus N Danmark 8200",
    "addr:housenumber":"129",
    "addr:postcode":"8200",
    "addr:street":"Skovvangsvej",
    "iso:country":"DK",
    "sg:address":"Skovvangsvej 129",
    "sg:city":"\u00c5rhus N",
    "sg:orig_category":"Fritidshjem",
    "sg:phone":"+45 86 16 81 40",
    "sg:postcode":"8200",
    "sg:province":"Danmark",
    "wof:name":"Skovvang, Fritidshjem",
    "wof:placetype":"venue"
},
  "geometry": {"coordinates":[4.9393601418,49.7092018127],"type":"Point"}
}