{
  "type": "Feature",
  "properties": {
    "addr:full":"Fmd.: Hanne Ebdrup, Vestergade 12, 1. Aalestrup Danmark 9620",
    "addr:housenumber":"12 1",
    "addr:postcode":"9620",
    "addr:street":"Vestergade",
    "iso:country":"DK",
    "sg:address":"Fmd.: Hanne Ebdrup, Vestergade 12, 1.",
    "sg:city":"Aalestrup",
    "sg:orig_category":"Hobbybetonede foreninger",
    "sg:phone":"+45 98 64 38 00",
    "sg:postcode":"9620",
    "sg:province":"Danmark",
    "wof:name":"Foreningen af Kreativt H\u00e5ndv\u00e6rk",
    "wof:placetype":"venue"
},
  "geometry": {"coordinates":[9.4901504517,56.6938285828],"type":"Point"}
}