{
  "type": "Feature",
  "properties": {
    "addr:full":"Jernbanegade 75 Middelfart Danmark 5500",
    "addr:housenumber":"75",
    "addr:postcode":"5500",
    "addr:street":"Jernbanegade",
    "iso:country":"DK",
    "sg:address":"Jernbanegade 75",
    "sg:city":"Middelfart",
    "sg:orig_category":"INGENI\u00c3\u02dcRER",
    "sg:phone":"+45 64 41 58 11",
    "sg:postcode":"5500",
    "sg:province":"Danmark",
    "wof:name":"\u00d8stergaard & Partner ApS",
    "wof:placetype":"venue"
},
  "geometry": {"coordinates":[9.7360467911,55.5019035339],"type":"Point"}
}