{
  "type": "Feature",
  "properties": {
    "addr:full":"\u00c5gade 13, Tejn Allinge Danmark 3770",
    "addr:housenumber":"13",
    "addr:postcode":"3770",
    "addr:street":"Aagade;Tejn",
    "iso:country":"DK",
    "sg:address":"\u00c5gade 13, Tejn",
    "sg:city":"Allinge",
    "sg:orig_category":"Flytteforretninger",
    "sg:phone":"+45 56 48 11 53",
    "sg:postcode":"3770",
    "sg:province":"Danmark",
    "wof:name":"Palles Antik & Flytteforretning",
    "wof:placetype":"venue"
},
  "geometry": {"coordinates":[14.7998552322,55.2743835449],"type":"Point"}
}