{
  "type": "Feature",
  "properties": {
    "addr:full":"Hvals\u00f8vej 16, Kr. Sonnerup Kirke S\u00e5by Danmark 4060",
    "addr:housenumber":"16 kr.",
    "addr:postcode":"4060",
    "addr:street":"Hvalsovej;Sonnerup Kirke",
    "iso:country":"DK",
    "sg:address":"Hvals\u00f8vej 16, Kr. Sonnerup",
    "sg:city":"Kirke S\u00e5by",
    "sg:orig_category":"Kulturcentre",
    "sg:phone":"+45 46 49 25 60",
    "sg:postcode":"4060",
    "sg:province":"Danmark",
    "wof:name":"Trudsholm Have- og Kunstcenter",
    "wof:placetype":"venue"
},
  "geometry": {"coordinates":[11.8739786148,55.6341285706],"type":"Point"}
}