{
  "type": "Feature",
  "properties": {
    "addr:full":"Frederiks Torv 1 Thisted Danmark 7700",
    "addr:housenumber":"1",
    "addr:postcode":"7700",
    "addr:street":"Frederiks Torv",
    "iso:country":"DK",
    "sg:address":"Frederiks Torv 1",
    "sg:city":"Thisted",
    "sg:orig_category":"Tandteknikere, Kliniske",
    "sg:phone":"+45 97 91 00 65",
    "sg:postcode":"7700",
    "sg:province":"Danmark",
    "wof:name":"Klitgaard, Erik",
    "wof:placetype":"venue"
},
  "geometry": {"coordinates":[8.6872825623,56.9542770386],"type":"Point"}
}