{
  "type": "Feature",
  "properties": {
    "addr:full":"Skolegade 25 Uldum Danmark 7171",
    "addr:housenumber":"25",
    "addr:postcode":"7171",
    "addr:street":"Skolegade",
    "iso:country":"DK",
    "sg:address":"Skolegade 25",
    "sg:city":"Uldum",
    "sg:orig_category":"Museer",
    "sg:phone":"+45 75 67 94 84",
    "sg:postcode":"7171",
    "sg:province":"Danmark",
    "wof:name":"Uldum M\u00f8lle",
    "wof:placetype":"venue"
},
  "geometry": {"coordinates":[9.5841646194,55.8459396362],"type":"Point"}
}