{
  "type": "Feature",
  "properties": {
    "addr:full":"Borggade 16 Gr\u00e5sten Danmark 6300",
    "addr:housenumber":"16",
    "addr:postcode":"6300",
    "addr:street":"Borggade",
    "iso:country":"DK",
    "sg:address":"Borggade 16",
    "sg:city":"Gr\u00e5sten",
    "sg:orig_category":"HOTELS: OG MOTELLER",
    "sg:phone":"+45 74 65 06 15",
    "sg:postcode":"6300",
    "sg:province":"Danmark",
    "wof:name":"Axelhus",
    "wof:placetype":"venue"
},
  "geometry": {"coordinates":[25.3302497864,60.2151107788],"type":"Point"}
}