{
  "type": "Feature",
  "properties": {
    "addr:full":"Frejlev Skolevej 7 Aalborg SV Danmark 9200",
    "addr:housenumber":"7",
    "addr:postcode":"9200",
    "addr:street":"Frejlev Skolevej",
    "iso:country":"DK",
    "sg:address":"Frejlev Skolevej 7",
    "sg:city":"Aalborg SV",
    "sg:orig_category":"Kommunale folkeskoler",
    "sg:phone":"+45 98 34 31 44",
    "sg:postcode":"9200",
    "sg:province":"Danmark",
    "wof:name":"Frejlev Skole",
    "wof:placetype":"venue"
},
  "geometry": {"coordinates":[9.8111524582,57.0071487427],"type":"Point"}
}