{
  "type": "Feature",
  "properties": {
    "addr:full":"\u00d8stergade 41 Hjallerup Danmark 9320",
    "addr:housenumber":"41",
    "addr:postcode":"9320",
    "addr:street":"Ostergade",
    "iso:country":"DK",
    "sg:address":"\u00d8stergade 41",
    "sg:city":"Hjallerup",
    "sg:orig_category":"Hudpleje",
    "sg:phone":"+45 98 28 30 40",
    "sg:postcode":"9320",
    "sg:province":"Danmark",
    "wof:name":"NU Consult",
    "wof:placetype":"venue"
},
  "geometry": {"coordinates":[10.1525087357,57.1685142517],"type":"Point"}
}