{
  "type": "Feature",
  "properties": {
    "addr:full":"Traneg\u00e5rdsvej 44 Hellerup Danmark 2900",
    "addr:housenumber":"44",
    "addr:postcode":"2900",
    "addr:street":"Tranegaardsvej",
    "iso:country":"DK",
    "sg:address":"Traneg\u00e5rdsvej 44",
    "sg:city":"Hellerup",
    "sg:orig_category":"Gulvafslibning",
    "sg:phone":"+45 39 61 22 95",
    "sg:postcode":"2900",
    "sg:province":"Danmark",
    "wof:name":"J. Y. Entreprise",
    "wof:placetype":"venue"
},
  "geometry": {"coordinates":[12.5651359558,55.7404708862],"type":"Point"}
}