{
  "type": "Feature",
  "properties": {
    "addr:full":"Nystrupvej 19 Thisted Danmark 7700",
    "addr:housenumber":"19",
    "addr:postcode":"7700",
    "addr:street":"Nystrupvej",
    "iso:country":"DK",
    "sg:address":"Nystrupvej 19",
    "sg:city":"Thisted",
    "sg:classifiers":[
        {
            "category":"Sports & Exercise",
            "subcategory":"Sports Center",
            "type":"Entertainment"
        }
    ],
    "sg:phone":"+45 97 97 41 41",
    "sg:postcode":"7700",
    "sg:province":"Danmark",
    "sg:tags":[
        "golf"
    ],
    "wof:name":"Nordvestjysk Golfklub",
    "wof:placetype":"venue"
},
  "geometry": {"coordinates":[8.5251960754,57.0117530823],"type":"Point"}
}