{
  "type": "Feature",
  "properties": {
    "addr:full":"Fmd.: Ole Gr\u00f8nb\u00e6k, Appevej 7 Tommerup Danmark 5690",
    "addr:housenumber":"7",
    "addr:postcode":"5690",
    "addr:street":"Appevej",
    "iso:country":"DK",
    "sg:address":"Fmd.: Ole Gr\u00f8nb\u00e6k, Appevej 7",
    "sg:city":"Tommerup",
    "sg:orig_category":"Kulturelle foreninger",
    "sg:phone":"+45 64 76 10 91",
    "sg:postcode":"5690",
    "sg:province":"Danmark",
    "sg:website":"tommerupfolkemusiklaug.f2s.com",
    "wof:name":"Tommerup Folkemusiklaug",
    "wof:placetype":"venue"
},
  "geometry": {"coordinates":[10.2489509583,55.3236503601],"type":"Point"}
}