{
  "type": "Feature",
  "properties": {
    "addr:full":"Ladelundsvej 10 Silkeborg Danmark 8600",
    "addr:housenumber":"10",
    "addr:postcode":"8600",
    "addr:street":"Ladelundsvej",
    "iso:country":"DK",
    "sg:address":"Ladelundsvej 10",
    "sg:city":"Silkeborg",
    "sg:orig_category":"Sko",
    "sg:phone":"+45 86 81 19 18",
    "sg:postcode":"8600",
    "sg:province":"Danmark",
    "wof:name":"Gj\u00f8ls-Andersen, Preben",
    "wof:placetype":"venue"
},
  "geometry": {"coordinates":[9.5118207932,56.1782722473],"type":"Point"}
}