{
  "type": "Feature",
  "properties": {
    "iso:country":"DK",
    "sg:address":"Lavhedevej 52",
    "sg:city":"Holstebro",
    "sg:orig_category":"Cykler",
    "sg:phone":"+45 97 42 12 22",
    "sg:postcode":"7500",
    "sg:province":"Danmark",
    "wof:name":"Cykel-b\u00f8rsen",
    "wof:placetype":"venue"
},
  "geometry": {"coordinates":[8.6166992188,56.3752937317],"type":"Point"}
}