{
  "type": "Feature",
  "properties": {
    "addr:full":"Jernbane All\u00e9 1, Dalum Odense SV Danmark 5250",
    "addr:housenumber":"1",
    "addr:postcode":"5250",
    "addr:street":"Jernbane Alle\u0301;Dalum",
    "iso:country":"DK",
    "sg:address":"Jernbane All\u00e9 1, Dalum",
    "sg:city":"Odense SV",
    "sg:orig_category":"Begravelsesforretninger",
    "sg:phone":"+45 66 13 24 55",
    "sg:postcode":"5250",
    "sg:province":"Danmark",
    "wof:name":"Begravelsesforretningen Dalum-Hjallese",
    "wof:placetype":"venue"
},
  "geometry": {"coordinates":[10.3153953552,55.3362998962],"type":"Point"}
}