{
  "type": "Feature",
  "properties": {
    "iso:country":"DK",
    "sg:address":"Bregnebjergvej 6",
    "sg:city":"Ringsted",
    "sg:orig_category":"INGENI\u00c3\u02dcRER",
    "sg:phone":"+45 57 61 31 36",
    "sg:postcode":"4100",
    "sg:province":"Danmark",
    "wof:name":"Guntofte & Bech",
    "wof:placetype":"venue"
},
  "geometry": {"coordinates":[11.7764396667,55.4492454529],"type":"Point"}
}