{
  "type": "Feature",
  "properties": {
    "addr:full":"Bredgade 83 Lem Danmark 6940",
    "addr:housenumber":"83",
    "addr:postcode":"6940",
    "addr:street":"Bredgade",
    "iso:country":"DK",
    "sg:address":"Bredgade 83",
    "sg:city":"Lem",
    "sg:orig_category":"Fotografer",
    "sg:phone":"+45 97 34 11 50",
    "sg:postcode":"6940",
    "sg:province":"Danmark",
    "wof:name":"Irenes Foto",
    "wof:placetype":"venue"
},
  "geometry": {"coordinates":[8.388669014,56.026599884],"type":"Point"}
}