{
  "type": "Feature",
  "properties": {
    "addr:full":"Ringvejen 6 Hadsund Danmark 9560",
    "addr:housenumber":"6",
    "addr:postcode":"9560",
    "addr:street":"Ringvejen",
    "iso:country":"DK",
    "sg:address":"Ringvejen 6",
    "sg:city":"Hadsund",
    "sg:orig_category":"Vinduer",
    "sg:phone":"+45 99 53 53 53",
    "sg:postcode":"9560",
    "sg:province":"Danmark",
    "sg:website":"www.multi-lite.dk",
    "wof:name":"Multi-Lite A/S",
    "wof:placetype":"venue"
},
  "geometry": {"coordinates":[10.1068181992,56.7265930176],"type":"Point"}
}