{
  "type": "Feature",
  "properties": {
    "addr:full":"Faurholtvej 8  Hampen Danmark 7362",
    "addr:housenumber":"8",
    "addr:postcode":"7362",
    "addr:street":"Faurholtvej",
    "iso:country":"DK",
    "sg:address":"Faurholtvej 8 ",
    "sg:city":"Hampen",
    "sg:classifiers":[
        {
            "category":"Manufacturing",
            "subcategory":"Lumber",
            "type":"Manufacturing & Wholesale Goods"
        }
    ],
    "sg:phone":"+45 86 86 91 00",
    "sg:postcode":"7362",
    "sg:province":"Danmark",
    "sg:tags":[
        "wood"
    ],
    "wof:name":"ST HJ\u00d8LLUND SAVV\u00c6RK A/S",
    "wof:placetype":"venue"
},
  "geometry": {"coordinates":[9.3927297592,56.0735206604],"type":"Point"}
}