{
  "type": "Feature",
  "properties": {
    "addr:full":"Bethania, Georg Hansens Vej 4 A S\u00f8nderborg Danmark 6400",
    "addr:housenumber":"4 a",
    "addr:postcode":"6400",
    "addr:street":"Georg Hansens Vej",
    "iso:country":"DK",
    "sg:address":"Bethania, Georg Hansens Vej 4 A",
    "sg:city":"S\u00f8nderborg",
    "sg:orig_category":"Trossamfund uden for folkekirken",
    "sg:phone":"+45 74 42 96 48",
    "sg:postcode":"6400",
    "sg:province":"Danmark",
    "wof:name":"Luthersk Missionsforening",
    "wof:placetype":"venue"
},
  "geometry": {"coordinates":[-80.3385009766,36.1813087463],"type":"Point"}
}