{
  "type": "Feature",
  "properties": {
    "addr:full":"Kongshvilebakken 66 Kongens Lyngby Danmark 2800",
    "addr:housenumber":"66",
    "addr:postcode":"2800",
    "addr:street":"Kongshvilebakken",
    "iso:country":"DK",
    "sg:address":"Kongshvilebakken 66",
    "sg:city":"Kongens Lyngby",
    "sg:orig_category":"Databehandling",
    "sg:phone":"+45 45 88 56 42",
    "sg:postcode":"2800",
    "sg:province":"Danmark",
    "wof:name":"Lyngby Programs ApS",
    "wof:placetype":"venue"
},
  "geometry": {"coordinates":[12.477604866,55.7723197937],"type":"Point"}
}