{
  "type": "Feature",
  "properties": {
    "iso:country":"DK",
    "sg:address":"Fiskergade 1, Postboks 130",
    "sg:city":"Struer",
    "sg:orig_category":"Dag- og distriktsblade",
    "sg:phone":"+45 97 85 55 44",
    "sg:postcode":"7600",
    "sg:province":"Danmark",
    "sg:website":"www.uge-avisen.dk",
    "wof:name":"Ugeavisen",
    "wof:placetype":"venue"
},
  "geometry": {"coordinates":[8.5946903229,56.491191864],"type":"Point"}
}