{
  "type": "Feature",
  "properties": {
    "addr:full":"Leder: Else Elisabeth Andersen, N\u00f8lev-Driften 150, N\u00f8lev Odder Danmark 8300",
    "addr:housenumber":"150",
    "addr:postcode":"8300",
    "addr:street":"Nolev-Driften;Nolev",
    "iso:country":"DK",
    "sg:address":"Leder: Else Elisabeth Andersen, N\u00f8lev-Driften 150, N\u00f8lev",
    "sg:city":"Odder",
    "sg:orig_category":"Oplysningsforbund",
    "sg:phone":"+45 86 55 80 22",
    "sg:postcode":"8300",
    "sg:province":"Danmark",
    "wof:name":"FOF Odder",
    "wof:placetype":"venue"
},
  "geometry": {"coordinates":[10.1497612,55.9733161926],"type":"Point"}
}