{
  "type": "Feature",
  "properties": {
    "addr:full":"Anebjergvej 7 Silkeborg Danmark 8600",
    "addr:housenumber":"7",
    "addr:postcode":"8600",
    "addr:street":"Anebjergvej",
    "iso:country":"DK",
    "sg:address":"Anebjergvej 7",
    "sg:city":"Silkeborg",
    "sg:orig_category":"Traktorer",
    "sg:phone":"+45 86 84 13 22",
    "sg:postcode":"8600",
    "sg:province":"Danmark",
    "sg:website":"www.midtjysktraktorlager.dk",
    "wof:name":"Midtjysk Traktorlager/ Harder & S\u00f8gaard A/S",
    "wof:placetype":"venue"
},
  "geometry": {"coordinates":[9.6972160339,56.1513252258],"type":"Point"}
}