{
  "type": "Feature",
  "properties": {
    "addr:full":"Strandvejen 3 Skive Danmark 7800",
    "addr:housenumber":"3",
    "addr:postcode":"7800",
    "addr:street":"Strandvejen",
    "iso:country":"DK",
    "sg:address":"Strandvejen 3",
    "sg:city":"Skive",
    "sg:classifiers":[
        {
            "category":"Restaurant",
            "type":"Food & Drink"
        }
    ],
    "sg:phone":"+45 97 52 53 25",
    "sg:postcode":"7800",
    "sg:province":"Danmark",
    "wof:name":"A Hereford Beefstouw Rosenh\u00f8j",
    "wof:placetype":"venue"
},
  "geometry": {"coordinates":[9.0496940613,56.577041626],"type":"Point"}
}