{
  "type": "Feature",
  "properties": {
    "addr:full":"Tempovej 4 Hadsund Danmark 9560",
    "addr:housenumber":"4",
    "addr:postcode":"9560",
    "addr:street":"Tempovej",
    "iso:country":"DK",
    "sg:address":"Tempovej 4",
    "sg:city":"Hadsund",
    "sg:orig_category":"Erhvervsskoler",
    "sg:phone":"+45 96 52 04 60",
    "sg:postcode":"9560",
    "sg:province":"Danmark",
    "sg:website":"www.hgmf.dk",
    "wof:name":"Handelsgymnasiet Mariager Fjord, Afdeling \u00d8st",
    "wof:placetype":"venue"
},
  "geometry": {"coordinates":[10.1295623779,56.7206382751],"type":"Point"}
}