{
  "type": "Feature",
  "properties": {
    "addr:full":"Hovedvejen 11, Ny Glim Roskilde Danmark 4000",
    "addr:housenumber":"11",
    "addr:postcode":"glim;4000",
    "addr:street":"Hovedvejen",
    "iso:country":"DK",
    "sg:address":"Hovedvejen 11, Ny Glim",
    "sg:city":"Roskilde",
    "sg:orig_category":"Fabrikker",
    "sg:phone":"+45 46 35 37 37",
    "sg:postcode":"4000",
    "sg:province":"Danmark",
    "wof:name":"Glim V\u00e6rkt\u00f8jsfabrik",
    "wof:placetype":"venue"
},
  "geometry": {"coordinates":[12.0909376144,55.6404838562],"type":"Point"}
}