{
  "type": "Feature",
  "properties": {
    "addr:full":"Roskildevej 138 A Valby Danmark 2500",
    "addr:housenumber":"138 a",
    "addr:postcode":"2500",
    "addr:street":"Roskildevej",
    "iso:country":"DK",
    "sg:address":"Roskildevej 138 A",
    "sg:city":"Valby",
    "sg:orig_category":"Vinduer",
    "sg:phone":"+45 38 74 20 33",
    "sg:postcode":"2500",
    "sg:province":"Danmark",
    "wof:name":"Primo-Vinduer Lintrup A/S",
    "wof:placetype":"venue"
},
  "geometry": {"coordinates":[12.4907999039,55.6726493835],"type":"Point"}
}