{
  "type": "Feature",
  "properties": {
    "addr:full":"Middelfartvej 113, Stubberup Assens Danmark 5610",
    "addr:housenumber":"113",
    "addr:postcode":"5610",
    "addr:street":"Middelfartvej",
    "iso:country":"DK",
    "sg:address":"Middelfartvej 113, Stubberup",
    "sg:city":"Assens",
    "sg:classifiers":[
        {
            "category":"Restaurant",
            "type":"Food & Drink"
        }
    ],
    "sg:phone":"+45 64 79 10 49",
    "sg:postcode":"5610",
    "sg:province":"Danmark",
    "wof:name":"Stubberup Kro",
    "wof:placetype":"venue"
},
  "geometry": {"coordinates":[9.8998937607,55.2702522278],"type":"Point"}
}