{
  "type": "Feature",
  "properties": {
    "addr:full":"Storegade 6 Hinnerup Danmark 8382",
    "addr:housenumber":"6",
    "addr:postcode":"8382",
    "addr:street":"Storegade",
    "iso:country":"DK",
    "sg:address":"Storegade 6",
    "sg:city":"Hinnerup",
    "sg:orig_category":"Ejendomshandel",
    "sg:phone":"+45 86 98 77 77",
    "sg:postcode":"8382",
    "sg:province":"Danmark",
    "wof:name":"EDC M\u00e6glerne Hinnerup",
    "wof:placetype":"venue"
},
  "geometry": {"coordinates":[10.062286377,56.2637405396],"type":"Point"}
}