{
  "type": "Feature",
  "properties": {
    "addr:full":"Vedb\u00e6kvej 1, Valsg\u00e5rd Hobro Danmark 9500",
    "addr:housenumber":"1",
    "addr:postcode":"9500",
    "addr:street":"Vedbaekvej;Valsgaard",
    "iso:country":"DK",
    "sg:address":"Vedb\u00e6kvej 1, Valsg\u00e5rd",
    "sg:city":"Hobro",
    "sg:orig_category":"Pelsvarer",
    "sg:phone":"+45 98 52 40 40",
    "sg:postcode":"9500",
    "sg:province":"Danmark",
    "wof:name":"Pelsg\u00e5rd, Arlis",
    "wof:placetype":"venue"
},
  "geometry": {"coordinates":[9.7946596146,56.6382789612],"type":"Point"}
}