{
  "type": "Feature",
  "properties": {
    "addr:full":"Sejerslevvej 3, S Sejerslev H\u00f8jer Danmark 6280",
    "addr:housenumber":"3",
    "addr:postcode":"6280",
    "addr:street":"Sejerslevvej;S Sejerslev Hojer Danmark",
    "iso:country":"DK",
    "sg:address":"Sejerslevvej 3, S Sejerslev",
    "sg:city":"H\u00f8jer",
    "sg:orig_category":"Forsamlingshuse",
    "sg:phone":"+45 74 78 95 00",
    "sg:postcode":"6280",
    "sg:province":"Danmark",
    "wof:name":"Emmerlev Sogns Forsamlingshus",
    "wof:placetype":"venue"
},
  "geometry": {"coordinates":[8.7432250977,54.9700012207],"type":"Point"}
}