{
  "type": "Feature",
  "properties": {
    "addr:full":"Stormgade 76 Esbjerg Danmark 6700",
    "addr:housenumber":"76",
    "addr:postcode":"6700",
    "addr:street":"Stormgade",
    "iso:country":"DK",
    "sg:address":"Stormgade 76",
    "sg:city":"Esbjerg",
    "sg:orig_category":"Arkitekter",
    "sg:phone":"+45 75 18 16 61",
    "sg:postcode":"6700",
    "sg:province":"Danmark",
    "wof:name":"Thomsen, Jens",
    "wof:placetype":"venue"
},
  "geometry": {"coordinates":[8.4452257156,55.4726715088],"type":"Point"}
}