{
  "type": "Feature",
  "properties": {
    "addr:full":"v/S\u00f8ren Gjedsig, Herningvej 73, Trandum Skive Danmark 7800",
    "addr:housenumber":"73",
    "addr:postcode":"7800",
    "addr:street":"Herningvej",
    "iso:country":"DK",
    "sg:address":"v/S\u00f8ren Gjedsig, Herningvej 73, Trandum",
    "sg:city":"Skive",
    "sg:orig_category":"\u00c3\u02dcvrig fritidsundervisning",
    "sg:phone":"+45 97 54 41 42",
    "sg:postcode":"7800",
    "sg:province":"Danmark",
    "wof:name":"Mogenstrup Aftenh\u00f8jskole",
    "wof:placetype":"venue"
},
  "geometry": {"coordinates":[9.0320358276,56.5666427612],"type":"Point"}
}