{
  "type": "Feature",
  "properties": {
    "addr:full":"Gr\u00f8nnegade 84 \u00c5rhus C Danmark 8000",
    "addr:housenumber":"84",
    "addr:postcode":"8000",
    "addr:street":"Gronnegade",
    "iso:country":"DK",
    "sg:address":"Gr\u00f8nnegade 84",
    "sg:city":"\u00c5rhus C",
    "sg:orig_category":"Autoudlejning",
    "sg:phone":"+45 86 12 32 30",
    "sg:postcode":"8000",
    "sg:province":"Danmark",
    "wof:name":"MLflyt",
    "wof:placetype":"venue"
},
  "geometry": {"coordinates":[4.717400074,49.7588005066],"type":"Point"}
}