{
  "type": "Feature",
  "properties": {
    "addr:full":"M\u00f8llev\u00e6nget 18, Raml\u00f8se Helsinge Danmark 3200",
    "addr:housenumber":"18",
    "addr:postcode":"3200",
    "addr:street":"Mollevaenget;Ramlose",
    "iso:country":"DK",
    "sg:address":"M\u00f8llev\u00e6nget 18, Raml\u00f8se",
    "sg:city":"Helsinge",
    "sg:orig_category":"Fabrikker",
    "sg:phone":"+45 48 71 27 37",
    "sg:postcode":"3200",
    "sg:province":"Danmark",
    "wof:name":"Strini Belysning ApS",
    "wof:placetype":"venue"
},
  "geometry": {"coordinates":[12.196846962,56.0224456787],"type":"Point"}
}