{
  "type": "Feature",
  "properties": {
    "addr:full":"Femagervej 33 Hvidovre Danmark 2650",
    "addr:housenumber":"33",
    "addr:postcode":"2650",
    "addr:street":"Femagervej",
    "iso:country":"DK",
    "sg:address":"Femagervej 33",
    "sg:city":"Hvidovre",
    "sg:orig_category":"Autoreparation og -service",
    "sg:phone":"+45 36 75 08 00",
    "sg:postcode":"2650",
    "sg:province":"Danmark",
    "wof:name":"PB Auto",
    "wof:placetype":"venue"
},
  "geometry": {"coordinates":[12.4680347443,55.6591529846],"type":"Point"}
}