{
  "type": "Feature",
  "properties": {
    "addr:full":"Grimsvej 4 Ebeltoft Danmark 8400",
    "addr:housenumber":"4",
    "addr:postcode":"8400",
    "addr:street":"Grimsvej",
    "iso:country":"DK",
    "sg:address":"Grimsvej 4",
    "sg:city":"Ebeltoft",
    "sg:classifiers":[
        {
            "category":"Taxi",
            "type":"Transportation"
        }
    ],
    "sg:phone":"+45 86 34 59 20",
    "sg:postcode":"8400",
    "sg:province":"Danmark",
    "wof:name":"Arne's Taxi",
    "wof:placetype":"venue"
},
  "geometry": {"coordinates":[10.6842832565,56.1977539062],"type":"Point"}
}