{
  "type": "Feature",
  "properties": {
    "addr:full":"Slotsgade 33 Aalborg Danmark 9000",
    "addr:housenumber":"33",
    "addr:postcode":"9000",
    "addr:street":"Slotsgade",
    "iso:country":"DK",
    "sg:address":"Slotsgade 33",
    "sg:city":"Aalborg",
    "sg:orig_category":"Cafeer",
    "sg:phone":"+45 98 11 37 80",
    "sg:postcode":"9000",
    "sg:province":"Danmark",
    "wof:name":"Charles, Caf\u00e9",
    "wof:placetype":"venue"
},
  "geometry": {"coordinates":[9.9252500534,57.0489082336],"type":"Point"}
}