{
  "type": "Feature",
  "properties": {
    "addr:full":"\u00d8sterbakken 5 Thisted Danmark 7700",
    "addr:housenumber":"5",
    "addr:postcode":"7700",
    "addr:street":"Osterbakken",
    "iso:country":"DK",
    "sg:address":"\u00d8sterbakken 5",
    "sg:city":"Thisted",
    "sg:classifiers":[
        {
            "category":"Restaurant",
            "type":"Food & Drink"
        }
    ],
    "sg:phone":"+45 97 91 00 83",
    "sg:postcode":"7700",
    "sg:province":"Danmark",
    "wof:name":"Matam-Alminah",
    "wof:placetype":"venue"
},
  "geometry": {"coordinates":[8.6931381226,56.9560432434],"type":"Point"}
}