{
  "type": "Feature",
  "properties": {
    "iso:country":"DK",
    "sg:address":"Eremitageparken 333",
    "sg:city":"Kongens Lyngby",
    "sg:orig_category":"Vuggestuer",
    "sg:phone":"+45 45 87 44 58",
    "sg:postcode":"2800",
    "sg:province":"Danmark",
    "wof:name":"Eremitageparkens Vuggestue",
    "wof:placetype":"venue"
},
  "geometry": {"coordinates":[12.5353097916,55.7962417603],"type":"Point"}
}