{
  "type": "Feature",
  "properties": {
    "iso:country":"DK",
    "sg:address":"Falkonerg\u00e5rdsvej 21",
    "sg:city":"Frederiksberg",
    "sg:orig_category":"Vuggestuer",
    "sg:phone":"+45 38 21 14 80",
    "sg:postcode":"1959",
    "sg:province":"Danmark",
    "wof:name":"Landbo, Frederiksberg Kommunes Vuggestue",
    "wof:placetype":"venue"
},
  "geometry": {"coordinates":[12.5412759781,55.686126709],"type":"Point"}
}