{
  "type": "Feature",
  "properties": {
    "addr:full":"Egevej 22 Karup Danmark 7470",
    "addr:housenumber":"22",
    "addr:postcode":"7470",
    "addr:street":"Egevej",
    "iso:country":"DK",
    "sg:address":"Egevej 22",
    "sg:city":"Karup",
    "sg:orig_category":"Integrerede institutioner",
    "sg:phone":"+45 96 62 55 55",
    "sg:postcode":"7470",
    "sg:province":"Danmark",
    "wof:name":"Lynghuset daginstitution",
    "wof:placetype":"venue"
},
  "geometry": {"coordinates":[9.1769647598,56.3089485168],"type":"Point"}
}