{
  "type": "Feature",
  "properties": {
    "iso:country":"DK",
    "sg:address":"Borgergade 5, Biersted",
    "sg:city":"Aabybro",
    "sg:orig_category":"Diners transportables",
    "sg:phone":"+45 98 26 80 10",
    "sg:postcode":"9440",
    "sg:province":"Danmark",
    "wof:name":"Biersted Kro",
    "wof:placetype":"venue"
},
  "geometry": {"coordinates":[9.7341356277,57.1588287354],"type":"Point"}
}