{
  "type": "Feature",
  "properties": {
    "addr:full":"Jernbanegade 11 Hj\u00f8rring Danmark 9800",
    "addr:housenumber":"11",
    "addr:postcode":"9800",
    "addr:street":"Jernbanegade",
    "iso:country":"DK",
    "sg:address":"Jernbanegade 11",
    "sg:city":"Hj\u00f8rring",
    "sg:orig_category":"Stoffer",
    "sg:phone":"+45 98 92 50 12",
    "sg:postcode":"9800",
    "sg:province":"Danmark",
    "wof:name":"T\u00f8jcentret",
    "wof:placetype":"venue"
},
  "geometry": {"coordinates":[9.9867744446,57.458152771],"type":"Point"}
}