{
  "type": "Feature",
  "properties": {
    "addr:full":"Hvidovrevej 205 Hvidovre Danmark 2650",
    "addr:housenumber":"205",
    "addr:postcode":"2650",
    "addr:street":"Hvidovrevej",
    "iso:country":"DK",
    "sg:address":"Hvidovrevej 205",
    "sg:city":"Hvidovre",
    "sg:orig_category":"Musik- og sangundervisning",
    "sg:phone":"+45 36 49 74 11",
    "sg:postcode":"2650",
    "sg:province":"Danmark",
    "wof:name":"Roepstorff, Marianne",
    "wof:placetype":"venue"
},
  "geometry": {"coordinates":[12.478433609,55.6463737488],"type":"Point"}
}