{
  "type": "Feature",
  "properties": {
    "addr:full":"Martin Hansens Vej 14 - 16 Ebeltoft Danmark 8400",
    "addr:housenumber":"14 16",
    "addr:postcode":"8400",
    "addr:street":"Martin Hansens Vej",
    "iso:country":"DK",
    "sg:address":"Martin Hansens Vej 14 - 16",
    "sg:city":"Ebeltoft",
    "sg:orig_category":"Tekstiltrykkerier",
    "sg:phone":"+45 86 34 48 77",
    "sg:postcode":"8400",
    "sg:province":"Danmark",
    "wof:name":"Danica Print A/S",
    "wof:placetype":"venue"
},
  "geometry": {"coordinates":[10.6841974258,56.1857032776],"type":"Point"}
}