{
  "type": "Feature",
  "properties": {
    "addr:full":"Fmd.: Jens Chr. Fjord, M\u00f8llegade 34, 1. tv. Skjern Danmark 6900",
    "addr:housenumber":"34 1 tv.",
    "addr:postcode":"6900",
    "addr:street":"Mollegade",
    "iso:country":"DK",
    "sg:address":"Fmd.: Jens Chr. Fjord, M\u00f8llegade 34, 1. tv.",
    "sg:city":"Skjern",
    "sg:orig_category":"Kirkelige foreninger",
    "sg:phone":"+45 97 35 04 53",
    "sg:postcode":"6900",
    "sg:province":"Danmark",
    "wof:name":"Indre Missions Samfund, Skjern",
    "wof:placetype":"venue"
},
  "geometry": {"coordinates":[8.492972374,55.9485740662],"type":"Point"}
}