{
  "type": "Feature",
  "properties": {
    "iso:country":"DK",
    "sg:address":"Kirkegade 8",
    "sg:city":"Aulum",
    "sg:classifiers":[
        {
            "category":"Communications",
            "type":"Services"
        }
    ],
    "sg:phone":"+45 97 47 20 26",
    "sg:postcode":"7490",
    "sg:province":"Danmark",
    "sg:tags":[
        "og",
        "tv",
        "radio"
    ],
    "sg:website":"www.2tal.dk/aulum",
    "wof:name":"N\u00f8rkj\u00e6r Radio - 2tal",
    "wof:placetype":"venue"
},
  "geometry": {"coordinates":[8.7976341248,56.2664222717],"type":"Point"}
}