{
  "type": "Feature",
  "properties": {
    "iso:country":"DK",
    "sg:address":"T\u00e5rnvej 25",
    "sg:city":"Hanstholm",
    "sg:orig_category":"Kirker",
    "sg:postcode":"7730",
    "sg:province":"Danmark",
    "wof:name":"Hansted Kirke",
    "wof:placetype":"venue"
},
  "geometry": {"coordinates":[8.5995817184,57.113483429],"type":"Point"}
}