{
  "type": "Feature",
  "properties": {
    "iso:country":"DK",
    "sg:address":"Farum Stationstorv 27",
    "sg:city":"Farum",
    "sg:orig_category":"Kiosker",
    "sg:phone":"+45 44 95 01 46",
    "sg:postcode":"3520",
    "sg:province":"Danmark",
    "wof:name":"DSB Kiosk",
    "wof:placetype":"venue"
},
  "geometry": {"coordinates":[12.3732414246,55.8125724792],"type":"Point"}
}