{
  "type": "Feature",
  "properties": {
    "iso:country":"DK",
    "sg:address":"Lillevangsvej 88",
    "sg:city":"Greve",
    "sg:orig_category":"Selskabslokaler",
    "sg:phone":"+45 43 90 25 36",
    "sg:postcode":"2670",
    "sg:province":"Danmark",
    "wof:name":"Langsiden, Restaurant",
    "wof:placetype":"venue"
},
  "geometry": {"coordinates":[12.3011627197,55.5936012268],"type":"Point"}
}