{
  "type": "Feature",
  "properties": {
    "addr:full":"Vesterhavsgade 134 B Thybor\u00f8n Danmark 7680",
    "addr:housenumber":"134 b",
    "addr:postcode":"7680",
    "addr:street":"Vesterhavsgade",
    "iso:country":"DK",
    "sg:address":"Vesterhavsgade 134 B",
    "sg:city":"Thybor\u00f8n",
    "sg:orig_category":"Fisk og vildt",
    "sg:phone":"+45 97 83 11 71",
    "sg:postcode":"7680",
    "sg:province":"Danmark",
    "wof:name":"Kalles\u00f8e, Hans",
    "wof:placetype":"venue"
},
  "geometry": {"coordinates":[-76.4168395996,37.452419281],"type":"Point"}
}