{
  "type": "Feature",
  "properties": {
    "addr:full":"L\u00f8vholmen 3 Svendborg Danmark 5700",
    "addr:housenumber":"3",
    "addr:postcode":"5700",
    "addr:street":"Lovholmen",
    "iso:country":"DK",
    "sg:address":"L\u00f8vholmen 3",
    "sg:city":"Svendborg",
    "sg:orig_category":"Rejsebureauer",
    "sg:phone":"+45 62 22 27 27",
    "sg:postcode":"5700",
    "sg:province":"Danmark",
    "sg:website":"www.bergholdt.dk",
    "wof:name":"Bergholdt",
    "wof:placetype":"venue"
},
  "geometry": {"coordinates":[10.6065101624,55.0595970154],"type":"Point"}
}