{
  "type": "Feature",
  "properties": {
    "addr:full":"Ravnsborgvej 3 K\u00f8ge Danmark 4600",
    "addr:housenumber":"3",
    "addr:postcode":"4600",
    "addr:street":"Ravnsborgvej",
    "iso:country":"DK",
    "sg:address":"Ravnsborgvej 3",
    "sg:city":"K\u00f8ge",
    "sg:classifiers":[
        {
            "category":"Restaurant",
            "type":"Food & Drink"
        }
    ],
    "sg:phone":"+45 56 66 01 70",
    "sg:postcode":"4600",
    "sg:province":"Danmark",
    "wof:name":"Ravnsborghallens Cafeteria",
    "wof:placetype":"venue"
},
  "geometry": {"coordinates":[12.1743335724,55.4437828064],"type":"Point"}
}