{
  "type": "Feature",
  "properties": {
    "iso:country":"DK",
    "sg:address":"Arendalsvej 367",
    "sg:city":"Silkeborg",
    "sg:orig_category":"Integrerede institutioner",
    "sg:phone":"+45 86 80 22 44",
    "sg:postcode":"8600",
    "sg:province":"Danmark",
    "wof:name":"Slugten Sm\u00e5b\u00f8rnsinstitution",
    "wof:placetype":"venue"
},
  "geometry": {"coordinates":[9.5906467438,56.1892738342],"type":"Point"}
}