{
  "type": "Feature",
  "properties": {
    "addr:full":"Hammerg\u00e5rdsvej 20, Gjerlev Gjerlev Danmark 8983",
    "addr:housenumber":"20",
    "addr:postcode":"8983",
    "addr:street":"Hammergaardsvej;Gjerlev Gjerlev Danmark",
    "iso:country":"DK",
    "sg:address":"Hammerg\u00e5rdsvej 20, Gjerlev",
    "sg:city":"Gjerlev",
    "sg:orig_category":"Plastvarefabrikker",
    "sg:phone":"+45 86 47 42 22",
    "sg:postcode":"8983",
    "sg:province":"Danmark",
    "wof:name":"Conplast",
    "wof:placetype":"venue"
},
  "geometry": {"coordinates":[10.1887750626,56.5788421631],"type":"Point"}
}