{
  "type": "Feature",
  "properties": {
    "addr:full":"Mejlsvej 45, Mejls Varde Danmark 6800",
    "addr:housenumber":"45",
    "addr:postcode":"6800",
    "addr:street":"Mejlsvej",
    "iso:country":"DK",
    "sg:address":"Mejlsvej 45, Mejls",
    "sg:city":"Varde",
    "sg:orig_category":"Private- og friskoler",
    "sg:phone":"+45 75 26 12 16",
    "sg:postcode":"6800",
    "sg:province":"Danmark",
    "wof:name":"Mejls-Orten-Tingh\u00f8j Friskole",
    "wof:placetype":"venue"
},
  "geometry": {"coordinates":[8.482629776,55.6220741272],"type":"Point"}
}