{
  "type": "Feature",
  "properties": {
    "addr:full":"Farum Gydevej 83 Farum Danmark 3520",
    "addr:housenumber":"83",
    "addr:postcode":"3520",
    "addr:street":"Farum Gydevej",
    "iso:country":"DK",
    "sg:address":"Farum Gydevej 83",
    "sg:city":"Farum",
    "sg:classifiers":[
        {
            "category":"Building & Trades",
            "subcategory":"Electrical",
            "type":"Services"
        }
    ],
    "sg:phone":"+45 44 95 68 69",
    "sg:postcode":"3520",
    "sg:province":"Danmark",
    "sg:tags":[
        "distributor"
    ],
    "wof:name":"Nord Distribution",
    "wof:placetype":"venue"
},
  "geometry": {"coordinates":[12.3615694046,55.8209075928],"type":"Point"}
}