{
  "type": "Feature",
  "properties": {
    "addr:full":"Koldingvej 24 Toftlund Danmark 6520",
    "addr:housenumber":"24",
    "addr:postcode":"6520",
    "addr:street":"Koldingvej",
    "iso:country":"DK",
    "sg:address":"Koldingvej 24",
    "sg:city":"Toftlund",
    "sg:orig_category":"Autoreparation og -service",
    "sg:phone":"+45 74 83 25 55",
    "sg:postcode":"6520",
    "sg:province":"Danmark",
    "wof:name":"Toftlund Auto & MC I/S",
    "wof:placetype":"venue"
},
  "geometry": {"coordinates":[9.0672740936,55.1859474182],"type":"Point"}
}