{
  "type": "Feature",
  "properties": {
    "addr:full":"Tinghusgade 21 Svendborg Danmark 5700",
    "addr:housenumber":"21",
    "addr:postcode":"5700",
    "addr:street":"Tinghusgade",
    "iso:country":"DK",
    "sg:address":"Tinghusgade 21",
    "sg:city":"Svendborg",
    "sg:orig_category":"Stoffer",
    "sg:phone":"+45 62 21 07 12",
    "sg:postcode":"5700",
    "sg:province":"Danmark",
    "sg:website":"www.stof2000.dk",
    "wof:name":"Stof 2000",
    "wof:placetype":"venue"
},
  "geometry": {"coordinates":[10.6041088104,55.0602149963],"type":"Point"}
}