{
  "type": "Feature",
  "properties": {
    "addr:full":"Griffenfeldsgade 7 A K\u00f8benhavn N Danmark 2200",
    "addr:housenumber":"7 a",
    "addr:postcode":"2200",
    "addr:street":"Griffenfeldsgade;Kobenhavn N Danmark",
    "iso:country":"DK",
    "sg:address":"Griffenfeldsgade 7 A",
    "sg:city":"K\u00f8benhavn N",
    "sg:orig_category":"Teatre",
    "sg:phone":"+45 35 36 61 22",
    "sg:postcode":"2200",
    "sg:province":"Danmark",
    "wof:name":"Comedievognens Broscene",
    "wof:placetype":"venue"
},
  "geometry": {"coordinates":[-76.4168395996,37.452419281],"type":"Point"}
}