{
  "type": "Feature",
  "properties": {
    "iso:country":"DK",
    "sg:address":"Fmd.: J\u00f8gen Christensen, Strandhaven 71",
    "sg:city":"Kalundborg",
    "sg:orig_category":"\u00c3\u2020ldreorganisationer og klubber",
    "sg:phone":"+45 59 56 56 05",
    "sg:postcode":"4400",
    "sg:province":"Danmark",
    "wof:name":"\u00c6ldre Sagen, Lokalkomite for Kalundborg, Bjergsted, Hvideb\u00e6k",
    "wof:placetype":"venue"
},
  "geometry": {"coordinates":[11.0934085846,55.6797485352],"type":"Point"}
}