{
  "type": "Feature",
  "properties": {
    "addr:full":"Lyngbyskovvej 20 Terndrup Danmark 9575",
    "addr:housenumber":"20",
    "addr:postcode":"9575",
    "addr:street":"Lyngbyskovvej;Danmark",
    "iso:country":"DK",
    "sg:address":"Lyngbyskovvej 20",
    "sg:city":"Terndrup",
    "sg:orig_category":"Autoforhandlere",
    "sg:phone":"+45 98 33 58 77",
    "sg:postcode":"9575",
    "sg:province":"Danmark",
    "wof:name":"K. B. Auto",
    "wof:placetype":"venue"
},
  "geometry": {"coordinates":[10.0405044556,56.8004150391],"type":"Point"}
}