{
  "type": "Feature",
  "properties": {
    "addr:full":"Vesterladenvej 6 Vodskov Danmark 9310",
    "addr:housenumber":"6",
    "addr:postcode":"9310",
    "addr:street":"Vesterladenvej",
    "iso:country":"DK",
    "sg:address":"Vesterladenvej 6",
    "sg:city":"Vodskov",
    "sg:orig_category":"Blomsterhandlere",
    "sg:phone":"+45 98 25 65 38",
    "sg:postcode":"9310",
    "sg:province":"Danmark",
    "wof:name":"Stakladen",
    "wof:placetype":"venue"
},
  "geometry": {"coordinates":[10.0566596985,57.0898933411],"type":"Point"}
}