{
  "type": "Feature",
  "properties": {
    "addr:full":"Jernet 4E Kolding Danmark 6000",
    "addr:housenumber":"4e",
    "addr:postcode":"6000",
    "addr:street":"Jernet",
    "iso:country":"DK",
    "sg:address":"Jernet 4E",
    "sg:city":"Kolding",
    "sg:orig_category":"Gulvfejemaskiner",
    "sg:phone":"+45 75 53 02 55",
    "sg:postcode":"6000",
    "sg:province":"Danmark",
    "sg:website":"www.fj-soendergaard.dk",
    "wof:name":"S\u00f8ndergaard Maskin-Center, F. J.",
    "wof:placetype":"venue"
},
  "geometry": {"coordinates":[9.477186203,55.4677848816],"type":"Point"}
}