{
  "type": "Feature",
  "properties": {
    "addr:full":"Holb\u00e6kvej 77 Vig Danmark 4560",
    "addr:housenumber":"77",
    "addr:postcode":"4560",
    "addr:street":"Holbaekvej",
    "iso:country":"DK",
    "sg:address":"Holb\u00e6kvej 77",
    "sg:city":"Vig",
    "sg:orig_category":"Hundefoder",
    "sg:phone":"+45 59 31 71 17",
    "sg:postcode":"4560",
    "sg:province":"Danmark",
    "wof:name":"Kennel-Food \u00d8st",
    "wof:placetype":"venue"
},
  "geometry": {"coordinates":[-82.79159545900001,39.2505378723],"type":"Point"}
}