{
  "type": "Feature",
  "properties": {
    "addr:full":"Sivkrovej 9, Bedsted L\u00f8gumkloster Danmark 6240",
    "addr:housenumber":"9",
    "addr:postcode":"6240",
    "addr:street":"Sivkrovej",
    "iso:country":"DK",
    "sg:address":"Sivkrovej 9, Bedsted",
    "sg:city":"L\u00f8gumkloster",
    "sg:orig_category":"Naturgas install. og -service",
    "sg:phone":"+45 74 77 72 19",
    "sg:postcode":"6240",
    "sg:province":"Danmark",
    "wof:name":"BE-L\u00d8 A/S",
    "wof:placetype":"venue"
},
  "geometry": {"coordinates":[8.9515838623,55.058506012],"type":"Point"}
}