{
  "type": "Feature",
  "properties": {
    "iso:country":"DK",
    "sg:address":"v/ T\u00f8nder Sygehus, Carstensgade 6 - 10",
    "sg:city":"T\u00f8nder",
    "sg:orig_category":"Jordemodercentre",
    "sg:phone":"+45 73 92 61 00",
    "sg:postcode":"6270",
    "sg:province":"Danmark",
    "wof:name":"T\u00f8nder Jordemodercenter",
    "wof:placetype":"venue"
},
  "geometry": {"coordinates":[12.5389003754,55.6683998108],"type":"Point"}
}