{
  "type": "Feature",
  "properties": {
    "iso:country":"DK",
    "sg:address":"Elskj\u00e6rbakken 7",
    "sg:city":"Skive",
    "sg:orig_category":"EDB - udstyr",
    "sg:phone":"+45 97 51 44 51",
    "sg:postcode":"7800",
    "sg:province":"Danmark",
    "sg:website":"www.nova-c.dk",
    "wof:name":"Nova Consult ApS",
    "wof:placetype":"venue"
},
  "geometry": {"coordinates":[9.0010433197,56.5706443787],"type":"Point"}
}