{
  "type": "Feature",
  "properties": {
    "addr:full":"Pederstrupvej 120 Torrig Danmark 4943",
    "addr:housenumber":"120",
    "addr:postcode":"4943",
    "addr:street":"Pederstrupvej",
    "iso:country":"DK",
    "sg:address":"Pederstrupvej 120",
    "sg:city":"Torrig",
    "sg:orig_category":"Efterskoler",
    "sg:phone":"+45 54 93 57 55",
    "sg:postcode":"4943",
    "sg:province":"Danmark",
    "wof:name":"Pederstrup Efterskole",
    "wof:placetype":"venue"
},
  "geometry": {"coordinates":[11.2601222992,54.8986625671],"type":"Point"}
}