{
  "type": "Feature",
  "properties": {
    "addr:full":"Rasmus Rasks Vej 10 Odense C Danmark 5000",
    "addr:housenumber":"10",
    "addr:postcode":"5000",
    "addr:street":"Rasmus Rasks Vej",
    "iso:country":"DK",
    "sg:address":"Rasmus Rasks Vej 10",
    "sg:city":"Odense C",
    "sg:orig_category":"Fagforbund og fagforeninger",
    "sg:phone":"+45 66 13 53 86",
    "sg:postcode":"5000",
    "sg:province":"Danmark",
    "wof:name":"Dansk L\u00e6gesekret\u00e6rforening",
    "wof:placetype":"venue"
},
  "geometry": {"coordinates":[10.3577823639,55.39868927],"type":"Point"}
}