{
  "type": "Feature",
  "properties": {
    "addr:full":"Graham Bells Vej 1, Skejby \u00c5rhus N Danmark 8200",
    "addr:housenumber":"1",
    "addr:postcode":"8200",
    "addr:street":"Graham Bells Vej;Skejby",
    "iso:country":"DK",
    "sg:address":"Graham Bells Vej 1, Skejby",
    "sg:city":"\u00c5rhus N",
    "sg:orig_category":"Specialskoler for handicappede",
    "sg:phone":"+45 86 10 99 33",
    "sg:postcode":"8200",
    "sg:province":"Danmark",
    "wof:name":"Lyng\u00e5skolen",
    "wof:placetype":"venue"
},
  "geometry": {"coordinates":[10.1754398346,56.2002601624],"type":"Point"}
}