{
  "type": "Feature",
  "properties": {
    "addr:full":"Tretommervej 65 - 67 Risskov Danmark 8240",
    "addr:housenumber":"65 67",
    "addr:postcode":"8240",
    "addr:street":"Tretommervej",
    "iso:country":"DK",
    "sg:address":"Tretommervej 65 - 67",
    "sg:city":"Risskov",
    "sg:orig_category":"Faglige organisationer og foreninger",
    "sg:phone":"+45 86 17 92 93",
    "sg:postcode":"8240",
    "sg:province":"Danmark",
    "sg:website":"www.tempus.dk",
    "wof:name":"Dansk Urmager-og Optiker Centralforening",
    "wof:placetype":"venue"
},
  "geometry": {"coordinates":[10.2198696136,56.1907844543],"type":"Point"}
}