{
  "type": "Feature",
  "properties": {
    "addr:full":"Centrumgaden 27 Ballerup Danmark 2750",
    "addr:housenumber":"27",
    "addr:postcode":"2750",
    "addr:street":"Centrumgaden",
    "iso:country":"DK",
    "sg:address":"Centrumgaden 27",
    "sg:city":"Ballerup",
    "sg:orig_category":"Non-Classified Establishments",
    "sg:phone":"+45 44 97 56 77",
    "sg:postcode":"2750",
    "sg:province":"Danmark",
    "wof:name":"Ostelageret",
    "wof:placetype":"venue"
},
  "geometry": {"coordinates":[12.3599243164,55.7288322449],"type":"Point"}
}