{
  "type": "Feature",
  "properties": {
    "iso:country":"DK",
    "sg:address":"Engvej 4",
    "sg:city":"Grindsted",
    "sg:orig_category":"Erhvervslokaler, Udlejning af",
    "sg:phone":"+45 75 32 55 77",
    "sg:postcode":"7200",
    "sg:province":"Danmark",
    "wof:name":"Jensen, Ove Baggesgaard",
    "wof:placetype":"venue"
},
  "geometry": {"coordinates":[8.8440647125,55.6992759705],"type":"Point"}
}