{
  "type": "Feature",
  "properties": {
    "iso:country":"DK",
    "sg:address":"Strandbygade 61",
    "sg:city":"Esbjerg",
    "sg:orig_category":"Ejendomshandel",
    "sg:phone":"+45 75 45 75 88",
    "sg:postcode":"6700",
    "sg:province":"Danmark",
    "wof:name":"Nybolig Rekrea",
    "wof:placetype":"venue"
},
  "geometry": {"coordinates":[8.4376583099,55.4722061157],"type":"Point"}
}