{
  "type": "Feature",
  "properties": {
    "iso:country":"DK",
    "sg:address":"Gartnervej 1",
    "sg:city":"Holmegaard",
    "sg:orig_category":"Blomsterhandlere",
    "sg:phone":"+45 55 56 24 80",
    "sg:postcode":"4684",
    "sg:province":"Danmark",
    "wof:name":"Birkevang Stue- & Havecenter",
    "wof:placetype":"venue"
},
  "geometry": {"coordinates":[11.8583097458,55.2594261169],"type":"Point"}
}