{
  "type": "Feature",
  "properties": {
    "addr:full":"L\u00e6rkevej 22 Slangerup Danmark 3550",
    "addr:housenumber":"22",
    "addr:postcode":"3550",
    "addr:street":"Laerkevej",
    "iso:country":"DK",
    "sg:address":"L\u00e6rkevej 22",
    "sg:city":"Slangerup",
    "sg:orig_category":"Trykluft",
    "sg:phone":"+45 47 38 29 30",
    "sg:postcode":"3550",
    "sg:province":"Danmark",
    "wof:name":"JC Trykluft Center I/S",
    "wof:placetype":"venue"
},
  "geometry": {"coordinates":[12.1661176682,55.8443031311],"type":"Point"}
}