{
  "type": "Feature",
  "properties": {
    "addr:full":"Elmegade 23 Kalundborg Danmark 4400",
    "addr:housenumber":"23",
    "addr:postcode":"4400",
    "addr:street":"Elmegade",
    "iso:country":"DK",
    "sg:address":"Elmegade 23",
    "sg:city":"Kalundborg",
    "sg:orig_category":"Faglige organisationer og foreninger",
    "sg:phone":"+45 59 51 05 12",
    "sg:postcode":"4400",
    "sg:province":"Danmark",
    "wof:name":"SID-Specialarbejderforbundet i Danmark - Kalundborg Afd.",
    "wof:placetype":"venue"
},
  "geometry": {"coordinates":[11.0991306305,55.6790504456],"type":"Point"}
}