{
  "type": "Feature",
  "properties": {
    "iso:country":"DK",
    "sg:address":"Gammel Kaplevej 5",
    "sg:city":"Virum",
    "sg:orig_category":"Non-Classified Establishments",
    "sg:phone":"+45 45 85 20 16",
    "sg:postcode":"2830",
    "sg:province":"Danmark",
    "wof:name":"Virum Hegn",
    "wof:placetype":"venue"
},
  "geometry": {"coordinates":[12.4687290192,55.7890014648],"type":"Point"}
}