{
  "type": "Feature",
  "properties": {
    "addr:full":"Nyker Strandvej 40, Muleby R\u00f8nne Danmark 3700",
    "addr:housenumber":"40",
    "addr:postcode":"3700",
    "addr:street":"Nyker Strandvej;Ronne",
    "iso:country":"DK",
    "sg:address":"Nyker Strandvej 40, Muleby",
    "sg:city":"R\u00f8nne",
    "sg:classifiers":[
        {
            "category":"Restaurant",
            "type":"Food & Drink"
        }
    ],
    "sg:phone":"+45 56 95 07 84",
    "sg:postcode":"3700",
    "sg:province":"Danmark",
    "sg:website":"www.bornholm.com",
    "wof:name":"Skovly, Restaurant & Hotel",
    "wof:placetype":"venue"
},
  "geometry": {"coordinates":[14.6975498199,55.0993003845],"type":"Point"}
}