{
  "type": "Feature",
  "properties": {
    "addr:full":"Kredsleder: Stig Larsen, H\u00f8rv\u00e6nget 11 Store Heddinge Danmark 4660",
    "addr:housenumber":"11",
    "addr:postcode":"4660",
    "addr:street":"Kredsleder Stig;Horvaenget",
    "iso:country":"DK",
    "sg:address":"Kredsleder: Stig Larsen, H\u00f8rv\u00e6nget 11",
    "sg:city":"Store Heddinge",
    "sg:orig_category":"Beredskabsforbund",
    "sg:phone":"+45 56 51 04 94",
    "sg:postcode":"4660",
    "sg:province":"Danmark",
    "wof:name":"Beredskabsforbundet Vall\u00f8/Stevns Kreds",
    "wof:placetype":"venue"
},
  "geometry": {"coordinates":[12.3895797729,55.3113174438],"type":"Point"}
}