{
  "type": "Feature",
  "properties": {
    "addr:full":"Fredericiavej 100 Vejle Danmark 7100",
    "addr:housenumber":"100",
    "addr:postcode":"7100",
    "addr:street":"Fredericiavej",
    "iso:country":"DK",
    "sg:address":"Fredericiavej 100",
    "sg:city":"Vejle",
    "sg:orig_category":"Kulturelle foreninger",
    "sg:phone":"+45 75 82 84 77",
    "sg:postcode":"7100",
    "sg:province":"Danmark",
    "sg:website":"www.ungdomsringen.dk",
    "wof:name":"Landsforeningen Ungdomsringen",
    "wof:placetype":"venue"
},
  "geometry": {"coordinates":[9.5551719666,55.6873779297],"type":"Point"}
}