{
  "type": "Feature",
  "properties": {
    "addr:full":"Jegstrupvej 64 Hasselager Danmark 8361",
    "addr:housenumber":"64",
    "addr:postcode":"8361",
    "addr:street":"Jegstrupvej",
    "iso:country":"DK",
    "sg:address":"Jegstrupvej 64",
    "sg:city":"Hasselager",
    "sg:orig_category":"Fotografer",
    "sg:phone":"+45 70 21 00 20",
    "sg:postcode":"8361",
    "sg:province":"Danmark",
    "wof:name":"Jydsk Skolefoto",
    "wof:placetype":"venue"
},
  "geometry": {"coordinates":[10.1105117798,56.1049156189],"type":"Point"}
}