{
  "type": "Feature",
  "properties": {
    "addr:full":"Ingemannsvej 5 Sor\u00f8 Danmark 4180",
    "addr:housenumber":"5",
    "addr:postcode":"4180",
    "addr:street":"Ingemannsvej",
    "iso:country":"DK",
    "sg:address":"Ingemannsvej 5",
    "sg:city":"Sor\u00f8",
    "sg:orig_category":"Danseundervisning",
    "sg:phone":"+45 57 83 11 49",
    "sg:postcode":"4180",
    "sg:province":"Danmark",
    "sg:website":"www.soroe-dans.dk",
    "wof:name":"Stenb\u00e6k & Lindholm, Danseinstitut",
    "wof:placetype":"venue"
},
  "geometry": {"coordinates":[11.5595302582,55.4321975708],"type":"Point"}
}