{
  "type": "Feature",
  "properties": {
    "addr:full":"Virkelyst 34, Gjellerup Herning Danmark 7400",
    "addr:housenumber":"34",
    "addr:postcode":"7400",
    "addr:street":"Virkelyst",
    "iso:country":"DK",
    "sg:address":"Virkelyst 34, Gjellerup",
    "sg:city":"Herning",
    "sg:orig_category":"Murermestre",
    "sg:phone":"+45 97 11 92 82",
    "sg:postcode":"7400",
    "sg:province":"Danmark",
    "wof:name":"Lund A/S, Byggefirmaet Mogens",
    "wof:placetype":"venue"
},
  "geometry": {"coordinates":[8.9768896103,56.1374168396],"type":"Point"}
}