{
  "type": "Feature",
  "properties": {
    "addr:full":"Hovedgaden 21 Alling\u00e5bro Danmark 8961",
    "addr:housenumber":"21",
    "addr:postcode":"8961",
    "addr:street":"Hovedgaden",
    "iso:country":"DK",
    "sg:address":"Hovedgaden 21",
    "sg:city":"Alling\u00e5bro",
    "sg:classifiers":[
        {
            "category":"Personal",
            "subcategory":"Massage",
            "type":"Services"
        }
    ],
    "sg:phone":"+45 86 48 09 19",
    "sg:postcode":"8961",
    "sg:province":"Danmark",
    "wof:name":"Nielsen, Erik",
    "wof:placetype":"venue"
},
  "geometry": {"coordinates":[-73.92324829099999,40.8257446289],"type":"Point"}
}