{
  "type": "Feature",
  "properties": {
    "addr:full":"Anl\u00e6gsvej 3, Farre Give Danmark 7323",
    "addr:housenumber":"3",
    "addr:postcode":"7323",
    "addr:street":"Anlaegsvej;Farre",
    "iso:country":"DK",
    "sg:address":"Anl\u00e6gsvej 3, Farre",
    "sg:city":"Give",
    "sg:orig_category":"Slagter og viktualie",
    "sg:phone":"+45 75 73 31 00",
    "sg:postcode":"7323",
    "sg:province":"Danmark",
    "wof:name":"Farre Slagterforretning",
    "wof:placetype":"venue"
},
  "geometry": {"coordinates":[9.2362060547,55.845413208],"type":"Point"}
}