{
  "type": "Feature",
  "properties": {
    "addr:full":"P. O. Pedersens Vej 28, Skejby \u00c5rhus N Danmark 8200",
    "addr:housenumber":"28",
    "addr:postcode":"8200",
    "addr:street":"P. O. Pedersens Vej;Skejby",
    "iso:country":"DK",
    "sg:address":"P. O. Pedersens Vej 28, Skejby",
    "sg:city":"\u00c5rhus N",
    "sg:orig_category":"Spedition",
    "sg:phone":"+45 86 78 59 00",
    "sg:postcode":"8200",
    "sg:province":"Danmark",
    "wof:name":"Nordisk Express as",
    "wof:placetype":"venue"
},
  "geometry": {"coordinates":[10.1754398346,56.2002601624],"type":"Point"}
}