{
  "type": "Feature",
  "properties": {
    "iso:country":"DK",
    "sg:address":"Vorup\u00f8rvej 168",
    "sg:city":"Thisted",
    "sg:orig_category":"Kommunale folkeskoler",
    "sg:phone":"+45 97 93 72 15",
    "sg:postcode":"7700",
    "sg:province":"Danmark",
    "sg:website":"www.hundborg-skole.thisted.dk",
    "wof:name":"Hundborg skole",
    "wof:placetype":"venue"
},
  "geometry": {"coordinates":[8.4959402084,56.9261703491],"type":"Point"}
}