{
  "type": "Feature",
  "properties": {
    "addr:full":"C. F. Tietgens Vej 5 A Kolding Danmark 6000",
    "addr:housenumber":"5 a",
    "addr:postcode":"6000",
    "addr:street":"C. F. Tietgens Vej",
    "iso:country":"DK",
    "sg:address":"C. F. Tietgens Vej 5 A",
    "sg:city":"Kolding",
    "sg:orig_category":"Emballage",
    "sg:phone":"+45 75 52 90 80",
    "sg:postcode":"6000",
    "sg:province":"Danmark",
    "wof:name":"Jessen Emballage",
    "wof:placetype":"venue"
},
  "geometry": {"coordinates":[9.4613780975,55.508026123],"type":"Point"}
}