{
  "type": "Feature",
  "properties": {
    "addr:full":"Poppelvej 33 Odense M Danmark 5230",
    "addr:housenumber":"33",
    "addr:postcode":"5230",
    "addr:street":"Poppelvej",
    "iso:country":"DK",
    "sg:address":"Poppelvej 33",
    "sg:city":"Odense M",
    "sg:orig_category":"Reklamebureauer",
    "sg:phone":"+45 66 14 58 91",
    "sg:postcode":"5230",
    "sg:province":"Danmark",
    "wof:name":"T K M Consult",
    "wof:placetype":"venue"
},
  "geometry": {"coordinates":[10.3931245804,55.3827667236],"type":"Point"}
}