{
  "type": "Feature",
  "properties": {
    "iso:country":"DK",
    "sg:address":"Clarasvej 2",
    "sg:city":"Horsens",
    "sg:orig_category":"Advokater",
    "sg:phone":"+45 76 28 20 10",
    "sg:postcode":"8700",
    "sg:province":"Danmark",
    "wof:name":"Advokaterne i Sundhuset",
    "wof:placetype":"venue"
},
  "geometry": {"coordinates":[9.894618988,55.86926651],"type":"Point"}
}