{
  "type": "Feature",
  "properties": {
    "addr:full":"Dortheasvej 27 Esbjerg Danmark 6700",
    "addr:housenumber":"27",
    "addr:postcode":"6700",
    "addr:street":"Dortheasvej",
    "iso:country":"DK",
    "sg:address":"Dortheasvej 27",
    "sg:city":"Esbjerg",
    "sg:orig_category":"Dyreklinikker og -hospitaler",
    "sg:phone":"+45 75 12 21 67",
    "sg:postcode":"6700",
    "sg:province":"Danmark",
    "wof:name":"Esbjerg Dyrehospital ApS",
    "wof:placetype":"venue"
},
  "geometry": {"coordinates":[8.4623832703,55.4831161499],"type":"Point"}
}