{
  "type": "Feature",
  "properties": {
    "iso:country":"DK",
    "sg:address":"Skallerup Skolevej 3",
    "sg:city":"Hj\u00f8rring",
    "sg:orig_category":"Kommunale folkeskoler",
    "sg:phone":"+45 98 96 81 00",
    "sg:postcode":"9800",
    "sg:province":"Danmark",
    "wof:name":"Skallerup skole",
    "wof:placetype":"venue"
},
  "geometry": {"coordinates":[9.8696298599,57.4603881836],"type":"Point"}
}