{
  "type": "Feature",
  "properties": {
    "iso:country":"DK",
    "sg:address":"Damhaven 12",
    "sg:city":"Vejle",
    "sg:orig_category":"Statslige direktorater og styrelser",
    "sg:phone":"+45 75 83 53 33",
    "sg:postcode":"7100",
    "sg:province":"Danmark",
    "wof:name":"Jordbrugskommission Vejle Amt",
    "wof:placetype":"venue"
},
  "geometry": {"coordinates":[9.5265474319,55.7051582336],"type":"Point"}
}