{
  "type": "Feature",
  "properties": {
    "addr:full":"Gilleleje Stationsvej 2 Gilleleje Danmark 3250",
    "addr:housenumber":"2",
    "addr:postcode":"3250",
    "addr:street":"Gilleleje Stationsvej",
    "iso:country":"DK",
    "sg:address":"Gilleleje Stationsvej 2",
    "sg:city":"Gilleleje",
    "sg:classifiers":[
        {
            "category":"Communications",
            "type":"Services"
        }
    ],
    "sg:phone":"+45 48 30 04 04",
    "sg:postcode":"3250",
    "sg:province":"Danmark",
    "sg:tags":[
        "og",
        "tv",
        "radio"
    ],
    "wof:name":"Gilleleje Radio",
    "wof:placetype":"venue"
},
  "geometry": {"coordinates":[12.3045625687,56.1267051697],"type":"Point"}
}