{
  "type": "Feature",
  "properties": {
    "addr:full":"Brillerne 4, Gl. Holte Holte Danmark 2840",
    "addr:housenumber":"4",
    "addr:postcode":"2840",
    "addr:street":"Brillerne;Gl. Holte",
    "iso:country":"DK",
    "sg:address":"Brillerne 4, Gl. Holte",
    "sg:city":"Holte",
    "sg:orig_category":"Integrerede institutioner",
    "sg:phone":"+45 45 80 00 44",
    "sg:postcode":"2840",
    "sg:province":"Danmark",
    "wof:name":"Troldeh\u00f8j Daginstitution",
    "wof:placetype":"venue"
},
  "geometry": {"coordinates":[12.4706554413,55.8122367859],"type":"Point"}
}