{
  "type": "Feature",
  "properties": {
    "iso:country":"DK",
    "sg:address":"Vestergade 50",
    "sg:city":"Odense C",
    "sg:classifiers":[
        {
            "category":"Restaurant",
            "type":"Food & Drink"
        }
    ],
    "sg:phone":"+45 65 91 91 80",
    "sg:postcode":"5000",
    "sg:province":"Danmark",
    "wof:name":"Piccolo I/S",
    "wof:placetype":"venue"
},
  "geometry": {"coordinates":[10.3846359253,55.3951301575],"type":"Point"}
}