{
  "type": "Feature",
  "properties": {
    "addr:full":"Havnegade 2, 1. Hobro Danmark 9500",
    "addr:housenumber":"2 1",
    "addr:postcode":"9500",
    "addr:street":"Havnegade",
    "iso:country":"DK",
    "sg:address":"Havnegade 2, 1.",
    "sg:city":"Hobro",
    "sg:orig_category":"Advokater",
    "sg:phone":"+45 98 52 05 66",
    "sg:postcode":"9500",
    "sg:province":"Danmark",
    "wof:name":"B\u00e6rnthsen, Advokatfirmaet Jens",
    "wof:placetype":"venue"
},
  "geometry": {"coordinates":[9.7947587967,56.6381568909],"type":"Point"}
}