{
  "type": "Feature",
  "properties": {
    "addr:full":"Dytm\u00e6rsken 14 Randers Danmark 8900",
    "addr:housenumber":"14",
    "addr:postcode":"8900",
    "addr:street":"Dytmaersken",
    "iso:country":"DK",
    "sg:address":"Dytm\u00e6rsken 14",
    "sg:city":"Randers",
    "sg:orig_category":"Varehuse",
    "sg:phone":"+45 86 40 45 00",
    "sg:postcode":"8900",
    "sg:province":"Danmark",
    "wof:name":"F\u00f8tex",
    "wof:placetype":"venue"
},
  "geometry": {"coordinates":[10.0397567749,56.4593887329],"type":"Point"}
}