{
  "type": "Feature",
  "properties": {
    "addr:full":"Fjordvejen 44, Kollund Krus\u00e5 Danmark 6340",
    "addr:housenumber":"44",
    "addr:postcode":"6340",
    "addr:street":"Fjordvejen",
    "iso:country":"DK",
    "sg:address":"Fjordvejen 44, Kollund",
    "sg:city":"Krus\u00e5",
    "sg:classifiers":[
        {
            "category":"Restaurant",
            "type":"Food & Drink"
        }
    ],
    "sg:phone":"+45 73 67 83 00",
    "sg:postcode":"6340",
    "sg:province":"Danmark",
    "sg:website":"www.fakkelgaarden.dk",
    "wof:name":"Fakkelgaarden, Hotel",
    "wof:placetype":"venue"
},
  "geometry": {"coordinates":[9.3991203308,54.8500900269],"type":"Point"}
}