{
  "type": "Feature",
  "properties": {
    "iso:country":"DK",
    "sg:address":"Fiskerihavnen 8",
    "sg:city":"R\u00f8dvig Stevns",
    "sg:orig_category":"Non-Classified Establishments",
    "sg:phone":"+45 56 50 61 45",
    "sg:postcode":"4673",
    "sg:province":"Danmark",
    "wof:name":"Statoil Kystsalg",
    "wof:placetype":"venue"
},
  "geometry": {"coordinates":[12.3775653839,55.2558746338],"type":"Point"}
}