{
  "type": "Feature",
  "properties": {
    "addr:full":"v/ Svend Thing, N\u00f8rskovvej 2, Jegind\u00f8 Thyholm Danmark 7790",
    "addr:housenumber":"2",
    "addr:postcode":"7790",
    "addr:street":"Norskovvej",
    "iso:country":"DK",
    "sg:address":"v/ Svend Thing, N\u00f8rskovvej 2, Jegind\u00f8",
    "sg:city":"Thyholm",
    "sg:orig_category":"Kulturelle foreninger",
    "sg:phone":"+45 97 87 93 37",
    "sg:postcode":"7790",
    "sg:province":"Danmark",
    "wof:name":"Kristelig Lytter- og Fjernseerforening, Jegind\u00f8",
    "wof:placetype":"venue"
},
  "geometry": {"coordinates":[8.525765419,56.6507072449],"type":"Point"}
}