{
  "type": "Feature",
  "properties": {
    "iso:country":"DK",
    "sg:address":"Tolderlundsvej 36",
    "sg:city":"Odense C",
    "sg:orig_category":"Stilladser",
    "sg:phone":"+45 66 11 70 18",
    "sg:postcode":"5000",
    "sg:province":"Danmark",
    "wof:name":"Fyens Stillads Co. A/S",
    "wof:placetype":"venue"
},
  "geometry": {"coordinates":[10.3869762421,55.4077987671],"type":"Point"}
}