{
  "type": "Feature",
  "properties": {
    "addr:full":"M\u00f8lleparken 11 Vejle Danmark 7100",
    "addr:housenumber":"11",
    "addr:postcode":"7100",
    "addr:street":"Molleparken",
    "iso:country":"DK",
    "sg:address":"M\u00f8lleparken 11",
    "sg:city":"Vejle",
    "sg:orig_category":"Murermestre",
    "sg:phone":"+45 75 86 31 82",
    "sg:postcode":"7100",
    "sg:province":"Danmark",
    "wof:name":"Iversen, Arne",
    "wof:placetype":"venue"
},
  "geometry": {"coordinates":[9.5784196854,55.789680481],"type":"Point"}
}