{
  "type": "Feature",
  "properties": {
    "addr:full":"Torvet 1 Middelfart Danmark 5500",
    "addr:housenumber":"1",
    "addr:postcode":"5500",
    "addr:street":"Torvet",
    "iso:country":"DK",
    "sg:address":"Torvet 1",
    "sg:city":"Middelfart",
    "sg:orig_category":"Forsikringer",
    "sg:phone":"+45 70 13 79 13",
    "sg:postcode":"5500",
    "sg:province":"Danmark",
    "wof:name":"Topdanmark",
    "wof:placetype":"venue"
},
  "geometry": {"coordinates":[9.730266571,55.5062637329],"type":"Point"}
}