{
  "type": "Feature",
  "properties": {
    "addr:full":"Kallemosen 58 Aabenraa Danmark 6200",
    "addr:housenumber":"58",
    "addr:postcode":"6200",
    "addr:street":"Kallemosen",
    "iso:country":"DK",
    "sg:address":"Kallemosen 58",
    "sg:city":"Aabenraa",
    "sg:orig_category":"Boligselskaber",
    "sg:phone":"+45 74 62 49 12",
    "sg:postcode":"6200",
    "sg:province":"Danmark",
    "wof:name":"Vanf\u00f8res Boligselskab, De",
    "wof:placetype":"venue"
},
  "geometry": {"coordinates":[9.4104890823,55.0297012329],"type":"Point"}
}