{
  "type": "Feature",
  "properties": {
    "addr:full":"v/ Anne Margrethe Jensen, N\u00f8ddek\u00e6rvej 11, Magleby Klippinge Danmark 4672",
    "addr:housenumber":"11",
    "addr:postcode":"4672",
    "addr:street":"Noddekaervej",
    "iso:country":"DK",
    "sg:address":"v/ Anne Margrethe Jensen, N\u00f8ddek\u00e6rvej 11, Magleby",
    "sg:city":"Klippinge",
    "sg:orig_category":"Kulturelle foreninger",
    "sg:phone":"+45 56 57 81 93",
    "sg:postcode":"4672",
    "sg:province":"Danmark",
    "wof:name":"Stevns H\u00f8jskoleforening",
    "wof:placetype":"venue"
},
  "geometry": {"coordinates":[12.3291807175,55.3516769409],"type":"Point"}
}