{
  "type": "Feature",
  "properties": {
    "addr:full":"S\u00f8ndergade 3 Hjallerup Danmark 9320",
    "addr:housenumber":"3",
    "addr:postcode":"9320",
    "addr:street":"Sondergade",
    "iso:country":"DK",
    "sg:address":"S\u00f8ndergade 3",
    "sg:city":"Hjallerup",
    "sg:orig_category":"Blomsterhandlere",
    "sg:phone":"+45 98 28 16 42",
    "sg:postcode":"9320",
    "sg:province":"Danmark",
    "wof:name":"Bonderosen",
    "wof:placetype":"venue"
},
  "geometry": {"coordinates":[10.1456737518,57.1685218811],"type":"Point"}
}