{
  "type": "Feature",
  "properties": {
    "addr:full":"Team Langeland, Torvet 5 Rudk\u00f8bing Danmark 5900",
    "addr:housenumber":"5",
    "addr:postcode":"5900",
    "addr:street":"Torvet",
    "iso:country":"DK",
    "sg:address":"Team Langeland, Torvet 5",
    "sg:city":"Rudk\u00f8bing",
    "sg:orig_category":"Turistforeninger",
    "sg:phone":"+45 62 51 35 05",
    "sg:postcode":"5900",
    "sg:province":"Danmark",
    "sg:website":"www.teamlangeland.com",
    "wof:name":"Langelands Turist- og Erhvervsforening",
    "wof:placetype":"venue"
},
  "geometry": {"coordinates":[10.6905498505,59.8094596863],"type":"Point"}
}