{
  "type": "Feature",
  "properties": {
    "addr:full":"Solhegnet 2 Greve Danmark 2670",
    "addr:housenumber":"2",
    "addr:postcode":"2670",
    "addr:street":"Solhegnet",
    "iso:country":"DK",
    "sg:address":"Solhegnet 2",
    "sg:city":"Greve",
    "sg:orig_category":"Kirker",
    "sg:postcode":"2670",
    "sg:province":"Danmark",
    "wof:name":"Nazar\u00e6erens Kirke",
    "wof:placetype":"venue"
},
  "geometry": {"coordinates":[12.2680120468,55.5799484253],"type":"Point"}
}