{
  "type": "Feature",
  "properties": {
    "addr:full":"Sundsvej 62  Herning Danmark 7400",
    "addr:housenumber":"62",
    "addr:postcode":"7400",
    "addr:street":"Sundsvej",
    "iso:country":"DK",
    "sg:address":"Sundsvej 62 ",
    "sg:city":"Herning",
    "sg:classifiers":[
        {
            "category":"Shopping",
            "subcategory":"Clothing, Apparel, & Fashions",
            "type":"Retail Goods"
        }
    ],
    "sg:phone":"+45 97 12 05 88",
    "sg:postcode":"7400",
    "sg:province":"Danmark",
    "sg:tags":[
        "clothes"
    ],
    "wof:name":"ANKY A/S",
    "wof:placetype":"venue"
},
  "geometry": {"coordinates":[9.0117759705,56.1627082825],"type":"Point"}
}