{
  "type": "Feature",
  "properties": {
    "iso:country":"DK",
    "sg:address":"Frederik d. 7's Gade 28",
    "sg:city":"Vejen",
    "sg:orig_category":"Autoforhandlere",
    "sg:phone":"+45 75 36 19 22",
    "sg:postcode":"6600",
    "sg:province":"Danmark",
    "wof:name":"Vejen Motor Compagni, A/S",
    "wof:placetype":"venue"
},
  "geometry": {"coordinates":[9.1450052261,55.4835853577],"type":"Point"}
}