{
  "type": "Feature",
  "properties": {
    "addr:full":"R\u00f8dovre Centrum 277 R\u00f8dovre Danmark 2610",
    "addr:housenumber":"277",
    "addr:postcode":"2610",
    "addr:street":"Centrum",
    "iso:country":"DK",
    "sg:address":"R\u00f8dovre Centrum 277",
    "sg:city":"R\u00f8dovre",
    "sg:orig_category":"Termografi",
    "sg:phone":"+45 36 70 73 04",
    "sg:postcode":"2610",
    "sg:province":"Danmark",
    "sg:website":"www.ka-thermografi.dk",
    "wof:name":"Andersen Thermografi, Kurt",
    "wof:placetype":"venue"
},
  "geometry": {"coordinates":[10.6992139816,61.1027755737],"type":"Point"}
}