{
  "type": "Feature",
  "properties": {
    "addr:full":"Fmd.: Yvonne Erbst, Mosevej 6, St. Linde Karise Danmark 4653",
    "addr:housenumber":"6",
    "addr:postcode":"4653",
    "addr:street":"Mosevej;St.",
    "iso:country":"DK",
    "sg:address":"Fmd.: Yvonne Erbst, Mosevej 6, St. Linde",
    "sg:city":"Karise",
    "sg:orig_category":"Kulturelle foreninger",
    "sg:phone":"+45 56 78 86 66",
    "sg:postcode":"4653",
    "sg:province":"Danmark",
    "wof:name":"Kunstnergruppen CaCO3",
    "wof:placetype":"venue"
},
  "geometry": {"coordinates":[12.1990203857,55.3030395508],"type":"Point"}
}