{
  "type": "Feature",
  "properties": {
    "addr:full":"Fmd.: Herman Johansen, \u00c5bakken 106, Ejby Kirke Hyllinge Danmark 4070",
    "addr:housenumber":"106",
    "addr:postcode":"4070",
    "addr:street":"Aabakken",
    "iso:country":"DK",
    "sg:address":"Fmd.: Herman Johansen, \u00c5bakken 106, Ejby",
    "sg:city":"Kirke Hyllinge",
    "sg:orig_category":"Grundejerforeninger",
    "sg:phone":"+45 46 40 67 97",
    "sg:postcode":"4070",
    "sg:province":"Danmark",
    "wof:name":"\u00c5svinget Grundejerforening",
    "wof:placetype":"venue"
},
  "geometry": {"coordinates":[11.9004745483,55.7080039978],"type":"Point"}
}