{
  "type": "Feature",
  "properties": {
    "iso:country":"DK",
    "sg:address":"Stenbukvej 3, Ejby",
    "sg:city":"Lille Skensved",
    "sg:orig_category":"Glarmestre og glarmagere",
    "sg:phone":"+45 56 82 09 06",
    "sg:postcode":"4623",
    "sg:province":"Danmark",
    "wof:name":"Green, J\u00f8rgen B.",
    "wof:placetype":"venue"
},
  "geometry": {"coordinates":[12.0822563171,55.4889717102],"type":"Point"}
}