{
  "type": "Feature",
  "properties": {
    "addr:full":"Varg\u00e5rdevej 40 Hejls Danmark 6094",
    "addr:housenumber":"40",
    "addr:postcode":"6094",
    "addr:street":"Vargaardevej",
    "iso:country":"DK",
    "sg:address":"Varg\u00e5rdevej 40",
    "sg:city":"Hejls",
    "sg:orig_category":"Skovbrug",
    "sg:phone":"+45 75 57 49 46",
    "sg:postcode":"6094",
    "sg:province":"Danmark",
    "wof:name":"Preben Straarup A/S",
    "wof:placetype":"venue"
},
  "geometry": {"coordinates":[9.5879049301,55.386428833],"type":"Point"}
}