{
  "type": "Feature",
  "properties": {
    "addr:full":"Skanderborgvej 13 Ry Danmark 8680",
    "addr:housenumber":"13",
    "addr:postcode":"8680",
    "addr:street":"Skanderborgvej",
    "iso:country":"DK",
    "sg:address":"Skanderborgvej 13",
    "sg:city":"Ry",
    "sg:orig_category":"Grillbarer",
    "sg:phone":"+45 86 89 36 36",
    "sg:postcode":"8680",
    "sg:province":"Danmark",
    "wof:name":"Gourmand",
    "wof:placetype":"venue"
},
  "geometry": {"coordinates":[9.7598590851,56.0920944214],"type":"Point"}
}