{
  "type": "Feature",
  "properties": {
    "addr:full":"R\u00f8gildvej 60, Arentsminde Brovst Danmark 9460",
    "addr:housenumber":"60",
    "addr:postcode":"9460",
    "addr:street":"Rogildvej",
    "iso:country":"DK",
    "sg:address":"R\u00f8gildvej 60, Arentsminde",
    "sg:city":"Brovst",
    "sg:orig_category":"Autoreparation og -service",
    "sg:phone":"+45 98 23 83 56",
    "sg:postcode":"9460",
    "sg:province":"Danmark",
    "wof:name":"Damg\u00e5rden",
    "wof:placetype":"venue"
},
  "geometry": {"coordinates":[9.5220241547,57.097366333],"type":"Point"}
}