{
  "type": "Feature",
  "properties": {
    "addr:full":"Elleg\u00e5rdvej 25 B S\u00f8nderborg Danmark 6400",
    "addr:housenumber":"25 b",
    "addr:postcode":"6400",
    "addr:street":"Ellegaardvej",
    "iso:country":"DK",
    "sg:address":"Elleg\u00e5rdvej 25 B",
    "sg:city":"S\u00f8nderborg",
    "sg:orig_category":"Datamaskiner",
    "sg:phone":"+45 74 43 66 00",
    "sg:postcode":"6400",
    "sg:province":"Danmark",
    "wof:name":"Win Production I/S",
    "wof:placetype":"venue"
},
  "geometry": {"coordinates":[77.2480392456,14.1354398727],"type":"Point"}
}