{
  "type": "Feature",
  "properties": {
    "addr:full":"Dianavej 13 Vejle Danmark 7100",
    "addr:housenumber":"13",
    "addr:postcode":"7100",
    "addr:street":"Dianavej",
    "iso:country":"DK",
    "sg:address":"Dianavej 13",
    "sg:city":"Vejle",
    "sg:orig_category":"Telefoner",
    "sg:phone":"+45 79 42 01 22",
    "sg:postcode":"7100",
    "sg:province":"Danmark",
    "sg:website":"www.tp-vejle.dk",
    "wof:name":"Jansson Kommunikation A/S",
    "wof:placetype":"venue"
},
  "geometry": {"coordinates":[9.5668849945,55.7199249268],"type":"Point"}
}