{
  "type": "Feature",
  "properties": {
    "addr:full":"Christian X's Alle 120 Kongens Lyngby Danmark 2800",
    "addr:housenumber":"120",
    "addr:postcode":"2800",
    "addr:street":"Christian X'S Alle",
    "iso:country":"DK",
    "sg:address":"Christian X's Alle 120",
    "sg:city":"Kongens Lyngby",
    "sg:orig_category":"Kirker",
    "sg:postcode":"2800",
    "sg:province":"Danmark",
    "wof:name":"Christianskirken",
    "wof:placetype":"venue"
},
  "geometry": {"coordinates":[12.5047941208,55.7639045715],"type":"Point"}
}