{
  "type": "Feature",
  "properties": {
    "addr:full":"Pr\u00e6stehaven 12 B, Gjellerup Herning Danmark 7400",
    "addr:housenumber":"12 b",
    "addr:postcode":"7400",
    "addr:street":"Praestehaven;Gjellerup",
    "iso:country":"DK",
    "sg:address":"Pr\u00e6stehaven 12 B, Gjellerup",
    "sg:city":"Herning",
    "sg:orig_category":"Forsikringer",
    "sg:phone":"+45 97 11 69 84",
    "sg:postcode":"7400",
    "sg:province":"Danmark",
    "wof:name":"JS Assurance",
    "wof:placetype":"venue"
},
  "geometry": {"coordinates":[8.9768896103,56.1374168396],"type":"Point"}
}