{
  "type": "Feature",
  "properties": {
    "addr:full":"Hovedgaden 17 B Kirke Hvals\u00f8 Danmark 4330",
    "addr:housenumber":"17 b",
    "addr:postcode":"4330",
    "addr:street":"Hovedgaden;Kirke Hvalso Danmark",
    "iso:country":"DK",
    "sg:address":"Hovedgaden 17 B",
    "sg:city":"Kirke Hvals\u00f8",
    "sg:orig_category":"Kirker",
    "sg:postcode":"4330",
    "sg:province":"Danmark",
    "wof:name":"Kirke Hvals\u00f8 Kirke",
    "wof:placetype":"venue"
},
  "geometry": {"coordinates":[9.2555503845,54.9375686646],"type":"Point"}
}