{
  "type": "Feature",
  "properties": {
    "iso:country":"DK",
    "sg:address":"Sankelmarksvej 10",
    "sg:city":"Vordingborg",
    "sg:orig_category":"Offentlige sygehuse",
    "sg:phone":"+45 55 36 18 14",
    "sg:postcode":"4760",
    "sg:province":"Danmark",
    "wof:name":"Vordingborg Sygehus",
    "wof:placetype":"venue"
},
  "geometry": {"coordinates":[11.9074754715,55.017490387],"type":"Point"}
}