{
  "type": "Feature",
  "properties": {
    "iso:country":"DK",
    "sg:address":"Industrivej 30",
    "sg:city":"Vemb",
    "sg:orig_category":"Blikkenslagere",
    "sg:phone":"+45 97 48 16 28",
    "sg:postcode":"7570",
    "sg:province":"Danmark",
    "wof:name":"Vemb Smede & VVS",
    "wof:placetype":"venue"
},
  "geometry": {"coordinates":[8.343463,56.346832],"type":"Point"}
}