{
  "type": "Feature",
  "properties": {
    "addr:full":"Bog\u00f8v\u00e6nget 25 Middelfart Danmark 5500",
    "addr:housenumber":"25",
    "addr:postcode":"5500",
    "addr:street":"Bogovaenget",
    "iso:country":"DK",
    "sg:address":"Bog\u00f8v\u00e6nget 25",
    "sg:city":"Middelfart",
    "sg:orig_category":"Reklamebureauer",
    "sg:phone":"+45 64 41 74 88",
    "sg:postcode":"5500",
    "sg:province":"Danmark",
    "wof:name":"Bonan Marketing ApS",
    "wof:placetype":"venue"
},
  "geometry": {"coordinates":[9.7417497635,55.5030250549],"type":"Point"}
}