{
  "type": "Feature",
  "properties": {
    "addr:full":"Havnegade 21 Odense C Danmark 5000",
    "addr:housenumber":"21",
    "addr:postcode":"5000",
    "addr:street":"Havnegade",
    "iso:country":"DK",
    "sg:address":"Havnegade 21",
    "sg:city":"Odense C",
    "sg:orig_category":"Boligtekstil",
    "sg:phone":"+45 66 11 30 17",
    "sg:postcode":"5000",
    "sg:province":"Danmark",
    "wof:name":"Nortex A/S",
    "wof:placetype":"venue"
},
  "geometry": {"coordinates":[10.3839406967,55.4115562439],"type":"Point"}
}