{
  "type": "Feature",
  "properties": {
    "addr:full":"Nym\u00f8llevej 115, Farstrup Nibe Danmark 9240",
    "addr:housenumber":"115",
    "addr:postcode":"9240",
    "addr:street":"Nymollevej;Farstrup",
    "iso:country":"DK",
    "sg:address":"Nym\u00f8llevej 115, Farstrup",
    "sg:city":"Nibe",
    "sg:orig_category":"Forsamlingshuse",
    "sg:phone":"+45 98 68 61 61",
    "sg:postcode":"9240",
    "sg:province":"Danmark",
    "wof:name":"Huset Farstrup",
    "wof:placetype":"venue"
},
  "geometry": {"coordinates":[9.6393280029,56.982421875],"type":"Point"}
}