{
  "type": "Feature",
  "properties": {
    "addr:full":"v/ Poul Rasmussen, Svalevej 15 Strandby Danmark 9970",
    "addr:housenumber":"15",
    "addr:postcode":"9970",
    "addr:street":"Rasmussen Svalevej",
    "iso:country":"DK",
    "sg:address":"v/ Poul Rasmussen, Svalevej 15",
    "sg:city":"Strandby",
    "sg:orig_category":"Trossamfund uden for folkekirken",
    "sg:phone":"+45 98 48 06 26",
    "sg:postcode":"9970",
    "sg:province":"Danmark",
    "wof:name":"Metodistkirken i L\u00f8kken",
    "wof:placetype":"venue"
},
  "geometry": {"coordinates":[10.4970350266,57.4932899475],"type":"Point"}
}