{
  "type": "Feature",
  "properties": {
    "addr:full":"Nyb\u00f8lnorvej 26, Skodsb\u00f8l Broager Danmark 6310",
    "addr:housenumber":"26",
    "addr:postcode":"6310",
    "addr:street":"Nybolnorvej;Skodsbol",
    "iso:country":"DK",
    "sg:address":"Nyb\u00f8lnorvej 26, Skodsb\u00f8l",
    "sg:city":"Broager",
    "sg:orig_category":"Lossepladser",
    "sg:phone":"+45 74 44 03 00",
    "sg:postcode":"6310",
    "sg:province":"Danmark",
    "wof:name":"Alssund Affald (ASA), I/S Deponi",
    "wof:placetype":"venue"
},
  "geometry": {"coordinates":[9.6673240662,54.8893623352],"type":"Point"}
}