{
  "type": "Feature",
  "properties": {
    "addr:full":"Hjortkj\u00e6rsvej 6 Aars Danmark 9600",
    "addr:housenumber":"6",
    "addr:postcode":"9600",
    "addr:street":"Hjortkjaersvej",
    "iso:country":"DK",
    "sg:address":"Hjortkj\u00e6rsvej 6",
    "sg:city":"Aars",
    "sg:orig_category":"Erhvervslokaler, Udlejning af",
    "sg:postcode":"9600",
    "sg:province":"Danmark",
    "wof:name":"Ejendomsanpartsselskabet Aars",
    "wof:placetype":"venue"
},
  "geometry": {"coordinates":[9.5011463165,56.8060836792],"type":"Point"}
}