{
  "type": "Feature",
  "properties": {
    "addr:full":"Oddesundvej 299 Hurup Danmark 7760",
    "addr:housenumber":"299",
    "addr:postcode":"7760",
    "addr:street":"Oddesundvej",
    "iso:country":"DK",
    "sg:address":"Oddesundvej 299",
    "sg:city":"Hurup",
    "sg:orig_category":"Brugskunst",
    "sg:phone":"+45 97 95 66 07",
    "sg:postcode":"7760",
    "sg:province":"Danmark",
    "wof:name":"Smediens Brugskunst",
    "wof:placetype":"venue"
},
  "geometry": {"coordinates":[8.4025602341,56.6927261353],"type":"Point"}
}