{
  "type": "Feature",
  "properties": {
    "addr:full":"Fmd.: J. Skou Hansen, Bredengen 3, Svogerslev Roskilde Danmark 4000",
    "addr:housenumber":"3",
    "addr:postcode":"4000",
    "addr:street":"Bredengen;Svogerslev",
    "iso:country":"DK",
    "sg:address":"Fmd.: J. Skou Hansen, Bredengen 3, Svogerslev",
    "sg:city":"Roskilde",
    "sg:orig_category":"Musik og sang",
    "sg:phone":"+45 46 38 34 43",
    "sg:postcode":"4000",
    "sg:province":"Danmark",
    "wof:name":"Lyngh\u00f8jkoret",
    "wof:placetype":"venue"
},
  "geometry": {"coordinates":[12.0909376144,55.6404838562],"type":"Point"}
}