{
  "type": "Feature",
  "properties": {
    "addr:full":"Kl\u00f8vervej 10B Billund Danmark 7190",
    "addr:housenumber":"10b",
    "addr:postcode":"7190",
    "addr:street":"Klovervej",
    "iso:country":"DK",
    "sg:address":"Kl\u00f8vervej 10B",
    "sg:city":"Billund",
    "sg:orig_category":"Arkitekter",
    "sg:phone":"+45 75 33 88 88",
    "sg:postcode":"7190",
    "sg:province":"Danmark",
    "sg:website":"lvj.webside.dk",
    "wof:name":"Johannsen's Tegnestue, L. C.",
    "wof:placetype":"venue"
},
  "geometry": {"coordinates":[9.1213140488,55.7233085632],"type":"Point"}
}