{
  "type": "Feature",
  "properties": {
    "addr:full":"Egensevej 46 Svendborg Danmark 5700",
    "addr:housenumber":"46",
    "addr:postcode":"5700",
    "addr:street":"Egensevej",
    "iso:country":"DK",
    "sg:address":"Egensevej 46",
    "sg:city":"Svendborg",
    "sg:orig_category":"Blomsterhandlere",
    "sg:phone":"+45 62 21 35 96",
    "sg:postcode":"5700",
    "sg:province":"Danmark",
    "wof:name":"Blomster-Boden",
    "wof:placetype":"venue"
},
  "geometry": {"coordinates":[10.5976848602,55.0584754944],"type":"Point"}
}