{
  "type": "Feature",
  "properties": {
    "addr:full":"Store Kongensgade 15 K\u00f8benhavn Danmark 1264",
    "addr:housenumber":"15;1264",
    "addr:street":"Store Kongensgade",
    "iso:country":"DK",
    "sg:address":"Store Kongensgade 15",
    "sg:city":"K\u00f8benhavn",
    "sg:classifiers":[
        {
            "category":"Restaurant",
            "type":"Food & Drink"
        }
    ],
    "sg:phone":"+45 33 16 12 13",
    "sg:postcode":"1264",
    "sg:province":"Danmark",
    "sg:website":"www.restaurantschultz.dk",
    "wof:name":"Restaurant Schultz",
    "wof:placetype":"venue"
},
  "geometry": {"coordinates":[12.5923995972,55.6865005493],"type":"Point"}
}