{
  "type": "Feature",
  "properties": {
    "iso:country":"DK",
    "sg:address":"\u00c5havevej 52",
    "sg:city":"Silkeborg",
    "sg:orig_category":"Reklamebureauer",
    "sg:phone":"+45 86 82 82 92",
    "sg:postcode":"8600",
    "sg:province":"Danmark",
    "wof:name":"Intekst",
    "wof:placetype":"venue"
},
  "geometry": {"coordinates":[9.55311203,56.1656723022],"type":"Point"}
}