{
  "type": "Feature",
  "properties": {
    "addr:full":"Hoptrup N\u00e6svej 18 Haderslev Danmark 6100",
    "addr:housenumber":"18",
    "addr:postcode":"6100",
    "addr:street":"Naesvej",
    "iso:country":"DK",
    "sg:address":"Hoptrup N\u00e6svej 18",
    "sg:city":"Haderslev",
    "sg:orig_category":"Paintball-baner",
    "sg:phone":"+45 29 28 35 74",
    "sg:postcode":"6100",
    "sg:province":"Danmark",
    "wof:name":"A-Team Paintball",
    "wof:placetype":"venue"
},
  "geometry": {"coordinates":[9.4980888367,55.1931648254],"type":"Point"}
}