{
  "type": "Feature",
  "properties": {
    "addr:full":"Fmd.: Vagn N\u00f8rskov, Nyvej 14 Skibby Danmark 4050",
    "addr:housenumber":"14",
    "addr:postcode":"4050",
    "addr:street":"Nyvej",
    "iso:country":"DK",
    "sg:address":"Fmd.: Vagn N\u00f8rskov, Nyvej 14",
    "sg:city":"Skibby",
    "sg:orig_category":"Boligselskaber",
    "sg:phone":"+45 47 52 75 02",
    "sg:postcode":"4050",
    "sg:province":"Danmark",
    "wof:name":"Skibby Boligforening",
    "wof:placetype":"venue"
},
  "geometry": {"coordinates":[11.9594116211,55.7502975464],"type":"Point"}
}