{
  "type": "Feature",
  "properties": {
    "addr:full":"Fogderup Bygade 18 Bylderup-Bov Danmark 6372",
    "addr:housenumber":"18",
    "addr:postcode":"6372",
    "addr:street":"Fogderup Bygade",
    "iso:country":"DK",
    "sg:address":"Fogderup Bygade 18",
    "sg:city":"Bylderup-Bov",
    "sg:orig_category":"Garn",
    "sg:phone":"+45 74 64 75 64",
    "sg:postcode":"6372",
    "sg:province":"Danmark",
    "wof:name":"Korup Uld Butik",
    "wof:placetype":"venue"
},
  "geometry": {"coordinates":[9.1834497452,55.0280189514],"type":"Point"}
}