{
  "type": "Feature",
  "properties": {
    "iso:country":"DK",
    "sg:address":"\u00c5nsbjergvej 4, Fristrup",
    "sg:city":"Hobro",
    "sg:orig_category":"Cykler",
    "sg:phone":"+45 98 54 63 16",
    "sg:postcode":"9500",
    "sg:province":"Danmark",
    "sg:website":"www.mosquito-fristrup.hobro.dk",
    "wof:name":"Fristrup Autocykler",
    "wof:placetype":"venue"
},
  "geometry": {"coordinates":[9.7946596146,56.6382789612],"type":"Point"}
}