{
  "type": "Feature",
  "properties": {
    "addr:full":"Damvej 11 Fredericia Danmark 7000",
    "addr:housenumber":"11",
    "addr:postcode":"7000",
    "addr:street":"Damvej",
    "iso:country":"DK",
    "sg:address":"Damvej 11",
    "sg:city":"Fredericia",
    "sg:orig_category":"Motionscentre",
    "sg:phone":"+45 75 91 28 88",
    "sg:postcode":"7000",
    "sg:province":"Danmark",
    "wof:name":"Aktiv Fritid Fitnesscenter",
    "wof:placetype":"venue"
},
  "geometry": {"coordinates":[9.7225017548,55.5614471436],"type":"Point"}
}