{
  "type": "Feature",
  "properties": {
    "addr:full":"v/ Torborg Carlsen, Solnavej 101, 2. S\u00f8borg Danmark 2860",
    "addr:housenumber":"101 2",
    "addr:postcode":"2860",
    "addr:street":"Solnavej",
    "iso:country":"DK",
    "sg:address":"v/ Torborg Carlsen, Solnavej 101, 2.",
    "sg:city":"S\u00f8borg",
    "sg:orig_category":"\u00c3\u02dcvrig fritidsundervisning",
    "sg:phone":"+45 39 69 01 93",
    "sg:postcode":"2860",
    "sg:province":"Danmark",
    "wof:name":"De Glade Motionister",
    "wof:placetype":"venue"
},
  "geometry": {"coordinates":[-101.39041900629999,35.6679611206],"type":"Point"}
}