{
  "type": "Feature",
  "properties": {
    "addr:full":"L\u00e5sbybanke 11 Kolding Danmark 6000",
    "addr:housenumber":"11",
    "addr:postcode":"6000",
    "addr:street":"Laasbybanke",
    "iso:country":"DK",
    "sg:address":"L\u00e5sbybanke 11",
    "sg:city":"Kolding",
    "sg:orig_category":"Brugskunst",
    "sg:phone":"+45 75 52 28 07",
    "sg:postcode":"6000",
    "sg:province":"Danmark",
    "wof:name":"Maria",
    "wof:placetype":"venue"
},
  "geometry": {"coordinates":[9.471531868,55.4915390015],"type":"Point"}
}