{
  "type": "Feature",
  "properties": {
    "addr:full":"B\u00e6kager Alle 36 Greve Danmark 2670",
    "addr:housenumber":"36",
    "addr:postcode":"2670",
    "addr:street":"Baekager Alle",
    "iso:country":"DK",
    "sg:address":"B\u00e6kager Alle 36",
    "sg:city":"Greve",
    "sg:orig_category":"Non-Classified Establishments",
    "sg:phone":"+45 43 90 12 36",
    "sg:postcode":"2670",
    "sg:province":"Danmark",
    "wof:name":"Greve Tr\u00e5dvarefabrik",
    "wof:placetype":"venue"
},
  "geometry": {"coordinates":[12.2803497314,55.5728988647],"type":"Point"}
}