{
  "type": "Feature",
  "properties": {
    "addr:full":"Fmd.: Kaare Dubin, Bjerrelide 9 Charlottenlund Danmark 2920",
    "addr:housenumber":"9",
    "addr:postcode":"2920",
    "addr:street":"Kaare;Bjerrelide",
    "iso:country":"DK",
    "sg:address":"Fmd.: Kaare Dubin, Bjerrelide 9",
    "sg:city":"Charlottenlund",
    "sg:orig_category":"Grundejerforeninger",
    "sg:phone":"+45 39 63 91 16",
    "sg:postcode":"2920",
    "sg:province":"Danmark",
    "wof:name":"Nordstrand Grundejerforening",
    "wof:placetype":"venue"
},
  "geometry": {"coordinates":[12.5721197128,55.7532615662],"type":"Point"}
}