{
  "type": "Feature",
  "properties": {
    "addr:full":"Virkevangen 13 Randers Danmark 8900",
    "addr:housenumber":"13",
    "addr:postcode":"8900",
    "addr:street":"Virkevangen",
    "iso:country":"DK",
    "sg:address":"Virkevangen 13",
    "sg:city":"Randers",
    "sg:orig_category":"Grafisk produktion",
    "sg:phone":"+45 86 49 51 88",
    "sg:postcode":"8900",
    "sg:province":"Danmark",
    "wof:name":"Holdt Repro A/S",
    "wof:placetype":"venue"
},
  "geometry": {"coordinates":[10.1594419479,56.4400749207],"type":"Point"}
}