{
  "type": "Feature",
  "properties": {
    "iso:country":"DK",
    "sg:address":"Adelgade 61",
    "sg:city":"Bogense",
    "sg:orig_category":"Kiosker",
    "sg:phone":"+45 64 81 16 14",
    "sg:postcode":"5400",
    "sg:province":"Danmark",
    "wof:name":"Isgrotten",
    "wof:placetype":"venue"
},
  "geometry": {"coordinates":[10.0895233154,55.565612793],"type":"Point"}
}