{
  "type": "Feature",
  "properties": {
    "addr:full":"v/ Poul Thomasen, Gelh\u00f8j 20, St. Valby Roskilde Danmark 4000",
    "addr:housenumber":"20",
    "addr:postcode":"4000",
    "addr:street":"Gelhoj",
    "iso:country":"DK",
    "sg:address":"v/ Poul Thomasen, Gelh\u00f8j 20, St. Valby",
    "sg:city":"Roskilde",
    "sg:orig_category":"Musik og sang",
    "sg:phone":"+45 46 78 71 28",
    "sg:postcode":"4000",
    "sg:province":"Danmark",
    "wof:name":"Roskilde Kristelige Sangkor",
    "wof:placetype":"venue"
},
  "geometry": {"coordinates":[12.0909376144,55.6404838562],"type":"Point"}
}