{
  "type": "Feature",
  "properties": {
    "iso:country":"DK",
    "sg:address":"Snavevej 15, Snave",
    "sg:city":"Haarby",
    "sg:orig_category":"Brugsforeninger",
    "sg:phone":"+45 64 77 10 17",
    "sg:postcode":"5683",
    "sg:province":"Danmark",
    "wof:name":"Lokalbrugsen",
    "wof:placetype":"venue"
},
  "geometry": {"coordinates":[10.1234750748,55.2234535217],"type":"Point"}
}