{
  "type": "Feature",
  "properties": {
    "addr:full":"Storkel\u00f8kken 102, Kirkendrup Odense N Danmark 5270",
    "addr:housenumber":"102",
    "addr:postcode":"5270",
    "addr:street":"Kirkendrup",
    "iso:country":"DK",
    "sg:address":"Storkel\u00f8kken 102, Kirkendrup",
    "sg:city":"Odense N",
    "sg:orig_category":"Boligselskaber",
    "sg:postcode":"5270",
    "sg:province":"Danmark",
    "wof:name":"Ejendommen Kirkendrupparken",
    "wof:placetype":"venue"
},
  "geometry": {"coordinates":[10.3306798935,55.4711418152],"type":"Point"}
}