{
  "type": "Feature",
  "properties": {
    "addr:full":"Lindeg\u00e5rdsvej 12 C Charlottenlund Danmark 2920",
    "addr:housenumber":"12 c",
    "addr:postcode":"2920",
    "addr:street":"Lindegaardsvej",
    "iso:country":"DK",
    "sg:address":"Lindeg\u00e5rdsvej 12 C",
    "sg:city":"Charlottenlund",
    "sg:orig_category":"INGENI\u00c3\u02dcRER",
    "sg:phone":"+45 39 63 61 07",
    "sg:postcode":"2920",
    "sg:province":"Danmark",
    "wof:name":"Johansen, J\u00f8rgen Gramkov",
    "wof:placetype":"venue"
},
  "geometry": {"coordinates":[12.5686321259,55.7586784363],"type":"Point"}
}