{
  "type": "Feature",
  "properties": {
    "iso:country":"DK",
    "sg:address":"Vestergade 18",
    "sg:city":"Varde",
    "sg:orig_category":"Boghandlere",
    "sg:phone":"+45 75 22 00 40",
    "sg:postcode":"6800",
    "sg:province":"Danmark",
    "wof:name":"Bog & Ide",
    "wof:placetype":"venue"
},
  "geometry": {"coordinates":[8.4789009094,55.6214904785],"type":"Point"}
}