{
  "type": "Feature",
  "properties": {
    "addr:full":"Hvidovrevej 73 B Hvidovre Danmark 2650",
    "addr:housenumber":"73 b",
    "addr:postcode":"2650",
    "addr:street":"Hvidovrevej",
    "iso:country":"DK",
    "sg:address":"Hvidovrevej 73 B",
    "sg:city":"Hvidovre",
    "sg:orig_category":"Hobbyartikler",
    "sg:phone":"+45 36 75 98 58",
    "sg:postcode":"2650",
    "sg:province":"Danmark",
    "wof:name":"Hvidovre Hobby og Gaveshop",
    "wof:placetype":"venue"
},
  "geometry": {"coordinates":[12.4737377167,55.6611061096],"type":"Point"}
}