{
  "type": "Feature",
  "properties": {
    "addr:full":"Stenh\u00f8jevej 16, Femm\u00f8ller Ebeltoft Danmark 8400",
    "addr:housenumber":"16",
    "addr:postcode":"8400",
    "addr:street":"Stenhojevej",
    "iso:country":"DK",
    "sg:address":"Stenh\u00f8jevej 16, Femm\u00f8ller",
    "sg:city":"Ebeltoft",
    "sg:orig_category":"Diners transportables",
    "sg:phone":"+45 86 36 26 66",
    "sg:postcode":"8400",
    "sg:province":"Danmark",
    "wof:name":"Overm\u00f8llen, Restaurant",
    "wof:placetype":"venue"
},
  "geometry": {"coordinates":[10.6778745651,56.199798584],"type":"Point"}
}