{
  "type": "Feature",
  "properties": {
    "addr:full":"Heliosvej 27 Vejle Danmark 7100",
    "addr:housenumber":"27",
    "addr:postcode":"7100",
    "addr:street":"Heliosvej",
    "iso:country":"DK",
    "sg:address":"Heliosvej 27",
    "sg:city":"Vejle",
    "sg:orig_category":"Malermestre",
    "sg:phone":"+45 75 82 77 45",
    "sg:postcode":"7100",
    "sg:province":"Danmark",
    "wof:name":"Vejle Maleren",
    "wof:placetype":"venue"
},
  "geometry": {"coordinates":[9.5096960068,55.7269172668],"type":"Point"}
}