{
  "type": "Feature",
  "properties": {
    "iso:country":"DK",
    "sg:address":"Kongensgade 13",
    "sg:city":"Esbjerg",
    "sg:classifiers":[
        {
            "category":"Banks & Credit Unions",
            "subcategory":"Bank",
            "type":"Services"
        }
    ],
    "sg:phone":"+45 75 12 88 77",
    "sg:postcode":"6700",
    "sg:province":"Danmark",
    "sg:tags":[
        "banker"
    ],
    "wof:name":"Arbejdernes Landsbank A/S",
    "wof:placetype":"venue"
},
  "geometry": {"coordinates":[8.454174,55.465897],"type":"Point"}
}