{
  "type": "Feature",
  "properties": {
    "addr:full":"Baneg\u00e5rdspladsen 3 Vejle Danmark 7100",
    "addr:housenumber":"3",
    "addr:postcode":"7100",
    "addr:street":"Banegaardspladsen",
    "iso:country":"DK",
    "sg:address":"Baneg\u00e5rdspladsen 3",
    "sg:city":"Vejle",
    "sg:orig_category":"Kiosker",
    "sg:phone":"+45 75 83 05 41",
    "sg:postcode":"7100",
    "sg:province":"Danmark",
    "wof:name":"DSB Kiosk",
    "wof:placetype":"venue"
},
  "geometry": {"coordinates":[9.5364522934,55.7072181702],"type":"Point"}
}