{
  "type": "Feature",
  "properties": {
    "addr:full":"H. C. Petersens Vej 2 Kolding Danmark 6000",
    "addr:housenumber":"2",
    "addr:postcode":"6000",
    "addr:street":"H. C. Petersens Vej",
    "iso:country":"DK",
    "sg:address":"H. C. Petersens Vej 2",
    "sg:city":"Kolding",
    "sg:orig_category":"Maskinfabrikker",
    "sg:phone":"+45 75 52 07 93",
    "sg:postcode":"6000",
    "sg:province":"Danmark",
    "wof:name":"Hansen Maskinfabrik A/S, N. P.",
    "wof:placetype":"venue"
},
  "geometry": {"coordinates":[9.4811925888,55.4945068359],"type":"Point"}
}