{
  "type": "Feature",
  "properties": {
    "addr:full":"Storgade 25 Sor\u00f8 Danmark 4180",
    "addr:housenumber":"25",
    "addr:postcode":"4180",
    "addr:street":"Storgade",
    "iso:country":"DK",
    "sg:address":"Storgade 25",
    "sg:city":"Sor\u00f8",
    "sg:classifiers":[
        {
            "category":"Restaurant",
            "type":"Food & Drink"
        }
    ],
    "sg:phone":"+45 57 83 22 22",
    "sg:postcode":"4180",
    "sg:province":"Danmark",
    "wof:name":"Postg\u00e5rden, Hotel",
    "wof:placetype":"venue"
},
  "geometry": {"coordinates":[-102.94467926030001,45.4534721375],"type":"Point"}
}