{
  "type": "Feature",
  "properties": {
    "addr:full":"Karlebyvej 201, St. Karleby Kirke Hyllinge Danmark 4070",
    "addr:housenumber":"201",
    "addr:postcode":"4070",
    "addr:street":"Karlebyvej",
    "iso:country":"DK",
    "sg:address":"Karlebyvej 201, St. Karleby",
    "sg:city":"Kirke Hyllinge",
    "sg:orig_category":"Autoruder",
    "sg:phone":"+45 46 40 66 64",
    "sg:postcode":"4070",
    "sg:province":"Danmark",
    "wof:name":"H.N. Glas",
    "wof:placetype":"venue"
},
  "geometry": {"coordinates":[11.9004745483,55.7080039978],"type":"Point"}
}