{
  "type": "Feature",
  "properties": {
    "addr:full":"M\u00e5gevej 21 Fjerritslev Danmark 9690",
    "addr:housenumber":"21",
    "addr:postcode":"9690",
    "addr:street":"Maagevej",
    "iso:country":"DK",
    "sg:address":"M\u00e5gevej 21",
    "sg:city":"Fjerritslev",
    "sg:orig_category":"Murermestre",
    "sg:phone":"+45 98 21 16 85",
    "sg:postcode":"9690",
    "sg:province":"Danmark",
    "wof:name":"Viborg, Murer- og kloakfirmaet Svend",
    "wof:placetype":"venue"
},
  "geometry": {"coordinates":[9.2599163055,57.0833587646],"type":"Point"}
}