{
  "type": "Feature",
  "properties": {
    "addr:full":"Lyngby Hovedgade 112 Kongens Lyngby Danmark 2800",
    "addr:housenumber":"112",
    "addr:postcode":"2800",
    "addr:street":"Lyngby Hovedgade",
    "iso:country":"DK",
    "sg:address":"Lyngby Hovedgade 112",
    "sg:city":"Kongens Lyngby",
    "sg:orig_category":"Skumgummi",
    "sg:phone":"+45 45 88 55 47",
    "sg:postcode":"2800",
    "sg:province":"Danmark",
    "wof:name":"Skumhuset ApS",
    "wof:placetype":"venue"
},
  "geometry": {"coordinates":[12.5118675232,55.7630653381],"type":"Point"}
}