{
  "type": "Feature",
  "properties": {
    "addr:full":"Amaliegade 45 Silkeborg Danmark 8600",
    "addr:housenumber":"45",
    "addr:postcode":"8600",
    "addr:street":"Amaliegade",
    "iso:country":"DK",
    "sg:address":"Amaliegade 45",
    "sg:city":"Silkeborg",
    "sg:orig_category":"Maskinservice",
    "sg:phone":"+45 86 80 63 20",
    "sg:postcode":"8600",
    "sg:province":"Danmark",
    "sg:website":"www.bactoforce.dk",
    "wof:name":"Bactoforce",
    "wof:placetype":"venue"
},
  "geometry": {"coordinates":[9.5494308472,56.1648826599],"type":"Point"}
}