{
  "type": "Feature",
  "properties": {
    "iso:country":"DK",
    "sg:address":"Porthusvej 119",
    "sg:city":"Svendborg",
    "sg:orig_category":"Smedemestre",
    "sg:phone":"+45 62 22 29 21",
    "sg:postcode":"5700",
    "sg:province":"Danmark",
    "wof:name":"Smedeassistancen",
    "wof:placetype":"venue"
},
  "geometry": {"coordinates":[10.6078186035,55.0763511658],"type":"Point"}
}