{
  "type": "Feature",
  "properties": {
    "addr:full":"Vestergade 35 Vejle Danmark 7100",
    "addr:housenumber":"35",
    "addr:postcode":"7100",
    "addr:street":"Vestergade",
    "iso:country":"DK",
    "sg:address":"Vestergade 35",
    "sg:city":"Vejle",
    "sg:orig_category":"Solcentre",
    "sg:phone":"+45 75 83 54 01",
    "sg:postcode":"7100",
    "sg:province":"Danmark",
    "wof:name":"Vestergades Sol Center",
    "wof:placetype":"venue"
},
  "geometry": {"coordinates":[9.5364227295,55.7129974365],"type":"Point"}
}