{
  "type": "Feature",
  "properties": {
    "addr:full":"Hjaltesvej 51 Hadsten Danmark 8370",
    "addr:housenumber":"51",
    "addr:postcode":"8370",
    "addr:street":"Hjaltesvej",
    "iso:country":"DK",
    "sg:address":"Hjaltesvej 51",
    "sg:city":"Hadsten",
    "sg:classifiers":[
        {
            "category":"Food & Beverages",
            "subcategory":"Liquor & Beverages",
            "type":"Retail Goods"
        }
    ],
    "sg:phone":"+45 86 98 17 16",
    "sg:postcode":"8370",
    "sg:province":"Danmark",
    "sg:tags":[
        "vin"
    ],
    "wof:name":"VinDirect-Hadsten",
    "wof:placetype":"venue"
},
  "geometry": {"coordinates":[10.0645923615,56.3332214355],"type":"Point"}
}