{
  "type": "Feature",
  "properties": {
    "iso:country":"DK",
    "sg:address":"Dalgaardsvej 3",
    "sg:city":"Aalestrup",
    "sg:orig_category":"Blikkenslagere",
    "sg:phone":"+45 98 64 31 83",
    "sg:postcode":"9620",
    "sg:province":"Danmark",
    "sg:website":"www.aalestrup-vvs.dk",
    "wof:name":"Aalestrup VVS- & Blikkenslagerforretning",
    "wof:placetype":"venue"
},
  "geometry": {"coordinates":[9.487117,56.699184],"type":"Point"}
}