{
  "type": "Feature",
  "properties": {
    "iso:country":"DK",
    "sg:address":"B\u00e6kvej 1",
    "sg:city":"Spjald",
    "sg:orig_category":"Maskinstationer",
    "sg:phone":"+45 97 38 19 66",
    "sg:postcode":"6971",
    "sg:province":"Danmark",
    "wof:name":"Eriksens Maskinstation A/S",
    "wof:placetype":"venue"
},
  "geometry": {"coordinates":[8.5123357773,56.1267929077],"type":"Point"}
}