{
  "type": "Feature",
  "properties": {
    "addr:full":"B\u00f8rsgade 1 K\u00f8benhavn Danmark 1215",
    "addr:housenumber":"1;1215",
    "addr:street":"Borsgade",
    "iso:country":"DK",
    "sg:address":"B\u00f8rsgade 1",
    "sg:city":"K\u00f8benhavn",
    "sg:orig_category":"Erhvervs- og brancheforeninger",
    "sg:phone":"+45 33 93 91 72",
    "sg:postcode":"1215",
    "sg:province":"Danmark",
    "wof:name":"St\u00e5lforeningen, Foreningen af Danske St\u00e5lgrossister",
    "wof:placetype":"venue"
},
  "geometry": {"coordinates":[76.3070983887,14.277130127],"type":"Point"}
}