{
  "type": "Feature",
  "properties": {
    "addr:full":"Kontaktpers.: Ingelise Madsen, Kl\u00f8vermarksvej 56, Ollerup Vester Skerninge Danmark 5762",
    "addr:housenumber":"56",
    "addr:postcode":"5762",
    "addr:street":"Klovermarksvej",
    "iso:country":"DK",
    "sg:address":"Kontaktpers.: Ingelise Madsen, Kl\u00f8vermarksvej 56, Ollerup",
    "sg:city":"Vester Skerninge",
    "sg:orig_category":"\u00c3\u2020ldreorganisationer og klubber",
    "sg:phone":"+45 62 24 24 62",
    "sg:postcode":"5762",
    "sg:province":"Danmark",
    "wof:name":"Klub 13 for blinde og svagtseende",
    "wof:placetype":"venue"
},
  "geometry": {"coordinates":[10.5008449554,55.070400238],"type":"Point"}
}