{
  "type": "Feature",
  "properties": {
    "iso:country":"DK",
    "sg:address":"S\u00f8ndergade 19 - 21",
    "sg:city":"Skive",
    "sg:orig_category":"Supermarkeder",
    "sg:phone":"+45 97 52 16 66",
    "sg:postcode":"7800",
    "sg:province":"Danmark",
    "wof:name":"F\u00f8tex",
    "wof:placetype":"venue"
},
  "geometry": {"coordinates":[9.0270900726,56.5620384216],"type":"Point"}
}