{
  "type": "Feature",
  "properties": {
    "addr:full":"Hjortkj\u00e6rsvej 1, kld. Aars Danmark 9600",
    "addr:housenumber":"1 kld.",
    "addr:postcode":"9600",
    "addr:street":"Hjortkjaersvej",
    "iso:country":"DK",
    "sg:address":"Hjortkj\u00e6rsvej 1, kld.",
    "sg:city":"Aars",
    "sg:orig_category":"Motionscentre",
    "sg:phone":"+45 98 62 48 91",
    "sg:postcode":"9600",
    "sg:province":"Danmark",
    "wof:name":"Fomsgaard, Motionscenter Peter",
    "wof:placetype":"venue"
},
  "geometry": {"coordinates":[9.5170412064,56.8031692505],"type":"Point"}
}