{
  "type": "Feature",
  "properties": {
    "addr:full":"Havvej 26, Vrinners Knebel Danmark 8420",
    "addr:housenumber":"26",
    "addr:postcode":"8420",
    "addr:street":"Havvej;Vrinners",
    "iso:country":"DK",
    "sg:address":"Havvej 26, Vrinners",
    "sg:city":"Knebel",
    "sg:orig_category":"Maskinstationer",
    "sg:phone":"+45 86 36 55 54",
    "sg:postcode":"8420",
    "sg:province":"Danmark",
    "wof:name":"Mols Kloak Service",
    "wof:placetype":"venue"
},
  "geometry": {"coordinates":[10.3770122528,56.1816596985],"type":"Point"}
}