{
  "type": "Feature",
  "properties": {
    "addr:full":"Afd.leder: Karen K. Mortensen, Fjordvej 162 Munkebo Danmark 5330",
    "addr:housenumber":"162",
    "addr:postcode":"5330",
    "addr:street":"Fjordvej",
    "iso:country":"DK",
    "sg:address":"Afd.leder: Karen K. Mortensen, Fjordvej 162",
    "sg:city":"Munkebo",
    "sg:orig_category":"Skolefritidsordninger",
    "sg:phone":"+45 65 97 72 80",
    "sg:postcode":"5330",
    "sg:province":"Danmark",
    "wof:name":"Skolefritidsordningen Stjerneskuddet",
    "wof:placetype":"venue"
},
  "geometry": {"coordinates":[10.5594701767,55.4595069885],"type":"Point"}
}