{
  "type": "Feature",
  "properties": {
    "addr:full":"Bygaden 55, Levring Kjellerup Danmark 8620",
    "addr:housenumber":"55",
    "addr:postcode":"8620",
    "addr:street":"Bygaden",
    "iso:country":"DK",
    "sg:address":"Bygaden 55, Levring",
    "sg:city":"Kjellerup",
    "sg:orig_category":"Kirker",
    "sg:postcode":"8620",
    "sg:province":"Danmark",
    "wof:name":"Levring Kirke",
    "wof:placetype":"venue"
},
  "geometry": {"coordinates":[9.430934906,56.2877655029],"type":"Point"}
}