{
  "type": "Feature",
  "properties": {
    "addr:full":"Odinsplads 3 Vojens Danmark 6500",
    "addr:housenumber":"3",
    "addr:postcode":"6500",
    "addr:street":"Odinsplads",
    "iso:country":"DK",
    "sg:address":"Odinsplads 3",
    "sg:city":"Vojens",
    "sg:orig_category":"Jernbaner",
    "sg:phone":"+45 70 13 14 15",
    "sg:postcode":"6500",
    "sg:province":"Danmark",
    "wof:name":"DSB Information og Pladsbestilling",
    "wof:placetype":"venue"
},
  "geometry": {"coordinates":[9.3053178787,55.2483825684],"type":"Point"}
}