{
  "type": "Feature",
  "properties": {
    "iso:country":"DK",
    "sg:address":"Marienlystvej 4",
    "sg:city":"Silkeborg",
    "sg:orig_category":"Dyreklinikker og -hospitaler",
    "sg:phone":"+45 86 83 75 10",
    "sg:postcode":"8600",
    "sg:province":"Danmark",
    "sg:website":"www.virklunddyreklinik.dk",
    "wof:name":"Virklund Dyreklinik",
    "wof:placetype":"venue"
},
  "geometry": {"coordinates":[9.5594482422,56.1376647949],"type":"Point"}
}