{
  "type": "Feature",
  "properties": {
    "iso:country":"DK",
    "sg:address":"Vestergade 22",
    "sg:city":"Maribo",
    "sg:orig_category":"Bagere",
    "sg:phone":"+45 54 78 38 71",
    "sg:postcode":"4930",
    "sg:province":"Danmark",
    "wof:name":"Guldbageren",
    "wof:placetype":"venue"
},
  "geometry": {"coordinates":[11.4977,54.774925],"type":"Point"}
}