{
  "type": "Feature",
  "properties": {
    "addr:full":"D\u00e6mningen 41 B Vejle Danmark 7100",
    "addr:housenumber":"41 b",
    "addr:postcode":"7100",
    "addr:street":"Daemningen",
    "iso:country":"DK",
    "sg:address":"D\u00e6mningen 41 B",
    "sg:city":"Vejle",
    "sg:orig_category":"Renserier",
    "sg:phone":"+45 75 82 61 03",
    "sg:postcode":"7100",
    "sg:province":"Danmark",
    "wof:name":"Clip Rens",
    "wof:placetype":"venue"
},
  "geometry": {"coordinates":[9.5359258652,55.7101898193],"type":"Point"}
}