{
  "type": "Feature",
  "properties": {
    "addr:full":"Sct. Clemens Vej 35 Skagen Danmark 9990",
    "addr:housenumber":"35",
    "addr:postcode":"9990",
    "addr:street":"Sct. Clemens Vej",
    "iso:country":"DK",
    "sg:address":"Sct. Clemens Vej 35",
    "sg:city":"Skagen",
    "sg:orig_category":"Farve og tapet",
    "sg:phone":"+45 98 44 13 35",
    "sg:postcode":"9990",
    "sg:province":"Danmark",
    "wof:name":"Skagens Farvehandel",
    "wof:placetype":"venue"
},
  "geometry": {"coordinates":[10.5814599991,57.720035553],"type":"Point"}
}