{
  "type": "Feature",
  "properties": {
    "addr:full":"V\u00f8lundsvej 11 Frederikssund Danmark 3600",
    "addr:housenumber":"11",
    "addr:postcode":"3600",
    "addr:street":"Volundsvej",
    "iso:country":"DK",
    "sg:address":"V\u00f8lundsvej 11",
    "sg:city":"Frederikssund",
    "sg:orig_category":"Autoforhandlere",
    "sg:phone":"+45 47 31 55 56",
    "sg:postcode":"3600",
    "sg:province":"Danmark",
    "wof:name":"Jacobil A/S",
    "wof:placetype":"venue"
},
  "geometry": {"coordinates":[12.0588407516,55.8495254517],"type":"Point"}
}