{
  "type": "Feature",
  "properties": {
    "addr:full":"Holb\u00e6kvej 108 Jyderup Danmark 4450",
    "addr:housenumber":"108",
    "addr:postcode":"4450",
    "addr:street":"Holbaekvej",
    "iso:country":"DK",
    "sg:address":"Holb\u00e6kvej 108",
    "sg:city":"Jyderup",
    "sg:orig_category":"Skolefritidsordninger",
    "sg:phone":"+45 59 27 61 11",
    "sg:postcode":"4450",
    "sg:province":"Danmark",
    "wof:name":"Bivognen Skolefritidsordning",
    "wof:placetype":"venue"
},
  "geometry": {"coordinates":[11.4163331985,55.6642417908],"type":"Point"}
}