{
  "type": "Feature",
  "properties": {
    "addr:full":"Struervej 29 Holstebro Danmark 7500",
    "addr:housenumber":"29",
    "addr:postcode":"7500",
    "addr:street":"Struervej",
    "iso:country":"DK",
    "sg:address":"Struervej 29",
    "sg:city":"Holstebro",
    "sg:orig_category":"Genbrugsbutikker",
    "sg:phone":"+45 97 41 42 83",
    "sg:postcode":"7500",
    "sg:province":"Danmark",
    "wof:name":"Ydre Missions Genbrug",
    "wof:placetype":"venue"
},
  "geometry": {"coordinates":[8.6183128357,56.3649749756],"type":"Point"}
}