{
  "type": "Feature",
  "properties": {
    "iso:country":"DK",
    "sg:address":"Farvervej 13 ",
    "sg:city":"Viborg",
    "sg:classifiers":[
        {
            "category":"Autos & Motor Vehicles",
            "subcategory":"Automobile Sales",
            "type":"Retail Goods"
        }
    ],
    "sg:phone":"+45 86 62 45 77",
    "sg:postcode":"8800",
    "sg:province":"Danmark",
    "sg:tags":[
        "industrial"
    ],
    "wof:name":"DAN-GLAS A/S",
    "wof:placetype":"venue"
},
  "geometry": {"coordinates":[9.3965215683,56.4639396667],"type":"Point"}
}