{
  "type": "Feature",
  "properties": {
    "addr:full":"Edelgave All\u00e9 8 Gentofte Danmark 2820",
    "addr:housenumber":"8",
    "addr:postcode":"2820",
    "addr:street":"Edelgave Alle\u0301",
    "iso:country":"DK",
    "sg:address":"Edelgave All\u00e9 8",
    "sg:city":"Gentofte",
    "sg:orig_category":"Indretningsarkitekter",
    "sg:phone":"+45 39 65 44 10",
    "sg:postcode":"2820",
    "sg:province":"Danmark",
    "wof:name":"Bisgaard, Ellen",
    "wof:placetype":"venue"
},
  "geometry": {"coordinates":[12.5459527969,55.7447357178],"type":"Point"}
}