{
  "type": "Feature",
  "properties": {
    "addr:full":"Fmd.: Kit Bisg\u00e5rd, Aastoften 14, Svogerslev Roskilde Danmark 4000",
    "addr:housenumber":"14",
    "addr:postcode":"4000",
    "addr:street":"Aastoften;Svogerslev",
    "iso:country":"DK",
    "sg:address":"Fmd.: Kit Bisg\u00e5rd, Aastoften 14, Svogerslev",
    "sg:city":"Roskilde",
    "sg:orig_category":"Kulturelle foreninger",
    "sg:phone":"+45 46 38 35 14",
    "sg:postcode":"4000",
    "sg:province":"Danmark",
    "wof:name":"Roskildeegnens Sl\u00e6gtsforskerforening",
    "wof:placetype":"venue"
},
  "geometry": {"coordinates":[12.0909376144,55.6404838562],"type":"Point"}
}