{
  "type": "Feature",
  "properties": {
    "addr:full":"Lundholmvej 45 Holstebro Danmark 7500",
    "addr:housenumber":"45",
    "addr:postcode":"7500",
    "addr:street":"Lundholmvej",
    "iso:country":"DK",
    "sg:address":"Lundholmvej 45",
    "sg:city":"Holstebro",
    "sg:orig_category":"Autoophug",
    "sg:phone":"+45 97 42 15 55",
    "sg:postcode":"7500",
    "sg:province":"Danmark",
    "sg:website":"www.midtjysk-autoophug.dk",
    "wof:name":"Midtjysk Autoophug A/S",
    "wof:placetype":"venue"
},
  "geometry": {"coordinates":[8.6176166534,56.3829498291],"type":"Point"}
}