{
  "type": "Feature",
  "properties": {
    "addr:full":"Pr\u00e6stevangen 25 Ansager Danmark 6823",
    "addr:housenumber":"25",
    "addr:postcode":"6823",
    "addr:street":"Praestevangen",
    "iso:country":"DK",
    "sg:address":"Pr\u00e6stevangen 25",
    "sg:city":"Ansager",
    "sg:orig_category":"Tryksager",
    "sg:phone":"+45 75 29 76 23",
    "sg:postcode":"6823",
    "sg:province":"Danmark",
    "sg:website":"www.amh-fotosats.dk",
    "wof:name":"amh Grafisk aps",
    "wof:placetype":"venue"
},
  "geometry": {"coordinates":[8.7578830719,55.7024154663],"type":"Point"}
}