{
  "type": "Feature",
  "properties": {
    "addr:full":"Enev S\u00f8rensens Vej 6 Kolding Danmark 6000",
    "addr:housenumber":"6",
    "addr:postcode":"6000",
    "addr:street":"Sorensens Vej",
    "iso:country":"DK",
    "sg:address":"Enev S\u00f8rensens Vej 6",
    "sg:city":"Kolding",
    "sg:orig_category":"Ejendomshandel",
    "sg:phone":"+45 75 52 48 66",
    "sg:postcode":"6000",
    "sg:province":"Danmark",
    "sg:website":"www.edc-ht.dk",
    "wof:name":"Heiwald & Thomsen, EDC Ejendomsm\u00e6glerfirmaet",
    "wof:placetype":"venue"
},
  "geometry": {"coordinates":[9.4692630768,55.4755134583],"type":"Point"}
}