{
  "type": "Feature",
  "properties": {
    "addr:full":"Storegade 27 Aabenraa Danmark 6200",
    "addr:housenumber":"27",
    "addr:postcode":"6200",
    "addr:street":"Storegade",
    "iso:country":"DK",
    "sg:address":"Storegade 27",
    "sg:city":"Aabenraa",
    "sg:orig_category":"Indretningsarkitekter",
    "sg:phone":"+45 74 62 76 55",
    "sg:postcode":"6200",
    "sg:province":"Danmark",
    "wof:name":"Rod, Hanne",
    "wof:placetype":"venue"
},
  "geometry": {"coordinates":[9.4189996719,55.0434265137],"type":"Point"}
}