{
  "type": "Feature",
  "properties": {
    "addr:full":"Fmd.: Lis A Rasmussen, Holebyvej 1 R\u00f8dby Danmark 4970",
    "addr:housenumber":"1",
    "addr:postcode":"4970",
    "addr:street":"Fmd. Lis A Rasmussen Holebyvej",
    "iso:country":"DK",
    "sg:address":"Fmd.: Lis A Rasmussen, Holebyvej 1",
    "sg:city":"R\u00f8dby",
    "sg:orig_category":"Hobbybetonede foreninger",
    "sg:phone":"+45 54 60 62 75",
    "sg:postcode":"4970",
    "sg:province":"Danmark",
    "wof:name":"R\u00f8dby Bridgeklub",
    "wof:placetype":"venue"
},
  "geometry": {"coordinates":[-94.804649353,47.8163146973],"type":"Point"}
}