{
  "type": "Feature",
  "properties": {
    "addr:full":"Oslo Plads 8 K\u00f8benhavn \u00d8 Danmark 2100",
    "addr:housenumber":"8",
    "addr:postcode":"2100",
    "addr:street":"Oslo Plads;O",
    "iso:country":"DK",
    "sg:address":"Oslo Plads 8",
    "sg:city":"K\u00f8benhavn \u00d8",
    "sg:orig_category":"Jernbaner",
    "sg:phone":"+45 33 91 09 90",
    "sg:postcode":"2100",
    "sg:province":"Danmark",
    "wof:name":"DSB, \u00d8sterport Station",
    "wof:placetype":"venue"
},
  "geometry": {"coordinates":[11.6836299896,60.2548065186],"type":"Point"}
}