{
  "type": "Feature",
  "properties": {
    "iso:country":"DK",
    "sg:address":"Hyldeholtvej 6",
    "sg:city":"Fakse Ladeplads",
    "sg:orig_category":"Efterskoler",
    "sg:phone":"+45 56 71 63 88",
    "sg:postcode":"4654",
    "sg:province":"Danmark",
    "wof:name":"Waldemarsbo Efterskole",
    "wof:placetype":"venue"
},
  "geometry": {"coordinates":[12.1675443649,55.2192573547],"type":"Point"}
}