{
  "type": "Feature",
  "properties": {
    "addr:full":"Englandsvej 392 Kastrup Danmark 2770",
    "addr:housenumber":"392",
    "addr:postcode":"2770",
    "addr:street":"Englandsvej",
    "iso:country":"DK",
    "sg:address":"Englandsvej 392",
    "sg:city":"Kastrup",
    "sg:orig_category":"Fritidshjem",
    "sg:phone":"+45 32 51 15 90",
    "sg:postcode":"2770",
    "sg:province":"Danmark",
    "wof:name":"T\u00e5rnbyg\u00e5rdskolen, Fritidshjemmet ved",
    "wof:placetype":"venue"
},
  "geometry": {"coordinates":[12.605383873,55.6190834045],"type":"Point"}
}