{
  "type": "Feature",
  "properties": {
    "addr:full":"Dyrehaven 7 Klampenborg Danmark 2930",
    "addr:housenumber":"7",
    "addr:postcode":"2930",
    "addr:street":"Dyrehaven",
    "iso:country":"DK",
    "sg:address":"Dyrehaven 7",
    "sg:city":"Klampenborg",
    "sg:classifiers":[
        {
            "category":"Restaurant",
            "type":"Food & Drink"
        }
    ],
    "sg:phone":"+45 70 26 02 12",
    "sg:postcode":"2930",
    "sg:province":"Danmark",
    "sg:website":"www.piil-co.dk",
    "wof:name":"Piil & Co, Restaurant",
    "wof:placetype":"venue"
},
  "geometry": {"coordinates":[12.5715093613,55.7771720886],"type":"Point"}
}