{
  "type": "Feature",
  "properties": {
    "addr:full":"Godth\u00e5bsvej 23 Herning Danmark 7400",
    "addr:housenumber":"23",
    "addr:postcode":"7400",
    "addr:street":"Godthaabsvej",
    "iso:country":"DK",
    "sg:address":"Godth\u00e5bsvej 23",
    "sg:city":"Herning",
    "sg:orig_category":"Kirkelige foreninger",
    "sg:postcode":"7400",
    "sg:province":"Danmark",
    "wof:name":"Luthersk Missionsforening",
    "wof:placetype":"venue"
},
  "geometry": {"coordinates":[8.9630947113,56.1320877075],"type":"Point"}
}