{
  "type": "Feature",
  "properties": {
    "addr:full":"Store Torv 9 \u00c5rhus C Danmark 8000",
    "addr:housenumber":"9",
    "addr:postcode":"8000",
    "addr:street":"Store Torv",
    "iso:country":"DK",
    "sg:address":"Store Torv 9",
    "sg:city":"\u00c5rhus C",
    "sg:orig_category":"Rejsebureauer",
    "sg:phone":"+45 86 20 87 87",
    "sg:postcode":"8000",
    "sg:province":"Danmark",
    "sg:website":"www.danskfolkeferie.dk",
    "wof:name":"Dansk Folkeferie",
    "wof:placetype":"venue"
},
  "geometry": {"coordinates":[4.717400074,49.7588005066],"type":"Point"}
}