{
  "type": "Feature",
  "properties": {
    "addr:full":"Harens Kvarter 26, Ejby Lille Skensved Danmark 4623",
    "addr:housenumber":"26",
    "addr:postcode":"4623",
    "addr:street":"Harens Kvarter",
    "iso:country":"DK",
    "sg:address":"Harens Kvarter 26, Ejby",
    "sg:city":"Lille Skensved",
    "sg:orig_category":"Murermestre",
    "sg:phone":"+45 56 82 15 09",
    "sg:postcode":"4623",
    "sg:province":"Danmark",
    "wof:name":"Pedersen, Jan",
    "wof:placetype":"venue"
},
  "geometry": {"coordinates":[12.0822563171,55.4889717102],"type":"Point"}
}