{
  "type": "Feature",
  "properties": {
    "addr:full":"\u00d8stergade 11 Hals Danmark 9370",
    "addr:housenumber":"11",
    "addr:postcode":"9370",
    "addr:street":"Ostergade",
    "iso:country":"DK",
    "sg:address":"\u00d8stergade 11",
    "sg:city":"Hals",
    "sg:orig_category":"Kosmetologer",
    "sg:phone":"+45 98 75 06 70",
    "sg:postcode":"9370",
    "sg:province":"Danmark",
    "wof:name":"Karmel, Klinik",
    "wof:placetype":"venue"
},
  "geometry": {"coordinates":[10.3085813522,56.9953384399],"type":"Point"}
}