{
  "type": "Feature",
  "properties": {
    "iso:country":"DK",
    "sg:address":"\u00c5strupvej 1 A",
    "sg:city":"Grenaa",
    "sg:orig_category":"Renserier",
    "sg:phone":"+45 86 32 00 09",
    "sg:postcode":"8500",
    "sg:province":"Danmark",
    "sg:website":"www.dansk-renseri-forening.dk",
    "wof:name":"Reno textil service",
    "wof:placetype":"venue"
},
  "geometry": {"coordinates":[10.878285408,56.4160461426],"type":"Point"}
}