{
  "type": "Feature",
  "properties": {
    "addr:full":"Fmd.: Jan Halsted Hansen, Vestervej 17 A Bagenkop Danmark 5935",
    "addr:housenumber":"17 a",
    "addr:postcode":"5935",
    "addr:street":"Jan;Vestervej",
    "iso:country":"DK",
    "sg:address":"Fmd.: Jan Halsted Hansen, Vestervej 17 A",
    "sg:city":"Bagenkop",
    "sg:orig_category":"Erhvervs- og brancheforeninger",
    "sg:phone":"+45 62 56 12 95",
    "sg:postcode":"5935",
    "sg:province":"Danmark",
    "wof:name":"Bagenkop Erhvervsforening",
    "wof:placetype":"venue"
},
  "geometry": {"coordinates":[10.6733856201,54.7496795654],"type":"Point"}
}