{
  "type": "Feature",
  "properties": {
    "addr:full":"Fmd.: Anton S\u00f8gaard, Bredekildevej 83 Kalundborg Danmark 4400",
    "addr:housenumber":"83",
    "addr:postcode":"4400",
    "addr:street":"Bredekildevej",
    "iso:country":"DK",
    "sg:address":"Fmd.: Anton S\u00f8gaard, Bredekildevej 83",
    "sg:city":"Kalundborg",
    "sg:orig_category":"Hobbybetonede foreninger",
    "sg:phone":"+45 59 51 45 23",
    "sg:postcode":"4400",
    "sg:province":"Danmark",
    "wof:name":"Kalundborg L'homre Klub af 1863",
    "wof:placetype":"venue"
},
  "geometry": {"coordinates":[11.0934085846,55.6797485352],"type":"Point"}
}