{
  "type": "Feature",
  "properties": {
    "addr:full":"Polarstjernevej 32 Skagen Danmark 9990",
    "addr:housenumber":"32",
    "addr:postcode":"9990",
    "addr:street":"Polarstjernevej",
    "iso:country":"DK",
    "sg:address":"Polarstjernevej 32",
    "sg:city":"Skagen",
    "sg:orig_category":"Murermestre",
    "sg:phone":"+45 98 44 20 88",
    "sg:postcode":"9990",
    "sg:province":"Danmark",
    "wof:name":"S\u00f8rensen, Tonny",
    "wof:placetype":"venue"
},
  "geometry": {"coordinates":[10.5888710022,57.7319335938],"type":"Point"}
}