{
  "type": "Feature",
  "properties": {
    "addr:full":"Liljehaven 31, Sm\u00f8rumnedre Sm\u00f8rum Danmark 2765",
    "addr:housenumber":"31",
    "addr:postcode":"2765",
    "addr:street":"Liljehaven",
    "iso:country":"DK",
    "sg:address":"Liljehaven 31, Sm\u00f8rumnedre",
    "sg:city":"Sm\u00f8rum",
    "sg:orig_category":"Forlag",
    "sg:phone":"+45 44 68 44 97",
    "sg:postcode":"2765",
    "sg:province":"Danmark",
    "wof:name":"Bane B\u00f8ger Aps",
    "wof:placetype":"venue"
},
  "geometry": {"coordinates":[-89.99810791020001,38.1321372986],"type":"Point"}
}