{
  "type": "Feature",
  "properties": {
    "addr:full":"Magnoliavej 10, Dyrup Odense SV Danmark 5250",
    "addr:housenumber":"10",
    "addr:postcode":"5250",
    "addr:street":"Magnoliavej;Dyrup",
    "iso:country":"DK",
    "sg:address":"Magnoliavej 10, Dyrup",
    "sg:city":"Odense SV",
    "sg:orig_category":"Databehandling",
    "sg:phone":"+45 66 17 54 86",
    "sg:postcode":"5250",
    "sg:province":"Danmark",
    "wof:name":"Acercon",
    "wof:placetype":"venue"
},
  "geometry": {"coordinates":[10.3153953552,55.3362998962],"type":"Point"}
}