{
  "type": "Feature",
  "properties": {
    "addr:full":"Haslevvej 282 Ringsted Danmark 4100",
    "addr:housenumber":"282",
    "addr:postcode":"4100",
    "addr:street":"Haslevvej",
    "iso:country":"DK",
    "sg:address":"Haslevvej 282",
    "sg:city":"Ringsted",
    "sg:orig_category":"Produkthandlere",
    "sg:phone":"+45 57 64 12 41",
    "sg:postcode":"4100",
    "sg:province":"Danmark",
    "wof:name":"Ren\u00e9s Produkthandel",
    "wof:placetype":"venue"
},
  "geometry": {"coordinates":[11.845949173,55.3845787048],"type":"Point"}
}