{
  "type": "Feature",
  "properties": {
    "addr:full":"Bog\u00f8vej 4 Hinnerup Danmark 8382",
    "addr:housenumber":"4",
    "addr:postcode":"8382",
    "addr:street":"Bogovej",
    "iso:country":"DK",
    "sg:address":"Bog\u00f8vej 4",
    "sg:city":"Hinnerup",
    "sg:classifiers":[
        {
            "category":"Building & Trades",
            "subcategory":"Construction",
            "type":"Services"
        }
    ],
    "sg:phone":"+45 86 98 64 68",
    "sg:postcode":"8382",
    "sg:province":"Danmark",
    "sg:tags":[
        "ventilation"
    ],
    "wof:name":"Rasmussen ApS, J\u00f8rgen",
    "wof:placetype":"venue"
},
  "geometry": {"coordinates":[10.0724039078,56.2516479492],"type":"Point"}
}