{
  "type": "Feature",
  "properties": {
    "iso:country":"DK",
    "sg:address":"Rolighedsvej 12 A",
    "sg:city":"Slagelse",
    "sg:orig_category":"Solcentre",
    "sg:phone":"+45 58 52 14 61",
    "sg:postcode":"4200",
    "sg:province":"Danmark",
    "wof:name":"Clinique Ajour",
    "wof:placetype":"venue"
},
  "geometry": {"coordinates":[11.3641347885,55.4097518921],"type":"Point"}
}