{
  "type": "Feature",
  "properties": {
    "addr:full":"H. I. Park 301 Herning Danmark 7400",
    "addr:housenumber":"301",
    "addr:postcode":"7400",
    "addr:street":"H. I. Park",
    "iso:country":"DK",
    "sg:address":"H. I. Park 301",
    "sg:city":"Herning",
    "sg:orig_category":"EDB - udstyr",
    "sg:phone":"+45 70 12 04 00",
    "sg:postcode":"7400",
    "sg:province":"Danmark",
    "sg:website":"www.atea.dk",
    "wof:name":"Atea Danmark A/S",
    "wof:placetype":"venue"
},
  "geometry": {"coordinates":[8.9768896103,56.1374168396],"type":"Point"}
}