{
  "type": "Feature",
  "properties": {
    "addr:full":"Birkev\u00e6nget 10, Hald Ege Viborg Danmark 8800",
    "addr:housenumber":"10",
    "addr:postcode":"8800",
    "addr:street":"Birkevaenget;Ege",
    "iso:country":"DK",
    "sg:address":"Birkev\u00e6nget 10, Hald Ege",
    "sg:city":"Viborg",
    "sg:orig_category":"Arkitekter",
    "sg:phone":"+45 86 63 86 86",
    "sg:postcode":"8800",
    "sg:province":"Danmark",
    "wof:name":"Dalgaard, Finn",
    "wof:placetype":"venue"
},
  "geometry": {"coordinates":[9.4071502686,56.452671051],"type":"Point"}
}