{
  "type": "Feature",
  "properties": {
    "iso:country":"DK",
    "sg:address":"F\u00e5rtoftvej 22 ",
    "sg:city":"Thisted",
    "sg:classifiers":[
        {
            "category":"Wholesale",
            "subcategory":"Machinery & Supplies",
            "type":"Manufacturing & Wholesale Goods"
        }
    ],
    "sg:phone":"+45 96 17 90 00",
    "sg:postcode":"7700",
    "sg:province":"Danmark",
    "sg:tags":[
        "-",
        "agriculture",
        "equipment"
    ],
    "wof:name":"A/S CIMBRIA",
    "wof:placetype":"venue"
},
  "geometry": {"coordinates":[8.7075719833,56.9558067322],"type":"Point"}
}