{
  "type": "Feature",
  "properties": {
    "addr:full":"Birkesigvej 17 Balle Danmark 8444",
    "addr:housenumber":"17",
    "addr:postcode":"8444",
    "addr:street":"Birkesigvej",
    "iso:country":"DK",
    "sg:address":"Birkesigvej 17",
    "sg:city":"Balle",
    "sg:orig_category":"Teltudlejning",
    "sg:phone":"+45 86 33 75 95",
    "sg:postcode":"8444",
    "sg:province":"Danmark",
    "wof:name":"Ebeltoft Budcentral",
    "wof:placetype":"venue"
},
  "geometry": {"coordinates":[10.8090896606,56.31640625],"type":"Point"}
}