{
  "type": "Feature",
  "properties": {
    "addr:full":"\u00c5sh\u00f8jvej 5 K\u00f8ge Danmark 4600",
    "addr:housenumber":"5",
    "addr:postcode":"4600",
    "addr:street":"Aashojvej",
    "iso:country":"DK",
    "sg:address":"\u00c5sh\u00f8jvej 5",
    "sg:city":"K\u00f8ge",
    "sg:orig_category":"Autoreparation og -service",
    "sg:phone":"+45 56 27 60 28",
    "sg:postcode":"4600",
    "sg:province":"Danmark",
    "wof:name":"J.P. Auto",
    "wof:placetype":"venue"
},
  "geometry": {"coordinates":[43.3657913208,42.3115196228],"type":"Point"}
}