{
  "type": "Feature",
  "properties": {
    "addr:full":"Rungsted Strandvej 302 H\u00f8rsholm Danmark 2970",
    "addr:housenumber":"302",
    "addr:postcode":"2970",
    "addr:street":"Rungsted Strandvej",
    "iso:country":"DK",
    "sg:address":"Rungsted Strandvej 302",
    "sg:city":"H\u00f8rsholm",
    "sg:classifiers":[
        {
            "category":"Restaurant",
            "type":"Food & Drink"
        }
    ],
    "sg:phone":"+45 45 76 63 13",
    "sg:postcode":"2970",
    "sg:province":"Danmark",
    "wof:name":"Mikkelgaard",
    "wof:placetype":"venue"
},
  "geometry": {"coordinates":[12.5234270096,55.9108047485],"type":"Point"}
}