{
  "type": "Feature",
  "properties": {
    "addr:full":"Nyropsgade 38 K\u00f8benhavn Danmark 1602",
    "addr:housenumber":"38;1602",
    "addr:street":"Nyropsgade",
    "iso:country":"DK",
    "sg:address":"Nyropsgade 38",
    "sg:city":"K\u00f8benhavn",
    "sg:orig_category":"Faglige organisationer og -foreninger",
    "sg:phone":"+45 33 63 20 00",
    "sg:postcode":"1602",
    "sg:province":"Danmark",
    "wof:name":"Metalarbejderforbund, Dansk",
    "wof:placetype":"venue"
},
  "geometry": {"coordinates":[12.5633001328,55.6786003113],"type":"Point"}
}