{
  "type": "Feature",
  "properties": {
    "addr:full":"Diget 6 Holb\u00e6k Danmark 4300",
    "addr:housenumber":"6",
    "addr:postcode":"4300",
    "addr:street":"Diget",
    "iso:country":"DK",
    "sg:address":"Diget 6",
    "sg:city":"Holb\u00e6k",
    "sg:orig_category":"Trossamfund uden for folkekirken",
    "sg:postcode":"4300",
    "sg:province":"Danmark",
    "wof:name":"Apostolsk Kirke",
    "wof:placetype":"venue"
},
  "geometry": {"coordinates":[11.7190132141,55.7124786377],"type":"Point"}
}