{
  "type": "Feature",
  "properties": {
    "addr:full":"Havnegade 95 Middelfart Danmark 5500",
    "addr:housenumber":"95",
    "addr:postcode":"5500",
    "addr:street":"Havnegade",
    "iso:country":"DK",
    "sg:address":"Havnegade 95",
    "sg:city":"Middelfart",
    "sg:classifiers":[
        {
            "category":"Restaurant",
            "type":"Food & Drink"
        }
    ],
    "sg:phone":"+45 64 41 08 48",
    "sg:postcode":"5500",
    "sg:province":"Danmark",
    "wof:name":"Toldbodvinhus",
    "wof:placetype":"venue"
},
  "geometry": {"coordinates":[9.7266387939,55.507270813],"type":"Point"}
}