{
  "type": "Feature",
  "properties": {
    "addr:full":"J\u00e6gersborgvej 47 Kongens Lyngby Danmark 2800",
    "addr:housenumber":"47",
    "addr:postcode":"2800",
    "addr:street":"Jaegersborgvej",
    "iso:country":"DK",
    "sg:address":"J\u00e6gersborgvej 47",
    "sg:city":"Kongens Lyngby",
    "sg:orig_category":"Hobbybetonede foreninger",
    "sg:phone":"+45 45 93 60 00",
    "sg:postcode":"2800",
    "sg:province":"Danmark",
    "sg:website":"www.haveselskab.dk",
    "wof:name":"Det Danske Haveselskab-\u00d8erne",
    "wof:placetype":"venue"
},
  "geometry": {"coordinates":[12.5195913315,55.7650718689],"type":"Point"}
}