{
  "type": "Feature",
  "properties": {
    "addr:full":"S\u00f8ndergade 33 Hjallerup Danmark 9320",
    "addr:housenumber":"33",
    "addr:postcode":"9320",
    "addr:street":"Sondergade",
    "iso:country":"DK",
    "sg:address":"S\u00f8ndergade 33",
    "sg:city":"Hjallerup",
    "sg:classifiers":[
        {
            "category":"Personal",
            "subcategory":"Piercing",
            "type":"Services"
        }
    ],
    "sg:phone":"+45 96 47 33 77",
    "sg:postcode":"9320",
    "sg:province":"Danmark",
    "wof:name":"Nordjysk Piercing & Tatoo",
    "wof:placetype":"venue"
},
  "geometry": {"coordinates":[10.1417961121,57.165397644],"type":"Point"}
}