{
  "type": "Feature",
  "properties": {
    "addr:full":"Algade 24 Middelfart Danmark 5500",
    "addr:housenumber":"24",
    "addr:postcode":"5500",
    "addr:street":"Algade",
    "iso:country":"DK",
    "sg:address":"Algade 24",
    "sg:city":"Middelfart",
    "sg:orig_category":"Advokater",
    "sg:phone":"+45 64 41 00 32",
    "sg:postcode":"5500",
    "sg:province":"Danmark",
    "wof:name":"ADVODAN SYD ADVOKATER",
    "wof:placetype":"venue"
},
  "geometry": {"coordinates":[9.7302465439,55.5057296753],"type":"Point"}
}