{
  "type": "Feature",
  "properties": {
    "addr:full":"\u00d8stergade 1 \u00c5rhus C Danmark 8000",
    "addr:housenumber":"1",
    "addr:postcode":"8000",
    "addr:street":"Ostergade",
    "iso:country":"DK",
    "sg:address":"\u00d8stergade 1",
    "sg:city":"\u00c5rhus C",
    "sg:orig_category":"Spedition",
    "sg:phone":"+45 70 20 80 11",
    "sg:postcode":"8000",
    "sg:province":"Danmark",
    "sg:website":"www.unoshipping.com",
    "wof:name":"Uno Shipping Aps",
    "wof:placetype":"venue"
},
  "geometry": {"coordinates":[4.717400074,49.7588005066],"type":"Point"}
}