{
  "type": "Feature",
  "properties": {
    "addr:full":"v/ Jens Peter Christiansen, Jasminvej 27 Bramming Danmark 6740",
    "addr:housenumber":"27",
    "addr:postcode":"6740",
    "addr:street":"Jasminvej",
    "iso:country":"DK",
    "sg:address":"v/ Jens Peter Christiansen, Jasminvej 27",
    "sg:city":"Bramming",
    "sg:orig_category":"Hobbybetonede foreninger",
    "sg:phone":"+45 75 17 27 46",
    "sg:postcode":"6740",
    "sg:province":"Danmark",
    "wof:name":"Bramming og Oplands Fuglevenner",
    "wof:placetype":"venue"
},
  "geometry": {"coordinates":[8.6974096298,55.4655303955],"type":"Point"}
}