{
  "type": "Feature",
  "properties": {
    "addr:full":"Bakkev\u00e6nge 23, \u00d8ster Lindet R\u00f8dding Danmark 6630",
    "addr:housenumber":"23",
    "addr:postcode":"6630",
    "addr:street":"Bakkevaenge;Lindet;Danmark",
    "iso:country":"DK",
    "sg:address":"Bakkev\u00e6nge 23, \u00d8ster Lindet",
    "sg:city":"R\u00f8dding",
    "sg:orig_category":"Musikere",
    "sg:phone":"+45 74 84 60 90",
    "sg:postcode":"6630",
    "sg:province":"Danmark",
    "wof:name":"Elneff, Bent",
    "wof:placetype":"venue"
},
  "geometry": {"coordinates":[9.2022953033,55.3564414978],"type":"Point"}
}