{
  "type": "Feature",
  "properties": {
    "addr:full":"Fmd.: Aage Husum, Fruerlundvej 5, \u00d8. Hurup Hadsund Danmark 9560",
    "addr:housenumber":"5 o.",
    "addr:postcode":"9560",
    "addr:street":"Aage;Fruerlundvej",
    "iso:country":"DK",
    "sg:address":"Fmd.: Aage Husum, Fruerlundvej 5, \u00d8. Hurup",
    "sg:city":"Hadsund",
    "sg:orig_category":"Kulturelle foreninger",
    "sg:phone":"+45 29 27 34 87",
    "sg:postcode":"9560",
    "sg:province":"Danmark",
    "wof:name":"Fruelundparken \u00d8ster Hurup",
    "wof:placetype":"venue"
},
  "geometry": {"coordinates":[10.115904808,56.7150764465],"type":"Point"}
}