{
  "type": "Feature",
  "properties": {
    "addr:full":"Fmd.: Kell Riis Olsen, Skarpeskadevej 12, Nyker R\u00f8nne Danmark 3700",
    "addr:housenumber":"12",
    "addr:postcode":"3700",
    "addr:street":"Skarpeskadevej",
    "iso:country":"DK",
    "sg:address":"Fmd.: Kell Riis Olsen, Skarpeskadevej 12, Nyker",
    "sg:city":"R\u00f8nne",
    "sg:orig_category":"Kirkelige foreninger",
    "sg:phone":"+45 56 96 81 68",
    "sg:postcode":"3700",
    "sg:province":"Danmark",
    "wof:name":"KFUM og KFUK i R\u00f8nne",
    "wof:placetype":"venue"
},
  "geometry": {"coordinates":[14.6975498199,55.0993003845],"type":"Point"}
}