{
  "type": "Feature",
  "properties": {
    "addr:full":"Faldborggade 1 Brovst Danmark 9460",
    "addr:housenumber":"1",
    "addr:postcode":"9460",
    "addr:street":"Faldborggade",
    "iso:country":"DK",
    "sg:address":"Faldborggade 1",
    "sg:city":"Brovst",
    "sg:orig_category":"Revisorer",
    "sg:phone":"+45 98 23 18 66",
    "sg:postcode":"9460",
    "sg:province":"Danmark",
    "wof:name":"Leth ApS, Revisionsfirma Moesgaard",
    "wof:placetype":"venue"
},
  "geometry": {"coordinates":[9.521985054,57.0989990234],"type":"Point"}
}