{
  "type": "Feature",
  "properties": {
    "addr:full":"Stenv\u00e6nget 1, Tj\u00f8rring Herning Danmark 7400",
    "addr:housenumber":"1",
    "addr:postcode":"7400",
    "addr:street":"Stenvaenget;Tjorring",
    "iso:country":"DK",
    "sg:address":"Stenv\u00e6nget 1, Tj\u00f8rring",
    "sg:city":"Herning",
    "sg:orig_category":"Tyverialarmer",
    "sg:phone":"+45 97 26 72 74",
    "sg:postcode":"7400",
    "sg:province":"Danmark",
    "wof:name":"L M Produkt",
    "wof:placetype":"venue"
},
  "geometry": {"coordinates":[8.9768896103,56.1374168396],"type":"Point"}
}