{
  "type": "Feature",
  "properties": {
    "iso:country":"DK",
    "sg:address":"Vestre Stationsvej 1",
    "sg:city":"Rungsted Kyst",
    "sg:orig_category":"Boligmontering",
    "sg:phone":"+45 45 76 00 18",
    "sg:postcode":"2960",
    "sg:province":"Danmark",
    "wof:name":"Maison & Jardin",
    "wof:placetype":"venue"
},
  "geometry": {"coordinates":[12.5293970108,55.8834533691],"type":"Point"}
}