{
  "type": "Feature",
  "properties": {
    "addr:full":"Idomvej 72, Idom Holstebro Danmark 7500",
    "addr:housenumber":"72",
    "addr:postcode":"7500",
    "addr:street":"Idomvej",
    "iso:country":"DK",
    "sg:address":"Idomvej 72, Idom",
    "sg:city":"Holstebro",
    "sg:orig_category":"Blikkenslagere",
    "sg:phone":"+45 97 42 31 69",
    "sg:postcode":"7500",
    "sg:province":"Danmark",
    "wof:name":"Blik og VVS - Gert Fl\u00e6ng",
    "wof:placetype":"venue"
},
  "geometry": {"coordinates":[8.620258,56.362522],"type":"Point"}
}