{
  "type": "Feature",
  "properties": {
    "addr:full":"Osvejen 17, Bjerge Os Store Fuglede Danmark 4480",
    "addr:housenumber":"17",
    "addr:postcode":"4480",
    "addr:street":"Osvejen;Bjerge",
    "iso:country":"DK",
    "sg:address":"Osvejen 17, Bjerge Os",
    "sg:city":"Store Fuglede",
    "sg:orig_category":"Campingpladser",
    "sg:phone":"+45 59 59 72 16",
    "sg:postcode":"4480",
    "sg:province":"Danmark",
    "wof:name":"Solholms Camping",
    "wof:placetype":"venue"
},
  "geometry": {"coordinates":[11.1577796936,55.5918502808],"type":"Point"}
}