{
  "type": "Feature",
  "properties": {
    "addr:full":"Aagade 20, Kliplev Aabenraa Danmark 6200",
    "addr:housenumber":"20",
    "addr:postcode":"6200",
    "addr:street":"Aagade;Kliplev",
    "iso:country":"DK",
    "sg:address":"Aagade 20, Kliplev",
    "sg:city":"Aabenraa",
    "sg:orig_category":"Dieselmotorer",
    "sg:phone":"+45 74 68 88 07",
    "sg:postcode":"6200",
    "sg:province":"Danmark",
    "wof:name":"ABC Scandinavia",
    "wof:placetype":"venue"
},
  "geometry": {"coordinates":[9.4213867188,55.0449562073],"type":"Point"}
}