{
  "type": "Feature",
  "properties": {
    "addr:full":"Gamstvej 20, Gamst Vejen Danmark 6600",
    "addr:housenumber":"20",
    "addr:postcode":"6600",
    "addr:street":"Gamstvej;Gamst",
    "iso:country":"DK",
    "sg:address":"Gamstvej 20, Gamst",
    "sg:city":"Vejen",
    "sg:orig_category":"Import-eksport",
    "sg:phone":"+45 75 36 45 65",
    "sg:postcode":"6600",
    "sg:province":"Danmark",
    "wof:name":"Impotex",
    "wof:placetype":"venue"
},
  "geometry": {"coordinates":[9.1396121979,55.4778175354],"type":"Point"}
}