{
  "type": "Feature",
  "properties": {
    "addr:full":"Damgade 11 Haderslev Danmark 6100",
    "addr:housenumber":"11",
    "addr:postcode":"6100",
    "addr:street":"Damgade",
    "iso:country":"DK",
    "sg:address":"Damgade 11",
    "sg:city":"Haderslev",
    "sg:orig_category":"Murermestre",
    "sg:phone":"+45 74 53 01 55",
    "sg:postcode":"6100",
    "sg:province":"Danmark",
    "sg:website":"www.thomas-hans.dk",
    "wof:name":"Thomas Hans Murer- & Fliseforretning",
    "wof:placetype":"venue"
},
  "geometry": {"coordinates":[9.4864244461,55.2462081909],"type":"Point"}
}