{
  "type": "Feature",
  "properties": {
    "addr:full":"Resenlund 20 Br\u00f8ndby Strand Danmark 2660",
    "addr:housenumber":"20",
    "addr:postcode":"2660",
    "addr:street":"Resenlund;Strand Danmark",
    "iso:country":"DK",
    "sg:address":"Resenlund 20",
    "sg:city":"Br\u00f8ndby Strand",
    "sg:orig_category":"Skolefritidsordninger",
    "sg:phone":"+45 43 28 29 80",
    "sg:postcode":"2660",
    "sg:province":"Danmark",
    "wof:name":"Resenlund SFO I",
    "wof:placetype":"venue"
},
  "geometry": {"coordinates":[-122.35903167719999,48.9091377258],"type":"Point"}
}