{
  "type": "Feature",
  "properties": {
    "iso:country":"DK",
    "sg:address":"S\u00f8ndergade 22",
    "sg:city":"Uldum",
    "sg:orig_category":"Bagere",
    "sg:phone":"+45 75 67 81 01",
    "sg:postcode":"7171",
    "sg:province":"Danmark",
    "wof:name":"Uldum Bageri",
    "wof:placetype":"venue"
},
  "geometry": {"coordinates":[9.5891590118,55.8461723328],"type":"Point"}
}