{
  "type": "Feature",
  "properties": {
    "addr:full":"Langelandsgade 2 Aalborg Danmark 9000",
    "addr:housenumber":"2",
    "addr:postcode":"9000",
    "addr:street":"Langelandsgade",
    "iso:country":"DK",
    "sg:address":"Langelandsgade 2",
    "sg:city":"Aalborg",
    "sg:orig_category":"Bodegaer",
    "sg:phone":"+45 98 11 37 08",
    "sg:postcode":"9000",
    "sg:province":"Danmark",
    "wof:name":"S\u00f8kroen",
    "wof:placetype":"venue"
},
  "geometry": {"coordinates":[9.9419221878,57.0420227051],"type":"Point"}
}