{
  "type": "Feature",
  "properties": {
    "addr:full":"Slotsgade 7 Skive Danmark 7800",
    "addr:housenumber":"7",
    "addr:postcode":"7800",
    "addr:street":"Slotsgade",
    "iso:country":"DK",
    "sg:address":"Slotsgade 7",
    "sg:city":"Skive",
    "sg:orig_category":"Faglige organisationer og foreninger",
    "sg:phone":"+45 97 51 20 11",
    "sg:postcode":"7800",
    "sg:province":"Danmark",
    "wof:name":"FOA - Forbundet af Offentligt Ansatte",
    "wof:placetype":"venue"
},
  "geometry": {"coordinates":[9.0271921158,56.5656852722],"type":"Point"}
}