{
  "type": "Feature",
  "properties": {
    "addr:full":"Clermontgade 22 Roskilde Danmark 4000",
    "addr:housenumber":"22",
    "addr:postcode":"4000",
    "addr:street":"Clermontgade",
    "iso:country":"DK",
    "sg:address":"Clermontgade 22",
    "sg:city":"Roskilde",
    "sg:orig_category":"Autoreparation og -service",
    "sg:phone":"+45 46 35 85 40",
    "sg:postcode":"4000",
    "sg:province":"Danmark",
    "wof:name":"Knudsens Auto",
    "wof:placetype":"venue"
},
  "geometry": {"coordinates":[12.0708341599,55.6450424194],"type":"Point"}
}