{
  "type": "Feature",
  "properties": {
    "addr:full":"N\u00e6ldebjergvej 2 Greve Danmark 2670",
    "addr:housenumber":"2",
    "addr:postcode":"2670",
    "addr:street":"Naeldebjergvej",
    "iso:country":"DK",
    "sg:address":"N\u00e6ldebjergvej 2",
    "sg:city":"Greve",
    "sg:orig_category":"Integrerede institutioner",
    "sg:phone":"+45 43 69 01 43",
    "sg:postcode":"2670",
    "sg:province":"Danmark",
    "wof:name":"Holmebo",
    "wof:placetype":"venue"
},
  "geometry": {"coordinates":[12.2941808701,55.5844078064],"type":"Point"}
}