{
  "type": "Feature",
  "properties": {
    "addr:full":"Gersonsvej 5 Hellerup Danmark 2900",
    "addr:housenumber":"5",
    "addr:postcode":"2900",
    "addr:street":"Gersonsvej",
    "iso:country":"DK",
    "sg:address":"Gersonsvej 5",
    "sg:city":"Hellerup",
    "sg:orig_category":"Integrerede institutioner",
    "sg:phone":"+45 39 62 52 82",
    "sg:postcode":"2900",
    "sg:province":"Danmark",
    "wof:name":"Skattekisten Daginstitution",
    "wof:placetype":"venue"
},
  "geometry": {"coordinates":[12.5675802231,55.7329559326],"type":"Point"}
}