{
  "type": "Feature",
  "properties": {
    "addr:full":"Farum, Postboks 118 Farum Danmark 3520",
    "addr:housenumber":"118",
    "addr:postcode":"3520",
    "iso:country":"DK",
    "sg:address":"Farum, Postboks 118",
    "sg:city":"Farum",
    "sg:classifiers":[
        {
            "category":"Taxi",
            "type":"Transportation"
        }
    ],
    "sg:phone":"+45 44 99 35 35",
    "sg:postcode":"3520",
    "sg:province":"Danmark",
    "sg:website":"www.farumtaxa.dk",
    "wof:name":"Farum Taxa",
    "wof:placetype":"venue"
},
  "geometry": {"coordinates":[12.3755493164,55.8150291443],"type":"Point"}
}