{
  "type": "Feature",
  "properties": {
    "addr:full":"Kongensgade 16 Kongerslev Danmark 9293",
    "addr:housenumber":"16",
    "addr:postcode":"9293",
    "addr:street":"Kongensgade",
    "iso:country":"DK",
    "sg:address":"Kongensgade 16",
    "sg:city":"Kongerslev",
    "sg:orig_category":"Lokalcentre",
    "sg:phone":"+45 98 33 20 82",
    "sg:postcode":"9293",
    "sg:province":"Danmark",
    "wof:name":"Kongerslev \u00c6ldrecenter",
    "wof:placetype":"venue"
},
  "geometry": {"coordinates":[10.1170864105,56.8868141174],"type":"Point"}
}