{
  "type": "Feature",
  "properties": {
    "addr:full":"S\u00f8nderborgvej 1 Krus\u00e5 Danmark 6340",
    "addr:housenumber":"1",
    "addr:postcode":"6340",
    "addr:street":"Sonderborgvej",
    "iso:country":"DK",
    "sg:address":"S\u00f8nderborgvej 1",
    "sg:city":"Krus\u00e5",
    "sg:orig_category":"Mejerier",
    "sg:phone":"+45 74 67 15 14",
    "sg:postcode":"6340",
    "sg:province":"Danmark",
    "wof:name":"Arla Food a.m.b.a.",
    "wof:placetype":"venue"
},
  "geometry": {"coordinates":[9.4050588608,54.8499641418],"type":"Point"}
}