{
  "type": "Feature",
  "properties": {
    "addr:full":"Frederiksborgvej 6 Frederikssund Danmark 3600",
    "addr:housenumber":"6",
    "addr:postcode":"3600",
    "addr:street":"Frederiksborgvej",
    "iso:country":"DK",
    "sg:address":"Frederiksborgvej 6",
    "sg:city":"Frederikssund",
    "sg:orig_category":"\u00c3\u2020ldrecentre",
    "sg:phone":"+45 47 35 03 91",
    "sg:postcode":"3600",
    "sg:province":"Danmark",
    "wof:name":"\u00d8stergaarden",
    "wof:placetype":"venue"
},
  "geometry": {"coordinates":[12.0705070496,55.8412132263],"type":"Point"}
}