{
  "type": "Feature",
  "properties": {
    "addr:full":"Sorgenfri All\u00e9 3, Dalum Odense SV Danmark 5250",
    "addr:housenumber":"3",
    "addr:postcode":"5250",
    "addr:street":"Sorgenfri Alle\u0301;Dalum",
    "iso:country":"DK",
    "sg:address":"Sorgenfri All\u00e9 3, Dalum",
    "sg:city":"Odense SV",
    "sg:orig_category":"Sko",
    "sg:phone":"+45 66 14 19 44",
    "sg:postcode":"5250",
    "sg:province":"Danmark",
    "wof:name":"Christensen, Erik R.",
    "wof:placetype":"venue"
},
  "geometry": {"coordinates":[10.3153953552,55.3362998962],"type":"Point"}
}