{
  "type": "Feature",
  "properties": {
    "iso:country":"DK",
    "sg:address":"Gunnar Clausens Vej 4",
    "sg:city":"Viby",
    "sg:orig_category":"Lastvogne",
    "sg:phone":"+45 87 38 28 75",
    "sg:postcode":"8260",
    "sg:province":"Danmark",
    "wof:name":"Viking Lastbil A/S",
    "wof:placetype":"venue"
},
  "geometry": {"coordinates":[10.1260070801,56.1111183167],"type":"Point"}
}