{
  "type": "Feature",
  "properties": {
    "addr:full":"Stormgade 3 Esbjerg Danmark 6700",
    "addr:housenumber":"3",
    "addr:postcode":"6700",
    "addr:street":"Stormgade",
    "iso:country":"DK",
    "sg:address":"Stormgade 3",
    "sg:city":"Esbjerg",
    "sg:classifiers":[
        {
            "category":"Restaurant",
            "type":"Food & Drink"
        }
    ],
    "sg:phone":"+45 75 12 10 81",
    "sg:postcode":"6700",
    "sg:province":"Danmark",
    "wof:name":"Br\u00e6ddehytten",
    "wof:placetype":"venue"
},
  "geometry": {"coordinates":[8.4432668686,55.4664611816],"type":"Point"}
}