{
  "type": "Feature",
  "properties": {
    "addr:full":"Sj\u00e6llandsgade 22 - 24 Aalborg Danmark 9000",
    "addr:housenumber":"22 24",
    "addr:postcode":"9000",
    "addr:street":"Sjaellandsgade",
    "iso:country":"DK",
    "sg:address":"Sj\u00e6llandsgade 22 - 24",
    "sg:city":"Aalborg",
    "sg:orig_category":"Farve og tapet",
    "sg:phone":"+45 98 13 03 33",
    "sg:postcode":"9000",
    "sg:province":"Danmark",
    "wof:name":"Ejby's Farvehandel",
    "wof:placetype":"venue"
},
  "geometry": {"coordinates":[9.9366569519,57.0403137207],"type":"Point"}
}