{
  "type": "Feature",
  "properties": {
    "addr:full":"Klyngen 37 Greve Danmark 2670",
    "addr:housenumber":"37",
    "addr:postcode":"2670",
    "addr:street":"Klyngen",
    "iso:country":"DK",
    "sg:address":"Klyngen 37",
    "sg:city":"Greve",
    "sg:orig_category":"Ejendomskontorer",
    "sg:phone":"+45 43 90 98 11",
    "sg:postcode":"2670",
    "sg:province":"Danmark",
    "wof:name":"Klyngen Ejendomskontor",
    "wof:placetype":"venue"
},
  "geometry": {"coordinates":[12.3307237625,55.6007156372],"type":"Point"}
}