{
  "type": "Feature",
  "properties": {
    "addr:full":"Storegade 2 Bredebro Danmark 6261",
    "addr:housenumber":"2",
    "addr:postcode":"6261",
    "addr:street":"Storegade",
    "iso:country":"DK",
    "sg:address":"Storegade 2",
    "sg:city":"Bredebro",
    "sg:classifiers":[
        {
            "category":"Banks & Credit Unions",
            "subcategory":"Bank",
            "type":"Services"
        }
    ],
    "sg:phone":"+45 74 71 14 63",
    "sg:postcode":"6261",
    "sg:province":"Danmark",
    "sg:tags":[
        "banker"
    ],
    "wof:name":"Sydbank",
    "wof:placetype":"venue"
},
  "geometry": {"coordinates":[8.8246221542,55.0584144592],"type":"Point"}
}