{
  "type": "Feature",
  "properties": {
    "iso:country":"DK",
    "sg:address":"Marbjerg Byvej 11",
    "sg:city":"Hedehusene",
    "sg:orig_category":"Beslagsmede",
    "sg:phone":"+45 21 64 02 59",
    "sg:postcode":"2640",
    "sg:province":"Danmark",
    "wof:name":"Gerner's Beslagsmedie ApS",
    "wof:placetype":"venue"
},
  "geometry": {"coordinates":[12.162938,55.663937],"type":"Point"}
}