{
  "type": "Feature",
  "properties": {
    "addr:full":"Ansager Omr\u00e5decenter, Pr\u00e6steg\u00e5rdsvej 5 Ansager Danmark 6823",
    "addr:housenumber":"5",
    "addr:postcode":"6823",
    "addr:street":"Praestegaardsvej",
    "iso:country":"DK",
    "sg:address":"Ansager Omr\u00e5decenter, Pr\u00e6steg\u00e5rdsvej 5",
    "sg:city":"Ansager",
    "sg:orig_category":"Lokalarkiver",
    "sg:phone":"+45 75 29 62 29",
    "sg:postcode":"6823",
    "sg:province":"Danmark",
    "sg:website":"www.ala.subnet.dk",
    "wof:name":"Ansager Lokalhistoriske Arkiv",
    "wof:placetype":"venue"
},
  "geometry": {"coordinates":[8.7533082962,55.7048492432],"type":"Point"}
}