{
  "type": "Feature",
  "properties": {
    "addr:full":"N\u00e6stvedvej 42 Ringsted Danmark 4100",
    "addr:housenumber":"42",
    "addr:postcode":"4100",
    "addr:street":"Naestvedvej",
    "iso:country":"DK",
    "sg:address":"N\u00e6stvedvej 42",
    "sg:city":"Ringsted",
    "sg:orig_category":"Motionscentre",
    "sg:phone":"+45 57 67 00 14",
    "sg:postcode":"4100",
    "sg:province":"Danmark",
    "wof:name":"LifeClub",
    "wof:placetype":"venue"
},
  "geometry": {"coordinates":[11.7920217514,55.4389610291],"type":"Point"}
}