{
  "type": "Feature",
  "properties": {
    "addr:full":"H\u00f8jensgaardsvej 11 Saltum Danmark 9493",
    "addr:housenumber":"11",
    "addr:postcode":"9493",
    "addr:street":"Hojensgaardsvej",
    "iso:country":"DK",
    "sg:address":"H\u00f8jensgaardsvej 11",
    "sg:city":"Saltum",
    "sg:orig_category":"Blikkenslagere",
    "sg:phone":"+45 98 88 14 77",
    "sg:postcode":"9493",
    "sg:province":"Danmark",
    "wof:name":"Lange VVS & Blik, Per",
    "wof:placetype":"venue"
},
  "geometry": {"coordinates":[9.698716,57.26709],"type":"Point"}
}