{
  "type": "Feature",
  "properties": {
    "iso:country":"DK",
    "sg:address":"Marslevvej 1",
    "sg:city":"Svendborg",
    "sg:orig_category":"Integrerede institutioner",
    "sg:phone":"+45 62 20 24 88",
    "sg:postcode":"5700",
    "sg:province":"Danmark",
    "wof:name":"Paraplyen",
    "wof:placetype":"venue"
},
  "geometry": {"coordinates":[10.6387252808,55.0736961365],"type":"Point"}
}