{
  "type": "Feature",
  "properties": {
    "addr:full":"R\u00e5dhuspladsen 5 Slagelse Danmark 4200",
    "addr:housenumber":"5",
    "addr:postcode":"4200",
    "addr:street":"Raadhuspladsen",
    "iso:country":"DK",
    "sg:address":"R\u00e5dhuspladsen 5",
    "sg:city":"Slagelse",
    "sg:orig_category":"Tobak",
    "sg:phone":"+45 58 52 51 96",
    "sg:postcode":"4200",
    "sg:province":"Danmark",
    "wof:name":"Excellent",
    "wof:placetype":"venue"
},
  "geometry": {"coordinates":[11.3558273315,55.404838562],"type":"Point"}
}