{
  "type": "Feature",
  "properties": {
    "addr:full":"Langbrokrovej 7 Vodskov Danmark 9310",
    "addr:housenumber":"7",
    "addr:postcode":"9310",
    "addr:street":"Langbrokrovej",
    "iso:country":"DK",
    "sg:address":"Langbrokrovej 7",
    "sg:city":"Vodskov",
    "sg:orig_category":"Kirker",
    "sg:postcode":"9310",
    "sg:province":"Danmark",
    "wof:name":"Vodskov Baptistkirke",
    "wof:placetype":"venue"
},
  "geometry": {"coordinates":[10.0266809464,57.1055526733],"type":"Point"}
}