{
  "type": "Feature",
  "properties": {
    "iso:country":"DK",
    "sg:address":"Margrethevej 27",
    "sg:city":"Holte",
    "sg:orig_category":"Integrerede institutioner",
    "sg:phone":"+45 45 41 20 01",
    "sg:postcode":"2840",
    "sg:province":"Danmark",
    "wof:name":"Karethen Daginstitution",
    "wof:placetype":"venue"
},
  "geometry": {"coordinates":[12.4743947983,55.8163528442],"type":"Point"}
}