{
  "type": "Feature",
  "properties": {
    "addr:full":"Fruestr\u00e6de 3 Svendborg Danmark 5700",
    "addr:housenumber":"3",
    "addr:postcode":"5700",
    "addr:street":"Fruestraede",
    "iso:country":"DK",
    "sg:address":"Fruestr\u00e6de 3",
    "sg:city":"Svendborg",
    "sg:orig_category":"Museer",
    "sg:postcode":"5700",
    "sg:province":"Danmark",
    "wof:name":"Anne Hvides G\u00e5rd",
    "wof:placetype":"venue"
},
  "geometry": {"coordinates":[10.6227207184,55.0639381409],"type":"Point"}
}