{
  "type": "Feature",
  "properties": {
    "iso:country":"DK",
    "sg:address":"Randersvej 72",
    "sg:city":"Viborg",
    "sg:orig_category":"Blomsterhandlere",
    "sg:phone":"+45 86 67 24 00",
    "sg:postcode":"8800",
    "sg:province":"Danmark",
    "wof:name":"Asmild Plantesalg",
    "wof:placetype":"venue"
},
  "geometry": {"coordinates":[9.4756307602,56.460067749],"type":"Point"}
}