{
  "type": "Feature",
  "properties": {
    "iso:country":"DK",
    "sg:address":"S\u00f8ndergade 14",
    "sg:city":"Viby Sj\u00e6lland",
    "sg:orig_category":"Blomsterhandlere",
    "sg:phone":"+45 46 19 44 43",
    "sg:postcode":"4130",
    "sg:province":"Danmark",
    "wof:name":"L J Blomster",
    "wof:placetype":"venue"
},
  "geometry": {"coordinates":[12.024274826,55.5473709106],"type":"Point"}
}