{
  "type": "Feature",
  "properties": {
    "addr:full":"Lindeengen 10 Skovlunde Danmark 2740",
    "addr:housenumber":"10",
    "addr:postcode":"2740",
    "addr:street":"Lindeengen",
    "iso:country":"DK",
    "sg:address":"Lindeengen 10",
    "sg:city":"Skovlunde",
    "sg:orig_category":"Elektronik",
    "sg:phone":"+45 44 84 33 11",
    "sg:postcode":"2740",
    "sg:province":"Danmark",
    "wof:name":"Camto Ltd.",
    "wof:placetype":"venue"
},
  "geometry": {"coordinates":[12.3850393295,55.7110595703],"type":"Point"}
}