{
  "type": "Feature",
  "properties": {
    "addr:full":"S\u00f8bjergvej 10, Vals\u00f8magle Ringsted Danmark 4100",
    "addr:housenumber":"10",
    "addr:postcode":"4100",
    "addr:street":"Sobjergvej;Valsomagle",
    "iso:country":"DK",
    "sg:address":"S\u00f8bjergvej 10, Vals\u00f8magle",
    "sg:city":"Ringsted",
    "sg:orig_category":"Glarmestre og glarmagere",
    "sg:phone":"+45 57 52 85 17",
    "sg:postcode":"4100",
    "sg:province":"Danmark",
    "wof:name":"Glas-Bo",
    "wof:placetype":"venue"
},
  "geometry": {"coordinates":[11.7875862122,55.4458961487],"type":"Point"}
}