{
  "type": "Feature",
  "properties": {
    "addr:full":"L\u00e6g\u00e5rdvej 91 Holstebro Danmark 7500",
    "addr:housenumber":"91",
    "addr:postcode":"7500",
    "addr:street":"Laegaardvej",
    "iso:country":"DK",
    "sg:address":"L\u00e6g\u00e5rdvej 91",
    "sg:city":"Holstebro",
    "sg:orig_category":"Forsikringer",
    "sg:phone":"+45 96 10 52 50",
    "sg:postcode":"7500",
    "sg:province":"Danmark",
    "wof:name":"Codan Forsikring",
    "wof:placetype":"venue"
},
  "geometry": {"coordinates":[8.6202583313,56.3625221252],"type":"Point"}
}