{
  "type": "Feature",
  "properties": {
    "addr:full":"Birk Centerpark 38 POSTBOKS 507  Herning Danmark 7400",
    "addr:housenumber":"38;507",
    "addr:postcode":"7400",
    "addr:street":"Birk Centerpark",
    "iso:country":"DK",
    "sg:address":"Birk Centerpark 38 POSTBOKS 507 ",
    "sg:city":"Herning",
    "sg:classifiers":[
        {
            "category":"Professional",
            "subcategory":"Business Services",
            "type":"Services"
        }
    ],
    "sg:phone":"+45 97 11 72 00",
    "sg:postcode":"7400",
    "sg:province":"Danmark",
    "sg:tags":[
        "advice"
    ],
    "wof:name":"DANSK TEXTIL & BEKL\u00c6DNING",
    "wof:placetype":"venue"
},
  "geometry": {"coordinates":[8.9768896103,56.1374168396],"type":"Point"}
}