{
  "type": "Feature",
  "properties": {
    "iso:country":"DK",
    "sg:address":"Skeevej 44, Skee",
    "sg:city":"Store Merl\u00f8se",
    "sg:orig_category":"Spejderkorps",
    "sg:postcode":"4370",
    "sg:province":"Danmark",
    "wof:name":"Danske Baptisters Spejderkorps Skee kreds",
    "wof:placetype":"venue"
},
  "geometry": {"coordinates":[11.7145853043,55.543346405],"type":"Point"}
}