{
  "type": "Feature",
  "properties": {
    "addr:full":"Fmd.: Ellen Ragnhof, Muldvad 17 Kongens Lyngby Danmark 2800",
    "addr:housenumber":"17",
    "addr:postcode":"2800",
    "addr:street":"Muldvad",
    "iso:country":"DK",
    "sg:address":"Fmd.: Ellen Ragnhof, Muldvad 17",
    "sg:city":"Kongens Lyngby",
    "sg:orig_category":"Grundejerforeninger",
    "sg:phone":"+45 44 98 37 82",
    "sg:postcode":"2800",
    "sg:province":"Danmark",
    "wof:name":"Mulvad Grundejerforening",
    "wof:placetype":"venue"
},
  "geometry": {"coordinates":[12.5368299484,55.7949905396],"type":"Point"}
}