{
  "type": "Feature",
  "properties": {
    "addr:full":"Faaborgvej 122, Dalum Odense SV Danmark 5250",
    "addr:housenumber":"122",
    "addr:postcode":"5250",
    "addr:street":"Faaborgvej;Dalum",
    "iso:country":"DK",
    "sg:address":"Faaborgvej 122, Dalum",
    "sg:city":"Odense SV",
    "sg:orig_category":"Benzinstationer",
    "sg:phone":"+45 66 17 35 56",
    "sg:postcode":"5250",
    "sg:province":"Danmark",
    "wof:name":"Statoil Servicecenter",
    "wof:placetype":"venue"
},
  "geometry": {"coordinates":[10.315395,55.3363],"type":"Point"}
}