{
  "type": "Feature",
  "properties": {
    "addr:full":"Ajstrup Strandvej 81 Malling Danmark 8340",
    "addr:housenumber":"81",
    "addr:postcode":"8340",
    "addr:street":"Ajstrup Strandvej",
    "iso:country":"DK",
    "sg:address":"Ajstrup Strandvej 81",
    "sg:city":"Malling",
    "sg:orig_category":"Supermarkeder",
    "sg:phone":"+45 86 93 35 35",
    "sg:postcode":"8340",
    "sg:province":"Danmark",
    "sg:website":"www.ajstrupstrand.dk",
    "wof:name":"Ajstrup Strand Super",
    "wof:placetype":"venue"
},
  "geometry": {"coordinates":[10.2643051147,56.0411300659],"type":"Point"}
}