{
  "type": "Feature",
  "properties": {
    "addr:full":"Storegade 46 Klovborg Danmark 8765",
    "addr:housenumber":"46",
    "addr:postcode":"8765",
    "addr:street":"Storegade",
    "iso:country":"DK",
    "sg:address":"Storegade 46",
    "sg:city":"Klovborg",
    "sg:orig_category":"Kommunale folkeskoler",
    "sg:phone":"+45 75 76 13 38",
    "sg:postcode":"8765",
    "sg:province":"Danmark",
    "wof:name":"Klovborg Skole",
    "wof:placetype":"venue"
},
  "geometry": {"coordinates":[9.4929618835,55.9309196472],"type":"Point"}
}