{
  "type": "Feature",
  "properties": {
    "iso:country":"DK",
    "sg:address":"Stationsalleen 44",
    "sg:city":"Herlev",
    "sg:orig_category":"Vuggestuer",
    "sg:phone":"+45 44 52 59 50",
    "sg:postcode":"2730",
    "sg:province":"Danmark",
    "wof:name":"Storkereden",
    "wof:placetype":"venue"
},
  "geometry": {"coordinates":[12.4446458817,55.7194862366],"type":"Point"}
}