{
  "type": "Feature",
  "properties": {
    "addr:full":"Teglb\u00e6kvej 25  Hasselager Danmark 8361",
    "addr:housenumber":"25",
    "addr:postcode":"8361",
    "addr:street":"Teglbaekvej",
    "iso:country":"DK",
    "sg:address":"Teglb\u00e6kvej 25 ",
    "sg:city":"Hasselager",
    "sg:classifiers":[
        {
            "category":"Professional",
            "subcategory":"Engineering",
            "type":"Services"
        }
    ],
    "sg:phone":"+45 86 28 39 82",
    "sg:postcode":"8361",
    "sg:province":"Danmark",
    "sg:tags":[
        "machine",
        "-",
        "mechanical"
    ],
    "wof:name":"TM INDUSTRI APS",
    "wof:placetype":"venue"
},
  "geometry": {"coordinates":[10.0982627869,56.1027450562],"type":"Point"}
}