{
  "type": "Feature",
  "properties": {
    "addr:full":"Gl. Holebyvej 12 Holeby Danmark 4960",
    "addr:housenumber":"12",
    "addr:postcode":"4960",
    "addr:street":"Gl. Holebyvej",
    "iso:country":"DK",
    "sg:address":"Gl. Holebyvej 12",
    "sg:city":"Holeby",
    "sg:orig_category":"Antikviteter",
    "sg:phone":"+45 54 60 60 30",
    "sg:postcode":"4960",
    "sg:province":"Danmark",
    "wof:name":"Borella, Antique",
    "wof:placetype":"venue"
},
  "geometry": {"coordinates":[11.4468832016,54.7108764648],"type":"Point"}
}