{
  "type": "Feature",
  "properties": {
    "iso:country":"DK",
    "sg:address":"Haugevej 32 ",
    "sg:city":"Herning",
    "sg:classifiers":[
        {
            "category":"Home & Garden",
            "subcategory":"Home Furnishings",
            "type":"Retail Goods"
        }
    ],
    "sg:phone":"+45 96 26 88 00",
    "sg:postcode":"7400",
    "sg:province":"Danmark",
    "sg:tags":[
        "household"
    ],
    "wof:name":"SYSTEMA HERNING",
    "wof:placetype":"venue"
},
  "geometry": {"coordinates":[9.0834789276,56.1065368652],"type":"Point"}
}