{
  "type": "Feature",
  "properties": {
    "addr:full":"Hovedgaden 12, Nordby Fan\u00f8 Danmark 6720",
    "addr:housenumber":"12",
    "addr:postcode":"6720",
    "addr:street":"Hovedgaden",
    "iso:country":"DK",
    "sg:address":"Hovedgaden 12, Nordby",
    "sg:city":"Fan\u00f8",
    "sg:orig_category":"Bagere",
    "sg:phone":"+45 75 16 20 32",
    "sg:postcode":"6720",
    "sg:province":"Danmark",
    "wof:name":"Bageriet Hovedgaden 12",
    "wof:placetype":"venue"
},
  "geometry": {"coordinates":[8.406946,55.448479],"type":"Point"}
}