{
  "type": "Feature",
  "properties": {
    "addr:full":"Kongensgade 59 Esbjerg Danmark 6700",
    "addr:housenumber":"59",
    "addr:postcode":"6700",
    "addr:street":"Kongensgade",
    "iso:country":"DK",
    "sg:address":"Kongensgade 59",
    "sg:city":"Esbjerg",
    "sg:orig_category":"Vikarbureauer",
    "sg:phone":"+45 75 13 77 97",
    "sg:postcode":"6700",
    "sg:province":"Danmark",
    "wof:name":"Private Nurse",
    "wof:placetype":"venue"
},
  "geometry": {"coordinates":[8.4481725693,55.4665374756],"type":"Point"}
}