{
  "type": "Feature",
  "properties": {
    "addr:full":"Vibevej 2, Nordenskov Varde Danmark 6800",
    "addr:housenumber":"2",
    "addr:postcode":"6800",
    "addr:street":"Vibevej",
    "iso:country":"DK",
    "sg:address":"Vibevej 2, Nordenskov",
    "sg:city":"Varde",
    "sg:orig_category":"Filialbiblioteker",
    "sg:phone":"+45 75 29 82 39",
    "sg:postcode":"6800",
    "sg:province":"Danmark",
    "wof:name":"Nordenskov Bibliotek",
    "wof:placetype":"venue"
},
  "geometry": {"coordinates":[8.482629776,55.6220741272],"type":"Point"}
}