{
  "type": "Feature",
  "properties": {
    "addr:full":"Solsikkevej 7 Vejle Danmark 7100",
    "addr:housenumber":"7",
    "addr:postcode":"7100",
    "addr:street":"Solsikkevej",
    "iso:country":"DK",
    "sg:address":"Solsikkevej 7",
    "sg:city":"Vejle",
    "sg:orig_category":"Arkitekter",
    "sg:phone":"+45 75 82 88 60",
    "sg:postcode":"7100",
    "sg:province":"Danmark",
    "wof:name":"Holbech, Poul Erik",
    "wof:placetype":"venue"
},
  "geometry": {"coordinates":[9.5115442276,55.695350647],"type":"Point"}
}