{
  "type": "Feature",
  "properties": {
    "addr:full":"Egebjergvej 43 Gedved Danmark 8751",
    "addr:housenumber":"43",
    "addr:postcode":"8751",
    "addr:street":"Egebjergvej",
    "iso:country":"DK",
    "sg:address":"Egebjergvej 43",
    "sg:city":"Gedved",
    "sg:orig_category":"Forsamlingshuse",
    "sg:phone":"+45 75 66 52 37",
    "sg:postcode":"8751",
    "sg:province":"Danmark",
    "wof:name":"H\u00f8jbo Forsamlingshus, Gedved",
    "wof:placetype":"venue"
},
  "geometry": {"coordinates":[9.841840744,55.9299736023],"type":"Point"}
}