{
  "type": "Feature",
  "properties": {
    "addr:full":"Granlyvej 4 A, Balslev Ejby Danmark 5592",
    "addr:housenumber":"4 a",
    "addr:postcode":"5592",
    "addr:street":"Granlyvej",
    "iso:country":"DK",
    "sg:address":"Granlyvej 4 A, Balslev",
    "sg:city":"Ejby",
    "sg:orig_category":"Kirker",
    "sg:postcode":"5592",
    "sg:province":"Danmark",
    "wof:name":"Balslev Kirke",
    "wof:placetype":"venue"
},
  "geometry": {"coordinates":[9.9277296066,55.4288444519],"type":"Point"}
}