{
  "type": "Feature",
  "properties": {
    "addr:full":"Vindingg\u00e5rd Center 11 Vejle Danmark 7100",
    "addr:housenumber":"11",
    "addr:postcode":"7100",
    "iso:country":"DK",
    "sg:address":"Vindingg\u00e5rd Center 11",
    "sg:city":"Vejle",
    "sg:classifiers":[
        {
            "category":"Communications",
            "type":"Services"
        }
    ],
    "sg:phone":"+45 75 82 22 99",
    "sg:postcode":"7100",
    "sg:province":"Danmark",
    "sg:tags":[
        "og",
        "tv",
        "radio"
    ],
    "wof:name":"M\u00f8lholm Radio & TV",
    "wof:placetype":"venue"
},
  "geometry": {"coordinates":[9.5518817902,55.6872901917],"type":"Point"}
}