{
  "type": "Feature",
  "properties": {
    "addr:full":"Bakkedraget 10 Vejle Danmark 7100",
    "addr:housenumber":"10",
    "addr:postcode":"7100",
    "addr:street":"Bakkedraget",
    "iso:country":"DK",
    "sg:address":"Bakkedraget 10",
    "sg:city":"Vejle",
    "sg:orig_category":"Cafeterier",
    "sg:phone":"+45 75 72 13 36",
    "sg:postcode":"7100",
    "sg:province":"Danmark",
    "wof:name":"Boldklubben Kammeraternes Cafeteria",
    "wof:placetype":"venue"
},
  "geometry": {"coordinates":[9.5249919891,55.6894035339],"type":"Point"}
}