{
  "type": "Feature",
  "properties": {
    "addr:full":"Schaumburgvej 3 Holstebro Danmark 7500",
    "addr:housenumber":"3",
    "addr:postcode":"7500",
    "addr:street":"Schaumburgvej",
    "iso:country":"DK",
    "sg:address":"Schaumburgvej 3",
    "sg:city":"Holstebro",
    "sg:orig_category":"Private hospitaler and klinikker",
    "sg:phone":"+45 97 41 10 66",
    "sg:postcode":"7500",
    "sg:province":"Danmark",
    "wof:name":"Nielsen, Torben",
    "wof:placetype":"venue"
},
  "geometry": {"coordinates":[8.6239347458,56.3629417419],"type":"Point"}
}