{
  "type": "Feature",
  "properties": {
    "addr:full":"\u00d8stergade 22 Hals Danmark 9370",
    "addr:housenumber":"22",
    "addr:postcode":"9370",
    "addr:street":"Ostergade",
    "iso:country":"DK",
    "sg:address":"\u00d8stergade 22",
    "sg:city":"Hals",
    "sg:orig_category":"Posthuse",
    "sg:phone":"+45 98 25 13 33",
    "sg:postcode":"9370",
    "sg:province":"Danmark",
    "wof:name":"Post Danmark, Hals Postkontor",
    "wof:placetype":"venue"
},
  "geometry": {"coordinates":[10.3098373413,56.9973373413],"type":"Point"}
}