{
  "type": "Feature",
  "properties": {
    "addr:full":"Gammel Flensborgvej 18 Aabenraa Danmark 6200",
    "addr:housenumber":"18",
    "addr:postcode":"6200",
    "addr:street":"Gammel Flensborgvej",
    "iso:country":"DK",
    "sg:address":"Gammel Flensborgvej 18",
    "sg:city":"Aabenraa",
    "sg:orig_category":"Indretningskonsulenter",
    "sg:phone":"+45 74 62 85 85",
    "sg:postcode":"6200",
    "sg:province":"Danmark",
    "wof:name":"Fischer, Jan",
    "wof:placetype":"venue"
},
  "geometry": {"coordinates":[9.4196100235,55.0340309143],"type":"Point"}
}