{
  "type": "Feature",
  "properties": {
    "addr:full":"Bog\u00f8gade 2 Aalborg Danmark 9000",
    "addr:housenumber":"2",
    "addr:postcode":"9000",
    "addr:street":"Bogogade",
    "iso:country":"DK",
    "sg:address":"Bog\u00f8gade 2",
    "sg:city":"Aalborg",
    "sg:orig_category":"Faglige organisationer og foreninger",
    "sg:phone":"+45 98 13 90 88",
    "sg:postcode":"9000",
    "sg:province":"Danmark",
    "wof:name":"Dansk Fris\u00f8r Og Kosmetiker Forbund, Aalborg Afdeling",
    "wof:placetype":"venue"
},
  "geometry": {"coordinates":[9.9352674484,57.041519165],"type":"Point"}
}