{
  "type": "Feature",
  "properties": {
    "addr:full":"H\u00f8jvangen 13 Esperg\u00e6rde Danmark 3060",
    "addr:housenumber":"13",
    "addr:postcode":"3060",
    "addr:street":"Hojvangen",
    "iso:country":"DK",
    "sg:address":"H\u00f8jvangen 13",
    "sg:city":"Esperg\u00e6rde",
    "sg:orig_category":"Arkitekter",
    "sg:phone":"+45 49 13 34 65",
    "sg:postcode":"3060",
    "sg:province":"Danmark",
    "sg:website":"www.cemcon.k",
    "wof:name":"Cemcon",
    "wof:placetype":"venue"
},
  "geometry": {"coordinates":[11.6512403488,47.8390617371],"type":"Point"}
}