{
  "type": "Feature",
  "properties": {
    "addr:full":"Fmd.: Eli Larsen, Broks\u00f8vej 1, Spragelse Herlufmagle Danmark 4160",
    "addr:housenumber":"1",
    "addr:postcode":"4160",
    "addr:street":"Broksovej",
    "iso:country":"DK",
    "sg:address":"Fmd.: Eli Larsen, Broks\u00f8vej 1, Spragelse",
    "sg:city":"Herlufmagle",
    "sg:orig_category":"\u00c3\u2020ldreorganisationer og klubber",
    "sg:phone":"+45 55 50 14 54",
    "sg:postcode":"4160",
    "sg:province":"Danmark",
    "wof:name":"\u00c6ldre Sagen, Sus\u00e5-Holmegaard",
    "wof:placetype":"venue"
},
  "geometry": {"coordinates":[11.7522201538,55.3147735596],"type":"Point"}
}