{
  "type": "Feature",
  "properties": {
    "addr:full":"Industriv\u00e6nget 7 Havdrup Danmark 4622",
    "addr:housenumber":"7",
    "addr:postcode":"4622",
    "addr:street":"Industrivaenget",
    "iso:country":"DK",
    "sg:address":"Industriv\u00e6nget 7",
    "sg:city":"Havdrup",
    "sg:orig_category":"Modelbyggere",
    "sg:phone":"+45 46 18 62 77",
    "sg:postcode":"4622",
    "sg:province":"Danmark",
    "wof:name":"Johannsen Bruno Procesklinik I/S",
    "wof:placetype":"venue"
},
  "geometry": {"coordinates":[12.1216859818,55.5515785217],"type":"Point"}
}