{
  "type": "Feature",
  "properties": {
    "addr:full":"\u00d8stergade 29 Rudk\u00f8bing Danmark 5900",
    "addr:housenumber":"29",
    "addr:postcode":"5900",
    "addr:street":"Ostergade",
    "iso:country":"DK",
    "sg:address":"\u00d8stergade 29",
    "sg:city":"Rudk\u00f8bing",
    "sg:orig_category":"Grillbarer",
    "sg:phone":"+45 62 51 42 20",
    "sg:postcode":"5900",
    "sg:province":"Danmark",
    "wof:name":"Drop Inn Grill & Caf\u00e9",
    "wof:placetype":"venue"
},
  "geometry": {"coordinates":[-114.0767440796,46.4432487488],"type":"Point"}
}