{
  "type": "Feature",
  "properties": {
    "iso:country":"DK",
    "sg:address":"N\u00f8rregade 10 A, Balling",
    "sg:city":"Sp\u00f8ttrup",
    "sg:classifiers":[
        {
            "category":"Banks & Credit Unions",
            "subcategory":"Bank",
            "type":"Services"
        }
    ],
    "sg:phone":"+45 97 56 44 77",
    "sg:postcode":"7860",
    "sg:province":"Danmark",
    "sg:tags":[
        "banker"
    ],
    "wof:name":"Salling Bank, Balling afd.",
    "wof:placetype":"venue"
},
  "geometry": {"coordinates":[8.742859,56.573326],"type":"Point"}
}