{
  "type": "Feature",
  "properties": {
    "addr:full":"Elmevej 10 Dianalund Danmark 4293",
    "addr:housenumber":"10",
    "addr:postcode":"4293",
    "addr:street":"Elmevej",
    "iso:country":"DK",
    "sg:address":"Elmevej 10",
    "sg:city":"Dianalund",
    "sg:orig_category":"Psykologer, praktiserende",
    "sg:phone":"+45 58 26 58 97",
    "sg:postcode":"4293",
    "sg:province":"Danmark",
    "wof:name":"Weber, Gerd",
    "wof:placetype":"venue"
},
  "geometry": {"coordinates":[11.5083732605,55.5261459351],"type":"Point"}
}