{
  "type": "Feature",
  "properties": {
    "addr:full":"Stevnsh\u00f8jvej 99 Store Heddinge Danmark 4660",
    "addr:housenumber":"99",
    "addr:postcode":"4660",
    "addr:street":"Stevnshojvej",
    "iso:country":"DK",
    "sg:address":"Stevnsh\u00f8jvej 99",
    "sg:city":"Store Heddinge",
    "sg:orig_category":"Plejehjem",
    "sg:phone":"+45 56 50 28 22",
    "sg:postcode":"4660",
    "sg:province":"Danmark",
    "wof:name":"\u00c6ldrecentrene og plejeboligerne i Stevns Kommune",
    "wof:placetype":"venue"
},
  "geometry": {"coordinates":[12.3895797729,55.3113174438],"type":"Point"}
}