{
  "type": "Feature",
  "properties": {
    "addr:full":"Skelh\u00f8jsvej 6 Suldrup Danmark 9541",
    "addr:housenumber":"6",
    "addr:postcode":"9541",
    "addr:street":"Skelhojsvej",
    "iso:country":"DK",
    "sg:address":"Skelh\u00f8jsvej 6",
    "sg:city":"Suldrup",
    "sg:orig_category":"Plastvarefabrikker",
    "sg:phone":"+45 98 37 88 33",
    "sg:postcode":"9541",
    "sg:province":"Danmark",
    "sg:website":"www.falutech.dk",
    "wof:name":"Falutech",
    "wof:placetype":"venue"
},
  "geometry": {"coordinates":[9.7005271912,56.8448143005],"type":"Point"}
}