{
  "type": "Feature",
  "properties": {
    "iso:country":"DK",
    "sg:address":"Amagerbrogade 154",
    "sg:city":"K\u00f8benhavn S",
    "sg:orig_category":"Ejendomshandel",
    "sg:phone":"+45 32 84 04 44",
    "sg:postcode":"2300",
    "sg:province":"Danmark",
    "wof:name":"Boligbutikken Home",
    "wof:placetype":"venue"
},
  "geometry": {"coordinates":[-82.5161514282,38.4401397705],"type":"Point"}
}