{
  "type": "Feature",
  "properties": {
    "iso:country":"DK",
    "sg:address":"Nordre Ringvej 57",
    "sg:city":"Glostrup",
    "sg:orig_category":"Blomsterhandlere",
    "sg:phone":"+45 43 63 26 63",
    "sg:postcode":"2600",
    "sg:province":"Danmark",
    "wof:name":"Blomster Kiosken",
    "wof:placetype":"venue"
},
  "geometry": {"coordinates":[12.3923416138,55.6705245972],"type":"Point"}
}