{
  "type": "Feature",
  "properties": {
    "addr:full":"Tordenskjoldsgade 16 Horsens Danmark 8700",
    "addr:housenumber":"16",
    "addr:postcode":"8700",
    "addr:street":"Tordenskjoldsgade",
    "iso:country":"DK",
    "sg:address":"Tordenskjoldsgade 16",
    "sg:city":"Horsens",
    "sg:orig_category":"Malermestre",
    "sg:phone":"+45 75 60 28 82",
    "sg:postcode":"8700",
    "sg:province":"Danmark",
    "wof:name":"Danotto I/S",
    "wof:placetype":"venue"
},
  "geometry": {"coordinates":[9.8391952515,55.8683853149],"type":"Point"}
}