{
  "type": "Feature",
  "properties": {
    "addr:full":"Realskolevej 18 - 20 Bjerringbro Danmark 8850",
    "addr:housenumber":"18 20",
    "addr:postcode":"8850",
    "addr:street":"Realskolevej",
    "iso:country":"DK",
    "sg:address":"Realskolevej 18 - 20",
    "sg:city":"Bjerringbro",
    "sg:orig_category":"Varmeforsyning",
    "sg:phone":"+45 86 68 14 22",
    "sg:postcode":"8850",
    "sg:province":"Danmark",
    "wof:name":"Bjerringbro Varmev\u00e6rk",
    "wof:placetype":"venue"
},
  "geometry": {"coordinates":[9.6554813385,56.3767585754],"type":"Point"}
}