{
  "type": "Feature",
  "properties": {
    "iso:country":"DK",
    "sg:address":"Sct. Mathias Gade 50",
    "sg:city":"Viborg",
    "sg:orig_category":"Ejendomshandel",
    "sg:phone":"+45 86 60 14 90",
    "sg:postcode":"8800",
    "sg:province":"Danmark",
    "wof:name":"Erhverv Viborg",
    "wof:placetype":"venue"
},
  "geometry": {"coordinates":[9.406255722,56.4490623474],"type":"Point"}
}