{
  "type": "Feature",
  "properties": {
    "addr:full":"Holstebrovej 463, Rettrup Sp\u00f8ttrup Danmark 7860",
    "addr:housenumber":"463",
    "addr:postcode":"7860",
    "addr:street":"Holstebrovej;Rettrup Spottrup Danmark",
    "iso:country":"DK",
    "sg:address":"Holstebrovej 463, Rettrup",
    "sg:city":"Sp\u00f8ttrup",
    "sg:orig_category":"Blomsterhandlere",
    "sg:phone":"+45 97 56 61 07",
    "sg:postcode":"7860",
    "sg:province":"Danmark",
    "wof:name":"Lundly, Gartneriet",
    "wof:placetype":"venue"
},
  "geometry": {"coordinates":[8.7428588867,56.5733261108],"type":"Point"}
}