{
  "type": "Feature",
  "properties": {
    "addr:full":"St\u00e6remosen 7 Gilleleje Danmark 3250",
    "addr:housenumber":"7",
    "addr:postcode":"3250",
    "addr:street":"Staeremosen",
    "iso:country":"DK",
    "sg:address":"St\u00e6remosen 7",
    "sg:city":"Gilleleje",
    "sg:orig_category":"Bogtrykkerier",
    "sg:phone":"+45 48 30 03 00",
    "sg:postcode":"3250",
    "sg:province":"Danmark",
    "wof:name":"Nordkystens Bogtrykkeri ApS",
    "wof:placetype":"venue"
},
  "geometry": {"coordinates":[12.3234138489,56.1133842468],"type":"Point"}
}