{
  "type": "Feature",
  "properties": {
    "addr:full":"R\u00f8dtj\u00f8rnevej 3 Sor\u00f8 Danmark 4180",
    "addr:housenumber":"3",
    "addr:postcode":"4180",
    "addr:street":"Rodtjornevej",
    "iso:country":"DK",
    "sg:address":"R\u00f8dtj\u00f8rnevej 3",
    "sg:city":"Sor\u00f8",
    "sg:orig_category":"Murermestre",
    "sg:phone":"+45 57 83 09 11",
    "sg:postcode":"4180",
    "sg:province":"Danmark",
    "wof:name":"Pedersen, Jens",
    "wof:placetype":"venue"
},
  "geometry": {"coordinates":[-102.94467926030001,45.4534721375],"type":"Point"}
}