{
  "type": "Feature",
  "properties": {
    "iso:country":"DK",
    "sg:address":"Roarsvej 20",
    "sg:city":"Frederiksberg",
    "sg:orig_category":"Blikkenslagere",
    "sg:phone":"+45 70 22 32 31",
    "sg:postcode":"2000",
    "sg:province":"Danmark",
    "wof:name":"Firma R\u00f8rBi VVS",
    "wof:placetype":"venue"
},
  "geometry": {"coordinates":[12.535485,55.684696],"type":"Point"}
}