{
  "type": "Feature",
  "properties": {
    "iso:country":"DK",
    "sg:address":"F\u00f8rslevvej",
    "sg:city":"Fuglebjerg",
    "sg:orig_category":"Kirker",
    "sg:postcode":"4250",
    "sg:province":"Danmark",
    "wof:name":"F\u00f8rslev Kirke",
    "wof:placetype":"venue"
},
  "geometry": {"coordinates":[11.5785074234,55.2774810791],"type":"Point"}
}