{
  "type": "Feature",
  "properties": {
    "addr:full":"Tytteb\u00e6rvej 6 Brabrand Danmark 8220",
    "addr:housenumber":"6",
    "addr:postcode":"8220",
    "addr:street":"Tyttebaervej",
    "iso:country":"DK",
    "sg:address":"Tytteb\u00e6rvej 6",
    "sg:city":"Brabrand",
    "sg:orig_category":"Autolakering",
    "sg:phone":"+45 86 26 05 13",
    "sg:postcode":"8220",
    "sg:province":"Danmark",
    "wof:name":"Brabrand Autolakering",
    "wof:placetype":"venue"
},
  "geometry": {"coordinates":[10.1189603806,56.1549453735],"type":"Point"}
}