{
  "type": "Feature",
  "properties": {
    "addr:full":"MAMMEN & DRESCHER, Sundkaj 47, Postboks 813 K\u00f8benhavn \u00d8 Danmark 2100",
    "addr:housenumber":"47;813",
    "addr:postcode":"2100",
    "addr:street":"Sundkaj;Kobenhavn O Danmark",
    "iso:country":"DK",
    "sg:address":"MAMMEN & DRESCHER, Sundkaj 47, Postboks 813",
    "sg:city":"K\u00f8benhavn \u00d8",
    "sg:orig_category":"Spedition",
    "sg:phone":"+45 39 27 41 41",
    "sg:postcode":"2100",
    "sg:province":"Danmark",
    "sg:website":"www.pakhus47.dk",
    "wof:name":"STS DANMARK A/S",
    "wof:placetype":"venue"
},
  "geometry": {"coordinates":[-96.2919006348,42.851398468],"type":"Point"}
}