{
  "type": "Feature",
  "properties": {
    "iso:country":"DK",
    "sg:address":"Vestergade 9 ",
    "sg:city":"Silkeborg",
    "sg:classifiers":[
        {
            "category":"Wholesale",
            "subcategory":"Medical Equipment & Supplies",
            "type":"Manufacturing & Wholesale Goods"
        }
    ],
    "sg:phone":"+45 86 82 83 33",
    "sg:postcode":"8600",
    "sg:province":"Danmark",
    "sg:tags":[
        "-",
        "health",
        "instrument"
    ],
    "wof:name":"PRAKTISERENDE TANDL\u00c6GERS LABORATORIER A/S",
    "wof:placetype":"venue"
},
  "geometry": {"coordinates":[9.548125267,56.1687355042],"type":"Point"}
}