{
  "type": "Feature",
  "properties": {
    "addr:full":"Fmd.: Hans J\u00f8rgen Hansen, Bl\u00e5kildeparken 19 Arden Danmark 9510",
    "addr:housenumber":"19",
    "addr:postcode":"9510",
    "addr:street":"Blaakildeparken",
    "iso:country":"DK",
    "sg:address":"Fmd.: Hans J\u00f8rgen Hansen, Bl\u00e5kildeparken 19",
    "sg:city":"Arden",
    "sg:orig_category":"\u00c3\u2020ldreorganisationer og klubber",
    "sg:phone":"+45 98 56 14 38",
    "sg:postcode":"9510",
    "sg:province":"Danmark",
    "wof:name":"Arden Pensionistforening",
    "wof:placetype":"venue"
},
  "geometry": {"coordinates":[9.8580989838,56.7683296204],"type":"Point"}
}