{
  "type": "Feature",
  "properties": {
    "iso:country":"DK",
    "sg:address":"Glarmestervej 8",
    "sg:city":"Svendborg",
    "sg:orig_category":"Kirkelige foreninger",
    "sg:phone":"+45 63 21 03 26",
    "sg:postcode":"5700",
    "sg:province":"Danmark",
    "sg:website":"www.fredenskirke.dk",
    "wof:name":"Fredens Sognehus/kirkekontor",
    "wof:placetype":"venue"
},
  "geometry": {"coordinates":[10.6290597916,55.0668258667],"type":"Point"}
}