{
  "type": "Feature",
  "properties": {
    "addr:full":"Prinsessegade 35 Fredericia Danmark 7000",
    "addr:housenumber":"35",
    "addr:postcode":"7000",
    "addr:street":"Prinsessegade",
    "iso:country":"DK",
    "sg:address":"Prinsessegade 35",
    "sg:city":"Fredericia",
    "sg:orig_category":"Gaveartikler",
    "sg:phone":"+45 75 92 38 61",
    "sg:postcode":"7000",
    "sg:province":"Danmark",
    "wof:name":"TK-Shopping Import og Eksport",
    "wof:placetype":"venue"
},
  "geometry": {"coordinates":[9.757818222,55.5663795471],"type":"Point"}
}