{
  "type": "Feature",
  "properties": {
    "addr:full":"Hostrupvej 21 Stenstrup Danmark 5771",
    "addr:housenumber":"21",
    "addr:postcode":"5771",
    "addr:street":"Hostrupvej",
    "iso:country":"DK",
    "sg:address":"Hostrupvej 21",
    "sg:city":"Stenstrup",
    "sg:orig_category":"Zoneterapeuter",
    "sg:phone":"+45 62 26 24 62",
    "sg:postcode":"5771",
    "sg:province":"Danmark",
    "wof:name":"Hansen, Arne",
    "wof:placetype":"venue"
},
  "geometry": {"coordinates":[10.5036716461,55.1303596497],"type":"Point"}
}