{
  "type": "Feature",
  "properties": {
    "addr:full":"Cort Adelers Gade 4 K\u00f8benhavn Danmark 1053",
    "addr:housenumber":"4",
    "addr:postcode":"1053",
    "addr:street":"Cort Adelers Gade",
    "iso:country":"DK",
    "sg:address":"Cort Adelers Gade 4",
    "sg:city":"K\u00f8benhavn",
    "sg:orig_category":"Plakater",
    "sg:phone":"+45 33 36 07 27",
    "sg:postcode":"1053",
    "sg:province":"Danmark",
    "sg:website":"www.posters-records.com",
    "wof:name":"Posters & Records",
    "wof:placetype":"venue"
},
  "geometry": {"coordinates":[12.5907297134,55.6780586243],"type":"Point"}
}