{
  "type": "Feature",
  "properties": {
    "addr:full":"Overgade 6 A Svendborg Danmark 5700",
    "addr:housenumber":"6 a",
    "addr:postcode":"5700",
    "addr:street":"Overgade",
    "iso:country":"DK",
    "sg:address":"Overgade 6 A",
    "sg:city":"Svendborg",
    "sg:orig_category":"Arbejdsmarkedsuddannelser",
    "sg:phone":"+45 62 21 04 84",
    "sg:postcode":"5700",
    "sg:province":"Danmark",
    "sg:website":"www.svesoef.dk",
    "wof:name":"Svendborg S\u00f8fartsskole",
    "wof:placetype":"venue"
},
  "geometry": {"coordinates":[10.6161632538,55.0652885437],"type":"Point"}
}