{
  "type": "Feature",
  "properties": {
    "iso:country":"DK",
    "sg:address":"Rullesten, Steng\u00e5rds Plads 2",
    "sg:city":"\u00d8lstykke",
    "sg:orig_category":"Skolefritidsordninger",
    "sg:phone":"+45 47 17 74 45",
    "sg:postcode":"3650",
    "sg:province":"Danmark",
    "wof:name":"Skolefritidsordning Steng\u00e5rden",
    "wof:placetype":"venue"
},
  "geometry": {"coordinates":[-68.9096984863,-37.3805999756],"type":"Point"}
}