{
  "type": "Feature",
  "properties": {
    "addr:full":"Sct. Laurentii Vej 66 A Skagen Danmark 9990",
    "addr:housenumber":"66 a",
    "addr:postcode":"9990",
    "addr:street":"Sct. Laurentii Vej",
    "iso:country":"DK",
    "sg:address":"Sct. Laurentii Vej 66 A",
    "sg:city":"Skagen",
    "sg:orig_category":"Ejendomshandel",
    "sg:phone":"+45 98 44 26 66",
    "sg:postcode":"9990",
    "sg:province":"Danmark",
    "sg:website":"www.home.dk",
    "wof:name":"Freddy,Skagen Ejendomshandel Nielsen",
    "wof:placetype":"venue"
},
  "geometry": {"coordinates":[10.5858049393,57.7213516235],"type":"Point"}
}