{
  "type": "Feature",
  "properties": {
    "iso:country":"DK",
    "sg:address":"Barfredsvej 87 ",
    "sg:city":"Frederikshavn",
    "sg:classifiers":[
        {
            "category":"Manufacturing",
            "subcategory":"Lumber",
            "type":"Manufacturing & Wholesale Goods"
        }
    ],
    "sg:phone":"+45 98 42 13 44",
    "sg:postcode":"9900",
    "sg:province":"Danmark",
    "sg:tags":[
        "wood"
    ],
    "wof:name":"JOHANNES JOHANSEN TR\u00c6LASTHANDEL A/S",
    "wof:placetype":"venue"
},
  "geometry": {"coordinates":[10.5346870422,57.447593689],"type":"Point"}
}