{
  "type": "Feature",
  "properties": {
    "addr:full":"Leer-Ager 4, Blistrup Gr\u00e6sted Danmark 3230",
    "addr:housenumber":"4",
    "addr:postcode":"3230",
    "addr:street":"Leer-Ager",
    "iso:country":"DK",
    "sg:address":"Leer-Ager 4, Blistrup",
    "sg:city":"Gr\u00e6sted",
    "sg:orig_category":"Oliefyr og service",
    "sg:phone":"+45 48 71 71 49",
    "sg:postcode":"3230",
    "sg:province":"Danmark",
    "wof:name":"H.P. Oliefyrservice",
    "wof:placetype":"venue"
},
  "geometry": {"coordinates":[12.3426475525,56.048500061],"type":"Point"}
}