{
  "type": "Feature",
  "properties": {
    "addr:full":"Gisselfeld All\u00e9 7 Gentofte Danmark 2820",
    "addr:housenumber":"7",
    "addr:postcode":"2820",
    "addr:street":"Gisselfeld Alle\u0301",
    "iso:country":"DK",
    "sg:address":"Gisselfeld All\u00e9 7",
    "sg:city":"Gentofte",
    "sg:orig_category":"Psykologer, praktiserende",
    "sg:phone":"+45 39 68 14 99",
    "sg:postcode":"2820",
    "sg:province":"Danmark",
    "wof:name":"S\u00f8rensen, Henrik",
    "wof:placetype":"venue"
},
  "geometry": {"coordinates":[12.551112175,55.7417106628],"type":"Point"}
}