{
  "type": "Feature",
  "properties": {
    "addr:full":"Toldbodgade 4 Thisted Danmark 7700",
    "addr:housenumber":"4",
    "addr:postcode":"7700",
    "addr:street":"Toldbodgade",
    "iso:country":"DK",
    "sg:address":"Toldbodgade 4",
    "sg:city":"Thisted",
    "sg:orig_category":"Advokater",
    "sg:phone":"+45 97 92 33 33",
    "sg:postcode":"7700",
    "sg:province":"Danmark",
    "wof:name":"Funch, Mogens/Kjeld Olesen & Peter S\u00f8rensen",
    "wof:placetype":"venue"
},
  "geometry": {"coordinates":[8.691649437,56.9539375305],"type":"Point"}
}