{
  "type": "Feature",
  "properties": {
    "addr:full":"Vestergade 11 Herning Danmark 7400",
    "addr:housenumber":"11",
    "addr:postcode":"7400",
    "addr:street":"Vestergade",
    "iso:country":"DK",
    "sg:address":"Vestergade 11",
    "sg:city":"Herning",
    "sg:orig_category":"Farve og tapet",
    "sg:phone":"+45 97 12 20 45",
    "sg:postcode":"7400",
    "sg:province":"Danmark",
    "wof:name":"Fl\u00fcgger farver",
    "wof:placetype":"venue"
},
  "geometry": {"coordinates":[8.9656143188,56.1361999512],"type":"Point"}
}