{
  "type": "Feature",
  "properties": {
    "addr:full":"Fmd.: Behrend Wind, Dyndeb\u00e6ksvej 4 \u00c6r\u00f8sk\u00f8bing Danmark 5970",
    "addr:housenumber":"4",
    "addr:postcode":"5970",
    "addr:street":"Dyndebaeksvej",
    "iso:country":"DK",
    "sg:address":"Fmd.: Behrend Wind, Dyndeb\u00e6ksvej 4",
    "sg:city":"\u00c6r\u00f8sk\u00f8bing",
    "sg:orig_category":"Hobbybetonede foreninger",
    "sg:phone":"+45 23 42 42 84",
    "sg:postcode":"5970",
    "sg:province":"Danmark",
    "wof:name":"Skakklubben Springeren",
    "wof:placetype":"venue"
},
  "geometry": {"coordinates":[-114.0767440796,46.4432487488],"type":"Point"}
}