{
  "type": "Feature",
  "properties": {
    "addr:full":"Springvandspladsen 6, Als Hadsund Danmark 9560",
    "addr:housenumber":"6",
    "addr:postcode":"9560",
    "addr:street":"Springvandspladsen;Als",
    "iso:country":"DK",
    "sg:address":"Springvandspladsen 6, Als",
    "sg:city":"Hadsund",
    "sg:orig_category":"Murermestre",
    "sg:phone":"+45 98 58 16 35",
    "sg:postcode":"9560",
    "sg:province":"Danmark",
    "wof:name":"Th\u00f8gersen ApS, Finn L.",
    "wof:placetype":"venue"
},
  "geometry": {"coordinates":[10.115904808,56.7150764465],"type":"Point"}
}