{
  "type": "Feature",
  "properties": {
    "addr:full":"Lyngby Torv 6 Kongens Lyngby Danmark 2800",
    "addr:housenumber":"6",
    "addr:postcode":"2800",
    "addr:street":"Lyngby Torv",
    "iso:country":"DK",
    "sg:address":"Lyngby Torv 6",
    "sg:city":"Kongens Lyngby",
    "sg:orig_category":"Rejsebureauer",
    "sg:phone":"+45 45 88 78 88",
    "sg:postcode":"2800",
    "sg:province":"Danmark",
    "sg:website":"www.kilroytravels.dk",
    "wof:name":"Kilroy travels Denmark A/S",
    "wof:placetype":"venue"
},
  "geometry": {"coordinates":[12.5031375885,55.7701683044],"type":"Point"}
}