{
  "type": "Feature",
  "properties": {
    "addr:full":"Vinkelvej 28 Hobro Danmark 9500",
    "addr:housenumber":"28",
    "addr:postcode":"9500",
    "addr:street":"Vinkelvej",
    "iso:country":"DK",
    "sg:address":"Vinkelvej 28",
    "sg:city":"Hobro",
    "sg:orig_category":"Stoffer",
    "sg:phone":"+45 98 51 02 11",
    "sg:postcode":"9500",
    "sg:province":"Danmark",
    "wof:name":"Margit, Boutique",
    "wof:placetype":"venue"
},
  "geometry": {"coordinates":[9.7950296402,56.6462440491],"type":"Point"}
}