{
  "type": "Feature",
  "properties": {
    "addr:full":"Dansk Bank Kommunikation, Holmens Kanal 2-12 K\u00f8benhavn Danmark 1060",
    "addr:housenumber":"2-12",
    "addr:postcode":"1060",
    "addr:street":"Holmens Kanal",
    "iso:country":"DK",
    "sg:address":"Dansk Bank Kommunikation, Holmens Kanal 2-12",
    "sg:city":"K\u00f8benhavn",
    "sg:orig_category":"Forsikringer",
    "sg:phone":"+45 45 23 23 23",
    "sg:postcode":"1060",
    "sg:province":"Danmark",
    "sg:website":"www.danskebank.dk/danica",
    "wof:name":"Danica Pension",
    "wof:placetype":"venue"
},
  "geometry": {"coordinates":[12.5861501694,55.6783103943],"type":"Point"}
}