{
  "type": "Feature",
  "properties": {
    "addr:full":"Lille Algade 5 Nibe Danmark 9240",
    "addr:housenumber":"5",
    "addr:postcode":"9240",
    "addr:street":"Lille Algade",
    "iso:country":"DK",
    "sg:address":"Lille Algade 5",
    "sg:city":"Nibe",
    "sg:orig_category":"Cykler",
    "sg:phone":"+45 98 35 20 55",
    "sg:postcode":"9240",
    "sg:province":"Danmark",
    "wof:name":"Nibe Cykel- & Bilistbutik",
    "wof:placetype":"venue"
},
  "geometry": {"coordinates":[9.6356449127,56.9826316833],"type":"Point"}
}