{
  "type": "Feature",
  "properties": {
    "addr:full":"Nyvej 10 Sk\u00e6lsk\u00f8r Danmark 4230",
    "addr:housenumber":"10",
    "addr:postcode":"4230",
    "addr:street":"Nyvej",
    "iso:country":"DK",
    "sg:address":"Nyvej 10",
    "sg:city":"Sk\u00e6lsk\u00f8r",
    "sg:orig_category":"Stenhuggere",
    "sg:phone":"+45 58 19 41 42",
    "sg:postcode":"4230",
    "sg:province":"Danmark",
    "wof:name":"Sk\u00e6lsk\u00f8r Monumentforretning & Stenhuggeri",
    "wof:placetype":"venue"
},
  "geometry": {"coordinates":[11.1915035248,55.2119750977],"type":"Point"}
}