{
  "type": "Feature",
  "properties": {
    "addr:full":"Sj\u00e6llandsvej 12 A Frederikshavn Danmark 9900",
    "addr:housenumber":"12 a",
    "addr:postcode":"9900",
    "addr:street":"Sjaellandsvej",
    "iso:country":"DK",
    "sg:address":"Sj\u00e6llandsvej 12 A",
    "sg:city":"Frederikshavn",
    "sg:orig_category":"Genbrugscentre",
    "sg:postcode":"9900",
    "sg:province":"Danmark",
    "wof:name":"Genbrugspladsen",
    "wof:placetype":"venue"
},
  "geometry": {"coordinates":[10.5089406967,57.4299125671],"type":"Point"}
}