{
  "type": "Feature",
  "properties": {
    "iso:country":"DK",
    "sg:address":"Sneb\u00e6rvej 33, Mou",
    "sg:city":"Storvorde",
    "sg:orig_category":"Gulvafslibning",
    "sg:phone":"+45 98 31 16 94",
    "sg:postcode":"9280",
    "sg:province":"Danmark",
    "wof:name":"Stensholt Gulvservice",
    "wof:placetype":"venue"
},
  "geometry": {"coordinates":[10.1014204025,57.0045547485],"type":"Point"}
}