{
  "type": "Feature",
  "properties": {
    "addr:full":"Fmd.: B\u00f8rge Gr\u00f8n-Iversen, H\u00f8vedstensvej 24 Hvidovre Danmark 2650",
    "addr:housenumber":"24",
    "addr:postcode":"2650",
    "addr:street":"Hovedstensvej",
    "iso:country":"DK",
    "sg:address":"Fmd.: B\u00f8rge Gr\u00f8n-Iversen, H\u00f8vedstensvej 24",
    "sg:city":"Hvidovre",
    "sg:orig_category":"Kirkelige foreninger",
    "sg:phone":"+45 36 78 73 60",
    "sg:postcode":"2650",
    "sg:province":"Danmark",
    "sg:website":"www.risbjergkirke.dk",
    "wof:name":"Risbjerg Hverdagskirke",
    "wof:placetype":"venue"
},
  "geometry": {"coordinates":[12.474360466,55.6366386414],"type":"Point"}
}