{
  "type": "Feature",
  "properties": {
    "iso:country":"DK",
    "sg:address":"Gammel Kirkevej 9",
    "sg:city":"St\u00f8vring",
    "sg:orig_category":"Betonvarefabrikker",
    "sg:phone":"+45 97 34 12 44",
    "sg:postcode":"9530",
    "sg:province":"Danmark",
    "wof:name":"Skagen Beton St\u00f8vring",
    "wof:placetype":"venue"
},
  "geometry": {"coordinates":[-103.398506,34.3909],"type":"Point"}
}