{
  "type": "Feature",
  "properties": {
    "iso:country":"DK",
    "sg:address":"Fmd.: Hans Lassen, Kirseb\u00e6rvej 71",
    "sg:city":"Vejen",
    "sg:orig_category":"Hobbybetonede foreninger",
    "sg:phone":"+45 75 36 05 60",
    "sg:postcode":"6600",
    "sg:province":"Danmark",
    "wof:name":"Vejen og Omegns Frim\u00e6rkeklub",
    "wof:placetype":"venue"
},
  "geometry": {"coordinates":[9.1396121979,55.4778175354],"type":"Point"}
}