{
  "type": "Feature",
  "properties": {
    "addr:full":"\u00d8stervoldgade 85 Nyborg Danmark 5800",
    "addr:housenumber":"85",
    "addr:postcode":"5800",
    "addr:street":"Ostervoldgade",
    "iso:country":"DK",
    "sg:address":"\u00d8stervoldgade 85",
    "sg:city":"Nyborg",
    "sg:orig_category":"Faglige organisationer og foreninger",
    "sg:phone":"+45 65 31 05 38",
    "sg:postcode":"5800",
    "sg:province":"Danmark",
    "wof:name":"SID Nyborg/\u00d8rb\u00e6k",
    "wof:placetype":"venue"
},
  "geometry": {"coordinates":[10.7952785492,55.3105697632],"type":"Point"}
}