{
  "type": "Feature",
  "properties": {
    "addr:full":"Holsted Park 29 N\u00e6stved Danmark 4700",
    "addr:housenumber":"29",
    "addr:postcode":"4700",
    "addr:street":"Holsted Park",
    "iso:country":"DK",
    "sg:address":"Holsted Park 29",
    "sg:city":"N\u00e6stved",
    "sg:orig_category":"Faglige organisationer og foreninger",
    "sg:phone":"+45 55 75 09 19",
    "sg:postcode":"4700",
    "sg:province":"Danmark",
    "wof:name":"Murernes Fagforening Sydsj\u00e6lland Afdeling",
    "wof:placetype":"venue"
},
  "geometry": {"coordinates":[11.7737617493,55.2490844727],"type":"Point"}
}