{
  "type": "Feature",
  "properties": {
    "addr:full":"v/ Nels Bechmann, M\u00f8llebr\u00f8ndstr\u00e6de 12 Stege Danmark 4780",
    "addr:housenumber":"12",
    "addr:postcode":"4780",
    "addr:street":"Mollebrondstraede",
    "iso:country":"DK",
    "sg:address":"v/ Nels Bechmann, M\u00f8llebr\u00f8ndstr\u00e6de 12",
    "sg:city":"Stege",
    "sg:orig_category":"Ungdomsklubber",
    "sg:phone":"+45 55 81 13 07",
    "sg:postcode":"4780",
    "sg:province":"Danmark",
    "wof:name":"Klub 15, Klub Musuk",
    "wof:placetype":"venue"
},
  "geometry": {"coordinates":[12.2875270844,54.9855155945],"type":"Point"}
}