{
  "type": "Feature",
  "properties": {
    "iso:country":"DK",
    "sg:address":"Elsenbakken 7",
    "sg:city":"Frederikssund",
    "sg:orig_category":"Kontorartikler",
    "sg:phone":"+45 47 31 54 84",
    "sg:postcode":"3600",
    "sg:province":"Danmark",
    "wof:name":"J.H. Produktion",
    "wof:placetype":"venue"
},
  "geometry": {"coordinates":[12.065486908,55.8497314453],"type":"Point"}
}