{
  "type": "Feature",
  "properties": {
    "iso:country":"DK",
    "sg:address":"Industrivej 4",
    "sg:city":"Roskilde",
    "sg:orig_category":"Gearmotorer",
    "sg:phone":"+45 46 77 70 00",
    "sg:postcode":"4000",
    "sg:province":"Danmark",
    "sg:website":"www.regal.dk",
    "wof:name":"REGAL A/S",
    "wof:placetype":"venue"
},
  "geometry": {"coordinates":[12.1122655869,55.6436882019],"type":"Point"}
}