{
  "type": "Feature",
  "properties": {
    "iso:country":"DK",
    "sg:address":"Fmd.: Susan Vang, Markgade 1",
    "sg:city":"T\u00f8nder",
    "sg:orig_category":"Kulturelle foreninger",
    "sg:phone":"+45 74 72 45 88",
    "sg:postcode":"6270",
    "sg:province":"Danmark",
    "wof:name":"T\u00f8nder Amat\u00f8rscene",
    "wof:placetype":"venue"
},
  "geometry": {"coordinates":[-98.13571929930001,48.9056892395],"type":"Point"}
}