{
  "type": "Feature",
  "properties": {
    "addr:full":"Fmd.: Ren\u00e9 Leen, Byenden 1 B, Sigerslev Store Heddinge Danmark 4660",
    "addr:housenumber":"1 b",
    "addr:postcode":"4660",
    "addr:street":"Leen Byenden;Sigerslev",
    "iso:country":"DK",
    "sg:address":"Fmd.: Ren\u00e9 Leen, Byenden 1 B, Sigerslev",
    "sg:city":"Store Heddinge",
    "sg:orig_category":"Grundejerforeninger",
    "sg:phone":"+45 56 50 36 06",
    "sg:postcode":"4660",
    "sg:province":"Danmark",
    "wof:name":"Sigerslev Grundejerforening",
    "wof:placetype":"venue"
},
  "geometry": {"coordinates":[12.3895797729,55.3113174438],"type":"Point"}
}