{
  "type": "Feature",
  "properties": {
    "addr:full":"Falkoner Alle 10 Frederiksberg Danmark 2000",
    "addr:housenumber":"10",
    "addr:postcode":"2000",
    "addr:street":"Falkoner Alle",
    "iso:country":"DK",
    "sg:address":"Falkoner Alle 10",
    "sg:city":"Frederiksberg",
    "sg:classifiers":[
        {
            "category":"Restaurant",
            "type":"Food & Drink"
        }
    ],
    "sg:phone":"+45 33 24 95 76",
    "sg:postcode":"2000",
    "sg:province":"Danmark",
    "wof:name":"San Marco, Restaurant",
    "wof:placetype":"venue"
},
  "geometry": {"coordinates":[12.533823967,55.6792984009],"type":"Point"}
}