{
  "type": "Feature",
  "properties": {
    "iso:country":"DK",
    "sg:address":"Bransagervej 30, Postboks 47",
    "sg:city":"Pandrup",
    "sg:classifiers":[
        {
            "category":"Communications",
            "type":"Services"
        }
    ],
    "sg:phone":"+45 96 73 04 00",
    "sg:postcode":"9490",
    "sg:province":"Danmark",
    "sg:tags":[
        "radio-",
        "og",
        "tv-stationer"
    ],
    "wof:name":"Radio 2 Nordjylland - 105,8",
    "wof:placetype":"venue"
},
  "geometry": {"coordinates":[9.6769151688,57.223815918],"type":"Point"}
}