{
  "type": "Feature",
  "properties": {
    "addr:full":"Lerbjergvej 15 Ballerup Danmark 2750",
    "addr:housenumber":"15",
    "addr:postcode":"2750",
    "addr:street":"Lerbjergvej",
    "iso:country":"DK",
    "sg:address":"Lerbjergvej 15",
    "sg:city":"Ballerup",
    "sg:orig_category":"Psykoterapi",
    "sg:phone":"+45 44 68 00 47",
    "sg:postcode":"2750",
    "sg:province":"Danmark",
    "wof:name":"Bruun, Inge",
    "wof:placetype":"venue"
},
  "geometry": {"coordinates":[12.3704681396,55.7297668457],"type":"Point"}
}