{
  "type": "Feature",
  "properties": {
    "addr:full":"Frydsvej 32 Horsens Danmark 8700",
    "addr:housenumber":"32",
    "addr:postcode":"8700",
    "addr:street":"Frydsvej",
    "iso:country":"DK",
    "sg:address":"Frydsvej 32",
    "sg:city":"Horsens",
    "sg:orig_category":"Energikonsulenter",
    "sg:phone":"+45 75 62 25 37",
    "sg:postcode":"8700",
    "sg:province":"Danmark",
    "wof:name":"Clorius",
    "wof:placetype":"venue"
},
  "geometry": {"coordinates":[9.8710565567,55.8675613403],"type":"Point"}
}