{
  "type": "Feature",
  "properties": {
    "iso:country":"DK",
    "sg:address":"Falen 29",
    "sg:city":"Odense C",
    "sg:orig_category":"Kirkelige foreninger",
    "sg:phone":"+45 66 12 33 96",
    "sg:postcode":"5000",
    "sg:province":"Danmark",
    "wof:name":"Dansk Kirkeskoleudvalg af 1946",
    "wof:placetype":"venue"
},
  "geometry": {"coordinates":[10.373295784,55.3921394348],"type":"Point"}
}