{
  "type": "Feature",
  "properties": {
    "addr:full":"\u00d8stergade 11 Aabybro Danmark 9440",
    "addr:housenumber":"11",
    "addr:postcode":"9440",
    "addr:street":"Ostergade",
    "iso:country":"DK",
    "sg:address":"\u00d8stergade 11",
    "sg:city":"Aabybro",
    "sg:orig_category":"Farve og tapet",
    "sg:phone":"+45 98 24 11 73",
    "sg:postcode":"9440",
    "sg:province":"Danmark",
    "wof:name":"Farvehandleren",
    "wof:placetype":"venue"
},
  "geometry": {"coordinates":[9.7307224274,57.1618041992],"type":"Point"}
}