{
  "type": "Feature",
  "properties": {
    "addr:full":"S\u00f8ndergade 19 Stoholm Danmark 7850",
    "addr:housenumber":"19",
    "addr:postcode":"7850",
    "addr:street":"Sondergade",
    "iso:country":"DK",
    "sg:address":"S\u00f8ndergade 19",
    "sg:city":"Stoholm",
    "sg:orig_category":"\u00c3\u2020ldrecentre",
    "sg:phone":"+45 97 54 18 22",
    "sg:postcode":"7850",
    "sg:province":"Danmark",
    "wof:name":"Birkegaarden \u00c6ldrecenter Midt",
    "wof:placetype":"venue"
},
  "geometry": {"coordinates":[9.1507024765,56.4836997986],"type":"Point"}
}