{
  "type": "Feature",
  "properties": {
    "addr:full":"Engparken 23 Hadsten Danmark 8370",
    "addr:housenumber":"23",
    "addr:postcode":"8370",
    "addr:street":"Engparken",
    "iso:country":"DK",
    "sg:address":"Engparken 23",
    "sg:city":"Hadsten",
    "sg:orig_category":"Musikere",
    "sg:phone":"+45 86 98 13 88",
    "sg:postcode":"8370",
    "sg:province":"Danmark",
    "wof:name":"Skov, Lars Ginge",
    "wof:placetype":"venue"
},
  "geometry": {"coordinates":[10.0355348587,56.3275146484],"type":"Point"}
}