{
  "type": "Feature",
  "properties": {
    "addr:full":"Klostervej 35, Grindersl. Kl. Roslev Danmark 7870",
    "addr:housenumber":"35",
    "addr:postcode":"7870",
    "addr:street":"Klostervej;Kl.",
    "iso:country":"DK",
    "sg:address":"Klostervej 35, Grindersl. Kl.",
    "sg:city":"Roslev",
    "sg:orig_category":"Kirker",
    "sg:postcode":"7870",
    "sg:province":"Danmark",
    "wof:name":"Grinderslev Kirke",
    "wof:placetype":"venue"
},
  "geometry": {"coordinates":[8.8715353012,56.7570304871],"type":"Point"}
}