{
  "type": "Feature",
  "properties": {
    "addr:full":"Stjernedalen 1, Fl\u00f8ng Hedehusene Danmark 2640",
    "addr:housenumber":"1",
    "addr:postcode":"2640",
    "addr:street":"Stjernedalen;Flong",
    "iso:country":"DK",
    "sg:address":"Stjernedalen 1, Fl\u00f8ng",
    "sg:city":"Hedehusene",
    "sg:orig_category":"Designere",
    "sg:phone":"+45 46 59 09 46",
    "sg:postcode":"2640",
    "sg:province":"Danmark",
    "wof:name":"Art Studio",
    "wof:placetype":"venue"
},
  "geometry": {"coordinates":[12.1993551254,55.6496009827],"type":"Point"}
}