{
  "type": "Feature",
  "properties": {
    "addr:full":"Lufthavnsvej 31 Billund Danmark 7190",
    "addr:housenumber":"31",
    "addr:postcode":"7190",
    "addr:street":"Lufthavnsvej",
    "iso:country":"DK",
    "sg:address":"Lufthavnsvej 31",
    "sg:city":"Billund",
    "sg:orig_category":"Reklame",
    "sg:phone":"+45 75 35 30 22",
    "sg:postcode":"7190",
    "sg:province":"Danmark",
    "wof:name":"Air Media",
    "wof:placetype":"venue"
},
  "geometry": {"coordinates":[9.1361255646,55.7485198975],"type":"Point"}
}