{
  "type": "Feature",
  "properties": {
    "iso:country":"DK",
    "sg:address":"Fanefjord Kirkevej 11, St. Damme",
    "sg:city":"Askeby",
    "sg:orig_category":"\u00c3\u02dcvrige skoler",
    "sg:phone":"+45 55 82 61 30",
    "sg:postcode":"4792",
    "sg:province":"Danmark",
    "wof:name":"Teaterbygningen Fanefjord, PMU-M\u00f8n",
    "wof:placetype":"venue"
},
  "geometry": {"coordinates":[12.1452455521,54.8838500977],"type":"Point"}
}