{
  "type": "Feature",
  "properties": {
    "addr:full":"Storegade 78 a Stege Danmark 4780",
    "addr:housenumber":"78 a",
    "addr:postcode":"4780",
    "addr:street":"Storegade",
    "iso:country":"DK",
    "sg:address":"Storegade 78 a",
    "sg:city":"Stege",
    "sg:orig_category":"Revisorer",
    "sg:phone":"+45 55 81 09 26",
    "sg:postcode":"4780",
    "sg:province":"Danmark",
    "wof:name":"Kirkegaard Revision I/S",
    "wof:placetype":"venue"
},
  "geometry": {"coordinates":[12.2886638641,54.9863624573],"type":"Point"}
}