{
  "type": "Feature",
  "properties": {
    "addr:full":"Vestergade 43 Horsens Danmark 8700",
    "addr:housenumber":"43",
    "addr:postcode":"8700",
    "addr:street":"Vestergade",
    "iso:country":"DK",
    "sg:address":"Vestergade 43",
    "sg:city":"Horsens",
    "sg:orig_category":"Kiosker",
    "sg:phone":"+45 75 62 58 62",
    "sg:postcode":"8700",
    "sg:province":"Danmark",
    "wof:name":"Vestergades Kiosk",
    "wof:placetype":"venue"
},
  "geometry": {"coordinates":[9.8398132324,55.8702087402],"type":"Point"}
}