{
  "type": "Feature",
  "properties": {
    "addr:full":"Fmd.: Thorkild Hedegaard Jensen, N\u00f8rre\u00e5vej 12, Vejrum Tjele Danmark 8830",
    "addr:housenumber":"12",
    "addr:postcode":"8830",
    "addr:street":"Norreaavej;Vejrum",
    "iso:country":"DK",
    "sg:address":"Fmd.: Thorkild Hedegaard Jensen, N\u00f8rre\u00e5vej 12, Vejrum",
    "sg:city":"Tjele",
    "sg:orig_category":"Soldaterforeninger",
    "sg:phone":"+45 86 65 42 16",
    "sg:postcode":"8830",
    "sg:province":"Danmark",
    "wof:name":"Garderhusarforeningen Jylland",
    "wof:placetype":"venue"
},
  "geometry": {"coordinates":[9.6264801025,56.4818611145],"type":"Point"}
}