{
  "type": "Feature",
  "properties": {
    "addr:full":"Villavej 6 Roskilde Danmark 4000",
    "addr:housenumber":"6",
    "addr:postcode":"4000",
    "addr:street":"Villavej",
    "iso:country":"DK",
    "sg:address":"Villavej 6",
    "sg:city":"Roskilde",
    "sg:orig_category":"Musik- og sangundervisning",
    "sg:phone":"+45 46 32 40 61",
    "sg:postcode":"4000",
    "sg:province":"Danmark",
    "wof:name":"Troensegaard, Elisabeth",
    "wof:placetype":"venue"
},
  "geometry": {"coordinates":[12.0754041672,55.642288208],"type":"Point"}
}