{
  "type": "Feature",
  "properties": {
    "addr:full":"Sj\u00e6llandsgade 42 Vejle Danmark 7100",
    "addr:housenumber":"42",
    "addr:postcode":"7100",
    "addr:street":"Sjaellandsgade",
    "iso:country":"DK",
    "sg:address":"Sj\u00e6llandsgade 42",
    "sg:city":"Vejle",
    "sg:orig_category":"Murermestre",
    "sg:phone":"+45 75 82 05 00",
    "sg:postcode":"7100",
    "sg:province":"Danmark",
    "wof:name":"Murernes Aktieselskab Vejle",
    "wof:placetype":"venue"
},
  "geometry": {"coordinates":[9.5448455811,55.7039299011],"type":"Point"}
}