{
  "type": "Feature",
  "properties": {
    "addr:full":"Vestergade 11 Sindal Danmark 9870",
    "addr:housenumber":"11",
    "addr:postcode":"9870",
    "addr:street":"Vestergade",
    "iso:country":"DK",
    "sg:address":"Vestergade 11",
    "sg:city":"Sindal",
    "sg:orig_category":"Supermarkeder",
    "sg:postcode":"9870",
    "sg:province":"Danmark",
    "wof:name":"Fakta",
    "wof:placetype":"venue"
},
  "geometry": {"coordinates":[10.2001924515,57.4706115723],"type":"Point"}
}