{
  "type": "Feature",
  "properties": {
    "addr:full":"Kj\u00e6rg\u00e5rdsvej 34, Hunderup Bramming Danmark 6740",
    "addr:housenumber":"34",
    "addr:postcode":"6740",
    "addr:street":"Kjaergaardsvej",
    "iso:country":"DK",
    "sg:address":"Kj\u00e6rg\u00e5rdsvej 34, Hunderup",
    "sg:city":"Bramming",
    "sg:orig_category":"Brugsforeninger",
    "sg:phone":"+45 75 17 35 01",
    "sg:postcode":"6740",
    "sg:province":"Danmark",
    "wof:name":"Lokal Brugsen Hunderup",
    "wof:placetype":"venue"
},
  "geometry": {"coordinates":[8.6974096298,55.4655303955],"type":"Point"}
}