{
  "type": "Feature",
  "properties": {
    "addr:full":"Kontraministerialbogf\u00f8rer: Mary Madsen, Fredensvej 20 Brovst Danmark 9460",
    "addr:housenumber":"20",
    "addr:postcode":"9460",
    "addr:street":"Fredensvej",
    "iso:country":"DK",
    "sg:address":"Kontraministerialbogf\u00f8rer: Mary Madsen, Fredensvej 20",
    "sg:city":"Brovst",
    "sg:orig_category":"Trossamfund uden for folkekirken",
    "sg:phone":"+45 98 23 12 38",
    "sg:postcode":"9460",
    "sg:province":"Danmark",
    "wof:name":"Brovst Baptistmenighed",
    "wof:placetype":"venue"
},
  "geometry": {"coordinates":[9.5220241547,57.097366333],"type":"Point"}
}