{
  "type": "Feature",
  "properties": {
    "addr:full":"Kastrupvej 161 K\u00f8benhavn S Danmark 2300",
    "addr:housenumber":"161",
    "addr:postcode":"2300",
    "addr:street":"Kastrupvej;S Danmark",
    "iso:country":"DK",
    "sg:address":"Kastrupvej 161",
    "sg:city":"K\u00f8benhavn S",
    "sg:orig_category":"Kiosker",
    "sg:phone":"+45 32 55 17 81",
    "sg:postcode":"2300",
    "sg:province":"Danmark",
    "wof:name":"Kongo Minimarked",
    "wof:placetype":"venue"
},
  "geometry": {"coordinates":[-122.29294586180001,47.1502342224],"type":"Point"}
}