{
  "type": "Feature",
  "properties": {
    "addr:full":"Gammel Kongevej 107 Frederiksberg Danmark 1850",
    "addr:housenumber":"107",
    "addr:postcode":"1850",
    "addr:street":"Gammel Kongevej",
    "iso:country":"DK",
    "sg:address":"Gammel Kongevej 107",
    "sg:city":"Frederiksberg",
    "sg:orig_category":"Lingeri",
    "sg:phone":"+45 33 24 78 70",
    "sg:postcode":"1850",
    "sg:province":"Danmark",
    "wof:name":"Emma Lingeri",
    "wof:placetype":"venue"
},
  "geometry": {"coordinates":[12.5457029343,55.6753692627],"type":"Point"}
}