{
  "type": "Feature",
  "properties": {
    "iso:country":"DK",
    "sg:address":"Stubbek\u00f8bingvej 98 B",
    "sg:city":"Nyk\u00f8bing",
    "sg:orig_category":"Kollegier",
    "sg:phone":"+45 54 82 02 50",
    "sg:postcode":"4800",
    "sg:province":"Danmark",
    "wof:name":"Vestensborg Kollegium A, B og C",
    "wof:placetype":"venue"
},
  "geometry": {"coordinates":[-114.0768203735,46.4432411194],"type":"Point"}
}