{
  "type": "Feature",
  "properties": {
    "addr:full":"Fmd.: Benny Christensen, Bjergvej 43, Kv\u00e6rkeby Ringsted Danmark 4100",
    "addr:housenumber":"43",
    "addr:postcode":"4100",
    "addr:street":"Bjergvej;Kvaerkeby",
    "iso:country":"DK",
    "sg:address":"Fmd.: Benny Christensen, Bjergvej 43, Kv\u00e6rkeby",
    "sg:city":"Ringsted",
    "sg:orig_category":"Grundejerforeninger",
    "sg:phone":"+45 57 52 56 37",
    "sg:postcode":"4100",
    "sg:province":"Danmark",
    "wof:name":"Bjergvejens Grundejerforening",
    "wof:placetype":"venue"
},
  "geometry": {"coordinates":[11.7875862122,55.4458961487],"type":"Point"}
}