{
  "type": "Feature",
  "properties": {
    "addr:full":"Solbjergs\u00f8vej 15, Blegind H\u00f8rning Danmark 8362",
    "addr:housenumber":"15",
    "addr:postcode":"8362",
    "addr:street":"Solbjergsovej;Horning Danmark",
    "iso:country":"DK",
    "sg:address":"Solbjergs\u00f8vej 15, Blegind",
    "sg:city":"H\u00f8rning",
    "sg:orig_category":"Gartnerier",
    "sg:phone":"+45 86 92 77 18",
    "sg:postcode":"8362",
    "sg:province":"Danmark",
    "wof:name":"Pedersen A/S, Gartneriet",
    "wof:placetype":"venue"
},
  "geometry": {"coordinates":[10.0397768021,56.0818252563],"type":"Point"}
}