{
  "type": "Feature",
  "properties": {
    "addr:full":"Messingvej 17 Randers Danmark 8900",
    "addr:housenumber":"17",
    "addr:postcode":"8900",
    "addr:street":"Messingvej",
    "iso:country":"DK",
    "sg:address":"Messingvej 17",
    "sg:city":"Randers",
    "sg:orig_category":"Flytteforretninger",
    "sg:phone":"+45 86 44 81 44",
    "sg:postcode":"8900",
    "sg:province":"Danmark",
    "sg:website":"www.j-odum.dk",
    "wof:name":"Randers Flytte-Service",
    "wof:placetype":"venue"
},
  "geometry": {"coordinates":[10.0512638092,56.4305229187],"type":"Point"}
}