{
  "type": "Feature",
  "properties": {
    "addr:full":"\u00c5gerupvej 48, \u00c5gerup Roskilde Danmark 4000",
    "addr:housenumber":"48",
    "addr:postcode":"4000",
    "addr:street":"Aagerupvej",
    "iso:country":"DK",
    "sg:address":"\u00c5gerupvej 48, \u00c5gerup",
    "sg:city":"Roskilde",
    "sg:orig_category":"Fotografer",
    "sg:phone":"+45 46 78 74 63",
    "sg:postcode":"4000",
    "sg:province":"Danmark",
    "wof:name":"Gregersen, Glennie",
    "wof:placetype":"venue"
},
  "geometry": {"coordinates":[12.0909376144,55.6404838562],"type":"Point"}
}