{
  "type": "Feature",
  "properties": {
    "addr:full":"Ving\u00e5rdsgade 27 Aalborg Danmark 9000",
    "addr:housenumber":"27",
    "addr:postcode":"9000",
    "addr:street":"Vingaardsgade",
    "iso:country":"DK",
    "sg:address":"Ving\u00e5rdsgade 27",
    "sg:city":"Aalborg",
    "sg:classifiers":[
        {
            "category":"Food & Beverages",
            "subcategory":"Liquor & Beverages",
            "type":"Retail Goods"
        }
    ],
    "sg:phone":"+45 98 10 17 64",
    "sg:postcode":"9000",
    "sg:province":"Danmark",
    "sg:tags":[
        "vin"
    ],
    "wof:name":"Enoteca Sangiovanni",
    "wof:placetype":"venue"
},
  "geometry": {"coordinates":[9.9156780243,57.047706604],"type":"Point"}
}