{
  "type": "Feature",
  "properties": {
    "addr:full":"v/ Joan Svarre, Kildekrogen 14 Bjerringbro Danmark 8850",
    "addr:housenumber":"14",
    "addr:postcode":"8850",
    "addr:street":"Kildekrogen",
    "iso:country":"DK",
    "sg:address":"v/ Joan Svarre, Kildekrogen 14",
    "sg:city":"Bjerringbro",
    "sg:orig_category":"Musik og sang",
    "sg:phone":"+45 86 68 41 14",
    "sg:postcode":"8850",
    "sg:province":"Danmark",
    "wof:name":"FDF Bjerringbro Brass Band",
    "wof:placetype":"venue"
},
  "geometry": {"coordinates":[9.6546850204,56.3754692078],"type":"Point"}
}