{
  "type": "Feature",
  "properties": {
    "addr:full":"Jernbanegade 34 D Fredensborg Danmark 3480",
    "addr:housenumber":"34 d",
    "addr:postcode":"3480",
    "addr:street":"Jernbanegade",
    "iso:country":"DK",
    "sg:address":"Jernbanegade 34 D",
    "sg:city":"Fredensborg",
    "sg:orig_category":"Finansiering",
    "sg:phone":"+45 48 47 67 00",
    "sg:postcode":"3480",
    "sg:province":"Danmark",
    "sg:website":"www.finanshus.dk",
    "wof:name":"FinansHuset",
    "wof:placetype":"venue"
},
  "geometry": {"coordinates":[12.4031572342,55.9768714905],"type":"Point"}
}