{
  "type": "Feature",
  "properties": {
    "addr:full":"R\u00f8nne Alle 10 A Gilleleje Danmark 3250",
    "addr:housenumber":"10 a",
    "addr:postcode":"3250",
    "addr:street":"Ronne Alle",
    "iso:country":"DK",
    "sg:address":"R\u00f8nne Alle 10 A",
    "sg:city":"Gilleleje",
    "sg:orig_category":"Murermestre",
    "sg:phone":"+45 48 35 54 30",
    "sg:postcode":"3250",
    "sg:province":"Danmark",
    "wof:name":"T.R. Murbyg",
    "wof:placetype":"venue"
},
  "geometry": {"coordinates":[12.2960720062,56.1234970093],"type":"Point"}
}