{
  "type": "Feature",
  "properties": {
    "addr:full":"Roestoftsvej 5, Ly\u00f8 Faaborg Danmark 5600",
    "addr:housenumber":"5",
    "addr:postcode":"5600",
    "addr:street":"Roestoftsvej;Lyo",
    "iso:country":"DK",
    "sg:address":"Roestoftsvej 5, Ly\u00f8",
    "sg:city":"Faaborg",
    "sg:orig_category":"Kulturelle foreninger",
    "sg:phone":"+45 62 61 91 19",
    "sg:postcode":"5600",
    "sg:province":"Danmark",
    "wof:name":"Ly\u00f8 Foredragsforening",
    "wof:placetype":"venue"
},
  "geometry": {"coordinates":[10.2400531769,55.0950622559],"type":"Point"}
}