{
  "type": "Feature",
  "properties": {
    "addr:full":"Chr. Kiers Plads 6 kl. \u00c5rhus C Danmark 8000",
    "addr:housenumber":"6 kl.",
    "addr:postcode":"8000",
    "addr:street":"Chr. Kiers Plads",
    "iso:country":"DK",
    "sg:address":"Chr. Kiers Plads 6 kl.",
    "sg:city":"\u00c5rhus C",
    "sg:orig_category":"Musik og sang",
    "sg:phone":"+45 86 13 84 55",
    "sg:postcode":"8000",
    "sg:province":"Danmark",
    "wof:name":"Festivalforeningen Tun\u00f8",
    "wof:placetype":"venue"
},
  "geometry": {"coordinates":[101.70761108400001,3.1500999928],"type":"Point"}
}