{
  "type": "Feature",
  "properties": {
    "iso:country":"DK",
    "sg:address":"Absalonsgade 16",
    "sg:city":"Sor\u00f8",
    "sg:orig_category":"Bagere",
    "sg:phone":"+45 57 83 22 42",
    "sg:postcode":"4180",
    "sg:province":"Danmark",
    "wof:name":"Sejer's Konditori",
    "wof:placetype":"venue"
},
  "geometry": {"coordinates":[11.560512,55.43399],"type":"Point"}
}