{
  "type": "Feature",
  "properties": {
    "addr:full":"City Vest, Gudrunsvej 7 Brabrand Danmark 8220",
    "addr:housenumber":"7",
    "addr:postcode":"8220",
    "addr:street":"Gudrunsvej",
    "iso:country":"DK",
    "sg:address":"City Vest, Gudrunsvej 7",
    "sg:city":"Brabrand",
    "sg:orig_category":"Sportsartikler",
    "sg:phone":"+45 86 25 19 33",
    "sg:postcode":"8220",
    "sg:province":"Danmark",
    "wof:name":"Intersport - J.O.Sport",
    "wof:placetype":"venue"
},
  "geometry": {"coordinates":[10.1293649673,56.1601295471],"type":"Point"}
}