{
  "type": "Feature",
  "properties": {
    "addr:full":"Absalonsgade 12 Odense C Danmark 5000",
    "addr:housenumber":"12",
    "addr:postcode":"5000",
    "addr:street":"Absalonsgade",
    "iso:country":"DK",
    "sg:address":"Absalonsgade 12",
    "sg:city":"Odense C",
    "sg:orig_category":"Kiosker",
    "sg:phone":"+45 66 13 48 19",
    "sg:postcode":"5000",
    "sg:province":"Danmark",
    "wof:name":"Elite K\u00f8bmandskiosk",
    "wof:placetype":"venue"
},
  "geometry": {"coordinates":[10.3915691376,55.3920478821],"type":"Point"}
}