{
  "type": "Feature",
  "properties": {
    "addr:full":"Agervej 2 Saksk\u00f8bing Danmark 4990",
    "addr:housenumber":"2",
    "addr:postcode":"4990",
    "addr:street":"Agervej",
    "iso:country":"DK",
    "sg:address":"Agervej 2",
    "sg:city":"Saksk\u00f8bing",
    "sg:orig_category":"Musikskoler, Kommunale",
    "sg:postcode":"4990",
    "sg:province":"Danmark",
    "wof:name":"Saksk\u00f8bing Musikskole",
    "wof:placetype":"venue"
},
  "geometry": {"coordinates":[-102.0896530151,42.0193557739],"type":"Point"}
}