{
  "type": "Feature",
  "properties": {
    "addr:full":"Rulkedalen 12, Stenl\u00f8se Odense S Danmark 5260",
    "addr:housenumber":"12",
    "addr:postcode":"5260",
    "addr:street":"Rulkedalen;Stenlose",
    "iso:country":"DK",
    "sg:address":"Rulkedalen 12, Stenl\u00f8se",
    "sg:city":"Odense S",
    "sg:orig_category":"Psykologer, praktiserende",
    "sg:phone":"+45 65 92 03 19",
    "sg:postcode":"5260",
    "sg:province":"Danmark",
    "wof:name":"Hansen, Ruth",
    "wof:placetype":"venue"
},
  "geometry": {"coordinates":[10.3157806396,55.3122825623],"type":"Point"}
}