{
  "type": "Feature",
  "properties": {
    "iso:country":"DK",
    "sg:address":"Gerritsgade 50",
    "sg:city":"Svendborg",
    "sg:orig_category":"RESTAURANTS: CAFEER",
    "sg:phone":"+45 62 21 83 08",
    "sg:postcode":"5700",
    "sg:province":"Danmark",
    "sg:website":"www.under-uret.com",
    "wof:name":"Under Uret",
    "wof:placetype":"venue"
},
  "geometry": {"coordinates":[10.606467247,55.0587844849],"type":"Point"}
}