{
  "type": "Feature",
  "properties": {
    "addr:full":"Metalvej 10 Kolding Danmark 6000",
    "addr:housenumber":"10",
    "addr:postcode":"6000",
    "addr:street":"Metalvej",
    "iso:country":"DK",
    "sg:address":"Metalvej 10",
    "sg:city":"Kolding",
    "sg:orig_category":"Metaller",
    "sg:phone":"+45 75 52 84 88",
    "sg:postcode":"6000",
    "sg:province":"Danmark",
    "wof:name":"Gotthard Aluminium A/S",
    "wof:placetype":"venue"
},
  "geometry": {"coordinates":[9.4497880936,55.509929657],"type":"Point"}
}