{
  "type": "Feature",
  "properties": {
    "iso:country":"DK",
    "sg:address":"Blomstervej 1",
    "sg:city":"Tilst",
    "sg:orig_category":"Laboratorier",
    "sg:phone":"+45 86 24 50 33",
    "sg:postcode":"8381",
    "sg:province":"Danmark",
    "sg:website":"www.deg.dk",
    "wof:name":"DEG - Dansk Erhvervsgartnerforening",
    "wof:placetype":"venue"
},
  "geometry": {"coordinates":[10.1243000031,56.1830558777],"type":"Point"}
}