{
  "type": "Feature",
  "properties": {
    "addr:full":"Fmd.: Andreas Stork, Nordmandshusene 10 Skibby Danmark 4050",
    "addr:housenumber":"10",
    "addr:postcode":"4050",
    "addr:street":"Nordmandshusene",
    "iso:country":"DK",
    "sg:address":"Fmd.: Andreas Stork, Nordmandshusene 10",
    "sg:city":"Skibby",
    "sg:orig_category":"\u00c3\u2020ldreorganisationer og klubber",
    "sg:phone":"+45 47 52 76 11",
    "sg:postcode":"4050",
    "sg:province":"Danmark",
    "wof:name":"Pensionistforeningen",
    "wof:placetype":"venue"
},
  "geometry": {"coordinates":[11.9594116211,55.7502975464],"type":"Point"}
}