{
  "type": "Feature",
  "properties": {
    "addr:full":"Kredsleder: Karen M\u00f8ller, N\u00e6stvedvej 82, Baarse Lundby Danmark 4750",
    "addr:housenumber":"82",
    "addr:postcode":"4750",
    "addr:street":"Naestvedvej",
    "iso:country":"DK",
    "sg:address":"Kredsleder: Karen M\u00f8ller, N\u00e6stvedvej 82, Baarse",
    "sg:city":"Lundby",
    "sg:orig_category":"Spejderkorps",
    "sg:phone":"+45 55 99 02 15",
    "sg:postcode":"4750",
    "sg:province":"Danmark",
    "wof:name":"FDF, B\u00e5rse",
    "wof:placetype":"venue"
},
  "geometry": {"coordinates":[11.8101682663,55.1197814941],"type":"Point"}
}