{
  "type": "Feature",
  "properties": {
    "addr:full":"Gadeg\u00e5rdsvej 2, Duelund Kjellerup Danmark 8620",
    "addr:housenumber":"2",
    "addr:postcode":"8620",
    "addr:street":"Gadegaardsvej",
    "iso:country":"DK",
    "sg:address":"Gadeg\u00e5rdsvej 2, Duelund",
    "sg:city":"Kjellerup",
    "sg:orig_category":"Planteskoler",
    "sg:phone":"+45 86 88 17 54",
    "sg:postcode":"8620",
    "sg:province":"Danmark",
    "wof:name":"Andresen, Henrik",
    "wof:placetype":"venue"
},
  "geometry": {"coordinates":[9.430934906,56.2877655029],"type":"Point"}
}