{
  "type": "Feature",
  "properties": {
    "iso:country":"DK",
    "sg:address":"S\u00f8ndergade 10",
    "sg:city":"Hadsten",
    "sg:orig_category":"Sportsartikler",
    "sg:phone":"+45 86 98 36 16",
    "sg:postcode":"8370",
    "sg:province":"Danmark",
    "sg:website":"www.us-sport.dk",
    "wof:name":"US Sport",
    "wof:placetype":"venue"
},
  "geometry": {"coordinates":[10.0449037552,56.3275032043],"type":"Point"}
}