{
  "type": "Feature",
  "properties": {
    "addr:full":"Fmd.: Morten Hagerup, Elmevej 8, Nr. S\u00f8by H\u00f8jslev Danmark 7840",
    "addr:housenumber":"8",
    "addr:postcode":"7840",
    "addr:street":"Morten Hagerup Elmevej",
    "iso:country":"DK",
    "sg:address":"Fmd.: Morten Hagerup, Elmevej 8, Nr. S\u00f8by",
    "sg:city":"H\u00f8jslev",
    "sg:orig_category":"Loger",
    "sg:phone":"+45 96 51 41 10",
    "sg:postcode":"7840",
    "sg:province":"Danmark",
    "wof:name":"Junior Chamber",
    "wof:placetype":"venue"
},
  "geometry": {"coordinates":[166.9221496582,-0.5282999873],"type":"Point"}
}