{
  "type": "Feature",
  "properties": {
    "addr:full":"R\u00e5dhusvej 2 Charlottenlund Danmark 2920",
    "addr:housenumber":"2",
    "addr:postcode":"2920",
    "addr:street":"Raadhusvej",
    "iso:country":"DK",
    "sg:address":"R\u00e5dhusvej 2",
    "sg:city":"Charlottenlund",
    "sg:orig_category":"Fotografer",
    "sg:phone":"+45 45 93 12 20",
    "sg:postcode":"2920",
    "sg:province":"Danmark",
    "sg:website":"www.portraet-galleriet.dk",
    "wof:name":"Portr\u00e6t Galleriet",
    "wof:placetype":"venue"
},
  "geometry": {"coordinates":[12.5721225739,55.7530326843],"type":"Point"}
}