{
  "type": "Feature",
  "properties": {
    "iso:country":"DK",
    "sg:address":"Sennelsvej 66",
    "sg:city":"Thisted",
    "sg:orig_category":"Autoreparation og -service",
    "sg:phone":"+45 97 98 60 44",
    "sg:postcode":"7700",
    "sg:province":"Danmark",
    "sg:website":"www.sennelsauto.dk",
    "wof:name":"Sennels Auto- & Traktorservice",
    "wof:placetype":"venue"
},
  "geometry": {"coordinates":[8.7734498978,56.9647293091],"type":"Point"}
}