{
  "type": "Feature",
  "properties": {
    "iso:country":"DK",
    "sg:address":"Lokalomr\u00e5de Skalborg, Stationsmestervej 1 - 24",
    "sg:city":"Aalborg SV",
    "sg:orig_category":"Boliger med kald",
    "sg:phone":"+45 99 31 34 92",
    "sg:postcode":"9200",
    "sg:province":"Danmark",
    "wof:name":"Stationsmestervej",
    "wof:placetype":"venue"
},
  "geometry": {"coordinates":[9.8565721512,57.00573349],"type":"Point"}
}