{
  "type": "Feature",
  "properties": {
    "addr:full":"Fmd.: Aage G. Friis, Kirkedalsvej 46, R\u00e5rup Juelsminde Danmark 7130",
    "addr:housenumber":"46",
    "addr:postcode":"7130",
    "addr:street":"Aage G. Friis Kirkedalsvej",
    "iso:country":"DK",
    "sg:address":"Fmd.: Aage G. Friis, Kirkedalsvej 46, R\u00e5rup",
    "sg:city":"Juelsminde",
    "sg:orig_category":"\u00c3\u2020ldreorganisationer og klubber",
    "sg:phone":"+45 75 68 52 87",
    "sg:postcode":"7130",
    "sg:province":"Danmark",
    "wof:name":"Juelsminde Efterl\u00f8ns- og Pensionistklub",
    "wof:placetype":"venue"
},
  "geometry": {"coordinates":[10.0143985748,55.7135848999],"type":"Point"}
}