{
  "type": "Feature",
  "properties": {
    "addr:full":"N\u00f8rre Boulevard 1 K\u00f8ge Danmark 4600",
    "addr:housenumber":"1",
    "addr:postcode":"4600",
    "addr:street":"Norre Boulevard",
    "iso:country":"DK",
    "sg:address":"N\u00f8rre Boulevard 1",
    "sg:city":"K\u00f8ge",
    "sg:orig_category":"Pizzeriaer",
    "sg:phone":"+45 56 63 58 17",
    "sg:postcode":"4600",
    "sg:province":"Danmark",
    "wof:name":"K\u00f8ge Pizza House",
    "wof:placetype":"venue"
},
  "geometry": {"coordinates":[-116.27327728269999,32.6635398865],"type":"Point"}
}