{
  "type": "Feature",
  "properties": {
    "iso:country":"DK",
    "sg:address":"Vestergade 9",
    "sg:city":"Kerteminde",
    "sg:orig_category":"Engros handel",
    "sg:phone":"+45 65 32 32 52",
    "sg:postcode":"5300",
    "sg:province":"Danmark",
    "wof:name":"CopyCare",
    "wof:placetype":"venue"
},
  "geometry": {"coordinates":[10.6565084457,55.4488220215],"type":"Point"}
}