{
  "type": "Feature",
  "properties": {
    "iso:country":"DK",
    "sg:address":"S\u00f8ndergade 49",
    "sg:city":"Horsens",
    "sg:orig_category":"Arkitekter",
    "sg:phone":"+45 75 62 28 77",
    "sg:postcode":"8700",
    "sg:province":"Danmark",
    "wof:name":"Knudsen & Halling as",
    "wof:placetype":"venue"
},
  "geometry": {"coordinates":[9.8507585526,55.8619155884],"type":"Point"}
}