{
  "type": "Feature",
  "properties": {
    "addr:full":"Klitten 10, Ven\u00f8 Struer Danmark 7600",
    "addr:housenumber":"10",
    "addr:postcode":"7600",
    "addr:street":"Klitten;Veno",
    "iso:country":"DK",
    "sg:address":"Klitten 10, Ven\u00f8",
    "sg:city":"Struer",
    "sg:orig_category":"Campingpladser",
    "sg:phone":"+45 97 86 80 02",
    "sg:postcode":"7600",
    "sg:province":"Danmark",
    "wof:name":"Ven\u00f8 Camping",
    "wof:placetype":"venue"
},
  "geometry": {"coordinates":[8.5946903229,56.491191864],"type":"Point"}
}