{
  "type": "Feature",
  "properties": {
    "iso:country":"DK",
    "sg:address":"Borupg\u00e5rdcentret 7",
    "sg:city":"Snekkersten",
    "sg:orig_category":"Bodegaer",
    "sg:phone":"+45 49 22 39 49",
    "sg:postcode":"3070",
    "sg:province":"Danmark",
    "wof:name":"Snekken Bodega",
    "wof:placetype":"venue"
},
  "geometry": {"coordinates":[12.584777832,56.0104217529],"type":"Point"}
}