{
  "type": "Feature",
  "properties": {
    "iso:country":"DK",
    "sg:address":"D\u00e6mningen 42",
    "sg:city":"Vejle",
    "sg:orig_category":"Blomsterhandlere",
    "sg:phone":"+45 75 82 11 47",
    "sg:postcode":"7100",
    "sg:province":"Danmark",
    "wof:name":"Blomsterk\u00e6lderen",
    "wof:placetype":"venue"
},
  "geometry": {"coordinates":[9.5360212326,55.7082366943],"type":"Point"}
}