{
  "type": "Feature",
  "properties": {
    "addr:full":"Vester Voldgade 123, 3. K\u00f8benhavn Danmark 1552",
    "addr:housenumber":"123 3;1552",
    "addr:street":"Vester Voldgade",
    "iso:country":"DK",
    "sg:address":"Vester Voldgade 123, 3.",
    "sg:city":"K\u00f8benhavn",
    "sg:orig_category":"Statslige direktorater og styrelser",
    "sg:phone":"+45 33 92 73 33",
    "sg:postcode":"1552",
    "sg:province":"Danmark",
    "sg:website":"www.jernbanetilsynet.dk",
    "wof:name":"Jernbanetilsynet",
    "wof:placetype":"venue"
},
  "geometry": {"coordinates":[12.570400238,55.6759986877],"type":"Point"}
}