{
  "type": "Feature",
  "properties": {
    "addr:full":"Glums\u00f8vej 34 Br\u00f8nsh\u00f8j Danmark 2700",
    "addr:housenumber":"34",
    "addr:postcode":"2700",
    "addr:street":"Glumsovej",
    "iso:country":"DK",
    "sg:address":"Glums\u00f8vej 34",
    "sg:city":"Br\u00f8nsh\u00f8j",
    "sg:orig_category":"Murermestre",
    "sg:phone":"+45 38 80 47 49",
    "sg:postcode":"2700",
    "sg:province":"Danmark",
    "wof:name":"Opstrup, Peter",
    "wof:placetype":"venue"
},
  "geometry": {"coordinates":[-65.6866531372,-23.1981296539],"type":"Point"}
}