{
  "type": "Feature",
  "properties": {
    "iso:country":"DK",
    "sg:address":"Gr\u00e6se Bygade 9",
    "sg:city":"Frederikssund",
    "sg:orig_category":"Hobbybetonede foreninger",
    "sg:phone":"+45 47 38 94 80",
    "sg:postcode":"3600",
    "sg:province":"Danmark",
    "wof:name":"Vegetarisk Spiseklub Frederikssund",
    "wof:placetype":"venue"
},
  "geometry": {"coordinates":[12.0661621094,55.8370323181],"type":"Point"}
}