{
  "type": "Feature",
  "properties": {
    "addr:full":"\u00d8stergade 11 Ikast Danmark 7430",
    "addr:housenumber":"11",
    "addr:postcode":"7430",
    "addr:street":"Ostergade",
    "iso:country":"DK",
    "sg:address":"\u00d8stergade 11",
    "sg:city":"Ikast",
    "sg:orig_category":"Posthuse",
    "sg:phone":"+45 96 60 03 05",
    "sg:postcode":"7430",
    "sg:province":"Danmark",
    "wof:name":"Post Danmark, Postkontoret",
    "wof:placetype":"venue"
},
  "geometry": {"coordinates":[9.1564445496,56.1396522522],"type":"Point"}
}