{
  "type": "Feature",
  "properties": {
    "addr:full":"Fmd.: Arne Gottlieb, \u00d8sterled 14, Nr. Nissum Lemvig Danmark 7620",
    "addr:housenumber":"14",
    "addr:postcode":"7620",
    "addr:street":"Arne Gottlieb Osterled",
    "iso:country":"DK",
    "sg:address":"Fmd.: Arne Gottlieb, \u00d8sterled 14, Nr. Nissum",
    "sg:city":"Lemvig",
    "sg:orig_category":"Borger- og beboerforeninger",
    "sg:phone":"+45 97 89 14 07",
    "sg:postcode":"7620",
    "sg:province":"Danmark",
    "wof:name":"Nr. Nissum Sogneforening",
    "wof:placetype":"venue"
},
  "geometry": {"coordinates":[8.3073654175,56.5505104065],"type":"Point"}
}