{
  "type": "Feature",
  "properties": {
    "addr:full":"Marselisborg Skov, \u00d8rneredevej 3 \u00c5rhus C Danmark 8000",
    "addr:housenumber":"3",
    "addr:postcode":"8000",
    "addr:street":"Marselisborg Skov Orneredevej",
    "iso:country":"DK",
    "sg:address":"Marselisborg Skov, \u00d8rneredevej 3",
    "sg:city":"\u00c5rhus C",
    "sg:classifiers":[
        {
            "category":"Restaurant",
            "type":"Food & Drink"
        }
    ],
    "sg:phone":"+45 86 14 04 00",
    "sg:postcode":"8000",
    "sg:province":"Danmark",
    "sg:website":"www.varna.dk",
    "wof:name":"Varna Pal\u00e6et",
    "wof:placetype":"venue"
},
  "geometry": {"coordinates":[4.717400074,49.7588005066],"type":"Point"}
}