{
  "type": "Feature",
  "properties": {
    "addr:full":"Bevtoftgade 6A K\u00f8benhavn Danmark 1736",
    "addr:housenumber":"6a",
    "addr:postcode":"1736",
    "addr:street":"Bevtoftgade",
    "iso:country":"DK",
    "sg:address":"Bevtoftgade 6A",
    "sg:city":"K\u00f8benhavn",
    "sg:orig_category":"Keramik",
    "sg:phone":"+45 33 23 99 04",
    "sg:postcode":"1736",
    "sg:province":"Danmark",
    "wof:name":"Keramikniels",
    "wof:placetype":"venue"
},
  "geometry": {"coordinates":[12.54529953,55.6646003723],"type":"Point"}
}