{
  "type": "Feature",
  "properties": {
    "addr:full":"Fmd.: Birger Frandsen, Gl. Viborgvej 43, Hvam Aalestrup Danmark 9620",
    "addr:housenumber":"43",
    "addr:postcode":"9620",
    "addr:street":"Birger Frandsen Gl. Viborgvej",
    "iso:country":"DK",
    "sg:address":"Fmd.: Birger Frandsen, Gl. Viborgvej 43, Hvam",
    "sg:city":"Aalestrup",
    "sg:orig_category":"Kulturelle foreninger",
    "sg:phone":"+45 98 64 80 15",
    "sg:postcode":"9620",
    "sg:province":"Danmark",
    "wof:name":"Br\u00f8nden, Hvam",
    "wof:placetype":"venue"
},
  "geometry": {"coordinates":[9.4901504517,56.6938285828],"type":"Point"}
}