{
  "type": "Feature",
  "properties": {
    "addr:full":"Anderupvej 64b, Anderup Odense N Danmark 5270",
    "addr:housenumber":"64b",
    "addr:postcode":"5270",
    "addr:street":"Anderupvej",
    "iso:country":"DK",
    "sg:address":"Anderupvej 64b, Anderup",
    "sg:city":"Odense N",
    "sg:orig_category":"Arkitekter",
    "sg:phone":"+45 66 18 80 22",
    "sg:postcode":"5270",
    "sg:province":"Danmark",
    "wof:name":"Hansen, Povl Edvard",
    "wof:placetype":"venue"
},
  "geometry": {"coordinates":[10.3306798935,55.4711418152],"type":"Point"}
}