{
  "type": "Feature",
  "properties": {
    "addr:full":"Herlev Hovedgade 96-98 Herlev Danmark 2730",
    "addr:postcode":"96-98;2730",
    "addr:street":"Herlev Hovedgade",
    "iso:country":"DK",
    "sg:address":"Herlev Hovedgade 96-98",
    "sg:city":"Herlev",
    "sg:orig_category":"Benzinstationer",
    "sg:phone":"+45 44 94 01 04",
    "sg:postcode":"2730",
    "sg:province":"Danmark",
    "sg:website":"www.herlev-auto.dk",
    "wof:name":"Herlev Autov\u00e6rksted",
    "wof:placetype":"venue"
},
  "geometry": {"coordinates":[12.4434652328,55.7224769592],"type":"Point"}
}