{
  "type": "Feature",
  "properties": {
    "addr:full":"Nybrovej 59 Gentofte Danmark 2820",
    "addr:housenumber":"59",
    "addr:postcode":"2820",
    "addr:street":"Nybrovej",
    "iso:country":"DK",
    "sg:address":"Nybrovej 59",
    "sg:city":"Gentofte",
    "sg:orig_category":"Autoreparation og -service",
    "sg:phone":"+45 45 88 96 84",
    "sg:postcode":"2820",
    "sg:province":"Danmark",
    "wof:name":"Skaanings Autoservice",
    "wof:placetype":"venue"
},
  "geometry": {"coordinates":[12.5059604645,55.7571258545],"type":"Point"}
}