{
  "type": "Feature",
  "properties": {
    "addr:full":"Fmd.: Ulla Kert, Glyng\u00f8revej 6, \u00d8ster D\u00f8lby Skive Danmark 7800",
    "addr:housenumber":"6",
    "addr:postcode":"dolby;7800",
    "addr:street":"Glyngorevej",
    "iso:country":"DK",
    "sg:address":"Fmd.: Ulla Kert, Glyng\u00f8revej 6, \u00d8ster D\u00f8lby",
    "sg:city":"Skive",
    "sg:orig_category":"Forsamlingshuse",
    "sg:phone":"+45 97 51 40 59",
    "sg:postcode":"7800",
    "sg:province":"Danmark",
    "wof:name":"D\u00f8lby forsamlingshus",
    "wof:placetype":"venue"
},
  "geometry": {"coordinates":[9.0320358276,56.5666427612],"type":"Point"}
}