{
  "type": "Feature",
  "properties": {
    "addr:full":"Torvegade 12 Nex\u00f8 Danmark 3730",
    "addr:housenumber":"12",
    "addr:postcode":"3730",
    "addr:street":"Torvegade",
    "iso:country":"DK",
    "sg:address":"Torvegade 12",
    "sg:city":"Nex\u00f8",
    "sg:orig_category":"Tolke",
    "sg:phone":"+45 56 49 22 14",
    "sg:postcode":"3730",
    "sg:province":"Danmark",
    "wof:name":"Bornholms Tolkeservice",
    "wof:placetype":"venue"
},
  "geometry": {"coordinates":[15.111371994,55.0189666748],"type":"Point"}
}