{
  "type": "Feature",
  "properties": {
    "iso:country":"DK",
    "sg:address":"v/ Vincent Jessen, Skovbyvej 14, Peberbjerg",
    "sg:city":"Sydals",
    "sg:orig_category":"Kulturelle foreninger",
    "sg:phone":"+45 74 41 57 47",
    "sg:postcode":"6470",
    "sg:province":"Danmark",
    "wof:name":"Selskabet for Nydamforskning",
    "wof:placetype":"venue"
},
  "geometry": {"coordinates":[9.8924627304,54.9105377197],"type":"Point"}
}