{
  "type": "Feature",
  "properties": {
    "iso:country":"DK",
    "sg:address":"Fredh\u00f8j Alle 1",
    "sg:city":"Herning",
    "sg:orig_category":"Kirkesogne",
    "sg:phone":"+45 97 22 29 95",
    "sg:postcode":"7400",
    "sg:province":"Danmark",
    "wof:name":"Sct. Johannes Sogns Kirkekontor",
    "wof:placetype":"venue"
},
  "geometry": {"coordinates":[8.9606752396,56.1403846741],"type":"Point"}
}