{
  "type": "Feature",
  "properties": {
    "addr:full":"Adelgade 71 Hobro Danmark 9500",
    "addr:housenumber":"71",
    "addr:postcode":"9500",
    "addr:street":"Adelgade",
    "iso:country":"DK",
    "sg:address":"Adelgade 71",
    "sg:city":"Hobro",
    "sg:orig_category":"Videobutikker og -klubber",
    "sg:phone":"+45 96 57 06 15",
    "sg:postcode":"9500",
    "sg:province":"Danmark",
    "sg:website":"www.blockbuster.dk",
    "wof:name":"Blockbuster",
    "wof:placetype":"venue"
},
  "geometry": {"coordinates":[9.7975578308,56.6361656189],"type":"Point"}
}