{
  "type": "Feature",
  "properties": {
    "addr:full":"Balstrupvej 58 Ringsted Danmark 4100",
    "addr:housenumber":"58",
    "addr:postcode":"4100",
    "addr:street":"Balstrupvej",
    "iso:country":"DK",
    "sg:address":"Balstrupvej 58",
    "sg:city":"Ringsted",
    "sg:orig_category":"Maskinudlejning",
    "sg:phone":"+45 57 67 61 55",
    "sg:postcode":"4100",
    "sg:province":"Danmark",
    "wof:name":"Altima Maskinudlejnign A/S",
    "wof:placetype":"venue"
},
  "geometry": {"coordinates":[11.8074398041,55.4372406006],"type":"Point"}
}