{
  "type": "Feature",
  "properties": {
    "addr:full":"Herluf Trolles Vej 142 Odense S\u00d8 Danmark 5220",
    "addr:housenumber":"142",
    "addr:postcode":"5220",
    "addr:street":"Herluf Trolles Vej",
    "iso:country":"DK",
    "sg:address":"Herluf Trolles Vej 142",
    "sg:city":"Odense S\u00d8",
    "sg:orig_category":"Medicinalvareindustri",
    "sg:phone":"+45 66 15 55 99",
    "sg:postcode":"5220",
    "sg:province":"Danmark",
    "wof:name":"Nomeco A/S",
    "wof:placetype":"venue"
},
  "geometry": {"coordinates":[10.4479980469,55.3882255554],"type":"Point"}
}