{
  "type": "Feature",
  "properties": {
    "addr:full":"Danmarksgade 27 Kongerslev Danmark 9293",
    "addr:housenumber":"27",
    "addr:postcode":"9293",
    "addr:street":"Danmarksgade",
    "iso:country":"DK",
    "sg:address":"Danmarksgade 27",
    "sg:city":"Kongerslev",
    "sg:classifiers":[
        {
            "category":"Communications",
            "type":"Services"
        }
    ],
    "sg:phone":"+45 98 33 20 70",
    "sg:postcode":"9293",
    "sg:province":"Danmark",
    "sg:tags":[
        "og",
        "tv",
        "radio"
    ],
    "wof:name":"Kongerslev Radio & TV",
    "wof:placetype":"venue"
},
  "geometry": {"coordinates":[10.1164722443,56.8849449158],"type":"Point"}
}