{
  "type": "Feature",
  "properties": {
    "addr:full":"Nybrovej 168 Kongens Lyngby Danmark 2800",
    "addr:housenumber":"168",
    "addr:postcode":"2800",
    "addr:street":"Nybrovej",
    "iso:country":"DK",
    "sg:address":"Nybrovej 168",
    "sg:city":"Kongens Lyngby",
    "sg:orig_category":"Farve- og stilanalyse",
    "sg:phone":"+45 45 88 08 18",
    "sg:postcode":"2800",
    "sg:province":"Danmark",
    "wof:name":"Rasmussen, Marianne Mehder",
    "wof:placetype":"venue"
},
  "geometry": {"coordinates":[12.4918327332,55.7640457153],"type":"Point"}
}