{
  "type": "Feature",
  "properties": {
    "addr:full":"Algade 70 Br\u00f8nderslev Danmark 9700",
    "addr:housenumber":"70",
    "addr:postcode":"9700",
    "addr:street":"Algade",
    "iso:country":"DK",
    "sg:address":"Algade 70",
    "sg:city":"Br\u00f8nderslev",
    "sg:orig_category":"Pizzeriaer",
    "sg:phone":"+45 98 80 08 25",
    "sg:postcode":"9700",
    "sg:province":"Danmark",
    "wof:name":"Tony's Pizza",
    "wof:placetype":"venue"
},
  "geometry": {"coordinates":[9.9190502167,57.0478210449],"type":"Point"}
}