{
  "type": "Feature",
  "properties": {
    "addr:full":"Tastumvej 33, Tastum Stoholm Danmark 7850",
    "addr:housenumber":"33",
    "addr:postcode":"7850",
    "addr:street":"Tastumvej",
    "iso:country":"DK",
    "sg:address":"Tastumvej 33, Tastum",
    "sg:city":"Stoholm",
    "sg:orig_category":"Forsamlingshuse",
    "sg:phone":"+45 97 54 12 50",
    "sg:postcode":"7850",
    "sg:province":"Danmark",
    "wof:name":"Tastum Forsamlingshus",
    "wof:placetype":"venue"
},
  "geometry": {"coordinates":[9.148730278,56.4856910706],"type":"Point"}
}