{
  "type": "Feature",
  "properties": {
    "iso:country":"DK",
    "sg:address":"Kjeldsg\u00e5rdsvej 40",
    "sg:city":"Valby",
    "sg:orig_category":"Diners transportables",
    "sg:phone":"+45 36 17 37 50",
    "sg:postcode":"2500",
    "sg:province":"Danmark",
    "wof:name":"H\u00f8jfeldts Diner Transportable",
    "wof:placetype":"venue"
},
  "geometry": {"coordinates":[12.5209598541,55.6608200073],"type":"Point"}
}