{
  "type": "Feature",
  "properties": {
    "addr:full":"Tagensvej 88 K\u00f8benhavn N Danmark 2200",
    "addr:housenumber":"88",
    "addr:postcode":"2200",
    "addr:street":"Tagensvej;Kobenhavn N Danmark",
    "iso:country":"DK",
    "sg:address":"Tagensvej 88",
    "sg:city":"K\u00f8benhavn N",
    "sg:classifiers":[
        {
            "category":"Communications",
            "subcategory":"Film & Video Production",
            "type":"Services"
        }
    ],
    "sg:phone":"+45 35 81 95 00",
    "sg:postcode":"2200",
    "sg:province":"Danmark",
    "sg:tags":[
        "radio-",
        "og",
        "tv-service"
    ],
    "wof:name":"A.A. / KM-TV D\u00f8gnservice",
    "wof:placetype":"venue"
},
  "geometry": {"coordinates":[-76.4168395996,37.452419281],"type":"Point"}
}