{
  "type": "Feature",
  "properties": {
    "iso:country":"DK",
    "sg:address":"Ved Byskellet 14",
    "sg:city":"Randers",
    "sg:orig_category":"Supermarkeder",
    "sg:phone":"+45 86 43 72 80",
    "sg:postcode":"8900",
    "sg:province":"Danmark",
    "wof:name":"Dan-K\u00f8b",
    "wof:placetype":"venue"
},
  "geometry": {"coordinates":[10.005979538,56.4807739258],"type":"Point"}
}