{
  "type": "Feature",
  "properties": {
    "addr:full":"Kolding Kirkeg\u00e5rd, Dag Hammarskj\u00f6lds Alle 10 K\u00f8benhavn \u00d8 Danmark 2100",
    "addr:housenumber":"10",
    "addr:postcode":"2100",
    "addr:street":"Dag Hammarskjoelds Alle;O",
    "iso:country":"DK",
    "sg:address":"Kolding Kirkeg\u00e5rd, Dag Hammarskj\u00f6lds Alle 10",
    "sg:city":"K\u00f8benhavn \u00d8",
    "sg:orig_category":"Faglige organisationer og -foreninger",
    "sg:phone":"+45 35 42 79 51",
    "sg:postcode":"2100",
    "sg:province":"Danmark",
    "wof:name":"Kirkeg\u00e5rdsledere, Foreningen af Danske",
    "wof:placetype":"venue"
},
  "geometry": {"coordinates":[9.4733896255,55.4863510132],"type":"Point"}
}