{
  "type": "Feature",
  "properties": {
    "addr:full":"Dalen 2, Aarsdale Svaneke Danmark 3740",
    "addr:housenumber":"2",
    "addr:postcode":"3740",
    "addr:street":"Dalen;Aarsdale",
    "iso:country":"DK",
    "sg:address":"Dalen 2, Aarsdale",
    "sg:city":"Svaneke",
    "sg:orig_category":"Brugskunst",
    "sg:phone":"+45 56 49 61 16",
    "sg:postcode":"3740",
    "sg:province":"Danmark",
    "wof:name":"HH Design",
    "wof:placetype":"venue"
},
  "geometry": {"coordinates":[15.140504837,55.1364555359],"type":"Point"}
}