{
  "type": "Feature",
  "properties": {
    "addr:full":"Vestergade 33 Vr\u00e5 Danmark 9760",
    "addr:housenumber":"33",
    "addr:postcode":"9760",
    "addr:street":"Vestergade",
    "iso:country":"DK",
    "sg:address":"Vestergade 33",
    "sg:city":"Vr\u00e5",
    "sg:orig_category":"\u00c3\u02dcvrig fritidsundervisning",
    "sg:phone":"+45 99 67 13 88",
    "sg:postcode":"9760",
    "sg:province":"Danmark",
    "wof:name":"L\u00f8kken-Vr\u00e5 Musikskole",
    "wof:placetype":"venue"
},
  "geometry": {"coordinates":[9.9376659393,57.355758667],"type":"Point"}
}