{
  "type": "Feature",
  "properties": {
    "addr:full":"Fmd.: Kai Petersen, Kirkevej 10, Hunseby Maribo Danmark 4930",
    "addr:housenumber":"10",
    "addr:postcode":"4930",
    "addr:street":"Kirkevej;Hunseby",
    "iso:country":"DK",
    "sg:address":"Fmd.: Kai Petersen, Kirkevej 10, Hunseby",
    "sg:city":"Maribo",
    "sg:orig_category":"Faglige organisationer og foreninger",
    "sg:phone":"+45 54 78 25 94",
    "sg:postcode":"4930",
    "sg:province":"Danmark",
    "wof:name":"Midtlollands Familiebrug",
    "wof:placetype":"venue"
},
  "geometry": {"coordinates":[11.502035141,54.7743835449],"type":"Point"}
}