{
  "type": "Feature",
  "properties": {
    "addr:full":"Klintevej 7 C Fakse Ladeplads Danmark 4654",
    "addr:housenumber":"7 c",
    "addr:postcode":"4654",
    "addr:street":"Klintevej",
    "iso:country":"DK",
    "sg:address":"Klintevej 7 C",
    "sg:city":"Fakse Ladeplads",
    "sg:orig_category":"Malermestre",
    "sg:phone":"+45 40 46 94 10",
    "sg:postcode":"4654",
    "sg:province":"Danmark",
    "wof:name":"Munk, Anne",
    "wof:placetype":"venue"
},
  "geometry": {"coordinates":[12.1711816788,55.2188415527],"type":"Point"}
}