{
  "type": "Feature",
  "properties": {
    "addr:full":"Motelvej 28 Roskilde Danmark 4000",
    "addr:housenumber":"28",
    "addr:postcode":"4000",
    "addr:street":"Motelvej",
    "iso:country":"DK",
    "sg:address":"Motelvej 28",
    "sg:city":"Roskilde",
    "sg:orig_category":"HOTELS: OG MOTELLER",
    "sg:phone":"+45 46 35 43 85",
    "sg:postcode":"4000",
    "sg:province":"Danmark",
    "wof:name":"Mr. Janny Motel",
    "wof:placetype":"venue"
},
  "geometry": {"coordinates":[12.096165657,55.6262969971],"type":"Point"}
}