{
  "type": "Feature",
  "properties": {
    "addr:full":"Fmd.: Ingeborg Hansen, Engg\u00e5rdsvej 24, Ubby Jerslev Sj\u00e6lland Danmark 4490",
    "addr:housenumber":"24",
    "addr:postcode":"4490",
    "addr:street":"Enggaardsvej;Ubby Jerslev Sjaelland Danmark",
    "iso:country":"DK",
    "sg:address":"Fmd.: Ingeborg Hansen, Engg\u00e5rdsvej 24, Ubby",
    "sg:city":"Jerslev Sj\u00e6lland",
    "sg:orig_category":"\u00c3\u2020ldreorganisationer og klubber",
    "sg:phone":"+45 59 59 54 32",
    "sg:postcode":"4490",
    "sg:province":"Danmark",
    "wof:name":"Pensionistforeningen i Hvideb\u00e6k",
    "wof:placetype":"venue"
},
  "geometry": {"coordinates":[11.213265419,55.619178772],"type":"Point"}
}