{
  "type": "Feature",
  "properties": {
    "addr:full":"v/ Vindinge Skole, St\u00e6rkendevej 5 B, Vindinge Roskilde Danmark 4000",
    "addr:housenumber":"5 b",
    "addr:postcode":"4000",
    "addr:street":"Staerkendevej;Vindinge",
    "iso:country":"DK",
    "sg:address":"v/ Vindinge Skole, St\u00e6rkendevej 5 B, Vindinge",
    "sg:city":"Roskilde",
    "sg:orig_category":"Kulturcentre",
    "sg:phone":"+45 46 35 13 66",
    "sg:postcode":"4000",
    "sg:province":"Danmark",
    "sg:website":"www.vindinge.dk",
    "wof:name":"Vindinge Kulturcenter",
    "wof:placetype":"venue"
},
  "geometry": {"coordinates":[12.0909376144,55.6404838562],"type":"Point"}
}