{
  "type": "Feature",
  "properties": {
    "iso:country":"DK",
    "sg:address":"Hejren 24",
    "sg:city":"Greve",
    "sg:orig_category":"Havne",
    "sg:phone":"+45 43 90 86 18",
    "sg:postcode":"2670",
    "sg:province":"Danmark",
    "sg:website":"www.hundige-havn.dk",
    "wof:name":"Hundige Havn, Havne\u00f8en Hejren",
    "wof:placetype":"venue"
},
  "geometry": {"coordinates":[12.3565292358,55.5939788818],"type":"Point"}
}