{
  "type": "Feature",
  "properties": {
    "addr:full":"Industrivej 1 Bolderslev Danmark 6392",
    "addr:housenumber":"1",
    "addr:postcode":"6392",
    "addr:street":"Industrivej",
    "iso:country":"DK",
    "sg:address":"Industrivej 1",
    "sg:city":"Bolderslev",
    "sg:orig_category":"Maskinfabrikker",
    "sg:phone":"+45 74 64 64 43",
    "sg:postcode":"6392",
    "sg:province":"Danmark",
    "wof:name":"Karl Ommen",
    "wof:placetype":"venue"
},
  "geometry": {"coordinates":[9.2714967728,54.9919509888],"type":"Point"}
}