{
  "type": "Feature",
  "properties": {
    "addr:full":"Vestergade 44 Vojens Danmark 6500",
    "addr:housenumber":"44",
    "addr:postcode":"6500",
    "addr:street":"Vestergade",
    "iso:country":"DK",
    "sg:address":"Vestergade 44",
    "sg:city":"Vojens",
    "sg:orig_category":"Renserier",
    "sg:phone":"+45 74 54 18 48",
    "sg:postcode":"6500",
    "sg:province":"Danmark",
    "sg:website":"www.vojens-vaskogrens.dk",
    "wof:name":"Vojens Vask- og Renseri",
    "wof:placetype":"venue"
},
  "geometry": {"coordinates":[9.2972078323,55.2456436157],"type":"Point"}
}