{
  "type": "Feature",
  "properties": {
    "addr:full":"Egtvedvej 4, Veerst Vejen Danmark 6600",
    "addr:housenumber":"4",
    "addr:postcode":"6600",
    "addr:street":"Egtvedvej;Veerst",
    "iso:country":"DK",
    "sg:address":"Egtvedvej 4, Veerst",
    "sg:city":"Vejen",
    "sg:orig_category":"Planteskoler",
    "sg:phone":"+45 75 55 50 08",
    "sg:postcode":"6600",
    "sg:province":"Danmark",
    "wof:name":"Veerst Planter Engros",
    "wof:placetype":"venue"
},
  "geometry": {"coordinates":[9.1396121979,55.4778175354],"type":"Point"}
}