{
  "type": "Feature",
  "properties": {
    "iso:country":"DK",
    "sg:address":"Damagervej 24",
    "sg:city":"Viby",
    "sg:classifiers":[
        {
            "category":"Building & Trades",
            "subcategory":"Construction",
            "type":"Services"
        }
    ],
    "sg:phone":"+45 86 14 59 00",
    "sg:postcode":"8260",
    "sg:province":"Danmark",
    "sg:tags":[
        "ventilation"
    ],
    "wof:name":"Maass og Co. A/S",
    "wof:placetype":"venue"
},
  "geometry": {"coordinates":[10.1495246887,56.1324119568],"type":"Point"}
}