{
  "type": "Feature",
  "properties": {
    "addr:full":"S\u00f8nderklit 30 Skagen Danmark 9990",
    "addr:housenumber":"30",
    "addr:postcode":"9990",
    "addr:street":"Sonderklit",
    "iso:country":"DK",
    "sg:address":"S\u00f8nderklit 30",
    "sg:city":"Skagen",
    "sg:classifiers":[
        {
            "category":"Banks & Credit Unions",
            "subcategory":"Investment Brokerage",
            "type":"Services"
        }
    ],
    "sg:phone":"+45 98 44 54 61",
    "sg:postcode":"9990",
    "sg:province":"Danmark",
    "sg:tags":[
        "healing"
    ],
    "wof:name":"Diget, Anna-Marie",
    "wof:placetype":"venue"
},
  "geometry": {"coordinates":[10.5958003998,57.7247200012],"type":"Point"}
}