{
  "type": "Feature",
  "properties": {
    "addr:full":"Hovedgaden 41 Borup Danmark 4140",
    "addr:housenumber":"41",
    "addr:postcode":"4140",
    "addr:street":"Hovedgaden",
    "iso:country":"DK",
    "sg:address":"Hovedgaden 41",
    "sg:city":"Borup",
    "sg:orig_category":"Kirker",
    "sg:postcode":"4140",
    "sg:province":"Danmark",
    "wof:name":"Borup Kirke",
    "wof:placetype":"venue"
},
  "geometry": {"coordinates":[11.976111412,55.4985313416],"type":"Point"}
}