{
  "type": "Feature",
  "properties": {
    "addr:full":"Glaspustervej 2 Hanstholm Danmark 7730",
    "addr:housenumber":"2",
    "addr:postcode":"7730",
    "addr:street":"Glaspustervej",
    "iso:country":"DK",
    "sg:address":"Glaspustervej 2",
    "sg:city":"Hanstholm",
    "sg:orig_category":"Redningsberedskab",
    "sg:postcode":"7730",
    "sg:province":"Danmark",
    "wof:name":"Hanstholm Redningsberedskab",
    "wof:placetype":"venue"
},
  "geometry": {"coordinates":[8.6225538254,57.1159477234],"type":"Point"}
}