{
  "type": "Feature",
  "properties": {
    "addr:full":"Fmd.: S\u00f8ren Hald, Elmegaardsvej 6 Aalestrup Danmark 9620",
    "addr:housenumber":"6",
    "addr:postcode":"9620",
    "addr:street":"Elmegaardsvej",
    "iso:country":"DK",
    "sg:address":"Fmd.: S\u00f8ren Hald, Elmegaardsvej 6",
    "sg:city":"Aalestrup",
    "sg:orig_category":"Varmeforsyning",
    "sg:phone":"+45 98 64 13 55",
    "sg:postcode":"9620",
    "sg:province":"Danmark",
    "wof:name":"Aalestrup Varmev\u00e6rk A.m.b.A.",
    "wof:placetype":"venue"
},
  "geometry": {"coordinates":[9.4901504517,56.6938285828],"type":"Point"}
}