{
  "type": "Feature",
  "properties": {
    "addr:full":"N\u00f8rrebrogade 200, 4.th. K\u00f8benhavn N Danmark 2200",
    "addr:housenumber":"200 4.th kobenhavn",
    "addr:postcode":"2200",
    "addr:street":"Norrebrogade;N Danmark",
    "iso:country":"DK",
    "sg:address":"N\u00f8rrebrogade 200, 4.th.",
    "sg:city":"K\u00f8benhavn N",
    "sg:orig_category":"\u00c3\u02dcvrige foreninger",
    "sg:phone":"+45 35 85 29 59",
    "sg:postcode":"2200",
    "sg:province":"Danmark",
    "wof:name":"Innospace",
    "wof:placetype":"venue"
},
  "geometry": {"coordinates":[-76.4168395996,37.452419281],"type":"Point"}
}