{
  "type": "Feature",
  "properties": {
    "addr:full":"Vissenbjergvej 4 Odense M Danmark 5230",
    "addr:housenumber":"4",
    "addr:postcode":"5230",
    "addr:street":"Vissenbjergvej",
    "iso:country":"DK",
    "sg:address":"Vissenbjergvej 4",
    "sg:city":"Odense M",
    "sg:orig_category":"Reklamebureauer",
    "sg:phone":"+45 65 91 95 37",
    "sg:postcode":"5230",
    "sg:province":"Danmark",
    "wof:name":"Rasmussens Skilte",
    "wof:placetype":"venue"
},
  "geometry": {"coordinates":[10.4080963135,55.386089325],"type":"Point"}
}