{
  "type": "Feature",
  "properties": {
    "addr:full":"Linien 32 Haarby Danmark 5683",
    "addr:housenumber":"32",
    "addr:postcode":"5683",
    "addr:street":"Linien",
    "iso:country":"DK",
    "sg:address":"Linien 32",
    "sg:city":"Haarby",
    "sg:orig_category":"Murermestre",
    "sg:phone":"+45 64 73 35 06",
    "sg:postcode":"5683",
    "sg:province":"Danmark",
    "wof:name":"BN Totalbyg I/S",
    "wof:placetype":"venue"
},
  "geometry": {"coordinates":[10.1280546188,55.2360801697],"type":"Point"}
}