{
  "type": "Feature",
  "properties": {
    "addr:full":"Havnevej 2 Aabenraa Danmark 6200",
    "addr:housenumber":"2",
    "addr:postcode":"6200",
    "addr:street":"Havnevej",
    "iso:country":"DK",
    "sg:address":"Havnevej 2",
    "sg:city":"Aabenraa",
    "sg:orig_category":"Faglige organisationer og foreninger",
    "sg:phone":"+45 74 62 21 87",
    "sg:postcode":"6200",
    "sg:province":"Danmark",
    "wof:name":"SID, Aabenraa-R\u00f8dekro",
    "wof:placetype":"venue"
},
  "geometry": {"coordinates":[9.4224023819,55.0432281494],"type":"Point"}
}