{
  "type": "Feature",
  "properties": {
    "addr:full":"Ulvevej 65 Esbjerg N Danmark 6715",
    "addr:housenumber":"65",
    "addr:postcode":"6715",
    "addr:street":"Ulvevej",
    "iso:country":"DK",
    "sg:address":"Ulvevej 65",
    "sg:city":"Esbjerg N",
    "sg:orig_category":"Handicapboliger",
    "sg:phone":"+45 75 45 16 56",
    "sg:postcode":"6715",
    "sg:province":"Danmark",
    "wof:name":"Vestkysthusene, Bo- og udviklingscentret",
    "wof:placetype":"venue"
},
  "geometry": {"coordinates":[8.4503231049,55.5077857971],"type":"Point"}
}