{
  "type": "Feature",
  "properties": {
    "addr:full":"Nygaardsvej 5 Vejen Danmark 6600",
    "addr:housenumber":"5",
    "addr:postcode":"6600",
    "addr:street":"Nygaardsvej",
    "iso:country":"DK",
    "sg:address":"Nygaardsvej 5",
    "sg:city":"Vejen",
    "sg:orig_category":"Autoudlejning",
    "sg:phone":"+45 75 36 03 47",
    "sg:postcode":"6600",
    "sg:province":"Danmark",
    "wof:name":"Duchs Biler",
    "wof:placetype":"venue"
},
  "geometry": {"coordinates":[9.1369009018,55.4700393677],"type":"Point"}
}