{
  "type": "Feature",
  "properties": {
    "addr:full":"Tingstedet 94, Voldb\u00e6k Brabrand Danmark 8220",
    "addr:housenumber":"94",
    "addr:postcode":"8220",
    "addr:street":"Tingstedet",
    "iso:country":"DK",
    "sg:address":"Tingstedet 94, Voldb\u00e6k",
    "sg:city":"Brabrand",
    "sg:orig_category":"Psykologer, praktiserende",
    "sg:phone":"+45 86 26 03 64",
    "sg:postcode":"8220",
    "sg:province":"Danmark",
    "wof:name":"Bremer, Karin",
    "wof:placetype":"venue"
},
  "geometry": {"coordinates":[10.1293649673,56.1601295471],"type":"Point"}
}