{
  "type": "Feature",
  "properties": {
    "addr:full":"Englandsvej 270 Kastrup Danmark 2770",
    "addr:housenumber":"270",
    "addr:postcode":"2770",
    "addr:street":"Englandsvej",
    "iso:country":"DK",
    "sg:address":"Englandsvej 270",
    "sg:city":"Kastrup",
    "sg:orig_category":"Revisorer",
    "sg:phone":"+45 32 52 23 53",
    "sg:postcode":"2770",
    "sg:province":"Danmark",
    "wof:name":"Gutfelt & Ploug",
    "wof:placetype":"venue"
},
  "geometry": {"coordinates":[12.6009998322,55.6344985962],"type":"Point"}
}