{
  "type": "Feature",
  "properties": {
    "iso:country":"DK",
    "sg:address":"Thrigesvej 20",
    "sg:city":"Ikast",
    "sg:orig_category":"Sliberier",
    "sg:phone":"+45 97 25 05 33",
    "sg:postcode":"7430",
    "sg:province":"Danmark",
    "wof:name":"Dansk\u00e6r Ikast A/S",
    "wof:placetype":"venue"
},
  "geometry": {"coordinates":[9.1414899826,56.1219940186],"type":"Point"}
}