{
  "type": "Feature",
  "properties": {
    "addr:full":"Kelleklintevej 7 Jerslev Sj\u00e6lland Danmark 4490",
    "addr:housenumber":"7",
    "addr:postcode":"4490",
    "addr:street":"Kelleklintevej",
    "iso:country":"DK",
    "sg:address":"Kelleklintevej 7",
    "sg:city":"Jerslev Sj\u00e6lland",
    "sg:orig_category":"Rejsebureauer",
    "sg:phone":"+45 59 59 50 53",
    "sg:postcode":"4490",
    "sg:province":"Danmark",
    "sg:website":"www.ugrejser.dk",
    "wof:name":"UG Rejser",
    "wof:placetype":"venue"
},
  "geometry": {"coordinates":[11.2560224533,55.623840332],"type":"Point"}
}