{
  "type": "Feature",
  "properties": {
    "addr:full":"Strandvejen 86 - 90 K\u00f8ge Danmark 4600",
    "addr:housenumber":"86 90",
    "addr:postcode":"4600",
    "addr:street":"Strandvejen",
    "iso:country":"DK",
    "sg:address":"Strandvejen 86 - 90",
    "sg:city":"K\u00f8ge",
    "sg:orig_category":"Servicestationer",
    "sg:phone":"+45 56 65 30 83",
    "sg:postcode":"4600",
    "sg:province":"Danmark",
    "wof:name":"Statoil Servicenter",
    "wof:placetype":"venue"
},
  "geometry": {"coordinates":[12.1904306412,55.4474868774],"type":"Point"}
}