{
  "type": "Feature",
  "properties": {
    "addr:full":"Fmd.: Karin Schmidt Nielsen, Danland \u00d8er Maritime Ferieby, \u00d8erkrogvejen 2, Ebeltoft Maritime Ferie Ebeltoft Danmark 8400",
    "addr:housenumber":"2",
    "addr:postcode":"ferie;8400",
    "addr:street":"Maritime Ferieby Oerkrogvejen",
    "iso:country":"DK",
    "sg:address":"Fmd.: Karin Schmidt Nielsen, Danland \u00d8er Maritime Ferieby, \u00d8erkrogvejen 2, Ebeltoft Maritime Ferie",
    "sg:city":"Ebeltoft",
    "sg:orig_category":"Turistforeninger",
    "sg:postcode":"8400",
    "sg:province":"Danmark",
    "wof:name":"Turistforeningen for Ebeltoft og Mols",
    "wof:placetype":"venue"
},
  "geometry": {"coordinates":[10.6778697968,56.199798584],"type":"Point"}
}