{
  "type": "Feature",
  "properties": {
    "addr:full":"Haderslevvej 67 Kolding Danmark 6000",
    "addr:housenumber":"67",
    "addr:postcode":"6000",
    "addr:street":"Haderslevvej",
    "iso:country":"DK",
    "sg:address":"Haderslevvej 67",
    "sg:city":"Kolding",
    "sg:orig_category":"Autoreparation og -service",
    "sg:phone":"+45 75 53 36 44",
    "sg:postcode":"6000",
    "sg:province":"Danmark",
    "wof:name":"Center Auto",
    "wof:placetype":"venue"
},
  "geometry": {"coordinates":[9.4696979523,55.4825744629],"type":"Point"}
}