{
  "type": "Feature",
  "properties": {
    "addr:full":"Overgade 53 Odense C Danmark 5000",
    "addr:housenumber":"53",
    "addr:postcode":"5000",
    "addr:street":"Overgade",
    "iso:country":"DK",
    "sg:address":"Overgade 53",
    "sg:city":"Odense C",
    "sg:orig_category":"Leasing, erhverv",
    "sg:phone":"+45 66 19 03 27",
    "sg:postcode":"5000",
    "sg:province":"Danmark",
    "wof:name":"Krogh, Aino Polk",
    "wof:placetype":"venue"
},
  "geometry": {"coordinates":[10.3942594528,55.3977622986],"type":"Point"}
}