{
  "type": "Feature",
  "properties": {
    "addr:full":"S\u00f8parken 133, Hjallese Odense S Danmark 5260",
    "addr:housenumber":"133",
    "addr:postcode":"5260",
    "addr:street":"Soparken;Hjallese",
    "iso:country":"DK",
    "sg:address":"S\u00f8parken 133, Hjallese",
    "sg:city":"Odense S",
    "sg:orig_category":"Murermestre",
    "sg:phone":"+45 66 15 07 83",
    "sg:postcode":"5260",
    "sg:province":"Danmark",
    "wof:name":"Aaskov, Gunner",
    "wof:placetype":"venue"
},
  "geometry": {"coordinates":[10.3157806396,55.3122825623],"type":"Point"}
}