{
  "type": "Feature",
  "properties": {
    "addr:full":"Granlunden 74 Esbjerg \u00d8 Danmark 6705",
    "addr:housenumber":"74",
    "addr:postcode":"6705",
    "addr:street":"Granlunden;Danmark",
    "iso:country":"DK",
    "sg:address":"Granlunden 74",
    "sg:city":"Esbjerg \u00d8",
    "sg:orig_category":"Malermestre",
    "sg:phone":"+45 75 14 08 90",
    "sg:postcode":"6705",
    "sg:province":"Danmark",
    "wof:name":"T\u00f8nder A/S, Malerfirmaet Vagn",
    "wof:placetype":"venue"
},
  "geometry": {"coordinates":[8.4892158508,55.4979782104],"type":"Point"}
}