{
  "type": "Feature",
  "properties": {
    "addr:full":"Kredsleder: Jan Vestentoft, Vinkelvej 13 Struer Danmark 7600",
    "addr:housenumber":"13",
    "addr:postcode":"7600",
    "addr:street":"Vinkelvej",
    "iso:country":"DK",
    "sg:address":"Kredsleder: Jan Vestentoft, Vinkelvej 13",
    "sg:city":"Struer",
    "sg:orig_category":"Beredskabsforbund",
    "sg:phone":"+45 97 84 03 31",
    "sg:postcode":"7600",
    "sg:province":"Danmark",
    "wof:name":"Beredskabs Forbundet",
    "wof:placetype":"venue"
},
  "geometry": {"coordinates":[8.59469,56.491192],"type":"Point"}
}