{
  "type": "Feature",
  "properties": {
    "addr:full":"R\u00e5dhuset, Toftevej 1 Holeby Danmark 4960",
    "addr:housenumber":"1",
    "addr:postcode":"4960",
    "addr:street":"Toftevej",
    "iso:country":"DK",
    "sg:address":"R\u00e5dhuset, Toftevej 1",
    "sg:city":"Holeby",
    "sg:orig_category":"Kommunen",
    "sg:phone":"+45 54 69 02 09",
    "sg:postcode":"4960",
    "sg:province":"Danmark",
    "sg:website":"www.nethotel.dk/holebykom/",
    "wof:name":"Holeby Kommune",
    "wof:placetype":"venue"
},
  "geometry": {"coordinates":[11.4715652466,54.7092895508],"type":"Point"}
}