{
  "type": "Feature",
  "properties": {
    "iso:country":"DK",
    "sg:address":"Vesterbrogade 1 A",
    "sg:city":"Fredericia",
    "sg:orig_category":"Blomsterhandlere",
    "sg:phone":"+45 75 93 03 53",
    "sg:postcode":"7000",
    "sg:province":"Danmark",
    "wof:name":"Blomster Pavillonen",
    "wof:placetype":"venue"
},
  "geometry": {"coordinates":[9.7468004227,55.5690612793],"type":"Point"}
}