{
  "type": "Feature",
  "properties": {
    "addr:full":"Vigsn\u00e6s Byvej 21 Guldborg Danmark 4862",
    "addr:housenumber":"21",
    "addr:postcode":"4862",
    "addr:street":"Vigsnaes Byvej",
    "iso:country":"DK",
    "sg:address":"Vigsn\u00e6s Byvej 21",
    "sg:city":"Guldborg",
    "sg:orig_category":"HOTELS: OG MOTELLER",
    "sg:phone":"+45 54 77 20 05",
    "sg:postcode":"4862",
    "sg:province":"Danmark",
    "wof:name":"Vigsn\u00e6s Gl. Skole",
    "wof:placetype":"venue"
},
  "geometry": {"coordinates":[11.7405948639,54.8682060242],"type":"Point"}
}