{
  "type": "Feature",
  "properties": {
    "addr:full":"Klostergade 32 \u00c5rhus C Danmark 8000",
    "addr:housenumber":"32",
    "addr:postcode":"8000",
    "addr:street":"Klostergade",
    "iso:country":"DK",
    "sg:address":"Klostergade 32",
    "sg:city":"\u00c5rhus C",
    "sg:orig_category":"Grillbarer",
    "sg:phone":"+45 86 12 19 52",
    "sg:postcode":"8000",
    "sg:province":"Danmark",
    "wof:name":"Karls Sandwichbar",
    "wof:placetype":"venue"
},
  "geometry": {"coordinates":[4.717400074,49.7588005066],"type":"Point"}
}