{
  "type": "Feature",
  "properties": {
    "addr:full":"Vestergade 51 Horsens Danmark 8700",
    "addr:housenumber":"51",
    "addr:postcode":"8700",
    "addr:street":"Vestergade",
    "iso:country":"DK",
    "sg:address":"Vestergade 51",
    "sg:city":"Horsens",
    "sg:orig_category":"Grillbarer",
    "sg:phone":"+45 75 60 22 20",
    "sg:postcode":"8700",
    "sg:province":"Danmark",
    "wof:name":"Vestergade's Grill Cafe",
    "wof:placetype":"venue"
},
  "geometry": {"coordinates":[9.8392963409,55.8703956604],"type":"Point"}
}