{
  "type": "Feature",
  "properties": {
    "addr:full":"Centrumgaden 8 Ballerup Danmark 2750",
    "addr:housenumber":"8",
    "addr:postcode":"2750",
    "addr:street":"Centrumgaden",
    "iso:country":"DK",
    "sg:address":"Centrumgaden 8",
    "sg:city":"Ballerup",
    "sg:orig_category":"Optikere",
    "sg:phone":"+45 44 97 12 60",
    "sg:postcode":"2750",
    "sg:province":"Danmark",
    "sg:website":"www.profiloptik-ballerup.dk",
    "wof:name":"Profil Optik",
    "wof:placetype":"venue"
},
  "geometry": {"coordinates":[12.3606433868,55.7312088013],"type":"Point"}
}