{
  "type": "Feature",
  "properties": {
    "addr:full":"Storegade 3 Horsens Danmark 8700",
    "addr:housenumber":"3",
    "addr:postcode":"8700",
    "addr:street":"Storegade",
    "iso:country":"DK",
    "sg:address":"Storegade 3",
    "sg:city":"Horsens",
    "sg:orig_category":"Grillbarer",
    "sg:phone":"+45 75 65 32 20",
    "sg:postcode":"8700",
    "sg:province":"Danmark",
    "wof:name":"Hatting Grill & Bodega",
    "wof:placetype":"venue"
},
  "geometry": {"coordinates":[9.7619190216,55.8542442322],"type":"Point"}
}