{
  "type": "Feature",
  "properties": {
    "addr:full":"M\u00f8llergade 32 Svendborg Danmark 5700",
    "addr:housenumber":"32",
    "addr:postcode":"5700",
    "addr:street":"Mollergade",
    "iso:country":"DK",
    "sg:address":"M\u00f8llergade 32",
    "sg:city":"Svendborg",
    "sg:orig_category":"RESTAURANTS: CAFEER",
    "sg:phone":"+45 62 21 09 01",
    "sg:postcode":"5700",
    "sg:province":"Danmark",
    "wof:name":"Rob Roy Inn",
    "wof:placetype":"venue"
},
  "geometry": {"coordinates":[10.6109008789,55.060256958],"type":"Point"}
}