{
  "type": "Feature",
  "properties": {
    "iso:country":"DK",
    "sg:address":"Hedelundvej 9",
    "sg:city":"Esbjerg \u00d8",
    "sg:orig_category":"Serigrafi",
    "sg:phone":"+45 75 47 10 66",
    "sg:postcode":"6705",
    "sg:province":"Danmark",
    "wof:name":"Deko-Art",
    "wof:placetype":"venue"
},
  "geometry": {"coordinates":[8.496495,55.482548],"type":"Point"}
}