{
  "type": "Feature",
  "properties": {
    "addr:full":"Vardevej 11 Tarm Danmark 6880",
    "addr:housenumber":"11",
    "addr:postcode":"6880",
    "addr:street":"Vardevej",
    "iso:country":"DK",
    "sg:address":"Vardevej 11",
    "sg:city":"Tarm",
    "sg:orig_category":"Kommunale folkeskoler",
    "sg:phone":"+45 99 48 21 00",
    "sg:postcode":"6880",
    "sg:province":"Danmark",
    "wof:name":"Tarm Skole",
    "wof:placetype":"venue"
},
  "geometry": {"coordinates":[8.5183105469,55.9032173157],"type":"Point"}
}