{
  "type": "Feature",
  "properties": {
    "iso:country":"DK",
    "sg:address":"Kirkebakken 26",
    "sg:city":"Hampen",
    "sg:orig_category":"Kirker",
    "sg:postcode":"7362",
    "sg:province":"Danmark",
    "wof:name":"Hampen Kirke",
    "wof:placetype":"venue"
},
  "geometry": {"coordinates":[9.3549957275,56.0112915039],"type":"Point"}
}