{
  "type": "Feature",
  "properties": {
    "addr:full":"Pr\u00e6stbrovej 317, \u00d8ster J\u00f8lby Erslev Danmark 7950",
    "addr:housenumber":"317",
    "addr:postcode":"7950",
    "addr:street":"Praestbrovej;Jolby",
    "iso:country":"DK",
    "sg:address":"Pr\u00e6stbrovej 317, \u00d8ster J\u00f8lby",
    "sg:city":"Erslev",
    "sg:orig_category":"Cafeterier",
    "sg:phone":"+45 97 74 13 10",
    "sg:postcode":"7950",
    "sg:province":"Danmark",
    "wof:name":"Hyggestedet",
    "wof:placetype":"venue"
},
  "geometry": {"coordinates":[8.7200698853,56.8354682922],"type":"Point"}
}