{
  "type": "Feature",
  "properties": {
    "addr:full":"Rosenh\u00f8j 14 B Viby Danmark 8260",
    "addr:housenumber":"14 b",
    "addr:postcode":"8260",
    "addr:street":"Rosenhoj",
    "iso:country":"DK",
    "sg:address":"Rosenh\u00f8j 14 B",
    "sg:city":"Viby",
    "sg:orig_category":"Psykologer, praktiserende",
    "sg:phone":"+45 86 29 62 22",
    "sg:postcode":"8260",
    "sg:province":"Danmark",
    "wof:name":"Hatt, Gunnar",
    "wof:placetype":"venue"
},
  "geometry": {"coordinates":[10.1446695328,56.1161384583],"type":"Point"}
}