{
  "type": "Feature",
  "properties": {
    "addr:full":"Kirkevej 2, Bastrup Vamdrup Danmark 6580",
    "addr:housenumber":"2",
    "addr:postcode":"6580",
    "addr:street":"Kirkevej;Bastrup",
    "iso:country":"DK",
    "sg:address":"Kirkevej 2, Bastrup",
    "sg:city":"Vamdrup",
    "sg:orig_category":"Pelsdyravl",
    "sg:phone":"+45 75 58 13 73",
    "sg:postcode":"6580",
    "sg:province":"Danmark",
    "wof:name":"Bastrup Pelsdyrfarm ApS",
    "wof:placetype":"venue"
},
  "geometry": {"coordinates":[9.2839107513,55.4266548157],"type":"Point"}
}