{
  "type": "Feature",
  "properties": {
    "addr:full":"Gr\u00e6kenlandsvej 22 K\u00f8benhavn S Danmark 2300",
    "addr:housenumber":"22",
    "addr:postcode":"2300",
    "addr:street":"Graekenlandsvej;S Danmark",
    "iso:country":"DK",
    "sg:address":"Gr\u00e6kenlandsvej 22",
    "sg:city":"K\u00f8benhavn S",
    "sg:orig_category":"Pizzeriaer",
    "sg:phone":"+45 32 59 14 15",
    "sg:postcode":"2300",
    "sg:province":"Danmark",
    "wof:name":"Pappas Pizza",
    "wof:placetype":"venue"
},
  "geometry": {"coordinates":[-78.1299133301,36.7267417908],"type":"Point"}
}