{
  "type": "Feature",
  "properties": {
    "addr:full":"Nyropsgade 47 K\u00f8benhavn Danmark 1602",
    "addr:housenumber":"47;1602",
    "addr:street":"Nyropsgade",
    "iso:country":"DK",
    "sg:address":"Nyropsgade 47",
    "sg:city":"K\u00f8benhavn",
    "sg:orig_category":"Flyvning",
    "sg:phone":"+45 33 12 22 11",
    "sg:postcode":"1602",
    "sg:province":"Danmark",
    "sg:website":"www.lanchile.com",
    "wof:name":"Lan Chile",
    "wof:placetype":"venue"
},
  "geometry": {"coordinates":[12.5633001328,55.6786003113],"type":"Point"}
}