{
  "type": "Feature",
  "properties": {
    "iso:country":"DK",
    "sg:address":"Greve Strandvej 4 C",
    "sg:city":"Greve",
    "sg:orig_category":"Typehuse",
    "sg:phone":"+45 43 69 04 04",
    "sg:postcode":"2670",
    "sg:province":"Danmark",
    "sg:website":"www.alti-byg.dk",
    "wof:name":"Alti-Byg",
    "wof:placetype":"venue"
},
  "geometry": {"coordinates":[12.3128547668,55.5830688477],"type":"Point"}
}