{
  "type": "Feature",
  "properties": {
    "addr:full":"T\u00f8ndervej 50, Sdr. Farup M Ribe Danmark 6760",
    "addr:housenumber":"50",
    "addr:postcode":"6760",
    "addr:street":"Tondervej;Sdr. Farup M",
    "iso:country":"DK",
    "sg:address":"T\u00f8ndervej 50, Sdr. Farup M",
    "sg:city":"Ribe",
    "sg:orig_category":"Isolering",
    "sg:phone":"+45 75 42 49 50",
    "sg:postcode":"6760",
    "sg:province":"Danmark",
    "wof:name":"Konge \u00c5 Isolering",
    "wof:placetype":"venue"
},
  "geometry": {"coordinates":[8.7656240463,55.3297042847],"type":"Point"}
}