{
  "type": "Feature",
  "properties": {
    "addr:full":"Jens Baggesens Vej 94 \u00c5rhus N Danmark 8200",
    "addr:housenumber":"94",
    "addr:postcode":"8200",
    "addr:street":"Jens Baggesens Vej",
    "iso:country":"DK",
    "sg:address":"Jens Baggesens Vej 94",
    "sg:city":"\u00c5rhus N",
    "sg:orig_category":"Vuggestuer",
    "sg:phone":"+45 86 16 30 14",
    "sg:postcode":"8200",
    "sg:province":"Danmark",
    "wof:name":"Katrinebjergparken, Vuggestue",
    "wof:placetype":"venue"
},
  "geometry": {"coordinates":[-76.4168395996,37.452419281],"type":"Point"}
}