{
  "type": "Feature",
  "properties": {
    "addr:full":"Marstrup Bygade 108 Haderslev Danmark 6100",
    "addr:housenumber":"108",
    "addr:postcode":"6100",
    "addr:street":"Marstrup Bygade",
    "iso:country":"DK",
    "sg:address":"Marstrup Bygade 108",
    "sg:city":"Haderslev",
    "sg:orig_category":"Blikkenslagere",
    "sg:phone":"+45 74 57 59 42",
    "sg:postcode":"6100",
    "sg:province":"Danmark",
    "wof:name":"Rohde, H. M.",
    "wof:placetype":"venue"
},
  "geometry": {"coordinates":[9.426361,55.199902],"type":"Point"}
}