{
  "type": "Feature",
  "properties": {
    "addr:full":"Bag Klostret 19 B Slagelse Danmark 4200",
    "addr:housenumber":"19 b",
    "addr:postcode":"4200",
    "addr:street":"Klostret",
    "iso:country":"DK",
    "sg:address":"Bag Klostret 19 B",
    "sg:city":"Slagelse",
    "sg:orig_category":"Fodterapeuter",
    "sg:phone":"+45 58 50 40 70",
    "sg:postcode":"4200",
    "sg:province":"Danmark",
    "wof:name":"Hallebye-Hansen, Hanne",
    "wof:placetype":"venue"
},
  "geometry": {"coordinates":[11.3488168716,55.4005737305],"type":"Point"}
}