{
  "type": "Feature",
  "properties": {
    "addr:full":"Sverigesvej 6 Hammel Danmark 8450",
    "addr:housenumber":"6",
    "addr:postcode":"8450",
    "addr:street":"Sverigesvej",
    "iso:country":"DK",
    "sg:address":"Sverigesvej 6",
    "sg:city":"Hammel",
    "sg:orig_category":"Maskinfabrikker",
    "sg:phone":"+45 86 96 95 11",
    "sg:postcode":"8450",
    "sg:province":"Danmark",
    "wof:name":"Jsp Maskinfabrik A/S",
    "wof:placetype":"venue"
},
  "geometry": {"coordinates":[9.8527488708,56.2495727539],"type":"Point"}
}