{
  "type": "Feature",
  "properties": {
    "addr:full":"Hjermvej 94 Hjerm Danmark 7560",
    "addr:housenumber":"94",
    "addr:postcode":"7560",
    "addr:street":"Hjermvej",
    "iso:country":"DK",
    "sg:address":"Hjermvej 94",
    "sg:city":"Hjerm",
    "sg:orig_category":"Landboorganisationer",
    "sg:phone":"+45 97 46 49 93",
    "sg:postcode":"7560",
    "sg:province":"Danmark",
    "wof:name":"Fors\u00f8gsvirksomheden Ytteborg",
    "wof:placetype":"venue"
},
  "geometry": {"coordinates":[8.6210174561,56.4461097717],"type":"Point"}
}