{
  "type": "Feature",
  "properties": {
    "addr:full":"Mads Clausens Vej 32 Hj\u00f8rring Danmark 9800",
    "addr:housenumber":"32",
    "addr:postcode":"9800",
    "addr:street":"Mads Clausens Vej",
    "iso:country":"DK",
    "sg:address":"Mads Clausens Vej 32",
    "sg:city":"Hj\u00f8rring",
    "sg:orig_category":"Autolakering",
    "sg:phone":"+45 98 92 23 66",
    "sg:postcode":"9800",
    "sg:province":"Danmark",
    "wof:name":"Hj\u00f8rring Autolakering",
    "wof:placetype":"venue"
},
  "geometry": {"coordinates":[10.0066728592,57.4402961731],"type":"Point"}
}