{
  "type": "Feature",
  "properties": {
    "addr:full":"Vestbirkvej 26, Vestbirk \u00d8stbirk Danmark 8752",
    "addr:housenumber":"26",
    "addr:postcode":"8752",
    "addr:street":"Vestbirkvej",
    "iso:country":"DK",
    "sg:address":"Vestbirkvej 26, Vestbirk",
    "sg:city":"\u00d8stbirk",
    "sg:orig_category":"Musikstudier",
    "sg:phone":"+45 75 78 16 13",
    "sg:postcode":"8752",
    "sg:province":"Danmark",
    "wof:name":"NO, Studie",
    "wof:placetype":"venue"
},
  "geometry": {"coordinates":[9.7709598541,56.0007743835],"type":"Point"}
}