{
  "type": "Feature",
  "properties": {
    "iso:country":"DK",
    "sg:address":"Brillantvej 24",
    "sg:city":"Jyllinge",
    "sg:orig_category":"Virksomhedskonsulenter",
    "sg:phone":"+45 46 78 95 01",
    "sg:postcode":"4040",
    "sg:province":"Danmark",
    "wof:name":"Dan Consult",
    "wof:placetype":"venue"
},
  "geometry": {"coordinates":[12.1119718552,55.7534408569],"type":"Point"}
}