{
  "type": "Feature",
  "properties": {
    "iso:country":"DK",
    "sg:address":"Tv\u00e6rmosevej 2",
    "sg:city":"Horbelev",
    "sg:orig_category":"Campingpladser",
    "sg:phone":"+45 54 44 52 19",
    "sg:postcode":"4871",
    "sg:province":"Danmark",
    "wof:name":"\u00d8stfalsters Familiecamping",
    "wof:placetype":"venue"
},
  "geometry": {"coordinates":[12.0522689819,54.8084869385],"type":"Point"}
}