{
  "type": "Feature",
  "properties": {
    "addr:full":"Glentevej 28 K\u00f8ge Danmark 4600",
    "addr:housenumber":"28",
    "addr:postcode":"4600",
    "addr:street":"Glentevej",
    "iso:country":"DK",
    "sg:address":"Glentevej 28",
    "sg:city":"K\u00f8ge",
    "sg:orig_category":"Murermestre",
    "sg:phone":"+45 56 64 36 37",
    "sg:postcode":"4600",
    "sg:province":"Danmark",
    "sg:website":"www.koege-byg.dk",
    "wof:name":"K\u00f8ge Bygningsentreprise A/S",
    "wof:placetype":"venue"
},
  "geometry": {"coordinates":[10.0347900391,56.4765014648],"type":"Point"}
}