{
  "type": "Feature",
  "properties": {
    "addr:full":"Gl. Hejlsmindevej 16, Anslet Haderslev Danmark 6100",
    "addr:housenumber":"16",
    "addr:postcode":"6100",
    "addr:street":"Gl. Hejlsmindevej;Anslet",
    "iso:country":"DK",
    "sg:address":"Gl. Hejlsmindevej 16, Anslet",
    "sg:city":"Haderslev",
    "sg:orig_category":"Malermestre",
    "sg:phone":"+45 74 56 60 44",
    "sg:postcode":"6100",
    "sg:province":"Danmark",
    "wof:name":"Flexlakering",
    "wof:placetype":"venue"
},
  "geometry": {"coordinates":[9.4879703522,55.2505493164],"type":"Point"}
}