{
  "type": "Feature",
  "properties": {
    "addr:full":"N\u00f8rremarken 10 Ansager Danmark 6823",
    "addr:housenumber":"10",
    "addr:postcode":"6823",
    "addr:street":"Norremarken",
    "iso:country":"DK",
    "sg:address":"N\u00f8rremarken 10",
    "sg:city":"Ansager",
    "sg:orig_category":"Varmeforsyning",
    "sg:phone":"+45 75 29 24 76",
    "sg:postcode":"6823",
    "sg:province":"Danmark",
    "wof:name":"Skovlund Varmev\u00e6rk",
    "wof:placetype":"venue"
},
  "geometry": {"coordinates":[8.7062625885,55.7406997681],"type":"Point"}
}