{
  "type": "Feature",
  "properties": {
    "addr:full":"Vestervangsvej 70 Hammel Danmark 8450",
    "addr:housenumber":"70",
    "addr:postcode":"8450",
    "addr:street":"Vestervangsvej",
    "iso:country":"DK",
    "sg:address":"Vestervangsvej 70",
    "sg:city":"Hammel",
    "sg:orig_category":"Automater",
    "sg:phone":"+45 86 96 36 73",
    "sg:postcode":"8450",
    "sg:province":"Danmark",
    "wof:name":"Eriks Automat Service",
    "wof:placetype":"venue"
},
  "geometry": {"coordinates":[9.8561477661,56.2588386536],"type":"Point"}
}