{
  "type": "Feature",
  "properties": {
    "addr:full":"v/ Aase Lehmann, Hemmingsvej 55 Karise Danmark 4653",
    "addr:housenumber":"55",
    "addr:postcode":"4653",
    "addr:street":"Hemmingsvej",
    "iso:country":"DK",
    "sg:address":"v/ Aase Lehmann, Hemmingsvej 55",
    "sg:city":"Karise",
    "sg:orig_category":"\u00c3\u2020ldreorganisationer og klubber",
    "sg:phone":"+45 56 78 82 50",
    "sg:postcode":"4653",
    "sg:province":"Danmark",
    "wof:name":"\u00c6ldreklubben for Karise, Alslev Sogn m.v.",
    "wof:placetype":"venue"
},
  "geometry": {"coordinates":[12.1990203857,55.3030395508],"type":"Point"}
}