{
  "type": "Feature",
  "properties": {
    "addr:full":"Hammerholmen 34-36 Hvidovre Danmark 2650",
    "addr:postcode":"34-36;2650",
    "addr:street":"Hammerholmen",
    "iso:country":"DK",
    "sg:address":"Hammerholmen 34-36",
    "sg:city":"Hvidovre",
    "sg:classifiers":[
        {
            "category":"Harbor",
            "type":"Transportation"
        }
    ],
    "sg:phone":"+45 36 77 55 77",
    "sg:postcode":"2650",
    "sg:province":"Danmark",
    "sg:tags":[
        "shipping"
    ],
    "wof:name":"Breinholt C A/S",
    "wof:placetype":"venue"
},
  "geometry": {"coordinates":[12.482260704,55.6091651917],"type":"Point"}
}