{
  "type": "Feature",
  "properties": {
    "addr:full":"Over Hadstenvej 22 Hadsten Danmark 8370",
    "addr:housenumber":"22",
    "addr:postcode":"8370",
    "addr:street":"Over Hadstenvej",
    "iso:country":"DK",
    "sg:address":"Over Hadstenvej 22",
    "sg:city":"Hadsten",
    "sg:orig_category":"Autoreparation og -service",
    "sg:phone":"+45 86 98 09 09",
    "sg:postcode":"8370",
    "sg:province":"Danmark",
    "wof:name":"Bach, Jens",
    "wof:placetype":"venue"
},
  "geometry": {"coordinates":[10.0379991531,56.3183288574],"type":"Point"}
}