{
  "type": "Feature",
  "properties": {
    "iso:country":"DK",
    "sg:address":"Enrumvej 9",
    "sg:city":"Skodsborg",
    "sg:orig_category":"Trikotage",
    "sg:phone":"+45 45 89 22 17",
    "sg:postcode":"2942",
    "sg:province":"Danmark",
    "wof:name":"Allerup Agentur, Bente",
    "wof:placetype":"venue"
},
  "geometry": {"coordinates":[12.5694694519,55.8381118774],"type":"Point"}
}