{
  "type": "Feature",
  "properties": {
    "addr:full":"Strandvejen 2 Ebeltoft Danmark 8400",
    "addr:housenumber":"2",
    "addr:postcode":"8400",
    "addr:street":"Strandvejen",
    "iso:country":"DK",
    "sg:address":"Strandvejen 2",
    "sg:city":"Ebeltoft",
    "sg:orig_category":"Turistbureau og -information",
    "sg:phone":"+45 86 34 14 00",
    "sg:postcode":"8400",
    "sg:province":"Danmark",
    "sg:website":"www.ebeltoftturist.dk",
    "wof:name":"Ebeltoft/Mols Turistbureau",
    "wof:placetype":"venue"
},
  "geometry": {"coordinates":[10.6743202209,56.1973609924],"type":"Point"}
}