{
  "type": "Feature",
  "properties": {
    "addr:full":"Holkegade 6 Faaborg Danmark 5600",
    "addr:housenumber":"6",
    "addr:postcode":"5600",
    "addr:street":"Holkegade",
    "iso:country":"DK",
    "sg:address":"Holkegade 6",
    "sg:city":"Faaborg",
    "sg:orig_category":"Antikviteter",
    "sg:phone":"+45 62 61 13 61",
    "sg:postcode":"5600",
    "sg:province":"Danmark",
    "wof:name":"Faaborg Antikhandel",
    "wof:placetype":"venue"
},
  "geometry": {"coordinates":[10.2399044037,55.0955162048],"type":"Point"}
}