{
  "type": "Feature",
  "properties": {
    "addr:full":"Jyllandsgade 24 Randers Danmark 8900",
    "addr:housenumber":"24",
    "addr:postcode":"8900",
    "addr:street":"Jyllandsgade",
    "iso:country":"DK",
    "sg:address":"Jyllandsgade 24",
    "sg:city":"Randers",
    "sg:orig_category":"Private skoler",
    "sg:phone":"+45 86 42 90 23",
    "sg:postcode":"8900",
    "sg:province":"Danmark",
    "wof:name":"C. la Cours Skole",
    "wof:placetype":"venue"
},
  "geometry": {"coordinates":[10.0157337189,56.4644126892],"type":"Point"}
}