{
  "type": "Feature",
  "properties": {
    "iso:country":"DK",
    "sg:address":"Fmd.: Tommy Nielsen, Kingosvej 10",
    "sg:city":"Svendborg",
    "sg:orig_category":"Loger",
    "sg:phone":"+45 62 20 16 66",
    "sg:postcode":"5700",
    "sg:province":"Danmark",
    "wof:name":"Junior Chamber Svendborg",
    "wof:placetype":"venue"
},
  "geometry": {"coordinates":[10.6065101624,55.0595970154],"type":"Point"}
}