{
  "type": "Feature",
  "properties": {
    "addr:full":"Vilhelm Kyhns Vej 7 Odense M Danmark 5230",
    "addr:housenumber":"7",
    "addr:postcode":"5230",
    "addr:street":"Vilhelm Kyhns Vej",
    "iso:country":"DK",
    "sg:address":"Vilhelm Kyhns Vej 7",
    "sg:city":"Odense M",
    "sg:orig_category":"Revisorer",
    "sg:phone":"+45 66 11 30 94",
    "sg:postcode":"5230",
    "sg:province":"Danmark",
    "wof:name":"Nygaard, Ruth",
    "wof:placetype":"venue"
},
  "geometry": {"coordinates":[10.4187068939,55.3915557861],"type":"Point"}
}