{
  "type": "Feature",
  "properties": {
    "addr:full":"Havnegade 24 - 26 \u00c5rhus C Danmark 8000",
    "addr:housenumber":"24 26",
    "addr:postcode":"8000",
    "addr:street":"Havnegade",
    "iso:country":"DK",
    "sg:address":"Havnegade 24 - 26",
    "sg:city":"\u00c5rhus C",
    "sg:orig_category":"Akupunktur",
    "sg:phone":"+45 86 18 20 96",
    "sg:postcode":"8000",
    "sg:province":"Danmark",
    "wof:name":"Aku-Specialist Lien-Ping",
    "wof:placetype":"venue"
},
  "geometry": {"coordinates":[10.2122001648,56.1551017761],"type":"Point"}
}