{
  "type": "Feature",
  "properties": {
    "addr:full":"Fabriksvej 5 Saksk\u00f8bing Danmark 4990",
    "addr:housenumber":"5",
    "addr:postcode":"4990",
    "addr:street":"Fabriksvej",
    "iso:country":"DK",
    "sg:address":"Fabriksvej 5",
    "sg:city":"Saksk\u00f8bing",
    "sg:orig_category":"Integrerede institutioner",
    "sg:phone":"+45 54 70 62 49",
    "sg:postcode":"4990",
    "sg:province":"Danmark",
    "wof:name":"R\u00f8nnebakken",
    "wof:placetype":"venue"
},
  "geometry": {"coordinates":[-114.0767440796,46.4432487488],"type":"Point"}
}