{
  "type": "Feature",
  "properties": {
    "addr:full":"Gilleleje Strandvej 20 B Gilleleje Danmark 3250",
    "addr:housenumber":"20 b",
    "addr:postcode":"3250",
    "addr:street":"Gilleleje Strandvej",
    "iso:country":"DK",
    "sg:address":"Gilleleje Strandvej 20 B",
    "sg:city":"Gilleleje",
    "sg:orig_category":"Fabrikker",
    "sg:phone":"+45 48 30 08 00",
    "sg:postcode":"3250",
    "sg:province":"Danmark",
    "wof:name":"Werner Sikringer",
    "wof:placetype":"venue"
},
  "geometry": {"coordinates":[12.3018074036,56.1268692017],"type":"Point"}
}