{
  "type": "Feature",
  "properties": {
    "addr:full":"Dalvangsvej 56 B Glostrup Danmark 2600",
    "addr:housenumber":"56 b",
    "addr:postcode":"2600",
    "addr:street":"Dalvangsvej",
    "iso:country":"DK",
    "sg:address":"Dalvangsvej 56 B",
    "sg:city":"Glostrup",
    "sg:orig_category":"Fritidsklubber",
    "sg:phone":"+45 43 44 30 64",
    "sg:postcode":"2600",
    "sg:province":"Danmark",
    "wof:name":"Klub Dalvangen Fritidsklub",
    "wof:placetype":"venue"
},
  "geometry": {"coordinates":[12.4116163254,55.6691055298],"type":"Point"}
}