{
  "type": "Feature",
  "properties": {
    "addr:full":"\u00d8stergade 49 Gedsted Danmark 9631",
    "addr:housenumber":"49",
    "addr:postcode":"9631",
    "addr:street":"Ostergade",
    "iso:country":"DK",
    "sg:address":"\u00d8stergade 49",
    "sg:city":"Gedsted",
    "sg:orig_category":"Korn og foderstoffer",
    "sg:phone":"+45 98 64 53 33",
    "sg:postcode":"9631",
    "sg:province":"Danmark",
    "wof:name":"DLG",
    "wof:placetype":"venue"
},
  "geometry": {"coordinates":[9.3441667557,56.6901931763],"type":"Point"}
}