{
  "type": "Feature",
  "properties": {
    "addr:full":"Svendsgade 1 K\u00f8benhavn Danmark 1659",
    "addr:housenumber":"1",
    "addr:postcode":"1659",
    "addr:street":"Svendsgade",
    "iso:country":"DK",
    "sg:address":"Svendsgade 1",
    "sg:city":"K\u00f8benhavn",
    "sg:orig_category":"Cafeer",
    "sg:phone":"+45 33 31 19 08",
    "sg:postcode":"1659",
    "sg:province":"Danmark",
    "wof:name":"Caf\u00e9 Skammekrogen",
    "wof:placetype":"venue"
},
  "geometry": {"coordinates":[12.5548400879,55.672000885],"type":"Point"}
}