{
  "type": "Feature",
  "properties": {
    "addr:full":"Hobrovej 452 Aalborg SV Danmark 9200",
    "addr:housenumber":"452",
    "addr:postcode":"9200",
    "addr:street":"Hobrovej",
    "iso:country":"DK",
    "sg:address":"Hobrovej 452",
    "sg:city":"Aalborg SV",
    "sg:orig_category":"Guldsmede",
    "sg:phone":"+45 98 18 82 66",
    "sg:postcode":"9200",
    "sg:province":"Danmark",
    "wof:name":"Golden Times",
    "wof:placetype":"venue"
},
  "geometry": {"coordinates":[9.878490448,57.0030212402],"type":"Point"}
}