{
  "type": "Feature",
  "properties": {
    "addr:full":"Thun\u00f8gade 54 \u00c5rhus C Danmark 8000",
    "addr:housenumber":"54",
    "addr:postcode":"8000",
    "addr:street":"Thunogade",
    "iso:country":"DK",
    "sg:address":"Thun\u00f8gade 54",
    "sg:city":"\u00c5rhus C",
    "sg:orig_category":"Psykologer, praktiserende",
    "sg:phone":"+45 86 19 90 69",
    "sg:postcode":"8000",
    "sg:province":"Danmark",
    "wof:name":"Andersen, Jens",
    "wof:placetype":"venue"
},
  "geometry": {"coordinates":[99.92501068120001,34.2430114746],"type":"Point"}
}