{
  "type": "Feature",
  "properties": {
    "addr:full":"Sognepr\u00e6st: Karin Langballe (K/B), Sundbyvej 30, Sundby Guldborg Danmark 4862",
    "addr:housenumber":"30",
    "addr:postcode":"4862",
    "addr:street":"Sundbyvej;Sundby",
    "iso:country":"DK",
    "sg:address":"Sognepr\u00e6st: Karin Langballe (K/B), Sundbyvej 30, Sundby",
    "sg:city":"Guldborg",
    "sg:orig_category":"Kirkesogne",
    "sg:phone":"+45 54 43 22 58",
    "sg:postcode":"4862",
    "sg:province":"Danmark",
    "wof:name":"Stadager og Brarup Sogne",
    "wof:placetype":"venue"
},
  "geometry": {"coordinates":[11.7405948639,54.8682060242],"type":"Point"}
}