{
  "type": "Feature",
  "properties": {
    "addr:full":"Hjultorvet 7 Viborg Danmark 8800",
    "addr:housenumber":"7",
    "addr:postcode":"8800",
    "addr:street":"Hjultorvet",
    "iso:country":"DK",
    "sg:address":"Hjultorvet 7",
    "sg:city":"Viborg",
    "sg:orig_category":"Helsekost",
    "sg:phone":"+45 86 62 38 00",
    "sg:postcode":"8800",
    "sg:province":"Danmark",
    "wof:name":"Helsam",
    "wof:placetype":"venue"
},
  "geometry": {"coordinates":[9.408624649,56.4499969482],"type":"Point"}
}