{
  "type": "Feature",
  "properties": {
    "addr:full":"Industrivej 22, Stilling Skanderborg Danmark 8660",
    "addr:housenumber":"22",
    "addr:postcode":"8660",
    "addr:street":"Industrivej;Stilling",
    "iso:country":"DK",
    "sg:address":"Industrivej 22, Stilling",
    "sg:city":"Skanderborg",
    "sg:classifiers":[
        {
            "category":"Manufacturing",
            "subcategory":"Tools & Machinery",
            "type":"Manufacturing & Wholesale Goods"
        }
    ],
    "sg:phone":"+45 86 57 12 22",
    "sg:postcode":"8660",
    "sg:province":"Danmark",
    "sg:tags":[
        "environment",
        "equipment",
        "-"
    ],
    "sg:website":"http://www.eurowater.com",
    "wof:name":"SILHORKO-EUROWATER A/S",
    "wof:placetype":"venue"
},
  "geometry": {"coordinates":[9.929974556,56.0380249023],"type":"Point"}
}