{
  "type": "Feature",
  "properties": {
    "addr:full":"Fmd.: Harald Gr\u00f8nlund, S\u00f8ndervold 335 Grindsted Danmark 7200",
    "addr:housenumber":"335",
    "addr:postcode":"7200",
    "iso:country":"DK",
    "sg:address":"Fmd.: Harald Gr\u00f8nlund, S\u00f8ndervold 335",
    "sg:city":"Grindsted",
    "sg:orig_category":"Loger",
    "sg:phone":"+45 76 72 04 72",
    "sg:postcode":"7200",
    "sg:province":"Danmark",
    "wof:name":"Junior Chamber Grindsted/Billund",
    "wof:placetype":"venue"
},
  "geometry": {"coordinates":[8.9288702011,55.7560272217],"type":"Point"}
}