{
  "type": "Feature",
  "properties": {
    "addr:full":"Marinavejen 1 Kerteminde Danmark 5300",
    "addr:housenumber":"1",
    "addr:postcode":"5300",
    "addr:street":"Marinavejen",
    "iso:country":"DK",
    "sg:address":"Marinavejen 1",
    "sg:city":"Kerteminde",
    "sg:orig_category":"Minigolfbaner",
    "sg:phone":"+45 65 32 34 66",
    "sg:postcode":"5300",
    "sg:province":"Danmark",
    "wof:name":"Kerteminde Minigolf",
    "wof:placetype":"venue"
},
  "geometry": {"coordinates":[10.6622447968,55.4545974731],"type":"Point"}
}