{
  "type": "Feature",
  "properties": {
    "iso:country":"DK",
    "sg:address":"Sognepr\u00e6st: J\u00f8rgen H. Erbs (K/B), Vorup\u00f8rvej 231",
    "sg:city":"Thisted",
    "sg:orig_category":"Kirkesogne",
    "sg:phone":"+45 97 93 70 20",
    "sg:postcode":"7700",
    "sg:province":"Danmark",
    "wof:name":"Hundborg, Jannerup, Vang og Vorup\u00f8r Sogne",
    "wof:placetype":"venue"
},
  "geometry": {"coordinates":[8.6919784546,56.9556121826],"type":"Point"}
}