{
  "type": "Feature",
  "properties": {
    "addr:full":"Kirstineh\u00f8j 13 Kastrup Danmark 2770",
    "addr:housenumber":"13",
    "addr:postcode":"2770",
    "addr:street":"Kirstinehoj",
    "iso:country":"DK",
    "sg:address":"Kirstineh\u00f8j 13",
    "sg:city":"Kastrup",
    "sg:orig_category":"Industrilakering",
    "sg:phone":"+45 32 52 70 64",
    "sg:postcode":"2770",
    "sg:province":"Danmark",
    "wof:name":"Laduco Industrilakereri A/S",
    "wof:placetype":"venue"
},
  "geometry": {"coordinates":[12.6166448593,55.614200592],"type":"Point"}
}