{
  "type": "Feature",
  "properties": {
    "addr:full":"Egebjergvej 173 Horsens Danmark 8700",
    "addr:housenumber":"173",
    "addr:postcode":"8700",
    "addr:street":"Egebjergvej",
    "iso:country":"DK",
    "sg:address":"Egebjergvej 173",
    "sg:city":"Horsens",
    "sg:orig_category":"Posthuse",
    "sg:phone":"+45 75 65 62 11",
    "sg:postcode":"8700",
    "sg:province":"Danmark",
    "wof:name":"Post Danmark, Postbutikken i Egebjerg",
    "wof:placetype":"venue"
},
  "geometry": {"coordinates":[9.8343687057,55.9104728699],"type":"Point"}
}