{
  "type": "Feature",
  "properties": {
    "iso:country":"DK",
    "sg:address":"Industrivej 9",
    "sg:city":"Slagelse",
    "sg:orig_category":"Non-Classified Establishments",
    "sg:phone":"+45 58 52 51 71",
    "sg:postcode":"4200",
    "sg:province":"Danmark",
    "wof:name":"RESA, Revalideringsv\u00e6rksted",
    "wof:placetype":"venue"
},
  "geometry": {"coordinates":[11.3815574646,55.4124641418],"type":"Point"}
}