{
  "type": "Feature",
  "properties": {
    "addr:full":"Fmd.: Kurt Palmqvist, Gadesvinget 20 Greve Danmark 2670",
    "addr:housenumber":"20",
    "addr:postcode":"2670",
    "addr:street":"Gadesvinget",
    "iso:country":"DK",
    "sg:address":"Fmd.: Kurt Palmqvist, Gadesvinget 20",
    "sg:city":"Greve",
    "sg:orig_category":"Grundejerforeninger",
    "sg:phone":"+45 43 61 10 26",
    "sg:postcode":"2670",
    "sg:province":"Danmark",
    "wof:name":"Kildeg\u00e5rden Grundejerforening",
    "wof:placetype":"venue"
},
  "geometry": {"coordinates":[12.2941808701,55.5844078064],"type":"Point"}
}