{
  "type": "Feature",
  "properties": {
    "addr:full":"Gravene 15 Viborg Danmark 8800",
    "addr:housenumber":"15",
    "addr:postcode":"8800",
    "addr:street":"Gravene",
    "iso:country":"DK",
    "sg:address":"Gravene 15",
    "sg:city":"Viborg",
    "sg:orig_category":"Jagt- og fiskeudstyr",
    "sg:phone":"+45 86 62 05 05",
    "sg:postcode":"8800",
    "sg:province":"Danmark",
    "wof:name":"Jagt & Fiskeri",
    "wof:placetype":"venue"
},
  "geometry": {"coordinates":[9.4055480957,56.4506645203],"type":"Point"}
}