{
  "type": "Feature",
  "properties": {
    "addr:full":"Bymarken 17 Viby Sj\u00e6lland Danmark 4130",
    "addr:housenumber":"17",
    "addr:postcode":"4130",
    "addr:street":"Bymarken",
    "iso:country":"DK",
    "sg:address":"Bymarken 17",
    "sg:city":"Viby Sj\u00e6lland",
    "sg:orig_category":"Autoreparation og -service",
    "sg:phone":"+45 46 19 32 70",
    "sg:postcode":"4130",
    "sg:province":"Danmark",
    "wof:name":"LJ Auto",
    "wof:placetype":"venue"
},
  "geometry": {"coordinates":[12.0252981186,55.5439224243],"type":"Point"}
}