{
  "type": "Feature",
  "properties": {
    "addr:full":"Torvegade 2 Saksk\u00f8bing Danmark 4990",
    "addr:housenumber":"2",
    "addr:postcode":"4990",
    "addr:street":"Torvegade",
    "iso:country":"DK",
    "sg:address":"Torvegade 2",
    "sg:city":"Saksk\u00f8bing",
    "sg:classifiers":[
        {
            "category":"Restaurant",
            "type":"Food & Drink"
        }
    ],
    "sg:phone":"+45 54 70 40 77",
    "sg:postcode":"4990",
    "sg:province":"Danmark",
    "wof:name":"M\u00f8llestenen, Restaurant",
    "wof:placetype":"venue"
},
  "geometry": {"coordinates":[11.6360788345,54.7998962402],"type":"Point"}
}