{
  "type": "Feature",
  "properties": {
    "addr:full":"Byvejen 15, D\u00e5strup Viby Sj\u00e6lland Danmark 4130",
    "addr:housenumber":"15",
    "addr:postcode":"4130",
    "addr:street":"Byvejen",
    "iso:country":"DK",
    "sg:address":"Byvejen 15, D\u00e5strup",
    "sg:city":"Viby Sj\u00e6lland",
    "sg:orig_category":"Forsamlingshuse",
    "sg:postcode":"4130",
    "sg:province":"Danmark",
    "wof:name":"D\u00e5strup Forsamlingshus",
    "wof:placetype":"venue"
},
  "geometry": {"coordinates":[12.024274826,55.5473709106],"type":"Point"}
}