{
  "type": "Feature",
  "properties": {
    "addr:full":"Jernbanegade 9 K\u00f8ge Danmark 4600",
    "addr:housenumber":"9",
    "addr:postcode":"4600",
    "addr:street":"Jernbanegade",
    "iso:country":"DK",
    "sg:address":"Jernbanegade 9",
    "sg:city":"K\u00f8ge",
    "sg:orig_category":"Optikere",
    "sg:phone":"+45 56 64 05 45",
    "sg:postcode":"4600",
    "sg:province":"Danmark",
    "sg:website":"www.profiloptik.dk",
    "wof:name":"Profil Optik",
    "wof:placetype":"venue"
},
  "geometry": {"coordinates":[12.2430353165,55.4170417786],"type":"Point"}
}