{
  "type": "Feature",
  "properties": {
    "iso:country":"DK",
    "sg:address":"V\u00e6rftsvej 1",
    "sg:city":"Thybor\u00f8n",
    "sg:orig_category":"Skibsmalere",
    "sg:phone":"+45 97 83 21 40",
    "sg:postcode":"7680",
    "sg:province":"Danmark",
    "wof:name":"Anwo, Malerfirmaet",
    "wof:placetype":"venue"
},
  "geometry": {"coordinates":[8.2213115692,56.6927757263],"type":"Point"}
}