{
  "type": "Feature",
  "properties": {
    "addr:full":"Horsev\u00e6nget 9 Viby Sj\u00e6lland Danmark 4130",
    "addr:housenumber":"9",
    "addr:postcode":"4130",
    "addr:street":"Horsevaenget",
    "iso:country":"DK",
    "sg:address":"Horsev\u00e6nget 9",
    "sg:city":"Viby Sj\u00e6lland",
    "sg:orig_category":"Hydraulik",
    "sg:phone":"+45 46 19 36 73",
    "sg:postcode":"4130",
    "sg:province":"Danmark",
    "wof:name":"B.H. Service",
    "wof:placetype":"venue"
},
  "geometry": {"coordinates":[12.024274826,55.5473709106],"type":"Point"}
}