{
  "type": "Feature",
  "properties": {
    "addr:full":"Nybovej 5, Nybo Kvistg\u00e5rd Danmark 3490",
    "addr:housenumber":"5",
    "addr:postcode":"3490",
    "addr:street":"Nybovej",
    "iso:country":"DK",
    "sg:address":"Nybovej 5, Nybo",
    "sg:city":"Kvistg\u00e5rd",
    "sg:classifiers":[
        {
            "category":"Sports & Exercise",
            "subcategory":"Sports Center",
            "type":"Entertainment"
        }
    ],
    "sg:phone":"+45 49 19 14 78",
    "sg:postcode":"3490",
    "sg:province":"Danmark",
    "sg:tags":[
        "golf"
    ],
    "wof:name":"Simon's Golf Club",
    "wof:placetype":"venue"
},
  "geometry": {"coordinates":[12.5004415512,55.9893493652],"type":"Point"}
}