{
  "type": "Feature",
  "properties": {
    "addr:full":"Titangade 16 K\u00f8benhavn N Danmark 2200",
    "addr:housenumber":"16",
    "addr:postcode":"2200",
    "addr:street":"Titangade;N Danmark",
    "iso:country":"DK",
    "sg:address":"Titangade 16",
    "sg:city":"K\u00f8benhavn N",
    "sg:classifiers":[
        {
            "category":"Professional",
            "subcategory":"Computer Services",
            "type":"Services"
        }
    ],
    "sg:phone":"+45 70 22 03 22",
    "sg:postcode":"2200",
    "sg:province":"Danmark",
    "sg:tags":[
        "edb",
        "-",
        "software"
    ],
    "sg:website":"www.navipartner.dk",
    "wof:name":"Navi Partner K\u00f8benhavn Aps",
    "wof:placetype":"venue"
},
  "geometry": {"coordinates":[-94.2525939941,47.9151039124],"type":"Point"}
}