{
  "type": "Feature",
  "properties": {
    "addr:full":"Egeg\u00e5rdsvej 56 R\u00f8dovre Danmark 2610",
    "addr:housenumber":"56",
    "addr:postcode":"2610",
    "addr:street":"Egegaardsvej",
    "iso:country":"DK",
    "sg:address":"Egeg\u00e5rdsvej 56",
    "sg:city":"R\u00f8dovre",
    "sg:orig_category":"Autoreparation og -service",
    "sg:phone":"+45 36 72 35 85",
    "sg:postcode":"2610",
    "sg:province":"Danmark",
    "sg:website":"www.roedovre-automontering.dk",
    "wof:name":"R\u00f8dovre Automontering",
    "wof:placetype":"venue"
},
  "geometry": {"coordinates":[10.6992139816,61.1027755737],"type":"Point"}
}