{
  "type": "Feature",
  "properties": {
    "addr:full":"Vestergade 10 Nyk\u00f8bing Danmark 7900",
    "addr:housenumber":"10",
    "addr:postcode":"7900",
    "addr:street":"Vestergade",
    "iso:country":"DK",
    "sg:address":"Vestergade 10",
    "sg:city":"Nyk\u00f8bing",
    "sg:orig_category":"Ejendomshandel",
    "sg:phone":"+45 97 72 30 20",
    "sg:postcode":"7900",
    "sg:province":"Danmark",
    "sg:website":"www.nybolig.dk",
    "wof:name":"Nybolig Mors\u00f8",
    "wof:placetype":"venue"
},
  "geometry": {"coordinates":[9.5455904007,56.1682090759],"type":"Point"}
}