{
  "type": "Feature",
  "properties": {
    "addr:full":"Frederikssundsvej 18 A K\u00f8benhavn NV Danmark 2400",
    "addr:housenumber":"18 a",
    "addr:postcode":"2400",
    "addr:street":"Frederikssundsvej",
    "iso:country":"DK",
    "sg:address":"Frederikssundsvej 18 A",
    "sg:city":"K\u00f8benhavn NV",
    "sg:orig_category":"Gulvbehandling",
    "sg:phone":"+45 70 25 52 56",
    "sg:postcode":"2400",
    "sg:province":"Danmark",
    "wof:name":"Mou Gulv Service",
    "wof:placetype":"venue"
},
  "geometry": {"coordinates":[-117.02272033689999,38.5024604797],"type":"Point"}
}