{
  "type": "Feature",
  "properties": {
    "addr:full":"Kastetvej 56 Aalborg Danmark 9000",
    "addr:housenumber":"56",
    "addr:postcode":"9000",
    "addr:street":"Kastetvej",
    "iso:country":"DK",
    "sg:address":"Kastetvej 56",
    "sg:city":"Aalborg",
    "sg:orig_category":"Pizzeriaer",
    "sg:phone":"+45 98 16 98 55",
    "sg:postcode":"9000",
    "sg:province":"Danmark",
    "wof:name":"K. N. Pizza & Kebab Express 2.",
    "wof:placetype":"venue"
},
  "geometry": {"coordinates":[9.9022197723,57.0541419983],"type":"Point"}
}