{
  "type": "Feature",
  "properties": {
    "addr:full":"N\u00f8rg\u00e5rdsvej 4  Holstebro Danmark 7500",
    "addr:housenumber":"4",
    "addr:postcode":"7500",
    "addr:street":"Norgaardsvej",
    "iso:country":"DK",
    "sg:address":"N\u00f8rg\u00e5rdsvej 4 ",
    "sg:city":"Holstebro",
    "sg:classifiers":[
        {
            "category":"Wholesale",
            "subcategory":"Medical Equipment & Supplies",
            "type":"Manufacturing & Wholesale Goods"
        }
    ],
    "sg:phone":"+45 97 42 40 44",
    "sg:postcode":"7500",
    "sg:province":"Danmark",
    "sg:tags":[
        "-",
        "health",
        "instrument"
    ],
    "wof:name":"VESTJYDSK DENTAL A/S",
    "wof:placetype":"venue"
},
  "geometry": {"coordinates":[8.6202583313,56.3625221252],"type":"Point"}
}