{
  "type": "Feature",
  "properties": {
    "addr:full":"Niels Finsens Vej 14 Holstebro Danmark 7500",
    "addr:housenumber":"14",
    "addr:postcode":"7500",
    "addr:street":"Niels Finsens Vej",
    "iso:country":"DK",
    "sg:address":"Niels Finsens Vej 14",
    "sg:city":"Holstebro",
    "sg:orig_category":"Malermestre",
    "sg:phone":"+45 97 42 78 77",
    "sg:postcode":"7500",
    "sg:province":"Danmark",
    "wof:name":"Johansen, Tage",
    "wof:placetype":"venue"
},
  "geometry": {"coordinates":[8.609372139,56.376083374],"type":"Point"}
}