{
  "type": "Feature",
  "properties": {
    "addr:full":"Errits\u00f8 Bygade 15, Errits\u00f8 Fredericia Danmark 7000",
    "addr:housenumber":"15",
    "addr:postcode":"7000",
    "addr:street":"Erritso Bygade",
    "iso:country":"DK",
    "sg:address":"Errits\u00f8 Bygade 15, Errits\u00f8",
    "sg:city":"Fredericia",
    "sg:orig_category":"Skolefritidsordninger",
    "sg:phone":"+45 72 10 54 33",
    "sg:postcode":"7000",
    "sg:province":"Danmark",
    "wof:name":"Bakkeskolens skolefritidsordning",
    "wof:placetype":"venue"
},
  "geometry": {"coordinates":[9.7591047287,55.566368103],"type":"Point"}
}