{
  "type": "Feature",
  "properties": {
    "addr:full":"Smidstrupvej 347, Smidstrup Vr\u00e5 Danmark 9760",
    "addr:housenumber":"347",
    "addr:postcode":"9760",
    "addr:street":"Smidstrupvej;Smidstrup Vraa Danmark",
    "iso:country":"DK",
    "sg:address":"Smidstrupvej 347, Smidstrup",
    "sg:city":"Vr\u00e5",
    "sg:orig_category":"Autoreparation og -service",
    "sg:phone":"+45 98 99 80 55",
    "sg:postcode":"9760",
    "sg:province":"Danmark",
    "wof:name":"Pedersen, Kjeld",
    "wof:placetype":"venue"
},
  "geometry": {"coordinates":[9.9477567673,57.3534927368],"type":"Point"}
}