{
  "type": "Feature",
  "properties": {
    "iso:country":"DK",
    "sg:address":"Suhrs Gade 1",
    "sg:city":"Maribo",
    "sg:orig_category":"Blomsterhandlere",
    "sg:phone":"+45 54 78 07 83",
    "sg:postcode":"4930",
    "sg:province":"Danmark",
    "wof:name":"Robert's Gr\u00f8nthandel",
    "wof:placetype":"venue"
},
  "geometry": {"coordinates":[11.4978628159,54.7750358582],"type":"Point"}
}