{
  "type": "Feature",
  "properties": {
    "addr:full":"Thorsvej 65 Holstebro Danmark 7500",
    "addr:housenumber":"65",
    "addr:postcode":"7500",
    "addr:street":"Thorsvej",
    "iso:country":"DK",
    "sg:address":"Thorsvej 65",
    "sg:city":"Holstebro",
    "sg:orig_category":"Plejehjem",
    "sg:phone":"+45 96 10 54 10",
    "sg:postcode":"7500",
    "sg:province":"Danmark",
    "wof:name":"Thorsh\u00f8j Plejehjem",
    "wof:placetype":"venue"
},
  "geometry": {"coordinates":[8.5976552963,56.3715324402],"type":"Point"}
}