{
  "type": "Feature",
  "properties": {
    "addr:full":"Slagterboderne 21 K\u00f8benhavn Danmark 1716",
    "addr:housenumber":"21",
    "addr:postcode":"1716",
    "addr:street":"Slagterboderne",
    "iso:country":"DK",
    "sg:address":"Slagterboderne 21",
    "sg:city":"K\u00f8benhavn",
    "sg:orig_category":"RESTAURANTS: ART",
    "sg:phone":"+45 33 24 11 22",
    "sg:postcode":"1716",
    "sg:province":"Danmark",
    "sg:website":"www.hwl.dk",
    "wof:name":"Larsen & S\u00f8nner A/S, H W",
    "wof:placetype":"venue"
},
  "geometry": {"coordinates":[12.558930397,55.668800354],"type":"Point"}
}