{
  "type": "Feature",
  "properties": {
    "addr:full":"Industrivej 7 Slagelse Danmark 4200",
    "addr:housenumber":"7",
    "addr:postcode":"4200",
    "addr:street":"Industrivej",
    "iso:country":"DK",
    "sg:address":"Industrivej 7",
    "sg:city":"Slagelse",
    "sg:orig_category":"Maskinfabrikker",
    "sg:phone":"+45 58 52 32 58",
    "sg:postcode":"4200",
    "sg:province":"Danmark",
    "wof:name":"Askemose",
    "wof:placetype":"venue"
},
  "geometry": {"coordinates":[11.380188942,55.4122467041],"type":"Point"}
}