{
  "type": "Feature",
  "properties": {
    "iso:country":"DK",
    "sg:address":"Saltv\u00e6rksvej 191",
    "sg:city":"Kastrup",
    "sg:orig_category":"Smedemestre",
    "sg:phone":"+45 32 50 01 41",
    "sg:postcode":"2770",
    "sg:province":"Danmark",
    "wof:name":"A B C Smeden",
    "wof:placetype":"venue"
},
  "geometry": {"coordinates":[12.6240310669,55.6359443665],"type":"Point"}
}