{
  "type": "Feature",
  "properties": {
    "iso:country":"DK",
    "sg:address":"V. T\u00f8rslev Bygade 2",
    "sg:city":"Mariager",
    "sg:orig_category":"Kirker",
    "sg:postcode":"9550",
    "sg:province":"Danmark",
    "wof:name":"Vester T\u00f8rslev Kirke",
    "wof:placetype":"venue"
},
  "geometry": {"coordinates":[10.0618648529,56.676902771],"type":"Point"}
}