{
  "type": "Feature",
  "properties": {
    "addr:full":"Bredgade 10 Pandrup Danmark 9490",
    "addr:housenumber":"10",
    "addr:postcode":"9490",
    "addr:street":"Bredgade",
    "iso:country":"DK",
    "sg:address":"Bredgade 10",
    "sg:city":"Pandrup",
    "sg:orig_category":"Ejendomshandel",
    "sg:phone":"+45 98 24 62 00",
    "sg:postcode":"9490",
    "sg:province":"Danmark",
    "sg:website":"www.edc.dk",
    "wof:name":"EDC - M\u00e6glerne Andersen & Co A/S",
    "wof:placetype":"venue"
},
  "geometry": {"coordinates":[9.6767311096,57.2237052917],"type":"Point"}
}