{
  "type": "Feature",
  "properties": {
    "addr:full":"Svendborgvej 11 Aalborg \u00d8 Danmark 9220",
    "addr:housenumber":"11",
    "addr:postcode":"9220",
    "addr:street":"Svendborgvej;Danmark",
    "iso:country":"DK",
    "sg:address":"Svendborgvej 11",
    "sg:city":"Aalborg \u00d8",
    "sg:classifiers":[
        {
            "category":"Utilities",
            "subcategory":"Refuse",
            "type":"Services"
        }
    ],
    "sg:phone":"+45 98 15 47 00",
    "sg:postcode":"9220",
    "sg:province":"Danmark",
    "sg:tags":[
        "catering"
    ],
    "wof:name":"Kalu-Food A/S",
    "wof:placetype":"venue"
},
  "geometry": {"coordinates":[10.0158901215,57.0290985107],"type":"Point"}
}