{
  "type": "Feature",
  "properties": {
    "iso:country":"DK",
    "sg:address":"Vestergade 3",
    "sg:city":"Silkeborg",
    "sg:classifiers":[
        {
            "category":"Banks & Credit Unions",
            "subcategory":"Bank",
            "type":"Services"
        }
    ],
    "sg:phone":"+45 87 22 60 00",
    "sg:postcode":"8600",
    "sg:province":"Danmark",
    "sg:tags":[
        "banker"
    ],
    "wof:name":"BG Bank",
    "wof:placetype":"venue"
},
  "geometry": {"coordinates":[9.5489,56.168922],"type":"Point"}
}