{
  "type": "Feature",
  "properties": {
    "addr:full":"H\u00f8jvang 5 Frederikssund Danmark 3600",
    "addr:housenumber":"5",
    "addr:postcode":"3600",
    "addr:street":"Hojvang",
    "iso:country":"DK",
    "sg:address":"H\u00f8jvang 5",
    "sg:city":"Frederikssund",
    "sg:orig_category":"Supermarkeder",
    "sg:phone":"+45 47 38 30 73",
    "sg:postcode":"3600",
    "sg:province":"Danmark",
    "wof:name":"Merko Gr\u00e6sebakkeby",
    "wof:placetype":"venue"
},
  "geometry": {"coordinates":[12.0661621094,55.8370323181],"type":"Point"}
}