{
  "type": "Feature",
  "properties": {
    "addr:full":"Aarestrupvej 162 Karup Danmark 7470",
    "addr:housenumber":"162",
    "addr:postcode":"7470",
    "addr:street":"Aarestrupvej",
    "iso:country":"DK",
    "sg:address":"Aarestrupvej 162",
    "sg:city":"Karup",
    "sg:orig_category":"Skovbrug",
    "sg:phone":"+45 86 66 17 90",
    "sg:postcode":"7470",
    "sg:province":"Danmark",
    "sg:website":"www.skovplanter.dk",
    "wof:name":"Aarestrup Planteskole",
    "wof:placetype":"venue"
},
  "geometry": {"coordinates":[9.2385826111,56.3071022034],"type":"Point"}
}