{
  "type": "Feature",
  "properties": {
    "addr:full":"\u00c5marksvej 5, Toreby Toreby Danmark 4891",
    "addr:housenumber":"5",
    "addr:postcode":"4891",
    "addr:street":"Aamarksvej;Toreby Toreby Danmark",
    "iso:country":"DK",
    "sg:address":"\u00c5marksvej 5, Toreby",
    "sg:city":"Toreby",
    "sg:orig_category":"\u00c3\u2020ldrecentre",
    "sg:phone":"+45 54 86 91 84",
    "sg:postcode":"4891",
    "sg:province":"Danmark",
    "wof:name":"Toreby Omr\u00e5decenter",
    "wof:placetype":"venue"
},
  "geometry": {"coordinates":[11.7701835632,54.7622375488],"type":"Point"}
}