{
  "type": "Feature",
  "properties": {
    "addr:full":"Industrivej 8 Aabenraa Danmark 6200",
    "addr:housenumber":"8",
    "addr:postcode":"6200",
    "addr:street":"Industrivej",
    "iso:country":"DK",
    "sg:address":"Industrivej 8",
    "sg:city":"Aabenraa",
    "sg:orig_category":"Bowlingcentre",
    "sg:phone":"+45 74 62 65 00",
    "sg:postcode":"6200",
    "sg:province":"Danmark",
    "sg:website":"www.sportscentrum.dk",
    "wof:name":"Sports Centrum",
    "wof:placetype":"venue"
},
  "geometry": {"coordinates":[9.4024381638,55.0483665466],"type":"Point"}
}