{
  "type": "Feature",
  "properties": {
    "iso:country":"DK",
    "sg:address":"Marina Park Sundkrogsgade 4",
    "sg:city":"K\u00f8benhavn \u00d8",
    "sg:classifiers":[
        {
            "category":"Banks & Credit Unions",
            "subcategory":"Bank",
            "type":"Services"
        }
    ],
    "sg:phone":"+45 31 20 77 11",
    "sg:postcode":"2100",
    "sg:province":"Danmark",
    "wof:name":"PFA Pension Koncernen",
    "wof:placetype":"venue"
},
  "geometry": {"coordinates":[12.578209,55.698887],"type":"Point"}
}