{
  "type": "Feature",
  "properties": {
    "iso:country":"DK",
    "sg:address":"Klintevej 28",
    "sg:city":"R\u00f8dvig Stevns",
    "sg:orig_category":"Handicapboliger",
    "sg:phone":"+45 56 50 60 08",
    "sg:postcode":"4673",
    "sg:province":"Danmark",
    "wof:name":"Feriehjemmet Strandholm",
    "wof:placetype":"venue"
},
  "geometry": {"coordinates":[12.3843832016,55.2564430237],"type":"Point"}
}