{
  "type": "Feature",
  "properties": {
    "addr:full":"Bl\u00e5kildevej 31 A, L\u00f8nborg Tarm Danmark 6880",
    "addr:housenumber":"31 a",
    "addr:postcode":"6880",
    "addr:street":"Blaakildevej;Lonborg",
    "iso:country":"DK",
    "sg:address":"Bl\u00e5kildevej 31 A, L\u00f8nborg",
    "sg:city":"Tarm",
    "sg:orig_category":"Malermestre",
    "sg:phone":"+45 97 37 24 04",
    "sg:postcode":"6880",
    "sg:province":"Danmark",
    "wof:name":"Jensen, Lissi",
    "wof:placetype":"venue"
},
  "geometry": {"coordinates":[8.5200052261,55.9060554504],"type":"Point"}
}