{
  "type": "Feature",
  "properties": {
    "addr:full":"Frydendalsvej 7 Aalborg Danmark 9000",
    "addr:housenumber":"7",
    "addr:postcode":"9000",
    "addr:street":"Frydendalsvej",
    "iso:country":"DK",
    "sg:address":"Frydendalsvej 7",
    "sg:city":"Aalborg",
    "sg:orig_category":"Fotografer",
    "sg:phone":"+45 98 13 11 44",
    "sg:postcode":"9000",
    "sg:province":"Danmark",
    "sg:website":"www.baghuset.dk",
    "wof:name":"Baghuset Presse Foto",
    "wof:placetype":"venue"
},
  "geometry": {"coordinates":[9.9311914444,57.0305671692],"type":"Point"}
}