{
  "type": "Feature",
  "properties": {
    "iso:country":"DK",
    "sg:address":"Gammelbrovej 74, Aar\u00f8sund",
    "sg:city":"Haderslev",
    "sg:orig_category":"Campingpladser",
    "sg:phone":"+45 74 58 42 97",
    "sg:postcode":"6100",
    "sg:province":"Danmark",
    "wof:name":"Aar\u00f8sund Camping",
    "wof:placetype":"venue"
},
  "geometry": {"coordinates":[9.4879703522,55.2505493164],"type":"Point"}
}