{
  "type": "Feature",
  "properties": {
    "iso:country":"DK",
    "sg:address":"Gartnerivej 9",
    "sg:city":"Holstebro",
    "sg:orig_category":"Kaffe og the",
    "sg:phone":"+45 97 42 11 99",
    "sg:postcode":"7500",
    "sg:province":"Danmark",
    "wof:name":"Meny Kaffe",
    "wof:placetype":"venue"
},
  "geometry": {"coordinates":[8.6128206253,56.3777923584],"type":"Point"}
}