{
  "type": "Feature",
  "properties": {
    "addr:full":"Malervej 9 Taastrup Danmark 2630",
    "addr:housenumber":"9",
    "addr:postcode":"2630",
    "addr:street":"Malervej",
    "iso:country":"DK",
    "sg:address":"Malervej 9",
    "sg:city":"Taastrup",
    "sg:orig_category":"Fabrikker",
    "sg:phone":"+45 43 99 48 55",
    "sg:postcode":"2630",
    "sg:province":"Danmark",
    "wof:name":"Ringsdals Maskinfabrik",
    "wof:placetype":"venue"
},
  "geometry": {"coordinates":[12.2870426178,55.6378746033],"type":"Point"}
}