{
  "type": "Feature",
  "properties": {
    "addr:full":"Vindingg\u00e5rd Center 17 Vejle Danmark 7100",
    "addr:housenumber":"17",
    "addr:postcode":"7100",
    "iso:country":"DK",
    "sg:address":"Vindingg\u00e5rd Center 17",
    "sg:city":"Vejle",
    "sg:orig_category":"Cykler",
    "sg:phone":"+45 75 82 03 06",
    "sg:postcode":"7100",
    "sg:province":"Danmark",
    "wof:name":"Mosquito Cykelcenter",
    "wof:placetype":"venue"
},
  "geometry": {"coordinates":[9.5512990952,55.6870918274],"type":"Point"}
}