{
  "type": "Feature",
  "properties": {
    "addr:full":"Havnegade 13 A Frederikssund Danmark 3600",
    "addr:housenumber":"13 a",
    "addr:postcode":"3600",
    "addr:street":"Havnegade",
    "iso:country":"DK",
    "sg:address":"Havnegade 13 A",
    "sg:city":"Frederikssund",
    "sg:orig_category":"Skomagere",
    "sg:phone":"+45 47 31 39 26",
    "sg:postcode":"3600",
    "sg:province":"Danmark",
    "wof:name":"Sko- og N\u00f8gleservice",
    "wof:placetype":"venue"
},
  "geometry": {"coordinates":[12.0575771332,55.8387870789],"type":"Point"}
}