{
  "type": "Feature",
  "properties": {
    "addr:full":"Hovslundvej 12 A, Hovslund St R\u00f8dekro Danmark 6230",
    "addr:housenumber":"12 a",
    "addr:postcode":"6230",
    "addr:street":"Hovslundvej;Hovslund St;Danmark",
    "iso:country":"DK",
    "sg:address":"Hovslundvej 12 A, Hovslund St",
    "sg:city":"R\u00f8dekro",
    "sg:orig_category":"Integrerede institutioner",
    "sg:phone":"+45 74 66 49 13",
    "sg:postcode":"6230",
    "sg:province":"Danmark",
    "wof:name":"B\u00f8rnehuset Spiren",
    "wof:placetype":"venue"
},
  "geometry": {"coordinates":[9.307510376,55.0235786438],"type":"Point"}
}