{
  "type": "Feature",
  "properties": {
    "addr:full":"Lodsgade 4 Frederikshavn Danmark 9900",
    "addr:housenumber":"4",
    "addr:postcode":"9900",
    "addr:street":"Lodsgade",
    "iso:country":"DK",
    "sg:address":"Lodsgade 4",
    "sg:city":"Frederikshavn",
    "sg:classifiers":[
        {
            "category":"Restaurant",
            "type":"Food & Drink"
        }
    ],
    "sg:phone":"+45 98 42 91 10",
    "sg:postcode":"9900",
    "sg:province":"Danmark",
    "wof:name":"Bella Italia",
    "wof:placetype":"venue"
},
  "geometry": {"coordinates":[10.5360946655,57.4379692078],"type":"Point"}
}