{
  "type": "Feature",
  "properties": {
    "addr:full":"Moselgade 28, st. K\u00f8benhavn S Danmark 2300",
    "addr:housenumber":"28",
    "addr:postcode":"2300",
    "addr:street":"Moselgade;Danmark",
    "iso:country":"DK",
    "sg:address":"Moselgade 28, st.",
    "sg:city":"K\u00f8benhavn S",
    "sg:orig_category":"Faglige organisationer og -foreninger",
    "sg:phone":"+45 32 58 48 27",
    "sg:postcode":"2300",
    "sg:province":"Danmark",
    "wof:name":"Kordirigent-foreningen",
    "wof:placetype":"venue"
},
  "geometry": {"coordinates":[-82.5031585693,38.4148597717],"type":"Point"}
}