{
  "type": "Feature",
  "properties": {
    "addr:full":"Fmd.: Palle Bruun Olsen, Pr\u00e6stegade 8 Kalundborg Danmark 4400",
    "addr:housenumber":"8",
    "addr:postcode":"4400",
    "addr:street":"Palle;Praestegade",
    "iso:country":"DK",
    "sg:address":"Fmd.: Palle Bruun Olsen, Pr\u00e6stegade 8",
    "sg:city":"Kalundborg",
    "sg:orig_category":"Kulturelle foreninger",
    "sg:phone":"+45 59 51 60 27",
    "sg:postcode":"4400",
    "sg:province":"Danmark",
    "wof:name":"Kalundborg Kunstforening",
    "wof:placetype":"venue"
},
  "geometry": {"coordinates":[11.0934085846,55.6797485352],"type":"Point"}
}