{
  "type": "Feature",
  "properties": {
    "addr:full":"Fmd.: Eva Hvam, Kirseb\u00e6rlunden 6 F S\u00f8nders\u00f8 Danmark 5471",
    "addr:housenumber":"6 f",
    "addr:postcode":"5471",
    "addr:street":"Kirsebaerlunden;Sonderso Danmark",
    "iso:country":"DK",
    "sg:address":"Fmd.: Eva Hvam, Kirseb\u00e6rlunden 6 F",
    "sg:city":"S\u00f8nders\u00f8",
    "sg:orig_category":"\u00c3\u2020ldreorganisationer og klubber",
    "sg:phone":"+45 64 89 27 22",
    "sg:postcode":"5471",
    "sg:province":"Danmark",
    "wof:name":"S\u00f8nders\u00f8-Skamby Pensionistforening",
    "wof:placetype":"venue"
},
  "geometry": {"coordinates":[10.0971403122,55.5018997192],"type":"Point"}
}