{
  "type": "Feature",
  "properties": {
    "addr:full":"Roskildevej 52 Frederiksberg Danmark 2000",
    "addr:housenumber":"52",
    "addr:postcode":"2000",
    "addr:street":"Roskildevej",
    "iso:country":"DK",
    "sg:address":"Roskildevej 52",
    "sg:city":"Frederiksberg",
    "sg:orig_category":"Stenhuggere",
    "sg:phone":"+45 36 16 16 50",
    "sg:postcode":"2000",
    "sg:province":"Danmark",
    "wof:name":"Nielsens Stenhuggerier A/S, E.",
    "wof:placetype":"venue"
},
  "geometry": {"coordinates":[12.5105409622,55.6722869873],"type":"Point"}
}