{
  "type": "Feature",
  "properties": {
    "addr:full":"Kl\u00f8vertoften 12, Felsted Aabenraa Danmark 6200",
    "addr:housenumber":"12",
    "addr:postcode":"6200",
    "addr:street":"Klovertoften;Felsted",
    "iso:country":"DK",
    "sg:address":"Kl\u00f8vertoften 12, Felsted",
    "sg:city":"Aabenraa",
    "sg:orig_category":"Revisorer",
    "sg:phone":"+45 74 68 56 09",
    "sg:postcode":"6200",
    "sg:province":"Danmark",
    "wof:name":"E.C. Servicekontor",
    "wof:placetype":"venue"
},
  "geometry": {"coordinates":[9.4213867188,55.0449562073],"type":"Point"}
}