{
  "type": "Feature",
  "properties": {
    "addr:full":"Fmd.: Lene J\u00f8rgensen, Bavnevej 28 Vamdrup Danmark 6580",
    "addr:housenumber":"28",
    "addr:postcode":"6580",
    "addr:street":"Lene;Bavnevej",
    "iso:country":"DK",
    "sg:address":"Fmd.: Lene J\u00f8rgensen, Bavnevej 28",
    "sg:city":"Vamdrup",
    "sg:orig_category":"Forbrugerorganisationer",
    "sg:phone":"+45 75 58 36 51",
    "sg:postcode":"6580",
    "sg:province":"Danmark",
    "wof:name":"Sociale Brugerr\u00e5d, Det",
    "wof:placetype":"venue"
},
  "geometry": {"coordinates":[9.2839107513,55.4266548157],"type":"Point"}
}