{
  "type": "Feature",
  "properties": {
    "iso:country":"DK",
    "sg:address":"Gerritsgade 15",
    "sg:city":"Svendborg",
    "sg:orig_category":"Optikere",
    "sg:phone":"+45 62 21 05 11",
    "sg:postcode":"5700",
    "sg:province":"Danmark",
    "sg:website":"www.finnravn.dk",
    "wof:name":"Ravn Optik, Finn",
    "wof:placetype":"venue"
},
  "geometry": {"coordinates":[10.6082296371,55.0589370728],"type":"Point"}
}