{
  "type": "Feature",
  "properties": {
    "addr:full":"Ravnens Kvarter 14 B Albertslund Danmark 2620",
    "addr:housenumber":"14 b",
    "addr:postcode":"2620",
    "addr:street":"Ravnens Kvarter",
    "iso:country":"DK",
    "sg:address":"Ravnens Kvarter 14 B",
    "sg:city":"Albertslund",
    "sg:orig_category":"Hobbybetonede foreninger",
    "sg:phone":"+45 43 64 88 08",
    "sg:postcode":"2620",
    "sg:province":"Danmark",
    "wof:name":"Dansk Cyklist Forbund Vestegnens lokalafd.",
    "wof:placetype":"venue"
},
  "geometry": {"coordinates":[12.3375911713,55.651725769],"type":"Point"}
}