{
  "type": "Feature",
  "properties": {
    "addr:full":"Torvet 25 Frederiksv\u00e6rk Danmark 3300",
    "addr:housenumber":"25",
    "addr:postcode":"3300",
    "addr:street":"Torvet",
    "iso:country":"DK",
    "sg:address":"Torvet 25",
    "sg:city":"Frederiksv\u00e6rk",
    "sg:orig_category":"Forsikringer",
    "sg:phone":"+45 47 76 04 10",
    "sg:postcode":"3300",
    "sg:province":"Danmark",
    "wof:name":"Tryg-Baltica",
    "wof:placetype":"venue"
},
  "geometry": {"coordinates":[9.9058914185,59.7713279724],"type":"Point"}
}