{
  "type": "Feature",
  "properties": {
    "addr:full":"Algade 79 Vordingborg Danmark 4760",
    "addr:housenumber":"79",
    "addr:postcode":"4760",
    "addr:street":"Algade",
    "iso:country":"DK",
    "sg:address":"Algade 79",
    "sg:city":"Vordingborg",
    "sg:classifiers":[
        {
            "category":"Home & Garden",
            "subcategory":"Home Furnishings",
            "type":"Retail Goods"
        }
    ],
    "sg:phone":"+45 55 37 00 40",
    "sg:postcode":"4760",
    "sg:province":"Danmark",
    "sg:tags":[
        "gardiner"
    ],
    "wof:name":"Sadolin Farveland",
    "wof:placetype":"venue"
},
  "geometry": {"coordinates":[11.9080429077,55.0092849731],"type":"Point"}
}