{
  "type": "Feature",
  "properties": {
    "iso:country":"DK",
    "sg:address":"Ballerup Centret, Banetoften 30",
    "sg:city":"Ballerup",
    "sg:orig_category":"Materialister",
    "sg:phone":"+45 44 65 79 77",
    "sg:postcode":"2750",
    "sg:province":"Danmark",
    "wof:name":"Matas p\u00e5 Toppen",
    "wof:placetype":"venue"
},
  "geometry": {"coordinates":[12.361000061,55.7301216125],"type":"Point"}
}