{
  "type": "Feature",
  "properties": {
    "addr:full":"Kratk\u00e6r 6, Sm\u00f8rumnedre Sm\u00f8rum Danmark 2765",
    "addr:housenumber":"6",
    "addr:postcode":"2765",
    "addr:street":"Kratkaer",
    "iso:country":"DK",
    "sg:address":"Kratk\u00e6r 6, Sm\u00f8rumnedre",
    "sg:city":"Sm\u00f8rum",
    "sg:orig_category":"Private skoler",
    "sg:phone":"+45 44 66 40 42",
    "sg:postcode":"2765",
    "sg:province":"Danmark",
    "wof:name":"Kratk\u00e6r Familieinstitutionen",
    "wof:placetype":"venue"
},
  "geometry": {"coordinates":[-89.99810791020001,38.1321372986],"type":"Point"}
}