{
  "type": "Feature",
  "properties": {
    "addr:full":"Norgesgade 35 K\u00f8benhavn S Danmark 2300",
    "addr:housenumber":"35",
    "addr:postcode":"2300",
    "addr:street":"Norgesgade;Kobenhavn S Danmark",
    "iso:country":"DK",
    "sg:address":"Norgesgade 35",
    "sg:city":"K\u00f8benhavn S",
    "sg:orig_category":"Tyverisikring",
    "sg:phone":"+45 32 95 85 20",
    "sg:postcode":"2300",
    "sg:province":"Danmark",
    "wof:name":"Gitternetto",
    "wof:placetype":"venue"
},
  "geometry": {"coordinates":[-98.57666015620001,47.9187011719],"type":"Point"}
}