{
  "type": "Feature",
  "properties": {
    "addr:full":"Skolegade 39 Karise Danmark 4653",
    "addr:housenumber":"39",
    "addr:postcode":"4653",
    "addr:street":"Skolegade",
    "iso:country":"DK",
    "sg:address":"Skolegade 39",
    "sg:city":"Karise",
    "sg:orig_category":"Kommunale folkeskoler",
    "sg:phone":"+45 56 78 83 20",
    "sg:postcode":"4653",
    "sg:province":"Danmark",
    "wof:name":"Karise Skole",
    "wof:placetype":"venue"
},
  "geometry": {"coordinates":[12.191860199,55.3089408875],"type":"Point"}
}