{
  "type": "Feature",
  "properties": {
    "addr:full":"Langelinie 53 Odense M Danmark 5230",
    "addr:housenumber":"53",
    "addr:postcode":"5230",
    "addr:street":"Langelinie",
    "iso:country":"DK",
    "sg:address":"Langelinie 53",
    "sg:city":"Odense M",
    "sg:orig_category":"INGENI\u00c3\u02dcRER",
    "sg:phone":"+45 66 12 61 41",
    "sg:postcode":"5230",
    "sg:province":"Danmark",
    "wof:name":"Hansen, Niels Uhd",
    "wof:placetype":"venue"
},
  "geometry": {"coordinates":[10.377409935,55.383354187],"type":"Point"}
}