{
  "type": "Feature",
  "properties": {
    "addr:full":"\u00d8sterbrogade 10 Lemvig Danmark 7620",
    "addr:housenumber":"10",
    "addr:postcode":"7620",
    "addr:street":"Osterbrogade",
    "iso:country":"DK",
    "sg:address":"\u00d8sterbrogade 10",
    "sg:city":"Lemvig",
    "sg:orig_category":"Faglige organisationer og foreninger",
    "sg:phone":"+45 97 82 09 34",
    "sg:postcode":"7620",
    "sg:province":"Danmark",
    "wof:name":"NNF - Slagterne, Lemvig afd.",
    "wof:placetype":"venue"
},
  "geometry": {"coordinates":[8.3117666245,56.5519561768],"type":"Point"}
}