{
  "type": "Feature",
  "properties": {
    "addr:full":"Gammel K\u00f8ge Landevej 264 D Hvidovre Danmark 2650",
    "addr:housenumber":"264 d",
    "addr:postcode":"2650",
    "addr:street":"Gammel Koge Landevej",
    "iso:country":"DK",
    "sg:address":"Gammel K\u00f8ge Landevej 264 D",
    "sg:city":"Hvidovre",
    "sg:orig_category":"Sportsartikler",
    "sg:phone":"+45 36 78 84 50",
    "sg:postcode":"2650",
    "sg:province":"Danmark",
    "wof:name":"Fair Play Sportswear ApS",
    "wof:placetype":"venue"
},
  "geometry": {"coordinates":[12.4939556122,55.636390686],"type":"Point"}
}