{
  "type": "Feature",
  "properties": {
    "iso:country":"DK",
    "sg:address":"Glentevej 19",
    "sg:city":"Hundested",
    "sg:orig_category":"Hobbybetonede foreninger",
    "sg:phone":"+45 47 98 03 02",
    "sg:postcode":"3390",
    "sg:province":"Danmark",
    "wof:name":"Badeklubben Trekanten",
    "wof:placetype":"venue"
},
  "geometry": {"coordinates":[11.8527984619,55.9705505371],"type":"Point"}
}