{
  "type": "Feature",
  "properties": {
    "iso:country":"DK",
    "sg:address":"Hovedgaden 31 B",
    "sg:city":"Hampen",
    "sg:orig_category":"Campingpladser",
    "sg:phone":"+45 75 77 52 55",
    "sg:postcode":"7362",
    "sg:province":"Danmark",
    "wof:name":"Hampen S\u00f8 Camping",
    "wof:placetype":"venue"
},
  "geometry": {"coordinates":[9.3636922836,56.0144271851],"type":"Point"}
}