{
  "type": "Feature",
  "properties": {
    "iso:country":"DK",
    "sg:address":"N\u00f8rregade 14",
    "sg:city":"Aalborg",
    "sg:orig_category":"Brugskunst",
    "sg:phone":"+45 98 11 45 44",
    "sg:postcode":"9000",
    "sg:province":"Danmark",
    "wof:name":"il Gusto",
    "wof:placetype":"venue"
},
  "geometry": {"coordinates":[9.9267454147,57.0465087891],"type":"Point"}
}