{
  "type": "Feature",
  "properties": {
    "addr:full":"S\u00f8ndergade 10 Aabenraa Danmark 6200",
    "addr:housenumber":"10",
    "addr:postcode":"6200",
    "addr:street":"Sondergade",
    "iso:country":"DK",
    "sg:address":"S\u00f8ndergade 10",
    "sg:city":"Aabenraa",
    "sg:orig_category":"Elektronik",
    "sg:phone":"+45 74 62 73 59",
    "sg:postcode":"6200",
    "sg:province":"Danmark",
    "wof:name":"Krambo-Radio",
    "wof:placetype":"venue"
},
  "geometry": {"coordinates":[9.419049263,55.0417442322],"type":"Point"}
}