{
  "type": "Feature",
  "properties": {
    "iso:country":"DK",
    "sg:address":"\u00d8ster Vedsted Vej 16 ",
    "sg:city":"Ribe",
    "sg:classifiers":[
        {
            "category":"Home & Garden",
            "subcategory":"Home Furnishings",
            "type":"Retail Goods"
        }
    ],
    "sg:phone":"+45 75 42 43 00",
    "sg:postcode":"6760",
    "sg:province":"Danmark",
    "sg:tags":[
        "household"
    ],
    "wof:name":"IB LAURSEN, RIBE APS",
    "wof:placetype":"venue"
},
  "geometry": {"coordinates":[8.7285442352,55.2837142944],"type":"Point"}
}