{
  "type": "Feature",
  "properties": {
    "iso:country":"DK",
    "sg:address":"M\u00f8llevej 1 A",
    "sg:city":"Vissenbjerg",
    "sg:orig_category":"Begravelsesforretninger",
    "sg:phone":"+45 64 47 14 87",
    "sg:postcode":"5492",
    "sg:province":"Danmark",
    "wof:name":"Vissenbjerg Begravelsesforretning",
    "wof:placetype":"venue"
},
  "geometry": {"coordinates":[10.130783,55.385803],"type":"Point"}
}