{
  "type": "Feature",
  "properties": {
    "addr:full":"Heimdalsvej 8 Frederikssund Danmark 3600",
    "addr:housenumber":"8",
    "addr:postcode":"3600",
    "addr:street":"Heimdalsvej",
    "iso:country":"DK",
    "sg:address":"Heimdalsvej 8",
    "sg:city":"Frederikssund",
    "sg:orig_category":"Ungdomsklubber",
    "sg:phone":"+45 47 31 72 41",
    "sg:postcode":"3600",
    "sg:province":"Danmark",
    "wof:name":"Fritids- & Ungdomsklubben Klub Nord",
    "wof:placetype":"venue"
},
  "geometry": {"coordinates":[12.0529985428,55.8516044617],"type":"Point"}
}