{
  "type": "Feature",
  "properties": {
    "addr:full":"Gunnar Clausens Vej 32 Viby Danmark 8260",
    "addr:housenumber":"32",
    "addr:postcode":"8260",
    "addr:street":"Gunnar Clausens Vej",
    "iso:country":"DK",
    "sg:address":"Gunnar Clausens Vej 32",
    "sg:city":"Viby",
    "sg:orig_category":"Typehuse",
    "sg:phone":"+45 86 29 19 00",
    "sg:postcode":"8260",
    "sg:province":"Danmark",
    "wof:name":"Holmbo-Huse",
    "wof:placetype":"venue"
},
  "geometry": {"coordinates":[10.1454305649,56.1089553833],"type":"Point"}
}