{
  "type": "Feature",
  "properties": {
    "addr:full":"Moltrupvej 49 Haderslev Danmark 6100",
    "addr:housenumber":"49",
    "addr:postcode":"6100",
    "addr:street":"Moltrupvej",
    "iso:country":"DK",
    "sg:address":"Moltrupvej 49",
    "sg:city":"Haderslev",
    "sg:classifiers":[
        {
            "category":"Banks & Credit Unions",
            "subcategory":"Bank",
            "type":"Services"
        }
    ],
    "sg:phone":"+45 73 52 10 10",
    "sg:postcode":"6100",
    "sg:province":"Danmark",
    "sg:tags":[
        "banker"
    ],
    "wof:name":"Fr\u00f8s Herreds Sparekasse",
    "wof:placetype":"venue"
},
  "geometry": {"coordinates":[9.47618,55.257519],"type":"Point"}
}