{
  "type": "Feature",
  "properties": {
    "iso:country":"DK",
    "sg:address":"Digevangen 23",
    "sg:city":"Gistrup",
    "sg:orig_category":"Transport",
    "sg:phone":"+45 98 32 33 04",
    "sg:postcode":"9260",
    "sg:province":"Danmark",
    "wof:name":"Kubicki Transport",
    "wof:placetype":"venue"
},
  "geometry": {"coordinates":[9.9932327271,56.9944267273],"type":"Point"}
}