{
  "type": "Feature",
  "properties": {
    "addr:full":"M\u00e5vej 8, Helberskov Hadsund Danmark 9560",
    "addr:housenumber":"8",
    "addr:postcode":"9560",
    "addr:street":"Maavej",
    "iso:country":"DK",
    "sg:address":"M\u00e5vej 8, Helberskov",
    "sg:city":"Hadsund",
    "sg:orig_category":"Engros handel",
    "sg:phone":"+45 98 58 17 14",
    "sg:postcode":"9560",
    "sg:province":"Danmark",
    "wof:name":"Jysk B\u00e5ndrensning",
    "wof:placetype":"venue"
},
  "geometry": {"coordinates":[10.115904808,56.7150764465],"type":"Point"}
}