{
  "type": "Feature",
  "properties": {
    "addr:full":"Havnepladsen 3 Svendborg Danmark 5700",
    "addr:housenumber":"3",
    "addr:postcode":"5700",
    "addr:street":"Havnepladsen",
    "iso:country":"DK",
    "sg:address":"Havnepladsen 3",
    "sg:city":"Svendborg",
    "sg:orig_category":"Advokater",
    "sg:phone":"+45 62 21 20 10",
    "sg:postcode":"5700",
    "sg:province":"Danmark",
    "sg:website":"www.dania-law.dk",
    "wof:name":"Hansen, Finn",
    "wof:placetype":"venue"
},
  "geometry": {"coordinates":[10.6145973206,55.0580101013],"type":"Point"}
}