{
  "type": "Feature",
  "properties": {
    "addr:full":"Reberbanen 2 Ringk\u00f8bing Danmark 6950",
    "addr:housenumber":"2",
    "addr:postcode":"6950",
    "addr:street":"Reberbanen",
    "iso:country":"DK",
    "sg:address":"Reberbanen 2",
    "sg:city":"Ringk\u00f8bing",
    "sg:orig_category":"INGENI\u00c3\u02dcRER",
    "sg:phone":"+45 97 32 54 55",
    "sg:postcode":"6950",
    "sg:province":"Danmark",
    "wof:name":"Ingeni\u00f8rkontor Vest ApS",
    "wof:placetype":"venue"
},
  "geometry": {"coordinates":[-102.0896530151,42.0193557739],"type":"Point"}
}