{
  "type": "Feature",
  "properties": {
    "addr:full":"N\u00f8rregade 8 Bramming Danmark 6740",
    "addr:housenumber":"8",
    "addr:postcode":"6740",
    "addr:street":"Norregade",
    "iso:country":"DK",
    "sg:address":"N\u00f8rregade 8",
    "sg:city":"Bramming",
    "sg:orig_category":"Boghandlere",
    "sg:phone":"+45 75 17 30 61",
    "sg:postcode":"6740",
    "sg:province":"Danmark",
    "wof:name":"Bramming Boghandel ApS",
    "wof:placetype":"venue"
},
  "geometry": {"coordinates":[8.7008180618,55.4654808044],"type":"Point"}
}