{
  "type": "Feature",
  "properties": {
    "iso:country":"DK",
    "sg:address":"Fmd.: Arne Thomsen, Bjergager 5",
    "sg:city":"Glostrup",
    "sg:orig_category":"Grundejerforeninger",
    "sg:postcode":"2600",
    "sg:province":"Danmark",
    "wof:name":"Bjergager",
    "wof:placetype":"venue"
},
  "geometry": {"coordinates":[12.3957901001,55.6654663086],"type":"Point"}
}