{
  "type": "Feature",
  "properties": {
    "addr:full":"Blomsterv\u00e6nget 17 Assens Danmark 5610",
    "addr:housenumber":"17",
    "addr:postcode":"5610",
    "addr:street":"Blomstervaenget",
    "iso:country":"DK",
    "sg:address":"Blomsterv\u00e6nget 17",
    "sg:city":"Assens",
    "sg:classifiers":[
        {
            "category":"Taxi",
            "type":"Transportation"
        }
    ],
    "sg:phone":"+45 64 71 17 69",
    "sg:postcode":"5610",
    "sg:province":"Danmark",
    "wof:name":"Assens City - Taxi",
    "wof:placetype":"venue"
},
  "geometry": {"coordinates":[9.8928108215,55.2761535645],"type":"Point"}
}