{
  "type": "Feature",
  "properties": {
    "addr:full":"Sankt Peders Vej 2 Hellerup Danmark 2900",
    "addr:housenumber":"2",
    "addr:postcode":"2900",
    "addr:street":"Sankt Peders Vej",
    "iso:country":"DK",
    "sg:address":"Sankt Peders Vej 2",
    "sg:city":"Hellerup",
    "sg:orig_category":"Tandteknikere, Kliniske",
    "sg:phone":"+45 39 62 53 32",
    "sg:postcode":"2900",
    "sg:province":"Danmark",
    "wof:name":"Bur\u00f8, Lars",
    "wof:placetype":"venue"
},
  "geometry": {"coordinates":[12.5757160187,55.7308158875],"type":"Point"}
}