{
  "type": "Feature",
  "properties": {
    "iso:country":"DK",
    "sg:address":"Fortunavej 1",
    "sg:city":"Hobro",
    "sg:orig_category":"Bogtrykkerier",
    "sg:phone":"+45 98 52 02 31",
    "sg:postcode":"9500",
    "sg:province":"Danmark",
    "wof:name":"Telefon-N\u00f8glen for Hobro og Opland",
    "wof:placetype":"venue"
},
  "geometry": {"coordinates":[9.790104866,56.6420707703],"type":"Point"}
}