{
  "type": "Feature",
  "properties": {
    "addr:full":"S\u00f8ndergade 12 Skive Danmark 7800",
    "addr:housenumber":"12",
    "addr:postcode":"7800",
    "addr:street":"Sondergade",
    "iso:country":"DK",
    "sg:address":"S\u00f8ndergade 12",
    "sg:city":"Skive",
    "sg:orig_category":"Grillbarer",
    "sg:phone":"+45 97 52 47 10",
    "sg:postcode":"7800",
    "sg:province":"Danmark",
    "wof:name":"Stoppestedet",
    "wof:placetype":"venue"
},
  "geometry": {"coordinates":[9.0258207321,56.5631866455],"type":"Point"}
}