{
  "type": "Feature",
  "properties": {
    "addr:full":"Falkoner Alle 67, 2.th. Frederiksberg Danmark 2000",
    "addr:housenumber":"67 2.th",
    "addr:postcode":"2000",
    "addr:street":"Falkoner Alle",
    "iso:country":"DK",
    "sg:address":"Falkoner Alle 67, 2.th.",
    "sg:city":"Frederiksberg",
    "sg:orig_category":"Konsulentvirksomheder",
    "sg:phone":"+45 38 11 89 10",
    "sg:postcode":"2000",
    "sg:province":"Danmark",
    "wof:name":"Scan-Soft",
    "wof:placetype":"venue"
},
  "geometry": {"coordinates":[12.5299301147,55.6787872314],"type":"Point"}
}