{
  "type": "Feature",
  "properties": {
    "addr:full":"Fmd.: Margit Linnemann, S\u00f8ndergade 45 Ebeltoft Danmark 8400",
    "addr:housenumber":"45",
    "addr:postcode":"8400",
    "addr:street":"Sondergade",
    "iso:country":"DK",
    "sg:address":"Fmd.: Margit Linnemann, S\u00f8ndergade 45",
    "sg:city":"Ebeltoft",
    "sg:orig_category":"Kulturelle foreninger",
    "sg:phone":"+45 86 34 14 90",
    "sg:postcode":"8400",
    "sg:province":"Danmark",
    "wof:name":"Dramat\u00f8rerne",
    "wof:placetype":"venue"
},
  "geometry": {"coordinates":[10.6778745651,56.199798584],"type":"Point"}
}