{
  "type": "Feature",
  "properties": {
    "addr:full":"Fmd.: Christian Dahl, \u00d8lsevej 3, Sandby Glums\u00f8 Danmark 4171",
    "addr:housenumber":"3",
    "addr:postcode":"4171",
    "addr:street":"Olsevej;Glumso",
    "iso:country":"DK",
    "sg:address":"Fmd.: Christian Dahl, \u00d8lsevej 3, Sandby",
    "sg:city":"Glums\u00f8",
    "sg:orig_category":"Folkedans",
    "sg:phone":"+45 57 64 36 69",
    "sg:postcode":"4171",
    "sg:province":"Danmark",
    "wof:name":"Tybjerg & Omegns Folkedanserforening",
    "wof:placetype":"venue"
},
  "geometry": {"coordinates":[11.6862697601,55.3553962708],"type":"Point"}
}