{
  "type": "Feature",
  "properties": {
    "addr:full":"Elisag\u00e5rdsvej 6 Roskilde Danmark 4000",
    "addr:housenumber":"6",
    "addr:postcode":"4000",
    "addr:street":"Elisagaardsvej",
    "iso:country":"DK",
    "sg:address":"Elisag\u00e5rdsvej 6",
    "sg:city":"Roskilde",
    "sg:orig_category":"Motorcykler",
    "sg:phone":"+45 46 35 47 19",
    "sg:postcode":"4000",
    "sg:province":"Danmark",
    "wof:name":"P.C. Motorcykler",
    "wof:placetype":"venue"
},
  "geometry": {"coordinates":[12.1018724442,55.642036438],"type":"Point"}
}