{
  "type": "Feature",
  "properties": {
    "addr:full":"R\u00e5dhuset, R\u00e5dhus Alle 1 S\u00f8borg Danmark 2860",
    "addr:housenumber":"1",
    "addr:postcode":"2860",
    "addr:street":"Raadhus Alle",
    "iso:country":"DK",
    "sg:address":"R\u00e5dhuset, R\u00e5dhus Alle 1",
    "sg:city":"S\u00f8borg",
    "sg:orig_category":"Kommunen",
    "sg:phone":"+45 39 57 50 00",
    "sg:postcode":"2860",
    "sg:province":"Danmark",
    "sg:website":"www.gladsaxe.dk",
    "wof:name":"Gladsaxe Kommune",
    "wof:placetype":"venue"
},
  "geometry": {"coordinates":[82.0155715942,24.8934593201],"type":"Point"}
}