{
  "type": "Feature",
  "properties": {
    "addr:full":"Wingesvej 77 Randers Danmark 8900",
    "addr:housenumber":"77",
    "addr:postcode":"8900",
    "addr:street":"Wingesvej",
    "iso:country":"DK",
    "sg:address":"Wingesvej 77",
    "sg:city":"Randers",
    "sg:orig_category":"INGENI\u00c3\u02dcRER",
    "sg:phone":"+45 86 41 20 73",
    "sg:postcode":"8900",
    "sg:province":"Danmark",
    "wof:name":"Kerstens, Ejnar",
    "wof:placetype":"venue"
},
  "geometry": {"coordinates":[9.9678440094,56.4537811279],"type":"Point"}
}