{
  "type": "Feature",
  "properties": {
    "iso:country":"DK",
    "sg:address":"Sortevej 11, Oddesund",
    "sg:city":"Thyholm",
    "sg:orig_category":"Borger- og beboerforeninger",
    "sg:phone":"+45 97 87 57 97",
    "sg:postcode":"7790",
    "sg:province":"Danmark",
    "wof:name":"Oddesund Nord Beboerforening og B\u00e5delaug",
    "wof:placetype":"venue"
},
  "geometry": {"coordinates":[8.525765419,56.6507072449],"type":"Point"}
}