{
  "type": "Feature",
  "properties": {
    "addr:full":"B\u00e5dvej 46 Odense N\u00d8 Danmark 5240",
    "addr:housenumber":"46",
    "addr:postcode":"5240",
    "addr:street":"Baadvej",
    "iso:country":"DK",
    "sg:address":"B\u00e5dvej 46",
    "sg:city":"Odense N\u00d8",
    "sg:orig_category":"Havearkitekter",
    "sg:phone":"+45 66 10 57 74",
    "sg:postcode":"5240",
    "sg:province":"Danmark",
    "wof:name":"JE-Bonsai",
    "wof:placetype":"venue"
},
  "geometry": {"coordinates":[10.4433708191,55.41198349],"type":"Point"}
}