{
  "type": "Feature",
  "properties": {
    "addr:full":"Torvet 2 Frederiksv\u00e6rk Danmark 3300",
    "addr:housenumber":"2",
    "addr:postcode":"3300",
    "addr:street":"Torvet",
    "iso:country":"DK",
    "sg:address":"Torvet 2",
    "sg:city":"Frederiksv\u00e6rk",
    "sg:orig_category":"Politi",
    "sg:phone":"+45 47 72 14 48",
    "sg:postcode":"3300",
    "sg:province":"Danmark",
    "wof:name":"Frederiksv\u00e6rk Politi",
    "wof:placetype":"venue"
},
  "geometry": {"coordinates":[9.9058914185,59.7713279724],"type":"Point"}
}