{
  "type": "Feature",
  "properties": {
    "iso:country":"DK",
    "sg:address":"Hovedgaden 52 A",
    "sg:city":"Humble",
    "sg:orig_category":"Botilbud",
    "sg:postcode":"5932",
    "sg:province":"Danmark",
    "wof:name":"Hovedgadens Bof\u00e6llesskab",
    "wof:placetype":"venue"
},
  "geometry": {"coordinates":[10.701128006,54.8309936523],"type":"Point"}
}