{
  "type": "Feature",
  "properties": {
    "addr:full":"Ahornsvinget 23, Nr. Felding Holstebro Danmark 7500",
    "addr:housenumber":"23",
    "addr:postcode":"7500",
    "addr:street":"Ahornsvinget;Felding",
    "iso:country":"DK",
    "sg:address":"Ahornsvinget 23, Nr. Felding",
    "sg:city":"Holstebro",
    "sg:orig_category":"Malermestre",
    "sg:phone":"+45 97 40 31 96",
    "sg:postcode":"7500",
    "sg:province":"Danmark",
    "sg:website":"www.holstebromalerfirma.dk",
    "wof:name":"Holstebro Malerfirma",
    "wof:placetype":"venue"
},
  "geometry": {"coordinates":[8.6202583313,56.3625221252],"type":"Point"}
}