{
  "type": "Feature",
  "properties": {
    "addr:full":"Horsensgade 1 \u00c5rhus C Danmark 8000",
    "addr:housenumber":"1",
    "addr:postcode":"8000",
    "addr:street":"Horsensgade",
    "iso:country":"DK",
    "sg:address":"Horsensgade 1",
    "sg:city":"\u00c5rhus C",
    "sg:orig_category":"Pizzeriaer",
    "sg:phone":"+45 86 18 03 84",
    "sg:postcode":"8000",
    "sg:province":"Danmark",
    "wof:name":"Flyvende T\u00e6ppe, Det",
    "wof:placetype":"venue"
},
  "geometry": {"coordinates":[4.717400074,49.7588005066],"type":"Point"}
}