{
  "type": "Feature",
  "properties": {
    "addr:full":"Borkvej 10, No Ringk\u00f8bing Danmark 6950",
    "addr:housenumber":"10",
    "addr:postcode":"6950",
    "addr:street":"Borkvej;No Ringkobing Danmark",
    "iso:country":"DK",
    "sg:address":"Borkvej 10, No",
    "sg:city":"Ringk\u00f8bing",
    "sg:orig_category":"Bogtrykkerier",
    "sg:phone":"+45 97 33 00 87",
    "sg:postcode":"6950",
    "sg:province":"Danmark",
    "wof:name":"After Hand - Hardsyssel Bogtrykkeri",
    "wof:placetype":"venue"
},
  "geometry": {"coordinates":[8.2507953644,56.0878334045],"type":"Point"}
}