{
  "type": "Feature",
  "properties": {
    "iso:country":"DK",
    "sg:address":"Nords\u00f8vej 2, S\u00f8ndervig",
    "sg:city":"Ringk\u00f8bing",
    "sg:orig_category":"HOTELS: OG MOTELLER",
    "sg:phone":"+45 97 33 90 02",
    "sg:postcode":"6950",
    "sg:province":"Danmark",
    "wof:name":"Strandkroen, Hotel",
    "wof:placetype":"venue"
},
  "geometry": {"coordinates":[-102.0896530151,42.0193557739],"type":"Point"}
}