{
  "type": "Feature",
  "properties": {
    "addr:full":"Amager Landevej 131 Kastrup Danmark 2770",
    "addr:housenumber":"131",
    "addr:postcode":"2770",
    "addr:street":"Amager Landevej",
    "iso:country":"DK",
    "sg:address":"Amager Landevej 131",
    "sg:city":"Kastrup",
    "sg:orig_category":"Kiosker",
    "sg:phone":"+45 32 52 48 22",
    "sg:postcode":"2770",
    "sg:province":"Danmark",
    "wof:name":"Service Kiosk",
    "wof:placetype":"venue"
},
  "geometry": {"coordinates":[12.623216629,55.6287307739],"type":"Point"}
}