{
  "type": "Feature",
  "properties": {
    "addr:full":"\u00d8stergade 64 Roskilde Danmark 4000",
    "addr:housenumber":"64",
    "addr:postcode":"4000",
    "addr:street":"Ostergade",
    "iso:country":"DK",
    "sg:address":"\u00d8stergade 64",
    "sg:city":"Roskilde",
    "sg:classifiers":[
        {
            "category":"Retail",
            "subcategory":"Storage",
            "type":"Services"
        }
    ],
    "sg:phone":"+45 46 32 62 42",
    "sg:postcode":"4000",
    "sg:province":"Danmark",
    "sg:tags":[
        "edb",
        "hardware",
        "-"
    ],
    "sg:website":"www.frisch-data.dk",
    "wof:name":"HiCoTech",
    "wof:placetype":"venue"
},
  "geometry": {"coordinates":[12.0973844528,55.6383895874],"type":"Point"}
}