{
  "type": "Feature",
  "properties": {
    "addr:full":"S\u00f8ndergade 6 Saltum Danmark 9493",
    "addr:housenumber":"6",
    "addr:postcode":"9493",
    "addr:street":"Sondergade",
    "iso:country":"DK",
    "sg:address":"S\u00f8ndergade 6",
    "sg:city":"Saltum",
    "sg:classifiers":[
        {
            "category":"Restaurant",
            "type":"Food & Drink"
        }
    ],
    "sg:phone":"+45 98 88 19 22",
    "sg:postcode":"9493",
    "sg:province":"Danmark",
    "wof:name":"Saltum Kro",
    "wof:placetype":"venue"
},
  "geometry": {"coordinates":[9.6974611282,57.2714996338],"type":"Point"}
}