{
  "type": "Feature",
  "properties": {
    "iso:country":"DK",
    "sg:address":"Sognepr\u00e6st: Hans J\u00f8rgen \u00d8stergaard (K/B), Pr\u00e6stegaardsvej 7, Felsted",
    "sg:city":"Aabenraa",
    "sg:orig_category":"Kirkesogne",
    "sg:phone":"+45 74 68 53 07",
    "sg:postcode":"6200",
    "sg:province":"Danmark",
    "wof:name":"Felsted Sogn",
    "wof:placetype":"venue"
},
  "geometry": {"coordinates":[9.4213867188,55.0449562073],"type":"Point"}
}