{
  "type": "Feature",
  "properties": {
    "addr:full":"Str\u00f8byvej 40 Hvidovre Danmark 2650",
    "addr:housenumber":"40",
    "addr:postcode":"2650",
    "addr:street":"Strobyvej",
    "iso:country":"DK",
    "sg:address":"Str\u00f8byvej 40",
    "sg:city":"Hvidovre",
    "sg:orig_category":"Selskabslokaler",
    "sg:phone":"+45 36 78 62 62",
    "sg:postcode":"2650",
    "sg:province":"Danmark",
    "wof:name":"Str\u00f8byhus Selskabslokaler",
    "wof:placetype":"venue"
},
  "geometry": {"coordinates":[12.4858455658,55.6405754089],"type":"Point"}
}