{
  "type": "Feature",
  "properties": {
    "addr:full":"Leder: Hans Henrik Jacobsen, Skolevej 9, N\u00e6sby Odense N Danmark 5270",
    "addr:housenumber":"9",
    "addr:postcode":"5270",
    "addr:street":"Jacobsen Skolevej;Naesby",
    "iso:country":"DK",
    "sg:address":"Leder: Hans Henrik Jacobsen, Skolevej 9, N\u00e6sby",
    "sg:city":"Odense N",
    "sg:orig_category":"Lokalarkiver",
    "sg:postcode":"5270",
    "sg:province":"Danmark",
    "wof:name":"Alles\u00f8-Broby-N\u00e6sby lokalarkiv",
    "wof:placetype":"venue"
},
  "geometry": {"coordinates":[10.3306798935,55.4711418152],"type":"Point"}
}