{
  "type": "Feature",
  "properties": {
    "iso:country":"DK",
    "sg:address":"Lyngby Hovedgade 59 - 61",
    "sg:city":"Kongens Lyngby",
    "sg:orig_category":"Sengeudstyr",
    "sg:phone":"+45 45 87 40 42",
    "sg:postcode":"2800",
    "sg:province":"Danmark",
    "wof:name":"Jysk Senget\u00f8jslager",
    "wof:placetype":"venue"
},
  "geometry": {"coordinates":[12.506858,55.768108],"type":"Point"}
}