{
  "type": "Feature",
  "properties": {
    "addr:full":"Storegade 60, Holsted St Holsted Danmark 6670",
    "addr:housenumber":"60",
    "addr:postcode":"6670",
    "addr:street":"Storegade;St;Danmark",
    "iso:country":"DK",
    "sg:address":"Storegade 60, Holsted St",
    "sg:city":"Holsted",
    "sg:orig_category":"Bagere",
    "sg:phone":"+45 75 39 24 17",
    "sg:postcode":"6670",
    "sg:province":"Danmark",
    "wof:name":"Vor Bager",
    "wof:placetype":"venue"
},
  "geometry": {"coordinates":[8.9169273376,55.5111999512],"type":"Point"}
}