{
  "type": "Feature",
  "properties": {
    "iso:country":"DK",
    "sg:address":"Byagervej 15",
    "sg:city":"Fuglebjerg",
    "sg:orig_category":"Genbrugsbutikker",
    "sg:phone":"+45 55 45 40 30",
    "sg:postcode":"4250",
    "sg:province":"Danmark",
    "wof:name":"Dansk R\u00f8de Kors Genbrug",
    "wof:placetype":"venue"
},
  "geometry": {"coordinates":[11.5470647812,55.3019447327],"type":"Point"}
}