{
  "type": "Feature",
  "properties": {
    "addr:full":"Ny Kongevej 6 Odense C Danmark 5000",
    "addr:housenumber":"6",
    "addr:postcode":"5000",
    "addr:street":"Kongevej",
    "iso:country":"DK",
    "sg:address":"Ny Kongevej 6",
    "sg:city":"Odense C",
    "sg:orig_category":"Vinduespolering",
    "sg:phone":"+45 66 19 34 58",
    "sg:postcode":"5000",
    "sg:province":"Danmark",
    "wof:name":"Thulstrups Eftf",
    "wof:placetype":"venue"
},
  "geometry": {"coordinates":[10.3669033051,55.4017028809],"type":"Point"}
}