{
  "type": "Feature",
  "properties": {
    "addr:full":"v/ Gerda Jacobsen, Bjerrevej 301, Bjerre Hornsyld Danmark 8783",
    "addr:housenumber":"301",
    "addr:postcode":"8783",
    "addr:street":"Bjerrevej",
    "iso:country":"DK",
    "sg:address":"v/ Gerda Jacobsen, Bjerrevej 301, Bjerre",
    "sg:city":"Hornsyld",
    "sg:orig_category":"Lokalarkiver",
    "sg:phone":"+45 75 68 10 07",
    "sg:postcode":"8783",
    "sg:province":"Danmark",
    "wof:name":"Bjerre Lokalarkiv",
    "wof:placetype":"venue"
},
  "geometry": {"coordinates":[9.8611288071,55.7560806274],"type":"Point"}
}