{
  "type": "Feature",
  "properties": {
    "addr:full":"Vestre Skovvej 16 Grenaa Danmark 8500",
    "addr:housenumber":"16",
    "addr:postcode":"8500",
    "addr:street":"Vestre Skovvej",
    "iso:country":"DK",
    "sg:address":"Vestre Skovvej 16",
    "sg:city":"Grenaa",
    "sg:orig_category":"Ejendomshandel",
    "sg:phone":"+45 86 32 10 01",
    "sg:postcode":"8500",
    "sg:province":"Danmark",
    "wof:name":"Petersens Ejendomskontor, Vita",
    "wof:placetype":"venue"
},
  "geometry": {"coordinates":[10.8786478043,56.4034309387],"type":"Point"}
}