{
  "type": "Feature",
  "properties": {
    "addr:full":"Odinsvej 2 Padborg Danmark 6330",
    "addr:housenumber":"2",
    "addr:postcode":"6330",
    "addr:street":"Odinsvej",
    "iso:country":"DK",
    "sg:address":"Odinsvej 2",
    "sg:city":"Padborg",
    "sg:orig_category":"Spedition",
    "sg:phone":"+45 74 67 04 30",
    "sg:postcode":"6330",
    "sg:province":"Danmark",
    "wof:name":"Norway Express Aps",
    "wof:placetype":"venue"
},
  "geometry": {"coordinates":[9.3405504227,54.8269004822],"type":"Point"}
}