{
  "type": "Feature",
  "properties": {
    "iso:country":"DK",
    "sg:address":"S\u00f8ndergade 5",
    "sg:city":"Glamsbjerg",
    "sg:classifiers":[
        {
            "category":"Banks & Credit Unions",
            "subcategory":"Bank",
            "type":"Services"
        }
    ],
    "sg:phone":"+45 63 72 74 80",
    "sg:postcode":"5620",
    "sg:province":"Danmark",
    "sg:tags":[
        "banker"
    ],
    "sg:website":"www.danskebank.dk",
    "wof:name":"Danske Bank",
    "wof:placetype":"venue"
},
  "geometry": {"coordinates":[10.105411,55.278324],"type":"Point"}
}