{
  "type": "Feature",
  "properties": {
    "addr:full":"Ny Allegade 8 Haderslev Danmark 6100",
    "addr:housenumber":"8",
    "addr:postcode":"6100",
    "addr:street":"Allegade",
    "iso:country":"DK",
    "sg:address":"Ny Allegade 8",
    "sg:city":"Haderslev",
    "sg:orig_category":"Arkitekter",
    "sg:phone":"+45 74 53 00 40",
    "sg:postcode":"6100",
    "sg:province":"Danmark",
    "sg:website":"www.jessenmaa.dk",
    "wof:name":"Jessen, J\u00f8rgen Toft",
    "wof:placetype":"venue"
},
  "geometry": {"coordinates":[9.4947462082,55.2523498535],"type":"Point"}
}