{
  "type": "Feature",
  "properties": {
    "iso:country":"DK",
    "sg:address":"Viborgvej 3",
    "sg:city":"\u00c5rhus C",
    "sg:orig_category":"Kirurgi",
    "sg:phone":"+45 86 19 86 11",
    "sg:postcode":"8000",
    "sg:province":"Danmark",
    "wof:name":"Gram-Hansen, J\u00f8rn",
    "wof:placetype":"venue"
},
  "geometry": {"coordinates":[4.717400074,49.7588005066],"type":"Point"}
}