{
  "type": "Feature",
  "properties": {
    "addr:full":"Svanholm Alle 2 Skibby Danmark 4050",
    "addr:housenumber":"2",
    "addr:postcode":"4050",
    "addr:street":"Svanholm Alle",
    "iso:country":"DK",
    "sg:address":"Svanholm Alle 2",
    "sg:city":"Skibby",
    "sg:orig_category":"Akupunktur",
    "sg:phone":"+45 47 56 66 36",
    "sg:postcode":"4050",
    "sg:province":"Danmark",
    "wof:name":"L\u00e6gaard, Elsebeth",
    "wof:placetype":"venue"
},
  "geometry": {"coordinates":[11.9420957565,55.7789421082],"type":"Point"}
}