{
  "type": "Feature",
  "properties": {
    "addr:full":"Birkevej 163, Fuglslev Ebeltoft Danmark 8400",
    "addr:housenumber":"163",
    "addr:postcode":"fuglslev;8400",
    "addr:street":"Birkevej",
    "iso:country":"DK",
    "sg:address":"Birkevej 163, Fuglslev",
    "sg:city":"Ebeltoft",
    "sg:orig_category":"Malermestre",
    "sg:phone":"+45 86 36 40 60",
    "sg:postcode":"8400",
    "sg:province":"Danmark",
    "wof:name":"Andersen, Benny",
    "wof:placetype":"venue"
},
  "geometry": {"coordinates":[10.6778745651,56.199798584],"type":"Point"}
}