{
  "type": "Feature",
  "properties": {
    "addr:full":"Tofteg\u00e5rds Plads 6 Valby Danmark 2500",
    "addr:housenumber":"6",
    "addr:postcode":"2500",
    "addr:street":"Toftegaards Plads",
    "iso:country":"DK",
    "sg:address":"Tofteg\u00e5rds Plads 6",
    "sg:city":"Valby",
    "sg:orig_category":"Bagere",
    "sg:phone":"+45 36 46 74 55",
    "sg:postcode":"2500",
    "sg:province":"Danmark",
    "wof:name":"Frista Konditori",
    "wof:placetype":"venue"
},
  "geometry": {"coordinates":[12.517767,55.662346],"type":"Point"}
}