{
  "type": "Feature",
  "properties": {
    "addr:full":"Havnegade 13 Frederikssund Danmark 3600",
    "addr:housenumber":"13",
    "addr:postcode":"3600",
    "addr:street":"Havnegade",
    "iso:country":"DK",
    "sg:address":"Havnegade 13",
    "sg:city":"Frederikssund",
    "sg:orig_category":"Begravelsesforretninger",
    "sg:phone":"+45 47 31 02 24",
    "sg:postcode":"3600",
    "sg:province":"Danmark",
    "wof:name":"Andersens Eftf.",
    "wof:placetype":"venue"
},
  "geometry": {"coordinates":[12.0575771332,55.8387870789],"type":"Point"}
}