{
  "type": "Feature",
  "properties": {
    "iso:country":"DK",
    "sg:address":"Skuderupvej 9",
    "sg:city":"Fakse",
    "sg:classifiers":[
        {
            "category":"Professional",
            "subcategory":"Business Services",
            "type":"Services"
        }
    ],
    "sg:phone":"+45 56 71 04 11",
    "sg:postcode":"4640",
    "sg:province":"Danmark",
    "sg:tags":[
        "import",
        "vin"
    ],
    "sg:website":"www.hvidlog-vin.dk",
    "wof:name":"Hvidl\u00f8g og Vin",
    "wof:placetype":"venue"
},
  "geometry": {"coordinates":[12.1203422546,55.2574195862],"type":"Point"}
}