{
  "type": "Feature",
  "properties": {
    "addr:full":"Fmd.: Poul S\u00f8ndergaard, Mosebyvej 18 Holstebro Danmark 7500",
    "addr:housenumber":"18",
    "addr:postcode":"7500",
    "addr:street":"Poul Sondergaard Mosebyvej",
    "iso:country":"DK",
    "sg:address":"Fmd.: Poul S\u00f8ndergaard, Mosebyvej 18",
    "sg:city":"Holstebro",
    "sg:orig_category":"Borger- og beboerforeninger",
    "sg:phone":"+45 97 42 99 54",
    "sg:postcode":"7500",
    "sg:province":"Danmark",
    "wof:name":"Hornsh\u00f8j-Smedevad Borgerforening",
    "wof:placetype":"venue"
},
  "geometry": {"coordinates":[8.6202583313,56.3625221252],"type":"Point"}
}