{
  "type": "Feature",
  "properties": {
    "addr:full":"Hadsundvej 2 Mariager Danmark 9550",
    "addr:housenumber":"2",
    "addr:postcode":"9550",
    "addr:street":"Hadsundvej",
    "iso:country":"DK",
    "sg:address":"Hadsundvej 2",
    "sg:city":"Mariager",
    "sg:orig_category":"Murermestre",
    "sg:phone":"+45 98 54 12 02",
    "sg:postcode":"9550",
    "sg:province":"Danmark",
    "wof:name":"\u00d8stergaard Nielsen, Viggo",
    "wof:placetype":"venue"
},
  "geometry": {"coordinates":[9.9940214157,56.660823822],"type":"Point"}
}