{
  "type": "Feature",
  "properties": {
    "addr:full":"\u00d8ster\u00e5gade 5 Aalborg Danmark 9000",
    "addr:housenumber":"5",
    "addr:postcode":"9000",
    "addr:street":"Osteraagade",
    "iso:country":"DK",
    "sg:address":"\u00d8ster\u00e5gade 5",
    "sg:city":"Aalborg",
    "sg:orig_category":"Forsikringer",
    "sg:phone":"+45 70 13 79 13",
    "sg:postcode":"9000",
    "sg:province":"Danmark",
    "wof:name":"Topdanmark",
    "wof:placetype":"venue"
},
  "geometry": {"coordinates":[9.9210119247,57.0481948853],"type":"Point"}
}