{
  "type": "Feature",
  "properties": {
    "addr:full":"Torvet 14, Askov Vejen Danmark 6600",
    "addr:housenumber":"14",
    "addr:postcode":"6600",
    "addr:street":"Torvet;Askov",
    "iso:country":"DK",
    "sg:address":"Torvet 14, Askov",
    "sg:city":"Vejen",
    "sg:orig_category":"Sengeudstyr",
    "sg:phone":"+45 75 36 77 11",
    "sg:postcode":"6600",
    "sg:province":"Danmark",
    "sg:website":"www.danolan.dk",
    "wof:name":"Danolan Magnetsenget\u00f8j",
    "wof:placetype":"venue"
},
  "geometry": {"coordinates":[9.1396121979,55.4778175354],"type":"Point"}
}