{
  "type": "Feature",
  "properties": {
    "addr:full":"Caroline Amalie Vej 59 Kongens Lyngby Danmark 2800",
    "addr:housenumber":"59",
    "addr:postcode":"2800",
    "addr:street":"Caroline Amalie Vej",
    "iso:country":"DK",
    "sg:address":"Caroline Amalie Vej 59",
    "sg:city":"Kongens Lyngby",
    "sg:orig_category":"Arkitekter",
    "sg:phone":"+45 45 88 56 52",
    "sg:postcode":"2800",
    "sg:province":"Danmark",
    "wof:name":"Vedtofte, Johannes",
    "wof:placetype":"venue"
},
  "geometry": {"coordinates":[12.5024662018,55.786075592],"type":"Point"}
}