{
  "type": "Feature",
  "properties": {
    "addr:full":"Skelmosevej 10 Valby Danmark 2500",
    "addr:housenumber":"10",
    "addr:postcode":"2500",
    "addr:street":"Skelmosevej",
    "iso:country":"DK",
    "sg:address":"Skelmosevej 10",
    "sg:city":"Valby",
    "sg:orig_category":"Fotografer",
    "sg:phone":"+45 36 16 46 06",
    "sg:postcode":"2500",
    "sg:province":"Danmark",
    "wof:name":"Djenner Fotografi ApS, Torben",
    "wof:placetype":"venue"
},
  "geometry": {"coordinates":[12.5118303299,55.6690979004],"type":"Point"}
}