{
  "type": "Feature",
  "properties": {
    "addr:full":"Bredgade 23 Kolind Danmark 8560",
    "addr:housenumber":"23",
    "addr:postcode":"8560",
    "addr:street":"Bredgade",
    "iso:country":"DK",
    "sg:address":"Bredgade 23",
    "sg:city":"Kolind",
    "sg:orig_category":"Blomsterhandlere",
    "sg:phone":"+45 86 39 11 01",
    "sg:postcode":"8560",
    "sg:province":"Danmark",
    "wof:name":"Ruths Blomster",
    "wof:placetype":"venue"
},
  "geometry": {"coordinates":[10.5893068314,56.3616256714],"type":"Point"}
}