{
  "type": "Feature",
  "properties": {
    "iso:country":"DK",
    "sg:address":"Egemosevej 28 B",
    "sg:city":"Vejstrup",
    "sg:orig_category":"Reklamebureauer",
    "sg:phone":"+45 26 16 99 16",
    "sg:postcode":"5882",
    "sg:province":"Danmark",
    "wof:name":"Eventmajeren",
    "wof:placetype":"venue"
},
  "geometry": {"coordinates":[10.7090911865,55.1073303223],"type":"Point"}
}