{
  "type": "Feature",
  "properties": {
    "addr:full":"Farum Bytorv 38 Farum Danmark 3520",
    "addr:housenumber":"38",
    "addr:postcode":"3520",
    "addr:street":"Farum Bytorv",
    "iso:country":"DK",
    "sg:address":"Farum Bytorv 38",
    "sg:city":"Farum",
    "sg:orig_category":"Optikere",
    "sg:phone":"+45 44 95 25 75",
    "sg:postcode":"3520",
    "sg:province":"Danmark",
    "wof:name":"Profil Optik",
    "wof:placetype":"venue"
},
  "geometry": {"coordinates":[12.3816976547,55.814781189],"type":"Point"}
}