{
  "type": "Feature",
  "properties": {
    "addr:full":"Lille Byhavevej 6, Tved Svendborg Danmark 5700",
    "addr:housenumber":"6",
    "addr:postcode":"5700",
    "addr:street":"Lille Byhavevej;Tved",
    "iso:country":"DK",
    "sg:address":"Lille Byhavevej 6, Tved",
    "sg:city":"Svendborg",
    "sg:orig_category":"Tryksager",
    "sg:phone":"+45 62 21 71 71",
    "sg:postcode":"5700",
    "sg:province":"Danmark",
    "wof:name":"Tryk P\u00e5",
    "wof:placetype":"venue"
},
  "geometry": {"coordinates":[10.6065101624,55.0595970154],"type":"Point"}
}