{
  "type": "Feature",
  "properties": {
    "addr:full":"T\u00f8mrergade 3 K\u00f8benhavn N Danmark 2200",
    "addr:housenumber":"3",
    "addr:postcode":"2200",
    "addr:street":"Tomrergade;N Danmark",
    "iso:country":"DK",
    "sg:address":"T\u00f8mrergade 3",
    "sg:city":"K\u00f8benhavn N",
    "sg:orig_category":"Arkitekter",
    "sg:phone":"+45 35 35 41 86",
    "sg:postcode":"2200",
    "sg:province":"Danmark",
    "wof:name":"Noes, Folmer",
    "wof:placetype":"venue"
},
  "geometry": {"coordinates":[-76.4447174072,37.4649467468],"type":"Point"}
}