{
  "type": "Feature",
  "properties": {
    "addr:full":"Kordilgade 1 Kalundborg Danmark 4400",
    "addr:housenumber":"1",
    "addr:postcode":"4400",
    "addr:street":"Kordilgade",
    "iso:country":"DK",
    "sg:address":"Kordilgade 1",
    "sg:city":"Kalundborg",
    "sg:orig_category":"HOTELS: OG MOTELLER",
    "sg:phone":"+45 59 51 01 65",
    "sg:postcode":"4400",
    "sg:province":"Danmark",
    "wof:name":"Lundsgaard, Ole",
    "wof:placetype":"venue"
},
  "geometry": {"coordinates":[11.0878677368,55.6809616089],"type":"Point"}
}