{
  "type": "Feature",
  "properties": {
    "addr:full":"Gryderupvej 145, Gryderup Boeslunde Danmark 4242",
    "addr:housenumber":"145",
    "addr:postcode":"4242",
    "addr:street":"Gryderupvej",
    "iso:country":"DK",
    "sg:address":"Gryderupvej 145, Gryderup",
    "sg:city":"Boeslunde",
    "sg:orig_category":"Vinduespolering",
    "sg:phone":"+45 58 38 53 28",
    "sg:postcode":"4242",
    "sg:province":"Danmark",
    "wof:name":"Ole's Vinduespolering",
    "wof:placetype":"venue"
},
  "geometry": {"coordinates":[11.2663583755,55.3043022156],"type":"Point"}
}