{
  "type": "Feature",
  "properties": {
    "addr:full":"Magnoliavej 14, Dyrup Odense SV Danmark 5250",
    "addr:housenumber":"14",
    "addr:postcode":"5250",
    "addr:street":"Magnoliavej;Dyrup",
    "iso:country":"DK",
    "sg:address":"Magnoliavej 14, Dyrup",
    "sg:city":"Odense SV",
    "sg:orig_category":"Reklamebureauer",
    "sg:phone":"+45 66 17 08 44",
    "sg:postcode":"5250",
    "sg:province":"Danmark",
    "wof:name":"K.E. Freelance Art - Direction ApS",
    "wof:placetype":"venue"
},
  "geometry": {"coordinates":[10.3153953552,55.3362998962],"type":"Point"}
}