{
  "type": "Feature",
  "properties": {
    "iso:country":"DK",
    "sg:address":"Vilvordevej 1",
    "sg:city":"Charlottenlund",
    "sg:orig_category":"Bagere",
    "sg:phone":"+45 39 64 03 08",
    "sg:postcode":"2920",
    "sg:province":"Danmark",
    "wof:name":"Femvejens Bageri",
    "wof:placetype":"venue"
},
  "geometry": {"coordinates":[12.5583696365,55.7583999634],"type":"Point"}
}