{
  "type": "Feature",
  "properties": {
    "addr:full":"Industrivej 34 Lemvig Danmark 7620",
    "addr:housenumber":"34",
    "addr:postcode":"7620",
    "addr:street":"Industrivej",
    "iso:country":"DK",
    "sg:address":"Industrivej 34",
    "sg:city":"Lemvig",
    "sg:orig_category":"Autoreparation og -service",
    "sg:phone":"+45 97 82 18 43",
    "sg:postcode":"7620",
    "sg:province":"Danmark",
    "wof:name":"Citro\u00ebn Lemvig",
    "wof:placetype":"venue"
},
  "geometry": {"coordinates":[8.2943658829,56.5410003662],"type":"Point"}
}