{
  "type": "Feature",
  "properties": {
    "addr:full":"Alstrupvej 9 Holstebro Danmark 7500",
    "addr:housenumber":"9",
    "addr:postcode":"7500",
    "addr:street":"Alstrupvej",
    "iso:country":"DK",
    "sg:address":"Alstrupvej 9",
    "sg:city":"Holstebro",
    "sg:orig_category":"Hobbybetonede foreninger",
    "sg:phone":"+45 97 41 16 51",
    "sg:postcode":"7500",
    "sg:province":"Danmark",
    "wof:name":"Motorcykelklubben Elmer",
    "wof:placetype":"venue"
},
  "geometry": {"coordinates":[8.5771903992,56.3934898376],"type":"Point"}
}