{
  "type": "Feature",
  "properties": {
    "addr:full":"Kystvej 22 Aabenraa Danmark 6200",
    "addr:housenumber":"22",
    "addr:postcode":"6200",
    "addr:street":"Kystvej",
    "iso:country":"DK",
    "sg:address":"Kystvej 22",
    "sg:city":"Aabenraa",
    "sg:orig_category":"Advokater",
    "sg:phone":"+45 73 33 31 00",
    "sg:postcode":"6200",
    "sg:province":"Danmark",
    "sg:website":"www.compasslaw.dk",
    "wof:name":"Compass Advokatfirma",
    "wof:placetype":"venue"
},
  "geometry": {"coordinates":[9.4213142395,55.0357093811],"type":"Point"}
}