{
  "type": "Feature",
  "properties": {
    "addr:full":"Bjernede Kirkevej 12 Sor\u00f8 Danmark 4180",
    "addr:housenumber":"12",
    "addr:postcode":"4180",
    "addr:street":"Bjernede Kirkevej",
    "iso:country":"DK",
    "sg:address":"Bjernede Kirkevej 12",
    "sg:city":"Sor\u00f8",
    "sg:orig_category":"Snedkermestre",
    "sg:phone":"+45 57 84 51 00",
    "sg:postcode":"4180",
    "sg:province":"Danmark",
    "wof:name":"Niels Larsen Fj\u00e6lleg\u00e5rd",
    "wof:placetype":"venue"
},
  "geometry": {"coordinates":[11.6269903183,55.4606666565],"type":"Point"}
}