{
  "type": "Feature",
  "properties": {
    "addr:full":"Sverigesvej 10 Hobro Danmark 9500",
    "addr:housenumber":"10",
    "addr:postcode":"9500",
    "addr:street":"Sverigesvej",
    "iso:country":"DK",
    "sg:address":"Sverigesvej 10",
    "sg:city":"Hobro",
    "sg:orig_category":"Ejendomshandel",
    "sg:phone":"+45 98 52 27 99",
    "sg:postcode":"9500",
    "sg:province":"Danmark",
    "wof:name":"Iversens Ejendomshandel",
    "wof:placetype":"venue"
},
  "geometry": {"coordinates":[9.8170261383,56.632270813],"type":"Point"}
}