{
  "type": "Feature",
  "properties": {
    "iso:country":"DK",
    "sg:address":"Fmd.: Jack Olsen, Gl. Landevej 66",
    "sg:city":"Vejle",
    "sg:orig_category":"Musik og sang",
    "sg:phone":"+45 75 83 40 54",
    "sg:postcode":"7100",
    "sg:province":"Danmark",
    "wof:name":"Cantemus",
    "wof:placetype":"venue"
},
  "geometry": {"coordinates":[9.5368051529,55.7113952637],"type":"Point"}
}