{
  "type": "Feature",
  "properties": {
    "iso:country":"DK",
    "sg:address":"Lindeg\u00e5rdsvej 51",
    "sg:city":"Charlottenlund",
    "sg:orig_category":"Advokater",
    "sg:phone":"+45 39 63 06 53",
    "sg:postcode":"2920",
    "sg:province":"Danmark",
    "sg:website":"www.boggild.dk",
    "wof:name":"B\u00f8ggild, David",
    "wof:placetype":"venue"
},
  "geometry": {"coordinates":[12.5697507858,55.7546234131],"type":"Point"}
}