{
  "type": "Feature",
  "properties": {
    "addr:full":"Jyllandsvej 9 Hobro Danmark 9500",
    "addr:housenumber":"9",
    "addr:postcode":"9500",
    "addr:street":"Jyllandsvej",
    "iso:country":"DK",
    "sg:address":"Jyllandsvej 9",
    "sg:city":"Hobro",
    "sg:orig_category":"Autolakering",
    "sg:phone":"+45 98 51 10 83",
    "sg:postcode":"9500",
    "sg:province":"Danmark",
    "wof:name":"Mejlstrups Autolakering",
    "wof:placetype":"venue"
},
  "geometry": {"coordinates":[9.8153400421,56.6304588318],"type":"Point"}
}