{
  "type": "Feature",
  "properties": {
    "addr:full":"Avder\u00f8dvej 20 Kokkedal Danmark 2980",
    "addr:housenumber":"20",
    "addr:postcode":"2980",
    "addr:street":"Avderodvej",
    "iso:country":"DK",
    "sg:address":"Avder\u00f8dvej 20",
    "sg:city":"Kokkedal",
    "sg:classifiers":[
        {
            "category":"Professional",
            "subcategory":"Computer Services",
            "type":"Services"
        }
    ],
    "sg:phone":"+45 48 28 38 38",
    "sg:postcode":"2980",
    "sg:province":"Danmark",
    "sg:tags":[
        "edb",
        "-",
        "software"
    ],
    "sg:website":"www.multimark.dk",
    "wof:name":"Software Innovation A/S",
    "wof:placetype":"venue"
},
  "geometry": {"coordinates":[12.438085556,55.918422699],"type":"Point"}
}