{
  "type": "Feature",
  "properties": {
    "iso:country":"DK",
    "sg:address":"Kilen 18 - 20",
    "sg:city":"Aabenraa",
    "sg:orig_category":"Slagterier",
    "sg:phone":"+45 74 62 49 40",
    "sg:postcode":"6200",
    "sg:province":"Danmark",
    "wof:name":"Knut Eriksen Export/Import,KEE",
    "wof:placetype":"venue"
},
  "geometry": {"coordinates":[9.4255828857,55.0467720032],"type":"Point"}
}