{
  "type": "Feature",
  "properties": {
    "addr:full":"Torvev\u00e6nget 224 Tranbjerg Danmark 8310",
    "addr:housenumber":"224",
    "addr:postcode":"8310",
    "iso:country":"DK",
    "sg:address":"Torvev\u00e6nget 224",
    "sg:city":"Tranbjerg",
    "sg:orig_category":"Psykologer, praktiserende",
    "sg:phone":"+45 86 29 02 94",
    "sg:postcode":"8310",
    "sg:province":"Danmark",
    "sg:website":"www.edith.dk",
    "wof:name":"Schow, Edith",
    "wof:placetype":"venue"
},
  "geometry": {"coordinates":[10.1377973557,56.0914382935],"type":"Point"}
}