{
  "type": "Feature",
  "properties": {
    "addr:full":"Ryesgade 18 - 20, Postboks 230 8100",
    "addr:housenumber":"18 20;230",
    "addr:postcode":"8100",
    "addr:street":"Ryesgade;Postboks",
    "iso:country":"DK",
    "sg:address":"Ryesgade 18 - 20, Postboks 230",
    "sg:classifiers":[
        {
            "category":"Professional",
            "subcategory":"Advertising",
            "type":"Services"
        }
    ],
    "sg:phone":"+45 86 13 19 11",
    "sg:postcode":"8100",
    "sg:tags":[
        "telemarketing"
    ],
    "wof:name":"Telescan",
    "wof:placetype":"venue"
},
  "geometry": {"coordinates":[2.0778300762,49.1431007385],"type":"Point"}
}