{
  "type": "Feature",
  "properties": {
    "addr:full":"Frederiksborgvej 20 Helsinge Danmark 3200",
    "addr:housenumber":"20",
    "addr:postcode":"3200",
    "addr:street":"Frederiksborgvej",
    "iso:country":"DK",
    "sg:address":"Frederiksborgvej 20",
    "sg:city":"Helsinge",
    "sg:orig_category":"Varehuse",
    "sg:phone":"+45 48 79 56 66",
    "sg:postcode":"3200",
    "sg:province":"Danmark",
    "wof:name":"Kvickly",
    "wof:placetype":"venue"
},
  "geometry": {"coordinates":[12.200138092,56.0197792053],"type":"Point"}
}