{
  "type": "Feature",
  "properties": {
    "addr:full":"Lystoften 10 Skovlunde Danmark 2740",
    "addr:housenumber":"10",
    "addr:postcode":"2740",
    "addr:street":"Lystoften",
    "iso:country":"DK",
    "sg:address":"Lystoften 10",
    "sg:city":"Skovlunde",
    "sg:orig_category":"Murermestre",
    "sg:phone":"+45 44 91 71 11",
    "sg:postcode":"2740",
    "sg:province":"Danmark",
    "sg:website":"www.murerchr.dk",
    "wof:name":"Christjansen A/S, Chr.",
    "wof:placetype":"venue"
},
  "geometry": {"coordinates":[12.3942508698,55.7184867859],"type":"Point"}
}