{
  "type": "Feature",
  "properties": {
    "iso:country":"DK",
    "sg:address":"Lagerg\u00e5rdsvej 11",
    "sg:city":"Gentofte",
    "sg:orig_category":"Maskinfabrikker",
    "sg:phone":"+45 39 65 45 66",
    "sg:postcode":"2820",
    "sg:province":"Danmark",
    "wof:name":"Stabergs Maskinfabrik",
    "wof:placetype":"venue"
},
  "geometry": {"coordinates":[12.5102844238,55.7562141418],"type":"Point"}
}