{
  "type": "Feature",
  "properties": {
    "addr:full":"M\u00f8lleg\u00e5rden 2 Outrup Danmark 6855",
    "addr:housenumber":"2",
    "addr:postcode":"6855",
    "addr:street":"Mollegaarden",
    "iso:country":"DK",
    "sg:address":"M\u00f8lleg\u00e5rden 2",
    "sg:city":"Outrup",
    "sg:orig_category":"Plejecentre",
    "sg:phone":"+45 75 25 11 14",
    "sg:postcode":"6855",
    "sg:province":"Danmark",
    "wof:name":"Pleje- og aktivitets centret M\u00f8lleg\u00e5rden",
    "wof:placetype":"venue"
},
  "geometry": {"coordinates":[8.3423900604,55.7216491699],"type":"Point"}
}