{
  "type": "Feature",
  "properties": {
    "addr:full":"N\u00f8rregade 18 Bjerringbro Danmark 8850",
    "addr:housenumber":"18",
    "addr:postcode":"8850",
    "addr:street":"Norregade",
    "iso:country":"DK",
    "sg:address":"N\u00f8rregade 18",
    "sg:city":"Bjerringbro",
    "sg:orig_category":"Pizzeriaer",
    "sg:phone":"+45 86 68 85 60",
    "sg:postcode":"8850",
    "sg:province":"Danmark",
    "wof:name":"Italiano, Restaurant",
    "wof:placetype":"venue"
},
  "geometry": {"coordinates":[9.6594333649,56.3760375977],"type":"Point"}
}