{
  "type": "Feature",
  "properties": {
    "addr:full":"Hobrovej 317 Aalborg SV Danmark 9200",
    "addr:housenumber":"317",
    "addr:postcode":"9200",
    "addr:street":"Hobrovej",
    "iso:country":"DK",
    "sg:address":"Hobrovej 317",
    "sg:city":"Aalborg SV",
    "sg:orig_category":"Revisorer",
    "sg:phone":"+45 96 34 19 00",
    "sg:postcode":"9200",
    "sg:province":"Danmark",
    "wof:name":"Revisionsfirmaet Peder Sj\u00e6lland A/S",
    "wof:placetype":"venue"
},
  "geometry": {"coordinates":[9.8969202042,57.0174217224],"type":"Point"}
}