{
  "type": "Feature",
  "properties": {
    "addr:full":"Fmd.: Leif Adolfsen, Bjergbakkevej 25 Glostrup Danmark 2600",
    "addr:housenumber":"25",
    "addr:postcode":"2600",
    "addr:street":"Bjergbakkevej",
    "iso:country":"DK",
    "sg:address":"Fmd.: Leif Adolfsen, Bjergbakkevej 25",
    "sg:city":"Glostrup",
    "sg:orig_category":"Grundejerforeninger",
    "sg:phone":"+45 43 96 40 17",
    "sg:postcode":"2600",
    "sg:province":"Danmark",
    "wof:name":"Bjergbakkevej",
    "wof:placetype":"venue"
},
  "geometry": {"coordinates":[12.3957901001,55.6654663086],"type":"Point"}
}