{
  "type": "Feature",
  "properties": {
    "iso:country":"DK",
    "sg:address":"Nystedvej 25",
    "sg:city":"Herning",
    "sg:orig_category":"Snedkermestre",
    "sg:phone":"+45 97 12 44 57",
    "sg:postcode":"7400",
    "sg:province":"Danmark",
    "wof:name":"Herning Bygge Industri",
    "wof:placetype":"venue"
},
  "geometry": {"coordinates":[8.973950386,56.1577796936],"type":"Point"}
}