{
  "type": "Feature",
  "properties": {
    "addr:full":"V\u00e6gtergade 9 Nyborg Danmark 5800",
    "addr:housenumber":"9",
    "addr:postcode":"5800",
    "addr:street":"Vaegtergade",
    "iso:country":"DK",
    "sg:address":"V\u00e6gtergade 9",
    "sg:city":"Nyborg",
    "sg:orig_category":"Amtskommunale and kommunale organisationer",
    "sg:phone":"+45 65 31 60 05",
    "sg:postcode":"5800",
    "sg:province":"Danmark",
    "wof:name":"Kommunale Biografledere, Foreningen af",
    "wof:placetype":"venue"
},
  "geometry": {"coordinates":[10.7920942307,55.3127784729],"type":"Point"}
}