{
  "type": "Feature",
  "properties": {
    "addr:full":"G\u00f8teborgvej 18 Aalborg SV Danmark 9200",
    "addr:housenumber":"18",
    "addr:postcode":"9200",
    "addr:street":"Goteborgvej",
    "iso:country":"DK",
    "sg:address":"G\u00f8teborgvej 18",
    "sg:city":"Aalborg SV",
    "sg:orig_category":"Revisorer",
    "sg:phone":"+45 98 18 01 33",
    "sg:postcode":"9200",
    "sg:province":"Danmark",
    "sg:website":"www.deloitte.dk",
    "wof:name":"Deloitte & Touche",
    "wof:placetype":"venue"
},
  "geometry": {"coordinates":[9.8932304382,57.0233650208],"type":"Point"}
}