{
  "type": "Feature",
  "properties": {
    "iso:country":"DK",
    "sg:address":"PBN SVERIGE AB, Lyngbyvej 20,3",
    "sg:city":"K\u00f8benhavn \u00d8",
    "sg:classifiers":[
        {
            "category":"Retail",
            "subcategory":"Storage",
            "type":"Services"
        }
    ],
    "sg:phone":"+45 39 15 81 00",
    "sg:postcode":"2100",
    "sg:province":"Danmark",
    "sg:tags":[
        "edb",
        "hardware",
        "-"
    ],
    "sg:website":"www.packardbell.dk",
    "wof:name":"Packard Bell NEC",
    "wof:placetype":"venue"
},
  "geometry": {"coordinates":[17.5514202118,62.1984481812],"type":"Point"}
}