{
  "type": "Feature",
  "properties": {
    "addr:full":"Batterivej 44 Skagen Danmark 9990",
    "addr:housenumber":"44",
    "addr:postcode":"9990",
    "addr:street":"Batterivej",
    "iso:country":"DK",
    "sg:address":"Batterivej 44",
    "sg:city":"Skagen",
    "sg:orig_category":"Forsvaret",
    "sg:phone":"+45 98 44 21 00",
    "sg:postcode":"9990",
    "sg:province":"Danmark",
    "wof:name":"Eskadrille 601",
    "wof:placetype":"venue"
},
  "geometry": {"coordinates":[10.6059484482,57.731590271],"type":"Point"}
}