{
  "type": "Feature",
  "properties": {
    "iso:country":"DK",
    "sg:address":"N\u00f8rreskov Bakke 35",
    "sg:city":"Silkeborg",
    "sg:orig_category":"Mejeriprodukter en gros",
    "sg:phone":"+45 86 82 12 58",
    "sg:postcode":"8600",
    "sg:province":"Danmark",
    "wof:name":"Centrifugeservice",
    "wof:placetype":"venue"
},
  "geometry": {"coordinates":[9.5829706192,56.1932945251],"type":"Point"}
}