{
  "type": "Feature",
  "properties": {
    "iso:country":"DK",
    "sg:address":"Herslevvej 25, Tr\u00e6llerup",
    "sg:city":"Roskilde",
    "sg:orig_category":"Spejderkorps",
    "sg:phone":"+45 46 40 13 88",
    "sg:postcode":"4000",
    "sg:province":"Danmark",
    "sg:website":"www.fdf.dk/gevninge",
    "wof:name":"FDF Gevninge",
    "wof:placetype":"venue"
},
  "geometry": {"coordinates":[12.0909376144,55.6404838562],"type":"Point"}
}