{
  "type": "Feature",
  "properties": {
    "addr:full":"Vestergade 9 Holstebro Danmark 7500",
    "addr:housenumber":"9",
    "addr:postcode":"7500",
    "addr:street":"Vestergade",
    "iso:country":"DK",
    "sg:address":"Vestergade 9",
    "sg:city":"Holstebro",
    "sg:orig_category":"Blomsterhandlere",
    "sg:phone":"+45 97 42 12 36",
    "sg:postcode":"7500",
    "sg:province":"Danmark",
    "wof:name":"Acacia Blomster",
    "wof:placetype":"venue"
},
  "geometry": {"coordinates":[8.6158456802,56.3582572937],"type":"Point"}
}