{
  "type": "Feature",
  "properties": {
    "addr:full":"Lejrevej 10 Svenstrup Danmark 9230",
    "addr:housenumber":"10",
    "addr:postcode":"9230",
    "addr:street":"Lejrevej",
    "iso:country":"DK",
    "sg:address":"Lejrevej 10",
    "sg:city":"Svenstrup",
    "sg:orig_category":"Botilbud",
    "sg:phone":"+45 98 38 25 55",
    "sg:postcode":"9230",
    "sg:province":"Danmark",
    "wof:name":"Svenstrupg\u00e5rd Bo- og Besk\u00e6ftigelsestilbud",
    "wof:placetype":"venue"
},
  "geometry": {"coordinates":[9.8534040451,56.9675483704],"type":"Point"}
}