{
  "type": "Feature",
  "properties": {
    "addr:full":"Nygade 18 Holb\u00e6k Danmark 4300",
    "addr:housenumber":"18",
    "addr:postcode":"4300",
    "addr:street":"Nygade",
    "iso:country":"DK",
    "sg:address":"Nygade 18",
    "sg:city":"Holb\u00e6k",
    "sg:classifiers":[
        {
            "category":"Food & Beverages",
            "subcategory":"Liquor & Beverages",
            "type":"Retail Goods"
        }
    ],
    "sg:phone":"+45 59 43 01 30",
    "sg:postcode":"4300",
    "sg:province":"Danmark",
    "sg:tags":[
        "vin"
    ],
    "sg:website":"www.alfred-nygade18.dk",
    "wof:name":"Pedersen Eftf., Alfred",
    "wof:placetype":"venue"
},
  "geometry": {"coordinates":[11.7100753784,55.717956543],"type":"Point"}
}