{
  "type": "Feature",
  "properties": {
    "addr:full":"Kochsgade 140, Postboks 62 5100",
    "addr:housenumber":"140;62",
    "addr:postcode":"5100",
    "addr:street":"Kochsgade",
    "iso:country":"DK",
    "sg:address":"Kochsgade 140, Postboks 62",
    "sg:classifiers":[
        {
            "category":"Banks & Credit Unions",
            "subcategory":"Bank",
            "type":"Services"
        }
    ],
    "sg:phone":"+45 66 12 38 15",
    "sg:postcode":"5100",
    "sg:tags":[
        "banker"
    ],
    "wof:name":"Nordea",
    "wof:placetype":"venue"
},
  "geometry": {"coordinates":[10.3908996582,55.3960914612],"type":"Point"}
}