{
  "type": "Feature",
  "properties": {
    "addr:full":"Mariagervej 46 Randers Danmark 8900",
    "addr:housenumber":"46",
    "addr:postcode":"8900",
    "addr:street":"Mariagervej",
    "iso:country":"DK",
    "sg:address":"Mariagervej 46",
    "sg:city":"Randers",
    "sg:orig_category":"Apoteker og -udsalg",
    "sg:phone":"+45 86 42 18 67",
    "sg:postcode":"8900",
    "sg:province":"Danmark",
    "wof:name":"Jernbane Apotekets Apoteksudsalg",
    "wof:placetype":"venue"
},
  "geometry": {"coordinates":[10.0323915482,56.467880249],"type":"Point"}
}