{
  "type": "Feature",
  "properties": {
    "addr:full":"Erhvervsvej 10, Knudlund Them Danmark 8653",
    "addr:housenumber":"10",
    "addr:postcode":"8653",
    "addr:street":"Erhvervsvej",
    "iso:country":"DK",
    "sg:address":"Erhvervsvej 10, Knudlund",
    "sg:city":"Them",
    "sg:orig_category":"EDB - udstyr",
    "sg:phone":"+45 86 84 83 33",
    "sg:postcode":"8653",
    "sg:province":"Danmark",
    "sg:website":"www.erhvervsgruppen.dk",
    "wof:name":"EDB-K\u00f8bmanden",
    "wof:placetype":"venue"
},
  "geometry": {"coordinates":[9.5489425659,56.0950088501],"type":"Point"}
}