{
  "type": "Feature",
  "properties": {
    "addr:full":"N\u00f8rregade 10 Sindal Danmark 9870",
    "addr:housenumber":"10",
    "addr:postcode":"9870",
    "addr:street":"Norregade",
    "iso:country":"DK",
    "sg:address":"N\u00f8rregade 10",
    "sg:city":"Sindal",
    "sg:orig_category":"Forsikringer",
    "sg:phone":"+45 98 93 48 68",
    "sg:postcode":"9870",
    "sg:province":"Danmark",
    "wof:name":"Assurance Kontoret",
    "wof:placetype":"venue"
},
  "geometry": {"coordinates":[10.2022809982,57.4716835022],"type":"Point"}
}