{
  "type": "Feature",
  "properties": {
    "addr:full":"Wibrandtsvej 50 K\u00f8benhavn S Danmark 2300",
    "addr:housenumber":"50",
    "addr:postcode":"2300",
    "addr:street":"Wibrandtsvej;S Danmark",
    "iso:country":"DK",
    "sg:address":"Wibrandtsvej 50",
    "sg:city":"K\u00f8benhavn S",
    "sg:orig_category":"Lotterikollektioner",
    "sg:phone":"+45 32 59 70 14",
    "sg:postcode":"2300",
    "sg:province":"Danmark",
    "wof:name":"Mogensen, Anni",
    "wof:placetype":"venue"
},
  "geometry": {"coordinates":[-78.1299133301,36.7267417908],"type":"Point"}
}