{
  "type": "Feature",
  "properties": {
    "addr:full":"Brinck Seidelins Gade 7 Hj\u00f8rring Danmark 9800",
    "addr:housenumber":"7",
    "addr:postcode":"9800",
    "addr:street":"Brinck Seidelins Gade",
    "iso:country":"DK",
    "sg:address":"Brinck Seidelins Gade 7",
    "sg:city":"Hj\u00f8rring",
    "sg:orig_category":"Kiropraktorer",
    "sg:phone":"+45 98 90 10 05",
    "sg:postcode":"9800",
    "sg:province":"Danmark",
    "wof:name":"Kiropraktisk Klinik",
    "wof:placetype":"venue"
},
  "geometry": {"coordinates":[99.92501068120001,34.2430114746],"type":"Point"}
}