{
  "type": "Feature",
  "properties": {
    "addr:full":"Fmd.: S\u00f8ren Jensen, Gartnerv\u00e6nget 27 Regstrup Danmark 4420",
    "addr:housenumber":"27",
    "addr:postcode":"4420",
    "iso:country":"DK",
    "sg:address":"Fmd.: S\u00f8ren Jensen, Gartnerv\u00e6nget 27",
    "sg:city":"Regstrup",
    "sg:orig_category":"Grundejerforeninger",
    "sg:phone":"+45 59 47 12 02",
    "sg:postcode":"4420",
    "sg:province":"Danmark",
    "wof:name":"Gartnerv\u00e6nget Grundejerforening",
    "wof:placetype":"venue"
},
  "geometry": {"coordinates":[11.6131772995,55.6769638062],"type":"Point"}
}