{
  "type": "Feature",
  "properties": {
    "addr:full":"Havnepladsen 2 A, Hvalpsund Fars\u00f8 Danmark 9640",
    "addr:housenumber":"2 a",
    "addr:postcode":"9640",
    "addr:street":"Havnepladsen;Hvalpsund Farso Danmark",
    "iso:country":"DK",
    "sg:address":"Havnepladsen 2 A, Hvalpsund",
    "sg:city":"Fars\u00f8",
    "sg:orig_category":"Grillbarer",
    "sg:phone":"+45 98 63 80 20",
    "sg:postcode":"9640",
    "sg:province":"Danmark",
    "wof:name":"P-Grillen",
    "wof:placetype":"venue"
},
  "geometry": {"coordinates":[9.1937885284,56.6945037842],"type":"Point"}
}