{
  "type": "Feature",
  "properties": {
    "addr:full":"Tyge Brahes Vej 11 Aalborg Danmark 9000",
    "addr:housenumber":"11",
    "addr:postcode":"9000",
    "addr:street":"Tyge Brahes Vej",
    "iso:country":"DK",
    "sg:address":"Tyge Brahes Vej 11",
    "sg:city":"Aalborg",
    "sg:orig_category":"Arkitekter",
    "sg:phone":"+45 98 13 52 96",
    "sg:postcode":"9000",
    "sg:province":"Danmark",
    "wof:name":"Engquist, Alf Kristian",
    "wof:placetype":"venue"
},
  "geometry": {"coordinates":[9.9110860825,57.0365715027],"type":"Point"}
}