{
  "type": "Feature",
  "properties": {
    "addr:full":"Vestervangen 51 Asn\u00e6s Danmark 4550",
    "addr:housenumber":"51",
    "addr:postcode":"4550",
    "addr:street":"Vestervangen",
    "iso:country":"DK",
    "sg:address":"Vestervangen 51",
    "sg:city":"Asn\u00e6s",
    "sg:orig_category":"Autoopretning",
    "sg:phone":"+45 59 65 06 37",
    "sg:postcode":"4550",
    "sg:province":"Danmark",
    "wof:name":"Asn\u00e6s Autoopretning",
    "wof:placetype":"venue"
},
  "geometry": {"coordinates":[-98.5411682129,48.1513710022],"type":"Point"}
}