{
  "type": "Feature",
  "properties": {
    "addr:full":"Jagtvej 71-73 K\u00f8benhavn N Danmark 2200",
    "addr:housenumber":"71-73",
    "addr:postcode":"2200",
    "addr:street":"Jagtvej;Kobenhavn N Danmark",
    "iso:country":"DK",
    "sg:address":"Jagtvej 71-73",
    "sg:city":"K\u00f8benhavn N",
    "sg:classifiers":[
        {
            "category":"Restaurant",
            "type":"Food & Drink"
        }
    ],
    "sg:phone":"+45 35 86 16 03",
    "sg:postcode":"2200",
    "sg:province":"Danmark",
    "wof:name":"Caf\u00e9 Saxons",
    "wof:placetype":"venue"
},
  "geometry": {"coordinates":[-94.28489685060001,47.8752212524],"type":"Point"}
}