{
  "type": "Feature",
  "properties": {
    "addr:full":"Nygade 6 Ryomg\u00e5rd Danmark 8550",
    "addr:housenumber":"6",
    "addr:postcode":"8550",
    "addr:street":"Nygade",
    "iso:country":"DK",
    "sg:address":"Nygade 6",
    "sg:city":"Ryomg\u00e5rd",
    "sg:orig_category":"Faglige organisationer og foreninger",
    "sg:phone":"+45 86 39 44 00",
    "sg:postcode":"8550",
    "sg:province":"Danmark",
    "wof:name":"SID",
    "wof:placetype":"venue"
},
  "geometry": {"coordinates":[10.5006446838,56.3809738159],"type":"Point"}
}