{
  "type": "Feature",
  "properties": {
    "iso:country":"DK",
    "sg:address":"Fmd.: Ove Henriksen, Solevadvej 14, Solevad",
    "sg:city":"Tommerup",
    "sg:orig_category":"Borger- og beboerforeninger",
    "sg:phone":"+45 64 75 26 20",
    "sg:postcode":"5690",
    "sg:province":"Danmark",
    "wof:name":"Frankfri-Solevad Beboerforening",
    "wof:placetype":"venue"
},
  "geometry": {"coordinates":[10.2489509583,55.3236503601],"type":"Point"}
}