{
  "type": "Feature",
  "properties": {
    "iso:country":"DK",
    "sg:address":"Emdrupvej 114",
    "sg:city":"K\u00f8benhavn NV",
    "sg:classifiers":[
        {
            "category":"Restaurant",
            "type":"Food & Drink"
        }
    ],
    "sg:phone":"+45 39 67 18 81",
    "sg:postcode":"2400",
    "sg:province":"Danmark",
    "wof:name":"Oasen",
    "wof:placetype":"venue"
},
  "geometry": {"coordinates":[-117.02272033689999,38.5024604797],"type":"Point"}
}