{
  "type": "Feature",
  "properties": {
    "iso:country":"DK",
    "sg:address":"Fmd.: J\u00f8rgen Trap, Skibsgade 7",
    "sg:city":"Hobro",
    "sg:orig_category":"Kulturelle foreninger",
    "sg:phone":"+45 98 52 20 34",
    "sg:postcode":"9500",
    "sg:province":"Danmark",
    "sg:website":"www.bremsen.dk",
    "wof:name":"Amat\u00f8rteatret Bremsen",
    "wof:placetype":"venue"
},
  "geometry": {"coordinates":[9.7946596146,56.6382789612],"type":"Point"}
}