{
  "type": "Feature",
  "properties": {
    "iso:country":"DK",
    "sg:address":"Holsted Park 25",
    "sg:city":"N\u00e6stved",
    "sg:orig_category":"Stilladser",
    "sg:phone":"+45 55 77 04 11",
    "sg:postcode":"4700",
    "sg:province":"Danmark",
    "wof:name":"Bera Stillads- og Liftudlejning A/S",
    "wof:placetype":"venue"
},
  "geometry": {"coordinates":[11.7718009949,55.2488861084],"type":"Point"}
}