{
  "type": "Feature",
  "properties": {
    "addr:full":"Slotsv\u00e6nget 23 A Kongens Lyngby Danmark 2800",
    "addr:housenumber":"23 a",
    "addr:postcode":"2800",
    "addr:street":"Slotsvaenget",
    "iso:country":"DK",
    "sg:address":"Slotsv\u00e6nget 23 A",
    "sg:city":"Kongens Lyngby",
    "sg:orig_category":"Socialpsykiatriske bosteder",
    "sg:phone":"+45 45 26 76 76",
    "sg:postcode":"2800",
    "sg:province":"Danmark",
    "sg:website":"www.slotsvaenget-kbhamt.dk",
    "wof:name":"Slotsv\u00e6nget",
    "wof:placetype":"venue"
},
  "geometry": {"coordinates":[12.5368299484,55.7949905396],"type":"Point"}
}