{
  "type": "Feature",
  "properties": {
    "iso:country":"DK",
    "sg:address":"Jernbanegade 7 ",
    "sg:city":"Frederikshavn",
    "sg:classifiers":[
        {
            "category":"Travel",
            "subcategory":"Travel Agent",
            "type":"Entertainment"
        }
    ],
    "sg:phone":"+45 98 42 22 55",
    "sg:postcode":"9900",
    "sg:province":"Danmark",
    "sg:tags":[
        "business"
    ],
    "wof:name":"PARK HOTEL",
    "wof:placetype":"venue"
},
  "geometry": {"coordinates":[10.5355062485,57.4413795471],"type":"Point"}
}