{
  "type": "Feature",
  "properties": {
    "addr:full":"Storegade 67 Hasle Danmark 3790",
    "addr:housenumber":"67",
    "addr:postcode":"3790",
    "addr:street":"Storegade",
    "iso:country":"DK",
    "sg:address":"Storegade 67",
    "sg:city":"Hasle",
    "sg:orig_category":"Brugsforeninger",
    "sg:phone":"+45 56 96 43 65",
    "sg:postcode":"3790",
    "sg:province":"Danmark",
    "sg:website":"www.fdb.dk",
    "wof:name":"SuperBrugsen Hasle",
    "wof:placetype":"venue"
},
  "geometry": {"coordinates":[14.7054290771,55.1846923828],"type":"Point"}
}