{
  "type": "Feature",
  "properties": {
    "addr:full":"Blomsterv\u00e6nget 8, Klokkerholm Hjallerup Danmark 9320",
    "addr:housenumber":"8",
    "addr:postcode":"9320",
    "addr:street":"Blomstervaenget;Klokkerholm",
    "iso:country":"DK",
    "sg:address":"Blomsterv\u00e6nget 8, Klokkerholm",
    "sg:city":"Hjallerup",
    "sg:orig_category":"Malermestre",
    "sg:phone":"+45 98 28 44 49",
    "sg:postcode":"9320",
    "sg:province":"Danmark",
    "sg:website":"www.malerenslagersalg.dk",
    "wof:name":"Klokkerholm Malerforretning",
    "wof:placetype":"venue"
},
  "geometry": {"coordinates":[10.1444702148,57.1677742004],"type":"Point"}
}