{
  "type": "Feature",
  "properties": {
    "addr:full":"Myhlenbergvej 16 Arden Danmark 9510",
    "addr:housenumber":"16",
    "addr:postcode":"9510",
    "addr:street":"Myhlenbergvej",
    "iso:country":"DK",
    "sg:address":"Myhlenbergvej 16",
    "sg:city":"Arden",
    "sg:orig_category":"Plejehjem",
    "sg:phone":"+45 98 56 13 60",
    "sg:postcode":"9510",
    "sg:province":"Danmark",
    "wof:name":"Arden Plejehjem",
    "wof:placetype":"venue"
},
  "geometry": {"coordinates":[9.854429245,56.7682991028],"type":"Point"}
}