{
  "type": "Feature",
  "properties": {
    "iso:country":"DK",
    "sg:address":"Stationsvej 4",
    "sg:city":"Vemb",
    "sg:orig_category":"Grillbarer",
    "sg:phone":"+45 97 48 11 48",
    "sg:postcode":"7570",
    "sg:province":"Danmark",
    "wof:name":"GrillKiosken",
    "wof:placetype":"venue"
},
  "geometry": {"coordinates":[8.3452310562,56.343788147],"type":"Point"}
}