{
  "type": "Feature",
  "properties": {
    "addr:full":"M\u00f8llergade 70 Svendborg Danmark 5700",
    "addr:housenumber":"70",
    "addr:postcode":"5700",
    "addr:street":"Mollergade",
    "iso:country":"DK",
    "sg:address":"M\u00f8llergade 70",
    "sg:city":"Svendborg",
    "sg:orig_category":"Farvehandlere",
    "sg:phone":"+45 62 22 28 48",
    "sg:postcode":"5700",
    "sg:province":"Danmark",
    "sg:website":"www.sadolinsvendborg.dk",
    "wof:name":"Sadolin Farveland / Sadolin Grossist Center",
    "wof:placetype":"venue"
},
  "geometry": {"coordinates":[10.611738205,55.0625343323],"type":"Point"}
}