{
  "type": "Feature",
  "properties": {
    "addr:full":"Hvidovre Enghavevej 18 Hvidovre Danmark 2650",
    "addr:housenumber":"18",
    "addr:postcode":"2650",
    "addr:street":"Hvidovre Enghavevej",
    "iso:country":"DK",
    "sg:address":"Hvidovre Enghavevej 18",
    "sg:city":"Hvidovre",
    "sg:orig_category":"Malermestre",
    "sg:phone":"+45 40 63 52 04",
    "sg:postcode":"2650",
    "sg:province":"Danmark",
    "sg:website":"www.per-rath.dk",
    "wof:name":"Rath, Malerfirmaet Per",
    "wof:placetype":"venue"
},
  "geometry": {"coordinates":[12.4784908295,55.6237068176],"type":"Point"}
}