{
  "type": "Feature",
  "properties": {
    "addr:full":"Fmd.: Hartley Nielsen, Jyllandsvej 20 Middelfart Danmark 5500",
    "addr:housenumber":"20",
    "addr:postcode":"5500",
    "addr:street":"Jyllandsvej",
    "iso:country":"DK",
    "sg:address":"Fmd.: Hartley Nielsen, Jyllandsvej 20",
    "sg:city":"Middelfart",
    "sg:orig_category":"Hobbybetonede foreninger",
    "sg:phone":"+45 70 20 19 76",
    "sg:postcode":"5500",
    "sg:province":"Danmark",
    "wof:name":"Dansk Land-Rover Klub",
    "wof:placetype":"venue"
},
  "geometry": {"coordinates":[9.7417497635,55.5030250549],"type":"Point"}
}