{
  "type": "Feature",
  "properties": {
    "addr:full":"Kappendrup 40 Otterup Danmark 5450",
    "addr:housenumber":"40",
    "addr:postcode":"5450",
    "addr:street":"Kappendrup",
    "iso:country":"DK",
    "sg:address":"Kappendrup 40",
    "sg:city":"Otterup",
    "sg:orig_category":"Forsamlingshuse",
    "sg:phone":"+45 64 85 15 06",
    "sg:postcode":"5450",
    "sg:province":"Danmark",
    "wof:name":"Kappendrup Forsamlingshus",
    "wof:placetype":"venue"
},
  "geometry": {"coordinates":[10.3471469879,55.5366172791],"type":"Point"}
}