{
  "type": "Feature",
  "properties": {
    "addr:full":"Drommelmor, Vester Thirupvej 30 Hj\u00f8rring Danmark 9800",
    "addr:housenumber":"30",
    "addr:postcode":"9800",
    "addr:street":"Vester Thirupvej",
    "iso:country":"DK",
    "sg:address":"Drommelmor, Vester Thirupvej 30",
    "sg:city":"Hj\u00f8rring",
    "sg:orig_category":"Private skoler",
    "sg:phone":"+45 98 91 05 40",
    "sg:postcode":"9800",
    "sg:province":"Danmark",
    "wof:name":"Rudolf Steiner B\u00f8rnehaven",
    "wof:placetype":"venue"
},
  "geometry": {"coordinates":[-85.2299499512,37.1363105774],"type":"Point"}
}