{
  "type": "Feature",
  "properties": {
    "iso:country":"DK",
    "sg:address":"Adelgade 56",
    "sg:city":"Skanderborg",
    "sg:orig_category":"Engros handel",
    "sg:phone":"+45 86 51 11 21",
    "sg:postcode":"8660",
    "sg:province":"Danmark",
    "wof:name":"Hansen, Klaus",
    "wof:placetype":"venue"
},
  "geometry": {"coordinates":[9.9326086044,56.032169342],"type":"Point"}
}