{
  "type": "Feature",
  "properties": {
    "addr:full":"Vestergade 32 R\u00f8dekro Danmark 6230",
    "addr:housenumber":"32",
    "addr:postcode":"6230",
    "addr:street":"Vestergade",
    "iso:country":"DK",
    "sg:address":"Vestergade 32",
    "sg:city":"R\u00f8dekro",
    "sg:orig_category":"Flytteforretninger",
    "sg:phone":"+45 74 66 28 57",
    "sg:postcode":"6230",
    "sg:province":"Danmark",
    "wof:name":"R\u00f8dekro Flytteforretning",
    "wof:placetype":"venue"
},
  "geometry": {"coordinates":[9.5455904007,56.1682090759],"type":"Point"}
}