{
  "type": "Feature",
  "properties": {
    "iso:country":"DK",
    "sg:address":"Gammel Havnevej 1, B\u00f8nnerup Str",
    "sg:city":"Glesborg",
    "sg:classifiers":[
        {
            "category":"Restaurant",
            "type":"Food & Drink"
        }
    ],
    "sg:phone":"+45 86 38 66 22",
    "sg:postcode":"8585",
    "sg:province":"Danmark",
    "wof:name":"Bl\u00e5 Kutter, Restaurant Den",
    "wof:placetype":"venue"
},
  "geometry": {"coordinates":[10.5884723663,56.5124320984],"type":"Point"}
}