{
  "type": "Feature",
  "properties": {
    "iso:country":"DK",
    "sg:address":"Adelgade 56",
    "sg:city":"Skanderborg",
    "sg:orig_category":"Cykler",
    "sg:phone":"+45 86 52 10 06",
    "sg:postcode":"8660",
    "sg:province":"Danmark",
    "wof:name":"Jensen, Kjeld",
    "wof:placetype":"venue"
},
  "geometry": {"coordinates":[9.9326086044,56.032169342],"type":"Point"}
}