{
  "type": "Feature",
  "properties": {
    "addr:full":"v/ J\u00f8rn J\u00f8rgensen, Fugledevej 16 Jerslev Sj\u00e6lland Danmark 4490",
    "addr:housenumber":"16",
    "addr:postcode":"4490",
    "addr:street":"Fugledevej",
    "iso:country":"DK",
    "sg:address":"v/ J\u00f8rn J\u00f8rgensen, Fugledevej 16",
    "sg:city":"Jerslev Sj\u00e6lland",
    "sg:orig_category":"Landboorganisationer",
    "sg:phone":"+45 59 59 60 42",
    "sg:postcode":"4490",
    "sg:province":"Danmark",
    "wof:name":"Vestsj\u00e6llands Familiebrug",
    "wof:placetype":"venue"
},
  "geometry": {"coordinates":[11.213265419,55.619178772],"type":"Point"}
}