{
  "type": "Feature",
  "properties": {
    "addr:full":"Laurids Skaus Gade 14 Haderslev Danmark 6100",
    "addr:housenumber":"14",
    "addr:postcode":"6100",
    "addr:street":"Laurids Skaus Gade",
    "iso:country":"DK",
    "sg:address":"Laurids Skaus Gade 14",
    "sg:city":"Haderslev",
    "sg:orig_category":"Advokater",
    "sg:phone":"+45 74 52 64 64",
    "sg:postcode":"6100",
    "sg:province":"Danmark",
    "wof:name":"Judica Advokaterne",
    "wof:placetype":"venue"
},
  "geometry": {"coordinates":[9.4858236313,55.2542762756],"type":"Point"}
}