{
  "type": "Feature",
  "properties": {
    "addr:full":"Riddergade 8 Viborg Danmark 8800",
    "addr:housenumber":"8",
    "addr:postcode":"8800",
    "addr:street":"Riddergade",
    "iso:country":"DK",
    "sg:address":"Riddergade 8",
    "sg:city":"Viborg",
    "sg:orig_category":"Museer",
    "sg:phone":"+45 87 25 26 05",
    "sg:postcode":"8800",
    "sg:province":"Danmark",
    "wof:name":"Kunsthallen Br\u00e6nderig\u00e5rden",
    "wof:placetype":"venue"
},
  "geometry": {"coordinates":[9.4156036377,56.4500083923],"type":"Point"}
}