{
  "type": "Feature",
  "properties": {
    "addr:full":"Hvidovrevej 178 Hvidovre Danmark 2650",
    "addr:housenumber":"178",
    "addr:postcode":"2650",
    "addr:street":"Hvidovrevej",
    "iso:country":"DK",
    "sg:address":"Hvidovrevej 178",
    "sg:city":"Hvidovre",
    "sg:orig_category":"Brugsforeninger",
    "sg:phone":"+45 36 32 40 00",
    "sg:postcode":"2650",
    "sg:province":"Danmark",
    "wof:name":"Kvickly",
    "wof:placetype":"venue"
},
  "geometry": {"coordinates":[12.474275589,55.6534843445],"type":"Point"}
}