{
  "type": "Feature",
  "properties": {
    "addr:full":"Gothersgade 35 Fredericia Danmark 7000",
    "addr:housenumber":"35",
    "addr:postcode":"7000",
    "addr:street":"Gothersgade",
    "iso:country":"DK",
    "sg:address":"Gothersgade 35",
    "sg:city":"Fredericia",
    "sg:orig_category":"Blomsterhandlere",
    "sg:phone":"+45 75 92 12 17",
    "sg:postcode":"7000",
    "sg:province":"Danmark",
    "wof:name":"Iris Blomster",
    "wof:placetype":"venue"
},
  "geometry": {"coordinates":[9.7567863464,55.5646934509],"type":"Point"}
}