{
  "type": "Feature",
  "properties": {
    "addr:full":"Kirkevej 8, Led\u00f8je Sm\u00f8rum Danmark 2765",
    "addr:housenumber":"8",
    "addr:postcode":"2765",
    "addr:street":"Kirkevej",
    "iso:country":"DK",
    "sg:address":"Kirkevej 8, Led\u00f8je",
    "sg:city":"Sm\u00f8rum",
    "sg:classifiers":[
        {
            "category":"Building & Trades",
            "subcategory":"Construction",
            "type":"Services"
        }
    ],
    "sg:phone":"+45 44 97 00 71",
    "sg:postcode":"2765",
    "sg:province":"Danmark",
    "sg:tags":[
        "ventilation"
    ],
    "sg:website":"www.bjogs.dk",
    "wof:name":"Johansen & S\u00f8nner A/S, Benny",
    "wof:placetype":"venue"
},
  "geometry": {"coordinates":[-89.99810791020001,38.1321372986],"type":"Point"}
}