{
  "type": "Feature",
  "properties": {
    "addr:full":"Bredgade 8 Herning Danmark 7400",
    "addr:housenumber":"8",
    "addr:postcode":"7400",
    "addr:street":"Bredgade",
    "iso:country":"DK",
    "sg:address":"Bredgade 8",
    "sg:city":"Herning",
    "sg:orig_category":"Boghandlere",
    "sg:phone":"+45 97 12 02 99",
    "sg:postcode":"7400",
    "sg:province":"Danmark",
    "sg:website":"www.herningonline.dk",
    "wof:name":"Erichsens, Henrik Boghandel - Arnold Busck",
    "wof:placetype":"venue"
},
  "geometry": {"coordinates":[8.9733314514,56.1364059448],"type":"Point"}
}