{
  "type": "Feature",
  "properties": {
    "addr:full":"Mathilde Fibigers Vej 13 Frederiksberg Danmark 2000",
    "addr:housenumber":"13",
    "addr:postcode":"2000",
    "addr:street":"Mathilde Fibigers Vej",
    "iso:country":"DK",
    "sg:address":"Mathilde Fibigers Vej 13",
    "sg:city":"Frederiksberg",
    "sg:orig_category":"Reklamebureauer",
    "sg:phone":"+45 38 86 35 97",
    "sg:postcode":"2000",
    "sg:province":"Danmark",
    "wof:name":"Ditlev Design, Niels",
    "wof:placetype":"venue"
},
  "geometry": {"coordinates":[12.5198316574,55.6888542175],"type":"Point"}
}