{
  "type": "Feature",
  "properties": {
    "addr:full":"\u00d8stergade 2 Toftlund Danmark 6520",
    "addr:housenumber":"2",
    "addr:postcode":"6520",
    "addr:street":"Ostergade",
    "iso:country":"DK",
    "sg:address":"\u00d8stergade 2",
    "sg:city":"Toftlund",
    "sg:orig_category":"Ejendomshandel",
    "sg:phone":"+45 74 83 12 18",
    "sg:postcode":"6520",
    "sg:province":"Danmark",
    "sg:website":"www.se-bolig.dk",
    "wof:name":"S\u00f8nderjydsk Ejendomsformidling",
    "wof:placetype":"venue"
},
  "geometry": {"coordinates":[9.0641345978,55.1924514771],"type":"Point"}
}