{
  "type": "Feature",
  "properties": {
    "addr:full":"Skomagergade 10 Roskilde Danmark 4000",
    "addr:housenumber":"10",
    "addr:postcode":"4000",
    "addr:street":"Skomagergade",
    "iso:country":"DK",
    "sg:address":"Skomagergade 10",
    "sg:city":"Roskilde",
    "sg:orig_category":"Ure og urmagere",
    "sg:phone":"+45 46 35 22 60",
    "sg:postcode":"4000",
    "sg:province":"Danmark",
    "wof:name":"Svend's Ure",
    "wof:placetype":"venue"
},
  "geometry": {"coordinates":[12.0792808533,55.6410636902],"type":"Point"}
}