{
  "type": "Feature",
  "properties": {
    "addr:full":"Ladelundvej 75, Malt Vejen Danmark 6600",
    "addr:housenumber":"75",
    "addr:postcode":"6600",
    "addr:street":"Ladelundvej",
    "iso:country":"DK",
    "sg:address":"Ladelundvej 75, Malt",
    "sg:city":"Vejen",
    "sg:orig_category":"Efterskoler",
    "sg:phone":"+45 75 38 10 06",
    "sg:postcode":"6600",
    "sg:province":"Danmark",
    "sg:website":"www.ladelundefterskole.dk",
    "wof:name":"Ladelund Efterskole",
    "wof:placetype":"venue"
},
  "geometry": {"coordinates":[9.1396121979,55.4778175354],"type":"Point"}
}