{
  "type": "Feature",
  "properties": {
    "addr:full":"Holger Drachmanns Gade 1 S\u00f8nderborg Danmark 6400",
    "addr:housenumber":"1",
    "addr:postcode":"6400",
    "addr:street":"Holger Drachmanns Gade",
    "iso:country":"DK",
    "sg:address":"Holger Drachmanns Gade 1",
    "sg:city":"S\u00f8nderborg",
    "sg:orig_category":"Boligselskaber",
    "sg:phone":"+45 74 42 57 95",
    "sg:postcode":"6400",
    "sg:province":"Danmark",
    "sg:website":"www.b42.dk",
    "wof:name":"Boligforeningen af 6.12.1942",
    "wof:placetype":"venue"
},
  "geometry": {"coordinates":[99.92501068120001,34.2430114746],"type":"Point"}
}