{
  "type": "Feature",
  "properties": {
    "addr:full":"Herlev Hovedgade 175 st., th. Herlev Danmark 2730",
    "addr:housenumber":"175",
    "addr:postcode":"2730",
    "addr:street":"Herlev Hovedgade",
    "iso:country":"DK",
    "sg:address":"Herlev Hovedgade 175 st., th.",
    "sg:city":"Herlev",
    "sg:orig_category":"Flytteforretninger",
    "sg:phone":"+45 44 84 85 61",
    "sg:postcode":"2730",
    "sg:province":"Danmark",
    "wof:name":"Lippert, Jan",
    "wof:placetype":"venue"
},
  "geometry": {"coordinates":[12.4382095337,55.7250595093],"type":"Point"}
}