{
  "type": "Feature",
  "properties": {
    "iso:country":"DK",
    "sg:address":"Vesterbro 25",
    "sg:city":"Odense C",
    "sg:orig_category":"Hudplejeklinikker",
    "sg:phone":"+45 66 13 92 22",
    "sg:postcode":"5000",
    "sg:province":"Danmark",
    "wof:name":"Beauty Klinik",
    "wof:placetype":"venue"
},
  "geometry": {"coordinates":[10.3776292801,55.3938369751],"type":"Point"}
}