{
  "type": "Feature",
  "properties": {
    "iso:country":"DK",
    "sg:address":"S\u00f8v\u00e6nget 1, Stilling",
    "sg:city":"Skanderborg",
    "sg:orig_category":"Kirkesogne",
    "sg:phone":"+45 86 57 17 51",
    "sg:postcode":"8660",
    "sg:province":"Danmark",
    "wof:name":"Stilling Sogns Kirkekontor",
    "wof:placetype":"venue"
},
  "geometry": {"coordinates":[9.929974556,56.0380249023],"type":"Point"}
}