{
  "type": "Feature",
  "properties": {
    "addr:full":"R\u00e5dhusparken 2 Glostrup Danmark 2600",
    "addr:housenumber":"2",
    "addr:postcode":"2600",
    "addr:street":"Raadhusparken",
    "iso:country":"DK",
    "sg:address":"R\u00e5dhusparken 2",
    "sg:city":"Glostrup",
    "sg:orig_category":"Sundhedspleje",
    "sg:phone":"+45 43 23 64 66",
    "sg:postcode":"2600",
    "sg:province":"Danmark",
    "wof:name":"Svanholt, Lisbeth",
    "wof:placetype":"venue"
},
  "geometry": {"coordinates":[12.394112587,55.6647491455],"type":"Point"}
}