{
  "type": "Feature",
  "properties": {
    "addr:full":"Doritshave 39 Egtved Danmark 6040",
    "addr:housenumber":"39",
    "addr:postcode":"6040",
    "addr:street":"Doritshave",
    "iso:country":"DK",
    "sg:address":"Doritshave 39",
    "sg:city":"Egtved",
    "sg:orig_category":"Faglige organisationer og foreninger",
    "sg:phone":"+45 75 55 11 56",
    "sg:postcode":"6040",
    "sg:province":"Danmark",
    "wof:name":"LO, Egtved",
    "wof:placetype":"venue"
},
  "geometry": {"coordinates":[9.3144397736,55.6106948853],"type":"Point"}
}