{
  "type": "Feature",
  "properties": {
    "iso:country":"DK",
    "sg:address":"Fmd.: Leif Klausen, Stationsvej 2, Tommerup St",
    "sg:city":"Tommerup",
    "sg:orig_category":"\u00c3\u02dcvrige foreninger",
    "sg:phone":"+45 64 76 23 02",
    "sg:postcode":"5690",
    "sg:province":"Danmark",
    "wof:name":"Foreningen Norden, Tommerup afd.",
    "wof:placetype":"venue"
},
  "geometry": {"coordinates":[10.2489509583,55.3236503601],"type":"Point"}
}