{
  "type": "Feature",
  "properties": {
    "iso:country":"DK",
    "sg:address":"Danmarksgade 81",
    "sg:city":"Fredericia",
    "sg:orig_category":"Ungdomsboliger og -hybler",
    "sg:phone":"+45 75 92 48 44",
    "sg:postcode":"7000",
    "sg:province":"Danmark",
    "sg:website":"www.socialt-boligbyggeri.dk",
    "wof:name":"M\u00f8llebo Alle's Ungdomsboliger",
    "wof:placetype":"venue"
},
  "geometry": {"coordinates":[9.7672786713,55.5671653748],"type":"Point"}
}