{
  "type": "Feature",
  "properties": {
    "iso:country":"DK",
    "sg:address":"\u00d8stergade 13",
    "sg:city":"Hammel",
    "sg:orig_category":"Revisorer",
    "sg:phone":"+45 86 96 91 00",
    "sg:postcode":"8450",
    "sg:province":"Danmark",
    "sg:website":"www.ey.dk",
    "wof:name":"Ernst & Young",
    "wof:placetype":"venue"
},
  "geometry": {"coordinates":[9.8664216995,56.2567214966],"type":"Point"}
}