{
  "type": "Feature",
  "properties": {
    "addr:full":"Jernbanegade 10 Ebeltoft Danmark 8400",
    "addr:housenumber":"10",
    "addr:postcode":"8400",
    "addr:street":"Jernbanegade",
    "iso:country":"DK",
    "sg:address":"Jernbanegade 10",
    "sg:city":"Ebeltoft",
    "sg:orig_category":"Genbrugsbutikker",
    "sg:phone":"+45 86 34 02 66",
    "sg:postcode":"8400",
    "sg:province":"Danmark",
    "wof:name":"Dansk R\u00f8de Kors Genbrugsforretning",
    "wof:placetype":"venue"
},
  "geometry": {"coordinates":[10.6779928207,56.199634552],"type":"Point"}
}