{
  "type": "Feature",
  "properties": {
    "addr:full":"N\u00f8rre Boulevard 71 Randers Danmark 8900",
    "addr:housenumber":"71",
    "addr:postcode":"8900",
    "addr:street":"Norre Boulevard",
    "iso:country":"DK",
    "sg:address":"N\u00f8rre Boulevard 71",
    "sg:city":"Randers",
    "sg:orig_category":"Grillbarer",
    "sg:phone":"+45 86 41 25 99",
    "sg:postcode":"8900",
    "sg:province":"Danmark",
    "wof:name":"Boulevard Grillen",
    "wof:placetype":"venue"
},
  "geometry": {"coordinates":[10.0319013596,56.4693222046],"type":"Point"}
}