{
  "type": "Feature",
  "properties": {
    "addr:full":"Sundhedscenter, Sygehusvej 7, 1. Skanderborg Danmark 8660",
    "addr:housenumber":"7 1",
    "addr:postcode":"8660",
    "addr:street":"Sygehusvej",
    "iso:country":"DK",
    "sg:address":"Sundhedscenter, Sygehusvej 7, 1.",
    "sg:city":"Skanderborg",
    "sg:orig_category":"Zoneterapeuter",
    "sg:phone":"+45 86 52 53 20",
    "sg:postcode":"8660",
    "sg:province":"Danmark",
    "wof:name":"Christensen, Annette",
    "wof:placetype":"venue"
},
  "geometry": {"coordinates":[9.929974556,56.0380249023],"type":"Point"}
}