{
  "type": "Feature",
  "properties": {
    "addr:full":"Danmarksgade 50 Frederikshavn Danmark 9900",
    "addr:housenumber":"50",
    "addr:postcode":"9900",
    "addr:street":"Danmarksgade",
    "iso:country":"DK",
    "sg:address":"Danmarksgade 50",
    "sg:city":"Frederikshavn",
    "sg:orig_category":"Gigtsygdomme Reumatologi",
    "sg:phone":"+45 98 43 58 00",
    "sg:postcode":"9900",
    "sg:province":"Danmark",
    "wof:name":"Schmidt-Olsen, S\u00f8ren",
    "wof:placetype":"venue"
},
  "geometry": {"coordinates":[10.5365524292,57.4409751892],"type":"Point"}
}