{
  "type": "Feature",
  "properties": {
    "addr:full":"Nyropsgade 21 K\u00f8benhavn Danmark 1602",
    "addr:housenumber":"21;1602",
    "addr:street":"Nyropsgade",
    "iso:country":"DK",
    "sg:address":"Nyropsgade 21",
    "sg:city":"K\u00f8benhavn",
    "sg:orig_category":"Realkreditinstitutter",
    "sg:phone":"+45 33 12 75 00",
    "sg:postcode":"1602",
    "sg:province":"Danmark",
    "sg:website":"www.lrf.dk",
    "wof:name":"LRF Landsbankernes Reall\u00e5nefond",
    "wof:placetype":"venue"
},
  "geometry": {"coordinates":[12.5633001328,55.6786003113],"type":"Point"}
}