{
  "type": "Feature",
  "properties": {
    "addr:full":"v/ Karen Christensen, S\u00f8parken 121 R\u00f8dekro Danmark 6230",
    "addr:housenumber":"121",
    "addr:postcode":"6230",
    "addr:street":"Soparken",
    "iso:country":"DK",
    "sg:address":"v/ Karen Christensen, S\u00f8parken 121",
    "sg:city":"R\u00f8dekro",
    "sg:orig_category":"\u00c3\u2020ldreorganisationer og klubber",
    "sg:phone":"+45 74 69 48 23",
    "sg:postcode":"6230",
    "sg:province":"Danmark",
    "wof:name":"R\u00f8dekro Pensionistforening og Omsorgsklub",
    "wof:placetype":"venue"
},
  "geometry": {"coordinates":[9.307510376,55.0235786438],"type":"Point"}
}