{
  "type": "Feature",
  "properties": {
    "addr:full":"Munkebjergvej 5 Kastrup Danmark 2770",
    "addr:housenumber":"5",
    "addr:postcode":"2770",
    "addr:street":"Munkebjergvej",
    "iso:country":"DK",
    "sg:address":"Munkebjergvej 5",
    "sg:city":"Kastrup",
    "sg:orig_category":"Vinduespolering",
    "sg:phone":"+45 32 51 99 50",
    "sg:postcode":"2770",
    "sg:province":"Danmark",
    "wof:name":"F.M. Totalservice Aps",
    "wof:placetype":"venue"
},
  "geometry": {"coordinates":[12.5976867676,55.6210746765],"type":"Point"}
}