{
  "type": "Feature",
  "properties": {
    "addr:full":"Rosengade 8 Kolding Danmark 6000",
    "addr:housenumber":"8",
    "addr:postcode":"6000",
    "addr:street":"Rosengade",
    "iso:country":"DK",
    "sg:address":"Rosengade 8",
    "sg:city":"Kolding",
    "sg:orig_category":"Fodterapeuter",
    "sg:phone":"+45 75 52 03 99",
    "sg:postcode":"6000",
    "sg:province":"Danmark",
    "wof:name":"Klinik for Fodterapi",
    "wof:placetype":"venue"
},
  "geometry": {"coordinates":[9.4686660767,55.4869384766],"type":"Point"}
}