{
  "type": "Feature",
  "properties": {
    "iso:country":"DK",
    "sg:address":"Nordmarksvej 2, Byrum",
    "sg:city":"L\u00e6s\u00f8",
    "sg:orig_category":"Oliefyr og service",
    "sg:phone":"+45 98 49 80 79",
    "sg:postcode":"9940",
    "sg:province":"Danmark",
    "wof:name":"L\u00e6s\u00f8 Oliefyr- & motorservice",
    "wof:placetype":"venue"
},
  "geometry": {"coordinates":[10.9232254028,57.2928199768],"type":"Point"}
}