{
  "type": "Feature",
  "properties": {
    "addr:full":"K\u00e6rvej 19, Jejsing T\u00f8nder Danmark 6270",
    "addr:housenumber":"19",
    "addr:postcode":"6270",
    "addr:street":"Kaervej",
    "iso:country":"DK",
    "sg:address":"K\u00e6rvej 19, Jejsing",
    "sg:city":"T\u00f8nder",
    "sg:orig_category":"Reklamebureauer",
    "sg:phone":"+45 74 73 40 01",
    "sg:postcode":"6270",
    "sg:province":"Danmark",
    "sg:website":"www.swingdesign.dk",
    "wof:name":"Swingdesign",
    "wof:placetype":"venue"
},
  "geometry": {"coordinates":[8.9661502838,54.9350318909],"type":"Point"}
}