{
  "type": "Feature",
  "properties": {
    "addr:full":"\u00d8stergade 14 Lemvig Danmark 7620",
    "addr:housenumber":"14",
    "addr:postcode":"7620",
    "addr:street":"Ostergade",
    "iso:country":"DK",
    "sg:address":"\u00d8stergade 14",
    "sg:city":"Lemvig",
    "sg:orig_category":"Ejendomshandel",
    "sg:phone":"+45 97 82 18 00",
    "sg:postcode":"7620",
    "sg:province":"Danmark",
    "wof:name":"Nybolig Lemvig",
    "wof:placetype":"venue"
},
  "geometry": {"coordinates":[8.3119697571,56.5502624512],"type":"Point"}
}