{
  "type": "Feature",
  "properties": {
    "iso:country":"DK",
    "sg:address":"Jagtvej 101",
    "sg:city":"K\u00f8benhavn N",
    "sg:classifiers":[
        {
            "category":"Restaurant",
            "type":"Food & Drink"
        }
    ],
    "sg:phone":"+45 35 85 33 41",
    "sg:postcode":"2200",
    "sg:province":"Danmark",
    "wof:name":"Effess Pizzabar",
    "wof:placetype":"venue"
},
  "geometry": {"coordinates":[-102.4915008545,48.8797645569],"type":"Point"}
}