{
  "type": "Feature",
  "properties": {
    "addr:full":"Astersvej 12 Slagelse Danmark 4200",
    "addr:housenumber":"12",
    "addr:postcode":"4200",
    "addr:street":"Astersvej",
    "iso:country":"DK",
    "sg:address":"Astersvej 12",
    "sg:city":"Slagelse",
    "sg:classifiers":[
        {
            "category":"Personal",
            "subcategory":"Massage",
            "type":"Services"
        }
    ],
    "sg:phone":"+45 58 53 09 75",
    "sg:postcode":"4200",
    "sg:province":"Danmark",
    "wof:name":"Pedersen, Annelise",
    "wof:placetype":"venue"
},
  "geometry": {"coordinates":[11.3540678024,55.3959121704],"type":"Point"}
}