{
  "type": "Feature",
  "properties": {
    "addr:full":"Fmd.: Morten Skov Nielsen, Solh\u00f8jparken 27, Storring Galten Danmark 8464",
    "addr:housenumber":"27",
    "addr:postcode":"8464",
    "addr:street":"Morten Skov Nielsen Solhojparken;Storring",
    "iso:country":"DK",
    "sg:address":"Fmd.: Morten Skov Nielsen, Solh\u00f8jparken 27, Storring",
    "sg:city":"Galten",
    "sg:orig_category":"Grundejerforeninger",
    "sg:phone":"+45 86 95 09 90",
    "sg:postcode":"8464",
    "sg:province":"Danmark",
    "wof:name":"Storring Grundejerforening",
    "wof:placetype":"venue"
},
  "geometry": {"coordinates":[9.9034748077,56.1558837891],"type":"Point"}
}