{
  "type": "Feature",
  "properties": {
    "addr:full":"L\u00e6rer: Winnie St\u00e6rke, H\u00f8jbjergvej 3, Kirkeby Stenstrup Danmark 5771",
    "addr:housenumber":"3",
    "addr:postcode":"5771",
    "addr:street":"Laerer;Hojbjergvej;Kirkeby",
    "iso:country":"DK",
    "sg:address":"L\u00e6rer: Winnie St\u00e6rke, H\u00f8jbjergvej 3, Kirkeby",
    "sg:city":"Stenstrup",
    "sg:orig_category":"\u00c3\u02dcvrige skoler",
    "sg:phone":"+45 62 26 11 88",
    "sg:postcode":"5771",
    "sg:province":"Danmark",
    "wof:name":"Tegneskolen Egebjerg",
    "wof:placetype":"venue"
},
  "geometry": {"coordinates":[10.5054998398,55.1317520142],"type":"Point"}
}