{
  "type": "Feature",
  "properties": {
    "addr:full":"N. O. Hansens Vej 4 Karup Danmark 7470",
    "addr:housenumber":"4",
    "addr:postcode":"7470",
    "addr:street":"O. Hansens Vej",
    "iso:country":"DK",
    "sg:address":"N. O. Hansens Vej 4",
    "sg:city":"Karup",
    "sg:orig_category":"Autoudlejning",
    "sg:phone":"+45 97 10 22 14",
    "sg:postcode":"7470",
    "sg:province":"Danmark",
    "sg:website":"www.avis.dk",
    "wof:name":"Avis Biludlejning",
    "wof:placetype":"venue"
},
  "geometry": {"coordinates":[9.1198348999,56.3097686768],"type":"Point"}
}