{
  "type": "Feature",
  "properties": {
    "addr:full":"Thulevej 39 Vejle Danmark 7100",
    "addr:housenumber":"39",
    "addr:postcode":"7100",
    "addr:street":"Thulevej",
    "iso:country":"DK",
    "sg:address":"Thulevej 39",
    "sg:city":"Vejle",
    "sg:orig_category":"Murermestre",
    "sg:phone":"+45 75 83 48 93",
    "sg:postcode":"7100",
    "sg:province":"Danmark",
    "wof:name":"Andersson, Anders",
    "wof:placetype":"venue"
},
  "geometry": {"coordinates":[9.5254182816,55.6813812256],"type":"Point"}
}