{
  "type": "Feature",
  "properties": {
    "addr:full":"Terndrup Center 1 Terndrup Danmark 9575",
    "addr:housenumber":"1",
    "addr:postcode":"9575",
    "addr:street":"Terndrup Center;Danmark",
    "iso:country":"DK",
    "sg:address":"Terndrup Center 1",
    "sg:city":"Terndrup",
    "sg:orig_category":"Brugsforeninger",
    "sg:phone":"+45 98 33 50 17",
    "sg:postcode":"9575",
    "sg:province":"Danmark",
    "wof:name":"Super Brugsen",
    "wof:placetype":"venue"
},
  "geometry": {"coordinates":[10.0582704544,56.8125228882],"type":"Point"}
}