{
  "type": "Feature",
  "properties": {
    "addr:full":"B\u00f8vlingvej 92, Ramme Lemvig Danmark 7620",
    "addr:housenumber":"92",
    "addr:postcode":"7620",
    "addr:street":"Bovlingvej",
    "iso:country":"DK",
    "sg:address":"B\u00f8vlingvej 92, Ramme",
    "sg:city":"Lemvig",
    "sg:orig_category":"Malermestre",
    "sg:phone":"+45 97 88 97 02",
    "sg:postcode":"7620",
    "sg:province":"Danmark",
    "wof:name":"Kildegaard, Ole",
    "wof:placetype":"venue"
},
  "geometry": {"coordinates":[8.3073654175,56.5505104065],"type":"Point"}
}