{
  "type": "Feature",
  "properties": {
    "iso:country":"DK",
    "sg:address":"B\u00f8dkervej 90",
    "sg:city":"Hanstholm",
    "sg:orig_category":"Dyreklinikker og -hospitaler",
    "sg:phone":"+45 97 96 00 01",
    "sg:postcode":"7730",
    "sg:province":"Danmark",
    "wof:name":"Hanstholm Dyrehospital",
    "wof:placetype":"venue"
},
  "geometry": {"coordinates":[8.6211795807,57.1178779602],"type":"Point"}
}