{
  "type": "Feature",
  "properties": {
    "iso:country":"DK",
    "sg:address":"L\u00f8ngangstr\u00e6de 39, st.",
    "sg:city":"K\u00f8benhavn",
    "sg:orig_category":"Diskoteker",
    "sg:phone":"+45 33 11 97 66",
    "sg:postcode":"1468",
    "sg:province":"Danmark",
    "wof:name":"Sabor Latino",
    "wof:placetype":"venue"
},
  "geometry": {"coordinates":[76.3070983887,14.277130127],"type":"Point"}
}