{
  "type": "Feature",
  "properties": {
    "addr:full":"\u00d8stergade 15 Hadsten Danmark 8370",
    "addr:housenumber":"15",
    "addr:postcode":"8370",
    "addr:street":"Ostergade",
    "iso:country":"DK",
    "sg:address":"\u00d8stergade 15",
    "sg:city":"Hadsten",
    "sg:classifiers":[
        {
            "category":"Banks & Credit Unions",
            "subcategory":"Bank",
            "type":"Services"
        }
    ],
    "sg:phone":"+45 86 98 15 00",
    "sg:postcode":"8370",
    "sg:province":"Danmark",
    "sg:tags":[
        "banker"
    ],
    "wof:name":"Hadsten Bank Aktieselskab",
    "wof:placetype":"venue"
},
  "geometry": {"coordinates":[10.047978,56.327614],"type":"Point"}
}