{
  "type": "Feature",
  "properties": {
    "addr:full":"Sognepr\u00e6st: Dorte Stenberg Isaksen, Silkeborgvej 235 B Horsens Danmark 8700",
    "addr:housenumber":"235 b",
    "addr:postcode":"8700",
    "addr:street":"Silkeborgvej",
    "iso:country":"DK",
    "sg:address":"Sognepr\u00e6st: Dorte Stenberg Isaksen, Silkeborgvej 235 B",
    "sg:city":"Horsens",
    "sg:orig_category":"Kirkesogne",
    "sg:phone":"+45 75 65 45 22",
    "sg:postcode":"8700",
    "sg:province":"Danmark",
    "wof:name":"Tamdrup sogn",
    "wof:placetype":"venue"
},
  "geometry": {"coordinates":[9.8432445526,55.8621063232],"type":"Point"}
}