{
  "type": "Feature",
  "properties": {
    "addr:full":"B\u00f8gebjergvej 60, Sdr. Broby Broby Danmark 5672",
    "addr:housenumber":"60",
    "addr:postcode":"5672",
    "addr:street":"Bogebjergvej;Sdr. Broby",
    "iso:country":"DK",
    "sg:address":"B\u00f8gebjergvej 60, Sdr. Broby",
    "sg:city":"Broby",
    "sg:orig_category":"Opvaskemaskiner",
    "sg:phone":"+45 62 63 10 91",
    "sg:postcode":"5672",
    "sg:province":"Danmark",
    "sg:website":"www.ken.dk",
    "wof:name":"KEN A/S",
    "wof:placetype":"venue"
},
  "geometry": {"coordinates":[10.3131303787,55.2695846558],"type":"Point"}
}