{
  "type": "Feature",
  "properties": {
    "addr:full":"Aved\u00f8reholmen 78B Hvidovre Danmark 2650",
    "addr:housenumber":"78b",
    "addr:postcode":"2650",
    "addr:street":"Avedoreholmen",
    "iso:country":"DK",
    "sg:address":"Aved\u00f8reholmen 78B",
    "sg:city":"Hvidovre",
    "sg:orig_category":"Hospital, udstyr til",
    "sg:phone":"+45 70 15 33 88",
    "sg:postcode":"2650",
    "sg:province":"Danmark",
    "sg:website":"www.scotsman.dk",
    "wof:name":"Scotsman K\u00f8leteknik A/S",
    "wof:placetype":"venue"
},
  "geometry": {"coordinates":[12.4675512314,55.6101646423],"type":"Point"}
}