{
  "type": "Feature",
  "properties": {
    "iso:country":"DK",
    "sg:address":"Hammershusvej 4 A",
    "sg:city":"Herning",
    "sg:orig_category":"Tekstilindustri",
    "sg:phone":"+45 97 21 24 11",
    "sg:postcode":"7400",
    "sg:province":"Danmark",
    "wof:name":"Pas Scandinavia ApS",
    "wof:placetype":"venue"
},
  "geometry": {"coordinates":[8.9722070694,56.1564292908],"type":"Point"}
}