{
  "type": "Feature",
  "properties": {
    "iso:country":"DK",
    "sg:address":"Meterbuen 3 ",
    "sg:city":"Skovlunde",
    "sg:classifiers":[
        {
            "category":"Wholesale",
            "subcategory":"Drugs",
            "type":"Manufacturing & Wholesale Goods"
        }
    ],
    "sg:phone":"+45 44 94 91 22",
    "sg:postcode":"2740",
    "sg:province":"Danmark",
    "sg:tags":[
        "chemical",
        "pharmaceutical"
    ],
    "wof:name":"SUN CHEMICAL INKS A/S",
    "wof:placetype":"venue"
},
  "geometry": {"coordinates":[12.4185428619,55.7150421143],"type":"Point"}
}