{
  "type": "Feature",
  "properties": {
    "addr:full":"Hostrupvej 39 Hobro Danmark 9500",
    "addr:housenumber":"39",
    "addr:postcode":"9500",
    "addr:street":"Hostrupvej",
    "iso:country":"DK",
    "sg:address":"Hostrupvej 39",
    "sg:city":"Hobro",
    "sg:orig_category":"Varmeforsyning",
    "sg:phone":"+45 98 52 18 25",
    "sg:postcode":"9500",
    "sg:province":"Danmark",
    "wof:name":"Hobro Varmev\u00e6rk A.m.b.A.",
    "wof:placetype":"venue"
},
  "geometry": {"coordinates":[9.7927970886,56.6432991028],"type":"Point"}
}