{
  "type": "Feature",
  "properties": {
    "iso:country":"DK",
    "sg:address":"Fonnesbechsgade 6",
    "sg:city":"Herning",
    "sg:orig_category":"Skomagere",
    "sg:phone":"+45 97 21 16 16",
    "sg:postcode":"7400",
    "sg:province":"Danmark",
    "wof:name":"Skaarup Ortop\u00e6disk H\u00e5ndskomageri",
    "wof:placetype":"venue"
},
  "geometry": {"coordinates":[8.9799356461,56.134967804],"type":"Point"}
}