{
  "type": "Feature",
  "properties": {
    "iso:country":"DK",
    "sg:address":"Fmd.: Tina Dam Pedersen, Hovedvejen 37, Hjarn\u00f8",
    "sg:city":"Horsens",
    "sg:orig_category":"Legestuer",
    "sg:phone":"+45 75 68 32 42",
    "sg:postcode":"8700",
    "sg:province":"Danmark",
    "wof:name":"Hjarn\u00f8 Legestue",
    "wof:placetype":"venue"
},
  "geometry": {"coordinates":[9.8432445526,55.8621063232],"type":"Point"}
}