{
  "type": "Feature",
  "properties": {
    "addr:full":"v/ Dagli' Brugsen, Vestergade 16, Asferg F\u00e5rup Danmark 8990",
    "addr:housenumber":"16",
    "addr:postcode":"8990",
    "addr:street":"Vestergade",
    "iso:country":"DK",
    "sg:address":"v/ Dagli' Brugsen, Vestergade 16, Asferg",
    "sg:city":"F\u00e5rup",
    "sg:orig_category":"Apoteker og -udsalg",
    "sg:phone":"+45 86 44 33 10",
    "sg:postcode":"8990",
    "sg:province":"Danmark",
    "wof:name":"H\u00e5ndk\u00f8bsudsalget",
    "wof:placetype":"venue"
},
  "geometry": {"coordinates":[9.9295606613,56.5465583801],"type":"Point"}
}