{
  "type": "Feature",
  "properties": {
    "addr:full":"Fasanv\u00e6nget 124, Uller\u00f8d Kokkedal Danmark 2980",
    "addr:housenumber":"124",
    "addr:postcode":"2980",
    "addr:street":"Ullerod",
    "iso:country":"DK",
    "sg:address":"Fasanv\u00e6nget 124, Uller\u00f8d",
    "sg:city":"Kokkedal",
    "sg:classifiers":[
        {
            "category":"Professional",
            "subcategory":"Computer Services",
            "type":"Services"
        }
    ],
    "sg:phone":"+45 49 14 26 14",
    "sg:postcode":"2980",
    "sg:province":"Danmark",
    "sg:tags":[
        "edb",
        "-",
        "software"
    ],
    "wof:name":"Colberg Consult",
    "wof:placetype":"venue"
},
  "geometry": {"coordinates":[12.4769096375,55.9091339111],"type":"Point"}
}