{
  "type": "Feature",
  "properties": {
    "iso:country":"DK",
    "sg:address":"J\u00e6gersborg All\u00e9 1 A",
    "sg:city":"Charlottenlund",
    "sg:orig_category":"Arkitekter",
    "sg:phone":"+45 39 40 14 11",
    "sg:postcode":"2920",
    "sg:province":"Danmark",
    "wof:name":"Mikkelsen & N\u00f8rg\u00e5rd ApS",
    "wof:placetype":"venue"
},
  "geometry": {"coordinates":[12.5721197128,55.7532615662],"type":"Point"}
}