{
  "type": "Feature",
  "properties": {
    "iso:country":"DK",
    "sg:address":"v/ Henrik Andersen, Unnerupvej 7 A, Kolsb\u00e6k",
    "sg:city":"Helsinge",
    "sg:orig_category":"Hobbybetonede foreninger",
    "sg:phone":"+45 48 71 68 72",
    "sg:postcode":"3200",
    "sg:province":"Danmark",
    "wof:name":"St\u00f8tteforeningen for Vejby Idr\u00e6tsforening",
    "wof:placetype":"venue"
},
  "geometry": {"coordinates":[12.196846962,56.0224456787],"type":"Point"}
}