{
  "type": "Feature",
  "properties": {
    "addr:full":"Havbakken 154, Hjerting Esbjerg V Danmark 6710",
    "addr:housenumber":"154",
    "addr:postcode":"6710",
    "addr:street":"Havbakken;Hjerting",
    "iso:country":"DK",
    "sg:address":"Havbakken 154, Hjerting",
    "sg:city":"Esbjerg V",
    "sg:orig_category":"Indretningsarkitekter",
    "sg:phone":"+45 75 11 76 06",
    "sg:postcode":"6710",
    "sg:province":"Danmark",
    "wof:name":"Holm, Ulla",
    "wof:placetype":"venue"
},
  "geometry": {"coordinates":[8.4009799957,55.5313110352],"type":"Point"}
}