{
  "type": "Feature",
  "properties": {
    "addr:full":"Hesselh\u00f8jvej 60 Silkeborg Danmark 8600",
    "addr:housenumber":"60",
    "addr:postcode":"8600",
    "addr:street":"Hesselhojvej",
    "iso:country":"DK",
    "sg:address":"Hesselh\u00f8jvej 60",
    "sg:city":"Silkeborg",
    "sg:orig_category":"Psykologer, praktiserende",
    "sg:phone":"+45 86 80 06 11",
    "sg:postcode":"8600",
    "sg:province":"Danmark",
    "wof:name":"Braskov, S\u00f8ren",
    "wof:placetype":"venue"
},
  "geometry": {"coordinates":[9.51836586,56.1774559021],"type":"Point"}
}