{
  "type": "Feature",
  "properties": {
    "iso:country":"DK",
    "sg:address":"Hjertingvej 24",
    "sg:city":"Esbjerg",
    "sg:orig_category":"Servicestationer",
    "sg:phone":"+45 75 12 67 16",
    "sg:postcode":"6700",
    "sg:province":"Danmark",
    "wof:name":"Q8 - Service",
    "wof:placetype":"venue"
},
  "geometry": {"coordinates":[8.4347686768,55.474773407],"type":"Point"}
}