{
  "type": "Feature",
  "properties": {
    "addr:full":"Byvej 36, Ballum Bredebro Danmark 6261",
    "addr:housenumber":"36",
    "addr:postcode":"6261",
    "addr:street":"Byvej",
    "iso:country":"DK",
    "sg:address":"Byvej 36, Ballum",
    "sg:city":"Bredebro",
    "sg:orig_category":"Sparekasser",
    "sg:phone":"+45 74 71 63 01",
    "sg:postcode":"6261",
    "sg:province":"Danmark",
    "wof:name":"Sparekassen Bredebro",
    "wof:placetype":"venue"
},
  "geometry": {"coordinates":[8.8284835815,55.0566978455],"type":"Point"}
}