{
  "type": "Feature",
  "properties": {
    "iso:country":"DK",
    "sg:address":"v/ J\u00f8rn Olsen, \u00d8sterled 73",
    "sg:city":"R\u00f8nne",
    "sg:orig_category":"Hobbybetonede foreninger",
    "sg:phone":"+45 56 95 59 05",
    "sg:postcode":"3700",
    "sg:province":"Danmark",
    "wof:name":"Dv\u00e6rgh\u00f8nseklubben Bornholm",
    "wof:placetype":"venue"
},
  "geometry": {"coordinates":[-36.775188446,-5.9064798355],"type":"Point"}
}