{
  "type": "Feature",
  "properties": {
    "addr:full":"Ingesvej 35 H\u00f8ng Danmark 4270",
    "addr:housenumber":"35",
    "addr:postcode":"4270",
    "addr:street":"Ingesvej;Hong Danmark",
    "iso:country":"DK",
    "sg:address":"Ingesvej 35",
    "sg:city":"H\u00f8ng",
    "sg:orig_category":"Forsamlingshuse",
    "sg:postcode":"4270",
    "sg:province":"Danmark",
    "wof:name":"Fuglereden",
    "wof:placetype":"venue"
},
  "geometry": {"coordinates":[11.295343399,55.5028915405],"type":"Point"}
}