{
  "type": "Feature",
  "properties": {
    "addr:full":"Borgergade 121 Glejbjerg Danmark 6752",
    "addr:housenumber":"121",
    "addr:postcode":"6752",
    "addr:street":"Borgergade",
    "iso:country":"DK",
    "sg:address":"Borgergade 121",
    "sg:city":"Glejbjerg",
    "sg:orig_category":"Lokalarkiver",
    "sg:phone":"+45 75 19 85 69",
    "sg:postcode":"6752",
    "sg:province":"Danmark",
    "wof:name":"Aastrup Sognearkiv",
    "wof:placetype":"venue"
},
  "geometry": {"coordinates":[8.826748848,55.5687980652],"type":"Point"}
}