{
  "type": "Feature",
  "properties": {
    "iso:country":"DK",
    "sg:address":"Holmsland Klitvej 255, S\u00f8ndervig",
    "sg:city":"Ringk\u00f8bing",
    "sg:orig_category":"Sommerhusudlejning",
    "sg:phone":"+45 97 33 81 22",
    "sg:postcode":"6950",
    "sg:province":"Danmark",
    "wof:name":"dansommer S\u00f8ndervig",
    "wof:placetype":"venue"
},
  "geometry": {"coordinates":[8.2507953644,56.0878334045],"type":"Point"}
}