{
  "type": "Feature",
  "properties": {
    "addr:full":"Nyk\u00f8bingvej 13, \u00d8rslev Slagelse Danmark 4200",
    "addr:housenumber":"13",
    "addr:postcode":"4200",
    "addr:street":"Nykobingvej;Orslev",
    "iso:country":"DK",
    "sg:address":"Nyk\u00f8bingvej 13, \u00d8rslev",
    "sg:city":"Slagelse",
    "sg:orig_category":"Murermestre",
    "sg:postcode":"4200",
    "sg:province":"Danmark",
    "wof:name":"Solbjerg Murerne",
    "wof:placetype":"venue"
},
  "geometry": {"coordinates":[11.3569850922,55.4050865173],"type":"Point"}
}