{
  "type": "Feature",
  "properties": {
    "addr:full":"Fmd.: Peder A. Pedersen, \u00d8stergade 16, Hoven Tarm Danmark 6880",
    "addr:housenumber":"16",
    "addr:postcode":"6880",
    "addr:street":"Peder;Ostergade",
    "iso:country":"DK",
    "sg:address":"Fmd.: Peder A. Pedersen, \u00d8stergade 16, Hoven",
    "sg:city":"Tarm",
    "sg:orig_category":"Kulturelle foreninger",
    "sg:phone":"+45 75 34 32 01",
    "sg:postcode":"6880",
    "sg:province":"Danmark",
    "wof:name":"Hoven Hyggeklub",
    "wof:placetype":"venue"
},
  "geometry": {"coordinates":[8.5200052261,55.9060554504],"type":"Point"}
}