{
  "type": "Feature",
  "properties": {
    "addr:full":"Gustav Johannsens Vej 3 Odense C Danmark 5000",
    "addr:housenumber":"3",
    "addr:postcode":"5000",
    "addr:street":"Gustav Johannsens Vej",
    "iso:country":"DK",
    "sg:address":"Gustav Johannsens Vej 3",
    "sg:city":"Odense C",
    "sg:orig_category":"Bodegaer",
    "sg:phone":"+45 66 12 54 35",
    "sg:postcode":"5000",
    "sg:province":"Danmark",
    "wof:name":"Wienerstuen",
    "wof:placetype":"venue"
},
  "geometry": {"coordinates":[10.3700351715,55.3776512146],"type":"Point"}
}