{
  "type": "Feature",
  "properties": {
    "addr:full":"Kalkv\u00e6rksvej 2, Hvidbjerg Thyholm Danmark 7790",
    "addr:housenumber":"2",
    "addr:postcode":"7790",
    "addr:street":"Kalkvaerksvej;Hvidbjerg",
    "iso:country":"DK",
    "sg:address":"Kalkv\u00e6rksvej 2, Hvidbjerg",
    "sg:city":"Thyholm",
    "sg:orig_category":"Oliefyr og service",
    "sg:phone":"+45 97 87 10 54",
    "sg:postcode":"7790",
    "sg:province":"Danmark",
    "wof:name":"Nielsen, J\u00f8rgen",
    "wof:placetype":"venue"
},
  "geometry": {"coordinates":[8.525765419,56.6507072449],"type":"Point"}
}