{
  "type": "Feature",
  "properties": {
    "addr:full":"Bispensgade 10 Aalborg Danmark 9000",
    "addr:housenumber":"10",
    "addr:postcode":"9000",
    "addr:street":"Bispensgade",
    "iso:country":"DK",
    "sg:address":"Bispensgade 10",
    "sg:city":"Aalborg",
    "sg:orig_category":"Fotografer",
    "sg:phone":"+45 98 12 40 04",
    "sg:postcode":"9000",
    "sg:province":"Danmark",
    "wof:name":"Centrum Fotolab",
    "wof:placetype":"venue"
},
  "geometry": {"coordinates":[9.9201669693,57.0494995117],"type":"Point"}
}