{
  "type": "Feature",
  "properties": {
    "addr:full":"Vestergade 1 Holstebro Danmark 7500",
    "addr:housenumber":"1",
    "addr:postcode":"7500",
    "addr:street":"Vestergade",
    "iso:country":"DK",
    "sg:address":"Vestergade 1",
    "sg:city":"Holstebro",
    "sg:classifiers":[
        {
            "category":"Communications",
            "type":"Services"
        }
    ],
    "sg:phone":"+45 96 10 75 00",
    "sg:postcode":"7500",
    "sg:province":"Danmark",
    "sg:tags":[
        "radio-",
        "og",
        "tv-stationer"
    ],
    "wof:name":"Radio Midt & Vest (Danmarks Radio).",
    "wof:placetype":"venue"
},
  "geometry": {"coordinates":[8.616733551,56.3580932617],"type":"Point"}
}