{
  "type": "Feature",
  "properties": {
    "addr:full":"Glasvej 3 K\u00f8benhavn NV Danmark 2400",
    "addr:housenumber":"3",
    "addr:postcode":"2400",
    "addr:street":"Glasvej",
    "iso:country":"DK",
    "sg:address":"Glasvej 3",
    "sg:city":"K\u00f8benhavn NV",
    "sg:orig_category":"Kiosker",
    "sg:phone":"+45 38 87 70 17",
    "sg:postcode":"2400",
    "sg:province":"Danmark",
    "wof:name":"Kiosk 3",
    "wof:placetype":"venue"
},
  "geometry": {"coordinates":[-117.02272033689999,38.5024604797],"type":"Point"}
}