{
  "type": "Feature",
  "properties": {
    "addr:full":"Windelsvej 81 Odense C Danmark 5000",
    "addr:housenumber":"81",
    "addr:postcode":"5000",
    "addr:street":"Windelsvej",
    "iso:country":"DK",
    "sg:address":"Windelsvej 81",
    "sg:city":"Odense C",
    "sg:orig_category":"Tekstiler",
    "sg:phone":"+45 65 90 39 00",
    "sg:postcode":"5000",
    "sg:province":"Danmark",
    "wof:name":"Franini",
    "wof:placetype":"venue"
},
  "geometry": {"coordinates":[10.3965301514,55.4189949036],"type":"Point"}
}