{
  "type": "Feature",
  "properties": {
    "addr:full":"H\u00f8sten Teglv\u00e6rksvej 85, Babberup Haslev Danmark 4690",
    "addr:housenumber":"85",
    "addr:postcode":"4690",
    "addr:street":"Teglvaerksvej",
    "iso:country":"DK",
    "sg:address":"H\u00f8sten Teglv\u00e6rksvej 85, Babberup",
    "sg:city":"Haslev",
    "sg:orig_category":"Vinduespolering",
    "sg:phone":"+45 40 25 41 62",
    "sg:postcode":"4690",
    "sg:province":"Danmark",
    "wof:name":"3x65 Vinduespolering v/J.R. Hansen",
    "wof:placetype":"venue"
},
  "geometry": {"coordinates":[11.9678049088,55.3230895996],"type":"Point"}
}