{
  "type": "Feature",
  "properties": {
    "addr:full":"Danhaven 5 Valby Danmark 2500",
    "addr:housenumber":"5",
    "addr:postcode":"2500",
    "addr:street":"Danhaven",
    "iso:country":"DK",
    "sg:address":"Danhaven 5",
    "sg:city":"Valby",
    "sg:orig_category":"Yogaundervisning",
    "sg:phone":"+45 36 45 56 25",
    "sg:postcode":"2500",
    "sg:province":"Danmark",
    "wof:name":"Feveile, Bett",
    "wof:placetype":"venue"
},
  "geometry": {"coordinates":[12.4928016663,55.6519927979],"type":"Point"}
}