{
  "type": "Feature",
  "properties": {
    "addr:full":"R\u00e5dhuset, Gothersgade 20 Fredericia Danmark 7000",
    "addr:housenumber":"20",
    "addr:postcode":"7000",
    "addr:street":"Gothersgade",
    "iso:country":"DK",
    "sg:address":"R\u00e5dhuset, Gothersgade 20",
    "sg:city":"Fredericia",
    "sg:orig_category":"Kommunen",
    "sg:phone":"+45 72 10 70 00",
    "sg:postcode":"7000",
    "sg:province":"Danmark",
    "wof:name":"Fredericia Kommune",
    "wof:placetype":"venue"
},
  "geometry": {"coordinates":[9.7591047287,55.566368103],"type":"Point"}
}