{
  "type": "Feature",
  "properties": {
    "addr:full":"Nordre Strandvej 53, 1. Risskov Danmark 8240",
    "addr:housenumber":"53 1",
    "addr:postcode":"8240",
    "addr:street":"Nordre Strandvej",
    "iso:country":"DK",
    "sg:address":"Nordre Strandvej 53, 1.",
    "sg:city":"Risskov",
    "sg:orig_category":"Reklamebureauer",
    "sg:phone":"+45 86 17 88 42",
    "sg:postcode":"8240",
    "sg:province":"Danmark",
    "sg:website":"www.doubleloop.dk",
    "wof:name":"Grafik DK",
    "wof:placetype":"venue"
},
  "geometry": {"coordinates":[10.2480831146,56.195602417],"type":"Point"}
}