{
  "type": "Feature",
  "properties": {
    "addr:full":"Odinsvej 19 Ringsted Danmark 4100",
    "addr:housenumber":"19",
    "addr:postcode":"4100",
    "addr:street":"Odinsvej",
    "iso:country":"DK",
    "sg:address":"Odinsvej 19",
    "sg:city":"Ringsted",
    "sg:orig_category":"Korn og foderstoffer",
    "sg:phone":"+45 57 61 51 39",
    "sg:postcode":"4100",
    "sg:province":"Danmark",
    "wof:name":"DLF - Trifolium A/S",
    "wof:placetype":"venue"
},
  "geometry": {"coordinates":[11.7983417511,55.4337501526],"type":"Point"}
}