{
  "type": "Feature",
  "properties": {
    "addr:full":"Hovedgaden 112, Poulstrup Vr\u00e5 Danmark 9760",
    "addr:housenumber":"112",
    "addr:postcode":"9760",
    "addr:street":"Hovedgaden",
    "iso:country":"DK",
    "sg:address":"Hovedgaden 112, Poulstrup",
    "sg:city":"Vr\u00e5",
    "sg:orig_category":"Taxameterservice",
    "sg:phone":"+45 98 98 85 07",
    "sg:postcode":"9760",
    "sg:province":"Danmark",
    "sg:website":"www.todbjerg.dk",
    "wof:name":"Todbjerg Nord ApS",
    "wof:placetype":"venue"
},
  "geometry": {"coordinates":[9.9477567673,57.3534927368],"type":"Point"}
}