{
  "type": "Feature",
  "properties": {
    "addr:full":"Krogvejen 20, Arnborg Herning Danmark 7400",
    "addr:housenumber":"20",
    "addr:postcode":"7400",
    "addr:street":"Krogvejen;Arnborg",
    "iso:country":"DK",
    "sg:address":"Krogvejen 20, Arnborg",
    "sg:city":"Herning",
    "sg:classifiers":[
        {
            "category":"Utilities",
            "subcategory":"Cable",
            "type":"Services"
        }
    ],
    "sg:phone":"+45 97 14 94 00",
    "sg:postcode":"7400",
    "sg:province":"Danmark",
    "sg:tags":[
        "trapper"
    ],
    "wof:name":"JNS Produkter ApS",
    "wof:placetype":"venue"
},
  "geometry": {"coordinates":[8.9768896103,56.1374168396],"type":"Point"}
}