{
  "type": "Feature",
  "properties": {
    "addr:full":"Andk\u00e6rvej 14 Vejle Danmark 7100",
    "addr:housenumber":"14",
    "addr:postcode":"7100",
    "addr:street":"Andkaervej",
    "iso:country":"DK",
    "sg:address":"Andk\u00e6rvej 14",
    "sg:city":"Vejle",
    "sg:classifiers":[
        {
            "category":"Communications",
            "type":"Services"
        }
    ],
    "sg:phone":"+45 75 85 73 00",
    "sg:postcode":"7100",
    "sg:province":"Danmark",
    "sg:tags":[
        "og",
        "tv",
        "radio"
    ],
    "sg:website":"www.drt.dk",
    "wof:name":"Dansk Radio Teknik A/S",
    "wof:placetype":"venue"
},
  "geometry": {"coordinates":[9.6052951813,55.6744804382],"type":"Point"}
}