{
  "type": "Feature",
  "properties": {
    "addr:full":"Estrupsgade 22 A Silkeborg Danmark 8600",
    "addr:housenumber":"22 a",
    "addr:postcode":"8600",
    "addr:street":"Estrupsgade",
    "iso:country":"DK",
    "sg:address":"Estrupsgade 22 A",
    "sg:city":"Silkeborg",
    "sg:orig_category":"Motionscentre",
    "sg:phone":"+45 86 80 60 48",
    "sg:postcode":"8600",
    "sg:province":"Danmark",
    "wof:name":"Beauty Form",
    "wof:placetype":"venue"
},
  "geometry": {"coordinates":[9.5443229675,56.1651763916],"type":"Point"}
}