{
  "type": "Feature",
  "properties": {
    "addr:full":"Enghaven 15 Holstebro Danmark 7500",
    "addr:housenumber":"15",
    "addr:postcode":"7500",
    "addr:street":"Enghaven",
    "iso:country":"DK",
    "sg:address":"Enghaven 15",
    "sg:city":"Holstebro",
    "sg:orig_category":"Designere",
    "sg:phone":"+45 97 40 38 00",
    "sg:postcode":"7500",
    "sg:province":"Danmark",
    "sg:website":"www.modus.dk",
    "wof:name":"Modus Exhibition A/S",
    "wof:placetype":"venue"
},
  "geometry": {"coordinates":[8.6051893234,56.3576774597],"type":"Point"}
}