{
  "type": "Feature",
  "properties": {
    "addr:full":"Fmd.: Poul S\u00f8by Nielsen, Gl. Landevej 136 Herning Danmark 7400",
    "addr:housenumber":"136",
    "addr:postcode":"7400",
    "addr:street":"Poul Soby Nielsen Gl. Landevej",
    "iso:country":"DK",
    "sg:address":"Fmd.: Poul S\u00f8by Nielsen, Gl. Landevej 136",
    "sg:city":"Herning",
    "sg:orig_category":"Hobbybetonede foreninger",
    "sg:phone":"+45 97 12 66 03",
    "sg:postcode":"7400",
    "sg:province":"Danmark",
    "wof:name":"Vestjysk Stenklub",
    "wof:placetype":"venue"
},
  "geometry": {"coordinates":[8.9768896103,56.1374168396],"type":"Point"}
}