{
  "type": "Feature",
  "properties": {
    "addr:full":"N\u00f8rregade 8, Vammen Tjele Danmark 8830",
    "addr:housenumber":"8",
    "addr:postcode":"8830",
    "addr:street":"Norregade;Vammen",
    "iso:country":"DK",
    "sg:address":"N\u00f8rregade 8, Vammen",
    "sg:city":"Tjele",
    "sg:classifiers":[
        {
            "category":"Banks & Credit Unions",
            "subcategory":"Bank",
            "type":"Services"
        }
    ],
    "sg:phone":"+45 86 69 03 55",
    "sg:postcode":"8830",
    "sg:province":"Danmark",
    "sg:tags":[
        "banker"
    ],
    "wof:name":"Vammen Andelskasse",
    "wof:placetype":"venue"
},
  "geometry": {"coordinates":[9.62648,56.481861],"type":"Point"}
}