{
  "type": "Feature",
  "properties": {
    "addr:full":"Skt. Clemens Torv 17, 3. tv. \u00c5rhus C Danmark 8000",
    "addr:housenumber":"17 3 tv.",
    "addr:postcode":"8000",
    "addr:street":"Skt. Clemens Torv",
    "iso:country":"DK",
    "sg:address":"Skt. Clemens Torv 17, 3. tv.",
    "sg:city":"\u00c5rhus C",
    "sg:orig_category":"Ejendomshandel",
    "sg:phone":"+45 86 13 40 33",
    "sg:postcode":"8000",
    "sg:province":"Danmark",
    "sg:website":"www.tlk.dk",
    "wof:name":"TLK Ejendomshandel",
    "wof:placetype":"venue"
},
  "geometry": {"coordinates":[14.8059501648,55.175239563],"type":"Point"}
}