{
  "type": "Feature",
  "properties": {
    "iso:country":"DK",
    "sg:address":"v/ Dianne Pedersen, Gr\u00f8lstedvej 9, Gr\u00f8lsted",
    "sg:city":"Thors\u00f8",
    "sg:orig_category":"Husflidsforeninger",
    "sg:phone":"+45 86 96 68 75",
    "sg:postcode":"8881",
    "sg:province":"Danmark",
    "wof:name":"Hammel Husmandsforenings Husholdningsudvalg",
    "wof:placetype":"venue"
},
  "geometry": {"coordinates":[-86.71593475340001,32.916103363],"type":"Point"}
}