{
  "type": "Feature",
  "properties": {
    "iso:country":"DK",
    "sg:address":"Chr. Winthers Vej 4 C",
    "sg:city":"Frederiksberg",
    "sg:orig_category":"Arkitekter",
    "sg:phone":"+45 33 22 12 45",
    "sg:postcode":"1860",
    "sg:province":"Danmark",
    "wof:name":"Voss, Henry",
    "wof:placetype":"venue"
},
  "geometry": {"coordinates":[12.5352373123,55.6809120178],"type":"Point"}
}