{
  "type": "Feature",
  "properties": {
    "addr:full":"Munkem\u00f8llestr\u00e6de 20 Odense C Danmark 5000",
    "addr:housenumber":"20",
    "addr:postcode":"5000",
    "addr:street":"Munkemollestraede",
    "iso:country":"DK",
    "sg:address":"Munkem\u00f8llestr\u00e6de 20",
    "sg:city":"Odense C",
    "sg:orig_category":"Kulturelle foreninger",
    "sg:phone":"+45 66 12 87 00",
    "sg:postcode":"5000",
    "sg:province":"Danmark",
    "sg:website":"www.studenterhus.dk",
    "wof:name":"Studenterhus Odense",
    "wof:placetype":"venue"
},
  "geometry": {"coordinates":[10.390794754,55.3961715698],"type":"Point"}
}