{
  "type": "Feature",
  "properties": {
    "addr:full":"Roskildevej 10 Frederikssund Danmark 3600",
    "addr:housenumber":"10",
    "addr:postcode":"3600",
    "addr:street":"Roskildevej",
    "iso:country":"DK",
    "sg:address":"Roskildevej 10",
    "sg:city":"Frederikssund",
    "sg:orig_category":"Skilte",
    "sg:phone":"+45 47 31 08 21",
    "sg:postcode":"3600",
    "sg:province":"Danmark",
    "wof:name":"Meltinis Skilte I/S",
    "wof:placetype":"venue"
},
  "geometry": {"coordinates":[12.0674161911,55.8349304199],"type":"Point"}
}