{
  "type": "Feature",
  "properties": {
    "addr:full":"Adm.: FynBus, Dannebrogsgade 10, Postboks 359 5100",
    "addr:housenumber":"10;359",
    "addr:postcode":"5100",
    "addr:street":"Dannebrogsgade",
    "iso:country":"DK",
    "sg:address":"Adm.: FynBus, Dannebrogsgade 10, Postboks 359",
    "sg:orig_category":"Rutebiler",
    "sg:postcode":"5100",
    "sg:website":"www.fynbus.dk",
    "wof:name":"Kollektiv Trafik Regionale Ruter",
    "wof:placetype":"venue"
},
  "geometry": {"coordinates":[10.3908996582,55.3960914612],"type":"Point"}
}