{
  "type": "Feature",
  "properties": {
    "addr:full":"Stationsmestervej 94 Aalborg SV Danmark 9200",
    "addr:housenumber":"94",
    "addr:postcode":"9200",
    "addr:street":"Stationsmestervej",
    "iso:country":"DK",
    "sg:address":"Stationsmestervej 94",
    "sg:city":"Aalborg SV",
    "sg:classifiers":[
        {
            "category":"Banks & Credit Unions",
            "subcategory":"Investment Brokerage",
            "type":"Services"
        }
    ],
    "sg:phone":"+45 98 18 80 90",
    "sg:postcode":"9200",
    "sg:province":"Danmark",
    "sg:tags":[
        "healing"
    ],
    "wof:name":"Lundholm, Hanne Lise",
    "wof:placetype":"venue"
},
  "geometry": {"coordinates":[9.8894701004,57.0083274841],"type":"Point"}
}