{
  "type": "Feature",
  "properties": {
    "addr:full":"Klokkest\u00f8bervej 16 Odense M Danmark 5230",
    "addr:housenumber":"16",
    "addr:postcode":"5230",
    "addr:street":"Klokkestobervej",
    "iso:country":"DK",
    "sg:address":"Klokkest\u00f8bervej 16",
    "sg:city":"Odense M",
    "sg:classifiers":[
        {
            "category":"Retail",
            "subcategory":"Storage",
            "type":"Services"
        }
    ],
    "sg:phone":"+45 66 15 98 35",
    "sg:postcode":"5230",
    "sg:province":"Danmark",
    "sg:tags":[
        "edb",
        "hardware",
        "-"
    ],
    "wof:name":"R D Data ApS",
    "wof:placetype":"venue"
},
  "geometry": {"coordinates":[10.4176282883,55.3800392151],"type":"Point"}
}