{
  "type": "Feature",
  "properties": {
    "iso:country":"DK",
    "sg:address":"Torvegade 4",
    "sg:city":"Padborg",
    "sg:orig_category":"Sko",
    "sg:phone":"+45 74 67 47 88",
    "sg:postcode":"6330",
    "sg:province":"Danmark",
    "wof:name":"Rasmussen Sko Tops",
    "wof:placetype":"venue"
},
  "geometry": {"coordinates":[9.3614187241,54.8258552551],"type":"Point"}
}