{
  "type": "Feature",
  "properties": {
    "iso:country":"DK",
    "sg:address":"Hjaltesvej 23 PO BOX 88 ",
    "sg:city":"Randers",
    "sg:classifiers":[
        {
            "category":"Manufacturing",
            "subcategory":"Glass & Minerals",
            "type":"Manufacturing & Wholesale Goods"
        }
    ],
    "sg:phone":"+45 86 42 16 33",
    "sg:postcode":"8900",
    "sg:province":"Danmark",
    "wof:name":"J.N. BECH A/S",
    "wof:placetype":"venue"
},
  "geometry": {"coordinates":[10.0357952118,56.4593734741],"type":"Point"}
}