{
  "type": "Feature",
  "properties": {
    "iso:country":"DK",
    "sg:address":"D\u00f8esvej 109",
    "sg:city":"Holstebro",
    "sg:orig_category":"Supermarkeder",
    "sg:phone":"+45 97 41 20 95",
    "sg:postcode":"7500",
    "sg:province":"Danmark",
    "wof:name":"Spar Supermarked",
    "wof:placetype":"venue"
},
  "geometry": {"coordinates":[8.6010227203,56.370349884],"type":"Point"}
}