{
  "type": "Feature",
  "properties": {
    "addr:full":"Bog\u00f8vej 49 Otterup Danmark 5450",
    "addr:housenumber":"49",
    "addr:postcode":"5450",
    "addr:street":"Bogovej",
    "iso:country":"DK",
    "sg:address":"Bog\u00f8vej 49",
    "sg:city":"Otterup",
    "sg:orig_category":"Fliser",
    "sg:phone":"+45 63 82 00 83",
    "sg:postcode":"5450",
    "sg:province":"Danmark",
    "wof:name":"Couleur Provence",
    "wof:placetype":"venue"
},
  "geometry": {"coordinates":[10.4692907333,55.5228881836],"type":"Point"}
}