{
  "type": "Feature",
  "properties": {
    "addr:full":"Borgergade 48 Stouby Danmark 7140",
    "addr:housenumber":"48",
    "addr:postcode":"7140",
    "addr:street":"Borgergade",
    "iso:country":"DK",
    "sg:address":"Borgergade 48",
    "sg:city":"Stouby",
    "sg:orig_category":"Apoteker og -udsalg",
    "sg:phone":"+45 75 89 72 15",
    "sg:postcode":"7140",
    "sg:province":"Danmark",
    "wof:name":"H\u00e5ndk\u00f8bsudsalget, Stouby Kiosk",
    "wof:placetype":"venue"
},
  "geometry": {"coordinates":[9.7904281616,55.700553894],"type":"Point"}
}