{
  "type": "Feature",
  "properties": {
    "addr:full":"Lundsbjerg Industrivej 1 Aabenraa Danmark 6200",
    "addr:housenumber":"1",
    "addr:postcode":"6200",
    "addr:street":"Lundsbjerg Industrivej",
    "iso:country":"DK",
    "sg:address":"Lundsbjerg Industrivej 1",
    "sg:city":"Aabenraa",
    "sg:orig_category":"Autoforhandlere",
    "sg:phone":"+45 74 61 31 33",
    "sg:postcode":"6200",
    "sg:province":"Danmark",
    "wof:name":"Skifter Lastbil A/S",
    "wof:placetype":"venue"
},
  "geometry": {"coordinates":[9.4400548935,55.003238678],"type":"Point"}
}