{
  "type": "Feature",
  "properties": {
    "addr:full":"Skibbrogade 30 Kalundborg Danmark 4400",
    "addr:housenumber":"30",
    "addr:postcode":"4400",
    "addr:street":"Skibbrogade",
    "iso:country":"DK",
    "sg:address":"Skibbrogade 30",
    "sg:city":"Kalundborg",
    "sg:orig_category":"Psykologer, praktiserende",
    "sg:phone":"+45 59 56 32 68",
    "sg:postcode":"4400",
    "sg:province":"Danmark",
    "wof:name":"Hvash\u00f8j, Per",
    "wof:placetype":"venue"
},
  "geometry": {"coordinates":[11.0865316391,55.679485321],"type":"Point"}
}