{
  "type": "Feature",
  "properties": {
    "addr:full":"St\u00f8berledsvej 8 Liseleje Danmark 3360",
    "addr:housenumber":"8",
    "addr:postcode":"3360",
    "addr:street":"Stoberledsvej",
    "iso:country":"DK",
    "sg:address":"St\u00f8berledsvej 8",
    "sg:city":"Liseleje",
    "sg:orig_category":"Alternativ behandling",
    "sg:phone":"+45 47 74 21 47",
    "sg:postcode":"3360",
    "sg:province":"Danmark",
    "wof:name":"Christensen, Anni",
    "wof:placetype":"venue"
},
  "geometry": {"coordinates":[11.9833059311,56.0065765381],"type":"Point"}
}