{
  "type": "Feature",
  "properties": {
    "addr:full":"Holb\u00e6kvej 3 B Svinninge Danmark 4520",
    "addr:housenumber":"3 b",
    "addr:postcode":"4520",
    "addr:street":"Holbaekvej",
    "iso:country":"DK",
    "sg:address":"Holb\u00e6kvej 3 B",
    "sg:city":"Svinninge",
    "sg:orig_category":"Revisorer",
    "sg:phone":"+45 59 26 10 20",
    "sg:postcode":"4520",
    "sg:province":"Danmark",
    "sg:website":"www.bbrevision.dk",
    "wof:name":"BB Revision",
    "wof:placetype":"venue"
},
  "geometry": {"coordinates":[11.471531868,55.7230300903],"type":"Point"}
}