{
  "type": "Feature",
  "properties": {
    "addr:full":"Dortheadalsvej 11, Ron\u00e6s Marstal Danmark 5960",
    "addr:housenumber":"11",
    "addr:postcode":"5960",
    "addr:street":"Dortheadalsvej;Ronaes",
    "iso:country":"DK",
    "sg:address":"Dortheadalsvej 11, Ron\u00e6s",
    "sg:city":"Marstal",
    "sg:orig_category":"Lufttransport",
    "sg:phone":"+45 62 53 33 94",
    "sg:postcode":"5960",
    "sg:province":"Danmark",
    "wof:name":"Starling Air",
    "wof:placetype":"venue"
},
  "geometry": {"coordinates":[10.5212097168,54.8543815613],"type":"Point"}
}