{
  "type": "Feature",
  "properties": {
    "iso:country":"DK",
    "sg:address":"Gammel Kongevej 149",
    "sg:city":"Frederiksberg",
    "sg:orig_category":"Brugskunst",
    "sg:phone":"+45 33 25 48 07",
    "sg:postcode":"1850",
    "sg:province":"Danmark",
    "wof:name":"Lafayette",
    "wof:placetype":"venue"
},
  "geometry": {"coordinates":[12.537899971,55.6771812439],"type":"Point"}
}