{
  "type": "Feature",
  "properties": {
    "iso:country":"DK",
    "sg:address":"Gammel Jernbanevej 30",
    "sg:city":"Valby",
    "sg:orig_category":"Antikviteter",
    "sg:phone":"+45 36 16 01 34",
    "sg:postcode":"2500",
    "sg:province":"Danmark",
    "wof:name":"Gallerie Pep\u00e9s Antik",
    "wof:placetype":"venue"
},
  "geometry": {"coordinates":[12.5186109543,55.6645050049],"type":"Point"}
}