{
  "type": "Feature",
  "properties": {
    "iso:country":"DK",
    "sg:address":"Amh\u00f8jvej 14",
    "sg:city":"Jelling",
    "sg:orig_category":"Integrerede institutioner",
    "sg:phone":"+45 75 87 28 18",
    "sg:postcode":"7300",
    "sg:province":"Danmark",
    "wof:name":"Grang\u00e5rden",
    "wof:placetype":"venue"
},
  "geometry": {"coordinates":[9.4184103012,55.7558555603],"type":"Point"}
}