{
  "type": "Feature",
  "properties": {
    "addr:full":"Thyrasvej 60 Herning Danmark 7400",
    "addr:housenumber":"60",
    "addr:postcode":"7400",
    "addr:street":"Thyrasvej",
    "iso:country":"DK",
    "sg:address":"Thyrasvej 60",
    "sg:city":"Herning",
    "sg:orig_category":"Grillbarer",
    "sg:phone":"+45 97 21 38 44",
    "sg:postcode":"7400",
    "sg:province":"Danmark",
    "wof:name":"Erlands Grill",
    "wof:placetype":"venue"
},
  "geometry": {"coordinates":[8.9986791611,56.133480072],"type":"Point"}
}