{
  "type": "Feature",
  "properties": {
    "addr:full":"Spedals\u00f8 7 Horsens Danmark 8700",
    "addr:housenumber":"7",
    "addr:postcode":"8700",
    "addr:street":"Spedalso",
    "iso:country":"DK",
    "sg:address":"Spedals\u00f8 7",
    "sg:city":"Horsens",
    "sg:classifiers":[
        {
            "category":"Restaurant",
            "type":"Food & Drink"
        }
    ],
    "sg:phone":"+45 75 61 45 10",
    "sg:postcode":"8700",
    "sg:province":"Danmark",
    "wof:name":"Klods Hans",
    "wof:placetype":"venue"
},
  "geometry": {"coordinates":[9.8383054733,55.8565177917],"type":"Point"}
}