{
  "type": "Feature",
  "properties": {
    "addr:full":"Vestre Hovedgade 26 Hjerm Danmark 7560",
    "addr:housenumber":"26",
    "addr:postcode":"7560",
    "addr:street":"Vestre Hovedgade",
    "iso:country":"DK",
    "sg:address":"Vestre Hovedgade 26",
    "sg:city":"Hjerm",
    "sg:orig_category":"Autolak",
    "sg:phone":"+45 97 46 41 10",
    "sg:postcode":"7560",
    "sg:province":"Danmark",
    "wof:name":"Autolak en gros",
    "wof:placetype":"venue"
},
  "geometry": {"coordinates":[8.6370811462,56.4381561279],"type":"Point"}
}