{
  "type": "Feature",
  "properties": {
    "addr:full":"Klingeberg 5 Slagelse Danmark 4200",
    "addr:housenumber":"5",
    "addr:postcode":"4200",
    "addr:street":"Klingeberg",
    "iso:country":"DK",
    "sg:address":"Klingeberg 5",
    "sg:city":"Slagelse",
    "sg:orig_category":"Cylinderservice",
    "sg:phone":"+45 58 52 12 05",
    "sg:postcode":"4200",
    "sg:province":"Danmark",
    "wof:name":"Slagelse Cylinder & Diesel Service",
    "wof:placetype":"venue"
},
  "geometry": {"coordinates":[11.3562889099,55.4018859863],"type":"Point"}
}