{
  "type": "Feature",
  "properties": {
    "addr:full":"Havnegade 17 Esbjerg Danmark 6700",
    "addr:housenumber":"17",
    "addr:postcode":"6700",
    "addr:street":"Havnegade",
    "iso:country":"DK",
    "sg:address":"Havnegade 17",
    "sg:city":"Esbjerg",
    "sg:orig_category":"Malermestre",
    "sg:phone":"+45 75 45 27 77",
    "sg:postcode":"6700",
    "sg:province":"Danmark",
    "wof:name":"Olsen, Ib",
    "wof:placetype":"venue"
},
  "geometry": {"coordinates":[8.453704834,55.4645729065],"type":"Point"}
}