{
  "type": "Feature",
  "properties": {
    "addr:full":"PO Box 95, Storegade 27-29 Broager Danmark 6310",
    "addr:housenumber":"po box 95",
    "addr:postcode":"27-29;6310",
    "addr:street":"Storegade",
    "iso:country":"DK",
    "sg:address":"PO Box 95, Storegade 27-29",
    "sg:city":"Broager",
    "sg:classifiers":[
        {
            "category":"Banks & Credit Unions",
            "subcategory":"Bank",
            "type":"Services"
        }
    ],
    "sg:phone":"+45 74 44 11 13",
    "sg:postcode":"6310",
    "sg:province":"Danmark",
    "sg:website":"http://www.broagersparekasse.dk",
    "wof:name":"Broager Spare-og Laanekasse",
    "wof:placetype":"venue"
},
  "geometry": {"coordinates":[9.667324,54.889362],"type":"Point"}
}