{
  "type": "Feature",
  "properties": {
    "addr:full":"Nyvej 51 A, Ulb\u00f8lle Vester Skerninge Danmark 5762",
    "addr:housenumber":"51 a",
    "addr:postcode":"5762",
    "addr:street":"Nyvej",
    "iso:country":"DK",
    "sg:address":"Nyvej 51 A, Ulb\u00f8lle",
    "sg:city":"Vester Skerninge",
    "sg:orig_category":"Kirker",
    "sg:postcode":"5762",
    "sg:province":"Danmark",
    "wof:name":"Ulb\u00f8lle Kirke",
    "wof:placetype":"venue"
},
  "geometry": {"coordinates":[10.5008449554,55.070400238],"type":"Point"}
}