{
  "type": "Feature",
  "properties": {
    "addr:full":"Lindevej 7 Fakse Danmark 4640",
    "addr:housenumber":"7",
    "addr:postcode":"4640",
    "addr:street":"Lindevej",
    "iso:country":"DK",
    "sg:address":"Lindevej 7",
    "sg:city":"Fakse",
    "sg:orig_category":"Fodterapeuter",
    "sg:phone":"+45 56 71 51 01",
    "sg:postcode":"4640",
    "sg:province":"Danmark",
    "wof:name":"Andersen, Inger",
    "wof:placetype":"venue"
},
  "geometry": {"coordinates":[12.1169652939,55.2530822754],"type":"Point"}
}