{
  "type": "Feature",
  "properties": {
    "iso:country":"DK",
    "sg:address":"Jonstrupvej 117",
    "sg:city":"Ballerup",
    "sg:orig_category":"Autoopretning",
    "sg:phone":"+45 44 65 28 42",
    "sg:postcode":"2750",
    "sg:province":"Danmark",
    "wof:name":"J-J Pladesmedie",
    "wof:placetype":"venue"
},
  "geometry": {"coordinates":[12.3532400131,55.7414970398],"type":"Point"}
}