{
  "type": "Feature",
  "properties": {
    "addr:full":"Dieselvej 5 Kolding Danmark 6000",
    "addr:housenumber":"5",
    "addr:postcode":"6000",
    "addr:street":"Dieselvej",
    "iso:country":"DK",
    "sg:address":"Dieselvej 5",
    "sg:city":"Kolding",
    "sg:orig_category":"Farve og tapet",
    "sg:phone":"+45 75 53 88 00",
    "sg:postcode":"6000",
    "sg:province":"Danmark",
    "wof:name":"Greising ApS, Farvecentret Keld",
    "wof:placetype":"venue"
},
  "geometry": {"coordinates":[9.4810028076,55.4723091125],"type":"Point"}
}