{
  "type": "Feature",
  "properties": {
    "addr:full":"Knabberupvej 118 Vejle Danmark 7100",
    "addr:housenumber":"118",
    "addr:postcode":"7100",
    "addr:street":"Knabberupvej",
    "iso:country":"DK",
    "sg:address":"Knabberupvej 118",
    "sg:city":"Vejle",
    "sg:orig_category":"Arkitekter",
    "sg:phone":"+45 75 88 18 66",
    "sg:postcode":"7100",
    "sg:province":"Danmark",
    "wof:name":"Mielby, Kuno",
    "wof:placetype":"venue"
},
  "geometry": {"coordinates":[9.4515066147,55.7150726318],"type":"Point"}
}