{
  "type": "Feature",
  "properties": {
    "addr:full":"\u00c6r\u00f8sk\u00f8bing Sygehus, Sygehusvejen 18 \u00c6r\u00f8sk\u00f8bing Danmark 5970",
    "addr:housenumber":"18",
    "addr:postcode":"5970",
    "addr:street":"Sygehusvejen",
    "iso:country":"DK",
    "sg:address":"\u00c6r\u00f8sk\u00f8bing Sygehus, Sygehusvejen 18",
    "sg:city":"\u00c6r\u00f8sk\u00f8bing",
    "sg:orig_category":"Jordemodercentre",
    "sg:postcode":"5970",
    "sg:province":"Danmark",
    "wof:name":"Jordemoderkonsultation",
    "wof:placetype":"venue"
},
  "geometry": {"coordinates":[-114.0767440796,46.4432487488],"type":"Point"}
}