{
  "type": "Feature",
  "properties": {
    "addr:full":"Det Gule Pakhus, Havnen 1 N\u00e6stved Danmark 4700",
    "addr:housenumber":"1",
    "addr:postcode":"4700",
    "addr:street":"Havnen",
    "iso:country":"DK",
    "sg:address":"Det Gule Pakhus, Havnen 1",
    "sg:city":"N\u00e6stved",
    "sg:orig_category":"Erhvervsudvikling",
    "sg:phone":"+45 55 73 66 99",
    "sg:postcode":"4700",
    "sg:province":"Danmark",
    "wof:name":"N\u00e6stved-Egnens Erhvervskontor A/S",
    "wof:placetype":"venue"
},
  "geometry": {"coordinates":[11.7542486191,55.2315444946],"type":"Point"}
}