{
  "type": "Feature",
  "properties": {
    "addr:full":"Ellestrup 4 Vejen Danmark 6600",
    "addr:housenumber":"4",
    "addr:postcode":"6600",
    "addr:street":"Ellestrup",
    "iso:country":"DK",
    "sg:address":"Ellestrup 4",
    "sg:city":"Vejen",
    "sg:classifiers":[
        {
            "category":"Professional",
            "subcategory":"Computer Services",
            "type":"Services"
        }
    ],
    "sg:phone":"+45 75 36 47 49",
    "sg:postcode":"6600",
    "sg:province":"Danmark",
    "sg:tags":[
        "edb",
        "-",
        "software"
    ],
    "wof:name":"Alkimea Data",
    "wof:placetype":"venue"
},
  "geometry": {"coordinates":[9.1295681,55.4624443054],"type":"Point"}
}