{
  "type": "Feature",
  "properties": {
    "addr:full":"M\u00f8lh\u00f8jvej 10 Esbjerg \u00d8 Danmark 6705",
    "addr:housenumber":"10",
    "addr:postcode":"6705",
    "addr:street":"Molhojvej;Danmark",
    "iso:country":"DK",
    "sg:address":"M\u00f8lh\u00f8jvej 10",
    "sg:city":"Esbjerg \u00d8",
    "sg:orig_category":"Lokalarkiver",
    "sg:postcode":"6705",
    "sg:province":"Danmark",
    "wof:name":"Skads Sognearkiv",
    "wof:placetype":"venue"
},
  "geometry": {"coordinates":[8.5338830948,55.5006523132],"type":"Point"}
}