{
  "type": "Feature",
  "properties": {
    "addr:full":"Simmelk\u00e6r Hovedgade 3 Sunds Danmark 7451",
    "addr:housenumber":"3",
    "addr:postcode":"7451",
    "addr:street":"Simmelkaer Hovedgade",
    "iso:country":"DK",
    "sg:address":"Simmelk\u00e6r Hovedgade 3",
    "sg:city":"Sunds",
    "sg:orig_category":"Landbrugsmaskiner",
    "sg:phone":"+45 97 14 30 22",
    "sg:postcode":"7451",
    "sg:province":"Danmark",
    "wof:name":"Simmelk\u00e6r Maskiner",
    "wof:placetype":"venue"
},
  "geometry": {"coordinates":[9.0027103424,56.2676315308],"type":"Point"}
}