{
  "type": "Feature",
  "properties": {
    "addr:full":"Mejlgade 48 \u00c5rhus C Danmark 8000",
    "addr:housenumber":"48",
    "addr:postcode":"8000",
    "addr:street":"Mejlgade",
    "iso:country":"DK",
    "sg:address":"Mejlgade 48",
    "sg:city":"\u00c5rhus C",
    "sg:orig_category":"Musikinstrumenter",
    "sg:phone":"+45 86 19 78 77",
    "sg:postcode":"8000",
    "sg:province":"Danmark",
    "wof:name":"Slagt\u00f8j Centret A/S",
    "wof:placetype":"venue"
},
  "geometry": {"coordinates":[4.717400074,49.7588005066],"type":"Point"}
}