{
  "type": "Feature",
  "properties": {
    "addr:full":"Vejlevej 21 Hedensted Danmark 8722",
    "addr:housenumber":"21",
    "addr:postcode":"8722",
    "addr:street":"Vejlevej",
    "iso:country":"DK",
    "sg:address":"Vejlevej 21",
    "sg:city":"Hedensted",
    "sg:orig_category":"Fabrikker",
    "sg:phone":"+45 75 89 15 11",
    "sg:postcode":"8722",
    "sg:province":"Danmark",
    "wof:name":"Dungs A/S, Karl",
    "wof:placetype":"venue"
},
  "geometry": {"coordinates":[9.6863136292,55.7646522522],"type":"Point"}
}