{
  "type": "Feature",
  "properties": {
    "addr:full":"Nordre Ringvej 69 Glostrup Danmark 2600",
    "addr:housenumber":"69",
    "addr:postcode":"2600",
    "addr:street":"Nordre Ringvej",
    "iso:country":"DK",
    "sg:address":"Nordre Ringvej 69",
    "sg:city":"Glostrup",
    "sg:orig_category":"Handicap-daginstitutioner",
    "sg:phone":"+45 43 45 00 81",
    "sg:postcode":"2600",
    "sg:province":"Danmark",
    "wof:name":"Kirseb\u00e6rhuset b\u00f8rnehave",
    "wof:placetype":"venue"
},
  "geometry": {"coordinates":[12.3928127289,55.6727218628],"type":"Point"}
}