{
  "type": "Feature",
  "properties": {
    "addr:full":"Nyl\u00f8kkevej 6 Silkeborg Danmark 8600",
    "addr:housenumber":"6",
    "addr:postcode":"8600",
    "addr:street":"Nylokkevej",
    "iso:country":"DK",
    "sg:address":"Nyl\u00f8kkevej 6",
    "sg:city":"Silkeborg",
    "sg:orig_category":"Murermestre",
    "sg:phone":"+45 86 82 28 20",
    "sg:postcode":"8600",
    "sg:province":"Danmark",
    "wof:name":"Pedersen, Poul E.",
    "wof:placetype":"venue"
},
  "geometry": {"coordinates":[9.6266708374,56.1564102173],"type":"Point"}
}