{
  "type": "Feature",
  "properties": {
    "addr:full":"Lokalfmd.: Ole Hillebrand J\u00f8rgensen, Bakkehaven 26 Kalundborg Danmark 4400",
    "addr:housenumber":"26",
    "addr:postcode":"4400",
    "addr:street":"Ole Hillebrand Jorgensen Bakkehaven",
    "iso:country":"DK",
    "sg:address":"Lokalfmd.: Ole Hillebrand J\u00f8rgensen, Bakkehaven 26",
    "sg:city":"Kalundborg",
    "sg:orig_category":"Faglige organisationer og foreninger",
    "sg:phone":"+45 59 51 40 92",
    "sg:postcode":"4400",
    "sg:province":"Danmark",
    "wof:name":"BYG Nordvestsj\u00e6lland, Kreds 3",
    "wof:placetype":"venue"
},
  "geometry": {"coordinates":[11.0934085846,55.6797485352],"type":"Point"}
}