{
  "type": "Feature",
  "properties": {
    "iso:country":"DK",
    "sg:address":"Torvet 3",
    "sg:city":"Gram",
    "sg:orig_category":"Apoteker og -udsalg",
    "sg:phone":"+45 74 82 15 15",
    "sg:postcode":"6510",
    "sg:province":"Danmark",
    "wof:name":"Gram Apotek",
    "wof:placetype":"venue"
},
  "geometry": {"coordinates":[9.0483074188,55.2882804871],"type":"Point"}
}