{
  "type": "Feature",
  "properties": {
    "addr:full":"S\u00f8ndertoften 228 Taastrup Danmark 2630",
    "addr:housenumber":"228",
    "addr:postcode":"2630",
    "addr:street":"Sondertoften",
    "iso:country":"DK",
    "sg:address":"S\u00f8ndertoften 228",
    "sg:city":"Taastrup",
    "sg:orig_category":"Naturopater",
    "sg:phone":"+45 43 52 79 88",
    "sg:postcode":"2630",
    "sg:province":"Danmark",
    "wof:name":"JEF-Data",
    "wof:placetype":"venue"
},
  "geometry": {"coordinates":[12.3112745285,55.6409301758],"type":"Point"}
}