{
  "type": "Feature",
  "properties": {
    "addr:full":"Vermundsgade 40 B, 1. K\u00f8benhavn \u00d8 Danmark 2100",
    "addr:housenumber":"40 b 1",
    "addr:postcode":"2100",
    "addr:street":"Vermundsgade;Kobenhavn O Danmark",
    "iso:country":"DK",
    "sg:address":"Vermundsgade 40 B, 1.",
    "sg:city":"K\u00f8benhavn \u00d8",
    "sg:orig_category":"Fotografer",
    "sg:phone":"+45 39 27 44 12",
    "sg:postcode":"2100",
    "sg:province":"Danmark",
    "sg:website":"www.jesperwestley.com",
    "wof:name":"Westley J\u00f8rgensen, Jesper",
    "wof:placetype":"venue"
},
  "geometry": {"coordinates":[77.2480392456,14.1354398727],"type":"Point"}
}