{
  "type": "Feature",
  "properties": {
    "iso:country":"DK",
    "sg:address":"Fmd.: Bent Greniman, Hviddingvej 16",
    "sg:city":"R\u00f8dovre",
    "sg:orig_category":"Grundejerforeninger",
    "sg:phone":"+45 36 70 05 85",
    "sg:postcode":"2610",
    "sg:province":"Danmark",
    "wof:name":"Hendriksholm Grundejerforening",
    "wof:placetype":"venue"
},
  "geometry": {"coordinates":[10.6992139816,61.1027755737],"type":"Point"}
}