{
  "type": "Feature",
  "properties": {
    "addr:full":"Nyborggade 12 Copenhagen 2100",
    "addr:housenumber":"12",
    "addr:postcode":"2100",
    "addr:street":"Nyborggade",
    "iso:country":"DK",
    "sg:address":"Nyborggade 12",
    "sg:city":"Copenhagen",
    "sg:classifiers":[
        {
            "category":"Professional",
            "subcategory":"Computer Services",
            "type":"Services"
        }
    ],
    "sg:postcode":"2100",
    "sg:website":"http://www.casaswap.com",
    "wof:name":"CasaSwap.com",
    "wof:placetype":"venue"
},
  "geometry": {"coordinates":[12.579332,55.709743],"type":"Point"}
}