{
  "type": "Feature",
  "properties": {
    "iso:country":"DK",
    "sg:address":"Hallelevvej 30 A, Hallelev",
    "sg:city":"Slagelse",
    "sg:orig_category":"Kommunale folkeskoler",
    "sg:phone":"+45 58 29 18 00",
    "sg:postcode":"4200",
    "sg:province":"Danmark",
    "sg:website":"www.vestermoseskole.dk",
    "wof:name":"Vestermose Skole",
    "wof:placetype":"venue"
},
  "geometry": {"coordinates":[11.3569850922,55.4050865173],"type":"Point"}
}