{
  "type": "Feature",
  "properties": {
    "addr:full":"Uglerupvej 31, Uglerup Holb\u00e6k Danmark 4300",
    "addr:housenumber":"31",
    "addr:postcode":"4300",
    "addr:street":"Uglerupvej",
    "iso:country":"DK",
    "sg:address":"Uglerupvej 31, Uglerup",
    "sg:city":"Holb\u00e6k",
    "sg:orig_category":"Gaveartikler",
    "sg:phone":"+45 59 46 16 23",
    "sg:postcode":"4300",
    "sg:province":"Danmark",
    "wof:name":"Tusen\u00e6s Kunsth\u00e5ndv\u00e6rk",
    "wof:placetype":"venue"
},
  "geometry": {"coordinates":[11.7100753784,55.717956543],"type":"Point"}
}