{
  "type": "Feature",
  "properties": {
    "addr:full":"Br\u00f8ndby Havnevej 20 Hvidovre Danmark 2650",
    "addr:housenumber":"20",
    "addr:postcode":"2650",
    "addr:street":"Brondby Havnevej",
    "iso:country":"DK",
    "sg:address":"Br\u00f8ndby Havnevej 20",
    "sg:city":"Hvidovre",
    "sg:classifiers":[
        {
            "category":"Restaurant",
            "type":"Food & Drink"
        }
    ],
    "sg:phone":"+45 43 73 68 00",
    "sg:postcode":"2650",
    "sg:province":"Danmark",
    "sg:website":"albatrossen.dk",
    "wof:name":"Restaurant Albatrossen",
    "wof:placetype":"venue"
},
  "geometry": {"coordinates":[12.442243576,55.6098175049],"type":"Point"}
}