{
  "type": "Feature",
  "properties": {
    "addr:full":"S\u00f8ndergade 15 A Kolding Danmark 6000",
    "addr:housenumber":"15 a",
    "addr:postcode":"6000",
    "addr:street":"Sondergade",
    "iso:country":"DK",
    "sg:address":"S\u00f8ndergade 15 A",
    "sg:city":"Kolding",
    "sg:orig_category":"Slagter og viktualie",
    "sg:phone":"+45 75 52 03 56",
    "sg:postcode":"6000",
    "sg:province":"Danmark",
    "wof:name":"Peters K\u00f8d",
    "wof:placetype":"venue"
},
  "geometry": {"coordinates":[9.4729337692,55.4874687195],"type":"Point"}
}