{
  "type": "Feature",
  "properties": {
    "addr:full":"K\u00f8bmagergade 7 - 9 K\u00f8benhavn Danmark 1150",
    "addr:housenumber":"7 9",
    "addr:postcode":"1150",
    "addr:street":"Kobmagergade",
    "iso:country":"DK",
    "sg:address":"K\u00f8bmagergade 7 - 9",
    "sg:city":"K\u00f8benhavn",
    "sg:classifiers":[
        {
            "category":"Professional",
            "subcategory":"Computer Services",
            "type":"Services"
        }
    ],
    "sg:phone":"+45 70 28 28 70",
    "sg:postcode":"1150",
    "sg:province":"Danmark",
    "sg:tags":[
        "edb",
        "-",
        "software"
    ],
    "sg:website":"www.sas.com/dk",
    "wof:name":"SAS Institute A/S",
    "wof:placetype":"venue"
},
  "geometry": {"coordinates":[76.3070983887,14.277130127],"type":"Point"}
}