{
  "type": "Feature",
  "properties": {
    "addr:full":"Tavlek\u00e6rsvej 71 Hvidovre Danmark 2650",
    "addr:housenumber":"71",
    "addr:postcode":"2650",
    "addr:street":"Tavlekaersvej",
    "iso:country":"DK",
    "sg:address":"Tavlek\u00e6rsvej 71",
    "sg:city":"Hvidovre",
    "sg:orig_category":"Non-Classified Establishments",
    "sg:phone":"+45 36 49 88 40",
    "sg:postcode":"2650",
    "sg:province":"Danmark",
    "wof:name":"Nelosoft",
    "wof:placetype":"venue"
},
  "geometry": {"coordinates":[12.4895458221,55.6296081543],"type":"Point"}
}