{
  "type": "Feature",
  "properties": {
    "addr:full":"Hellerupvej 11 Hellerup Danmark 2900",
    "addr:housenumber":"11",
    "addr:postcode":"2900",
    "addr:street":"Hellerupvej",
    "iso:country":"DK",
    "sg:address":"Hellerupvej 11",
    "sg:city":"Hellerup",
    "sg:orig_category":"Legestuer",
    "sg:phone":"+45 39 62 65 46",
    "sg:postcode":"2900",
    "sg:province":"Danmark",
    "wof:name":"Bernadotteskolens Legestue",
    "wof:placetype":"venue"
},
  "geometry": {"coordinates":[12.5725593567,55.7316627502],"type":"Point"}
}