{
  "type": "Feature",
  "properties": {
    "addr:full":"Wilhelm Marstrands Gade 20 K\u00f8benhavn \u00d8 Danmark 2100",
    "addr:housenumber":"20",
    "addr:postcode":"2100",
    "addr:street":"Wilhelm Marstrands Gade;O",
    "iso:country":"DK",
    "sg:address":"Wilhelm Marstrands Gade 20",
    "sg:city":"K\u00f8benhavn \u00d8",
    "sg:orig_category":"Psykologer, praktiserende",
    "sg:phone":"+45 35 38 88 71",
    "sg:postcode":"2100",
    "sg:province":"Danmark",
    "sg:website":"www.fobiskoleaften.dk",
    "wof:name":"ForbiskoleAften",
    "wof:placetype":"venue"
},
  "geometry": {"coordinates":[11.589050293,57.8867683411],"type":"Point"}
}