{
  "type": "Feature",
  "properties": {
    "addr:full":"Bakkesvinget 9, Esb\u00f8nderup Gr\u00e6sted Danmark 3230",
    "addr:housenumber":"9",
    "addr:postcode":"3230",
    "addr:street":"Bakkesvinget",
    "iso:country":"DK",
    "sg:address":"Bakkesvinget 9, Esb\u00f8nderup",
    "sg:city":"Gr\u00e6sted",
    "sg:orig_category":"Arkitekter",
    "sg:phone":"+45 48 39 07 16",
    "sg:postcode":"3230",
    "sg:province":"Danmark",
    "wof:name":"Arkitektstudio 90",
    "wof:placetype":"venue"
},
  "geometry": {"coordinates":[-78.6975326538,35.0151481628],"type":"Point"}
}