{
  "type": "Feature",
  "properties": {
    "addr:full":"Nyvej 22 Gadstrup Danmark 4621",
    "addr:housenumber":"22",
    "addr:postcode":"4621",
    "addr:street":"Nyvej",
    "iso:country":"DK",
    "sg:address":"Nyvej 22",
    "sg:city":"Gadstrup",
    "sg:orig_category":"Malermestre",
    "sg:phone":"+45 46 19 05 71",
    "sg:postcode":"4621",
    "sg:province":"Danmark",
    "wof:name":"Eriksen, Jan",
    "wof:placetype":"venue"
},
  "geometry": {"coordinates":[12.0932788849,55.5715866089],"type":"Point"}
}