{
  "type": "Feature",
  "properties": {
    "addr:full":"Markv\u00e6nget 32 Aars Danmark 9600",
    "addr:housenumber":"32",
    "addr:postcode":"9600",
    "addr:street":"Markvaenget",
    "iso:country":"DK",
    "sg:address":"Markv\u00e6nget 32",
    "sg:city":"Aars",
    "sg:orig_category":"Autoreparation og -service",
    "sg:phone":"+45 98 62 33 33",
    "sg:postcode":"9600",
    "sg:province":"Danmark",
    "wof:name":"Gunnars Taxi",
    "wof:placetype":"venue"
},
  "geometry": {"coordinates":[9.5170412064,56.8031692505],"type":"Point"}
}