{
  "type": "Feature",
  "properties": {
    "addr:full":"Centervej 13 Auning Danmark 8963",
    "addr:housenumber":"13",
    "addr:postcode":"8963",
    "addr:street":"Centervej",
    "iso:country":"DK",
    "sg:address":"Centervej 13",
    "sg:city":"Auning",
    "sg:orig_category":"Apoteker og -udsalg",
    "sg:phone":"+45 86 48 43 48",
    "sg:postcode":"8963",
    "sg:province":"Danmark",
    "wof:name":"Auning Apoteksudsalg",
    "wof:placetype":"venue"
},
  "geometry": {"coordinates":[10.3748397827,56.431224823],"type":"Point"}
}