{
  "type": "Feature",
  "properties": {
    "addr:full":"S\u00f8ndermarksvej 409 Billund Danmark 7190",
    "addr:housenumber":"409",
    "addr:postcode":"7190",
    "addr:street":"Sondermarksvej",
    "iso:country":"DK",
    "sg:address":"S\u00f8ndermarksvej 409",
    "sg:city":"Billund",
    "sg:orig_category":"Psykologer, praktiserende",
    "sg:phone":"+45 75 33 14 70",
    "sg:postcode":"7190",
    "sg:province":"Danmark",
    "wof:name":"Bruhn, Bodil",
    "wof:placetype":"venue"
},
  "geometry": {"coordinates":[9.107375145,55.7262153625],"type":"Point"}
}