{
  "type": "Feature",
  "properties": {
    "addr:full":"Fmd.: Rigmor Nissen, S\u00f8m\u00e6rkevej 40, Stenbjerg Snedsted Danmark 7752",
    "addr:housenumber":"40",
    "addr:postcode":"7752",
    "addr:street":"Somaerkevej;Stenbjerg",
    "iso:country":"DK",
    "sg:address":"Fmd.: Rigmor Nissen, S\u00f8m\u00e6rkevej 40, Stenbjerg",
    "sg:city":"Snedsted",
    "sg:orig_category":"Museer",
    "sg:phone":"+45 97 93 82 28",
    "sg:postcode":"7752",
    "sg:province":"Danmark",
    "wof:name":"Stenbjerg Redningsmuseum",
    "wof:placetype":"venue"
},
  "geometry": {"coordinates":[8.5276002884,56.8460388184],"type":"Point"}
}