{
  "type": "Feature",
  "properties": {
    "addr:full":"Kl\u00f8vervej 44 Kolding Danmark 6000",
    "addr:housenumber":"44",
    "addr:postcode":"6000",
    "addr:street":"Klovervej",
    "iso:country":"DK",
    "sg:address":"Kl\u00f8vervej 44",
    "sg:city":"Kolding",
    "sg:orig_category":"Plejehjem",
    "sg:phone":"+45 76 34 74 44",
    "sg:postcode":"6000",
    "sg:province":"Danmark",
    "wof:name":"Kl\u00f8verh\u00f8j plejecenter",
    "wof:placetype":"venue"
},
  "geometry": {"coordinates":[9.5010147095,55.4842796326],"type":"Point"}
}