{
  "type": "Feature",
  "properties": {
    "iso:country":"DK",
    "sg:address":"Nordre Fasanvej 99",
    "sg:city":"Frederiksberg",
    "sg:orig_category":"INGENI\u00c3\u02dcRER",
    "sg:phone":"+45 38 88 30 01",
    "sg:postcode":"2000",
    "sg:province":"Danmark",
    "wof:name":"Schmidt, Peter",
    "wof:placetype":"venue"
},
  "geometry": {"coordinates":[12.5282688141,55.6890106201],"type":"Point"}
}