{
  "type": "Feature",
  "properties": {
    "addr:full":"S\u00e5derupvej 1 Ullerslev Danmark 5540",
    "addr:housenumber":"1",
    "addr:postcode":"5540",
    "addr:street":"Saaderupvej",
    "iso:country":"DK",
    "sg:address":"S\u00e5derupvej 1",
    "sg:city":"Ullerslev",
    "sg:orig_category":"Planteskoler",
    "sg:phone":"+45 65 35 11 57",
    "sg:postcode":"5540",
    "sg:province":"Danmark",
    "wof:name":"S\u00e5derup Planteskole",
    "wof:placetype":"venue"
},
  "geometry": {"coordinates":[10.6677951813,55.3239936829],"type":"Point"}
}