{
  "type": "Feature",
  "properties": {
    "addr:full":"Egebjerg Bygade 34 Ballerup Danmark 2750",
    "addr:housenumber":"34",
    "addr:postcode":"2750",
    "addr:street":"Egebjerg Bygade",
    "iso:country":"DK",
    "sg:address":"Egebjerg Bygade 34",
    "sg:city":"Ballerup",
    "sg:orig_category":"\u00c3\u2020ldrecentre",
    "sg:postcode":"2750",
    "sg:province":"Danmark",
    "wof:name":"Egely",
    "wof:placetype":"venue"
},
  "geometry": {"coordinates":[12.3778533936,55.7470474243],"type":"Point"}
}