{
  "type": "Feature",
  "properties": {
    "iso:country":"DK",
    "sg:address":"T\u00f8mmergangen 7",
    "sg:city":"Ribe",
    "sg:classifiers":[
        {
            "category":"Banks & Credit Unions",
            "subcategory":"Bank",
            "type":"Services"
        }
    ],
    "sg:phone":"+45 75 42 29 11",
    "sg:postcode":"6760",
    "sg:province":"Danmark",
    "sg:tags":[
        "banker"
    ],
    "wof:name":"Sydbank",
    "wof:placetype":"venue"
},
  "geometry": {"coordinates":[8.767334938,55.3309555054],"type":"Point"}
}