{
  "type": "Feature",
  "properties": {
    "addr:full":"Barrit Langgade 190 Barrit Danmark 7150",
    "addr:housenumber":"190",
    "addr:postcode":"7150",
    "addr:street":"Barrit Langgade",
    "iso:country":"DK",
    "sg:address":"Barrit Langgade 190",
    "sg:city":"Barrit",
    "sg:orig_category":"Maskinfabrikker",
    "sg:phone":"+45 76 82 12 22",
    "sg:postcode":"7150",
    "sg:province":"Danmark",
    "sg:website":"www.stenhoj.dk",
    "wof:name":"Stenh\u00f8j A/S",
    "wof:placetype":"venue"
},
  "geometry": {"coordinates":[9.9016532898,55.7001914978],"type":"Point"}
}