{
  "type": "Feature",
  "properties": {
    "addr:full":"Englandsvej 19 Nyk\u00f8bing Danmark 4800",
    "addr:housenumber":"19",
    "addr:postcode":"4800",
    "addr:street":"Englandsvej",
    "iso:country":"DK",
    "sg:address":"Englandsvej 19",
    "sg:city":"Nyk\u00f8bing",
    "sg:classifiers":[
        {
            "category":"Building & Trades",
            "subcategory":"Construction",
            "type":"Services"
        }
    ],
    "sg:phone":"+45 54 85 14 01",
    "sg:postcode":"4800",
    "sg:province":"Danmark",
    "sg:tags":[
        "renovation"
    ],
    "wof:name":"Rotox",
    "wof:placetype":"venue"
},
  "geometry": {"coordinates":[-114.0768203735,46.4432411194],"type":"Point"}
}