{
  "type": "Feature",
  "properties": {
    "addr:full":"Parkvej 9 Sandved Danmark 4262",
    "addr:housenumber":"9",
    "addr:postcode":"4262",
    "addr:street":"Parkvej",
    "iso:country":"DK",
    "sg:address":"Parkvej 9",
    "sg:city":"Sandved",
    "sg:orig_category":"Vikarbureauer",
    "sg:phone":"+45 55 46 16 19",
    "sg:postcode":"4262",
    "sg:province":"Danmark",
    "wof:name":"Fuglebjerg Vikarbureau",
    "wof:placetype":"venue"
},
  "geometry": {"coordinates":[11.5207948685,55.2621383667],"type":"Point"}
}