{
  "type": "Feature",
  "properties": {
    "addr:full":"S\u00f8ndergade 15 Horsens Danmark 8700",
    "addr:housenumber":"15",
    "addr:postcode":"8700",
    "addr:street":"Sondergade",
    "iso:country":"DK",
    "sg:address":"S\u00f8ndergade 15",
    "sg:city":"Horsens",
    "sg:orig_category":"Boghandlere",
    "sg:phone":"+45 75 61 01 44",
    "sg:postcode":"8700",
    "sg:province":"Danmark",
    "wof:name":"Papyrus",
    "wof:placetype":"venue"
},
  "geometry": {"coordinates":[9.8473072052,55.8620605469],"type":"Point"}
}