{
  "type": "Feature",
  "properties": {
    "addr:full":"B\u00e6kmojenvej 31 Frederikshavn Danmark 9900",
    "addr:housenumber":"31",
    "addr:postcode":"9900",
    "addr:street":"Baekmojenvej",
    "iso:country":"DK",
    "sg:address":"B\u00e6kmojenvej 31",
    "sg:city":"Frederikshavn",
    "sg:orig_category":"Malermestre",
    "sg:phone":"+45 24 40 71 43",
    "sg:postcode":"9900",
    "sg:province":"Danmark",
    "sg:website":"www.schjunk.dk",
    "wof:name":"Johansen - Peter Schjunk, Niels Erik",
    "wof:placetype":"venue"
},
  "geometry": {"coordinates":[10.471072197,57.4565467834],"type":"Point"}
}