{
  "type": "Feature",
  "properties": {
    "iso:country":"DK",
    "sg:address":"Hjelmevej 1, Henne Strand",
    "sg:city":"Henne",
    "sg:orig_category":"Sportsartikler",
    "sg:phone":"+45 75 25 60 70",
    "sg:postcode":"6854",
    "sg:province":"Danmark",
    "wof:name":"West Wind Sport & Mode",
    "wof:placetype":"venue"
},
  "geometry": {"coordinates":[8.2223901749,55.7346534729],"type":"Point"}
}