{
  "type": "Feature",
  "properties": {
    "addr:full":"Fmd.: Kathrine Stensgaard, \u00c5kildevej 15, \u00d8. Skerninge Vester Skerninge Danmark 5762",
    "addr:housenumber":"15 o.",
    "addr:postcode":"5762",
    "addr:street":"Aakildevej;Skerninge",
    "iso:country":"DK",
    "sg:address":"Fmd.: Kathrine Stensgaard, \u00c5kildevej 15, \u00d8. Skerninge",
    "sg:city":"Vester Skerninge",
    "sg:orig_category":"Kulturelle foreninger",
    "sg:phone":"+45 62 24 13 15",
    "sg:postcode":"5762",
    "sg:province":"Danmark",
    "wof:name":"Foreningen Norden, Svendborg afd.",
    "wof:placetype":"venue"
},
  "geometry": {"coordinates":[10.5008449554,55.070400238],"type":"Point"}
}