{
  "type": "Feature",
  "properties": {
    "addr:full":"Fmd.: Svenning Andersen, N\u00f8rredigevej 120, Gj\u00f8l Aabybro Danmark 9440",
    "addr:housenumber":"120",
    "addr:postcode":"9440",
    "addr:street":"Norredigevej;Gjol",
    "iso:country":"DK",
    "sg:address":"Fmd.: Svenning Andersen, N\u00f8rredigevej 120, Gj\u00f8l",
    "sg:city":"Aabybro",
    "sg:orig_category":"Folkedans",
    "sg:phone":"+45 98 27 72 54",
    "sg:postcode":"9440",
    "sg:province":"Danmark",
    "wof:name":"Gj\u00f8l Folkedanserforening",
    "wof:placetype":"venue"
},
  "geometry": {"coordinates":[9.7341356277,57.1588287354],"type":"Point"}
}