{
  "type": "Feature",
  "properties": {
    "addr:full":"Mogenstrup Parkvej 10, Mogenstrup N\u00e6stved Danmark 4700",
    "addr:housenumber":"10",
    "addr:postcode":"4700",
    "addr:street":"Mogenstrup Parkvej",
    "iso:country":"DK",
    "sg:address":"Mogenstrup Parkvej 10, Mogenstrup",
    "sg:city":"N\u00e6stved",
    "sg:orig_category":"Tandklinikker, Kommunale",
    "sg:phone":"+45 55 76 19 29",
    "sg:postcode":"4700",
    "sg:province":"Danmark",
    "wof:name":"B\u00f8rnetandklinikken p\u00e5 Mogenstrupskolen",
    "wof:placetype":"venue"
},
  "geometry": {"coordinates":[11.7542486191,55.2315444946],"type":"Point"}
}