{
  "type": "Feature",
  "properties": {
    "addr:full":"Magleparken 218 Ballerup Danmark 2750",
    "addr:housenumber":"218",
    "addr:postcode":"2750",
    "addr:street":"Magleparken",
    "iso:country":"DK",
    "sg:address":"Magleparken 218",
    "sg:city":"Ballerup",
    "sg:orig_category":"Fritidshjem",
    "sg:phone":"+45 44 77 22 79",
    "sg:postcode":"2750",
    "sg:province":"Danmark",
    "wof:name":"Asg\u00e5rd, Fritidshjemmet",
    "wof:placetype":"venue"
},
  "geometry": {"coordinates":[12.3627271652,55.7126197815],"type":"Point"}
}