{
  "type": "Feature",
  "properties": {
    "addr:full":"Kongensgade 25, st Esbjerg Danmark 6700",
    "addr:housenumber":"25",
    "addr:postcode":"6700",
    "addr:street":"Kongensgade",
    "iso:country":"DK",
    "sg:address":"Kongensgade 25, st",
    "sg:city":"Esbjerg",
    "sg:orig_category":"Bagere",
    "sg:phone":"+45 75 13 41 07",
    "sg:postcode":"6700",
    "sg:province":"Danmark",
    "wof:name":"Baker Street",
    "wof:placetype":"venue"
},
  "geometry": {"coordinates":[8.456905,55.465221],"type":"Point"}
}