{
  "type": "Feature",
  "properties": {
    "addr:full":"\u00d8stre Stationsvej 6 Rungsted Kyst Danmark 2960",
    "addr:housenumber":"6",
    "addr:postcode":"2960",
    "addr:street":"Ostre Stationsvej",
    "iso:country":"DK",
    "sg:address":"\u00d8stre Stationsvej 6",
    "sg:city":"Rungsted Kyst",
    "sg:orig_category":"Blomsterhandlere",
    "sg:phone":"+45 45 86 00 79",
    "sg:postcode":"2960",
    "sg:province":"Danmark",
    "wof:name":"Gitte's Blomster",
    "wof:placetype":"venue"
},
  "geometry": {"coordinates":[12.5320911407,55.8823394775],"type":"Point"}
}