{
  "type": "Feature",
  "properties": {
    "iso:country":"DK",
    "sg:address":"Sivlandv\u00e6nget 11 B, Hjallese",
    "sg:city":"Odense S",
    "sg:orig_category":"Hospital, udstyr til",
    "sg:phone":"+45 63 12 90 00",
    "sg:postcode":"5260",
    "sg:province":"Danmark",
    "sg:website":"www.parscientific.com",
    "wof:name":"PAR SCIENTIFIC A/S",
    "wof:placetype":"venue"
},
  "geometry": {"coordinates":[10.3157806396,55.3122825623],"type":"Point"}
}