{
  "type": "Feature",
  "properties": {
    "addr:full":"Hans Baghs Vej 6 Skagen Danmark 9990",
    "addr:housenumber":"6",
    "addr:postcode":"9990",
    "addr:street":"Hans Baghs Vej",
    "iso:country":"DK",
    "sg:address":"Hans Baghs Vej 6",
    "sg:city":"Skagen",
    "sg:orig_category":"Servicestationer",
    "sg:phone":"+45 98 44 64 38",
    "sg:postcode":"9990",
    "sg:province":"Danmark",
    "wof:name":"Q8 Service",
    "wof:placetype":"venue"
},
  "geometry": {"coordinates":[10.57970047,57.7172584534],"type":"Point"}
}