{
  "type": "Feature",
  "properties": {
    "iso:country":"DK",
    "sg:address":"Odinsvej 2",
    "sg:city":"Struer",
    "sg:orig_category":"Autoreparation og -service",
    "sg:phone":"+45 97 85 48 47",
    "sg:postcode":"7600",
    "sg:province":"Danmark",
    "wof:name":"Madsen, Peter Grimstrup",
    "wof:placetype":"venue"
},
  "geometry": {"coordinates":[8.604681015,56.4774055481],"type":"Point"}
}