{
  "type": "Feature",
  "properties": {
    "iso:country":"DK",
    "sg:address":"Astrupvej 3, S\u00e6dding",
    "sg:city":"Skjern",
    "sg:orig_category":"Efterskoler",
    "sg:phone":"+45 97 36 22 00",
    "sg:postcode":"6900",
    "sg:province":"Danmark",
    "wof:name":"S\u00e6dding Efterskole",
    "wof:placetype":"venue"
},
  "geometry": {"coordinates":[8.492972374,55.9485740662],"type":"Point"}
}