{
  "type": "Feature",
  "properties": {
    "addr:full":"v/ Svend Elsborg, Byvej 30 Gudbjerg Danmark 5892",
    "addr:housenumber":"30",
    "addr:postcode":"5892",
    "addr:street":"Elsborg Byvej",
    "iso:country":"DK",
    "sg:address":"v/ Svend Elsborg, Byvej 30",
    "sg:city":"Gudbjerg",
    "sg:orig_category":"Hobbybetonede foreninger",
    "sg:phone":"+45 62 25 16 02",
    "sg:postcode":"5892",
    "sg:province":"Danmark",
    "wof:name":"Gudme Billard Klub",
    "wof:placetype":"venue"
},
  "geometry": {"coordinates":[10.6627902985,55.1708755493],"type":"Point"}
}