{
  "type": "Feature",
  "properties": {
    "iso:country":"DK",
    "sg:address":"Vestervang 8",
    "sg:city":"F\u00e5rvang",
    "sg:orig_category":"Kontorservice",
    "sg:phone":"+45 86 87 11 28",
    "sg:postcode":"8882",
    "sg:province":"Danmark",
    "wof:name":"Christensen, Vibeke Maria Juul",
    "wof:placetype":"venue"
},
  "geometry": {"coordinates":[9.7256641388,56.2693710327],"type":"Point"}
}