{
  "type": "Feature",
  "properties": {
    "iso:country":"DK",
    "sg:address":"N\u00f8rrebrogade 20, 1.",
    "sg:city":"K\u00f8benhavn N",
    "sg:orig_category":"Dag- og distriktsblade",
    "sg:phone":"+45 35 39 73 31",
    "sg:postcode":"2200",
    "sg:province":"Danmark",
    "wof:name":"P\u00e5Gaden",
    "wof:placetype":"venue"
},
  "geometry": {"coordinates":[-76.4168395996,37.452419281],"type":"Point"}
}