{
  "type": "Feature",
  "properties": {
    "addr:full":"Fmd.: Anders Bertelsen, Engvej 152, 2.tv. K\u00f8benhavn S Danmark 2300",
    "addr:housenumber":"152",
    "addr:postcode":"2.tv;2300",
    "addr:street":"Engvej;Kobenhavn S Danmark",
    "iso:country":"DK",
    "sg:address":"Fmd.: Anders Bertelsen, Engvej 152, 2.tv.",
    "sg:city":"K\u00f8benhavn S",
    "sg:orig_category":"Hobbybetonede foreninger",
    "sg:phone":"+45 32 55 07 14",
    "sg:postcode":"2300",
    "sg:province":"Danmark",
    "sg:website":"www.geocities.com/hearhant/hills/6313",
    "wof:name":"Amager Fugleforening",
    "wof:placetype":"venue"
},
  "geometry": {"coordinates":[-78.1299133301,36.7267417908],"type":"Point"}
}