{
  "type": "Feature",
  "properties": {
    "addr:full":"\u00d8stergade 1 Fjerritslev Danmark 9690",
    "addr:housenumber":"1",
    "addr:postcode":"9690",
    "addr:street":"Ostergade",
    "iso:country":"DK",
    "sg:address":"\u00d8stergade 1",
    "sg:city":"Fjerritslev",
    "sg:orig_category":"Museer",
    "sg:phone":"+45 98 21 31 92",
    "sg:postcode":"9690",
    "sg:province":"Danmark",
    "wof:name":"Fjerritslev Bryggeri- og Egnsmuseum",
    "wof:placetype":"venue"
},
  "geometry": {"coordinates":[9.2660322189,57.088306427],"type":"Point"}
}