{
  "type": "Feature",
  "properties": {
    "addr:full":"B\u00f8rnehave og vuggestue, Agervej 36 Kalundborg Danmark 4400",
    "addr:housenumber":"36",
    "addr:postcode":"4400",
    "addr:street":"Agervej",
    "iso:country":"DK",
    "sg:address":"B\u00f8rnehave og vuggestue, Agervej 36",
    "sg:city":"Kalundborg",
    "sg:orig_category":"Integrerede institutioner",
    "sg:phone":"+45 59 51 18 44",
    "sg:postcode":"4400",
    "sg:province":"Danmark",
    "wof:name":"Agervej, b\u00f8rnehus",
    "wof:placetype":"venue"
},
  "geometry": {"coordinates":[11.0934085846,55.6797485352],"type":"Point"}
}