{
  "type": "Feature",
  "properties": {
    "addr:full":"Nordborggade 20 \u00c5rhus C Danmark 8000",
    "addr:housenumber":"20",
    "addr:postcode":"8000",
    "addr:street":"Nordborggade",
    "iso:country":"DK",
    "sg:address":"Nordborggade 20",
    "sg:city":"\u00c5rhus C",
    "sg:orig_category":"Kiosker",
    "sg:phone":"+45 86 14 46 22",
    "sg:postcode":"8000",
    "sg:province":"Danmark",
    "wof:name":"Langen\u00e6s-Kiosken",
    "wof:placetype":"venue"
},
  "geometry": {"coordinates":[4.717400074,49.7588005066],"type":"Point"}
}