{
  "type": "Feature",
  "properties": {
    "iso:country":"DK",
    "sg:address":"Maglemervej 18",
    "sg:city":"Maribo",
    "sg:orig_category":"Skilte",
    "sg:phone":"+45 54 75 55 11",
    "sg:postcode":"4930",
    "sg:province":"Danmark",
    "wof:name":"KB Skilte",
    "wof:placetype":"venue"
},
  "geometry": {"coordinates":[11.500207901,54.7792015076],"type":"Point"}
}