{
  "type": "Feature",
  "properties": {
    "addr:full":"Pantholm 42 Slagelse Danmark 4200",
    "addr:housenumber":"42",
    "addr:postcode":"4200",
    "addr:street":"Pantholm",
    "iso:country":"DK",
    "sg:address":"Pantholm 42",
    "sg:city":"Slagelse",
    "sg:orig_category":"Ejendomshandel",
    "sg:phone":"+45 58 50 60 60",
    "sg:postcode":"4200",
    "sg:province":"Danmark",
    "wof:name":"Kjelkvist, Ejvind",
    "wof:placetype":"venue"
},
  "geometry": {"coordinates":[11.3858633041,55.4077644348],"type":"Point"}
}