{
  "type": "Feature",
  "properties": {
    "addr:full":"Ravnsvej 3, Hegedal Str Glesborg Danmark 8585",
    "addr:housenumber":"3",
    "addr:postcode":"8585",
    "addr:street":"Ravnsvej;Hegedal Str Glesborg Danmark",
    "iso:country":"DK",
    "sg:address":"Ravnsvej 3, Hegedal Str",
    "sg:city":"Glesborg",
    "sg:orig_category":"Kiosker",
    "sg:phone":"+45 86 31 77 50",
    "sg:postcode":"8585",
    "sg:province":"Danmark",
    "sg:website":"www.fdm.dk",
    "wof:name":"Hegedal Strand Kiosk",
    "wof:placetype":"venue"
},
  "geometry": {"coordinates":[10.5884723663,56.5124320984],"type":"Point"}
}