{
  "type": "Feature",
  "properties": {
    "addr:full":"Tretommervej 31 Risskov Danmark 8240",
    "addr:housenumber":"31",
    "addr:postcode":"8240",
    "addr:street":"Tretommervej",
    "iso:country":"DK",
    "sg:address":"Tretommervej 31",
    "sg:city":"Risskov",
    "sg:orig_category":"Erhvervsskoler",
    "sg:phone":"+45 86 17 89 33",
    "sg:postcode":"8240",
    "sg:province":"Danmark",
    "sg:website":"www.vl.dk",
    "wof:name":"Vejlby Landbrugsskole",
    "wof:placetype":"venue"
},
  "geometry": {"coordinates":[10.2225465775,56.1889686584],"type":"Point"}
}