{
  "type": "Feature",
  "properties": {
    "addr:full":"K\u00f8gevej 40 Ringsted Danmark 4100",
    "addr:housenumber":"40",
    "addr:postcode":"4100",
    "addr:street":"Kogevej",
    "iso:country":"DK",
    "sg:address":"K\u00f8gevej 40",
    "sg:city":"Ringsted",
    "sg:orig_category":"Supermarkeder",
    "sg:phone":"+45 57 61 64 17",
    "sg:postcode":"4100",
    "sg:province":"Danmark",
    "wof:name":"Super Best 4'eren",
    "wof:placetype":"venue"
},
  "geometry": {"coordinates":[11.8032894135,55.4431266785],"type":"Point"}
}