{
  "type": "Feature",
  "properties": {
    "addr:full":"Kredsleder: Maren Stausholm, Grundtvigsvej 20 A Holstebro Danmark 7500",
    "addr:housenumber":"20 a",
    "addr:postcode":"7500",
    "addr:street":"Grundtvigsvej",
    "iso:country":"DK",
    "sg:address":"Kredsleder: Maren Stausholm, Grundtvigsvej 20 A",
    "sg:city":"Holstebro",
    "sg:orig_category":"Beredskabsforbund",
    "sg:phone":"+45 97 42 61 40",
    "sg:postcode":"7500",
    "sg:province":"Danmark",
    "wof:name":"Beredskabs-Forbundet Holstebro",
    "wof:placetype":"venue"
},
  "geometry": {"coordinates":[8.620258,56.362522],"type":"Point"}
}