{
  "type": "Feature",
  "properties": {
    "iso:country":"DK",
    "sg:address":"v/ Erling Steffensen, Lundek\u00e6rsvej 40, Bellinge",
    "sg:city":"Odense SV",
    "sg:orig_category":"Musik og sang",
    "sg:phone":"+45 65 96 15 16",
    "sg:postcode":"5250",
    "sg:province":"Danmark",
    "wof:name":"Herrekoret Arion",
    "wof:placetype":"venue"
},
  "geometry": {"coordinates":[10.3153953552,55.3362998962],"type":"Point"}
}