{
  "type": "Feature",
  "properties": {
    "iso:country":"DK",
    "sg:address":"\u00d8stergade 18, Postboks 154",
    "sg:city":"Vojens",
    "sg:orig_category":"Dag- og distriktsblade",
    "sg:phone":"+45 73 24 10 40",
    "sg:postcode":"6500",
    "sg:province":"Danmark",
    "wof:name":"Vojens Ugeavis",
    "wof:placetype":"venue"
},
  "geometry": {"coordinates":[9.2987146378,55.2457237244],"type":"Point"}
}