{
  "type": "Feature",
  "properties": {
    "addr:full":"Dannebrogsgade 20 \u00c5rhus C Danmark 8000",
    "addr:housenumber":"20",
    "addr:postcode":"8000",
    "addr:street":"Dannebrogsgade",
    "iso:country":"DK",
    "sg:address":"Dannebrogsgade 20",
    "sg:city":"\u00c5rhus C",
    "sg:orig_category":"Psykologer, praktiserende",
    "sg:phone":"+45 86 18 05 44",
    "sg:postcode":"8000",
    "sg:province":"Danmark",
    "sg:website":"www.bramsen-hendil.dk",
    "wof:name":"Bramsen & Hendil",
    "wof:placetype":"venue"
},
  "geometry": {"coordinates":[10.1944389343,56.1457595825],"type":"Point"}
}