{
  "type": "Feature",
  "properties": {
    "iso:country":"DK",
    "sg:address":"Hjallesevej 209",
    "sg:city":"Odense M",
    "sg:orig_category":"Bagere",
    "sg:phone":"+45 66 17 67 07",
    "sg:postcode":"5230",
    "sg:province":"Danmark",
    "wof:name":"Folkebos Conditori",
    "wof:placetype":"venue"
},
  "geometry": {"coordinates":[10.395512,55.374813],"type":"Point"}
}