{
  "type": "Feature",
  "properties": {
    "addr:full":"Hovedgaden 66 B Tisvildeleje Danmark 3220",
    "addr:housenumber":"66 b",
    "addr:postcode":"3220",
    "addr:street":"Hovedgaden",
    "iso:country":"DK",
    "sg:address":"Hovedgaden 66 B",
    "sg:city":"Tisvildeleje",
    "sg:classifiers":[
        {
            "category":"Restaurant",
            "type":"Food & Drink"
        }
    ],
    "sg:phone":"+45 48 70 70 02",
    "sg:postcode":"3220",
    "sg:province":"Danmark",
    "sg:website":"www.olifanten.dk",
    "wof:name":"Olifanten",
    "wof:placetype":"venue"
},
  "geometry": {"coordinates":[12.0722160339,56.0593986511],"type":"Point"}
}