{
  "type": "Feature",
  "properties": {
    "iso:country":"DK",
    "sg:address":"Skolegade 20",
    "sg:city":"Ruds Vedby",
    "sg:orig_category":"Skolefritidsordninger",
    "sg:phone":"+45 58 26 16 89",
    "sg:postcode":"4291",
    "sg:province":"Danmark",
    "wof:name":"Ruds-Vedby Skolefritidsordning",
    "wof:placetype":"venue"
},
  "geometry": {"coordinates":[11.3721351624,55.5372962952],"type":"Point"}
}