{
  "type": "Feature",
  "properties": {
    "addr:full":"Grusbakken 14  Gentofte Danmark 2820",
    "addr:housenumber":"14",
    "addr:postcode":"2820",
    "addr:street":"Grusbakken",
    "iso:country":"DK",
    "sg:address":"Grusbakken 14 ",
    "sg:city":"Gentofte",
    "sg:classifiers":[
        {
            "category":"Shopping",
            "subcategory":"Jewelry",
            "type":"Retail Goods"
        }
    ],
    "sg:phone":"+45 45 26 91 00",
    "sg:postcode":"2820",
    "sg:province":"Danmark",
    "sg:tags":[
        "jewellery"
    ],
    "wof:name":"HENNING ST\u00c6HR A/S",
    "wof:placetype":"venue"
},
  "geometry": {"coordinates":[12.5015449524,55.7586898804],"type":"Point"}
}