{
  "type": "Feature",
  "properties": {
    "addr:full":"Paludan-M\u00fcllers Vej 48 \u00c5rhus N Danmark 8200",
    "addr:housenumber":"48",
    "addr:postcode":"8200",
    "addr:street":"Paludan-Muellers Vej",
    "iso:country":"DK",
    "sg:address":"Paludan-M\u00fcllers Vej 48",
    "sg:city":"\u00c5rhus N",
    "sg:orig_category":"Faglige organisationer og foreninger",
    "sg:phone":"+45 87 39 18 88",
    "sg:postcode":"8200",
    "sg:province":"Danmark",
    "wof:name":"Forbundet Tr\u00e6-Industri-Byg, Afdeling 12 \u00c5rhus",
    "wof:placetype":"venue"
},
  "geometry": {"coordinates":[4.9393601418,49.7092018127],"type":"Point"}
}