{
  "type": "Feature",
  "properties": {
    "addr:full":"\u00d8stergade 84 Assens Danmark 5610",
    "addr:housenumber":"84",
    "addr:postcode":"5610",
    "addr:street":"Ostergade",
    "iso:country":"DK",
    "sg:address":"\u00d8stergade 84",
    "sg:city":"Assens",
    "sg:classifiers":[
        {
            "category":"Restaurant",
            "type":"Food & Drink"
        }
    ],
    "sg:phone":"+45 64 71 22 63",
    "sg:postcode":"5610",
    "sg:province":"Danmark",
    "wof:name":"Vestfyn, Restaurant",
    "wof:placetype":"venue"
},
  "geometry": {"coordinates":[9.9016361237,55.2701263428],"type":"Point"}
}