{
  "type": "Feature",
  "properties": {
    "iso:country":"DK",
    "sg:address":"Jernbanegade 2",
    "sg:city":"Outrup",
    "sg:orig_category":"HOTELS: OG MOTELLER",
    "sg:phone":"+45 75 25 18 00",
    "sg:postcode":"6855",
    "sg:province":"Danmark",
    "wof:name":"Outrup, Hotel",
    "wof:placetype":"venue"
},
  "geometry": {"coordinates":[8.3451051712,55.7182388306],"type":"Point"}
}