{
  "type": "Feature",
  "properties": {
    "iso:country":"DK",
    "sg:address":"Gentoftegade 26",
    "sg:city":"Gentofte",
    "sg:orig_category":"Blomsterhandlere",
    "sg:phone":"+45 39 65 11 44",
    "sg:postcode":"2820",
    "sg:province":"Danmark",
    "wof:name":"Gentofte Blomster",
    "wof:placetype":"venue"
},
  "geometry": {"coordinates":[12.5409832001,55.7496681213],"type":"Point"}
}