{
  "type": "Feature",
  "properties": {
    "addr:full":"Merkurvej 11, S\u00f8ften Hinnerup Danmark 8382",
    "addr:housenumber":"11",
    "addr:postcode":"8382",
    "addr:street":"Merkurvej;Soften",
    "iso:country":"DK",
    "sg:address":"Merkurvej 11, S\u00f8ften",
    "sg:city":"Hinnerup",
    "sg:orig_category":"Psykologer, praktiserende",
    "sg:phone":"+45 86 98 55 12",
    "sg:postcode":"8382",
    "sg:province":"Danmark",
    "wof:name":"Broberg, Leif H\u00f8j",
    "wof:placetype":"venue"
},
  "geometry": {"coordinates":[10.0614156723,56.2650604248],"type":"Point"}
}