{
  "type": "Feature",
  "properties": {
    "iso:country":"DK",
    "sg:address":"H. P. Hanssens Gade 30",
    "sg:city":"Aabenraa",
    "sg:orig_category":"Servicestationer",
    "sg:phone":"+45 74 62 40 24",
    "sg:postcode":"6200",
    "sg:province":"Danmark",
    "wof:name":"Q8 Service",
    "wof:placetype":"venue"
},
  "geometry": {"coordinates":[9.4206352234,55.0459747314],"type":"Point"}
}