{
  "type": "Feature",
  "properties": {
    "addr:full":"Nordgrundvej 18, Raml\u00f8se Helsinge Danmark 3200",
    "addr:housenumber":"18",
    "addr:postcode":"3200",
    "addr:street":"Nordgrundvej;Ramlose",
    "iso:country":"DK",
    "sg:address":"Nordgrundvej 18, Raml\u00f8se",
    "sg:city":"Helsinge",
    "sg:orig_category":"Psykoterapi",
    "sg:phone":"+45 48 71 36 27",
    "sg:postcode":"3200",
    "sg:province":"Danmark",
    "wof:name":"Taksdal, Ren\u00e8",
    "wof:placetype":"venue"
},
  "geometry": {"coordinates":[12.196846962,56.0224456787],"type":"Point"}
}