{
  "type": "Feature",
  "properties": {
    "addr:full":"Skanderborgvej 234 Viby Danmark 8260",
    "addr:housenumber":"234",
    "addr:postcode":"8260",
    "addr:street":"Skanderborgvej",
    "iso:country":"DK",
    "sg:address":"Skanderborgvej 234",
    "sg:city":"Viby",
    "sg:orig_category":"Forsikringer",
    "sg:phone":"+45 86 28 88 11",
    "sg:postcode":"8260",
    "sg:province":"Danmark",
    "wof:name":"Aon Pensionsr\u00e5dgivning A/S",
    "wof:placetype":"venue"
},
  "geometry": {"coordinates":[10.1387176514,56.118270874],"type":"Point"}
}