{
  "type": "Feature",
  "properties": {
    "addr:full":"Borgergade 9 Silkeborg Danmark 8600",
    "addr:housenumber":"9",
    "addr:postcode":"8600",
    "addr:street":"Borgergade",
    "iso:country":"DK",
    "sg:address":"Borgergade 9",
    "sg:city":"Silkeborg",
    "sg:orig_category":"Cykler",
    "sg:phone":"+45 86 82 09 55",
    "sg:postcode":"8600",
    "sg:province":"Danmark",
    "sg:website":"www.fricykler.dk",
    "wof:name":"Fri Cykler",
    "wof:placetype":"venue"
},
  "geometry": {"coordinates":[9.5547981262,56.1764602661],"type":"Point"}
}