{
  "type": "Feature",
  "properties": {
    "addr:full":"Fmd.: S\u00f8ren Bork-Pedersen, M\u00f8lleparken 162 Billund Danmark 7190",
    "addr:housenumber":"162",
    "addr:postcode":"7190",
    "addr:street":"Molleparken",
    "iso:country":"DK",
    "sg:address":"Fmd.: S\u00f8ren Bork-Pedersen, M\u00f8lleparken 162",
    "sg:city":"Billund",
    "sg:orig_category":"Kulturelle foreninger",
    "sg:phone":"+45 75 33 15 05",
    "sg:postcode":"7190",
    "sg:province":"Danmark",
    "wof:name":"Folkeuniversitetet i Billund/Vorbasse",
    "wof:placetype":"venue"
},
  "geometry": {"coordinates":[9.1138372421,55.7316017151],"type":"Point"}
}