{
  "type": "Feature",
  "properties": {
    "addr:full":"Hovedgaden 12, Lyngsb\u00e6k Ebeltoft Danmark 8400",
    "addr:housenumber":"12",
    "addr:postcode":"8400",
    "addr:street":"Hovedgaden",
    "iso:country":"DK",
    "sg:address":"Hovedgaden 12, Lyngsb\u00e6k",
    "sg:city":"Ebeltoft",
    "sg:classifiers":[
        {
            "category":"Restaurant",
            "type":"Food & Drink"
        }
    ],
    "sg:phone":"+45 86 36 25 24",
    "sg:postcode":"8400",
    "sg:province":"Danmark",
    "wof:name":"Jydepotten",
    "wof:placetype":"venue"
},
  "geometry": {"coordinates":[10.6778745651,56.199798584],"type":"Point"}
}