{
  "type": "Feature",
  "properties": {
    "addr:full":"Emerholtsvej 15 Kolding Danmark 6000",
    "addr:housenumber":"15",
    "addr:postcode":"6000",
    "addr:street":"Emerholtsvej",
    "iso:country":"DK",
    "sg:address":"Emerholtsvej 15",
    "sg:city":"Kolding",
    "sg:classifiers":[
        {
            "category":"Sports & Exercise",
            "subcategory":"Sports Center",
            "type":"Entertainment"
        }
    ],
    "sg:phone":"+45 75 52 37 93",
    "sg:postcode":"6000",
    "sg:province":"Danmark",
    "sg:tags":[
        "golf"
    ],
    "wof:name":"Kolding Golf Klub",
    "wof:placetype":"venue"
},
  "geometry": {"coordinates":[9.4677906036,55.5134506226],"type":"Point"}
}