{
  "type": "Feature",
  "properties": {
    "iso:country":"DK",
    "sg:address":"Torvet 22",
    "sg:city":"Horsens",
    "sg:orig_category":"Helseprodukter",
    "sg:phone":"+45 75 62 46 88",
    "sg:postcode":"8700",
    "sg:province":"Danmark",
    "wof:name":"Matas-Materialisten",
    "wof:placetype":"venue"
},
  "geometry": {"coordinates":[9.8526649475,55.862071991],"type":"Point"}
}