{
  "type": "Feature",
  "properties": {
    "addr:full":"Teglb\u00e6kvej 20 Hasselager Danmark 8361",
    "addr:housenumber":"20",
    "addr:postcode":"8361",
    "addr:street":"Teglbaekvej",
    "iso:country":"DK",
    "sg:address":"Teglb\u00e6kvej 20",
    "sg:city":"Hasselager",
    "sg:orig_category":"Konsulentvirksomheder",
    "sg:phone":"+45 72 20 38 00",
    "sg:postcode":"8361",
    "sg:province":"Danmark",
    "sg:website":"www.teknologisk.dk",
    "wof:name":"Teknologisk Institut, Murv\u00e6rk",
    "wof:placetype":"venue"
},
  "geometry": {"coordinates":[10.0980548859,56.1017990112],"type":"Point"}
}