{
  "type": "Feature",
  "properties": {
    "addr:full":"Sdr. Landevej 2, Nylars R\u00f8nne Danmark 3700",
    "addr:housenumber":"2",
    "addr:postcode":"3700",
    "addr:street":"Sdr. Landevej;Ronne",
    "iso:country":"DK",
    "sg:address":"Sdr. Landevej 2, Nylars",
    "sg:city":"R\u00f8nne",
    "sg:orig_category":"Diners transportables",
    "sg:phone":"+45 56 91 34 15",
    "sg:postcode":"3700",
    "sg:province":"Danmark",
    "wof:name":"Nyker Madservice",
    "wof:placetype":"venue"
},
  "geometry": {"coordinates":[14.6975498199,55.0993003845],"type":"Point"}
}