{
  "type": "Feature",
  "properties": {
    "iso:country":"DK",
    "sg:address":"Fmd.: Ellen B. Th\u00f8gersen, Landevejen 45, S\u00f8nderho",
    "sg:city":"Fan\u00f8",
    "sg:orig_category":"Kulturelle foreninger",
    "sg:phone":"+45 75 16 40 45",
    "sg:postcode":"6720",
    "sg:province":"Danmark",
    "wof:name":"Fan\u00f8 Gr\u00e6nseforening",
    "wof:placetype":"venue"
},
  "geometry": {"coordinates":[-119.1350784302,36.3733062744],"type":"Point"}
}