{
  "type": "Feature",
  "properties": {
    "addr:full":"Industrivej 26 A Padborg Danmark 6330",
    "addr:housenumber":"26 a",
    "addr:postcode":"6330",
    "addr:street":"Industrivej",
    "iso:country":"DK",
    "sg:address":"Industrivej 26 A",
    "sg:city":"Padborg",
    "sg:orig_category":"Spedition",
    "sg:phone":"+45 74 67 39 85",
    "sg:postcode":"6330",
    "sg:province":"Danmark",
    "sg:website":"www.hkjessen.dk",
    "wof:name":"Jessen A/S, H. K.",
    "wof:placetype":"venue"
},
  "geometry": {"coordinates":[9.3447113037,54.836391449],"type":"Point"}
}