{
  "type": "Feature",
  "properties": {
    "addr:full":"Bagerv\u00e6nget 9 Barrit Danmark 7150",
    "addr:housenumber":"9",
    "addr:postcode":"7150",
    "addr:street":"Bagervaenget",
    "iso:country":"DK",
    "sg:address":"Bagerv\u00e6nget 9",
    "sg:city":"Barrit",
    "sg:orig_category":"Processtyring",
    "sg:phone":"+45 75 69 18 78",
    "sg:postcode":"7150",
    "sg:province":"Danmark",
    "wof:name":"Uni-Tech",
    "wof:placetype":"venue"
},
  "geometry": {"coordinates":[9.9013900757,55.7076950073],"type":"Point"}
}