{
  "type": "Feature",
  "properties": {
    "iso:country":"DK",
    "sg:address":"Brordrupvej 15, Kamstrup",
    "sg:city":"Roskilde",
    "sg:orig_category":"Hestepensioner",
    "sg:phone":"+45 40 79 20 79",
    "sg:postcode":"4000",
    "sg:province":"Danmark",
    "wof:name":"Rytters Hestepension",
    "wof:placetype":"venue"
},
  "geometry": {"coordinates":[12.0909376144,55.6404838562],"type":"Point"}
}