{
  "type": "Feature",
  "properties": {
    "addr:full":"v/ Vagn Kristensen, K\u00e6ret 19, Veders\u00f8 Ulfborg Danmark 6990",
    "addr:housenumber":"19",
    "addr:postcode":"6990",
    "addr:street":"Vederso",
    "iso:country":"DK",
    "sg:address":"v/ Vagn Kristensen, K\u00e6ret 19, Veders\u00f8",
    "sg:city":"Ulfborg",
    "sg:orig_category":"\u00c3\u02dcvrig fritidsundervisning",
    "sg:phone":"+45 97 33 11 10",
    "sg:postcode":"6990",
    "sg:province":"Danmark",
    "wof:name":"Veders\u00f8 Borgerforening",
    "wof:placetype":"venue"
},
  "geometry": {"coordinates":[8.3210029602,56.2727661133],"type":"Point"}
}