{
  "type": "Feature",
  "properties": {
    "addr:full":"Lyngvej 18 Jyderup Danmark 4450",
    "addr:housenumber":"18",
    "addr:postcode":"4450",
    "addr:street":"Lyngvej",
    "iso:country":"DK",
    "sg:address":"Lyngvej 18",
    "sg:city":"Jyderup",
    "sg:orig_category":"Metalvarefabrikker",
    "sg:phone":"+45 59 20 80 37",
    "sg:postcode":"4450",
    "sg:province":"Danmark",
    "sg:website":"www.lmp-jyderup.dk",
    "wof:name":"Larsen Metal & Pakkeri ApS",
    "wof:placetype":"venue"
},
  "geometry": {"coordinates":[11.409778595,55.6595077515],"type":"Point"}
}