{
  "type": "Feature",
  "properties": {
    "addr:full":"Dorphs Alle 10 Taastrup Danmark 2630",
    "addr:housenumber":"10",
    "addr:postcode":"2630",
    "addr:street":"Dorphs Alle",
    "iso:country":"DK",
    "sg:address":"Dorphs Alle 10",
    "sg:city":"Taastrup",
    "sg:orig_category":"Jordemodercentre",
    "sg:phone":"+45 43 99 50 82",
    "sg:postcode":"2630",
    "sg:province":"Danmark",
    "wof:name":"Jordemodercentret.",
    "wof:placetype":"venue"
},
  "geometry": {"coordinates":[12.3034858704,55.6488685608],"type":"Point"}
}