{
  "type": "Feature",
  "properties": {
    "addr:full":"Bygaden 20 A, Asserballe Augustenborg Danmark 6440",
    "addr:housenumber":"20 a",
    "addr:postcode":"6440",
    "addr:street":"Bygaden;Asserballe",
    "iso:country":"DK",
    "sg:address":"Bygaden 20 A, Asserballe",
    "sg:city":"Augustenborg",
    "sg:orig_category":"Biblioteker",
    "sg:phone":"+45 74 47 35 26",
    "sg:postcode":"6440",
    "sg:province":"Danmark",
    "wof:name":"Asserballe Bibliotek",
    "wof:placetype":"venue"
},
  "geometry": {"coordinates":[9.8727750778,54.9459037781],"type":"Point"}
}