{
  "type": "Feature",
  "properties": {
    "addr:full":"Staupudevej 24, Aasum Odense N\u00d8 Danmark 5240",
    "addr:housenumber":"24",
    "addr:postcode":"5240",
    "addr:street":"Staupudevej;Aasum",
    "iso:country":"DK",
    "sg:address":"Staupudevej 24, Aasum",
    "sg:city":"Odense N\u00d8",
    "sg:orig_category":"Hundepensioner",
    "sg:phone":"+45 66 10 40 20",
    "sg:postcode":"5240",
    "sg:province":"Danmark",
    "sg:website":"home19.inet.tele.dk/holmens",
    "wof:name":"Holmens Hunde- & Kattepension",
    "wof:placetype":"venue"
},
  "geometry": {"coordinates":[10.444185257,55.4261131287],"type":"Point"}
}