{
  "type": "Feature",
  "properties": {
    "iso:country":"DK",
    "sg:address":"Slotsholmsgade 1, 3.",
    "sg:city":"K\u00f8benhavn",
    "sg:orig_category":"Statslige direktorater og styrelser",
    "sg:phone":"+45 33 92 61 00",
    "sg:postcode":"1216",
    "sg:province":"Danmark",
    "sg:website":"www.ligestillingsminister.dk",
    "wof:name":"Minister for ligestilling",
    "wof:placetype":"venue"
},
  "geometry": {"coordinates":[12.5853004456,55.674331665],"type":"Point"}
}