{
  "type": "Feature",
  "properties": {
    "iso:country":"DK",
    "sg:address":"Sydhavnsvej 8",
    "sg:city":"Frederikshavn",
    "sg:orig_category":"Cafeterier",
    "sg:phone":"+45 98 43 11 77",
    "sg:postcode":"9900",
    "sg:province":"Danmark",
    "wof:name":"Havne-super Bistro",
    "wof:placetype":"venue"
},
  "geometry": {"coordinates":[10.538318634,57.4362373352],"type":"Point"}
}