{
  "type": "Feature",
  "properties": {
    "addr:full":"R\u00f8gindvej 19 Lem Danmark 6940",
    "addr:housenumber":"19",
    "addr:postcode":"6940",
    "addr:street":"Rogindvej",
    "iso:country":"DK",
    "sg:address":"R\u00f8gindvej 19",
    "sg:city":"Lem",
    "sg:orig_category":"Autoreparation og -service",
    "sg:phone":"+45 97 34 30 67",
    "sg:postcode":"6940",
    "sg:province":"Danmark",
    "wof:name":"H\u00f8jmark Autov\u00e6rksted",
    "wof:placetype":"venue"
},
  "geometry": {"coordinates":[8.3939809799,56.054069519],"type":"Point"}
}