{
  "type": "Feature",
  "properties": {
    "iso:country":"DK",
    "sg:address":"Fmd.: Henning Falkesgaard, Valmuev\u00e6nget 12, Gr\u00f8nnemose",
    "sg:city":"Aarup",
    "sg:orig_category":"\u00c3\u02dcvrige foreninger",
    "sg:phone":"+45 64 43 15 90",
    "sg:postcode":"5560",
    "sg:province":"Danmark",
    "wof:name":"Foreningen til Dyrenes beskyttelse i Danmark",
    "wof:placetype":"venue"
},
  "geometry": {"coordinates":[10.0490245819,55.3808059692],"type":"Point"}
}