{
  "type": "Feature",
  "properties": {
    "addr:full":"Stenh\u00f8jv\u00e6nget 1 Helsinge Danmark 3200",
    "addr:housenumber":"1",
    "addr:postcode":"3200",
    "addr:street":"Stenhojvaenget",
    "iso:country":"DK",
    "sg:address":"Stenh\u00f8jv\u00e6nget 1",
    "sg:city":"Helsinge",
    "sg:orig_category":"Personaleudvikling",
    "sg:phone":"+45 48 79 71 99",
    "sg:postcode":"3200",
    "sg:province":"Danmark",
    "wof:name":"Outdoor Adventure",
    "wof:placetype":"venue"
},
  "geometry": {"coordinates":[12.196846962,56.0224456787],"type":"Point"}
}