{
  "type": "Feature",
  "properties": {
    "addr:full":"Glimsholtvej 669 Sindal Danmark 9870",
    "addr:housenumber":"669",
    "addr:postcode":"9870",
    "addr:street":"Glimsholtvej",
    "iso:country":"DK",
    "sg:address":"Glimsholtvej 669",
    "sg:city":"Sindal",
    "sg:orig_category":"Autoreparation og -service",
    "sg:phone":"+45 98 47 36 53",
    "sg:postcode":"9870",
    "sg:province":"Danmark",
    "wof:name":"LM Auto",
    "wof:placetype":"venue"
},
  "geometry": {"coordinates":[10.2807302475,57.40599823],"type":"Point"}
}