{
  "type": "Feature",
  "properties": {
    "addr:full":"Pr\u00e6st: Kirsten Dissing Overg\u00e5rd, Torsh\u00f8jv\u00e6nget 15, Bering Hasselager Danmark 8361",
    "addr:housenumber":"15",
    "addr:postcode":"8361",
    "addr:street":"Bering",
    "iso:country":"DK",
    "sg:address":"Pr\u00e6st: Kirsten Dissing Overg\u00e5rd, Torsh\u00f8jv\u00e6nget 15, Bering",
    "sg:city":"Hasselager",
    "sg:orig_category":"Valg- og frimenigheder",
    "sg:phone":"+45 86 92 12 37",
    "sg:postcode":"8361",
    "sg:province":"Danmark",
    "wof:name":"Bering Valgmenighed",
    "wof:placetype":"venue"
},
  "geometry": {"coordinates":[10.094414711,56.105014801],"type":"Point"}
}