{
  "type": "Feature",
  "properties": {
    "addr:full":"R\u00f8nne Alle 2 Sunds Danmark 7451",
    "addr:housenumber":"2",
    "addr:postcode":"7451",
    "addr:street":"Ronne Alle",
    "iso:country":"DK",
    "sg:address":"R\u00f8nne Alle 2",
    "sg:city":"Sunds",
    "sg:orig_category":"Lokalarkiver",
    "sg:phone":"+45 97 14 11 71",
    "sg:postcode":"7451",
    "sg:province":"Danmark",
    "wof:name":"Sunds Lokalhistoriske Arkiv",
    "wof:placetype":"venue"
},
  "geometry": {"coordinates":[9.0142536163,56.2063102722],"type":"Point"}
}