{
  "type": "Feature",
  "properties": {
    "addr:full":"Nordholmen 2 Hvidovre Danmark 2650",
    "addr:housenumber":"2",
    "addr:postcode":"2650",
    "addr:street":"Nordholmen",
    "iso:country":"DK",
    "sg:address":"Nordholmen 2",
    "sg:city":"Hvidovre",
    "sg:classifiers":[
        {
            "category":"Harbor",
            "type":"Transportation"
        }
    ],
    "sg:phone":"+45 36 34 47 88",
    "sg:postcode":"2650",
    "sg:province":"Danmark",
    "sg:tags":[
        "shipping"
    ],
    "wof:name":"Scandinavian Shipping Consultants",
    "wof:placetype":"venue"
},
  "geometry": {"coordinates":[12.4700689316,55.6124763489],"type":"Point"}
}