{
  "type": "Feature",
  "properties": {
    "addr:full":"Glentevej 39 K\u00f8ge Danmark 4600",
    "addr:housenumber":"39",
    "addr:postcode":"4600",
    "addr:street":"Glentevej",
    "iso:country":"DK",
    "sg:address":"Glentevej 39",
    "sg:city":"K\u00f8ge",
    "sg:orig_category":"Stenhuggere",
    "sg:phone":"+45 56 65 77 16",
    "sg:postcode":"4600",
    "sg:province":"Danmark",
    "wof:name":"K\u00f8ge Stenhuggeri",
    "wof:placetype":"venue"
},
  "geometry": {"coordinates":[10.0347900391,56.4765014648],"type":"Point"}
}