{
  "type": "Feature",
  "properties": {
    "addr:full":"K\u00f8benhavnsvej 44 B K\u00f8ge Danmark 4600",
    "addr:housenumber":"44 b",
    "addr:postcode":"4600",
    "addr:street":"Kobenhavnsvej",
    "iso:country":"DK",
    "sg:address":"K\u00f8benhavnsvej 44 B",
    "sg:city":"K\u00f8ge",
    "sg:orig_category":"Grillbarer",
    "sg:phone":"+45 56 63 20 40",
    "sg:postcode":"4600",
    "sg:province":"Danmark",
    "wof:name":"Syvm\u00f8llens Grill",
    "wof:placetype":"venue"
},
  "geometry": {"coordinates":[77.2480392456,14.1354398727],"type":"Point"}
}