{
  "type": "Feature",
  "properties": {
    "addr:full":"Mosetoften 20 Hedensted Danmark 8722",
    "addr:housenumber":"20",
    "addr:postcode":"8722",
    "addr:street":"Mosetoften",
    "iso:country":"DK",
    "sg:address":"Mosetoften 20",
    "sg:city":"Hedensted",
    "sg:orig_category":"Maskinfabrikker",
    "sg:phone":"+45 75 89 16 99",
    "sg:postcode":"8722",
    "sg:province":"Danmark",
    "sg:website":"www.jwl-pneumatic.com",
    "wof:name":"JWL Maskin- og Plastfabrik",
    "wof:placetype":"venue"
},
  "geometry": {"coordinates":[9.6979961395,55.7788314819],"type":"Point"}
}