{
  "type": "Feature",
  "properties": {
    "addr:full":"Sverigesvej 11 Slagelse Danmark 4200",
    "addr:housenumber":"11",
    "addr:postcode":"4200",
    "addr:street":"Sverigesvej",
    "iso:country":"DK",
    "sg:address":"Sverigesvej 11",
    "sg:city":"Slagelse",
    "sg:classifiers":[
        {
            "category":"Building & Trades",
            "subcategory":"Construction",
            "type":"Services"
        }
    ],
    "sg:phone":"+45 58 50 14 18",
    "sg:postcode":"4200",
    "sg:province":"Danmark",
    "sg:tags":[
        "ventilation"
    ],
    "wof:name":"HRS Luftteknik A/S",
    "wof:placetype":"venue"
},
  "geometry": {"coordinates":[11.3710737228,55.4051055908],"type":"Point"}
}