{
  "type": "Feature",
  "properties": {
    "iso:country":"DK",
    "sg:address":"Nygade 21",
    "sg:city":"Ringk\u00f8bing",
    "sg:orig_category":"Biografer",
    "sg:phone":"+45 97 32 61 44",
    "sg:postcode":"6950",
    "sg:province":"Danmark",
    "wof:name":"Ringk\u00f8bing Bio",
    "wof:placetype":"venue"
},
  "geometry": {"coordinates":[8.250795,56.087833],"type":"Point"}
}