{
  "type": "Feature",
  "properties": {
    "iso:country":"DK",
    "sg:address":"Kattesund 24",
    "sg:city":"Horsens",
    "sg:orig_category":"Vaskerier",
    "sg:phone":"+45 75 62 77 72",
    "sg:postcode":"8700",
    "sg:province":"Danmark",
    "wof:name":"S\u00f8strene Larsen's Vaskeri",
    "wof:placetype":"venue"
},
  "geometry": {"coordinates":[9.8545255661,55.8623008728],"type":"Point"}
}