{
  "type": "Feature",
  "properties": {
    "addr:full":"Hedeg\u00e5rdsvej 11, Boulstrup Odder Danmark 8300",
    "addr:housenumber":"11",
    "addr:postcode":"8300",
    "addr:street":"Hedegaardsvej;Boulstrup",
    "iso:country":"DK",
    "sg:address":"Hedeg\u00e5rdsvej 11, Boulstrup",
    "sg:city":"Odder",
    "sg:orig_category":"Beslag",
    "sg:phone":"+45 87 81 74 00",
    "sg:postcode":"8300",
    "sg:province":"Danmark",
    "wof:name":"BMF Bygningsbeslag A/S",
    "wof:placetype":"venue"
},
  "geometry": {"coordinates":[10.1497612,55.9733161926],"type":"Point"}
}