{
  "type": "Feature",
  "properties": {
    "addr:full":"Reberbanegade 3, Amager Centret K\u00f8benhavn S Danmark 2300",
    "addr:housenumber":"3",
    "addr:postcode":"2300",
    "addr:street":"Reberbanegade;Amager Centret Kobenhavn S Danmark",
    "iso:country":"DK",
    "sg:address":"Reberbanegade 3, Amager Centret",
    "sg:city":"K\u00f8benhavn S",
    "sg:orig_category":"Vagtbureauer",
    "sg:phone":"+45 32 95 22 35",
    "sg:postcode":"2300",
    "sg:province":"Danmark",
    "sg:website":"www.acvagt.dk",
    "wof:name":"AC Vagt ApS",
    "wof:placetype":"venue"
},
  "geometry": {"coordinates":[12.6044902802,55.6631202698],"type":"Point"}
}