{
  "type": "Feature",
  "properties": {
    "iso:country":"DK",
    "sg:address":"Holstebrovej 141",
    "sg:city":"Viborg",
    "sg:orig_category":"Servicestationer",
    "sg:phone":"+45 86 64 71 42",
    "sg:postcode":"8800",
    "sg:province":"Danmark",
    "wof:name":"Ravnstrup Shell Service/Mercasol Center",
    "wof:placetype":"venue"
},
  "geometry": {"coordinates":[9.3050670624,56.4498214722],"type":"Point"}
}