{
  "type": "Feature",
  "properties": {
    "iso:country":"DK",
    "sg:address":"Pasteursvej 1",
    "sg:city":"Silkeborg",
    "sg:orig_category":"Maskinfabrikker",
    "sg:phone":"+45 89 22 89 22",
    "sg:postcode":"8600",
    "sg:province":"Danmark",
    "wof:name":"APV",
    "wof:placetype":"venue"
},
  "geometry": {"coordinates":[9.5671958923,56.2017860413],"type":"Point"}
}