{
  "type": "Feature",
  "properties": {
    "addr:full":"Greve Strandvej 24 Greve Danmark 2670",
    "addr:housenumber":"24",
    "addr:postcode":"2670",
    "addr:street":"Greve Strandvej",
    "iso:country":"DK",
    "sg:address":"Greve Strandvej 24",
    "sg:city":"Greve",
    "sg:orig_category":"Aviser",
    "sg:phone":"+45 43 90 44 22",
    "sg:postcode":"2670",
    "sg:province":"Danmark",
    "sg:website":"www.sydkysten.dk",
    "wof:name":"Dagbladet",
    "wof:placetype":"venue"
},
  "geometry": {"coordinates":[12.3097743988,55.5821456909],"type":"Point"}
}