{
  "type": "Feature",
  "properties": {
    "addr:full":"Vesterbro 72 Odense C Danmark 5000",
    "addr:housenumber":"72",
    "addr:postcode":"5000",
    "addr:street":"Vesterbro",
    "iso:country":"DK",
    "sg:address":"Vesterbro 72",
    "sg:city":"Odense C",
    "sg:classifiers":[
        {
            "category":"Restaurant",
            "type":"Food & Drink"
        }
    ],
    "sg:phone":"+45 66 12 70 65",
    "sg:postcode":"5000",
    "sg:province":"Danmark",
    "wof:name":"West-end",
    "wof:placetype":"venue"
},
  "geometry": {"coordinates":[10.3745002747,55.3940200806],"type":"Point"}
}