{
  "type": "Feature",
  "properties": {
    "iso:country":"DK",
    "sg:address":"Skelvej 29",
    "sg:city":"Assens",
    "sg:orig_category":"Skolefritidsordninger",
    "sg:phone":"+45 64 71 21 13",
    "sg:postcode":"5610",
    "sg:province":"Danmark",
    "wof:name":"Skelvejsskolens Fritidsordning",
    "wof:placetype":"venue"
},
  "geometry": {"coordinates":[9.900592804,55.2731208801],"type":"Point"}
}