{
  "type": "Feature",
  "properties": {
    "addr:full":"N\u00f8rregade 52 Odense C Danmark 5000",
    "addr:housenumber":"52",
    "addr:postcode":"5000",
    "addr:street":"Norregade",
    "iso:country":"DK",
    "sg:address":"N\u00f8rregade 52",
    "sg:city":"Odense C",
    "sg:orig_category":"Non-Classified Establishments",
    "sg:phone":"+45 66 12 51 52",
    "sg:postcode":"5000",
    "sg:province":"Danmark",
    "wof:name":"Producenten",
    "wof:placetype":"venue"
},
  "geometry": {"coordinates":[10.3886451721,55.4001731873],"type":"Point"}
}