{
  "type": "Feature",
  "properties": {
    "addr:full":"Store Kongensgade 49 K\u00f8benhavn Danmark 1264",
    "addr:housenumber":"49;1264",
    "addr:street":"Store Kongensgade",
    "iso:country":"DK",
    "sg:address":"Store Kongensgade 49",
    "sg:city":"K\u00f8benhavn",
    "sg:orig_category":"Advokater",
    "sg:phone":"+45 33 15 15 32",
    "sg:postcode":"1264",
    "sg:province":"Danmark",
    "wof:name":"Steffensen, Michael",
    "wof:placetype":"venue"
},
  "geometry": {"coordinates":[12.5923995972,55.6865005493],"type":"Point"}
}