{
  "type": "Feature",
  "properties": {
    "addr:full":"Silkeborgvej 67 Horsens Danmark 8700",
    "addr:housenumber":"67",
    "addr:postcode":"8700",
    "addr:street":"Silkeborgvej",
    "iso:country":"DK",
    "sg:address":"Silkeborgvej 67",
    "sg:city":"Horsens",
    "sg:orig_category":"Blomsterhandlere",
    "sg:phone":"+45 75 62 26 46",
    "sg:postcode":"8700",
    "sg:province":"Danmark",
    "sg:website":"www.fwj&post4.tele.dk",
    "wof:name":"Johansens Planteskole",
    "wof:placetype":"venue"
},
  "geometry": {"coordinates":[9.8066625595,55.8776931763],"type":"Point"}
}