{
  "type": "Feature",
  "properties": {
    "addr:full":"Bredgade 2 Bording Danmark 7441",
    "addr:housenumber":"2",
    "addr:postcode":"7441",
    "addr:street":"Bredgade",
    "iso:country":"DK",
    "sg:address":"Bredgade 2",
    "sg:city":"Bording",
    "sg:orig_category":"HOTELS: OG MOTELLER",
    "sg:phone":"+45 86 86 10 21",
    "sg:postcode":"7441",
    "sg:province":"Danmark",
    "wof:name":"Bording Hotel",
    "wof:placetype":"venue"
},
  "geometry": {"coordinates":[9.2766952515,56.1465415955],"type":"Point"}
}