{
  "type": "Feature",
  "properties": {
    "addr:full":"Valdemarsgade 6 B Vordingborg Danmark 4760",
    "addr:housenumber":"6 b",
    "addr:postcode":"4760",
    "addr:street":"Valdemarsgade",
    "iso:country":"DK",
    "sg:address":"Valdemarsgade 6 B",
    "sg:city":"Vordingborg",
    "sg:orig_category":"Kiropraktorer",
    "sg:phone":"+45 55 34 11 50",
    "sg:postcode":"4760",
    "sg:province":"Danmark",
    "wof:name":"Dalgaard, Erik",
    "wof:placetype":"venue"
},
  "geometry": {"coordinates":[11.9037761688,55.0126457214],"type":"Point"}
}