{
  "type": "Feature",
  "properties": {
    "addr:full":"Espeskovvej 14, \u00d8rslev Ringsted Danmark 4100",
    "addr:housenumber":"14",
    "addr:postcode":"4100",
    "addr:street":"Espeskovvej;Orslev",
    "iso:country":"DK",
    "sg:address":"Espeskovvej 14, \u00d8rslev",
    "sg:city":"Ringsted",
    "sg:orig_category":"Forsamlingshuse",
    "sg:phone":"+45 56 38 15 10",
    "sg:postcode":"4100",
    "sg:province":"Danmark",
    "wof:name":"\u00d8rslev Forsamlingshus",
    "wof:placetype":"venue"
},
  "geometry": {"coordinates":[11.7875862122,55.4458961487],"type":"Point"}
}