{
  "type": "Feature",
  "properties": {
    "addr:full":"Skjoldh\u00f8j All\u00e9 6, F Charlottenlund Danmark 2920",
    "addr:housenumber":"6 f",
    "addr:postcode":"2920",
    "addr:street":"Skjoldhoj Alle\u0301",
    "iso:country":"DK",
    "sg:address":"Skjoldh\u00f8j All\u00e9 6, F",
    "sg:city":"Charlottenlund",
    "sg:orig_category":"Sportsartikler",
    "sg:phone":"+45 39 63 84 63",
    "sg:postcode":"2920",
    "sg:province":"Danmark",
    "sg:website":"www.allstar-danmark.dk",
    "wof:name":"Allstar-Danmark",
    "wof:placetype":"venue"
},
  "geometry": {"coordinates":[12.5721197128,55.7532615662],"type":"Point"}
}