{
  "type": "Feature",
  "properties": {
    "addr:full":"Peter Fabers Vej 37, gavlen \u00c5rhus V Danmark 8210",
    "addr:housenumber":"37",
    "addr:postcode":"8210",
    "addr:street":"Peter Fabers Vej",
    "iso:country":"DK",
    "sg:address":"Peter Fabers Vej 37, gavlen",
    "sg:city":"\u00c5rhus V",
    "sg:orig_category":"Psykologer, praktiserende",
    "sg:phone":"+45 86 10 04 97",
    "sg:postcode":"8210",
    "sg:province":"Danmark",
    "wof:name":"Psykologerne i Centrum",
    "wof:placetype":"venue"
},
  "geometry": {"coordinates":[15.4325647354,67.2548675537],"type":"Point"}
}