{
  "type": "Feature",
  "properties": {
    "addr:full":"Ledetvej 10 Sindal Danmark 9870",
    "addr:housenumber":"10",
    "addr:postcode":"9870",
    "addr:street":"Ledetvej",
    "iso:country":"DK",
    "sg:address":"Ledetvej 10",
    "sg:city":"Sindal",
    "sg:orig_category":"Lossepladser",
    "sg:phone":"+45 98 92 66 44",
    "sg:postcode":"9870",
    "sg:province":"Danmark",
    "wof:name":"AVV Genbrugspladsen",
    "wof:placetype":"venue"
},
  "geometry": {"coordinates":[10.2053403854,57.4871406555],"type":"Point"}
}