{
  "type": "Feature",
  "properties": {
    "addr:full":"Auningvej 8, \u00d8ster Alling Mark Auning Danmark 8963",
    "addr:housenumber":"8",
    "addr:postcode":"8963",
    "addr:street":"Auningvej",
    "iso:country":"DK",
    "sg:address":"Auningvej 8, \u00d8ster Alling Mark",
    "sg:city":"Auning",
    "sg:orig_category":"Fiskeredskaber",
    "sg:phone":"+45 86 49 25 52",
    "sg:postcode":"8963",
    "sg:province":"Danmark",
    "wof:name":"Poulsen, Jens",
    "wof:placetype":"venue"
},
  "geometry": {"coordinates":[10.3770084381,56.430065155],"type":"Point"}
}