{
  "type": "Feature",
  "properties": {
    "addr:full":"Hjermvej 69 Hjerm Danmark 7560",
    "addr:housenumber":"69",
    "addr:postcode":"7560",
    "addr:street":"Hjermvej",
    "iso:country":"DK",
    "sg:address":"Hjermvej 69",
    "sg:city":"Hjerm",
    "sg:orig_category":"Blomsterhandlere",
    "sg:phone":"+45 97 46 51 00",
    "sg:postcode":"7560",
    "sg:province":"Danmark",
    "wof:name":"Hjerm Blomster & Brugskunst",
    "wof:placetype":"venue"
},
  "geometry": {"coordinates":[8.6281776428,56.4399261475],"type":"Point"}
}