{
  "type": "Feature",
  "properties": {
    "addr:full":"Fmd.: Helge Lassen, Kl\u00f8vervej 11, Jels R\u00f8dding Danmark 6630",
    "addr:housenumber":"11",
    "addr:postcode":"6630",
    "addr:street":"Klovervej",
    "iso:country":"DK",
    "sg:address":"Fmd.: Helge Lassen, Kl\u00f8vervej 11, Jels",
    "sg:city":"R\u00f8dding",
    "sg:orig_category":"Antenneforeninger",
    "sg:phone":"+45 74 55 21 52",
    "sg:postcode":"6630",
    "sg:province":"Danmark",
    "sg:website":"www.jels-net.dk",
    "wof:name":"Jels Antenneforening",
    "wof:placetype":"venue"
},
  "geometry": {"coordinates":[9.2022953033,55.3564414978],"type":"Point"}
}