{
  "type": "Feature",
  "properties": {
    "addr:full":"Farum Hovedgade 50 A Farum Danmark 3520",
    "addr:housenumber":"50 a",
    "addr:postcode":"3520",
    "addr:street":"Farum Hovedgade",
    "iso:country":"DK",
    "sg:address":"Farum Hovedgade 50 A",
    "sg:city":"Farum",
    "sg:orig_category":"Malermestre",
    "sg:phone":"+45 44 95 08 37",
    "sg:postcode":"3520",
    "sg:province":"Danmark",
    "wof:name":"Hansen, Malerfirmaet Eskild",
    "wof:placetype":"venue"
},
  "geometry": {"coordinates":[12.3663482666,55.8106994629],"type":"Point"}
}