{
  "type": "Feature",
  "properties": {
    "iso:country":"DK",
    "sg:address":"Vridsl\u00f8sevej 1",
    "sg:city":"N\u00e6stved",
    "sg:orig_category":"Havebrugsmaskiner",
    "sg:phone":"+45 55 72 53 76",
    "sg:postcode":"4700",
    "sg:province":"Danmark",
    "wof:name":"Honda Minitraktorg\u00e5rden",
    "wof:placetype":"venue"
},
  "geometry": {"coordinates":[-73.5234451294,41.9641532898],"type":"Point"}
}