{
  "type": "Feature",
  "properties": {
    "addr:full":"Vinkelvej 18 B Kjellerup Danmark 8620",
    "addr:housenumber":"18 b",
    "addr:postcode":"8620",
    "addr:street":"Vinkelvej",
    "iso:country":"DK",
    "sg:address":"Vinkelvej 18 B",
    "sg:city":"Kjellerup",
    "sg:orig_category":"Autoreparation og -service",
    "sg:phone":"+45 86 88 38 36",
    "sg:postcode":"8620",
    "sg:province":"Danmark",
    "wof:name":"K. B. Auto",
    "wof:placetype":"venue"
},
  "geometry": {"coordinates":[9.4174194336,56.2850723267],"type":"Point"}
}