{
  "type": "Feature",
  "properties": {
    "addr:full":"T\u00f8mrerstykket 2, Smidstrup Gilleleje Danmark 3250",
    "addr:housenumber":"2",
    "addr:postcode":"3250",
    "addr:street":"Tomrerstykket;Smidstrup",
    "iso:country":"DK",
    "sg:address":"T\u00f8mrerstykket 2, Smidstrup",
    "sg:city":"Gilleleje",
    "sg:orig_category":"Skorstene",
    "sg:phone":"+45 48 31 89 71",
    "sg:postcode":"3250",
    "sg:province":"Danmark",
    "wof:name":"Dantrin",
    "wof:placetype":"venue"
},
  "geometry": {"coordinates":[12.3087387085,56.123462677],"type":"Point"}
}