{
  "type": "Feature",
  "properties": {
    "addr:full":"Spellingevej 3, R\u00f8 Gudhjem Danmark 3760",
    "addr:housenumber":"3",
    "addr:postcode":"3760",
    "addr:street":"Spellingevej",
    "iso:country":"DK",
    "sg:address":"Spellingevej 3, R\u00f8",
    "sg:city":"Gudhjem",
    "sg:classifiers":[
        {
            "category":"Sports & Exercise",
            "subcategory":"Sports Center",
            "type":"Entertainment"
        }
    ],
    "sg:phone":"+45 56 48 40 50",
    "sg:postcode":"3760",
    "sg:province":"Danmark",
    "sg:tags":[
        "golf"
    ],
    "sg:website":"www.danskgolf.dk",
    "wof:name":"Nordbornholms Golf Klub",
    "wof:placetype":"venue"
},
  "geometry": {"coordinates":[15.1870470047,55.3205566406],"type":"Point"}
}