{
  "type": "Feature",
  "properties": {
    "addr:full":"Gothersgade 4 Fredericia Danmark 7000",
    "addr:housenumber":"4",
    "addr:postcode":"7000",
    "addr:street":"Gothersgade",
    "iso:country":"DK",
    "sg:address":"Gothersgade 4",
    "sg:city":"Fredericia",
    "sg:orig_category":"Sko",
    "sg:phone":"+45 75 92 87 53",
    "sg:postcode":"7000",
    "sg:province":"Danmark",
    "wof:name":"G. Sko",
    "wof:placetype":"venue"
},
  "geometry": {"coordinates":[9.7563447952,55.5667800903],"type":"Point"}
}