{
  "type": "Feature",
  "properties": {
    "addr:full":"Askh\u00f8jvej 18 Silkeborg Danmark 8600",
    "addr:housenumber":"18",
    "addr:postcode":"8600",
    "addr:street":"Askhojvej",
    "iso:country":"DK",
    "sg:address":"Askh\u00f8jvej 18",
    "sg:city":"Silkeborg",
    "sg:orig_category":"Campingpladser",
    "sg:phone":"+45 86 84 12 82",
    "sg:postcode":"8600",
    "sg:province":"Danmark",
    "wof:name":"Askeh\u00f8j, Camping",
    "wof:placetype":"venue"
},
  "geometry": {"coordinates":[9.6908082962,56.1355934143],"type":"Point"}
}