{
  "type": "Feature",
  "properties": {
    "addr:full":"Kongevejen 94 Holte Danmark 2840",
    "addr:housenumber":"94",
    "addr:postcode":"2840",
    "addr:street":"Kongevejen",
    "iso:country":"DK",
    "sg:address":"Kongevejen 94",
    "sg:city":"Holte",
    "sg:orig_category":"Servicestationer",
    "sg:phone":"+45 45 42 40 90",
    "sg:postcode":"2840",
    "sg:province":"Danmark",
    "wof:name":"Shell Service",
    "wof:placetype":"venue"
},
  "geometry": {"coordinates":[12.467871666,55.8187484741],"type":"Point"}
}