{
  "type": "Feature",
  "properties": {
    "addr:full":"Industrivej 3 B Jyderup Danmark 4450",
    "addr:housenumber":"3 b",
    "addr:postcode":"4450",
    "addr:street":"Industrivej",
    "iso:country":"DK",
    "sg:address":"Industrivej 3 B",
    "sg:city":"Jyderup",
    "sg:orig_category":"Autolakering",
    "sg:phone":"+45 59 27 63 04",
    "sg:postcode":"4450",
    "sg:province":"Danmark",
    "wof:name":"Aulakto",
    "wof:placetype":"venue"
},
  "geometry": {"coordinates":[11.4114542007,55.6601333618],"type":"Point"}
}