{
  "type": "Feature",
  "properties": {
    "iso:country":"DK",
    "sg:address":"Sandlodsvej 53",
    "sg:city":"Kalundborg",
    "sg:orig_category":"Kaffe og the",
    "sg:phone":"+45 59 50 87 19",
    "sg:postcode":"4400",
    "sg:province":"Danmark",
    "sg:website":"www.keramikstuen.dk",
    "wof:name":"Keramikstuen",
    "wof:placetype":"venue"
},
  "geometry": {"coordinates":[11.0135889053,55.711151123],"type":"Point"}
}