{
  "type": "Feature",
  "properties": {
    "addr:full":"N\u00e6ssundvej 240 Redsted Danmark 7970",
    "addr:housenumber":"240",
    "addr:postcode":"7970",
    "addr:street":"Naessundvej",
    "iso:country":"DK",
    "sg:address":"N\u00e6ssundvej 240",
    "sg:city":"Redsted",
    "sg:orig_category":"Landbrugsmaskiner",
    "sg:phone":"+45 97 76 24 33",
    "sg:postcode":"7970",
    "sg:province":"Danmark",
    "wof:name":"A. T. Hedebo",
    "wof:placetype":"venue"
},
  "geometry": {"coordinates":[8.6513853073,56.7510910034],"type":"Point"}
}