{
  "type": "Feature",
  "properties": {
    "addr:full":"Norddigesvej 8 Risskov Danmark 8240",
    "addr:housenumber":"8",
    "addr:postcode":"8240",
    "addr:street":"Norddigesvej",
    "iso:country":"DK",
    "sg:address":"Norddigesvej 8",
    "sg:city":"Risskov",
    "sg:orig_category":"Autoreparation og -service",
    "sg:phone":"+45 86 21 14 88",
    "sg:postcode":"8240",
    "sg:province":"Danmark",
    "wof:name":"Hansen K\u00f8leanl\u00e6g A/S, Knud",
    "wof:placetype":"venue"
},
  "geometry": {"coordinates":[10.2164182663,56.2108078003],"type":"Point"}
}