{
  "type": "Feature",
  "properties": {
    "addr:full":"Vestergade 26 Ringe Danmark 5750",
    "addr:housenumber":"26",
    "addr:postcode":"5750",
    "addr:street":"Vestergade",
    "iso:country":"DK",
    "sg:address":"Vestergade 26",
    "sg:city":"Ringe",
    "sg:orig_category":"Grillbarer",
    "sg:phone":"+45 62 62 40 62",
    "sg:postcode":"5750",
    "sg:province":"Danmark",
    "wof:name":"H\u00f8keren",
    "wof:placetype":"venue"
},
  "geometry": {"coordinates":[10.4747238159,55.2343025208],"type":"Point"}
}