{
  "type": "Feature",
  "properties": {
    "addr:full":"v/ S. P. Rasmussen, Bredgade 8, Gramrode Juelsminde Danmark 7130",
    "addr:housenumber":"8",
    "addr:postcode":"7130",
    "addr:street":"Bredgade;Gramrode",
    "iso:country":"DK",
    "sg:address":"v/ S. P. Rasmussen, Bredgade 8, Gramrode",
    "sg:city":"Juelsminde",
    "sg:orig_category":"Borger- og beboerforeninger",
    "sg:phone":"+45 75 68 55 02",
    "sg:postcode":"7130",
    "sg:province":"Danmark",
    "wof:name":"Gramrode Gadelys og Grundejerforening",
    "wof:placetype":"venue"
},
  "geometry": {"coordinates":[10.0143985748,55.7135848999],"type":"Point"}
}