{
  "type": "Feature",
  "properties": {
    "iso:country":"DK",
    "sg:address":"Torvet 37",
    "sg:city":"Frederiksv\u00e6rk",
    "sg:classifiers":[
        {
            "category":"Banks & Credit Unions",
            "subcategory":"Bank",
            "type":"Services"
        }
    ],
    "sg:phone":"+45 47 72 24 11",
    "sg:postcode":"3300",
    "sg:province":"Danmark",
    "sg:tags":[
        "banker"
    ],
    "wof:name":"Unibank",
    "wof:placetype":"venue"
},
  "geometry": {"coordinates":[9.9058914185,59.7713279724],"type":"Point"}
}