{
  "type": "Feature",
  "properties": {
    "iso:country":"DK",
    "sg:address":"Arres\u00f8vej 29",
    "sg:city":"Risskov",
    "sg:orig_category":"Autoreparation og -service",
    "sg:phone":"+45 86 17 40 35",
    "sg:postcode":"8240",
    "sg:province":"Danmark",
    "wof:name":"Stoltenberg-Auto",
    "wof:placetype":"venue"
},
  "geometry": {"coordinates":[10.2314805984,56.2035598755],"type":"Point"}
}