{
  "type": "Feature",
  "properties": {
    "addr:full":"Gyldendalsvej 14 Kongens Lyngby Danmark 2800",
    "addr:housenumber":"14",
    "addr:postcode":"2800",
    "addr:street":"Gyldendalsvej",
    "iso:country":"DK",
    "sg:address":"Gyldendalsvej 14",
    "sg:city":"Kongens Lyngby",
    "sg:orig_category":"Autoreparation og -service",
    "sg:phone":"+45 45 87 42 11",
    "sg:postcode":"2800",
    "sg:province":"Danmark",
    "wof:name":"Mazdag\u00e5rden",
    "wof:placetype":"venue"
},
  "geometry": {"coordinates":[12.5084466934,55.7680892944],"type":"Point"}
}