{
  "type": "Feature",
  "properties": {
    "addr:full":"J\u00e6gerg\u00e5rdsgade 65 \u00c5rhus C Danmark 8000",
    "addr:housenumber":"65",
    "addr:postcode":"8000",
    "addr:street":"Jaegergaardsgade",
    "iso:country":"DK",
    "sg:address":"J\u00e6gerg\u00e5rdsgade 65",
    "sg:city":"\u00c5rhus C",
    "sg:orig_category":"Bodegaer",
    "sg:phone":"+45 86 13 12 21",
    "sg:postcode":"8000",
    "sg:province":"Danmark",
    "wof:name":"Bodega 65",
    "wof:placetype":"venue"
},
  "geometry": {"coordinates":[-66.94068145750001,-27.6476192474],"type":"Point"}
}