{
  "type": "Feature",
  "properties": {
    "iso:country":"DK",
    "sg:address":"Bredalk\u00e6rvej 39",
    "sg:city":"Vejle \u00d8",
    "sg:orig_category":"Akupunktur",
    "sg:phone":"+45 75 81 61 42",
    "sg:postcode":"7120",
    "sg:province":"Danmark",
    "wof:name":"Pade, Sus",
    "wof:placetype":"venue"
},
  "geometry": {"coordinates":[9.6571302414,55.7422103882],"type":"Point"}
}