{
  "type": "Feature",
  "properties": {
    "iso:country":"DK",
    "sg:address":"v/ Frede Boll, Redstedvej 24",
    "sg:city":"Redsted",
    "sg:orig_category":"Hobbybetonede foreninger",
    "sg:phone":"+45 97 76 21 68",
    "sg:postcode":"7970",
    "sg:province":"Danmark",
    "wof:name":"Dansk Borgward Klub",
    "wof:placetype":"venue"
},
  "geometry": {"coordinates":[8.6130647659,56.7446250916],"type":"Point"}
}