{
  "type": "Feature",
  "properties": {
    "iso:country":"DK",
    "sg:address":"Fmd.: Birthe J\u00f8rgensen, Himmerlandsgade 29",
    "sg:city":"Hadsund",
    "sg:orig_category":"Kulturelle foreninger",
    "sg:phone":"+45 98 57 35 26",
    "sg:postcode":"9560",
    "sg:province":"Danmark",
    "wof:name":"Foreningen Norden",
    "wof:placetype":"venue"
},
  "geometry": {"coordinates":[10.115904808,56.7150764465],"type":"Point"}
}