{
  "type": "Feature",
  "properties": {
    "addr:full":"Poppelvej 10 Hurup Danmark 7760",
    "addr:housenumber":"10",
    "addr:postcode":"7760",
    "addr:street":"Poppelvej",
    "iso:country":"DK",
    "sg:address":"Poppelvej 10",
    "sg:city":"Hurup",
    "sg:orig_category":"Daginstitution for voksne",
    "sg:phone":"+45 97 95 31 71",
    "sg:postcode":"7760",
    "sg:province":"Danmark",
    "wof:name":"Aktivitetshuset Limfjorden",
    "wof:placetype":"venue"
},
  "geometry": {"coordinates":[8.4290857315,56.749458313],"type":"Point"}
}