{
  "type": "Feature",
  "properties": {
    "addr:full":"Adelgade 42 Ebeltoft Danmark 8400",
    "addr:housenumber":"42",
    "addr:postcode":"8400",
    "addr:street":"Adelgade",
    "iso:country":"DK",
    "sg:address":"Adelgade 42",
    "sg:city":"Ebeltoft",
    "sg:orig_category":"Lingeri",
    "sg:phone":"+45 86 34 53 55",
    "sg:postcode":"8400",
    "sg:province":"Danmark",
    "wof:name":"Cherie",
    "wof:placetype":"venue"
},
  "geometry": {"coordinates":[10.6791687012,56.1997528076],"type":"Point"}
}