{
  "type": "Feature",
  "properties": {
    "addr:full":"Amagervej 6 Skjern Danmark 6900",
    "addr:housenumber":"6",
    "addr:postcode":"6900",
    "addr:street":"Amagervej",
    "iso:country":"DK",
    "sg:address":"Amagervej 6",
    "sg:city":"Skjern",
    "sg:orig_category":"Papir en gros",
    "sg:phone":"+45 97 35 05 29",
    "sg:postcode":"6900",
    "sg:province":"Danmark",
    "wof:name":"Schmidt Papirimport, Carl",
    "wof:placetype":"venue"
},
  "geometry": {"coordinates":[8.4866695404,55.9468727112],"type":"Point"}
}