{
  "type": "Feature",
  "properties": {
    "addr:full":"\u00d8stergade 2 A Sindal Danmark 9870",
    "addr:housenumber":"2 a",
    "addr:postcode":"9870",
    "addr:street":"Ostergade",
    "iso:country":"DK",
    "sg:address":"\u00d8stergade 2 A",
    "sg:city":"Sindal",
    "sg:orig_category":"Advokater",
    "sg:phone":"+45 98 93 55 55",
    "sg:postcode":"9870",
    "sg:province":"Danmark",
    "wof:name":"Funch, Johannes",
    "wof:placetype":"venue"
},
  "geometry": {"coordinates":[10.2025136948,57.4707489014],"type":"Point"}
}