{
  "type": "Feature",
  "properties": {
    "iso:country":"DK",
    "sg:address":"Hiller\u00f8dvejen 91",
    "sg:city":"Fredensborg",
    "sg:orig_category":"Campingpladser",
    "sg:phone":"+45 48 48 18 92",
    "sg:postcode":"3480",
    "sg:province":"Danmark",
    "wof:name":"N\u00f8debo Camping",
    "wof:placetype":"venue"
},
  "geometry": {"coordinates":[12.3628454208,55.9592971802],"type":"Point"}
}