{
  "type": "Feature",
  "properties": {
    "iso:country":"DK",
    "sg:address":"Tilstedvej 20",
    "sg:city":"Thisted",
    "sg:orig_category":"Boghandlere",
    "sg:phone":"+45 97 91 13 90",
    "sg:postcode":"7700",
    "sg:province":"Danmark",
    "wof:name":"Kristent Bogsalg",
    "wof:placetype":"venue"
},
  "geometry": {"coordinates":[8.6589174271,56.9495582581],"type":"Point"}
}