{
  "type": "Feature",
  "properties": {
    "addr:full":"Hjalmar Kjems All\u00e9 6 Skive Danmark 7800",
    "addr:housenumber":"6",
    "addr:postcode":"7800",
    "addr:street":"Hjalmar Kjems Alle\u0301",
    "iso:country":"DK",
    "sg:address":"Hjalmar Kjems All\u00e9 6",
    "sg:city":"Skive",
    "sg:orig_category":"Voksenuddannelsescentre",
    "sg:phone":"+45 97 52 18 22",
    "sg:postcode":"7800",
    "sg:province":"Danmark",
    "sg:website":"www.vibamt.dk/vuc/skive",
    "wof:name":"VUC Skive",
    "wof:placetype":"venue"
},
  "geometry": {"coordinates":[9.0278892517,56.5714569092],"type":"Point"}
}