{
  "type": "Feature",
  "properties": {
    "addr:full":"Greve Strandvej 154 Greve Danmark 2670",
    "addr:housenumber":"154",
    "addr:postcode":"2670",
    "addr:street":"Greve Strandvej",
    "iso:country":"DK",
    "sg:address":"Greve Strandvej 154",
    "sg:city":"Greve",
    "sg:orig_category":"Genbrugsbutikker",
    "sg:phone":"+45 43 90 60 43",
    "sg:postcode":"2670",
    "sg:province":"Danmark",
    "wof:name":"R\u00f8de Kors Genbrug",
    "wof:placetype":"venue"
},
  "geometry": {"coordinates":[12.2905979156,55.5733184814],"type":"Point"}
}