{
  "type": "Feature",
  "properties": {
    "addr:full":"Byrstedhedevej 24, Bradsted Suldrup Danmark 9541",
    "addr:housenumber":"24",
    "addr:postcode":"9541",
    "addr:street":"Byrstedhedevej",
    "iso:country":"DK",
    "sg:address":"Byrstedhedevej 24, Bradsted",
    "sg:city":"Suldrup",
    "sg:orig_category":"Hundepensioner",
    "sg:phone":"+45 98 38 72 88",
    "sg:postcode":"9541",
    "sg:province":"Danmark",
    "wof:name":"Byrsted Hundepension",
    "wof:placetype":"venue"
},
  "geometry": {"coordinates":[9.701379776,56.8489303589],"type":"Point"}
}