{
  "type": "Feature",
  "properties": {
    "iso:country":"DK",
    "sg:address":"N\u00f8rregade 34",
    "sg:city":"Skive",
    "sg:classifiers":[
        {
            "category":"Banks & Credit Unions",
            "subcategory":"Bank",
            "type":"Services"
        }
    ],
    "sg:phone":"+45 97 52 88 77",
    "sg:postcode":"7800",
    "sg:province":"Danmark",
    "sg:tags":[
        "banker"
    ],
    "wof:name":"Arbejdernes Landsbank",
    "wof:placetype":"venue"
},
  "geometry": {"coordinates":[9.028017,56.569046],"type":"Point"}
}