{
  "type": "Feature",
  "properties": {
    "addr:full":"Fmd.: Erna Storgaard, M\u00f8lg\u00e5rdvej 40, \u00d8rnsholt Vonge Danmark 7173",
    "addr:housenumber":"40",
    "addr:postcode":"7173",
    "addr:street":"Molgaardvej;Ornsholt",
    "iso:country":"DK",
    "sg:address":"Fmd.: Erna Storgaard, M\u00f8lg\u00e5rdvej 40, \u00d8rnsholt",
    "sg:city":"Vonge",
    "sg:orig_category":"Borger- og beboerforeninger",
    "sg:phone":"+45 75 80 36 28",
    "sg:postcode":"7173",
    "sg:province":"Danmark",
    "wof:name":"Vonge og Omegns Borgerforening",
    "wof:placetype":"venue"
},
  "geometry": {"coordinates":[9.4188747406,55.8598136902],"type":"Point"}
}