{
  "type": "Feature",
  "properties": {
    "addr:full":"Borgergade 13 Gjern Danmark 8883",
    "addr:housenumber":"13",
    "addr:postcode":"8883",
    "addr:street":"Borgergade",
    "iso:country":"DK",
    "sg:address":"Borgergade 13",
    "sg:city":"Gjern",
    "sg:orig_category":"Genbrugsbutikker",
    "sg:phone":"+45 86 87 53 58",
    "sg:postcode":"8883",
    "sg:province":"Danmark",
    "wof:name":"Folkekirkens N\u00f8dhj\u00e6lps Genbrugsbutik",
    "wof:placetype":"venue"
},
  "geometry": {"coordinates":[9.7394037247,56.2305335999],"type":"Point"}
}