{
  "type": "Feature",
  "properties": {
    "addr:full":"Fmd.: Rita Holt, Lindalsbakken 8 Hadsund Danmark 9560",
    "addr:housenumber":"8",
    "addr:postcode":"9560",
    "addr:street":"Holt Lindalsbakken",
    "iso:country":"DK",
    "sg:address":"Fmd.: Rita Holt, Lindalsbakken 8",
    "sg:city":"Hadsund",
    "sg:orig_category":"Hobbybetonede foreninger",
    "sg:phone":"+45 98 57 19 46",
    "sg:postcode":"9560",
    "sg:province":"Danmark",
    "wof:name":"Fodslaw Hadsund",
    "wof:placetype":"venue"
},
  "geometry": {"coordinates":[10.115904808,56.7150764465],"type":"Point"}
}