{
  "type": "Feature",
  "properties": {
    "addr:full":"Bispebjerg Torv 8 K\u00f8benhavn NV Danmark 2400",
    "addr:housenumber":"8",
    "addr:postcode":"2400",
    "addr:street":"Bispebjerg Torv",
    "iso:country":"DK",
    "sg:address":"Bispebjerg Torv 8",
    "sg:city":"K\u00f8benhavn NV",
    "sg:orig_category":"Cafeer",
    "sg:phone":"+45 35 81 71 41",
    "sg:postcode":"2400",
    "sg:province":"Danmark",
    "wof:name":"Cafe Bjerget",
    "wof:placetype":"venue"
},
  "geometry": {"coordinates":[12.5311403275,55.7115707397],"type":"Point"}
}