{
  "type": "Feature",
  "properties": {
    "addr:full":"Trekronervej 12 - 14 Viborg Danmark 8800",
    "addr:housenumber":"12 14",
    "addr:postcode":"8800",
    "addr:street":"Trekronervej",
    "iso:country":"DK",
    "sg:address":"Trekronervej 12 - 14",
    "sg:city":"Viborg",
    "sg:orig_category":"Private skoler",
    "sg:phone":"+45 86 62 08 88",
    "sg:postcode":"8800",
    "sg:province":"Danmark",
    "wof:name":"Viborg Private Realskole",
    "wof:placetype":"venue"
},
  "geometry": {"coordinates":[9.4020423889,56.4490242004],"type":"Point"}
}