{
  "type": "Feature",
  "properties": {
    "addr:full":"Bakkelunden 120 Munkebo Danmark 5330",
    "addr:housenumber":"120",
    "addr:postcode":"5330",
    "addr:street":"Bakkelunden",
    "iso:country":"DK",
    "sg:address":"Bakkelunden 120",
    "sg:city":"Munkebo",
    "sg:orig_category":"Zoneterapeuter",
    "sg:phone":"+45 65 97 52 20",
    "sg:postcode":"5330",
    "sg:province":"Danmark",
    "wof:name":"Riishede, Tove Kolstrup",
    "wof:placetype":"venue"
},
  "geometry": {"coordinates":[10.5448493958,55.452205658],"type":"Point"}
}