{
  "type": "Feature",
  "properties": {
    "addr:full":"Lygten 2C K\u00f8benhavn NV Danmark 2400",
    "addr:housenumber":"2c",
    "addr:postcode":"2400",
    "addr:street":"Lygten",
    "iso:country":"DK",
    "sg:address":"Lygten 2C",
    "sg:city":"K\u00f8benhavn NV",
    "sg:orig_category":"Kolonial en gros",
    "sg:phone":"+45 35 83 66 88",
    "sg:postcode":"2400",
    "sg:province":"Danmark",
    "wof:name":"F.I.S. Scandinavia A/S",
    "wof:placetype":"venue"
},
  "geometry": {"coordinates":[-117.02272033689999,38.5024604797],"type":"Point"}
}