{
  "type": "Feature",
  "properties": {
    "iso:country":"DK",
    "sg:address":"Lyngbygade 8",
    "sg:city":"Silkeborg",
    "sg:orig_category":"Kirker",
    "sg:postcode":"8600",
    "sg:province":"Danmark",
    "wof:name":"Adventskirken",
    "wof:placetype":"venue"
},
  "geometry": {"coordinates":[9.5498733521,56.1630592346],"type":"Point"}
}