{
  "type": "Feature",
  "properties": {
    "iso:country":"DK",
    "sg:address":"Kr\u00e6mmergade 11",
    "sg:city":"Varde",
    "sg:orig_category":"Telebutikker",
    "sg:phone":"+45 75 22 30 50",
    "sg:postcode":"6800",
    "sg:province":"Danmark",
    "wof:name":"Tele Danmark - Telebutik",
    "wof:placetype":"venue"
},
  "geometry": {"coordinates":[8.4822063446,55.6208267212],"type":"Point"}
}