{
  "type": "Feature",
  "properties": {
    "addr:full":"Strandbygade 60 Esbjerg Danmark 6700",
    "addr:housenumber":"60",
    "addr:postcode":"6700",
    "addr:street":"Strandbygade",
    "iso:country":"DK",
    "sg:address":"Strandbygade 60",
    "sg:city":"Esbjerg",
    "sg:orig_category":"Blomsterhandlere",
    "sg:phone":"+45 75 45 09 00",
    "sg:postcode":"6700",
    "sg:province":"Danmark",
    "wof:name":"Karin's Blomster",
    "wof:placetype":"venue"
},
  "geometry": {"coordinates":[8.4379148483,55.4714279175],"type":"Point"}
}