{
  "type": "Feature",
  "properties": {
    "addr:full":"Bastemosevej 6, Bastemose Tranek\u00e6r Danmark 5953",
    "addr:housenumber":"6",
    "addr:postcode":"5953",
    "addr:street":"Bastemosevej",
    "iso:country":"DK",
    "sg:address":"Bastemosevej 6, Bastemose",
    "sg:city":"Tranek\u00e6r",
    "sg:orig_category":"Hundekenneler",
    "sg:phone":"+45 62 55 14 57",
    "sg:postcode":"5953",
    "sg:province":"Danmark",
    "wof:name":"Skovfryd, Kennel",
    "wof:placetype":"venue"
},
  "geometry": {"coordinates":[10.8026809692,54.960609436],"type":"Point"}
}