{
  "type": "Feature",
  "properties": {
    "addr:full":"Storegade 56 Haderslev Danmark 6100",
    "addr:housenumber":"56",
    "addr:postcode":"6100",
    "addr:street":"Storegade",
    "iso:country":"DK",
    "sg:address":"Storegade 56",
    "sg:city":"Haderslev",
    "sg:orig_category":"Zoneterapeuter",
    "sg:phone":"+45 74 52 48 77",
    "sg:postcode":"6100",
    "sg:province":"Danmark",
    "wof:name":"Sch\u00f8ning, Pernille Burich",
    "wof:placetype":"venue"
},
  "geometry": {"coordinates":[9.48087883,55.2523422241],"type":"Point"}
}