{
  "type": "Feature",
  "properties": {
    "addr:full":"Havk\u00e6rvej 13, Tilst Tilst Danmark 8381",
    "addr:housenumber":"13",
    "addr:postcode":"8381",
    "addr:street":"Havkaervej",
    "iso:country":"DK",
    "sg:address":"Havk\u00e6rvej 13, Tilst",
    "sg:city":"Tilst",
    "sg:orig_category":"Blikkenslagere",
    "sg:phone":"+45 86 24 18 22",
    "sg:postcode":"8381",
    "sg:province":"Danmark",
    "wof:name":"Balle Rasmussen, Erik",
    "wof:placetype":"venue"
},
  "geometry": {"coordinates":[10.107815,56.188202],"type":"Point"}
}