{
  "type": "Feature",
  "properties": {
    "addr:full":"Grejsdalsvej 4 Vejle Danmark 7100",
    "addr:housenumber":"4",
    "addr:postcode":"7100",
    "addr:street":"Grejsdalsvej",
    "iso:country":"DK",
    "sg:address":"Grejsdalsvej 4",
    "sg:city":"Vejle",
    "sg:orig_category":"Motorer",
    "sg:phone":"+45 75 82 29 08",
    "sg:postcode":"7100",
    "sg:province":"Danmark",
    "wof:name":"Jydsk Cylinder Service",
    "wof:placetype":"venue"
},
  "geometry": {"coordinates":[9.5341739655,55.7162361145],"type":"Point"}
}