{
  "type": "Feature",
  "properties": {
    "addr:full":"Jernbanegade 30 Roskilde Danmark 4000",
    "addr:housenumber":"30",
    "addr:postcode":"4000",
    "addr:street":"Jernbanegade",
    "iso:country":"DK",
    "sg:address":"Jernbanegade 30",
    "sg:city":"Roskilde",
    "sg:orig_category":"Maskinfabrikker",
    "sg:phone":"+45 46 35 14 50",
    "sg:postcode":"4000",
    "sg:province":"Danmark",
    "wof:name":"Kornerup & S\u00f8n ApS, Maskinfabrikken",
    "wof:placetype":"venue"
},
  "geometry": {"coordinates":[12.0828638077,55.6379585266],"type":"Point"}
}