{
  "type": "Feature",
  "properties": {
    "addr:full":"Amalievej 20 Frederiksberg Danmark 1875",
    "addr:housenumber":"20",
    "addr:postcode":"1875",
    "addr:street":"Amalievej",
    "iso:country":"DK",
    "sg:address":"Amalievej 20",
    "sg:city":"Frederiksberg",
    "sg:orig_category":"Erhvervs- og brancheforeninger",
    "sg:phone":"+45 33 24 42 66",
    "sg:postcode":"1875",
    "sg:province":"Danmark",
    "sg:website":"www.skovforeningen.dk",
    "wof:name":"Skovforening, Dansk",
    "wof:placetype":"venue"
},
  "geometry": {"coordinates":[12.5463438034,55.6785583496],"type":"Point"}
}