{
  "type": "Feature",
  "properties": {
    "addr:full":"Fmd.: Poul Haase, Sch\u00f8dtsmindevej 3, Skovby Galten Danmark 8464",
    "addr:housenumber":"3",
    "addr:postcode":"8464",
    "addr:street":"Poul;Schodtsmindevej;Skovby",
    "iso:country":"DK",
    "sg:address":"Fmd.: Poul Haase, Sch\u00f8dtsmindevej 3, Skovby",
    "sg:city":"Galten",
    "sg:orig_category":"Hobbybetonede foreninger",
    "sg:phone":"+45 86 94 35 85",
    "sg:postcode":"8464",
    "sg:province":"Danmark",
    "sg:website":"www.geocities.com/legetojssamlere",
    "wof:name":"Leget\u00f8jssamlere af 1988",
    "wof:placetype":"venue"
},
  "geometry": {"coordinates":[9.9034748077,56.1558837891],"type":"Point"}
}