{
  "type": "Feature",
  "properties": {
    "addr:full":"Laurids Skaus Gade 8 A,1. Haderslev Danmark 6100",
    "addr:housenumber":"8 a 1",
    "addr:postcode":"6100",
    "addr:street":"Laurids Skaus Gade",
    "iso:country":"DK",
    "sg:address":"Laurids Skaus Gade 8 A,1.",
    "sg:city":"Haderslev",
    "sg:orig_category":"Psykologer, praktiserende",
    "sg:phone":"+45 74 52 00 11",
    "sg:postcode":"6100",
    "sg:province":"Danmark",
    "wof:name":"Christensen, Hans",
    "wof:placetype":"venue"
},
  "geometry": {"coordinates":[9.4874477386,55.254119873],"type":"Point"}
}