{
  "type": "Feature",
  "properties": {
    "addr:full":"Dalsvinget 113 Silkeborg Danmark 8600",
    "addr:housenumber":"113",
    "addr:postcode":"8600",
    "addr:street":"Dalsvinget",
    "iso:country":"DK",
    "sg:address":"Dalsvinget 113",
    "sg:city":"Silkeborg",
    "sg:classifiers":[
        {
            "category":"Personal",
            "subcategory":"Psychics & Astrologers",
            "type":"Services"
        }
    ],
    "sg:phone":"+45 86 82 44 43",
    "sg:postcode":"8600",
    "sg:province":"Danmark",
    "sg:tags":[
        "clairvoyance"
    ],
    "wof:name":"Stolfer, H\u00e5kan",
    "wof:placetype":"venue"
},
  "geometry": {"coordinates":[9.5442609787,56.1881217957],"type":"Point"}
}