{
  "type": "Feature",
  "properties": {
    "addr:full":"Sj\u00e6llandsgade 2 Ringsted Danmark 4100",
    "addr:housenumber":"2",
    "addr:postcode":"4100",
    "addr:street":"Sjaellandsgade",
    "iso:country":"DK",
    "sg:address":"Sj\u00e6llandsgade 2",
    "sg:city":"Ringsted",
    "sg:orig_category":"Farve og tapet",
    "sg:phone":"+45 57 61 31 21",
    "sg:postcode":"4100",
    "sg:province":"Danmark",
    "wof:name":"Farvecentret",
    "wof:placetype":"venue"
},
  "geometry": {"coordinates":[11.7892427444,55.4418296814],"type":"Point"}
}