{
  "type": "Feature",
  "properties": {
    "addr:full":"Herlev Hovedgade 203 B Herlev Danmark 2730",
    "addr:housenumber":"203 b",
    "addr:postcode":"2730",
    "addr:street":"Herlev Hovedgade",
    "iso:country":"DK",
    "sg:address":"Herlev Hovedgade 203 B",
    "sg:city":"Herlev",
    "sg:orig_category":"El-artikler",
    "sg:phone":"+45 44 84 83 00",
    "sg:postcode":"2730",
    "sg:province":"Danmark",
    "wof:name":"Duelco a/s",
    "wof:placetype":"venue"
},
  "geometry": {"coordinates":[12.4201622009,55.7253112793],"type":"Point"}
}