{
  "type": "Feature",
  "properties": {
    "addr:full":"Vandmestervej 38 Taastrup Danmark 2630",
    "addr:housenumber":"38",
    "addr:postcode":"2630",
    "addr:street":"Vandmestervej",
    "iso:country":"DK",
    "sg:address":"Vandmestervej 38",
    "sg:city":"Taastrup",
    "sg:orig_category":"Autoforhandlere",
    "sg:phone":"+45 43 52 40 33",
    "sg:postcode":"2630",
    "sg:province":"Danmark",
    "wof:name":"Saab Taastrup ApS",
    "wof:placetype":"venue"
},
  "geometry": {"coordinates":[12.2834501266,55.6373176575],"type":"Point"}
}