{
  "type": "Feature",
  "properties": {
    "addr:full":"Heilskovsgade 6 Aalborg Danmark 9000",
    "addr:housenumber":"6",
    "addr:postcode":"9000",
    "addr:street":"Heilskovsgade",
    "iso:country":"DK",
    "sg:address":"Heilskovsgade 6",
    "sg:city":"Aalborg",
    "sg:orig_category":"Malermestre",
    "sg:phone":"+45 98 13 46 63",
    "sg:postcode":"9000",
    "sg:province":"Danmark",
    "wof:name":"Larsen, Bjarne",
    "wof:placetype":"venue"
},
  "geometry": {"coordinates":[9.944688797,57.0365982056],"type":"Point"}
}