{
  "type": "Feature",
  "properties": {
    "iso:country":"DK",
    "sg:address":"Herluf Trolles Vej 24",
    "sg:city":"Odense S\u00d8",
    "sg:orig_category":"Malervarer",
    "sg:phone":"+45 65 93 03 11",
    "sg:postcode":"5220",
    "sg:province":"Danmark",
    "wof:name":"A/S Hyg\u00e6a Farver og Lakker Malergrossisten Hygros",
    "wof:placetype":"venue"
},
  "geometry": {"coordinates":[10.4432411194,55.388381958],"type":"Point"}
}