{
  "type": "Feature",
  "properties": {
    "addr:full":"Vejlevej 232, Moseg\u00e5rd Give Danmark 7323",
    "addr:housenumber":"232",
    "addr:postcode":"7323",
    "addr:street":"Vejlevej",
    "iso:country":"DK",
    "sg:address":"Vejlevej 232, Moseg\u00e5rd",
    "sg:city":"Give",
    "sg:orig_category":"Maskinsnedkerier",
    "sg:phone":"+45 75 73 11 95",
    "sg:postcode":"7323",
    "sg:province":"Danmark",
    "sg:website":"www.vgtraeteknik.dk",
    "wof:name":"V.G. Tr\u00e6teknik",
    "wof:placetype":"venue"
},
  "geometry": {"coordinates":[9.2362060547,55.845413208],"type":"Point"}
}