{
  "type": "Feature",
  "properties": {
    "addr:full":"Ericavej 161-163 Gentofte Danmark 2820",
    "addr:housenumber":"161-163",
    "addr:postcode":"2820",
    "addr:street":"Ericavej",
    "iso:country":"DK",
    "sg:address":"Ericavej 161-163",
    "sg:city":"Gentofte",
    "sg:orig_category":"Supermarkeder",
    "sg:postcode":"2820",
    "sg:province":"Danmark",
    "wof:name":"D\u00f8gnetto",
    "wof:placetype":"venue"
},
  "geometry": {"coordinates":[12.5075283051,55.7454032898],"type":"Point"}
}