{
  "type": "Feature",
  "properties": {
    "iso:country":"DK",
    "sg:address":"Fmd.: Jan Ravnmark, Engvej 23, Tommerup St",
    "sg:city":"Tommerup",
    "sg:orig_category":"Antenneforeninger",
    "sg:phone":"+45 64 76 34 46",
    "sg:postcode":"5690",
    "sg:province":"Danmark",
    "wof:name":"Tommerup St. Antenneforening",
    "wof:placetype":"venue"
},
  "geometry": {"coordinates":[10.2489509583,55.3236503601],"type":"Point"}
}