{
  "type": "Feature",
  "properties": {
    "addr:full":"Moseg\u00e5rdsvej 10, Nim Horsens Danmark 8700",
    "addr:housenumber":"10",
    "addr:postcode":"8700",
    "addr:street":"Mosegaardsvej;Nim",
    "iso:country":"DK",
    "sg:address":"Moseg\u00e5rdsvej 10, Nim",
    "sg:city":"Horsens",
    "sg:orig_category":"Murermestre",
    "sg:phone":"+45 75 67 11 62",
    "sg:postcode":"8700",
    "sg:province":"Danmark",
    "wof:name":"Jensen, Niels",
    "wof:placetype":"venue"
},
  "geometry": {"coordinates":[9.8432445526,55.8621063232],"type":"Point"}
}