{
  "type": "Feature",
  "properties": {
    "addr:full":"Slugten 9, Hald Ege Viborg Danmark 8800",
    "addr:housenumber":"9",
    "addr:postcode":"8800",
    "addr:street":"Slugten;Hald Ege",
    "iso:country":"DK",
    "sg:address":"Slugten 9, Hald Ege",
    "sg:city":"Viborg",
    "sg:orig_category":"Malermestre",
    "sg:phone":"+45 86 63 81 83",
    "sg:postcode":"8800",
    "sg:province":"Danmark",
    "wof:name":"Skou, Arne",
    "wof:placetype":"venue"
},
  "geometry": {"coordinates":[9.4071502686,56.452671051],"type":"Point"}
}