{
  "type": "Feature",
  "properties": {
    "addr:full":"Matolievej 4, Gudmindrup L H\u00f8jby Danmark 4573",
    "addr:housenumber":"4",
    "addr:postcode":"4573",
    "addr:street":"Matolievej;Gudmindrup L Hojby Danmark",
    "iso:country":"DK",
    "sg:address":"Matolievej 4, Gudmindrup L",
    "sg:city":"H\u00f8jby",
    "sg:orig_category":"Pianostemmere",
    "sg:phone":"+45 59 30 51 68",
    "sg:postcode":"4573",
    "sg:province":"Danmark",
    "wof:name":"Haugland, Olav",
    "wof:placetype":"venue"
},
  "geometry": {"coordinates":[11.5945587158,55.912021637],"type":"Point"}
}