{
  "type": "Feature",
  "properties": {
    "addr:full":"Frederiksberg Runddel Frederiksberg Danmark 2000",
    "addr:postcode":"2000",
    "addr:street":"Frederiksberg Runddel",
    "iso:country":"DK",
    "sg:address":"Frederiksberg Runddel",
    "sg:city":"Frederiksberg",
    "sg:orig_category":"Museer",
    "sg:phone":"+45 38 86 05 23",
    "sg:postcode":"2000",
    "sg:province":"Danmark",
    "wof:name":"Storm P.- Museet",
    "wof:placetype":"venue"
},
  "geometry": {"coordinates":[12.5168104172,55.6813583374],"type":"Point"}
}