{
  "type": "Feature",
  "properties": {
    "addr:full":"Fmd.: Jens Lassen, Engpibervej 56 Maribo Danmark 4930",
    "addr:housenumber":"56",
    "addr:postcode":"4930",
    "addr:street":"Engpibervej",
    "iso:country":"DK",
    "sg:address":"Fmd.: Jens Lassen, Engpibervej 56",
    "sg:city":"Maribo",
    "sg:orig_category":"Grundejerforeninger",
    "sg:postcode":"4930",
    "sg:province":"Danmark",
    "wof:name":"Grundejerforeningen Ny Bl\u00e6senborg \u00d8st",
    "wof:placetype":"venue"
},
  "geometry": {"coordinates":[11.502035141,54.7743835449],"type":"Point"}
}