{
  "type": "Feature",
  "properties": {
    "addr:full":"Reinholdts Bakke 27 Lunderskov Danmark 6640",
    "addr:housenumber":"27",
    "addr:postcode":"6640",
    "addr:street":"Reinholdts Bakke",
    "iso:country":"DK",
    "sg:address":"Reinholdts Bakke 27",
    "sg:city":"Lunderskov",
    "sg:orig_category":"Plejehjem",
    "sg:phone":"+45 75 58 54 37",
    "sg:postcode":"6640",
    "sg:province":"Danmark",
    "wof:name":"Kongsbjerghjemmet",
    "wof:placetype":"venue"
},
  "geometry": {"coordinates":[9.289440155,55.4802131653],"type":"Point"}
}