{
  "type": "Feature",
  "properties": {
    "addr:full":"O. J. Steinckes Vej 18, Postboks 232 Frederikshavn Danmark 9900",
    "addr:housenumber":"18;232",
    "addr:postcode":"9900",
    "addr:street":"Steinckes Vej",
    "iso:country":"DK",
    "sg:address":"O. J. Steinckes Vej 18, Postboks 232",
    "sg:city":"Frederikshavn",
    "sg:orig_category":"Blomsterhandlere",
    "sg:phone":"+45 98 42 10 52",
    "sg:postcode":"9900",
    "sg:province":"Danmark",
    "wof:name":"PARK Blomster",
    "wof:placetype":"venue"
},
  "geometry": {"coordinates":[10.5362997055,57.4396400452],"type":"Point"}
}