{
  "type": "Feature",
  "properties": {
    "addr:full":"\u00c5toften 8, Toreby Toreby Danmark 4891",
    "addr:housenumber":"8",
    "addr:postcode":"4891",
    "addr:street":"Aatoften;Toreby Toreby Danmark",
    "iso:country":"DK",
    "sg:address":"\u00c5toften 8, Toreby",
    "sg:city":"Toreby",
    "sg:orig_category":"Dentallaboratorier",
    "sg:phone":"+45 54 86 28 62",
    "sg:postcode":"4891",
    "sg:province":"Danmark",
    "wof:name":"Adental",
    "wof:placetype":"venue"
},
  "geometry": {"coordinates":[11.7701835632,54.7622375488],"type":"Point"}
}