{
  "type": "Feature",
  "properties": {
    "addr:full":"\u00d8stergade 1 Hjallerup Danmark 9320",
    "addr:housenumber":"1",
    "addr:postcode":"9320",
    "addr:street":"Ostergade",
    "iso:country":"DK",
    "sg:address":"\u00d8stergade 1",
    "sg:city":"Hjallerup",
    "sg:orig_category":"Optikere",
    "sg:phone":"+45 98 28 23 23",
    "sg:postcode":"9320",
    "sg:province":"Danmark",
    "wof:name":"Hjallerup Optik",
    "wof:placetype":"venue"
},
  "geometry": {"coordinates":[10.1464729309,57.1691818237],"type":"Point"}
}