{
  "type": "Feature",
  "properties": {
    "addr:full":"Fmd.: Frits Flansmose, \u00d8. Skibelundvej 42 Vejen Danmark 6600",
    "addr:housenumber":"42",
    "addr:postcode":"6600",
    "addr:street":"Skibelundvej",
    "iso:country":"DK",
    "sg:address":"Fmd.: Frits Flansmose, \u00d8. Skibelundvej 42",
    "sg:city":"Vejen",
    "sg:orig_category":"Kulturelle foreninger",
    "sg:postcode":"6600",
    "sg:province":"Danmark",
    "wof:name":"Sl\u00f8jdscenens Askov Amat\u00f8rteater",
    "wof:placetype":"venue"
},
  "geometry": {"coordinates":[9.1396121979,55.4778175354],"type":"Point"}
}