{
  "type": "Feature",
  "properties": {
    "addr:full":"\u00d8stergade 18 Hjallerup Danmark 9320",
    "addr:housenumber":"18",
    "addr:postcode":"9320",
    "addr:street":"Ostergade",
    "iso:country":"DK",
    "sg:address":"\u00d8stergade 18",
    "sg:city":"Hjallerup",
    "sg:orig_category":"Genbrugsbutikker",
    "sg:phone":"+45 98 28 32 30",
    "sg:postcode":"9320",
    "sg:province":"Danmark",
    "wof:name":"Janes Handel & Import",
    "wof:placetype":"venue"
},
  "geometry": {"coordinates":[10.149682045,57.1684150696],"type":"Point"}
}