{
  "type": "Feature",
  "properties": {
    "addr:full":"Roskildevej 53 Frederikssund Danmark 3600",
    "addr:housenumber":"53",
    "addr:postcode":"3600",
    "addr:street":"Roskildevej",
    "iso:country":"DK",
    "sg:address":"Roskildevej 53",
    "sg:city":"Frederikssund",
    "sg:orig_category":"Engros handel",
    "sg:phone":"+45 47 31 56 87",
    "sg:postcode":"3600",
    "sg:province":"Danmark",
    "wof:name":"Fecomm ApS",
    "wof:placetype":"venue"
},
  "geometry": {"coordinates":[12.0734424591,55.8321075439],"type":"Point"}
}