{
  "type": "Feature",
  "properties": {
    "addr:full":"Algade 26 Middelfart Danmark 5500",
    "addr:housenumber":"26",
    "addr:postcode":"5500",
    "addr:street":"Algade",
    "iso:country":"DK",
    "sg:address":"Algade 26",
    "sg:city":"Middelfart",
    "sg:orig_category":"Materialister",
    "sg:phone":"+45 64 41 01 16",
    "sg:postcode":"5500",
    "sg:province":"Danmark",
    "wof:name":"Middelfart Matas",
    "wof:placetype":"venue"
},
  "geometry": {"coordinates":[9.7303524017,55.5056533813],"type":"Point"}
}