{
  "type": "Feature",
  "properties": {
    "addr:full":"Kannikeg\u00e5rdsvej 10, Bodilsker Nex\u00f8 Danmark 3730",
    "addr:housenumber":"10",
    "addr:postcode":"3730",
    "addr:street":"Kannikegaardsvej",
    "iso:country":"DK",
    "sg:address":"Kannikeg\u00e5rdsvej 10, Bodilsker",
    "sg:city":"Nex\u00f8",
    "sg:orig_category":"Cykler",
    "sg:phone":"+45 56 49 44 74",
    "sg:postcode":"3730",
    "sg:province":"Danmark",
    "sg:website":"www.bosscykler.dk",
    "wof:name":"Boss Cykler",
    "wof:placetype":"venue"
},
  "geometry": {"coordinates":[15.1096076965,55.0267219543],"type":"Point"}
}