{
  "type": "Feature",
  "properties": {
    "addr:full":"\u00d8stergade 32 Hammel Danmark 8450",
    "addr:housenumber":"32",
    "addr:postcode":"8450",
    "addr:street":"Ostergade",
    "iso:country":"DK",
    "sg:address":"\u00d8stergade 32",
    "sg:city":"Hammel",
    "sg:orig_category":"Materialister",
    "sg:phone":"+45 86 96 10 20",
    "sg:postcode":"8450",
    "sg:province":"Danmark",
    "wof:name":"Matas",
    "wof:placetype":"venue"
},
  "geometry": {"coordinates":[9.8678102493,56.2569351196],"type":"Point"}
}