{
  "type": "Feature",
  "properties": {
    "iso:country":"DK",
    "sg:address":"Gr\u00f8nnegade 19",
    "sg:city":"Faaborg",
    "sg:orig_category":"Blikkenslagere",
    "sg:phone":"+45 62 61 05 45",
    "sg:postcode":"5600",
    "sg:province":"Danmark",
    "wof:name":"Fentz & S\u00f8n, Chr.",
    "wof:placetype":"venue"
},
  "geometry": {"coordinates":[10.242646,55.096115],"type":"Point"}
}