{
  "type": "Feature",
  "properties": {
    "addr:full":"Strandgade 75 Helsing\u00f8r Danmark 3000",
    "addr:housenumber":"75",
    "addr:postcode":"3000",
    "addr:street":"Strandgade",
    "iso:country":"DK",
    "sg:address":"Strandgade 75",
    "sg:city":"Helsing\u00f8r",
    "sg:classifiers":[
        {
            "category":"Restaurant",
            "type":"Food & Drink"
        }
    ],
    "sg:phone":"+45 49 21 17 83",
    "sg:postcode":"3000",
    "sg:province":"Danmark",
    "wof:name":"Borgerkroen",
    "wof:placetype":"venue"
},
  "geometry": {"coordinates":[12.6138763428,56.0343055725],"type":"Point"}
}