{
  "type": "Feature",
  "properties": {
    "addr:full":"Margrethevej 7 B Hellerup Danmark 2900",
    "addr:housenumber":"7 b",
    "addr:postcode":"2900",
    "addr:street":"Margrethevej",
    "iso:country":"DK",
    "sg:address":"Margrethevej 7 B",
    "sg:city":"Hellerup",
    "sg:orig_category":"Kirkesogne",
    "sg:phone":"+45 39 62 11 41",
    "sg:postcode":"2900",
    "sg:province":"Danmark",
    "wof:name":"Hellerup Sogns Kirkekontor",
    "wof:placetype":"venue"
},
  "geometry": {"coordinates":[12.5730371475,55.7343902588],"type":"Point"}
}