{
  "type": "Feature",
  "properties": {
    "iso:country":"DK",
    "sg:address":"Grang\u00e5rdscentret 5",
    "sg:city":"St\u00f8vring",
    "sg:orig_category":"Revisorer",
    "sg:phone":"+45 98 37 32 22",
    "sg:postcode":"9530",
    "sg:province":"Danmark",
    "wof:name":"Nielsen & Christensen Statsautoriseret Revisionsaktieselskab",
    "wof:placetype":"venue"
},
  "geometry": {"coordinates":[-103.3109588623,34.3324546814],"type":"Point"}
}