{
  "type": "Feature",
  "properties": {
    "iso:country":"DK",
    "sg:address":"Haderslevvej 3, Friskmark",
    "sg:city":"Gram",
    "sg:orig_category":"Snedkermestre",
    "sg:phone":"+45 74 82 24 02",
    "sg:postcode":"6510",
    "sg:province":"Danmark",
    "wof:name":"H\u00e5ndv\u00e6rkerg\u00e5rden Peter Prinds ApS",
    "wof:placetype":"venue"
},
  "geometry": {"coordinates":[9.0481977463,55.2877807617],"type":"Point"}
}