{
  "type": "Feature",
  "properties": {
    "addr:full":"Prangervej 25, Skr\u00e6 Kjellerup Danmark 8620",
    "addr:housenumber":"25",
    "addr:postcode":"8620",
    "addr:street":"Prangervej;Skrae",
    "iso:country":"DK",
    "sg:address":"Prangervej 25, Skr\u00e6",
    "sg:city":"Kjellerup",
    "sg:orig_category":"Murermestre",
    "sg:phone":"+45 86 88 02 07",
    "sg:postcode":"8620",
    "sg:province":"Danmark",
    "wof:name":"Mogensen, Murerfirmaet",
    "wof:placetype":"venue"
},
  "geometry": {"coordinates":[9.430934906,56.2877655029],"type":"Point"}
}