{
  "type": "Feature",
  "properties": {
    "iso:country":"DK",
    "sg:address":"Riis Toft 12 A",
    "sg:city":"Kolding",
    "sg:orig_category":"Tandklinikker, Kommunale",
    "sg:phone":"+45 79 30 25 80",
    "sg:postcode":"6000",
    "sg:province":"Danmark",
    "wof:name":"Centralklinikken",
    "wof:placetype":"venue"
},
  "geometry": {"coordinates":[9.4669094086,55.4835739136],"type":"Point"}
}