{
  "type": "Feature",
  "properties": {
    "addr:full":"Storegade 18 Glums\u00f8 Danmark 4171",
    "addr:housenumber":"18",
    "addr:postcode":"4171",
    "addr:street":"Storegade",
    "iso:country":"DK",
    "sg:address":"Storegade 18",
    "sg:city":"Glums\u00f8",
    "sg:orig_category":"Pizzeriaer",
    "sg:phone":"+45 57 64 65 19",
    "sg:postcode":"4171",
    "sg:province":"Danmark",
    "wof:name":"Glums\u00f8 Pizza House",
    "wof:placetype":"venue"
},
  "geometry": {"coordinates":[11.688996315,55.3540000916],"type":"Point"}
}