{
  "type": "Feature",
  "properties": {
    "addr:full":"Tr\u00f8jborgvej 75 H \u00c5rhus N Danmark 8200",
    "addr:housenumber":"75 h",
    "addr:postcode":"8200",
    "addr:street":"Trojborgvej",
    "iso:country":"DK",
    "sg:address":"Tr\u00f8jborgvej 75 H",
    "sg:city":"\u00c5rhus N",
    "sg:classifiers":[
        {
            "category":"Personal",
            "subcategory":"Massage",
            "type":"Services"
        }
    ],
    "sg:phone":"+45 86 13 49 99",
    "sg:postcode":"8200",
    "sg:province":"Danmark",
    "wof:name":"Norsk Sekvenstr\u00e6ning ApS",
    "wof:placetype":"venue"
},
  "geometry": {"coordinates":[4.9393601418,49.7092018127],"type":"Point"}
}