{
  "type": "Feature",
  "properties": {
    "addr:full":"Tagensvej 100 K\u00f8benhavn N Danmark 2200",
    "addr:housenumber":"100",
    "addr:postcode":"2200",
    "addr:street":"Tagensvej;Kobenhavn N Danmark",
    "iso:country":"DK",
    "sg:address":"Tagensvej 100",
    "sg:city":"K\u00f8benhavn N",
    "sg:classifiers":[
        {
            "category":"Restaurant",
            "type":"Food & Drink"
        }
    ],
    "sg:phone":"+45 35 85 78 34",
    "sg:postcode":"2200",
    "sg:province":"Danmark",
    "wof:name":"Vagabondos Pizza Bar",
    "wof:placetype":"venue"
},
  "geometry": {"coordinates":[-102.49151611329999,48.8652877808],"type":"Point"}
}