{
  "type": "Feature",
  "properties": {
    "addr:full":"Dalsagervej 18 Hirtshals Danmark 9850",
    "addr:housenumber":"18",
    "addr:postcode":"9850",
    "addr:street":"Dalsagervej",
    "iso:country":"DK",
    "sg:address":"Dalsagervej 18",
    "sg:city":"Hirtshals",
    "sg:orig_category":"Emballage",
    "sg:phone":"+45 98 94 39 55",
    "sg:postcode":"9850",
    "sg:province":"Danmark",
    "wof:name":"Sundolitt as",
    "wof:placetype":"venue"
},
  "geometry": {"coordinates":[9.9834251404,57.5727386475],"type":"Point"}
}