{
  "type": "Feature",
  "properties": {
    "iso:country":"DK",
    "sg:address":"Gammelby Ringvej 11",
    "sg:city":"Esbjerg",
    "sg:orig_category":"Blikkenslagere",
    "sg:phone":"+45 75 13 35 68",
    "sg:postcode":"6700",
    "sg:province":"Danmark",
    "wof:name":"Andersen, Dieter Wemmer",
    "wof:placetype":"venue"
},
  "geometry": {"coordinates":[8.467012,55.463181],"type":"Point"}
}