{
  "type": "Feature",
  "properties": {
    "addr:full":"Lyngby Hovedgade 42 Kongens Lyngby Danmark 2800",
    "addr:housenumber":"42",
    "addr:postcode":"2800",
    "addr:street":"Lyngby Hovedgade",
    "iso:country":"DK",
    "sg:address":"Lyngby Hovedgade 42",
    "sg:city":"Kongens Lyngby",
    "sg:orig_category":"Pizzeriaer",
    "sg:phone":"+45 45 87 81 76",
    "sg:postcode":"2800",
    "sg:province":"Danmark",
    "wof:name":"Lyngby Pizzeria",
    "wof:placetype":"venue"
},
  "geometry": {"coordinates":[12.5010023117,55.7721939087],"type":"Point"}
}