{
  "type": "Feature",
  "properties": {
    "addr:full":"Krikvej 58 A Vestervig Danmark 7770",
    "addr:housenumber":"58 a",
    "addr:postcode":"7770",
    "addr:street":"Krikvej",
    "iso:country":"DK",
    "sg:address":"Krikvej 58 A",
    "sg:city":"Vestervig",
    "sg:classifiers":[
        {
            "category":"Retail",
            "subcategory":"Storage",
            "type":"Services"
        }
    ],
    "sg:phone":"+45 96 88 40 50",
    "sg:postcode":"7770",
    "sg:province":"Danmark",
    "sg:tags":[
        "edb",
        "hardware",
        "-"
    ],
    "wof:name":"Nordvest Data",
    "wof:placetype":"venue"
},
  "geometry": {"coordinates":[8.2752199173,56.7716445923],"type":"Point"}
}