{
  "type": "Feature",
  "properties": {
    "addr:full":"v/ Aase Harekilde-Petersen, Lundby Hovedgade 69 Lundby Danmark 4750",
    "addr:housenumber":"69",
    "addr:postcode":"4750",
    "addr:street":"Lundby Hovedgade",
    "iso:country":"DK",
    "sg:address":"v/ Aase Harekilde-Petersen, Lundby Hovedgade 69",
    "sg:city":"Lundby",
    "sg:orig_category":"\u00c3\u02dcvrige foreninger",
    "sg:phone":"+45 55 76 33 55",
    "sg:postcode":"4750",
    "sg:province":"Danmark",
    "wof:name":"Dansk Edgar Cayce Selskab",
    "wof:placetype":"venue"
},
  "geometry": {"coordinates":[11.8101682663,55.1197814941],"type":"Point"}
}