{
  "type": "Feature",
  "properties": {
    "iso:country":"DK",
    "sg:address":"Gruppeleder: Lisbeth Jespersen, \u00d8ster Lemvej 6",
    "sg:city":"Lem",
    "sg:orig_category":"Spejderkorps",
    "sg:phone":"+45 97 34 34 60",
    "sg:postcode":"6940",
    "sg:province":"Danmark",
    "wof:name":"KFUM Spejderne - Lem Gruppe",
    "wof:placetype":"venue"
},
  "geometry": {"coordinates":[8.3932304382,56.0546112061],"type":"Point"}
}