{
  "type": "Feature",
  "properties": {
    "iso:country":"DK",
    "sg:address":"Vesterbro 61 B",
    "sg:city":"Aalborg",
    "sg:orig_category":"INGENI\u00c3\u02dcRER",
    "sg:phone":"+45 98 16 33 11",
    "sg:postcode":"9000",
    "sg:province":"Danmark",
    "wof:name":"Lindgaard Christensen A/S",
    "wof:placetype":"venue"
},
  "geometry": {"coordinates":[9.9145803452,57.047290802],"type":"Point"}
}