{
  "type": "Feature",
  "properties": {
    "addr:full":"Strandgade 22 Assens Danmark 5610",
    "addr:housenumber":"22",
    "addr:postcode":"5610",
    "addr:street":"Strandgade",
    "iso:country":"DK",
    "sg:address":"Strandgade 22",
    "sg:city":"Assens",
    "sg:orig_category":"HOTELS: OG MOTELLER",
    "sg:phone":"+45 64 71 10 89",
    "sg:postcode":"5610",
    "sg:province":"Danmark",
    "wof:name":"Marcussens Hotel",
    "wof:placetype":"venue"
},
  "geometry": {"coordinates":[9.8905677795,55.2708282471],"type":"Point"}
}