{
  "type": "Feature",
  "properties": {
    "iso:country":"DK",
    "sg:address":"Kl\u00f8vertoften 76",
    "sg:city":"Skovlunde",
    "sg:orig_category":"INGENI\u00c3\u02dcRER",
    "sg:phone":"+45 44 94 29 40",
    "sg:postcode":"2740",
    "sg:province":"Danmark",
    "wof:name":"Langvad, Jens",
    "wof:placetype":"venue"
},
  "geometry": {"coordinates":[12.3870296478,55.7147789001],"type":"Point"}
}