{
  "type": "Feature",
  "properties": {
    "iso:country":"DK",
    "sg:address":"Fmd.: Olav Grue, T\u00f8nnesvej 4, S\u00f8hus",
    "sg:city":"Odense N",
    "sg:orig_category":"Kulturelle foreninger",
    "sg:phone":"+45 66 18 98 08",
    "sg:postcode":"5270",
    "sg:province":"Danmark",
    "wof:name":"Odense H\u00f8jskoleforening",
    "wof:placetype":"venue"
},
  "geometry": {"coordinates":[10.3306798935,55.4711418152],"type":"Point"}
}