{
  "type": "Feature",
  "properties": {
    "addr:full":"Ny \u00d8stergade 11 Roskilde Danmark 4000",
    "addr:housenumber":"11",
    "addr:postcode":"4000",
    "addr:street":"Ostergade",
    "iso:country":"DK",
    "sg:address":"Ny \u00d8stergade 11",
    "sg:city":"Roskilde",
    "sg:orig_category":"Revisorer",
    "sg:phone":"+45 46 35 00 35",
    "sg:postcode":"4000",
    "sg:province":"Danmark",
    "sg:website":"www.ey.dk",
    "wof:name":"Ernst & Young",
    "wof:placetype":"venue"
},
  "geometry": {"coordinates":[12.0909376144,55.6404838562],"type":"Point"}
}