{
  "type": "Feature",
  "properties": {
    "addr:full":"Kass.: Flemming Rasmussen, Vesterbro 48, kld. Nyk\u00f8bing Danmark 4500",
    "addr:housenumber":"48 kld. nykobing",
    "addr:postcode":"4500",
    "addr:street":"Kass.;Vesterbro",
    "iso:country":"DK",
    "sg:address":"Kass.: Flemming Rasmussen, Vesterbro 48, kld.",
    "sg:city":"Nyk\u00f8bing",
    "sg:orig_category":"Hobbybetonede foreninger",
    "sg:phone":"+45 40 46 86 79",
    "sg:postcode":"4500",
    "sg:province":"Danmark",
    "wof:name":"Eksperimenterende Danske Radioamat\u00f8rer (EDR), Odsherred",
    "wof:placetype":"venue"
},
  "geometry": {"coordinates":[11.6107749939,55.938621521],"type":"Point"}
}