{
  "type": "Feature",
  "properties": {
    "addr:full":"Fmd.: Hans J. Kj\u00e6rg\u00e5rd, Uglevej 21 Fars\u00f8 Danmark 9640",
    "addr:housenumber":"21",
    "addr:postcode":"9640",
    "addr:street":"Uglevej",
    "iso:country":"DK",
    "sg:address":"Fmd.: Hans J. Kj\u00e6rg\u00e5rd, Uglevej 21",
    "sg:city":"Fars\u00f8",
    "sg:orig_category":"Kirkelige foreninger",
    "sg:phone":"+45 98 63 31 35",
    "sg:postcode":"9640",
    "sg:province":"Danmark",
    "wof:name":"Indre Missions Samfund - Fars\u00f8",
    "wof:placetype":"venue"
},
  "geometry": {"coordinates":[-109.44831848139999,42.1062355042],"type":"Point"}
}