{
  "type": "Feature",
  "properties": {
    "addr:full":"N\u00f8rrebrogade 151 A K\u00f8benhavn N Danmark 2200",
    "addr:housenumber":"151 a",
    "addr:postcode":"2200",
    "addr:street":"Norrebrogade;Kobenhavn N Danmark",
    "iso:country":"DK",
    "sg:address":"N\u00f8rrebrogade 151 A",
    "sg:city":"K\u00f8benhavn N",
    "sg:orig_category":"Cafeer",
    "sg:phone":"+45 35 85 46 47",
    "sg:postcode":"2200",
    "sg:province":"Danmark",
    "wof:name":"Caf\u00e9 Runddelen",
    "wof:placetype":"venue"
},
  "geometry": {"coordinates":[-76.4168395996,37.452419281],"type":"Point"}
}