{
  "type": "Feature",
  "properties": {
    "addr:full":"Rosensgade 26, 1. \u00c5rhus C Danmark 8000",
    "addr:housenumber":"26 1",
    "addr:postcode":"8000",
    "addr:street":"Rosensgade",
    "iso:country":"DK",
    "sg:address":"Rosensgade 26, 1.",
    "sg:city":"\u00c5rhus C",
    "sg:orig_category":"Ejendomsadministration",
    "sg:phone":"+45 86 18 34 88",
    "sg:postcode":"8000",
    "sg:province":"Danmark",
    "wof:name":"H & W Holding \u00c5rhus ApS",
    "wof:placetype":"venue"
},
  "geometry": {"coordinates":[4.717400074,49.7588005066],"type":"Point"}
}