{
  "type": "Feature",
  "properties": {
    "addr:full":"\u00d8ster Bordingvej 39 Silkeborg Danmark 8600",
    "addr:housenumber":"39",
    "addr:postcode":"8600",
    "addr:street":"Oster Bordingvej",
    "iso:country":"DK",
    "sg:address":"\u00d8ster Bordingvej 39",
    "sg:city":"Silkeborg",
    "sg:orig_category":"Forsamlingshuse",
    "sg:phone":"+45 86 85 60 19",
    "sg:postcode":"8600",
    "sg:province":"Danmark",
    "wof:name":"Rullende K\u00f8kken, Det",
    "wof:placetype":"venue"
},
  "geometry": {"coordinates":[9.4885873795,56.1806869507],"type":"Point"}
}