{
  "type": "Feature",
  "properties": {
    "addr:full":"Vestergade 52 Randers Danmark 8900",
    "addr:housenumber":"52",
    "addr:postcode":"8900",
    "addr:street":"Vestergade",
    "iso:country":"DK",
    "sg:address":"Vestergade 52",
    "sg:city":"Randers",
    "sg:classifiers":[
        {
            "category":"Restaurant",
            "type":"Food & Drink"
        }
    ],
    "sg:phone":"+45 86 42 32 39",
    "sg:postcode":"8900",
    "sg:province":"Danmark",
    "wof:name":"Casablanca",
    "wof:placetype":"venue"
},
  "geometry": {"coordinates":[10.0264911652,56.4616127014],"type":"Point"}
}