{
  "type": "Feature",
  "properties": {
    "iso:country":"DK",
    "sg:address":"Fur Landevej 37, \u00d8. Lyby",
    "sg:city":"Skive",
    "sg:orig_category":"Stutterier",
    "sg:phone":"+45 97 58 42 85",
    "sg:postcode":"7800",
    "sg:province":"Danmark",
    "wof:name":"Laursen, J\u00f8rn",
    "wof:placetype":"venue"
},
  "geometry": {"coordinates":[9.0320358276,56.5666427612],"type":"Point"}
}