{
  "type": "Feature",
  "properties": {
    "iso:country":"DK",
    "sg:address":"Islandsgade 2",
    "sg:city":"Aalborg",
    "sg:orig_category":"Bodegaer",
    "sg:phone":"+45 98 11 48 80",
    "sg:postcode":"9000",
    "sg:province":"Danmark",
    "wof:name":"Kroghs Vinstue",
    "wof:placetype":"venue"
},
  "geometry": {"coordinates":[9.943312645,57.0452804565],"type":"Point"}
}