{
  "type": "Feature",
  "properties": {
    "iso:country":"DK",
    "sg:address":"Tranderupgade 61",
    "sg:city":"\u00c6r\u00f8sk\u00f8bing",
    "sg:orig_category":"Efterskoler",
    "sg:phone":"+45 62 52 17 24",
    "sg:postcode":"5970",
    "sg:province":"Danmark",
    "wof:name":"\u00c6r\u00f8 Efterskole",
    "wof:placetype":"venue"
},
  "geometry": {"coordinates":[-114.0767440796,46.4432487488],"type":"Point"}
}