{
  "type": "Feature",
  "properties": {
    "addr:full":"A. C. Hansensvej 7 Frederikssund Danmark 3600",
    "addr:housenumber":"7",
    "addr:postcode":"3600",
    "addr:street":"A. C. Hansensvej",
    "iso:country":"DK",
    "sg:address":"A. C. Hansensvej 7",
    "sg:city":"Frederikssund",
    "sg:orig_category":"Vaskeriservice",
    "sg:phone":"+45 47 38 44 22",
    "sg:postcode":"3600",
    "sg:province":"Danmark",
    "wof:name":"D.V.T. Sorttech A/S",
    "wof:placetype":"venue"
},
  "geometry": {"coordinates":[12.0666389465,55.8323554993],"type":"Point"}
}