{
  "type": "Feature",
  "properties": {
    "addr:full":"Domkirkepladsen 0 Viborg Danmark 8800",
    "addr:housenumber":"0",
    "addr:postcode":"8800",
    "addr:street":"Domkirkepladsen",
    "iso:country":"DK",
    "sg:address":"Domkirkepladsen 0",
    "sg:city":"Viborg",
    "sg:orig_category":"Kirker",
    "sg:postcode":"8800",
    "sg:province":"Danmark",
    "wof:name":"Viborg Domkirke",
    "wof:placetype":"venue"
},
  "geometry": {"coordinates":[9.4123296738,56.4510803223],"type":"Point"}
}