{
  "type": "Feature",
  "properties": {
    "addr:full":"(Formand Thomas Larsen), Messinavej 22 st -4 K\u00f8benhavn S Danmark 2300",
    "addr:housenumber":"22;-4",
    "addr:postcode":"2300",
    "addr:street":"Messinavej;St;Kobenhavn S Danmark",
    "iso:country":"DK",
    "sg:address":"(Formand Thomas Larsen), Messinavej 22 st -4",
    "sg:city":"K\u00f8benhavn S",
    "sg:orig_category":"Foreninger og organisationer",
    "sg:phone":"+45 32 55 42 23",
    "sg:postcode":"2300",
    "sg:province":"Danmark",
    "sg:website":"www.24timers-mcbloeb.dk",
    "wof:name":"H\u00f8rsholm Mountainbike Klub",
    "wof:placetype":"venue"
},
  "geometry": {"coordinates":[-78.1299133301,36.7267417908],"type":"Point"}
}