{
  "type": "Feature",
  "properties": {
    "addr:full":"Stensballe Strandvej 51 Horsens Danmark 8700",
    "addr:housenumber":"51",
    "addr:postcode":"8700",
    "addr:street":"Stensballe Strandvej",
    "iso:country":"DK",
    "sg:address":"Stensballe Strandvej 51",
    "sg:city":"Horsens",
    "sg:orig_category":"EDB - udstyr",
    "sg:phone":"+45 75 65 81 10",
    "sg:postcode":"8700",
    "sg:province":"Danmark",
    "wof:name":"Rein Computer",
    "wof:placetype":"venue"
},
  "geometry": {"coordinates":[9.9067993164,55.8660354614],"type":"Point"}
}