{
  "type": "Feature",
  "properties": {
    "addr:full":"Gransvinget 69 Ebeltoft Danmark 8400",
    "addr:housenumber":"69",
    "addr:postcode":"8400",
    "addr:street":"Gransvinget",
    "iso:country":"DK",
    "sg:address":"Gransvinget 69",
    "sg:city":"Ebeltoft",
    "sg:orig_category":"Handicapboliger",
    "sg:phone":"+45 86 34 51 22",
    "sg:postcode":"8400",
    "sg:province":"Danmark",
    "wof:name":"Bof\u00e6llesskaberne i Ebeltoft",
    "wof:placetype":"venue"
},
  "geometry": {"coordinates":[10.6832008362,56.1792907715],"type":"Point"}
}