{
  "type": "Feature",
  "properties": {
    "addr:full":"Fmd.: Helle Pr\u00e6st Pedersen, Kong Christians Alle 11 Frederikshavn Danmark 9900",
    "addr:housenumber":"11",
    "addr:postcode":"9900",
    "addr:street":"Helle;Kong Christians Alle",
    "iso:country":"DK",
    "sg:address":"Fmd.: Helle Pr\u00e6st Pedersen, Kong Christians Alle 11",
    "sg:city":"Frederikshavn",
    "sg:orig_category":"Husflidsforeninger",
    "sg:phone":"+45 98 43 07 31",
    "sg:postcode":"9900",
    "sg:province":"Danmark",
    "wof:name":"S\u00f8mandskoneforeningen af 1976 Frederikshavn afdeling",
    "wof:placetype":"venue"
},
  "geometry": {"coordinates":[10.5362997055,57.4396400452],"type":"Point"}
}