{
  "type": "Feature",
  "properties": {
    "iso:country":"DK",
    "sg:address":"Martin Hansens Vej 32",
    "sg:city":"Ebeltoft",
    "sg:orig_category":"Blikkenslagere",
    "sg:phone":"+45 86 34 46 00",
    "sg:postcode":"8400",
    "sg:province":"Danmark",
    "wof:name":"A.G. Service",
    "wof:placetype":"venue"
},
  "geometry": {"coordinates":[10.68671,56.186741],"type":"Point"}
}