{
  "type": "Feature",
  "properties": {
    "addr:full":"\u00d8rnevej 2 Struer Danmark 7600",
    "addr:housenumber":"2",
    "addr:postcode":"7600",
    "addr:street":"Ornevej",
    "iso:country":"DK",
    "sg:address":"\u00d8rnevej 2",
    "sg:city":"Struer",
    "sg:orig_category":"Homeparties",
    "sg:phone":"+45 97 85 07 30",
    "sg:postcode":"7600",
    "sg:province":"Danmark",
    "wof:name":"Andersen, M\u00f8rch",
    "wof:placetype":"venue"
},
  "geometry": {"coordinates":[8.5946903229,56.491191864],"type":"Point"}
}