{
  "type": "Feature",
  "properties": {
    "iso:country":"DK",
    "sg:address":"Skovr\u00e6kken 9, Vall\u00f8",
    "sg:city":"K\u00f8ge",
    "sg:orig_category":"Tyverisikring",
    "sg:phone":"+45 70 23 50 38",
    "sg:postcode":"4600",
    "sg:province":"Danmark",
    "wof:name":"MM Sikring ApS",
    "wof:placetype":"venue"
},
  "geometry": {"coordinates":[12.2328977585,55.4053459167],"type":"Point"}
}