{
  "type": "Feature",
  "properties": {
    "iso:country":"DK",
    "sg:address":"Friseng\u00e5rdsvej 91",
    "sg:city":"Nyborg",
    "sg:orig_category":"Supermarkeder",
    "sg:phone":"+45 65 31 07 31",
    "sg:postcode":"5800",
    "sg:province":"Danmark",
    "wof:name":"Aktiv Super",
    "wof:placetype":"venue"
},
  "geometry": {"coordinates":[10.7970638275,55.3218536377],"type":"Point"}
}