{
  "type": "Feature",
  "properties": {
    "iso:country":"DK",
    "sg:address":"Bastrup Skolevej 24",
    "sg:city":"Vamdrup",
    "sg:orig_category":"Hunde, artikler for",
    "sg:phone":"+45 75 58 31 22",
    "sg:postcode":"6580",
    "sg:province":"Danmark",
    "wof:name":"Dog Butterfly",
    "wof:placetype":"venue"
},
  "geometry": {"coordinates":[9.2591733932,55.410900116],"type":"Point"}
}