{
  "type": "Feature",
  "properties": {
    "addr:full":"K\u00e6rvang 7, Sejerslev Nyk\u00f8bing Danmark 7900",
    "addr:housenumber":"7",
    "addr:postcode":"7900",
    "addr:street":"Kaervang",
    "iso:country":"DK",
    "sg:address":"K\u00e6rvang 7, Sejerslev",
    "sg:city":"Nyk\u00f8bing",
    "sg:orig_category":"Campingpladser",
    "sg:phone":"+45 97 75 10 93",
    "sg:postcode":"7900",
    "sg:province":"Danmark",
    "wof:name":"Gerlis Camping",
    "wof:placetype":"venue"
},
  "geometry": {"coordinates":[8.8630752563,56.7945251465],"type":"Point"}
}