{
  "type": "Feature",
  "properties": {
    "addr:full":"Anl\u00e6gsvej 7 Ringsted Danmark 4100",
    "addr:housenumber":"7",
    "addr:postcode":"4100",
    "addr:street":"Anlaegsvej",
    "iso:country":"DK",
    "sg:address":"Anl\u00e6gsvej 7",
    "sg:city":"Ringsted",
    "sg:orig_category":"Fritidsklubber",
    "sg:phone":"+45 57 62 71 80",
    "sg:postcode":"4100",
    "sg:province":"Danmark",
    "wof:name":"H\u00f8jbohus Fritidshjem og -klub",
    "wof:placetype":"venue"
},
  "geometry": {"coordinates":[11.7875862122,55.4458961487],"type":"Point"}
}