{
  "type": "Feature",
  "properties": {
    "addr:full":"Fmd.: Hardy Thorup, Jernbanegade 28 Vamdrup Danmark 6580",
    "addr:housenumber":"28",
    "addr:postcode":"6580",
    "addr:street":"Jernbanegade",
    "iso:country":"DK",
    "sg:address":"Fmd.: Hardy Thorup, Jernbanegade 28",
    "sg:city":"Vamdrup",
    "sg:orig_category":"Faglige organisationer og foreninger",
    "sg:phone":"+45 75 58 18 65",
    "sg:postcode":"6580",
    "sg:province":"Danmark",
    "wof:name":"LO Vamdrup/Lunderskov",
    "wof:placetype":"venue"
},
  "geometry": {"coordinates":[9.2839107513,55.4266548157],"type":"Point"}
}