{
  "type": "Feature",
  "properties": {
    "addr:full":"Svinkl\u00f8vvej 102, Kollerup Fjerritslev Danmark 9690",
    "addr:housenumber":"102",
    "addr:postcode":"9690",
    "addr:street":"Svinklovvej;Kollerup",
    "iso:country":"DK",
    "sg:address":"Svinkl\u00f8vvej 102, Kollerup",
    "sg:city":"Fjerritslev",
    "sg:orig_category":"Psykoterapi",
    "sg:phone":"+45 98 21 14 53",
    "sg:postcode":"9690",
    "sg:province":"Danmark",
    "sg:website":"www.brobygger.dk",
    "wof:name":"S\u00f8ndergaard, Inger K.",
    "wof:placetype":"venue"
},
  "geometry": {"coordinates":[9.2667350769,57.0882301331],"type":"Point"}
}