{
  "type": "Feature",
  "properties": {
    "addr:full":"Gaden 62 Sindal Danmark 9870",
    "addr:housenumber":"62",
    "addr:postcode":"9870",
    "addr:street":"Gaden",
    "iso:country":"DK",
    "sg:address":"Gaden 62",
    "sg:city":"Sindal",
    "sg:orig_category":"Traktorer",
    "sg:phone":"+45 98 93 63 66",
    "sg:postcode":"9870",
    "sg:province":"Danmark",
    "wof:name":"Sindal Traktorkompagni A/S",
    "wof:placetype":"venue"
},
  "geometry": {"coordinates":[10.2020931244,57.4876937866],"type":"Point"}
}