{
  "type": "Feature",
  "properties": {
    "iso:country":"DK",
    "sg:address":"Skivevej 7, Selde",
    "sg:city":"Roslev",
    "sg:orig_category":"Brugsforeninger",
    "sg:phone":"+45 97 59 60 04",
    "sg:postcode":"7870",
    "sg:province":"Danmark",
    "wof:name":"Lokal Brugsen",
    "wof:placetype":"venue"
},
  "geometry": {"coordinates":[8.8715353012,56.7570304871],"type":"Point"}
}