{
  "type": "Feature",
  "properties": {
    "addr:full":"Tuenvej 23 Frederikshavn Danmark 9900",
    "addr:housenumber":"23",
    "addr:postcode":"9900",
    "addr:street":"Tuenvej",
    "iso:country":"DK",
    "sg:address":"Tuenvej 23",
    "sg:city":"Frederikshavn",
    "sg:orig_category":"Kirker",
    "sg:postcode":"9900",
    "sg:province":"Danmark",
    "wof:name":"Elling Kirke",
    "wof:placetype":"venue"
},
  "geometry": {"coordinates":[10.4732599258,57.475189209],"type":"Point"}
}