{
  "type": "Feature",
  "properties": {
    "addr:full":"Stabelsvej 2, Mejlby Spentrup Danmark 8981",
    "addr:housenumber":"2",
    "addr:postcode":"8981",
    "addr:street":"Stabelsvej;Mejlby",
    "iso:country":"DK",
    "sg:address":"Stabelsvej 2, Mejlby",
    "sg:city":"Spentrup",
    "sg:orig_category":"Murermestre",
    "sg:phone":"+45 86 44 24 29",
    "sg:postcode":"8981",
    "sg:province":"Danmark",
    "wof:name":"Boel, Ole",
    "wof:placetype":"venue"
},
  "geometry": {"coordinates":[10.0408000946,56.5371284485],"type":"Point"}
}