{
  "type": "Feature",
  "properties": {
    "iso:country":"DK",
    "sg:address":"Fuglebjerglundvej 5",
    "sg:city":"Fuglebjerg",
    "sg:orig_category":"Kul og koks",
    "sg:phone":"+45 55 45 32 71",
    "sg:postcode":"4250",
    "sg:province":"Danmark",
    "wof:name":"Michael og Co. I/S, Brdr.",
    "wof:placetype":"venue"
},
  "geometry": {"coordinates":[11.5512504578,55.3197479248],"type":"Point"}
}