{
  "type": "Feature",
  "properties": {
    "addr:full":"Hulvej 33 Horsens Danmark 8700",
    "addr:housenumber":"33",
    "addr:postcode":"8700",
    "addr:street":"Hulvej",
    "iso:country":"DK",
    "sg:address":"Hulvej 33",
    "sg:city":"Horsens",
    "sg:orig_category":"Antikviteter",
    "sg:phone":"+45 75 60 19 60",
    "sg:postcode":"8700",
    "sg:province":"Danmark",
    "wof:name":"Urlev Antik",
    "wof:placetype":"venue"
},
  "geometry": {"coordinates":[9.8578577042,55.8648986816],"type":"Point"}
}