{
  "type": "Feature",
  "properties": {
    "iso:country":"DK",
    "sg:address":"Merkurvej 401",
    "sg:city":"Herning",
    "sg:orig_category":"EDB - udstyr",
    "sg:phone":"+45 97 12 54 33",
    "sg:postcode":"7400",
    "sg:province":"Danmark",
    "wof:name":"Center Data A/S",
    "wof:placetype":"venue"
},
  "geometry": {"coordinates":[8.9993495941,56.1350402832],"type":"Point"}
}