{
  "type": "Feature",
  "properties": {
    "addr:full":"Vester S\u00f8gade 10 K\u00f8benhavn Danmark 1601",
    "addr:housenumber":"10;1601",
    "addr:street":"Sogade",
    "iso:country":"DK",
    "sg:address":"Vester S\u00f8gade 10",
    "sg:city":"K\u00f8benhavn",
    "sg:orig_category":"Statslige direktorater og styrelser",
    "sg:phone":"+45 33 93 52 00",
    "sg:postcode":"1601",
    "sg:province":"Danmark",
    "wof:name":"Sund & B\u00e6lt Holding A/S",
    "wof:placetype":"venue"
},
  "geometry": {"coordinates":[-85.2299499512,37.1363105774],"type":"Point"}
}