{
  "type": "Feature",
  "properties": {
    "iso:country":"DK",
    "sg:address":"F\u00e5borgvej 113",
    "sg:city":"Vester Skerninge",
    "sg:orig_category":"Regnskabsassistance",
    "sg:phone":"+45 62 24 32 70",
    "sg:postcode":"5762",
    "sg:province":"Danmark",
    "wof:name":"E.J Kontor-Assistance ApS",
    "wof:placetype":"venue"
},
  "geometry": {"coordinates":[10.4360733032,55.0749359131],"type":"Point"}
}