{
  "type": "Feature",
  "properties": {
    "addr:full":"Bottrupvej 48, Bottrup L\u00f8sning Danmark 8723",
    "addr:housenumber":"48",
    "addr:postcode":"8723",
    "addr:street":"Bottrupvej",
    "iso:country":"DK",
    "sg:address":"Bottrupvej 48, Bottrup",
    "sg:city":"L\u00f8sning",
    "sg:orig_category":"Skilte",
    "sg:phone":"+45 76 74 30 30",
    "sg:postcode":"8723",
    "sg:province":"Danmark",
    "sg:website":"www.hm-grafisk.dk",
    "wof:name":"HM Grafisk",
    "wof:placetype":"venue"
},
  "geometry": {"coordinates":[9.7620611191,55.8105201721],"type":"Point"}
}