{
  "type": "Feature",
  "properties": {
    "iso:country":"DK",
    "sg:address":"S\u00f8ndergade 9",
    "sg:city":"Herning",
    "sg:orig_category":"Sko",
    "sg:phone":"+45 97 12 11 77",
    "sg:postcode":"7400",
    "sg:province":"Danmark",
    "wof:name":"Engelbredt Sko",
    "wof:placetype":"venue"
},
  "geometry": {"coordinates":[8.9760913849,56.1360664368],"type":"Point"}
}