{
  "type": "Feature",
  "properties": {
    "addr:full":"Strandgade 69 A Helsing\u00f8r Danmark 3000",
    "addr:housenumber":"69 a",
    "addr:postcode":"3000",
    "addr:street":"Strandgade",
    "iso:country":"DK",
    "sg:address":"Strandgade 69 A",
    "sg:city":"Helsing\u00f8r",
    "sg:orig_category":"Videobutikker og -klubber",
    "sg:phone":"+45 49 21 04 27",
    "sg:postcode":"3000",
    "sg:province":"Danmark",
    "wof:name":"Bogart Video",
    "wof:placetype":"venue"
},
  "geometry": {"coordinates":[12.6133966446,56.0341911316],"type":"Point"}
}