{
  "type": "Feature",
  "properties": {
    "addr:full":"Fynsvej 1 Brande Danmark 7330",
    "addr:housenumber":"1",
    "addr:postcode":"7330",
    "addr:street":"Fynsvej",
    "iso:country":"DK",
    "sg:address":"Fynsvej 1",
    "sg:city":"Brande",
    "sg:orig_category":"Landbrugsmaskiner",
    "sg:phone":"+45 97 18 21 00",
    "sg:postcode":"7330",
    "sg:province":"Danmark",
    "wof:name":"Brande Maskincenter",
    "wof:placetype":"venue"
},
  "geometry": {"coordinates":[9.1565237045,55.9278526306],"type":"Point"}
}