{
  "type": "Feature",
  "properties": {
    "addr:full":"Stadion All\u00e9 1 Grenaa Danmark 8500",
    "addr:housenumber":"1",
    "addr:postcode":"8500",
    "addr:street":"Stadion Alle\u0301",
    "iso:country":"DK",
    "sg:address":"Stadion All\u00e9 1",
    "sg:city":"Grenaa",
    "sg:orig_category":"Skolefritidsordninger",
    "sg:postcode":"8500",
    "sg:province":"Danmark",
    "wof:name":"Info'en",
    "wof:placetype":"venue"
},
  "geometry": {"coordinates":[10.8862924576,56.405632019],"type":"Point"}
}