{
  "type": "Feature",
  "properties": {
    "addr:full":"Strandvejen 196, Hasmark Otterup Danmark 5450",
    "addr:housenumber":"196",
    "addr:postcode":"5450",
    "addr:street":"Strandvejen;Hasmark",
    "iso:country":"DK",
    "sg:address":"Strandvejen 196, Hasmark",
    "sg:city":"Otterup",
    "sg:orig_category":"Slagter og viktualie",
    "sg:phone":"+45 64 82 14 28",
    "sg:postcode":"5450",
    "sg:province":"Danmark",
    "wof:name":"Hasmark Slagterforretning",
    "wof:placetype":"venue"
},
  "geometry": {"coordinates":[10.4545049667,55.5641746521],"type":"Point"}
}