{
  "type": "Feature",
  "properties": {
    "addr:full":"Hesselhoved 10, Verninge Tommerup Danmark 5690",
    "addr:housenumber":"10",
    "addr:postcode":"5690",
    "addr:street":"Hesselhoved;Verninge",
    "iso:country":"DK",
    "sg:address":"Hesselhoved 10, Verninge",
    "sg:city":"Tommerup",
    "sg:orig_category":"Akvarier",
    "sg:phone":"+45 64 75 16 92",
    "sg:postcode":"5690",
    "sg:province":"Danmark",
    "wof:name":"Verninge Fisk og Akvariehandel",
    "wof:placetype":"venue"
},
  "geometry": {"coordinates":[10.2489509583,55.3236503601],"type":"Point"}
}