{
  "type": "Feature",
  "properties": {
    "iso:country":"DK",
    "sg:address":"Torvestr\u00e6det 22-24",
    "sg:city":"Skovlunde",
    "sg:classifiers":[
        {
            "category":"Banks & Credit Unions",
            "subcategory":"Bank",
            "type":"Services"
        }
    ],
    "sg:phone":"+45 44 94 56 56",
    "sg:postcode":"2740",
    "sg:province":"Danmark",
    "sg:tags":[
        "banker"
    ],
    "wof:name":"Nordea",
    "wof:placetype":"venue"
},
  "geometry": {"coordinates":[12.4008970261,55.7209205627],"type":"Point"}
}