{
  "type": "Feature",
  "properties": {
    "addr:full":"Egeb\u00e6kg\u00e5rd, Egeb\u00e6kvej 98, Gl. Holte N\u00e6rum Danmark 2850",
    "addr:housenumber":"98",
    "addr:postcode":"2850",
    "addr:street":"Egebaekvej;Gl. Holte;Danmark",
    "iso:country":"DK",
    "sg:address":"Egeb\u00e6kg\u00e5rd, Egeb\u00e6kvej 98, Gl. Holte",
    "sg:city":"N\u00e6rum",
    "sg:orig_category":"Faglige organisationer og -foreninger",
    "sg:phone":"+45 45 80 78 77",
    "sg:postcode":"2850",
    "sg:province":"Danmark",
    "sg:website":"www.tun.dk",
    "wof:name":"Tr\u00e6lasthandlerunionen TUN",
    "wof:placetype":"venue"
},
  "geometry": {"coordinates":[-89.99810791020001,38.1321372986],"type":"Point"}
}