{
  "type": "Feature",
  "properties": {
    "iso:country":"DK",
    "sg:address":"\u00d8stergade 32 H",
    "sg:city":"Frederikssund",
    "sg:orig_category":"Blomsterhandlere",
    "sg:phone":"+45 47 31 05 05",
    "sg:postcode":"3600",
    "sg:province":"Danmark",
    "wof:name":"Acacia Blomster",
    "wof:placetype":"venue"
},
  "geometry": {"coordinates":[12.0661621094,55.8370323181],"type":"Point"}
}