{
  "type": "Feature",
  "properties": {
    "addr:full":"Sunds\u00f8revej 73, Thise Roslev Danmark 7870",
    "addr:housenumber":"73",
    "addr:postcode":"7870",
    "addr:street":"Sundsorevej",
    "iso:country":"DK",
    "sg:address":"Sunds\u00f8revej 73, Thise",
    "sg:city":"Roslev",
    "sg:classifiers":[
        {
            "category":"Taxi",
            "type":"Transportation"
        }
    ],
    "sg:phone":"+45 97 57 80 29",
    "sg:postcode":"7870",
    "sg:province":"Danmark",
    "wof:name":"Thise Taxi og Turistbusser",
    "wof:placetype":"venue"
},
  "geometry": {"coordinates":[8.8715353012,56.7570304871],"type":"Point"}
}