{
  "type": "Feature",
  "properties": {
    "addr:full":"Ly\u00f8vej 2 Nyborg Danmark 5800",
    "addr:housenumber":"2",
    "addr:postcode":"5800",
    "addr:street":"Lyovej",
    "iso:country":"DK",
    "sg:address":"Ly\u00f8vej 2",
    "sg:city":"Nyborg",
    "sg:orig_category":"Servicestationer",
    "sg:phone":"+45 65 31 34 22",
    "sg:postcode":"5800",
    "sg:province":"Danmark",
    "wof:name":"Hydro-Texaco",
    "wof:placetype":"venue"
},
  "geometry": {"coordinates":[10.7560882568,55.3099937439],"type":"Point"}
}