{
  "type": "Feature",
  "properties": {
    "addr:full":"Hattemagervej 6 Aalborg Danmark 9000",
    "addr:housenumber":"6",
    "addr:postcode":"9000",
    "addr:street":"Hattemagervej",
    "iso:country":"DK",
    "sg:address":"Hattemagervej 6",
    "sg:city":"Aalborg",
    "sg:orig_category":"Malervarer",
    "sg:phone":"+45 98 16 11 11",
    "sg:postcode":"9000",
    "sg:province":"Danmark",
    "wof:name":"Beckers Grossistcenter",
    "wof:placetype":"venue"
},
  "geometry": {"coordinates":[9.9245281219,57.0346870422],"type":"Point"}
}