{
  "type": "Feature",
  "properties": {
    "addr:full":"Torvegade 1 Saksk\u00f8bing Danmark 4990",
    "addr:housenumber":"1",
    "addr:postcode":"4990",
    "addr:street":"Torvegade",
    "iso:country":"DK",
    "sg:address":"Torvegade 1",
    "sg:city":"Saksk\u00f8bing",
    "sg:orig_category":"Optikere",
    "sg:phone":"+45 54 70 74 16",
    "sg:postcode":"4990",
    "sg:province":"Danmark",
    "wof:name":"S\u00f8rens Briller",
    "wof:placetype":"venue"
},
  "geometry": {"coordinates":[11.6356697083,54.7999191284],"type":"Point"}
}