{
  "type": "Feature",
  "properties": {
    "addr:full":"\u00d8stergade 21 Karup Danmark 7470",
    "addr:housenumber":"21",
    "addr:postcode":"7470",
    "addr:street":"Ostergade",
    "iso:country":"DK",
    "sg:address":"\u00d8stergade 21",
    "sg:city":"Karup",
    "sg:orig_category":"Fritidshjem",
    "sg:phone":"+45 96 62 55 65",
    "sg:postcode":"7470",
    "sg:province":"Danmark",
    "sg:website":"www.karup.dk/daginstitutioner/inst02/inst02.html",
    "wof:name":"Paraplyen Fritidshjem",
    "wof:placetype":"venue"
},
  "geometry": {"coordinates":[9.17070961,56.3068389893],"type":"Point"}
}