{
  "type": "Feature",
  "properties": {
    "addr:full":"Slotsgade 5 Nyk\u00f8bing Danmark 4800",
    "addr:housenumber":"5",
    "addr:postcode":"4800",
    "addr:street":"Slotsgade",
    "iso:country":"DK",
    "sg:address":"Slotsgade 5",
    "sg:city":"Nyk\u00f8bing",
    "sg:orig_category":"Forsikringer",
    "sg:phone":"+45 70 13 79 13",
    "sg:postcode":"4800",
    "sg:province":"Danmark",
    "wof:name":"Topdanmark",
    "wof:placetype":"venue"
},
  "geometry": {"coordinates":[-114.0768203735,46.4432411194],"type":"Point"}
}