{
  "type": "Feature",
  "properties": {
    "addr:full":"Billensteinsvej 15 Vejle \u00d8 Danmark 7120",
    "addr:housenumber":"15",
    "addr:postcode":"7120",
    "addr:street":"Billensteinsvej",
    "iso:country":"DK",
    "sg:address":"Billensteinsvej 15",
    "sg:city":"Vejle \u00d8",
    "sg:orig_category":"Psykologer, praktiserende",
    "sg:phone":"+45 75 71 26 70",
    "sg:postcode":"7120",
    "sg:province":"Danmark",
    "wof:name":"Nielsen, Ida Waage",
    "wof:placetype":"venue"
},
  "geometry": {"coordinates":[9.6213111877,55.7115325928],"type":"Point"}
}