{
  "type": "Feature",
  "properties": {
    "addr:full":"Fmd.: Ole Ballisager, Heimdalsvej 9 Kolding Danmark 6000",
    "addr:housenumber":"9",
    "addr:postcode":"6000",
    "addr:street":"Heimdalsvej",
    "iso:country":"DK",
    "sg:address":"Fmd.: Ole Ballisager, Heimdalsvej 9",
    "sg:city":"Kolding",
    "sg:orig_category":"Kulturelle foreninger",
    "sg:phone":"+45 75 52 94 41",
    "sg:postcode":"6000",
    "sg:province":"Danmark",
    "sg:website":"www.teatervejleamt.dk",
    "wof:name":"Foreningen Norden",
    "wof:placetype":"venue"
},
  "geometry": {"coordinates":[9.4733953476,55.4863586426],"type":"Point"}
}