{
  "type": "Feature",
  "properties": {
    "addr:full":"Politig\u00e5rden, Nybrogade 5 Nakskov Danmark 4900",
    "addr:housenumber":"5",
    "addr:postcode":"4900",
    "addr:street":"Nybrogade",
    "iso:country":"DK",
    "sg:address":"Politig\u00e5rden, Nybrogade 5",
    "sg:city":"Nakskov",
    "sg:orig_category":"Politi",
    "sg:phone":"+45 54 92 14 48",
    "sg:postcode":"4900",
    "sg:province":"Danmark",
    "wof:name":"Nakskov Politikreds.",
    "wof:placetype":"venue"
},
  "geometry": {"coordinates":[11.1359500885,54.8330116272],"type":"Point"}
}