{
  "type": "Feature",
  "properties": {
    "addr:full":"H\u00f8jbyvej 45, H\u00f8jby Odense S Danmark 5260",
    "addr:housenumber":"45",
    "addr:postcode":"5260",
    "addr:street":"Hojbyvej;Hojby",
    "iso:country":"DK",
    "sg:address":"H\u00f8jbyvej 45, H\u00f8jby",
    "sg:city":"Odense S",
    "sg:orig_category":"Engros handel",
    "sg:phone":"+45 65 95 83 49",
    "sg:postcode":"5260",
    "sg:province":"Danmark",
    "wof:name":"Rie's Keramik",
    "wof:placetype":"venue"
},
  "geometry": {"coordinates":[10.3157806396,55.3122825623],"type":"Point"}
}