{
  "type": "Feature",
  "properties": {
    "addr:full":"Skovbrynet 17 Nyborg Danmark 5800",
    "addr:housenumber":"17",
    "addr:postcode":"5800",
    "addr:street":"Skovbrynet",
    "iso:country":"DK",
    "sg:address":"Skovbrynet 17",
    "sg:city":"Nyborg",
    "sg:orig_category":"\u00c3\u02dcvrige skoler",
    "sg:phone":"+45 65 31 21 09",
    "sg:postcode":"5800",
    "sg:province":"Danmark",
    "sg:website":"www.asv-oestfyn.dk",
    "wof:name":"ASV \u00d8stfyn",
    "wof:placetype":"venue"
},
  "geometry": {"coordinates":[10.8065156937,55.3180541992],"type":"Point"}
}