{
  "type": "Feature",
  "properties": {
    "iso:country":"DK",
    "sg:address":"Nygade 16",
    "sg:city":"Silkeborg",
    "sg:orig_category":"Cafeer",
    "sg:phone":"+45 86 81 91 03",
    "sg:postcode":"8600",
    "sg:province":"Danmark",
    "wof:name":"HumleChok, Caf\u00e9",
    "wof:placetype":"venue"
},
  "geometry": {"coordinates":[9.5476579666,56.1674766541],"type":"Point"}
}