{
  "type": "Feature",
  "properties": {
    "addr:full":"Mosetoften 2 Hedensted Danmark 8722",
    "addr:housenumber":"2",
    "addr:postcode":"8722",
    "addr:street":"Mosetoften",
    "iso:country":"DK",
    "sg:address":"Mosetoften 2",
    "sg:city":"Hedensted",
    "sg:orig_category":"Malermestre",
    "sg:phone":"+45 75 89 16 46",
    "sg:postcode":"8722",
    "sg:province":"Danmark",
    "wof:name":"Hedensted Malerforretning og Farvehandel",
    "wof:placetype":"venue"
},
  "geometry": {"coordinates":[9.6962976456,55.7773666382],"type":"Point"}
}