{
  "type": "Feature",
  "properties": {
    "addr:full":"Vestre Strand 1 Gedser Danmark 4874",
    "addr:housenumber":"1",
    "addr:postcode":"4874",
    "addr:street":"Vestre Strand",
    "iso:country":"DK",
    "sg:address":"Vestre Strand 1",
    "sg:city":"Gedser",
    "sg:classifiers":[
        {
            "category":"Restaurant",
            "type":"Food & Drink"
        }
    ],
    "sg:phone":"+45 54 17 02 87",
    "sg:postcode":"4874",
    "sg:province":"Danmark",
    "wof:name":"Najaden, Restaurant",
    "wof:placetype":"venue"
},
  "geometry": {"coordinates":[11.8850698471,54.6599006653],"type":"Point"}
}