{
  "type": "Feature",
  "properties": {
    "addr:full":"Plantagev\u00e6nget 6 Bogense Danmark 5400",
    "addr:housenumber":"6",
    "addr:postcode":"5400",
    "addr:street":"Plantagevaenget",
    "iso:country":"DK",
    "sg:address":"Plantagev\u00e6nget 6",
    "sg:city":"Bogense",
    "sg:orig_category":"Musik- og sangundervisning",
    "sg:phone":"+45 64 81 20 22",
    "sg:postcode":"5400",
    "sg:province":"Danmark",
    "wof:name":"Bogense Musikskole",
    "wof:placetype":"venue"
},
  "geometry": {"coordinates":[10.0942802429,55.5623779297],"type":"Point"}
}