{
  "type": "Feature",
  "properties": {
    "addr:full":"S\u00f8ndre Fasanvej 80 f, 1 th Frederiksberg Danmark 2000",
    "addr:housenumber":"80 f 1",
    "addr:postcode":"2000",
    "addr:street":"Sondre Fasanvej;Th",
    "iso:country":"DK",
    "sg:address":"S\u00f8ndre Fasanvej 80 f, 1 th",
    "sg:city":"Frederiksberg",
    "sg:orig_category":"Revisorer",
    "sg:phone":"+45 36 44 30 48",
    "sg:postcode":"2000",
    "sg:province":"Danmark",
    "wof:name":"Comaccount",
    "wof:placetype":"venue"
},
  "geometry": {"coordinates":[12.5299301147,55.6787872314],"type":"Point"}
}