{
  "type": "Feature",
  "properties": {
    "addr:full":"Vestergade 7 Egtved Danmark 6040",
    "addr:housenumber":"7",
    "addr:postcode":"6040",
    "addr:street":"Vestergade",
    "iso:country":"DK",
    "sg:address":"Vestergade 7",
    "sg:city":"Egtved",
    "sg:orig_category":"Dag- og distriktsblade",
    "sg:phone":"+45 75 55 15 33",
    "sg:postcode":"6040",
    "sg:province":"Danmark",
    "wof:name":"Vejle Amts Folkeblad A/S",
    "wof:placetype":"venue"
},
  "geometry": {"coordinates":[9.3063154221,55.616153717],"type":"Point"}
}