{
  "type": "Feature",
  "properties": {
    "addr:full":"Hjortsvangen 4 Give Danmark 7323",
    "addr:housenumber":"4",
    "addr:postcode":"7323",
    "addr:street":"Hjortsvangen",
    "iso:country":"DK",
    "sg:address":"Hjortsvangen 4",
    "sg:city":"Give",
    "sg:orig_category":"Typehuse",
    "sg:phone":"+45 75 73 13 77",
    "sg:postcode":"7323",
    "sg:province":"Danmark",
    "wof:name":"Give-Huset A/S",
    "wof:placetype":"venue"
},
  "geometry": {"coordinates":[9.2501277924,55.860496521],"type":"Point"}
}