{
  "type": "Feature",
  "properties": {
    "addr:full":"Ravnstrupvej 2 A Holmegaard Danmark 4684",
    "addr:housenumber":"2 a",
    "addr:postcode":"4684",
    "addr:street":"Ravnstrupvej",
    "iso:country":"DK",
    "sg:address":"Ravnstrupvej 2 A",
    "sg:city":"Holmegaard",
    "sg:orig_category":"Autoforhandlere",
    "sg:phone":"+45 55 56 10 20",
    "sg:postcode":"4684",
    "sg:province":"Danmark",
    "wof:name":"KIm S\u00f8rensen Automobiler",
    "wof:placetype":"venue"
},
  "geometry": {"coordinates":[11.8711614609,55.2595481873],"type":"Point"}
}