{
  "type": "Feature",
  "properties": {
    "iso:country":"DK",
    "sg:address":"Strandvejen 185",
    "sg:city":"Hellerup",
    "sg:orig_category":"Bagere",
    "sg:phone":"+45 39 62 00 73",
    "sg:postcode":"2900",
    "sg:province":"Danmark",
    "wof:name":"Vagn, Caf\u00e9",
    "wof:placetype":"venue"
},
  "geometry": {"coordinates":[12.574776,55.734589],"type":"Point"}
}