{
  "type": "Feature",
  "properties": {
    "addr:full":"Hundige Storcenter 15 B Greve Danmark 2670",
    "addr:housenumber":"15",
    "addr:postcode":"2670",
    "addr:street":"B",
    "iso:country":"DK",
    "sg:address":"Hundige Storcenter 15 B",
    "sg:city":"Greve",
    "sg:orig_category":"Materialister",
    "sg:phone":"+45 43 90 88 94",
    "sg:postcode":"2670",
    "sg:province":"Danmark",
    "wof:name":"Matas",
    "wof:placetype":"venue"
},
  "geometry": {"coordinates":[12.3288841248,55.5985870361],"type":"Point"}
}