{
  "type": "Feature",
  "properties": {
    "addr:full":"Smedegade 94 Horsens Danmark 8700",
    "addr:housenumber":"94",
    "addr:postcode":"8700",
    "addr:street":"Smedegade",
    "iso:country":"DK",
    "sg:address":"Smedegade 94",
    "sg:city":"Horsens",
    "sg:orig_category":"Systuer",
    "sg:phone":"+45 75 61 33 12",
    "sg:postcode":"8700",
    "sg:province":"Danmark",
    "wof:name":"Skindv\u00e6rkstedet",
    "wof:placetype":"venue"
},
  "geometry": {"coordinates":[9.8461112976,55.8680000305],"type":"Point"}
}