{
  "type": "Feature",
  "properties": {
    "addr:full":"Havnegade 3 Vejle Danmark 7100",
    "addr:housenumber":"3",
    "addr:postcode":"7100",
    "addr:street":"Havnegade",
    "iso:country":"DK",
    "sg:address":"Havnegade 3",
    "sg:city":"Vejle",
    "sg:orig_category":"Tandteknikere, Kliniske",
    "sg:phone":"+45 75 82 14 13",
    "sg:postcode":"7100",
    "sg:province":"Danmark",
    "wof:name":"Steen, Hanne",
    "wof:placetype":"venue"
},
  "geometry": {"coordinates":[9.5362148285,55.707611084],"type":"Point"}
}