{
  "type": "Feature",
  "properties": {
    "addr:full":"Fmd.: Heidi Maibritt Larsen, Christianshedevej 45 Bording Danmark 7441",
    "addr:housenumber":"45",
    "addr:postcode":"7441",
    "addr:street":"Christianshedevej",
    "iso:country":"DK",
    "sg:address":"Fmd.: Heidi Maibritt Larsen, Christianshedevej 45",
    "sg:city":"Bording",
    "sg:orig_category":"Husflidsforeninger",
    "sg:phone":"+45 86 86 93 13",
    "sg:postcode":"7441",
    "sg:province":"Danmark",
    "wof:name":"DDH Foreningen Aktive Kvinder Christianshede",
    "wof:placetype":"venue"
},
  "geometry": {"coordinates":[9.2792396545,56.1449508667],"type":"Point"}
}