{
  "type": "Feature",
  "properties": {
    "iso:country":"DK",
    "sg:address":"Hammersholt Byvej 1, Hammersholt",
    "sg:city":"Hiller\u00f8d",
    "sg:orig_category":"Beslagsmede",
    "sg:phone":"+45 48 17 29 40",
    "sg:postcode":"3400",
    "sg:province":"Danmark",
    "wof:name":"Larsen, Kurt",
    "wof:placetype":"venue"
},
  "geometry": {"coordinates":[12.30561,55.928822],"type":"Point"}
}