{
  "type": "Feature",
  "properties": {
    "addr:full":"Rubinvej 1 Hasle Danmark 3790",
    "addr:housenumber":"1",
    "addr:postcode":"3790",
    "addr:street":"Rubinvej",
    "iso:country":"DK",
    "sg:address":"Rubinvej 1",
    "sg:city":"Hasle",
    "sg:orig_category":"Sommerhusudlejning",
    "sg:phone":"+45 56 94 60 40",
    "sg:postcode":"3790",
    "sg:province":"Danmark",
    "sg:website":"www.skovhuse-rubin.dk",
    "wof:name":"Rubins\u00f8ens Skovhuse",
    "wof:placetype":"venue"
},
  "geometry": {"coordinates":[14.7065896988,55.1830863953],"type":"Point"}
}