{
  "type": "Feature",
  "properties": {
    "addr:full":"Bautah\u00f8jvej 2 C, Skoven J\u00e6gerspris Danmark 3630",
    "addr:housenumber":"2 c",
    "addr:postcode":"3630",
    "addr:street":"Bautahojvej;Skoven Jaegerspris Danmark",
    "iso:country":"DK",
    "sg:address":"Bautah\u00f8jvej 2 C, Skoven",
    "sg:city":"J\u00e6gerspris",
    "sg:orig_category":"Forsamlingshuse",
    "sg:phone":"+45 47 53 00 89",
    "sg:postcode":"3630",
    "sg:province":"Danmark",
    "wof:name":"Skovens Forsamlingshus",
    "wof:placetype":"venue"
},
  "geometry": {"coordinates":[11.9136800766,55.9269866943],"type":"Point"}
}