{
  "type": "Feature",
  "properties": {
    "addr:full":"Herstedvang 7c  Albertslund Danmark 2620",
    "addr:housenumber":"7c",
    "addr:postcode":"2620",
    "addr:street":"Herstedvang",
    "iso:country":"DK",
    "sg:address":"Herstedvang 7c ",
    "sg:city":"Albertslund",
    "sg:classifiers":[
        {
            "category":"Professional",
            "subcategory":"Computer Services",
            "type":"Services"
        }
    ],
    "sg:phone":"+45 70 26 98 99",
    "sg:postcode":"2620",
    "sg:province":"Danmark",
    "sg:tags":[
        "information",
        "technology"
    ],
    "wof:name":"INVENTIO IT APS",
    "wof:placetype":"venue"
},
  "geometry": {"coordinates":[12.367357254,55.6668624878],"type":"Point"}
}