{
  "type": "Feature",
  "properties": {
    "addr:full":"Klattrup Bygade 6 Fredericia Danmark 7000",
    "addr:housenumber":"6",
    "addr:postcode":"7000",
    "addr:street":"Klattrup Bygade",
    "iso:country":"DK",
    "sg:address":"Klattrup Bygade 6",
    "sg:city":"Fredericia",
    "sg:orig_category":"Servicestationer",
    "sg:phone":"+45 75 86 05 22",
    "sg:postcode":"7000",
    "sg:province":"Danmark",
    "wof:name":"Shell Sk\u00e6rup Vest",
    "wof:placetype":"venue"
},
  "geometry": {"coordinates":[9.5559930801,55.6382026672],"type":"Point"}
}