{
  "type": "Feature",
  "properties": {
    "addr:full":"Toreby Vestergade 58, Toreby Toreby Danmark 4891",
    "addr:housenumber":"58",
    "addr:postcode":"4891",
    "addr:street":"Toreby Vestergade",
    "iso:country":"DK",
    "sg:address":"Toreby Vestergade 58, Toreby",
    "sg:city":"Toreby",
    "sg:orig_category":"Murermestre",
    "sg:phone":"+45 54 86 95 00",
    "sg:postcode":"4891",
    "sg:province":"Danmark",
    "wof:name":"Petersen, Ernst",
    "wof:placetype":"venue"
},
  "geometry": {"coordinates":[11.7701835632,54.7622375488],"type":"Point"}
}