{
  "type": "Feature",
  "properties": {
    "addr:full":"Fjellerup Bygade 6, Fjellerup Glesborg Danmark 8585",
    "addr:housenumber":"6",
    "addr:postcode":"8585",
    "addr:street":"Fjellerup Bygade;Fjellerup",
    "iso:country":"DK",
    "sg:address":"Fjellerup Bygade 6, Fjellerup",
    "sg:city":"Glesborg",
    "sg:classifiers":[
        {
            "category":"Banks & Credit Unions",
            "subcategory":"Bank",
            "type":"Services"
        }
    ],
    "sg:phone":"+45 86 31 70 55",
    "sg:postcode":"8585",
    "sg:province":"Danmark",
    "sg:tags":[
        "banker"
    ],
    "sg:website":"www.djurslandsbank.dk",
    "wof:name":"Djurslands Bank A/S",
    "wof:placetype":"venue"
},
  "geometry": {"coordinates":[10.588472,56.512432],"type":"Point"}
}