{
  "type": "Feature",
  "properties": {
    "addr:full":"Bandholmvej 79 Torrig Danmark 4943",
    "addr:housenumber":"79",
    "addr:postcode":"4943",
    "addr:street":"Bandholmvej",
    "iso:country":"DK",
    "sg:address":"Bandholmvej 79",
    "sg:city":"Torrig",
    "sg:orig_category":"Forsamlingshuse",
    "sg:phone":"+45 54 93 71 63",
    "sg:postcode":"4943",
    "sg:province":"Danmark",
    "wof:name":"Signe Stubs Sogneg\u00e5rd",
    "wof:placetype":"venue"
},
  "geometry": {"coordinates":[11.3322153091,54.9025840759],"type":"Point"}
}