{
  "type": "Feature",
  "properties": {
    "iso:country":"DK",
    "sg:address":"V\u00e6vervej 33 -35 ",
    "sg:city":"Aulum",
    "sg:classifiers":[
        {
            "category":"Home & Garden",
            "subcategory":"Home Furnishings",
            "type":"Retail Goods"
        }
    ],
    "sg:phone":"+45 97 47 24 88",
    "sg:postcode":"7490",
    "sg:province":"Danmark",
    "sg:tags":[
        "household"
    ],
    "wof:name":"OJ SYSTEM A/S",
    "wof:placetype":"venue"
},
  "geometry": {"coordinates":[8.7845697403,56.2600250244],"type":"Point"}
}