{
  "type": "Feature",
  "properties": {
    "iso:country":"DK",
    "sg:address":"Fmd.: Emmy S\u00f8rensen, Krogg\u00e5rdsv\u00e6nget 3, Brylle",
    "sg:city":"Tommerup",
    "sg:orig_category":"\u00c3\u2020ldreorganisationer og klubber",
    "sg:phone":"+45 64 75 15 21",
    "sg:postcode":"5690",
    "sg:province":"Danmark",
    "wof:name":"Tommerup pensionistforening",
    "wof:placetype":"venue"
},
  "geometry": {"coordinates":[10.2489509583,55.3236503601],"type":"Point"}
}