{
  "type": "Feature",
  "properties": {
    "addr:full":"Leder: Mogens Lauridsen, T\u00e6byvej 3 R\u00f8dovre Danmark 2610",
    "addr:housenumber":"3",
    "addr:postcode":"2610",
    "addr:street":"Taebyvej",
    "iso:country":"DK",
    "sg:address":"Leder: Mogens Lauridsen, T\u00e6byvej 3",
    "sg:city":"R\u00f8dovre",
    "sg:orig_category":"Fritidscentre",
    "sg:phone":"+45 36 47 17 16",
    "sg:postcode":"2610",
    "sg:province":"Danmark",
    "wof:name":"Multihallen - R\u00f8dovre",
    "wof:placetype":"venue"
},
  "geometry": {"coordinates":[10.6992139816,61.1027755737],"type":"Point"}
}