{
  "type": "Feature",
  "properties": {
    "addr:full":"Kontaktpers.: Kirsten Fjordbak, Kaprifolievej 5 K\u00f8ge Danmark 4600",
    "addr:housenumber":"5",
    "addr:postcode":"4600",
    "addr:street":"Kaprifolievej",
    "iso:country":"DK",
    "sg:address":"Kontaktpers.: Kirsten Fjordbak, Kaprifolievej 5",
    "sg:city":"K\u00f8ge",
    "sg:orig_category":"Politiske foreninger, \u00c3\u02dcvrige",
    "sg:phone":"+45 56 66 32 85",
    "sg:postcode":"4600",
    "sg:province":"Danmark",
    "wof:name":"Folkebev\u00e6gelsen Mod EF-Unionen - K\u00f8ge",
    "wof:placetype":"venue"
},
  "geometry": {"coordinates":[12.1611499786,55.4433403015],"type":"Point"}
}