{
  "type": "Feature",
  "properties": {
    "iso:country":"DK",
    "sg:address":"\u00d8stergade 2",
    "sg:city":"Skjern",
    "sg:orig_category":"Optikere",
    "sg:phone":"+45 97 35 46 76",
    "sg:postcode":"6900",
    "sg:province":"Danmark",
    "sg:website":"www.profiloptik.dk",
    "wof:name":"Profil Optik Skjern ApS",
    "wof:placetype":"venue"
},
  "geometry": {"coordinates":[8.4924850464,55.9483375549],"type":"Point"}
}