{
  "type": "Feature",
  "properties": {
    "addr:full":"Hindingvej 37 Thisted Danmark 7700",
    "addr:housenumber":"37",
    "addr:postcode":"7700",
    "addr:street":"Hindingvej",
    "iso:country":"DK",
    "sg:address":"Hindingvej 37",
    "sg:city":"Thisted",
    "sg:orig_category":"Autoreparation og -service",
    "sg:phone":"+45 97 98 11 63",
    "sg:postcode":"7700",
    "sg:province":"Danmark",
    "wof:name":"Hinding Auto",
    "wof:placetype":"venue"
},
  "geometry": {"coordinates":[8.6357440948,57.0395393372],"type":"Point"}
}