{
  "type": "Feature",
  "properties": {
    "addr:full":"Falck - Huset, Polititorvet 2 1780",
    "addr:housenumber":"2",
    "addr:postcode":"1780",
    "addr:street":"Polititorvet",
    "iso:country":"DK",
    "sg:address":"Falck - Huset, Polititorvet 2",
    "sg:orig_category":"Redningskorps",
    "sg:phone":"+45 33 15 83 20",
    "sg:postcode":"1780",
    "sg:website":"www.falck.dk",
    "wof:name":"Falcks Redningskorps",
    "wof:placetype":"venue"
},
  "geometry": {"coordinates":[12.5727996826,55.6692008972],"type":"Point"}
}