{
  "type": "Feature",
  "properties": {
    "addr:full":"Kristrupvej 129 Randers Danmark 8900",
    "addr:housenumber":"129",
    "addr:postcode":"8900",
    "addr:street":"Kristrupvej",
    "iso:country":"DK",
    "sg:address":"Kristrupvej 129",
    "sg:city":"Randers",
    "sg:orig_category":"Kirker",
    "sg:postcode":"8900",
    "sg:province":"Danmark",
    "wof:name":"Kristrup Kirke",
    "wof:placetype":"venue"
},
  "geometry": {"coordinates":[10.0631809235,56.4457855225],"type":"Point"}
}