{
  "type": "Feature",
  "properties": {
    "addr:full":"Matildevej 18 Slagelse Danmark 4200",
    "addr:housenumber":"18",
    "addr:postcode":"4200",
    "addr:street":"Matildevej",
    "iso:country":"DK",
    "sg:address":"Matildevej 18",
    "sg:city":"Slagelse",
    "sg:orig_category":"Maskinudlejning",
    "sg:phone":"+45 58 52 73 54",
    "sg:postcode":"4200",
    "sg:province":"Danmark",
    "wof:name":"Entrepren\u00f8r Mogens Larsen",
    "wof:placetype":"venue"
},
  "geometry": {"coordinates":[11.320684433,55.3958244324],"type":"Point"}
}