{
  "type": "Feature",
  "properties": {
    "addr:full":"Skovvej 12 C Hinnerup Danmark 8382",
    "addr:housenumber":"12 c",
    "addr:postcode":"8382",
    "addr:street":"Skovvej",
    "iso:country":"DK",
    "sg:address":"Skovvej 12 C",
    "sg:city":"Hinnerup",
    "sg:orig_category":"Fritidscentre",
    "sg:phone":"+45 86 98 58 10",
    "sg:postcode":"8382",
    "sg:province":"Danmark",
    "wof:name":"Hinnerup Fritidscenter",
    "wof:placetype":"venue"
},
  "geometry": {"coordinates":[10.0614156723,56.2650604248],"type":"Point"}
}