{
  "type": "Feature",
  "properties": {
    "iso:country":"DK",
    "sg:address":"N\u00f8rrevang 11",
    "sg:city":"Sunds",
    "sg:orig_category":"Telte",
    "sg:phone":"+45 97 14 40 98",
    "sg:postcode":"7451",
    "sg:province":"Danmark",
    "sg:website":"www.herningudlejning.dk",
    "wof:name":"Herning Telt- og Serviceudlejning",
    "wof:placetype":"venue"
},
  "geometry": {"coordinates":[9.0137872696,56.2038192749],"type":"Point"}
}