{
  "type": "Feature",
  "properties": {
    "iso:country":"DK",
    "sg:address":"Fmd.: Finn Sinding, Egense Birkevej 1",
    "sg:city":"Svendborg",
    "sg:orig_category":"Hobbybetonede foreninger",
    "sg:phone":"+45 62 20 89 20",
    "sg:postcode":"5700",
    "sg:province":"Danmark",
    "sg:website":"www.bridge.dk/4578",
    "wof:name":"Svendborg Bridgeklub",
    "wof:placetype":"venue"
},
  "geometry": {"coordinates":[10.6065101624,55.0595970154],"type":"Point"}
}