{
  "type": "Feature",
  "properties": {
    "addr:full":"Fmd.: Svend Lassen, Valsb\u00f8lgade 31, Bov Padborg Danmark 6330",
    "addr:housenumber":"31",
    "addr:postcode":"6330",
    "addr:street":"Valsbolgade;Bov",
    "iso:country":"DK",
    "sg:address":"Fmd.: Svend Lassen, Valsb\u00f8lgade 31, Bov",
    "sg:city":"Padborg",
    "sg:orig_category":"Hobbybetonede foreninger",
    "sg:phone":"+45 74 67 51 00",
    "sg:postcode":"6330",
    "sg:province":"Danmark",
    "wof:name":"Krus\u00e5-Padborg Flyveklub",
    "wof:placetype":"venue"
},
  "geometry": {"coordinates":[9.3618345261,54.8222312927],"type":"Point"}
}