{
  "type": "Feature",
  "properties": {
    "addr:full":"v/Annette Kristensen, Lindevang 2, \u00d8strup Veks\u00f8 Sj\u00e6lland Danmark 3670",
    "addr:housenumber":"2",
    "addr:postcode":"3670",
    "addr:street":"Lindevang",
    "iso:country":"DK",
    "sg:address":"v/Annette Kristensen, Lindevang 2, \u00d8strup",
    "sg:city":"Veks\u00f8 Sj\u00e6lland",
    "sg:orig_category":"Grundejerforeninger",
    "sg:phone":"+45 46 76 93 35",
    "sg:postcode":"3670",
    "sg:province":"Danmark",
    "wof:name":"Grundejerforeningen Kastanieh\u00f8j",
    "wof:placetype":"venue"
},
  "geometry": {"coordinates":[-76.0886383057,38.7291030884],"type":"Point"}
}