{
  "type": "Feature",
  "properties": {
    "addr:full":"M\u00e5gevej 3 Thybor\u00f8n Danmark 7680",
    "addr:housenumber":"3",
    "addr:postcode":"7680",
    "addr:street":"Maagevej",
    "iso:country":"DK",
    "sg:address":"M\u00e5gevej 3",
    "sg:city":"Thybor\u00f8n",
    "sg:orig_category":"Erhvervsskoler",
    "sg:phone":"+45 97 83 23 54",
    "sg:postcode":"7680",
    "sg:province":"Danmark",
    "wof:name":"Thybor\u00f8n Skipperskole",
    "wof:placetype":"venue"
},
  "geometry": {"coordinates":[-76.4447174072,37.4649467468],"type":"Point"}
}