{
  "type": "Feature",
  "properties": {
    "addr:full":"L\u00e5sbygade 1 Kolding Danmark 6000",
    "addr:housenumber":"1",
    "addr:postcode":"6000",
    "addr:street":"Laasbygade",
    "iso:country":"DK",
    "sg:address":"L\u00e5sbygade 1",
    "sg:city":"Kolding",
    "sg:orig_category":"Genbrugsbutikker",
    "sg:phone":"+45 75 50 26 22",
    "sg:postcode":"6000",
    "sg:province":"Danmark",
    "wof:name":"Byttecentralen / L\u00e6sehesten 4 I/S",
    "wof:placetype":"venue"
},
  "geometry": {"coordinates":[9.4714546204,55.4917144775],"type":"Point"}
}