{
  "type": "Feature",
  "properties": {
    "iso:country":"DK",
    "sg:address":"\u00d8sterparken 8",
    "sg:city":"Taastrup",
    "sg:orig_category":"Brugsforeninger",
    "sg:phone":"+45 43 99 25 77",
    "sg:postcode":"2630",
    "sg:province":"Danmark",
    "wof:name":"Super Brugsen Taastrup",
    "wof:placetype":"venue"
},
  "geometry": {"coordinates":[12.3031320572,55.6500282288],"type":"Point"}
}