{
  "type": "Feature",
  "properties": {
    "addr:full":"Lindumvej 25, Hvornum Hobro Danmark 9500",
    "addr:housenumber":"25",
    "addr:postcode":"9500",
    "addr:street":"Lindumvej",
    "iso:country":"DK",
    "sg:address":"Lindumvej 25, Hvornum",
    "sg:city":"Hobro",
    "sg:orig_category":"Hunde",
    "sg:phone":"+45 98 54 64 68",
    "sg:postcode":"9500",
    "sg:province":"Danmark",
    "wof:name":"Hotel Vov - Vov",
    "wof:placetype":"venue"
},
  "geometry": {"coordinates":[9.7946596146,56.6382789612],"type":"Point"}
}