{
  "type": "Feature",
  "properties": {
    "addr:full":"Lille Vokstrupvej 7 Gr\u00e6sted Danmark 3230",
    "addr:housenumber":"7",
    "addr:postcode":"3230",
    "addr:street":"Lille Vokstrupvej",
    "iso:country":"DK",
    "sg:address":"Lille Vokstrupvej 7",
    "sg:city":"Gr\u00e6sted",
    "sg:orig_category":"Revisorer",
    "sg:phone":"+45 48 39 34 34",
    "sg:postcode":"3230",
    "sg:province":"Danmark",
    "wof:name":"Faurby, Erik",
    "wof:placetype":"venue"
},
  "geometry": {"coordinates":[3.5755519867,46.6060409546],"type":"Point"}
}