{
  "type": "Feature",
  "properties": {
    "addr:full":"Fmd.: Peder Paaske, Hans Tausensgade 63 Langeskov Danmark 5550",
    "addr:housenumber":"63",
    "addr:postcode":"5550",
    "addr:street":"Hans Tausensgade",
    "iso:country":"DK",
    "sg:address":"Fmd.: Peder Paaske, Hans Tausensgade 63",
    "sg:city":"Langeskov",
    "sg:orig_category":"Hobbybetonede foreninger",
    "sg:phone":"+45 65 95 20 98",
    "sg:postcode":"5550",
    "sg:province":"Danmark",
    "wof:name":"Danmarks Civile Hundef\u00f8rerforening, Langeskov",
    "wof:placetype":"venue"
},
  "geometry": {"coordinates":[10.5878953934,55.3595466614],"type":"Point"}
}