{
  "type": "Feature",
  "properties": {
    "addr:full":"Augustenborg Landevej 7 Soenderborg DK - 6400",
    "addr:housenumber":"7",
    "addr:postcode":"6400",
    "addr:street":"Augustenborg Landevej;Dk",
    "iso:country":"DK",
    "sg:address":"Augustenborg Landevej 7",
    "sg:city":"Soenderborg",
    "sg:classifiers":[
        {
            "category":"Manufacturing",
            "subcategory":"Electronics",
            "type":"Manufacturing & Wholesale Goods"
        }
    ],
    "sg:postcode":"DK - 6400",
    "sg:website":"http://www.acon.dk",
    "wof:name":"aCon",
    "wof:placetype":"venue"
},
  "geometry": {"coordinates":[9.8114974,54.9201429],"type":"Point"}
}