{
  "type": "Feature",
  "properties": {
    "addr:full":"Japanvej 3 Slagelse Danmark 4200",
    "addr:housenumber":"3",
    "addr:postcode":"4200",
    "addr:street":"Japanvej",
    "iso:country":"DK",
    "sg:address":"Japanvej 3",
    "sg:city":"Slagelse",
    "sg:orig_category":"Fagforbund og -foreninger",
    "sg:phone":"+45 58 52 99 93",
    "sg:postcode":"4200",
    "sg:province":"Danmark",
    "wof:name":"Dansk Socialr\u00e5dgiverforening Vestsj\u00e6llands Amt",
    "wof:placetype":"venue"
},
  "geometry": {"coordinates":[11.325633049,55.3882522583],"type":"Point"}
}