{
  "type": "Feature",
  "properties": {
    "iso:country":"DK",
    "sg:address":"Fmd.: Henrik Nielsen, Brorsonsvej 16",
    "sg:city":"Bjerringbro",
    "sg:orig_category":"Hobbybetonede foreninger",
    "sg:phone":"+45 86 68 34 79",
    "sg:postcode":"8850",
    "sg:province":"Danmark",
    "wof:name":"Bjerringbro Modeljernbane",
    "wof:placetype":"venue"
},
  "geometry": {"coordinates":[9.6546850204,56.3754692078],"type":"Point"}
}