{
  "type": "Feature",
  "properties": {
    "iso:country":"DK",
    "sg:address":"Bavnevangen 31",
    "sg:city":"Br\u00f8nsh\u00f8j",
    "sg:orig_category":"Snedkermestre",
    "sg:phone":"+45 38 60 69 02",
    "sg:postcode":"2700",
    "sg:province":"Danmark",
    "wof:name":"Nielsen, Jes",
    "wof:placetype":"venue"
},
  "geometry": {"coordinates":[-65.6866531372,-23.1981296539],"type":"Point"}
}