{
  "type": "Feature",
  "properties": {
    "iso:country":"DK",
    "sg:address":"Havnen 17 - 19",
    "sg:city":"K\u00f8ge",
    "sg:orig_category":"Diskoteker",
    "sg:phone":"+45 56 65 81 98",
    "sg:postcode":"4600",
    "sg:province":"Danmark",
    "wof:name":"Road House, Diskotek",
    "wof:placetype":"venue"
},
  "geometry": {"coordinates":[12.2430353165,55.4170417786],"type":"Point"}
}