{
  "type": "Feature",
  "properties": {
    "addr:full":"Centrumpladsen 6 Svendborg Danmark 5700",
    "addr:housenumber":"6",
    "addr:postcode":"5700",
    "addr:street":"Centrumpladsen",
    "iso:country":"DK",
    "sg:address":"Centrumpladsen 6",
    "sg:city":"Svendborg",
    "sg:orig_category":"Ejendomshandel",
    "sg:phone":"+45 62 21 44 84",
    "sg:postcode":"5700",
    "sg:province":"Danmark",
    "wof:name":"DanBolig",
    "wof:placetype":"venue"
},
  "geometry": {"coordinates":[10.6074371338,55.060005188],"type":"Point"}
}