{
  "type": "Feature",
  "properties": {
    "iso:country":"DK",
    "sg:address":"Dals\u00f8 Park 142, Kr. V\u00e6rl\u00f8se",
    "sg:city":"V\u00e6rl\u00f8se",
    "sg:orig_category":"Revisorer",
    "sg:phone":"+45 44 47 52 42",
    "sg:postcode":"3500",
    "sg:province":"Danmark",
    "sg:website":"www.raffli.dk",
    "wof:name":"Raffli Revision",
    "wof:placetype":"venue"
},
  "geometry": {"coordinates":[127.0173568726,37.6389884949],"type":"Point"}
}