{
  "type": "Feature",
  "properties": {
    "iso:country":"DK",
    "sg:address":"Svends Alle 67",
    "sg:city":"Kongens Lyngby",
    "sg:orig_category":"Snedkermestre",
    "sg:phone":"+45 40 25 82 35",
    "sg:postcode":"2800",
    "sg:province":"Danmark",
    "wof:name":"Miks Snedkerservice",
    "wof:placetype":"venue"
},
  "geometry": {"coordinates":[12.4808349609,55.7523384094],"type":"Point"}
}