{
  "type": "Feature",
  "properties": {
    "addr:full":"Esbjerggade 2 Frederikshavn Danmark 9900",
    "addr:housenumber":"2",
    "addr:postcode":"9900",
    "addr:street":"Esbjerggade",
    "iso:country":"DK",
    "sg:address":"Esbjerggade 2",
    "sg:city":"Frederikshavn",
    "sg:orig_category":"Glarmestre og glarmagere",
    "sg:phone":"+45 98 42 00 90",
    "sg:postcode":"9900",
    "sg:province":"Danmark",
    "sg:website":"www.bentfick.dk",
    "wof:name":"Fick, Bent",
    "wof:placetype":"venue"
},
  "geometry": {"coordinates":[10.5240573883,57.4565658569],"type":"Point"}
}