{
  "type": "Feature",
  "properties": {
    "addr:full":"Kirkevejen 29 Lunderskov Danmark 6640",
    "addr:housenumber":"29",
    "addr:postcode":"6640",
    "addr:street":"Kirkevejen",
    "iso:country":"DK",
    "sg:address":"Kirkevejen 29",
    "sg:city":"Lunderskov",
    "sg:orig_category":"Glasfiberindustri",
    "sg:phone":"+45 75 58 65 51",
    "sg:postcode":"6640",
    "sg:province":"Danmark",
    "wof:name":"Glasfiber Service",
    "wof:placetype":"venue"
},
  "geometry": {"coordinates":[9.3064746857,55.4738273621],"type":"Point"}
}