{
  "type": "Feature",
  "properties": {
    "iso:country":"DK",
    "sg:address":"Dortesvej 47",
    "sg:city":"Brabrand",
    "sg:orig_category":"Ungdomsklubber",
    "sg:phone":"+45 86 25 03 33",
    "sg:postcode":"8220",
    "sg:province":"Danmark",
    "wof:name":"Fritids- og Ungdomsklubben i Gellerup",
    "wof:placetype":"venue"
},
  "geometry": {"coordinates":[10.1349773407,56.1586303711],"type":"Point"}
}