{
  "type": "Feature",
  "properties": {
    "iso:country":"DK",
    "sg:address":"Sandb\u00e6kvej 7 ",
    "sg:city":"R\u00f8dovre",
    "sg:classifiers":[
        {
            "category":"Wholesale",
            "subcategory":"Drugs",
            "type":"Manufacturing & Wholesale Goods"
        }
    ],
    "sg:phone":"+45 44 94 88 22",
    "sg:postcode":"2610",
    "sg:province":"Danmark",
    "sg:tags":[
        "chemical",
        "pharmaceutical"
    ],
    "wof:name":"BIE & BERNTSEN A/S",
    "wof:placetype":"venue"
},
  "geometry": {"coordinates":[10.6992139816,61.1027755737],"type":"Point"}
}