{
  "type": "Feature",
  "properties": {
    "addr:full":"Kirkegade 15 Bramming Danmark 6740",
    "addr:housenumber":"15",
    "addr:postcode":"6740",
    "addr:street":"Kirkegade",
    "iso:country":"DK",
    "sg:address":"Kirkegade 15",
    "sg:city":"Bramming",
    "sg:orig_category":"Zoneterapeuter",
    "sg:phone":"+45 75 19 04 25",
    "sg:postcode":"6740",
    "sg:province":"Danmark",
    "wof:name":"Kokholm, Lilian",
    "wof:placetype":"venue"
},
  "geometry": {"coordinates":[8.6943712234,55.4675521851],"type":"Point"}
}