{
  "type": "Feature",
  "properties": {
    "iso:country":"DK",
    "sg:address":"Skovlytoften 33 ",
    "sg:city":"Holte",
    "sg:classifiers":[
        {
            "category":"Farming",
            "subcategory":"Livestock Farm",
            "type":"Manufacturing & Wholesale Goods"
        }
    ],
    "sg:phone":"+45 45 46 90 00",
    "sg:postcode":"2840",
    "sg:province":"Danmark",
    "sg:tags":[
        "agriculture"
    ],
    "wof:name":"CERESTAR SCANDINAVIA A/S",
    "wof:placetype":"venue"
},
  "geometry": {"coordinates":[12.4881038666,55.8203773499],"type":"Point"}
}