{
  "type": "Feature",
  "properties": {
    "iso:country":"DK",
    "sg:address":"B\u00f8gedal 25",
    "sg:city":"Ans",
    "sg:orig_category":"Asfalt",
    "sg:phone":"+45 87 70 87 00",
    "sg:postcode":"8643",
    "sg:province":"Danmark",
    "wof:name":"Tarco Vej A/S",
    "wof:placetype":"venue"
},
  "geometry": {"coordinates":[9.6525697708,56.3011627197],"type":"Point"}
}