{
  "type": "Feature",
  "properties": {
    "addr:full":"Bjerring Hede 7 Bjerringbro Danmark 8850",
    "addr:housenumber":"7",
    "addr:postcode":"8850",
    "addr:street":"Bjerring Hede",
    "iso:country":"DK",
    "sg:address":"Bjerring Hede 7",
    "sg:city":"Bjerringbro",
    "sg:orig_category":"Malermestre",
    "sg:phone":"+45 86 68 28 80",
    "sg:postcode":"8850",
    "sg:province":"Danmark",
    "wof:name":"Pedersen, Toni",
    "wof:placetype":"venue"
},
  "geometry": {"coordinates":[9.6209764481,56.3813667297],"type":"Point"}
}