{
  "type": "Feature",
  "properties": {
    "addr:full":"Korevej 15 Aalborg S\u00d8 Danmark 9210",
    "addr:housenumber":"15",
    "addr:postcode":"9210",
    "addr:street":"Korevej",
    "iso:country":"DK",
    "sg:address":"Korevej 15",
    "sg:city":"Aalborg S\u00d8",
    "sg:orig_category":"Vagtbureauer",
    "sg:phone":"+45 96 33 02 00",
    "sg:postcode":"9210",
    "sg:province":"Danmark",
    "sg:website":"www.nordjyskvagt.dk",
    "wof:name":"Nordjydsk Vagtservice",
    "wof:placetype":"venue"
},
  "geometry": {"coordinates":[9.9545106888,57.0114822388],"type":"Point"}
}