{
  "type": "Feature",
  "properties": {
    "iso:country":"DK",
    "sg:address":"Vodroffsvej 56 A, st.",
    "sg:city":"Frederiksberg",
    "sg:orig_category":"Intern Medicin, Medicinske hormonsygdomme Medicinsk endokrinologi",
    "sg:phone":"+45 35 36 10 81",
    "sg:postcode":"1900",
    "sg:province":"Danmark",
    "wof:name":"K\u00f8lendorf, Klaus",
    "wof:placetype":"venue"
},
  "geometry": {"coordinates":[12.5545854568,55.6779708862],"type":"Point"}
}