{
  "type": "Feature",
  "properties": {
    "iso:country":"DK",
    "sg:address":"v/ Bjarne Olsen, Snerlevej 2",
    "sg:city":"Grenaa",
    "sg:orig_category":"Hobbybetonede foreninger",
    "sg:phone":"+45 86 32 70 42",
    "sg:postcode":"8500",
    "sg:province":"Danmark",
    "sg:website":"www.haveselskab.dk",
    "wof:name":"Det jydske Haveselskab, \u00d8stdjurs Havekreds",
    "wof:placetype":"venue"
},
  "geometry": {"coordinates":[10.8774929047,56.4126853943],"type":"Point"}
}