{
  "type": "Feature",
  "properties": {
    "addr:full":"Suderbovej 16 Frederikshavn Danmark 9900",
    "addr:housenumber":"16",
    "addr:postcode":"9900",
    "addr:street":"Suderbovej",
    "iso:country":"DK",
    "sg:address":"Suderbovej 16",
    "sg:city":"Frederikshavn",
    "sg:orig_category":"Flyselskaber",
    "sg:phone":"+45 98 43 30 00",
    "sg:postcode":"9900",
    "sg:province":"Danmark",
    "wof:name":"Fly Bus Nord/K\u00e6rholms Turistbusser",
    "wof:placetype":"venue"
},
  "geometry": {"coordinates":[10.494058609,57.442565918],"type":"Point"}
}