{
  "type": "Feature",
  "properties": {
    "addr:full":"Aldersrogade 3 A K\u00f8benhavn \u00d8 Danmark 2100",
    "addr:housenumber":"3 a",
    "addr:postcode":"2100",
    "addr:street":"Aldersrogade;Kobenhavn O Danmark",
    "iso:country":"DK",
    "sg:address":"Aldersrogade 3 A",
    "sg:city":"K\u00f8benhavn \u00d8",
    "sg:orig_category":"Reklamebureauer",
    "sg:phone":"+45 39 15 02 00",
    "sg:postcode":"2100",
    "sg:province":"Danmark",
    "sg:website":"www.newconnexion.dk",
    "wof:name":"New Connexion",
    "wof:placetype":"venue"
},
  "geometry": {"coordinates":[11.6836299896,60.2548065186],"type":"Point"}
}