{
  "type": "Feature",
  "properties": {
    "addr:full":"Voldum-Rud Vej 40, Voldum Hadsten Danmark 8370",
    "addr:housenumber":"40",
    "addr:postcode":"8370",
    "addr:street":"Voldum-Rud Vej;Voldum",
    "iso:country":"DK",
    "sg:address":"Voldum-Rud Vej 40, Voldum",
    "sg:city":"Hadsten",
    "sg:orig_category":"Kommunale folkeskoler",
    "sg:phone":"+45 86 49 10 03",
    "sg:postcode":"8370",
    "sg:province":"Danmark",
    "wof:name":"Voldum Skole",
    "wof:placetype":"venue"
},
  "geometry": {"coordinates":[10.047659874,56.3287239075],"type":"Point"}
}