{
  "type": "Feature",
  "properties": {
    "addr:full":"v/ Sonja Sveistrup, Spurvevej 3 Hobro Danmark 9500",
    "addr:housenumber":"3",
    "addr:postcode":"9500",
    "addr:street":"Spurvevej",
    "iso:country":"DK",
    "sg:address":"v/ Sonja Sveistrup, Spurvevej 3",
    "sg:city":"Hobro",
    "sg:orig_category":"Oplysningsforbund",
    "sg:phone":"+45 98 51 29 80",
    "sg:postcode":"9500",
    "sg:province":"Danmark",
    "wof:name":"LOF",
    "wof:placetype":"venue"
},
  "geometry": {"coordinates":[9.7946596146,56.6382789612],"type":"Point"}
}