{
  "type": "Feature",
  "properties": {
    "addr:full":"Frugtmarkedet 19 Valby Danmark 2500",
    "addr:housenumber":"19",
    "addr:postcode":"2500",
    "addr:street":"Frugtmarkedet",
    "iso:country":"DK",
    "sg:address":"Frugtmarkedet 19",
    "sg:city":"Valby",
    "sg:orig_category":"Farvehandlere",
    "sg:phone":"+45 36 46 87 09",
    "sg:postcode":"2500",
    "sg:province":"Danmark",
    "sg:website":"www.roverkob.dk",
    "wof:name":"R\u00d8VERK\u00d8B",
    "wof:placetype":"venue"
},
  "geometry": {"coordinates":[12.505988121,55.6567802429],"type":"Point"}
}