{
  "type": "Feature",
  "properties": {
    "iso:country":"DK",
    "sg:address":"Vestergade 5",
    "sg:city":"Fjerritslev",
    "sg:orig_category":"Sundhedscentre",
    "sg:phone":"+45 96 50 11 83",
    "sg:postcode":"9690",
    "sg:province":"Danmark",
    "wof:name":"Sund By Butikken",
    "wof:placetype":"venue"
},
  "geometry": {"coordinates":[9.264837265,57.0881958008],"type":"Point"}
}