{
  "type": "Feature",
  "properties": {
    "iso:country":"DK",
    "sg:address":"\u00d8stergade 65",
    "sg:city":"Assens",
    "sg:classifiers":[
        {
            "category":"Manufacturing",
            "subcategory":"Tobacco Products",
            "type":"Manufacturing & Wholesale Goods"
        }
    ],
    "sg:phone":"+45 64 71 32 51",
    "sg:postcode":"5610",
    "sg:province":"Danmark",
    "sg:tags":[
        "manufacturer"
    ],
    "wof:name":"Modemagasinet",
    "wof:placetype":"venue"
},
  "geometry": {"coordinates":[9.9001121521,55.2703933716],"type":"Point"}
}