{
  "type": "Feature",
  "properties": {
    "addr:full":"Bl\u00e5vandvej 3 Bl\u00e5vand Danmark 6857",
    "addr:housenumber":"3",
    "addr:postcode":"6857",
    "addr:street":"Blaavandvej",
    "iso:country":"DK",
    "sg:address":"Bl\u00e5vandvej 3",
    "sg:city":"Bl\u00e5vand",
    "sg:orig_category":"Stearinlys",
    "sg:phone":"+45 75 27 94 94",
    "sg:postcode":"6857",
    "sg:province":"Danmark",
    "wof:name":"Bl\u00e5vand Lys",
    "wof:placetype":"venue"
},
  "geometry": {"coordinates":[-121.969581604,38.2857437134],"type":"Point"}
}