{
  "type": "Feature",
  "properties": {
    "iso:country":"DK",
    "sg:address":"Ceresvej 1",
    "sg:city":"Frederiksberg",
    "sg:orig_category":"Skuespillere",
    "sg:phone":"+45 33 24 30 27",
    "sg:postcode":"1863",
    "sg:province":"Danmark",
    "wof:name":"L\u00f8ye, Hanne",
    "wof:placetype":"venue"
},
  "geometry": {"coordinates":[12.5368967056,55.6791114807],"type":"Point"}
}