{
  "type": "Feature",
  "properties": {
    "addr:full":"Sct. J\u00f8rgensbjerg 44 Kalundborg Danmark 4400",
    "addr:housenumber":"44",
    "addr:postcode":"4400",
    "iso:country":"DK",
    "sg:address":"Sct. J\u00f8rgensbjerg 44",
    "sg:city":"Kalundborg",
    "sg:orig_category":"Flytteforretninger",
    "sg:phone":"+45 59 51 03 24",
    "sg:postcode":"4400",
    "sg:province":"Danmark",
    "sg:website":"www.kalundborg-flytteforretning.dk",
    "wof:name":"Kalundborg Flytteforretning & H\u00e5ndv\u00e6rkerservice",
    "wof:placetype":"venue"
},
  "geometry": {"coordinates":[11.0934085846,55.6797485352],"type":"Point"}
}