{
  "type": "Feature",
  "properties": {
    "addr:full":"Kildeg\u00e5rdsvej 71 Hellerup Danmark 2900",
    "addr:housenumber":"71",
    "addr:postcode":"2900",
    "addr:street":"Kildegaardsvej",
    "iso:country":"DK",
    "sg:address":"Kildeg\u00e5rdsvej 71",
    "sg:city":"Hellerup",
    "sg:orig_category":"Politi",
    "sg:phone":"+45 39 68 14 48",
    "sg:postcode":"2900",
    "sg:province":"Danmark",
    "wof:name":"Politikontoret i Gentofte.",
    "wof:placetype":"venue"
},
  "geometry": {"coordinates":[12.5477991104,55.7371253967],"type":"Point"}
}