{
  "type": "Feature",
  "properties": {
    "addr:full":"Kirkevej 14 Ranum Danmark 9681",
    "addr:housenumber":"14",
    "addr:postcode":"9681",
    "addr:street":"Kirkevej",
    "iso:country":"DK",
    "sg:address":"Kirkevej 14",
    "sg:city":"Ranum",
    "sg:orig_category":"Malermestre",
    "sg:phone":"+45 98 67 62 04",
    "sg:postcode":"9681",
    "sg:province":"Danmark",
    "wof:name":"Hansen, John Rindom",
    "wof:placetype":"venue"
},
  "geometry": {"coordinates":[9.2282400131,56.8956680298],"type":"Point"}
}