{
  "type": "Feature",
  "properties": {
    "addr:full":"Gl. \u00c5rhusvej 398 Viborg Danmark 8800",
    "addr:housenumber":"398",
    "addr:postcode":"8800",
    "addr:street":"Gl. Aarhusvej",
    "iso:country":"DK",
    "sg:address":"Gl. \u00c5rhusvej 398",
    "sg:city":"Viborg",
    "sg:orig_category":"Murermestre",
    "sg:phone":"+45 86 63 96 83",
    "sg:postcode":"8800",
    "sg:province":"Danmark",
    "wof:name":"M\u00f8ller & Thomsen ApS, Mesterbyg",
    "wof:placetype":"venue"
},
  "geometry": {"coordinates":[9.4368896484,56.3975143433],"type":"Point"}
}