{
  "type": "Feature",
  "properties": {
    "addr:full":"Peder Godskes Vej 4 Virum Danmark 2830",
    "addr:housenumber":"4",
    "addr:postcode":"2830",
    "addr:street":"Peder Godskes Vej",
    "iso:country":"DK",
    "sg:address":"Peder Godskes Vej 4",
    "sg:city":"Virum",
    "sg:orig_category":"Forlag",
    "sg:phone":"+45 45 85 19 01",
    "sg:postcode":"2830",
    "sg:province":"Danmark",
    "wof:name":"Libero, Forlaget",
    "wof:placetype":"venue"
},
  "geometry": {"coordinates":[12.4561672211,55.7927436829],"type":"Point"}
}