{
  "type": "Feature",
  "properties": {
    "addr:full":"Sct. J\u00f8rgens Gade 17 Holstebro Danmark 7500",
    "addr:housenumber":"17",
    "addr:postcode":"7500",
    "addr:street":"Jorgens Gade",
    "iso:country":"DK",
    "sg:address":"Sct. J\u00f8rgens Gade 17",
    "sg:city":"Holstebro",
    "sg:orig_category":"Motionscentre",
    "sg:phone":"+45 97 42 79 09",
    "sg:postcode":"7500",
    "sg:province":"Danmark",
    "wof:name":"Fysioterapeutens Tr\u00e6nings- & Motionscenter",
    "wof:placetype":"venue"
},
  "geometry": {"coordinates":[8.6202583313,56.3625221252],"type":"Point"}
}