{
  "type": "Feature",
  "properties": {
    "iso:country":"DK",
    "sg:address":"Skolevej 70",
    "sg:city":"Galten",
    "sg:orig_category":"Efterskoler",
    "sg:phone":"+45 86 94 41 66",
    "sg:postcode":"8464",
    "sg:province":"Danmark",
    "sg:website":"www.klank-efterskole",
    "wof:name":"Klank Efterskole",
    "wof:placetype":"venue"
},
  "geometry": {"coordinates":[9.9139661789,56.1492347717],"type":"Point"}
}