{
  "type": "Feature",
  "properties": {
    "addr:full":"Strandvejen 159 Esperg\u00e6rde Danmark 3060",
    "addr:housenumber":"159",
    "addr:postcode":"3060",
    "addr:street":"Strandvejen",
    "iso:country":"DK",
    "sg:address":"Strandvejen 159",
    "sg:city":"Esperg\u00e6rde",
    "sg:classifiers":[
        {
            "category":"Restaurant",
            "type":"Food & Drink"
        }
    ],
    "sg:phone":"+45 49 13 50 25",
    "sg:postcode":"3060",
    "sg:province":"Danmark",
    "wof:name":"Gallo D'oro, Ristorante - Pizzeria",
    "wof:placetype":"venue"
},
  "geometry": {"coordinates":[11.6512403488,47.8390617371],"type":"Point"}
}