{
  "type": "Feature",
  "properties": {
    "addr:full":"Odensevej 137, Harritslev Bogense Danmark 5400",
    "addr:housenumber":"137",
    "addr:postcode":"5400",
    "addr:street":"Odensevej;Harritslev",
    "iso:country":"DK",
    "sg:address":"Odensevej 137, Harritslev",
    "sg:city":"Bogense",
    "sg:orig_category":"Autoreparation og -service",
    "sg:phone":"+45 64 81 12 03",
    "sg:postcode":"5400",
    "sg:province":"Danmark",
    "wof:name":"Harritslev Autoservice",
    "wof:placetype":"venue"
},
  "geometry": {"coordinates":[10.0943098068,55.5637893677],"type":"Point"}
}