{
  "type": "Feature",
  "properties": {
    "addr:full":"Hostrupvej 64 Hobro Danmark 9500",
    "addr:housenumber":"64",
    "addr:postcode":"9500",
    "addr:street":"Hostrupvej",
    "iso:country":"DK",
    "sg:address":"Hostrupvej 64",
    "sg:city":"Hobro",
    "sg:orig_category":"Autoreservedele",
    "sg:phone":"+45 98 51 16 60",
    "sg:postcode":"9500",
    "sg:province":"Danmark",
    "wof:name":"Chandi Import ApS",
    "wof:placetype":"venue"
},
  "geometry": {"coordinates":[9.79296875,56.6445884705],"type":"Point"}
}