{
  "type": "Feature",
  "properties": {
    "addr:full":"Algade 27 Store Heddinge Danmark 4660",
    "addr:housenumber":"27",
    "addr:postcode":"4660",
    "addr:street":"Algade",
    "iso:country":"DK",
    "sg:address":"Algade 27",
    "sg:city":"Store Heddinge",
    "sg:orig_category":"Sko",
    "sg:phone":"+45 56 50 21 69",
    "sg:postcode":"4660",
    "sg:province":"Danmark",
    "wof:name":"Hansen Sko A/S, Oluf",
    "wof:placetype":"venue"
},
  "geometry": {"coordinates":[12.3893461227,55.311340332],"type":"Point"}
}