{
  "type": "Feature",
  "properties": {
    "addr:full":"Skoleleder: Betty Madsen, Gedhusvej 31, Ilskov Sunds Danmark 7451",
    "addr:housenumber":"31",
    "addr:postcode":"7451",
    "addr:street":"Betty;Gedhusvej;Ilskov",
    "iso:country":"DK",
    "sg:address":"Skoleleder: Betty Madsen, Gedhusvej 31, Ilskov",
    "sg:city":"Sunds",
    "sg:orig_category":"Oplysningsforbund",
    "sg:phone":"+45 97 14 59 33",
    "sg:postcode":"7451",
    "sg:province":"Danmark",
    "wof:name":"LOF - Liberalt Oplysnings Forbund",
    "wof:placetype":"venue"
},
  "geometry": {"coordinates":[9.0151100159,56.2057800293],"type":"Point"}
}