{
  "type": "Feature",
  "properties": {
    "addr:full":"Billeshavev\u00e6nget 7, Korup Odense NV Danmark 5210",
    "addr:housenumber":"7",
    "addr:postcode":"5210",
    "addr:street":"Billeshavevaenget;Korup",
    "iso:country":"DK",
    "sg:address":"Billeshavev\u00e6nget 7, Korup",
    "sg:city":"Odense NV",
    "sg:orig_category":"Engros handel",
    "sg:phone":"+45 65 94 25 28",
    "sg:postcode":"5210",
    "sg:province":"Danmark",
    "wof:name":"Maple Leaf Imports",
    "wof:placetype":"venue"
},
  "geometry": {"coordinates":[10.274764061,55.4303321838],"type":"Point"}
}