{
  "type": "Feature",
  "properties": {
    "iso:country":"DK",
    "sg:address":"N\u00f8rremarksvej 38",
    "sg:city":"Klarup",
    "sg:orig_category":"Solcentre",
    "sg:phone":"+45 98 31 01 80",
    "sg:postcode":"9270",
    "sg:province":"Danmark",
    "wof:name":"Dan Sun",
    "wof:placetype":"venue"
},
  "geometry": {"coordinates":[10.0521068573,57.0164527893],"type":"Point"}
}