{
  "type": "Feature",
  "properties": {
    "iso:country":"DK",
    "sg:address":"Benl\u00f8se By 45 A",
    "sg:city":"Ringsted",
    "sg:orig_category":"Kirker",
    "sg:postcode":"4100",
    "sg:province":"Danmark",
    "wof:name":"Benl\u00f8se Kirke",
    "wof:placetype":"venue"
},
  "geometry": {"coordinates":[11.7875862122,55.4458961487],"type":"Point"}
}