{
  "type": "Feature",
  "properties": {
    "addr:full":"Dalgas Have 46 Frederiksberg Danmark 2000",
    "addr:housenumber":"46",
    "addr:postcode":"2000",
    "addr:street":"Dalgas Have",
    "iso:country":"DK",
    "sg:address":"Dalgas Have 46",
    "sg:city":"Frederiksberg",
    "sg:classifiers":[
        {
            "category":"Restaurant",
            "type":"Food & Drink"
        }
    ],
    "sg:phone":"+45 38 88 38 36",
    "sg:postcode":"2000",
    "sg:province":"Danmark",
    "sg:website":"the5senses.dalgashave.dk",
    "wof:name":"Anversen, Caf\u00e9",
    "wof:placetype":"venue"
},
  "geometry": {"coordinates":[12.5158481598,55.6838722229],"type":"Point"}
}