{
  "type": "Feature",
  "properties": {
    "addr:full":"Nyvej 6 Hornslet Danmark 8543",
    "addr:housenumber":"6",
    "addr:postcode":"8543",
    "addr:street":"Nyvej",
    "iso:country":"DK",
    "sg:address":"Nyvej 6",
    "sg:city":"Hornslet",
    "sg:orig_category":"Politi",
    "sg:phone":"+45 86 99 40 24",
    "sg:postcode":"8543",
    "sg:province":"Danmark",
    "wof:name":"Politistationen i Hornslet",
    "wof:placetype":"venue"
},
  "geometry": {"coordinates":[10.3182725906,56.3172454834],"type":"Point"}
}