{
  "type": "Feature",
  "properties": {
    "addr:full":"Vestergade 17 Roskilde Danmark 4000",
    "addr:housenumber":"17",
    "addr:postcode":"4000",
    "addr:street":"Vestergade",
    "iso:country":"DK",
    "sg:address":"Vestergade 17",
    "sg:city":"Roskilde",
    "sg:orig_category":"Handicap-daginstitutioner",
    "sg:phone":"+45 46 36 43 93",
    "sg:postcode":"4000",
    "sg:province":"Danmark",
    "wof:name":"Klub Vi",
    "wof:placetype":"venue"
},
  "geometry": {"coordinates":[12.0673246384,55.6449203491],"type":"Point"}
}