{
  "type": "Feature",
  "properties": {
    "addr:full":"Sorovej 26  Ruds Vedby Danmark 4291",
    "addr:housenumber":"26",
    "addr:postcode":"4291",
    "addr:street":"Sorovej",
    "iso:country":"DK",
    "sg:address":"Sorovej 26 ",
    "sg:city":"Ruds Vedby",
    "sg:classifiers":[
        {
            "category":"Shopping",
            "subcategory":"Clothing, Apparel, & Fashions",
            "type":"Retail Goods"
        }
    ],
    "sg:phone":"+45 58 26 13 33",
    "sg:postcode":"4291",
    "sg:province":"Danmark",
    "sg:tags":[
        "clothes"
    ],
    "wof:name":"TIPPY A/S",
    "wof:placetype":"venue"
},
  "geometry": {"coordinates":[11.3854322433,55.5407028198],"type":"Point"}
}