{
  "type": "Feature",
  "properties": {
    "iso:country":"DK",
    "sg:address":"Heagervej 1, Nordenskov",
    "sg:city":"Varde",
    "sg:orig_category":"Bagere",
    "sg:phone":"+45 75 29 80 03",
    "sg:postcode":"6800",
    "sg:province":"Danmark",
    "wof:name":"Nordenskov Bageri",
    "wof:placetype":"venue"
},
  "geometry": {"coordinates":[8.48263,55.622074],"type":"Point"}
}