{
  "type": "Feature",
  "properties": {
    "addr:full":"Lillelundvej 6 - 8 Herning Danmark 7400",
    "addr:housenumber":"6 8",
    "addr:postcode":"7400",
    "addr:street":"Lillelundvej",
    "iso:country":"DK",
    "sg:address":"Lillelundvej 6 - 8",
    "sg:city":"Herning",
    "sg:orig_category":"Fabrikker",
    "sg:phone":"+45 97 12 58 88",
    "sg:postcode":"7400",
    "sg:province":"Danmark",
    "wof:name":"Selandia Paneler A/S",
    "wof:placetype":"venue"
},
  "geometry": {"coordinates":[8.9935407639,56.1480484009],"type":"Point"}
}