{
  "type": "Feature",
  "properties": {
    "addr:full":"Johannevej 24 Odense C Danmark 5000",
    "addr:housenumber":"24",
    "addr:postcode":"5000",
    "addr:street":"Johannevej",
    "iso:country":"DK",
    "sg:address":"Johannevej 24",
    "sg:city":"Odense C",
    "sg:classifiers":[
        {
            "category":"Arts & Performance",
            "subcategory":"Festival",
            "type":"Entertainment"
        }
    ],
    "sg:phone":"+45 66 12 87 50",
    "sg:postcode":"5000",
    "sg:province":"Danmark",
    "sg:tags":[
        "tekstilindustri"
    ],
    "wof:name":"Price",
    "wof:placetype":"venue"
},
  "geometry": {"coordinates":[10.3642072678,55.4042282104],"type":"Point"}
}