{
  "type": "Feature",
  "properties": {
    "addr:full":"Vildmosevej 16, Dokkedal Storvorde Danmark 9280",
    "addr:housenumber":"16",
    "addr:postcode":"9280",
    "addr:street":"Vildmosevej;Dokkedal",
    "iso:country":"DK",
    "sg:address":"Vildmosevej 16, Dokkedal",
    "sg:city":"Storvorde",
    "sg:orig_category":"Naturvejledning",
    "sg:phone":"+45 96 77 66 33",
    "sg:postcode":"9280",
    "sg:province":"Danmark",
    "sg:website":"www.vildmosegaard.dk",
    "wof:name":"Naturskolen i Lille Vildmose Vildmosegaard",
    "wof:placetype":"venue"
},
  "geometry": {"coordinates":[10.1014204025,57.0045547485],"type":"Point"}
}