{
  "type": "Feature",
  "properties": {
    "addr:full":"Lemmingvej 9 Silkeborg Danmark 8600",
    "addr:housenumber":"9",
    "addr:postcode":"8600",
    "addr:street":"Lemmingvej",
    "iso:country":"DK",
    "sg:address":"Lemmingvej 9",
    "sg:city":"Silkeborg",
    "sg:orig_category":"Kirker",
    "sg:postcode":"8600",
    "sg:province":"Danmark",
    "wof:name":"Sejling Kirke",
    "wof:placetype":"venue"
},
  "geometry": {"coordinates":[9.5190811157,56.2185173035],"type":"Point"}
}