{
  "type": "Feature",
  "properties": {
    "addr:full":"Ryttermarken 9 Svendborg Danmark 5700",
    "addr:housenumber":"9",
    "addr:postcode":"5700",
    "addr:street":"Ryttermarken",
    "iso:country":"DK",
    "sg:address":"Ryttermarken 9",
    "sg:city":"Svendborg",
    "sg:classifiers":[
        {
            "category":"Wholesale",
            "subcategory":"Chemicals & Plastics",
            "type":"Manufacturing & Wholesale Goods"
        }
    ],
    "sg:phone":"+45 62 21 36 35",
    "sg:postcode":"5700",
    "sg:province":"Danmark",
    "wof:name":"Plastard - Erik M\u00f8lgaard",
    "wof:placetype":"venue"
},
  "geometry": {"coordinates":[10.5746021271,55.0666007996],"type":"Point"}
}