{
  "type": "Feature",
  "properties": {
    "iso:country":"DK",
    "sg:address":"Bjerrevej 184",
    "sg:city":"Horsens",
    "sg:orig_category":"Skilte",
    "sg:phone":"+45 75 64 51 48",
    "sg:postcode":"8700",
    "sg:province":"Danmark",
    "wof:name":"Horsens Reklamecenter",
    "wof:placetype":"venue"
},
  "geometry": {"coordinates":[9.8503265381,55.828918457],"type":"Point"}
}