{
  "type": "Feature",
  "properties": {
    "addr:full":"N\u00f8rregade 13 Ringsted Danmark 4100",
    "addr:housenumber":"13",
    "addr:postcode":"4100",
    "addr:street":"Norregade",
    "iso:country":"DK",
    "sg:address":"N\u00f8rregade 13",
    "sg:city":"Ringsted",
    "sg:orig_category":"Vikarbureauer",
    "sg:phone":"+45 57 66 09 34",
    "sg:postcode":"4100",
    "sg:province":"Danmark",
    "sg:website":"www.temp-team.dk",
    "wof:name":"Temp-Team",
    "wof:placetype":"venue"
},
  "geometry": {"coordinates":[11.7887792587,55.4467887878],"type":"Point"}
}