{
  "type": "Feature",
  "properties": {
    "iso:country":"DK",
    "sg:address":"G\u00f8teborgvej 6",
    "sg:city":"Aalborg SV",
    "sg:orig_category":"Sejlmagere",
    "sg:phone":"+45 98 18 48 30",
    "sg:postcode":"9200",
    "sg:province":"Danmark",
    "wof:name":"Aalborg Sejlmageri",
    "wof:placetype":"venue"
},
  "geometry": {"coordinates":[9.8955841064,57.0200767517],"type":"Point"}
}