{
  "type": "Feature",
  "properties": {
    "addr:full":"Sneb\u00e6rvej 37 Svenstrup Danmark 9230",
    "addr:housenumber":"37",
    "addr:postcode":"9230",
    "addr:street":"Snebaervej",
    "iso:country":"DK",
    "sg:address":"Sneb\u00e6rvej 37",
    "sg:city":"Svenstrup",
    "sg:orig_category":"Murermestre",
    "sg:phone":"+45 98 38 22 48",
    "sg:postcode":"9230",
    "sg:province":"Danmark",
    "wof:name":"Kragelund, Poul H.",
    "wof:placetype":"venue"
},
  "geometry": {"coordinates":[9.8160915375,56.9656181335],"type":"Point"}
}