{
  "type": "Feature",
  "properties": {
    "addr:full":"Viborgvej 79, Mejrup Holstebro Danmark 7500",
    "addr:housenumber":"79",
    "addr:postcode":"7500",
    "addr:street":"Viborgvej;Mejrup",
    "iso:country":"DK",
    "sg:address":"Viborgvej 79, Mejrup",
    "sg:city":"Holstebro",
    "sg:orig_category":"Landbrugsmaskiner",
    "sg:phone":"+45 97 42 09 66",
    "sg:postcode":"7500",
    "sg:province":"Danmark",
    "wof:name":"Nielsen, A/S Henry D.",
    "wof:placetype":"venue"
},
  "geometry": {"coordinates":[8.6202583313,56.3625221252],"type":"Point"}
}