{
  "type": "Feature",
  "properties": {
    "addr:full":"Strandvejen 183, 1. th. Hellerup Danmark 2900",
    "addr:housenumber":"183 1 th.",
    "addr:postcode":"2900",
    "addr:street":"Strandvejen",
    "iso:country":"DK",
    "sg:address":"Strandvejen 183, 1. th.",
    "sg:city":"Hellerup",
    "sg:orig_category":"Arkitekter",
    "sg:phone":"+45 39 62 48 11",
    "sg:postcode":"2900",
    "sg:province":"Danmark",
    "sg:website":"www.mannik-storm.dk",
    "wof:name":"Mannik & Storm A/S Arkitekter MAA",
    "wof:placetype":"venue"
},
  "geometry": {"coordinates":[12.5788497925,55.7413787842],"type":"Point"}
}