{
  "type": "Feature",
  "properties": {
    "addr:full":"Hammeren 6, Tarp Esbjerg N Danmark 6715",
    "addr:housenumber":"6",
    "addr:postcode":"6715",
    "addr:street":"Hammeren",
    "iso:country":"DK",
    "sg:address":"Hammeren 6, Tarp",
    "sg:city":"Esbjerg N",
    "sg:orig_category":"Stenhuggere",
    "sg:phone":"+45 75 16 75 95",
    "sg:postcode":"6715",
    "sg:province":"Danmark",
    "wof:name":"Asger Natursten",
    "wof:placetype":"venue"
},
  "geometry": {"coordinates":[8.4780550003,55.535610199],"type":"Point"}
}