{
  "type": "Feature",
  "properties": {
    "addr:full":"Skimmedevej 10, \u00c5gerup Vipper\u00f8d Danmark 4390",
    "addr:housenumber":"10",
    "addr:postcode":"4390",
    "addr:street":"Skimmedevej",
    "iso:country":"DK",
    "sg:address":"Skimmedevej 10, \u00c5gerup",
    "sg:city":"Vipper\u00f8d",
    "sg:orig_category":"Emballage",
    "sg:phone":"+45 59 11 11 11",
    "sg:postcode":"4390",
    "sg:province":"Danmark",
    "sg:website":"www.superfos.com",
    "wof:name":"Superfos Packaging A/S",
    "wof:placetype":"venue"
},
  "geometry": {"coordinates":[11.770031929,55.6723098755],"type":"Point"}
}