{
  "type": "Feature",
  "properties": {
    "iso:country":"DK",
    "sg:address":"Torvet 2",
    "sg:city":"Dianalund",
    "sg:orig_category":"Blomsterhandlere",
    "sg:phone":"+45 58 24 11 25",
    "sg:postcode":"4293",
    "sg:province":"Danmark",
    "wof:name":"UKrudten",
    "wof:placetype":"venue"
},
  "geometry": {"coordinates":[11.4961156845,55.5267181396],"type":"Point"}
}