{
  "type": "Feature",
  "properties": {
    "addr:full":"Br\u00f8ndvej 4 B Hedehusene Danmark 2640",
    "addr:housenumber":"4 b",
    "addr:postcode":"2640",
    "addr:street":"Brondvej",
    "iso:country":"DK",
    "sg:address":"Br\u00f8ndvej 4 B",
    "sg:city":"Hedehusene",
    "sg:orig_category":"Murermestre",
    "sg:phone":"+45 43 99 20 10",
    "sg:postcode":"2640",
    "sg:province":"Danmark",
    "wof:name":"Haahr ApS, Murerfirma J. E.",
    "wof:placetype":"venue"
},
  "geometry": {"coordinates":[12.1916418076,55.6428451538],"type":"Point"}
}