{
  "type": "Feature",
  "properties": {
    "addr:full":"Skovvangen 42, Kolding Storcenter Kolding Danmark 6000",
    "addr:housenumber":"42",
    "addr:postcode":"6000",
    "addr:street":"Skovvangen;Storcenter",
    "iso:country":"DK",
    "sg:address":"Skovvangen 42, Kolding Storcenter",
    "sg:city":"Kolding",
    "sg:orig_category":"Sko",
    "sg:phone":"+45 75 50 13 36",
    "sg:postcode":"6000",
    "sg:province":"Danmark",
    "wof:name":"Skoringen",
    "wof:placetype":"venue"
},
  "geometry": {"coordinates":[9.4733953476,55.4863586426],"type":"Point"}
}