{
  "type": "Feature",
  "properties": {
    "iso:country":"DK",
    "sg:address":"v/ Arne Svendsen, Bavnet 9",
    "sg:city":"Aakirkeby",
    "sg:orig_category":"Hobbybetonede foreninger",
    "sg:phone":"+45 56 97 45 55",
    "sg:postcode":"3720",
    "sg:province":"Danmark",
    "wof:name":"Danmarks Fjerkr\u00e6avlerforening for Raceavl",
    "wof:placetype":"venue"
},
  "geometry": {"coordinates":[14.9202880859,55.070110321],"type":"Point"}
}