{
  "type": "Feature",
  "properties": {
    "iso:country":"DK",
    "sg:address":"Uggerh\u00f8jvej 7, Uggerby",
    "sg:city":"Hj\u00f8rring",
    "sg:orig_category":"Serigrafi",
    "sg:phone":"+45 98 97 50 33",
    "sg:postcode":"9800",
    "sg:province":"Danmark",
    "wof:name":"PE Serigrafi",
    "wof:placetype":"venue"
},
  "geometry": {"coordinates":[9.988539,57.459476],"type":"Point"}
}