{
  "type": "Feature",
  "properties": {
    "addr:full":"Industrivej 3 A, Stilling Skanderborg Danmark 8660",
    "addr:housenumber":"3 a",
    "addr:postcode":"8660",
    "addr:street":"Industrivej;Stilling",
    "iso:country":"DK",
    "sg:address":"Industrivej 3 A, Stilling",
    "sg:city":"Skanderborg",
    "sg:orig_category":"Elektronik",
    "sg:phone":"+45 86 57 00 22",
    "sg:postcode":"8660",
    "sg:province":"Danmark",
    "sg:website":"www.tnv-electronic.com",
    "wof:name":"TNV Electronic A/S",
    "wof:placetype":"venue"
},
  "geometry": {"coordinates":[9.929974556,56.0380249023],"type":"Point"}
}