{
  "type": "Feature",
  "properties": {
    "addr:full":"Lin\u00e5 Bygade 5 Silkeborg Danmark 8600",
    "addr:housenumber":"5",
    "addr:postcode":"8600",
    "addr:street":"Linaa Bygade",
    "iso:country":"DK",
    "sg:address":"Lin\u00e5 Bygade 5",
    "sg:city":"Silkeborg",
    "sg:orig_category":"Forsamlingshuse",
    "sg:phone":"+45 86 84 10 69",
    "sg:postcode":"8600",
    "sg:province":"Danmark",
    "wof:name":"Lin\u00e5 Forsamlingshus",
    "wof:placetype":"venue"
},
  "geometry": {"coordinates":[9.6873674393,56.1531524658],"type":"Point"}
}