{
  "type": "Feature",
  "properties": {
    "iso:country":"DK",
    "sg:address":"H\u00f8jmarksvej 1 ",
    "sg:city":"Odder",
    "sg:classifiers":[
        {
            "category":"Farming",
            "subcategory":"Livestock Farm",
            "type":"Manufacturing & Wholesale Goods"
        }
    ],
    "sg:phone":"+45 87 80 14 00",
    "sg:postcode":"8300",
    "sg:province":"Danmark",
    "sg:tags":[
        "agriculture"
    ],
    "wof:name":"AARHUHEGNENS ANDEL",
    "wof:placetype":"venue"
},
  "geometry": {"coordinates":[10.1467485428,55.9861488342],"type":"Point"}
}