{
  "type": "Feature",
  "properties": {
    "addr:full":"Fmd.: Ole Flink, Bredstrupvej 15, Roerslev Otterup Danmark 5450",
    "addr:housenumber":"15",
    "addr:postcode":"5450",
    "addr:street":"Bredstrupvej;Roerslev",
    "iso:country":"DK",
    "sg:address":"Fmd.: Ole Flink, Bredstrupvej 15, Roerslev",
    "sg:city":"Otterup",
    "sg:orig_category":"Antenneforeninger",
    "sg:phone":"+45 64 87 20 47",
    "sg:postcode":"5450",
    "sg:province":"Danmark",
    "wof:name":"Roerslev Antenneforening",
    "wof:placetype":"venue"
},
  "geometry": {"coordinates":[10.4545049667,55.5641746521],"type":"Point"}
}