{
  "type": "Feature",
  "properties": {
    "addr:full":"Dr. Larsens Vej 14 Hadsten Danmark 8370",
    "addr:housenumber":"14",
    "addr:postcode":"8370",
    "addr:street":"Dr. Larsens Vej",
    "iso:country":"DK",
    "sg:address":"Dr. Larsens Vej 14",
    "sg:city":"Hadsten",
    "sg:orig_category":"Fotografer",
    "sg:phone":"+45 86 98 32 52",
    "sg:postcode":"8370",
    "sg:province":"Danmark",
    "wof:name":"Linder, Rolf",
    "wof:placetype":"venue"
},
  "geometry": {"coordinates":[10.0454702377,56.3306884766],"type":"Point"}
}