{
  "type": "Feature",
  "properties": {
    "addr:full":"Gr\u00f8nl\u00f8kkevej 6 Odense C Danmark 5000",
    "addr:housenumber":"6",
    "addr:postcode":"5000",
    "addr:street":"Gronlokkevej",
    "iso:country":"DK",
    "sg:address":"Gr\u00f8nl\u00f8kkevej 6",
    "sg:city":"Odense C",
    "sg:orig_category":"Bryggerier",
    "sg:phone":"+45 66 12 12 22",
    "sg:postcode":"5000",
    "sg:province":"Danmark",
    "wof:name":"Carlsberg Bryggeriernes Odense Depot",
    "wof:placetype":"venue"
},
  "geometry": {"coordinates":[10.390794754,55.3961715698],"type":"Point"}
}