{
  "type": "Feature",
  "properties": {
    "iso:country":"DK",
    "sg:address":"T\u00e5rnvej 213",
    "sg:city":"R\u00f8dovre",
    "sg:orig_category":"Bagere",
    "sg:phone":"+45 36 70 49 87",
    "sg:postcode":"2610",
    "sg:province":"Danmark",
    "wof:name":"Carlsro Bageri",
    "wof:placetype":"venue"
},
  "geometry": {"coordinates":[10.699214,61.102776],"type":"Point"}
}