{
  "type": "Feature",
  "properties": {
    "addr:full":"Thistedvej 294, Klim Fjerritslev Danmark 9690",
    "addr:housenumber":"294",
    "addr:postcode":"9690",
    "addr:street":"Thistedvej;Klim",
    "iso:country":"DK",
    "sg:address":"Thistedvej 294, Klim",
    "sg:city":"Fjerritslev",
    "sg:orig_category":"Autoreparation og -service",
    "sg:phone":"+45 98 22 52 18",
    "sg:postcode":"9690",
    "sg:province":"Danmark",
    "wof:name":"Klim Autov\u00e6rksted",
    "wof:placetype":"venue"
},
  "geometry": {"coordinates":[9.2667350769,57.0882301331],"type":"Point"}
}