{
  "type": "Feature",
  "properties": {
    "addr:full":"Fmd.: Eskild Gormsen, Kohavevej 5, Vedelshave Asperup Danmark 5466",
    "addr:housenumber":"5",
    "addr:postcode":"5466",
    "addr:street":"Kohavevej",
    "iso:country":"DK",
    "sg:address":"Fmd.: Eskild Gormsen, Kohavevej 5, Vedelshave",
    "sg:city":"Asperup",
    "sg:orig_category":"Kulturelle foreninger",
    "sg:phone":"+45 64 44 13 57",
    "sg:postcode":"5466",
    "sg:province":"Danmark",
    "wof:name":"Gr\u00e6nseforeningen for Asperup og Roerslev",
    "wof:placetype":"venue"
},
  "geometry": {"coordinates":[9.9057912827,55.4908866882],"type":"Point"}
}