{
  "type": "Feature",
  "properties": {
    "iso:country":"DK",
    "sg:address":"Fuglebakken 52",
    "sg:city":"Viborg",
    "sg:orig_category":"Zoneterapeuter",
    "sg:phone":"+45 86 62 77 38",
    "sg:postcode":"8800",
    "sg:province":"Danmark",
    "wof:name":"Jensen, Mie",
    "wof:placetype":"venue"
},
  "geometry": {"coordinates":[9.3769626617,56.4440383911],"type":"Point"}
}