{
  "type": "Feature",
  "properties": {
    "iso:country":"DK",
    "sg:address":"Tidemandsvej 10",
    "sg:city":"Holb\u00e6k",
    "sg:orig_category":"Bagere",
    "sg:phone":"+45 59 43 02 03",
    "sg:postcode":"4300",
    "sg:province":"Danmark",
    "wof:name":"Bageriet i Tidemandsvej",
    "wof:placetype":"venue"
},
  "geometry": {"coordinates":[76.307098,14.27713],"type":"Point"}
}