{
  "type": "Feature",
  "properties": {
    "addr:full":"Jennumvej 12 Spentrup Danmark 8981",
    "addr:housenumber":"12",
    "addr:postcode":"8981",
    "addr:street":"Jennumvej",
    "iso:country":"DK",
    "sg:address":"Jennumvej 12",
    "sg:city":"Spentrup",
    "sg:orig_category":"Autoreparation og -service",
    "sg:phone":"+45 86 47 70 94",
    "sg:postcode":"8981",
    "sg:province":"Danmark",
    "wof:name":"Spentrup Auto",
    "wof:placetype":"venue"
},
  "geometry": {"coordinates":[10.0442380905,56.5343284607],"type":"Point"}
}