{
  "type": "Feature",
  "properties": {
    "addr:full":"Strandfogedvej 11 Nakskov Danmark 4900",
    "addr:housenumber":"11",
    "addr:postcode":"4900",
    "addr:street":"Strandfogedvej",
    "iso:country":"DK",
    "sg:address":"Strandfogedvej 11",
    "sg:city":"Nakskov",
    "sg:orig_category":"Murermestre",
    "sg:phone":"+45 54 92 47 64",
    "sg:postcode":"4900",
    "sg:province":"Danmark",
    "wof:name":"Christensen, Per",
    "wof:placetype":"venue"
},
  "geometry": {"coordinates":[11.1162996292,54.8354148865],"type":"Point"}
}