{
  "type": "Feature",
  "properties": {
    "addr:full":"Rasmus F\u00e6rchs Vej 19 Holstebro Danmark 7500",
    "addr:housenumber":"19",
    "addr:postcode":"7500",
    "addr:street":"Faerchs Vej",
    "iso:country":"DK",
    "sg:address":"Rasmus F\u00e6rchs Vej 19",
    "sg:city":"Holstebro",
    "sg:orig_category":"Bogbinderier",
    "sg:phone":"+45 97 42 23 44",
    "sg:postcode":"7500",
    "sg:province":"Danmark",
    "sg:website":"www.rounborg.dk",
    "wof:name":"Rounborgs grafiske hus ApS",
    "wof:placetype":"venue"
},
  "geometry": {"coordinates":[8.6349191666,56.3787612915],"type":"Point"}
}