{
  "type": "Feature",
  "properties": {
    "addr:full":"Kong Valdemars Vej 3 Roskilde Danmark 4000",
    "addr:housenumber":"3",
    "addr:postcode":"4000",
    "addr:street":"Kong Valdemars Vej",
    "iso:country":"DK",
    "sg:address":"Kong Valdemars Vej 3",
    "sg:city":"Roskilde",
    "sg:orig_category":"Gravstene",
    "sg:phone":"+45 46 35 21 21",
    "sg:postcode":"4000",
    "sg:province":"Danmark",
    "sg:website":"www.stenhugger.dk",
    "wof:name":"Roskilde Stenhuggeri",
    "wof:placetype":"venue"
},
  "geometry": {"coordinates":[12.0922937393,55.6409339905],"type":"Point"}
}