{
  "type": "Feature",
  "properties": {
    "addr:full":"Strandg\u00e5rdsh\u00f8j 27 Ebeltoft Danmark 8400",
    "addr:housenumber":"27",
    "addr:postcode":"8400",
    "addr:street":"Strandgaardshoj",
    "iso:country":"DK",
    "sg:address":"Strandg\u00e5rdsh\u00f8j 27",
    "sg:city":"Ebeltoft",
    "sg:orig_category":"Trykkerier",
    "sg:phone":"+45 86 34 25 00",
    "sg:postcode":"8400",
    "sg:province":"Danmark",
    "sg:website":"www.djurs-gruppen.dk",
    "wof:name":"Hasn\u00e6s Tryk A/S",
    "wof:placetype":"venue"
},
  "geometry": {"coordinates":[10.6778745651,56.199798584],"type":"Point"}
}