{
  "type": "Feature",
  "properties": {
    "addr:full":"Lille Sct. Peder Str\u00e6de 10 Viborg Danmark 8800",
    "addr:housenumber":"10",
    "addr:postcode":"8800",
    "addr:street":"Lille Sct. Peder Straede",
    "iso:country":"DK",
    "sg:address":"Lille Sct. Peder Str\u00e6de 10",
    "sg:city":"Viborg",
    "sg:orig_category":"Apoteker og -udsalg",
    "sg:phone":"+45 86 62 00 22",
    "sg:postcode":"8800",
    "sg:province":"Danmark",
    "sg:website":"www.apotekeren.dk",
    "wof:name":"Svane Apoteket",
    "wof:placetype":"venue"
},
  "geometry": {"coordinates":[9.4068861008,56.4476165771],"type":"Point"}
}