{
  "type": "Feature",
  "properties": {
    "addr:full":"J\u00f8rgensmaj 1 Aabenraa Danmark 6200",
    "addr:housenumber":"1",
    "addr:postcode":"6200",
    "addr:street":"Jorgensmaj",
    "iso:country":"DK",
    "sg:address":"J\u00f8rgensmaj 1",
    "sg:city":"Aabenraa",
    "sg:orig_category":"Non-Classified Establishments",
    "sg:phone":"+45 74 62 18 66",
    "sg:postcode":"6200",
    "sg:province":"Danmark",
    "sg:website":"www.computerfirmaet.dk",
    "wof:name":"Computerfirmaet",
    "wof:placetype":"venue"
},
  "geometry": {"coordinates":[9.4256458282,55.0492134094],"type":"Point"}
}