{
  "type": "Feature",
  "properties": {
    "iso:country":"DK",
    "sg:address":"Leder: Leila Noesgaard, Tr\u00f8strupvej 16, Torsted",
    "sg:city":"Tim",
    "sg:orig_category":"Ungdomsklubber",
    "sg:phone":"+45 97 33 32 47",
    "sg:postcode":"6980",
    "sg:province":"Danmark",
    "wof:name":"Torsted Ungdomsklub",
    "wof:placetype":"venue"
},
  "geometry": {"coordinates":[8.3066711426,56.1961898804],"type":"Point"}
}