{
  "type": "Feature",
  "properties": {
    "addr:full":"Kerteminde skole, N\u00f8rregade 21 Kerteminde Danmark 5300",
    "addr:housenumber":"21",
    "addr:postcode":"5300",
    "addr:street":"Norregade",
    "iso:country":"DK",
    "sg:address":"Kerteminde skole, N\u00f8rregade 21",
    "sg:city":"Kerteminde",
    "sg:orig_category":"Skolefritidsordninger",
    "sg:phone":"+45 65 32 38 46",
    "sg:postcode":"5300",
    "sg:province":"Danmark",
    "wof:name":"Skolefritidsordningen Kernehuset",
    "wof:placetype":"venue"
},
  "geometry": {"coordinates":[10.6600999832,55.4506492615],"type":"Point"}
}