{
  "type": "Feature",
  "properties": {
    "addr:full":"Kertemindevej 26, Fl\u00f8dstrup Ullerslev Danmark 5540",
    "addr:housenumber":"26",
    "addr:postcode":"5540",
    "addr:street":"Kertemindevej;Flodstrup",
    "iso:country":"DK",
    "sg:address":"Kertemindevej 26, Fl\u00f8dstrup",
    "sg:city":"Ullerslev",
    "sg:orig_category":"Kirker",
    "sg:postcode":"5540",
    "sg:province":"Danmark",
    "wof:name":"Fl\u00f8dstrup Kirke",
    "wof:placetype":"venue"
},
  "geometry": {"coordinates":[10.6675348282,55.3605728149],"type":"Point"}
}