{
  "type": "Feature",
  "properties": {
    "addr:full":"Egelykke 8, Vollerup S\u00f8nderborg Danmark 6400",
    "addr:housenumber":"8",
    "addr:postcode":"6400",
    "addr:street":"Egelykke",
    "iso:country":"DK",
    "sg:address":"Egelykke 8, Vollerup",
    "sg:city":"S\u00f8nderborg",
    "sg:orig_category":"Pressefotografer",
    "sg:phone":"+45 74 43 33 33",
    "sg:postcode":"6400",
    "sg:province":"Danmark",
    "wof:name":"Free Press",
    "wof:placetype":"venue"
},
  "geometry": {"coordinates":[9.7899465561,54.9100151062],"type":"Point"}
}