{
  "type": "Feature",
  "properties": {
    "addr:full":"Horsev\u00e6nget 182 R\u00f8dovre Danmark 2610",
    "addr:housenumber":"182",
    "addr:postcode":"2610",
    "addr:street":"Rodovre Danmark",
    "iso:country":"DK",
    "sg:address":"Horsev\u00e6nget 182",
    "sg:city":"R\u00f8dovre",
    "sg:orig_category":"Dataservice",
    "sg:postcode":"2610",
    "sg:province":"Danmark",
    "wof:name":"KA Merchant",
    "wof:placetype":"venue"
},
  "geometry": {"coordinates":[10.6992139816,61.1027755737],"type":"Point"}
}