{
  "type": "Feature",
  "properties": {
    "addr:full":"Mikkelsgade 9 Bjerringbro Danmark 8850",
    "addr:housenumber":"9",
    "addr:postcode":"8850",
    "addr:street":"Mikkelsgade",
    "iso:country":"DK",
    "sg:address":"Mikkelsgade 9",
    "sg:city":"Bjerringbro",
    "sg:orig_category":"Faglige organisationer og foreninger",
    "sg:phone":"+45 86 68 36 53",
    "sg:postcode":"8850",
    "sg:province":"Danmark",
    "wof:name":"LO Bjerringbro",
    "wof:placetype":"venue"
},
  "geometry": {"coordinates":[9.6621961594,56.3707008362],"type":"Point"}
}