{
  "type": "Feature",
  "properties": {
    "iso:country":"DK",
    "sg:address":"Kertemindevejen 36",
    "sg:city":"Marslev",
    "sg:orig_category":"Hospital, udstyr til",
    "sg:phone":"+45 65 95 12 66",
    "sg:postcode":"5290",
    "sg:province":"Danmark",
    "sg:website":"www.beka.dk",
    "wof:name":"Beka A/S Beremo, Fabrikken",
    "wof:placetype":"venue"
},
  "geometry": {"coordinates":[10.532500267,55.3963470459],"type":"Point"}
}