{
  "type": "Feature",
  "properties": {
    "addr:full":"Gammel Kongevej 37 A K\u00f8benhavn Danmark 1610",
    "addr:housenumber":"37 a;1610",
    "addr:street":"Gammel Kongevej",
    "iso:country":"DK",
    "sg:address":"Gammel Kongevej 37 A",
    "sg:city":"K\u00f8benhavn",
    "sg:orig_category":"Fotohandlere",
    "sg:phone":"+45 33 22 79 40",
    "sg:postcode":"1610",
    "sg:province":"Danmark",
    "wof:name":"Tang Foto",
    "wof:placetype":"venue"
},
  "geometry": {"coordinates":[12.543299675,55.6758003235],"type":"Point"}
}