{
  "type": "Feature",
  "properties": {
    "addr:full":"Hovedgaden 2 Ulstrup Danmark 8860",
    "addr:housenumber":"2",
    "addr:postcode":"8860",
    "addr:street":"Hovedgaden",
    "iso:country":"DK",
    "sg:address":"Hovedgaden 2",
    "sg:city":"Ulstrup",
    "sg:orig_category":"Efterskoler",
    "sg:phone":"+45 86 46 31 33",
    "sg:postcode":"8860",
    "sg:province":"Danmark",
    "wof:name":"Guden\u00e5dalens Ungdomsskole",
    "wof:placetype":"venue"
},
  "geometry": {"coordinates":[9.7937717438,56.3923149109],"type":"Point"}
}