{
  "type": "Feature",
  "properties": {
    "addr:full":"Skolegade 3 A Vejle Danmark 7100",
    "addr:housenumber":"3 a",
    "addr:postcode":"7100",
    "addr:street":"Skolegade",
    "iso:country":"DK",
    "sg:address":"Skolegade 3 A",
    "sg:city":"Vejle",
    "sg:orig_category":"Motorkontorer",
    "sg:phone":"+45 76 43 14 48",
    "sg:postcode":"7100",
    "sg:province":"Danmark",
    "wof:name":"Motorkontoret.",
    "wof:placetype":"venue"
},
  "geometry": {"coordinates":[9.5267782211,55.7118721008],"type":"Point"}
}