{
  "type": "Feature",
  "properties": {
    "addr:full":"Tinggade 18 Ringsted Danmark 4100",
    "addr:housenumber":"18",
    "addr:postcode":"4100",
    "addr:street":"Tinggade",
    "iso:country":"DK",
    "sg:address":"Tinggade 18",
    "sg:city":"Ringsted",
    "sg:orig_category":"Fotohandlere",
    "sg:phone":"+45 57 61 47 50",
    "sg:postcode":"4100",
    "sg:province":"Danmark",
    "sg:website":"www.jims-foto.dk",
    "wof:name":"Jim's Foto",
    "wof:placetype":"venue"
},
  "geometry": {"coordinates":[11.7903213501,55.4440345764],"type":"Point"}
}