{
  "type": "Feature",
  "properties": {
    "addr:full":"R\u00f8nne Alle 15 Gilleleje Danmark 3250",
    "addr:housenumber":"15",
    "addr:postcode":"3250",
    "addr:street":"Ronne Alle",
    "iso:country":"DK",
    "sg:address":"R\u00f8nne Alle 15",
    "sg:city":"Gilleleje",
    "sg:orig_category":"Malermestre",
    "sg:phone":"+45 48 35 44 07",
    "sg:postcode":"3250",
    "sg:province":"Danmark",
    "wof:name":"Laursen, Leo",
    "wof:placetype":"venue"
},
  "geometry": {"coordinates":[12.2966051102,56.1225509644],"type":"Point"}
}