{
  "type": "Feature",
  "properties": {
    "addr:full":"Gl. \u00c5rhusvej 19 Viborg Danmark 8800",
    "addr:housenumber":"19",
    "addr:postcode":"8800",
    "addr:street":"Gl. Aarhusvej",
    "iso:country":"DK",
    "sg:address":"Gl. \u00c5rhusvej 19",
    "sg:city":"Viborg",
    "sg:orig_category":"Non-Classified Establishments",
    "sg:phone":"+45 87 27 33 33",
    "sg:postcode":"8800",
    "sg:province":"Danmark",
    "sg:website":"www.datafilen.dk",
    "wof:name":"DataFilen",
    "wof:placetype":"venue"
},
  "geometry": {"coordinates":[9.4041595459,56.4425506592],"type":"Point"}
}