{
  "type": "Feature",
  "properties": {
    "addr:full":"Hobrovej 26 A Randers Danmark 8900",
    "addr:housenumber":"26 a",
    "addr:postcode":"8900",
    "addr:street":"Hobrovej",
    "iso:country":"DK",
    "sg:address":"Hobrovej 26 A",
    "sg:city":"Randers",
    "sg:orig_category":"Private skoler",
    "sg:phone":"+45 86 42 07 40",
    "sg:postcode":"8900",
    "sg:province":"Danmark",
    "wof:name":"Forberedelsesskolen",
    "wof:placetype":"venue"
},
  "geometry": {"coordinates":[10.0280990601,56.464389801],"type":"Point"}
}