{
  "type": "Feature",
  "properties": {
    "addr:full":"Henv.: Jens Aage Uldal M\u00f8ller, Baarse Nakke 4 Lundby Danmark 4750",
    "addr:housenumber":"4",
    "addr:postcode":"4750",
    "addr:street":"Nakke",
    "iso:country":"DK",
    "sg:address":"Henv.: Jens Aage Uldal M\u00f8ller, Baarse Nakke 4",
    "sg:city":"Lundby",
    "sg:orig_category":"Museer",
    "sg:postcode":"4750",
    "sg:province":"Danmark",
    "wof:name":"Grundtvigs Mindestuer i Udby Pr\u00e6steg\u00e5rd",
    "wof:placetype":"venue"
},
  "geometry": {"coordinates":[11.8101682663,55.1197814941],"type":"Point"}
}