{
  "type": "Feature",
  "properties": {
    "addr:full":"Havnevej 39, Udbyh\u00f8j Havndal Danmark 8970",
    "addr:housenumber":"39",
    "addr:postcode":"8970",
    "addr:street":"Havnevej",
    "iso:country":"DK",
    "sg:address":"Havnevej 39, Udbyh\u00f8j",
    "sg:city":"Havndal",
    "sg:orig_category":"Fisk og vildt",
    "sg:phone":"+45 86 47 20 43",
    "sg:postcode":"8970",
    "sg:province":"Danmark",
    "wof:name":"Bent Fiskemand",
    "wof:placetype":"venue"
},
  "geometry": {"coordinates":[10.1937646866,56.6534461975],"type":"Point"}
}