{
  "type": "Feature",
  "properties": {
    "iso:country":"DK",
    "sg:address":"Storegade 18",
    "sg:city":"Varde",
    "sg:orig_category":"Botilbud",
    "sg:phone":"+45 75 21 05 55",
    "sg:postcode":"6800",
    "sg:province":"Danmark",
    "wof:name":"Center B\u00f8gely, KFUM's beskyttede pensionat",
    "wof:placetype":"venue"
},
  "geometry": {"coordinates":[8.4834871292,55.6200637817],"type":"Point"}
}