{
  "type": "Feature",
  "properties": {
    "iso:country":"DK",
    "sg:address":"Fredensgade 2",
    "sg:city":"Silkeborg",
    "sg:orig_category":"Blomsterhandlere",
    "sg:phone":"+45 86 82 60 99",
    "sg:postcode":"8600",
    "sg:province":"Danmark",
    "sg:website":"www.birgits-blomster.dk",
    "wof:name":"Birgits Blomster",
    "wof:placetype":"venue"
},
  "geometry": {"coordinates":[9.5367822647,56.1650161743],"type":"Point"}
}