{
  "type": "Feature",
  "properties": {
    "addr:full":"Sognepr\u00e6st: J\u00f8rgen Storgaard (K/B), Hovedgaden 112 Tinglev Danmark 6360",
    "addr:housenumber":"112",
    "addr:postcode":"6360",
    "addr:street":"Hovedgaden",
    "iso:country":"DK",
    "sg:address":"Sognepr\u00e6st: J\u00f8rgen Storgaard (K/B), Hovedgaden 112",
    "sg:city":"Tinglev",
    "sg:orig_category":"Kirkesogne",
    "sg:phone":"+45 74 64 40 50",
    "sg:postcode":"6360",
    "sg:province":"Danmark",
    "wof:name":"Tinglev Sogn",
    "wof:placetype":"venue"
},
  "geometry": {"coordinates":[9.2476491928,54.9349365234],"type":"Point"}
}