{
  "type": "Feature",
  "properties": {
    "iso:country":"DK",
    "sg:address":"Godth\u00e5bsvej 11",
    "sg:city":"Svenstrup",
    "sg:orig_category":"Grillbarer",
    "sg:phone":"+45 98 38 04 18",
    "sg:postcode":"9230",
    "sg:province":"Danmark",
    "wof:name":"Torve Grill og Pizza",
    "wof:placetype":"venue"
},
  "geometry": {"coordinates":[9.8523635864,56.9722595215],"type":"Point"}
}