{
  "type": "Feature",
  "properties": {
    "addr:full":"Ryg\u00e5rds All\u00e9 11 Hellerup Danmark 2900",
    "addr:housenumber":"11",
    "addr:postcode":"2900",
    "addr:street":"Rygaards Alle\u0301",
    "iso:country":"DK",
    "sg:address":"Ryg\u00e5rds All\u00e9 11",
    "sg:city":"Hellerup",
    "sg:orig_category":"Vaskerier",
    "sg:phone":"+45 39 62 18 59",
    "sg:postcode":"2900",
    "sg:province":"Danmark",
    "wof:name":"Forenede Dampvaskerier, De",
    "wof:placetype":"venue"
},
  "geometry": {"coordinates":[12.5631685257,55.7339553833],"type":"Point"}
}