{
  "type": "Feature",
  "properties": {
    "addr:full":"Fmd.: Erling Hansen, Filskovvej 28, Bl\u00e5h\u00f8j Brande Danmark 7330",
    "addr:housenumber":"28",
    "addr:postcode":"7330",
    "addr:street":"Erling;Filskovvej",
    "iso:country":"DK",
    "sg:address":"Fmd.: Erling Hansen, Filskovvej 28, Bl\u00e5h\u00f8j",
    "sg:city":"Brande",
    "sg:orig_category":"Grundejerforeninger",
    "sg:phone":"+45 75 34 51 64",
    "sg:postcode":"7330",
    "sg:province":"Danmark",
    "wof:name":"Grundejerforeningen Skuldb\u00f8l Syd, Hemmet",
    "wof:placetype":"venue"
},
  "geometry": {"coordinates":[9.1280345917,55.942779541],"type":"Point"}
}