{
  "type": "Feature",
  "properties": {
    "addr:full":"Knud Erik Rasmussen, Sallingeskovvej 20, Sallinge Ringe Danmark 5750",
    "addr:housenumber":"20",
    "addr:postcode":"5750",
    "addr:street":"Knud Erik Rasmussen Sallingeskovvej;Sallinge",
    "iso:country":"DK",
    "sg:address":"Knud Erik Rasmussen, Sallingeskovvej 20, Sallinge",
    "sg:city":"Ringe",
    "sg:orig_category":"Hobbybetonede foreninger",
    "sg:phone":"+45 62 69 12 21",
    "sg:postcode":"5750",
    "sg:province":"Danmark",
    "sg:website":"hjem.get2net.dk/aselavl",
    "wof:name":"Landsforeningen Dansk \u00c6selavl",
    "wof:placetype":"venue"
},
  "geometry": {"coordinates":[10.4781074524,55.2356643677],"type":"Point"}
}