{
  "type": "Feature",
  "properties": {
    "addr:full":"N\u00f8rregade 15 A Vamdrup Danmark 6580",
    "addr:housenumber":"15 a",
    "addr:postcode":"6580",
    "addr:street":"Norregade",
    "iso:country":"DK",
    "sg:address":"N\u00f8rregade 15 A",
    "sg:city":"Vamdrup",
    "sg:orig_category":"Pizzeriaer",
    "sg:phone":"+45 75 58 03 20",
    "sg:postcode":"6580",
    "sg:province":"Danmark",
    "wof:name":"Kilis Pizzeria",
    "wof:placetype":"venue"
},
  "geometry": {"coordinates":[9.2831192017,55.4278030396],"type":"Point"}
}