{
  "type": "Feature",
  "properties": {
    "addr:full":"Rugmarken 83 Fjerritslev Danmark 9690",
    "addr:housenumber":"83",
    "addr:postcode":"9690",
    "addr:street":"Rugmarken",
    "iso:country":"DK",
    "sg:address":"Rugmarken 83",
    "sg:city":"Fjerritslev",
    "sg:orig_category":"Musikere",
    "sg:phone":"+45 98 21 21 73",
    "sg:postcode":"9690",
    "sg:province":"Danmark",
    "wof:name":"Torben & Alex",
    "wof:placetype":"venue"
},
  "geometry": {"coordinates":[9.2790899277,57.093624115],"type":"Point"}
}