{
  "type": "Feature",
  "properties": {
    "addr:full":"B\u00e6kkevang 51 Kongens Lyngby Danmark 2800",
    "addr:housenumber":"51",
    "addr:postcode":"2800",
    "addr:street":"Baekkevang",
    "iso:country":"DK",
    "sg:address":"B\u00e6kkevang 51",
    "sg:city":"Kongens Lyngby",
    "sg:orig_category":"Alternativ behandling",
    "sg:phone":"+45 45 88 51 56",
    "sg:postcode":"2800",
    "sg:province":"Danmark",
    "wof:name":"Pommer, Rita",
    "wof:placetype":"venue"
},
  "geometry": {"coordinates":[12.5368299484,55.7949905396],"type":"Point"}
}