{
  "type": "Feature",
  "properties": {
    "iso:country":"DK",
    "sg:address":"S\u00f8kildevej 89",
    "sg:city":"Ry",
    "sg:orig_category":"Autoforhandlere",
    "sg:phone":"+45 86 89 15 99",
    "sg:postcode":"8680",
    "sg:province":"Danmark",
    "wof:name":"Bj\u00f8rn, Kurt",
    "wof:placetype":"venue"
},
  "geometry": {"coordinates":[9.7593002319,56.0920562744],"type":"Point"}
}