{
  "type": "Feature",
  "properties": {
    "iso:country":"DK",
    "sg:address":"Engvej 56",
    "sg:city":"Odense M",
    "sg:orig_category":"Datamaskiner",
    "sg:phone":"+45 66 12 92 09",
    "sg:postcode":"5230",
    "sg:province":"Danmark",
    "wof:name":"Balslev, Ivar",
    "wof:placetype":"venue"
},
  "geometry": {"coordinates":[10.3805580139,55.3780822754],"type":"Point"}
}