{
  "type": "Feature",
  "properties": {
    "addr:full":"Kantinekrogen 4 Aalborg Danmark 9000",
    "addr:housenumber":"4",
    "addr:postcode":"9000",
    "addr:street":"Kantinekrogen",
    "iso:country":"DK",
    "sg:address":"Kantinekrogen 4",
    "sg:city":"Aalborg",
    "sg:orig_category":"Faglige organisationer og foreninger",
    "sg:phone":"+45 98 10 90 20",
    "sg:postcode":"9000",
    "sg:province":"Danmark",
    "wof:name":"S\u00f8m\u00e6ndenes Forbund",
    "wof:placetype":"venue"
},
  "geometry": {"coordinates":[9.9544000626,57.0485992432],"type":"Point"}
}