{
  "type": "Feature",
  "properties": {
    "addr:full":"Hundige Strandvej 157 Greve Danmark 2670",
    "addr:housenumber":"157",
    "addr:postcode":"2670",
    "addr:street":"Hundige Strandvej",
    "iso:country":"DK",
    "sg:address":"Hundige Strandvej 157",
    "sg:city":"Greve",
    "sg:orig_category":"Kiropraktorer",
    "sg:phone":"+45 43 90 01 11",
    "sg:postcode":"2670",
    "sg:province":"Danmark",
    "wof:name":"J\u00f8rgensen, Helle",
    "wof:placetype":"venue"
},
  "geometry": {"coordinates":[12.3437595367,55.5945091248],"type":"Point"}
}