{
  "type": "Feature",
  "properties": {
    "addr:full":"Sofienbergparken 3 Nyborg Danmark 5800",
    "addr:housenumber":"3",
    "addr:postcode":"5800",
    "addr:street":"Sofienbergparken",
    "iso:country":"DK",
    "sg:address":"Sofienbergparken 3",
    "sg:city":"Nyborg",
    "sg:orig_category":"Vagtbureauer",
    "sg:phone":"+45 65 31 64 30",
    "sg:postcode":"5800",
    "sg:province":"Danmark",
    "wof:name":"\u00d8stfyns Vagtservice",
    "wof:placetype":"venue"
},
  "geometry": {"coordinates":[10.7660942078,55.3061561584],"type":"Point"}
}