{
  "type": "Feature",
  "properties": {
    "addr:full":"Guldstjernevej 13, Vester Hjermitslev Br\u00f8nderslev Danmark 9700",
    "addr:housenumber":"13",
    "addr:postcode":"9700",
    "addr:street":"Guldstjernevej",
    "iso:country":"DK",
    "sg:address":"Guldstjernevej 13, Vester Hjermitslev",
    "sg:city":"Br\u00f8nderslev",
    "sg:orig_category":"Homeparties",
    "sg:phone":"+45 98 88 74 78",
    "sg:postcode":"9700",
    "sg:province":"Danmark",
    "wof:name":"Ge-Profil",
    "wof:placetype":"venue"
},
  "geometry": {"coordinates":[9.7584476471,57.2860298157],"type":"Point"}
}