{
  "type": "Feature",
  "properties": {
    "addr:full":"Mariagervej 64 Randers Danmark 8900",
    "addr:housenumber":"64",
    "addr:postcode":"8900",
    "addr:street":"Mariagervej",
    "iso:country":"DK",
    "sg:address":"Mariagervej 64",
    "sg:city":"Randers",
    "sg:orig_category":"Servicestationer",
    "sg:phone":"+45 86 42 90 17",
    "sg:postcode":"8900",
    "sg:province":"Danmark",
    "wof:name":"Q 8",
    "wof:placetype":"venue"
},
  "geometry": {"coordinates":[10.0315341949,56.4695091248],"type":"Point"}
}