{
  "type": "Feature",
  "properties": {
    "addr:full":"Ryg\u00e5rds Alle 131 A Hellerup Danmark 2900",
    "addr:housenumber":"131 a",
    "addr:postcode":"2900",
    "addr:street":"Rygaards Alle",
    "iso:country":"DK",
    "sg:address":"Ryg\u00e5rds Alle 131 A",
    "sg:city":"Hellerup",
    "sg:orig_category":"Non-Classified Establishments",
    "sg:phone":"+45 70 22 98 00",
    "sg:postcode":"2900",
    "sg:province":"Danmark",
    "sg:website":"www.edg.dk",
    "wof:name":"EDG ApS",
    "wof:placetype":"venue"
},
  "geometry": {"coordinates":[12.5597038269,55.7225456238],"type":"Point"}
}