{
  "type": "Feature",
  "properties": {
    "addr:full":"Agersigen 9, Vester\u00f8 Havn L\u00e6s\u00f8 Danmark 9940",
    "addr:housenumber":"9",
    "addr:postcode":"9940",
    "addr:street":"Agersigen;Vestero Havn;Danmark",
    "iso:country":"DK",
    "sg:address":"Agersigen 9, Vester\u00f8 Havn",
    "sg:city":"L\u00e6s\u00f8",
    "sg:orig_category":"Pelsdyravl",
    "sg:phone":"+45 98 49 93 97",
    "sg:postcode":"9940",
    "sg:province":"Danmark",
    "wof:name":"L\u00e6s\u00f8 Pelsrenseri",
    "wof:placetype":"venue"
},
  "geometry": {"coordinates":[-82.5803909302,38.4235534668],"type":"Point"}
}