{
  "type": "Feature",
  "properties": {
    "addr:full":"Lindevej 26 Hals Danmark 9370",
    "addr:housenumber":"26",
    "addr:postcode":"9370",
    "addr:street":"Lindevej",
    "iso:country":"DK",
    "sg:address":"Lindevej 26",
    "sg:city":"Hals",
    "sg:orig_category":"Skorstensfejere",
    "sg:phone":"+45 98 25 16 71",
    "sg:postcode":"9370",
    "sg:province":"Danmark",
    "wof:name":"Henriksen, Ole J.",
    "wof:placetype":"venue"
},
  "geometry": {"coordinates":[10.3151016235,56.9956359863],"type":"Point"}
}