{
  "type": "Feature",
  "properties": {
    "addr:full":"Nyk\u00e6rsvej 12 Skjern Danmark 6900",
    "addr:housenumber":"12",
    "addr:postcode":"6900",
    "addr:street":"Nykaersvej",
    "iso:country":"DK",
    "sg:address":"Nyk\u00e6rsvej 12",
    "sg:city":"Skjern",
    "sg:orig_category":"Vinduespolering",
    "sg:phone":"+45 97 35 40 40",
    "sg:postcode":"6900",
    "sg:province":"Danmark",
    "wof:name":"Jensens Reng\u00f8ring ApS",
    "wof:placetype":"venue"
},
  "geometry": {"coordinates":[8.5117406845,55.9504814148],"type":"Point"}
}