{
  "type": "Feature",
  "properties": {
    "addr:full":"Bj\u00f8rnevej 5  Thisted Danmark 7700",
    "addr:housenumber":"5",
    "addr:postcode":"7700",
    "addr:street":"Bjornevej",
    "iso:country":"DK",
    "sg:address":"Bj\u00f8rnevej 5 ",
    "sg:city":"Thisted",
    "sg:classifiers":[
        {
            "category":"Shopping",
            "subcategory":"Clothing, Apparel, & Fashions",
            "type":"Retail Goods"
        }
    ],
    "sg:phone":"+45 97 92 24 55",
    "sg:postcode":"7700",
    "sg:province":"Danmark",
    "sg:tags":[
        "clothes"
    ],
    "wof:name":"LANIEL A/S",
    "wof:placetype":"venue"
},
  "geometry": {"coordinates":[8.7336559296,56.9622955322],"type":"Point"}
}