{
  "type": "Feature",
  "properties": {
    "addr:full":"B\u00f8gekildevej 8 Hasselager Danmark 8361",
    "addr:housenumber":"8",
    "addr:postcode":"8361",
    "addr:street":"Bogekildevej",
    "iso:country":"DK",
    "sg:address":"B\u00f8gekildevej 8",
    "sg:city":"Hasselager",
    "sg:orig_category":"Maskinfabrikker",
    "sg:phone":"+45 86 28 04 00",
    "sg:postcode":"8361",
    "sg:province":"Danmark",
    "wof:name":"Christensen Maskinfabrik A/S, B.",
    "wof:placetype":"venue"
},
  "geometry": {"coordinates":[10.0925788879,56.1038131714],"type":"Point"}
}