{
  "type": "Feature",
  "properties": {
    "addr:full":"Skolesvinget 10 S\u00f8borg Danmark 2860",
    "addr:housenumber":"10",
    "addr:postcode":"2860",
    "addr:street":"Skolesvinget",
    "iso:country":"DK",
    "sg:address":"Skolesvinget 10",
    "sg:city":"S\u00f8borg",
    "sg:orig_category":"Kommunale folkeskoler",
    "sg:phone":"+45 39 69 57 11",
    "sg:postcode":"2860",
    "sg:province":"Danmark",
    "wof:name":"H\u00f8je Gladsaxe Skole",
    "wof:placetype":"venue"
},
  "geometry": {"coordinates":[-101.3829040527,35.6775283813],"type":"Point"}
}