{
  "type": "Feature",
  "properties": {
    "addr:full":"Aggerupvej 7, Aggerup H\u00e5rlev Danmark 4652",
    "addr:housenumber":"7",
    "addr:postcode":"4652",
    "addr:street":"Aggerupvej",
    "iso:country":"DK",
    "sg:address":"Aggerupvej 7, Aggerup",
    "sg:city":"H\u00e5rlev",
    "sg:orig_category":"Gulve",
    "sg:phone":"+45 56 28 55 22",
    "sg:postcode":"4652",
    "sg:province":"Danmark",
    "wof:name":"Aagaard, Frank",
    "wof:placetype":"venue"
},
  "geometry": {"coordinates":[12.2393083572,55.3467025757],"type":"Point"}
}