{
  "type": "Feature",
  "properties": {
    "iso:country":"DK",
    "sg:address":"Naverland 2 PO BOX 1326 ",
    "sg:city":"Glostrup",
    "sg:classifiers":[
        {
            "category":"Wholesale",
            "subcategory":"Drugs",
            "type":"Manufacturing & Wholesale Goods"
        }
    ],
    "sg:phone":"+45 43 46 02 46",
    "sg:postcode":"2600",
    "sg:province":"Danmark",
    "sg:tags":[
        "chemical",
        "pharmaceutical"
    ],
    "wof:name":"AKCROS CHEMICALS NORDIC A/S",
    "wof:placetype":"venue"
},
  "geometry": {"coordinates":[12.3957901001,55.6654663086],"type":"Point"}
}