{
  "type": "Feature",
  "properties": {
    "addr:full":"Resedavej 101 Silkeborg Danmark 8600",
    "addr:housenumber":"101",
    "addr:postcode":"8600",
    "addr:street":"Resedavej",
    "iso:country":"DK",
    "sg:address":"Resedavej 101",
    "sg:city":"Silkeborg",
    "sg:orig_category":"Vuggestuer",
    "sg:phone":"+45 86 82 52 24",
    "sg:postcode":"8600",
    "sg:province":"Danmark",
    "wof:name":"Sm\u00f8rblomsten, Vuggestuen",
    "wof:placetype":"venue"
},
  "geometry": {"coordinates":[9.5495662689,56.1855316162],"type":"Point"}
}