{
  "type": "Feature",
  "properties": {
    "addr:full":"Valby Langgade 70 Valby Danmark 2500",
    "addr:housenumber":"70",
    "addr:postcode":"2500",
    "addr:street":"Valby Langgade",
    "iso:country":"DK",
    "sg:address":"Valby Langgade 70",
    "sg:city":"Valby",
    "sg:orig_category":"Pelsvarer",
    "sg:phone":"+45 36 46 67 67",
    "sg:postcode":"2500",
    "sg:province":"Danmark",
    "wof:name":"Pels-Skind",
    "wof:placetype":"venue"
},
  "geometry": {"coordinates":[12.5135736465,55.6661643982],"type":"Point"}
}