{
  "type": "Feature",
  "properties": {
    "addr:full":"Industriparken 44  Ballerup Danmark 2750",
    "addr:housenumber":"44",
    "addr:postcode":"2750",
    "addr:street":"Industriparken",
    "iso:country":"DK",
    "sg:address":"Industriparken 44 ",
    "sg:city":"Ballerup",
    "sg:classifiers":[
        {
            "category":"Professional",
            "subcategory":"Computer Services",
            "type":"Services"
        }
    ],
    "sg:phone":"+45 44 57 09 10",
    "sg:postcode":"2750",
    "sg:province":"Danmark",
    "sg:tags":[
        "information",
        "technology"
    ],
    "wof:name":"EG DATA INFORM A/S",
    "wof:placetype":"venue"
},
  "geometry": {"coordinates":[12.3849916458,55.7273101807],"type":"Point"}
}