{
  "type": "Feature",
  "properties": {
    "addr:full":"Egevangshusene 119 Taastrup Danmark 2630",
    "addr:housenumber":"119",
    "addr:postcode":"2630",
    "addr:street":"Egevangshusene",
    "iso:country":"DK",
    "sg:address":"Egevangshusene 119",
    "sg:city":"Taastrup",
    "sg:orig_category":"Malermestre",
    "sg:phone":"+45 43 99 88 64",
    "sg:postcode":"2630",
    "sg:province":"Danmark",
    "wof:name":"Kl\u00fcsmann, Malerfirmaet Kim",
    "wof:placetype":"venue"
},
  "geometry": {"coordinates":[12.282828331,55.6453437805],"type":"Point"}
}