{
  "type": "Feature",
  "properties": {
    "addr:full":"Klerkegade 25 B K\u00f8benhavn Danmark 1308",
    "addr:housenumber":"25 b;1308",
    "addr:street":"Klerkegade",
    "iso:country":"DK",
    "sg:address":"Klerkegade 25 B",
    "sg:city":"K\u00f8benhavn",
    "sg:orig_category":"Arkitekter",
    "sg:phone":"+45 33 13 14 20",
    "sg:postcode":"1308",
    "sg:province":"Danmark",
    "wof:name":"Jacob Sebastian Bangs Tegnestue",
    "wof:placetype":"venue"
},
  "geometry": {"coordinates":[12.587100029,55.6856994629],"type":"Point"}
}