{
  "type": "Feature",
  "properties": {
    "addr:full":"Odensevej 33, 1. Middelfart Danmark 5500",
    "addr:housenumber":"33 1",
    "addr:postcode":"5500",
    "addr:street":"Odensevej",
    "iso:country":"DK",
    "sg:address":"Odensevej 33, 1.",
    "sg:city":"Middelfart",
    "sg:orig_category":"Revisorer",
    "sg:phone":"+45 64 41 54 44",
    "sg:postcode":"5500",
    "sg:province":"Danmark",
    "sg:website":"www.lod.dk",
    "wof:name":"Olsen, Leo & Dalgaard",
    "wof:placetype":"venue"
},
  "geometry": {"coordinates":[9.7444419861,55.5025749207],"type":"Point"}
}