{
  "type": "Feature",
  "properties": {
    "addr:full":"Fmd: Niels H. Rohde, S\u00f8nder Hostrup Bygade 32, Sdr. Hostrup Aabenraa Danmark 6200",
    "addr:housenumber":"32",
    "addr:postcode":"6200",
    "addr:street":"Niels H. Rohde Sonder Hostrup Bygade;Sdr. Hostrup",
    "iso:country":"DK",
    "sg:address":"Fmd: Niels H. Rohde, S\u00f8nder Hostrup Bygade 32, Sdr. Hostrup",
    "sg:city":"Aabenraa",
    "sg:orig_category":"Borger- og beboerforeninger",
    "sg:phone":"+45 74 61 39 73",
    "sg:postcode":"6200",
    "sg:province":"Danmark",
    "wof:name":"S\u00f8nder Hostrup og Omegns Borgerforening",
    "wof:placetype":"venue"
},
  "geometry": {"coordinates":[9.4213867188,55.0449562073],"type":"Point"}
}