{
  "type": "Feature",
  "properties": {
    "addr:full":"Lundholmvej 1 Holstebro Danmark 7500",
    "addr:housenumber":"1",
    "addr:postcode":"7500",
    "addr:street":"Lundholmvej",
    "iso:country":"DK",
    "sg:address":"Lundholmvej 1",
    "sg:city":"Holstebro",
    "sg:orig_category":"Autoforhandlere",
    "sg:phone":"+45 97 42 34 11",
    "sg:postcode":"7500",
    "sg:province":"Danmark",
    "wof:name":"STS-Biler A/S",
    "wof:placetype":"venue"
},
  "geometry": {"coordinates":[8.6181325912,56.378364563],"type":"Point"}
}