{
  "type": "Feature",
  "properties": {
    "iso:country":"DK",
    "sg:address":"Ulvevej 21",
    "sg:city":"Skive",
    "sg:orig_category":"Maskinfabrikker",
    "sg:phone":"+45 97 52 37 00",
    "sg:postcode":"7800",
    "sg:province":"Danmark",
    "sg:website":"www.sfkilde.dk",
    "wof:name":"Kilde A/S, S. F.",
    "wof:placetype":"venue"
},
  "geometry": {"coordinates":[9.0205621719,56.5397529602],"type":"Point"}
}