{
  "type": "Feature",
  "properties": {
    "addr:full":"v/ Ernst Duelund, Toften 21, Mogenstrup N\u00e6stved Danmark 4700",
    "addr:housenumber":"21",
    "addr:postcode":"4700",
    "addr:street":"Toften",
    "iso:country":"DK",
    "sg:address":"v/ Ernst Duelund, Toften 21, Mogenstrup",
    "sg:city":"N\u00e6stved",
    "sg:orig_category":"Loger",
    "sg:phone":"+45 55 76 16 44",
    "sg:postcode":"4700",
    "sg:province":"Danmark",
    "wof:name":"Lions Club, Pr\u00e6st\u00f8 og Flads\u00e5",
    "wof:placetype":"venue"
},
  "geometry": {"coordinates":[11.7542486191,55.2315444946],"type":"Point"}
}