{
  "type": "Feature",
  "properties": {
    "addr:full":"Gyldenbjergsvej 31 Svendborg Danmark 5700",
    "addr:housenumber":"31",
    "addr:postcode":"5700",
    "addr:street":"Gyldenbjergsvej",
    "iso:country":"DK",
    "sg:address":"Gyldenbjergsvej 31",
    "sg:city":"Svendborg",
    "sg:orig_category":"Skolefritidsordninger",
    "sg:phone":"+45 62 22 12 24",
    "sg:postcode":"5700",
    "sg:province":"Danmark",
    "wof:name":"Vestre skoles skolefritidsordning",
    "wof:placetype":"venue"
},
  "geometry": {"coordinates":[10.5848989487,55.0640907288],"type":"Point"}
}