{
  "type": "Feature",
  "properties": {
    "iso:country":"DK",
    "sg:address":"Boulevarden 12",
    "sg:city":"Vordingborg",
    "sg:orig_category":"Bodegaer",
    "sg:phone":"+45 55 34 44 08",
    "sg:postcode":"4760",
    "sg:province":"Danmark",
    "wof:name":"Boulevard Pubben",
    "wof:placetype":"venue"
},
  "geometry": {"coordinates":[11.9038248062,55.0132980347],"type":"Point"}
}