{
  "type": "Feature",
  "properties": {
    "addr:full":"Haraldsgade 10 Vejle Danmark 7100",
    "addr:housenumber":"10",
    "addr:postcode":"7100",
    "addr:street":"Haraldsgade",
    "iso:country":"DK",
    "sg:address":"Haraldsgade 10",
    "sg:city":"Vejle",
    "sg:orig_category":"Kirkesogne",
    "sg:phone":"+45 75 82 55 38",
    "sg:postcode":"7100",
    "sg:province":"Danmark",
    "wof:name":"Sct. Johannes Sogns Kirkekontor",
    "wof:placetype":"venue"
},
  "geometry": {"coordinates":[9.5241146088,55.7146072388],"type":"Point"}
}