{
  "type": "Feature",
  "properties": {
    "iso:country":"DK",
    "sg:address":"Taarb\u00e6k Strandvej 95",
    "sg:city":"Klampenborg",
    "sg:classifiers":[
        {
            "category":"Banks & Credit Unions",
            "subcategory":"Bank",
            "type":"Services"
        }
    ],
    "sg:phone":"+45 39 96 22 30",
    "sg:postcode":"2930",
    "sg:province":"Danmark",
    "sg:tags":[
        "banker"
    ],
    "sg:website":"www.danskebank.dk",
    "wof:name":"Danske Bank",
    "wof:placetype":"venue"
},
  "geometry": {"coordinates":[12.5942420959,55.7878646851],"type":"Point"}
}