{
  "type": "Feature",
  "properties": {
    "addr:full":"Strandbysvinget 1, 2. Esbjerg Danmark 6700",
    "addr:housenumber":"1 2",
    "addr:postcode":"6700",
    "addr:street":"Strandbysvinget",
    "iso:country":"DK",
    "sg:address":"Strandbysvinget 1, 2.",
    "sg:city":"Esbjerg",
    "sg:orig_category":"Malermestre",
    "sg:phone":"+45 75 13 97 68",
    "sg:postcode":"6700",
    "sg:province":"Danmark",
    "wof:name":"Berg, Rudolf",
    "wof:placetype":"venue"
},
  "geometry": {"coordinates":[8.4363298416,55.4749794006],"type":"Point"}
}