{
  "type": "Feature",
  "properties": {
    "addr:full":"Borgergade 11 Gjern Danmark 8883",
    "addr:housenumber":"11",
    "addr:postcode":"8883",
    "addr:street":"Borgergade",
    "iso:country":"DK",
    "sg:address":"Borgergade 11",
    "sg:city":"Gjern",
    "sg:orig_category":"Faglige organisationer og foreninger",
    "sg:phone":"+45 87 56 02 20",
    "sg:postcode":"8883",
    "sg:province":"Danmark",
    "wof:name":"SID",
    "wof:placetype":"venue"
},
  "geometry": {"coordinates":[9.7394037247,56.2305335999],"type":"Point"}
}