{
  "type": "Feature",
  "properties": {
    "iso:country":"DK",
    "sg:address":"Toldbodgade 3",
    "sg:city":"Randers",
    "sg:classifiers":[
        {
            "category":"Museum",
            "type":"Entertainment"
        }
    ],
    "sg:phone":"+45 89 11 73 00",
    "sg:postcode":"8900",
    "sg:province":"Danmark",
    "sg:tags":[
        "og",
        "skat",
        "told"
    ],
    "wof:name":"Told- og Skatteregion Randers.",
    "wof:placetype":"venue"
},
  "geometry": {"coordinates":[10.0455589294,56.4606513977],"type":"Point"}
}