{
  "type": "Feature",
  "properties": {
    "iso:country":"DK",
    "sg:address":"Jagtvej, Jagtvej 64",
    "sg:city":"K\u00f8benhavn N",
    "sg:classifiers":[
        {
            "category":"Banks & Credit Unions",
            "subcategory":"Bank",
            "type":"Services"
        }
    ],
    "sg:phone":"+45 35 24 58 20",
    "sg:postcode":"2200",
    "sg:province":"Danmark",
    "sg:tags":[
        "banker"
    ],
    "wof:name":"BG Bank",
    "wof:placetype":"venue"
},
  "geometry": {"coordinates":[-76.41683999999999,37.452419],"type":"Point"}
}