{
  "type": "Feature",
  "properties": {
    "addr:full":"Sct. Laurentii Vej 26 Skagen Danmark 9990",
    "addr:housenumber":"26",
    "addr:postcode":"9990",
    "addr:street":"Sct. Laurentii Vej",
    "iso:country":"DK",
    "sg:address":"Sct. Laurentii Vej 26",
    "sg:city":"Skagen",
    "sg:orig_category":"Bedriftssundhedstjenester",
    "sg:phone":"+45 70 10 61 10",
    "sg:postcode":"9990",
    "sg:province":"Danmark",
    "sg:website":"www.bedriftssundhedstjeneste.dk",
    "wof:name":"Nordjysk BST",
    "wof:placetype":"venue"
},
  "geometry": {"coordinates":[10.591207,57.723236],"type":"Point"}
}