{
  "type": "Feature",
  "properties": {
    "addr:full":"Oddevej 2 A Skagen Danmark 9990",
    "addr:housenumber":"2 a",
    "addr:postcode":"9990",
    "addr:street":"Oddevej",
    "iso:country":"DK",
    "sg:address":"Oddevej 2 A",
    "sg:city":"Skagen",
    "sg:orig_category":"Museer",
    "sg:phone":"+45 98 44 21 08",
    "sg:postcode":"9990",
    "sg:province":"Danmark",
    "wof:name":"Bamsehuset",
    "wof:placetype":"venue"
},
  "geometry": {"coordinates":[10.5978031158,57.7258110046],"type":"Point"}
}