{
  "type": "Feature",
  "properties": {
    "iso:country":"DK",
    "sg:address":"Notgangen 5 C",
    "sg:city":"Karlslunde",
    "sg:orig_category":"Industrilakering",
    "sg:phone":"+45 46 15 31 99",
    "sg:postcode":"2690",
    "sg:province":"Danmark",
    "sg:website":"www.cuwilak.dk",
    "wof:name":"Cuwilak A/S",
    "wof:placetype":"venue"
},
  "geometry": {"coordinates":[12.2383546829,55.5714035034],"type":"Point"}
}