{
  "type": "Feature",
  "properties": {
    "addr:full":"Vemmingbund Strandvej 66 Broager Danmark 6310",
    "addr:housenumber":"66",
    "addr:postcode":"6310",
    "addr:street":"Vemmingbund Strandvej",
    "iso:country":"DK",
    "sg:address":"Vemmingbund Strandvej 66",
    "sg:city":"Broager",
    "sg:orig_category":"Malermestre",
    "sg:phone":"+45 74 44 00 55",
    "sg:postcode":"6310",
    "sg:province":"Danmark",
    "wof:name":"Broagerlands Malerforretning",
    "wof:placetype":"venue"
},
  "geometry": {"coordinates":[9.6990146637,54.8948364258],"type":"Point"}
}