{
  "type": "Feature",
  "properties": {
    "addr:full":"Roskildevej 324 Taastrup Danmark 2630",
    "addr:housenumber":"324",
    "addr:postcode":"2630",
    "addr:street":"Roskildevej",
    "iso:country":"DK",
    "sg:address":"Roskildevej 324",
    "sg:city":"Taastrup",
    "sg:classifiers":[
        {
            "category":"Home & Garden",
            "subcategory":"Home Furnishings",
            "type":"Retail Goods"
        }
    ],
    "sg:phone":"+45 44 44 34 12",
    "sg:postcode":"2630",
    "sg:province":"Danmark",
    "sg:tags":[
        "el-installation"
    ],
    "wof:name":"Petersen A/S, Flemming",
    "wof:placetype":"venue"
},
  "geometry": {"coordinates":[12.3054656982,55.6585998535],"type":"Point"}
}