{
  "type": "Feature",
  "properties": {
    "addr:full":"Pr\u00e6stev\u00e6nget 3 E, Guderup Nordborg Danmark 6430",
    "addr:housenumber":"3 e",
    "addr:postcode":"6430",
    "addr:street":"Praestevaenget;Guderup",
    "iso:country":"DK",
    "sg:address":"Pr\u00e6stev\u00e6nget 3 E, Guderup",
    "sg:city":"Nordborg",
    "sg:orig_category":"Kulturelle foreninger",
    "sg:phone":"+45 74 45 93 01",
    "sg:postcode":"6430",
    "sg:province":"Danmark",
    "wof:name":"Egen Sogns Lokalhistoriske forening",
    "wof:placetype":"venue"
},
  "geometry": {"coordinates":[9.7496232986,55.0542755127],"type":"Point"}
}