{
  "type": "Feature",
  "properties": {
    "addr:full":"Trudsh\u00f8jvej 8 Vordingborg Danmark 4760",
    "addr:housenumber":"8",
    "addr:postcode":"4760",
    "addr:street":"Trudshojvej",
    "iso:country":"DK",
    "sg:address":"Trudsh\u00f8jvej 8",
    "sg:city":"Vordingborg",
    "sg:orig_category":"Antikviteter",
    "sg:phone":"+45 55 98 25 26",
    "sg:postcode":"4760",
    "sg:province":"Danmark",
    "sg:website":"www.antikboden.dk",
    "wof:name":"Blommeg\u00e5rden",
    "wof:placetype":"venue"
},
  "geometry": {"coordinates":[11.9514942169,55.0654373169],"type":"Point"}
}