{
  "type": "Feature",
  "properties": {
    "addr:full":"Kuldyssen 15-17 Taastrup Danmark 2630",
    "addr:postcode":"15-17;2630",
    "addr:street":"Kuldyssen",
    "iso:country":"DK",
    "sg:address":"Kuldyssen 15-17",
    "sg:city":"Taastrup",
    "sg:orig_category":"Fabrikker",
    "sg:phone":"+45 43 99 22 44",
    "sg:postcode":"2630",
    "sg:province":"Danmark",
    "sg:website":"www.trepko.dk",
    "wof:name":"Trepko A/S",
    "wof:placetype":"venue"
},
  "geometry": {"coordinates":[12.2875089645,55.6484642029],"type":"Point"}
}