{
  "type": "Feature",
  "properties": {
    "addr:full":"Fmd.: J\u00f8rgen Nielsen, Mosevej 1 Slangerup Danmark 3550",
    "addr:housenumber":"1",
    "addr:postcode":"3550",
    "addr:street":"Nielsen Mosevej",
    "iso:country":"DK",
    "sg:address":"Fmd.: J\u00f8rgen Nielsen, Mosevej 1",
    "sg:city":"Slangerup",
    "sg:orig_category":"Grundejerforeninger",
    "sg:phone":"+45 47 33 48 45",
    "sg:postcode":"3550",
    "sg:province":"Danmark",
    "wof:name":"Brob\u00e6k, Grundejerforeningen",
    "wof:placetype":"venue"
},
  "geometry": {"coordinates":[12.1717596054,55.8460769653],"type":"Point"}
}