{
  "type": "Feature",
  "properties": {
    "addr:full":"Golfvej 60, Postboks 273 Frederikshavn Danmark 9900",
    "addr:housenumber":"60;273",
    "addr:postcode":"9900",
    "addr:street":"Golfvej",
    "iso:country":"DK",
    "sg:address":"Golfvej 60, Postboks 273",
    "sg:city":"Frederikshavn",
    "sg:classifiers":[
        {
            "category":"Sports & Exercise",
            "subcategory":"Sports Center",
            "type":"Entertainment"
        }
    ],
    "sg:phone":"+45 98 43 55 88",
    "sg:postcode":"9900",
    "sg:province":"Danmark",
    "sg:tags":[
        "golf"
    ],
    "sg:website":"www.frederikshavngolfklub.dk",
    "wof:name":"Frederikshavn Golf Klub",
    "wof:placetype":"venue"
},
  "geometry": {"coordinates":[10.5362997055,57.4396400452],"type":"Point"}
}