{
  "type": "Feature",
  "properties": {
    "addr:full":"N\u00f8rregade 10, Laurbjerg Lang\u00e5 Danmark 8870",
    "addr:housenumber":"10",
    "addr:postcode":"8870",
    "addr:street":"Norregade",
    "iso:country":"DK",
    "sg:address":"N\u00f8rregade 10, Laurbjerg",
    "sg:city":"Lang\u00e5",
    "sg:orig_category":"Listefabrikker",
    "sg:phone":"+45 86 46 84 00",
    "sg:postcode":"8870",
    "sg:province":"Danmark",
    "wof:name":"Laurbjerg Listesnedkeri",
    "wof:placetype":"venue"
},
  "geometry": {"coordinates":[9.8955049515,56.3900756836],"type":"Point"}
}