{
  "type": "Feature",
  "properties": {
    "iso:country":"DK",
    "sg:address":"\u00c6blegyden 14, Indsl-T\u00e5rup",
    "sg:city":"Ejby",
    "sg:orig_category":"Kunsthandlere",
    "sg:phone":"+45 64 46 20 45",
    "sg:postcode":"5592",
    "sg:province":"Danmark",
    "wof:name":"Snejbjerg Kunsthandel",
    "wof:placetype":"venue"
},
  "geometry": {"coordinates":[9.9277296066,55.4288444519],"type":"Point"}
}