{
  "type": "Feature",
  "properties": {
    "addr:full":"Tigervej 16 Thisted Danmark 7700",
    "addr:housenumber":"16",
    "addr:postcode":"7700",
    "addr:street":"Tigervej",
    "iso:country":"DK",
    "sg:address":"Tigervej 16",
    "sg:city":"Thisted",
    "sg:orig_category":"Autoforhandlere",
    "sg:phone":"+45 96 17 24 35",
    "sg:postcode":"7700",
    "sg:province":"Danmark",
    "wof:name":"Viking Lastbil A/S",
    "wof:placetype":"venue"
},
  "geometry": {"coordinates":[8.7295780182,56.9606399536],"type":"Point"}
}