{
  "type": "Feature",
  "properties": {
    "iso:country":"DK",
    "sg:address":"Gravh\u00f8jvej 25, Spark\u00e6r",
    "sg:city":"Viborg",
    "sg:orig_category":"Reklame",
    "sg:phone":"+45 86 64 55 86",
    "sg:postcode":"8800",
    "sg:province":"Danmark",
    "wof:name":"Lindermann, Find",
    "wof:placetype":"venue"
},
  "geometry": {"coordinates":[9.4071502686,56.452671051],"type":"Point"}
}