{
  "type": "Feature",
  "properties": {
    "iso:country":"DK",
    "sg:address":"Fmd.: S\u00f8ren Thode, Hyrdebakken 114",
    "sg:city":"Viborg",
    "sg:orig_category":"Spejderkorps",
    "sg:phone":"+45 86 67 10 40",
    "sg:postcode":"8800",
    "sg:province":"Danmark",
    "sg:website":"www.waingunga-spejder.dk",
    "wof:name":"Danske Spejderkorps - Waingunga-Stammen, Det",
    "wof:placetype":"venue"
},
  "geometry": {"coordinates":[9.4071502686,56.452671051],"type":"Point"}
}