{
  "type": "Feature",
  "properties": {
    "addr:full":"Skolevej 20 Gentofte Danmark 2820",
    "addr:housenumber":"20",
    "addr:postcode":"2820",
    "addr:street":"Skolevej",
    "iso:country":"DK",
    "sg:address":"Skolevej 20",
    "sg:city":"Gentofte",
    "sg:orig_category":"Malermestre",
    "sg:phone":"+45 39 65 51 53",
    "sg:postcode":"2820",
    "sg:province":"Danmark",
    "wof:name":"Hansen, Johannes",
    "wof:placetype":"venue"
},
  "geometry": {"coordinates":[12.5477895737,55.7451324463],"type":"Point"}
}