{
  "type": "Feature",
  "properties": {
    "addr:full":"Torvegade 20, 2. Vejle Danmark 7100",
    "addr:housenumber":"20 2",
    "addr:postcode":"7100",
    "addr:street":"Torvegade",
    "iso:country":"DK",
    "sg:address":"Torvegade 20, 2.",
    "sg:city":"Vejle",
    "sg:orig_category":"Landskabsarkitekter",
    "sg:phone":"+45 75 82 87 11",
    "sg:postcode":"7100",
    "sg:province":"Danmark",
    "wof:name":"Landskabsarkitekterne H.P. Kofoed-Hansen & J\u00f8rgen Nielsen",
    "wof:placetype":"venue"
},
  "geometry": {"coordinates":[9.5331821442,55.7087516785],"type":"Point"}
}