{
  "type": "Feature",
  "properties": {
    "iso:country":"DK",
    "sg:address":"Dalbyvej 2",
    "sg:city":"Br\u00f8nsh\u00f8j",
    "sg:orig_category":"Integrerede institutioner",
    "sg:phone":"+45 38 79 40 10",
    "sg:postcode":"2700",
    "sg:province":"Danmark",
    "sg:website":"www.radisen.subnet.dk",
    "wof:name":"B\u00f8rnehuset Radisen",
    "wof:placetype":"venue"
},
  "geometry": {"coordinates":[-65.6866531372,-23.1981296539],"type":"Point"}
}