{
  "type": "Feature",
  "properties": {
    "iso:country":"DK",
    "sg:address":"Strandstr\u00e6de 15",
    "sg:city":"R\u00f8dvig Stevns",
    "sg:orig_category":"Antikviteter",
    "sg:phone":"+45 56 50 64 77",
    "sg:postcode":"4673",
    "sg:province":"Danmark",
    "wof:name":"Eghuset Antik",
    "wof:placetype":"venue"
},
  "geometry": {"coordinates":[12.3775653839,55.2558746338],"type":"Point"}
}