{
  "type": "Feature",
  "properties": {
    "addr:full":"T\u00e5rnholmsvej 7 Br\u00f8nsh\u00f8j Danmark 2700",
    "addr:housenumber":"7",
    "addr:postcode":"2700",
    "addr:street":"Taarnholmsvej",
    "iso:country":"DK",
    "sg:address":"T\u00e5rnholmsvej 7",
    "sg:city":"Br\u00f8nsh\u00f8j",
    "sg:orig_category":"Revisorer",
    "sg:phone":"+45 38 80 20 15",
    "sg:postcode":"2700",
    "sg:province":"Danmark",
    "sg:website":"www.re-vision.dk",
    "wof:name":"Lorenzen Revision",
    "wof:placetype":"venue"
},
  "geometry": {"coordinates":[-65.6866531372,-23.1981296539],"type":"Point"}
}