{
  "type": "Feature",
  "properties": {
    "addr:full":"\u00c5havevej 44 Grindsted Danmark 7200",
    "addr:housenumber":"44",
    "addr:postcode":"7200",
    "addr:street":"Aahavevej",
    "iso:country":"DK",
    "sg:address":"\u00c5havevej 44",
    "sg:city":"Grindsted",
    "sg:orig_category":"Kostvejledning",
    "sg:phone":"+45 75 31 01 23",
    "sg:postcode":"7200",
    "sg:province":"Danmark",
    "wof:name":"Fjordg\u00e5rd, Marianne",
    "wof:placetype":"venue"
},
  "geometry": {"coordinates":[8.8968849182,55.7599029541],"type":"Point"}
}