{
  "type": "Feature",
  "properties": {
    "addr:full":"Tr\u00f8strupvej 4, Torsted Tim Danmark 6980",
    "addr:housenumber":"4",
    "addr:postcode":"6980",
    "addr:street":"Trostrupvej",
    "iso:country":"DK",
    "sg:address":"Tr\u00f8strupvej 4, Torsted",
    "sg:city":"Tim",
    "sg:orig_category":"Murermestre",
    "sg:phone":"+45 97 33 32 81",
    "sg:postcode":"6980",
    "sg:province":"Danmark",
    "wof:name":"Kjeldgaard, Ejgil",
    "wof:placetype":"venue"
},
  "geometry": {"coordinates":[8.3066711426,56.1961898804],"type":"Point"}
}