{
  "type": "Feature",
  "properties": {
    "iso:country":"DK",
    "sg:address":"Gothersgade 2",
    "sg:city":"Fredericia",
    "sg:orig_category":"Garn",
    "sg:phone":"+45 75 92 00 51",
    "sg:postcode":"7000",
    "sg:province":"Danmark",
    "wof:name":"Standard",
    "wof:placetype":"venue"
},
  "geometry": {"coordinates":[9.7563476562,55.56690979],"type":"Point"}
}