{
  "type": "Feature",
  "properties": {
    "addr:full":"Nyelandsvej 63 Frederiksberg Danmark 2000",
    "addr:housenumber":"63",
    "addr:postcode":"2000",
    "addr:street":"Nyelandsvej",
    "iso:country":"DK",
    "sg:address":"Nyelandsvej 63",
    "sg:city":"Frederiksberg",
    "sg:classifiers":[
        {
            "category":"Personal",
            "subcategory":"Massage",
            "type":"Services"
        }
    ],
    "sg:phone":"+45 38 86 00 90",
    "sg:postcode":"2000",
    "sg:province":"Danmark",
    "wof:name":"Simmelhack, Elke",
    "wof:placetype":"venue"
},
  "geometry": {"coordinates":[12.5247850418,55.6841316223],"type":"Point"}
}