{
  "type": "Feature",
  "properties": {
    "addr:full":"Lerb\u00e6kvej 6, Skodsb\u00f8l Broager Danmark 6310",
    "addr:housenumber":"6",
    "addr:postcode":"6310",
    "addr:street":"Lerbaekvej;Skodsbol",
    "iso:country":"DK",
    "sg:address":"Lerb\u00e6kvej 6, Skodsb\u00f8l",
    "sg:city":"Broager",
    "sg:orig_category":"Murermestre",
    "sg:phone":"+45 74 44 10 44",
    "sg:postcode":"6310",
    "sg:province":"Danmark",
    "sg:website":"www.aj-byg.dk",
    "wof:name":"AJ - Byg",
    "wof:placetype":"venue"
},
  "geometry": {"coordinates":[9.6673240662,54.8893623352],"type":"Point"}
}