{
  "type": "Feature",
  "properties": {
    "addr:full":"Assensvej 217 Stenstrup Danmark 5771",
    "addr:housenumber":"217",
    "addr:postcode":"5771",
    "addr:street":"Assensvej",
    "iso:country":"DK",
    "sg:address":"Assensvej 217",
    "sg:city":"Stenstrup",
    "sg:orig_category":"Slagter og viktualie",
    "sg:phone":"+45 62 26 34 00",
    "sg:postcode":"5771",
    "sg:province":"Danmark",
    "wof:name":"Stenstrup Slagteren",
    "wof:placetype":"venue"
},
  "geometry": {"coordinates":[10.4990663528,55.1307640076],"type":"Point"}
}