{
  "type": "Feature",
  "properties": {
    "iso:country":"DK",
    "sg:address":"Vesterk\u00f8b 8",
    "sg:city":"Hedehusene",
    "sg:orig_category":"Begravelsesforretninger",
    "sg:phone":"+45 46 55 18 44",
    "sg:postcode":"2640",
    "sg:province":"Danmark",
    "wof:name":"Begravelsesforretningen danmark",
    "wof:placetype":"venue"
},
  "geometry": {"coordinates":[12.197053,55.649658],"type":"Point"}
}