{
  "type": "Feature",
  "properties": {
    "addr:full":"Gruppeleder: Hemming Andersen, Bym\u00f8llevej 1 Marstal Danmark 5960",
    "addr:housenumber":"1",
    "addr:postcode":"5960",
    "addr:street":"Bymollevej",
    "iso:country":"DK",
    "sg:address":"Gruppeleder: Hemming Andersen, Bym\u00f8llevej 1",
    "sg:city":"Marstal",
    "sg:orig_category":"Spejderkorps",
    "sg:phone":"+45 62 53 21 28",
    "sg:postcode":"5960",
    "sg:province":"Danmark",
    "wof:name":"KFUM-spejderne, Marstal",
    "wof:placetype":"venue"
},
  "geometry": {"coordinates":[10.5212097168,54.8543815613],"type":"Point"}
}