{
  "type": "Feature",
  "properties": {
    "addr:full":"Sejerbyvej 39, Sejerby Sejer\u00f8 Danmark 4592",
    "addr:housenumber":"39",
    "addr:postcode":"4592",
    "addr:street":"Sejerbyvej",
    "iso:country":"DK",
    "sg:address":"Sejerbyvej 39, Sejerby",
    "sg:city":"Sejer\u00f8",
    "sg:orig_category":"Apoteker og -udsalg",
    "sg:phone":"+45 59 59 00 24",
    "sg:postcode":"4592",
    "sg:province":"Danmark",
    "wof:name":"H\u00e5ndk\u00f8bsudsalget p\u00e5 Sejer\u00f8",
    "wof:placetype":"venue"
},
  "geometry": {"coordinates":[11.137257576,55.8811302185],"type":"Point"}
}