{
  "type": "Feature",
  "properties": {
    "addr:full":"Borrekrattet 20 Kongens Lyngby Danmark 2800",
    "addr:housenumber":"20",
    "addr:postcode":"2800",
    "addr:street":"Borrekrattet",
    "iso:country":"DK",
    "sg:address":"Borrekrattet 20",
    "sg:city":"Kongens Lyngby",
    "sg:orig_category":"Psykologer, praktiserende",
    "sg:phone":"+45 45 93 41 08",
    "sg:postcode":"2800",
    "sg:province":"Danmark",
    "wof:name":"Troen, Elisa",
    "wof:placetype":"venue"
},
  "geometry": {"coordinates":[12.5036535263,55.7923545837],"type":"Point"}
}