{
  "type": "Feature",
  "properties": {
    "iso:country":"DK",
    "sg:address":"Tarp Byvej 147",
    "sg:city":"Esbjerg N",
    "sg:orig_category":"Isolering",
    "sg:phone":"+45 70 20 06 13",
    "sg:postcode":"6715",
    "sg:province":"Danmark",
    "wof:name":"Persolit",
    "wof:placetype":"venue"
},
  "geometry": {"coordinates":[8.4837732315,55.5188369751],"type":"Point"}
}