{
  "type": "Feature",
  "properties": {
    "addr:full":"Hvidovrevej 434 Hvidovre Danmark 2650",
    "addr:housenumber":"434",
    "addr:postcode":"2650",
    "addr:street":"Hvidovrevej",
    "iso:country":"DK",
    "sg:address":"Hvidovrevej 434",
    "sg:city":"Hvidovre",
    "sg:orig_category":"Apoteker og -udsalg",
    "sg:phone":"+45 36 78 44 33",
    "sg:postcode":"2650",
    "sg:province":"Danmark",
    "wof:name":"Apoteket Friheden",
    "wof:placetype":"venue"
},
  "geometry": {"coordinates":[12.4816169739,55.6282806396],"type":"Point"}
}