{
  "type": "Feature",
  "properties": {
    "addr:full":"R\u00e5dhuset, R\u00e5dhusvej 1 S\u00e6by Danmark 9300",
    "addr:housenumber":"1",
    "addr:postcode":"9300",
    "addr:street":"Raadhusvej",
    "iso:country":"DK",
    "sg:address":"R\u00e5dhuset, R\u00e5dhusvej 1",
    "sg:city":"S\u00e6by",
    "sg:orig_category":"Kommunen",
    "sg:phone":"+45 98 46 11 11",
    "sg:postcode":"9300",
    "sg:province":"Danmark",
    "sg:website":"www.saeby.dk",
    "wof:name":"S\u00e6by Kommune",
    "wof:placetype":"venue"
},
  "geometry": {"coordinates":[-78.0637512207,43.0498466492],"type":"Point"}
}