{
  "type": "Feature",
  "properties": {
    "addr:full":"Hvedebakken 4, Lendemarke Stege Danmark 4780",
    "addr:housenumber":"4",
    "addr:postcode":"4780",
    "addr:street":"Hvedebakken;Lendemarke",
    "iso:country":"DK",
    "sg:address":"Hvedebakken 4, Lendemarke",
    "sg:city":"Stege",
    "sg:orig_category":"Kiosker",
    "sg:postcode":"4780",
    "sg:province":"Danmark",
    "wof:name":"Is- og P\u00f8lsehytten Klintholm Havn",
    "wof:placetype":"venue"
},
  "geometry": {"coordinates":[12.2875270844,54.9855155945],"type":"Point"}
}