{
  "type": "Feature",
  "properties": {
    "addr:full":"Vigerslevvej 231 Valby Danmark 2500",
    "addr:housenumber":"231",
    "addr:postcode":"2500",
    "addr:street":"Vigerslevvej",
    "iso:country":"DK",
    "sg:address":"Vigerslevvej 231",
    "sg:city":"Valby",
    "sg:orig_category":"Grillbarer",
    "sg:phone":"+45 36 16 84 74",
    "sg:postcode":"2500",
    "sg:province":"Danmark",
    "wof:name":"Viggo's P\u00f8lsebar",
    "wof:placetype":"venue"
},
  "geometry": {"coordinates":[12.487903595,55.6535606384],"type":"Point"}
}