{
  "type": "Feature",
  "properties": {
    "addr:full":"Islandsvej 28 Horsens Danmark 8700",
    "addr:housenumber":"28",
    "addr:postcode":"8700",
    "addr:street":"Islandsvej",
    "iso:country":"DK",
    "sg:address":"Islandsvej 28",
    "sg:city":"Horsens",
    "sg:orig_category":"Elektronik",
    "sg:phone":"+45 76 28 29 30",
    "sg:postcode":"8700",
    "sg:province":"Danmark",
    "sg:website":"www.dantrafo.dk",
    "wof:name":"Dantrafo Horsens A/S",
    "wof:placetype":"venue"
},
  "geometry": {"coordinates":[9.8082199097,55.8608665466],"type":"Point"}
}