{
  "type": "Feature",
  "properties": {
    "addr:full":"Nitivej 8 Frederiksberg Danmark 2000",
    "addr:housenumber":"8",
    "addr:postcode":"2000",
    "addr:street":"Nitivej",
    "iso:country":"DK",
    "sg:address":"Nitivej 8",
    "sg:city":"Frederiksberg",
    "sg:orig_category":"Trossamfund uden for folkekirken",
    "sg:postcode":"2000",
    "sg:province":"Danmark",
    "wof:name":"Jesu Kristi Kirke af Sidste Dages Hellige",
    "wof:placetype":"venue"
},
  "geometry": {"coordinates":[12.5337114334,55.6916732788],"type":"Point"}
}