{
  "type": "Feature",
  "properties": {
    "addr:full":"Halvej 3 Alling\u00e5bro Danmark 8961",
    "addr:housenumber":"3",
    "addr:postcode":"8961",
    "addr:street":"Halvej",
    "iso:country":"DK",
    "sg:address":"Halvej 3",
    "sg:city":"Alling\u00e5bro",
    "sg:orig_category":"Dagcentre",
    "sg:phone":"+45 86 48 10 10",
    "sg:postcode":"8961",
    "sg:province":"Danmark",
    "wof:name":"Dagcenter",
    "wof:placetype":"venue"
},
  "geometry": {"coordinates":[-73.931640625,40.8079681396],"type":"Point"}
}