{
  "type": "Feature",
  "properties": {
    "addr:full":"Stadionsvej 21, Onsbjerg Sams\u00f8 Danmark 8305",
    "addr:housenumber":"21",
    "addr:postcode":"8305",
    "addr:street":"Stadionsvej",
    "iso:country":"DK",
    "sg:address":"Stadionsvej 21, Onsbjerg",
    "sg:city":"Sams\u00f8",
    "sg:orig_category":"Plejehjem",
    "sg:phone":"+45 86 59 05 46",
    "sg:postcode":"8305",
    "sg:province":"Danmark",
    "wof:name":"Solhjemmet",
    "wof:placetype":"venue"
},
  "geometry": {"coordinates":[10.5885000229,55.8320198059],"type":"Point"}
}