{
  "type": "Feature",
  "properties": {
    "addr:full":"Fmd.: Poul Lund Pedersen, Kystvej 230, Dokkedal Storvorde Danmark 9280",
    "addr:housenumber":"230",
    "addr:postcode":"9280",
    "addr:street":"Poul Lund;Kystvej",
    "iso:country":"DK",
    "sg:address":"Fmd.: Poul Lund Pedersen, Kystvej 230, Dokkedal",
    "sg:city":"Storvorde",
    "sg:orig_category":"Borger- og beboerforeninger",
    "sg:phone":"+45 98 31 08 04",
    "sg:postcode":"9280",
    "sg:province":"Danmark",
    "wof:name":"Dokkedal Borgerforening",
    "wof:placetype":"venue"
},
  "geometry": {"coordinates":[10.1014204025,57.0045547485],"type":"Point"}
}