{
  "type": "Feature",
  "properties": {
    "addr:full":"Robenheje 11 K\u00f8ge Danmark 4600",
    "addr:housenumber":"11",
    "addr:postcode":"4600",
    "addr:street":"Robenheje",
    "iso:country":"DK",
    "sg:address":"Robenheje 11",
    "sg:city":"K\u00f8ge",
    "sg:orig_category":"Malermestre",
    "sg:phone":"+45 56 65 89 98",
    "sg:postcode":"4600",
    "sg:province":"Danmark",
    "wof:name":"Carlsen, Palle Ring",
    "wof:placetype":"venue"
},
  "geometry": {"coordinates":[12.1801347733,55.4496994019],"type":"Point"}
}