{
  "type": "Feature",
  "properties": {
    "addr:full":"Sognepr\u00e6st: Elin Hjuler-S\u00f8rensen (K/B), Farup Kirkevej 6, K\u00e6rb\u00f8l Ribe Danmark 6760",
    "addr:housenumber":"6",
    "addr:postcode":"6760",
    "addr:street":"Farup Kirkevej",
    "iso:country":"DK",
    "sg:address":"Sognepr\u00e6st: Elin Hjuler-S\u00f8rensen (K/B), Farup Kirkevej 6, K\u00e6rb\u00f8l",
    "sg:city":"Ribe",
    "sg:orig_category":"Kirkesogne",
    "sg:phone":"+45 75 42 16 12",
    "sg:postcode":"6760",
    "sg:province":"Danmark",
    "wof:name":"Farup Sogn",
    "wof:placetype":"venue"
},
  "geometry": {"coordinates":[8.7656240463,55.3297042847],"type":"Point"}
}