{
  "type": "Feature",
  "properties": {
    "addr:full":"\u00d8ksendrupvej 23, \u00d8ksendrup Fr\u00f8rup Danmark 5871",
    "addr:housenumber":"23",
    "addr:postcode":"5871",
    "addr:street":"Oksendrupvej",
    "iso:country":"DK",
    "sg:address":"\u00d8ksendrupvej 23, \u00d8ksendrup",
    "sg:city":"Fr\u00f8rup",
    "sg:orig_category":"Forsamlingshuse",
    "sg:phone":"+45 65 37 15 77",
    "sg:postcode":"5871",
    "sg:province":"Danmark",
    "wof:name":"\u00d8ksendrup Forsamlingshus",
    "wof:placetype":"venue"
},
  "geometry": {"coordinates":[-93.1630935669,32.8507347107],"type":"Point"}
}