{
  "type": "Feature",
  "properties": {
    "addr:full":"Monrads Vej 11 Maribo Danmark 4930",
    "addr:housenumber":"11",
    "addr:postcode":"4930",
    "addr:street":"Monrads Vej",
    "iso:country":"DK",
    "sg:address":"Monrads Vej 11",
    "sg:city":"Maribo",
    "sg:orig_category":"Faglige organisationer og foreninger",
    "sg:phone":"+45 54 78 12 99",
    "sg:postcode":"4930",
    "sg:province":"Danmark",
    "wof:name":"Danmarks Skolelederforening Storstr\u00f8ms Amt",
    "wof:placetype":"venue"
},
  "geometry": {"coordinates":[11.5163440704,54.7733078003],"type":"Point"}
}