{
  "type": "Feature",
  "properties": {
    "iso:country":"DK",
    "sg:address":"Fmd.: Tejl H. Rasmussen, \u00d8stparken 45 B, Ejsing",
    "sg:city":"Vinderup",
    "sg:orig_category":"Hobbybetonede foreninger",
    "sg:phone":"+45 97 44 63 83",
    "sg:postcode":"7830",
    "sg:province":"Danmark",
    "wof:name":"Vinderup Lystfiskerforening",
    "wof:placetype":"venue"
},
  "geometry": {"coordinates":[8.7796897888,56.482635498],"type":"Point"}
}