{
  "type": "Feature",
  "properties": {
    "addr:full":"Storegade 3 Grenaa Danmark 8500",
    "addr:housenumber":"3",
    "addr:postcode":"8500",
    "addr:street":"Storegade",
    "iso:country":"DK",
    "sg:address":"Storegade 3",
    "sg:city":"Grenaa",
    "sg:orig_category":"Optikere",
    "sg:phone":"+45 86 32 63 22",
    "sg:postcode":"8500",
    "sg:province":"Danmark",
    "wof:name":"Grenaa Special Optik & Kontaktlinseklinik",
    "wof:placetype":"venue"
},
  "geometry": {"coordinates":[10.8749742508,56.4133872986],"type":"Point"}
}