{
  "type": "Feature",
  "properties": {
    "addr:full":"Fmd.: Arne Gr\u00f8n, Ouevej 37, Oue Hobro Danmark 9500",
    "addr:housenumber":"37",
    "addr:postcode":"9500",
    "addr:street":"Arne;Ouevej",
    "iso:country":"DK",
    "sg:address":"Fmd.: Arne Gr\u00f8n, Ouevej 37, Oue",
    "sg:city":"Hobro",
    "sg:orig_category":"Faglige organisationer og foreninger",
    "sg:phone":"+45 98 55 82 64",
    "sg:postcode":"9500",
    "sg:province":"Danmark",
    "wof:name":"Oue/Rostrup Husmandsforening",
    "wof:placetype":"venue"
},
  "geometry": {"coordinates":[9.7946596146,56.6382789612],"type":"Point"}
}