{
  "type": "Feature",
  "properties": {
    "addr:full":"Hospitalsgade 21 Horsens Danmark 8700",
    "addr:housenumber":"21",
    "addr:postcode":"8700",
    "addr:street":"Hospitalsgade",
    "iso:country":"DK",
    "sg:address":"Hospitalsgade 21",
    "sg:city":"Horsens",
    "sg:orig_category":"Tobak",
    "sg:phone":"+45 75 62 17 71",
    "sg:postcode":"8700",
    "sg:province":"Danmark",
    "wof:name":"Madsen, Iver",
    "wof:placetype":"venue"
},
  "geometry": {"coordinates":[9.845536232,55.8607597351],"type":"Point"}
}