{
  "type": "Feature",
  "properties": {
    "iso:country":"DK",
    "sg:address":"Vestergade 11",
    "sg:city":"Vamdrup",
    "sg:classifiers":[
        {
            "category":"Restaurant",
            "type":"Food & Drink"
        }
    ],
    "sg:phone":"+45 75 58 19 62",
    "sg:postcode":"6580",
    "sg:province":"Danmark",
    "wof:name":"Pusterummet",
    "wof:placetype":"venue"
},
  "geometry": {"coordinates":[9.2811927795,55.4262733459],"type":"Point"}
}