{
  "type": "Feature",
  "properties": {
    "addr:full":"Knudevejen 22  Vejen Danmark 6600",
    "addr:housenumber":"22",
    "addr:postcode":"6600",
    "addr:street":"Knudevejen",
    "iso:country":"DK",
    "sg:address":"Knudevejen 22 ",
    "sg:city":"Vejen",
    "sg:classifiers":[
        {
            "category":"Autos & Motor Vehicles",
            "subcategory":"Boat Sales",
            "type":"Retail Goods"
        }
    ],
    "sg:phone":"+45 75 36 50 11",
    "sg:postcode":"6600",
    "sg:province":"Danmark",
    "wof:name":"KC B\u00c6DE APS",
    "wof:placetype":"venue"
},
  "geometry": {"coordinates":[9.1448888779,55.4675865173],"type":"Point"}
}