{
  "type": "Feature",
  "properties": {
    "iso:country":"DK",
    "sg:address":"Mads Clausens Vej 1",
    "sg:city":"Silkeborg",
    "sg:orig_category":"Kemisk industri",
    "sg:phone":"+45 86 80 05 33",
    "sg:postcode":"8600",
    "sg:province":"Danmark",
    "sg:website":"www.kemex.dk",
    "wof:name":"Kemex A/S",
    "wof:placetype":"venue"
},
  "geometry": {"coordinates":[9.5866098404,56.2006340027],"type":"Point"}
}