{
  "type": "Feature",
  "properties": {
    "addr:full":"S\u00f8ndergade 19 Outrup Danmark 6855",
    "addr:housenumber":"19",
    "addr:postcode":"6855",
    "addr:street":"Sondergade",
    "iso:country":"DK",
    "sg:address":"S\u00f8ndergade 19",
    "sg:city":"Outrup",
    "sg:orig_category":"Piber",
    "sg:phone":"+45 75 25 12 20",
    "sg:postcode":"6855",
    "sg:province":"Danmark",
    "wof:name":"H\u00e5ndsk\u00e5rne Piber",
    "wof:placetype":"venue"
},
  "geometry": {"coordinates":[8.3478345871,55.7164840698],"type":"Point"}
}