{
  "type": "Feature",
  "properties": {
    "addr:full":"Silstrupvej 34 Thisted Danmark 7700",
    "addr:housenumber":"34",
    "addr:postcode":"7700",
    "addr:street":"Silstrupvej",
    "iso:country":"DK",
    "sg:address":"Silstrupvej 34",
    "sg:city":"Thisted",
    "sg:orig_category":"INGENI\u00c3\u02dcRER",
    "sg:phone":"+45 96 19 31 33",
    "sg:postcode":"7700",
    "sg:province":"Danmark",
    "wof:name":"Daninco",
    "wof:placetype":"venue"
},
  "geometry": {"coordinates":[8.6458749771,56.9494438171],"type":"Point"}
}