{
  "type": "Feature",
  "properties": {
    "addr:full":"S\u00f8ndertoften 58 Hobro Danmark 9500",
    "addr:housenumber":"58",
    "addr:postcode":"9500",
    "addr:street":"Sondertoften",
    "iso:country":"DK",
    "sg:address":"S\u00f8ndertoften 58",
    "sg:city":"Hobro",
    "sg:orig_category":"Malermestre",
    "sg:phone":"+45 98 52 45 26",
    "sg:postcode":"9500",
    "sg:province":"Danmark",
    "wof:name":"Telsing, Kurt E.",
    "wof:placetype":"venue"
},
  "geometry": {"coordinates":[9.7992401123,56.6295013428],"type":"Point"}
}