{
  "type": "Feature",
  "properties": {
    "addr:full":"Salbyvej 210 K\u00f8ge Danmark 4600",
    "addr:housenumber":"210",
    "addr:postcode":"4600",
    "addr:street":"Salbyvej",
    "iso:country":"DK",
    "sg:address":"Salbyvej 210",
    "sg:city":"K\u00f8ge",
    "sg:orig_category":"Hunde",
    "sg:phone":"+45 56 82 09 67",
    "sg:postcode":"4600",
    "sg:province":"Danmark",
    "wof:name":"Nibika, Kennel",
    "wof:placetype":"venue"
},
  "geometry": {"coordinates":[12.1585416794,55.469417572],"type":"Point"}
}