{
  "type": "Feature",
  "properties": {
    "addr:full":"Hedelundsvej 19 Sindal Danmark 9870",
    "addr:housenumber":"19",
    "addr:postcode":"9870",
    "addr:street":"Hedelundsvej",
    "iso:country":"DK",
    "sg:address":"Hedelundsvej 19",
    "sg:city":"Sindal",
    "sg:classifiers":[
        {
            "category":"Utilities",
            "subcategory":"Natural Gas",
            "type":"Services"
        }
    ],
    "sg:phone":"+45 98 93 62 66",
    "sg:postcode":"9870",
    "sg:province":"Danmark",
    "wof:name":"Sindal VVS",
    "wof:placetype":"venue"
},
  "geometry": {"coordinates":[10.1990776062,57.4926452637],"type":"Point"}
}