{
  "type": "Feature",
  "properties": {
    "addr:full":"Dalsvinget 16 Slagelse Danmark 4200",
    "addr:housenumber":"16",
    "addr:postcode":"4200",
    "addr:street":"Dalsvinget",
    "iso:country":"DK",
    "sg:address":"Dalsvinget 16",
    "sg:city":"Slagelse",
    "sg:orig_category":"Industri",
    "sg:phone":"+45 58 52 75 22",
    "sg:postcode":"4200",
    "sg:province":"Danmark",
    "wof:name":"Slagelse Industricenter",
    "wof:placetype":"venue"
},
  "geometry": {"coordinates":[11.3444919586,55.41563797],"type":"Point"}
}