{
  "type": "Feature",
  "properties": {
    "addr:full":"\u00d8stergade 32-34 K\u00f8benhavn Danmark 1100",
    "addr:housenumber":"32-34;1100",
    "addr:street":"Ostergade",
    "iso:country":"DK",
    "sg:address":"\u00d8stergade 32-34",
    "sg:city":"K\u00f8benhavn",
    "sg:orig_category":"Konditorier",
    "sg:phone":"+45 33 13 78 16",
    "sg:postcode":"1100",
    "sg:province":"Danmark",
    "wof:name":"Arkade Konditoriet",
    "wof:placetype":"venue"
},
  "geometry": {"coordinates":[76.3070983887,14.277130127],"type":"Point"}
}