{
  "type": "Feature",
  "properties": {
    "addr:full":"Fmd.: Knud J\u00f8rgensen, Strandlystg\u00e5rdsvej 19, Yderby Lyng Sj\u00e6llands Odde Danmark 4583",
    "addr:housenumber":"19",
    "addr:postcode":"4583",
    "addr:street":"Knud Jorgensen Strandlystgaardsvej;Yderby Lyng Sjaellands Odde Danmark",
    "iso:country":"DK",
    "sg:address":"Fmd.: Knud J\u00f8rgensen, Strandlystg\u00e5rdsvej 19, Yderby Lyng",
    "sg:city":"Sj\u00e6llands Odde",
    "sg:orig_category":"Grundejerforeninger",
    "sg:phone":"+45 59 32 71 60",
    "sg:postcode":"4583",
    "sg:province":"Danmark",
    "wof:name":"Strandlystg\u00e5rd Grundejerforening",
    "wof:placetype":"venue"
},
  "geometry": {"coordinates":[11.3198680878,55.9799728394],"type":"Point"}
}