{
  "type": "Feature",
  "properties": {
    "iso:country":"DK",
    "sg:address":"Gl. Revlvej 2 A, Hauge",
    "sg:city":"Kjellerup",
    "sg:orig_category":"Maskinstationer",
    "sg:phone":"+45 86 88 84 88",
    "sg:postcode":"8620",
    "sg:province":"Danmark",
    "wof:name":"Hauge Maskinstation",
    "wof:placetype":"venue"
},
  "geometry": {"coordinates":[9.430934906,56.2877655029],"type":"Point"}
}