{
  "type": "Feature",
  "properties": {
    "addr:full":"Fmd.: Finn Jensen, S\u00f8lvagervej 8 A, Under\u00f8d Nyk\u00f8bing Danmark 4500",
    "addr:housenumber":"8 a",
    "addr:postcode":"4500",
    "addr:street":"Solvagervej",
    "iso:country":"DK",
    "sg:address":"Fmd.: Finn Jensen, S\u00f8lvagervej 8 A, Under\u00f8d",
    "sg:city":"Nyk\u00f8bing",
    "sg:orig_category":"Hobbybetonede foreninger",
    "sg:phone":"+45 59 32 88 15",
    "sg:postcode":"4500",
    "sg:province":"Danmark",
    "wof:name":"Dansk drageklub",
    "wof:placetype":"venue"
},
  "geometry": {"coordinates":[16.0969600677,78.3159866333],"type":"Point"}
}