{
  "type": "Feature",
  "properties": {
    "addr:full":"Odensevej 169 Middelfart Danmark 5500",
    "addr:housenumber":"169",
    "addr:postcode":"5500",
    "addr:street":"Odensevej",
    "iso:country":"DK",
    "sg:address":"Odensevej 169",
    "sg:city":"Middelfart",
    "sg:orig_category":"Faglige organisationer og foreninger",
    "sg:phone":"+45 64 41 09 05",
    "sg:postcode":"5500",
    "sg:province":"Danmark",
    "wof:name":"Dansk Metalarbejderforbund",
    "wof:placetype":"venue"
},
  "geometry": {"coordinates":[9.7595615387,55.4991874695],"type":"Point"}
}