{
  "type": "Feature",
  "properties": {
    "addr:full":"L\u00f8vtoften 23 Taastrup Danmark 2630",
    "addr:housenumber":"23",
    "addr:postcode":"2630",
    "addr:street":"Lovtoften",
    "iso:country":"DK",
    "sg:address":"L\u00f8vtoften 23",
    "sg:city":"Taastrup",
    "sg:orig_category":"Revisorer",
    "sg:phone":"+45 43 99 56 17",
    "sg:postcode":"2630",
    "sg:province":"Danmark",
    "wof:name":"J\u00fcrgensen, Gunnar",
    "wof:placetype":"venue"
},
  "geometry": {"coordinates":[12.3099966049,55.6612205505],"type":"Point"}
}