{
  "type": "Feature",
  "properties": {
    "addr:full":"Ravnholtvej 57, Ravnholt \u00d8rb\u00e6k Danmark 5853",
    "addr:housenumber":"57",
    "addr:postcode":"5853",
    "addr:street":"Ravnholtvej;Ravnholt Orbaek Danmark",
    "iso:country":"DK",
    "sg:address":"Ravnholtvej 57, Ravnholt",
    "sg:city":"\u00d8rb\u00e6k",
    "sg:orig_category":"Skovbrug",
    "sg:phone":"+45 62 67 10 02",
    "sg:postcode":"5853",
    "sg:province":"Danmark",
    "wof:name":"Ravnholt Skovbrug Godskontoret",
    "wof:placetype":"venue"
},
  "geometry": {"coordinates":[10.6713848114,55.2553749084],"type":"Point"}
}