{
  "type": "Feature",
  "properties": {
    "addr:full":"Vindingevej 6 Roskilde Danmark 4000",
    "addr:housenumber":"6",
    "addr:postcode":"4000",
    "addr:street":"Vindingevej",
    "iso:country":"DK",
    "sg:address":"Vindingevej 6",
    "sg:city":"Roskilde",
    "sg:orig_category":"Marskandisere",
    "sg:phone":"+45 46 32 06 05",
    "sg:postcode":"4000",
    "sg:province":"Danmark",
    "wof:name":"Marskandiserbutikken",
    "wof:placetype":"venue"
},
  "geometry": {"coordinates":[12.0953407288,55.639629364],"type":"Point"}
}