{
  "type": "Feature",
  "properties": {
    "addr:full":"A. E. Hansens Vej 15 Nakskov Danmark 4900",
    "addr:housenumber":"15",
    "addr:postcode":"4900",
    "addr:street":"A. E. Hansens Vej",
    "iso:country":"DK",
    "sg:address":"A. E. Hansens Vej 15",
    "sg:city":"Nakskov",
    "sg:orig_category":"Autoreparation og -service",
    "sg:phone":"+45 54 95 31 40",
    "sg:postcode":"4900",
    "sg:province":"Danmark",
    "wof:name":"Auto-Centret",
    "wof:placetype":"venue"
},
  "geometry": {"coordinates":[11.1310796738,54.834186554],"type":"Point"}
}