{
  "type": "Feature",
  "properties": {
    "addr:full":"Tingerupvej 52, Tingerup Kirke Hvals\u00f8 Danmark 4330",
    "addr:housenumber":"52",
    "addr:postcode":"4330",
    "addr:street":"Tingerupvej;Tingerup",
    "iso:country":"DK",
    "sg:address":"Tingerupvej 52, Tingerup",
    "sg:city":"Kirke Hvals\u00f8",
    "sg:orig_category":"Dyreklinikker og -hospitaler",
    "sg:phone":"+45 70 20 11 44",
    "sg:postcode":"4330",
    "sg:province":"Danmark",
    "wof:name":"BIO Dyreklinik",
    "wof:placetype":"venue"
},
  "geometry": {"coordinates":[11.8626852036,55.5937385559],"type":"Point"}
}