{
  "type": "Feature",
  "properties": {
    "addr:full":"K\u00f8gevej 123 Taastrup Danmark 2630",
    "addr:housenumber":"123",
    "addr:postcode":"2630",
    "addr:street":"Kogevej",
    "iso:country":"DK",
    "sg:address":"K\u00f8gevej 123",
    "sg:city":"Taastrup",
    "sg:orig_category":"Slagter og viktualie",
    "sg:phone":"+45 43 99 11 96",
    "sg:postcode":"2630",
    "sg:province":"Danmark",
    "wof:name":"Kruse, Slagter",
    "wof:placetype":"venue"
},
  "geometry": {"coordinates":[12.3020896912,55.6506767273],"type":"Point"}
}