{
  "type": "Feature",
  "properties": {
    "addr:full":"Ny M\u00e5rumvej 174 Gr\u00e6sted Danmark 3230",
    "addr:housenumber":"174",
    "addr:postcode":"3230",
    "addr:street":"Maarumvej",
    "iso:country":"DK",
    "sg:address":"Ny M\u00e5rumvej 174",
    "sg:city":"Gr\u00e6sted",
    "sg:orig_category":"Benzinstationer",
    "sg:phone":"+45 48 79 41 01",
    "sg:postcode":"3230",
    "sg:province":"Danmark",
    "wof:name":"DK K\u00f8bmanden",
    "wof:placetype":"venue"
},
  "geometry": {"coordinates":[-76.50189208979999,42.8563194275],"type":"Point"}
}