{
  "type": "Feature",
  "properties": {
    "iso:country":"DK",
    "sg:address":"Linde Alle 8",
    "sg:city":"Ikast",
    "sg:orig_category":"Tekstilindustri",
    "sg:phone":"+45 97 15 15 17",
    "sg:postcode":"7430",
    "sg:province":"Danmark",
    "wof:name":"Uls\u00f8 Design",
    "wof:placetype":"venue"
},
  "geometry": {"coordinates":[9.1543483734,56.1463317871],"type":"Point"}
}