{
  "type": "Feature",
  "properties": {
    "addr:full":"Marie Grubbes Alle 28 Kongens Lyngby Danmark 2800",
    "addr:housenumber":"28",
    "addr:postcode":"2800",
    "addr:street":"Marie Grubbes Alle",
    "iso:country":"DK",
    "sg:address":"Marie Grubbes Alle 28",
    "sg:city":"Kongens Lyngby",
    "sg:orig_category":"Malermestre",
    "sg:phone":"+45 44 44 01 76",
    "sg:postcode":"2800",
    "sg:province":"Danmark",
    "wof:name":"Olsen, Henning \u00d8strup",
    "wof:placetype":"venue"
},
  "geometry": {"coordinates":[12.4772644043,55.757358551],"type":"Point"}
}