{
  "type": "Feature",
  "properties": {
    "iso:country":"DK",
    "sg:address":"Svenstrupvej 86",
    "sg:city":"Kalundborg",
    "sg:orig_category":"Snedkermestre",
    "sg:phone":"+45 59 50 20 29",
    "sg:postcode":"4400",
    "sg:province":"Danmark",
    "wof:name":"Jensen's Eftf. ApS, Aage Th.",
    "wof:placetype":"venue"
},
  "geometry": {"coordinates":[11.0967216492,55.7260932922],"type":"Point"}
}