{
  "type": "Feature",
  "properties": {
    "addr:full":"Lille Torv 6 \u00c5rhus C Danmark 8000",
    "addr:housenumber":"6",
    "addr:postcode":"8000",
    "addr:street":"Lille Torv",
    "iso:country":"DK",
    "sg:address":"Lille Torv 6",
    "sg:city":"\u00c5rhus C",
    "sg:orig_category":"Advokater",
    "sg:phone":"+45 87 32 20 00",
    "sg:postcode":"8000",
    "sg:province":"Danmark",
    "wof:name":"Korsager, Torben",
    "wof:placetype":"venue"
},
  "geometry": {"coordinates":[4.717400074,49.7588005066],"type":"Point"}
}