{
  "type": "Feature",
  "properties": {
    "addr:full":"Store Bredlundvej 1, Vrads Bryrup Danmark 8654",
    "addr:housenumber":"1",
    "addr:postcode":"8654",
    "addr:street":"Bredlundvej",
    "iso:country":"DK",
    "sg:address":"Store Bredlundvej 1, Vrads",
    "sg:city":"Bryrup",
    "sg:orig_category":"Kirker",
    "sg:postcode":"8654",
    "sg:province":"Danmark",
    "wof:name":"Vrads Kirke",
    "wof:placetype":"venue"
},
  "geometry": {"coordinates":[9.5107898712,56.0237388611],"type":"Point"}
}