{
  "type": "Feature",
  "properties": {
    "addr:full":"S\u00f8ndergade 12 Hadsten Danmark 8370",
    "addr:housenumber":"12",
    "addr:postcode":"8370",
    "addr:street":"Sondergade",
    "iso:country":"DK",
    "sg:address":"S\u00f8ndergade 12",
    "sg:city":"Hadsten",
    "sg:orig_category":"Kiosker",
    "sg:phone":"+45 86 98 21 00",
    "sg:postcode":"8370",
    "sg:province":"Danmark",
    "wof:name":"Hadsten D\u00f8gnkiosk",
    "wof:placetype":"venue"
},
  "geometry": {"coordinates":[10.0447540283,56.327457428],"type":"Point"}
}