{
  "type": "Feature",
  "properties": {
    "iso:country":"DK",
    "sg:address":"Kastruplundgade 7",
    "sg:city":"Kastrup",
    "sg:orig_category":"Kirkelige foreninger",
    "sg:postcode":"2770",
    "sg:province":"Danmark",
    "wof:name":"Noahs Ark - Babelst\u00e5rnet, Kastrup kirkes b\u00f8rneklubber",
    "wof:placetype":"venue"
},
  "geometry": {"coordinates":[12.6387176514,55.6341781616],"type":"Point"}
}