{
  "type": "Feature",
  "properties": {
    "iso:country":"DK",
    "sg:address":"\u00d8stergade 20",
    "sg:city":"Grenaa",
    "sg:orig_category":"Sko",
    "sg:phone":"+45 86 32 26 26",
    "sg:postcode":"8500",
    "sg:province":"Danmark",
    "wof:name":"Bianco Footwear",
    "wof:placetype":"venue"
},
  "geometry": {"coordinates":[10.8790559769,56.4131965637],"type":"Point"}
}