{
  "type": "Feature",
  "properties": {
    "addr:full":"Vestergade 29 A Store Heddinge Danmark 4660",
    "addr:housenumber":"29 a",
    "addr:postcode":"4660",
    "addr:street":"Vestergade",
    "iso:country":"DK",
    "sg:address":"Vestergade 29 A",
    "sg:city":"Store Heddinge",
    "sg:orig_category":"Isolering",
    "sg:phone":"+45 56 50 33 20",
    "sg:postcode":"4660",
    "sg:province":"Danmark",
    "wof:name":"\u00d8stsj\u00e6llands Isolering",
    "wof:placetype":"venue"
},
  "geometry": {"coordinates":[12.3848800659,55.3084907532],"type":"Point"}
}