{
  "type": "Feature",
  "properties": {
    "addr:full":"Edwin Rahrs Vej 52 Brabrand Danmark 8220",
    "addr:housenumber":"52",
    "addr:postcode":"8220",
    "addr:street":"Edwin Rahrs Vej",
    "iso:country":"DK",
    "sg:address":"Edwin Rahrs Vej 52",
    "sg:city":"Brabrand",
    "sg:orig_category":"Botilbud",
    "sg:phone":"+45 86 26 21 00",
    "sg:postcode":"8220",
    "sg:province":"Danmark",
    "wof:name":"Basen, Beskyttet Pensionat",
    "wof:placetype":"venue"
},
  "geometry": {"coordinates":[10.1188240051,56.1636657715],"type":"Point"}
}