{
  "type": "Feature",
  "properties": {
    "addr:full":"Fmd.: Henning Schmidt, Randerup 35 Bredebro Danmark 6261",
    "addr:housenumber":"35",
    "addr:postcode":"6261",
    "addr:street":"Randerup",
    "iso:country":"DK",
    "sg:address":"Fmd.: Henning Schmidt, Randerup 35",
    "sg:city":"Bredebro",
    "sg:orig_category":"Forsamlingshuse",
    "sg:phone":"+45 74 71 64 39",
    "sg:postcode":"6261",
    "sg:province":"Danmark",
    "wof:name":"Randerup Forsamlingsg\u00e5rd",
    "wof:placetype":"venue"
},
  "geometry": {"coordinates":[8.8284835815,55.0566978455],"type":"Point"}
}