{
  "type": "Feature",
  "properties": {
    "iso:country":"DK",
    "sg:address":"Vesterhavsvej 15",
    "sg:city":"Billum",
    "sg:orig_category":"Ungdomsklubber",
    "sg:phone":"+45 29 45 46 43",
    "sg:postcode":"6852",
    "sg:province":"Danmark",
    "wof:name":"Billum Junior- og Ungdomsklub",
    "wof:placetype":"venue"
},
  "geometry": {"coordinates":[8.3317317963,55.6175613403],"type":"Point"}
}