{
  "type": "Feature",
  "properties": {
    "addr:full":"N\u00f8rretorv 2 Horsens Danmark 8700",
    "addr:housenumber":"2",
    "addr:postcode":"8700",
    "addr:street":"Norretorv",
    "iso:country":"DK",
    "sg:address":"N\u00f8rretorv 2",
    "sg:city":"Horsens",
    "sg:orig_category":"Kiosker",
    "sg:phone":"+45 75 62 50 55",
    "sg:postcode":"8700",
    "sg:province":"Danmark",
    "wof:name":"N\u00f8rrebros Kiosk",
    "wof:placetype":"venue"
},
  "geometry": {"coordinates":[9.8432445526,55.8621063232],"type":"Point"}
}