{
  "type": "Feature",
  "properties": {
    "addr:full":"Lindegade 48 Christiansfeld Danmark 6070",
    "addr:housenumber":"48",
    "addr:postcode":"6070",
    "addr:street":"Lindegade",
    "iso:country":"DK",
    "sg:address":"Lindegade 48",
    "sg:city":"Christiansfeld",
    "sg:orig_category":"Dag- og distriktsblade",
    "sg:phone":"+45 74 56 14 33",
    "sg:postcode":"6070",
    "sg:province":"Danmark",
    "wof:name":"Christiansfeld Avis, Tyrstrup Herreds Tidende",
    "wof:placetype":"venue"
},
  "geometry": {"coordinates":[9.4853830338,55.3554496765],"type":"Point"}
}