{
  "type": "Feature",
  "properties": {
    "addr:full":"Jordbrovej 25 \u00c5rhus N Danmark 8200",
    "addr:housenumber":"25",
    "addr:postcode":"8200",
    "addr:street":"Jordbrovej",
    "iso:country":"DK",
    "sg:address":"Jordbrovej 25",
    "sg:city":"\u00c5rhus N",
    "sg:orig_category":"Pizzeriaer",
    "sg:phone":"+45 86 10 81 20",
    "sg:postcode":"8200",
    "sg:province":"Danmark",
    "wof:name":"Pizza Torino",
    "wof:placetype":"venue"
},
  "geometry": {"coordinates":[4.9393601418,49.7092018127],"type":"Point"}
}