{
  "type": "Feature",
  "properties": {
    "addr:full":"St. Sct. Hans Gade 6 Viborg Danmark 8800",
    "addr:housenumber":"6",
    "addr:postcode":"8800",
    "addr:street":"Hans Gade",
    "iso:country":"DK",
    "sg:address":"St. Sct. Hans Gade 6",
    "sg:city":"Viborg",
    "sg:orig_category":"Sundhedspleje",
    "sg:phone":"+45 87 25 25 25",
    "sg:postcode":"8800",
    "sg:province":"Danmark",
    "wof:name":"Familieafdelingen",
    "wof:placetype":"venue"
},
  "geometry": {"coordinates":[9.4095716476,56.4516601562],"type":"Point"}
}