{
  "type": "Feature",
  "properties": {
    "iso:country":"DK",
    "sg:address":"Sevelvej 81, Svenstrup",
    "sg:city":"Vinderup",
    "sg:orig_category":"Tagrenovering",
    "sg:phone":"+45 40 41 17 14",
    "sg:postcode":"7830",
    "sg:province":"Danmark",
    "wof:name":"P. R. Montage",
    "wof:placetype":"venue"
},
  "geometry": {"coordinates":[8.7796897888,56.482635498],"type":"Point"}
}