{
  "type": "Feature",
  "properties": {
    "addr:full":"N\u00f8rre Alle 11 Fredericia Danmark 7000",
    "addr:housenumber":"11",
    "addr:postcode":"7000",
    "addr:street":"Norre Alle",
    "iso:country":"DK",
    "sg:address":"N\u00f8rre Alle 11",
    "sg:city":"Fredericia",
    "sg:orig_category":"Revisorer",
    "sg:phone":"+45 75 92 72 22",
    "sg:postcode":"7000",
    "sg:province":"Danmark",
    "sg:website":"www.deloitte.dk",
    "wof:name":"Deloitte & Touche",
    "wof:placetype":"venue"
},
  "geometry": {"coordinates":[9.7264232635,55.5723953247],"type":"Point"}
}