{
  "type": "Feature",
  "properties": {
    "addr:full":"Virklundvej 46 Silkeborg Danmark 8600",
    "addr:housenumber":"46",
    "addr:postcode":"8600",
    "addr:street":"Virklundvej",
    "iso:country":"DK",
    "sg:address":"Virklundvej 46",
    "sg:city":"Silkeborg",
    "sg:orig_category":"Kopi- og reproduktionsmaskiner",
    "sg:phone":"+45 86 83 68 22",
    "sg:postcode":"8600",
    "sg:province":"Danmark",
    "wof:name":"Jysk Com Service/Micro Worm",
    "wof:placetype":"venue"
},
  "geometry": {"coordinates":[9.5609397888,56.1256484985],"type":"Point"}
}