{
  "type": "Feature",
  "properties": {
    "addr:full":"Metavang 9 Greve Danmark 2670",
    "addr:housenumber":"9",
    "addr:postcode":"2670",
    "addr:street":"Metavang",
    "iso:country":"DK",
    "sg:address":"Metavang 9",
    "sg:city":"Greve",
    "sg:orig_category":"Import-eksport",
    "sg:phone":"+45 43 69 42 46",
    "sg:postcode":"2670",
    "sg:province":"Danmark",
    "wof:name":"Dansant Import",
    "wof:placetype":"venue"
},
  "geometry": {"coordinates":[12.2999229431,55.5838012695],"type":"Point"}
}