{
  "type": "Feature",
  "properties": {
    "iso:country":"DK",
    "sg:address":"Forstander: Leif Heby, Stengade 16, 1, Postboks 119",
    "sg:city":"Helsing\u00f8r",
    "sg:orig_category":"Oplysningsforbund",
    "sg:phone":"+45 49 21 61 41",
    "sg:postcode":"3000",
    "sg:province":"Danmark",
    "sg:website":"www.fof.dk",
    "wof:name":"FOF Folkeligt Oplysnings Forbund",
    "wof:placetype":"venue"
},
  "geometry": {"coordinates":[16.8642692566,59.9382781982],"type":"Point"}
}