{
  "type": "Feature",
  "properties": {
    "addr:full":"Fmd.: Regner Hansen, Fasanvej 53 Vandel Danmark 7184",
    "addr:housenumber":"53",
    "addr:postcode":"7184",
    "addr:street":"Fasanvej",
    "iso:country":"DK",
    "sg:address":"Fmd.: Regner Hansen, Fasanvej 53",
    "sg:city":"Vandel",
    "sg:orig_category":"Hobbybetonede foreninger",
    "sg:phone":"+45 75 88 55 94",
    "sg:postcode":"7184",
    "sg:province":"Danmark",
    "wof:name":"Randb\u00f8l Sogns Jagtforening",
    "wof:placetype":"venue"
},
  "geometry": {"coordinates":[9.2151947021,55.708984375],"type":"Point"}
}