{
  "type": "Feature",
  "properties": {
    "addr:full":"Fmd.: Torben Kirkegaard, Silkehalevej 18, Boeslum Ebeltoft Danmark 8400",
    "addr:housenumber":"18",
    "addr:postcode":"8400",
    "addr:street":"Silkehalevej",
    "iso:country":"DK",
    "sg:address":"Fmd.: Torben Kirkegaard, Silkehalevej 18, Boeslum",
    "sg:city":"Ebeltoft",
    "sg:orig_category":"Hobbybetonede foreninger",
    "sg:phone":"+45 86 34 48 81",
    "sg:postcode":"8400",
    "sg:province":"Danmark",
    "wof:name":"\u00d8er Havn B\u00e5delaug",
    "wof:placetype":"venue"
},
  "geometry": {"coordinates":[10.6778745651,56.199798584],"type":"Point"}
}