{
  "type": "Feature",
  "properties": {
    "iso:country":"DK",
    "sg:address":"S\u00f8ndergade 8",
    "sg:city":"Kjellerup",
    "sg:classifiers":[
        {
            "category":"Banks & Credit Unions",
            "subcategory":"Bank",
            "type":"Services"
        }
    ],
    "sg:phone":"+45 86 88 25 00",
    "sg:postcode":"8620",
    "sg:province":"Danmark",
    "sg:tags":[
        "banker"
    ],
    "wof:name":"Nordea",
    "wof:placetype":"venue"
},
  "geometry": {"coordinates":[9.4305744171,56.2880401611],"type":"Point"}
}