{
  "type": "Feature",
  "properties": {
    "addr:full":"v/ Per Alex S\u00f8rensen, Skivumvej 95, Skivum Nibe Danmark 9240",
    "addr:housenumber":"95",
    "addr:postcode":"9240",
    "addr:street":"Skivumvej",
    "iso:country":"DK",
    "sg:address":"v/ Per Alex S\u00f8rensen, Skivumvej 95, Skivum",
    "sg:city":"Nibe",
    "sg:orig_category":"Borger- og beboerforeninger",
    "sg:phone":"+45 98 66 63 05",
    "sg:postcode":"9240",
    "sg:province":"Danmark",
    "wof:name":"Skivum og Omegns Beboerforening",
    "wof:placetype":"venue"
},
  "geometry": {"coordinates":[9.6393280029,56.982421875],"type":"Point"}
}