{
  "type": "Feature",
  "properties": {
    "addr:full":"Skoleholmen 19 - 21 Greve Danmark 2670",
    "addr:housenumber":"19 21",
    "addr:postcode":"2670",
    "addr:street":"Skoleholmen",
    "iso:country":"DK",
    "sg:address":"Skoleholmen 19 - 21",
    "sg:city":"Greve",
    "sg:orig_category":"Psykologer, praktiserende",
    "sg:phone":"+45 43 60 02 30",
    "sg:postcode":"2670",
    "sg:province":"Danmark",
    "wof:name":"Rasmussen, Karin",
    "wof:placetype":"venue"
},
  "geometry": {"coordinates":[12.2973051071,55.5809860229],"type":"Point"}
}