{
  "type": "Feature",
  "properties": {
    "addr:full":"Kl\u00f8vermarksvej 3 Hobro Danmark 9500",
    "addr:housenumber":"3",
    "addr:postcode":"9500",
    "addr:street":"Klovermarksvej",
    "iso:country":"DK",
    "sg:address":"Kl\u00f8vermarksvej 3",
    "sg:city":"Hobro",
    "sg:orig_category":"Naturgas install. og -service",
    "sg:phone":"+45 98 52 37 16",
    "sg:postcode":"9500",
    "sg:province":"Danmark",
    "wof:name":"Varmeforretningen A/S",
    "wof:placetype":"venue"
},
  "geometry": {"coordinates":[9.802113533,56.6504631042],"type":"Point"}
}