{
  "type": "Feature",
  "properties": {
    "addr:full":"Havnefoged: Gunnar Romedahl M\u00f8ller, Sandbanken 3, B\u00f8nnerup Str Glesborg Danmark 8585",
    "addr:housenumber":"3",
    "addr:postcode":"8585",
    "addr:street":"Sandbanken;Str Glesborg Danmark",
    "iso:country":"DK",
    "sg:address":"Havnefoged: Gunnar Romedahl M\u00f8ller, Sandbanken 3, B\u00f8nnerup Str",
    "sg:city":"Glesborg",
    "sg:orig_category":"Havne",
    "sg:phone":"+45 86 38 61 33",
    "sg:postcode":"8585",
    "sg:province":"Danmark",
    "wof:name":"B\u00f8nnerup Havn",
    "wof:placetype":"venue"
},
  "geometry": {"coordinates":[10.5884723663,56.5124320984],"type":"Point"}
}