{
  "type": "Feature",
  "properties": {
    "addr:full":"Ved Svaleb\u00f8gen 8, Gjerrild Grenaa Danmark 8500",
    "addr:housenumber":"8",
    "addr:postcode":"8500",
    "addr:street":"Ved Svalebogen;Gjerrild",
    "iso:country":"DK",
    "sg:address":"Ved Svaleb\u00f8gen 8, Gjerrild",
    "sg:city":"Grenaa",
    "sg:orig_category":"Fodplejere",
    "sg:phone":"+45 86 38 43 32",
    "sg:postcode":"8500",
    "sg:province":"Danmark",
    "wof:name":"Christiansen, Iris",
    "wof:placetype":"venue"
},
  "geometry": {"coordinates":[10.8774929047,56.4126853943],"type":"Point"}
}