{
  "type": "Feature",
  "properties": {
    "addr:full":"Knarreborg M\u00f8llevej 25 Oure Danmark 5883",
    "addr:housenumber":"25",
    "addr:postcode":"5883",
    "addr:street":"Mollevej",
    "iso:country":"DK",
    "sg:address":"Knarreborg M\u00f8llevej 25",
    "sg:city":"Oure",
    "sg:orig_category":"Campingpladser",
    "sg:phone":"+45 62 28 10 56",
    "sg:postcode":"5883",
    "sg:province":"Danmark",
    "wof:name":"Knarreborg M\u00f8lle Camping",
    "wof:placetype":"venue"
},
  "geometry": {"coordinates":[10.7738704681,55.1267929077],"type":"Point"}
}