{
  "type": "Feature",
  "properties": {
    "addr:full":"Drejerensvej 11 Svenstrup Danmark 9230",
    "addr:housenumber":"11",
    "addr:postcode":"9230",
    "addr:street":"Drejerensvej",
    "iso:country":"DK",
    "sg:address":"Drejerensvej 11",
    "sg:city":"Svenstrup",
    "sg:orig_category":"Planteskoler",
    "sg:phone":"+45 98 38 30 88",
    "sg:postcode":"9230",
    "sg:province":"Danmark",
    "wof:name":"Bennys Planteskole",
    "wof:placetype":"venue"
},
  "geometry": {"coordinates":[9.8011131287,56.9696159363],"type":"Point"}
}