{
  "type": "Feature",
  "properties": {
    "addr:full":"v/ Kaj A E Pedersen, Herlev Hovedgade 9 A Herlev Danmark 2730",
    "addr:housenumber":"9 a",
    "addr:postcode":"2730",
    "addr:street":"Herlev Hovedgade",
    "iso:country":"DK",
    "sg:address":"v/ Kaj A E Pedersen, Herlev Hovedgade 9 A",
    "sg:city":"Herlev",
    "sg:orig_category":"Grundejerforeninger",
    "sg:phone":"+45 44 91 19 31",
    "sg:postcode":"2730",
    "sg:province":"Danmark",
    "wof:name":"V\u00e6gterv\u00e6nget Grundejerforening",
    "wof:placetype":"venue"
},
  "geometry": {"coordinates":[12.4382095337,55.7250595093],"type":"Point"}
}