{
  "type": "Feature",
  "properties": {
    "iso:country":"DK",
    "sg:address":"Vesterk\u00f8b 21",
    "sg:city":"Hedehusene",
    "sg:orig_category":"Blomsterhandlere",
    "sg:phone":"+45 46 56 03 80",
    "sg:postcode":"2640",
    "sg:province":"Danmark",
    "wof:name":"Bittens Blomster",
    "wof:placetype":"venue"
},
  "geometry": {"coordinates":[12.1961545944,55.6514472961],"type":"Point"}
}