{
  "type": "Feature",
  "properties": {
    "addr:full":"Hovedgaden 403 Hedehusene Danmark 2640",
    "addr:housenumber":"403",
    "addr:postcode":"2640",
    "addr:street":"Hovedgaden",
    "iso:country":"DK",
    "sg:address":"Hovedgaden 403",
    "sg:city":"Hedehusene",
    "sg:orig_category":"Broderi",
    "sg:phone":"+45 46 56 00 04",
    "sg:postcode":"2640",
    "sg:province":"Danmark",
    "wof:name":"B\u00f8rresen, Aase",
    "wof:placetype":"venue"
},
  "geometry": {"coordinates":[12.2023859024,55.6497612],"type":"Point"}
}