{
  "type": "Feature",
  "properties": {
    "addr:full":"Rims\u00f8vej 6 Glesborg Danmark 8585",
    "addr:housenumber":"6",
    "addr:postcode":"8585",
    "addr:street":"Rimsovej",
    "iso:country":"DK",
    "sg:address":"Rims\u00f8vej 6",
    "sg:city":"Glesborg",
    "sg:orig_category":"Autoreparation og -service",
    "sg:phone":"+45 86 38 71 44",
    "sg:postcode":"8585",
    "sg:province":"Danmark",
    "wof:name":"Lunden Auto I/S",
    "wof:placetype":"venue"
},
  "geometry": {"coordinates":[10.7387924194,56.4731483459],"type":"Point"}
}