{
  "type": "Feature",
  "properties": {
    "addr:full":"Store Torv 8 Holstebro Danmark 7500",
    "addr:housenumber":"8",
    "addr:postcode":"7500",
    "addr:street":"Store Torv",
    "iso:country":"DK",
    "sg:address":"Store Torv 8",
    "sg:city":"Holstebro",
    "sg:orig_category":"Apoteker og -udsalg",
    "sg:phone":"+45 97 42 00 43",
    "sg:postcode":"7500",
    "sg:province":"Danmark",
    "wof:name":"Holstebro L\u00f8veapotek",
    "wof:placetype":"venue"
},
  "geometry": {"coordinates":[8.6169395447,56.3579216003],"type":"Point"}
}