{
  "type": "Feature",
  "properties": {
    "addr:full":"Pr\u00e6stemarksvej 20 Roskilde Danmark 4000",
    "addr:housenumber":"20",
    "addr:postcode":"4000",
    "addr:street":"Praestemarksvej",
    "iso:country":"DK",
    "sg:address":"Pr\u00e6stemarksvej 20",
    "sg:city":"Roskilde",
    "sg:orig_category":"Alternativ behandling",
    "sg:phone":"+45 46 75 00 14",
    "sg:postcode":"4000",
    "sg:province":"Danmark",
    "wof:name":"Mogensen, Herdis M.",
    "wof:placetype":"venue"
},
  "geometry": {"coordinates":[12.111492157,55.6448669434],"type":"Point"}
}