{
  "type": "Feature",
  "properties": {
    "iso:country":"DK",
    "sg:address":"K\u00e6rvej 8",
    "sg:city":"Sk\u00e5rup",
    "sg:orig_category":"\u00c3\u2020ldreorganisationer og klubber",
    "sg:phone":"+45 62 23 10 84",
    "sg:postcode":"5881",
    "sg:province":"Danmark",
    "wof:name":"Damg\u00e5rdsklubben",
    "wof:placetype":"venue"
},
  "geometry": {"coordinates":[10.6890459061,55.0917205811],"type":"Point"}
}