{
  "type": "Feature",
  "properties": {
    "addr:full":"Skoleleder: Anne K. Paulsen, Teglg\u00e5rdsparken 101 Middelfart Danmark 5500",
    "addr:housenumber":"101",
    "addr:postcode":"5500",
    "addr:street":"Teglgaardsparken",
    "iso:country":"DK",
    "sg:address":"Skoleleder: Anne K. Paulsen, Teglg\u00e5rdsparken 101",
    "sg:city":"Middelfart",
    "sg:orig_category":"Oplysningsforbund",
    "sg:postcode":"5500",
    "sg:province":"Danmark",
    "wof:name":"AOF Assens",
    "wof:placetype":"venue"
},
  "geometry": {"coordinates":[9.7417497635,55.5030250549],"type":"Point"}
}