{
  "type": "Feature",
  "properties": {
    "addr:full":"Ellerupvej 49 Gjern Danmark 8883",
    "addr:housenumber":"49",
    "addr:postcode":"8883",
    "addr:street":"Ellerupvej",
    "iso:country":"DK",
    "sg:address":"Ellerupvej 49",
    "sg:city":"Gjern",
    "sg:orig_category":"Kunstmalere",
    "sg:phone":"+45 86 87 50 17",
    "sg:postcode":"8883",
    "sg:province":"Danmark",
    "wof:name":"Fyhn, Villy",
    "wof:placetype":"venue"
},
  "geometry": {"coordinates":[9.7533473969,56.2325248718],"type":"Point"}
}