{
  "type": "Feature",
  "properties": {
    "addr:full":"Moselundvej 12 Silkeborg Danmark 8600",
    "addr:housenumber":"12",
    "addr:postcode":"8600",
    "addr:street":"Moselundvej",
    "iso:country":"DK",
    "sg:address":"Moselundvej 12",
    "sg:city":"Silkeborg",
    "sg:orig_category":"Konservatorer",
    "sg:phone":"+45 86 85 12 44",
    "sg:postcode":"8600",
    "sg:province":"Danmark",
    "wof:name":"Karup & S\u00f8n",
    "wof:placetype":"venue"
},
  "geometry": {"coordinates":[9.4104499817,56.1490631104],"type":"Point"}
}