{
  "type": "Feature",
  "properties": {
    "iso:country":"DK",
    "sg:address":"Gabelsvej 8",
    "sg:city":"Bramming",
    "sg:orig_category":"Kommunale folkeskoler",
    "sg:phone":"+45 75 17 39 66",
    "sg:postcode":"6740",
    "sg:province":"Danmark",
    "wof:name":"Nordre Skole",
    "wof:placetype":"venue"
},
  "geometry": {"coordinates":[8.6967992783,55.4729499817],"type":"Point"}
}