{
  "type": "Feature",
  "properties": {
    "addr:full":"Sdr. Vr\u00e5vej 4 Vr\u00e5 Danmark 9760",
    "addr:housenumber":"4",
    "addr:postcode":"9760",
    "addr:street":"Vraavej",
    "iso:country":"DK",
    "sg:address":"Sdr. Vr\u00e5vej 4",
    "sg:city":"Vr\u00e5",
    "sg:orig_category":"Plejehjem",
    "sg:phone":"+45 99 67 15 44",
    "sg:postcode":"9760",
    "sg:province":"Danmark",
    "wof:name":"De Gamles Hjem",
    "wof:placetype":"venue"
},
  "geometry": {"coordinates":[9.9455356598,57.3512077332],"type":"Point"}
}