{
  "type": "Feature",
  "properties": {
    "addr:full":"Norupvej 146, Norup Otterup Danmark 5450",
    "addr:housenumber":"146",
    "addr:postcode":"5450",
    "addr:street":"Norupvej;Norup",
    "iso:country":"DK",
    "sg:address":"Norupvej 146, Norup",
    "sg:city":"Otterup",
    "sg:orig_category":"Snedkermestre",
    "sg:phone":"+45 64 82 12 74",
    "sg:postcode":"5450",
    "sg:province":"Danmark",
    "wof:name":"Norup M\u00f8belsnedkeri A/S",
    "wof:placetype":"venue"
},
  "geometry": {"coordinates":[10.4545049667,55.5641746521],"type":"Point"}
}