{
  "type": "Feature",
  "properties": {
    "addr:full":"Gieseg\u00e5rdvej 19, Nordrup Ringsted Danmark 4100",
    "addr:housenumber":"19",
    "addr:postcode":"4100",
    "addr:street":"Giesegaardvej;Nordrup",
    "iso:country":"DK",
    "sg:address":"Gieseg\u00e5rdvej 19, Nordrup",
    "sg:city":"Ringsted",
    "sg:orig_category":"Engros handel",
    "sg:phone":"+45 57 64 01 40",
    "sg:postcode":"4100",
    "sg:province":"Danmark",
    "wof:name":"B.C. Blomsterk\u00f8b A/S",
    "wof:placetype":"venue"
},
  "geometry": {"coordinates":[11.7875862122,55.4458961487],"type":"Point"}
}