{
  "type": "Feature",
  "properties": {
    "addr:full":"Lindevej 5 Gudme Danmark 5884",
    "addr:housenumber":"5",
    "addr:postcode":"5884",
    "addr:street":"Lindevej",
    "iso:country":"DK",
    "sg:address":"Lindevej 5",
    "sg:city":"Gudme",
    "sg:orig_category":"Revisorer",
    "sg:phone":"+45 62 25 12 68",
    "sg:postcode":"5884",
    "sg:province":"Danmark",
    "wof:name":"P.H. Revision",
    "wof:placetype":"venue"
},
  "geometry": {"coordinates":[10.7076072693,55.1488571167],"type":"Point"}
}