{
  "type": "Feature",
  "properties": {
    "addr:full":"Kastanievej 13 Holte Danmark 2840",
    "addr:housenumber":"13",
    "addr:postcode":"2840",
    "addr:street":"Kastanievej",
    "iso:country":"DK",
    "sg:address":"Kastanievej 13",
    "sg:city":"Holte",
    "sg:orig_category":"Psykologer, praktiserende",
    "sg:phone":"+45 45 42 59 18",
    "sg:postcode":"2840",
    "sg:province":"Danmark",
    "wof:name":"Tolstrup, Inger",
    "wof:placetype":"venue"
},
  "geometry": {"coordinates":[12.4712457657,55.8185653687],"type":"Point"}
}