{
  "type": "Feature",
  "properties": {
    "addr:full":"Fmd.: Allan Poulsen, Tved 112 T\u00f8nder Danmark 6270",
    "addr:housenumber":"112",
    "addr:postcode":"6270",
    "addr:street":"Tved",
    "iso:country":"DK",
    "sg:address":"Fmd.: Allan Poulsen, Tved 112",
    "sg:city":"T\u00f8nder",
    "sg:orig_category":"Soldaterforeninger",
    "sg:phone":"+45 74 72 09 21",
    "sg:postcode":"6270",
    "sg:province":"Danmark",
    "wof:name":"De Danske Forsvarsbr\u00f8dre for T\u00f8nder Amt",
    "wof:placetype":"venue"
},
  "geometry": {"coordinates":[8.6816797256,57.055480957],"type":"Point"}
}