{
  "type": "Feature",
  "properties": {
    "iso:country":"DK",
    "sg:address":"N\u00f8rregade 42",
    "sg:city":"Glamsbjerg",
    "sg:orig_category":"Voksenuddannelsescentre",
    "sg:phone":"+45 63 72 20 80",
    "sg:postcode":"5620",
    "sg:province":"Danmark",
    "wof:name":"VUC Glamsbjerg",
    "wof:placetype":"venue"
},
  "geometry": {"coordinates":[10.1004362106,55.2815551758],"type":"Point"}
}