{
  "type": "Feature",
  "properties": {
    "addr:full":"Fabriksvej 15 Gram Danmark 6510",
    "addr:housenumber":"15",
    "addr:postcode":"6510",
    "addr:street":"Fabriksvej",
    "iso:country":"DK",
    "sg:address":"Fabriksvej 15",
    "sg:city":"Gram",
    "sg:orig_category":"Industrilakering",
    "sg:phone":"+45 74 82 33 33",
    "sg:postcode":"6510",
    "sg:province":"Danmark",
    "wof:name":"Gram Industricoat",
    "wof:placetype":"venue"
},
  "geometry": {"coordinates":[9.0516729355,55.2944412231],"type":"Point"}
}