{
  "type": "Feature",
  "properties": {
    "addr:full":"Mommarkvej 270, Tandslet Sydals Danmark 6470",
    "addr:housenumber":"270",
    "addr:postcode":"6470",
    "addr:street":"Mommarkvej;Tandslet",
    "iso:country":"DK",
    "sg:address":"Mommarkvej 270, Tandslet",
    "sg:city":"Sydals",
    "sg:classifiers":[
        {
            "category":"Banks & Credit Unions",
            "subcategory":"Bank",
            "type":"Services"
        }
    ],
    "sg:phone":"+45 74 40 77 20",
    "sg:postcode":"6470",
    "sg:province":"Danmark",
    "sg:tags":[
        "banker"
    ],
    "wof:name":"Sydbank",
    "wof:placetype":"venue"
},
  "geometry": {"coordinates":[9.892463,54.910538],"type":"Point"}
}