{
  "type": "Feature",
  "properties": {
    "addr:full":"Fyrvej 100 Hanstholm Danmark 7730",
    "addr:housenumber":"100",
    "addr:postcode":"7730",
    "addr:street":"Fyrvej",
    "iso:country":"DK",
    "sg:address":"Fyrvej 100",
    "sg:city":"Hanstholm",
    "sg:orig_category":"Kommunale folkeskoler",
    "sg:phone":"+45 97 96 11 55",
    "sg:postcode":"7730",
    "sg:province":"Danmark",
    "sg:website":"www.hanstholm-skole.dk",
    "wof:name":"Hanstholm Skole",
    "wof:placetype":"venue"
},
  "geometry": {"coordinates":[8.6092605591,57.1107902527],"type":"Point"}
}