{
  "type": "Feature",
  "properties": {
    "addr:full":"Bavneh\u00f8jvej 9 Silkeborg Danmark 8600",
    "addr:housenumber":"9",
    "addr:postcode":"8600",
    "addr:street":"Bavnehojvej",
    "iso:country":"DK",
    "sg:address":"Bavneh\u00f8jvej 9",
    "sg:city":"Silkeborg",
    "sg:orig_category":"Engros handel",
    "sg:phone":"+45 86 81 61 22",
    "sg:postcode":"8600",
    "sg:province":"Danmark",
    "wof:name":"Fix A/S",
    "wof:placetype":"venue"
},
  "geometry": {"coordinates":[9.5782232285,56.1861152649],"type":"Point"}
}