{
  "type": "Feature",
  "properties": {
    "addr:full":"Allegade 30 Horsens Danmark 8700",
    "addr:housenumber":"30",
    "addr:postcode":"8700",
    "addr:street":"Allegade",
    "iso:country":"DK",
    "sg:address":"Allegade 30",
    "sg:city":"Horsens",
    "sg:orig_category":"Fotografer",
    "sg:phone":"+45 75 62 76 92",
    "sg:postcode":"8700",
    "sg:province":"Danmark",
    "wof:name":"Albertus, Lis",
    "wof:placetype":"venue"
},
  "geometry": {"coordinates":[9.8445892334,55.8663635254],"type":"Point"}
}