{
  "type": "Feature",
  "properties": {
    "iso:country":"DK",
    "sg:address":"Indre Vordingborgvej, Ostenfeldtsvej 4",
    "sg:city":"N\u00e6stved",
    "sg:orig_category":"Stenhuggere",
    "sg:phone":"+45 55 72 18 09",
    "sg:postcode":"4700",
    "sg:province":"Danmark",
    "wof:name":"Stenhuggeriet - Eigil Caspersen's Eftf.",
    "wof:placetype":"venue"
},
  "geometry": {"coordinates":[5.9268698692,43.9433097839],"type":"Point"}
}