{
  "type": "Feature",
  "properties": {
    "addr:full":"Hj\u00f8rringvej 158 Frederikshavn Danmark 9900",
    "addr:housenumber":"158",
    "addr:postcode":"9900",
    "addr:street":"Hjorringvej",
    "iso:country":"DK",
    "sg:address":"Hj\u00f8rringvej 158",
    "sg:city":"Frederikshavn",
    "sg:orig_category":"Autoforhandlere",
    "sg:phone":"+45 98 42 44 44",
    "sg:postcode":"9900",
    "sg:province":"Danmark",
    "sg:website":"www.peugeot.dk/frederikshavn",
    "wof:name":"Peugeot",
    "wof:placetype":"venue"
},
  "geometry": {"coordinates":[10.504529953,57.4466896057],"type":"Point"}
}