{
  "type": "Feature",
  "properties": {
    "addr:full":"Skolegade 57 Silkeborg Danmark 8600",
    "addr:housenumber":"57",
    "addr:postcode":"8600",
    "addr:street":"Skolegade",
    "iso:country":"DK",
    "sg:address":"Skolegade 57",
    "sg:city":"Silkeborg",
    "sg:orig_category":"Grafisk produktion",
    "sg:phone":"+45 86 81 36 87",
    "sg:postcode":"8600",
    "sg:province":"Danmark",
    "sg:website":"www.ddsign.dk",
    "wof:name":"Dd\u00a2sign ApS",
    "wof:placetype":"venue"
},
  "geometry": {"coordinates":[9.5388526917,56.1651039124],"type":"Point"}
}