{
  "type": "Feature",
  "properties": {
    "addr:full":"Blegdamsvej 28 E K\u00f8benhavn N Danmark 2200",
    "addr:housenumber":"28 e",
    "addr:postcode":"2200",
    "addr:street":"Blegdamsvej;Kobenhavn N Danmark",
    "iso:country":"DK",
    "sg:address":"Blegdamsvej 28 E",
    "sg:city":"K\u00f8benhavn N",
    "sg:classifiers":[
        {
            "category":"Professional",
            "subcategory":"Computer Services",
            "type":"Services"
        }
    ],
    "sg:phone":"+45 35 37 57 11",
    "sg:postcode":"2200",
    "sg:province":"Danmark",
    "sg:tags":[
        "edb",
        "-",
        "software"
    ],
    "wof:name":"Master Data",
    "wof:placetype":"venue"
},
  "geometry": {"coordinates":[-73.9864273071,43.6976699829],"type":"Point"}
}