{
  "type": "Feature",
  "properties": {
    "addr:full":"Kikhavnvejen 28 Hundested Danmark 3390",
    "addr:housenumber":"28",
    "addr:postcode":"3390",
    "addr:street":"Kikhavnvejen",
    "iso:country":"DK",
    "sg:address":"Kikhavnvejen 28",
    "sg:city":"Hundested",
    "sg:orig_category":"Grundejerforeninger",
    "sg:phone":"+45 47 94 02 43",
    "sg:postcode":"3390",
    "sg:province":"Danmark",
    "wof:name":"Kikhavn Bylav",
    "wof:placetype":"venue"
},
  "geometry": {"coordinates":[11.8739814758,55.9801139832],"type":"Point"}
}