{
  "type": "Feature",
  "properties": {
    "addr:full":"Glentevej 14 Esbjerg \u00d8 Danmark 6705",
    "addr:housenumber":"14",
    "addr:postcode":"6705",
    "addr:street":"Glentevej;Danmark",
    "iso:country":"DK",
    "sg:address":"Glentevej 14",
    "sg:city":"Esbjerg \u00d8",
    "sg:orig_category":"Faglige organisationer og foreninger",
    "sg:phone":"+45 75 14 28 55",
    "sg:postcode":"6705",
    "sg:province":"Danmark",
    "wof:name":"Dansk Metalarbejder Forbund",
    "wof:placetype":"venue"
},
  "geometry": {"coordinates":[8.4698734283,55.4893684387],"type":"Point"}
}