{
  "type": "Feature",
  "properties": {
    "iso:country":"DK",
    "sg:address":"Dorphs Alle 10",
    "sg:city":"Taastrup",
    "sg:orig_category":"Revisorer",
    "sg:phone":"+45 43 99 01 01",
    "sg:postcode":"2630",
    "sg:province":"Danmark",
    "wof:name":"Dan Revision",
    "wof:placetype":"venue"
},
  "geometry": {"coordinates":[12.3034858704,55.6488685608],"type":"Point"}
}