{
  "type": "Feature",
  "properties": {
    "addr:full":"Havnepladsen 2 Marstal Danmark 5960",
    "addr:housenumber":"2",
    "addr:postcode":"5960",
    "addr:street":"Havnepladsen",
    "iso:country":"DK",
    "sg:address":"Havnepladsen 2",
    "sg:city":"Marstal",
    "sg:orig_category":"Kiosker",
    "sg:phone":"+45 62 53 18 94",
    "sg:postcode":"5960",
    "sg:province":"Danmark",
    "wof:name":"Havnekiosken",
    "wof:placetype":"venue"
},
  "geometry": {"coordinates":[10.5208625793,54.8556976318],"type":"Point"}
}