{
  "type": "Feature",
  "properties": {
    "addr:full":"Nordg\u00e5rdsvej 1 Fakse Danmark 4640",
    "addr:housenumber":"1",
    "addr:postcode":"4640",
    "addr:street":"Nordgaardsvej",
    "iso:country":"DK",
    "sg:address":"Nordg\u00e5rdsvej 1",
    "sg:city":"Fakse",
    "sg:orig_category":"Planteskoler",
    "sg:phone":"+45 56 71 52 46",
    "sg:postcode":"4640",
    "sg:province":"Danmark",
    "sg:website":"www.stengaardens.dk",
    "wof:name":"Steng\u00e5rdens Rododendron",
    "wof:placetype":"venue"
},
  "geometry": {"coordinates":[12.107714653,55.2679214478],"type":"Point"}
}