{
  "type": "Feature",
  "properties": {
    "iso:country":"DK",
    "sg:address":"Kobbervej 6 ",
    "sg:city":"Skjern",
    "sg:classifiers":[
        {
            "category":"Wholesale",
            "subcategory":"Machinery & Supplies",
            "type":"Manufacturing & Wholesale Goods"
        }
    ],
    "sg:phone":"+45 97 35 01 00",
    "sg:postcode":"6900",
    "sg:province":"Danmark",
    "sg:tags":[
        "-",
        "agriculture",
        "equipment"
    ],
    "wof:name":"CHR C GRENE A/S",
    "wof:placetype":"venue"
},
  "geometry": {"coordinates":[8.501666069,55.9585762024],"type":"Point"}
}