{
  "type": "Feature",
  "properties": {
    "addr:full":"M\u00e5gevej 4 Frederikssund Danmark 3600",
    "addr:housenumber":"4",
    "addr:postcode":"3600",
    "addr:street":"Maagevej",
    "iso:country":"DK",
    "sg:address":"M\u00e5gevej 4",
    "sg:city":"Frederikssund",
    "sg:orig_category":"Web- og Internetdesign",
    "sg:phone":"+45 47 31 02 26",
    "sg:postcode":"3600",
    "sg:province":"Danmark",
    "sg:website":"www.cicero-webdesign.dk",
    "wof:name":"Cicero Webdesign",
    "wof:placetype":"venue"
},
  "geometry": {"coordinates":[12.0612182617,55.8365402222],"type":"Point"}
}