{
  "type": "Feature",
  "properties": {
    "addr:full":"Niels Bohrs Vej 19  Skanderborg Danmark 8660",
    "addr:housenumber":"19",
    "addr:postcode":"8660",
    "addr:street":"Niels Bohrs Vej",
    "iso:country":"DK",
    "sg:address":"Niels Bohrs Vej 19 ",
    "sg:city":"Skanderborg",
    "sg:classifiers":[
        {
            "category":"Shopping",
            "subcategory":"Clothing, Apparel, & Fashions",
            "type":"Retail Goods"
        }
    ],
    "sg:phone":"+45 87 93 88 88",
    "sg:postcode":"8660",
    "sg:province":"Danmark",
    "sg:tags":[
        "clothes"
    ],
    "wof:name":"MIND COMPANIES A/S",
    "wof:placetype":"venue"
},
  "geometry": {"coordinates":[9.9856433868,56.0679473877],"type":"Point"}
}