{
  "type": "Feature",
  "properties": {
    "addr:full":"Jernbanevej 3 Skanderborg Danmark 8660",
    "addr:housenumber":"3",
    "addr:postcode":"8660",
    "addr:street":"Jernbanevej",
    "iso:country":"DK",
    "sg:address":"Jernbanevej 3",
    "sg:city":"Skanderborg",
    "sg:orig_category":"Kiosker",
    "sg:phone":"+45 86 52 46 30",
    "sg:postcode":"8660",
    "sg:province":"Danmark",
    "wof:name":"DSB Kombikiosk",
    "wof:placetype":"venue"
},
  "geometry": {"coordinates":[9.9285335541,56.0439834595],"type":"Point"}
}