{
  "type": "Feature",
  "properties": {
    "addr:full":"Sk\u00e6lsk\u00f8rvej 34 Sor\u00f8 Danmark 4180",
    "addr:housenumber":"34",
    "addr:postcode":"4180",
    "addr:street":"Skaelskorvej",
    "iso:country":"DK",
    "sg:address":"Sk\u00e6lsk\u00f8rvej 34",
    "sg:city":"Sor\u00f8",
    "sg:classifiers":[
        {
            "category":"Restaurant",
            "type":"Food & Drink"
        }
    ],
    "sg:phone":"+45 57 84 92 00",
    "sg:postcode":"4180",
    "sg:province":"Danmark",
    "wof:name":"Kongskilde Friluftsg\u00e5rd/Sor\u00f8 Vandrerhjem",
    "wof:placetype":"venue"
},
  "geometry": {"coordinates":[-102.94467926030001,45.4534721375],"type":"Point"}
}