{
  "type": "Feature",
  "properties": {
    "addr:full":"Wilkensvej 26 B, 4.th Frederiksberg Danmark 2000",
    "addr:housenumber":"26 b 4.th",
    "addr:postcode":"2000",
    "addr:street":"Wilkensvej",
    "iso:country":"DK",
    "sg:address":"Wilkensvej 26 B, 4.th",
    "sg:city":"Frederiksberg",
    "sg:orig_category":"Telekommunikation",
    "sg:phone":"+45 38 33 70 01",
    "sg:postcode":"2000",
    "sg:province":"Danmark",
    "wof:name":"Teleconomy",
    "wof:placetype":"venue"
},
  "geometry": {"coordinates":[12.5299301147,55.6787872314],"type":"Point"}
}