{
  "type": "Feature",
  "properties": {
    "addr:full":"Mosevej 3, Herskind Galten Danmark 8464",
    "addr:housenumber":"3",
    "addr:postcode":"8464",
    "addr:street":"Mosevej;Herskind",
    "iso:country":"DK",
    "sg:address":"Mosevej 3, Herskind",
    "sg:city":"Galten",
    "sg:orig_category":"Planteskoler",
    "sg:phone":"+45 86 95 43 30",
    "sg:postcode":"8464",
    "sg:province":"Danmark",
    "wof:name":"Hansen, Jytte",
    "wof:placetype":"venue"
},
  "geometry": {"coordinates":[9.9034748077,56.1558837891],"type":"Point"}
}