{
  "type": "Feature",
  "properties": {
    "addr:full":"Valby Langgade 151 Valby Danmark 2500",
    "addr:housenumber":"151",
    "addr:postcode":"2500",
    "addr:street":"Valby Langgade",
    "iso:country":"DK",
    "sg:address":"Valby Langgade 151",
    "sg:city":"Valby",
    "sg:orig_category":"Kiosker",
    "sg:phone":"+45 36 30 77 31",
    "sg:postcode":"2500",
    "sg:province":"Danmark",
    "wof:name":"Kiosk 151",
    "wof:placetype":"venue"
},
  "geometry": {"coordinates":[12.5000276566,55.6675376892],"type":"Point"}
}