{
  "type": "Feature",
  "properties": {
    "iso:country":"DK",
    "sg:address":"Spanien 63",
    "sg:city":"\u00c5rhus C",
    "sg:orig_category":"Servicestationer",
    "sg:phone":"+45 86 19 68 00",
    "sg:postcode":"8000",
    "sg:province":"Danmark",
    "wof:name":"Hydro Texaco",
    "wof:placetype":"venue"
},
  "geometry": {"coordinates":[-2.9886798859,39.8950195312],"type":"Point"}
}