{
  "type": "Feature",
  "properties": {
    "addr:full":"Houmeden 9 Randers Danmark 8900",
    "addr:housenumber":"9",
    "addr:postcode":"8900",
    "addr:street":"Houmeden",
    "iso:country":"DK",
    "sg:address":"Houmeden 9",
    "sg:city":"Randers",
    "sg:orig_category":"Sko",
    "sg:phone":"+45 86 41 08 06",
    "sg:postcode":"8900",
    "sg:province":"Danmark",
    "wof:name":"Picasso",
    "wof:placetype":"venue"
},
  "geometry": {"coordinates":[10.0350999832,56.4605712891],"type":"Point"}
}