{
  "type": "Feature",
  "properties": {
    "addr:full":"Rosmarksvej 1 Nakskov Danmark 4900",
    "addr:housenumber":"1",
    "addr:postcode":"4900",
    "addr:street":"Rosmarksvej",
    "iso:country":"DK",
    "sg:address":"Rosmarksvej 1",
    "sg:city":"Nakskov",
    "sg:orig_category":"El-forsyning",
    "sg:phone":"+45 54 94 85 98",
    "sg:postcode":"4900",
    "sg:province":"Danmark",
    "wof:name":"Rudbjerg Vindm\u00f8llelaug II",
    "wof:placetype":"venue"
},
  "geometry": {"coordinates":[11.0568332672,54.7748336792],"type":"Point"}
}