{
  "type": "Feature",
  "properties": {
    "addr:full":"B\u00e6kvej 10, V. T\u00f8rslev Mariager Danmark 9550",
    "addr:housenumber":"10",
    "addr:postcode":"9550",
    "addr:street":"Baekvej;Torslev",
    "iso:country":"DK",
    "sg:address":"B\u00e6kvej 10, V. T\u00f8rslev",
    "sg:city":"Mariager",
    "sg:orig_category":"Malermestre",
    "sg:phone":"+45 98 55 52 76",
    "sg:postcode":"9550",
    "sg:province":"Danmark",
    "wof:name":"E. K. M.",
    "wof:placetype":"venue"
},
  "geometry": {"coordinates":[10.0618648529,56.676902771],"type":"Point"}
}