{
  "type": "Feature",
  "properties": {
    "addr:full":"Mastruph\u00f8j 3 St\u00f8vring Danmark 9530",
    "addr:housenumber":"3",
    "addr:postcode":"9530",
    "addr:street":"Mastruphoj",
    "iso:country":"DK",
    "sg:address":"Mastruph\u00f8j 3",
    "sg:city":"St\u00f8vring",
    "sg:classifiers":[
        {
            "category":"Personal",
            "subcategory":"Massage",
            "type":"Services"
        }
    ],
    "sg:phone":"+45 98 37 44 52",
    "sg:postcode":"9530",
    "sg:province":"Danmark",
    "sg:website":"www.kropsplejere.dk",
    "wof:name":"Klinik for Sundhed og Velv\u00e6re",
    "wof:placetype":"venue"
},
  "geometry": {"coordinates":[-103.3591003418,34.3032836914],"type":"Point"}
}