{
  "type": "Feature",
  "properties": {
    "iso:country":"DK",
    "sg:address":"R\u00e5dmandsgade 6",
    "sg:city":"K\u00f8benhavn N",
    "sg:orig_category":"Kopiering",
    "sg:phone":"+45 70 22 29 90",
    "sg:postcode":"2200",
    "sg:province":"Danmark",
    "sg:website":"www.xlprint.dk",
    "wof:name":"XL Print ApS",
    "wof:placetype":"venue"
},
  "geometry": {"coordinates":[-76.4168395996,37.452419281],"type":"Point"}
}