{
  "type": "Feature",
  "properties": {
    "addr:full":"M\u00f8llegade 27 Silkeborg Danmark 8600",
    "addr:housenumber":"27",
    "addr:postcode":"8600",
    "addr:street":"Mollegade",
    "iso:country":"DK",
    "sg:address":"M\u00f8llegade 27",
    "sg:city":"Silkeborg",
    "sg:orig_category":"Finmekanikere",
    "sg:phone":"+45 86 82 16 74",
    "sg:postcode":"8600",
    "sg:province":"Danmark",
    "wof:name":"Jensen, Preben",
    "wof:placetype":"venue"
},
  "geometry": {"coordinates":[9.5480003357,56.1654167175],"type":"Point"}
}