{
  "type": "Feature",
  "properties": {
    "addr:full":"Aalborg Storcenter, Hobrovej 452 Aalborg SV Danmark 9200",
    "addr:housenumber":"452",
    "addr:postcode":"9200",
    "addr:street":"Hobrovej",
    "iso:country":"DK",
    "sg:address":"Aalborg Storcenter, Hobrovej 452",
    "sg:city":"Aalborg SV",
    "sg:orig_category":"Materialister",
    "sg:phone":"+45 98 18 80 33",
    "sg:postcode":"9200",
    "sg:province":"Danmark",
    "wof:name":"Matas",
    "wof:placetype":"venue"
},
  "geometry": {"coordinates":[9.8565721512,57.00573349],"type":"Point"}
}