{
  "type": "Feature",
  "properties": {
    "addr:full":"Stationsgade 30 - 32 Risskov Danmark 8240",
    "addr:housenumber":"30 32",
    "addr:postcode":"8240",
    "addr:street":"Stationsgade",
    "iso:country":"DK",
    "sg:address":"Stationsgade 30 - 32",
    "sg:city":"Risskov",
    "sg:orig_category":"Revisorer",
    "sg:phone":"+45 86 17 76 81",
    "sg:postcode":"8240",
    "sg:province":"Danmark",
    "wof:name":"Marcussen, Per & Anders",
    "wof:placetype":"venue"
},
  "geometry": {"coordinates":[10.2355394363,56.1832237244],"type":"Point"}
}