{
  "type": "Feature",
  "properties": {
    "addr:full":"Fmd.: Kirsten Vestergaard, H\u00f8jg\u00e5rdsparken 98 Hjerm Danmark 7560",
    "addr:housenumber":"98",
    "addr:postcode":"7560",
    "addr:street":"Hojgaardsparken",
    "iso:country":"DK",
    "sg:address":"Fmd.: Kirsten Vestergaard, H\u00f8jg\u00e5rdsparken 98",
    "sg:city":"Hjerm",
    "sg:orig_category":"Musik og sang",
    "sg:phone":"+45 97 46 40 95",
    "sg:postcode":"7560",
    "sg:province":"Danmark",
    "wof:name":"Beokoret",
    "wof:placetype":"venue"
},
  "geometry": {"coordinates":[8.6395950317,56.4384765625],"type":"Point"}
}