{
  "type": "Feature",
  "properties": {
    "iso:country":"DK",
    "sg:address":"Tofth\u00f8jvej 32",
    "sg:city":"Storvorde",
    "sg:orig_category":"Kommunale folkeskoler",
    "sg:phone":"+45 98 31 84 90",
    "sg:postcode":"9280",
    "sg:province":"Danmark",
    "sg:website":"www.tofthoej-skolen.dk",
    "wof:name":"Tofth\u00f8jskolen",
    "wof:placetype":"venue"
},
  "geometry": {"coordinates":[10.1020059586,56.9971427917],"type":"Point"}
}