{
  "type": "Feature",
  "properties": {
    "iso:country":"DK",
    "sg:address":"Sabrovej 30",
    "sg:city":"Sabro",
    "sg:orig_category":"Skorstensfejere",
    "sg:phone":"+45 86 24 76 01",
    "sg:postcode":"8471",
    "sg:province":"Danmark",
    "wof:name":"Lindquist, John",
    "wof:placetype":"venue"
},
  "geometry": {"coordinates":[10.0451107025,56.2088088989],"type":"Point"}
}