{
  "type": "Feature",
  "properties": {
    "addr:full":"Gravene 5 Glamsbjerg Danmark 5620",
    "addr:housenumber":"5",
    "addr:postcode":"5620",
    "addr:street":"Gravene",
    "iso:country":"DK",
    "sg:address":"Gravene 5",
    "sg:city":"Glamsbjerg",
    "sg:orig_category":"Antikviteter",
    "sg:phone":"+45 64 72 22 38",
    "sg:postcode":"5620",
    "sg:province":"Danmark",
    "wof:name":"Rasmussen, Hardy",
    "wof:placetype":"venue"
},
  "geometry": {"coordinates":[10.0938272476,55.2840156555],"type":"Point"}
}