{
  "type": "Feature",
  "properties": {
    "addr:full":"H\u00e5ndv\u00e6rkervej 14 Hundested Danmark 3390",
    "addr:housenumber":"14",
    "addr:postcode":"3390",
    "addr:street":"Haandvaerkervej",
    "iso:country":"DK",
    "sg:address":"H\u00e5ndv\u00e6rkervej 14",
    "sg:city":"Hundested",
    "sg:orig_category":"Varmeforsyning",
    "sg:phone":"+45 47 98 08 01",
    "sg:postcode":"3390",
    "sg:province":"Danmark",
    "wof:name":"Energi E2 - Hundested Kraftvarmev\u00e6rk",
    "wof:placetype":"venue"
},
  "geometry": {"coordinates":[11.8530349731,55.958530426],"type":"Point"}
}