{
  "type": "Feature",
  "properties": {
    "addr:full":"Toftevangen 47, Gelsted Gelsted Danmark 5591",
    "addr:housenumber":"47",
    "addr:postcode":"5591",
    "addr:street":"Toftevangen",
    "iso:country":"DK",
    "sg:address":"Toftevangen 47, Gelsted",
    "sg:city":"Gelsted",
    "sg:orig_category":"Malermestre",
    "sg:phone":"+45 64 49 19 62",
    "sg:postcode":"5591",
    "sg:province":"Danmark",
    "wof:name":"Tayler, Michael",
    "wof:placetype":"venue"
},
  "geometry": {"coordinates":[9.9734048843,55.3995094299],"type":"Point"}
}