{
  "type": "Feature",
  "properties": {
    "addr:full":"Jernbanegade 53, Postboks 100 Vamdrup Danmark 6580",
    "addr:housenumber":"53;100",
    "addr:postcode":"6580",
    "addr:street":"Jernbanegade",
    "iso:country":"DK",
    "sg:address":"Jernbanegade 53, Postboks 100",
    "sg:city":"Vamdrup",
    "sg:orig_category":"Revisorer",
    "sg:phone":"+45 75 58 29 19",
    "sg:postcode":"6580",
    "sg:province":"Danmark",
    "sg:website":"www.revision-fdr.dk",
    "wof:name":"Bojsen, Bjerre",
    "wof:placetype":"venue"
},
  "geometry": {"coordinates":[9.2839107513,55.4266548157],"type":"Point"}
}