{
  "type": "Feature",
  "properties": {
    "addr:full":"\u00d8rstedsvej 28 Ribe Danmark 6760",
    "addr:housenumber":"28",
    "addr:postcode":"6760",
    "addr:street":"Orstedsvej",
    "iso:country":"DK",
    "sg:address":"\u00d8rstedsvej 28",
    "sg:city":"Ribe",
    "sg:orig_category":"\u00c3\u02dcl- og mineralvandsdepoter",
    "sg:phone":"+45 75 42 12 60",
    "sg:postcode":"6760",
    "sg:province":"Danmark",
    "wof:name":"Thor Depot",
    "wof:placetype":"venue"
},
  "geometry": {"coordinates":[8.7717399597,55.3535003662],"type":"Point"}
}