{
  "type": "Feature",
  "properties": {
    "addr:full":"F\u00e5borgvej 109 Vester Skerninge Danmark 5762",
    "addr:housenumber":"109",
    "addr:postcode":"5762",
    "addr:street":"Faaborgvej",
    "iso:country":"DK",
    "sg:address":"F\u00e5borgvej 109",
    "sg:city":"Vester Skerninge",
    "sg:orig_category":"Hundepensioner",
    "sg:phone":"+45 62 24 14 58",
    "sg:postcode":"5762",
    "sg:province":"Danmark",
    "wof:name":"Lille Hundepension, Den",
    "wof:placetype":"venue"
},
  "geometry": {"coordinates":[10.4368543625,55.0746002197],"type":"Point"}
}