{
  "type": "Feature",
  "properties": {
    "addr:full":"Betty Nansens Alle 57 Frederiksberg Danmark 2000",
    "addr:housenumber":"57",
    "addr:postcode":"2000",
    "addr:street":"Betty Nansens Alle",
    "iso:country":"DK",
    "sg:address":"Betty Nansens Alle 57",
    "sg:city":"Frederiksberg",
    "sg:orig_category":"Dagcentre",
    "sg:phone":"+45 36 46 08 06",
    "sg:postcode":"2000",
    "sg:province":"Danmark",
    "wof:name":"Norden Dagcenter",
    "wof:placetype":"venue"
},
  "geometry": {"coordinates":[12.5019197464,55.6699981689],"type":"Point"}
}