{
  "type": "Feature",
  "properties": {
    "addr:full":"Skolev\u00e6nget 17, Lind Herning Danmark 7400",
    "addr:housenumber":"17",
    "addr:postcode":"7400",
    "addr:street":"Skolevaenget",
    "iso:country":"DK",
    "sg:address":"Skolev\u00e6nget 17, Lind",
    "sg:city":"Herning",
    "sg:orig_category":"Kommunale ungdomsskoler",
    "sg:phone":"+45 97 12 68 71",
    "sg:postcode":"7400",
    "sg:province":"Danmark",
    "wof:name":"Ungdomsskolen Rusk",
    "wof:placetype":"venue"
},
  "geometry": {"coordinates":[8.9768896103,56.1374168396],"type":"Point"}
}