{
  "type": "Feature",
  "properties": {
    "iso:country":"DK",
    "sg:address":"B\u00f8rsholmsvej 3",
    "sg:city":"Gedser",
    "sg:orig_category":"Varmeforsyning",
    "sg:phone":"+45 54 17 92 78",
    "sg:postcode":"4874",
    "sg:province":"Danmark",
    "wof:name":"Gedser Fjernvarmev\u00e6rk A.m.b.a.",
    "wof:placetype":"venue"
},
  "geometry": {"coordinates":[11.9307689667,54.5773696899],"type":"Point"}
}