{
  "type": "Feature",
  "properties": {
    "iso:country":"DK",
    "sg:address":"M\u00f8gelt\u00f8nder Omfartsvej 4, Toghale",
    "sg:city":"T\u00f8nder",
    "sg:classifiers":[
        {
            "category":"Taxi",
            "type":"Transportation"
        }
    ],
    "sg:phone":"+45 74 72 29 00",
    "sg:postcode":"6270",
    "sg:province":"Danmark",
    "wof:name":"T\u00f8nder Taxa",
    "wof:placetype":"venue"
},
  "geometry": {"coordinates":[8.8009996414,54.9552383423],"type":"Point"}
}