{
  "type": "Feature",
  "properties": {
    "addr:full":"Vejlevej 13 - 15 Horsens Danmark 8700",
    "addr:housenumber":"13 15",
    "addr:postcode":"8700",
    "addr:street":"Vejlevej",
    "iso:country":"DK",
    "sg:address":"Vejlevej 13 - 15",
    "sg:city":"Horsens",
    "sg:orig_category":"Hospital, udstyr til",
    "sg:phone":"+45 76 25 25 25",
    "sg:postcode":"8700",
    "sg:province":"Danmark",
    "sg:website":"www.hn.dk",
    "wof:name":"Nielsen A/S, Hede",
    "wof:placetype":"venue"
},
  "geometry": {"coordinates":[9.8294172287,55.8507766724],"type":"Point"}
}