{
  "type": "Feature",
  "properties": {
    "addr:full":"Anb\u00e6kvej 36 Hammel Danmark 8450",
    "addr:housenumber":"36",
    "addr:postcode":"8450",
    "addr:street":"Anbaekvej",
    "iso:country":"DK",
    "sg:address":"Anb\u00e6kvej 36",
    "sg:city":"Hammel",
    "sg:orig_category":"Autoreparation og -service",
    "sg:phone":"+45 86 96 38 55",
    "sg:postcode":"8450",
    "sg:province":"Danmark",
    "wof:name":"Shell Hammel",
    "wof:placetype":"venue"
},
  "geometry": {"coordinates":[9.8599214554,56.2516593933],"type":"Point"}
}