{
  "type": "Feature",
  "properties": {
    "addr:full":"Ulsn\u00e6s 1 Gr\u00e5sten Danmark 6300",
    "addr:housenumber":"1",
    "addr:postcode":"6300",
    "addr:street":"Ulsnaes",
    "iso:country":"DK",
    "sg:address":"Ulsn\u00e6s 1",
    "sg:city":"Gr\u00e5sten",
    "sg:orig_category":"Bodegaer",
    "sg:phone":"+45 74 65 33 65",
    "sg:postcode":"6300",
    "sg:province":"Danmark",
    "wof:name":"Magitte, Bodega",
    "wof:placetype":"venue"
},
  "geometry": {"coordinates":[25.3302497864,60.2151107788],"type":"Point"}
}