{
  "type": "Feature",
  "properties": {
    "addr:full":"\u00d8ster Bregninge 43 \u00c6r\u00f8sk\u00f8bing Danmark 5970",
    "addr:housenumber":"43",
    "addr:postcode":"5970",
    "addr:street":"Oster Bregninge",
    "iso:country":"DK",
    "sg:address":"\u00d8ster Bregninge 43",
    "sg:city":"\u00c6r\u00f8sk\u00f8bing",
    "sg:orig_category":"Advokater",
    "sg:phone":"+45 62 58 20 11",
    "sg:postcode":"5970",
    "sg:province":"Danmark",
    "wof:name":"Christensen, Bente Gaarde",
    "wof:placetype":"venue"
},
  "geometry": {"coordinates":[10.4097261429,54.8888473511],"type":"Point"}
}