{
  "type": "Feature",
  "properties": {
    "addr:full":"Stormgade 90 Esbjerg Danmark 6700",
    "addr:housenumber":"90",
    "addr:postcode":"6700",
    "addr:street":"Stormgade",
    "iso:country":"DK",
    "sg:address":"Stormgade 90",
    "sg:city":"Esbjerg",
    "sg:orig_category":"Faglige organisationer og foreninger",
    "sg:phone":"+45 75 12 21 55",
    "sg:postcode":"6700",
    "sg:province":"Danmark",
    "wof:name":"SID Industri",
    "wof:placetype":"venue"
},
  "geometry": {"coordinates":[8.4456958771,55.4740829468],"type":"Point"}
}