{
  "type": "Feature",
  "properties": {
    "addr:full":"Sognepr\u00e6st: Karl Erik Jensen (K/B), Pr\u00e6steg\u00e5rdsvej 1 A, \u00d8. Velling Randers Danmark 8900",
    "addr:housenumber":"1 a o.",
    "addr:postcode":"8900",
    "addr:street":"Praestegaardsvej;Velling",
    "iso:country":"DK",
    "sg:address":"Sognepr\u00e6st: Karl Erik Jensen (K/B), Pr\u00e6steg\u00e5rdsvej 1 A, \u00d8. Velling",
    "sg:city":"Randers",
    "sg:orig_category":"Kirkesogne",
    "sg:phone":"+45 86 46 70 08",
    "sg:postcode":"8900",
    "sg:province":"Danmark",
    "wof:name":"\u00d8. Velling, Helstrup og Grensten Sogne",
    "wof:placetype":"venue"
},
  "geometry": {"coordinates":[10.0357952118,56.4593734741],"type":"Point"}
}