{
  "type": "Feature",
  "properties": {
    "addr:full":"Bredalsvej 71 Odense C Danmark 5000",
    "addr:housenumber":"71",
    "addr:postcode":"5000",
    "addr:street":"Bredalsvej",
    "iso:country":"DK",
    "sg:address":"Bredalsvej 71",
    "sg:city":"Odense C",
    "sg:orig_category":"Gaveartikler",
    "sg:phone":"+45 66 14 28 30",
    "sg:postcode":"5000",
    "sg:province":"Danmark",
    "wof:name":"Lauritzen, Katsumi",
    "wof:placetype":"venue"
},
  "geometry": {"coordinates":[10.4130010605,55.3916511536],"type":"Point"}
}