{
  "type": "Feature",
  "properties": {
    "addr:full":"Postv\u00e6nget 2, Haarby Haarby Danmark 5683",
    "addr:housenumber":"2",
    "addr:postcode":"5683",
    "addr:street":"Postvaenget",
    "iso:country":"DK",
    "sg:address":"Postv\u00e6nget 2, Haarby",
    "sg:city":"Haarby",
    "sg:orig_category":"Posthuse",
    "sg:phone":"+45 65 43 32 00",
    "sg:postcode":"5683",
    "sg:province":"Danmark",
    "wof:name":"Post Danmark, Haarby Posthus",
    "wof:placetype":"venue"
},
  "geometry": {"coordinates":[10.1234750748,55.2234535217],"type":"Point"}
}