{
  "type": "Feature",
  "properties": {
    "addr:full":"\u00d8stergade 7 H Silkeborg Danmark 8600",
    "addr:housenumber":"7 h",
    "addr:postcode":"8600",
    "addr:street":"Ostergade",
    "iso:country":"DK",
    "sg:address":"\u00d8stergade 7 H",
    "sg:city":"Silkeborg",
    "sg:orig_category":"Skomagere",
    "sg:phone":"+45 86 82 20 12",
    "sg:postcode":"8600",
    "sg:province":"Danmark",
    "wof:name":"Skaarups Ortop\u00e6disk Haandskomageri",
    "wof:placetype":"venue"
},
  "geometry": {"coordinates":[9.5524425507,56.1693305969],"type":"Point"}
}