{
  "type": "Feature",
  "properties": {
    "addr:full":"v/ Bent Olsen, Kattegatvejen 10 Hundested Danmark 3390",
    "addr:housenumber":"10",
    "addr:postcode":"3390",
    "addr:street":"Kattegatvejen",
    "iso:country":"DK",
    "sg:address":"v/ Bent Olsen, Kattegatvejen 10",
    "sg:city":"Hundested",
    "sg:orig_category":"Spejderkorps",
    "sg:phone":"+45 47 93 73 60",
    "sg:postcode":"3390",
    "sg:province":"Danmark",
    "wof:name":"Ungdomsg\u00e5rden Kikhavn, Adventistsamfundets Spejderkorps",
    "wof:placetype":"venue"
},
  "geometry": {"coordinates":[11.8530349731,55.958530426],"type":"Point"}
}