{
  "type": "Feature",
  "properties": {
    "addr:full":"S\u00f8ndergade 28 Frederikshavn Danmark 9900",
    "addr:housenumber":"28",
    "addr:postcode":"9900",
    "addr:street":"Sondergade",
    "iso:country":"DK",
    "sg:address":"S\u00f8ndergade 28",
    "sg:city":"Frederikshavn",
    "sg:orig_category":"EDB - udstyr",
    "sg:phone":"+45 98 42 89 33",
    "sg:postcode":"9900",
    "sg:province":"Danmark",
    "wof:name":"EDB Hj\u00f8rnet",
    "wof:placetype":"venue"
},
  "geometry": {"coordinates":[10.5320529938,57.4358024597],"type":"Point"}
}