{
  "type": "Feature",
  "properties": {
    "iso:country":"DK",
    "sg:address":"Havrevangen 1",
    "sg:city":"Aalborg",
    "sg:orig_category":"Non-Classified Establishments",
    "sg:phone":"+45 96 31 35 50",
    "sg:postcode":"9000",
    "sg:province":"Danmark",
    "wof:name":"Revalideringscentret Ydun",
    "wof:placetype":"venue"
},
  "geometry": {"coordinates":[9.9447479248,57.0353088379],"type":"Point"}
}