{
  "type": "Feature",
  "properties": {
    "addr:full":"Store Valby Vej 240, Gunds\u00f8lille Roskilde Danmark 4000",
    "addr:housenumber":"240",
    "addr:postcode":"4000",
    "addr:street":"Store Valby Vej;Gundsolille",
    "iso:country":"DK",
    "sg:address":"Store Valby Vej 240, Gunds\u00f8lille",
    "sg:city":"Roskilde",
    "sg:orig_category":"Autoforhandlere",
    "sg:phone":"+45 46 78 78 85",
    "sg:postcode":"4000",
    "sg:province":"Danmark",
    "sg:website":"www.schmolker.dk",
    "wof:name":"Schm\u00f8lker Trading",
    "wof:placetype":"venue"
},
  "geometry": {"coordinates":[12.0909376144,55.6404838562],"type":"Point"}
}