{
  "type": "Feature",
  "properties": {
    "addr:full":"Vesterhavsvej 17 Blokhus Danmark 9492",
    "addr:housenumber":"17",
    "addr:postcode":"9492",
    "addr:street":"Vesterhavsvej",
    "iso:country":"DK",
    "sg:address":"Vesterhavsvej 17",
    "sg:city":"Blokhus",
    "sg:orig_category":"Transportmateriel",
    "sg:phone":"+45 96 73 74 00",
    "sg:postcode":"9492",
    "sg:province":"Danmark",
    "sg:website":"www.m-tec.dk",
    "wof:name":"M-Tec A/S",
    "wof:placetype":"venue"
},
  "geometry": {"coordinates":[9.616736412,57.2486953735],"type":"Point"}
}