{
  "type": "Feature",
  "properties": {
    "iso:country":"DK",
    "sg:address":"H. C. \u00d8rsteds Vej 2",
    "sg:city":"Nyk\u00f8bing",
    "sg:orig_category":"Oplysningsforbund",
    "sg:phone":"+45 97 71 17 77",
    "sg:postcode":"7900",
    "sg:province":"Danmark",
    "wof:name":"AOF Mors\u00f8",
    "wof:placetype":"venue"
},
  "geometry": {"coordinates":[-114.0768203735,46.4432411194],"type":"Point"}
}