{
  "type": "Feature",
  "properties": {
    "addr:full":"v/ Kenneth Thoft-Madsen, Den kommunale Ungdomsskole, Skovvej 2 Terndrup Danmark 9575",
    "addr:housenumber":"2",
    "addr:postcode":"9575",
    "addr:street":"Skovvej;Danmark",
    "iso:country":"DK",
    "sg:address":"v/ Kenneth Thoft-Madsen, Den kommunale Ungdomsskole, Skovvej 2",
    "sg:city":"Terndrup",
    "sg:orig_category":"Fritidsklubber",
    "sg:phone":"+45 99 82 84 45",
    "sg:postcode":"9575",
    "sg:province":"Danmark",
    "wof:name":"B\u00e6lum Junior- og Ungdomsklub",
    "wof:placetype":"venue"
},
  "geometry": {"coordinates":[10.058382988,56.8162651062],"type":"Point"}
}