{
  "type": "Feature",
  "properties": {
    "addr:full":"Kanslergade 8 Odense C Danmark 5000",
    "addr:housenumber":"8",
    "addr:postcode":"5000",
    "addr:street":"Kanslergade",
    "iso:country":"DK",
    "sg:address":"Kanslergade 8",
    "sg:city":"Odense C",
    "sg:orig_category":"Plejecentre",
    "sg:phone":"+45 66 13 13 72",
    "sg:postcode":"5000",
    "sg:province":"Danmark",
    "wof:name":"Lokalcenter Lille Glasvej",
    "wof:placetype":"venue"
},
  "geometry": {"coordinates":[10.3699064255,55.3979377747],"type":"Point"}
}