{
  "type": "Feature",
  "properties": {
    "addr:full":"Louisendalvej 12, Gudum Storvorde Danmark 9280",
    "addr:housenumber":"12",
    "addr:postcode":"9280",
    "addr:street":"Louisendalvej;Gudum",
    "iso:country":"DK",
    "sg:address":"Louisendalvej 12, Gudum",
    "sg:city":"Storvorde",
    "sg:orig_category":"Forsamlingshuse",
    "sg:phone":"+45 98 33 34 58",
    "sg:postcode":"9280",
    "sg:province":"Danmark",
    "wof:name":"Gudum Forsamlingshus",
    "wof:placetype":"venue"
},
  "geometry": {"coordinates":[10.1014204025,57.0045547485],"type":"Point"}
}