{
  "type": "Feature",
  "properties": {
    "addr:full":"Klingenberg 2, Postboks 1140 5100",
    "addr:housenumber":"2;1140",
    "addr:postcode":"5100",
    "addr:street":"Klingenberg",
    "iso:country":"DK",
    "sg:address":"Klingenberg 2, Postboks 1140",
    "sg:orig_category":"Statslige direktorater og styrelser",
    "sg:phone":"+45 66 12 30 24",
    "sg:postcode":"5100",
    "sg:website":"www.fyensstifts.dk",
    "wof:name":"Fyens Stift",
    "wof:placetype":"venue"
},
  "geometry": {"coordinates":[10.3908996582,55.3960914612],"type":"Point"}
}