{
  "type": "Feature",
  "properties": {
    "addr:full":"Bejstrupvej 127, Bejstrup Fjerritslev Danmark 9690",
    "addr:housenumber":"127",
    "addr:postcode":"9690",
    "addr:street":"Bejstrupvej",
    "iso:country":"DK",
    "sg:address":"Bejstrupvej 127, Bejstrup",
    "sg:city":"Fjerritslev",
    "sg:orig_category":"Maskinstationer",
    "sg:phone":"+45 70 10 54 00",
    "sg:postcode":"9690",
    "sg:province":"Danmark",
    "wof:name":"Bejstrup Maskinstation A/S",
    "wof:placetype":"venue"
},
  "geometry": {"coordinates":[9.2667350769,57.0882301331],"type":"Point"}
}