{
  "type": "Feature",
  "properties": {
    "iso:country":"DK",
    "sg:address":"Fmd.: John Dyrb\u00f8l, Dalstr\u00f8get 8",
    "sg:city":"Haslev",
    "sg:orig_category":"Grundejerforeninger",
    "sg:phone":"+45 56 31 34 94",
    "sg:postcode":"4690",
    "sg:province":"Danmark",
    "wof:name":"\u00c6rtebjergparken grundejerforening",
    "wof:placetype":"venue"
},
  "geometry": {"coordinates":[11.9678049088,55.3230895996],"type":"Point"}
}