{
  "type": "Feature",
  "properties": {
    "addr:full":"\u00d8stergade 2 Ejstrupholm Danmark 7361",
    "addr:housenumber":"2",
    "addr:postcode":"7361",
    "addr:street":"Ostergade",
    "iso:country":"DK",
    "sg:address":"\u00d8stergade 2",
    "sg:city":"Ejstrupholm",
    "sg:orig_category":"Slagter og viktualie",
    "sg:phone":"+45 75 77 20 21",
    "sg:postcode":"7361",
    "sg:province":"Danmark",
    "wof:name":"Ejstrupholm Slagterforretning",
    "wof:placetype":"venue"
},
  "geometry": {"coordinates":[9.2904453278,55.9837837219],"type":"Point"}
}