{
  "type": "Feature",
  "properties": {
    "addr:full":"Sognepr\u00e6st: Aksel Laustsen, Tranemosevej 9, Reerslev Ruds Vedby Danmark 4291",
    "addr:housenumber":"9",
    "addr:postcode":"4291",
    "addr:street":"Aksel;Tranemosevej",
    "iso:country":"DK",
    "sg:address":"Sognepr\u00e6st: Aksel Laustsen, Tranemosevej 9, Reerslev",
    "sg:city":"Ruds Vedby",
    "sg:orig_category":"Kirkesogne",
    "sg:phone":"+45 58 26 20 31",
    "sg:postcode":"4291",
    "sg:province":"Danmark",
    "wof:name":"Reerslev og Buerup sogne",
    "wof:placetype":"venue"
},
  "geometry": {"coordinates":[11.3734693527,55.5409049988],"type":"Point"}
}