{
  "type": "Feature",
  "properties": {
    "addr:full":"K\u00f8benhavnsvej 78 K\u00f8ge Danmark 4600",
    "addr:housenumber":"78",
    "addr:postcode":"4600",
    "addr:street":"Kobenhavnsvej",
    "iso:country":"DK",
    "sg:address":"K\u00f8benhavnsvej 78",
    "sg:city":"K\u00f8ge",
    "sg:orig_category":"Autotransport",
    "sg:phone":"+45 56 66 13 40",
    "sg:postcode":"4600",
    "sg:province":"Danmark",
    "wof:name":"Ole's Autotransport",
    "wof:placetype":"venue"
},
  "geometry": {"coordinates":[12.1814451218,55.4707870483],"type":"Point"}
}