{
  "type": "Feature",
  "properties": {
    "addr:full":"Pr\u00e6sident: Charlotte Mikkelsen, Volstrupvej 2 Hjerm Danmark 7560",
    "addr:housenumber":"2",
    "addr:postcode":"7560",
    "addr:street":"Volstrupvej",
    "iso:country":"DK",
    "sg:address":"Pr\u00e6sident: Charlotte Mikkelsen, Volstrupvej 2",
    "sg:city":"Hjerm",
    "sg:orig_category":"Loger",
    "sg:phone":"+45 97 85 00 87",
    "sg:postcode":"7560",
    "sg:province":"Danmark",
    "wof:name":"Inner Wheel",
    "wof:placetype":"venue"
},
  "geometry": {"coordinates":[8.6395950317,56.4384765625],"type":"Point"}
}