{
  "type": "Feature",
  "properties": {
    "addr:full":"Revninge Bygade 61, Revninge Kerteminde Danmark 5300",
    "addr:housenumber":"61",
    "addr:postcode":"5300",
    "addr:street":"Revninge Bygade",
    "iso:country":"DK",
    "sg:address":"Revninge Bygade 61, Revninge",
    "sg:city":"Kerteminde",
    "sg:orig_category":"Forsamlingshuse",
    "sg:phone":"+45 65 32 18 53",
    "sg:postcode":"5300",
    "sg:province":"Danmark",
    "wof:name":"Revninge Sogneg\u00e5rd",
    "wof:placetype":"venue"
},
  "geometry": {"coordinates":[10.6600999832,55.4506492615],"type":"Point"}
}