{
  "type": "Feature",
  "properties": {
    "addr:full":"Bredegade 19 Slagelse Danmark 4200",
    "addr:housenumber":"19",
    "addr:postcode":"4200",
    "addr:street":"Bredegade",
    "iso:country":"DK",
    "sg:address":"Bredegade 19",
    "sg:city":"Slagelse",
    "sg:orig_category":"Fodterapeuter",
    "sg:phone":"+45 58 53 24 55",
    "sg:postcode":"4200",
    "sg:province":"Danmark",
    "wof:name":"Klinik for fodterapi",
    "wof:placetype":"venue"
},
  "geometry": {"coordinates":[11.3497686386,55.4013557434],"type":"Point"}
}