{
  "type": "Feature",
  "properties": {
    "addr:full":"Tingvejen 57 Kalundborg Danmark 4400",
    "addr:housenumber":"57",
    "addr:postcode":"4400",
    "addr:street":"Tingvejen",
    "iso:country":"DK",
    "sg:address":"Tingvejen 57",
    "sg:city":"Kalundborg",
    "sg:orig_category":"Redningskorps",
    "sg:phone":"+45 40 54 04 11",
    "sg:postcode":"4400",
    "sg:province":"Danmark",
    "wof:name":"Dansk Autohj\u00e6lp",
    "wof:placetype":"venue"
},
  "geometry": {"coordinates":[11.1722784042,55.6641082764],"type":"Point"}
}