{
  "type": "Feature",
  "properties": {
    "addr:full":"Helledivej 69 Vestbjerg Danmark 9380",
    "addr:housenumber":"69",
    "addr:postcode":"9380",
    "addr:street":"Helledivej",
    "iso:country":"DK",
    "sg:address":"Helledivej 69",
    "sg:city":"Vestbjerg",
    "sg:orig_category":"Flytteforretninger",
    "sg:phone":"+45 98 29 88 33",
    "sg:postcode":"9380",
    "sg:province":"Danmark",
    "wof:name":"Knudb\u00f8rges Budcentral",
    "wof:placetype":"venue"
},
  "geometry": {"coordinates":[9.9502153397,57.1292266846],"type":"Point"}
}