{
  "type": "Feature",
  "properties": {
    "addr:full":"Skibbrogade 30 Kalundborg Danmark 4400",
    "addr:housenumber":"30",
    "addr:postcode":"4400",
    "addr:street":"Skibbrogade",
    "iso:country":"DK",
    "sg:address":"Skibbrogade 30",
    "sg:city":"Kalundborg",
    "sg:orig_category":"Fodterapeuter",
    "sg:phone":"+45 59 56 60 07",
    "sg:postcode":"4400",
    "sg:province":"Danmark",
    "sg:website":"www.fodterapeut.dk",
    "wof:name":"Klinik for fodterapi",
    "wof:placetype":"venue"
},
  "geometry": {"coordinates":[11.0865316391,55.679485321],"type":"Point"}
}