{
  "type": "Feature",
  "properties": {
    "addr:full":"Fmd.: Helle Andersen, M\u00e5rh\u00f8j 30 Gedved Danmark 8751",
    "addr:housenumber":"30",
    "addr:postcode":"8751",
    "addr:street":"Maarhoj",
    "iso:country":"DK",
    "sg:address":"Fmd.: Helle Andersen, M\u00e5rh\u00f8j 30",
    "sg:city":"Gedved",
    "sg:orig_category":"Grundejerforeninger",
    "sg:phone":"+45 75 66 56 41",
    "sg:postcode":"8751",
    "sg:province":"Danmark",
    "wof:name":"Grundejerforeningen M\u00e5rh\u00f8j",
    "wof:placetype":"venue"
},
  "geometry": {"coordinates":[9.8441801071,55.9348068237],"type":"Point"}
}