{
  "type": "Feature",
  "properties": {
    "addr:full":"M\u00e5gevej 28 Hvidovre Danmark 2650",
    "addr:housenumber":"28",
    "addr:postcode":"2650",
    "addr:street":"Maagevej",
    "iso:country":"DK",
    "sg:address":"M\u00e5gevej 28",
    "sg:city":"Hvidovre",
    "sg:orig_category":"Glarmestre og glarmagere",
    "sg:phone":"+45 36 78 88 21",
    "sg:postcode":"2650",
    "sg:province":"Danmark",
    "wof:name":"G B C Holiday",
    "wof:placetype":"venue"
},
  "geometry": {"coordinates":[12.469953537,55.6192398071],"type":"Point"}
}