{
  "type": "Feature",
  "properties": {
    "addr:full":"\u00d8stergade 33 Faaborg Danmark 5600",
    "addr:housenumber":"33",
    "addr:postcode":"5600",
    "addr:street":"Ostergade",
    "iso:country":"DK",
    "sg:address":"\u00d8stergade 33",
    "sg:city":"Faaborg",
    "sg:orig_category":"Pizzeriaer",
    "sg:phone":"+45 62 61 00 44",
    "sg:postcode":"5600",
    "sg:province":"Danmark",
    "wof:name":"Palermo Pizza",
    "wof:placetype":"venue"
},
  "geometry": {"coordinates":[10.2460041046,55.0947494507],"type":"Point"}
}