{
  "type": "Feature",
  "properties": {
    "addr:full":"Vongevej 48, Sandvad Jelling Danmark 7300",
    "addr:housenumber":"48",
    "addr:postcode":"7300",
    "addr:street":"Vongevej;Sandvad",
    "iso:country":"DK",
    "sg:address":"Vongevej 48, Sandvad",
    "sg:city":"Jelling",
    "sg:orig_category":"Forsamlingshuse og selskaber",
    "sg:phone":"+45 75 87 30 06",
    "sg:postcode":"7300",
    "sg:province":"Danmark",
    "wof:name":"Sandvad Sogneg\u00e5rd",
    "wof:placetype":"venue"
},
  "geometry": {"coordinates":[9.4184103012,55.7558555603],"type":"Point"}
}