{
  "type": "Feature",
  "properties": {
    "addr:full":"Jels S\u00f8ndergade 10 R\u00f8dding Danmark 6630",
    "addr:housenumber":"10",
    "addr:postcode":"6630",
    "addr:street":"Sondergade",
    "iso:country":"DK",
    "sg:address":"Jels S\u00f8ndergade 10",
    "sg:city":"R\u00f8dding",
    "sg:orig_category":"Malermestre",
    "sg:phone":"+45 74 55 23 14",
    "sg:postcode":"6630",
    "sg:province":"Danmark",
    "wof:name":"Hansen, Jonny",
    "wof:placetype":"venue"
},
  "geometry": {"coordinates":[9.2032499313,55.3558158875],"type":"Point"}
}