{
  "type": "Feature",
  "properties": {
    "iso:country":"DK",
    "sg:address":"Assensvej 4",
    "sg:city":"Slagelse",
    "sg:orig_category":"Genbrugspladser",
    "sg:phone":"+45 58 52 50 45",
    "sg:postcode":"4200",
    "sg:province":"Danmark",
    "wof:name":"Genbrugsstation",
    "wof:placetype":"venue"
},
  "geometry": {"coordinates":[11.3478689194,55.4169273376],"type":"Point"}
}