{
  "type": "Feature",
  "properties": {
    "addr:full":"Bavneh\u00f8j 1, B\u00f8lling Skjern Danmark 6900",
    "addr:housenumber":"1",
    "addr:postcode":"6900",
    "addr:street":"Bavnehoj;Bolling",
    "iso:country":"DK",
    "sg:address":"Bavneh\u00f8j 1, B\u00f8lling",
    "sg:city":"Skjern",
    "sg:orig_category":"Autoreparation og -service",
    "sg:phone":"+45 97 36 81 59",
    "sg:postcode":"6900",
    "sg:province":"Danmark",
    "wof:name":"B\u00f8lling Auto",
    "wof:placetype":"venue"
},
  "geometry": {"coordinates":[8.492972374,55.9485740662],"type":"Point"}
}