{
  "type": "Feature",
  "properties": {
    "iso:country":"DK",
    "sg:address":"Skamstrupvej 43, Skamstrup",
    "sg:city":"M\u00f8rk\u00f8v",
    "sg:orig_category":"Rideudstyr",
    "sg:phone":"+45 21 77 90 08",
    "sg:postcode":"4440",
    "sg:province":"Danmark",
    "sg:website":"www.safir-rideudstyr.dk",
    "wof:name":"Safir Rideudstyr",
    "wof:placetype":"venue"
},
  "geometry": {"coordinates":[11.4997396469,55.6530609131],"type":"Point"}
}