{
  "type": "Feature",
  "properties": {
    "addr:full":"Midtergade 23 Hals Danmark 9370",
    "addr:housenumber":"23",
    "addr:postcode":"9370",
    "addr:street":"Midtergade",
    "iso:country":"DK",
    "sg:address":"Midtergade 23",
    "sg:city":"Hals",
    "sg:orig_category":"Bagere",
    "sg:phone":"+45 98 25 11 02",
    "sg:postcode":"9370",
    "sg:province":"Danmark",
    "wof:name":"Top's Bageri A/S",
    "wof:placetype":"venue"
},
  "geometry": {"coordinates":[10.307226,56.998009],"type":"Point"}
}