{
  "type": "Feature",
  "properties": {
    "addr:full":"Fmd.: Anders Fisker, Olaf Poulsens Alle 2 Fredensborg Danmark 3480",
    "addr:housenumber":"2",
    "addr:postcode":"3480",
    "addr:street":"Anders;Olaf Poulsens Alle",
    "iso:country":"DK",
    "sg:address":"Fmd.: Anders Fisker, Olaf Poulsens Alle 2",
    "sg:city":"Fredensborg",
    "sg:orig_category":"Hobbybetonede foreninger",
    "sg:phone":"+45 48 48 53 00",
    "sg:postcode":"3480",
    "sg:province":"Danmark",
    "wof:name":"S\u00f8rup Havn B\u00e5delav",
    "wof:placetype":"venue"
},
  "geometry": {"coordinates":[12.4070329666,55.9813461304],"type":"Point"}
}