{
  "type": "Feature",
  "properties": {
    "addr:full":"Gullev Byvej 33 Bjerringbro Danmark 8850",
    "addr:housenumber":"33",
    "addr:postcode":"8850",
    "addr:street":"Gullev Byvej",
    "iso:country":"DK",
    "sg:address":"Gullev Byvej 33",
    "sg:city":"Bjerringbro",
    "sg:classifiers":[
        {
            "category":"Professional",
            "subcategory":"Computer Services",
            "type":"Services"
        }
    ],
    "sg:phone":"+45 86 68 18 35",
    "sg:postcode":"8850",
    "sg:province":"Danmark",
    "sg:tags":[
        "edb",
        "-",
        "software"
    ],
    "wof:name":"SC Soft",
    "wof:placetype":"venue"
},
  "geometry": {"coordinates":[9.6820478439,56.3535232544],"type":"Point"}
}