{
  "type": "Feature",
  "properties": {
    "addr:full":"Frederiksberggade 16 K\u00f8benhavn Danmark 1459",
    "addr:housenumber":"16;1459",
    "addr:street":"Frederiksberggade",
    "iso:country":"DK",
    "sg:address":"Frederiksberggade 16",
    "sg:city":"K\u00f8benhavn",
    "sg:orig_category":"Advokater",
    "sg:phone":"+45 33 11 45 45",
    "sg:postcode":"1459",
    "sg:province":"Danmark",
    "wof:name":"Presfeldt, Jan",
    "wof:placetype":"venue"
},
  "geometry": {"coordinates":[12.5700597763,55.6768302917],"type":"Point"}
}