{
  "type": "Feature",
  "properties": {
    "addr:full":"Dalumvej 30, Dalum Odense SV Danmark 5250",
    "addr:housenumber":"30",
    "addr:postcode":"5250",
    "addr:street":"Dalumvej;Dalum",
    "iso:country":"DK",
    "sg:address":"Dalumvej 30, Dalum",
    "sg:city":"Odense SV",
    "sg:orig_category":"Diners transportables",
    "sg:phone":"+45 66 11 59 48",
    "sg:postcode":"5250",
    "sg:province":"Danmark",
    "wof:name":"Kok, Kurt",
    "wof:placetype":"venue"
},
  "geometry": {"coordinates":[10.3153953552,55.3362998962],"type":"Point"}
}