{
  "type": "Feature",
  "properties": {
    "addr:full":"Dronning Margrethes Vej 39 Roskilde Danmark 4000",
    "addr:housenumber":"39",
    "addr:postcode":"4000",
    "addr:street":"Dronning Margrethes Vej",
    "iso:country":"DK",
    "sg:address":"Dronning Margrethes Vej 39",
    "sg:city":"Roskilde",
    "sg:orig_category":"Plejehjem",
    "sg:phone":"+45 46 31 55 30",
    "sg:postcode":"4000",
    "sg:province":"Danmark",
    "wof:name":"Amtsplejestiftelsen",
    "wof:placetype":"venue"
},
  "geometry": {"coordinates":[12.0941257477,55.6428794861],"type":"Point"}
}