{
  "type": "Feature",
  "properties": {
    "addr:full":"Saltv\u00e6rksvej 75 Kastrup Danmark 2770",
    "addr:housenumber":"75",
    "addr:postcode":"2770",
    "addr:street":"Saltvaerksvej",
    "iso:country":"DK",
    "sg:address":"Saltv\u00e6rksvej 75",
    "sg:city":"Kastrup",
    "sg:orig_category":"Grillbarer",
    "sg:phone":"+45 32 51 40 00",
    "sg:postcode":"2770",
    "sg:province":"Danmark",
    "wof:name":"Kastrup Grillen",
    "wof:placetype":"venue"
},
  "geometry": {"coordinates":[12.634595871,55.6372680664],"type":"Point"}
}