{
  "type": "Feature",
  "properties": {
    "iso:country":"DK",
    "sg:address":"Gunhilds Plads 6",
    "sg:city":"Vejle",
    "sg:orig_category":"INGENI\u00c3\u02dcRER",
    "sg:phone":"+45 79 43 53 00",
    "sg:postcode":"7100",
    "sg:province":"Danmark",
    "sg:website":"www.hundsbaek.dk",
    "wof:name":"Hundsb\u00e6k & Henriksen a/s",
    "wof:placetype":"venue"
},
  "geometry": {"coordinates":[9.5359840393,55.71301651],"type":"Point"}
}