{
  "type": "Feature",
  "properties": {
    "iso:country":"DK",
    "sg:address":"Frichsvej 19 ",
    "sg:city":"Silkeborg",
    "sg:classifiers":[
        {
            "category":"Shopping",
            "subcategory":"Clothing, Apparel, & Fashions",
            "type":"Retail Goods"
        }
    ],
    "sg:phone":"+45 86 82 77 11",
    "sg:postcode":"8600",
    "sg:province":"Danmark",
    "sg:tags":[
        "clothes"
    ],
    "wof:name":"OLE FRANDSEN DAMEKONFEKTION A/S",
    "wof:placetype":"venue"
},
  "geometry": {"coordinates":[9.5658950806,56.1958961487],"type":"Point"}
}