{
  "type": "Feature",
  "properties": {
    "addr:full":"Industrivej 1, Hvidbjerg Thyholm Danmark 7790",
    "addr:housenumber":"1",
    "addr:postcode":"7790",
    "addr:street":"Industrivej;Hvidbjerg",
    "iso:country":"DK",
    "sg:address":"Industrivej 1, Hvidbjerg",
    "sg:city":"Thyholm",
    "sg:orig_category":"Korn og foderstoffer",
    "sg:phone":"+45 97 87 10 48",
    "sg:postcode":"7790",
    "sg:province":"Danmark",
    "wof:name":"DLG Limfjord",
    "wof:placetype":"venue"
},
  "geometry": {"coordinates":[8.525765419,56.6507072449],"type":"Point"}
}