{
  "type": "Feature",
  "properties": {
    "addr:full":"Norgeskajen 5 Hirtshals Danmark 9850",
    "addr:housenumber":"5",
    "addr:postcode":"9850",
    "addr:street":"Norgeskajen",
    "iso:country":"DK",
    "sg:address":"Norgeskajen 5",
    "sg:city":"Hirtshals",
    "sg:orig_category":"Fiskeindustri",
    "sg:phone":"+45 98 94 33 77",
    "sg:postcode":"9850",
    "sg:province":"Danmark",
    "wof:name":"Vandkrog Fisk",
    "wof:placetype":"venue"
},
  "geometry": {"coordinates":[9.9645385742,57.5933685303],"type":"Point"}
}