{
  "type": "Feature",
  "properties": {
    "addr:full":"Storegade 20 Lunderskov Danmark 6640",
    "addr:housenumber":"20",
    "addr:postcode":"6640",
    "addr:street":"Storegade",
    "iso:country":"DK",
    "sg:address":"Storegade 20",
    "sg:city":"Lunderskov",
    "sg:classifiers":[
        {
            "category":"Banks & Credit Unions",
            "subcategory":"Bank",
            "type":"Services"
        }
    ],
    "sg:phone":"+45 76 92 32 20",
    "sg:postcode":"6640",
    "sg:province":"Danmark",
    "sg:tags":[
        "banker"
    ],
    "wof:name":"Sydbank",
    "wof:placetype":"venue"
},
  "geometry": {"coordinates":[9.300971,55.479683],"type":"Point"}
}