{
  "type": "Feature",
  "properties": {
    "addr:full":"S\u00f8nderballevej 13 Gudbjerg Danmark 5892",
    "addr:housenumber":"13",
    "addr:postcode":"5892",
    "addr:street":"Sonderballevej",
    "iso:country":"DK",
    "sg:address":"S\u00f8nderballevej 13",
    "sg:city":"Gudbjerg",
    "sg:orig_category":"Musik og sang",
    "sg:phone":"+45 62 25 30 05",
    "sg:postcode":"5892",
    "sg:province":"Danmark",
    "wof:name":"Pedersen, Halvor A.",
    "wof:placetype":"venue"
},
  "geometry": {"coordinates":[10.6638889313,55.1505126953],"type":"Point"}
}