{
  "type": "Feature",
  "properties": {
    "addr:full":"Spodsbjergvej 271, Nr. Longelse Rudk\u00f8bing Danmark 5900",
    "addr:housenumber":"271",
    "addr:postcode":"5900",
    "addr:street":"Spodsbjergvej",
    "iso:country":"DK",
    "sg:address":"Spodsbjergvej 271, Nr. Longelse",
    "sg:city":"Rudk\u00f8bing",
    "sg:orig_category":"Kirker",
    "sg:postcode":"5900",
    "sg:province":"Danmark",
    "wof:name":"Longelse Kirke",
    "wof:placetype":"venue"
},
  "geometry": {"coordinates":[10.7163152695,54.9352607727],"type":"Point"}
}