{
  "type": "Feature",
  "properties": {
    "iso:country":"DK",
    "sg:address":"Havnegade 61",
    "sg:city":"Esbjerg",
    "sg:orig_category":"Revisorer",
    "sg:phone":"+45 75 12 90 88",
    "sg:postcode":"6700",
    "sg:province":"Danmark",
    "wof:name":"Andersen, Flemming Revisionsaktieselskabet",
    "wof:placetype":"venue"
},
  "geometry": {"coordinates":[8.4449129105,55.4656982422],"type":"Point"}
}