{
  "type": "Feature",
  "properties": {
    "addr:full":"Bodenhoffs Plads 4, 3 tv. K\u00f8benhavn Danmark 1430",
    "addr:housenumber":"4 3 tv.",
    "addr:postcode":"1430",
    "addr:street":"Bodenhoffs Plads",
    "iso:country":"DK",
    "sg:address":"Bodenhoffs Plads 4, 3 tv.",
    "sg:city":"K\u00f8benhavn",
    "sg:orig_category":"Psykologer, praktiserende",
    "sg:phone":"+45 32 54 49 26",
    "sg:postcode":"1430",
    "sg:province":"Danmark",
    "wof:name":"Nielsen, Mogens",
    "wof:placetype":"venue"
},
  "geometry": {"coordinates":[12.6016998291,55.6757011414],"type":"Point"}
}