{
  "type": "Feature",
  "properties": {
    "addr:full":"Vintapperbuen 2 Kirke Hyllinge Danmark 4070",
    "addr:housenumber":"2",
    "addr:postcode":"4070",
    "addr:street":"Vintapperbuen",
    "iso:country":"DK",
    "sg:address":"Vintapperbuen 2",
    "sg:city":"Kirke Hyllinge",
    "sg:orig_category":"Engros handel",
    "sg:phone":"+45 46 40 33 98",
    "sg:postcode":"4070",
    "sg:province":"Danmark",
    "wof:name":"Hemmingsen og Jakobsen A/S",
    "wof:placetype":"venue"
},
  "geometry": {"coordinates":[11.887752533,55.7012672424],"type":"Point"}
}