{
  "type": "Feature",
  "properties": {
    "addr:full":"Vinkelvej 2 Sindal Danmark 9870",
    "addr:housenumber":"2",
    "addr:postcode":"9870",
    "addr:street":"Vinkelvej",
    "iso:country":"DK",
    "sg:address":"Vinkelvej 2",
    "sg:city":"Sindal",
    "sg:classifiers":[
        {
            "category":"Utilities",
            "subcategory":"Cable",
            "type":"Services"
        }
    ],
    "sg:phone":"+45 98 93 54 33",
    "sg:postcode":"9870",
    "sg:province":"Danmark",
    "sg:tags":[
        "trapper"
    ],
    "sg:website":"www.sindal-trappen.dk",
    "wof:name":"Sindal Trappen",
    "wof:placetype":"venue"
},
  "geometry": {"coordinates":[10.2027215958,57.4781570435],"type":"Point"}
}