{
  "type": "Feature",
  "properties": {
    "addr:full":"Store Regnegade 12, 2 K\u00f8benhavn Danmark 1110",
    "addr:housenumber":"12 2",
    "addr:postcode":"1110",
    "addr:street":"Store Regnegade",
    "iso:country":"DK",
    "sg:address":"Store Regnegade 12, 2",
    "sg:city":"K\u00f8benhavn",
    "sg:classifiers":[
        {
            "category":"Professional",
            "subcategory":"Computer Services",
            "type":"Services"
        }
    ],
    "sg:phone":"+45 33 32 57 00",
    "sg:postcode":"1110",
    "sg:province":"Danmark",
    "sg:tags":[
        "edb",
        "-",
        "software"
    ],
    "sg:website":"entragroup.com",
    "wof:name":"Entra Financial Software A/S",
    "wof:placetype":"venue"
},
  "geometry": {"coordinates":[12.5845003128,55.6806983948],"type":"Point"}
}