{
  "type": "Feature",
  "properties": {
    "addr:full":"\u00d8stergade 25 Grenaa Danmark 8500",
    "addr:housenumber":"25",
    "addr:postcode":"8500",
    "addr:street":"Ostergade",
    "iso:country":"DK",
    "sg:address":"\u00d8stergade 25",
    "sg:city":"Grenaa",
    "sg:orig_category":"Faglige organisationer og foreninger",
    "sg:phone":"+45 86 32 11 55",
    "sg:postcode":"8500",
    "sg:province":"Danmark",
    "wof:name":"SID",
    "wof:placetype":"venue"
},
  "geometry": {"coordinates":[10.8808431625,56.4136657715],"type":"Point"}
}