{
  "type": "Feature",
  "properties": {
    "addr:full":"K\u00f8bmagergade 9 Nex\u00f8 Danmark 3730",
    "addr:housenumber":"9",
    "addr:postcode":"3730",
    "addr:street":"Kobmagergade",
    "iso:country":"DK",
    "sg:address":"K\u00f8bmagergade 9",
    "sg:city":"Nex\u00f8",
    "sg:orig_category":"Politi",
    "sg:phone":"+45 56 49 14 48",
    "sg:postcode":"3730",
    "sg:province":"Danmark",
    "wof:name":"Nex\u00f8 Politi",
    "wof:placetype":"venue"
},
  "geometry": {"coordinates":[15.1096076965,55.0267219543],"type":"Point"}
}