{
  "type": "Feature",
  "properties": {
    "iso:country":"DK",
    "sg:address":"\u00d8stergade 10",
    "sg:city":"Holstebro",
    "sg:orig_category":"Brugskunst",
    "sg:phone":"+45 96 10 29 10",
    "sg:postcode":"7500",
    "sg:province":"Danmark",
    "wof:name":"S\u00f8e's Trendhouse",
    "wof:placetype":"venue"
},
  "geometry": {"coordinates":[8.61901474,56.358215332],"type":"Point"}
}