{
  "type": "Feature",
  "properties": {
    "addr:full":"Romancevej 37 Herlev Danmark 2730",
    "addr:housenumber":"37",
    "addr:postcode":"2730",
    "addr:street":"Romancevej",
    "iso:country":"DK",
    "sg:address":"Romancevej 37",
    "sg:city":"Herlev",
    "sg:orig_category":"Stilladser",
    "sg:phone":"+45 44 91 59 10",
    "sg:postcode":"2730",
    "sg:province":"Danmark",
    "wof:name":"Herlev Stilladser ApS",
    "wof:placetype":"venue"
},
  "geometry": {"coordinates":[12.4493923187,55.7166595459],"type":"Point"}
}