{
  "type": "Feature",
  "properties": {
    "addr:full":"Retortvej 42 Valby Danmark 2500",
    "addr:housenumber":"42",
    "addr:postcode":"2500",
    "addr:street":"Retortvej",
    "iso:country":"DK",
    "sg:address":"Retortvej 42",
    "sg:city":"Valby",
    "sg:orig_category":"Autoreparation og -service",
    "sg:phone":"+45 36 16 25 00",
    "sg:postcode":"2500",
    "sg:province":"Danmark",
    "wof:name":"E.B. Auto",
    "wof:placetype":"venue"
},
  "geometry": {"coordinates":[12.5018672943,55.653301239],"type":"Point"}
}