{
  "type": "Feature",
  "properties": {
    "addr:full":"Rosenvang 17, Postboks 2 Hornslet Danmark 8543",
    "addr:housenumber":"17;2",
    "addr:postcode":"8543",
    "addr:street":"Rosenvang;Postboks",
    "iso:country":"DK",
    "sg:address":"Rosenvang 17, Postboks 2",
    "sg:city":"Hornslet",
    "sg:orig_category":"Boligselskaber",
    "sg:phone":"+45 87 85 06 10",
    "sg:postcode":"8543",
    "sg:province":"Danmark",
    "wof:name":"Boligforeningen Djursland",
    "wof:placetype":"venue"
},
  "geometry": {"coordinates":[10.3180999756,56.3159866333],"type":"Point"}
}