{
  "type": "Feature",
  "properties": {
    "addr:full":"Aabenraavej 1 A Haderslev Danmark 6100",
    "addr:housenumber":"1 a",
    "addr:postcode":"6100",
    "addr:street":"Aabenraavej",
    "iso:country":"DK",
    "sg:address":"Aabenraavej 1 A",
    "sg:city":"Haderslev",
    "sg:orig_category":"Revisorer",
    "sg:phone":"+45 74 53 42 20",
    "sg:postcode":"6100",
    "sg:province":"Danmark",
    "wof:name":"KJ Revision",
    "wof:placetype":"venue"
},
  "geometry": {"coordinates":[9.4903612137,55.2450294495],"type":"Point"}
}