{
  "type": "Feature",
  "properties": {
    "addr:full":"Elmevej 4, Postboks 49 Jyderup Danmark 4450",
    "addr:housenumber":"4;49",
    "addr:postcode":"4450",
    "addr:street":"Elmevej",
    "iso:country":"DK",
    "sg:address":"Elmevej 4, Postboks 49",
    "sg:city":"Jyderup",
    "sg:orig_category":"Boligselskaber",
    "sg:phone":"+45 59 27 69 96",
    "sg:postcode":"4450",
    "sg:province":"Danmark",
    "wof:name":"Vestsj\u00e6llands Amts Boligselskab",
    "wof:placetype":"venue"
},
  "geometry": {"coordinates":[11.4029512405,55.6602401733],"type":"Point"}
}