{
  "type": "Feature",
  "properties": {
    "addr:full":"Slotsgade 9 Fredensborg Danmark 3480",
    "addr:housenumber":"9",
    "addr:postcode":"3480",
    "addr:street":"Slotsgade",
    "iso:country":"DK",
    "sg:address":"Slotsgade 9",
    "sg:city":"Fredensborg",
    "sg:orig_category":"Museer",
    "sg:phone":"+45 48 48 04 25",
    "sg:postcode":"3480",
    "sg:province":"Danmark",
    "wof:name":"Villa Bournonville",
    "wof:placetype":"venue"
},
  "geometry": {"coordinates":[12.39656353,55.9778556824],"type":"Point"}
}