{
  "type": "Feature",
  "properties": {
    "addr:full":"Fmd.: Bente Hansen, Sejerbyvej 6, Sejerby Sejer\u00f8 Danmark 4592",
    "addr:housenumber":"6",
    "addr:postcode":"4592",
    "addr:street":"Fmd. Bente;Sejerbyvej",
    "iso:country":"DK",
    "sg:address":"Fmd.: Bente Hansen, Sejerbyvej 6, Sejerby",
    "sg:city":"Sejer\u00f8",
    "sg:orig_category":"\u00c3\u02dcvrig fritidsundervisning",
    "sg:phone":"+45 59 59 02 69",
    "sg:postcode":"4592",
    "sg:province":"Danmark",
    "wof:name":"Sejer\u00f8 Husholdningsforening",
    "wof:placetype":"venue"
},
  "geometry": {"coordinates":[11.137257576,55.8811302185],"type":"Point"}
}