{
  "type": "Feature",
  "properties": {
    "addr:full":"S\u00f8g\u00e5rdvej 39 Hejnsvig Danmark 7250",
    "addr:housenumber":"39",
    "addr:postcode":"7250",
    "addr:street":"Sogaardvej",
    "iso:country":"DK",
    "sg:address":"S\u00f8g\u00e5rdvej 39",
    "sg:city":"Hejnsvig",
    "sg:orig_category":"\u00c3\u2020ldreorganisationer og klubber",
    "sg:phone":"+45 75 33 50 93",
    "sg:postcode":"7250",
    "sg:province":"Danmark",
    "wof:name":"Hejnsvig Pensionistforening",
    "wof:placetype":"venue"
},
  "geometry": {"coordinates":[8.9966459274,55.6951141357],"type":"Point"}
}