{
  "type": "Feature",
  "properties": {
    "addr:full":"K\u00f8bingsmarkvej 3 Nordborg Danmark 6430",
    "addr:housenumber":"3",
    "addr:postcode":"6430",
    "addr:street":"Kobingsmarkvej",
    "iso:country":"DK",
    "sg:address":"K\u00f8bingsmarkvej 3",
    "sg:city":"Nordborg",
    "sg:orig_category":"Beslagsmede",
    "sg:postcode":"6430",
    "sg:province":"Danmark",
    "wof:name":"Beslagsmedien",
    "wof:placetype":"venue"
},
  "geometry": {"coordinates":[9.7403936386,55.061340332],"type":"Point"}
}