{
  "type": "Feature",
  "properties": {
    "addr:full":"Haarlem Alle 49 Drag\u00f8r Danmark 2791",
    "addr:housenumber":"49",
    "addr:postcode":"2791",
    "addr:street":"Haarlem Alle",
    "iso:country":"DK",
    "sg:address":"Haarlem Alle 49",
    "sg:city":"Drag\u00f8r",
    "sg:orig_category":"Regnskabsassistance",
    "sg:phone":"+45 26 23 86 12",
    "sg:postcode":"2791",
    "sg:province":"Danmark",
    "wof:name":"\u00d8ens Regnskab",
    "wof:placetype":"venue"
},
  "geometry": {"coordinates":[4.642250061,52.3805618286],"type":"Point"}
}