{
  "type": "Feature",
  "properties": {
    "addr:full":"v/ Ole Andersen, Spangsmosevej 30 B, Broballe Nordborg Danmark 6430",
    "addr:housenumber":"30 b",
    "addr:postcode":"6430",
    "addr:street":"Spangsmosevej",
    "iso:country":"DK",
    "sg:address":"v/ Ole Andersen, Spangsmosevej 30 B, Broballe",
    "sg:city":"Nordborg",
    "sg:orig_category":"Musik og sang",
    "sg:phone":"+45 74 49 05 19",
    "sg:postcode":"6430",
    "sg:province":"Danmark",
    "wof:name":"Kirkekorene",
    "wof:placetype":"venue"
},
  "geometry": {"coordinates":[9.7496232986,55.0542755127],"type":"Point"}
}