{
  "type": "Feature",
  "properties": {
    "addr:full":"Frederiksberg 1 D Sveb\u00f8lle Danmark 4470",
    "addr:housenumber":"1 d",
    "addr:postcode":"4470",
    "addr:street":"Frederiksberg;Danmark",
    "iso:country":"DK",
    "sg:address":"Frederiksberg 1 D",
    "sg:city":"Sveb\u00f8lle",
    "sg:orig_category":"Varmeforsyning",
    "sg:phone":"+45 59 29 46 04",
    "sg:postcode":"4470",
    "sg:province":"Danmark",
    "wof:name":"Sveb\u00f8lle - Viskinge Fjernvarmeselskab A.m.b.A.",
    "wof:placetype":"venue"
},
  "geometry": {"coordinates":[11.2961053848,55.6523666382],"type":"Point"}
}