{
  "type": "Feature",
  "properties": {
    "iso:country":"DK",
    "sg:address":"Dybk\u00e6rvej 1, Stubb\u00e6k",
    "sg:city":"Aabenraa",
    "sg:orig_category":"Genbrugspladser",
    "sg:postcode":"6200",
    "sg:province":"Danmark",
    "wof:name":"Mini-Milj\u00f8station i Stubb\u00e6k",
    "wof:placetype":"venue"
},
  "geometry": {"coordinates":[9.4213867188,55.0449562073],"type":"Point"}
}