{
  "type": "Feature",
  "properties": {
    "addr:full":"N\u00e6rumv\u00e6nge 1 N\u00e6rum Danmark 2850",
    "addr:housenumber":"1",
    "addr:postcode":"2850",
    "addr:street":"Naerumvaenge",
    "iso:country":"DK",
    "sg:address":"N\u00e6rumv\u00e6nge 1",
    "sg:city":"N\u00e6rum",
    "sg:orig_category":"Grillbarer",
    "sg:phone":"+45 45 80 36 21",
    "sg:postcode":"2850",
    "sg:province":"Danmark",
    "wof:name":"Torvets P\u00f8lsebod",
    "wof:placetype":"venue"
},
  "geometry": {"coordinates":[-89.99810791020001,38.1321372986],"type":"Point"}
}