{
  "type": "Feature",
  "properties": {
    "addr:full":"Abildgaardsvej 96 Virum DK-2830",
    "addr:housenumber":"96",
    "addr:postcode":"dk-2830",
    "addr:street":"Abildgaardsvej",
    "iso:country":"DK",
    "sg:address":"Abildgaardsvej 96",
    "sg:city":"Virum",
    "sg:classifiers":[
        {
            "category":"Professional",
            "subcategory":"Computer Services",
            "type":"Services"
        }
    ],
    "sg:postcode":"DK-2830",
    "sg:website":"http://www.webcrm.com",
    "wof:name":"webCRM",
    "wof:placetype":"venue"
},
  "geometry": {"coordinates":[12.470372,55.782596],"type":"Point"}
}