{
  "type": "Feature",
  "properties": {
    "iso:country":"DK",
    "sg:address":"Storegade 16-18",
    "sg:city":"Nordborg",
    "sg:orig_category":"Voksenuddannelsescentre",
    "sg:phone":"+45 74 49 13 09",
    "sg:postcode":"6430",
    "sg:province":"Danmark",
    "wof:name":"VUC Nordborg afd.",
    "wof:placetype":"venue"
},
  "geometry": {"coordinates":[9.7434072495,55.0575942993],"type":"Point"}
}