{
  "type": "Feature",
  "properties": {
    "addr:full":"Skolegade 12 R Valby Danmark 2500",
    "addr:housenumber":"12 r",
    "addr:postcode":"2500",
    "addr:street":"Skolegade",
    "iso:country":"DK",
    "sg:address":"Skolegade 12 R",
    "sg:city":"Valby",
    "sg:classifiers":[
        {
            "category":"Communications",
            "type":"Services"
        }
    ],
    "sg:phone":"+45 36 45 80 80",
    "sg:postcode":"2500",
    "sg:province":"Danmark",
    "sg:tags":[
        "og",
        "tv",
        "radio"
    ],
    "wof:name":"System Audio A/S",
    "wof:placetype":"venue"
},
  "geometry": {"coordinates":[12.5170240402,55.6659469604],"type":"Point"}
}