{
  "type": "Feature",
  "properties": {
    "addr:full":"Haderslevgade 7 \u00c5rhus C Danmark 8000",
    "addr:housenumber":"7",
    "addr:postcode":"8000",
    "addr:street":"Haderslevgade",
    "iso:country":"DK",
    "sg:address":"Haderslevgade 7",
    "sg:city":"\u00c5rhus C",
    "sg:orig_category":"Cykler",
    "sg:phone":"+45 86 14 31 36",
    "sg:postcode":"8000",
    "sg:province":"Danmark",
    "wof:name":"Stoffer's Cykel og Knallertservice",
    "wof:placetype":"venue"
},
  "geometry": {"coordinates":[10.1862373352,56.1449890137],"type":"Point"}
}