{
  "type": "Feature",
  "properties": {
    "addr:full":"Fmd.: Niels Stylsvig S\u00f8rensen, Smedevej 3, Klintebjerg Otterup Danmark 5450",
    "addr:housenumber":"3",
    "addr:postcode":"5450",
    "addr:street":"Sorensen Smedevej;Klintebjerg",
    "iso:country":"DK",
    "sg:address":"Fmd.: Niels Stylsvig S\u00f8rensen, Smedevej 3, Klintebjerg",
    "sg:city":"Otterup",
    "sg:orig_category":"Havne",
    "sg:postcode":"5450",
    "sg:province":"Danmark",
    "wof:name":"Klintebjerg Lystb\u00e5dehavn",
    "wof:placetype":"venue"
},
  "geometry": {"coordinates":[10.4545049667,55.5641746521],"type":"Point"}
}