{
  "type": "Feature",
  "properties": {
    "addr:full":"Fmd.: Bente Aalling, Gyvelvej 73 Gesten Danmark 6621",
    "addr:housenumber":"73",
    "addr:postcode":"6621",
    "addr:street":"Fmd. Bente;Gyvelvej",
    "iso:country":"DK",
    "sg:address":"Fmd.: Bente Aalling, Gyvelvej 73",
    "sg:city":"Gesten",
    "sg:orig_category":"Spejderkorps",
    "sg:phone":"+45 75 55 74 97",
    "sg:postcode":"6621",
    "sg:province":"Danmark",
    "wof:name":"Det Danske Spejderkorps Gesten Gruppe",
    "wof:placetype":"venue"
},
  "geometry": {"coordinates":[9.2085962296,55.52551651],"type":"Point"}
}