{
  "type": "Feature",
  "properties": {
    "addr:full":"Mellemgade 10 Faaborg Danmark 5600",
    "addr:housenumber":"10",
    "addr:postcode":"5600",
    "addr:street":"Mellemgade",
    "iso:country":"DK",
    "sg:address":"Mellemgade 10",
    "sg:city":"Faaborg",
    "sg:orig_category":"Ure og urmagere",
    "sg:phone":"+45 62 61 01 15",
    "sg:postcode":"5600",
    "sg:province":"Danmark",
    "wof:name":"Ansbjerg, Poul Krog",
    "wof:placetype":"venue"
},
  "geometry": {"coordinates":[10.2414522171,55.0960350037],"type":"Point"}
}