{
  "type": "Feature",
  "properties": {
    "iso:country":"DK",
    "sg:address":"Fmd.: Geert S\u00f8rensen, Tj\u00f8rneg\u00e5rdsparken 14",
    "sg:city":"Trustrup",
    "sg:orig_category":"Hobbybetonede foreninger",
    "sg:phone":"+45 86 33 44 75",
    "sg:postcode":"8570",
    "sg:province":"Danmark",
    "wof:name":"Fodslaw Gren\u00e5",
    "wof:placetype":"venue"
},
  "geometry": {"coordinates":[10.7718954086,56.3482666016],"type":"Point"}
}