{
  "type": "Feature",
  "properties": {
    "addr:full":"Park Alle 25 Ikast Danmark 7430",
    "addr:housenumber":"25",
    "addr:postcode":"7430",
    "addr:street":"Park Alle",
    "iso:country":"DK",
    "sg:address":"Park Alle 25",
    "sg:city":"Ikast",
    "sg:orig_category":"Rejsebureauer",
    "sg:phone":"+45 97 25 25 24",
    "sg:postcode":"7430",
    "sg:province":"Danmark",
    "sg:website":"www.osteuropa-rejser.dk",
    "wof:name":"\u00d8steuropa Rejser",
    "wof:placetype":"venue"
},
  "geometry": {"coordinates":[9.1636581421,56.1423454285],"type":"Point"}
}