{
  "type": "Feature",
  "properties": {
    "addr:full":"Gentoftegade 34 Gentofte Danmark 2820",
    "addr:housenumber":"34",
    "addr:postcode":"2820",
    "addr:street":"Gentoftegade",
    "iso:country":"DK",
    "sg:address":"Gentoftegade 34",
    "sg:city":"Gentofte",
    "sg:orig_category":"Videobutikker og -klubber",
    "sg:phone":"+45 39 68 12 10",
    "sg:postcode":"2820",
    "sg:province":"Danmark",
    "wof:name":"Play Time Video",
    "wof:placetype":"venue"
},
  "geometry": {"coordinates":[12.5408658981,55.7489624023],"type":"Point"}
}