{
  "type": "Feature",
  "properties": {
    "addr:full":"Nyholms Alle 7 R\u00f8dovre Danmark 2610",
    "addr:housenumber":"7",
    "addr:postcode":"2610",
    "addr:street":"Nyholms Alle",
    "iso:country":"DK",
    "sg:address":"Nyholms Alle 7",
    "sg:city":"R\u00f8dovre",
    "sg:orig_category":"Bogtrykkerier",
    "sg:phone":"+45 36 41 09 41",
    "sg:postcode":"2610",
    "sg:province":"Danmark",
    "wof:name":"Lyhnes Specialtryk ApS",
    "wof:placetype":"venue"
},
  "geometry": {"coordinates":[10.6992139816,61.1027755737],"type":"Point"}
}