{
  "type": "Feature",
  "properties": {
    "iso:country":"DK",
    "sg:address":"Langelinie 2",
    "sg:city":"Vejle",
    "sg:orig_category":"Marskandisere",
    "sg:phone":"+45 75 72 19 60",
    "sg:postcode":"7100",
    "sg:province":"Danmark",
    "wof:name":"Basse's Kram",
    "wof:placetype":"venue"
},
  "geometry": {"coordinates":[9.5388307571,55.7073516846],"type":"Point"}
}