{
  "type": "Feature",
  "properties": {
    "iso:country":"DK",
    "sg:address":"Funder Skolevej 8",
    "sg:city":"Silkeborg",
    "sg:orig_category":"Cykler",
    "sg:phone":"+45 86 85 15 06",
    "sg:postcode":"8600",
    "sg:province":"Danmark",
    "wof:name":"Cykelreparationsv\u00e6rkstedet",
    "wof:placetype":"venue"
},
  "geometry": {"coordinates":[9.4769163132,56.1432228088],"type":"Point"}
}