{
  "type": "Feature",
  "properties": {
    "addr:full":"L\u00e5sbygade 25 Kolding Danmark 6000",
    "addr:housenumber":"25",
    "addr:postcode":"6000",
    "addr:street":"Laasbygade",
    "iso:country":"DK",
    "sg:address":"L\u00e5sbygade 25",
    "sg:city":"Kolding",
    "sg:orig_category":"Fotografer",
    "sg:phone":"+45 75 52 96 22",
    "sg:postcode":"6000",
    "sg:province":"Danmark",
    "wof:name":"Studio 14",
    "wof:placetype":"venue"
},
  "geometry": {"coordinates":[9.4701833725,55.4923095703],"type":"Point"}
}