{
  "type": "Feature",
  "properties": {
    "iso:country":"DK",
    "sg:address":"Sprangade 8 POSTBOKS 30 ",
    "sg:city":"Hasle",
    "sg:classifiers":[
        {
            "category":"Farming",
            "subcategory":"Livestock Farm",
            "type":"Manufacturing & Wholesale Goods"
        }
    ],
    "sg:phone":"+45 56 96 53 11",
    "sg:postcode":"3790",
    "sg:province":"Danmark",
    "sg:tags":[
        "agriculture"
    ],
    "wof:name":"A. ESPERSEN A/S",
    "wof:placetype":"venue"
},
  "geometry": {"coordinates":[14.7065896988,55.1830863953],"type":"Point"}
}