{
  "type": "Feature",
  "properties": {
    "addr:full":"Strandvej 57 Strandby Danmark 9970",
    "addr:housenumber":"57",
    "addr:postcode":"9970",
    "addr:street":"Strandvej",
    "iso:country":"DK",
    "sg:address":"Strandvej 57",
    "sg:city":"Strandby",
    "sg:classifiers":[
        {
            "category":"Professional",
            "subcategory":"Art Services",
            "type":"Services"
        }
    ],
    "sg:phone":"+45 98 48 00 99",
    "sg:postcode":"9970",
    "sg:province":"Danmark",
    "sg:tags":[
        "blomster"
    ],
    "wof:name":"Nordjysk B\u00e5ndtryk",
    "wof:placetype":"venue"
},
  "geometry": {"coordinates":[10.49588,57.494049],"type":"Point"}
}