{
  "type": "Feature",
  "properties": {
    "addr:full":"Skovkrogen 7 Ullerslev Danmark 5540",
    "addr:housenumber":"7",
    "addr:postcode":"5540",
    "addr:street":"Skovkrogen",
    "iso:country":"DK",
    "sg:address":"Skovkrogen 7",
    "sg:city":"Ullerslev",
    "sg:orig_category":"Flytteforretninger",
    "sg:phone":"+45 65 35 13 99",
    "sg:postcode":"5540",
    "sg:province":"Danmark",
    "wof:name":"Nyborg, M\u00f8beltransporten",
    "wof:placetype":"venue"
},
  "geometry": {"coordinates":[10.6619186401,55.3620872498],"type":"Point"}
}