{
  "type": "Feature",
  "properties": {
    "addr:full":"Skelb\u00e6kvej 1 Fjenneslev Danmark 4173",
    "addr:housenumber":"1",
    "addr:postcode":"4173",
    "addr:street":"Skelbaekvej",
    "iso:country":"DK",
    "sg:address":"Skelb\u00e6kvej 1",
    "sg:city":"Fjenneslev",
    "sg:orig_category":"El-motorer",
    "sg:phone":"+45 57 80 95 00",
    "sg:postcode":"4173",
    "sg:province":"Danmark",
    "wof:name":"Del Con ApS",
    "wof:placetype":"venue"
},
  "geometry": {"coordinates":[11.6519145966,55.4302597046],"type":"Point"}
}