{
  "type": "Feature",
  "properties": {
    "addr:full":"Nordre Frihavnsgade 50 K\u00f8benhavn \u00d8 Danmark 2100",
    "addr:housenumber":"50",
    "addr:postcode":"2100",
    "addr:street":"Nordre Frihavnsgade;O",
    "iso:country":"DK",
    "sg:address":"Nordre Frihavnsgade 50",
    "sg:city":"K\u00f8benhavn \u00d8",
    "sg:orig_category":"Farvehandlere",
    "sg:phone":"+45 35 26 85 09",
    "sg:postcode":"2100",
    "sg:province":"Danmark",
    "sg:website":"www.roverkob.dk",
    "wof:name":"R\u00d8VERK\u00d8B",
    "wof:placetype":"venue"
},
  "geometry": {"coordinates":[12.035369873,60.8038711548],"type":"Point"}
}