{
  "type": "Feature",
  "properties": {
    "addr:full":"S\u00f8nderskovvej 35, Halling Hornslet Danmark 8543",
    "addr:housenumber":"35",
    "addr:postcode":"8543",
    "addr:street":"Sonderskovvej",
    "iso:country":"DK",
    "sg:address":"S\u00f8nderskovvej 35, Halling",
    "sg:city":"Hornslet",
    "sg:orig_category":"Autoforhandlere",
    "sg:phone":"+45 86 99 93 56",
    "sg:postcode":"8543",
    "sg:province":"Danmark",
    "wof:name":"Halling Autohandel ApS",
    "wof:placetype":"venue"
},
  "geometry": {"coordinates":[10.3180999756,56.3159866333],"type":"Point"}
}