{
  "type": "Feature",
  "properties": {
    "addr:full":"N\u00f8rregade 11 Vejle Danmark 7100",
    "addr:housenumber":"11",
    "addr:postcode":"7100",
    "addr:street":"Norregade",
    "iso:country":"DK",
    "sg:address":"N\u00f8rregade 11",
    "sg:city":"Vejle",
    "sg:orig_category":"Arkitekter",
    "sg:phone":"+45 75 83 86 33",
    "sg:postcode":"7100",
    "sg:province":"Danmark",
    "wof:name":"S\u00f8holm Arkitekterne m.a.a.",
    "wof:placetype":"venue"
},
  "geometry": {"coordinates":[9.5338230133,55.7101631165],"type":"Point"}
}