{
  "type": "Feature",
  "properties": {
    "addr:full":"Sdr. F\u00e6lledvej 7 Auning Danmark 8963",
    "addr:housenumber":"7",
    "addr:postcode":"8963",
    "addr:street":"Faelledvej",
    "iso:country":"DK",
    "sg:address":"Sdr. F\u00e6lledvej 7",
    "sg:city":"Auning",
    "sg:orig_category":"Skolefritidsordninger",
    "sg:phone":"+45 86 48 44 07",
    "sg:postcode":"8963",
    "sg:province":"Danmark",
    "wof:name":"Auning skoles skolefritidsordning",
    "wof:placetype":"venue"
},
  "geometry": {"coordinates":[10.3770084381,56.430065155],"type":"Point"}
}