{
  "type": "Feature",
  "properties": {
    "iso:country":"DK",
    "sg:address":"S\u00f8ndergade 30, Hornsyld",
    "sg:city":"Hornsyld",
    "sg:orig_category":"Autoophug",
    "sg:phone":"+45 75 68 71 91",
    "sg:postcode":"8783",
    "sg:province":"Danmark",
    "wof:name":"Ford Ophug",
    "wof:placetype":"venue"
},
  "geometry": {"coordinates":[9.8611288071,55.7560806274],"type":"Point"}
}