{
  "type": "Feature",
  "properties": {
    "addr:full":"Bl\u00e5hegnet 9 Greve Danmark 2670",
    "addr:housenumber":"9",
    "addr:postcode":"2670",
    "addr:street":"Blaahegnet",
    "iso:country":"DK",
    "sg:address":"Bl\u00e5hegnet 9",
    "sg:city":"Greve",
    "sg:orig_category":"Grafiske tegnestuer",
    "sg:phone":"+45 43 61 03 14",
    "sg:postcode":"2670",
    "sg:province":"Danmark",
    "sg:website":"www.hassdesign.dk",
    "wof:name":"HassDesign",
    "wof:placetype":"venue"
},
  "geometry": {"coordinates":[12.2632923126,55.5794944763],"type":"Point"}
}