{
  "type": "Feature",
  "properties": {
    "addr:full":"Nordre Fasanvej 45 Frederiksberg Danmark 2000",
    "addr:housenumber":"45",
    "addr:postcode":"2000",
    "addr:street":"Nordre Fasanvej",
    "iso:country":"DK",
    "sg:address":"Nordre Fasanvej 45",
    "sg:city":"Frederiksberg",
    "sg:orig_category":"Autoreparation og -service",
    "sg:phone":"+45 38 86 20 60",
    "sg:postcode":"2000",
    "sg:province":"Danmark",
    "wof:name":"Creutzberg's Autov\u00e6rksted",
    "wof:placetype":"venue"
},
  "geometry": {"coordinates":[12.5241680145,55.6840209961],"type":"Point"}
}