{
  "type": "Feature",
  "properties": {
    "iso:country":"DK",
    "sg:address":"Mariagervej 47",
    "sg:city":"Randers",
    "sg:orig_category":"Sparekasser",
    "sg:phone":"+45 86 43 22 11",
    "sg:postcode":"8900",
    "sg:province":"Danmark",
    "wof:name":"Sparekassen Kronjylland Nordre afd.",
    "wof:placetype":"venue"
},
  "geometry": {"coordinates":[10.0309066772,56.4698562622],"type":"Point"}
}