{
  "type": "Feature",
  "properties": {
    "addr:full":"Virringvej 88, Virring Skanderborg Danmark 8660",
    "addr:housenumber":"88",
    "addr:postcode":"8660",
    "addr:street":"Virringvej",
    "iso:country":"DK",
    "sg:address":"Virringvej 88, Virring",
    "sg:city":"Skanderborg",
    "sg:orig_category":"Psykologer, praktiserende",
    "sg:phone":"+45 86 92 80 67",
    "sg:postcode":"8660",
    "sg:province":"Danmark",
    "wof:name":"Siggaard, Gerda",
    "wof:placetype":"venue"
},
  "geometry": {"coordinates":[9.929974556,56.0380249023],"type":"Point"}
}