{
  "type": "Feature",
  "properties": {
    "addr:full":"Herningvej 50, Gedhus Karup Danmark 7470",
    "addr:housenumber":"50",
    "addr:postcode":"7470",
    "addr:street":"Herningvej;Gedhus Karup Danmark",
    "iso:country":"DK",
    "sg:address":"Herningvej 50, Gedhus",
    "sg:city":"Karup",
    "sg:orig_category":"Museer",
    "sg:phone":"+45 97 10 15 50",
    "sg:postcode":"7470",
    "sg:province":"Danmark",
    "wof:name":"Museet Flyvestationen Karup",
    "wof:placetype":"venue"
},
  "geometry": {"coordinates":[9.2525548935,56.3398017883],"type":"Point"}
}