{
  "type": "Feature",
  "properties": {
    "iso:country":"DK",
    "sg:address":"N\u00e5lemagervej 6",
    "sg:city":"Aulum",
    "sg:orig_category":"Kontorartikler",
    "sg:phone":"+45 97 47 36 15",
    "sg:postcode":"7490",
    "sg:province":"Danmark",
    "wof:name":"3S Scandinavian Supplier Service",
    "wof:placetype":"venue"
},
  "geometry": {"coordinates":[8.779009819,56.2650489807],"type":"Point"}
}