{
  "type": "Feature",
  "properties": {
    "addr:full":"K\u00e6rvej 10 St\u00f8vring Danmark 9530",
    "addr:housenumber":"10",
    "addr:postcode":"9530",
    "addr:street":"Kaervej",
    "iso:country":"DK",
    "sg:address":"K\u00e6rvej 10",
    "sg:city":"St\u00f8vring",
    "sg:orig_category":"Systuer",
    "sg:phone":"+45 98 37 33 82",
    "sg:postcode":"9530",
    "sg:province":"Danmark",
    "wof:name":"Dys Desing og Sy",
    "wof:placetype":"venue"
},
  "geometry": {"coordinates":[-103.46831512449999,34.4049034119],"type":"Point"}
}