{
  "type": "Feature",
  "properties": {
    "iso:country":"DK",
    "sg:address":"H\u00f8jbov\u00e6nge 29",
    "sg:city":"Store Heddinge",
    "sg:orig_category":"Boligselskaber",
    "sg:phone":"+45 56 50 25 61",
    "sg:postcode":"4660",
    "sg:province":"Danmark",
    "wof:name":"Store-Heddinge Andelsboligforening",
    "wof:placetype":"venue"
},
  "geometry": {"coordinates":[12.3895797729,55.3113174438],"type":"Point"}
}