{
  "type": "Feature",
  "properties": {
    "iso:country":"DK",
    "sg:address":"Ulvevej 13",
    "sg:city":"Havdrup",
    "sg:orig_category":"Belysning",
    "sg:phone":"+45 46 18 60 33",
    "sg:postcode":"4622",
    "sg:province":"Danmark",
    "wof:name":"Zarp Danmark ApS",
    "wof:placetype":"venue"
},
  "geometry": {"coordinates":[12.119946,55.550037],"type":"Point"}
}