{
  "type": "Feature",
  "properties": {
    "addr:full":"Roustvej 50 Varde Danmark 6800",
    "addr:housenumber":"50",
    "addr:postcode":"6800",
    "addr:street":"Roustvej",
    "iso:country":"DK",
    "sg:address":"Roustvej 50",
    "sg:city":"Varde",
    "sg:orig_category":"Boblebade",
    "sg:phone":"+45 75 22 46 88",
    "sg:postcode":"6800",
    "sg:province":"Danmark",
    "sg:website":"www.hydro-air.com",
    "wof:name":"HydroAir - DK",
    "wof:placetype":"venue"
},
  "geometry": {"coordinates":[8.4995622635,55.6097640991],"type":"Point"}
}