{
  "type": "Feature",
  "properties": {
    "iso:country":"DK",
    "sg:address":"Struerv. 91 ",
    "sg:city":"Holstebro",
    "sg:classifiers":[
        {
            "category":"Professional",
            "subcategory":"Business Services",
            "type":"Services"
        }
    ],
    "sg:phone":"+45 96 12 16 00",
    "sg:postcode":"7500",
    "sg:province":"Danmark",
    "sg:tags":[
        "advice"
    ],
    "wof:name":"HOLSTEBRO P\u00c6DAGOGSEMNARIUM",
    "wof:placetype":"venue"
},
  "geometry": {"coordinates":[8.6202583313,56.3625221252],"type":"Point"}
}