{
  "type": "Feature",
  "properties": {
    "iso:country":"DK",
    "sg:address":"Rugv\u00e6nget 2",
    "sg:city":"Taastrup",
    "sg:orig_category":"\u00c3\u2020ldrecentre",
    "sg:phone":"+45 43 35 25 42",
    "sg:postcode":"2630",
    "sg:province":"Danmark",
    "wof:name":"\u00c6ldrecentret Kl\u00f8verhuset",
    "wof:placetype":"venue"
},
  "geometry": {"coordinates":[12.3020896912,55.6506767273],"type":"Point"}
}