{
  "type": "Feature",
  "properties": {
    "addr:full":"Gr\u00f8nl\u00f8kke Alle 11 Tranbjerg Danmark 8310",
    "addr:housenumber":"11",
    "addr:postcode":"8310",
    "addr:street":"Gronlokke Alle",
    "iso:country":"DK",
    "sg:address":"Gr\u00f8nl\u00f8kke Alle 11",
    "sg:city":"Tranbjerg",
    "sg:orig_category":"Fritidshjem",
    "sg:phone":"+45 86 29 56 03",
    "sg:postcode":"8310",
    "sg:province":"Danmark",
    "wof:name":"Gr\u00f8nl\u00f8kke Alle, Fritidshjem",
    "wof:placetype":"venue"
},
  "geometry": {"coordinates":[10.1221866608,56.0949363708],"type":"Point"}
}