{
  "type": "Feature",
  "properties": {
    "addr:full":"Ulbjerggade 23 Nordborg Danmark 6430",
    "addr:housenumber":"23",
    "addr:postcode":"6430",
    "addr:street":"Ulbjerggade",
    "iso:country":"DK",
    "sg:address":"Ulbjerggade 23",
    "sg:city":"Nordborg",
    "sg:orig_category":"Blomsterhandlere",
    "sg:phone":"+45 74 45 14 44",
    "sg:postcode":"6430",
    "sg:province":"Danmark",
    "wof:name":"Randi's Blomster & Planter",
    "wof:placetype":"venue"
},
  "geometry": {"coordinates":[9.7401132584,55.0564422607],"type":"Point"}
}