{
  "type": "Feature",
  "properties": {
    "addr:full":"Tv\u00e6rgade 17 Silkeborg Danmark 8600",
    "addr:housenumber":"17",
    "addr:postcode":"8600",
    "addr:street":"Tvaergade",
    "iso:country":"DK",
    "sg:address":"Tv\u00e6rgade 17",
    "sg:city":"Silkeborg",
    "sg:orig_category":"Arkitekter",
    "sg:phone":"+45 86 82 10 88",
    "sg:postcode":"8600",
    "sg:province":"Danmark",
    "sg:website":"www.arkitekthuset.dk",
    "wof:name":"Arkitekthuset A/S",
    "wof:placetype":"venue"
},
  "geometry": {"coordinates":[9.5481500626,56.1674499512],"type":"Point"}
}