{
  "type": "Feature",
  "properties": {
    "iso:country":"DK",
    "sg:address":"Fmd.: Ren\u00e9 Petersen, Lillemarken 10",
    "sg:city":"Harpelunde",
    "sg:orig_category":"Spejderkorps",
    "sg:phone":"+45 54 93 15 55",
    "sg:postcode":"4912",
    "sg:province":"Danmark",
    "wof:name":"KFUM-spejderne, Ravnsborg gruppe",
    "wof:placetype":"venue"
},
  "geometry": {"coordinates":[11.0865898132,54.8770065308],"type":"Point"}
}