{
  "type": "Feature",
  "properties": {
    "iso:country":"DK",
    "sg:address":"Lyngageren 31, Svogerslev",
    "sg:city":"Roskilde",
    "sg:orig_category":"Grusgrave",
    "sg:phone":"+45 46 38 39 09",
    "sg:postcode":"4000",
    "sg:province":"Danmark",
    "wof:name":"Dansk Grusindustri A/S",
    "wof:placetype":"venue"
},
  "geometry": {"coordinates":[12.0909376144,55.6404838562],"type":"Point"}
}