{
  "type": "Feature",
  "properties": {
    "addr:full":"Skolevej 50 Hesselager Danmark 5874",
    "addr:housenumber":"50",
    "addr:postcode":"5874",
    "addr:street":"Skolevej",
    "iso:country":"DK",
    "sg:address":"Skolevej 50",
    "sg:city":"Hesselager",
    "sg:orig_category":"Skolefritidsordninger",
    "sg:phone":"+45 63 25 15 90",
    "sg:postcode":"5874",
    "sg:province":"Danmark",
    "wof:name":"Skolefritidsordningen v/ Hesselager Skole",
    "wof:placetype":"venue"
},
  "geometry": {"coordinates":[10.7495450974,55.1805648804],"type":"Point"}
}