{
  "type": "Feature",
  "properties": {
    "addr:full":"v/ Valter Jensen, Munkerisvej 21, 1. tv. Odense M Danmark 5230",
    "addr:housenumber":"21 1 tv.",
    "addr:postcode":"5230",
    "addr:street":"Munkerisvej",
    "iso:country":"DK",
    "sg:address":"v/ Valter Jensen, Munkerisvej 21, 1. tv.",
    "sg:city":"Odense M",
    "sg:orig_category":"Faglige organisationer og -foreninger",
    "sg:phone":"+45 66 12 85 21",
    "sg:postcode":"5230",
    "sg:province":"Danmark",
    "wof:name":"Provins-Skr\u00e6dderlauget",
    "wof:placetype":"venue"
},
  "geometry": {"coordinates":[10.3966598511,55.3816184998],"type":"Point"}
}