{
  "type": "Feature",
  "properties": {
    "addr:full":"K\u00f8bmagergade 27 Fredericia Danmark 7000",
    "addr:housenumber":"27",
    "addr:postcode":"7000",
    "addr:street":"Kobmagergade",
    "iso:country":"DK",
    "sg:address":"K\u00f8bmagergade 27",
    "sg:city":"Fredericia",
    "sg:orig_category":"EDB - udstyr",
    "sg:phone":"+45 75 91 44 34",
    "sg:postcode":"7000",
    "sg:province":"Danmark",
    "wof:name":"LB Datatek A/S",
    "wof:placetype":"venue"
},
  "geometry": {"coordinates":[9.7593803406,55.5679092407],"type":"Point"}
}