{
  "type": "Feature",
  "properties": {
    "addr:full":"Torvet 1 Kjellerup Danmark 8620",
    "addr:housenumber":"1",
    "addr:postcode":"8620",
    "addr:street":"Torvet",
    "iso:country":"DK",
    "sg:address":"Torvet 1",
    "sg:city":"Kjellerup",
    "sg:orig_category":"Cafeterier",
    "sg:phone":"+45 86 88 32 44",
    "sg:postcode":"8620",
    "sg:province":"Danmark",
    "wof:name":"Torvegrillen",
    "wof:placetype":"venue"
},
  "geometry": {"coordinates":[9.4306507111,56.2881622314],"type":"Point"}
}