{
  "type": "Feature",
  "properties": {
    "addr:full":"Ryes M\u00f8llevej 15 B Haderslev Danmark 6100",
    "addr:housenumber":"15 b",
    "addr:postcode":"6100",
    "addr:street":"Mollevej",
    "iso:country":"DK",
    "sg:address":"Ryes M\u00f8llevej 15 B",
    "sg:city":"Haderslev",
    "sg:orig_category":"Arbejdsformidling",
    "sg:phone":"+45 74 22 21 41",
    "sg:postcode":"6100",
    "sg:province":"Danmark",
    "wof:name":"Arbejdsmarked Ryes M\u00f8llevej",
    "wof:placetype":"venue"
},
  "geometry": {"coordinates":[9.4921684265,55.2443237305],"type":"Point"}
}