{
  "type": "Feature",
  "properties": {
    "iso:country":"DK",
    "sg:address":"Gr\u00f8nlandsvej 96",
    "sg:city":"Vejle",
    "sg:orig_category":"Betonelementer",
    "sg:phone":"+45 75 83 01 11",
    "sg:postcode":"7100",
    "sg:province":"Danmark",
    "wof:name":"Centrum P\u00e6le A/S",
    "wof:placetype":"venue"
},
  "geometry": {"coordinates":[9.529947,55.677895],"type":"Point"}
}