{
  "type": "Feature",
  "properties": {
    "addr:full":"\u00c6blegrenen 37 Odense S\u00d8 Danmark 5220",
    "addr:housenumber":"37",
    "addr:postcode":"5220",
    "addr:street":"Aeblegrenen",
    "iso:country":"DK",
    "sg:address":"\u00c6blegrenen 37",
    "sg:city":"Odense S\u00d8",
    "sg:orig_category":"Homeparties",
    "sg:phone":"+45 65 93 51 53",
    "sg:postcode":"5220",
    "sg:province":"Danmark",
    "wof:name":"Nielsen, Verner",
    "wof:placetype":"venue"
},
  "geometry": {"coordinates":[10.4477815628,55.3814926147],"type":"Point"}
}