{
  "type": "Feature",
  "properties": {
    "addr:full":"Byplanvej 105, Postboks 16 9100",
    "addr:housenumber":"105;16",
    "addr:postcode":"9100",
    "addr:street":"Byplanvej",
    "iso:country":"DK",
    "sg:address":"Byplanvej 105, Postboks 16",
    "sg:classifiers":[
        {
            "category":"Communications",
            "type":"Services"
        }
    ],
    "sg:phone":"+45 98 14 75 11",
    "sg:postcode":"9100",
    "sg:tags":[
        "radio-",
        "og",
        "tv-stationer"
    ],
    "wof:name":"LUMI Radio",
    "wof:placetype":"venue"
},
  "geometry": {"coordinates":[9.9162597656,57.0493583679],"type":"Point"}
}