{
  "type": "Feature",
  "properties": {
    "addr:full":"Gren\u00e5vej 51 Randers Danmark 8900",
    "addr:housenumber":"51",
    "addr:postcode":"8900",
    "addr:street":"Grenaavej",
    "iso:country":"DK",
    "sg:address":"Gren\u00e5vej 51",
    "sg:city":"Randers",
    "sg:orig_category":"Autoforhandlere",
    "sg:phone":"+45 86 43 13 66",
    "sg:postcode":"8900",
    "sg:province":"Danmark",
    "wof:name":"H. C. Autocenter A/S - SAAB",
    "wof:placetype":"venue"
},
  "geometry": {"coordinates":[10.0577669144,56.4500770569],"type":"Point"}
}