{
  "type": "Feature",
  "properties": {
    "addr:full":"v/ Svend Andersen, Skolelodden 7 Tisvildeleje Danmark 3220",
    "addr:housenumber":"7",
    "addr:postcode":"3220",
    "addr:street":"Skolelodden",
    "iso:country":"DK",
    "sg:address":"v/ Svend Andersen, Skolelodden 7",
    "sg:city":"Tisvildeleje",
    "sg:orig_category":"Grundejerforeninger",
    "sg:phone":"+45 48 70 82 23",
    "sg:postcode":"3220",
    "sg:province":"Danmark",
    "wof:name":"Skolelodden Grundejerforening",
    "wof:placetype":"venue"
},
  "geometry": {"coordinates":[12.0764846802,56.0589904785],"type":"Point"}
}