{
  "type": "Feature",
  "properties": {
    "addr:full":"Akt\u00e6ons Alle 5 Hvidovre Danmark 2650",
    "addr:housenumber":"5",
    "addr:postcode":"2650",
    "addr:street":"Aktaeons Alle",
    "iso:country":"DK",
    "sg:address":"Akt\u00e6ons Alle 5",
    "sg:city":"Hvidovre",
    "sg:orig_category":"Elektro",
    "sg:phone":"+45 36 78 51 52",
    "sg:postcode":"2650",
    "sg:province":"Danmark",
    "wof:name":"Jugodan",
    "wof:placetype":"venue"
},
  "geometry": {"coordinates":[12.476773262,55.6318244934],"type":"Point"}
}