{
  "type": "Feature",
  "properties": {
    "addr:full":"N\u00e5rupvej 15 Gjern Danmark 8883",
    "addr:housenumber":"15",
    "addr:postcode":"8883",
    "addr:street":"Naarupvej",
    "iso:country":"DK",
    "sg:address":"N\u00e5rupvej 15",
    "sg:city":"Gjern",
    "sg:classifiers":[
        {
            "category":"Taxi",
            "type":"Transportation"
        }
    ],
    "sg:phone":"+45 86 87 50 97",
    "sg:postcode":"8883",
    "sg:province":"Danmark",
    "wof:name":"Gjern Taxi og Turistfart",
    "wof:placetype":"venue"
},
  "geometry": {"coordinates":[9.7657814026,56.247013092],"type":"Point"}
}