{
  "type": "Feature",
  "properties": {
    "addr:full":"Havnealle 37 Horsens Danmark 8700",
    "addr:housenumber":"37",
    "addr:postcode":"8700",
    "addr:street":"Havnealle",
    "iso:country":"DK",
    "sg:address":"Havnealle 37",
    "sg:city":"Horsens",
    "sg:orig_category":"Pizzeriaer",
    "sg:phone":"+45 75 60 17 60",
    "sg:postcode":"8700",
    "sg:province":"Danmark",
    "wof:name":"Pizza Expressen",
    "wof:placetype":"venue"
},
  "geometry": {"coordinates":[9.857334137,55.8598594666],"type":"Point"}
}