{
  "type": "Feature",
  "properties": {
    "addr:full":"N\u00f8rregade 32 \u00c5rhus C Danmark 8000",
    "addr:housenumber":"32",
    "addr:postcode":"8000",
    "addr:street":"Norregade",
    "iso:country":"DK",
    "sg:address":"N\u00f8rregade 32",
    "sg:city":"\u00c5rhus C",
    "sg:orig_category":"Farve og tapet",
    "sg:phone":"+45 86 13 64 99",
    "sg:postcode":"8000",
    "sg:province":"Danmark",
    "sg:website":"www.paintstore.dk",
    "wof:name":"Paint Store",
    "wof:placetype":"venue"
},
  "geometry": {"coordinates":[4.717400074,49.7588005066],"type":"Point"}
}