{
  "type": "Feature",
  "properties": {
    "addr:full":"Albanigade 39 Odense C Danmark 5000",
    "addr:housenumber":"39",
    "addr:postcode":"5000",
    "addr:street":"Albanigade",
    "iso:country":"DK",
    "sg:address":"Albanigade 39",
    "sg:city":"Odense C",
    "sg:orig_category":"Farve og tapet",
    "sg:phone":"+45 66 14 22 57",
    "sg:postcode":"5000",
    "sg:province":"Danmark",
    "wof:name":"Farve & Tapet Centret",
    "wof:placetype":"venue"
},
  "geometry": {"coordinates":[10.3955974579,55.3931427002],"type":"Point"}
}