{
  "type": "Feature",
  "properties": {
    "addr:full":"Kystvej 55 Aabenraa Danmark 6200",
    "addr:housenumber":"55",
    "addr:postcode":"6200",
    "addr:street":"Kystvej",
    "iso:country":"DK",
    "sg:address":"Kystvej 55",
    "sg:city":"Aabenraa",
    "sg:classifiers":[
        {
            "category":"Restaurant",
            "type":"Food & Drink"
        }
    ],
    "sg:phone":"+45 74 62 66 84",
    "sg:postcode":"6200",
    "sg:province":"Danmark",
    "wof:name":"Sejlclubben, Restaurant",
    "wof:placetype":"venue"
},
  "geometry": {"coordinates":[9.4215574265,55.0354194641],"type":"Point"}
}