{
  "type": "Feature",
  "properties": {
    "addr:full":"Oventoften 22 Gedved Danmark 8751",
    "addr:housenumber":"22",
    "addr:postcode":"8751",
    "addr:street":"Oventoften",
    "iso:country":"DK",
    "sg:address":"Oventoften 22",
    "sg:city":"Gedved",
    "sg:orig_category":"Reklame",
    "sg:phone":"+45 75 66 56 45",
    "sg:postcode":"8751",
    "sg:province":"Danmark",
    "wof:name":"Grafisk Profil",
    "wof:placetype":"venue"
},
  "geometry": {"coordinates":[9.8472070694,55.92760849],"type":"Point"}
}