{
  "type": "Feature",
  "properties": {
    "addr:full":"Lerbjergvej 1 B Hundested Danmark 3390",
    "addr:housenumber":"1 b",
    "addr:postcode":"3390",
    "addr:street":"Lerbjergvej",
    "iso:country":"DK",
    "sg:address":"Lerbjergvej 1 B",
    "sg:city":"Hundested",
    "sg:orig_category":"Tandklinikker, Kommunale",
    "sg:phone":"+45 47 93 77 41",
    "sg:postcode":"3390",
    "sg:province":"Danmark",
    "wof:name":"Lerbjergskolens tandklinik",
    "wof:placetype":"venue"
},
  "geometry": {"coordinates":[11.8680086136,55.9649963379],"type":"Point"}
}