{
  "type": "Feature",
  "properties": {
    "addr:full":"K\u00f8gevej 24 - 26 Ringsted Danmark 4100",
    "addr:housenumber":"24 26",
    "addr:postcode":"4100",
    "addr:street":"Kogevej",
    "iso:country":"DK",
    "sg:address":"K\u00f8gevej 24 - 26",
    "sg:city":"Ringsted",
    "sg:classifiers":[
        {
            "category":"Restaurant",
            "type":"Food & Drink"
        }
    ],
    "sg:phone":"+45 57 67 00 75",
    "sg:postcode":"4100",
    "sg:province":"Danmark",
    "wof:name":"Shangrila",
    "wof:placetype":"venue"
},
  "geometry": {"coordinates":[11.7996587753,55.4428367615],"type":"Point"}
}