{
  "type": "Feature",
  "properties": {
    "addr:full":"Frederikssundsvej 128 C Br\u00f8nsh\u00f8j Danmark 2700",
    "addr:housenumber":"128 c",
    "addr:postcode":"2700",
    "addr:street":"Frederikssundsvej",
    "iso:country":"DK",
    "sg:address":"Frederikssundsvej 128 C",
    "sg:city":"Br\u00f8nsh\u00f8j",
    "sg:orig_category":"Ejendomsservice",
    "sg:phone":"+45 38 28 73 76",
    "sg:postcode":"2700",
    "sg:province":"Danmark",
    "sg:website":"www.erhvervsastrologi.dk",
    "wof:name":"K.B. Service",
    "wof:placetype":"venue"
},
  "geometry": {"coordinates":[-65.6866531372,-23.1981296539],"type":"Point"}
}