{
  "type": "Feature",
  "properties": {
    "iso:country":"DK",
    "sg:address":"Vorbjergbakken 12",
    "sg:city":"Risskov",
    "sg:orig_category":"Malermestre",
    "sg:phone":"+45 86 21 21 73",
    "sg:postcode":"8240",
    "sg:province":"Danmark",
    "wof:name":"Vejlby Maler- og Beregnerfirma",
    "wof:placetype":"venue"
},
  "geometry": {"coordinates":[10.2303323746,56.2008934021],"type":"Point"}
}