{
  "type": "Feature",
  "properties": {
    "addr:full":"F\u00e5borgvej 28, Sallinge Ringe Danmark 5750",
    "addr:housenumber":"28",
    "addr:postcode":"5750",
    "addr:street":"Faaborgvej;Sallinge",
    "iso:country":"DK",
    "sg:address":"F\u00e5borgvej 28, Sallinge",
    "sg:city":"Ringe",
    "sg:orig_category":"Analyseinstitutter",
    "sg:phone":"+45 62 64 19 21",
    "sg:postcode":"5750",
    "sg:province":"Danmark",
    "wof:name":"Bregneh\u00f8jgaard A/S",
    "wof:placetype":"venue"
},
  "geometry": {"coordinates":[10.4781074524,55.2356643677],"type":"Point"}
}