{
  "type": "Feature",
  "properties": {
    "addr:full":"v/ Karin Gade Dahl, J H Schmidts Vej 42 Vojens Danmark 6500",
    "addr:housenumber":"42",
    "addr:postcode":"6500",
    "addr:street":"Gade;J H Schmidts Vej",
    "iso:country":"DK",
    "sg:address":"v/ Karin Gade Dahl, J H Schmidts Vej 42",
    "sg:city":"Vojens",
    "sg:orig_category":"Ungdomsklubber",
    "sg:phone":"+45 74 54 06 76",
    "sg:postcode":"6500",
    "sg:province":"Danmark",
    "wof:name":"Over Jerstal Ungdomsklub",
    "wof:placetype":"venue"
},
  "geometry": {"coordinates":[9.2987146378,55.2457237244],"type":"Point"}
}