{
  "type": "Feature",
  "properties": {
    "addr:full":"Frijsenborgvej 5, Veri Center Risskov Danmark 8240",
    "addr:housenumber":"5",
    "addr:postcode":"8240",
    "addr:street":"Frijsenborgvej",
    "iso:country":"DK",
    "sg:address":"Frijsenborgvej 5, Veri Center",
    "sg:city":"Risskov",
    "sg:classifiers":[
        {
            "category":"Banks & Credit Unions",
            "subcategory":"Bank",
            "type":"Services"
        }
    ],
    "sg:phone":"+45 87 42 61 70",
    "sg:postcode":"8240",
    "sg:province":"Danmark",
    "sg:tags":[
        "banker"
    ],
    "sg:website":"www.danskebank.dk",
    "wof:name":"Danske Bank",
    "wof:placetype":"venue"
},
  "geometry": {"coordinates":[10.2244901657,56.1874389648],"type":"Point"}
}