{
  "type": "Feature",
  "properties": {
    "addr:full":"Bakkevej 1 Kolding Danmark 6000",
    "addr:housenumber":"1",
    "addr:postcode":"6000",
    "addr:street":"Bakkevej",
    "iso:country":"DK",
    "sg:address":"Bakkevej 1",
    "sg:city":"Kolding",
    "sg:orig_category":"Kollegier",
    "sg:postcode":"6000",
    "sg:province":"Danmark",
    "wof:name":"Kolding Nordre Kollegium",
    "wof:placetype":"venue"
},
  "geometry": {"coordinates":[9.4645586014,55.4961433411],"type":"Point"}
}