{
  "type": "Feature",
  "properties": {
    "addr:full":"S\u00f8ndergade 3 Randers Danmark 8900",
    "addr:housenumber":"3",
    "addr:postcode":"8900",
    "addr:street":"Sondergade",
    "iso:country":"DK",
    "sg:address":"S\u00f8ndergade 3",
    "sg:city":"Randers",
    "sg:orig_category":"Mobiltelefoner",
    "sg:phone":"+45 86 40 91 00",
    "sg:postcode":"8900",
    "sg:province":"Danmark",
    "wof:name":"Unitalk A/S",
    "wof:placetype":"venue"
},
  "geometry": {"coordinates":[10.0391025543,56.4573402405],"type":"Point"}
}