{
  "type": "Feature",
  "properties": {
    "addr:full":"Industrivej 3 A Jyderup Danmark 4450",
    "addr:housenumber":"3 a",
    "addr:postcode":"4450",
    "addr:street":"Industrivej",
    "iso:country":"DK",
    "sg:address":"Industrivej 3 A",
    "sg:city":"Jyderup",
    "sg:classifiers":[
        {
            "category":"Taxi",
            "type":"Transportation"
        }
    ],
    "sg:phone":"+45 59 27 63 24",
    "sg:postcode":"4450",
    "sg:province":"Danmark",
    "wof:name":"Radiobilen",
    "wof:placetype":"venue"
},
  "geometry": {"coordinates":[11.4114542007,55.6601333618],"type":"Point"}
}