{
  "type": "Feature",
  "properties": {
    "addr:full":"Anholtvej 2 Hobro Danmark 9500",
    "addr:housenumber":"2",
    "addr:postcode":"9500",
    "addr:street":"Anholtvej",
    "iso:country":"DK",
    "sg:address":"Anholtvej 2",
    "sg:city":"Hobro",
    "sg:orig_category":"EDB - udstyr",
    "sg:phone":"+45 98 51 03 88",
    "sg:postcode":"9500",
    "sg:province":"Danmark",
    "sg:website":"www.trigetang.dk",
    "wof:name":"Trige & Tang",
    "wof:placetype":"venue"
},
  "geometry": {"coordinates":[9.7946596146,56.6382789612],"type":"Point"}
}