{
  "type": "Feature",
  "properties": {
    "addr:full":"Herningvej 98 Silkeborg Danmark 8600",
    "addr:housenumber":"98",
    "addr:postcode":"8600",
    "addr:street":"Herningvej",
    "iso:country":"DK",
    "sg:address":"Herningvej 98",
    "sg:city":"Silkeborg",
    "sg:orig_category":"Web- og Internetdesign",
    "sg:phone":"+45 86 82 30 08",
    "sg:postcode":"8600",
    "sg:province":"Danmark",
    "wof:name":"Intens Marketing ApS",
    "wof:placetype":"venue"
},
  "geometry": {"coordinates":[9.5058441162,56.1552238464],"type":"Point"}
}