{
  "type": "Feature",
  "properties": {
    "addr:full":"Skibbrogade 17 Kalundborg Danmark 4400",
    "addr:housenumber":"17",
    "addr:postcode":"4400",
    "addr:street":"Skibbrogade",
    "iso:country":"DK",
    "sg:address":"Skibbrogade 17",
    "sg:city":"Kalundborg",
    "sg:orig_category":"Cykler",
    "sg:phone":"+45 59 51 03 06",
    "sg:postcode":"4400",
    "sg:province":"Danmark",
    "wof:name":"Madsen Cykler",
    "wof:placetype":"venue"
},
  "geometry": {"coordinates":[11.0855102539,55.6786804199],"type":"Point"}
}