{
  "type": "Feature",
  "properties": {
    "addr:full":"Lille Tingvej 11 Aars Danmark 9600",
    "addr:housenumber":"11",
    "addr:postcode":"9600",
    "addr:street":"Lille Tingvej",
    "iso:country":"DK",
    "sg:address":"Lille Tingvej 11",
    "sg:city":"Aars",
    "sg:orig_category":"Fagforbund og fagforeninger",
    "sg:phone":"+45 98 62 40 62",
    "sg:postcode":"9600",
    "sg:province":"Danmark",
    "wof:name":"N\u00e6rings- og Nydelsemiddelarbejder Forbundet",
    "wof:placetype":"venue"
},
  "geometry": {"coordinates":[9.5115118027,56.8052253723],"type":"Point"}
}