{
  "type": "Feature",
  "properties": {
    "addr:full":"Skolebakken 2 Kolind Danmark 8560",
    "addr:housenumber":"2",
    "addr:postcode":"8560",
    "addr:street":"Skolebakken",
    "iso:country":"DK",
    "sg:address":"Skolebakken 2",
    "sg:city":"Kolind",
    "sg:orig_category":"Skolefritidsordninger",
    "sg:phone":"+45 86 39 22 39",
    "sg:postcode":"8560",
    "sg:province":"Danmark",
    "wof:name":"Kolind Centralskoles Fritidsordning",
    "wof:placetype":"venue"
},
  "geometry": {"coordinates":[10.582857132,56.3608779907],"type":"Point"}
}