{
  "type": "Feature",
  "properties": {
    "addr:full":"Sognepr\u00e6st: Jan Brogaard (K/B), Gudum Bygade 6, Gudum Storvorde Danmark 9280",
    "addr:housenumber":"6",
    "addr:postcode":"9280",
    "addr:street":"Jan;Gudum Bygade;Gudum",
    "iso:country":"DK",
    "sg:address":"Sognepr\u00e6st: Jan Brogaard (K/B), Gudum Bygade 6, Gudum",
    "sg:city":"Storvorde",
    "sg:orig_category":"Kirkesogne",
    "sg:phone":"+45 98 33 31 57",
    "sg:postcode":"9280",
    "sg:province":"Danmark",
    "wof:name":"Gudum og Lillevorde Sogne",
    "wof:placetype":"venue"
},
  "geometry": {"coordinates":[10.1014204025,57.0045547485],"type":"Point"}
}