{
  "type": "Feature",
  "properties": {
    "addr:full":"Fmd.: Ivan Vium, B\u00f8geparken 5 Kongens Lyngby Danmark 2800",
    "addr:housenumber":"5",
    "addr:postcode":"2800",
    "addr:street":"Bogeparken",
    "iso:country":"DK",
    "sg:address":"Fmd.: Ivan Vium, B\u00f8geparken 5",
    "sg:city":"Kongens Lyngby",
    "sg:orig_category":"Kulturelle foreninger",
    "sg:phone":"+45 45 93 65 75",
    "sg:postcode":"2800",
    "sg:province":"Danmark",
    "wof:name":"Foreningen Norden, S\u00f8ller\u00f8d Afdeling",
    "wof:placetype":"venue"
},
  "geometry": {"coordinates":[12.5368299484,55.7949905396],"type":"Point"}
}