{
  "type": "Feature",
  "properties": {
    "addr:full":"Overgade 23 Ebeltoft Danmark 8400",
    "addr:housenumber":"23",
    "addr:postcode":"8400",
    "addr:street":"Overgade",
    "iso:country":"DK",
    "sg:address":"Overgade 23",
    "sg:city":"Ebeltoft",
    "sg:orig_category":"Bodegaer",
    "sg:phone":"+45 86 34 37 97",
    "sg:postcode":"8400",
    "sg:province":"Danmark",
    "wof:name":"Sk\u00e6ve Bar, Den",
    "wof:placetype":"venue"
},
  "geometry": {"coordinates":[10.6777849197,56.1966781616],"type":"Point"}
}