{
  "type": "Feature",
  "properties": {
    "addr:full":"Bredgade 32 Kalundborg Danmark 4400",
    "addr:housenumber":"32",
    "addr:postcode":"4400",
    "addr:street":"Bredgade",
    "iso:country":"DK",
    "sg:address":"Bredgade 32",
    "sg:city":"Kalundborg",
    "sg:orig_category":"Medborgerhuse",
    "sg:phone":"+45 59 51 70 38",
    "sg:postcode":"4400",
    "sg:province":"Danmark",
    "wof:name":"Kalundborg Medborgerhus",
    "wof:placetype":"venue"
},
  "geometry": {"coordinates":[11.0905704498,55.679058075],"type":"Point"}
}