{
  "type": "Feature",
  "properties": {
    "addr:full":"H\u00e5ndv\u00e6rkervej 36 A Hjallerup Danmark 9320",
    "addr:housenumber":"36 a",
    "addr:postcode":"9320",
    "addr:street":"Haandvaerkervej",
    "iso:country":"DK",
    "sg:address":"H\u00e5ndv\u00e6rkervej 36 A",
    "sg:city":"Hjallerup",
    "sg:orig_category":"Forsikringer",
    "sg:phone":"+45 98 28 33 22",
    "sg:postcode":"9320",
    "sg:province":"Danmark",
    "wof:name":"Hjallerup Assurance",
    "wof:placetype":"venue"
},
  "geometry": {"coordinates":[10.1444702148,57.1677742004],"type":"Point"}
}