{
  "type": "Feature",
  "properties": {
    "addr:full":"F\u00e5rupvej 38 Jelling Danmark 7300",
    "addr:housenumber":"38",
    "addr:postcode":"7300",
    "addr:street":"Faarupvej",
    "iso:country":"DK",
    "sg:address":"F\u00e5rupvej 38",
    "sg:city":"Jelling",
    "sg:orig_category":"Autoforhandlere",
    "sg:phone":"+45 75 87 12 63",
    "sg:postcode":"7300",
    "sg:province":"Danmark",
    "sg:website":"www.autohjornet-jelling.dk",
    "wof:name":"Autohj\u00f8rnet",
    "wof:placetype":"venue"
},
  "geometry": {"coordinates":[9.4133062363,55.7403717041],"type":"Point"}
}