{
  "type": "Feature",
  "properties": {
    "addr:full":"Nordre Fasanvej 57-59 Frederiksberg Danmark 2000",
    "addr:postcode":"57-59;2000",
    "addr:street":"Nordre Fasanvej",
    "iso:country":"DK",
    "sg:address":"Nordre Fasanvej 57-59",
    "sg:city":"Frederiksberg",
    "sg:orig_category":"Offentlige sygehuse",
    "sg:phone":"+45 38 16 38 16",
    "sg:postcode":"2000",
    "sg:province":"Danmark",
    "wof:name":"Frederiksberg Hospital./H:S Hovedstadens Sygehusf\u00e6llesskab",
    "wof:placetype":"venue"
},
  "geometry": {"coordinates":[12.5254688263,55.6856651306],"type":"Point"}
}