{
  "type": "Feature",
  "properties": {
    "addr:full":"Stovbakken 4, Kastrup M\u00f8rke Danmark 8544",
    "addr:housenumber":"4",
    "addr:postcode":"8544",
    "addr:street":"Stovbakken",
    "iso:country":"DK",
    "sg:address":"Stovbakken 4, Kastrup",
    "sg:city":"M\u00f8rke",
    "sg:orig_category":"Musik- og sangundervisning",
    "sg:phone":"+45 86 99 71 55",
    "sg:postcode":"8544",
    "sg:province":"Danmark",
    "wof:name":"Ernst, Lotte",
    "wof:placetype":"venue"
},
  "geometry": {"coordinates":[10.2458581924,56.3858413696],"type":"Point"}
}