{
  "type": "Feature",
  "properties": {
    "iso:country":"DK",
    "sg:address":"Vig Hovedgade 16",
    "sg:city":"Vig",
    "sg:classifiers":[
        {
            "category":"Restaurant",
            "type":"Food & Drink"
        }
    ],
    "sg:phone":"+45 59 36 22 32",
    "sg:postcode":"4560",
    "sg:province":"Danmark",
    "wof:name":"Hot Pot",
    "wof:placetype":"venue"
},
  "geometry": {"coordinates":[-82.79159545900001,39.2505378723],"type":"Point"}
}