{
  "type": "Feature",
  "properties": {
    "addr:full":"Fmd.: Egon Kragh, M\u00f8llel\u00f8kken 6 Them Danmark 8653",
    "addr:housenumber":"6",
    "addr:postcode":"8653",
    "addr:street":"Mollelokken",
    "iso:country":"DK",
    "sg:address":"Fmd.: Egon Kragh, M\u00f8llel\u00f8kken 6",
    "sg:city":"Them",
    "sg:orig_category":"Spejderkorps",
    "sg:phone":"+45 86 84 74 33",
    "sg:postcode":"8653",
    "sg:province":"Danmark",
    "wof:name":"FDF, Silkeborg gamle Drenge",
    "wof:placetype":"venue"
},
  "geometry": {"coordinates":[9.5489425659,56.0950088501],"type":"Point"}
}