{
  "type": "Feature",
  "properties": {
    "iso:country":"DK",
    "sg:address":"Kastanie Alle 4",
    "sg:city":"Engesvang",
    "sg:orig_category":"Oliefyr og service",
    "sg:phone":"+45 86 86 57 68",
    "sg:postcode":"7442",
    "sg:province":"Danmark",
    "wof:name":"Midtjysk Olie & VVS Service",
    "wof:placetype":"venue"
},
  "geometry": {"coordinates":[9.3522901535,56.1704750061],"type":"Point"}
}