{
  "type": "Feature",
  "properties": {
    "iso:country":"DK",
    "sg:address":"Industrivej 10 ",
    "sg:city":"Vamdrup",
    "sg:classifiers":[
        {
            "category":"Parking",
            "subcategory":"Lot",
            "type":"Transportation"
        }
    ],
    "sg:phone":"+45 75 58 32 22",
    "sg:postcode":"6580",
    "sg:province":"Danmark",
    "sg:tags":[
        "transport",
        "road"
    ],
    "wof:name":"VAMDRUP SPECIALTRANSPORT APS",
    "wof:placetype":"venue"
},
  "geometry": {"coordinates":[9.2922172546,55.4287910461],"type":"Point"}
}