{
  "type": "Feature",
  "properties": {
    "iso:country":"DK",
    "sg:address":"Vestergade 14",
    "sg:city":"Give",
    "sg:orig_category":"Solcentre",
    "sg:phone":"+45 75 73 52 00",
    "sg:postcode":"7323",
    "sg:province":"Danmark",
    "wof:name":"Byens f\u00f8rende Solcenter",
    "wof:placetype":"venue"
},
  "geometry": {"coordinates":[9.2355184555,55.8446617126],"type":"Point"}
}