{
  "type": "Feature",
  "properties": {
    "addr:full":"Holmedal 28, Voerladeg\u00e5rd Skanderborg Danmark 8660",
    "addr:housenumber":"28",
    "addr:postcode":"8660",
    "addr:street":"Holmedal",
    "iso:country":"DK",
    "sg:address":"Holmedal 28, Voerladeg\u00e5rd",
    "sg:city":"Skanderborg",
    "sg:orig_category":"Slagter og viktualie",
    "sg:phone":"+45 75 78 20 40",
    "sg:postcode":"8660",
    "sg:province":"Danmark",
    "wof:name":"Voerladeg\u00e5rd Slagteri",
    "wof:placetype":"venue"
},
  "geometry": {"coordinates":[9.929974556,56.0380249023],"type":"Point"}
}