{
  "type": "Feature",
  "properties": {
    "addr:full":"Lille Havdrupvej 6, Gl. Havdrup Havdrup Danmark 4622",
    "addr:housenumber":"6",
    "addr:postcode":"4622",
    "addr:street":"Lille Havdrupvej;Gl.",
    "iso:country":"DK",
    "sg:address":"Lille Havdrupvej 6, Gl. Havdrup",
    "sg:city":"Havdrup",
    "sg:orig_category":"INGENI\u00c3\u02dcRER",
    "sg:phone":"+45 46 18 64 00",
    "sg:postcode":"4622",
    "sg:province":"Danmark",
    "wof:name":"Bivi-Byg Aps",
    "wof:placetype":"venue"
},
  "geometry": {"coordinates":[12.1158895493,55.5443534851],"type":"Point"}
}