{
  "type": "Feature",
  "properties": {
    "addr:full":"Christiansborggade 1 K\u00f8benhavn Danmark 1558",
    "addr:housenumber":"1;1558",
    "addr:street":"Christiansborggade",
    "iso:country":"DK",
    "sg:address":"Christiansborggade 1",
    "sg:city":"K\u00f8benhavn",
    "sg:classifiers":[
        {
            "category":"Communications",
            "type":"Services"
        }
    ],
    "sg:phone":"+45 33 32 90 66",
    "sg:postcode":"1558",
    "sg:province":"Danmark",
    "sg:tags":[
        "og",
        "tv",
        "radio"
    ],
    "sg:website":"www.bfe.dk",
    "wof:name":"BFE-Leverand\u00f8rforeningen for Telecom",
    "wof:placetype":"venue"
},
  "geometry": {"coordinates":[12.5781002045,55.6712989807],"type":"Point"}
}