{
  "type": "Feature",
  "properties": {
    "addr:full":"M\u00f8llergade 66 Svendborg Danmark 5700",
    "addr:housenumber":"66",
    "addr:postcode":"5700",
    "addr:street":"Mollergade",
    "iso:country":"DK",
    "sg:address":"M\u00f8llergade 66",
    "sg:city":"Svendborg",
    "sg:orig_category":"Antikvariater",
    "sg:phone":"+45 62 21 31 48",
    "sg:postcode":"5700",
    "sg:province":"Danmark",
    "wof:name":"\u00c6sel\u00f8ret",
    "wof:placetype":"venue"
},
  "geometry": {"coordinates":[10.6112346649,55.0620994568],"type":"Point"}
}