{
  "type": "Feature",
  "properties": {
    "addr:full":"Skolevej 7 Lemvig Danmark 7620",
    "addr:housenumber":"7",
    "addr:postcode":"7620",
    "addr:street":"Skolevej",
    "iso:country":"DK",
    "sg:address":"Skolevej 7",
    "sg:city":"Lemvig",
    "sg:orig_category":"Handicapboliger",
    "sg:phone":"+45 97 82 33 22",
    "sg:postcode":"7620",
    "sg:province":"Danmark",
    "wof:name":"Tj\u00f8rnebo",
    "wof:placetype":"venue"
},
  "geometry": {"coordinates":[8.3031873703,56.5429496765],"type":"Point"}
}