{
  "type": "Feature",
  "properties": {
    "addr:full":"Fynsvej 13 K\u00f8ge Danmark 4600",
    "addr:housenumber":"13",
    "addr:postcode":"4600",
    "addr:street":"Fynsvej",
    "iso:country":"DK",
    "sg:address":"Fynsvej 13",
    "sg:city":"K\u00f8ge",
    "sg:classifiers":[
        {
            "category":"Home & Garden",
            "subcategory":"Home Furnishings",
            "type":"Retail Goods"
        }
    ],
    "sg:phone":"+45 56 65 23 32",
    "sg:postcode":"4600",
    "sg:province":"Danmark",
    "sg:tags":[
        "gardiner"
    ],
    "wof:name":"JH Montage ApS",
    "wof:placetype":"venue"
},
  "geometry": {"coordinates":[12.1535196304,55.4337882996],"type":"Point"}
}