{
  "type": "Feature",
  "properties": {
    "iso:country":"DK",
    "sg:address":"Skovbakken 5, Hjerup",
    "sg:city":"Aarup",
    "sg:orig_category":"Autoophug",
    "sg:phone":"+45 64 79 12 08",
    "sg:postcode":"5560",
    "sg:province":"Danmark",
    "wof:name":"Hjerup Autoophug",
    "wof:placetype":"venue"
},
  "geometry": {"coordinates":[10.0490245819,55.3808059692],"type":"Point"}
}