{
  "type": "Feature",
  "properties": {
    "addr:full":"T\u00e5derupvej 3 Dianalund Danmark 4293",
    "addr:housenumber":"3",
    "addr:postcode":"4293",
    "addr:street":"Taaderupvej",
    "iso:country":"DK",
    "sg:address":"T\u00e5derupvej 3",
    "sg:city":"Dianalund",
    "sg:orig_category":"Cykler",
    "sg:phone":"+45 58 26 33 15",
    "sg:postcode":"4293",
    "sg:province":"Danmark",
    "wof:name":"Skellebjerg Cykelv\u00e6rksted",
    "wof:placetype":"venue"
},
  "geometry": {"coordinates":[11.4433479309,55.5328330994],"type":"Point"}
}