{
  "type": "Feature",
  "properties": {
    "addr:full":"Helligkildevej 5 Vejle Danmark 7100",
    "addr:housenumber":"5",
    "addr:postcode":"7100",
    "addr:street":"Helligkildevej",
    "iso:country":"DK",
    "sg:address":"Helligkildevej 5",
    "sg:city":"Vejle",
    "sg:orig_category":"Campingpladser",
    "sg:phone":"+45 75 82 33 35",
    "sg:postcode":"7100",
    "sg:province":"Danmark",
    "wof:name":"Vejle Camping",
    "wof:placetype":"venue"
},
  "geometry": {"coordinates":[9.566608429,55.7133178711],"type":"Point"}
}