{
  "type": "Feature",
  "properties": {
    "iso:country":"DK",
    "sg:address":"N\u00f8rrevangstorvet 1-3",
    "sg:city":"Slagelse",
    "sg:orig_category":"Kirkesogne",
    "sg:phone":"+45 58 50 11 16",
    "sg:postcode":"4200",
    "sg:province":"Danmark",
    "wof:name":"N\u00f8rrevangskirkens Kontor",
    "wof:placetype":"venue"
},
  "geometry": {"coordinates":[11.3645429611,55.4175720215],"type":"Point"}
}