{
  "type": "Feature",
  "properties": {
    "addr:full":"Bagergade 40 B Svendborg Danmark 5700",
    "addr:housenumber":"40 b",
    "addr:postcode":"5700",
    "addr:street":"Bagergade",
    "iso:country":"DK",
    "sg:address":"Bagergade 40 B",
    "sg:city":"Svendborg",
    "sg:orig_category":"Arkitekter",
    "sg:phone":"+45 62 21 69 79",
    "sg:postcode":"5700",
    "sg:province":"Danmark",
    "wof:name":"Skovmand M.A.A. P.A.R, Arkitektfirmaet Steen",
    "wof:placetype":"venue"
},
  "geometry": {"coordinates":[10.6070375443,55.0616188049],"type":"Point"}
}