{
  "type": "Feature",
  "properties": {
    "iso:country":"DK",
    "sg:address":"Elmegade 28",
    "sg:city":"Middelfart",
    "sg:orig_category":"Stoffer",
    "sg:phone":"+45 64 41 52 51",
    "sg:postcode":"5500",
    "sg:province":"Danmark",
    "wof:name":"Stof & Mode",
    "wof:placetype":"venue"
},
  "geometry": {"coordinates":[9.7379016876,55.5024833679],"type":"Point"}
}