{
  "type": "Feature",
  "properties": {
    "addr:full":"Fmd.: Carina Nygaard Simonsen, \u00d8ster Vase 21, K\u00e6rsholm Storvorde Danmark 9280",
    "addr:housenumber":"21",
    "addr:postcode":"9280",
    "addr:street":"Vase;Kaersholm",
    "iso:country":"DK",
    "sg:address":"Fmd.: Carina Nygaard Simonsen, \u00d8ster Vase 21, K\u00e6rsholm",
    "sg:city":"Storvorde",
    "sg:orig_category":"Kirkelige foreninger",
    "sg:phone":"+45 98 31 62 72",
    "sg:postcode":"9280",
    "sg:province":"Danmark",
    "wof:name":"KFUM og KFUK i \u00d8sthimmerland",
    "wof:placetype":"venue"
},
  "geometry": {"coordinates":[10.1014204025,57.0045547485],"type":"Point"}
}