{
  "type": "Feature",
  "properties": {
    "addr:full":"Rosenv\u00e6nget 8 Dalmose Danmark 4261",
    "addr:housenumber":"8",
    "addr:postcode":"4261",
    "addr:street":"Rosenvaenget",
    "iso:country":"DK",
    "sg:address":"Rosenv\u00e6nget 8",
    "sg:city":"Dalmose",
    "sg:orig_category":"Malermestre",
    "sg:phone":"+45 58 18 82 33",
    "sg:postcode":"4261",
    "sg:province":"Danmark",
    "wof:name":"Christensen, Carl Ove",
    "wof:placetype":"venue"
},
  "geometry": {"coordinates":[11.423330307,55.2912635803],"type":"Point"}
}