{
  "type": "Feature",
  "properties": {
    "addr:full":"\u00c5dalen 38 Hurup Danmark 7760",
    "addr:housenumber":"38",
    "addr:postcode":"7760",
    "addr:street":"Aadalen",
    "iso:country":"DK",
    "sg:address":"\u00c5dalen 38",
    "sg:city":"Hurup",
    "sg:orig_category":"Glasfiberindustri",
    "sg:phone":"+45 97 95 32 22",
    "sg:postcode":"7760",
    "sg:province":"Danmark",
    "wof:name":"Bach Glasfiber ApS",
    "wof:placetype":"venue"
},
  "geometry": {"coordinates":[8.4310407639,56.750289917],"type":"Point"}
}