{
  "type": "Feature",
  "properties": {
    "addr:full":"Hovedvejen 104 Glostrup Danmark 2600",
    "addr:housenumber":"104",
    "addr:postcode":"2600",
    "addr:street":"Hovedvejen",
    "iso:country":"DK",
    "sg:address":"Hovedvejen 104",
    "sg:city":"Glostrup",
    "sg:orig_category":"Ejendomshandel",
    "sg:phone":"+45 43 43 42 88",
    "sg:postcode":"2600",
    "sg:province":"Danmark",
    "sg:website":"www.edc.dk",
    "wof:name":"Aastrup, EDC M\u00e6glerne Allan",
    "wof:placetype":"venue"
},
  "geometry": {"coordinates":[12.3994407654,55.6662216187],"type":"Point"}
}