{
  "type": "Feature",
  "properties": {
    "addr:full":"Valdemarsgade 53 Svendborg Danmark 5700",
    "addr:housenumber":"53",
    "addr:postcode":"5700",
    "addr:street":"Valdemarsgade",
    "iso:country":"DK",
    "sg:address":"Valdemarsgade 53",
    "sg:city":"Svendborg",
    "sg:orig_category":"Kiosker",
    "sg:phone":"+45 62 20 14 15",
    "sg:postcode":"5700",
    "sg:province":"Danmark",
    "wof:name":"Sygehuskiosken Svendborg Sygehus",
    "wof:placetype":"venue"
},
  "geometry": {"coordinates":[10.6078042984,55.0567207336],"type":"Point"}
}