{
  "type": "Feature",
  "properties": {
    "addr:full":"Tietgensvej 7 Silkeborg Danmark 8600",
    "addr:housenumber":"7",
    "addr:postcode":"8600",
    "addr:street":"Tietgensvej",
    "iso:country":"DK",
    "sg:address":"Tietgensvej 7",
    "sg:city":"Silkeborg",
    "sg:orig_category":"Hobbybetonede foreninger",
    "sg:phone":"+45 86 82 42 83",
    "sg:postcode":"8600",
    "sg:province":"Danmark",
    "wof:name":"Silkeborg Walkie-Talkie Klub",
    "wof:placetype":"venue"
},
  "geometry": {"coordinates":[9.5773200989,56.1974830627],"type":"Point"}
}