{
  "type": "Feature",
  "properties": {
    "addr:full":"Teestrupvej 44 Haslev Danmark 4690",
    "addr:housenumber":"44",
    "addr:postcode":"4690",
    "addr:street":"Teestrupvej",
    "iso:country":"DK",
    "sg:address":"Teestrupvej 44",
    "sg:city":"Haslev",
    "sg:orig_category":"Slagter og viktualie",
    "sg:phone":"+45 56 38 00 35",
    "sg:postcode":"4690",
    "sg:province":"Danmark",
    "wof:name":"Teestrup Slagtehus",
    "wof:placetype":"venue"
},
  "geometry": {"coordinates":[11.8823881149,55.3255653381],"type":"Point"}
}