{
  "type": "Feature",
  "properties": {
    "addr:full":"Algade 133 Vordingborg Danmark 4760",
    "addr:housenumber":"133",
    "addr:postcode":"4760",
    "addr:street":"Algade",
    "iso:country":"DK",
    "sg:address":"Algade 133",
    "sg:city":"Vordingborg",
    "sg:classifiers":[
        {
            "category":"Airport",
            "type":"Transportation"
        }
    ],
    "sg:phone":"+45 55 37 20 95",
    "sg:postcode":"4760",
    "sg:province":"Danmark",
    "sg:tags":[
        "automation"
    ],
    "sg:website":"www.insatech.com",
    "wof:name":"Insatech A/S",
    "wof:placetype":"venue"
},
  "geometry": {"coordinates":[11.9160108566,55.0071296692],"type":"Point"}
}