{
  "type": "Feature",
  "properties": {
    "addr:full":"v/ Hanne J\u00e6ger, Lysh\u00f8jg\u00e5rdsvej 43 Valby Danmark 2500",
    "addr:housenumber":"43",
    "addr:postcode":"2500",
    "addr:street":"Lyshojgaardsvej",
    "iso:country":"DK",
    "sg:address":"v/ Hanne J\u00e6ger, Lysh\u00f8jg\u00e5rdsvej 43",
    "sg:city":"Valby",
    "sg:orig_category":"\u00c3\u02dcvrig fritidsundervisning",
    "sg:phone":"+45 36 46 32 08",
    "sg:postcode":"2500",
    "sg:province":"Danmark",
    "wof:name":"Skolen for Afasiramte",
    "wof:placetype":"venue"
},
  "geometry": {"coordinates":[12.5170240402,55.6659469604],"type":"Point"}
}