{
  "type": "Feature",
  "properties": {
    "addr:full":"Ansvej 51, Postboks 23 Ans Danmark 8643",
    "addr:housenumber":"51;23",
    "addr:postcode":"8643",
    "addr:street":"Ansvej",
    "iso:country":"DK",
    "sg:address":"Ansvej 51, Postboks 23",
    "sg:city":"Ans",
    "sg:orig_category":"Planteskoler",
    "sg:phone":"+45 86 87 03 33",
    "sg:postcode":"8643",
    "sg:province":"Danmark",
    "wof:name":"Hulk\u00e6rhus Planteskole",
    "wof:placetype":"venue"
},
  "geometry": {"coordinates":[9.6200656891,56.2750320435],"type":"Point"}
}