{
  "type": "Feature",
  "properties": {
    "iso:country":"DK",
    "sg:address":"Slotsgade 3",
    "sg:city":"Fredensborg",
    "sg:classifiers":[
        {
            "category":"Restaurant",
            "type":"Food & Drink"
        }
    ],
    "sg:phone":"+45 48 47 62 68",
    "sg:postcode":"3480",
    "sg:province":"Danmark",
    "wof:name":"Hua Fu, Restaurant",
    "wof:placetype":"venue"
},
  "geometry": {"coordinates":[12.3964557648,55.9785499573],"type":"Point"}
}