{
  "type": "Feature",
  "properties": {
    "addr:full":"Trehuse 2 Engesvang Danmark 7442",
    "addr:housenumber":"2",
    "addr:postcode":"7442",
    "addr:street":"Trehuse",
    "iso:country":"DK",
    "sg:address":"Trehuse 2",
    "sg:city":"Engesvang",
    "sg:classifiers":[
        {
            "category":"Arts & Performance",
            "subcategory":"Dance",
            "type":"Entertainment"
        }
    ],
    "sg:phone":"+45 23 34 15 90",
    "sg:postcode":"7442",
    "sg:province":"Danmark",
    "sg:tags":[
        "montage"
    ],
    "wof:name":"JE Teknik",
    "wof:placetype":"venue"
},
  "geometry": {"coordinates":[9.3237762451,56.15675354],"type":"Point"}
}