{
  "type": "Feature",
  "properties": {
    "addr:full":"Falkoner Alle 9, kl. Frederiksberg Danmark 2000",
    "addr:housenumber":"9 kl.",
    "addr:postcode":"2000",
    "addr:street":"Falkoner Alle",
    "iso:country":"DK",
    "sg:address":"Falkoner Alle 9, kl.",
    "sg:city":"Frederiksberg",
    "sg:orig_category":"Motionscentre",
    "sg:phone":"+45 38 10 90 70",
    "sg:postcode":"2000",
    "sg:province":"Danmark",
    "wof:name":"Form & Fitness",
    "wof:placetype":"venue"
},
  "geometry": {"coordinates":[12.5299301147,55.6787872314],"type":"Point"}
}