{
  "type": "Feature",
  "properties": {
    "addr:full":"\u00d8sterbro 71 Aalborg Danmark 9000",
    "addr:housenumber":"71",
    "addr:postcode":"9000",
    "addr:street":"Osterbro",
    "iso:country":"DK",
    "sg:address":"\u00d8sterbro 71",
    "sg:city":"Aalborg",
    "sg:classifiers":[
        {
            "category":"Personal",
            "subcategory":"Massage",
            "type":"Services"
        }
    ],
    "sg:phone":"+45 98 11 46 40",
    "sg:postcode":"9000",
    "sg:province":"Danmark",
    "wof:name":"Klinikken",
    "wof:placetype":"venue"
},
  "geometry": {"coordinates":[9.9444770813,57.045501709],"type":"Point"}
}