{
  "type": "Feature",
  "properties": {
    "addr:full":"Ladeg\u00e5rdsvej 6, Kv\u00e6rs Gr\u00e5sten Danmark 6300",
    "addr:housenumber":"6",
    "addr:postcode":"6300",
    "addr:street":"Ladegaardsvej;Graasten Danmark",
    "iso:country":"DK",
    "sg:address":"Ladeg\u00e5rdsvej 6, Kv\u00e6rs",
    "sg:city":"Gr\u00e5sten",
    "sg:orig_category":"Fodplejere",
    "sg:phone":"+45 74 65 92 20",
    "sg:postcode":"6300",
    "sg:province":"Danmark",
    "wof:name":"Anne Mette's Fodpleje",
    "wof:placetype":"venue"
},
  "geometry": {"coordinates":[-53.6545410156,-30.415309906],"type":"Point"}
}