{
  "type": "Feature",
  "properties": {
    "addr:full":"Herschendsgavevej 18, Gammel Gjesing Skanderborg Danmark 8660",
    "addr:housenumber":"18",
    "addr:postcode":"8660",
    "addr:street":"Herschendsgavevej;Gammel Gjesing",
    "iso:country":"DK",
    "sg:address":"Herschendsgavevej 18, Gammel Gjesing",
    "sg:city":"Skanderborg",
    "sg:orig_category":"\u00c3\u02dcvrig fritidsundervisning",
    "sg:phone":"+45 86 53 14 46",
    "sg:postcode":"8660",
    "sg:province":"Danmark",
    "wof:name":"Gjesing Fritidsskole",
    "wof:placetype":"venue"
},
  "geometry": {"coordinates":[9.929974556,56.0380249023],"type":"Point"}
}