{
  "type": "Feature",
  "properties": {
    "addr:full":"Lystrupvej 42 Risskov Danmark 8240",
    "addr:housenumber":"42",
    "addr:postcode":"8240",
    "addr:street":"Lystrupvej",
    "iso:country":"DK",
    "sg:address":"Lystrupvej 42",
    "sg:city":"Risskov",
    "sg:orig_category":"Malermestre",
    "sg:phone":"+45 86 17 14 25",
    "sg:postcode":"8240",
    "sg:province":"Danmark",
    "wof:name":"Christina's Malerfirma I/S",
    "wof:placetype":"venue"
},
  "geometry": {"coordinates":[10.2363882065,56.2051467896],"type":"Point"}
}