{
  "type": "Feature",
  "properties": {
    "addr:full":"Gammel Jernbanevej 11 Valby Danmark 2500",
    "addr:housenumber":"11",
    "addr:postcode":"2500",
    "addr:street":"Gammel Jernbanevej",
    "iso:country":"DK",
    "sg:address":"Gammel Jernbanevej 11",
    "sg:city":"Valby",
    "sg:orig_category":"Sange",
    "sg:phone":"+45 36 17 70 25",
    "sg:postcode":"2500",
    "sg:province":"Danmark",
    "wof:name":"Stegmann, Knud",
    "wof:placetype":"venue"
},
  "geometry": {"coordinates":[12.5203561783,55.6656723022],"type":"Point"}
}