{
  "type": "Feature",
  "properties": {
    "addr:full":"Nordlandsvej 114 Risskov Danmark 8240",
    "addr:housenumber":"114",
    "addr:postcode":"8240",
    "addr:street":"Nordlandsvej",
    "iso:country":"DK",
    "sg:address":"Nordlandsvej 114",
    "sg:city":"Risskov",
    "sg:orig_category":"Reklamebureauer",
    "sg:phone":"+45 86 21 16 00",
    "sg:postcode":"8240",
    "sg:province":"Danmark",
    "wof:name":"Roland Marketing/ Reklame-Bureau A/S",
    "wof:placetype":"venue"
},
  "geometry": {"coordinates":[10.2175569534,56.2080459595],"type":"Point"}
}