{
  "type": "Feature",
  "properties": {
    "addr:full":"Jernbanevej 10 Kongens Lyngby Danmark 2800",
    "addr:housenumber":"10",
    "addr:postcode":"2800",
    "addr:street":"Jernbanevej",
    "iso:country":"DK",
    "sg:address":"Jernbanevej 10",
    "sg:city":"Kongens Lyngby",
    "sg:orig_category":"Pizzeriaer",
    "sg:phone":"+45 45 88 88 99",
    "sg:postcode":"2800",
    "sg:province":"Danmark",
    "wof:name":"Pizzeria Big Mamma",
    "wof:placetype":"venue"
},
  "geometry": {"coordinates":[12.499587059,55.7707138062],"type":"Point"}
}