{
  "type": "Feature",
  "properties": {
    "addr:full":"Jerlev Landevej 14, \u00d8dsted Vejle Danmark 7100",
    "addr:housenumber":"14",
    "addr:postcode":"7100",
    "addr:street":"Jerlev Landevej",
    "iso:country":"DK",
    "sg:address":"Jerlev Landevej 14, \u00d8dsted",
    "sg:city":"Vejle",
    "sg:orig_category":"Tekstbehandling",
    "sg:phone":"+45 75 86 41 44",
    "sg:postcode":"7100",
    "sg:province":"Danmark",
    "wof:name":"VAC Text",
    "wof:placetype":"venue"
},
  "geometry": {"coordinates":[9.5368051529,55.7113952637],"type":"Point"}
}