{
  "type": "Feature",
  "properties": {
    "addr:full":"Sekretariatet, Enrumvej 6A, S\u00f8hus Odense N Danmark 5270",
    "addr:housenumber":"6a",
    "addr:postcode":"5270",
    "addr:street":"Enrumvej;Sohus",
    "iso:country":"DK",
    "sg:address":"Sekretariatet, Enrumvej 6A, S\u00f8hus",
    "sg:city":"Odense N",
    "sg:orig_category":"Fritidsorganisationer og -foreninger",
    "sg:phone":"+45 66 18 58 60",
    "sg:postcode":"5270",
    "sg:province":"Danmark",
    "wof:name":"Folkedansere, Landsforeningen Danske",
    "wof:placetype":"venue"
},
  "geometry": {"coordinates":[10.3306798935,55.4711418152],"type":"Point"}
}