{
  "type": "Feature",
  "properties": {
    "addr:full":"M\u00f8llegade 60, Holm Nordborg Danmark 6430",
    "addr:housenumber":"60",
    "addr:postcode":"6430",
    "addr:street":"Mollegade",
    "iso:country":"DK",
    "sg:address":"M\u00f8llegade 60, Holm",
    "sg:city":"Nordborg",
    "sg:orig_category":"\u00c3\u02dcvrige foreninger",
    "sg:phone":"+45 74 45 33 24",
    "sg:postcode":"6430",
    "sg:province":"Danmark",
    "wof:name":"Holm Sogneg\u00e5rd",
    "wof:placetype":"venue"
},
  "geometry": {"coordinates":[9.7496232986,55.0542755127],"type":"Point"}
}