{
  "type": "Feature",
  "properties": {
    "addr:full":"K. Kalmo, Drosselvej 6 Frederiksv\u00e6rk Danmark 3300",
    "addr:housenumber":"6",
    "addr:postcode":"3300",
    "addr:street":"K. Kalmo Drosselvej",
    "iso:country":"DK",
    "sg:address":"K. Kalmo, Drosselvej 6",
    "sg:city":"Frederiksv\u00e6rk",
    "sg:orig_category":"Fotografer",
    "sg:phone":"+45 47 77 07 87",
    "sg:postcode":"3300",
    "sg:province":"Danmark",
    "wof:name":"Kalmo, Karl",
    "wof:placetype":"venue"
},
  "geometry": {"coordinates":[16.7672996521,57.6150588989],"type":"Point"}
}