{
  "type": "Feature",
  "properties": {
    "addr:full":"Hvenekildevej 27, Seden Odense N\u00d8 Danmark 5240",
    "addr:housenumber":"27",
    "addr:postcode":"5240",
    "addr:street":"Hvenekildevej;Seden",
    "iso:country":"DK",
    "sg:address":"Hvenekildevej 27, Seden",
    "sg:city":"Odense N\u00d8",
    "sg:orig_category":"Gartnerier",
    "sg:phone":"+45 66 10 72 08",
    "sg:postcode":"5240",
    "sg:province":"Danmark",
    "wof:name":"Pedersen, Lars Ulrik",
    "wof:placetype":"venue"
},
  "geometry": {"coordinates":[10.444185257,55.4261131287],"type":"Point"}
}