{
  "type": "Feature",
  "properties": {
    "addr:full":"Blaak\u00e6rvej 5 Ryslinge Danmark 5856",
    "addr:housenumber":"5",
    "addr:postcode":"5856",
    "addr:street":"Blaakaervej",
    "iso:country":"DK",
    "sg:address":"Blaak\u00e6rvej 5",
    "sg:city":"Ryslinge",
    "sg:orig_category":"Slagter og viktualie",
    "sg:phone":"+45 62 67 10 29",
    "sg:postcode":"5856",
    "sg:province":"Danmark",
    "wof:name":"Ryslinge Slagterforretning",
    "wof:placetype":"venue"
},
  "geometry": {"coordinates":[10.5349359512,55.2435760498],"type":"Point"}
}