{
  "type": "Feature",
  "properties": {
    "addr:full":"Krajbjergvej 10, Vorre Sk\u00f8dstrup Danmark 8541",
    "addr:housenumber":"10",
    "addr:postcode":"8541",
    "addr:street":"Krajbjergvej",
    "iso:country":"DK",
    "sg:address":"Krajbjergvej 10, Vorre",
    "sg:city":"Sk\u00f8dstrup",
    "sg:orig_category":"Hundepensioner",
    "sg:phone":"+45 86 99 31 19",
    "sg:postcode":"8541",
    "sg:province":"Danmark",
    "sg:website":"www.vorre-hundecenter.dk",
    "wof:name":"Vorre Hundepension",
    "wof:placetype":"venue"
},
  "geometry": {"coordinates":[10.3167448044,56.277305603],"type":"Point"}
}