{
  "type": "Feature",
  "properties": {
    "addr:full":"Jordk\u00e6rvej 23 Silkeborg Danmark 8600",
    "addr:housenumber":"23",
    "addr:postcode":"8600",
    "addr:street":"Jordkaervej",
    "iso:country":"DK",
    "sg:address":"Jordk\u00e6rvej 23",
    "sg:city":"Silkeborg",
    "sg:orig_category":"Fabrikker",
    "sg:phone":"+45 86 85 51 42",
    "sg:postcode":"8600",
    "sg:province":"Danmark",
    "wof:name":"Hunde Huse & Hundesenge",
    "wof:placetype":"venue"
},
  "geometry": {"coordinates":[9.4822731018,56.1840782166],"type":"Point"}
}