{
  "type": "Feature",
  "properties": {
    "addr:full":"Byvej 4, Thorlund Ejstrupholm Danmark 7361",
    "addr:housenumber":"4",
    "addr:postcode":"7361",
    "addr:street":"Byvej",
    "iso:country":"DK",
    "sg:address":"Byvej 4, Thorlund",
    "sg:city":"Ejstrupholm",
    "sg:orig_category":"Private- og friskoler",
    "sg:phone":"+45 75 77 31 17",
    "sg:postcode":"7361",
    "sg:province":"Danmark",
    "wof:name":"Friskolen i Thorlund",
    "wof:placetype":"venue"
},
  "geometry": {"coordinates":[9.289560318,55.9840965271],"type":"Point"}
}