{
  "type": "Feature",
  "properties": {
    "addr:full":"Havnefoged: Poul Flohr, Mariagervej 2 Hadsund Danmark 9560",
    "addr:housenumber":"2",
    "addr:postcode":"9560",
    "addr:street":"Poul;Mariagervej",
    "iso:country":"DK",
    "sg:address":"Havnefoged: Poul Flohr, Mariagervej 2",
    "sg:city":"Hadsund",
    "sg:orig_category":"Havne",
    "sg:phone":"+45 98 57 21 65",
    "sg:postcode":"9560",
    "sg:province":"Danmark",
    "wof:name":"Hadsund Fiskerihavn - Hadsund Trafikhavn",
    "wof:placetype":"venue"
},
  "geometry": {"coordinates":[10.115904808,56.7150764465],"type":"Point"}
}