{
  "type": "Feature",
  "properties": {
    "addr:full":"Godthaabsvej 20 Fjerritslev Danmark 9690",
    "addr:housenumber":"20",
    "addr:postcode":"9690",
    "addr:street":"Godthaabsvej",
    "iso:country":"DK",
    "sg:address":"Godthaabsvej 20",
    "sg:city":"Fjerritslev",
    "sg:orig_category":"Autoforhandlere",
    "sg:phone":"+45 98 21 18 50",
    "sg:postcode":"9690",
    "sg:province":"Danmark",
    "wof:name":"JPC Handel",
    "wof:placetype":"venue"
},
  "geometry": {"coordinates":[9.2624292374,57.0859832764],"type":"Point"}
}