{
  "type": "Feature",
  "properties": {
    "addr:full":"Storetorv 10 Aabenraa Danmark 6200",
    "addr:housenumber":"10",
    "addr:postcode":"6200",
    "addr:street":"Storetorv",
    "iso:country":"DK",
    "sg:address":"Storetorv 10",
    "sg:city":"Aabenraa",
    "sg:orig_category":"Dag- og distriktsblade",
    "sg:phone":"+45 79 12 45 00",
    "sg:postcode":"6200",
    "sg:province":"Danmark",
    "sg:website":"www.jv.dk",
    "wof:name":"Jydske Vestkysten",
    "wof:placetype":"venue"
},
  "geometry": {"coordinates":[9.418806076,55.0422821045],"type":"Point"}
}