{
  "type": "Feature",
  "properties": {
    "iso:country":"DK",
    "sg:address":"Solvangsvej 27",
    "sg:city":"Ebeltoft",
    "sg:orig_category":"Hobbybetonede foreninger",
    "sg:phone":"+45 86 34 26 16",
    "sg:postcode":"8400",
    "sg:province":"Danmark",
    "wof:name":"V\u00e6vekredsen",
    "wof:placetype":"venue"
},
  "geometry": {"coordinates":[10.6871137619,56.1990585327],"type":"Point"}
}