{
  "type": "Feature",
  "properties": {
    "addr:full":"Metalgangen 1 - 3 Karlslunde Danmark 2690",
    "addr:housenumber":"1 3",
    "addr:postcode":"2690",
    "addr:street":"Metalgangen",
    "iso:country":"DK",
    "sg:address":"Metalgangen 1 - 3",
    "sg:city":"Karlslunde",
    "sg:classifiers":[
        {
            "category":"Autos & Motor Vehicles",
            "subcategory":"Automobile Sales",
            "type":"Retail Goods"
        }
    ],
    "sg:phone":"+45 46 15 00 23",
    "sg:postcode":"2690",
    "sg:province":"Danmark",
    "sg:tags":[
        "truck"
    ],
    "wof:name":"Nielsen Balling A/S, NC",
    "wof:placetype":"venue"
},
  "geometry": {"coordinates":[12.2389287949,55.5775032043],"type":"Point"}
}