{
  "type": "Feature",
  "properties": {
    "iso:country":"DK",
    "sg:address":"N\u00f8rregade 44",
    "sg:city":"Vejen",
    "sg:orig_category":"Bagere",
    "sg:phone":"+45 75 36 00 54",
    "sg:postcode":"6600",
    "sg:province":"Danmark",
    "sg:website":"www.bagerchristensen.dk",
    "wof:name":"Christensen, Bager",
    "wof:placetype":"venue"
},
  "geometry": {"coordinates":[9.139162,55.478455],"type":"Point"}
}