{
  "type": "Feature",
  "properties": {
    "addr:full":"Flintebakken 2 Risskov Danmark 8240",
    "addr:housenumber":"2",
    "addr:postcode":"8240",
    "addr:street":"Flintebakken",
    "iso:country":"DK",
    "sg:address":"Flintebakken 2",
    "sg:city":"Risskov",
    "sg:orig_category":"Integrerede institutioner",
    "sg:phone":"+45 86 21 92 22",
    "sg:postcode":"8240",
    "sg:province":"Danmark",
    "wof:name":"Gnisten, Integreret Inst.",
    "wof:placetype":"venue"
},
  "geometry": {"coordinates":[10.2106151581,56.206073761],"type":"Point"}
}