{
  "type": "Feature",
  "properties": {
    "addr:full":"Hermannsv\u00e6nget 2, S\u00f8hus Odense N Danmark 5270",
    "addr:housenumber":"2",
    "addr:postcode":"5270",
    "addr:street":"Hermannsvaenget;Sohus",
    "iso:country":"DK",
    "sg:address":"Hermannsv\u00e6nget 2, S\u00f8hus",
    "sg:city":"Odense N",
    "sg:orig_category":"Forlag",
    "sg:phone":"+45 66 18 71 25",
    "sg:postcode":"5270",
    "sg:province":"Danmark",
    "wof:name":"L\u00f8ven, Forlaget",
    "wof:placetype":"venue"
},
  "geometry": {"coordinates":[10.3306798935,55.4711418152],"type":"Point"}
}