{
  "type": "Feature",
  "properties": {
    "iso:country":"DK",
    "sg:address":"Godth\u00e5bsvej 12",
    "sg:city":"Silkeborg",
    "sg:orig_category":"Cafeer",
    "sg:phone":"+45 86 80 55 20",
    "sg:postcode":"8600",
    "sg:province":"Danmark",
    "wof:name":"Don Vito Caf\u00e9",
    "wof:placetype":"venue"
},
  "geometry": {"coordinates":[9.5524597168,56.1713447571],"type":"Point"}
}