{
  "type": "Feature",
  "properties": {
    "addr:full":"Bjerrevej 32 Horsens Danmark 8700",
    "addr:housenumber":"32",
    "addr:postcode":"8700",
    "addr:street":"Bjerrevej",
    "iso:country":"DK",
    "sg:address":"Bjerrevej 32",
    "sg:city":"Horsens",
    "sg:orig_category":"Zoneterapeuter",
    "sg:phone":"+45 75 64 68 99",
    "sg:postcode":"8700",
    "sg:province":"Danmark",
    "wof:name":"Andersen, Inga T.",
    "wof:placetype":"venue"
},
  "geometry": {"coordinates":[9.845085144,55.8504905701],"type":"Point"}
}