{
  "type": "Feature",
  "properties": {
    "addr:full":"Fmd.: Kresten Vestergaard, \u00d8rnh\u00f8jvej 28, Gr\u00f8nbjerg Spjald Danmark 6971",
    "addr:housenumber":"28",
    "addr:postcode":"6971",
    "addr:street":"Kresten;Ornhojvej;Gronbjerg",
    "iso:country":"DK",
    "sg:address":"Fmd.: Kresten Vestergaard, \u00d8rnh\u00f8jvej 28, Gr\u00f8nbjerg",
    "sg:city":"Spjald",
    "sg:orig_category":"Borger- og beboerforeninger",
    "sg:phone":"+45 97 38 42 00",
    "sg:postcode":"6971",
    "sg:province":"Danmark",
    "wof:name":"Gr\u00f8nbjerg Sogneforening",
    "wof:placetype":"venue"
},
  "geometry": {"coordinates":[8.5089349747,56.1276893616],"type":"Point"}
}