{
  "type": "Feature",
  "properties": {
    "iso:country":"DK",
    "sg:address":"Nyvangsvej 25",
    "sg:city":"Randers",
    "sg:orig_category":"Vuggestuer",
    "sg:phone":"+45 86 41 30 11",
    "sg:postcode":"8900",
    "sg:province":"Danmark",
    "wof:name":"Daginstitutionen Minimax",
    "wof:placetype":"venue"
},
  "geometry": {"coordinates":[10.0249233246,56.4678077698],"type":"Point"}
}