{
  "type": "Feature",
  "properties": {
    "addr:full":"Lyngens Kvarter 225, Hedebyen Herning Danmark 7400",
    "addr:housenumber":"225",
    "addr:postcode":"7400",
    "addr:street":"Lyngens Kvarter;Hedebyen",
    "iso:country":"DK",
    "sg:address":"Lyngens Kvarter 225, Hedebyen",
    "sg:city":"Herning",
    "sg:orig_category":"Ungdomsklubber",
    "sg:phone":"+45 97 22 48 78",
    "sg:postcode":"7400",
    "sg:province":"Danmark",
    "wof:name":"Ungdomsklubben Hedeg\u00e5rden",
    "wof:placetype":"venue"
},
  "geometry": {"coordinates":[8.9768896103,56.1374168396],"type":"Point"}
}