{
  "type": "Feature",
  "properties": {
    "addr:full":"Or\u00f8v\u00e6nget 33, True Tilst Danmark 8381",
    "addr:housenumber":"33",
    "addr:postcode":"8381",
    "addr:street":"Orovaenget",
    "iso:country":"DK",
    "sg:address":"Or\u00f8v\u00e6nget 33, True",
    "sg:city":"Tilst",
    "sg:orig_category":"Murermestre",
    "sg:phone":"+45 86 24 43 14",
    "sg:postcode":"8381",
    "sg:province":"Danmark",
    "wof:name":"Murerfirmaet, P. M. Holme",
    "wof:placetype":"venue"
},
  "geometry": {"coordinates":[10.1078147888,56.1882019043],"type":"Point"}
}