{
  "type": "Feature",
  "properties": {
    "addr:full":"Gammel M\u00f8llevej 49 Redsted Danmark 7970",
    "addr:housenumber":"49",
    "addr:postcode":"7970",
    "addr:street":"Gammel Mollevej",
    "iso:country":"DK",
    "sg:address":"Gammel M\u00f8llevej 49",
    "sg:city":"Redsted",
    "sg:orig_category":"Landbrugsmaskiner",
    "sg:phone":"+45 96 70 66 00",
    "sg:postcode":"7970",
    "sg:province":"Danmark",
    "sg:website":"www.vilsgaard.dk",
    "wof:name":"Vilsgaard A/S",
    "wof:placetype":"venue"
},
  "geometry": {"coordinates":[8.6521482468,56.7371139526],"type":"Point"}
}