{
  "type": "Feature",
  "properties": {
    "addr:full":"Industrivej 34 Ikast Danmark 7430",
    "addr:housenumber":"34",
    "addr:postcode":"7430",
    "addr:street":"Industrivej",
    "iso:country":"DK",
    "sg:address":"Industrivej 34",
    "sg:city":"Ikast",
    "sg:orig_category":"Tekstilindustri",
    "sg:phone":"+45 97 15 51 02",
    "sg:postcode":"7430",
    "sg:province":"Danmark",
    "wof:name":"Lau Strik",
    "wof:placetype":"venue"
},
  "geometry": {"coordinates":[9.1707401276,56.1234054565],"type":"Point"}
}