{
  "type": "Feature",
  "properties": {
    "addr:full":"Malmbergsvej 1, Gl. Holte N\u00e6rum Danmark 2850",
    "addr:housenumber":"1",
    "addr:postcode":"2850",
    "addr:street":"Malmbergsvej;Gl. Holte;Danmark",
    "iso:country":"DK",
    "sg:address":"Malmbergsvej 1, Gl. Holte",
    "sg:city":"N\u00e6rum",
    "sg:classifiers":[
        {
            "category":"Restaurant",
            "type":"Food & Drink"
        }
    ],
    "sg:phone":"+45 45 80 99 50",
    "sg:postcode":"2850",
    "sg:province":"Danmark",
    "wof:name":"Junker's L\u00e6kre Mad",
    "wof:placetype":"venue"
},
  "geometry": {"coordinates":[-89.99810791020001,38.1321372986],"type":"Point"}
}