{
  "type": "Feature",
  "properties": {
    "addr:full":"Kirkevej 26, Tyrsted Horsens Danmark 8700",
    "addr:housenumber":"26",
    "addr:postcode":"8700",
    "addr:street":"Kirkevej;Tyrsted",
    "iso:country":"DK",
    "sg:address":"Kirkevej 26, Tyrsted",
    "sg:city":"Horsens",
    "sg:orig_category":"Kirkesogne",
    "sg:phone":"+45 75 64 32 33",
    "sg:postcode":"8700",
    "sg:province":"Danmark",
    "wof:name":"Tyrsted og Uth Sognes Kirkekontor",
    "wof:placetype":"venue"
},
  "geometry": {"coordinates":[9.8432445526,55.8621063232],"type":"Point"}
}