{
  "type": "Feature",
  "properties": {
    "addr:full":"Fmd.: Birgit Nielsen, \u00d8stre Alle 11 Hurup Danmark 7760",
    "addr:housenumber":"11",
    "addr:postcode":"7760",
    "addr:street":"Ostre Alle",
    "iso:country":"DK",
    "sg:address":"Fmd.: Birgit Nielsen, \u00d8stre Alle 11",
    "sg:city":"Hurup",
    "sg:orig_category":"Kirkelige foreninger",
    "sg:phone":"+45 97 95 23 97",
    "sg:postcode":"7760",
    "sg:province":"Danmark",
    "wof:name":"I.M.-Samfund i Hurup",
    "wof:placetype":"venue"
},
  "geometry": {"coordinates":[8.4233045578,56.7485847473],"type":"Point"}
}