{
  "type": "Feature",
  "properties": {
    "addr:full":"B\u00f8rne- og Kulturforvaltningen, \u00d8stre Havnevej 12 Kalundborg Danmark 4400",
    "addr:housenumber":"12",
    "addr:postcode":"4400",
    "addr:street":"Ostre Havnevej",
    "iso:country":"DK",
    "sg:address":"B\u00f8rne- og Kulturforvaltningen, \u00d8stre Havnevej 12",
    "sg:city":"Kalundborg",
    "sg:orig_category":"Dagplejeformidling",
    "sg:phone":"+45 59 51 53 00",
    "sg:postcode":"4400",
    "sg:province":"Danmark",
    "wof:name":"Kalundborg Kommunes Dagpleje",
    "wof:placetype":"venue"
},
  "geometry": {"coordinates":[11.0934085846,55.6797485352],"type":"Point"}
}