{
  "type": "Feature",
  "properties": {
    "iso:country":"DK",
    "sg:address":"Mellemgade 1",
    "sg:city":"Faaborg",
    "sg:orig_category":"Skomagere",
    "sg:phone":"+45 62 61 81 62",
    "sg:postcode":"5600",
    "sg:province":"Danmark",
    "wof:name":"Leif Skomager",
    "wof:placetype":"venue"
},
  "geometry": {"coordinates":[10.2409534454,55.0955352783],"type":"Point"}
}