{
  "type": "Feature",
  "properties": {
    "iso:country":"DK",
    "sg:address":"Niels Juhlers Toft 2, Skrydstrup",
    "sg:city":"Vojens",
    "sg:orig_category":"Snedkermestre",
    "sg:phone":"+45 74 54 07 86",
    "sg:postcode":"6500",
    "sg:province":"Danmark",
    "wof:name":"Skrydstrup T\u00f8mrer- og Snedkerforretning",
    "wof:placetype":"venue"
},
  "geometry": {"coordinates":[9.2987146378,55.2457237244],"type":"Point"}
}