{
  "type": "Feature",
  "properties": {
    "iso:country":"DK",
    "sg:address":"Skarrids\u00f8gade 17",
    "sg:city":"Jyderup",
    "sg:classifiers":[
        {
            "category":"Banks & Credit Unions",
            "subcategory":"Bank",
            "type":"Services"
        }
    ],
    "sg:phone":"+45 59 27 61 76",
    "sg:postcode":"4450",
    "sg:province":"Danmark",
    "sg:tags":[
        "banker"
    ],
    "wof:name":"Nordea",
    "wof:placetype":"venue"
},
  "geometry": {"coordinates":[11.399936,55.659592],"type":"Point"}
}