{
  "type": "Feature",
  "properties": {
    "addr:full":"Tjelevej 12, \u00d8rum Tjele Danmark 8830",
    "addr:housenumber":"12",
    "addr:postcode":"8830",
    "addr:street":"Tjelevej;Orum",
    "iso:country":"DK",
    "sg:address":"Tjelevej 12, \u00d8rum",
    "sg:city":"Tjele",
    "sg:orig_category":"Faglige organisationer og foreninger",
    "sg:phone":"+45 86 65 23 88",
    "sg:postcode":"8830",
    "sg:province":"Danmark",
    "wof:name":"SID",
    "wof:placetype":"venue"
},
  "geometry": {"coordinates":[9.6264801025,56.4818611145],"type":"Point"}
}