{
  "type": "Feature",
  "properties": {
    "addr:full":"v/ Henrik & Annelise Petersen, Vesterborgvej 36 Vesterborg Danmark 4953",
    "addr:housenumber":"36",
    "addr:postcode":"4953",
    "addr:street":"Vesterborgvej",
    "iso:country":"DK",
    "sg:address":"v/ Henrik & Annelise Petersen, Vesterborgvej 36",
    "sg:city":"Vesterborg",
    "sg:orig_category":"Apoteker og -udsalg",
    "sg:phone":"+45 54 93 93 47",
    "sg:postcode":"4953",
    "sg:province":"Danmark",
    "wof:name":"H\u00e5ndk\u00f8bsudsalget",
    "wof:placetype":"venue"
},
  "geometry": {"coordinates":[11.2703399658,54.8583946228],"type":"Point"}
}