{
  "type": "Feature",
  "properties": {
    "addr:full":"Ahlgade 10 Holb\u00e6k Danmark 4300",
    "addr:housenumber":"10",
    "addr:postcode":"4300",
    "addr:street":"Ahlgade",
    "iso:country":"DK",
    "sg:address":"Ahlgade 10",
    "sg:city":"Holb\u00e6k",
    "sg:orig_category":"Pool-Centre",
    "sg:phone":"+45 59 44 25 50",
    "sg:postcode":"4300",
    "sg:province":"Danmark",
    "wof:name":"Break Point",
    "wof:placetype":"venue"
},
  "geometry": {"coordinates":[76.3070983887,14.277130127],"type":"Point"}
}