{
  "type": "Feature",
  "properties": {
    "addr:full":"Gravene 2 Viborg Danmark 8800",
    "addr:housenumber":"2",
    "addr:postcode":"8800",
    "addr:street":"Gravene",
    "iso:country":"DK",
    "sg:address":"Gravene 2",
    "sg:city":"Viborg",
    "sg:orig_category":"Arkitekter",
    "sg:phone":"+45 86 61 15 33",
    "sg:postcode":"8800",
    "sg:province":"Danmark",
    "sg:website":"www.arkitektnet.dk",
    "wof:name":"Kjelgaard & Pedersen A/S",
    "wof:placetype":"venue"
},
  "geometry": {"coordinates":[9.4043884277,56.4496192932],"type":"Point"}
}