{
  "type": "Feature",
  "properties": {
    "addr:full":"Duevej 94 Frederiksberg Danmark 2000",
    "addr:housenumber":"94",
    "addr:postcode":"2000",
    "addr:street":"Duevej",
    "iso:country":"DK",
    "sg:address":"Duevej 94",
    "sg:city":"Frederiksberg",
    "sg:orig_category":"Psykologer, praktiserende",
    "sg:phone":"+45 38 10 34 03",
    "sg:postcode":"2000",
    "sg:province":"Danmark",
    "wof:name":"Selmer, Hanne",
    "wof:placetype":"venue"
},
  "geometry": {"coordinates":[12.5302181244,55.6923522949],"type":"Point"}
}