{
  "type": "Feature",
  "properties": {
    "addr:full":"Sydbanegade 7-11 Kolding Danmark 6000",
    "addr:housenumber":"7-11",
    "addr:postcode":"6000",
    "addr:street":"Sydbanegade",
    "iso:country":"DK",
    "sg:address":"Sydbanegade 7-11",
    "sg:city":"Kolding",
    "sg:orig_category":"Autoudlejning",
    "sg:phone":"+45 75 52 58 55",
    "sg:postcode":"6000",
    "sg:province":"Danmark",
    "sg:website":"www.hertzdk.dk",
    "wof:name":"Hertz Biludlejning A/S",
    "wof:placetype":"venue"
},
  "geometry": {"coordinates":[9.4622850418,55.4852981567],"type":"Point"}
}