{
  "type": "Feature",
  "properties": {
    "addr:full":"Carl Lendorfs Vej 11 Gilleleje Danmark 3250",
    "addr:housenumber":"11",
    "addr:postcode":"3250",
    "addr:street":"Carl Lendorfs Vej",
    "iso:country":"DK",
    "sg:address":"Carl Lendorfs Vej 11",
    "sg:city":"Gilleleje",
    "sg:orig_category":"Feriekolonier",
    "sg:phone":"+45 48 30 03 64",
    "sg:postcode":"3250",
    "sg:province":"Danmark",
    "wof:name":"Elim - Den danske Diakonissestiftelse",
    "wof:placetype":"venue"
},
  "geometry": {"coordinates":[12.3199090958,56.1226959229],"type":"Point"}
}