{
  "type": "Feature",
  "properties": {
    "addr:full":"Havnegade 47 K\u00f8benhavn Danmark 1058",
    "addr:housenumber":"47;1058",
    "addr:street":"Havnegade",
    "iso:country":"DK",
    "sg:address":"Havnegade 47",
    "sg:city":"K\u00f8benhavn",
    "sg:classifiers":[
        {
            "category":"Restaurant",
            "type":"Food & Drink"
        }
    ],
    "sg:phone":"+45 33 11 32 16",
    "sg:postcode":"1058",
    "sg:province":"Danmark",
    "wof:name":"El Gusto La Mexicana",
    "wof:placetype":"venue"
},
  "geometry": {"coordinates":[12.5905895233,55.6773414612],"type":"Point"}
}