{
  "type": "Feature",
  "properties": {
    "iso:country":"DK",
    "sg:address":"Borgergade 36",
    "sg:city":"Aalborg",
    "sg:classifiers":[
        {
            "category":"Restaurant",
            "type":"Food & Drink"
        }
    ],
    "sg:phone":"+45 98 11 55 40",
    "sg:postcode":"9000",
    "sg:province":"Danmark",
    "wof:name":"West-End, Restaurant",
    "wof:placetype":"venue"
},
  "geometry": {"coordinates":[9.913233757,57.0519752502],"type":"Point"}
}