{
  "type": "Feature",
  "properties": {
    "addr:full":"v/ Jens Askov, J\u00e6gervang 32 Birker\u00f8d Danmark 3460",
    "addr:housenumber":"32",
    "addr:postcode":"3460",
    "addr:street":"Birkerod Danmark",
    "iso:country":"DK",
    "sg:address":"v/ Jens Askov, J\u00e6gervang 32",
    "sg:city":"Birker\u00f8d",
    "sg:orig_category":"Grundejerforeninger",
    "sg:phone":"+45 45 81 40 43",
    "sg:postcode":"3460",
    "sg:province":"Danmark",
    "wof:name":"Eskemosevang Grundejerforening",
    "wof:placetype":"venue"
},
  "geometry": {"coordinates":[-92.7824630737,46.1881904602],"type":"Point"}
}