{
  "type": "Feature",
  "properties": {
    "iso:country":"DK",
    "sg:address":"Sct. Hansgade 33",
    "sg:city":"Ringsted",
    "sg:orig_category":"Ure og urmagere",
    "sg:phone":"+45 57 61 10 45",
    "sg:postcode":"4100",
    "sg:province":"Danmark",
    "wof:name":"Klokken",
    "wof:placetype":"venue"
},
  "geometry": {"coordinates":[11.7922182083,55.4438667297],"type":"Point"}
}