{
  "type": "Feature",
  "properties": {
    "addr:full":"Bredgade 45, 1. Herning Danmark 7400",
    "addr:housenumber":"45 1",
    "addr:postcode":"7400",
    "addr:street":"Bredgade",
    "iso:country":"DK",
    "sg:address":"Bredgade 45, 1.",
    "sg:city":"Herning",
    "sg:orig_category":"Forsikringer",
    "sg:phone":"+45 70 11 25 25",
    "sg:postcode":"7400",
    "sg:province":"Danmark",
    "wof:name":"Danica Pension",
    "wof:placetype":"venue"
},
  "geometry": {"coordinates":[8.970123291,56.1361351013],"type":"Point"}
}