{
  "type": "Feature",
  "properties": {
    "iso:country":"DK",
    "sg:address":"\u00d8stergade 5",
    "sg:city":"K\u00f8benhavn",
    "sg:classifiers":[
        {
            "category":"Professional",
            "subcategory":"Computer Services",
            "type":"Services"
        }
    ],
    "sg:phone":"+45 43 63 38 11",
    "sg:postcode":"1100",
    "sg:province":"Danmark",
    "sg:tags":[
        "edb",
        "-",
        "software"
    ],
    "wof:name":"Admiral Danmark A/S",
    "wof:placetype":"venue"
},
  "geometry": {"coordinates":[76.3070983887,14.277130127],"type":"Point"}
}