{
  "type": "Feature",
  "properties": {
    "addr:full":"Industrivej 17 Skibby Danmark 4050",
    "addr:housenumber":"17",
    "addr:postcode":"4050",
    "addr:street":"Industrivej",
    "iso:country":"DK",
    "sg:address":"Industrivej 17",
    "sg:city":"Skibby",
    "sg:orig_category":"Autolakering",
    "sg:phone":"+45 47 52 82 73",
    "sg:postcode":"4050",
    "sg:province":"Danmark",
    "wof:name":"Skibby Autolakereri",
    "wof:placetype":"venue"
},
  "geometry": {"coordinates":[11.9562044144,55.7563591003],"type":"Point"}
}