{
  "type": "Feature",
  "properties": {
    "addr:full":"Ny Moesg\u00e5rdvej 27 H\u00f8jbjerg Danmark 8270",
    "addr:housenumber":"27",
    "addr:postcode":"8270",
    "addr:street":"Moesgaardvej",
    "iso:country":"DK",
    "sg:address":"Ny Moesg\u00e5rdvej 27",
    "sg:city":"H\u00f8jbjerg",
    "sg:orig_category":"Radiotelefoner",
    "sg:phone":"+45 86 27 99 99",
    "sg:postcode":"8270",
    "sg:province":"Danmark",
    "wof:name":"Dansk Finans-Erhverv",
    "wof:placetype":"venue"
},
  "geometry": {"coordinates":[-76.50189208979999,42.8563194275],"type":"Point"}
}