{
  "type": "Feature",
  "properties": {
    "addr:full":"R\u00e5dhusgade 94 Odder Danmark 8300",
    "addr:housenumber":"94",
    "addr:postcode":"8300",
    "addr:street":"Raadhusgade",
    "iso:country":"DK",
    "sg:address":"R\u00e5dhusgade 94",
    "sg:city":"Odder",
    "sg:orig_category":"Campingvogne",
    "sg:phone":"+45 86 54 30 74",
    "sg:postcode":"8300",
    "sg:province":"Danmark",
    "sg:website":"www.odder-campingcenter.dk",
    "wof:name":"Odder Caravan-Center",
    "wof:placetype":"venue"
},
  "geometry": {"coordinates":[10.1524114609,55.9827384949],"type":"Point"}
}