{
  "type": "Feature",
  "properties": {
    "addr:full":"Gormsgade 25 Vejle Danmark 7100",
    "addr:housenumber":"25",
    "addr:postcode":"7100",
    "addr:street":"Gormsgade",
    "iso:country":"DK",
    "sg:address":"Gormsgade 25",
    "sg:city":"Vejle",
    "sg:orig_category":"Autotransport",
    "sg:phone":"+45 75 83 19 25",
    "sg:postcode":"7100",
    "sg:province":"Danmark",
    "wof:name":"Vejle Auto Transport",
    "wof:placetype":"venue"
},
  "geometry": {"coordinates":[9.53424263,55.7157897949],"type":"Point"}
}