{
  "type": "Feature",
  "properties": {
    "addr:full":"Karolinelundsvej Aalborg Danmark 9000",
    "addr:postcode":"9000",
    "addr:street":"Karolinelundsvej",
    "iso:country":"DK",
    "sg:address":"Karolinelundsvej",
    "sg:city":"Aalborg",
    "sg:orig_category":"Forlystelser",
    "sg:phone":"+45 98 12 33 15",
    "sg:postcode":"9000",
    "sg:province":"Danmark",
    "sg:website":"www.tivoliland.dk",
    "wof:name":"Tivoliland",
    "wof:placetype":"venue"
},
  "geometry": {"coordinates":[9.9343099594,57.0482139587],"type":"Point"}
}