{
  "type": "Feature",
  "properties": {
    "addr:full":"Peder Stubs Vej 24 Aars Danmark 9600",
    "addr:housenumber":"24",
    "addr:postcode":"9600",
    "addr:street":"Peder Stubs Vej",
    "iso:country":"DK",
    "sg:address":"Peder Stubs Vej 24",
    "sg:city":"Aars",
    "sg:orig_category":"Autoforhandlere",
    "sg:phone":"+45 98 62 20 84",
    "sg:postcode":"9600",
    "sg:province":"Danmark",
    "wof:name":"Kristensen, Niels Holst",
    "wof:placetype":"venue"
},
  "geometry": {"coordinates":[9.5264415741,56.7989273071],"type":"Point"}
}