{
  "type": "Feature",
  "properties": {
    "addr:full":"Horsev\u00e6nget 10, Vester Nebel Esbjerg N Danmark 6715",
    "addr:housenumber":"10",
    "addr:postcode":"6715",
    "addr:street":"Horsevaenget;Vester Nebel",
    "iso:country":"DK",
    "sg:address":"Horsev\u00e6nget 10, Vester Nebel",
    "sg:city":"Esbjerg N",
    "sg:orig_category":"Murermestre",
    "sg:phone":"+45 75 16 94 65",
    "sg:postcode":"6715",
    "sg:province":"Danmark",
    "wof:name":"Jensen, Elvin",
    "wof:placetype":"venue"
},
  "geometry": {"coordinates":[8.4780550003,55.535610199],"type":"Point"}
}