{
  "type": "Feature",
  "properties": {
    "addr:full":"Hvidelvej 8 Herning Danmark 7400",
    "addr:housenumber":"8",
    "addr:postcode":"7400",
    "addr:street":"Hvidelvej",
    "iso:country":"DK",
    "sg:address":"Hvidelvej 8",
    "sg:city":"Herning",
    "sg:orig_category":"Autoreparation og -service",
    "sg:phone":"+45 97 21 41 20",
    "sg:postcode":"7400",
    "sg:province":"Danmark",
    "wof:name":"Werners Auto",
    "wof:placetype":"venue"
},
  "geometry": {"coordinates":[8.9321222305,56.1282157898],"type":"Point"}
}