{
  "type": "Feature",
  "properties": {
    "addr:full":"Rosenlunden 15 - 17 Odense C Danmark 5000",
    "addr:housenumber":"15 17",
    "addr:postcode":"5000",
    "addr:street":"Rosenlunden",
    "iso:country":"DK",
    "sg:address":"Rosenlunden 15 - 17",
    "sg:city":"Odense C",
    "sg:orig_category":"Trossamfund uden for folkekirken",
    "sg:phone":"+45 66 19 10 05",
    "sg:postcode":"5000",
    "sg:province":"Danmark",
    "wof:name":"Missionsforbundets Kirke (Godth\u00e5bskirken)",
    "wof:placetype":"venue"
},
  "geometry": {"coordinates":[10.3940200806,55.3900985718],"type":"Point"}
}