{
  "type": "Feature",
  "properties": {
    "addr:full":"Vintappervej 88, Jenslev Kirke Hyllinge Danmark 4070",
    "addr:housenumber":"88",
    "addr:postcode":"4070",
    "addr:street":"Vintappervej;Jenslev",
    "iso:country":"DK",
    "sg:address":"Vintappervej 88, Jenslev",
    "sg:city":"Kirke Hyllinge",
    "sg:orig_category":"Socialpsykiatriske bosteder",
    "sg:phone":"+45 46 40 50 45",
    "sg:postcode":"4070",
    "sg:province":"Danmark",
    "wof:name":"Solvang",
    "wof:placetype":"venue"
},
  "geometry": {"coordinates":[11.9004745483,55.7080039978],"type":"Point"}
}