{
  "type": "Feature",
  "properties": {
    "addr:full":"Borneovej 7 K\u00f8benhavn S Danmark 2300",
    "addr:housenumber":"7",
    "addr:postcode":"2300",
    "addr:street":"Borneovej;S Danmark",
    "iso:country":"DK",
    "sg:address":"Borneovej 7",
    "sg:city":"K\u00f8benhavn S",
    "sg:orig_category":"Murermestre",
    "sg:phone":"+45 32 58 97 79",
    "sg:postcode":"2300",
    "sg:province":"Danmark",
    "wof:name":"Pedersen, Niels Erik",
    "wof:placetype":"venue"
},
  "geometry": {"coordinates":[-72.34271240229999,41.1164283752],"type":"Point"}
}