{
  "type": "Feature",
  "properties": {
    "addr:full":"\u00c6girsgade 49 K\u00f8benhavn N Danmark 2200",
    "addr:housenumber":"49",
    "addr:postcode":"2200",
    "addr:street":"Aegirsgade;Kobenhavn N Danmark",
    "iso:country":"DK",
    "sg:address":"\u00c6girsgade 49",
    "sg:city":"K\u00f8benhavn N",
    "sg:classifiers":[
        {
            "category":"Restaurant",
            "type":"Food & Drink"
        }
    ],
    "sg:phone":"+45 35 85 73 00",
    "sg:postcode":"2200",
    "sg:province":"Danmark",
    "wof:name":"Esperia Pizza Bar",
    "wof:placetype":"venue"
},
  "geometry": {"coordinates":[-75.7513656616,43.2285461426],"type":"Point"}
}