{
  "type": "Feature",
  "properties": {
    "addr:full":"Skolevangen 6 Hornslet Danmark 8543",
    "addr:housenumber":"6",
    "addr:postcode":"8543",
    "addr:street":"Skolevangen",
    "iso:country":"DK",
    "sg:address":"Skolevangen 6",
    "sg:city":"Hornslet",
    "sg:orig_category":"Cykler",
    "sg:phone":"+45 86 99 50 33",
    "sg:postcode":"8543",
    "sg:province":"Danmark",
    "wof:name":"ABC Centeret",
    "wof:placetype":"venue"
},
  "geometry": {"coordinates":[10.3171510696,56.3157653809],"type":"Point"}
}