{
  "type": "Feature",
  "properties": {
    "addr:full":"Formervangen 15 A Glostrup Danmark 2600",
    "addr:housenumber":"15 a",
    "addr:postcode":"2600",
    "addr:street":"Formervangen",
    "iso:country":"DK",
    "sg:address":"Formervangen 15 A",
    "sg:city":"Glostrup",
    "sg:orig_category":"Autoreparation og -service",
    "sg:phone":"+45 43 96 32 18",
    "sg:postcode":"2600",
    "sg:province":"Danmark",
    "sg:website":"www.torbens-autocenter.dk",
    "wof:name":"Torben's Autocenter ApS",
    "wof:placetype":"venue"
},
  "geometry": {"coordinates":[12.371846199,55.681186676],"type":"Point"}
}