{
  "type": "Feature",
  "properties": {
    "addr:full":"Gasv\u00e6rksvej 4 Aabenraa Danmark 6200",
    "addr:housenumber":"4",
    "addr:postcode":"6200",
    "addr:street":"Gasvaerksvej",
    "iso:country":"DK",
    "sg:address":"Gasv\u00e6rksvej 4",
    "sg:city":"Aabenraa",
    "sg:orig_category":"Faglige organisationer og foreninger",
    "sg:phone":"+45 74 62 84 22",
    "sg:postcode":"6200",
    "sg:province":"Danmark",
    "wof:name":"SID Chauff\u00f8rernes Fagforening",
    "wof:placetype":"venue"
},
  "geometry": {"coordinates":[9.4231767654,55.0441513062],"type":"Point"}
}