{
  "type": "Feature",
  "properties": {
    "addr:full":"N\u00f8rremarksvej 19, \u00d8land Brovst Danmark 9460",
    "addr:housenumber":"19",
    "addr:postcode":"9460",
    "addr:street":"Norremarksvej;Oland",
    "iso:country":"DK",
    "sg:address":"N\u00f8rremarksvej 19, \u00d8land",
    "sg:city":"Brovst",
    "sg:orig_category":"Autoforhandlere",
    "sg:phone":"+45 98 23 62 99",
    "sg:postcode":"9460",
    "sg:province":"Danmark",
    "wof:name":"Br\u00f8ndum Biler",
    "wof:placetype":"venue"
},
  "geometry": {"coordinates":[9.5220241547,57.097366333],"type":"Point"}
}