{
  "type": "Feature",
  "properties": {
    "iso:country":"DK",
    "sg:address":"Hjelmvej 9, Mogenstrup",
    "sg:city":"Skive",
    "sg:orig_category":"Gallerier",
    "sg:phone":"+45 97 54 40 86",
    "sg:postcode":"7800",
    "sg:province":"Danmark",
    "wof:name":"Petrea, Galleri",
    "wof:placetype":"venue"
},
  "geometry": {"coordinates":[9.0320358276,56.5666427612],"type":"Point"}
}