{
  "type": "Feature",
  "properties": {
    "iso:country":"DK",
    "sg:address":"Nygade 19",
    "sg:city":"Nyk\u00f8bing",
    "sg:orig_category":"Cykler",
    "sg:phone":"+45 97 72 02 68",
    "sg:postcode":"7900",
    "sg:province":"Danmark",
    "wof:name":"Skov's Cykler",
    "wof:placetype":"venue"
},
  "geometry": {"coordinates":[8.8630752563,56.7945251465],"type":"Point"}
}