{
  "type": "Feature",
  "properties": {
    "addr:full":"Stenholt 3, Klinting S\u00f8nderborg Danmark 6400",
    "addr:housenumber":"3",
    "addr:postcode":"6400",
    "addr:street":"Stenholt",
    "iso:country":"DK",
    "sg:address":"Stenholt 3, Klinting",
    "sg:city":"S\u00f8nderborg",
    "sg:orig_category":"Rideskoler",
    "sg:phone":"+45 74 42 22 96",
    "sg:postcode":"6400",
    "sg:province":"Danmark",
    "wof:name":"Stenholt Ridecenter",
    "wof:placetype":"venue"
},
  "geometry": {"coordinates":[9.7899465561,54.9100151062],"type":"Point"}
}