{
  "type": "Feature",
  "properties": {
    "addr:full":"Danmarksgade 17, 1. Odense C Danmark 5000",
    "addr:housenumber":"17 1",
    "addr:postcode":"5000",
    "addr:street":"Danmarksgade",
    "iso:country":"DK",
    "sg:address":"Danmarksgade 17, 1.",
    "sg:city":"Odense C",
    "sg:classifiers":[
        {
            "category":"Professional",
            "subcategory":"Computer Services",
            "type":"Services"
        }
    ],
    "sg:phone":"+45 66 12 44 34",
    "sg:postcode":"5000",
    "sg:province":"Danmark",
    "sg:tags":[
        "edb",
        "-",
        "software"
    ],
    "wof:name":"Hylleberg, Roar",
    "wof:placetype":"venue"
},
  "geometry": {"coordinates":[10.3994474411,55.4002380371],"type":"Point"}
}