{
  "type": "Feature",
  "properties": {
    "addr:full":"Fjordvej 25 Randers Danmark 8900",
    "addr:housenumber":"25",
    "addr:postcode":"8900",
    "addr:street":"Fjordvej",
    "iso:country":"DK",
    "sg:address":"Fjordvej 25",
    "sg:city":"Randers",
    "sg:orig_category":"Bilinspektion",
    "sg:phone":"+45 86 43 45 10",
    "sg:postcode":"8900",
    "sg:province":"Danmark",
    "sg:website":"www.bilsyn.dk",
    "wof:name":"Statens Bilinspektion",
    "wof:placetype":"venue"
},
  "geometry": {"coordinates":[10.08002,56.4697],"type":"Point"}
}