{
  "type": "Feature",
  "properties": {
    "addr:full":"Fanefjordgade 49, Askeby Askeby Danmark 4792",
    "addr:housenumber":"49",
    "addr:postcode":"4792",
    "addr:street":"Fanefjordgade",
    "iso:country":"DK",
    "sg:address":"Fanefjordgade 49, Askeby",
    "sg:city":"Askeby",
    "sg:orig_category":"Malermestre",
    "sg:phone":"+45 55 81 75 76",
    "sg:postcode":"4792",
    "sg:province":"Danmark",
    "wof:name":"Jutta & J\u00f8rgens Malerfirma",
    "wof:placetype":"venue"
},
  "geometry": {"coordinates":[12.1452455521,54.8838500977],"type":"Point"}
}