{
  "type": "Feature",
  "properties": {
    "addr:full":"Kastanievej 21 Rudk\u00f8bing Danmark 5900",
    "addr:housenumber":"21",
    "addr:postcode":"5900",
    "addr:street":"Kastanievej",
    "iso:country":"DK",
    "sg:address":"Kastanievej 21",
    "sg:city":"Rudk\u00f8bing",
    "sg:orig_category":"Engros handel",
    "sg:phone":"+45 62 51 47 10",
    "sg:postcode":"5900",
    "sg:province":"Danmark",
    "wof:name":"Riis, S\u00f8ren Bjerregaard",
    "wof:placetype":"venue"
},
  "geometry": {"coordinates":[10.7170124054,54.9404296875],"type":"Point"}
}