{
  "type": "Feature",
  "properties": {
    "addr:full":"Skovbrynet 9 Bjerringbro Danmark 8850",
    "addr:housenumber":"9",
    "addr:postcode":"8850",
    "addr:street":"Skovbrynet",
    "iso:country":"DK",
    "sg:address":"Skovbrynet 9",
    "sg:city":"Bjerringbro",
    "sg:classifiers":[
        {
            "category":"Taxi",
            "type":"Transportation"
        }
    ],
    "sg:phone":"+45 86 68 25 22",
    "sg:postcode":"8850",
    "sg:province":"Danmark",
    "wof:name":"S\u00f8nderbro's Taxi",
    "wof:placetype":"venue"
},
  "geometry": {"coordinates":[9.6521863937,56.380027771],"type":"Point"}
}