{
  "type": "Feature",
  "properties": {
    "addr:full":"v/ Aage Larsen, Kystvej 161, Dokkedal Storvorde Danmark 9280",
    "addr:housenumber":"161",
    "addr:postcode":"9280",
    "addr:street":"Kystvej;Dokkedal",
    "iso:country":"DK",
    "sg:address":"v/ Aage Larsen, Kystvej 161, Dokkedal",
    "sg:city":"Storvorde",
    "sg:orig_category":"Hobbybetonede foreninger",
    "sg:phone":"+45 98 31 16 83",
    "sg:postcode":"9280",
    "sg:province":"Danmark",
    "wof:name":"Dokkedal B\u00e5delaug",
    "wof:placetype":"venue"
},
  "geometry": {"coordinates":[10.1014204025,57.0045547485],"type":"Point"}
}