{
  "type": "Feature",
  "properties": {
    "iso:country":"DK",
    "sg:address":"Hovedgaden 55, Ingstrup",
    "sg:city":"L\u00f8kken",
    "sg:orig_category":"Brugskunst",
    "sg:phone":"+45 98 88 32 88",
    "sg:postcode":"9480",
    "sg:province":"Danmark",
    "wof:name":"Aspects of Life",
    "wof:placetype":"venue"
},
  "geometry": {"coordinates":[9.715880394,57.3703308105],"type":"Point"}
}