{
  "type": "Feature",
  "properties": {
    "addr:full":"Fmd.: Peter Lassen, S\u00f8ndergade 35 Nibe Danmark 9240",
    "addr:housenumber":"35",
    "addr:postcode":"9240",
    "addr:street":"Sondergade",
    "iso:country":"DK",
    "sg:address":"Fmd.: Peter Lassen, S\u00f8ndergade 35",
    "sg:city":"Nibe",
    "sg:orig_category":"Hobbybetonede foreninger",
    "sg:phone":"+45 98 35 13 29",
    "sg:postcode":"9240",
    "sg:province":"Danmark",
    "wof:name":"Nibe Havekreds",
    "wof:placetype":"venue"
},
  "geometry": {"coordinates":[9.6393280029,56.982421875],"type":"Point"}
}