{
  "type": "Feature",
  "properties": {
    "addr:full":"Spliidsvej 25 A Skagen Danmark 9990",
    "addr:housenumber":"25 a",
    "addr:postcode":"9990",
    "addr:street":"Spliidsvej",
    "iso:country":"DK",
    "sg:address":"Spliidsvej 25 A",
    "sg:city":"Skagen",
    "sg:orig_category":"Revisorer",
    "sg:phone":"+45 96 79 19 00",
    "sg:postcode":"9990",
    "sg:province":"Danmark",
    "sg:website":"www.bdo.dk",
    "wof:name":"BDO ScanRevision",
    "wof:placetype":"venue"
},
  "geometry": {"coordinates":[10.5937566757,57.7277908325],"type":"Point"}
}