{
  "type": "Feature",
  "properties": {
    "addr:full":"Stensagervej 8, Sdr. Bork Hemmet Danmark 6893",
    "addr:housenumber":"8",
    "addr:postcode":"6893",
    "addr:street":"Stensagervej;Bork",
    "iso:country":"DK",
    "sg:address":"Stensagervej 8, Sdr. Bork",
    "sg:city":"Hemmet",
    "sg:orig_category":"Autoforhandlere",
    "sg:phone":"+45 75 28 08 07",
    "sg:postcode":"6893",
    "sg:province":"Danmark",
    "wof:name":"Autohandel",
    "wof:placetype":"venue"
},
  "geometry": {"coordinates":[8.2862300873,55.8409957886],"type":"Point"}
}