{
  "type": "Feature",
  "properties": {
    "addr:full":"S\u00f8ager 5, St. Valby Roskilde Danmark 4000",
    "addr:housenumber":"5",
    "addr:postcode":"4000",
    "addr:street":"Soager",
    "iso:country":"DK",
    "sg:address":"S\u00f8ager 5, St. Valby",
    "sg:city":"Roskilde",
    "sg:orig_category":"Glarmestre og glarmagere",
    "sg:phone":"+45 46 78 72 83",
    "sg:postcode":"4000",
    "sg:province":"Danmark",
    "wof:name":"Alt i glas - Gunds\u00f8 Glarmesteren",
    "wof:placetype":"venue"
},
  "geometry": {"coordinates":[12.0909376144,55.6404838562],"type":"Point"}
}