{
  "type": "Feature",
  "properties": {
    "addr:full":"Rantzausgade 37 Aalborg Danmark 9000",
    "addr:housenumber":"37",
    "addr:postcode":"9000",
    "addr:street":"Rantzausgade",
    "iso:country":"DK",
    "sg:address":"Rantzausgade 37",
    "sg:city":"Aalborg",
    "sg:orig_category":"Psykoterapi",
    "sg:phone":"+45 98 13 32 61",
    "sg:postcode":"9000",
    "sg:province":"Danmark",
    "wof:name":"Sandegaard, Knud Lynge",
    "wof:placetype":"venue"
},
  "geometry": {"coordinates":[9.920290947,57.0434799194],"type":"Point"}
}