{
  "type": "Feature",
  "properties": {
    "addr:full":"Hovedgaden 17 C Ulstrup Danmark 8860",
    "addr:housenumber":"17 c",
    "addr:postcode":"8860",
    "addr:street":"Hovedgaden",
    "iso:country":"DK",
    "sg:address":"Hovedgaden 17 C",
    "sg:city":"Ulstrup",
    "sg:orig_category":"Blomsterhandlere",
    "sg:phone":"+45 86 46 39 67",
    "sg:postcode":"8860",
    "sg:province":"Danmark",
    "wof:name":"Blomster torvet",
    "wof:placetype":"venue"
},
  "geometry": {"coordinates":[9.794251442,56.3913459778],"type":"Point"}
}