{
  "type": "Feature",
  "properties": {
    "addr:full":"Skolegade 1, Thorsminde Ulfborg Danmark 6990",
    "addr:housenumber":"1",
    "addr:postcode":"6990",
    "addr:street":"Skolegade;Thorsminde",
    "iso:country":"DK",
    "sg:address":"Skolegade 1, Thorsminde",
    "sg:city":"Ulfborg",
    "sg:classifiers":[
        {
            "category":"Banks & Credit Unions",
            "subcategory":"Bank",
            "type":"Services"
        }
    ],
    "sg:phone":"+45 97 49 72 66",
    "sg:postcode":"6990",
    "sg:province":"Danmark",
    "sg:tags":[
        "banker"
    ],
    "wof:name":"Ringkj\u00f8bing Landbobank A/S - Thorsminde afd.",
    "wof:placetype":"venue"
},
  "geometry": {"coordinates":[8.321003,56.272766],"type":"Point"}
}