{
  "type": "Feature",
  "properties": {
    "addr:full":"Fmd.: Erling Hansen, Ellestedvej 5, Ellested \u00d8rb\u00e6k Danmark 5853",
    "addr:housenumber":"5",
    "addr:postcode":"5853",
    "addr:street":"Erling;Ellestedvej",
    "iso:country":"DK",
    "sg:address":"Fmd.: Erling Hansen, Ellestedvej 5, Ellested",
    "sg:city":"\u00d8rb\u00e6k",
    "sg:orig_category":"Faglige organisationer og foreninger",
    "sg:phone":"+45 65 33 15 01",
    "sg:postcode":"5853",
    "sg:province":"Danmark",
    "sg:website":"www.korekort.dk",
    "wof:name":"Dansk K\u00f8rel\u00e6rer Union",
    "wof:placetype":"venue"
},
  "geometry": {"coordinates":[10.6713848114,55.2553749084],"type":"Point"}
}