{
  "type": "Feature",
  "properties": {
    "iso:country":"DK",
    "sg:address":"N\u00f8r-Eng 6, \u00d8. Vedsted",
    "sg:city":"Ribe",
    "sg:orig_category":"Kommunale folkeskoler",
    "sg:phone":"+45 75 42 31 90",
    "sg:postcode":"6760",
    "sg:province":"Danmark",
    "wof:name":"\u00d8. Vedsted Skole",
    "wof:placetype":"venue"
},
  "geometry": {"coordinates":[8.7656240463,55.3297042847],"type":"Point"}
}