{
  "type": "Feature",
  "properties": {
    "addr:full":"Algade 70 Middelfart Danmark 5500",
    "addr:housenumber":"70",
    "addr:postcode":"5500",
    "addr:street":"Algade",
    "iso:country":"DK",
    "sg:address":"Algade 70",
    "sg:city":"Middelfart",
    "sg:orig_category":"Sportsartikler",
    "sg:phone":"+45 64 41 66 11",
    "sg:postcode":"5500",
    "sg:province":"Danmark",
    "wof:name":"\u00d8stergaard Sport ApS",
    "wof:placetype":"venue"
},
  "geometry": {"coordinates":[9.7346105576,55.5044937134],"type":"Point"}
}