{
  "type": "Feature",
  "properties": {
    "iso:country":"DK",
    "sg:address":"Kilen 40 ",
    "sg:city":"Aabenraa",
    "sg:classifiers":[
        {
            "category":"Autos & Motor Vehicles",
            "subcategory":"Boat Sales",
            "type":"Retail Goods"
        }
    ],
    "sg:phone":"+45 74 62 25 20",
    "sg:postcode":"6200",
    "sg:province":"Danmark",
    "wof:name":"\u00c5BENR\u00c5 V\u00c6RFT A/S",
    "wof:placetype":"venue"
},
  "geometry": {"coordinates":[6.9277501106,62.3078384399],"type":"Point"}
}