{
  "type": "Feature",
  "properties": {
    "addr:full":"Fmd.: Janet \u00d8rnby Andersen, Flintevej 35, Fensmark N\u00e6stved Danmark 4700",
    "addr:housenumber":"35",
    "addr:postcode":"4700",
    "addr:street":"Flintevej",
    "iso:country":"DK",
    "sg:address":"Fmd.: Janet \u00d8rnby Andersen, Flintevej 35, Fensmark",
    "sg:city":"N\u00e6stved",
    "sg:orig_category":"Grundejerforeninger",
    "sg:phone":"+45 55 54 69 70",
    "sg:postcode":"4700",
    "sg:province":"Danmark",
    "wof:name":"Lundeg\u00e5rden, Grundejerforeningen",
    "wof:placetype":"venue"
},
  "geometry": {"coordinates":[11.7542486191,55.2315444946],"type":"Point"}
}