{
  "type": "Feature",
  "properties": {
    "addr:full":"Rendebanen 14 Kolding Danmark 6000",
    "addr:housenumber":"14",
    "addr:postcode":"6000",
    "addr:street":"Rendebanen",
    "iso:country":"DK",
    "sg:address":"Rendebanen 14",
    "sg:city":"Kolding",
    "sg:classifiers":[
        {
            "category":"Banks & Credit Unions",
            "subcategory":"Bank",
            "type":"Services"
        }
    ],
    "sg:phone":"+45 76 30 23 70",
    "sg:postcode":"6000",
    "sg:province":"Danmark",
    "sg:tags":[
        "banker"
    ],
    "wof:name":"Alm. Brand Bank",
    "wof:placetype":"venue"
},
  "geometry": {"coordinates":[9.4723653793,55.4889564514],"type":"Point"}
}