{
  "type": "Feature",
  "properties": {
    "addr:full":"B\u00e6kg\u00e5rdsvej 2 Borup Danmark 4140",
    "addr:housenumber":"2",
    "addr:postcode":"4140",
    "addr:street":"Baekgaardsvej",
    "iso:country":"DK",
    "sg:address":"B\u00e6kg\u00e5rdsvej 2",
    "sg:city":"Borup",
    "sg:orig_category":"Bogtrykkerier",
    "sg:phone":"+45 57 52 62 96",
    "sg:postcode":"4140",
    "sg:province":"Danmark",
    "sg:website":"www.altatryk.dk",
    "wof:name":"Alta Tryk",
    "wof:placetype":"venue"
},
  "geometry": {"coordinates":[11.9749145508,55.4920845032],"type":"Point"}
}