{
  "type": "Feature",
  "properties": {
    "iso:country":"DK",
    "sg:address":"Industrivej 12 - 20",
    "sg:city":"Langeskov",
    "sg:orig_category":"Industri",
    "sg:phone":"+45 63 38 22 22",
    "sg:postcode":"5550",
    "sg:province":"Danmark",
    "sg:website":"www.iai.dk",
    "wof:name":"Andresen Industri A/S, Ib",
    "wof:placetype":"venue"
},
  "geometry": {"coordinates":[10.5718994141,55.3551025391],"type":"Point"}
}