{
  "type": "Feature",
  "properties": {
    "addr:full":"Farverland 6 Glostrup Danmark 2600",
    "addr:housenumber":"6",
    "addr:postcode":"2600",
    "addr:street":"Farverland",
    "iso:country":"DK",
    "sg:address":"Farverland 6",
    "sg:city":"Glostrup",
    "sg:orig_category":"Trykkerier",
    "sg:phone":"+45 43 43 40 00",
    "sg:postcode":"2600",
    "sg:province":"Danmark",
    "wof:name":"Levison+Johnsen+Johnsen a/s",
    "wof:placetype":"venue"
},
  "geometry": {"coordinates":[12.3833236694,55.6823425293],"type":"Point"}
}