{
  "type": "Feature",
  "properties": {
    "addr:full":"Gl. \u00c5rhusvej 136 Viborg Danmark 8800",
    "addr:housenumber":"136",
    "addr:postcode":"8800",
    "addr:street":"Gl. Aarhusvej",
    "iso:country":"DK",
    "sg:address":"Gl. \u00c5rhusvej 136",
    "sg:city":"Viborg",
    "sg:orig_category":"EDB - udstyr",
    "sg:phone":"+45 86 61 40 40",
    "sg:postcode":"8800",
    "sg:province":"Danmark",
    "sg:website":"www.egc.dk",
    "wof:name":"Engros Center",
    "wof:placetype":"venue"
},
  "geometry": {"coordinates":[9.4027671814,56.4267044067],"type":"Point"}
}