{
  "type": "Feature",
  "properties": {
    "addr:full":"Stenskovvej 16, Fensmark N\u00e6stved Danmark 4700",
    "addr:housenumber":"16",
    "addr:postcode":"4700",
    "addr:street":"Stenskovvej",
    "iso:country":"DK",
    "sg:address":"Stenskovvej 16, Fensmark",
    "sg:city":"N\u00e6stved",
    "sg:classifiers":[
        {
            "category":"Personal",
            "subcategory":"Massage",
            "type":"Services"
        }
    ],
    "sg:phone":"+45 55 54 53 04",
    "sg:postcode":"4700",
    "sg:province":"Danmark",
    "wof:name":"Aphisara Sun",
    "wof:placetype":"venue"
},
  "geometry": {"coordinates":[11.7542486191,55.2315444946],"type":"Point"}
}