{
  "type": "Feature",
  "properties": {
    "iso:country":"DK",
    "sg:address":"Gammel K\u00f8ge Landevej 55 3.",
    "sg:city":"Valby",
    "sg:classifiers":[
        {
            "category":"Internet Cafe",
            "subcategory":"None",
            "type":"Food & Drink"
        }
    ],
    "sg:phone":"+45 77 30 06 70",
    "sg:postcode":"2500",
    "sg:province":"Danmark",
    "sg:website":"www.dk-hostmaster.dk",
    "wof:name":"Dk Hostmaster A/S",
    "wof:placetype":"venue"
},
  "geometry": {"coordinates":[12.5140161514,55.6579818726],"type":"Point"}
}