{
  "type": "Feature",
  "properties": {
    "addr:full":"Fabjergstad 34, Fabjerg Lemvig Danmark 7620",
    "addr:housenumber":"34",
    "addr:postcode":"7620",
    "addr:street":"Fabjergstad",
    "iso:country":"DK",
    "sg:address":"Fabjergstad 34, Fabjerg",
    "sg:city":"Lemvig",
    "sg:orig_category":"Integrerede institutioner",
    "sg:phone":"+45 97 89 30 73",
    "sg:postcode":"7620",
    "sg:province":"Danmark",
    "wof:name":"Solstr\u00e5len",
    "wof:placetype":"venue"
},
  "geometry": {"coordinates":[8.3073654175,56.5505104065],"type":"Point"}
}