{
  "type": "Feature",
  "properties": {
    "addr:full":"C. S. M\u00f8llers Vej 4 Skagen Danmark 9990",
    "addr:housenumber":"4",
    "addr:postcode":"9990",
    "addr:street":"C. S. Mollers Vej",
    "iso:country":"DK",
    "sg:address":"C. S. M\u00f8llers Vej 4",
    "sg:city":"Skagen",
    "sg:orig_category":"Erhvervsudvikling",
    "sg:phone":"+45 99 79 55 13",
    "sg:postcode":"9990",
    "sg:province":"Danmark",
    "sg:website":"www.skagen-erhverv.dk",
    "wof:name":"Erhvervshuset",
    "wof:placetype":"venue"
},
  "geometry": {"coordinates":[10.58527565,57.7196731567],"type":"Point"}
}