{
  "type": "Feature",
  "properties": {
    "addr:full":"Algade 5, Ramme Lemvig Danmark 7620",
    "addr:housenumber":"5",
    "addr:postcode":"7620",
    "addr:street":"Algade",
    "iso:country":"DK",
    "sg:address":"Algade 5, Ramme",
    "sg:city":"Lemvig",
    "sg:orig_category":"Malermestre",
    "sg:phone":"+45 97 88 97 24",
    "sg:postcode":"7620",
    "sg:province":"Danmark",
    "wof:name":"Dybdahl, Aage",
    "wof:placetype":"venue"
},
  "geometry": {"coordinates":[8.3073654175,56.5505104065],"type":"Point"}
}