{
  "type": "Feature",
  "properties": {
    "iso:country":"DK",
    "sg:address":"Hovedgaden Regstrup 41, Nr. Jernl\u00f8se",
    "sg:city":"Regstrup",
    "sg:orig_category":"Biavlere",
    "sg:phone":"+45 59 47 14 57",
    "sg:postcode":"4420",
    "sg:province":"Danmark",
    "wof:name":"Rasmussen, Frede",
    "wof:placetype":"venue"
},
  "geometry": {"coordinates":[11.613177,55.676964],"type":"Point"}
}