{
  "type": "Feature",
  "properties": {
    "iso:country":"DK",
    "sg:address":"Fynsvej 5",
    "sg:city":"Bogense",
    "sg:orig_category":"Varmeforsyning",
    "sg:phone":"+45 64 81 16 10",
    "sg:postcode":"5400",
    "sg:province":"Danmark",
    "wof:name":"Andelsselskabet Bogense Fjernvarme",
    "wof:placetype":"venue"
},
  "geometry": {"coordinates":[10.0878887177,55.5522918701],"type":"Point"}
}