{
  "type": "Feature",
  "properties": {
    "addr:full":"Vestergade 7 A Aabenraa Danmark 6200",
    "addr:housenumber":"7 a",
    "addr:postcode":"6200",
    "addr:street":"Vestergade",
    "iso:country":"DK",
    "sg:address":"Vestergade 7 A",
    "sg:city":"Aabenraa",
    "sg:classifiers":[
        {
            "category":"Restaurant",
            "type":"Food & Drink"
        }
    ],
    "sg:phone":"+45 74 62 27 36",
    "sg:postcode":"6200",
    "sg:province":"Danmark",
    "wof:name":"Mongolian Barbeque",
    "wof:placetype":"venue"
},
  "geometry": {"coordinates":[9.4181203842,55.0421676636],"type":"Point"}
}