{
  "type": "Feature",
  "properties": {
    "addr:full":"Knud Rasmussens Vej 14 S\u00f8borg Danmark 2860",
    "addr:housenumber":"14",
    "addr:postcode":"2860",
    "addr:street":"Knud Rasmussens Vej",
    "iso:country":"DK",
    "sg:address":"Knud Rasmussens Vej 14",
    "sg:city":"S\u00f8borg",
    "sg:orig_category":"Alternativ behandling",
    "sg:phone":"+45 39 67 16 19",
    "sg:postcode":"2860",
    "sg:province":"Danmark",
    "sg:website":"www.image.dk/~fm_as/marna/",
    "wof:name":"Helsehuset",
    "wof:placetype":"venue"
},
  "geometry": {"coordinates":[-101.38994598390001,35.6939697266],"type":"Point"}
}