{
  "type": "Feature",
  "properties": {
    "addr:full":"Arres\u00f8vej 12 Risskov Danmark 8240",
    "addr:housenumber":"12",
    "addr:postcode":"8240",
    "addr:street":"Arresovej",
    "iso:country":"DK",
    "sg:address":"Arres\u00f8vej 12",
    "sg:city":"Risskov",
    "sg:orig_category":"Autoreparation og -service",
    "sg:phone":"+45 86 17 38 00",
    "sg:postcode":"8240",
    "sg:province":"Danmark",
    "wof:name":"Hennings Auto ApS",
    "wof:placetype":"venue"
},
  "geometry": {"coordinates":[10.2341432571,56.2024345398],"type":"Point"}
}