{
  "type": "Feature",
  "properties": {
    "iso:country":"DK",
    "sg:address":"Storegade 23",
    "sg:city":"Thisted",
    "sg:orig_category":"Arkitekter",
    "sg:phone":"+45 97 92 57 22",
    "sg:postcode":"7700",
    "sg:province":"Danmark",
    "wof:name":"Christoffersen, Niels",
    "wof:placetype":"venue"
},
  "geometry": {"coordinates":[8.6937427521,56.9550514221],"type":"Point"}
}