{
  "type": "Feature",
  "properties": {
    "addr:full":"Diskovej 2 Vejle Danmark 7100",
    "addr:housenumber":"2",
    "addr:postcode":"7100",
    "addr:street":"Diskovej",
    "iso:country":"DK",
    "sg:address":"Diskovej 2",
    "sg:city":"Vejle",
    "sg:orig_category":"Isolering",
    "sg:phone":"+45 75 82 17 22",
    "sg:postcode":"7100",
    "sg:province":"Danmark",
    "wof:name":"Persolit A/S",
    "wof:placetype":"venue"
},
  "geometry": {"coordinates":[9.5313186646,55.6751251221],"type":"Point"}
}