{
  "type": "Feature",
  "properties": {
    "addr:full":"Svendborgvej 68 Faaborg Danmark 5600",
    "addr:housenumber":"68",
    "addr:postcode":"5600",
    "addr:street":"Svendborgvej",
    "iso:country":"DK",
    "sg:address":"Svendborgvej 68",
    "sg:city":"Faaborg",
    "sg:orig_category":"Blomsterhandlere",
    "sg:phone":"+45 62 61 12 12",
    "sg:postcode":"5600",
    "sg:province":"Danmark",
    "wof:name":"Blomstersmeden",
    "wof:placetype":"venue"
},
  "geometry": {"coordinates":[10.2613897324,55.0873908997],"type":"Point"}
}