{
  "type": "Feature",
  "properties": {
    "addr:full":"Mj\u00f8lnersvej 4 Glostrup Danmark 2600",
    "addr:housenumber":"4",
    "addr:postcode":"2600",
    "addr:street":"Mjolnersvej",
    "iso:country":"DK",
    "sg:address":"Mj\u00f8lnersvej 4",
    "sg:city":"Glostrup",
    "sg:orig_category":"Engros handel",
    "sg:phone":"+45 46 96 00 00",
    "sg:postcode":"2600",
    "sg:province":"Danmark",
    "sg:website":"www.armatec.dk",
    "wof:name":"Armatec A/S",
    "wof:placetype":"venue"
},
  "geometry": {"coordinates":[12.3797988892,55.6639900208],"type":"Point"}
}