{
  "type": "Feature",
  "properties": {
    "addr:full":"Kirkevej 1 B Klampenborg Danmark 2930",
    "addr:housenumber":"1 b",
    "addr:postcode":"2930",
    "addr:street":"Kirkevej",
    "iso:country":"DK",
    "sg:address":"Kirkevej 1 B",
    "sg:city":"Klampenborg",
    "sg:orig_category":"Zoneterapeuter",
    "sg:phone":"+45 39 63 16 65",
    "sg:postcode":"2930",
    "sg:province":"Danmark",
    "wof:name":"Falkj\u00e6r, Birgit",
    "wof:placetype":"venue"
},
  "geometry": {"coordinates":[12.5929489136,55.7898101807],"type":"Point"}
}