{
  "type": "Feature",
  "properties": {
    "addr:full":"Amagerbrogade 68, 3.tv. K\u00f8benhavn S Danmark 2300",
    "addr:housenumber":"68",
    "addr:postcode":"2300",
    "addr:street":"Amagerbrogade;Kobenhavn S Danmark",
    "iso:country":"DK",
    "sg:address":"Amagerbrogade 68, 3.tv.",
    "sg:city":"K\u00f8benhavn S",
    "sg:orig_category":"Malermestre",
    "sg:phone":"+45 32 57 52 42",
    "sg:postcode":"2300",
    "sg:province":"Danmark",
    "wof:name":"Halkj\u00e6r, Fini",
    "wof:placetype":"venue"
},
  "geometry": {"coordinates":[-78.1299133301,36.7267417908],"type":"Point"}
}