{
  "type": "Feature",
  "properties": {
    "addr:full":"Enghavevej 11 Vejle Danmark 7100",
    "addr:housenumber":"11",
    "addr:postcode":"7100",
    "addr:street":"Enghavevej",
    "iso:country":"DK",
    "sg:address":"Enghavevej 11",
    "sg:city":"Vejle",
    "sg:orig_category":"El-en gros",
    "sg:phone":"+45 70 20 13 11",
    "sg:postcode":"7100",
    "sg:province":"Danmark",
    "sg:website":"www.eurothermdrives.dk",
    "wof:name":"Eurotherm Drives",
    "wof:placetype":"venue"
},
  "geometry": {"coordinates":[9.5289201736,55.7061920166],"type":"Point"}
}