{
  "type": "Feature",
  "properties": {
    "addr:full":"H\u00e5gendrupvejen 6 A Hundested Danmark 3390",
    "addr:housenumber":"6 a",
    "addr:postcode":"3390",
    "addr:street":"Haagendrupvejen",
    "iso:country":"DK",
    "sg:address":"H\u00e5gendrupvejen 6 A",
    "sg:city":"Hundested",
    "sg:orig_category":"Forsamlingshuse og selskaber",
    "sg:phone":"+45 47 92 32 42",
    "sg:postcode":"3390",
    "sg:province":"Danmark",
    "wof:name":"Torup Landsbycenter af 1995",
    "wof:placetype":"venue"
},
  "geometry": {"coordinates":[11.9444847107,55.9838790894],"type":"Point"}
}