{
  "type": "Feature",
  "properties": {
    "addr:full":"Edisonsvej 6 Frederiksberg Danmark 1856",
    "addr:housenumber":"6",
    "addr:postcode":"1856",
    "addr:street":"Edisonsvej",
    "iso:country":"DK",
    "sg:address":"Edisonsvej 6",
    "sg:city":"Frederiksberg",
    "sg:orig_category":"Trossamfund uden for folkekirken",
    "sg:phone":"+45 33 22 55 11",
    "sg:postcode":"1856",
    "sg:province":"Danmark",
    "wof:name":"Jehovas Vidners Rigssalsforening-Danmark",
    "wof:placetype":"venue"
},
  "geometry": {"coordinates":[12.5369691849,55.6770133972],"type":"Point"}
}