{
  "type": "Feature",
  "properties": {
    "addr:full":"Silkeborgvej 45 - 47 \u00c5rhus C Danmark 8000",
    "addr:housenumber":"45 47",
    "addr:postcode":"8000",
    "addr:street":"Silkeborgvej",
    "iso:country":"DK",
    "sg:address":"Silkeborgvej 45 - 47",
    "sg:city":"\u00c5rhus C",
    "sg:orig_category":"Senge",
    "sg:phone":"+45 86 15 03 00",
    "sg:postcode":"8000",
    "sg:province":"Danmark",
    "wof:name":"Jysk Senget\u00f8jslager A/S",
    "wof:placetype":"venue"
},
  "geometry": {"coordinates":[4.717400074,49.7588005066],"type":"Point"}
}