{
  "type": "Feature",
  "properties": {
    "addr:full":"\u00c5gade 1 B Frederikssund Danmark 3600",
    "addr:housenumber":"1 b",
    "addr:postcode":"3600",
    "addr:street":"Aagade",
    "iso:country":"DK",
    "sg:address":"\u00c5gade 1 B",
    "sg:city":"Frederikssund",
    "sg:orig_category":"Realkreditinstitutter",
    "sg:phone":"+45 47 36 06 36",
    "sg:postcode":"3600",
    "sg:province":"Danmark",
    "sg:website":"www.nykredit.dk",
    "wof:name":"Nykredit A/S",
    "wof:placetype":"venue"
},
  "geometry": {"coordinates":[12.0550632477,55.8394470215],"type":"Point"}
}