{
  "type": "Feature",
  "properties": {
    "iso:country":"DK",
    "sg:address":"Fmd.: Robert Kjeldg\u00e5rd, M\u00f8llebakken 2",
    "sg:city":"Give",
    "sg:orig_category":"\u00c3\u2020ldreorganisationer og klubber",
    "sg:phone":"+45 75 73 14 78",
    "sg:postcode":"7323",
    "sg:province":"Danmark",
    "wof:name":"\u00c6ldre Sagen",
    "wof:placetype":"venue"
},
  "geometry": {"coordinates":[9.2362060547,55.845413208],"type":"Point"}
}