{
  "type": "Feature",
  "properties": {
    "iso:country":"DK",
    "sg:address":"Br\u00e6nderig\u00e6nget 6",
    "sg:city":"Svaneke",
    "sg:orig_category":"Gallerier",
    "sg:phone":"+45 56 49 71 11",
    "sg:postcode":"3740",
    "sg:province":"Danmark",
    "sg:website":"www.anders-nyborg.dk",
    "wof:name":"Svaneke, Galleri",
    "wof:placetype":"venue"
},
  "geometry": {"coordinates":[15.140504837,55.1364555359],"type":"Point"}
}