{
  "type": "Feature",
  "properties": {
    "addr:full":"S\u00f8bladvej 3 K\u00f8ge Danmark 4600",
    "addr:housenumber":"3",
    "addr:postcode":"4600",
    "addr:street":"Sobladvej",
    "iso:country":"DK",
    "sg:address":"S\u00f8bladvej 3",
    "sg:city":"K\u00f8ge",
    "sg:orig_category":"Cykler",
    "sg:phone":"+45 56 65 66 20",
    "sg:postcode":"4600",
    "sg:province":"Danmark",
    "wof:name":"Marksvingets Cykler",
    "wof:placetype":"venue"
},
  "geometry": {"coordinates":[12.152765274,55.4434127808],"type":"Point"}
}