{
  "type": "Feature",
  "properties": {
    "iso:country":"DK",
    "sg:address":"Strandvejen 96",
    "sg:city":"Hellerup",
    "sg:orig_category":"Babyudstyr",
    "sg:phone":"+45 39 40 18 19",
    "sg:postcode":"2900",
    "sg:province":"Danmark",
    "wof:name":"Kids Babyudstyr",
    "wof:placetype":"venue"
},
  "geometry": {"coordinates":[12.575964,55.732063],"type":"Point"}
}