{
  "type": "Feature",
  "properties": {
    "addr:full":"Ristingevej 49 Humble Danmark 5932",
    "addr:housenumber":"49",
    "addr:postcode":"5932",
    "addr:street":"Ristingevej",
    "iso:country":"DK",
    "sg:address":"Ristingevej 49",
    "sg:city":"Humble",
    "sg:orig_category":"Forsamlingshuse",
    "sg:phone":"+45 62 57 11 27",
    "sg:postcode":"5932",
    "sg:province":"Danmark",
    "wof:name":"Tryggelev Forsamlingshus",
    "wof:placetype":"venue"
},
  "geometry": {"coordinates":[10.688129425,54.8246803284],"type":"Point"}
}