{
  "type": "Feature",
  "properties": {
    "addr:full":"John F. Kennedys Plads 45 Aalborg Danmark 9000",
    "addr:housenumber":"45",
    "addr:postcode":"9000",
    "addr:street":"John F. Kennedys Plads",
    "iso:country":"DK",
    "sg:address":"John F. Kennedys Plads 45",
    "sg:city":"Aalborg",
    "sg:orig_category":"Private hospitaler and klinikker",
    "sg:phone":"+45 98 11 33 55",
    "sg:postcode":"9000",
    "sg:province":"Danmark",
    "sg:website":"www.kalstrup.dk",
    "wof:name":"Kalstrup, \u00d8jenklinikken",
    "wof:placetype":"venue"
},
  "geometry": {"coordinates":[9.9187421799,57.0427894592],"type":"Point"}
}