{
  "type": "Feature",
  "properties": {
    "addr:full":"Storegade 17 Allinge Danmark 3770",
    "addr:housenumber":"17",
    "addr:postcode":"3770",
    "addr:street":"Storegade",
    "iso:country":"DK",
    "sg:address":"Storegade 17",
    "sg:city":"Allinge",
    "sg:orig_category":"Autoreparation og -service",
    "sg:phone":"+45 56 48 01 02",
    "sg:postcode":"3770",
    "sg:province":"Danmark",
    "wof:name":"Allinge Autov\u00e6rksted",
    "wof:placetype":"venue"
},
  "geometry": {"coordinates":[14.8004837036,55.2741851807],"type":"Point"}
}