{
  "type": "Feature",
  "properties": {
    "addr:full":"Buddingevej 87 Kongens Lyngby Danmark 2800",
    "addr:housenumber":"87",
    "addr:postcode":"2800",
    "addr:street":"Buddingevej",
    "iso:country":"DK",
    "sg:address":"Buddingevej 87",
    "sg:city":"Kongens Lyngby",
    "sg:orig_category":"Dykkerudstyr",
    "sg:phone":"+45 45 88 44 20",
    "sg:postcode":"2800",
    "sg:province":"Danmark",
    "wof:name":"Marina Dykker Center ApS",
    "wof:placetype":"venue"
},
  "geometry": {"coordinates":[12.4955587387,55.7599449158],"type":"Point"}
}