{
  "type": "Feature",
  "properties": {
    "addr:full":"v/Gellerup Kirke, Gudrunsvej 88 Brabrand Danmark 8220",
    "addr:housenumber":"88",
    "addr:postcode":"8220",
    "addr:street":"Gudrunsvej",
    "iso:country":"DK",
    "sg:address":"v/Gellerup Kirke, Gudrunsvej 88",
    "sg:city":"Brabrand",
    "sg:orig_category":"\u00c3\u02dcvrig fritidsundervisning",
    "sg:phone":"+45 86 25 18 10",
    "sg:postcode":"8220",
    "sg:province":"Danmark",
    "wof:name":"Gellerup Kirkeh\u00f8jskole",
    "wof:placetype":"venue"
},
  "geometry": {"coordinates":[10.1293649673,56.1601295471],"type":"Point"}
}