{
  "type": "Feature",
  "properties": {
    "addr:full":"Drosselvej 9 Roskilde Danmark 4000",
    "addr:housenumber":"9",
    "addr:postcode":"4000",
    "addr:street":"Drosselvej",
    "iso:country":"DK",
    "sg:address":"Drosselvej 9",
    "sg:city":"Roskilde",
    "sg:classifiers":[
        {
            "category":"Professional",
            "subcategory":"Computer Services",
            "type":"Services"
        }
    ],
    "sg:phone":"+45 46 37 31 96",
    "sg:postcode":"4000",
    "sg:province":"Danmark",
    "sg:tags":[
        "edb",
        "-",
        "software"
    ],
    "sg:website":"www.BEware.dk",
    "wof:name":"BEware",
    "wof:placetype":"venue"
},
  "geometry": {"coordinates":[12.1015300751,55.6486167908],"type":"Point"}
}