{
  "type": "Feature",
  "properties": {
    "addr:full":"H. C. \u00d8rsteds Vej 53 Frederiksberg Danmark 1879",
    "addr:housenumber":"53",
    "addr:postcode":"1879",
    "addr:street":"H. C. Orsteds Vej",
    "iso:country":"DK",
    "sg:address":"H. C. \u00d8rsteds Vej 53",
    "sg:city":"Frederiksberg",
    "sg:classifiers":[
        {
            "category":"Restaurant",
            "type":"Food & Drink"
        }
    ],
    "sg:phone":"+45 35 39 18 72",
    "sg:postcode":"1879",
    "sg:province":"Danmark",
    "wof:name":"Thailand Restaurant",
    "wof:placetype":"venue"
},
  "geometry": {"coordinates":[12.5432500839,55.6777114868],"type":"Point"}
}