{
  "type": "Feature",
  "properties": {
    "iso:country":"DK",
    "sg:address":"Skejbytoften 230, Skejby",
    "sg:city":"\u00c5rhus N",
    "sg:orig_category":"Integrerede institutioner",
    "sg:phone":"+45 86 78 30 88",
    "sg:postcode":"8200",
    "sg:province":"Danmark",
    "wof:name":"Skibet, Integreret Inst.",
    "wof:placetype":"venue"
},
  "geometry": {"coordinates":[10.1754398346,56.2002601624],"type":"Point"}
}