{
  "type": "Feature",
  "properties": {
    "addr:full":"Hotelvej 4 D, Stilling Skanderborg Danmark 8660",
    "addr:housenumber":"4 d",
    "addr:postcode":"8660",
    "addr:street":"Hotelvej;Stilling",
    "iso:country":"DK",
    "sg:address":"Hotelvej 4 D, Stilling",
    "sg:city":"Skanderborg",
    "sg:orig_category":"Motorcykler",
    "sg:phone":"+45 86 57 00 75",
    "sg:postcode":"8660",
    "sg:province":"Danmark",
    "wof:name":"Skanderborg Motorcykel Shop",
    "wof:placetype":"venue"
},
  "geometry": {"coordinates":[9.929974556,56.0380249023],"type":"Point"}
}