{
  "type": "Feature",
  "properties": {
    "addr:full":"Kirkebakken 4 Beder Danmark 8330",
    "addr:housenumber":"4",
    "addr:postcode":"8330",
    "addr:street":"Kirkebakken",
    "iso:country":"DK",
    "sg:address":"Kirkebakken 4",
    "sg:city":"Beder",
    "sg:classifiers":[
        {
            "category":"Restaurant",
            "type":"Food & Drink"
        }
    ],
    "sg:phone":"+45 86 93 88 77",
    "sg:postcode":"8330",
    "sg:province":"Danmark",
    "wof:name":"Break",
    "wof:placetype":"venue"
},
  "geometry": {"coordinates":[10.2048931122,56.0590591431],"type":"Point"}
}