{
  "type": "Feature",
  "properties": {
    "addr:full":"Stageh\u00f8jvej 3 Silkeborg Danmark 8600",
    "addr:housenumber":"3",
    "addr:postcode":"8600",
    "addr:street":"Stagehojvej",
    "iso:country":"DK",
    "sg:address":"Stageh\u00f8jvej 3",
    "sg:city":"Silkeborg",
    "sg:orig_category":"Autoforhandlere",
    "sg:phone":"+45 72 11 65 00",
    "sg:postcode":"8600",
    "sg:province":"Danmark",
    "sg:website":"www.hesselbiler.dk",
    "wof:name":"Hessel, Ejner",
    "wof:placetype":"venue"
},
  "geometry": {"coordinates":[9.5721492767,56.1865997314],"type":"Point"}
}