{
  "type": "Feature",
  "properties": {
    "addr:full":"Fmd.: Kurt Eriksen, N\u00f8rrebakken 24 Horsens Danmark 8700",
    "addr:housenumber":"24",
    "addr:postcode":"8700",
    "addr:street":"Norrebakken",
    "iso:country":"DK",
    "sg:address":"Fmd.: Kurt Eriksen, N\u00f8rrebakken 24",
    "sg:city":"Horsens",
    "sg:orig_category":"Kolonihaveforeninger",
    "sg:phone":"+45 75 60 27 75",
    "sg:postcode":"8700",
    "sg:province":"Danmark",
    "wof:name":"Haveselskabet Nordmarken",
    "wof:placetype":"venue"
},
  "geometry": {"coordinates":[9.8432445526,55.8621063232],"type":"Point"}
}