{
  "type": "Feature",
  "properties": {
    "addr:full":"Hostrups Have 58 Frederiksberg Danmark 1954",
    "addr:housenumber":"58",
    "addr:postcode":"1954",
    "addr:street":"Hostrups Have",
    "iso:country":"DK",
    "sg:address":"Hostrups Have 58",
    "sg:city":"Frederiksberg",
    "sg:orig_category":"Psykologer, praktiserende",
    "sg:phone":"+45 35 35 14 68",
    "sg:postcode":"1954",
    "sg:province":"Danmark",
    "wof:name":"R\u00f8pke, Lene",
    "wof:placetype":"venue"
},
  "geometry": {"coordinates":[12.5390701294,55.6843490601],"type":"Point"}
}