{
  "type": "Feature",
  "properties": {
    "addr:full":"Almstokvej 23 Billund Danmark 7190",
    "addr:housenumber":"23",
    "addr:postcode":"7190",
    "addr:street":"Almstokvej",
    "iso:country":"DK",
    "sg:address":"Almstokvej 23",
    "sg:city":"Billund",
    "sg:orig_category":"Autoreparation og -service",
    "sg:phone":"+45 75 33 33 18",
    "sg:postcode":"7190",
    "sg:province":"Danmark",
    "wof:name":"J\u00f8rgensen, Gunnar",
    "wof:placetype":"venue"
},
  "geometry": {"coordinates":[9.1271753311,55.6868476868],"type":"Point"}
}