{
  "type": "Feature",
  "properties": {
    "addr:full":"R\u00e5dhusstr\u00e6de 4 K\u00f8benhavn Danmark 1466",
    "addr:housenumber":"4;1466",
    "addr:street":"Raadhusstraede",
    "iso:country":"DK",
    "sg:address":"R\u00e5dhusstr\u00e6de 4",
    "sg:city":"K\u00f8benhavn",
    "sg:orig_category":"Ure og urmagere",
    "sg:phone":"+45 33 13 83 00",
    "sg:postcode":"1466",
    "sg:province":"Danmark",
    "sg:website":"www.mads-laier.dk",
    "wof:name":"Laier, Mads",
    "wof:placetype":"venue"
},
  "geometry": {"coordinates":[76.3070983887,14.277130127],"type":"Point"}
}