{
  "type": "Feature",
  "properties": {
    "iso:country":"DK",
    "sg:address":"Leder: Eskild Marcussen, Ved Kirken 6",
    "sg:city":"Frederikssund",
    "sg:orig_category":"Kulturcentre",
    "sg:phone":"+45 47 38 52 91",
    "sg:postcode":"3600",
    "sg:province":"Danmark",
    "sg:website":"www.kulturhus.com",
    "wof:name":"Kulturhuset Elv\u00e6rket",
    "wof:placetype":"venue"
},
  "geometry": {"coordinates":[12.0661621094,55.8370323181],"type":"Point"}
}