{
  "type": "Feature",
  "properties": {
    "addr:full":"Jernbanegade 7 Hj\u00f8rring Danmark 9800",
    "addr:housenumber":"7",
    "addr:postcode":"9800",
    "addr:street":"Jernbanegade",
    "iso:country":"DK",
    "sg:address":"Jernbanegade 7",
    "sg:city":"Hj\u00f8rring",
    "sg:classifiers":[
        {
            "category":"Restaurant",
            "type":"Food & Drink"
        }
    ],
    "sg:phone":"+45 98 91 19 22",
    "sg:postcode":"9800",
    "sg:province":"Danmark",
    "wof:name":"Bambino, Pizzaria",
    "wof:placetype":"venue"
},
  "geometry": {"coordinates":[9.9868974686,57.4584846497],"type":"Point"}
}