{
  "type": "Feature",
  "properties": {
    "iso:country":"DK",
    "sg:address":"Tv\u00e6rgade 12",
    "sg:city":"Odder",
    "sg:orig_category":"Kommunale folkeskoler",
    "sg:phone":"+45 87 80 36 00",
    "sg:postcode":"8300",
    "sg:province":"Danmark",
    "wof:name":"Skovbakkeskolen",
    "wof:placetype":"venue"
},
  "geometry": {"coordinates":[10.14494133,55.9709281921],"type":"Point"}
}