{
  "type": "Feature",
  "properties": {
    "addr:full":"Enstensvej 16 Vejby Danmark 3210",
    "addr:housenumber":"16",
    "addr:postcode":"3210",
    "addr:street":"Enstensvej",
    "iso:country":"DK",
    "sg:address":"Enstensvej 16",
    "sg:city":"Vejby",
    "sg:orig_category":"Musikere",
    "sg:phone":"+45 48 70 69 02",
    "sg:postcode":"3210",
    "sg:province":"Danmark",
    "wof:name":"S\u00f8rensen, Johnny Erhardt",
    "wof:placetype":"venue"
},
  "geometry": {"coordinates":[12.135424614,56.0737915039],"type":"Point"}
}