{
  "type": "Feature",
  "properties": {
    "addr:full":"Kr\u00f8yersvej 5 A Klampenborg Danmark 2930",
    "addr:housenumber":"5 a",
    "addr:postcode":"2930",
    "addr:street":"Kroyersvej",
    "iso:country":"DK",
    "sg:address":"Kr\u00f8yersvej 5 A",
    "sg:city":"Klampenborg",
    "sg:classifiers":[
        {
            "category":"Restaurant",
            "type":"Food & Drink"
        }
    ],
    "sg:phone":"+45 39 63 24 56",
    "sg:postcode":"2930",
    "sg:province":"Danmark",
    "wof:name":"S. I. F., Restaurant",
    "wof:placetype":"venue"
},
  "geometry": {"coordinates":[12.5917692184,55.7631607056],"type":"Point"}
}