{
  "type": "Feature",
  "properties": {
    "addr:full":"Faaborgvej 12, Dalum Odense SV Danmark 5250",
    "addr:housenumber":"12",
    "addr:postcode":"5250",
    "addr:street":"Faaborgvej;Dalum",
    "iso:country":"DK",
    "sg:address":"Faaborgvej 12, Dalum",
    "sg:city":"Odense SV",
    "sg:orig_category":"Cykler",
    "sg:phone":"+45 66 14 99 88",
    "sg:postcode":"5250",
    "sg:province":"Danmark",
    "sg:website":"www.multiatleten.dk",
    "wof:name":"Multi Atleten Sport",
    "wof:placetype":"venue"
},
  "geometry": {"coordinates":[10.3153953552,55.3362998962],"type":"Point"}
}