{
  "type": "Feature",
  "properties": {
    "addr:full":"Ejby Industrivej 106 Glostrup Danmark 2600",
    "addr:housenumber":"106",
    "addr:postcode":"2600",
    "addr:street":"Ejby Industrivej",
    "iso:country":"DK",
    "sg:address":"Ejby Industrivej 106",
    "sg:city":"Glostrup",
    "sg:orig_category":"Fabrikker",
    "sg:phone":"+45 43 43 99 99",
    "sg:postcode":"2600",
    "sg:province":"Danmark",
    "wof:name":"danbroLOGO ApS",
    "wof:placetype":"venue"
},
  "geometry": {"coordinates":[12.4219522476,55.6961021423],"type":"Point"}
}