{
  "type": "Feature",
  "properties": {
    "addr:full":"Skibstedvej 27, Skibsted Kongerslev Danmark 9293",
    "addr:housenumber":"27",
    "addr:postcode":"9293",
    "addr:street":"Skibstedvej;Skibsted",
    "iso:country":"DK",
    "sg:address":"Skibstedvej 27, Skibsted",
    "sg:city":"Kongerslev",
    "sg:orig_category":"Forsamlingshuse",
    "sg:phone":"+45 98 33 13 00",
    "sg:postcode":"9293",
    "sg:province":"Danmark",
    "wof:name":"Skibsted Forsamlingshus",
    "wof:placetype":"venue"
},
  "geometry": {"coordinates":[10.1150007248,56.8851165771],"type":"Point"}
}