{
  "type": "Feature",
  "properties": {
    "addr:full":"S\u00f8husvej 107, Kirkendrup Odense N Danmark 5270",
    "addr:housenumber":"107",
    "addr:postcode":"5270",
    "addr:street":"Sohusvej",
    "iso:country":"DK",
    "sg:address":"S\u00f8husvej 107, Kirkendrup",
    "sg:city":"Odense N",
    "sg:orig_category":"Ungdomsklubber",
    "sg:phone":"+45 66 18 86 28",
    "sg:postcode":"5270",
    "sg:province":"Danmark",
    "wof:name":"N\u00e6sby Knallertklub",
    "wof:placetype":"venue"
},
  "geometry": {"coordinates":[10.3306798935,55.4711418152],"type":"Point"}
}