{
  "type": "Feature",
  "properties": {
    "addr:full":"Islevhusvej 9 Br\u00f8nsh\u00f8j Danmark 2700",
    "addr:housenumber":"9",
    "addr:postcode":"2700",
    "addr:street":"Islevhusvej",
    "iso:country":"DK",
    "sg:address":"Islevhusvej 9",
    "sg:city":"Br\u00f8nsh\u00f8j",
    "sg:orig_category":"Grillbarer",
    "sg:phone":"+45 38 60 04 94",
    "sg:postcode":"2700",
    "sg:province":"Danmark",
    "wof:name":"Emilo's Pizzeria & Snackbar",
    "wof:placetype":"venue"
},
  "geometry": {"coordinates":[-65.6866531372,-23.1981296539],"type":"Point"}
}