{
  "type": "Feature",
  "properties": {
    "addr:full":"Tuborg Boulevard 5 Hellerup Danmark 2900",
    "addr:housenumber":"5",
    "addr:postcode":"2900",
    "addr:street":"Tuborg Boulevard",
    "iso:country":"DK",
    "sg:address":"Tuborg Boulevard 5",
    "sg:city":"Hellerup",
    "sg:orig_category":"Konsulentvirksomheder",
    "sg:phone":"+45 39 25 50 00",
    "sg:postcode":"2900",
    "sg:province":"Danmark",
    "sg:website":"www.paconsulting.com",
    "wof:name":"PA Consulting Group A/S",
    "wof:placetype":"venue"
},
  "geometry": {"coordinates":[12.5808858871,55.7278251648],"type":"Point"}
}