{
  "type": "Feature",
  "properties": {
    "addr:full":"Ravmarken 8 Strandby Danmark 9970",
    "addr:housenumber":"8",
    "addr:postcode":"9970",
    "addr:street":"Ravmarken",
    "iso:country":"DK",
    "sg:address":"Ravmarken 8",
    "sg:city":"Strandby",
    "sg:orig_category":"Varmeforsyning",
    "sg:phone":"+45 98 48 13 58",
    "sg:postcode":"9970",
    "sg:province":"Danmark",
    "wof:name":"Strandby Varmev\u00e6rk A.m.b.A.",
    "wof:placetype":"venue"
},
  "geometry": {"coordinates":[10.4866914749,57.4870834351],"type":"Point"}
}