{
  "type": "Feature",
  "properties": {
    "addr:full":"Fmd.: Birgit Munk-Petersen, Hestehavevej 8 Stokkemarke Danmark 4952",
    "addr:housenumber":"8",
    "addr:postcode":"4952",
    "addr:street":"Hestehavevej",
    "iso:country":"DK",
    "sg:address":"Fmd.: Birgit Munk-Petersen, Hestehavevej 8",
    "sg:city":"Stokkemarke",
    "sg:orig_category":"Husflidsforeninger",
    "sg:phone":"+45 54 71 22 02",
    "sg:postcode":"4952",
    "sg:province":"Danmark",
    "wof:name":"Stokkemarke Husholdningsforening",
    "wof:placetype":"venue"
},
  "geometry": {"coordinates":[11.3643407822,54.8373832703],"type":"Point"}
}