{
  "type": "Feature",
  "properties": {
    "addr:full":"Bromb\u00e6rranken 5 2., Tornbjerg Odense S\u00d8 Danmark 5220",
    "addr:housenumber":"5 2",
    "addr:postcode":"5220",
    "addr:street":"Brombaerranken;Tornbjerg",
    "iso:country":"DK",
    "sg:address":"Bromb\u00e6rranken 5 2., Tornbjerg",
    "sg:city":"Odense S\u00d8",
    "sg:orig_category":"INGENI\u00c3\u02dcRER",
    "sg:phone":"+45 28 26 59 49",
    "sg:postcode":"5220",
    "sg:province":"Danmark",
    "sg:website":"www.insitu.dk",
    "wof:name":"Insitu",
    "wof:placetype":"venue"
},
  "geometry": {"coordinates":[10.4583454132,55.3316917419],"type":"Point"}
}