{
  "type": "Feature",
  "properties": {
    "addr:full":"Skautrupvej 16  Holstebro Danmark 7500",
    "addr:housenumber":"16",
    "addr:postcode":"7500",
    "addr:street":"Skautrupvej",
    "iso:country":"DK",
    "sg:address":"Skautrupvej 16 ",
    "sg:city":"Holstebro",
    "sg:classifiers":[
        {
            "category":"Home & Garden",
            "subcategory":"Home Furnishings",
            "type":"Retail Goods"
        }
    ],
    "sg:phone":"+45 97 43 52 00",
    "sg:postcode":"7500",
    "sg:province":"Danmark",
    "sg:tags":[
        "household"
    ],
    "wof:name":"TVIS K\u00d8KKENER A/S",
    "wof:placetype":"venue"
},
  "geometry": {"coordinates":[8.7083730698,56.3190002441],"type":"Point"}
}