{
  "type": "Feature",
  "properties": {
    "iso:country":"DK",
    "sg:address":"Adelgade 13",
    "sg:city":"Randers",
    "sg:orig_category":"Hobbyartikler",
    "sg:phone":"+45 86 43 39 23",
    "sg:postcode":"8900",
    "sg:province":"Danmark",
    "wof:name":"Randers Hobby Import",
    "wof:placetype":"venue"
},
  "geometry": {"coordinates":[10.034113884,56.462348938],"type":"Point"}
}