{
  "type": "Feature",
  "properties": {
    "addr:full":"Fmd.: Randi Hansen, Bredsten Ldv. 82, Bindesb\u00f8l Give Danmark 7323",
    "addr:housenumber":"82",
    "addr:postcode":"7323",
    "addr:street":"Bindesbol",
    "iso:country":"DK",
    "sg:address":"Fmd.: Randi Hansen, Bredsten Ldv. 82, Bindesb\u00f8l",
    "sg:city":"Give",
    "sg:orig_category":"Borger- og beboerforeninger",
    "sg:phone":"+45 75 73 82 96",
    "sg:postcode":"7323",
    "sg:province":"Danmark",
    "wof:name":"Uhe Borgerforening",
    "wof:placetype":"venue"
},
  "geometry": {"coordinates":[9.2362060547,55.845413208],"type":"Point"}
}