{
  "type": "Feature",
  "properties": {
    "addr:full":"Sitkagranen 20 Kjellerup Danmark 8620",
    "addr:housenumber":"20",
    "addr:postcode":"8620",
    "addr:street":"Sitkagranen",
    "iso:country":"DK",
    "sg:address":"Sitkagranen 20",
    "sg:city":"Kjellerup",
    "sg:orig_category":"Selskabslokaler",
    "sg:phone":"+45 87 70 24 22",
    "sg:postcode":"8620",
    "sg:province":"Danmark",
    "wof:name":"Sj\u00f8rslev Sogneg\u00e5rd",
    "wof:placetype":"venue"
},
  "geometry": {"coordinates":[9.4456691742,56.2815551758],"type":"Point"}
}