{
  "type": "Feature",
  "properties": {
    "addr:full":"Solh\u00f8jsvej 28 Silkeborg Danmark 8600",
    "addr:housenumber":"28",
    "addr:postcode":"8600",
    "addr:street":"Solhojsvej",
    "iso:country":"DK",
    "sg:address":"Solh\u00f8jsvej 28",
    "sg:city":"Silkeborg",
    "sg:orig_category":"Sportsartikler",
    "sg:phone":"+45 86 80 50 51",
    "sg:postcode":"8600",
    "sg:province":"Danmark",
    "wof:name":"Fysio Sport",
    "wof:placetype":"venue"
},
  "geometry": {"coordinates":[9.5346879959,56.1571350098],"type":"Point"}
}