{
  "type": "Feature",
  "properties": {
    "addr:full":"R\u00e5dhuspladsen 2 Slagelse Danmark 4200",
    "addr:housenumber":"2",
    "addr:postcode":"4200",
    "addr:street":"Raadhuspladsen",
    "iso:country":"DK",
    "sg:address":"R\u00e5dhuspladsen 2",
    "sg:city":"Slagelse",
    "sg:orig_category":"Forsikringer",
    "sg:phone":"+45 70 13 79 13",
    "sg:postcode":"4200",
    "sg:province":"Danmark",
    "wof:name":"Topdanmark Forsikring A/S",
    "wof:placetype":"venue"
},
  "geometry": {"coordinates":[11.3573360443,55.4049949646],"type":"Point"}
}