{
  "type": "Feature",
  "properties": {
    "iso:country":"DK",
    "sg:address":"Bredgade 59",
    "sg:city":"Aarup",
    "sg:orig_category":"Bodegaer",
    "sg:phone":"+45 64 43 16 49",
    "sg:postcode":"5560",
    "sg:province":"Danmark",
    "wof:name":"Arnes Bodega",
    "wof:placetype":"venue"
},
  "geometry": {"coordinates":[10.0482940674,55.3794937134],"type":"Point"}
}