{
  "type": "Feature",
  "properties": {
    "addr:full":"Skads Byvej 102 Esbjerg \u00d8 Danmark 6705",
    "addr:housenumber":"102",
    "addr:postcode":"6705",
    "addr:street":"Skads Byvej;Danmark",
    "iso:country":"DK",
    "sg:address":"Skads Byvej 102",
    "sg:city":"Esbjerg \u00d8",
    "sg:orig_category":"Autoophug",
    "sg:phone":"+45 75 16 02 02",
    "sg:postcode":"6705",
    "sg:province":"Danmark",
    "wof:name":"Skads Autoophug",
    "wof:placetype":"venue"
},
  "geometry": {"coordinates":[8.5714626312,55.519733429],"type":"Point"}
}