{
  "type": "Feature",
  "properties": {
    "iso:country":"DK",
    "sg:address":"Nyborgvej 144",
    "sg:city":"Odense C",
    "sg:orig_category":"Redningskorps",
    "sg:phone":"+45 66 12 42 84",
    "sg:postcode":"5000",
    "sg:province":"Danmark",
    "wof:name":"Redningstjenesten Fyn",
    "wof:placetype":"venue"
},
  "geometry": {"coordinates":[10.4148521423,55.3936347961],"type":"Point"}
}