{
  "type": "Feature",
  "properties": {
    "addr:full":"Hoptrup Hovedgade 49 Haderslev Danmark 6100",
    "addr:housenumber":"49",
    "addr:postcode":"6100",
    "addr:street":"Hoptrup Hovedgade",
    "iso:country":"DK",
    "sg:address":"Hoptrup Hovedgade 49",
    "sg:city":"Haderslev",
    "sg:orig_category":"Oliefyr og service",
    "sg:phone":"+45 74 57 55 73",
    "sg:postcode":"6100",
    "sg:province":"Danmark",
    "wof:name":"Hydro Texaco Olie Center",
    "wof:placetype":"venue"
},
  "geometry": {"coordinates":[9.449930191,55.1660385132],"type":"Point"}
}