{
  "type": "Feature",
  "properties": {
    "addr:full":"Bredgade 57 N\u00f8rre Nebel Danmark 6830",
    "addr:housenumber":"57",
    "addr:postcode":"6830",
    "addr:street":"Bredgade",
    "iso:country":"DK",
    "sg:address":"Bredgade 57",
    "sg:city":"N\u00f8rre Nebel",
    "sg:orig_category":"Tandteknikere, Kliniske",
    "sg:phone":"+45 75 28 84 28",
    "sg:postcode":"6830",
    "sg:province":"Danmark",
    "sg:website":"www.larskongsbak.dk",
    "wof:name":"Nr. Nebel Tandteknik",
    "wof:placetype":"venue"
},
  "geometry": {"coordinates":[8.2917842865,55.778968811],"type":"Point"}
}