{
  "type": "Feature",
  "properties": {
    "addr:full":"Hjortkj\u00e6rsvej 10 Aars Danmark 9600",
    "addr:housenumber":"10",
    "addr:postcode":"9600",
    "addr:street":"Hjortkjaersvej",
    "iso:country":"DK",
    "sg:address":"Hjortkj\u00e6rsvej 10",
    "sg:city":"Aars",
    "sg:orig_category":"Korn og foderstoffer",
    "sg:phone":"+45 98 62 22 66",
    "sg:postcode":"9600",
    "sg:province":"Danmark",
    "wof:name":"Aars Korn A/S",
    "wof:placetype":"venue"
},
  "geometry": {"coordinates":[9.5001001358,56.8060874939],"type":"Point"}
}