{
  "type": "Feature",
  "properties": {
    "addr:full":"Fmd.: S\u00f8ren Nielsen, Stenten 59, B\u00f8geskov Fredericia Danmark 7000",
    "addr:housenumber":"59",
    "addr:postcode":"7000",
    "addr:street":"Stenten",
    "iso:country":"DK",
    "sg:address":"Fmd.: S\u00f8ren Nielsen, Stenten 59, B\u00f8geskov",
    "sg:city":"Fredericia",
    "sg:orig_category":"Musik og sang",
    "sg:phone":"+45 75 95 78 65",
    "sg:postcode":"7000",
    "sg:province":"Danmark",
    "wof:name":"Fredericia Spillemandslaug",
    "wof:placetype":"venue"
},
  "geometry": {"coordinates":[9.7591047287,55.566368103],"type":"Point"}
}