{
  "type": "Feature",
  "properties": {
    "addr:full":"Tordenskjoldsgade 85 \u00c5rhus N Danmark 8200",
    "addr:housenumber":"85",
    "addr:postcode":"8200",
    "addr:street":"Tordenskjoldsgade",
    "iso:country":"DK",
    "sg:address":"Tordenskjoldsgade 85",
    "sg:city":"\u00c5rhus N",
    "sg:orig_category":"Advokater",
    "sg:phone":"+45 86 16 22 99",
    "sg:postcode":"8200",
    "sg:province":"Danmark",
    "wof:name":"Carstensen, J\u00f8rgen",
    "wof:placetype":"venue"
},
  "geometry": {"coordinates":[10.2169780731,56.1742553711],"type":"Point"}
}