{
  "type": "Feature",
  "properties": {
    "addr:full":"Ravnholmvej 17 Kongens Lyngby Danmark 2800",
    "addr:housenumber":"17",
    "addr:postcode":"2800",
    "addr:street":"Ravnholmvej",
    "iso:country":"DK",
    "sg:address":"Ravnholmvej 17",
    "sg:city":"Kongens Lyngby",
    "sg:orig_category":"Tegnere og tegnestuer",
    "sg:phone":"+45 45 88 28 69",
    "sg:postcode":"2800",
    "sg:province":"Danmark",
    "wof:name":"Frisvad, Felicia",
    "wof:placetype":"venue"
},
  "geometry": {"coordinates":[12.5247974396,55.7992362976],"type":"Point"}
}