{
  "type": "Feature",
  "properties": {
    "addr:full":"\u00d8strevej 17, Hasle \u00c5rhus V Danmark 8210",
    "addr:housenumber":"17",
    "addr:postcode":"8210",
    "addr:street":"Ostrevej",
    "iso:country":"DK",
    "sg:address":"\u00d8strevej 17, Hasle",
    "sg:city":"\u00c5rhus V",
    "sg:orig_category":"Glarmestre og glarmagere",
    "sg:phone":"+45 86 15 31 00",
    "sg:postcode":"8210",
    "sg:province":"Danmark",
    "wof:name":"Ellemann, E.",
    "wof:placetype":"venue"
},
  "geometry": {"coordinates":[14.7065896988,55.1830787659],"type":"Point"}
}