{
  "type": "Feature",
  "properties": {
    "iso:country":"DK",
    "sg:address":"Fr\u00f8strupvej 230",
    "sg:city":"Outrup",
    "sg:orig_category":"\u00c3\u02dcvrige skoler",
    "sg:phone":"+45 75 26 11 55",
    "sg:postcode":"6855",
    "sg:province":"Danmark",
    "sg:website":"www.koordineringscentret.dk",
    "wof:name":"Koordineringscentret",
    "wof:placetype":"venue"
},
  "geometry": {"coordinates":[8.4502916336,55.7170677185],"type":"Point"}
}