{
  "type": "Feature",
  "properties": {
    "addr:full":"Borgergade 37 Silkeborg Danmark 8600",
    "addr:housenumber":"37",
    "addr:postcode":"8600",
    "addr:street":"Borgergade",
    "iso:country":"DK",
    "sg:address":"Borgergade 37",
    "sg:city":"Silkeborg",
    "sg:orig_category":"Grillbarer",
    "sg:phone":"+45 86 81 13 55",
    "sg:postcode":"8600",
    "sg:province":"Danmark",
    "wof:name":"Birgits Grillhj\u00f8rne",
    "wof:placetype":"venue"
},
  "geometry": {"coordinates":[9.5526580811,56.1782188416],"type":"Point"}
}