{
  "type": "Feature",
  "properties": {
    "addr:full":"Krovej 3, Klitm\u00f8ller Thisted Danmark 7700",
    "addr:housenumber":"3",
    "addr:postcode":"7700",
    "addr:street":"Krovej;Klitmoller",
    "iso:country":"DK",
    "sg:address":"Krovej 3, Klitm\u00f8ller",
    "sg:city":"Thisted",
    "sg:orig_category":"Filialbiblioteker",
    "sg:phone":"+45 97 97 52 35",
    "sg:postcode":"7700",
    "sg:province":"Danmark",
    "wof:name":"Klitm\u00f8ller Bibliotek",
    "wof:placetype":"venue"
},
  "geometry": {"coordinates":[8.6919784546,56.9556121826],"type":"Point"}
}