{
  "type": "Feature",
  "properties": {
    "iso:country":"DK",
    "sg:address":"Gartnervej 5, Nustrup",
    "sg:city":"Vojens",
    "sg:orig_category":"Gartnerier",
    "sg:phone":"+45 74 87 13 21",
    "sg:postcode":"6500",
    "sg:province":"Danmark",
    "wof:name":"Nustrup Handelsgartneri",
    "wof:placetype":"venue"
},
  "geometry": {"coordinates":[9.2987146378,55.2457237244],"type":"Point"}
}