{
  "type": "Feature",
  "properties": {
    "addr:full":"Slotsgade 1, 1. Skive Danmark 7800",
    "addr:housenumber":"1 1",
    "addr:postcode":"7800",
    "addr:street":"Slotsgade",
    "iso:country":"DK",
    "sg:address":"Slotsgade 1, 1.",
    "sg:city":"Skive",
    "sg:orig_category":"Faglige organisationer og foreninger",
    "sg:phone":"+45 97 52 22 12",
    "sg:postcode":"7800",
    "sg:province":"Danmark",
    "wof:name":"Kvindeligt Arbejderforbund",
    "wof:placetype":"venue"
},
  "geometry": {"coordinates":[9.0261907578,56.565700531],"type":"Point"}
}