{
  "type": "Feature",
  "properties": {
    "iso:country":"DK",
    "sg:address":"B\u00f8dtchersvej 12",
    "sg:city":"Odense M",
    "sg:orig_category":"Konsulentvirksomheder",
    "sg:phone":"+45 66 11 67 25",
    "sg:postcode":"5230",
    "sg:province":"Danmark",
    "wof:name":"Nek Management",
    "wof:placetype":"venue"
},
  "geometry": {"coordinates":[10.3846921921,55.374332428],"type":"Point"}
}