{
  "type": "Feature",
  "properties": {
    "addr:full":"Erhvervsvej 4  Glostrup Danmark 2600",
    "addr:housenumber":"4",
    "addr:postcode":"2600",
    "addr:street":"Erhvervsvej",
    "iso:country":"DK",
    "sg:address":"Erhvervsvej 4 ",
    "sg:city":"Glostrup",
    "sg:classifiers":[
        {
            "category":"Professional",
            "subcategory":"Computer Services",
            "type":"Services"
        }
    ],
    "sg:phone":"+45 43 24 70 00",
    "sg:postcode":"2600",
    "sg:province":"Danmark",
    "sg:tags":[
        "information",
        "technology"
    ],
    "wof:name":"TGI SCANDINAVIA A/S",
    "wof:placetype":"venue"
},
  "geometry": {"coordinates":[12.4238948822,55.6974945068],"type":"Point"}
}