{
  "type": "Feature",
  "properties": {
    "iso:country":"DK",
    "sg:address":"Dronningensgade 2 - 4",
    "sg:city":"Randers",
    "sg:orig_category":"Maskinfabrikker",
    "sg:phone":"+45 86 43 61 33",
    "sg:postcode":"8900",
    "sg:province":"Danmark",
    "wof:name":"Becks Maskinfabrik Eftf.",
    "wof:placetype":"venue"
},
  "geometry": {"coordinates":[10.0462150574,56.4620857239],"type":"Point"}
}