{
  "type": "Feature",
  "properties": {
    "iso:country":"DK",
    "sg:address":"Hovedgaden 79",
    "sg:city":"Snedsted",
    "sg:orig_category":"Blomsterhandlere",
    "sg:phone":"+45 97 93 40 22",
    "sg:postcode":"7752",
    "sg:province":"Danmark",
    "wof:name":"Jeppesen, Poul Erik",
    "wof:placetype":"venue"
},
  "geometry": {"coordinates":[8.5212392807,56.8925285339],"type":"Point"}
}