{
  "type": "Feature",
  "properties": {
    "addr:full":"G\u00e5sk\u00e6rvej 4, Drenderup Vamdrup Danmark 6580",
    "addr:housenumber":"4",
    "addr:postcode":"6580",
    "addr:street":"Gaaskaervej",
    "iso:country":"DK",
    "sg:address":"G\u00e5sk\u00e6rvej 4, Drenderup",
    "sg:city":"Vamdrup",
    "sg:orig_category":"Autoreparation og -service",
    "sg:phone":"+45 75 59 84 42",
    "sg:postcode":"6580",
    "sg:province":"Danmark",
    "wof:name":"Bents Biler",
    "wof:placetype":"venue"
},
  "geometry": {"coordinates":[9.2839107513,55.4266548157],"type":"Point"}
}