{
  "type": "Feature",
  "properties": {
    "iso:country":"DK",
    "sg:address":"Dengs\u00f8vej 16, Vester Velling",
    "sg:city":"Ulstrup",
    "sg:orig_category":"Staldinventar og -montage",
    "sg:phone":"+45 24 67 63 54",
    "sg:postcode":"8860",
    "sg:province":"Danmark",
    "wof:name":"Salvana Midtjylland",
    "wof:placetype":"venue"
},
  "geometry": {"coordinates":[9.7940101624,56.3912200928],"type":"Point"}
}