{
  "type": "Feature",
  "properties": {
    "addr:full":"J\u00f8rgens Alle 42 Bjerringbro Danmark 8850",
    "addr:housenumber":"42",
    "addr:postcode":"8850",
    "addr:street":"Jorgens Alle",
    "iso:country":"DK",
    "sg:address":"J\u00f8rgens Alle 42",
    "sg:city":"Bjerringbro",
    "sg:orig_category":"Aktivitetscentre",
    "sg:phone":"+45 86 68 07 44",
    "sg:postcode":"8850",
    "sg:province":"Danmark",
    "wof:name":"Aktivitetscentret Engg\u00e5rden",
    "wof:placetype":"venue"
},
  "geometry": {"coordinates":[9.6708183289,56.3847389221],"type":"Point"}
}