{
  "type": "Feature",
  "properties": {
    "iso:country":"DK",
    "sg:address":"Grydh\u00f8jvej 16 A",
    "sg:city":"\u00c5rhus N",
    "sg:orig_category":"Integrerede institutioner",
    "sg:phone":"+45 86 16 75 50",
    "sg:postcode":"8200",
    "sg:province":"Danmark",
    "wof:name":"B\u00f8rnebakken, Integreret Inst.",
    "wof:placetype":"venue"
},
  "geometry": {"coordinates":[4.9393601418,49.7092018127],"type":"Point"}
}