{
  "type": "Feature",
  "properties": {
    "addr:full":"Sirvej 49 Holstebro Danmark 7500",
    "addr:housenumber":"49",
    "addr:postcode":"7500",
    "addr:street":"Sirvej",
    "iso:country":"DK",
    "sg:address":"Sirvej 49",
    "sg:city":"Holstebro",
    "sg:orig_category":"Psykologer, praktiserende",
    "sg:phone":"+45 97 43 22 60",
    "sg:postcode":"7500",
    "sg:province":"Danmark",
    "sg:website":"www.marc-levin-consult.com",
    "wof:name":"Levin, Marc",
    "wof:placetype":"venue"
},
  "geometry": {"coordinates":[8.5955972672,56.406288147],"type":"Point"}
}