{
  "type": "Feature",
  "properties": {
    "addr:full":"T\u00f8ndervej 8 Ribe Danmark 6760",
    "addr:housenumber":"8",
    "addr:postcode":"6760",
    "addr:street":"Tondervej",
    "iso:country":"DK",
    "sg:address":"T\u00f8ndervej 8",
    "sg:city":"Ribe",
    "sg:orig_category":"Emballage",
    "sg:phone":"+45 75 42 37 11",
    "sg:postcode":"6760",
    "sg:province":"Danmark",
    "wof:name":"Dansk Tr\u00e6emballage A/S",
    "wof:placetype":"venue"
},
  "geometry": {"coordinates":[8.7563123703,55.3248672485],"type":"Point"}
}