{
  "type": "Feature",
  "properties": {
    "addr:full":"Havnegade 20 B Frederikssund Danmark 3600",
    "addr:housenumber":"20 b",
    "addr:postcode":"3600",
    "addr:street":"Havnegade",
    "iso:country":"DK",
    "sg:address":"Havnegade 20 B",
    "sg:city":"Frederikssund",
    "sg:orig_category":"Pizzeriaer",
    "sg:phone":"+45 47 38 59 38",
    "sg:postcode":"3600",
    "sg:province":"Danmark",
    "wof:name":"Frederikssund Shawarma & Pizzaria",
    "wof:placetype":"venue"
},
  "geometry": {"coordinates":[12.0580749512,55.8387908936],"type":"Point"}
}