{
  "type": "Feature",
  "properties": {
    "addr:full":"Ringstedvej 669 Ringsted Danmark 4100",
    "addr:housenumber":"669",
    "addr:postcode":"4100",
    "addr:street":"Ringstedvej",
    "iso:country":"DK",
    "sg:address":"Ringstedvej 669",
    "sg:city":"Ringsted",
    "sg:orig_category":"Trailerudlejning",
    "sg:phone":"+45 56 87 91 11",
    "sg:postcode":"4100",
    "sg:province":"Danmark",
    "wof:name":"DK Benzin",
    "wof:placetype":"venue"
},
  "geometry": {"coordinates":[11.9597072601,55.4484138489],"type":"Point"}
}