{
  "type": "Feature",
  "properties": {
    "iso:country":"DK",
    "sg:address":"Borgergade 4",
    "sg:city":"Grindsted",
    "sg:orig_category":"Ure og urmagere",
    "sg:phone":"+45 75 32 23 11",
    "sg:postcode":"7200",
    "sg:province":"Danmark",
    "wof:name":"Kirk-Thomsen Ure og Smykker",
    "wof:placetype":"venue"
},
  "geometry": {"coordinates":[8.9279537201,55.7572669983],"type":"Point"}
}