{
  "type": "Feature",
  "properties": {
    "addr:full":"Carl Blochs Vej 5 Fredericia Danmark 7000",
    "addr:housenumber":"5",
    "addr:postcode":"7000",
    "addr:street":"Carl Blochs Vej",
    "iso:country":"DK",
    "sg:address":"Carl Blochs Vej 5",
    "sg:city":"Fredericia",
    "sg:orig_category":"Autoruder",
    "sg:phone":"+45 75 92 85 06",
    "sg:postcode":"7000",
    "sg:province":"Danmark",
    "wof:name":"Glass Tech System",
    "wof:placetype":"venue"
},
  "geometry": {"coordinates":[9.7701177597,55.5959968567],"type":"Point"}
}