{
  "type": "Feature",
  "properties": {
    "iso:country":"DK",
    "sg:address":"Fmd.: Lars B\u00f8ttern, Vibevej 24",
    "sg:city":"Tarm",
    "sg:orig_category":"Grundejerforeninger",
    "sg:phone":"+45 97 37 10 16",
    "sg:postcode":"6880",
    "sg:province":"Danmark",
    "wof:name":"Beboer- og Grundejerforening Fuglekvarteret ",
    "wof:placetype":"venue"
},
  "geometry": {"coordinates":[8.5200052261,55.9060554504],"type":"Point"}
}