{
  "type": "Feature",
  "properties": {
    "addr:full":"Danmarksgade 52 Aalborg Danmark 9000",
    "addr:housenumber":"52",
    "addr:postcode":"9000",
    "addr:street":"Danmarksgade",
    "iso:country":"DK",
    "sg:address":"Danmarksgade 52",
    "sg:city":"Aalborg",
    "sg:orig_category":"Kirkelige foreninger",
    "sg:phone":"+45 98 16 64 59",
    "sg:postcode":"9000",
    "sg:province":"Danmark",
    "wof:name":"KFUM og KFUK i Aalborg",
    "wof:placetype":"venue"
},
  "geometry": {"coordinates":[9.9203720093,57.0451087952],"type":"Point"}
}