{
  "type": "Feature",
  "properties": {
    "addr:full":"Holbergsgade 24 Aalborg Danmark 9000",
    "addr:housenumber":"24",
    "addr:postcode":"9000",
    "addr:street":"Holbergsgade",
    "iso:country":"DK",
    "sg:address":"Holbergsgade 24",
    "sg:city":"Aalborg",
    "sg:orig_category":"Farve- og stilanalyse",
    "sg:phone":"+45 98 10 31 90",
    "sg:postcode":"9000",
    "sg:province":"Danmark",
    "wof:name":"Stil Studio",
    "wof:placetype":"venue"
},
  "geometry": {"coordinates":[9.9146127701,57.049446106],"type":"Point"}
}