{
  "type": "Feature",
  "properties": {
    "iso:country":"DK",
    "sg:address":"Hjerndrup N\u00f8rrevej 7",
    "sg:city":"Christiansfeld",
    "sg:orig_category":"Autoreparation og -service",
    "sg:phone":"+45 74 56 26 57",
    "sg:postcode":"6070",
    "sg:province":"Danmark",
    "wof:name":"Weiland, Christian",
    "wof:placetype":"venue"
},
  "geometry": {"coordinates":[9.4187583923,55.3337593079],"type":"Point"}
}