{
  "type": "Feature",
  "properties": {
    "addr:full":"Priorgade 3 Sor\u00f8 Danmark 4180",
    "addr:housenumber":"3",
    "addr:postcode":"4180",
    "addr:street":"Priorgade",
    "iso:country":"DK",
    "sg:address":"Priorgade 3",
    "sg:city":"Sor\u00f8",
    "sg:orig_category":"Revisorer",
    "sg:phone":"+45 57 86 00 86",
    "sg:postcode":"4180",
    "sg:province":"Danmark",
    "wof:name":"Deloitte & Touche",
    "wof:placetype":"venue"
},
  "geometry": {"coordinates":[-102.94467926030001,45.4534721375],"type":"Point"}
}