{
  "type": "Feature",
  "properties": {
    "addr:full":"H\u00f8jn\u00e6svej 42 R\u00f8dovre Danmark 2610",
    "addr:housenumber":"42",
    "addr:postcode":"2610",
    "addr:street":"Hojnaesvej",
    "iso:country":"DK",
    "sg:address":"H\u00f8jn\u00e6svej 42",
    "sg:city":"R\u00f8dovre",
    "sg:orig_category":"El-artikler",
    "sg:phone":"+45 36 72 22 00",
    "sg:postcode":"2610",
    "sg:province":"Danmark",
    "wof:name":"Elthermo Searchlight A/S",
    "wof:placetype":"venue"
},
  "geometry": {"coordinates":[10.6992139816,61.1027755737],"type":"Point"}
}