{
  "type": "Feature",
  "properties": {
    "addr:full":"Krystalgade 1 S\u00e6by Danmark 9300",
    "addr:housenumber":"1",
    "addr:postcode":"9300",
    "addr:street":"Krystalgade",
    "iso:country":"DK",
    "sg:address":"Krystalgade 1",
    "sg:city":"S\u00e6by",
    "sg:classifiers":[
        {
            "category":"Taxi",
            "type":"Transportation"
        }
    ],
    "sg:phone":"+45 98 46 12 14",
    "sg:postcode":"9300",
    "sg:province":"Danmark",
    "wof:name":"Taxa Ring Bilen",
    "wof:placetype":"venue"
},
  "geometry": {"coordinates":[10.5188646317,57.3343887329],"type":"Point"}
}