{
  "type": "Feature",
  "properties": {
    "addr:full":"Thorsvej 2 Kongens Lyngby Danmark 2800",
    "addr:housenumber":"2",
    "addr:postcode":"2800",
    "addr:street":"Thorsvej",
    "iso:country":"DK",
    "sg:address":"Thorsvej 2",
    "sg:city":"Kongens Lyngby",
    "sg:orig_category":"Telte, Udlejning af",
    "sg:phone":"+45 45 88 78 93",
    "sg:postcode":"2800",
    "sg:province":"Danmark",
    "wof:name":"Cirkus 3's teltudlejning",
    "wof:placetype":"venue"
},
  "geometry": {"coordinates":[12.4941806793,55.7685508728],"type":"Point"}
}