{
  "type": "Feature",
  "properties": {
    "addr:full":"v/ Niels Tryde, Ravnsborggade 12 K\u00f8benhavn N Danmark 2200",
    "addr:housenumber":"12",
    "addr:postcode":"2200",
    "addr:street":"Ravnsborggade;N Danmark",
    "iso:country":"DK",
    "sg:address":"v/ Niels Tryde, Ravnsborggade 12",
    "sg:city":"K\u00f8benhavn N",
    "sg:orig_category":"Antikviteter",
    "sg:phone":"+45 36 44 31 42",
    "sg:postcode":"2200",
    "sg:province":"Danmark",
    "wof:name":"Vejrhanen",
    "wof:placetype":"venue"
},
  "geometry": {"coordinates":[11.2520399094,53.3618812561],"type":"Point"}
}