{
  "type": "Feature",
  "properties": {
    "addr:full":"Pal\u00e6gade 6 - 8 Jerslev Danmark 9740",
    "addr:housenumber":"6 8",
    "addr:postcode":"9740",
    "addr:street":"Palaegade",
    "iso:country":"DK",
    "sg:address":"Pal\u00e6gade 6 - 8",
    "sg:city":"Jerslev",
    "sg:orig_category":"Varmeforsyning",
    "sg:phone":"+45 98 83 13 08",
    "sg:postcode":"9740",
    "sg:province":"Danmark",
    "wof:name":"Jerslev Kraftvarmev\u00e6rk",
    "wof:placetype":"venue"
},
  "geometry": {"coordinates":[10.0935983658,57.2854728699],"type":"Point"}
}