{
  "type": "Feature",
  "properties": {
    "iso:country":"DK",
    "sg:address":"Rebekkavej 31",
    "sg:city":"Hellerup",
    "sg:orig_category":"Ergonomi",
    "sg:phone":"+45 70 20 18 80",
    "sg:postcode":"2900",
    "sg:province":"Danmark",
    "sg:website":"www.ergodanmark.dk",
    "wof:name":"Ergo Danmark",
    "wof:placetype":"venue"
},
  "geometry": {"coordinates":[12.5638771057,55.7306785583],"type":"Point"}
}