{
  "type": "Feature",
  "properties": {
    "addr:full":"Ymersvej 5 Frederikssund Danmark 3600",
    "addr:housenumber":"5",
    "addr:postcode":"3600",
    "addr:street":"Ymersvej",
    "iso:country":"DK",
    "sg:address":"Ymersvej 5",
    "sg:city":"Frederikssund",
    "sg:orig_category":"Fodterapeuter",
    "sg:phone":"+45 47 31 56 59",
    "sg:postcode":"3600",
    "sg:province":"Danmark",
    "wof:name":"Pedersen, Sonja",
    "wof:placetype":"venue"
},
  "geometry": {"coordinates":[12.0559358597,55.8473625183],"type":"Point"}
}