{
  "type": "Feature",
  "properties": {
    "addr:full":"Maglemosevej 21 Hellerup Danmark 2900",
    "addr:housenumber":"21",
    "addr:postcode":"2900",
    "addr:street":"Maglemosevej",
    "iso:country":"DK",
    "sg:address":"Maglemosevej 21",
    "sg:city":"Hellerup",
    "sg:orig_category":"Engros handel",
    "sg:phone":"+45 39 63 63 35",
    "sg:postcode":"2900",
    "sg:province":"Danmark",
    "wof:name":"Himmel & Hav",
    "wof:placetype":"venue"
},
  "geometry": {"coordinates":[12.5781841278,55.7441825867],"type":"Point"}
}