{
  "type": "Feature",
  "properties": {
    "addr:full":"Tangmosevej 101 K\u00f8ge Danmark 4600",
    "addr:housenumber":"101",
    "addr:postcode":"4600",
    "addr:street":"Tangmosevej",
    "iso:country":"DK",
    "sg:address":"Tangmosevej 101",
    "sg:city":"K\u00f8ge",
    "sg:orig_category":"Autoforhandlere",
    "sg:phone":"+45 56 65 68 00",
    "sg:postcode":"4600",
    "sg:province":"Danmark",
    "sg:website":"www.maxdue.dk",
    "wof:name":"Fiat-Alfa-Lancia, Max Due A/S",
    "wof:placetype":"venue"
},
  "geometry": {"coordinates":[12.1853628159,55.4730758667],"type":"Point"}
}