{
  "type": "Feature",
  "properties": {
    "addr:full":"Dyrh\u00f8jvej 10 Odense M Danmark 5230",
    "addr:housenumber":"10",
    "addr:postcode":"5230",
    "addr:street":"Dyrhojvej",
    "iso:country":"DK",
    "sg:address":"Dyrh\u00f8jvej 10",
    "sg:city":"Odense M",
    "sg:orig_category":"Engros handel",
    "sg:phone":"+45 66 13 21 06",
    "sg:postcode":"5230",
    "sg:province":"Danmark",
    "wof:name":"Faltum Denmark ApS",
    "wof:placetype":"venue"
},
  "geometry": {"coordinates":[10.4118947983,55.3874053955],"type":"Point"}
}