{
  "type": "Feature",
  "properties": {
    "addr:full":"v/ Jesper H. Andersen, Klattrupgade 27 Havndal Danmark 8970",
    "addr:housenumber":"27",
    "addr:postcode":"8970",
    "addr:street":"Klattrupgade",
    "iso:country":"DK",
    "sg:address":"v/ Jesper H. Andersen, Klattrupgade 27",
    "sg:city":"Havndal",
    "sg:orig_category":"Forsamlingshuse",
    "sg:phone":"+45 86 47 08 48",
    "sg:postcode":"8970",
    "sg:province":"Danmark",
    "wof:name":"Forsamlingshuset Estraden",
    "wof:placetype":"venue"
},
  "geometry": {"coordinates":[10.1937646866,56.6534461975],"type":"Point"}
}