{
  "type": "Feature",
  "properties": {
    "addr:full":"Herlev Torv 2 Herlev Danmark 2730",
    "addr:housenumber":"2",
    "addr:postcode":"2730",
    "addr:street":"Herlev Torv",
    "iso:country":"DK",
    "sg:address":"Herlev Torv 2",
    "sg:city":"Herlev",
    "sg:orig_category":"Kontorartikler",
    "sg:phone":"+45 44 91 31 33",
    "sg:postcode":"2730",
    "sg:province":"Danmark",
    "wof:name":"Herlev Kontorforsyning",
    "wof:placetype":"venue"
},
  "geometry": {"coordinates":[12.4394464493,55.7235069275],"type":"Point"}
}