{
  "type": "Feature",
  "properties": {
    "addr:full":"Fmd.: Vibeke Pedersen, Gl. Kongevej 1 K, Tarm Tarm Danmark 6880",
    "addr:housenumber":"1 k",
    "addr:postcode":"6880",
    "addr:street":"Pedersen Gl. Kongevej",
    "iso:country":"DK",
    "sg:address":"Fmd.: Vibeke Pedersen, Gl. Kongevej 1 K, Tarm",
    "sg:city":"Tarm",
    "sg:orig_category":"Andelsboligforeninger",
    "sg:phone":"+45 97 37 22 72",
    "sg:postcode":"6880",
    "sg:province":"Danmark",
    "wof:name":"Andelsboligforeningen Hj\u00f8rnebo Gl. Kongevej 1 A-K",
    "wof:placetype":"venue"
},
  "geometry": {"coordinates":[8.5200052261,55.9060554504],"type":"Point"}
}