{
  "type": "Feature",
  "properties": {
    "addr:full":"\u00c6rtebjergg\u00e5rdvej 43, Kirkendrup Odense N Danmark 5270",
    "addr:housenumber":"43",
    "addr:postcode":"5270",
    "addr:street":"Aertebjerggaardvej",
    "iso:country":"DK",
    "sg:address":"\u00c6rtebjergg\u00e5rdvej 43, Kirkendrup",
    "sg:city":"Odense N",
    "sg:orig_category":"Engros handel",
    "sg:phone":"+45 66 18 24 84",
    "sg:postcode":"5270",
    "sg:province":"Danmark",
    "wof:name":"Borgermann, B\u00f8rge",
    "wof:placetype":"venue"
},
  "geometry": {"coordinates":[10.3306798935,55.4711418152],"type":"Point"}
}