{
  "type": "Feature",
  "properties": {
    "addr:full":"Skt. Klemens V\u00e6nge 5, Skt Klemens Odense S Danmark 5260",
    "addr:housenumber":"5",
    "addr:postcode":"5260",
    "addr:street":"Skt.;Vaenge;Skt Klemens",
    "iso:country":"DK",
    "sg:address":"Skt. Klemens V\u00e6nge 5, Skt Klemens",
    "sg:city":"Odense S",
    "sg:orig_category":"Isenkram en gros",
    "sg:phone":"+45 66 15 11 23",
    "sg:postcode":"5260",
    "sg:province":"Danmark",
    "wof:name":"Emperto",
    "wof:placetype":"venue"
},
  "geometry": {"coordinates":[10.3157806396,55.3122825623],"type":"Point"}
}