{
  "type": "Feature",
  "properties": {
    "iso:country":"DK",
    "sg:address":"\u00d8stergade 15",
    "sg:city":"Maribo",
    "sg:orig_category":"Slagter og viktualie",
    "sg:phone":"+45 54 78 16 46",
    "sg:postcode":"4930",
    "sg:province":"Danmark",
    "sg:website":"www.blomster-almue.subnet.dk",
    "wof:name":"Slagteren i Maribo",
    "wof:placetype":"venue"
},
  "geometry": {"coordinates":[11.502035141,54.7743835449],"type":"Point"}
}