{
  "type": "Feature",
  "properties": {
    "iso:country":"DK",
    "sg:address":"N. A. Christensensvej 11",
    "sg:city":"Nyk\u00f8bing",
    "sg:orig_category":"Blikkenslagere",
    "sg:phone":"+45 97 71 13 11",
    "sg:postcode":"7900",
    "sg:province":"Danmark",
    "wof:name":"Rughave, Klaus",
    "wof:placetype":"venue"
},
  "geometry": {"coordinates":[-114.07682,46.443241],"type":"Point"}
}