{
  "type": "Feature",
  "properties": {
    "addr:full":"Gruppestyrelsesfmd.: Ebba Fuglsang, Annasvej 11 Hj\u00f8rring Danmark 9800",
    "addr:housenumber":"11",
    "addr:postcode":"9800",
    "addr:street":"Ebba Fuglsang Annasvej",
    "iso:country":"DK",
    "sg:address":"Gruppestyrelsesfmd.: Ebba Fuglsang, Annasvej 11",
    "sg:city":"Hj\u00f8rring",
    "sg:orig_category":"Spejderkorps",
    "sg:phone":"+45 98 92 23 61",
    "sg:postcode":"9800",
    "sg:province":"Danmark",
    "sg:website":"www.hjoerring-spejder.dk",
    "wof:name":"DDS - 1. Hj\u00f8rring gruppe",
    "wof:placetype":"venue"
},
  "geometry": {"coordinates":[9.9885387421,57.4594764709],"type":"Point"}
}