{
  "type": "Feature",
  "properties": {
    "addr:full":"Hovmarken 4 Lystrup Danmark 8520",
    "addr:housenumber":"4",
    "addr:postcode":"8520",
    "addr:street":"Hovmarken",
    "iso:country":"DK",
    "sg:address":"Hovmarken 4",
    "sg:city":"Lystrup",
    "sg:orig_category":"Elektro",
    "sg:phone":"+45 87 43 60 00",
    "sg:postcode":"8520",
    "sg:province":"Danmark",
    "wof:name":"TERMA Elektronik A/S",
    "wof:placetype":"venue"
},
  "geometry": {"coordinates":[10.2420015335,56.234161377],"type":"Point"}
}