{
  "type": "Feature",
  "properties": {
    "addr:full":"Bregneg\u00e5rdsvej 21 B Hellerup Danmark 2900",
    "addr:housenumber":"21 b",
    "addr:postcode":"2900",
    "addr:street":"Bregnegaardsvej",
    "iso:country":"DK",
    "sg:address":"Bregneg\u00e5rdsvej 21 B",
    "sg:city":"Hellerup",
    "sg:orig_category":"Kommunale ungdomsskoler",
    "sg:phone":"+45 39 46 02 20",
    "sg:postcode":"2900",
    "sg:province":"Danmark",
    "sg:website":"www.gentofte-ungdomsskole.dk",
    "wof:name":"Gentofte Kommunes Ungdomsskole",
    "wof:placetype":"venue"
},
  "geometry": {"coordinates":[12.5683794022,55.7438774109],"type":"Point"}
}