{
  "type": "Feature",
  "properties": {
    "iso:country":"DK",
    "sg:address":"Metheasvej 1",
    "sg:city":"Hvide Sande",
    "sg:orig_category":"Advokater",
    "sg:phone":"+45 97 31 14 57",
    "sg:postcode":"6960",
    "sg:province":"Danmark",
    "wof:name":"Jepsen & Stensg\u00e5rd",
    "wof:placetype":"venue"
},
  "geometry": {"coordinates":[8.1266012192,55.9992141724],"type":"Point"}
}