{
  "type": "Feature",
  "properties": {
    "iso:country":"DK",
    "sg:address":"Nyboesgade 35",
    "sg:city":"Vejle",
    "sg:classifiers":[
        {
            "category":"Communications",
            "type":"Services"
        }
    ],
    "sg:phone":"+45 75 83 88 22",
    "sg:postcode":"7100",
    "sg:province":"Danmark",
    "sg:tags":[
        "radio-",
        "og",
        "tv-stationer"
    ],
    "wof:name":"VLR",
    "wof:placetype":"venue"
},
  "geometry": {"coordinates":[9.5282611847,55.7126464844],"type":"Point"}
}