{
  "type": "Feature",
  "properties": {
    "addr:full":"Havhusevej 4, Egens R\u00f8nde Danmark 8410",
    "addr:housenumber":"4 egens",
    "addr:postcode":"8410",
    "addr:street":"Havhusevej",
    "iso:country":"DK",
    "sg:address":"Havhusevej 4, Egens",
    "sg:city":"R\u00f8nde",
    "sg:orig_category":"Keramik",
    "sg:phone":"+45 86 37 30 00",
    "sg:postcode":"8410",
    "sg:province":"Danmark",
    "sg:website":"www.malene-moeller-hansen.dk",
    "wof:name":"Holmen, Sverre Tveito & Malene M\u00f8ller Hansen",
    "wof:placetype":"venue"
},
  "geometry": {"coordinates":[10.4288892746,56.295917511],"type":"Point"}
}