{
  "type": "Feature",
  "properties": {
    "iso:country":"DK",
    "sg:address":"Ringk\u00f8bingvej 70",
    "sg:city":"Varde",
    "sg:orig_category":"Blomsterhandlere",
    "sg:phone":"+45 75 22 47 55",
    "sg:postcode":"6800",
    "sg:province":"Danmark",
    "wof:name":"Nielsens Planteskole",
    "wof:placetype":"venue"
},
  "geometry": {"coordinates":[8.4843473434,55.6313896179],"type":"Point"}
}