{
  "type": "Feature",
  "properties": {
    "addr:full":"Katrinegade 23 Kolding Danmark 6000",
    "addr:housenumber":"23",
    "addr:postcode":"6000",
    "addr:street":"Katrinegade",
    "iso:country":"DK",
    "sg:address":"Katrinegade 23",
    "sg:city":"Kolding",
    "sg:orig_category":"Kopimaskiner",
    "sg:phone":"+45 75 50 85 55",
    "sg:postcode":"6000",
    "sg:province":"Danmark",
    "sg:website":"www.bodenhoff.dk",
    "wof:name":"Bodenhoff A/S",
    "wof:placetype":"venue"
},
  "geometry": {"coordinates":[9.4677095413,55.4910392761],"type":"Point"}
}