{
  "type": "Feature",
  "properties": {
    "addr:full":"Els\u00f8vej 101 Nyk\u00f8bing Danmark 7900",
    "addr:housenumber":"101",
    "addr:postcode":"7900",
    "addr:street":"Elsovej",
    "iso:country":"DK",
    "sg:address":"Els\u00f8vej 101",
    "sg:city":"Nyk\u00f8bing",
    "sg:orig_category":"\u00c3\u02dcvrige skoler",
    "sg:phone":"+45 97 71 10 22",
    "sg:postcode":"7900",
    "sg:province":"Danmark",
    "wof:name":"Rolstruphus, Mors\u00f8 Produktionsskole",
    "wof:placetype":"venue"
},
  "geometry": {"coordinates":[-114.0768203735,46.4432411194],"type":"Point"}
}