{
  "type": "Feature",
  "properties": {
    "addr:full":"Byvej 24, 1. Frederikssund Danmark 3600",
    "addr:housenumber":"24 1",
    "addr:postcode":"3600",
    "addr:street":"Byvej",
    "iso:country":"DK",
    "sg:address":"Byvej 24, 1.",
    "sg:city":"Frederikssund",
    "sg:orig_category":"Faglige organisationer og foreninger",
    "sg:phone":"+45 47 31 33 69",
    "sg:postcode":"3600",
    "sg:province":"Danmark",
    "wof:name":"Danmarks L\u00e6rerforening, Kreds 37",
    "wof:placetype":"venue"
},
  "geometry": {"coordinates":[12.0637626648,55.850227356],"type":"Point"}
}