{
  "type": "Feature",
  "properties": {
    "addr:full":"K\u00f8gevej 108 D Roskilde Danmark 4000",
    "addr:housenumber":"108 d",
    "addr:postcode":"4000",
    "addr:street":"Kogevej",
    "iso:country":"DK",
    "sg:address":"K\u00f8gevej 108 D",
    "sg:city":"Roskilde",
    "sg:orig_category":"Apoteker og -udsalg",
    "sg:phone":"+45 46 32 77 55",
    "sg:postcode":"4000",
    "sg:province":"Danmark",
    "wof:name":"Apoteksudsalget",
    "wof:placetype":"venue"
},
  "geometry": {"coordinates":[12.0897026062,55.6316795349],"type":"Point"}
}