{
  "type": "Feature",
  "properties": {
    "addr:full":"Industrivej 6 Hadsten Danmark 8370",
    "addr:housenumber":"6",
    "addr:postcode":"8370",
    "addr:street":"Industrivej",
    "iso:country":"DK",
    "sg:address":"Industrivej 6",
    "sg:city":"Hadsten",
    "sg:orig_category":"Industrilakering",
    "sg:phone":"+45 86 98 36 99",
    "sg:postcode":"8370",
    "sg:province":"Danmark",
    "wof:name":"Capricorn",
    "wof:placetype":"venue"
},
  "geometry": {"coordinates":[10.052116394,56.3330230713],"type":"Point"}
}