{
  "type": "Feature",
  "properties": {
    "addr:full":"\u00d8stervangsvej 2 Stege Danmark 4780",
    "addr:housenumber":"2",
    "addr:postcode":"4780",
    "addr:street":"Ostervangsvej",
    "iso:country":"DK",
    "sg:address":"\u00d8stervangsvej 2",
    "sg:city":"Stege",
    "sg:orig_category":"Produktionsskoler",
    "sg:phone":"+45 55 81 03 70",
    "sg:postcode":"4780",
    "sg:province":"Danmark",
    "wof:name":"M\u00f8n Produktionsskole",
    "wof:placetype":"venue"
},
  "geometry": {"coordinates":[12.2918272018,54.989906311],"type":"Point"}
}