{
  "type": "Feature",
  "properties": {
    "addr:full":"\u00c5rhusvej 22 A Grenaa Danmark 8500",
    "addr:housenumber":"22 a",
    "addr:postcode":"8500",
    "addr:street":"Aarhusvej",
    "iso:country":"DK",
    "sg:address":"\u00c5rhusvej 22 A",
    "sg:city":"Grenaa",
    "sg:orig_category":"Psykologer, praktiserende",
    "sg:phone":"+45 86 32 75 10",
    "sg:postcode":"8500",
    "sg:province":"Danmark",
    "wof:name":"Psykologisk - Terapeutisk Klinik",
    "wof:placetype":"venue"
},
  "geometry": {"coordinates":[10.8724393845,56.4086151123],"type":"Point"}
}