{
  "type": "Feature",
  "properties": {
    "addr:full":"Tilegade 28 Nakskov Danmark 4900",
    "addr:housenumber":"28",
    "addr:postcode":"4900",
    "addr:street":"Tilegade",
    "iso:country":"DK",
    "sg:address":"Tilegade 28",
    "sg:city":"Nakskov",
    "sg:orig_category":"Cykler",
    "sg:phone":"+45 54 92 41 54",
    "sg:postcode":"4900",
    "sg:province":"Danmark",
    "wof:name":"Storgaard Cykler",
    "wof:placetype":"venue"
},
  "geometry": {"coordinates":[11.1384134293,54.8312759399],"type":"Point"}
}