{
  "type": "Feature",
  "properties": {
    "addr:full":"Femkanten G 7 Taastrup Danmark 2630",
    "addr:housenumber":"7",
    "addr:postcode":"2630",
    "addr:street":"Femkanten G",
    "iso:country":"DK",
    "sg:address":"Femkanten G 7",
    "sg:city":"Taastrup",
    "sg:orig_category":"Personaleudvikling",
    "sg:phone":"+45 43 52 16 95",
    "sg:postcode":"2630",
    "sg:province":"Danmark",
    "wof:name":"Jobtek Management",
    "wof:placetype":"venue"
},
  "geometry": {"coordinates":[12.3157129288,55.6433563232],"type":"Point"}
}