{
  "type": "Feature",
  "properties": {
    "addr:full":"Stationstorvet 12 Albertslund Danmark 2620",
    "addr:housenumber":"12",
    "addr:postcode":"2620",
    "addr:street":"Stationstorvet",
    "iso:country":"DK",
    "sg:address":"Stationstorvet 12",
    "sg:city":"Albertslund",
    "sg:orig_category":"Tandklinikker, Kommunale",
    "sg:phone":"+45 43 64 55 82",
    "sg:postcode":"2620",
    "sg:province":"Danmark",
    "wof:name":"Tandreguleringsklinik",
    "wof:placetype":"venue"
},
  "geometry": {"coordinates":[12.3540477753,55.6576805115],"type":"Point"}
}