{
  "type": "Feature",
  "properties": {
    "addr:full":"Maren Turis Gade 2 Aalborg Danmark 9000",
    "addr:housenumber":"2",
    "addr:postcode":"9000",
    "addr:street":"Maren Turis Gade",
    "iso:country":"DK",
    "sg:address":"Maren Turis Gade 2",
    "sg:city":"Aalborg",
    "sg:classifiers":[
        {
            "category":"Banks & Credit Unions",
            "subcategory":"Financial Services",
            "type":"Services"
        }
    ],
    "sg:phone":"+45 98 11 11 88",
    "sg:postcode":"9000",
    "sg:province":"Danmark",
    "sg:tags":[
        "banking",
        "finance",
        "insurance"
    ],
    "wof:name":"NORSOFT HOLDING A/S",
    "wof:placetype":"venue"
},
  "geometry": {"coordinates":[9.9208698273,57.0494003296],"type":"Point"}
}