{
  "type": "Feature",
  "properties": {
    "addr:full":"Nokiavej 10 Horsens Danmark 8700",
    "addr:housenumber":"10",
    "addr:postcode":"8700",
    "addr:street":"Nokiavej",
    "iso:country":"DK",
    "sg:address":"Nokiavej 10",
    "sg:city":"Horsens",
    "sg:orig_category":"Maskinfabrikker",
    "sg:phone":"+45 76 27 33 00",
    "sg:postcode":"8700",
    "sg:province":"Danmark",
    "sg:website":"www.okm.dk",
    "wof:name":"Otto K\u00f8hlers Maskinfabrik A/S",
    "wof:placetype":"venue"
},
  "geometry": {"coordinates":[9.7777938843,55.8864212036],"type":"Point"}
}