{
  "type": "Feature",
  "properties": {
    "addr:full":"D\u00e5dyrvej 85 Skibby Danmark 4050",
    "addr:housenumber":"85",
    "addr:postcode":"4050",
    "addr:street":"Daadyrvej",
    "iso:country":"DK",
    "sg:address":"D\u00e5dyrvej 85",
    "sg:city":"Skibby",
    "sg:orig_category":"Revisorer",
    "sg:phone":"+45 47 51 21 51",
    "sg:postcode":"4050",
    "sg:province":"Danmark",
    "wof:name":"KP Revision",
    "wof:placetype":"venue"
},
  "geometry": {"coordinates":[11.9720191956,55.7441177368],"type":"Point"}
}