{
  "type": "Feature",
  "properties": {
    "addr:full":"Stationsvej 11 Vemmelev Danmark 4241",
    "addr:housenumber":"11",
    "addr:postcode":"4241",
    "addr:street":"Stationsvej",
    "iso:country":"DK",
    "sg:address":"Stationsvej 11",
    "sg:city":"Vemmelev",
    "sg:orig_category":"Plejehjem",
    "sg:phone":"+45 58 38 22 26",
    "sg:postcode":"4241",
    "sg:province":"Danmark",
    "wof:name":"Vemmelev Plejehjem",
    "wof:placetype":"venue"
},
  "geometry": {"coordinates":[11.2591285706,55.3650093079],"type":"Point"}
}