{
  "type": "Feature",
  "properties": {
    "addr:full":"Englerup Gade 27 A, Englerup Kirke S\u00e5by Danmark 4060",
    "addr:housenumber":"27 a",
    "addr:postcode":"4060",
    "addr:street":"Englerup Gade;Englerup Kirke",
    "iso:country":"DK",
    "sg:address":"Englerup Gade 27 A, Englerup",
    "sg:city":"Kirke S\u00e5by",
    "sg:orig_category":"Revisorer",
    "sg:phone":"+45 46 49 92 80",
    "sg:postcode":"4060",
    "sg:province":"Danmark",
    "wof:name":"S\u00f8rensen, Agnes C.T.",
    "wof:placetype":"venue"
},
  "geometry": {"coordinates":[11.8739786148,55.6341285706],"type":"Point"}
}