{
  "type": "Feature",
  "properties": {
    "addr:full":"v/ Kirsten Andersen, Christiansgade 1 Hobro Danmark 9500",
    "addr:housenumber":"1",
    "addr:postcode":"9500",
    "addr:street":"Christiansgade",
    "iso:country":"DK",
    "sg:address":"v/ Kirsten Andersen, Christiansgade 1",
    "sg:city":"Hobro",
    "sg:orig_category":"Tandklinikker, Kommunale",
    "sg:phone":"+45 98 52 24 30",
    "sg:postcode":"9500",
    "sg:province":"Danmark",
    "wof:name":"Sdr. Skoles Tandklinik",
    "wof:placetype":"venue"
},
  "geometry": {"coordinates":[9.7946596146,56.6382789612],"type":"Point"}
}