{
  "type": "Feature",
  "properties": {
    "iso:country":"DK",
    "sg:address":"Bogfinkevej 1",
    "sg:city":"Skanderborg",
    "sg:orig_category":"Brandsikring",
    "sg:phone":"+45 86 52 42 72",
    "sg:postcode":"8660",
    "sg:province":"Danmark",
    "wof:name":"E-Montage Port- og d\u00f8rservice",
    "wof:placetype":"venue"
},
  "geometry": {"coordinates":[9.9560079575,56.0410575867],"type":"Point"}
}