{
  "type": "Feature",
  "properties": {
    "iso:country":"DK",
    "sg:address":"Brendstrupg\u00e5rdsvej 100",
    "sg:city":"\u00c5rhus N",
    "sg:orig_category":"Offentlige sygehuse",
    "sg:phone":"+45 89 49 55 66",
    "sg:postcode":"8200",
    "sg:province":"Danmark",
    "wof:name":"Skejby Sygehus",
    "wof:placetype":"venue"
},
  "geometry": {"coordinates":[4.9393601418,49.7092018127],"type":"Point"}
}