{
  "type": "Feature",
  "properties": {
    "iso:country":"DK",
    "sg:address":"Kirkevej 4",
    "sg:city":"Strandby",
    "sg:orig_category":"Malermestre",
    "sg:phone":"+45 98 48 16 66",
    "sg:postcode":"9970",
    "sg:province":"Danmark",
    "wof:name":"Strandby Malerforretning",
    "wof:placetype":"venue"
},
  "geometry": {"coordinates":[10.4996366501,57.4929733276],"type":"Point"}
}