{
  "type": "Feature",
  "properties": {
    "addr:full":"Danmarksgade 78, 1. Frederikshavn Danmark 9900",
    "addr:housenumber":"78 1",
    "addr:postcode":"9900",
    "addr:street":"Danmarksgade",
    "iso:country":"DK",
    "sg:address":"Danmarksgade 78, 1.",
    "sg:city":"Frederikshavn",
    "sg:classifiers":[
        {
            "category":"Communications",
            "type":"Services"
        }
    ],
    "sg:phone":"+45 98 42 55 42",
    "sg:postcode":"9900",
    "sg:province":"Danmark",
    "sg:tags":[
        "radio-",
        "og",
        "tv-stationer"
    ],
    "sg:website":"www.fmr.adsl.dk",
    "wof:name":"Frederikshavn Multietniske Forening og Radio",
    "wof:placetype":"venue"
},
  "geometry": {"coordinates":[10.5350608826,57.4385719299],"type":"Point"}
}