{
  "type": "Feature",
  "properties": {
    "addr:full":"Bredgade 18 B Hedensted Danmark 8722",
    "addr:housenumber":"18 b",
    "addr:postcode":"8722",
    "addr:street":"Bredgade",
    "iso:country":"DK",
    "sg:address":"Bredgade 18 B",
    "sg:city":"Hedensted",
    "sg:orig_category":"Ejendomshandel",
    "sg:phone":"+45 75 89 23 24",
    "sg:postcode":"8722",
    "sg:province":"Danmark",
    "wof:name":"Bankes Ejendomskontor",
    "wof:placetype":"venue"
},
  "geometry": {"coordinates":[9.6970472336,55.7703781128],"type":"Point"}
}