{
  "type": "Feature",
  "properties": {
    "addr:full":"Ryesgade 9, Postboks 348 8100",
    "addr:housenumber":"9;348",
    "addr:postcode":"8100",
    "addr:street":"Ryesgade",
    "iso:country":"DK",
    "sg:address":"Ryesgade 9, Postboks 348",
    "sg:orig_category":"Advokater",
    "sg:phone":"+45 86 12 28 22",
    "sg:postcode":"8100",
    "wof:name":"Winther-Rasmussen, Allan",
    "wof:placetype":"venue"
},
  "geometry": {"coordinates":[2.0778300762,49.1431007385],"type":"Point"}
}