{
  "type": "Feature",
  "properties": {
    "addr:full":"Sindshvilevej 6 1 Th Frederiksberg Danmark 2000",
    "addr:housenumber":"6 1",
    "addr:postcode":"2000",
    "addr:street":"Sindshvilevej;Th",
    "iso:country":"DK",
    "sg:address":"Sindshvilevej 6 1 Th",
    "sg:city":"Frederiksberg",
    "sg:orig_category":"Reklamebureauer",
    "sg:phone":"+45 33 13 39 96",
    "sg:postcode":"2000",
    "sg:province":"Danmark",
    "wof:name":"Focus",
    "wof:placetype":"venue"
},
  "geometry": {"coordinates":[12.5299301147,55.6787872314],"type":"Point"}
}