{
  "type": "Feature",
  "properties": {
    "addr:full":"Jernbanegade 30 T\u00f8nder Danmark 6270",
    "addr:housenumber":"30",
    "addr:postcode":"6270",
    "addr:street":"Jernbanegade",
    "iso:country":"DK",
    "sg:address":"Jernbanegade 30",
    "sg:city":"T\u00f8nder",
    "sg:orig_category":"Redningsberedskab",
    "sg:phone":"+45 74 72 25 00",
    "sg:postcode":"6270",
    "sg:province":"Danmark",
    "sg:website":"home19.inet.tele.dk/alarm",
    "wof:name":"Beredskabsforvaltningen i Bredebro, H\u00f8jer, L\u00f8gumkloster og T\u00f8nder Kommuner",
    "wof:placetype":"venue"
},
  "geometry": {"coordinates":[8.8612442017,54.9327430725],"type":"Point"}
}