{
  "type": "Feature",
  "properties": {
    "addr:full":"Nr. Viumvej 66 A, Egeris Videb\u00e6k Danmark 6920",
    "addr:housenumber":"66 a",
    "addr:postcode":"6920",
    "addr:street":"Viumvej;Egeris Videbaek Danmark",
    "iso:country":"DK",
    "sg:address":"Nr. Viumvej 66 A, Egeris",
    "sg:city":"Videb\u00e6k",
    "sg:orig_category":"Genbrugspladser",
    "sg:postcode":"6920",
    "sg:province":"Danmark",
    "wof:name":"Genbrugspladsen i Egeris",
    "wof:placetype":"venue"
},
  "geometry": {"coordinates":[8.7436800003,55.9904136658],"type":"Point"}
}