{
  "type": "Feature",
  "properties": {
    "addr:full":"Kelstrupvej 34, Kelstrup Vig Danmark 4560",
    "addr:housenumber":"34",
    "addr:postcode":"4560",
    "addr:street":"Kelstrupvej;Kelstrup",
    "iso:country":"DK",
    "sg:address":"Kelstrupvej 34, Kelstrup",
    "sg:city":"Vig",
    "sg:orig_category":"Rideskoler",
    "sg:phone":"+45 59 31 62 57",
    "sg:postcode":"4560",
    "sg:province":"Danmark",
    "wof:name":"Ketilstorp Ridecenter",
    "wof:placetype":"venue"
},
  "geometry": {"coordinates":[11.5269098282,55.858795166],"type":"Point"}
}