{
  "type": "Feature",
  "properties": {
    "addr:full":"Storegade 95 Haderslev Danmark 6100",
    "addr:housenumber":"95",
    "addr:postcode":"6100",
    "addr:street":"Storegade",
    "iso:country":"DK",
    "sg:address":"Storegade 95",
    "sg:city":"Haderslev",
    "sg:orig_category":"Kirker",
    "sg:postcode":"6100",
    "sg:province":"Danmark",
    "wof:name":"Gl. Haderslev Kirke/Sct. Severin",
    "wof:placetype":"venue"
},
  "geometry": {"coordinates":[9.4771213531,55.2515602112],"type":"Point"}
}