{
  "type": "Feature",
  "properties": {
    "addr:full":"Vejlands Alle 140 K\u00f8benhavn S Danmark 2300",
    "addr:housenumber":"140",
    "addr:postcode":"2300",
    "addr:street":"Vejlands Alle;S Danmark",
    "iso:country":"DK",
    "sg:address":"Vejlands Alle 140",
    "sg:city":"K\u00f8benhavn S",
    "sg:orig_category":"Benzinstationer",
    "sg:phone":"+45 32 58 23 21",
    "sg:postcode":"2300",
    "sg:province":"Danmark",
    "wof:name":"Q8 Service",
    "wof:placetype":"venue"
},
  "geometry": {"coordinates":[-78.1299133301,36.7267417908],"type":"Point"}
}