{
  "type": "Feature",
  "properties": {
    "addr:full":"T\u00f8ndervej 56 Aabenraa Danmark 6200",
    "addr:housenumber":"56",
    "addr:postcode":"6200",
    "addr:street":"Tondervej",
    "iso:country":"DK",
    "sg:address":"T\u00f8ndervej 56",
    "sg:city":"Aabenraa",
    "sg:orig_category":"Maskinfabrikker",
    "sg:phone":"+45 74 62 49 00",
    "sg:postcode":"6200",
    "sg:province":"Danmark",
    "wof:name":"L\u00f8jt Maskinfabrik",
    "wof:placetype":"venue"
},
  "geometry": {"coordinates":[9.4128141403,55.0347671509],"type":"Point"}
}