{
  "type": "Feature",
  "properties": {
    "iso:country":"DK",
    "sg:address":"Kildegade 25",
    "sg:city":"Odder",
    "sg:orig_category":"Bogtrykkerier",
    "sg:phone":"+45 86 54 03 99",
    "sg:postcode":"8300",
    "sg:province":"Danmark",
    "wof:name":"KJ Bogtryk/Offset",
    "wof:placetype":"venue"
},
  "geometry": {"coordinates":[10.1519708633,55.9773139954],"type":"Point"}
}