{
  "type": "Feature",
  "properties": {
    "addr:full":"Fmd.: Carsten Jensen, Hjortevej 10 Horsens Danmark 8700",
    "addr:housenumber":"10",
    "addr:postcode":"8700",
    "addr:street":"Hjortevej",
    "iso:country":"DK",
    "sg:address":"Fmd.: Carsten Jensen, Hjortevej 10",
    "sg:city":"Horsens",
    "sg:orig_category":"Musik og sang",
    "sg:phone":"+45 75 61 42 92",
    "sg:postcode":"8700",
    "sg:province":"Danmark",
    "wof:name":"Horsens Harmonikaklub",
    "wof:placetype":"venue"
},
  "geometry": {"coordinates":[9.8432445526,55.8621063232],"type":"Point"}
}