{
  "type": "Feature",
  "properties": {
    "iso:country":"DK",
    "sg:address":"Nyg\u00e5rdterrasserne 250 D",
    "sg:city":"Farum",
    "sg:orig_category":"Kunsthandlere",
    "sg:phone":"+45 44 95 01 82",
    "sg:postcode":"3520",
    "sg:province":"Danmark",
    "wof:name":"To's Kunsthandel",
    "wof:placetype":"venue"
},
  "geometry": {"coordinates":[12.3781795502,55.8202018738],"type":"Point"}
}