{
  "type": "Feature",
  "properties": {
    "addr:full":"Bygade Vonge Danmark 7173",
    "addr:postcode":"7173",
    "addr:street":"Bygade",
    "iso:country":"DK",
    "sg:address":"Bygade",
    "sg:city":"Vonge",
    "sg:orig_category":"Kirker",
    "sg:postcode":"7173",
    "sg:province":"Danmark",
    "wof:name":"Vonge Kirke",
    "wof:placetype":"venue"
},
  "geometry": {"coordinates":[9.412604332,55.8623466492],"type":"Point"}
}