{
  "type": "Feature",
  "properties": {
    "addr:full":"Silkeborgvej 46 Them Danmark 8653",
    "addr:housenumber":"46",
    "addr:postcode":"8653",
    "addr:street":"Silkeborgvej",
    "iso:country":"DK",
    "sg:address":"Silkeborgvej 46",
    "sg:city":"Them",
    "sg:classifiers":[
        {
            "category":"Restaurant",
            "type":"Food & Drink"
        }
    ],
    "sg:phone":"+45 86 84 76 30",
    "sg:postcode":"8653",
    "sg:province":"Danmark",
    "wof:name":"Molino",
    "wof:placetype":"venue"
},
  "geometry": {"coordinates":[9.5491304398,56.0953102112],"type":"Point"}
}