{
  "type": "Feature",
  "properties": {
    "addr:full":"Amager Landevej 71 Kastrup Danmark 2770",
    "addr:housenumber":"71",
    "addr:postcode":"2770",
    "addr:street":"Amager Landevej",
    "iso:country":"DK",
    "sg:address":"Amager Landevej 71",
    "sg:city":"Kastrup",
    "sg:orig_category":"Posthuse",
    "sg:phone":"+45 32 87 01 00",
    "sg:postcode":"2770",
    "sg:province":"Danmark",
    "wof:name":"Post Danmark, Kastrup Postkontor",
    "wof:placetype":"venue"
},
  "geometry": {"coordinates":[12.6207008362,55.6337280273],"type":"Point"}
}