{
  "type": "Feature",
  "properties": {
    "addr:full":"Gammel Ribevej 235 Aabenraa Danmark 6200",
    "addr:housenumber":"235",
    "addr:postcode":"6200",
    "addr:street":"Gammel Ribevej",
    "iso:country":"DK",
    "sg:address":"Gammel Ribevej 235",
    "sg:city":"Aabenraa",
    "sg:orig_category":"Autoophug",
    "sg:phone":"+45 74 62 68 00",
    "sg:postcode":"6200",
    "sg:province":"Danmark",
    "wof:name":"S\u00f8nderjydsk Autoophug ApS",
    "wof:placetype":"venue"
},
  "geometry": {"coordinates":[9.3829250336,55.0877609253],"type":"Point"}
}