{
  "type": "Feature",
  "properties": {
    "addr:full":"S\u00f8ndergyden 25 B R\u00f8dding Danmark 6630",
    "addr:housenumber":"25 b",
    "addr:postcode":"6630",
    "addr:street":"Sondergyden",
    "iso:country":"DK",
    "sg:address":"S\u00f8ndergyden 25 B",
    "sg:city":"R\u00f8dding",
    "sg:orig_category":"Autolakering",
    "sg:phone":"+45 74 84 11 19",
    "sg:postcode":"6630",
    "sg:province":"Danmark",
    "wof:name":"R\u00f8dding Autolakering",
    "wof:placetype":"venue"
},
  "geometry": {"coordinates":[77.2480392456,14.1354398727],"type":"Point"}
}