{
  "type": "Feature",
  "properties": {
    "addr:full":"Budolfi Plads 1 Aalborg Danmark 9000",
    "addr:housenumber":"1",
    "addr:postcode":"9000",
    "addr:street":"Budolfi Plads",
    "iso:country":"DK",
    "sg:address":"Budolfi Plads 1",
    "sg:city":"Aalborg",
    "sg:orig_category":"Gaveartikler",
    "sg:phone":"+45 98 13 98 13",
    "sg:postcode":"9000",
    "sg:province":"Danmark",
    "wof:name":"Olivia",
    "wof:placetype":"venue"
},
  "geometry": {"coordinates":[9.9193239212,57.047580719],"type":"Point"}
}