{
  "type": "Feature",
  "properties": {
    "iso:country":"DK",
    "sg:address":"N\u00f8rre Torv 1",
    "sg:city":"Grindsted",
    "sg:classifiers":[
        {
            "category":"Communications",
            "type":"Services"
        }
    ],
    "sg:phone":"+45 75 32 24 44",
    "sg:postcode":"7200",
    "sg:province":"Danmark",
    "sg:tags":[
        "og",
        "tv",
        "radio"
    ],
    "wof:name":"2tal Svend Aage's Radio",
    "wof:placetype":"venue"
},
  "geometry": {"coordinates":[8.9272098541,55.7584609985],"type":"Point"}
}