{
  "type": "Feature",
  "properties": {
    "addr:full":"Herstedvesterstr\u00e6de 66 Albertslund Danmark 2620",
    "addr:housenumber":"66",
    "addr:postcode":"2620",
    "addr:street":"Herstedvesterstraede",
    "iso:country":"DK",
    "sg:address":"Herstedvesterstr\u00e6de 66",
    "sg:city":"Albertslund",
    "sg:orig_category":"Forsamlingshuse",
    "sg:phone":"+45 43 62 45 50",
    "sg:postcode":"2620",
    "sg:province":"Danmark",
    "wof:name":"Herstedvester Forsamlingshus",
    "wof:placetype":"venue"
},
  "geometry": {"coordinates":[12.3384513855,55.6768302917],"type":"Point"}
}