{
  "type": "Feature",
  "properties": {
    "iso:country":"DK",
    "sg:address":"S\u00f8nderlundsvej 3, Bj\u00f8dstrup",
    "sg:city":"Skanderborg",
    "sg:orig_category":"Botilbud",
    "sg:phone":"+45 86 57 93 85",
    "sg:postcode":"8660",
    "sg:province":"Danmark",
    "sg:website":"www.stainagaard.dk",
    "wof:name":"Stainag\u00e5rd",
    "wof:placetype":"venue"
},
  "geometry": {"coordinates":[9.929974556,56.0380249023],"type":"Point"}
}