{
  "type": "Feature",
  "properties": {
    "addr:full":"Ulrikkenborg Plads 12, 1.th Kongens Lyngby Danmark 2800",
    "addr:housenumber":"12 1.th",
    "addr:postcode":"2800",
    "addr:street":"Ulrikkenborg Plads",
    "iso:country":"DK",
    "sg:address":"Ulrikkenborg Plads 12, 1.th",
    "sg:city":"Kongens Lyngby",
    "sg:orig_category":"Psykoterapi",
    "sg:phone":"+45 45 87 15 05",
    "sg:postcode":"2800",
    "sg:province":"Danmark",
    "wof:name":"Psykoterapeutisk V\u00e6rksted",
    "wof:placetype":"venue"
},
  "geometry": {"coordinates":[12.5368299484,55.7949905396],"type":"Point"}
}