{
  "type": "Feature",
  "properties": {
    "addr:full":"Klokkest\u00f8bergade 17 Aalborg Danmark 9000",
    "addr:housenumber":"17",
    "addr:postcode":"9000",
    "addr:street":"Klokkestobergade",
    "iso:country":"DK",
    "sg:address":"Klokkest\u00f8bergade 17",
    "sg:city":"Aalborg",
    "sg:orig_category":"Faglige organisationer og foreninger",
    "sg:phone":"+45 98 12 65 77",
    "sg:postcode":"9000",
    "sg:province":"Danmark",
    "wof:name":"Bupl Nordjylland",
    "wof:placetype":"venue"
},
  "geometry": {"coordinates":[9.9243974686,57.0456581116],"type":"Point"}
}