{
  "type": "Feature",
  "properties": {
    "addr:full":"Svanevej 22 K\u00f8benhavn NV Danmark 2400",
    "addr:housenumber":"22",
    "addr:postcode":"2400",
    "addr:street":"Svanevej",
    "iso:country":"DK",
    "sg:address":"Svanevej 22",
    "sg:city":"K\u00f8benhavn NV",
    "sg:orig_category":"Faglige organisationer og -foreninger",
    "sg:phone":"+45 38 14 02 00",
    "sg:postcode":"2400",
    "sg:province":"Danmark",
    "wof:name":"Chauff\u00f8rernes fagforening",
    "wof:placetype":"venue"
},
  "geometry": {"coordinates":[-117.02272033689999,38.5024604797],"type":"Point"}
}