{
  "type": "Feature",
  "properties": {
    "addr:full":"Jernbanegade 33 S\u00f8nderborg Danmark 6400",
    "addr:housenumber":"33",
    "addr:postcode":"6400",
    "addr:street":"Jernbanegade",
    "iso:country":"DK",
    "sg:address":"Jernbanegade 33",
    "sg:city":"S\u00f8nderborg",
    "sg:orig_category":"Fisk og vildt",
    "sg:phone":"+45 74 42 25 68",
    "sg:postcode":"6400",
    "sg:province":"Danmark",
    "wof:name":"S\u00f8nderborg Fiskehandel og R\u00f8geri + Vildt",
    "wof:placetype":"venue"
},
  "geometry": {"coordinates":[9.7897396088,54.9106369019],"type":"Point"}
}