{
  "type": "Feature",
  "properties": {
    "addr:full":"Fmd.: Egon Stilling, S\u00f8ndre Ringvej 41 Br\u00f8ndby Danmark 2605",
    "addr:housenumber":"41",
    "addr:postcode":"2605",
    "addr:street":"Sondre Ringvej",
    "iso:country":"DK",
    "sg:address":"Fmd.: Egon Stilling, S\u00f8ndre Ringvej 41",
    "sg:city":"Br\u00f8ndby",
    "sg:orig_category":"Faglige organisationer og foreninger",
    "sg:phone":"+45 43 96 15 82",
    "sg:postcode":"2605",
    "sg:province":"Danmark",
    "wof:name":"Glostrup og Omegns VVS-Installat\u00f8rforening",
    "wof:placetype":"venue"
},
  "geometry": {"coordinates":[12.4375448227,55.662109375],"type":"Point"}
}