{
  "type": "Feature",
  "properties": {
    "addr:full":"Tinggade 5 Ringsted Danmark 4100",
    "addr:housenumber":"5",
    "addr:postcode":"4100",
    "addr:street":"Tinggade",
    "iso:country":"DK",
    "sg:address":"Tinggade 5",
    "sg:city":"Ringsted",
    "sg:orig_category":"Vikarbureauer",
    "sg:phone":"+45 20 20 47 37",
    "sg:postcode":"4100",
    "sg:province":"Danmark",
    "wof:name":"Care One",
    "wof:placetype":"venue"
},
  "geometry": {"coordinates":[11.7898569107,55.4433517456],"type":"Point"}
}