{
  "type": "Feature",
  "properties": {
    "addr:full":"Fmd.: Anita Wilhardt, Vinkelvej 26 Holsted Danmark 6670",
    "addr:housenumber":"26",
    "addr:postcode":"6670",
    "addr:street":"Vinkelvej",
    "iso:country":"DK",
    "sg:address":"Fmd.: Anita Wilhardt, Vinkelvej 26",
    "sg:city":"Holsted",
    "sg:orig_category":"Kulturelle foreninger",
    "sg:phone":"+45 75 39 32 95",
    "sg:postcode":"6670",
    "sg:province":"Danmark",
    "wof:name":"Spilopperne",
    "wof:placetype":"venue"
},
  "geometry": {"coordinates":[8.9169273376,55.5111999512],"type":"Point"}
}