{
  "type": "Feature",
  "properties": {
    "addr:full":"R\u00e5dhusstr\u00e6de 11 K\u00f8benhavn Danmark 1466",
    "addr:housenumber":"11;1466",
    "addr:street":"Raadhusstraede",
    "iso:country":"DK",
    "sg:address":"R\u00e5dhusstr\u00e6de 11",
    "sg:city":"K\u00f8benhavn",
    "sg:orig_category":"Antikviteter",
    "sg:phone":"+45 33 93 15 75",
    "sg:postcode":"1466",
    "sg:province":"Danmark",
    "wof:name":"Antik Sofie-Amalie",
    "wof:placetype":"venue"
},
  "geometry": {"coordinates":[76.3070983887,14.277130127],"type":"Point"}
}