{
  "type": "Feature",
  "properties": {
    "addr:full":"Algade 35-37 Middelfart Danmark 5500",
    "addr:postcode":"35-37;5500",
    "addr:street":"Algade",
    "iso:country":"DK",
    "sg:address":"Algade 35-37",
    "sg:city":"Middelfart",
    "sg:classifiers":[
        {
            "category":"Banks & Credit Unions",
            "subcategory":"Bank",
            "type":"Services"
        }
    ],
    "sg:phone":"+45 63 41 40 40",
    "sg:postcode":"5500",
    "sg:province":"Danmark",
    "sg:tags":[
        "banker"
    ],
    "sg:website":"www.danskebank.dk",
    "wof:name":"Danske Bank",
    "wof:placetype":"venue"
},
  "geometry": {"coordinates":[9.730532,55.505901],"type":"Point"}
}