{
  "type": "Feature",
  "properties": {
    "addr:full":"Tigervej 20 K\u00f8ge Danmark 4600",
    "addr:housenumber":"20",
    "addr:postcode":"4600",
    "addr:street":"Tigervej",
    "iso:country":"DK",
    "sg:address":"Tigervej 20",
    "sg:city":"K\u00f8ge",
    "sg:orig_category":"Integrerede institutioner",
    "sg:phone":"+45 56 65 72 14",
    "sg:postcode":"4600",
    "sg:province":"Danmark",
    "wof:name":"Tigerbo",
    "wof:placetype":"venue"
},
  "geometry": {"coordinates":[12.1702957153,55.4747047424],"type":"Point"}
}