{
  "type": "Feature",
  "properties": {
    "iso:country":"DK",
    "sg:address":"v/ Lone Deleuran, N\u00f8dholmsvej 58, Regerup",
    "sg:city":"Glums\u00f8",
    "sg:orig_category":"Kulturelle foreninger",
    "sg:phone":"+45 57 64 65 60",
    "sg:postcode":"4171",
    "sg:province":"Danmark",
    "wof:name":"Sus\u00e5 Filmklub",
    "wof:placetype":"venue"
},
  "geometry": {"coordinates":[11.6862697601,55.3553962708],"type":"Point"}
}