{
  "type": "Feature",
  "properties": {
    "addr:full":"Falkoner Alle 104 Frederiksberg Danmark 2000",
    "addr:housenumber":"104",
    "addr:postcode":"2000",
    "addr:street":"Falkoner Alle",
    "iso:country":"DK",
    "sg:address":"Falkoner Alle 104",
    "sg:city":"Frederiksberg",
    "sg:orig_category":"Hudpleje",
    "sg:phone":"+45 35 35 49 45",
    "sg:postcode":"2000",
    "sg:province":"Danmark",
    "wof:name":"Jo Marie Hudplejeklinik",
    "wof:placetype":"venue"
},
  "geometry": {"coordinates":[12.5402345657,55.6865997314],"type":"Point"}
}