{
  "type": "Feature",
  "properties": {
    "iso:country":"DK",
    "sg:address":"Hedelandsvej 14",
    "sg:city":"Herning",
    "sg:orig_category":"Autoreparation og -service",
    "sg:phone":"+45 97 21 68 22",
    "sg:postcode":"7400",
    "sg:province":"Danmark",
    "wof:name":"Midt-Vest Service-Center",
    "wof:placetype":"venue"
},
  "geometry": {"coordinates":[8.9359836578,56.1274032593],"type":"Point"}
}