{
  "type": "Feature",
  "properties": {
    "addr:full":"Langmarksvej 85 Horsens Danmark 8700",
    "addr:housenumber":"85",
    "addr:postcode":"8700",
    "addr:street":"Langmarksvej",
    "iso:country":"DK",
    "sg:address":"Langmarksvej 85",
    "sg:city":"Horsens",
    "sg:orig_category":"Dagcentre",
    "sg:phone":"+45 75 61 58 00",
    "sg:postcode":"8700",
    "sg:province":"Danmark",
    "wof:name":"Lindeh\u00f8j Dagcenter",
    "wof:placetype":"venue"
},
  "geometry": {"coordinates":[9.8542098999,55.8710594177],"type":"Point"}
}