{
  "type": "Feature",
  "properties": {
    "addr:full":"Trynbakkevej 6 Bindslev Danmark 9881",
    "addr:housenumber":"6",
    "addr:postcode":"9881",
    "addr:street":"Trynbakkevej",
    "iso:country":"DK",
    "sg:address":"Trynbakkevej 6",
    "sg:city":"Bindslev",
    "sg:orig_category":"Maskinstationer",
    "sg:phone":"+45 98 93 72 60",
    "sg:postcode":"9881",
    "sg:province":"Danmark",
    "wof:name":"Bindslev Entrepren\u00f8r- og Maskinstation",
    "wof:placetype":"venue"
},
  "geometry": {"coordinates":[10.2335729599,57.5393257141],"type":"Point"}
}