{
  "type": "Feature",
  "properties": {
    "addr:full":"\u00d8sterparken 20 Taastrup Danmark 2630",
    "addr:housenumber":"20",
    "addr:postcode":"2630",
    "addr:street":"Osterparken",
    "iso:country":"DK",
    "sg:address":"\u00d8sterparken 20",
    "sg:city":"Taastrup",
    "sg:classifiers":[
        {
            "category":"Restaurant",
            "type":"Food & Drink"
        }
    ],
    "sg:phone":"+45 43 99 40 76",
    "sg:postcode":"2630",
    "sg:province":"Danmark",
    "wof:name":"Ming Garden, Restaurant",
    "wof:placetype":"venue"
},
  "geometry": {"coordinates":[12.3024244308,55.6497612],"type":"Point"}
}