{
  "type": "Feature",
  "properties": {
    "addr:full":"Nyholmsvej 15 Randers Danmark 8900",
    "addr:housenumber":"15",
    "addr:postcode":"8900",
    "addr:street":"Nyholmsvej",
    "iso:country":"DK",
    "sg:address":"Nyholmsvej 15",
    "sg:city":"Randers",
    "sg:orig_category":"Hydraulik",
    "sg:phone":"+45 87 11 00 66",
    "sg:postcode":"8900",
    "sg:province":"Danmark",
    "wof:name":"Sawo Hydraulic A/S",
    "wof:placetype":"venue"
},
  "geometry": {"coordinates":[10.0840568542,56.4712600708],"type":"Point"}
}