{
  "type": "Feature",
  "properties": {
    "addr:full":"Kai Lindbergs Gade 22 Hanstholm Danmark 7730",
    "addr:housenumber":"22",
    "addr:postcode":"7730",
    "addr:street":"Kai Lindbergs Gade",
    "iso:country":"DK",
    "sg:address":"Kai Lindbergs Gade 22",
    "sg:city":"Hanstholm",
    "sg:orig_category":"Fiskeeksport",
    "sg:phone":"+45 97 96 24 44",
    "sg:postcode":"7730",
    "sg:province":"Danmark",
    "wof:name":"Scampex",
    "wof:placetype":"venue"
},
  "geometry": {"coordinates":[8.6077508926,57.1220245361],"type":"Point"}
}