{
  "type": "Feature",
  "properties": {
    "addr:full":"\u00c5lborgvej 18 Hals Danmark 9370",
    "addr:housenumber":"18",
    "addr:postcode":"9370",
    "addr:street":"Aalborgvej",
    "iso:country":"DK",
    "sg:address":"\u00c5lborgvej 18",
    "sg:city":"Hals",
    "sg:orig_category":"Kiosker",
    "sg:phone":"+45 98 25 16 99",
    "sg:postcode":"9370",
    "sg:province":"Danmark",
    "wof:name":"Byens Kiosk",
    "wof:placetype":"venue"
},
  "geometry": {"coordinates":[10.3070840836,56.9987297058],"type":"Point"}
}