{
  "type": "Feature",
  "properties": {
    "addr:full":"Kvievej 13 Ansager Danmark 6823",
    "addr:housenumber":"13",
    "addr:postcode":"6823",
    "addr:street":"Kvievej",
    "iso:country":"DK",
    "sg:address":"Kvievej 13",
    "sg:city":"Ansager",
    "sg:orig_category":"Undervognsbehandling",
    "sg:phone":"+45 75 29 67 99",
    "sg:postcode":"6823",
    "sg:province":"Danmark",
    "wof:name":"Ansager Antirust og Bilplejecenter",
    "wof:placetype":"venue"
},
  "geometry": {"coordinates":[8.7679262161,55.7082557678],"type":"Point"}
}