{
  "type": "Feature",
  "properties": {
    "addr:full":"Industrivej 6 Padborg Danmark 6330",
    "addr:housenumber":"6",
    "addr:postcode":"6330",
    "addr:street":"Industrivej",
    "iso:country":"DK",
    "sg:address":"Industrivej 6",
    "sg:city":"Padborg",
    "sg:orig_category":"Spedition",
    "sg:phone":"+45 74 67 33 16",
    "sg:postcode":"6330",
    "sg:province":"Danmark",
    "wof:name":"Danexim A/S",
    "wof:placetype":"venue"
},
  "geometry": {"coordinates":[9.3550615311,54.8244132996],"type":"Point"}
}