{
  "type": "Feature",
  "properties": {
    "addr:full":"Brunbankevej 1 Viborg Danmark 8800",
    "addr:housenumber":"1",
    "addr:postcode":"8800",
    "addr:street":"Brunbankevej",
    "iso:country":"DK",
    "sg:address":"Brunbankevej 1",
    "sg:city":"Viborg",
    "sg:orig_category":"Autoreparation og -service",
    "sg:phone":"+45 86 64 23 61",
    "sg:postcode":"8800",
    "sg:province":"Danmark",
    "wof:name":"Vesterg\u00e5rd Autov\u00e6rksted",
    "wof:placetype":"venue"
},
  "geometry": {"coordinates":[9.3967857361,56.4979934692],"type":"Point"}
}