{
  "type": "Feature",
  "properties": {
    "addr:full":"\u00d8stbirkvej 17, Seden Odense N\u00d8 Danmark 5240",
    "addr:housenumber":"17",
    "addr:postcode":"5240",
    "addr:street":"Ostbirkvej;Seden",
    "iso:country":"DK",
    "sg:address":"\u00d8stbirkvej 17, Seden",
    "sg:city":"Odense N\u00d8",
    "sg:orig_category":"Carporte",
    "sg:phone":"+45 66 10 99 50",
    "sg:postcode":"5240",
    "sg:province":"Danmark",
    "wof:name":"Fyns Garage Fabrik ApS",
    "wof:placetype":"venue"
},
  "geometry": {"coordinates":[10.444185257,55.4261131287],"type":"Point"}
}