{
  "type": "Feature",
  "properties": {
    "iso:country":"DK",
    "sg:address":"Kongevejen 111",
    "sg:city":"Virum",
    "sg:orig_category":"Autoreparation og -service",
    "sg:phone":"+45 45 85 79 40",
    "sg:postcode":"2830",
    "sg:province":"Danmark",
    "wof:name":"Klokholm's Autov\u00e6rksted",
    "wof:placetype":"venue"
},
  "geometry": {"coordinates":[12.4806995392,55.7987785339],"type":"Point"}
}