{
  "type": "Feature",
  "properties": {
    "iso:country":"DK",
    "sg:address":"Sverigesgade 16",
    "sg:city":"Odense C",
    "sg:orig_category":"Spedition",
    "sg:phone":"+45 66 11 88 38",
    "sg:postcode":"5000",
    "sg:province":"Danmark",
    "wof:name":"Hansen & Co. A/S, N. P.",
    "wof:placetype":"venue"
},
  "geometry": {"coordinates":[10.3818702698,55.4125099182],"type":"Point"}
}