{
  "type": "Feature",
  "properties": {
    "addr:full":"S\u00f8ndergade 87, Agerup N\u00e6stved Danmark 4700",
    "addr:housenumber":"87",
    "addr:postcode":"4700",
    "addr:street":"Sondergade",
    "iso:country":"DK",
    "sg:address":"S\u00f8ndergade 87, Agerup",
    "sg:city":"N\u00e6stved",
    "sg:orig_category":"Alternativ behandling",
    "sg:phone":"+45 55 45 59 15",
    "sg:postcode":"4700",
    "sg:province":"Danmark",
    "sg:website":"www.helsecentret.dk",
    "wof:name":"Helsecentret",
    "wof:placetype":"venue"
},
  "geometry": {"coordinates":[11.7542486191,55.2315444946],"type":"Point"}
}