{
  "type": "Feature",
  "properties": {
    "addr:full":"v/ Jess Andersen, Ndr. Ringgade 1 Slagelse Danmark 4200",
    "addr:housenumber":"1",
    "addr:postcode":"4200",
    "addr:street":"Ndr. Ringgade",
    "iso:country":"DK",
    "sg:address":"v/ Jess Andersen, Ndr. Ringgade 1",
    "sg:city":"Slagelse",
    "sg:orig_category":"Autoforhandlere",
    "sg:phone":"+45 58 52 66 88",
    "sg:postcode":"4200",
    "sg:province":"Danmark",
    "wof:name":"Olsen A/S, P.M.",
    "wof:placetype":"venue"
},
  "geometry": {"coordinates":[11.3569850922,55.4050865173],"type":"Point"}
}