{
  "type": "Feature",
  "properties": {
    "iso:country":"DK",
    "sg:address":"Lang\u00f8revej 12",
    "sg:city":"Sams\u00f8",
    "sg:orig_category":"\u00c3\u02dcvrige skoler",
    "sg:phone":"+45 86 59 64 54",
    "sg:postcode":"8305",
    "sg:province":"Danmark",
    "wof:name":"Sams\u00f8 Naturskole",
    "wof:placetype":"venue"
},
  "geometry": {"coordinates":[-107.9639587402,38.1021232605],"type":"Point"}
}