{
  "type": "Feature",
  "properties": {
    "addr:full":"Sandbjergvej Horsens Danmark 8700",
    "addr:postcode":"8700",
    "addr:street":"Sandbjergvej",
    "iso:country":"DK",
    "sg:address":"Sandbjergvej",
    "sg:city":"Horsens",
    "sg:orig_category":"Kirker",
    "sg:postcode":"8700",
    "sg:province":"Danmark",
    "wof:name":"S\u00f8vind Kirke",
    "wof:placetype":"venue"
},
  "geometry": {"coordinates":[10.0045385361,55.893497467],"type":"Point"}
}