{
  "type": "Feature",
  "properties": {
    "iso:country":"DK",
    "sg:address":"Fmd.: Susanne Neiiendam, Askh\u00f8j 17",
    "sg:city":"N\u00e6rum",
    "sg:orig_category":"Grundejerforeninger",
    "sg:phone":"+45 45 80 48 81",
    "sg:postcode":"2850",
    "sg:province":"Danmark",
    "wof:name":"Askh\u00f8j Grundejerforening",
    "wof:placetype":"venue"
},
  "geometry": {"coordinates":[-89.99810791020001,38.1321372986],"type":"Point"}
}