{
  "type": "Feature",
  "properties": {
    "addr:full":"Kirkevejen 61, Ommel Marstal Danmark 5960",
    "addr:housenumber":"61",
    "addr:postcode":"5960",
    "addr:street":"Kirkevejen",
    "iso:country":"DK",
    "sg:address":"Kirkevejen 61, Ommel",
    "sg:city":"Marstal",
    "sg:orig_category":"Maskinstationer",
    "sg:phone":"+45 62 53 17 10",
    "sg:postcode":"5960",
    "sg:province":"Danmark",
    "wof:name":"Ommel Maskinstation",
    "wof:placetype":"venue"
},
  "geometry": {"coordinates":[10.5212097168,54.8543815613],"type":"Point"}
}