{
  "type": "Feature",
  "properties": {
    "addr:full":"Hovedgaden 24 Borup Danmark 4140",
    "addr:housenumber":"24",
    "addr:postcode":"4140",
    "addr:street":"Hovedgaden",
    "iso:country":"DK",
    "sg:address":"Hovedgaden 24",
    "sg:city":"Borup",
    "sg:classifiers":[
        {
            "category":"Banks & Credit Unions",
            "subcategory":"Bank",
            "type":"Services"
        }
    ],
    "sg:phone":"+45 57 56 19 80",
    "sg:postcode":"4140",
    "sg:province":"Danmark",
    "sg:tags":[
        "banker"
    ],
    "sg:website":"www.danskebank.dk",
    "wof:name":"Danske Bank",
    "wof:placetype":"venue"
},
  "geometry": {"coordinates":[11.973007,55.496044],"type":"Point"}
}