{
  "type": "Feature",
  "properties": {
    "addr:full":"Strandvejen 147 Hellerup Danmark 2900",
    "addr:housenumber":"147",
    "addr:postcode":"2900",
    "addr:street":"Strandvejen",
    "iso:country":"DK",
    "sg:address":"Strandvejen 147",
    "sg:city":"Hellerup",
    "sg:orig_category":"Blomsterhandlere",
    "sg:phone":"+45 39 62 20 15",
    "sg:postcode":"2900",
    "sg:province":"Danmark",
    "wof:name":"Brita Blomster",
    "wof:placetype":"venue"
},
  "geometry": {"coordinates":[12.576256752,55.7300987244],"type":"Point"}
}