{
  "type": "Feature",
  "properties": {
    "addr:full":"Kildeh\u00f8jen 180 Risskov Danmark 8240",
    "addr:housenumber":"180",
    "addr:postcode":"8240",
    "iso:country":"DK",
    "sg:address":"Kildeh\u00f8jen 180",
    "sg:city":"Risskov",
    "sg:orig_category":"Vinduespolering",
    "sg:phone":"+45 86 21 00 54",
    "sg:postcode":"8240",
    "sg:province":"Danmark",
    "wof:name":"Eklund's Vinduespolering",
    "wof:placetype":"venue"
},
  "geometry": {"coordinates":[10.2179965973,56.198261261],"type":"Point"}
}