{
  "type": "Feature",
  "properties": {
    "addr:full":"N\u00f8rregade 32 Dronninglund Danmark 9330",
    "addr:housenumber":"32",
    "addr:postcode":"9330",
    "addr:street":"Norregade",
    "iso:country":"DK",
    "sg:address":"N\u00f8rregade 32",
    "sg:city":"Dronninglund",
    "sg:orig_category":"Musikere",
    "sg:phone":"+45 98 84 33 84",
    "sg:postcode":"9330",
    "sg:province":"Danmark",
    "wof:name":"Henrik M\u00f8lbjerg",
    "wof:placetype":"venue"
},
  "geometry": {"coordinates":[10.2910041809,57.1624107361],"type":"Point"}
}