{
  "type": "Feature",
  "properties": {
    "iso:country":"DK",
    "sg:address":"Oddersk\u00e6rvej 4, Borris",
    "sg:city":"Skjern",
    "sg:orig_category":"Hundefoder",
    "sg:phone":"+45 97 36 64 92",
    "sg:postcode":"6900",
    "sg:province":"Danmark",
    "wof:name":"Borris Hundefoder",
    "wof:placetype":"venue"
},
  "geometry": {"coordinates":[8.492972374,55.9485740662],"type":"Point"}
}