{
  "type": "Feature",
  "properties": {
    "addr:full":"Jens Juuls Vej 10 Viby Danmark 8260",
    "addr:housenumber":"10",
    "addr:postcode":"8260",
    "addr:street":"Jens Juuls Vej",
    "iso:country":"DK",
    "sg:address":"Jens Juuls Vej 10",
    "sg:city":"Viby",
    "sg:orig_category":"Galvanisering",
    "sg:phone":"+45 86 28 69 28",
    "sg:postcode":"8260",
    "sg:province":"Danmark",
    "sg:website":"www.tychsen.dk",
    "wof:name":"Tychsen Galvanisering",
    "wof:placetype":"venue"
},
  "geometry": {"coordinates":[10.1368341446,56.1146278381],"type":"Point"}
}