{
  "type": "Feature",
  "properties": {
    "iso:country":"DK",
    "sg:address":"Frisholtvej 108",
    "sg:city":"Bjerringbro",
    "sg:orig_category":"Hundekenneler",
    "sg:phone":"+45 86 68 46 31",
    "sg:postcode":"8850",
    "sg:province":"Danmark",
    "wof:name":"J\u00e6gerhorn, Kennel",
    "wof:placetype":"venue"
},
  "geometry": {"coordinates":[9.6228313446,56.32056427],"type":"Point"}
}