{
  "type": "Feature",
  "properties": {
    "iso:country":"DK",
    "sg:address":"Fmd.: Mette Foldager, Bavneh\u00f8jvej 7",
    "sg:city":"Esbjerg",
    "sg:orig_category":"Hobbybetonede foreninger",
    "sg:phone":"+45 75 12 86 32",
    "sg:postcode":"6700",
    "sg:province":"Danmark",
    "sg:website":"www.perseren.dk",
    "wof:name":"Katteklubben for alle racer, Perseren",
    "wof:placetype":"venue"
},
  "geometry": {"coordinates":[8.456905365,55.465221405],"type":"Point"}
}