{
  "type": "Feature",
  "properties": {
    "iso:country":"DK",
    "sg:address":"Centervej 21",
    "sg:city":"H\u00f8ng",
    "sg:orig_category":"Materialister",
    "sg:phone":"+45 58 85 33 11",
    "sg:postcode":"4270",
    "sg:province":"Danmark",
    "wof:name":"Matas",
    "wof:placetype":"venue"
},
  "geometry": {"coordinates":[11.2899398804,55.5040016174],"type":"Point"}
}