{
  "type": "Feature",
  "properties": {
    "addr:full":"Tr\u00e6holtvej 66, Bjergby Hj\u00f8rring Danmark 9800",
    "addr:housenumber":"66",
    "addr:postcode":"9800",
    "addr:street":"Traeholtvej;Bjergby Hjorring Danmark",
    "iso:country":"DK",
    "sg:address":"Tr\u00e6holtvej 66, Bjergby",
    "sg:city":"Hj\u00f8rring",
    "sg:orig_category":"Engros handel",
    "sg:phone":"+45 98 97 14 22",
    "sg:postcode":"9800",
    "sg:province":"Danmark",
    "wof:name":"Skovbo Maskiner",
    "wof:placetype":"venue"
},
  "geometry": {"coordinates":[9.9885387421,57.4594764709],"type":"Point"}
}