{
  "type": "Feature",
  "properties": {
    "addr:full":"Finlandsgade 10 Haslev Danmark 4690",
    "addr:housenumber":"10",
    "addr:postcode":"4690",
    "addr:street":"Finlandsgade",
    "iso:country":"DK",
    "sg:address":"Finlandsgade 10",
    "sg:city":"Haslev",
    "sg:orig_category":"Autoforhandlere",
    "sg:phone":"+45 56 31 10 01",
    "sg:postcode":"4690",
    "sg:province":"Danmark",
    "sg:website":"opel-haslev.dk",
    "wof:name":"Bilhuset Opel i Haslev",
    "wof:placetype":"venue"
},
  "geometry": {"coordinates":[11.9385547638,55.3264389038],"type":"Point"}
}