{
  "type": "Feature",
  "properties": {
    "addr:full":"Hovedgaden 48, Ingstrup L\u00f8kken Danmark 9480",
    "addr:housenumber":"48",
    "addr:postcode":"9480",
    "addr:street":"Hovedgaden",
    "iso:country":"DK",
    "sg:address":"Hovedgaden 48, Ingstrup",
    "sg:city":"L\u00f8kken",
    "sg:orig_category":"Mejerier",
    "sg:phone":"+45 98 88 30 13",
    "sg:postcode":"9480",
    "sg:province":"Danmark",
    "sg:website":"www.ingstrup-ost.dk",
    "wof:name":"Ingstrup Andelsmejeri",
    "wof:placetype":"venue"
},
  "geometry": {"coordinates":[9.715880394,57.3703308105],"type":"Point"}
}