{
  "type": "Feature",
  "properties": {
    "addr:full":"v/ J\u00f8rgen Hansen, Horne Skole, Skolevej 2, Horne Faaborg Danmark 5600",
    "addr:housenumber":"2",
    "addr:postcode":"5600",
    "addr:street":"Skolevej;Horne",
    "iso:country":"DK",
    "sg:address":"v/ J\u00f8rgen Hansen, Horne Skole, Skolevej 2, Horne",
    "sg:city":"Faaborg",
    "sg:orig_category":"Lokalarkiver",
    "sg:postcode":"5600",
    "sg:province":"Danmark",
    "wof:name":"Horne Lands Folkemindesamlings Arkiv",
    "wof:placetype":"venue"
},
  "geometry": {"coordinates":[10.2400531769,55.0950622559],"type":"Point"}
}