{
  "type": "Feature",
  "properties": {
    "addr:full":"\u00d8sterbakken 7 Thisted Danmark 7700",
    "addr:housenumber":"7",
    "addr:postcode":"7700",
    "addr:street":"Osterbakken",
    "iso:country":"DK",
    "sg:address":"\u00d8sterbakken 7",
    "sg:city":"Thisted",
    "sg:classifiers":[
        {
            "category":"Restaurant",
            "type":"Food & Drink"
        }
    ],
    "sg:phone":"+45 97 92 51 85",
    "sg:postcode":"7700",
    "sg:province":"Danmark",
    "wof:name":"Nielsen By Night",
    "wof:placetype":"venue"
},
  "geometry": {"coordinates":[8.6969480515,56.9552688599],"type":"Point"}
}