{
  "type": "Feature",
  "properties": {
    "iso:country":"DK",
    "sg:address":"N\u00f8rregade 18",
    "sg:city":"Fars\u00f8",
    "sg:orig_category":"Servicestationer",
    "sg:phone":"+45 98 63 16 00",
    "sg:postcode":"9640",
    "sg:province":"Danmark",
    "wof:name":"Statoil Service Center",
    "wof:placetype":"venue"
},
  "geometry": {"coordinates":[-109.44831848139999,42.1062355042],"type":"Point"}
}