{
  "type": "Feature",
  "properties": {
    "addr:full":"Strandvejen 337 Klampenborg Danmark 2930",
    "addr:housenumber":"337",
    "addr:postcode":"2930",
    "addr:street":"Strandvejen",
    "iso:country":"DK",
    "sg:address":"Strandvejen 337",
    "sg:city":"Klampenborg",
    "sg:orig_category":"Arkitekter",
    "sg:phone":"+45 39 63 25 51",
    "sg:postcode":"2930",
    "sg:province":"Danmark",
    "wof:name":"Andersens Tegnestue A/S, Flemming",
    "wof:placetype":"venue"
},
  "geometry": {"coordinates":[12.5967140198,55.7638969421],"type":"Point"}
}