{
  "type": "Feature",
  "properties": {
    "addr:full":"Fmd.: Doris J\u00f8rgensen, Eskj\u00e6r M\u00f8llevej 4, Stouby Roslev Danmark 7870",
    "addr:housenumber":"4",
    "addr:postcode":"7870",
    "addr:street":"Mollevej",
    "iso:country":"DK",
    "sg:address":"Fmd.: Doris J\u00f8rgensen, Eskj\u00e6r M\u00f8llevej 4, Stouby",
    "sg:city":"Roslev",
    "sg:orig_category":"Husflidsforeninger",
    "sg:phone":"+45 97 57 65 40",
    "sg:postcode":"7870",
    "sg:province":"Danmark",
    "wof:name":"\u00d8stsalling Familielag",
    "wof:placetype":"venue"
},
  "geometry": {"coordinates":[8.8715353012,56.7570304871],"type":"Point"}
}