{
  "type": "Feature",
  "properties": {
    "addr:full":"Istedgade 109 K\u00f8benhavn Danmark 1650",
    "addr:housenumber":"109;1650",
    "addr:street":"Istedgade",
    "iso:country":"DK",
    "sg:address":"Istedgade 109",
    "sg:city":"K\u00f8benhavn",
    "sg:orig_category":"Fotohandlere",
    "sg:phone":"+45 33 21 39 39",
    "sg:postcode":"1650",
    "sg:province":"Danmark",
    "wof:name":"Vesterbro Foto",
    "wof:placetype":"venue"
},
  "geometry": {"coordinates":[12.5565004349,55.6693000793],"type":"Point"}
}