{
  "type": "Feature",
  "properties": {
    "addr:full":"Kredsleder: Kim Pedersen, Bj\u00f8rnsknudevej 1, 1. Juelsminde Danmark 7130",
    "addr:housenumber":"1 1",
    "addr:postcode":"7130",
    "addr:street":"Bjornsknudevej",
    "iso:country":"DK",
    "sg:address":"Kredsleder: Kim Pedersen, Bj\u00f8rnsknudevej 1, 1.",
    "sg:city":"Juelsminde",
    "sg:orig_category":"Spejderkorps",
    "sg:phone":"+45 76 83 00 80",
    "sg:postcode":"7130",
    "sg:province":"Danmark",
    "wof:name":"FDF - Juelsminde",
    "wof:placetype":"venue"
},
  "geometry": {"coordinates":[10.0143985748,55.7135848999],"type":"Point"}
}