{
  "type": "Feature",
  "properties": {
    "addr:full":"\u00d8sterl\u00f8kke 7, Bov Padborg Danmark 6330",
    "addr:housenumber":"7",
    "addr:postcode":"6330",
    "addr:street":"Osterlokke;Bov",
    "iso:country":"DK",
    "sg:address":"\u00d8sterl\u00f8kke 7, Bov",
    "sg:city":"Padborg",
    "sg:orig_category":"Murermestre",
    "sg:phone":"+45 74 67 01 07",
    "sg:postcode":"6330",
    "sg:province":"Danmark",
    "wof:name":"E.B.H. - Byg",
    "wof:placetype":"venue"
},
  "geometry": {"coordinates":[9.3618345261,54.8222312927],"type":"Point"}
}