{
  "type": "Feature",
  "properties": {
    "addr:full":"Aved\u00f8reholmen 68 Hvidovre Danmark 2650",
    "addr:housenumber":"68",
    "addr:postcode":"2650",
    "addr:street":"Avedoreholmen",
    "iso:country":"DK",
    "sg:address":"Aved\u00f8reholmen 68",
    "sg:city":"Hvidovre",
    "sg:orig_category":"Varme- og ventilation, Art.for",
    "sg:phone":"+45 36 78 42 18",
    "sg:postcode":"2650",
    "sg:province":"Danmark",
    "wof:name":"Reci ApS",
    "wof:placetype":"venue"
},
  "geometry": {"coordinates":[12.467382431,55.611579895],"type":"Point"}
}