{
  "type": "Feature",
  "properties": {
    "addr:full":"\u00d8stre Strandvej 63 Skagen Danmark 9990",
    "addr:housenumber":"63",
    "addr:postcode":"9990",
    "addr:street":"Ostre Strandvej",
    "iso:country":"DK",
    "sg:address":"\u00d8stre Strandvej 63",
    "sg:city":"Skagen",
    "sg:orig_category":"HOTELS: OG MOTELLER",
    "sg:phone":"+45 98 45 01 55",
    "sg:postcode":"9990",
    "sg:province":"Danmark",
    "sg:website":"www.skaw.dk/finnshotelpension",
    "wof:name":"Finns Hotel Pension",
    "wof:placetype":"venue"
},
  "geometry": {"coordinates":[10.6010694504,57.723991394],"type":"Point"}
}