{
  "type": "Feature",
  "properties": {
    "addr:full":"Clausholmvej 21 Randers Danmark 8900",
    "addr:housenumber":"21",
    "addr:postcode":"8900",
    "addr:street":"Clausholmvej",
    "iso:country":"DK",
    "sg:address":"Clausholmvej 21",
    "sg:city":"Randers",
    "sg:orig_category":"Fodterapeuter",
    "sg:phone":"+45 86 40 53 54",
    "sg:postcode":"8900",
    "sg:province":"Danmark",
    "wof:name":"Jensen, Charlotte",
    "wof:placetype":"venue"
},
  "geometry": {"coordinates":[10.0680112839,56.4425010681],"type":"Point"}
}