{
  "type": "Feature",
  "properties": {
    "iso:country":"DK",
    "sg:address":"N\u00f8rrebro 6",
    "sg:city":"Rudk\u00f8bing",
    "sg:orig_category":"Bagere",
    "sg:phone":"+45 62 51 15 12",
    "sg:postcode":"5900",
    "sg:province":"Danmark",
    "wof:name":"N\u00f8rrebros Bageri",
    "wof:placetype":"venue"
},
  "geometry": {"coordinates":[-114.076744,46.443249],"type":"Point"}
}