{
  "type": "Feature",
  "properties": {
    "addr:full":"Eneb\u00e6rhaven 118 Kokkedal Danmark 2980",
    "addr:housenumber":"118",
    "addr:postcode":"2980",
    "addr:street":"Enebaerhaven",
    "iso:country":"DK",
    "sg:address":"Eneb\u00e6rhaven 118",
    "sg:city":"Kokkedal",
    "sg:orig_category":"Malermestre",
    "sg:phone":"+45 49 14 73 74",
    "sg:postcode":"2980",
    "sg:province":"Danmark",
    "wof:name":"Clasen, Niels",
    "wof:placetype":"venue"
},
  "geometry": {"coordinates":[12.4859857559,55.9176521301],"type":"Point"}
}