{
  "type": "Feature",
  "properties": {
    "addr:full":"Jernbanegade 24 Frederikssund Danmark 3600",
    "addr:housenumber":"24",
    "addr:postcode":"3600",
    "addr:street":"Jernbanegade",
    "iso:country":"DK",
    "sg:address":"Jernbanegade 24",
    "sg:city":"Frederikssund",
    "sg:orig_category":"Biblioteker",
    "sg:phone":"+45 47 31 25 25",
    "sg:postcode":"3600",
    "sg:province":"Danmark",
    "sg:website":"www.frederikssund-bibliotek.dk",
    "wof:name":"Frederikssund Bibliotek",
    "wof:placetype":"venue"
},
  "geometry": {"coordinates":[12.0640115738,55.8377685547],"type":"Point"}
}