{
  "type": "Feature",
  "properties": {
    "addr:full":"Fmd.: Ellen Velling, Hannerupvej 5, H\u00f8rby Hobro Danmark 9500",
    "addr:housenumber":"5",
    "addr:postcode":"9500",
    "addr:street":"Velling Hannerupvej",
    "iso:country":"DK",
    "sg:address":"Fmd.: Ellen Velling, Hannerupvej 5, H\u00f8rby",
    "sg:city":"Hobro",
    "sg:orig_category":"Kulturelle foreninger",
    "sg:phone":"+45 98 51 03 64",
    "sg:postcode":"9500",
    "sg:province":"Danmark",
    "wof:name":"St\u00f8tteforeningen for Hobro Medborgerhus",
    "wof:placetype":"venue"
},
  "geometry": {"coordinates":[9.7946596146,56.6382789612],"type":"Point"}
}