{
  "type": "Feature",
  "properties": {
    "addr:full":"L\u00e6s\u00f8vej 2B Viborg Danmark 8800",
    "addr:housenumber":"2b",
    "addr:postcode":"8800",
    "addr:street":"Laesovej",
    "iso:country":"DK",
    "sg:address":"L\u00e6s\u00f8vej 2B",
    "sg:city":"Viborg",
    "sg:orig_category":"Revisorer",
    "sg:phone":"+45 86 60 32 22",
    "sg:postcode":"8800",
    "sg:province":"Danmark",
    "wof:name":"rebo Revision & Bogf\u00f8ring",
    "wof:placetype":"venue"
},
  "geometry": {"coordinates":[9.4071502686,56.452671051],"type":"Point"}
}