{
  "type": "Feature",
  "properties": {
    "addr:full":"Fmd.: Bodil Koch, R\u00e5gevej 14 Glostrup Danmark 2600",
    "addr:housenumber":"14",
    "addr:postcode":"2600",
    "addr:street":"Raagevej",
    "iso:country":"DK",
    "sg:address":"Fmd.: Bodil Koch, R\u00e5gevej 14",
    "sg:city":"Glostrup",
    "sg:orig_category":"Kulturelle foreninger",
    "sg:phone":"+45 43 96 62 51",
    "sg:postcode":"2600",
    "sg:province":"Danmark",
    "wof:name":"Kunstnerforeningen K 21",
    "wof:placetype":"venue"
},
  "geometry": {"coordinates":[12.3957901001,55.6654663086],"type":"Point"}
}