{
  "type": "Feature",
  "properties": {
    "iso:country":"DK",
    "sg:address":"Kongensgade 22",
    "sg:city":"Christiansfeld",
    "sg:orig_category":"Grillbarer",
    "sg:phone":"+45 74 56 01 16",
    "sg:postcode":"6070",
    "sg:province":"Danmark",
    "wof:name":"Felder - Grillen",
    "wof:placetype":"venue"
},
  "geometry": {"coordinates":[9.4834709167,55.3568000793],"type":"Point"}
}