{
  "type": "Feature",
  "properties": {
    "addr:full":"Vesterbro 9 B Odense C Danmark 5000",
    "addr:housenumber":"9 b",
    "addr:postcode":"5000",
    "addr:street":"Vesterbro",
    "iso:country":"DK",
    "sg:address":"Vesterbro 9 B",
    "sg:city":"Odense C",
    "sg:orig_category":"Menighedshuse",
    "sg:postcode":"5000",
    "sg:province":"Danmark",
    "wof:name":"Luthersk Missionsforenings Missionshus",
    "wof:placetype":"venue"
},
  "geometry": {"coordinates":[10.3789167404,55.3938179016],"type":"Point"}
}