{
  "type": "Feature",
  "properties": {
    "addr:full":"Jens Thorleif Nielsen, Lyngager 16 Greve Danmark 2670",
    "addr:housenumber":"16",
    "addr:postcode":"2670",
    "addr:street":"Jens Thorleif Nielsen Lyngager",
    "iso:country":"DK",
    "sg:address":"Jens Thorleif Nielsen, Lyngager 16",
    "sg:city":"Greve",
    "sg:orig_category":"Spejderkorps",
    "sg:phone":"+45 43 90 03 99",
    "sg:postcode":"2670",
    "sg:province":"Danmark",
    "wof:name":"Danske Spejderkorps, Det",
    "wof:placetype":"venue"
},
  "geometry": {"coordinates":[12.2941808701,55.5844078064],"type":"Point"}
}