{
  "type": "Feature",
  "properties": {
    "addr:full":"Danmarksvej 32 B Skanderborg Danmark 8660",
    "addr:housenumber":"32 b",
    "addr:postcode":"8660",
    "addr:street":"Danmarksvej",
    "iso:country":"DK",
    "sg:address":"Danmarksvej 32 B",
    "sg:city":"Skanderborg",
    "sg:orig_category":"Maskinfabrikker",
    "sg:phone":"+45 86 57 01 12",
    "sg:postcode":"8660",
    "sg:province":"Danmark",
    "sg:website":"www.Lmf-engineering.dk",
    "wof:name":"LMF Engineering & Trading ApS",
    "wof:placetype":"venue"
},
  "geometry": {"coordinates":[9.9556760788,56.0518684387],"type":"Point"}
}