{
  "type": "Feature",
  "properties": {
    "addr:full":"Hyttefadsvej 9 Strandby Danmark 9970",
    "addr:housenumber":"9",
    "addr:postcode":"9970",
    "addr:street":"Hyttefadsvej",
    "iso:country":"DK",
    "sg:address":"Hyttefadsvej 9",
    "sg:city":"Strandby",
    "sg:orig_category":"Fiskeeksport",
    "sg:phone":"+45 98 48 10 42",
    "sg:postcode":"9970",
    "sg:province":"Danmark",
    "wof:name":"J\u00f8rgensen og S\u00f8n A/S, Arne",
    "wof:placetype":"venue"
},
  "geometry": {"coordinates":[10.5024595261,57.4952659607],"type":"Point"}
}