{
  "type": "Feature",
  "properties": {
    "addr:full":"v/ Knud Peder Rasmussen, B\u00e6kkevej 8, Heden Ringe Danmark 5750",
    "addr:housenumber":"8",
    "addr:postcode":"5750",
    "addr:street":"Peder;Baekkevej",
    "iso:country":"DK",
    "sg:address":"v/ Knud Peder Rasmussen, B\u00e6kkevej 8, Heden",
    "sg:city":"Ringe",
    "sg:orig_category":"\u00c3\u2020ldreorganisationer og klubber",
    "sg:phone":"+45 62 66 13 70",
    "sg:postcode":"5750",
    "sg:province":"Danmark",
    "wof:name":"Heden Hyggeklub",
    "wof:placetype":"venue"
},
  "geometry": {"coordinates":[10.4781074524,55.2356643677],"type":"Point"}
}