{
  "type": "Feature",
  "properties": {
    "iso:country":"DK",
    "sg:address":"Roseng\u00e5rds Alle 106",
    "sg:city":"Vejle",
    "sg:orig_category":"Integrerede institutioner",
    "sg:phone":"+45 75 82 16 88",
    "sg:postcode":"7100",
    "sg:province":"Danmark",
    "wof:name":"Alfeh\u00f8j",
    "wof:placetype":"venue"
},
  "geometry": {"coordinates":[9.5503721237,55.6825141907],"type":"Point"}
}