{
  "type": "Feature",
  "properties": {
    "iso:country":"DK",
    "sg:address":"M\u00f8llevej 10, \u00c5vang",
    "sg:city":"Lejre",
    "sg:orig_category":"Blomsterhandlere",
    "sg:phone":"+45 46 48 07 96",
    "sg:postcode":"4320",
    "sg:province":"Danmark",
    "wof:name":"Morgenfruen",
    "wof:placetype":"venue"
},
  "geometry": {"coordinates":[11.9678316116,55.6005630493],"type":"Point"}
}