{
  "type": "Feature",
  "properties": {
    "iso:country":"DK",
    "sg:address":"Grenevej 13",
    "sg:city":"Billund",
    "sg:orig_category":"Hundepensioner",
    "sg:phone":"+45 75 33 10 80",
    "sg:postcode":"7190",
    "sg:province":"Danmark",
    "wof:name":"Bluebell Hundepension",
    "wof:placetype":"venue"
},
  "geometry": {"coordinates":[9.100812912,55.7104606628],"type":"Point"}
}