{
  "type": "Feature",
  "properties": {
    "addr:full":"Vadehavsvej 1 Billum Danmark 6852",
    "addr:housenumber":"1",
    "addr:postcode":"6852",
    "addr:street":"Vadehavsvej",
    "iso:country":"DK",
    "sg:address":"Vadehavsvej 1",
    "sg:city":"Billum",
    "sg:orig_category":"Stoffer",
    "sg:phone":"+45 75 25 88 90",
    "sg:postcode":"6852",
    "sg:province":"Danmark",
    "wof:name":"Butikken",
    "wof:placetype":"venue"
},
  "geometry": {"coordinates":[8.3258047104,55.6135864258],"type":"Point"}
}