{
  "type": "Feature",
  "properties": {
    "addr:full":"Fredericiagade 19 Holstebro Danmark 7500",
    "addr:housenumber":"19",
    "addr:postcode":"7500",
    "addr:street":"Fredericiagade",
    "iso:country":"DK",
    "sg:address":"Fredericiagade 19",
    "sg:city":"Holstebro",
    "sg:orig_category":"Engros handel",
    "sg:phone":"+45 97 47 29 24",
    "sg:postcode":"7500",
    "sg:province":"Danmark",
    "wof:name":"BJ Trading",
    "wof:placetype":"venue"
},
  "geometry": {"coordinates":[8.6165103912,56.3633308411],"type":"Point"}
}