{
  "type": "Feature",
  "properties": {
    "addr:full":"\u00d8stergade 26 K\u00f8benhavn Danmark 1100",
    "addr:housenumber":"26;1100",
    "addr:street":"Ostergade",
    "iso:country":"DK",
    "sg:address":"\u00d8stergade 26",
    "sg:city":"K\u00f8benhavn",
    "sg:classifiers":[
        {
            "category":"Organizations",
            "subcategory":"Community Association",
            "type":"Services"
        }
    ],
    "sg:phone":"+45 33 32 78 78",
    "sg:postcode":"1100",
    "sg:province":"Danmark",
    "sg:tags":[
        "relation",
        "public"
    ],
    "sg:website":"www.bm.com",
    "wof:name":"Burson-Marsteller A/S",
    "wof:placetype":"venue"
},
  "geometry": {"coordinates":[76.3070983887,14.277130127],"type":"Point"}
}