{
  "type": "Feature",
  "properties": {
    "addr:full":"\u00d8rstedsvej 41 Aalborg Danmark 9000",
    "addr:housenumber":"41",
    "addr:postcode":"9000",
    "addr:street":"Orstedsvej",
    "iso:country":"DK",
    "sg:address":"\u00d8rstedsvej 41",
    "sg:city":"Aalborg",
    "sg:orig_category":"Rideudstyr",
    "sg:phone":"+45 98 12 10 75",
    "sg:postcode":"9000",
    "sg:province":"Danmark",
    "wof:name":"Bach Rideudstyr",
    "wof:placetype":"venue"
},
  "geometry": {"coordinates":[9.9046697617,57.0362129211],"type":"Point"}
}