{
  "type": "Feature",
  "properties": {
    "addr:full":"Hedevej 41 Risskov Danmark 8240",
    "addr:housenumber":"41",
    "addr:postcode":"8240",
    "addr:street":"Hedevej",
    "iso:country":"DK",
    "sg:address":"Hedevej 41",
    "sg:city":"Risskov",
    "sg:classifiers":[
        {
            "category":"Personal",
            "subcategory":"Massage",
            "type":"Services"
        }
    ],
    "sg:phone":"+45 86 17 45 30",
    "sg:postcode":"8240",
    "sg:province":"Danmark",
    "wof:name":"Herl\u00f8v, S\u00f8ren",
    "wof:placetype":"venue"
},
  "geometry": {"coordinates":[10.2415924072,56.2040634155],"type":"Point"}
}