{
  "type": "Feature",
  "properties": {
    "addr:full":"Egesholm 38 Horsens Danmark 8700",
    "addr:housenumber":"38",
    "addr:postcode":"8700",
    "addr:street":"Egesholm",
    "iso:country":"DK",
    "sg:address":"Egesholm 38",
    "sg:city":"Horsens",
    "sg:orig_category":"Akupunktur",
    "sg:phone":"+45 75 65 63 67",
    "sg:postcode":"8700",
    "sg:province":"Danmark",
    "wof:name":"Egebjeg Klinikken",
    "wof:placetype":"venue"
},
  "geometry": {"coordinates":[9.8325080872,55.904296875],"type":"Point"}
}