{
  "type": "Feature",
  "properties": {
    "addr:full":"Jyllandsvej 14 Hobro Danmark 9500",
    "addr:housenumber":"14",
    "addr:postcode":"9500",
    "addr:street":"Jyllandsvej",
    "iso:country":"DK",
    "sg:address":"Jyllandsvej 14",
    "sg:city":"Hobro",
    "sg:orig_category":"Metalvarefabrikker",
    "sg:phone":"+45 96 57 43 00",
    "sg:postcode":"9500",
    "sg:province":"Danmark",
    "sg:website":"www.sintex.dk",
    "wof:name":"Sintex a/s",
    "wof:placetype":"venue"
},
  "geometry": {"coordinates":[9.8175420761,56.6293067932],"type":"Point"}
}