{
  "type": "Feature",
  "properties": {
    "addr:full":"Annebergvej 2 Aalborg Danmark 9000",
    "addr:housenumber":"2",
    "addr:postcode":"9000",
    "addr:street":"Annebergvej",
    "iso:country":"DK",
    "sg:address":"Annebergvej 2",
    "sg:city":"Aalborg",
    "sg:orig_category":"Kirkesogne",
    "sg:phone":"+45 98 12 13 87",
    "sg:postcode":"9000",
    "sg:province":"Danmark",
    "wof:name":"Vor Frelsers Sogns Kirkekontor",
    "wof:placetype":"venue"
},
  "geometry": {"coordinates":[9.9060678482,57.049785614],"type":"Point"}
}