{
  "type": "Feature",
  "properties": {
    "iso:country":"DK",
    "sg:address":"Fmd.: Bjarne Jensen, M\u00f8rkh\u00f8jvej 8, Ganl\u00f8se M\u00f8rke",
    "sg:city":"Stenl\u00f8se",
    "sg:orig_category":"Soldaterforeninger",
    "sg:phone":"+45 48 18 48 50",
    "sg:postcode":"3660",
    "sg:province":"Danmark",
    "wof:name":"Gardehusarforeningen Fr.borg Amt",
    "wof:placetype":"venue"
},
  "geometry": {"coordinates":[-109.33489990229999,40.3696899414],"type":"Point"}
}