{
  "type": "Feature",
  "properties": {
    "iso:country":"DK",
    "sg:address":"Marienbergvej 98",
    "sg:city":"Vordingborg",
    "sg:orig_category":"Bolchefabrikker",
    "sg:phone":"+45 55 34 02 03",
    "sg:postcode":"4760",
    "sg:province":"Danmark",
    "wof:name":"Prins J\u00f8rgens Bolcher",
    "wof:placetype":"venue"
},
  "geometry": {"coordinates":[11.8953065872,55.0010108948],"type":"Point"}
}