{
  "type": "Feature",
  "properties": {
    "addr:full":"Vor Frue Hovedgade 71, Vor Frue Roskilde Danmark 4000",
    "addr:housenumber":"71",
    "addr:postcode":"4000",
    "addr:street":"Vor Frue Hovedgade;Frue",
    "iso:country":"DK",
    "sg:address":"Vor Frue Hovedgade 71, Vor Frue",
    "sg:city":"Roskilde",
    "sg:orig_category":"Fritidscentre",
    "sg:phone":"+45 46 37 07 74",
    "sg:postcode":"4000",
    "sg:province":"Danmark",
    "wof:name":"Vor Frue Fritidscenter",
    "wof:placetype":"venue"
},
  "geometry": {"coordinates":[12.0909376144,55.6404838562],"type":"Point"}
}