{
  "type": "Feature",
  "properties": {
    "addr:full":"Jegstrupvej 10 Viborg Danmark 8800",
    "addr:housenumber":"10",
    "addr:postcode":"8800",
    "addr:street":"Jegstrupvej",
    "iso:country":"DK",
    "sg:address":"Jegstrupvej 10",
    "sg:city":"Viborg",
    "sg:orig_category":"Maskinservice",
    "sg:phone":"+45 86 61 36 00",
    "sg:postcode":"8800",
    "sg:province":"Danmark",
    "wof:name":"Viborg Havemaskiner",
    "wof:placetype":"venue"
},
  "geometry": {"coordinates":[9.3947963715,56.4543800354],"type":"Point"}
}