{
  "type": "Feature",
  "properties": {
    "addr:full":"Askevej 33 Horsens Danmark 8700",
    "addr:housenumber":"33",
    "addr:postcode":"8700",
    "addr:street":"Askevej",
    "iso:country":"DK",
    "sg:address":"Askevej 33",
    "sg:city":"Horsens",
    "sg:orig_category":"Sprogundervisning",
    "sg:phone":"+45 75 61 21 13",
    "sg:postcode":"8700",
    "sg:province":"Danmark",
    "wof:name":"Logos-IT",
    "wof:placetype":"venue"
},
  "geometry": {"coordinates":[9.8782052994,55.8741798401],"type":"Point"}
}