{
  "type": "Feature",
  "properties": {
    "addr:full":"Bastrup Skolevej 26 Vamdrup Danmark 6580",
    "addr:housenumber":"26",
    "addr:postcode":"6580",
    "addr:street":"Bastrup Skolevej",
    "iso:country":"DK",
    "sg:address":"Bastrup Skolevej 26",
    "sg:city":"Vamdrup",
    "sg:orig_category":"Fabrikker",
    "sg:phone":"+45 75 58 13 98",
    "sg:postcode":"6580",
    "sg:province":"Danmark",
    "wof:name":"Friis-Knutsen A/S",
    "wof:placetype":"venue"
},
  "geometry": {"coordinates":[9.2582912445,55.4108963013],"type":"Point"}
}