{
  "type": "Feature",
  "properties": {
    "addr:full":"Revninge Bygade 55, Revninge Kerteminde Danmark 5300",
    "addr:housenumber":"55",
    "addr:postcode":"5300",
    "addr:street":"Revninge Bygade",
    "iso:country":"DK",
    "sg:address":"Revninge Bygade 55, Revninge",
    "sg:city":"Kerteminde",
    "sg:orig_category":"Private skoler",
    "sg:phone":"+45 65 32 12 62",
    "sg:postcode":"5300",
    "sg:province":"Danmark",
    "sg:website":"www.kertemindeegnens-friskole.dk",
    "wof:name":"Kertemindeegnens Friskole",
    "wof:placetype":"venue"
},
  "geometry": {"coordinates":[10.6600999832,55.4506492615],"type":"Point"}
}