{
  "type": "Feature",
  "properties": {
    "iso:country":"DK",
    "sg:address":"Galgebakken Torv 7, 14 A",
    "sg:city":"Albertslund",
    "sg:classifiers":[
        {
            "category":"Banks & Credit Unions",
            "subcategory":"Investment Brokerage",
            "type":"Services"
        }
    ],
    "sg:phone":"+45 43 62 23 36",
    "sg:postcode":"2620",
    "sg:province":"Danmark",
    "sg:tags":[
        "healing"
    ],
    "wof:name":"Turi Rye Thomsen",
    "wof:placetype":"venue"
},
  "geometry": {"coordinates":[12.3485555649,55.6789588928],"type":"Point"}
}