{
  "type": "Feature",
  "properties": {
    "addr:full":"Vangede Bygade 92 Gentofte Danmark 2820",
    "addr:housenumber":"92",
    "addr:postcode":"2820",
    "addr:street":"Vangede Bygade",
    "iso:country":"DK",
    "sg:address":"Vangede Bygade 92",
    "sg:city":"Gentofte",
    "sg:orig_category":"Materialister",
    "sg:phone":"+45 39 65 33 22",
    "sg:postcode":"2820",
    "sg:province":"Danmark",
    "wof:name":"Matas",
    "wof:placetype":"venue"
},
  "geometry": {"coordinates":[12.5179738998,55.7498016357],"type":"Point"}
}