{
  "type": "Feature",
  "properties": {
    "addr:full":"v/ Steen Larsen, N\u00f8rregade 8, Hou Hals Danmark 9370",
    "addr:housenumber":"8",
    "addr:postcode":"9370",
    "addr:street":"Norregade",
    "iso:country":"DK",
    "sg:address":"v/ Steen Larsen, N\u00f8rregade 8, Hou",
    "sg:city":"Hals",
    "sg:orig_category":"Oplysningsforbund",
    "sg:phone":"+45 96 54 66 66",
    "sg:postcode":"9370",
    "sg:province":"Danmark",
    "wof:name":"AOF",
    "wof:placetype":"venue"
},
  "geometry": {"coordinates":[10.3669347763,57.0597991943],"type":"Point"}
}