{
  "type": "Feature",
  "properties": {
    "addr:full":"Dysseg\u00e5rdsvej 30 A Gadstrup Danmark 4621",
    "addr:housenumber":"30 a",
    "addr:postcode":"4621",
    "addr:street":"Dyssegaardsvej",
    "iso:country":"DK",
    "sg:address":"Dysseg\u00e5rdsvej 30 A",
    "sg:city":"Gadstrup",
    "sg:orig_category":"Kirker",
    "sg:postcode":"4621",
    "sg:province":"Danmark",
    "wof:name":"Gadstrup Kirke",
    "wof:placetype":"venue"
},
  "geometry": {"coordinates":[12.099656105,55.5686378479],"type":"Point"}
}