{
  "type": "Feature",
  "properties": {
    "addr:full":"Fmd.: Helle Godiksen, Gl. \u00c5lborgvej 76, Bjerget Fr\u00f8strup Danmark 7741",
    "addr:housenumber":"76",
    "addr:postcode":"7741",
    "addr:street":"Godiksen Gl. Aalborgvej",
    "iso:country":"DK",
    "sg:address":"Fmd.: Helle Godiksen, Gl. \u00c5lborgvej 76, Bjerget",
    "sg:city":"Fr\u00f8strup",
    "sg:orig_category":"Borger- og beboerforeninger",
    "sg:phone":"+45 97 98 25 36",
    "sg:postcode":"7741",
    "sg:province":"Danmark",
    "wof:name":"Lild Sogns Beboerforening",
    "wof:placetype":"venue"
},
  "geometry": {"coordinates":[8.9638395309,57.1506538391],"type":"Point"}
}