{
  "type": "Feature",
  "properties": {
    "iso:country":"DK",
    "sg:address":"Kirstineh\u00f8j 38 B",
    "sg:city":"Kastrup",
    "sg:classifiers":[
        {
            "category":"Professional",
            "subcategory":"Art Services",
            "type":"Services"
        }
    ],
    "sg:phone":"+45 32 52 12 22",
    "sg:postcode":"2770",
    "sg:province":"Danmark",
    "sg:tags":[
        "blomster"
    ],
    "sg:website":"www.ratje.dk",
    "wof:name":"Ratje ApS Kurve, Michael",
    "wof:placetype":"venue"
},
  "geometry": {"coordinates":[12.622138,55.61755],"type":"Point"}
}