{
  "type": "Feature",
  "properties": {
    "addr:full":"Ellehammersvej 2 Kolding Danmark 6000",
    "addr:housenumber":"2",
    "addr:postcode":"6000",
    "addr:street":"Ellehammersvej",
    "iso:country":"DK",
    "sg:address":"Ellehammersvej 2",
    "sg:city":"Kolding",
    "sg:orig_category":"Trossamfund uden for folkekirken",
    "sg:phone":"+45 75 53 78 40",
    "sg:postcode":"6000",
    "sg:province":"Danmark",
    "wof:name":"Jehovas Vidners Rigssal",
    "wof:placetype":"venue"
},
  "geometry": {"coordinates":[9.4591770172,55.5084571838],"type":"Point"}
}