{
  "type": "Feature",
  "properties": {
    "addr:full":"Fredrikstadvej 16 Aalborg SV Danmark 9200",
    "addr:housenumber":"16",
    "addr:postcode":"9200",
    "addr:street":"Fredrikstadvej",
    "iso:country":"DK",
    "sg:address":"Fredrikstadvej 16",
    "sg:city":"Aalborg SV",
    "sg:orig_category":"Autoforhandlere",
    "sg:phone":"+45 98 18 17 00",
    "sg:postcode":"9200",
    "sg:province":"Danmark",
    "wof:name":"SMC-Biler Gr\u00f8nland A/S",
    "wof:placetype":"venue"
},
  "geometry": {"coordinates":[9.8959293365,57.0200462341],"type":"Point"}
}