{
  "type": "Feature",
  "properties": {
    "iso:country":"DK",
    "sg:address":"Kr\u00e6mmergade 10",
    "sg:city":"Varde",
    "sg:orig_category":"Konfekture",
    "sg:phone":"+45 75 22 50 45",
    "sg:postcode":"6800",
    "sg:province":"Danmark",
    "wof:name":"BON-BON",
    "wof:placetype":"venue"
},
  "geometry": {"coordinates":[8.4823579788,55.6205635071],"type":"Point"}
}