{
  "type": "Feature",
  "properties": {
    "addr:full":"Larixvej 4 Sabro Danmark 8471",
    "addr:housenumber":"4",
    "addr:postcode":"8471",
    "addr:street":"Larixvej",
    "iso:country":"DK",
    "sg:address":"Larixvej 4",
    "sg:city":"Sabro",
    "sg:orig_category":"Autoreparation og -service",
    "sg:phone":"+45 86 94 85 70",
    "sg:postcode":"8471",
    "sg:province":"Danmark",
    "wof:name":"Brunsgaard's Autov\u00e6rksted",
    "wof:placetype":"venue"
},
  "geometry": {"coordinates":[10.0380353928,56.2081298828],"type":"Point"}
}