{
  "type": "Feature",
  "properties": {
    "addr:full":"v/ John Desvil, Norupvej 42, Jydby Otterup Danmark 5450",
    "addr:housenumber":"42",
    "addr:postcode":"5450",
    "addr:street":"Norupvej",
    "iso:country":"DK",
    "sg:address":"v/ John Desvil, Norupvej 42, Jydby",
    "sg:city":"Otterup",
    "sg:orig_category":"Museer",
    "sg:phone":"+45 64 82 45 50",
    "sg:postcode":"5450",
    "sg:province":"Danmark",
    "wof:name":"Otterup Museum",
    "wof:placetype":"venue"
},
  "geometry": {"coordinates":[10.4545049667,55.5641746521],"type":"Point"}
}