{
  "type": "Feature",
  "properties": {
    "iso:country":"DK",
    "sg:address":"Valh\u00f8js Alle 160 ",
    "sg:city":"R\u00f8dovre",
    "sg:classifiers":[
        {
            "category":"Professional",
            "subcategory":"Computer Services",
            "type":"Services"
        }
    ],
    "sg:phone":"+45 72 21 21 21",
    "sg:postcode":"2610",
    "sg:province":"Danmark",
    "sg:tags":[
        "information",
        "technology"
    ],
    "wof:name":"MINOLTA DANMARK A/S",
    "wof:placetype":"venue"
},
  "geometry": {"coordinates":[10.6992139816,61.1027755737],"type":"Point"}
}