{
  "type": "Feature",
  "properties": {
    "iso:country":"DK",
    "sg:address":"Fmd.:Henry Rasmussen, Rytterv\u00e6nget 30",
    "sg:city":"R\u00f8dekro",
    "sg:orig_category":"Boligselskaber",
    "sg:phone":"+45 74 66 23 70",
    "sg:postcode":"6230",
    "sg:province":"Danmark",
    "wof:name":"R\u00f8dekro Andelsboligforening",
    "wof:placetype":"venue"
},
  "geometry": {"coordinates":[-85.3986663818,39.9317703247],"type":"Point"}
}