{
  "type": "Feature",
  "properties": {
    "iso:country":"DK",
    "sg:address":"Egelundsvej 5",
    "sg:city":"Albertslund",
    "sg:orig_category":"Benzinstationer",
    "sg:phone":"+45 43 64 53 19",
    "sg:postcode":"2620",
    "sg:province":"Danmark",
    "wof:name":"Hydro - Texaco Trafik Center",
    "wof:placetype":"venue"
},
  "geometry": {"coordinates":[12.33273,55.661232],"type":"Point"}
}