{
  "type": "Feature",
  "properties": {
    "addr:full":"Kass.: Jytte Pedersen, Uhre Byvej 7 Brande Danmark 7330",
    "addr:housenumber":"7",
    "addr:postcode":"7330",
    "addr:street":"Uhre Byvej",
    "iso:country":"DK",
    "sg:address":"Kass.: Jytte Pedersen, Uhre Byvej 7",
    "sg:city":"Brande",
    "sg:orig_category":"Kulturelle foreninger",
    "sg:phone":"+45 97 18 71 17",
    "sg:postcode":"7330",
    "sg:province":"Danmark",
    "wof:name":"Arbejdernes Radio og TV klub",
    "wof:placetype":"venue"
},
  "geometry": {"coordinates":[9.1280345917,55.942779541],"type":"Point"}
}