{
  "type": "Feature",
  "properties": {
    "addr:full":"v/ K\u00f8bmandshj\u00f8rnet, Sennelsvej 112 Thisted Danmark 7700",
    "addr:housenumber":"112",
    "addr:postcode":"7700",
    "addr:street":"Sennelsvej",
    "iso:country":"DK",
    "sg:address":"v/ K\u00f8bmandshj\u00f8rnet, Sennelsvej 112",
    "sg:city":"Thisted",
    "sg:orig_category":"Apoteker og -udsalg",
    "sg:phone":"+45 97 98 50 17",
    "sg:postcode":"7700",
    "sg:province":"Danmark",
    "wof:name":"Receptudleveringsstedet i Sennels",
    "wof:placetype":"venue"
},
  "geometry": {"coordinates":[8.6919784546,56.9556121826],"type":"Point"}
}