{
  "type": "Feature",
  "properties": {
    "addr:full":"Lervadvej 16 Ullerslev Danmark 5540",
    "addr:housenumber":"16",
    "addr:postcode":"5540",
    "addr:street":"Lervadvej",
    "iso:country":"DK",
    "sg:address":"Lervadvej 16",
    "sg:city":"Ullerslev",
    "sg:classifiers":[
        {
            "category":"Building & Trades",
            "subcategory":"Electrical",
            "type":"Services"
        }
    ],
    "sg:phone":"+45 22 10 66 16",
    "sg:postcode":"5540",
    "sg:province":"Danmark",
    "sg:tags":[
        "distributor"
    ],
    "wof:name":"Nielsen, Brian",
    "wof:placetype":"venue"
},
  "geometry": {"coordinates":[10.6427335739,55.3623275757],"type":"Point"}
}