{
  "type": "Feature",
  "properties": {
    "addr:full":"Skovh\u00f8j 17 Kolding Danmark 6000",
    "addr:housenumber":"17",
    "addr:postcode":"6000",
    "addr:street":"Skovhoj",
    "iso:country":"DK",
    "sg:address":"Skovh\u00f8j 17",
    "sg:city":"Kolding",
    "sg:orig_category":"Revisorer",
    "sg:phone":"+45 75 50 24 60",
    "sg:postcode":"6000",
    "sg:province":"Danmark",
    "wof:name":"SC Revision",
    "wof:placetype":"venue"
},
  "geometry": {"coordinates":[9.4716186523,55.4820098877],"type":"Point"}
}