{
  "type": "Feature",
  "properties": {
    "iso:country":"DK",
    "sg:address":"Sankt Jacobs Vej 4",
    "sg:city":"Ballerup",
    "sg:orig_category":"Begravelsesforretninger",
    "sg:phone":"+45 44 97 48 48",
    "sg:postcode":"2750",
    "sg:province":"Danmark",
    "wof:name":"Ballerup og Omegns Ligkistemagasin",
    "wof:placetype":"venue"
},
  "geometry": {"coordinates":[12.361349,55.731457],"type":"Point"}
}