{
  "type": "Feature",
  "properties": {
    "addr:full":"\u00d8stervang 29, Spark\u00e6r Viborg Danmark 8800",
    "addr:housenumber":"29",
    "addr:postcode":"8800",
    "addr:street":"Ostervang",
    "iso:country":"DK",
    "sg:address":"\u00d8stervang 29, Spark\u00e6r",
    "sg:city":"Viborg",
    "sg:orig_category":"Forsikringer",
    "sg:phone":"+45 86 64 52 36",
    "sg:postcode":"8800",
    "sg:province":"Danmark",
    "wof:name":"Topdanmark",
    "wof:placetype":"venue"
},
  "geometry": {"coordinates":[9.4071502686,56.452671051],"type":"Point"}
}