{
  "type": "Feature",
  "properties": {
    "addr:full":"Fmd.: Jens Broholt, Allan C. Hansen ApS, Vendersgade 22 Nyk\u00f8bing Danmark 4800",
    "addr:housenumber":"22",
    "addr:postcode":"4800",
    "addr:street":"Vendersgade",
    "iso:country":"DK",
    "sg:address":"Fmd.: Jens Broholt, Allan C. Hansen ApS, Vendersgade 22",
    "sg:city":"Nyk\u00f8bing",
    "sg:orig_category":"Faglige organisationer og foreninger",
    "sg:phone":"+45 54 85 37 00",
    "sg:postcode":"4800",
    "sg:province":"Danmark",
    "wof:name":"Dansk Arbejdsgiverforening i Nyk\u00f8bing F.",
    "wof:placetype":"venue"
},
  "geometry": {"coordinates":[11.8678541183,54.769241333],"type":"Point"}
}