{
  "type": "Feature",
  "properties": {
    "iso:country":"DK",
    "sg:address":"Fmd.: Holger Jespersen, Kong Hans Alle 103",
    "sg:city":"S\u00f8borg",
    "sg:orig_category":"Kirkelige foreninger",
    "sg:phone":"+45 39 69 27 78",
    "sg:postcode":"2860",
    "sg:province":"Danmark",
    "wof:name":"Kirkelig Forening for den Indre Mission i Danmark, Buddinge Afd.",
    "wof:placetype":"venue"
},
  "geometry": {"coordinates":[-101.39041900629999,35.6679611206],"type":"Point"}
}