{
  "type": "Feature",
  "properties": {
    "addr:full":"Hadsundvej 13 Terndrup Danmark 9575",
    "addr:housenumber":"13",
    "addr:postcode":"9575",
    "addr:street":"Hadsundvej;Danmark",
    "iso:country":"DK",
    "sg:address":"Hadsundvej 13",
    "sg:city":"Terndrup",
    "sg:orig_category":"Metervarer",
    "sg:phone":"+45 98 33 55 74",
    "sg:postcode":"9575",
    "sg:province":"Danmark",
    "wof:name":"BF-Dress",
    "wof:placetype":"venue"
},
  "geometry": {"coordinates":[10.0576429367,56.8126754761],"type":"Point"}
}