{
  "type": "Feature",
  "properties": {
    "iso:country":"DK",
    "sg:address":"Fmd.: Ingolf Nielsen, Skolegade 15 A",
    "sg:city":"Karise",
    "sg:orig_category":"Spejderkorps",
    "sg:phone":"+45 56 76 90 08",
    "sg:postcode":"4653",
    "sg:province":"Danmark",
    "wof:name":"DDS Lynggruppen",
    "wof:placetype":"venue"
},
  "geometry": {"coordinates":[12.1990203857,55.3030395508],"type":"Point"}
}