{
  "type": "Feature",
  "properties": {
    "addr:full":"Fmd.: Agnete Hastrup Pedersen, \u00d8ster Alle 26, Hammerum Herning Danmark 7400",
    "addr:housenumber":"26",
    "addr:postcode":"7400",
    "addr:street":"Oster Alle;Hammerum",
    "iso:country":"DK",
    "sg:address":"Fmd.: Agnete Hastrup Pedersen, \u00d8ster Alle 26, Hammerum",
    "sg:city":"Herning",
    "sg:orig_category":"Valg- og frimenigheder",
    "sg:phone":"+45 97 11 93 01",
    "sg:postcode":"7400",
    "sg:province":"Danmark",
    "wof:name":"Gjellerup Valgmenigheds Bestyrelse",
    "wof:placetype":"venue"
},
  "geometry": {"coordinates":[8.9768896103,56.1374168396],"type":"Point"}
}