{
  "type": "Feature",
  "properties": {
    "addr:full":"S\u00f8ndergade 9 Aabenraa Danmark 6200",
    "addr:housenumber":"9",
    "addr:postcode":"6200",
    "addr:street":"Sondergade",
    "iso:country":"DK",
    "sg:address":"S\u00f8ndergade 9",
    "sg:city":"Aabenraa",
    "sg:orig_category":"Slagter og viktualie",
    "sg:phone":"+45 74 62 33 22",
    "sg:postcode":"6200",
    "sg:province":"Danmark",
    "wof:name":"Johansen, Slagter",
    "wof:placetype":"venue"
},
  "geometry": {"coordinates":[9.4194068909,55.0416412354],"type":"Point"}
}