{
  "type": "Feature",
  "properties": {
    "iso:country":"DK",
    "sg:address":"Skolebakken 20",
    "sg:city":"Gentofte",
    "sg:orig_category":"Kommunale folkeskoler",
    "sg:phone":"+45 39 65 20 17",
    "sg:postcode":"2820",
    "sg:province":"Danmark",
    "sg:website":"www.bakkegaard.gentofte-skoler.dk",
    "wof:name":"Bakkeg\u00e5rdsskolen",
    "wof:placetype":"venue"
},
  "geometry": {"coordinates":[12.5249853134,55.74634552],"type":"Point"}
}