{
  "type": "Feature",
  "properties": {
    "addr:full":"Skovvej 31 Gentofte Danmark 2820",
    "addr:housenumber":"31",
    "addr:postcode":"2820",
    "addr:street":"Skovvej",
    "iso:country":"DK",
    "sg:address":"Skovvej 31",
    "sg:city":"Gentofte",
    "sg:orig_category":"Musikere",
    "sg:phone":"+45 39 63 64 63",
    "sg:postcode":"2820",
    "sg:province":"Danmark",
    "wof:name":"Nissen, Peter",
    "wof:placetype":"venue"
},
  "geometry": {"coordinates":[12.5457983017,55.7636871338],"type":"Point"}
}