{
  "type": "Feature",
  "properties": {
    "addr:full":"Asminder\u00f8dgade 46 Fredensborg Danmark 3480",
    "addr:housenumber":"46",
    "addr:postcode":"3480",
    "addr:street":"Asminderodgade",
    "iso:country":"DK",
    "sg:address":"Asminder\u00f8dgade 46",
    "sg:city":"Fredensborg",
    "sg:orig_category":"Musikinstrumenter",
    "sg:phone":"+45 48 48 50 52",
    "sg:postcode":"3480",
    "sg:province":"Danmark",
    "wof:name":"Lydmuren",
    "wof:placetype":"venue"
},
  "geometry": {"coordinates":[12.4067993164,55.9695396423],"type":"Point"}
}