{
  "type": "Feature",
  "properties": {
    "addr:full":"Skolegade 12 Lemvig Danmark 7620",
    "addr:housenumber":"12",
    "addr:postcode":"7620",
    "addr:street":"Skolegade",
    "iso:country":"DK",
    "sg:address":"Skolegade 12",
    "sg:city":"Lemvig",
    "sg:orig_category":"Botilbud",
    "sg:phone":"+45 97 82 25 85",
    "sg:postcode":"7620",
    "sg:province":"Danmark",
    "wof:name":"Borgerskolen, KFUM's beskyttede pensionat",
    "wof:placetype":"venue"
},
  "geometry": {"coordinates":[8.310095787,56.5491485596],"type":"Point"}
}