{
  "type": "Feature",
  "properties": {
    "addr:full":"Fmd.: Poul Holm, F\u00e6llesdigevej 19 Gedser Danmark 4874",
    "addr:housenumber":"19",
    "addr:postcode":"4874",
    "addr:street":"Poul Holm Faellesdigevej",
    "iso:country":"DK",
    "sg:address":"Fmd.: Poul Holm, F\u00e6llesdigevej 19",
    "sg:city":"Gedser",
    "sg:orig_category":"Grundejerforeninger",
    "sg:phone":"+45 36 49 04 13",
    "sg:postcode":"4874",
    "sg:province":"Danmark",
    "wof:name":"Gedesby \u00d8stre Strand Grundejerforening",
    "wof:placetype":"venue"
},
  "geometry": {"coordinates":[11.9617109299,54.600353241],"type":"Point"}
}