{
  "type": "Feature",
  "properties": {
    "addr:full":"Langmarksvej 34  Horsens Danmark 8700",
    "addr:housenumber":"34",
    "addr:postcode":"8700",
    "addr:street":"Langmarksvej",
    "iso:country":"DK",
    "sg:address":"Langmarksvej 34 ",
    "sg:city":"Horsens",
    "sg:classifiers":[
        {
            "category":"Utilities",
            "subcategory":"Telephone",
            "type":"Services"
        }
    ],
    "sg:phone":"+45 75 60 28 50",
    "sg:postcode":"8700",
    "sg:province":"Danmark",
    "sg:tags":[
        "telecommunication"
    ],
    "wof:name":"KIRK TELECOM A/S",
    "wof:placetype":"venue"
},
  "geometry": {"coordinates":[9.8506574631,55.8715782166],"type":"Point"}
}