{
  "type": "Feature",
  "properties": {
    "addr:full":"Stenbjergvej 2, L\u00f8nborg Tarm Danmark 6880",
    "addr:housenumber":"2",
    "addr:postcode":"6880",
    "addr:street":"Stenbjergvej",
    "iso:country":"DK",
    "sg:address":"Stenbjergvej 2, L\u00f8nborg",
    "sg:city":"Tarm",
    "sg:orig_category":"Kirkesogne",
    "sg:phone":"+45 97 37 40 06",
    "sg:postcode":"6880",
    "sg:province":"Danmark",
    "wof:name":"L\u00f8nborg og Egvad kirkekontor",
    "wof:placetype":"venue"
},
  "geometry": {"coordinates":[8.5200052261,55.9060554504],"type":"Point"}
}