{
  "type": "Feature",
  "properties": {
    "addr:full":"Trekronergade 126 Valby Danmark 2500",
    "addr:housenumber":"126",
    "addr:postcode":"2500",
    "addr:street":"Trekronergade",
    "iso:country":"DK",
    "sg:address":"Trekronergade 126",
    "sg:city":"Valby",
    "sg:classifiers":[
        {
            "category":"Professional",
            "subcategory":"Computer Services",
            "type":"Services"
        }
    ],
    "sg:phone":"+45 70 23 38 00",
    "sg:postcode":"2500",
    "sg:province":"Danmark",
    "sg:tags":[
        "edb",
        "-",
        "software"
    ],
    "wof:name":"Duo Data Partner Aps",
    "wof:placetype":"venue"
},
  "geometry": {"coordinates":[12.5201349258,55.6520614624],"type":"Point"}
}