{
  "type": "Feature",
  "properties": {
    "addr:full":"v/ Ole Egge, Smedeg\u00e5rdsvej 2 Viborg Danmark 8800",
    "addr:housenumber":"2",
    "addr:postcode":"8800",
    "addr:street":"Egge Smedegaardsvej",
    "iso:country":"DK",
    "sg:address":"v/ Ole Egge, Smedeg\u00e5rdsvej 2",
    "sg:city":"Viborg",
    "sg:orig_category":"Trossamfund uden for folkekirken",
    "sg:postcode":"8800",
    "sg:province":"Danmark",
    "wof:name":"Jehovas Vidners Rigssal",
    "wof:placetype":"venue"
},
  "geometry": {"coordinates":[9.4071502686,56.452671051],"type":"Point"}
}