{
  "type": "Feature",
  "properties": {
    "addr:full":"Algade 75 Middelfart Danmark 5500",
    "addr:housenumber":"75",
    "addr:postcode":"5500",
    "addr:street":"Algade",
    "iso:country":"DK",
    "sg:address":"Algade 75",
    "sg:city":"Middelfart",
    "sg:orig_category":"Sko",
    "sg:phone":"+45 64 41 33 33",
    "sg:postcode":"5500",
    "sg:province":"Danmark",
    "wof:name":"G - Sko",
    "wof:placetype":"venue"
},
  "geometry": {"coordinates":[9.7343254089,55.5048599243],"type":"Point"}
}