{
  "type": "Feature",
  "properties": {
    "iso:country":"DK",
    "sg:address":"Sct. Mathias Gade 23",
    "sg:city":"Viborg",
    "sg:orig_category":"Advokater",
    "sg:phone":"+45 87 27 01 10",
    "sg:postcode":"8800",
    "sg:province":"Danmark",
    "sg:website":"www.steffensenoghorstmann.dk",
    "wof:name":"Steffensen, Horstmann & Partnere",
    "wof:placetype":"venue"
},
  "geometry": {"coordinates":[9.4056921005,56.4494171143],"type":"Point"}
}