{
  "type": "Feature",
  "properties": {
    "addr:full":"Kraghedevej 230 Tylstrup Danmark 9382",
    "addr:housenumber":"230",
    "addr:postcode":"9382",
    "addr:street":"Kraghedevej",
    "iso:country":"DK",
    "sg:address":"Kraghedevej 230",
    "sg:city":"Tylstrup",
    "sg:orig_category":"Murermestre",
    "sg:phone":"+45 98 83 58 58",
    "sg:postcode":"9382",
    "sg:province":"Danmark",
    "wof:name":"EC H\u00e5ndv\u00e6rkerservice",
    "wof:placetype":"venue"
},
  "geometry": {"coordinates":[10.01212883,57.2035865784],"type":"Point"}
}