{
  "type": "Feature",
  "properties": {
    "addr:full":"Fmd.: Ove Villumsen, \u00d8sterbyvej 10, B\u00f8lling Skjern Danmark 6900",
    "addr:housenumber":"10",
    "addr:postcode":"6900",
    "addr:street":"Osterbyvej;Bolling",
    "iso:country":"DK",
    "sg:address":"Fmd.: Ove Villumsen, \u00d8sterbyvej 10, B\u00f8lling",
    "sg:city":"Skjern",
    "sg:orig_category":"Kirkelige foreninger",
    "sg:phone":"+45 97 36 82 02",
    "sg:postcode":"6900",
    "sg:province":"Danmark",
    "wof:name":"KFUM og KFUK's Ungdomsafdeling, B\u00f8lling-S\u00e6dding",
    "wof:placetype":"venue"
},
  "geometry": {"coordinates":[8.492972374,55.9485740662],"type":"Point"}
}