{
  "type": "Feature",
  "properties": {
    "addr:full":"Baneg\u00e5rdsgade 3 Odder Danmark 8300",
    "addr:housenumber":"3",
    "addr:postcode":"8300",
    "addr:street":"Banegaardsgade",
    "iso:country":"DK",
    "sg:address":"Baneg\u00e5rdsgade 3",
    "sg:city":"Odder",
    "sg:orig_category":"Turistbureau og -information",
    "sg:phone":"+45 86 54 26 00",
    "sg:postcode":"8300",
    "sg:province":"Danmark",
    "wof:name":"Odder Turistbureau",
    "wof:placetype":"venue"
},
  "geometry": {"coordinates":[10.1498603821,55.9722251892],"type":"Point"}
}