{
  "type": "Feature",
  "properties": {
    "addr:full":"Henv.: Inge Marie Jensen, N\u00f8rre\u00e5vej 3, Vester Velling Ulstrup Danmark 8860",
    "addr:housenumber":"3",
    "addr:postcode":"8860",
    "addr:street":"Norreaavej;Vester Velling",
    "iso:country":"DK",
    "sg:address":"Henv.: Inge Marie Jensen, N\u00f8rre\u00e5vej 3, Vester Velling",
    "sg:city":"Ulstrup",
    "sg:orig_category":"Legestuer",
    "sg:phone":"+45 86 46 63 83",
    "sg:postcode":"8860",
    "sg:province":"Danmark",
    "wof:name":"V. Velling private legestue",
    "wof:placetype":"venue"
},
  "geometry": {"coordinates":[9.7940101624,56.3912200928],"type":"Point"}
}