{
  "type": "Feature",
  "properties": {
    "addr:full":"Fmd.: Niels G. P. Wetche, Harres\u00f8vej 7, Skovb\u00f8lling Jelling Danmark 7300",
    "addr:housenumber":"7",
    "addr:postcode":"7300",
    "addr:street":"Niels G. P. Wetche Harresovej",
    "iso:country":"DK",
    "sg:address":"Fmd.: Niels G. P. Wetche, Harres\u00f8vej 7, Skovb\u00f8lling",
    "sg:city":"Jelling",
    "sg:orig_category":"Soldaterforeninger",
    "sg:phone":"+45 75 87 16 01",
    "sg:postcode":"7300",
    "sg:province":"Danmark",
    "wof:name":"Feltartilleriforeningen, Vejle Amt",
    "wof:placetype":"venue"
},
  "geometry": {"coordinates":[9.4184103012,55.7558555603],"type":"Point"}
}