{
  "type": "Feature",
  "properties": {
    "addr:full":"Diern\u00e6svej 218 Haderslev Danmark 6100",
    "addr:housenumber":"218",
    "addr:postcode":"6100",
    "addr:street":"Diernaesvej",
    "iso:country":"DK",
    "sg:address":"Diern\u00e6svej 218",
    "sg:city":"Haderslev",
    "sg:orig_category":"Campingpladser",
    "sg:phone":"+45 74 69 89 33",
    "sg:postcode":"6100",
    "sg:province":"Danmark",
    "wof:name":"S\u00f8nderballe Camping",
    "wof:placetype":"venue"
},
  "geometry": {"coordinates":[9.4762716293,55.132434845],"type":"Point"}
}