{
  "type": "Feature",
  "properties": {
    "addr:full":"Galgemark 16 Bredebro Danmark 6261",
    "addr:housenumber":"16",
    "addr:postcode":"6261",
    "addr:street":"Galgemark",
    "iso:country":"DK",
    "sg:address":"Galgemark 16",
    "sg:city":"Bredebro",
    "sg:orig_category":"Arkitekter",
    "sg:phone":"+45 74 71 14 55",
    "sg:postcode":"6261",
    "sg:province":"Danmark",
    "wof:name":"Christian Carstensen",
    "wof:placetype":"venue"
},
  "geometry": {"coordinates":[8.8398656845,55.0503578186],"type":"Point"}
}