{
  "type": "Feature",
  "properties": {
    "iso:country":"DK",
    "sg:address":"Fmd.: Erik Pallisg\u00e5rd, H\u00f8gevej 8",
    "sg:city":"Fars\u00f8",
    "sg:orig_category":"\u00c3\u02dcvrige foreninger",
    "sg:phone":"+45 98 63 26 82",
    "sg:postcode":"9640",
    "sg:province":"Danmark",
    "wof:name":"St\u00f8tteforeningen H\u00f8jg\u00e5rdens Venner",
    "wof:placetype":"venue"
},
  "geometry": {"coordinates":[-109.44831848139999,42.1062355042],"type":"Point"}
}