{
  "type": "Feature",
  "properties": {
    "addr:full":"Fmd.: S\u00f8ren Paltoft, Eriksvej 79 Ringsted Danmark 4100",
    "addr:housenumber":"79",
    "addr:postcode":"4100",
    "addr:street":"Eriksvej",
    "iso:country":"DK",
    "sg:address":"Fmd.: S\u00f8ren Paltoft, Eriksvej 79",
    "sg:city":"Ringsted",
    "sg:orig_category":"Grundejerforeninger",
    "sg:phone":"+45 57 61 28 44",
    "sg:postcode":"4100",
    "sg:province":"Danmark",
    "wof:name":"Grundejerforeningen M\u00f8llemarksg\u00e5rd",
    "wof:placetype":"venue"
},
  "geometry": {"coordinates":[11.7875862122,55.4458961487],"type":"Point"}
}