{
  "type": "Feature",
  "properties": {
    "addr:full":"Jernbanegade 1 A, Hornum Aars Danmark 9600",
    "addr:housenumber":"1 a",
    "addr:postcode":"9600",
    "addr:street":"Jernbanegade",
    "iso:country":"DK",
    "sg:address":"Jernbanegade 1 A, Hornum",
    "sg:city":"Aars",
    "sg:classifiers":[
        {
            "category":"Banks & Credit Unions",
            "subcategory":"Bank",
            "type":"Services"
        }
    ],
    "sg:phone":"+45 98 66 10 33",
    "sg:postcode":"9600",
    "sg:province":"Danmark",
    "sg:tags":[
        "banker"
    ],
    "wof:name":"Spar Nord Bank A/S",
    "wof:placetype":"venue"
},
  "geometry": {"coordinates":[9.5170412064,56.8031692505],"type":"Point"}
}