{
  "type": "Feature",
  "properties": {
    "addr:full":"Kv\u00e6dehaven 52 Glostrup Danmark 2600",
    "addr:housenumber":"52",
    "addr:postcode":"2600",
    "addr:street":"Kvaedehaven",
    "iso:country":"DK",
    "sg:address":"Kv\u00e6dehaven 52",
    "sg:city":"Glostrup",
    "sg:orig_category":"Pressebureauer",
    "sg:phone":"+45 43 45 76 70",
    "sg:postcode":"2600",
    "sg:province":"Danmark",
    "wof:name":"Look Press",
    "wof:placetype":"venue"
},
  "geometry": {"coordinates":[12.3957901001,55.6654663086],"type":"Point"}
}