{
  "type": "Feature",
  "properties": {
    "addr:full":"Strandv\u00e6nget 14 Esbjerg V Danmark 6710",
    "addr:housenumber":"14",
    "addr:postcode":"6710",
    "addr:street":"Strandvaenget",
    "iso:country":"DK",
    "sg:address":"Strandv\u00e6nget 14",
    "sg:city":"Esbjerg V",
    "sg:orig_category":"\u00c3\u2020ldrecentre",
    "sg:phone":"+45 76 11 75 00",
    "sg:postcode":"6710",
    "sg:province":"Danmark",
    "wof:name":"Lyngvejs \u00c6ldrecenter",
    "wof:placetype":"venue"
},
  "geometry": {"coordinates":[8.3953723907,55.5005111694],"type":"Point"}
}