{
  "type": "Feature",
  "properties": {
    "addr:full":"Brolandvej 10 F, Bullerup Agedrup Danmark 5320",
    "addr:housenumber":"10 f",
    "addr:postcode":"5320",
    "addr:street":"Brolandvej;Bullerup",
    "iso:country":"DK",
    "sg:address":"Brolandvej 10 F, Bullerup",
    "sg:city":"Agedrup",
    "sg:classifiers":[
        {
            "category":"Professional",
            "subcategory":"Computer Services",
            "type":"Services"
        }
    ],
    "sg:phone":"+45 65 93 83 73",
    "sg:postcode":"5320",
    "sg:province":"Danmark",
    "sg:tags":[
        "edb",
        "-",
        "software"
    ],
    "wof:name":"Betasupport",
    "wof:placetype":"venue"
},
  "geometry": {"coordinates":[10.4700860977,55.4257240295],"type":"Point"}
}