{
  "type": "Feature",
  "properties": {
    "addr:full":"Bredgade 73 - 77, Postboks 46 Skjern Danmark 6900",
    "addr:housenumber":"73 77;46",
    "addr:postcode":"6900",
    "addr:street":"Bredgade;Postboks",
    "iso:country":"DK",
    "sg:address":"Bredgade 73 - 77, Postboks 46",
    "sg:city":"Skjern",
    "sg:orig_category":"Museer",
    "sg:phone":"+45 97 35 19 00",
    "sg:postcode":"6900",
    "sg:province":"Danmark",
    "wof:name":"Skjern \u00c5 Udstilling - Alle tiders \u00c5",
    "wof:placetype":"venue"
},
  "geometry": {"coordinates":[8.492972374,55.9485740662],"type":"Point"}
}