{
  "type": "Feature",
  "properties": {
    "iso:country":"DK",
    "sg:address":"Lykkeb\u00e6kvej 1",
    "sg:city":"K\u00f8ge",
    "sg:orig_category":"Offentlige sygehuse",
    "sg:phone":"+45 56 63 15 00",
    "sg:postcode":"4600",
    "sg:province":"Danmark",
    "wof:name":"Roskilde Amtssygehus K\u00f8ge.",
    "wof:placetype":"venue"
},
  "geometry": {"coordinates":[12.1640672684,55.4764099121],"type":"Point"}
}