{
  "type": "Feature",
  "properties": {
    "addr:full":"Lindegade 25 Christiansfeld Danmark 6070",
    "addr:housenumber":"25",
    "addr:postcode":"6070",
    "addr:street":"Lindegade",
    "iso:country":"DK",
    "sg:address":"Lindegade 25",
    "sg:city":"Christiansfeld",
    "sg:orig_category":"HOTELS: OG MOTELLER",
    "sg:phone":"+45 74 56 17 10",
    "sg:postcode":"6070",
    "sg:province":"Danmark",
    "sg:website":"www.gert-s.dk",
    "wof:name":"Br\u00f8dre Menighedens Hotel",
    "wof:placetype":"venue"
},
  "geometry": {"coordinates":[9.4837408066,55.3556938171],"type":"Point"}
}