{
  "type": "Feature",
  "properties": {
    "addr:full":"Rosensgade 5 Odder Danmark 8300",
    "addr:housenumber":"5",
    "addr:postcode":"8300",
    "addr:street":"Rosensgade",
    "iso:country":"DK",
    "sg:address":"Rosensgade 5",
    "sg:city":"Odder",
    "sg:orig_category":"Ejendomshandel",
    "sg:phone":"+45 86 54 32 66",
    "sg:postcode":"8300",
    "sg:province":"Danmark",
    "sg:website":"www.danbolig.dk",
    "wof:name":"DanBolig",
    "wof:placetype":"venue"
},
  "geometry": {"coordinates":[10.1493234634,55.972442627],"type":"Point"}
}