{
  "type": "Feature",
  "properties": {
    "addr:full":"v/ Poul Mortensen, Klirevej 9 Hinnerup Danmark 8382",
    "addr:housenumber":"9",
    "addr:postcode":"8382",
    "addr:street":"Mortensen Klirevej",
    "iso:country":"DK",
    "sg:address":"v/ Poul Mortensen, Klirevej 9",
    "sg:city":"Hinnerup",
    "sg:orig_category":"Grundejerforeninger",
    "sg:phone":"+45 86 98 62 29",
    "sg:postcode":"8382",
    "sg:province":"Danmark",
    "wof:name":"Klirevejs Grundejerforening",
    "wof:placetype":"venue"
},
  "geometry": {"coordinates":[10.0614156723,56.2650604248],"type":"Point"}
}