{
  "type": "Feature",
  "properties": {
    "addr:full":"Lange L\u00f8ng 12 Sor\u00f8 Danmark 4180",
    "addr:housenumber":"12",
    "addr:postcode":"4180",
    "addr:street":"Lange Long",
    "iso:country":"DK",
    "sg:address":"Lange L\u00f8ng 12",
    "sg:city":"Sor\u00f8",
    "sg:orig_category":"Rideudstyr",
    "sg:phone":"+45 57 82 00 93",
    "sg:postcode":"4180",
    "sg:province":"Danmark",
    "wof:name":"Lobri Rideudstyr",
    "wof:placetype":"venue"
},
  "geometry": {"coordinates":[-102.94467926030001,45.4534721375],"type":"Point"}
}