{
  "type": "Feature",
  "properties": {
    "addr:full":"B\u00e5dehavnsvej 11 Aalborg Danmark 9000",
    "addr:housenumber":"11",
    "addr:postcode":"9000",
    "addr:street":"Baadehavnsvej",
    "iso:country":"DK",
    "sg:address":"B\u00e5dehavnsvej 11",
    "sg:city":"Aalborg",
    "sg:classifiers":[
        {
            "category":"Restaurant",
            "type":"Food & Drink"
        }
    ],
    "sg:phone":"+45 98 13 75 00",
    "sg:postcode":"9000",
    "sg:province":"Danmark",
    "sg:website":"www.kompasset.dk",
    "wof:name":"Kompasset, Restaurant",
    "wof:placetype":"venue"
},
  "geometry": {"coordinates":[9.9008827209,57.0568313599],"type":"Point"}
}