{
  "type": "Feature",
  "properties": {
    "addr:full":"\u00c5rhus, Postboks 33 Beder Danmark 8330",
    "addr:housenumber":"33",
    "addr:postcode":"8330",
    "iso:country":"DK",
    "sg:address":"\u00c5rhus, Postboks 33",
    "sg:city":"Beder",
    "sg:orig_category":"Musik og sang",
    "sg:postcode":"8330",
    "sg:province":"Danmark",
    "sg:website":"www.jyske-opera.dk/venner",
    "wof:name":"Den Jyske Operas Venner",
    "wof:placetype":"venue"
},
  "geometry": {"coordinates":[10.2062501907,56.059173584],"type":"Point"}
}