{
  "type": "Feature",
  "properties": {
    "addr:full":"Maltvej 16, Askov Vejen Danmark 6600",
    "addr:housenumber":"16",
    "addr:postcode":"6600",
    "addr:street":"Maltvej;Askov",
    "iso:country":"DK",
    "sg:address":"Maltvej 16, Askov",
    "sg:city":"Vejen",
    "sg:orig_category":"Posthuse",
    "sg:phone":"+45 75 36 18 64",
    "sg:postcode":"6600",
    "sg:province":"Danmark",
    "wof:name":"Post Danmark, Askov Postbutik",
    "wof:placetype":"venue"
},
  "geometry": {"coordinates":[9.1396121979,55.4778175354],"type":"Point"}
}