{
  "type": "Feature",
  "properties": {
    "addr:full":"Dannebrogsgade 24 Odense C Danmark 5000",
    "addr:housenumber":"24",
    "addr:postcode":"5000",
    "addr:street":"Dannebrogsgade",
    "iso:country":"DK",
    "sg:address":"Dannebrogsgade 24",
    "sg:city":"Odense C",
    "sg:orig_category":"Museer",
    "sg:phone":"+45 66 13 66 30",
    "sg:postcode":"5000",
    "sg:province":"Danmark",
    "sg:website":"www.jernbanemuseum.dk",
    "wof:name":"Danmarks Jernbanemuseum",
    "wof:placetype":"venue"
},
  "geometry": {"coordinates":[10.3862533569,55.402431488],"type":"Point"}
}