{
  "type": "Feature",
  "properties": {
    "iso:country":"DK",
    "sg:address":"Schlegels Alle 3, st. tv.",
    "sg:city":"Frederiksberg",
    "sg:orig_category":"Konservatorer",
    "sg:phone":"+45 33 25 38 28",
    "sg:postcode":"1807",
    "sg:province":"Danmark",
    "wof:name":"Gallery Vision Studio",
    "wof:placetype":"venue"
},
  "geometry": {"coordinates":[12.5332098007,55.6710014343],"type":"Point"}
}