{
  "type": "Feature",
  "properties": {
    "addr:full":"Fmd.:Poul Erik Christensen, Sallingvej 13 Hobro Danmark 9500",
    "addr:housenumber":"13",
    "addr:postcode":"9500",
    "addr:street":"Poul Erik;Sallingvej",
    "iso:country":"DK",
    "sg:address":"Fmd.:Poul Erik Christensen, Sallingvej 13",
    "sg:city":"Hobro",
    "sg:orig_category":"Kulturelle foreninger",
    "sg:phone":"+45 98 52 02 36",
    "sg:postcode":"9500",
    "sg:province":"Danmark",
    "wof:name":"Soldaternes Venner, Hobro kredsen",
    "wof:placetype":"venue"
},
  "geometry": {"coordinates":[9.7946596146,56.6382789612],"type":"Point"}
}