{
  "type": "Feature",
  "properties": {
    "addr:full":"R\u00f8dhus Kirkevej 7, R\u00f8dhus Pandrup Danmark 9490",
    "addr:housenumber":"7",
    "addr:postcode":"9490",
    "addr:street":"Kirkevej",
    "iso:country":"DK",
    "sg:address":"R\u00f8dhus Kirkevej 7, R\u00f8dhus",
    "sg:city":"Pandrup",
    "sg:orig_category":"Kirker",
    "sg:phone":"+45 98 24 90 02",
    "sg:postcode":"9490",
    "sg:province":"Danmark",
    "wof:name":"R\u00f8dhus Kirke",
    "wof:placetype":"venue"
},
  "geometry": {"coordinates":[9.6769151688,57.223815918],"type":"Point"}
}