{
  "type": "Feature",
  "properties": {
    "addr:full":"\u00c5l\u00f8kke All\u00e9 2 Odense C Danmark 5000",
    "addr:housenumber":"2",
    "addr:postcode":"5000",
    "addr:street":"Aalokke Alle\u0301",
    "iso:country":"DK",
    "sg:address":"\u00c5l\u00f8kke All\u00e9 2",
    "sg:city":"Odense C",
    "sg:orig_category":"Autoreparation og -service",
    "sg:phone":"+45 66 11 97 92",
    "sg:postcode":"5000",
    "sg:province":"Danmark",
    "wof:name":"Aal\u00f8kkesholm Autov\u00e6rksted A/S",
    "wof:placetype":"venue"
},
  "geometry": {"coordinates":[10.390794754,55.3961715698],"type":"Point"}
}