{
  "type": "Feature",
  "properties": {
    "addr:full":"S\u00f8ndergade 17 Saksk\u00f8bing Danmark 4990",
    "addr:housenumber":"17",
    "addr:postcode":"4990",
    "addr:street":"Sondergade",
    "iso:country":"DK",
    "sg:address":"S\u00f8ndergade 17",
    "sg:city":"Saksk\u00f8bing",
    "sg:classifiers":[
        {
            "category":"Food & Beverages",
            "subcategory":"Liquor & Beverages",
            "type":"Retail Goods"
        }
    ],
    "sg:phone":"+45 54 70 41 51",
    "sg:postcode":"4990",
    "sg:province":"Danmark",
    "sg:tags":[
        "vin"
    ],
    "wof:name":"TH's Vink\u00e6lder",
    "wof:placetype":"venue"
},
  "geometry": {"coordinates":[-114.0767440796,46.4432487488],"type":"Point"}
}