{
  "type": "Feature",
  "properties": {
    "iso:country":"DK",
    "sg:address":"Klosterport 4 E",
    "sg:city":"\u00c5rhus C",
    "sg:orig_category":"Reproanstalter",
    "sg:phone":"+45 86 19 79 00",
    "sg:postcode":"8000",
    "sg:province":"Danmark",
    "wof:name":"Re-Produktion \u00c5rhus ApS",
    "wof:placetype":"venue"
},
  "geometry": {"coordinates":[4.717400074,49.7588005066],"type":"Point"}
}