{
  "type": "Feature",
  "properties": {
    "addr:full":"Fmd.: Bjarne Mikkelsen, Steng\u00e6rdet 11 Esbjerg \u00d8 Danmark 6705",
    "addr:housenumber":"11",
    "addr:postcode":"6705",
    "addr:street":"Stengaerdet;Danmark",
    "iso:country":"DK",
    "sg:address":"Fmd.: Bjarne Mikkelsen, Steng\u00e6rdet 11",
    "sg:city":"Esbjerg \u00d8",
    "sg:orig_category":"Politiske foreninger, \u00c3\u02dcvrige",
    "sg:phone":"+45 27 12 37 45",
    "sg:postcode":"6705",
    "sg:province":"Danmark",
    "sg:website":"www.vu.dk/esbjerg",
    "wof:name":"Venstres Ungdom i Esbjerg",
    "wof:placetype":"venue"
},
  "geometry": {"coordinates":[8.5338830948,55.5006523132],"type":"Point"}
}