{
  "type": "Feature",
  "properties": {
    "addr:full":"Algade 103 A Vordingborg Danmark 4760",
    "addr:housenumber":"103 a",
    "addr:postcode":"4760",
    "addr:street":"Algade",
    "iso:country":"DK",
    "sg:address":"Algade 103 A",
    "sg:city":"Vordingborg",
    "sg:orig_category":"\u00c3\u2020ldreorganisationer og klubber",
    "sg:phone":"+45 55 34 29 95",
    "sg:postcode":"4760",
    "sg:province":"Danmark",
    "wof:name":"\u00c6ldre hj\u00e6lper \u00c6ldre, M\u00f8destedet",
    "wof:placetype":"venue"
},
  "geometry": {"coordinates":[11.9116210938,55.0083618164],"type":"Point"}
}