{
  "type": "Feature",
  "properties": {
    "addr:full":"Boestoftevej 55, Boestofte R\u00f8dvig Stevns Danmark 4673",
    "addr:housenumber":"55",
    "addr:postcode":"4673",
    "addr:street":"Boestoftevej",
    "iso:country":"DK",
    "sg:address":"Boestoftevej 55, Boestofte",
    "sg:city":"R\u00f8dvig Stevns",
    "sg:orig_category":"Kommunale folkeskoler",
    "sg:phone":"+45 56 50 83 12",
    "sg:postcode":"4673",
    "sg:province":"Danmark",
    "wof:name":"Boestofteskolen",
    "wof:placetype":"venue"
},
  "geometry": {"coordinates":[12.3775653839,55.2558746338],"type":"Point"}
}