{
  "type": "Feature",
  "properties": {
    "addr:full":"Rusk\u00e6rvej 13 Bording Danmark 7441",
    "addr:housenumber":"13",
    "addr:postcode":"7441",
    "addr:street":"Ruskaervej",
    "iso:country":"DK",
    "sg:address":"Rusk\u00e6rvej 13",
    "sg:city":"Bording",
    "sg:orig_category":"Autoreparation og -service",
    "sg:phone":"+45 86 86 12 18",
    "sg:postcode":"7441",
    "sg:province":"Danmark",
    "wof:name":"Hoff, Kaj Verner",
    "wof:placetype":"venue"
},
  "geometry": {"coordinates":[9.1804170609,56.2044754028],"type":"Point"}
}