{
  "type": "Feature",
  "properties": {
    "addr:full":"Thorupvej 43 Sunds Danmark 7451",
    "addr:housenumber":"43",
    "addr:postcode":"7451",
    "addr:street":"Thorupvej",
    "iso:country":"DK",
    "sg:address":"Thorupvej 43",
    "sg:city":"Sunds",
    "sg:orig_category":"Systuer",
    "sg:phone":"+45 97 14 25 07",
    "sg:postcode":"7451",
    "sg:province":"Danmark",
    "wof:name":"Thorup L\u00f8nsy",
    "wof:placetype":"venue"
},
  "geometry": {"coordinates":[9.0617513657,56.1896820068],"type":"Point"}
}