{
  "type": "Feature",
  "properties": {
    "addr:full":"\u00d8stergade 7 Vojens Danmark 6500",
    "addr:housenumber":"7",
    "addr:postcode":"6500",
    "addr:street":"Ostergade",
    "iso:country":"DK",
    "sg:address":"\u00d8stergade 7",
    "sg:city":"Vojens",
    "sg:orig_category":"Videobutikker og -klubber",
    "sg:phone":"+45 74 59 11 12",
    "sg:postcode":"6500",
    "sg:province":"Danmark",
    "wof:name":"City Video - Cinematik",
    "wof:placetype":"venue"
},
  "geometry": {"coordinates":[9.3082561493,55.2479400635],"type":"Point"}
}