{
  "type": "Feature",
  "properties": {
    "addr:full":"Skanderborgvej 190 Viby Danmark 8260",
    "addr:housenumber":"190",
    "addr:postcode":"8260",
    "addr:street":"Skanderborgvej",
    "iso:country":"DK",
    "sg:address":"Skanderborgvej 190",
    "sg:city":"Viby",
    "sg:classifiers":[
        {
            "category":"Banks & Credit Unions",
            "subcategory":"Bank",
            "type":"Services"
        }
    ],
    "sg:phone":"+45 86 14 54 55",
    "sg:postcode":"8260",
    "sg:province":"Danmark",
    "sg:tags":[
        "banker"
    ],
    "wof:name":"Nordea",
    "wof:placetype":"venue"
},
  "geometry": {"coordinates":[10.1617136002,56.1284942627],"type":"Point"}
}