{
  "type": "Feature",
  "properties": {
    "addr:full":"Poppel Alle 11, Hareskov V\u00e6rl\u00f8se Danmark 3500",
    "addr:housenumber":"11",
    "addr:postcode":"3500",
    "addr:street":"Poppel Alle",
    "iso:country":"DK",
    "sg:address":"Poppel Alle 11, Hareskov",
    "sg:city":"V\u00e6rl\u00f8se",
    "sg:orig_category":"Ungdomsboliger og -hybler",
    "sg:postcode":"3500",
    "sg:province":"Danmark",
    "wof:name":"Poppelg\u00e5rden",
    "wof:placetype":"venue"
},
  "geometry": {"coordinates":[12.4117698669,55.754650116],"type":"Point"}
}