{
  "type": "Feature",
  "properties": {
    "addr:full":"Fyrrev\u00e6nget 18, Hou Odder Danmark 8300",
    "addr:housenumber":"18",
    "addr:postcode":"8300",
    "addr:street":"Fyrrevaenget;Hou",
    "iso:country":"DK",
    "sg:address":"Fyrrev\u00e6nget 18, Hou",
    "sg:city":"Odder",
    "sg:orig_category":"Psykologer, praktiserende",
    "sg:phone":"+45 86 55 72 77",
    "sg:postcode":"8300",
    "sg:province":"Danmark",
    "wof:name":"Mark, J\u00f8rgen",
    "wof:placetype":"venue"
},
  "geometry": {"coordinates":[10.1497612,55.9733161926],"type":"Point"}
}