{
  "type": "Feature",
  "properties": {
    "addr:full":"Parkvej 78 Taastrup Danmark 2630",
    "addr:housenumber":"78",
    "addr:postcode":"2630",
    "addr:street":"Parkvej",
    "iso:country":"DK",
    "sg:address":"Parkvej 78",
    "sg:city":"Taastrup",
    "sg:orig_category":"Fritidsklubber",
    "sg:phone":"+45 43 35 35 80",
    "sg:postcode":"2630",
    "sg:province":"Danmark",
    "wof:name":"Trillingeklubberne",
    "wof:placetype":"venue"
},
  "geometry": {"coordinates":[12.3176517487,55.6524505615],"type":"Point"}
}