{
  "type": "Feature",
  "properties": {
    "iso:country":"DK",
    "sg:address":"Bredgade 36",
    "sg:city":"Pandrup",
    "sg:orig_category":"Servicestationer",
    "sg:phone":"+45 98 24 62 11",
    "sg:postcode":"9490",
    "sg:province":"Danmark",
    "wof:name":"Statoil Servicenter",
    "wof:placetype":"venue"
},
  "geometry": {"coordinates":[9.6761951447,57.2210426331],"type":"Point"}
}