{
  "type": "Feature",
  "properties": {
    "iso:country":"DK",
    "sg:address":"Fmd.: Poul Andreasen, Udsholt Byvej 15",
    "sg:city":"Gr\u00e6sted",
    "sg:orig_category":"Husflidsforeninger",
    "sg:phone":"+45 48 71 43 17",
    "sg:postcode":"3230",
    "sg:province":"Danmark",
    "wof:name":"Blistrup Husflidsforening",
    "wof:placetype":"venue"
},
  "geometry": {"coordinates":[12.3426475525,56.048500061],"type":"Point"}
}