{
  "type": "Feature",
  "properties": {
    "addr:full":"Viggo Barfoeds Alle 51 Ballerup Danmark 2750",
    "addr:housenumber":"51",
    "addr:postcode":"2750",
    "addr:street":"Viggo Barfoeds Alle",
    "iso:country":"DK",
    "sg:address":"Viggo Barfoeds Alle 51",
    "sg:city":"Ballerup",
    "sg:orig_category":"Pianostemmere",
    "sg:phone":"+45 44 97 70 99",
    "sg:postcode":"2750",
    "sg:province":"Danmark",
    "wof:name":"Bengtsson, Aage",
    "wof:placetype":"venue"
},
  "geometry": {"coordinates":[12.3791284561,55.7410316467],"type":"Point"}
}