{
  "type": "Feature",
  "properties": {
    "addr:full":"Kirkevej 16 Gedved Danmark 8751",
    "addr:housenumber":"16",
    "addr:postcode":"8751",
    "addr:street":"Kirkevej",
    "iso:country":"DK",
    "sg:address":"Kirkevej 16",
    "sg:city":"Gedved",
    "sg:orig_category":"Kommunale folkeskoler",
    "sg:phone":"+45 75 66 50 98",
    "sg:postcode":"8751",
    "sg:province":"Danmark",
    "wof:name":"Gedved Skole",
    "wof:placetype":"venue"
},
  "geometry": {"coordinates":[9.8565511703,55.9312362671],"type":"Point"}
}