{
  "type": "Feature",
  "properties": {
    "iso:country":"DK",
    "sg:address":"T\u00f8mmerupvej 6",
    "sg:city":"Kalundborg",
    "sg:orig_category":"Skolefritidsordninger",
    "sg:phone":"+45 59 50 75 08",
    "sg:postcode":"4400",
    "sg:province":"Danmark",
    "wof:name":"T\u00f8mmerup Skoles Skolefritidsordning",
    "wof:placetype":"venue"
},
  "geometry": {"coordinates":[11.1483802795,55.6879005432],"type":"Point"}
}