{
  "type": "Feature",
  "properties": {
    "addr:full":"Assensvej 15, H\u00e5re Gelsted Danmark 5591",
    "addr:housenumber":"15",
    "addr:postcode":"5591",
    "addr:street":"Assensvej",
    "iso:country":"DK",
    "sg:address":"Assensvej 15, H\u00e5re",
    "sg:city":"Gelsted",
    "sg:orig_category":"Maskinstationer",
    "sg:phone":"+45 40 16 38 14",
    "sg:postcode":"5591",
    "sg:province":"Danmark",
    "wof:name":"Minendal Maskinstation I/S",
    "wof:placetype":"venue"
},
  "geometry": {"coordinates":[9.9734048843,55.3995094299],"type":"Point"}
}