{
  "type": "Feature",
  "properties": {
    "addr:full":"Lillev\u00e6nget 3 Veflinge Danmark 5474",
    "addr:housenumber":"3",
    "addr:postcode":"5474",
    "addr:street":"Lillevaenget",
    "iso:country":"DK",
    "sg:address":"Lillev\u00e6nget 3",
    "sg:city":"Veflinge",
    "sg:orig_category":"Murermestre",
    "sg:phone":"+45 64 80 16 27",
    "sg:postcode":"5474",
    "sg:province":"Danmark",
    "wof:name":"S\u00f8berg & Nielsen, Murermestrene",
    "wof:placetype":"venue"
},
  "geometry": {"coordinates":[10.1596345901,55.4755935669],"type":"Point"}
}