{
  "type": "Feature",
  "properties": {
    "addr:full":"Algade 95 M, 0005 Vordingborg Danmark 4760",
    "addr:housenumber":"95 m",
    "addr:postcode":"0005;4760",
    "addr:street":"Algade",
    "iso:country":"DK",
    "sg:address":"Algade 95 M, 0005",
    "sg:city":"Vordingborg",
    "sg:orig_category":"Fotografer",
    "sg:phone":"+45 55 34 60 40",
    "sg:postcode":"4760",
    "sg:province":"Danmark",
    "wof:name":"Billedgalleriet",
    "wof:placetype":"venue"
},
  "geometry": {"coordinates":[11.9124183655,55.0085449219],"type":"Point"}
}