{
  "type": "Feature",
  "properties": {
    "addr:full":"Mariegade 8 Haderslev Danmark 6100",
    "addr:housenumber":"8",
    "addr:postcode":"6100",
    "addr:street":"Mariegade",
    "iso:country":"DK",
    "sg:address":"Mariegade 8",
    "sg:city":"Haderslev",
    "sg:orig_category":"Trossamfund uden for folkekirken",
    "sg:phone":"+45 74 52 23 26",
    "sg:postcode":"6100",
    "sg:province":"Danmark",
    "wof:name":"Romersk-Katolske Trossamfund, Det",
    "wof:placetype":"venue"
},
  "geometry": {"coordinates":[9.4932556152,55.2525405884],"type":"Point"}
}