{
  "type": "Feature",
  "properties": {
    "addr:full":"Fisketorvet 6 Slagelse Danmark 4200",
    "addr:housenumber":"6",
    "addr:postcode":"4200",
    "addr:street":"Fisketorvet",
    "iso:country":"DK",
    "sg:address":"Fisketorvet 6",
    "sg:city":"Slagelse",
    "sg:orig_category":"Ejendomshandel",
    "sg:phone":"+45 58 50 21 10",
    "sg:postcode":"4200",
    "sg:province":"Danmark",
    "wof:name":"Home - Madsen og Oppermann",
    "wof:placetype":"venue"
},
  "geometry": {"coordinates":[11.3555870056,55.4033203125],"type":"Point"}
}