{
  "type": "Feature",
  "properties": {
    "addr:full":"Neversvej 38 - 40 Tommerup Danmark 5690",
    "addr:housenumber":"38 40",
    "addr:postcode":"5690",
    "addr:street":"Neversvej",
    "iso:country":"DK",
    "sg:address":"Neversvej 38 - 40",
    "sg:city":"Tommerup",
    "sg:orig_category":"Gartnerier",
    "sg:phone":"+45 64 75 12 23",
    "sg:postcode":"5690",
    "sg:province":"Danmark",
    "wof:name":"Nielsen, Svend",
    "wof:placetype":"venue"
},
  "geometry": {"coordinates":[10.1671562195,55.3004455566],"type":"Point"}
}