{
  "type": "Feature",
  "properties": {
    "addr:full":"Rudbjergvej 2, Halsted Nakskov Danmark 4900",
    "addr:housenumber":"2",
    "addr:postcode":"4900",
    "addr:street":"Rudbjergvej;Halsted",
    "iso:country":"DK",
    "sg:address":"Rudbjergvej 2, Halsted",
    "sg:city":"Nakskov",
    "sg:orig_category":"Efterskoler",
    "sg:phone":"+45 54 93 96 31",
    "sg:postcode":"4900",
    "sg:province":"Danmark",
    "wof:name":"Halstedhus Efterskole",
    "wof:placetype":"venue"
},
  "geometry": {"coordinates":[11.1359500885,54.8330116272],"type":"Point"}
}