{
  "type": "Feature",
  "properties": {
    "addr:full":"Herningvej 4 Karup Danmark 7470",
    "addr:housenumber":"4",
    "addr:postcode":"7470",
    "addr:street":"Herningvej",
    "iso:country":"DK",
    "sg:address":"Herningvej 4",
    "sg:city":"Karup",
    "sg:orig_category":"Malermestre",
    "sg:phone":"+45 97 10 27 28",
    "sg:postcode":"7470",
    "sg:province":"Danmark",
    "wof:name":"Mortens Malerfirma",
    "wof:placetype":"venue"
},
  "geometry": {"coordinates":[9.1641798019,56.3086166382],"type":"Point"}
}