{
  "type": "Feature",
  "properties": {
    "iso:country":"DK",
    "sg:address":"Gammel Havn 7",
    "sg:city":"Vejle",
    "sg:orig_category":"Grundejerforeninger",
    "sg:phone":"+45 75 82 11 84",
    "sg:postcode":"7100",
    "sg:province":"Danmark",
    "wof:name":"Grundejerforeningen",
    "wof:placetype":"venue"
},
  "geometry": {"coordinates":[9.5339136124,55.7048377991],"type":"Point"}
}