{
  "type": "Feature",
  "properties": {
    "addr:full":"Lufthavnsvej 50 Roskilde Danmark 4000",
    "addr:housenumber":"50",
    "addr:postcode":"4000",
    "addr:street":"Lufthavnsvej",
    "iso:country":"DK",
    "sg:address":"Lufthavnsvej 50",
    "sg:city":"Roskilde",
    "sg:orig_category":"Lufttransport",
    "sg:phone":"+45 46 19 15 55",
    "sg:postcode":"4000",
    "sg:province":"Danmark",
    "sg:website":"www.jetair.dk",
    "wof:name":"Jetair Flight Academy",
    "wof:placetype":"venue"
},
  "geometry": {"coordinates":[12.1262989044,55.5921707153],"type":"Point"}
}