{
  "type": "Feature",
  "properties": {
    "addr:full":"Jernbanegade 37 Ringe Danmark 5750",
    "addr:housenumber":"37",
    "addr:postcode":"5750",
    "addr:street":"Jernbanegade",
    "iso:country":"DK",
    "sg:address":"Jernbanegade 37",
    "sg:city":"Ringe",
    "sg:classifiers":[
        {
            "category":"Shopping",
            "subcategory":"Crafts & Fabrics",
            "type":"Retail Goods"
        }
    ],
    "sg:phone":"+45 62 62 32 65",
    "sg:postcode":"5750",
    "sg:province":"Danmark",
    "sg:tags":[
        "go-kart"
    ],
    "wof:name":"Racing Motor",
    "wof:placetype":"venue"
},
  "geometry": {"coordinates":[10.4837312698,55.2409286499],"type":"Point"}
}