{
  "type": "Feature",
  "properties": {
    "iso:country":"DK",
    "sg:address":"Fan\u00f8vej 15",
    "sg:city":"Hinnerup",
    "sg:orig_category":"Varmeforsyning",
    "sg:phone":"+45 86 98 53 40",
    "sg:postcode":"8382",
    "sg:province":"Danmark",
    "wof:name":"Hinnerup Fjernvarme A.m.b.A.",
    "wof:placetype":"venue"
},
  "geometry": {"coordinates":[10.0763587952,56.2493057251],"type":"Point"}
}