{
  "type": "Feature",
  "properties": {
    "addr:full":"Kildevej 4 Karup Danmark 7470",
    "addr:housenumber":"4",
    "addr:postcode":"7470",
    "addr:street":"Kildevej",
    "iso:country":"DK",
    "sg:address":"Kildevej 4",
    "sg:city":"Karup",
    "sg:orig_category":"Fiskeindustri",
    "sg:phone":"+45 97 10 10 18",
    "sg:postcode":"7470",
    "sg:province":"Danmark",
    "wof:name":"I/S Karup M\u00f8lles Fiskeri",
    "wof:placetype":"venue"
},
  "geometry": {"coordinates":[9.1653862,56.30519104],"type":"Point"}
}