{
  "type": "Feature",
  "properties": {
    "addr:full":"Sverigesvej 9 Allinge Danmark 3770",
    "addr:housenumber":"9",
    "addr:postcode":"3770",
    "addr:street":"Sverigesvej",
    "iso:country":"DK",
    "sg:address":"Sverigesvej 9",
    "sg:city":"Allinge",
    "sg:orig_category":"Cafeterier",
    "sg:phone":"+45 56 48 17 89",
    "sg:postcode":"3770",
    "sg:province":"Danmark",
    "wof:name":"Allinge Havneburger",
    "wof:placetype":"venue"
},
  "geometry": {"coordinates":[14.8002195358,55.2796516418],"type":"Point"}
}