{
  "type": "Feature",
  "properties": {
    "addr:full":"Byskellet 4 Jyllinge Danmark 4040",
    "addr:housenumber":"4",
    "addr:postcode":"4040",
    "addr:street":"Byskellet",
    "iso:country":"DK",
    "sg:address":"Byskellet 4",
    "sg:city":"Jyllinge",
    "sg:orig_category":"Vinduer",
    "sg:phone":"+45 46 73 08 05",
    "sg:postcode":"4040",
    "sg:province":"Danmark",
    "wof:name":"Arp-Hansen Renovering",
    "wof:placetype":"venue"
},
  "geometry": {"coordinates":[12.1044025421,55.755645752],"type":"Point"}
}