{
  "type": "Feature",
  "properties": {
    "iso:country":"DK",
    "sg:address":"Gr\u00f8nnegade 38",
    "sg:city":"Vejle",
    "sg:orig_category":"Gaveartikler",
    "sg:phone":"+45 75 72 50 62",
    "sg:postcode":"7100",
    "sg:province":"Danmark",
    "wof:name":"Salam",
    "wof:placetype":"venue"
},
  "geometry": {"coordinates":[9.533908844,55.7094306946],"type":"Point"}
}