{
  "type": "Feature",
  "properties": {
    "addr:full":"Pr\u00e6stevej 39, Raml\u00f8se Helsinge Danmark 3200",
    "addr:housenumber":"39",
    "addr:postcode":"3200",
    "addr:street":"Praestevej;Ramlose",
    "iso:country":"DK",
    "sg:address":"Pr\u00e6stevej 39, Raml\u00f8se",
    "sg:city":"Helsinge",
    "sg:orig_category":"EDB - undervisning",
    "sg:phone":"+45 48 71 25 95",
    "sg:postcode":"3200",
    "sg:province":"Danmark",
    "wof:name":"Raml\u00f8se Gruppen",
    "wof:placetype":"venue"
},
  "geometry": {"coordinates":[12.196846962,56.0224456787],"type":"Point"}
}