{
  "type": "Feature",
  "properties": {
    "addr:full":"L\u00e5sbygade 11 Kolding Danmark 6000",
    "addr:housenumber":"11",
    "addr:postcode":"6000",
    "addr:street":"Laasbygade",
    "iso:country":"DK",
    "sg:address":"L\u00e5sbygade 11",
    "sg:city":"Kolding",
    "sg:classifiers":[
        {
            "category":"Restaurant",
            "type":"Food & Drink"
        }
    ],
    "sg:phone":"+45 74 55 09 43",
    "sg:postcode":"6000",
    "sg:province":"Danmark",
    "wof:name":"China Wok House",
    "wof:placetype":"venue"
},
  "geometry": {"coordinates":[9.471036911,55.4918441772],"type":"Point"}
}