{
  "type": "Feature",
  "properties": {
    "addr:full":"Prinsensgade 36 Aalborg Danmark 9000",
    "addr:housenumber":"36",
    "addr:postcode":"9000",
    "addr:street":"Prinsensgade",
    "iso:country":"DK",
    "sg:address":"Prinsensgade 36",
    "sg:city":"Aalborg",
    "sg:orig_category":"Plejehjemsboliger",
    "sg:phone":"+45 98 10 31 32",
    "sg:postcode":"9000",
    "sg:province":"Danmark",
    "wof:name":"Egestadshus",
    "wof:placetype":"venue"
},
  "geometry": {"coordinates":[9.9156522751,57.0455932617],"type":"Point"}
}