{
  "type": "Feature",
  "properties": {
    "addr:full":"Plantagevej 1, Bodilsker Nex\u00f8 Danmark 3730",
    "addr:housenumber":"1",
    "addr:postcode":"3730",
    "addr:street":"Plantagevej",
    "iso:country":"DK",
    "sg:address":"Plantagevej 1, Bodilsker",
    "sg:city":"Nex\u00f8",
    "sg:orig_category":"Kursussteder",
    "sg:phone":"+45 20 48 32 08",
    "sg:postcode":"3730",
    "sg:province":"Danmark",
    "wof:name":"Sun Bornholm",
    "wof:placetype":"venue"
},
  "geometry": {"coordinates":[15.1096076965,55.0267219543],"type":"Point"}
}