{
  "type": "Feature",
  "properties": {
    "addr:full":"Thorningvej 49 Kjellerup Danmark 8620",
    "addr:housenumber":"49",
    "addr:postcode":"8620",
    "addr:street":"Thorningvej",
    "iso:country":"DK",
    "sg:address":"Thorningvej 49",
    "sg:city":"Kjellerup",
    "sg:orig_category":"Maskinudlejning",
    "sg:phone":"+45 86 88 30 06",
    "sg:postcode":"8620",
    "sg:province":"Danmark",
    "wof:name":"VMP Maskinudlejning",
    "wof:placetype":"venue"
},
  "geometry": {"coordinates":[9.4171895981,56.2871742249],"type":"Point"}
}