{
  "type": "Feature",
  "properties": {
    "iso:country":"DK",
    "sg:address":"Hjaltesvej 5 A",
    "sg:city":"Skive",
    "sg:orig_category":"Handicapboliger",
    "sg:phone":"+45 96 15 55 55",
    "sg:postcode":"7800",
    "sg:province":"Danmark",
    "wof:name":"Bostedet",
    "wof:placetype":"venue"
},
  "geometry": {"coordinates":[9.0513896942,56.5512046814],"type":"Point"}
}