{
  "type": "Feature",
  "properties": {
    "addr:full":"Bredgade 15 Hurup Danmark 7760",
    "addr:housenumber":"15",
    "addr:postcode":"7760",
    "addr:street":"Bredgade",
    "iso:country":"DK",
    "sg:address":"Bredgade 15",
    "sg:city":"Hurup",
    "sg:orig_category":"Diners transportables",
    "sg:phone":"+45 97 95 14 84",
    "sg:postcode":"7760",
    "sg:province":"Danmark",
    "sg:website":"www.mollekroen.dk",
    "wof:name":"M\u00f8llekroen",
    "wof:placetype":"venue"
},
  "geometry": {"coordinates":[8.432759285,56.7452354431],"type":"Point"}
}