{
  "type": "Feature",
  "properties": {
    "addr:full":"Smallegade 40 Frederiksberg Danmark 2000",
    "addr:housenumber":"40",
    "addr:postcode":"2000",
    "addr:street":"Smallegade",
    "iso:country":"DK",
    "sg:address":"Smallegade 40",
    "sg:city":"Frederiksberg",
    "sg:orig_category":"Slagter og viktualie",
    "sg:phone":"+45 38 88 05 16",
    "sg:postcode":"2000",
    "sg:province":"Danmark",
    "wof:name":"Hansens Mad og Vin",
    "wof:placetype":"venue"
},
  "geometry": {"coordinates":[12.5253801346,55.6795120239],"type":"Point"}
}