{
  "type": "Feature",
  "properties": {
    "iso:country":"DK",
    "sg:address":"L\u00f8vegade 6",
    "sg:city":"Slagelse",
    "sg:orig_category":"Pengeskabe",
    "sg:phone":"+45 58 52 85 65",
    "sg:postcode":"4200",
    "sg:province":"Danmark",
    "wof:name":"Bagger L\u00e5se & Alarm",
    "wof:placetype":"venue"
},
  "geometry": {"coordinates":[11.3522071838,55.4040756226],"type":"Point"}
}