{
  "type": "Feature",
  "properties": {
    "iso:country":"DK",
    "sg:address":"Jagtvej 21",
    "sg:city":"K\u00f8benhavn N",
    "sg:classifiers":[
        {
            "category":"Restaurant",
            "type":"Food & Drink"
        }
    ],
    "sg:phone":"+45 38 86 46 59",
    "sg:postcode":"2200",
    "sg:province":"Danmark",
    "wof:name":"Lenco Bar",
    "wof:placetype":"venue"
},
  "geometry": {"coordinates":[-82.6304473877,42.9909095764],"type":"Point"}
}