{
  "type": "Feature",
  "properties": {
    "addr:full":"v/ Toby Johansen, Byskovvej 114, Onsevig Horslunde Danmark 4913",
    "addr:housenumber":"114",
    "addr:postcode":"4913",
    "addr:street":"Byskovvej",
    "iso:country":"DK",
    "sg:address":"v/ Toby Johansen, Byskovvej 114, Onsevig",
    "sg:city":"Horslunde",
    "sg:orig_category":"Havne",
    "sg:phone":"+45 54 93 30 73",
    "sg:postcode":"4913",
    "sg:province":"Danmark",
    "wof:name":"Den Selvejende Institution - Onsevig Havn",
    "wof:placetype":"venue"
},
  "geometry": {"coordinates":[11.2169551849,54.9111862183],"type":"Point"}
}