{
  "type": "Feature",
  "properties": {
    "addr:full":"Kornvej 7 Give Danmark 7323",
    "addr:housenumber":"7",
    "addr:postcode":"7323",
    "addr:street":"Kornvej",
    "iso:country":"DK",
    "sg:address":"Kornvej 7",
    "sg:city":"Give",
    "sg:orig_category":"Parketgulve",
    "sg:phone":"+45 75 73 16 11",
    "sg:postcode":"7323",
    "sg:province":"Danmark",
    "wof:name":"Selandia Parket ApS",
    "wof:placetype":"venue"
},
  "geometry": {"coordinates":[9.2273197174,55.8451690674],"type":"Point"}
}