{
  "type": "Feature",
  "properties": {
    "addr:full":"Sandagervej 18 Herning Danmark 7400",
    "addr:housenumber":"18",
    "addr:postcode":"7400",
    "addr:street":"Sandagervej",
    "iso:country":"DK",
    "sg:address":"Sandagervej 18",
    "sg:city":"Herning",
    "sg:classifiers":[
        {
            "category":"Food & Beverages",
            "subcategory":"Candy",
            "type":"Retail Goods"
        }
    ],
    "sg:phone":"+45 97 12 55 37",
    "sg:postcode":"7400",
    "sg:province":"Danmark",
    "sg:tags":[
        "finer"
    ],
    "wof:name":"Herning ny Finercentral ApS",
    "wof:placetype":"venue"
},
  "geometry": {"coordinates":[8.939745903,56.127658844],"type":"Point"}
}