{
  "type": "Feature",
  "properties": {
    "addr:full":"Thomas B.Thriges Gd. 26 Odense C Danmark 5000",
    "addr:postcode":"5000",
    "addr:street":"Gd. 26",
    "iso:country":"DK",
    "sg:address":"Thomas B.Thriges Gd. 26",
    "sg:city":"Odense C",
    "sg:orig_category":"Erhvervslokaler, Udlejning af",
    "sg:phone":"+45 66 11 77 55",
    "sg:postcode":"5000",
    "sg:province":"Danmark",
    "wof:name":"H\u00f8jby Byggeselskab A/S",
    "wof:placetype":"venue"
},
  "geometry": {"coordinates":[10.3897266388,55.3998451233],"type":"Point"}
}