{
  "type": "Feature",
  "properties": {
    "addr:full":"Tornerosevej 127 A Herlev Danmark 2730",
    "addr:housenumber":"127 a",
    "addr:postcode":"2730",
    "addr:street":"Tornerosevej",
    "iso:country":"DK",
    "sg:address":"Tornerosevej 127 A",
    "sg:city":"Herlev",
    "sg:classifiers":[
        {
            "category":"Internet Cafe",
            "subcategory":"None",
            "type":"Food & Drink"
        }
    ],
    "sg:phone":"+45 44 92 99 16",
    "sg:postcode":"2730",
    "sg:province":"Danmark",
    "wof:name":"Net Fokus",
    "wof:placetype":"venue"
},
  "geometry": {"coordinates":[12.447971344,55.7310447693],"type":"Point"}
}