{
  "type": "Feature",
  "properties": {
    "addr:full":"Folkvarsvej 20 Frederiksberg Danmark 2000",
    "addr:housenumber":"20",
    "addr:postcode":"2000",
    "addr:street":"Folkvarsvej",
    "iso:country":"DK",
    "sg:address":"Folkvarsvej 20",
    "sg:city":"Frederiksberg",
    "sg:classifiers":[
        {
            "category":"Communications",
            "type":"Services"
        }
    ],
    "sg:phone":"+45 38 87 85 00",
    "sg:postcode":"2000",
    "sg:province":"Danmark",
    "sg:tags":[
        "radio-",
        "og",
        "tv-stationer"
    ],
    "wof:name":"Radio Falcon",
    "wof:placetype":"venue"
},
  "geometry": {"coordinates":[12.5333948135,55.6831130981],"type":"Point"}
}