{
  "type": "Feature",
  "properties": {
    "iso:country":"DK",
    "sg:address":"Havrebakken 5",
    "sg:city":"Kolind",
    "sg:orig_category":"Kiropraktorer",
    "sg:phone":"+45 86 39 16 66",
    "sg:postcode":"8560",
    "sg:province":"Danmark",
    "wof:name":"Victor-Larsen, H.",
    "wof:placetype":"venue"
},
  "geometry": {"coordinates":[10.5818061829,56.3594551086],"type":"Point"}
}