{
  "type": "Feature",
  "properties": {
    "addr:full":"Leder: Jan Erik Hansen, Stagstrup skole, Stagstrup Skolevej 5 Snedsted Danmark 7752",
    "addr:housenumber":"5",
    "addr:postcode":"7752",
    "addr:street":"Erik;Stagstrup Skolevej",
    "iso:country":"DK",
    "sg:address":"Leder: Jan Erik Hansen, Stagstrup skole, Stagstrup Skolevej 5",
    "sg:city":"Snedsted",
    "sg:orig_category":"\u00c3\u02dcvrig fritidsundervisning",
    "sg:phone":"+45 97 93 69 15",
    "sg:postcode":"7752",
    "sg:province":"Danmark",
    "wof:name":"Thy Gospel Kor",
    "wof:placetype":"venue"
},
  "geometry": {"coordinates":[8.5276002884,56.8460388184],"type":"Point"}
}