{
  "type": "Feature",
  "properties": {
    "addr:full":"\u00d8stergade 19 Mariager Danmark 9550",
    "addr:housenumber":"19",
    "addr:postcode":"9550",
    "addr:street":"Ostergade",
    "iso:country":"DK",
    "sg:address":"\u00d8stergade 19",
    "sg:city":"Mariager",
    "sg:orig_category":"Handicapboliger",
    "sg:phone":"+45 98 54 16 78",
    "sg:postcode":"9550",
    "sg:province":"Danmark",
    "wof:name":"Bof\u00e6llesskaberne i Mariager",
    "wof:placetype":"venue"
},
  "geometry": {"coordinates":[9.9835996628,56.6525192261],"type":"Point"}
}