{
  "type": "Feature",
  "properties": {
    "addr:full":"Viborgvej 2 Holstebro Danmark 7500",
    "addr:housenumber":"2",
    "addr:postcode":"7500",
    "addr:street":"Viborgvej",
    "iso:country":"DK",
    "sg:address":"Viborgvej 2",
    "sg:city":"Holstebro",
    "sg:orig_category":"Glarmestre og glarmagere",
    "sg:phone":"+45 97 40 19 99",
    "sg:postcode":"7500",
    "sg:province":"Danmark",
    "wof:name":"Vestjydsk Autoglas I/S",
    "wof:placetype":"venue"
},
  "geometry": {"coordinates":[8.6240825653,56.3578186035],"type":"Point"}
}