{
  "type": "Feature",
  "properties": {
    "addr:full":"Pr\u00e6steg\u00e5rds Alle 19 Br\u00f8nsh\u00f8j Danmark 2700",
    "addr:housenumber":"19",
    "addr:postcode":"2700",
    "addr:street":"Praestegaards Alle",
    "iso:country":"DK",
    "sg:address":"Pr\u00e6steg\u00e5rds Alle 19",
    "sg:city":"Br\u00f8nsh\u00f8j",
    "sg:orig_category":"HOTELS: OG MOTELLER",
    "sg:phone":"+45 38 60 11 05",
    "sg:postcode":"2700",
    "sg:province":"Danmark",
    "sg:website":"www.brhhotel.aok.dk",
    "wof:name":"Br\u00f8nsh\u00f8j Nye Selskabslokaler & Hotel",
    "wof:placetype":"venue"
},
  "geometry": {"coordinates":[-65.6866531372,-23.1981296539],"type":"Point"}
}