{
  "type": "Feature",
  "properties": {
    "iso:country":"DK",
    "sg:address":"Marielundvej 29 ",
    "sg:city":"Herlev",
    "sg:classifiers":[
        {
            "category":"Communications",
            "subcategory":"Television Station",
            "type":"Services"
        }
    ],
    "sg:phone":"+45 44 53 30 11",
    "sg:postcode":"2730",
    "sg:province":"Danmark",
    "sg:tags":[
        "audio-visual"
    ],
    "wof:name":"KINOVOX A/S",
    "wof:placetype":"venue"
},
  "geometry": {"coordinates":[12.4291543961,55.7175636292],"type":"Point"}
}