{
  "type": "Feature",
  "properties": {
    "iso:country":"DK",
    "sg:address":"Prinsensgade 19",
    "sg:city":"Fredericia",
    "sg:orig_category":"Maskinfabrikker",
    "sg:phone":"+45 75 92 21 81",
    "sg:postcode":"7000",
    "sg:province":"Danmark",
    "wof:name":"Fredericia Maskinv\u00e6rksted",
    "wof:placetype":"venue"
},
  "geometry": {"coordinates":[9.7598209381,55.5687294006],"type":"Point"}
}