{
  "type": "Feature",
  "properties": {
    "addr:full":"Fmd.: K. Konstantin-Hansen, Kongsh\u00f8j Alle 133 Kerteminde Danmark 5300",
    "addr:housenumber":"133",
    "addr:postcode":"5300",
    "addr:street":"Kongshoj Alle",
    "iso:country":"DK",
    "sg:address":"Fmd.: K. Konstantin-Hansen, Kongsh\u00f8j Alle 133",
    "sg:city":"Kerteminde",
    "sg:orig_category":"Kulturelle foreninger",
    "sg:phone":"+45 65 32 38 83",
    "sg:postcode":"5300",
    "sg:province":"Danmark",
    "wof:name":"Roklubbens Venner",
    "wof:placetype":"venue"
},
  "geometry": {"coordinates":[10.6600999832,55.4506492615],"type":"Point"}
}