{
  "type": "Feature",
  "properties": {
    "addr:full":"Munkholmvej 32 Holb\u00e6k Danmark 4300",
    "addr:housenumber":"32",
    "addr:postcode":"4300",
    "addr:street":"Munkholmvej",
    "iso:country":"DK",
    "sg:address":"Munkholmvej 32",
    "sg:city":"Holb\u00e6k",
    "sg:classifiers":[
        {
            "category":"Communications",
            "type":"Services"
        }
    ],
    "sg:phone":"+45 59 43 66 49",
    "sg:postcode":"4300",
    "sg:province":"Danmark",
    "sg:tags":[
        "og",
        "tv",
        "radio"
    ],
    "wof:name":"A.P. Radio",
    "wof:placetype":"venue"
},
  "geometry": {"coordinates":[76.3070983887,14.277130127],"type":"Point"}
}