{
  "type": "Feature",
  "properties": {
    "addr:full":"Hovedgaden 71 Brabrand Danmark 8220",
    "addr:housenumber":"71",
    "addr:postcode":"8220",
    "addr:street":"Hovedgaden",
    "iso:country":"DK",
    "sg:address":"Hovedgaden 71",
    "sg:city":"Brabrand",
    "sg:orig_category":"Fabrikker",
    "sg:phone":"+45 86 26 20 61",
    "sg:postcode":"8220",
    "sg:province":"Danmark",
    "wof:name":"Elektropak Consult ApS",
    "wof:placetype":"venue"
},
  "geometry": {"coordinates":[10.1006135941,56.1530914307],"type":"Point"}
}