{
  "type": "Feature",
  "properties": {
    "iso:country":"DK",
    "sg:address":"Rosenv\u00e6nget 7, Hvidbjerg",
    "sg:city":"Thyholm",
    "sg:orig_category":"Blikkenslagere",
    "sg:phone":"+45 97 87 15 07",
    "sg:postcode":"7790",
    "sg:province":"Danmark",
    "wof:name":"Thyholm Blikkenslagerforretning",
    "wof:placetype":"venue"
},
  "geometry": {"coordinates":[8.525765,56.650707],"type":"Point"}
}