{
  "type": "Feature",
  "properties": {
    "iso:country":"DK",
    "sg:address":"Sjellebrovej 10, Lime",
    "sg:city":"M\u00f8rke",
    "sg:orig_category":"Korn og foderstoffer",
    "sg:phone":"+45 86 97 41 00",
    "sg:postcode":"8544",
    "sg:province":"Danmark",
    "wof:name":"Dansk Vilomix A/S",
    "wof:placetype":"venue"
},
  "geometry": {"coordinates":[10.2458581924,56.3858413696],"type":"Point"}
}