{
  "type": "Feature",
  "properties": {
    "addr:full":"Lindevej 6 Sandved Danmark 4262",
    "addr:housenumber":"6",
    "addr:postcode":"4262",
    "addr:street":"Lindevej",
    "iso:country":"DK",
    "sg:address":"Lindevej 6",
    "sg:city":"Sandved",
    "sg:orig_category":"Murermestre",
    "sg:phone":"+45 55 45 60 27",
    "sg:postcode":"4262",
    "sg:province":"Danmark",
    "wof:name":"Jensen, Erling",
    "wof:placetype":"venue"
},
  "geometry": {"coordinates":[11.516620636,55.2600364685],"type":"Point"}
}