{
  "type": "Feature",
  "properties": {
    "addr:full":"Lillevangsparken 23 Greve Danmark 2670",
    "addr:housenumber":"23",
    "addr:postcode":"2670",
    "addr:street":"Lillevangsparken",
    "iso:country":"DK",
    "sg:address":"Lillevangsparken 23",
    "sg:city":"Greve",
    "sg:orig_category":"INGENI\u00c3\u02dcRER",
    "sg:phone":"+45 43 90 34 72",
    "sg:postcode":"2670",
    "sg:province":"Danmark",
    "wof:name":"HHB Consult ApS",
    "wof:placetype":"venue"
},
  "geometry": {"coordinates":[12.3042984009,55.5911178589],"type":"Point"}
}