{
  "type": "Feature",
  "properties": {
    "addr:full":"Fmd.: Ole Bisp, Silkehalevej 15, Boeslum Ebeltoft Danmark 8400",
    "addr:housenumber":"15",
    "addr:postcode":"8400",
    "addr:street":"Bisp Silkehalevej",
    "iso:country":"DK",
    "sg:address":"Fmd.: Ole Bisp, Silkehalevej 15, Boeslum",
    "sg:city":"Ebeltoft",
    "sg:orig_category":"Soldaterforeninger",
    "sg:phone":"+45 86 34 22 53",
    "sg:postcode":"8400",
    "sg:province":"Danmark",
    "wof:name":"V\u00e5benbr\u00f8dreforeningen for Ebeltoft og Omegn",
    "wof:placetype":"venue"
},
  "geometry": {"coordinates":[10.6778745651,56.199798584],"type":"Point"}
}