{
  "type": "Feature",
  "properties": {
    "addr:full":"Vestermarksvej 54, Kvissel Frederikshavn Danmark 9900",
    "addr:housenumber":"54",
    "addr:postcode":"9900",
    "addr:street":"Vestermarksvej;Kvissel",
    "iso:country":"DK",
    "sg:address":"Vestermarksvej 54, Kvissel",
    "sg:city":"Frederikshavn",
    "sg:orig_category":"Forsikringer",
    "sg:phone":"+45 98 48 41 48",
    "sg:postcode":"9900",
    "sg:province":"Danmark",
    "wof:name":"Plus Forsikring",
    "wof:placetype":"venue"
},
  "geometry": {"coordinates":[10.5362997055,57.4396400452],"type":"Point"}
}