{
  "type": "Feature",
  "properties": {
    "addr:full":"K\u00e6rhusvej 4 Tarm Danmark 6880",
    "addr:housenumber":"4",
    "addr:postcode":"6880",
    "addr:street":"Kaerhusvej",
    "iso:country":"DK",
    "sg:address":"K\u00e6rhusvej 4",
    "sg:city":"Tarm",
    "sg:orig_category":"Industrimontage",
    "sg:phone":"+45 75 34 34 34",
    "sg:postcode":"6880",
    "sg:province":"Danmark",
    "wof:name":"F. H. Industrimontage A/S",
    "wof:placetype":"venue"
},
  "geometry": {"coordinates":[8.7689962387,55.8486595154],"type":"Point"}
}