{
  "type": "Feature",
  "properties": {
    "addr:full":"\u00c5sbjerg 16 Give Danmark 7323",
    "addr:housenumber":"16",
    "addr:postcode":"7323",
    "addr:street":"Aasbjerg",
    "iso:country":"DK",
    "sg:address":"\u00c5sbjerg 16",
    "sg:city":"Give",
    "sg:orig_category":"Murermestre",
    "sg:phone":"+45 75 73 11 70",
    "sg:postcode":"7323",
    "sg:province":"Danmark",
    "wof:name":"JP Byg",
    "wof:placetype":"venue"
},
  "geometry": {"coordinates":[9.1770887375,55.7954711914],"type":"Point"}
}