{
  "type": "Feature",
  "properties": {
    "addr:full":"Fmd.: Jess Kongeskov, Sveasvej 20 K\u00f8ge Danmark 4600",
    "addr:housenumber":"20",
    "addr:postcode":"4600",
    "addr:street":"Sveasvej",
    "iso:country":"DK",
    "sg:address":"Fmd.: Jess Kongeskov, Sveasvej 20",
    "sg:city":"K\u00f8ge",
    "sg:orig_category":"Faglige organisationer og foreninger",
    "sg:phone":"+45 56 65 83 76",
    "sg:postcode":"4600",
    "sg:province":"Danmark",
    "wof:name":"Ledernes Hovedorganisation",
    "wof:placetype":"venue"
},
  "geometry": {"coordinates":[12.2430353165,55.4170417786],"type":"Point"}
}