{
  "type": "Feature",
  "properties": {
    "addr:full":"\u00d8rb\u00e6kvej 7 Brande Danmark 7330",
    "addr:housenumber":"7",
    "addr:postcode":"7330",
    "addr:street":"Orbaekvej",
    "iso:country":"DK",
    "sg:address":"\u00d8rb\u00e6kvej 7",
    "sg:city":"Brande",
    "sg:orig_category":"Autoreservedele",
    "sg:phone":"+45 97 18 04 38",
    "sg:postcode":"7330",
    "sg:province":"Danmark",
    "wof:name":"Brask, John",
    "wof:placetype":"venue"
},
  "geometry": {"coordinates":[9.1280345917,55.942779541],"type":"Point"}
}