{
  "type": "Feature",
  "properties": {
    "addr:full":"Vardevej 12, T\u00f8mmerby Bramming Danmark 6740",
    "addr:housenumber":"12",
    "addr:postcode":"6740",
    "addr:street":"Vardevej;Tommerby",
    "iso:country":"DK",
    "sg:address":"Vardevej 12, T\u00f8mmerby",
    "sg:city":"Bramming",
    "sg:orig_category":"Engros handel",
    "sg:phone":"+45 75 17 45 47",
    "sg:postcode":"6740",
    "sg:province":"Danmark",
    "wof:name":"M.I.J. En Gros I/S, K. J. M\u00e5tter",
    "wof:placetype":"venue"
},
  "geometry": {"coordinates":[8.6974096298,55.4655303955],"type":"Point"}
}