{
  "type": "Feature",
  "properties": {
    "addr:full":"Gr\u00e6stedvej 20, Nejlinge Helsinge Danmark 3200",
    "addr:housenumber":"20",
    "addr:postcode":"3200",
    "addr:street":"Graestedvej;Nejlinge",
    "iso:country":"DK",
    "sg:address":"Gr\u00e6stedvej 20, Nejlinge",
    "sg:city":"Helsinge",
    "sg:orig_category":"Autoreparation og -service",
    "sg:phone":"+45 48 79 52 40",
    "sg:postcode":"3200",
    "sg:province":"Danmark",
    "wof:name":"Nejlinge Autoservice",
    "wof:placetype":"venue"
},
  "geometry": {"coordinates":[12.196846962,56.0224456787],"type":"Point"}
}