{
  "type": "Feature",
  "properties": {
    "addr:full":"v/ Preben Olsson, Klostervej 10, Breum Roslev Danmark 7870",
    "addr:housenumber":"10",
    "addr:postcode":"7870",
    "addr:street":"Klostervej;Breum",
    "iso:country":"DK",
    "sg:address":"v/ Preben Olsson, Klostervej 10, Breum",
    "sg:city":"Roslev",
    "sg:orig_category":"Hobbybetonede foreninger",
    "sg:phone":"+45 97 57 64 03",
    "sg:postcode":"7870",
    "sg:province":"Danmark",
    "wof:name":"Skive M\u00f8ntforening",
    "wof:placetype":"venue"
},
  "geometry": {"coordinates":[9.0636148453,56.6878509521],"type":"Point"}
}