{
  "type": "Feature",
  "properties": {
    "addr:full":"Fmd.: Lars Ege, Klaus Berntsens Vej 14, Eskilstrup Ringe Danmark 5750",
    "addr:housenumber":"14",
    "addr:postcode":"5750",
    "addr:street":"Klaus Berntsens Vej",
    "iso:country":"DK",
    "sg:address":"Fmd.: Lars Ege, Klaus Berntsens Vej 14, Eskilstrup",
    "sg:city":"Ringe",
    "sg:orig_category":"Borger- og beboerforeninger",
    "sg:phone":"+45 62 67 24 06",
    "sg:postcode":"5750",
    "sg:province":"Danmark",
    "wof:name":"S\u00f8llinge-Hellerup Borgerforening",
    "wof:placetype":"venue"
},
  "geometry": {"coordinates":[10.4781074524,55.2356643677],"type":"Point"}
}