{
  "type": "Feature",
  "properties": {
    "iso:country":"DK",
    "sg:address":"Sp\u00e5nneb\u00e6k 5",
    "sg:city":"Holb\u00e6k",
    "sg:orig_category":"Autolakering",
    "sg:phone":"+45 59 44 00 81",
    "sg:postcode":"4300",
    "sg:province":"Danmark",
    "sg:website":"www.autolakering.dk",
    "wof:name":"Holb\u00e6k Autolakering ApS",
    "wof:placetype":"venue"
},
  "geometry": {"coordinates":[76.3070983887,14.277130127],"type":"Point"}
}