{
  "type": "Feature",
  "properties": {
    "addr:full":"N\u00f8rregade 31, 1. Hirtshals Danmark 9850",
    "addr:housenumber":"31 1",
    "addr:postcode":"9850",
    "addr:street":"Norregade",
    "iso:country":"DK",
    "sg:address":"N\u00f8rregade 31, 1.",
    "sg:city":"Hirtshals",
    "sg:orig_category":"Faglige organisationer og foreninger",
    "sg:phone":"+45 98 94 17 99",
    "sg:postcode":"9850",
    "sg:province":"Danmark",
    "wof:name":"Kvindeligt Arbejderforbund",
    "wof:placetype":"venue"
},
  "geometry": {"coordinates":[9.9592294693,57.588432312],"type":"Point"}
}