{
  "type": "Feature",
  "properties": {
    "iso:country":"DK",
    "sg:address":"Fmd.: Karsten Mehlsen, Pallesh\u00f8j 23, Lind",
    "sg:city":"Herning",
    "sg:orig_category":"Loger",
    "sg:phone":"+45 97 21 17 53",
    "sg:postcode":"7400",
    "sg:province":"Danmark",
    "sg:website":"www.jeh.dk",
    "wof:name":"Junior Chamber Herning",
    "wof:placetype":"venue"
},
  "geometry": {"coordinates":[8.9768896103,56.1374168396],"type":"Point"}
}