{
  "type": "Feature",
  "properties": {
    "iso:country":"DK",
    "sg:address":"Bymidten 2",
    "sg:city":"Skibby",
    "sg:orig_category":"Boghandlere",
    "sg:phone":"+45 47 51 25 02",
    "sg:postcode":"4050",
    "sg:province":"Danmark",
    "wof:name":"Bog & Ide, Skibby",
    "wof:placetype":"venue"
},
  "geometry": {"coordinates":[11.9585342407,55.7515449524],"type":"Point"}
}