{
  "type": "Feature",
  "properties": {
    "iso:country":"DK",
    "sg:address":"J\u00e6gerg\u00e5rdsgade 152",
    "sg:city":"\u00c5rhus C",
    "sg:classifiers":[
        {
            "category":"Communications",
            "type":"Services"
        }
    ],
    "sg:phone":"+45 87 32 11 66",
    "sg:postcode":"8000",
    "sg:province":"Danmark",
    "sg:tags":[
        "radio-",
        "og",
        "tv-stationer"
    ],
    "sg:website":"www.radio-daab.dk",
    "wof:name":"\u00c5bne B\u00e5ndv\u00e6rksted, Det",
    "wof:placetype":"venue"
},
  "geometry": {"coordinates":[4.717400074,49.7588005066],"type":"Point"}
}