{
  "type": "Feature",
  "properties": {
    "addr:full":"Lindenborgvej 146, Gevninge Roskilde Danmark 4000",
    "addr:housenumber":"146",
    "addr:postcode":"4000",
    "addr:street":"Lindenborgvej;Gevninge",
    "iso:country":"DK",
    "sg:address":"Lindenborgvej 146, Gevninge",
    "sg:city":"Roskilde",
    "sg:orig_category":"Autoreparation og -service",
    "sg:phone":"+45 46 40 24 19",
    "sg:postcode":"4000",
    "sg:province":"Danmark",
    "wof:name":"Gevninge Autov\u00e6rksted",
    "wof:placetype":"venue"
},
  "geometry": {"coordinates":[12.0909376144,55.6404838562],"type":"Point"}
}