{
  "type": "Feature",
  "properties": {
    "addr:full":"Gammel Gugvej 21 Aalborg Danmark 9000",
    "addr:housenumber":"21",
    "addr:postcode":"9000",
    "addr:street":"Gammel Gugvej",
    "iso:country":"DK",
    "sg:address":"Gammel Gugvej 21",
    "sg:city":"Aalborg",
    "sg:orig_category":"Tips- og spilleforhandlere",
    "sg:phone":"+45 98 13 57 35",
    "sg:postcode":"9000",
    "sg:province":"Danmark",
    "wof:name":"Spilleboxen",
    "wof:placetype":"venue"
},
  "geometry": {"coordinates":[9.9289751053,57.0304412842],"type":"Point"}
}