{
  "type": "Feature",
  "properties": {
    "iso:country":"DK",
    "sg:address":"Naverland 2 - 9",
    "sg:city":"Glostrup",
    "sg:classifiers":[
        {
            "category":"Professional",
            "subcategory":"Computer Services",
            "type":"Services"
        }
    ],
    "sg:phone":"+45 43 43 95 95",
    "sg:postcode":"2600",
    "sg:province":"Danmark",
    "sg:tags":[
        "edb",
        "-",
        "software"
    ],
    "wof:name":"Fics Danmark A/S",
    "wof:placetype":"venue"
},
  "geometry": {"coordinates":[12.3885526657,55.6796646118],"type":"Point"}
}