{
  "type": "Feature",
  "properties": {
    "addr:full":"Marselis Boulevard 179 \u00c5rhus C Danmark 8000",
    "addr:housenumber":"179",
    "addr:postcode":"8000",
    "addr:street":"Marselis Boulevard",
    "iso:country":"DK",
    "sg:address":"Marselis Boulevard 179",
    "sg:city":"\u00c5rhus C",
    "sg:orig_category":"Behandlingshjem",
    "sg:phone":"+45 86 14 31 44",
    "sg:postcode":"8000",
    "sg:province":"Danmark",
    "wof:name":"\u00c5haven, Behandlingshjem for Sm\u00e5b\u00f8rn",
    "wof:placetype":"venue"
},
  "geometry": {"coordinates":[-116.27327728269999,32.6635398865],"type":"Point"}
}