{
  "type": "Feature",
  "properties": {
    "addr:full":"Finlandsvej 21 Vejle Danmark 7100",
    "addr:housenumber":"21",
    "addr:postcode":"7100",
    "addr:street":"Finlandsvej",
    "iso:country":"DK",
    "sg:address":"Finlandsvej 21",
    "sg:city":"Vejle",
    "sg:orig_category":"Integrerede institutioner",
    "sg:phone":"+45 76 42 06 30",
    "sg:postcode":"7100",
    "sg:province":"Danmark",
    "wof:name":"N\u00f8rremarken integreret institution",
    "wof:placetype":"venue"
},
  "geometry": {"coordinates":[9.5619411469,55.7208061218],"type":"Point"}
}