{
  "type": "Feature",
  "properties": {
    "addr:full":"Mads Clausens Vej 12 Silkeborg Danmark 8600",
    "addr:housenumber":"12",
    "addr:postcode":"8600",
    "addr:street":"Mads Clausens Vej",
    "iso:country":"DK",
    "sg:address":"Mads Clausens Vej 12",
    "sg:city":"Silkeborg",
    "sg:orig_category":"Elektronik",
    "sg:phone":"+45 86 81 10 55",
    "sg:postcode":"8600",
    "sg:province":"Danmark",
    "wof:name":"Arepa Firenew, Aktieselskabet",
    "wof:placetype":"venue"
},
  "geometry": {"coordinates":[9.591884613,56.2007446289],"type":"Point"}
}