{
  "type": "Feature",
  "properties": {
    "addr:full":"Langemosevej 3 Ringsted Danmark 4100",
    "addr:housenumber":"3",
    "addr:postcode":"4100",
    "addr:street":"Langemosevej",
    "iso:country":"DK",
    "sg:address":"Langemosevej 3",
    "sg:city":"Ringsted",
    "sg:orig_category":"Blomsterhandlere",
    "sg:phone":"+45 57 67 07 17",
    "sg:postcode":"4100",
    "sg:province":"Danmark",
    "wof:name":"Ringsted Planteforum",
    "wof:placetype":"venue"
},
  "geometry": {"coordinates":[11.7495059967,55.4344367981],"type":"Point"}
}