{
  "type": "Feature",
  "properties": {
    "addr:full":"Vejlevej 41, Hodde Tistrup Danmark 6862",
    "addr:housenumber":"41",
    "addr:postcode":"6862",
    "addr:street":"Vejlevej",
    "iso:country":"DK",
    "sg:address":"Vejlevej 41, Hodde",
    "sg:city":"Tistrup",
    "sg:orig_category":"Forsamlingshuse",
    "sg:phone":"+45 75 29 93 38",
    "sg:postcode":"6862",
    "sg:province":"Danmark",
    "wof:name":"Hodde Forsamlingshus",
    "wof:placetype":"venue"
},
  "geometry": {"coordinates":[8.6105747223,55.7163848877],"type":"Point"}
}