{
  "type": "Feature",
  "properties": {
    "iso:country":"DK",
    "sg:address":"Fmd.: Vita Thielsen, L\u00f8vsangervej 11",
    "sg:city":"Vejle",
    "sg:orig_category":"Hobbybetonede foreninger",
    "sg:phone":"+45 75 83 25 59",
    "sg:postcode":"7100",
    "sg:province":"Danmark",
    "wof:name":"Naturhistorisk Forening, Vejle",
    "wof:placetype":"venue"
},
  "geometry": {"coordinates":[9.5368051529,55.7113952637],"type":"Point"}
}