{
  "type": "Feature",
  "properties": {
    "addr:full":"Fmd.: Harald G. Jensen, Nisset Bygade 1 Lemming Danmark 8632",
    "addr:housenumber":"1",
    "addr:postcode":"8632",
    "addr:street":"Harald G. Jensen Nisset Bygade",
    "iso:country":"DK",
    "sg:address":"Fmd.: Harald G. Jensen, Nisset Bygade 1",
    "sg:city":"Lemming",
    "sg:orig_category":"Kulturelle foreninger",
    "sg:phone":"+45 86 85 98 02",
    "sg:postcode":"8632",
    "sg:province":"Danmark",
    "wof:name":"Naturbalancehuset i Silkeborg",
    "wof:placetype":"venue"
},
  "geometry": {"coordinates":[9.4890699387,56.2441940308],"type":"Point"}
}