{
  "type": "Feature",
  "properties": {
    "addr:full":"Pr\u00e6steskoven 30 - 111 Aabenraa Danmark 6200",
    "addr:housenumber":"30",
    "addr:postcode":"111;6200",
    "addr:street":"Praesteskoven",
    "iso:country":"DK",
    "sg:address":"Pr\u00e6steskoven 30 - 111",
    "sg:city":"Aabenraa",
    "sg:orig_category":"Underholdning",
    "sg:phone":"+45 70 20 30 66",
    "sg:postcode":"6200",
    "sg:province":"Danmark",
    "sg:website":"www.stripdanmark.dk",
    "wof:name":"Stripdanmark",
    "wof:placetype":"venue"
},
  "geometry": {"coordinates":[9.4022893906,55.0555953979],"type":"Point"}
}