{
  "type": "Feature",
  "properties": {
    "addr:full":"\u00d8stergade 23 Toftlund Danmark 6520",
    "addr:housenumber":"23",
    "addr:postcode":"6520",
    "addr:street":"Ostergade",
    "iso:country":"DK",
    "sg:address":"\u00d8stergade 23",
    "sg:city":"Toftlund",
    "sg:orig_category":"Autoforhandlere",
    "sg:phone":"+45 74 83 11 22",
    "sg:postcode":"6520",
    "sg:province":"Danmark",
    "sg:website":"www.toftlund.opel.dk",
    "wof:name":"Henriksen, A/S Peter",
    "wof:placetype":"venue"
},
  "geometry": {"coordinates":[9.0683240891,55.1925163269],"type":"Point"}
}