{
  "type": "Feature",
  "properties": {
    "addr:full":"Skovagervej 6, N\u00f8rb\u00e6k F\u00e5rup Danmark 8990",
    "addr:housenumber":"6",
    "addr:postcode":"8990",
    "addr:street":"Skovagervej",
    "iso:country":"DK",
    "sg:address":"Skovagervej 6, N\u00f8rb\u00e6k",
    "sg:city":"F\u00e5rup",
    "sg:orig_category":"Forsamlingshuse",
    "sg:phone":"+45 86 45 24 75",
    "sg:postcode":"8990",
    "sg:province":"Danmark",
    "wof:name":"N\u00f8rb\u00e6k Forsamlingshus",
    "wof:placetype":"venue"
},
  "geometry": {"coordinates":[-93.1630935669,32.8507347107],"type":"Point"}
}