{
  "type": "Feature",
  "properties": {
    "addr:full":"Fmd.: Inger Holm, Parkalle 13, Frederiks Karup Danmark 7470",
    "addr:housenumber":"13",
    "addr:postcode":"7470",
    "addr:street":"Holm Parkalle;Frederiks Karup Danmark",
    "iso:country":"DK",
    "sg:address":"Fmd.: Inger Holm, Parkalle 13, Frederiks",
    "sg:city":"Karup",
    "sg:orig_category":"\u00c3\u2020ldreorganisationer og klubber",
    "sg:phone":"+45 86 66 10 12",
    "sg:postcode":"7470",
    "sg:province":"Danmark",
    "wof:name":"Frederiks Pensionistforening",
    "wof:placetype":"venue"
},
  "geometry": {"coordinates":[9.2525548935,56.3398017883],"type":"Point"}
}