{
  "type": "Feature",
  "properties": {
    "addr:full":"Strandvejen 72 Vejle \u00d8 Danmark 7120",
    "addr:housenumber":"72",
    "addr:postcode":"7120",
    "addr:street":"Strandvejen",
    "iso:country":"DK",
    "sg:address":"Strandvejen 72",
    "sg:city":"Vejle \u00d8",
    "sg:orig_category":"Arkitekter",
    "sg:phone":"+45 75 81 55 66",
    "sg:postcode":"7120",
    "sg:province":"Danmark",
    "wof:name":"Pedersen Arkitektfirmaet, J. Malling ApS",
    "wof:placetype":"venue"
},
  "geometry": {"coordinates":[9.6065807343,55.7089767456],"type":"Point"}
}