{
  "type": "Feature",
  "properties": {
    "addr:full":"Falkevej 72, Ebdrup Mark Kolind Danmark 8560",
    "addr:housenumber":"72",
    "addr:postcode":"8560",
    "addr:street":"Falkevej;Ebdrup Mark",
    "iso:country":"DK",
    "sg:address":"Falkevej 72, Ebdrup Mark",
    "sg:city":"Kolind",
    "sg:orig_category":"Revisorer",
    "sg:phone":"+45 86 34 11 50",
    "sg:postcode":"8560",
    "sg:province":"Danmark",
    "wof:name":"AMG Revision & Bogf\u00f8ring",
    "wof:placetype":"venue"
},
  "geometry": {"coordinates":[10.5873975754,56.3618812561],"type":"Point"}
}