{
  "type": "Feature",
  "properties": {
    "iso:country":"DK",
    "sg:address":"Fuglebjergvej 4, Nr. Herlev",
    "sg:city":"Hiller\u00f8d",
    "sg:orig_category":"Stutterier",
    "sg:phone":"+45 48 24 48 52",
    "sg:postcode":"3400",
    "sg:province":"Danmark",
    "wof:name":"Stutteri Kirseb\u00e6rg\u00e5rden",
    "wof:placetype":"venue"
},
  "geometry": {"coordinates":[12.3056097031,55.9288215637],"type":"Point"}
}