{
  "type": "Feature",
  "properties": {
    "iso:country":"DK",
    "sg:address":"Niels Juels Vej 25",
    "sg:city":"Frederikshavn",
    "sg:orig_category":"Genbrugscentre",
    "sg:postcode":"9900",
    "sg:province":"Danmark",
    "wof:name":"Genbrugspladsen",
    "wof:placetype":"venue"
},
  "geometry": {"coordinates":[10.5185260773,57.4480171204],"type":"Point"}
}