{
  "type": "Feature",
  "properties": {
    "addr:full":"Vestergade 37 R\u00f8dekro Danmark 6230",
    "addr:housenumber":"37",
    "addr:postcode":"6230",
    "addr:street":"Vestergade",
    "iso:country":"DK",
    "sg:address":"Vestergade 37",
    "sg:city":"R\u00f8dekro",
    "sg:orig_category":"Fodterapeuter",
    "sg:phone":"+45 74 66 19 48",
    "sg:postcode":"6230",
    "sg:province":"Danmark",
    "wof:name":"Adolpsen, Hanne",
    "wof:placetype":"venue"
},
  "geometry": {"coordinates":[9.5455904007,56.1682090759],"type":"Point"}
}