{
  "type": "Feature",
  "properties": {
    "addr:full":"Langelinie 48 Stege Danmark 4780",
    "addr:housenumber":"48",
    "addr:postcode":"4780",
    "addr:street":"Langelinie",
    "iso:country":"DK",
    "sg:address":"Langelinie 48",
    "sg:city":"Stege",
    "sg:orig_category":"HOTELS: OG MOTELLER",
    "sg:phone":"+45 55 81 54 54",
    "sg:postcode":"4780",
    "sg:province":"Danmark",
    "wof:name":"Ellens Cabaret",
    "wof:placetype":"venue"
},
  "geometry": {"coordinates":[12.2798671722,54.98985672],"type":"Point"}
}