{
  "type": "Feature",
  "properties": {
    "addr:full":"Borupvej 76 Hornslet Danmark 8543",
    "addr:housenumber":"76",
    "addr:postcode":"8543",
    "addr:street":"Borupvej",
    "iso:country":"DK",
    "sg:address":"Borupvej 76",
    "sg:city":"Hornslet",
    "sg:orig_category":"Dyreklinikker og -hospitaler",
    "sg:phone":"+45 86 99 61 00",
    "sg:postcode":"8543",
    "sg:province":"Danmark",
    "wof:name":"Hornslet Dyreklinik",
    "wof:placetype":"venue"
},
  "geometry": {"coordinates":[10.2948408127,56.3286590576],"type":"Point"}
}