{
  "type": "Feature",
  "properties": {
    "iso:country":"DK",
    "sg:address":"Storegade 19",
    "sg:city":"Lunderskov",
    "sg:orig_category":"Genbrugsbutikker",
    "sg:phone":"+45 75 58 67 27",
    "sg:postcode":"6640",
    "sg:province":"Danmark",
    "wof:name":"R\u00f8de Kors Genbrugsbutik",
    "wof:placetype":"venue"
},
  "geometry": {"coordinates":[9.3004274368,55.4794120789],"type":"Point"}
}