{
  "type": "Feature",
  "properties": {
    "addr:full":"Marieh\u00f8nevej 7 Aalborg Danmark 9000",
    "addr:housenumber":"7",
    "addr:postcode":"9000",
    "addr:street":"Mariehonevej",
    "iso:country":"DK",
    "sg:address":"Marieh\u00f8nevej 7",
    "sg:city":"Aalborg",
    "sg:orig_category":"Flytteforretninger",
    "sg:phone":"+45 98 34 11 45",
    "sg:postcode":"9000",
    "sg:province":"Danmark",
    "wof:name":"Leo's Flytteservice",
    "wof:placetype":"venue"
},
  "geometry": {"coordinates":[9.8930606842,57.0479125977],"type":"Point"}
}