{
  "type": "Feature",
  "properties": {
    "addr:full":"Valeursvej 11-13 Herning Danmark 7400",
    "addr:postcode":"11-13;7400",
    "addr:street":"Valeursvej",
    "iso:country":"DK",
    "sg:address":"Valeursvej 11-13",
    "sg:city":"Herning",
    "sg:orig_category":"Daginstitution for voksne",
    "sg:phone":"+45 97 12 58 44",
    "sg:postcode":"7400",
    "sg:province":"Danmark",
    "sg:website":"www.reva-herning.dk",
    "wof:name":"Reva-Herning",
    "wof:placetype":"venue"
},
  "geometry": {"coordinates":[8.9925985336,56.1464004517],"type":"Point"}
}