{
  "type": "Feature",
  "properties": {
    "addr:full":"Tyrolsgade 16 K\u00f8benhavn S Danmark 2300",
    "addr:housenumber":"16",
    "addr:postcode":"2300",
    "addr:street":"Tyrolsgade;S Danmark",
    "iso:country":"DK",
    "sg:address":"Tyrolsgade 16",
    "sg:city":"K\u00f8benhavn S",
    "sg:orig_category":"Autoreparation og -service",
    "sg:phone":"+45 32 58 72 73",
    "sg:postcode":"2300",
    "sg:province":"Danmark",
    "wof:name":"I. M. Autoskadecenter ApS",
    "wof:placetype":"venue"
},
  "geometry": {"coordinates":[-80.0381698608,40.397403717],"type":"Point"}
}