{
  "type": "Feature",
  "properties": {
    "addr:full":"Kanadavej 8 K\u00f8benhavn S Danmark 2300",
    "addr:housenumber":"8",
    "addr:postcode":"2300",
    "addr:street":"Kanadavej;S Danmark",
    "iso:country":"DK",
    "sg:address":"Kanadavej 8",
    "sg:city":"K\u00f8benhavn S",
    "sg:orig_category":"Fugning",
    "sg:phone":"+45 32 52 60 60",
    "sg:postcode":"2300",
    "sg:province":"Danmark",
    "sg:website":"www.kims-fugeservice.dk",
    "wof:name":"Kim's Fugeservice",
    "wof:placetype":"venue"
},
  "geometry": {"coordinates":[-78.1299133301,36.7267417908],"type":"Point"}
}