{
  "type": "Feature",
  "properties": {
    "iso:country":"DK",
    "sg:address":"Borgergade 57",
    "sg:city":"Silkeborg",
    "sg:orig_category":"Bodegaer",
    "sg:phone":"+45 86 81 39 60",
    "sg:postcode":"8600",
    "sg:province":"Danmark",
    "wof:name":"Rottehullet",
    "wof:placetype":"venue"
},
  "geometry": {"coordinates":[9.5505256653,56.1797485352],"type":"Point"}
}