{
  "type": "Feature",
  "properties": {
    "addr:full":"Fmd.: Grethe Bitsch, Uls\u00f8evej 1, M\u00e5bjerg Holstebro Danmark 7500",
    "addr:housenumber":"1",
    "addr:postcode":"7500",
    "addr:street":"Ulsoevej",
    "iso:country":"DK",
    "sg:address":"Fmd.: Grethe Bitsch, Uls\u00f8evej 1, M\u00e5bjerg",
    "sg:city":"Holstebro",
    "sg:orig_category":"Kirkelige foreninger",
    "sg:phone":"+45 97 42 08 41",
    "sg:postcode":"7500",
    "sg:province":"Danmark",
    "wof:name":"M\u00e5bjerg Kvindekreds DMS",
    "wof:placetype":"venue"
},
  "geometry": {"coordinates":[8.6202583313,56.3625221252],"type":"Point"}
}