{
  "type": "Feature",
  "properties": {
    "addr:full":"Prags Boulevard 80 K\u00f8benhavn S Danmark 2300",
    "addr:housenumber":"80",
    "addr:postcode":"2300",
    "addr:street":"Prags Boulevard;Kobenhavn S Danmark",
    "iso:country":"DK",
    "sg:address":"Prags Boulevard 80",
    "sg:city":"K\u00f8benhavn S",
    "sg:orig_category":"Telekommunikation",
    "sg:phone":"+45 82 33 70 00",
    "sg:postcode":"2300",
    "sg:province":"Danmark",
    "sg:website":"www.orangedk.com",
    "wof:name":"Orange A/S",
    "wof:placetype":"venue"
},
  "geometry": {"coordinates":[12.1321201324,46.7195549011],"type":"Point"}
}