{
  "type": "Feature",
  "properties": {
    "addr:full":"Ved Gr\u00e6nsen 47 Frederiksberg Danmark 2000",
    "addr:housenumber":"47",
    "addr:postcode":"2000",
    "addr:street":"Ved Graensen",
    "iso:country":"DK",
    "sg:address":"Ved Gr\u00e6nsen 47",
    "sg:city":"Frederiksberg",
    "sg:orig_category":"Alexanderteknik",
    "sg:phone":"+45 38 71 28 71",
    "sg:postcode":"2000",
    "sg:province":"Danmark",
    "wof:name":"Ingerslev, Lisbeth Feldmann",
    "wof:placetype":"venue"
},
  "geometry": {"coordinates":[12.4962873459,55.6833572388],"type":"Point"}
}