{
  "type": "Feature",
  "properties": {
    "addr:full":"Jacobys Alle 16 Frederiksberg Danmark 1806",
    "addr:housenumber":"16",
    "addr:postcode":"1806",
    "addr:street":"Jacobys Alle",
    "iso:country":"DK",
    "sg:address":"Jacobys Alle 16",
    "sg:city":"Frederiksberg",
    "sg:orig_category":"Malermestre",
    "sg:phone":"+45 33 22 72 34",
    "sg:postcode":"1806",
    "sg:province":"Danmark",
    "wof:name":"Kahrs, Petter",
    "wof:placetype":"venue"
},
  "geometry": {"coordinates":[12.534453392,55.6719894409],"type":"Point"}
}