{
  "type": "Feature",
  "properties": {
    "addr:full":"Vigersdal Fmd.: Kai T. Madsen, Roskildevej 302 Ringsted Danmark 4100",
    "addr:housenumber":"302",
    "addr:postcode":"4100",
    "addr:street":"Roskildevej",
    "iso:country":"DK",
    "sg:address":"Vigersdal Fmd.: Kai T. Madsen, Roskildevej 302",
    "sg:city":"Ringsted",
    "sg:orig_category":"Erhvervs- og brancheforeninger",
    "sg:phone":"+45 57 52 83 44",
    "sg:postcode":"4100",
    "sg:province":"Danmark",
    "wof:name":"Midtsj\u00e6llands Fr\u00f8avlerforening",
    "wof:placetype":"venue"
},
  "geometry": {"coordinates":[11.7875862122,55.4458961487],"type":"Point"}
}