{
  "type": "Feature",
  "properties": {
    "addr:full":"Humleg\u00e5rdsb\u00e6k 4 Haderslev Danmark 6100",
    "addr:housenumber":"4",
    "addr:postcode":"6100",
    "addr:street":"Humlegaardsbaek",
    "iso:country":"DK",
    "sg:address":"Humleg\u00e5rdsb\u00e6k 4",
    "sg:city":"Haderslev",
    "sg:orig_category":"Zoneterapeuter",
    "sg:phone":"+45 74 53 49 47",
    "sg:postcode":"6100",
    "sg:province":"Danmark",
    "wof:name":"Klinik For Akupunktur & Zoneterapi",
    "wof:placetype":"venue"
},
  "geometry": {"coordinates":[9.4879703522,55.2505493164],"type":"Point"}
}