{
  "type": "Feature",
  "properties": {
    "addr:full":"Dokvej 2 Kolding Danmark 6000",
    "addr:housenumber":"2",
    "addr:postcode":"6000",
    "addr:street":"Dokvej",
    "iso:country":"DK",
    "sg:address":"Dokvej 2",
    "sg:city":"Kolding",
    "sg:orig_category":"Autoreparation og -service",
    "sg:phone":"+45 75 53 90 90",
    "sg:postcode":"6000",
    "sg:province":"Danmark",
    "wof:name":"M\u00f8rks Autoservice",
    "wof:placetype":"venue"
},
  "geometry": {"coordinates":[9.4934263229,55.4936485291],"type":"Point"}
}