{
  "type": "Feature",
  "properties": {
    "iso:country":"DK",
    "sg:address":"Brede Bygade 1",
    "sg:city":"Bredebro",
    "sg:orig_category":"Skomagere",
    "sg:phone":"+45 74 71 00 31",
    "sg:postcode":"6261",
    "sg:province":"Danmark",
    "wof:name":"Eriks Skomageri",
    "wof:placetype":"venue"
},
  "geometry": {"coordinates":[8.8234586716,55.0586280823],"type":"Point"}
}