{
  "type": "Feature",
  "properties": {
    "iso:country":"DK",
    "sg:address":"Brovejen 10-14",
    "sg:city":"Maribo",
    "sg:orig_category":"Dag- og distriktsblade",
    "sg:phone":"+45 54 76 00 44",
    "sg:postcode":"4930",
    "sg:province":"Danmark",
    "wof:name":"Lollands Posten",
    "wof:placetype":"venue"
},
  "geometry": {"coordinates":[11.4973402023,54.7764015198],"type":"Point"}
}