{
  "type": "Feature",
  "properties": {
    "addr:full":"Magleh\u00f8jvej 58 Nakskov Danmark 4900",
    "addr:housenumber":"58",
    "addr:postcode":"4900",
    "addr:street":"Maglehojvej",
    "iso:country":"DK",
    "sg:address":"Magleh\u00f8jvej 58",
    "sg:city":"Nakskov",
    "sg:orig_category":"Lufthavn",
    "sg:phone":"+45 54 95 23 07",
    "sg:postcode":"4900",
    "sg:province":"Danmark",
    "wof:name":"Flyvepladsen",
    "wof:placetype":"venue"
},
  "geometry": {"coordinates":[11.1384401321,54.820438385],"type":"Point"}
}