{
  "type": "Feature",
  "properties": {
    "iso:country":"DK",
    "sg:address":"Bjerrevej 344, Bjerre",
    "sg:city":"Hornsyld",
    "sg:orig_category":"Gaveartikler",
    "sg:postcode":"8783",
    "sg:province":"Danmark",
    "sg:website":"www.engro.dk",
    "wof:name":"Upstairs",
    "wof:placetype":"venue"
},
  "geometry": {"coordinates":[9.8611288071,55.7560806274],"type":"Point"}
}