{
  "type": "Feature",
  "properties": {
    "addr:full":"R\u00f8stofte Mark 7 Mern Danmark 4735",
    "addr:housenumber":"7",
    "addr:postcode":"4735",
    "addr:street":"Mark",
    "iso:country":"DK",
    "sg:address":"R\u00f8stofte Mark 7",
    "sg:city":"Mern",
    "sg:orig_category":"Malermestre",
    "sg:phone":"+45 55 98 40 91",
    "sg:postcode":"4735",
    "sg:province":"Danmark",
    "wof:name":"Hansen, Carl-Emil",
    "wof:placetype":"venue"
},
  "geometry": {"coordinates":[12.0018138885,55.0476493835],"type":"Point"}
}