{
  "type": "Feature",
  "properties": {
    "iso:country":"DK",
    "sg:address":"Valby Langgade 231",
    "sg:city":"Valby",
    "sg:orig_category":"Gulvbehandling",
    "sg:phone":"+45 36 46 00 68",
    "sg:postcode":"2500",
    "sg:province":"Danmark",
    "wof:name":"Valby Gulve",
    "wof:placetype":"venue"
},
  "geometry": {"coordinates":[12.4856290817,55.6712532043],"type":"Point"}
}