{
  "type": "Feature",
  "properties": {
    "iso:country":"DK",
    "sg:address":"Duemosevej 8",
    "sg:city":"Helsinge",
    "sg:orig_category":"Haveservice",
    "sg:phone":"+45 48 79 11 36",
    "sg:postcode":"3200",
    "sg:province":"Danmark",
    "wof:name":"Egedal Hus- og Haveservice",
    "wof:placetype":"venue"
},
  "geometry": {"coordinates":[12.2502393723,56.009727478],"type":"Point"}
}