{
  "type": "Feature",
  "properties": {
    "iso:country":"DK",
    "sg:address":"Finsensvej 37",
    "sg:city":"Frederiksberg",
    "sg:orig_category":"Snedkermestre",
    "sg:phone":"+45 38 86 60 92",
    "sg:postcode":"2000",
    "sg:province":"Danmark",
    "wof:name":"Snedkerfirmaet Andersen & Nielsen ApS",
    "wof:placetype":"venue"
},
  "geometry": {"coordinates":[12.5141077042,55.6814956665],"type":"Point"}
}