{
  "type": "Feature",
  "properties": {
    "addr:full":"Bogyden 26, Lillemose Assens Danmark 5610",
    "addr:housenumber":"26",
    "addr:postcode":"5610",
    "addr:street":"Bogyden;Lillemose",
    "iso:country":"DK",
    "sg:address":"Bogyden 26, Lillemose",
    "sg:city":"Assens",
    "sg:orig_category":"Maskinstationer",
    "sg:phone":"+45 64 79 14 35",
    "sg:postcode":"5610",
    "sg:province":"Danmark",
    "wof:name":"Andersen Maskinstation, Mogens",
    "wof:placetype":"venue"
},
  "geometry": {"coordinates":[9.8998937607,55.2702522278],"type":"Point"}
}