{
  "type": "Feature",
  "properties": {
    "addr:full":"Engdraget 7 Frederikssund Danmark 3600",
    "addr:housenumber":"7",
    "addr:postcode":"3600",
    "addr:street":"Engdraget",
    "iso:country":"DK",
    "sg:address":"Engdraget 7",
    "sg:city":"Frederikssund",
    "sg:orig_category":"Hundesaloner",
    "sg:phone":"+45 47 31 59 40",
    "sg:postcode":"3600",
    "sg:province":"Danmark",
    "wof:name":"Tina's Hundesalon",
    "wof:placetype":"venue"
},
  "geometry": {"coordinates":[12.059214592,55.8512306213],"type":"Point"}
}