{
  "type": "Feature",
  "properties": {
    "addr:full":"\u00d8stergade 25 Herning Danmark 7400",
    "addr:housenumber":"25",
    "addr:postcode":"7400",
    "addr:street":"Ostergade",
    "iso:country":"DK",
    "sg:address":"\u00d8stergade 25",
    "sg:city":"Herning",
    "sg:classifiers":[
        {
            "category":"Food & Beverages",
            "subcategory":"Liquor & Beverages",
            "type":"Retail Goods"
        }
    ],
    "sg:phone":"+45 97 12 12 50",
    "sg:postcode":"7400",
    "sg:province":"Danmark",
    "sg:tags":[
        "vin"
    ],
    "wof:name":"Skjold Burne Vinhandel",
    "wof:placetype":"venue"
},
  "geometry": {"coordinates":[8.9793291092,56.1359481812],"type":"Point"}
}