{
  "type": "Feature",
  "properties": {
    "iso:country":"DK",
    "sg:address":"Torvegade 14",
    "sg:city":"Faaborg",
    "sg:orig_category":"Sportsartikler",
    "sg:phone":"+45 62 61 38 39",
    "sg:postcode":"5600",
    "sg:province":"Danmark",
    "wof:name":"Sportsmaster",
    "wof:placetype":"venue"
},
  "geometry": {"coordinates":[10.2412700653,55.0954742432],"type":"Point"}
}