{
  "type": "Feature",
  "properties": {
    "addr:full":"Gl. Landevej 16, Obbekj\u00e6r Ribe Danmark 6760",
    "addr:housenumber":"16",
    "addr:postcode":"6760",
    "addr:street":"Gl. Landevej",
    "iso:country":"DK",
    "sg:address":"Gl. Landevej 16, Obbekj\u00e6r",
    "sg:city":"Ribe",
    "sg:orig_category":"Forsamlingshuse",
    "sg:phone":"+45 75 44 13 70",
    "sg:postcode":"6760",
    "sg:province":"Danmark",
    "wof:name":"Obbek\u00e6r Forsamlingshus",
    "wof:placetype":"venue"
},
  "geometry": {"coordinates":[8.7656240463,55.3297042847],"type":"Point"}
}