{
  "type": "Feature",
  "properties": {
    "addr:full":"Saltrup Mark 11 Gr\u00e6sted Danmark 3230",
    "addr:housenumber":"11",
    "addr:postcode":"3230",
    "addr:street":"Saltrup Mark",
    "iso:country":"DK",
    "sg:address":"Saltrup Mark 11",
    "sg:city":"Gr\u00e6sted",
    "sg:orig_category":"Maskinstationer",
    "sg:phone":"+45 48 39 02 56",
    "sg:postcode":"3230",
    "sg:province":"Danmark",
    "wof:name":"Eriksen, Ole",
    "wof:placetype":"venue"
},
  "geometry": {"coordinates":[12.3371362686,56.0662765503],"type":"Point"}
}