{
  "type": "Feature",
  "properties": {
    "addr:full":"Fmd.: Birgit Christiansen, Sl\u00e5envangen 9, Lammefjord Grevinge Danmark 4571",
    "addr:housenumber":"9",
    "addr:postcode":"4571",
    "addr:street":"Slaaenvangen",
    "iso:country":"DK",
    "sg:address":"Fmd.: Birgit Christiansen, Sl\u00e5envangen 9, Lammefjord",
    "sg:city":"Grevinge",
    "sg:orig_category":"Grundejerforeninger",
    "sg:phone":"+45 59 65 98 55",
    "sg:postcode":"4571",
    "sg:province":"Danmark",
    "wof:name":"Lundsbogaard Grundejerforening",
    "wof:placetype":"venue"
},
  "geometry": {"coordinates":[11.5593652725,55.7873153687],"type":"Point"}
}