{
  "type": "Feature",
  "properties": {
    "addr:full":"Leder: Christian Odg\u00e5rd, Vildrosen 3 Arden Danmark 9510",
    "addr:housenumber":"3",
    "addr:postcode":"9510",
    "addr:street":"Vildrosen",
    "iso:country":"DK",
    "sg:address":"Leder: Christian Odg\u00e5rd, Vildrosen 3",
    "sg:city":"Arden",
    "sg:orig_category":"\u00c3\u02dcvrig fritidsundervisning",
    "sg:phone":"+45 98 56 17 28",
    "sg:postcode":"9510",
    "sg:province":"Danmark",
    "wof:name":"Dansk R\u00f8de Kors",
    "wof:placetype":"venue"
},
  "geometry": {"coordinates":[9.8580989838,56.7683296204],"type":"Point"}
}