{
  "type": "Feature",
  "properties": {
    "iso:country":"DK",
    "sg:address":"Uvelse Byvej 1, Uvelse",
    "sg:city":"Slangerup",
    "sg:orig_category":"Brugsforeninger",
    "sg:phone":"+45 48 27 80 20",
    "sg:postcode":"3550",
    "sg:province":"Danmark",
    "wof:name":"Brugsen i Uvelse",
    "wof:placetype":"venue"
},
  "geometry": {"coordinates":[12.1717596054,55.8460769653],"type":"Point"}
}