{
  "type": "Feature",
  "properties": {
    "addr:full":"Birkemosevej 95, Eltang Kolding Danmark 6000",
    "addr:housenumber":"95",
    "addr:postcode":"6000",
    "addr:street":"Birkemosevej;Eltang",
    "iso:country":"DK",
    "sg:address":"Birkemosevej 95, Eltang",
    "sg:city":"Kolding",
    "sg:orig_category":"Arbejderbeskyttelse",
    "sg:phone":"+45 76 32 74 00",
    "sg:postcode":"6000",
    "sg:province":"Danmark",
    "wof:name":"Contextus",
    "wof:placetype":"venue"
},
  "geometry": {"coordinates":[9.4733953476,55.4863586426],"type":"Point"}
}