{
  "type": "Feature",
  "properties": {
    "addr:full":"Danmarksgade 29 -31 Fredericia Danmark 7000",
    "addr:housenumber":"29 -31",
    "addr:postcode":"7000",
    "addr:street":"Danmarksgade",
    "iso:country":"DK",
    "sg:address":"Danmarksgade 29 -31",
    "sg:city":"Fredericia",
    "sg:orig_category":"Cykler",
    "sg:phone":"+45 75 93 24 47",
    "sg:postcode":"7000",
    "sg:province":"Danmark",
    "sg:website":"www.bjerggeden.dk",
    "wof:name":"Bjerggeden & Byrotten",
    "wof:placetype":"venue"
},
  "geometry": {"coordinates":[9.7586641312,55.567237854],"type":"Point"}
}