{
  "type": "Feature",
  "properties": {
    "addr:full":"Kildemosevej 5, Illeb\u00f8lle Rudk\u00f8bing Danmark 5900",
    "addr:housenumber":"5",
    "addr:postcode":"5900",
    "addr:street":"Kildemosevej",
    "iso:country":"DK",
    "sg:address":"Kildemosevej 5, Illeb\u00f8lle",
    "sg:city":"Rudk\u00f8bing",
    "sg:orig_category":"Murermestre",
    "sg:phone":"+45 62 57 18 61",
    "sg:postcode":"5900",
    "sg:province":"Danmark",
    "wof:name":"Hougaard, Jan",
    "wof:placetype":"venue"
},
  "geometry": {"coordinates":[-114.0767440796,46.4432487488],"type":"Point"}
}