{
  "type": "Feature",
  "properties": {
    "addr:full":"Frederikssundsvej 5 K\u00f8benhavn NV Danmark 2400",
    "addr:housenumber":"5",
    "addr:postcode":"2400",
    "addr:street":"Frederikssundsvej",
    "iso:country":"DK",
    "sg:address":"Frederikssundsvej 5",
    "sg:city":"K\u00f8benhavn NV",
    "sg:orig_category":"Motionscentre",
    "sg:phone":"+45 35 81 22 83",
    "sg:postcode":"2400",
    "sg:province":"Danmark",
    "wof:name":"HardWork Studio",
    "wof:placetype":"venue"
},
  "geometry": {"coordinates":[-117.02272033689999,38.5024604797],"type":"Point"}
}