{
  "type": "Feature",
  "properties": {
    "addr:full":"\u00c5lykkecentret 5 Odder Danmark 8300",
    "addr:housenumber":"5",
    "addr:postcode":"8300",
    "addr:street":"Aalykkecentret",
    "iso:country":"DK",
    "sg:address":"\u00c5lykkecentret 5",
    "sg:city":"Odder",
    "sg:orig_category":"Lokalcentre",
    "sg:phone":"+45 87 80 35 21",
    "sg:postcode":"8300",
    "sg:province":"Danmark",
    "wof:name":"Omr\u00e5de Nord",
    "wof:placetype":"venue"
},
  "geometry": {"coordinates":[10.1510448456,55.9741096497],"type":"Point"}
}