{
  "type": "Feature",
  "properties": {
    "iso:country":"DK",
    "sg:address":"Tr\u00e6lborgvadvej 3, Borup",
    "sg:city":"Nibe",
    "sg:orig_category":"Hobbyartikler",
    "sg:phone":"+45 98 66 92 94",
    "sg:postcode":"9240",
    "sg:province":"Danmark",
    "wof:name":"B-Design",
    "wof:placetype":"venue"
},
  "geometry": {"coordinates":[9.6393280029,56.982421875],"type":"Point"}
}