{
  "type": "Feature",
  "properties": {
    "addr:full":"Gl. Landevej 109 Herning Danmark 7400",
    "addr:housenumber":"109",
    "addr:postcode":"7400",
    "addr:street":"Gl. Landevej",
    "iso:country":"DK",
    "sg:address":"Gl. Landevej 109",
    "sg:city":"Herning",
    "sg:orig_category":"Malermestre",
    "sg:phone":"+45 97 18 48 72",
    "sg:postcode":"7400",
    "sg:province":"Danmark",
    "wof:name":"Larsen, J\u00f8rgen",
    "wof:placetype":"venue"
},
  "geometry": {"coordinates":[8.9673252106,56.1407356262],"type":"Point"}
}