{
  "type": "Feature",
  "properties": {
    "addr:full":"Mosel\u00f8kkevej 4 Allinge Danmark 3770",
    "addr:housenumber":"4",
    "addr:postcode":"3770",
    "addr:street":"Moselokkevej",
    "iso:country":"DK",
    "sg:address":"Mosel\u00f8kkevej 4",
    "sg:city":"Allinge",
    "sg:orig_category":"Museer",
    "sg:phone":"+45 56 48 04 68",
    "sg:postcode":"3770",
    "sg:province":"Danmark",
    "wof:name":"Mosel\u00f8kken Stenbrudsmuseum",
    "wof:placetype":"venue"
},
  "geometry": {"coordinates":[14.7780513763,55.2730064392],"type":"Point"}
}