{
  "type": "Feature",
  "properties": {
    "iso:country":"DK",
    "sg:address":"Skovdongvej 1",
    "sg:city":"Sk\u00e5rup",
    "sg:orig_category":"Malermestre",
    "sg:phone":"+45 62 23 23 28",
    "sg:postcode":"5881",
    "sg:province":"Danmark",
    "sg:website":"www.tvedbyg.dk",
    "wof:name":"Tved-Byg A/S",
    "wof:placetype":"venue"
},
  "geometry": {"coordinates":[10.6582307816,55.0951004028],"type":"Point"}
}