{
  "type": "Feature",
  "properties": {
    "iso:country":"DK",
    "sg:address":"Brommevej 10, R\u00f8",
    "sg:city":"Gudhjem",
    "sg:classifiers":[
        {
            "category":"Taxi",
            "type":"Transportation"
        }
    ],
    "sg:phone":"+45 56 48 44 12",
    "sg:postcode":"3760",
    "sg:province":"Danmark",
    "wof:name":"Gudhjem Taxi",
    "wof:placetype":"venue"
},
  "geometry": {"coordinates":[15.1870470047,55.3205566406],"type":"Point"}
}