{
  "type": "Feature",
  "properties": {
    "addr:full":"Boulevarden 5 Odder Danmark 8300",
    "addr:housenumber":"5",
    "addr:postcode":"8300",
    "addr:street":"Boulevarden",
    "iso:country":"DK",
    "sg:address":"Boulevarden 5",
    "sg:city":"Odder",
    "sg:orig_category":"Zoneterapeuter",
    "sg:phone":"+45 86 54 52 42",
    "sg:postcode":"8300",
    "sg:province":"Danmark",
    "sg:website":"www.home12.inet.tele.dk/z_klinik",
    "wof:name":"Zoneterapi-klinikken",
    "wof:placetype":"venue"
},
  "geometry": {"coordinates":[10.1473445892,55.9706459045],"type":"Point"}
}