{
  "type": "Feature",
  "properties": {
    "iso:country":"DK",
    "sg:address":"Petersmindevej 11",
    "sg:city":"Fuglebjerg",
    "sg:orig_category":"Skovbrug",
    "sg:phone":"+45 55 45 34 50",
    "sg:postcode":"4250",
    "sg:province":"Danmark",
    "wof:name":"F\u00f8rslevg\u00e5rd Skovdistrikt",
    "wof:placetype":"venue"
},
  "geometry": {"coordinates":[11.5991010666,55.2991676331],"type":"Point"}
}