{
  "type": "Feature",
  "properties": {
    "addr:full":"Havk\u00e6rvej 83, Tilst Tilst Danmark 8381",
    "addr:housenumber":"83",
    "addr:postcode":"8381",
    "addr:street":"Havkaervej",
    "iso:country":"DK",
    "sg:address":"Havk\u00e6rvej 83, Tilst",
    "sg:city":"Tilst",
    "sg:classifiers":[
        {
            "category":"Harbor",
            "type":"Transportation"
        }
    ],
    "sg:phone":"+45 86 24 85 00",
    "sg:postcode":"8381",
    "sg:province":"Danmark",
    "sg:tags":[
        "shipping"
    ],
    "wof:name":"Svedan Transport & Spedition A/S",
    "wof:placetype":"venue"
},
  "geometry": {"coordinates":[10.1078147888,56.1882019043],"type":"Point"}
}