{
  "type": "Feature",
  "properties": {
    "addr:full":"Vissevej 5 B Aalborg S\u00d8 Danmark 9210",
    "addr:housenumber":"5 b",
    "addr:postcode":"9210",
    "addr:street":"Vissevej",
    "iso:country":"DK",
    "sg:address":"Vissevej 5 B",
    "sg:city":"Aalborg S\u00d8",
    "sg:orig_category":"Autoforhandlere",
    "sg:phone":"+45 98 14 75 66",
    "sg:postcode":"9210",
    "sg:province":"Danmark",
    "wof:name":"Auto-M\u00e6gleren",
    "wof:placetype":"venue"
},
  "geometry": {"coordinates":[9.9239120483,57.0052108765],"type":"Point"}
}