{
  "type": "Feature",
  "properties": {
    "addr:full":"Erhvervenes Hus, Skottenborg 12 Viborg Danmark 8800",
    "addr:housenumber":"12",
    "addr:postcode":"8800",
    "addr:street":"Skottenborg",
    "iso:country":"DK",
    "sg:address":"Erhvervenes Hus, Skottenborg 12",
    "sg:city":"Viborg",
    "sg:orig_category":"Faglige organisationer og -foreninger",
    "sg:phone":"+45 86 62 42 22",
    "sg:postcode":"8800",
    "sg:province":"Danmark",
    "sg:website":"www.danskarbejde.dk",
    "wof:name":"Dansk Arbejde, Landsforeningen",
    "wof:placetype":"venue"
},
  "geometry": {"coordinates":[9.4071502686,56.452671051],"type":"Point"}
}