{
  "type": "Feature",
  "properties": {
    "iso:country":"DK",
    "sg:address":"Poul la Cours Vej 27",
    "sg:city":"Skanderborg",
    "sg:orig_category":"Boligselskaber",
    "sg:phone":"+45 86 52 21 77",
    "sg:postcode":"8660",
    "sg:province":"Danmark",
    "wof:name":"Midtjysk Boligselskab.",
    "wof:placetype":"venue"
},
  "geometry": {"coordinates":[9.9502496719,56.0457496643],"type":"Point"}
}