{
  "type": "Feature",
  "properties": {
    "addr:full":"Holstebrovej 6 Ulfborg Danmark 6990",
    "addr:housenumber":"6",
    "addr:postcode":"6990",
    "addr:street":"Holstebrovej",
    "iso:country":"DK",
    "sg:address":"Holstebrovej 6",
    "sg:city":"Ulfborg",
    "sg:orig_category":"Autoreparation og -service",
    "sg:phone":"+45 97 49 13 51",
    "sg:postcode":"6990",
    "sg:province":"Danmark",
    "wof:name":"Nyholm Auto Service",
    "wof:placetype":"venue"
},
  "geometry": {"coordinates":[8.3492927551,56.2935638428],"type":"Point"}
}