{
  "type": "Feature",
  "properties": {
    "iso:country":"DK",
    "sg:address":"Norregade 21",
    "sg:classifiers":[
        {
            "category":"Professional",
            "subcategory":"Advertising",
            "type":"Services"
        }
    ],
    "sg:phone":"+45 33 43 77 77",
    "sg:postcode":"0900",
    "sg:tags":[
        "communication",
        "medium"
    ],
    "wof:name":"TELE DANMARK A/S",
    "wof:placetype":"venue"
},
  "geometry": {"coordinates":[12.5710763931,55.6803131104],"type":"Point"}
}