{
  "type": "Feature",
  "properties": {
    "addr:full":"Kirkegade 7 Helsinge Danmark 3200",
    "addr:housenumber":"7",
    "addr:postcode":"3200",
    "addr:street":"Kirkegade",
    "iso:country":"DK",
    "sg:address":"Kirkegade 7",
    "sg:city":"Helsinge",
    "sg:orig_category":"Trykkerier",
    "sg:phone":"+45 48 79 42 59",
    "sg:postcode":"3200",
    "sg:province":"Danmark",
    "wof:name":"Nielsen, Helge",
    "wof:placetype":"venue"
},
  "geometry": {"coordinates":[12.1981077194,56.0234603882],"type":"Point"}
}