{
  "type": "Feature",
  "properties": {
    "addr:full":"Bilds\u00f8vej 99, Keldstrup Slagelse Danmark 4200",
    "addr:housenumber":"99",
    "addr:postcode":"4200",
    "addr:street":"Bildsovej",
    "iso:country":"DK",
    "sg:address":"Bilds\u00f8vej 99, Keldstrup",
    "sg:city":"Slagelse",
    "sg:orig_category":"Afsyring",
    "sg:phone":"+45 58 54 97 07",
    "sg:postcode":"4200",
    "sg:province":"Danmark",
    "sg:website":"www.storebalt-antik.dk",
    "wof:name":"Storeb\u00e6lt\u00b4s Antik & Genbrug",
    "wof:placetype":"venue"
},
  "geometry": {"coordinates":[11.3569850922,55.4050865173],"type":"Point"}
}