{
  "type": "Feature",
  "properties": {
    "iso:country":"DK",
    "sg:address":"Brydegaardsvej 13, Brydegaard",
    "sg:city":"Haarby",
    "sg:orig_category":"Kunstmalere",
    "sg:phone":"+45 64 77 17 55",
    "sg:postcode":"5683",
    "sg:province":"Danmark",
    "wof:name":"Skov, Irene",
    "wof:placetype":"venue"
},
  "geometry": {"coordinates":[10.1234750748,55.2234535217],"type":"Point"}
}