{
  "type": "Feature",
  "properties": {
    "addr:full":"Kalundborgvej 65 Slagelse Danmark 4200",
    "addr:housenumber":"65",
    "addr:postcode":"4200",
    "addr:street":"Kalundborgvej",
    "iso:country":"DK",
    "sg:address":"Kalundborgvej 65",
    "sg:city":"Slagelse",
    "sg:orig_category":"Golfudstyr",
    "sg:phone":"+45 58 53 32 34",
    "sg:postcode":"4200",
    "sg:province":"Danmark",
    "wof:name":"In - Golf",
    "wof:placetype":"venue"
},
  "geometry": {"coordinates":[11.3368453979,55.4137802124],"type":"Point"}
}