{
  "type": "Feature",
  "properties": {
    "addr:full":"M\u00f8llevej 11 Borup Danmark 4140",
    "addr:housenumber":"11",
    "addr:postcode":"4140",
    "addr:street":"Mollevej",
    "iso:country":"DK",
    "sg:address":"M\u00f8llevej 11",
    "sg:city":"Borup",
    "sg:orig_category":"Fodterapeuter",
    "sg:phone":"+45 56 65 31 75",
    "sg:postcode":"4140",
    "sg:province":"Danmark",
    "wof:name":"Klinik for Fodterapi",
    "wof:placetype":"venue"
},
  "geometry": {"coordinates":[11.9823999405,55.4995536804],"type":"Point"}
}