{
  "type": "Feature",
  "properties": {
    "addr:full":"Vib\u00e6k Strandvej 8 Ebeltoft Danmark 8400",
    "addr:housenumber":"8",
    "addr:postcode":"8400",
    "addr:street":"Vibaek Strandvej",
    "iso:country":"DK",
    "sg:address":"Vib\u00e6k Strandvej 8",
    "sg:city":"Ebeltoft",
    "sg:orig_category":"Sommerhusudlejning",
    "sg:phone":"+45 86 34 57 90",
    "sg:postcode":"8400",
    "sg:province":"Danmark",
    "wof:name":"Novasol A/S",
    "wof:placetype":"venue"
},
  "geometry": {"coordinates":[10.6760129929,56.2145385742],"type":"Point"}
}