{
  "type": "Feature",
  "properties": {
    "iso:country":"DK",
    "sg:address":"Sevelvej 27",
    "sg:city":"Vinderup",
    "sg:orig_category":"Kommunale ungdomsskoler",
    "sg:phone":"+45 97 44 18 92",
    "sg:postcode":"7830",
    "sg:province":"Danmark",
    "wof:name":"Vinderup Kommunale Ungdomsskole",
    "wof:placetype":"venue"
},
  "geometry": {"coordinates":[8.7833108902,56.479095459],"type":"Point"}
}