{
  "type": "Feature",
  "properties": {
    "addr:full":"Brogade 6 - 8, 1. Odense C Danmark 5000",
    "addr:housenumber":"6 8 1",
    "addr:postcode":"5000",
    "addr:street":"Brogade",
    "iso:country":"DK",
    "sg:address":"Brogade 6 - 8, 1.",
    "sg:city":"Odense C",
    "sg:orig_category":"Sparekasser",
    "sg:phone":"+45 66 11 22 31",
    "sg:postcode":"5000",
    "sg:province":"Danmark",
    "wof:name":"Folkesparekassen",
    "wof:placetype":"venue"
},
  "geometry": {"coordinates":[10.390794754,55.3961715698],"type":"Point"}
}