{
  "type": "Feature",
  "properties": {
    "addr:full":"Gravene 4 Viborg Danmark 8800",
    "addr:housenumber":"4",
    "addr:postcode":"8800",
    "addr:street":"Gravene",
    "iso:country":"DK",
    "sg:address":"Gravene 4",
    "sg:city":"Viborg",
    "sg:orig_category":"Musikinstrumenter",
    "sg:phone":"+45 86 61 29 99",
    "sg:postcode":"8800",
    "sg:province":"Danmark",
    "wof:name":"Eskildsen, Knud",
    "wof:placetype":"venue"
},
  "geometry": {"coordinates":[9.4045562744,56.4497108459],"type":"Point"}
}