{
  "type": "Feature",
  "properties": {
    "addr:full":"Fmd.: Grethe Olsen, Baunevej 208 Taastrup Danmark 2630",
    "addr:housenumber":"208",
    "addr:postcode":"2630",
    "addr:street":"Baunevej",
    "iso:country":"DK",
    "sg:address":"Fmd.: Grethe Olsen, Baunevej 208",
    "sg:city":"Taastrup",
    "sg:orig_category":"Musik og sang",
    "sg:phone":"+45 43 99 10 60",
    "sg:postcode":"2630",
    "sg:province":"Danmark",
    "wof:name":"Hedehuskoret",
    "wof:placetype":"venue"
},
  "geometry": {"coordinates":[12.3020896912,55.6506767273],"type":"Point"}
}