{
  "type": "Feature",
  "properties": {
    "iso:country":"DK",
    "sg:address":"Amtsvejen 8 A, Gassum",
    "sg:city":"Spentrup",
    "sg:orig_category":"Kirker",
    "sg:postcode":"8981",
    "sg:province":"Danmark",
    "wof:name":"Gassum Kirke",
    "wof:placetype":"venue"
},
  "geometry": {"coordinates":[10.0408000946,56.5371284485],"type":"Point"}
}