{
  "type": "Feature",
  "properties": {
    "addr:full":"Gugvej 181 Aalborg S\u00d8 Danmark 9210",
    "addr:housenumber":"181",
    "addr:postcode":"9210",
    "addr:street":"Gugvej",
    "iso:country":"DK",
    "sg:address":"Gugvej 181",
    "sg:city":"Aalborg S\u00d8",
    "sg:orig_category":"Reklamebureauer",
    "sg:phone":"+45 96 33 01 44",
    "sg:postcode":"9210",
    "sg:province":"Danmark",
    "wof:name":"Aalborg Reklame & EDB ApS",
    "wof:placetype":"venue"
},
  "geometry": {"coordinates":[9.9257907867,57.0125389099],"type":"Point"}
}