{
  "type": "Feature",
  "properties": {
    "iso:country":"DK",
    "sg:address":"Finlandsvej 5",
    "sg:city":"Skanderborg",
    "sg:orig_category":"\u00c3\u02dcl- og mineralvandsdepoter",
    "sg:phone":"+45 86 52 08 42",
    "sg:postcode":"8660",
    "sg:province":"Danmark",
    "wof:name":"Faxe Ceres Thor Skanderborg depot",
    "wof:placetype":"venue"
},
  "geometry": {"coordinates":[9.9500389099,56.0524368286],"type":"Point"}
}