{
  "type": "Feature",
  "properties": {
    "iso:country":"DK",
    "sg:address":"Viborgvej 155 F, Hasle",
    "sg:city":"\u00c5rhus V",
    "sg:orig_category":"Senge",
    "sg:phone":"+45 86 15 81 11",
    "sg:postcode":"8210",
    "sg:province":"Danmark",
    "wof:name":"Christensen, Ingvard",
    "wof:placetype":"venue"
},
  "geometry": {"coordinates":[14.70659,55.183079],"type":"Point"}
}