{
  "type": "Feature",
  "properties": {
    "addr:full":"Fabriksvej 1 Fjerritslev Danmark 9690",
    "addr:housenumber":"1",
    "addr:postcode":"9690",
    "addr:street":"Fabriksvej",
    "iso:country":"DK",
    "sg:address":"Fabriksvej 1",
    "sg:city":"Fjerritslev",
    "sg:orig_category":"Autolakering",
    "sg:phone":"+45 98 21 22 97",
    "sg:postcode":"9690",
    "sg:province":"Danmark",
    "wof:name":"Fjerritslev Autolakering I/S",
    "wof:placetype":"venue"
},
  "geometry": {"coordinates":[9.2455368042,57.0879211426],"type":"Point"}
}