{
  "type": "Feature",
  "properties": {
    "addr:full":"Skovbrynet 16 Grenaa Danmark 8500",
    "addr:housenumber":"16",
    "addr:postcode":"8500",
    "addr:street":"Skovbrynet",
    "iso:country":"DK",
    "sg:address":"Skovbrynet 16",
    "sg:city":"Grenaa",
    "sg:orig_category":"Malermestre",
    "sg:phone":"+45 86 30 01 44",
    "sg:postcode":"8500",
    "sg:province":"Danmark",
    "wof:name":"Carlsen, Per",
    "wof:placetype":"venue"
},
  "geometry": {"coordinates":[10.8759479523,56.4018783569],"type":"Point"}
}