{
  "type": "Feature",
  "properties": {
    "addr:full":"Stadionvej 4 Faaborg Danmark 5600",
    "addr:housenumber":"4",
    "addr:postcode":"5600",
    "addr:street":"Stadionvej",
    "iso:country":"DK",
    "sg:address":"Stadionvej 4",
    "sg:city":"Faaborg",
    "sg:orig_category":"Iskiosker",
    "sg:phone":"+45 62 61 09 13",
    "sg:postcode":"5600",
    "sg:province":"Danmark",
    "wof:name":"Idr\u00e6tsparkens Kiosk",
    "wof:placetype":"venue"
},
  "geometry": {"coordinates":[10.2579593658,55.0929069519],"type":"Point"}
}