{
  "type": "Feature",
  "properties": {
    "iso:country":"DK",
    "sg:address":"\u00c5bovej 18, Tversted",
    "sg:city":"Bindslev",
    "sg:orig_category":"Campingpladser",
    "sg:phone":"+45 98 93 12 34",
    "sg:postcode":"9881",
    "sg:province":"Danmark",
    "wof:name":"\u00c5bo Camping",
    "wof:placetype":"venue"
},
  "geometry": {"coordinates":[10.1876945496,57.5861968994],"type":"Point"}
}