{
  "type": "Feature",
  "properties": {
    "iso:country":"DK",
    "sg:address":"Egelund A 19 ",
    "sg:city":"Aabenraa",
    "sg:classifiers":[
        {
            "category":"Professional",
            "subcategory":"Engineering",
            "type":"Services"
        }
    ],
    "sg:phone":"+45 74 62 15 14",
    "sg:postcode":"6200",
    "sg:province":"Danmark",
    "sg:tags":[
        "machine",
        "-",
        "mechanical"
    ],
    "wof:name":"FRITEK MASKINFABRIK A/S",
    "wof:placetype":"venue"
},
  "geometry": {"coordinates":[9.3680429459,55.0676231384],"type":"Point"}
}