{
  "type": "Feature",
  "properties": {
    "addr:full":"Hornv\u00e6rket 12 Frederikshavn Danmark 9900",
    "addr:housenumber":"12",
    "addr:postcode":"9900",
    "addr:street":"Hornvaerket",
    "iso:country":"DK",
    "sg:address":"Hornv\u00e6rket 12",
    "sg:city":"Frederikshavn",
    "sg:orig_category":"Pelsdyrartikler",
    "sg:phone":"+45 98 42 48 11",
    "sg:postcode":"9900",
    "sg:province":"Danmark",
    "wof:name":"Frederikshavn Fodercentral",
    "wof:placetype":"venue"
},
  "geometry": {"coordinates":[10.5452241898,57.4408302307],"type":"Point"}
}