{
  "type": "Feature",
  "properties": {
    "addr:full":"Jernbanegade 14 C, Postboks 1 St\u00f8vring Danmark 9530",
    "addr:housenumber":"14 c;1",
    "addr:postcode":"9530",
    "addr:street":"Jernbanegade;Postboks",
    "iso:country":"DK",
    "sg:address":"Jernbanegade 14 C, Postboks 1",
    "sg:city":"St\u00f8vring",
    "sg:orig_category":"Revisorer",
    "sg:phone":"+45 98 37 13 55",
    "sg:postcode":"9530",
    "sg:province":"Danmark",
    "wof:name":"St\u00f8vring Revisionskontor Registreret Revisionsaktieselskab",
    "wof:placetype":"venue"
},
  "geometry": {"coordinates":[9.7493667603,56.9364624023],"type":"Point"}
}