{
  "type": "Feature",
  "properties": {
    "addr:full":"Skelb\u00e6kvej 8 A \u00d8lstykke Danmark 3650",
    "addr:housenumber":"8 a",
    "addr:postcode":"3650",
    "addr:street":"Skelbaekvej",
    "iso:country":"DK",
    "sg:address":"Skelb\u00e6kvej 8 A",
    "sg:city":"\u00d8lstykke",
    "sg:orig_category":"Kommunale folkeskoler",
    "sg:phone":"+45 47 17 63 30",
    "sg:postcode":"3650",
    "sg:province":"Danmark",
    "wof:name":"Magleh\u00f8jskolen",
    "wof:placetype":"venue"
},
  "geometry": {"coordinates":[8.8281869888,59.9946365356],"type":"Point"}
}