{
  "type": "Feature",
  "properties": {
    "iso:country":"DK",
    "sg:address":"\u00d8sterv\u00e6nget 9",
    "sg:city":"Sor\u00f8",
    "sg:orig_category":"Dentallaboratorier",
    "sg:phone":"+45 57 82 15 07",
    "sg:postcode":"4180",
    "sg:province":"Danmark",
    "wof:name":"Sor\u00f8 Dentallaboratorium",
    "wof:placetype":"venue"
},
  "geometry": {"coordinates":[-102.94467926030001,45.4534721375],"type":"Point"}
}