{
  "type": "Feature",
  "properties": {
    "addr:full":"Smedevej 5 Helsinge Danmark 3200",
    "addr:housenumber":"5",
    "addr:postcode":"3200",
    "addr:street":"Smedevej",
    "iso:country":"DK",
    "sg:address":"Smedevej 5",
    "sg:city":"Helsinge",
    "sg:orig_category":"Autoreparation og -service",
    "sg:phone":"+45 48 79 97 50",
    "sg:postcode":"3200",
    "sg:province":"Danmark",
    "wof:name":"Citro\u00e9n Specialisten",
    "wof:placetype":"venue"
},
  "geometry": {"coordinates":[12.1965150833,56.0164260864],"type":"Point"}
}