{
  "type": "Feature",
  "properties": {
    "addr:full":"Baneg\u00e5rdsvej 3 Aars Danmark 9600",
    "addr:housenumber":"3",
    "addr:postcode":"9600",
    "addr:street":"Banegaardsvej",
    "iso:country":"DK",
    "sg:address":"Baneg\u00e5rdsvej 3",
    "sg:city":"Aars",
    "sg:orig_category":"Ejendomshandel",
    "sg:phone":"+45 98 62 12 88",
    "sg:postcode":"9600",
    "sg:province":"Danmark",
    "wof:name":"Andersen , Richard",
    "wof:placetype":"venue"
},
  "geometry": {"coordinates":[9.5123262405,56.8031768799],"type":"Point"}
}