{
  "type": "Feature",
  "properties": {
    "addr:full":"\u00d8stergade 12 Ejstrupholm Danmark 7361",
    "addr:housenumber":"12",
    "addr:postcode":"7361",
    "addr:street":"Ostergade",
    "iso:country":"DK",
    "sg:address":"\u00d8stergade 12",
    "sg:city":"Ejstrupholm",
    "sg:orig_category":"INGENI\u00c3\u02dcRER",
    "sg:phone":"+45 75 77 32 33",
    "sg:postcode":"7361",
    "sg:province":"Danmark",
    "wof:name":"Henriksen, Ove Bro",
    "wof:placetype":"venue"
},
  "geometry": {"coordinates":[9.2912454605,55.9836273193],"type":"Point"}
}