{
  "type": "Feature",
  "properties": {
    "iso:country":"DK",
    "sg:address":"v/ Anne Lise Mortensen, Guldstjernevej 10, Vester Hjermitslev",
    "sg:city":"Br\u00f8nderslev",
    "sg:orig_category":"Lokalarkiver",
    "sg:phone":"+45 98 88 70 91",
    "sg:postcode":"9700",
    "sg:province":"Danmark",
    "wof:name":"Thise lokalhistoriske Arkiv",
    "wof:placetype":"venue"
},
  "geometry": {"coordinates":[9.7584476471,57.2860298157],"type":"Point"}
}