{
  "type": "Feature",
  "properties": {
    "iso:country":"DK",
    "sg:address":"Storstr\u00f8msvej 55",
    "sg:city":"Esbjerg N",
    "sg:orig_category":"Gartneriartikler",
    "sg:phone":"+45 76 14 76 76",
    "sg:postcode":"6715",
    "sg:province":"Danmark",
    "wof:name":"Ellegaard A/S",
    "wof:placetype":"venue"
},
  "geometry": {"coordinates":[8.4748897552,55.5045013428],"type":"Point"}
}