{
  "type": "Feature",
  "properties": {
    "addr:full":"Bytorvet 5 Albertslund Danmark 2620",
    "addr:housenumber":"5",
    "addr:postcode":"2620",
    "addr:street":"Bytorvet",
    "iso:country":"DK",
    "sg:address":"Bytorvet 5",
    "sg:city":"Albertslund",
    "sg:orig_category":"Apoteker og -udsalg",
    "sg:phone":"+45 43 64 85 90",
    "sg:postcode":"2620",
    "sg:province":"Danmark",
    "sg:website":"www.albertslundapotek.dk",
    "wof:name":"Albertslund Apotek",
    "wof:placetype":"venue"
},
  "geometry": {"coordinates":[12.354886055,55.6563911438],"type":"Point"}
}