{
  "type": "Feature",
  "properties": {
    "addr:full":"Vestergade 3 Viborg Danmark 8800",
    "addr:housenumber":"3",
    "addr:postcode":"8800",
    "addr:street":"Vestergade",
    "iso:country":"DK",
    "sg:address":"Vestergade 3",
    "sg:city":"Viborg",
    "sg:orig_category":"Ure og urmagere",
    "sg:phone":"+45 86 62 08 22",
    "sg:postcode":"8800",
    "sg:province":"Danmark",
    "wof:name":"Pedersen, Germann",
    "wof:placetype":"venue"
},
  "geometry": {"coordinates":[9.4071922302,56.4507446289],"type":"Point"}
}