{
  "type": "Feature",
  "properties": {
    "addr:full":"N\u00e6stvedvej 349 B Ringsted Danmark 4100",
    "addr:housenumber":"349 b",
    "addr:postcode":"4100",
    "addr:street":"Naestvedvej",
    "iso:country":"DK",
    "sg:address":"N\u00e6stvedvej 349 B",
    "sg:city":"Ringsted",
    "sg:orig_category":"Skolefritidsordninger",
    "sg:phone":"+45 57 62 76 20",
    "sg:postcode":"4100",
    "sg:province":"Danmark",
    "wof:name":"Vetterslev-H\u00f8mskoles SFO I og SFO II",
    "wof:placetype":"venue"
},
  "geometry": {"coordinates":[11.7742023468,55.3987541199],"type":"Point"}
}