{
  "type": "Feature",
  "properties": {
    "addr:full":"Jernbanegade 24, 2. Kolding Danmark 6000",
    "addr:housenumber":"24 2",
    "addr:postcode":"6000",
    "addr:street":"Jernbanegade",
    "iso:country":"DK",
    "sg:address":"Jernbanegade 24, 2.",
    "sg:city":"Kolding",
    "sg:orig_category":"Faglige organisationer og foreninger",
    "sg:phone":"+45 76 34 74 10",
    "sg:postcode":"6000",
    "sg:province":"Danmark",
    "wof:name":"Ingeni\u00f8rforeningen i Danmark",
    "wof:placetype":"venue"
},
  "geometry": {"coordinates":[9.4764213562,55.4900474548],"type":"Point"}
}