{
  "type": "Feature",
  "properties": {
    "addr:full":"Godth\u00e5bsvej 21 Svenstrup Danmark 9230",
    "addr:housenumber":"21",
    "addr:postcode":"9230",
    "addr:street":"Godthaabsvej",
    "iso:country":"DK",
    "sg:address":"Godth\u00e5bsvej 21",
    "sg:city":"Svenstrup",
    "sg:orig_category":"Advokater",
    "sg:phone":"+45 98 38 10 55",
    "sg:postcode":"9230",
    "sg:province":"Danmark",
    "wof:name":"Lindberg, Charles",
    "wof:placetype":"venue"
},
  "geometry": {"coordinates":[9.8503322601,56.9723358154],"type":"Point"}
}