{
  "type": "Feature",
  "properties": {
    "addr:full":"Kl\u00f8vervej 73 Haderslev Danmark 6100",
    "addr:housenumber":"73",
    "addr:postcode":"6100",
    "addr:street":"Klovervej",
    "iso:country":"DK",
    "sg:address":"Kl\u00f8vervej 73",
    "sg:city":"Haderslev",
    "sg:orig_category":"Autoforhandlere",
    "sg:phone":"+45 74 52 46 68",
    "sg:postcode":"6100",
    "sg:province":"Danmark",
    "sg:website":"www.toyota-haderslev.dk",
    "wof:name":"Toyota Haderslev Autoforum A/S",
    "wof:placetype":"venue"
},
  "geometry": {"coordinates":[9.4879703522,55.2505493164],"type":"Point"}
}