{
  "type": "Feature",
  "properties": {
    "addr:full":"v/ Johnny B. Hansen, Hvedevej 21 Aulum Danmark 7490",
    "addr:housenumber":"21",
    "addr:postcode":"7490",
    "addr:street":"Hvedevej",
    "iso:country":"DK",
    "sg:address":"v/ Johnny B. Hansen, Hvedevej 21",
    "sg:city":"Aulum",
    "sg:orig_category":"Hobbybetonede foreninger",
    "sg:phone":"+45 97 47 12 21",
    "sg:postcode":"7490",
    "sg:province":"Danmark",
    "wof:name":"Boxerklubben, Gruppe Holstebro",
    "wof:placetype":"venue"
},
  "geometry": {"coordinates":[8.7971401215,56.2653999329],"type":"Point"}
}