{
  "type": "Feature",
  "properties": {
    "addr:full":"Toftegaardsvej 5 Aalestrup Danmark 9620",
    "addr:housenumber":"5",
    "addr:postcode":"9620",
    "addr:street":"Toftegaardsvej",
    "iso:country":"DK",
    "sg:address":"Toftegaardsvej 5",
    "sg:city":"Aalestrup",
    "sg:orig_category":"Genbrugspladser",
    "sg:postcode":"9620",
    "sg:province":"Danmark",
    "wof:name":"Genbrugspladsen",
    "wof:placetype":"venue"
},
  "geometry": {"coordinates":[9.4869842529,56.696269989],"type":"Point"}
}