{
  "type": "Feature",
  "properties": {
    "addr:full":"Kirkerupvej 18, S\u00f8rbymagle Slagelse Danmark 4200",
    "addr:housenumber":"18",
    "addr:postcode":"4200",
    "addr:street":"Kirkerupvej;Sorbymagle",
    "iso:country":"DK",
    "sg:address":"Kirkerupvej 18, S\u00f8rbymagle",
    "sg:city":"Slagelse",
    "sg:orig_category":"Kommunale folkeskoler",
    "sg:phone":"+45 58 54 51 38",
    "sg:postcode":"4200",
    "sg:province":"Danmark",
    "wof:name":"Hvilebjergskolen",
    "wof:placetype":"venue"
},
  "geometry": {"coordinates":[11.3569850922,55.4050865173],"type":"Point"}
}