{
  "type": "Feature",
  "properties": {
    "iso:country":"DK",
    "sg:address":"R\u00e5brovej 22, Lille Sm\u00f8rum",
    "sg:city":"Sm\u00f8rum",
    "sg:orig_category":"Skolefritidsordninger",
    "sg:phone":"+45 44 65 13 15",
    "sg:postcode":"2765",
    "sg:province":"Danmark",
    "wof:name":"S\u00f8ager",
    "wof:placetype":"venue"
},
  "geometry": {"coordinates":[3.0627999306,50.6371803284],"type":"Point"}
}