{
  "type": "Feature",
  "properties": {
    "iso:country":"DK",
    "sg:address":"Nylandsvej 48",
    "sg:city":"Lem",
    "sg:orig_category":"El-automatik",
    "sg:phone":"+45 97 34 11 00",
    "sg:postcode":"6940",
    "sg:province":"Danmark",
    "sg:website":"www.hoejmark-automatic.dk",
    "wof:name":"H\u00f8jmark Automatic a/s",
    "wof:placetype":"venue"
},
  "geometry": {"coordinates":[8.3743982315,56.0242004395],"type":"Point"}
}