{
  "type": "Feature",
  "properties": {
    "addr:full":"Holte Midtpunkt 17, 1. Holte Danmark 2840",
    "addr:housenumber":"17 1",
    "addr:postcode":"2840",
    "addr:street":"Holte Midtpunkt",
    "iso:country":"DK",
    "sg:address":"Holte Midtpunkt 17, 1.",
    "sg:city":"Holte",
    "sg:orig_category":"Sko",
    "sg:phone":"+45 45 41 34 10",
    "sg:postcode":"2840",
    "sg:province":"Danmark",
    "wof:name":"Paliann Sko",
    "wof:placetype":"venue"
},
  "geometry": {"coordinates":[12.4705371857,55.8111686707],"type":"Point"}
}