{
  "type": "Feature",
  "properties": {
    "addr:full":"S\u00f8ndergade 77 Frederikshavn Danmark 9900",
    "addr:housenumber":"77",
    "addr:postcode":"9900",
    "addr:street":"Sondergade",
    "iso:country":"DK",
    "sg:address":"S\u00f8ndergade 77",
    "sg:city":"Frederikshavn",
    "sg:orig_category":"Stoffer",
    "sg:phone":"+45 98 42 12 31",
    "sg:postcode":"9900",
    "sg:province":"Danmark",
    "wof:name":"De Flittige H\u00e6nder",
    "wof:placetype":"venue"
},
  "geometry": {"coordinates":[10.5269193649,57.4325256348],"type":"Point"}
}