{
  "type": "Feature",
  "properties": {
    "addr:full":"\u00c5rbygade 1 Kalundborg Danmark 4400",
    "addr:housenumber":"1",
    "addr:postcode":"4400",
    "addr:street":"Aarbygade",
    "iso:country":"DK",
    "sg:address":"\u00c5rbygade 1",
    "sg:city":"Kalundborg",
    "sg:orig_category":"Flytteforretninger",
    "sg:phone":"+45 40 76 19 64",
    "sg:postcode":"4400",
    "sg:province":"Danmark",
    "wof:name":"Kim's Transport- & Flytteservice",
    "wof:placetype":"venue"
},
  "geometry": {"coordinates":[11.0934085846,55.6797485352],"type":"Point"}
}