{
  "type": "Feature",
  "properties": {
    "addr:full":"Kirkehelle 5 Vissenbjerg Danmark 5492",
    "addr:housenumber":"5",
    "addr:postcode":"5492",
    "addr:street":"Kirkehelle",
    "iso:country":"DK",
    "sg:address":"Kirkehelle 5",
    "sg:city":"Vissenbjerg",
    "sg:orig_category":"Dyreparker",
    "sg:phone":"+45 64 47 18 50",
    "sg:postcode":"5492",
    "sg:province":"Danmark",
    "wof:name":"Terrariet Vissenbjerg",
    "wof:placetype":"venue"
},
  "geometry": {"coordinates":[10.1314649582,55.3838043213],"type":"Point"}
}