{
  "type": "Feature",
  "properties": {
    "addr:full":"Valby Langgade 217 Valby Danmark 2500",
    "addr:housenumber":"217",
    "addr:postcode":"2500",
    "addr:street":"Valby Langgade",
    "iso:country":"DK",
    "sg:address":"Valby Langgade 217",
    "sg:city":"Valby",
    "sg:orig_category":"INGENI\u00c3\u02dcRER",
    "sg:phone":"+45 36 45 07 10",
    "sg:postcode":"2500",
    "sg:province":"Danmark",
    "wof:name":"Hansen, Ib",
    "wof:placetype":"venue"
},
  "geometry": {"coordinates":[12.4882154465,55.6706008911],"type":"Point"}
}