{
  "type": "Feature",
  "properties": {
    "iso:country":"DK",
    "sg:address":"R\u00f8nnevej 3",
    "sg:city":"Herning",
    "sg:orig_category":"Kaffe og the",
    "sg:phone":"+45 97 12 93 11",
    "sg:postcode":"7400",
    "sg:province":"Danmark",
    "wof:name":"Herning Kafferisteri A/S",
    "wof:placetype":"venue"
},
  "geometry": {"coordinates":[8.9937171936,56.1501846313],"type":"Point"}
}