{
  "type": "Feature",
  "properties": {
    "addr:full":"Odensevej 45 Ringe Danmark 5750",
    "addr:housenumber":"45",
    "addr:postcode":"5750",
    "addr:street":"Odensevej",
    "iso:country":"DK",
    "sg:address":"Odensevej 45",
    "sg:city":"Ringe",
    "sg:orig_category":"Autoforhandlere",
    "sg:phone":"+45 62 62 21 12",
    "sg:postcode":"5750",
    "sg:province":"Danmark",
    "wof:name":"Weiskvist Biler",
    "wof:placetype":"venue"
},
  "geometry": {"coordinates":[10.4767904282,55.2444725037],"type":"Point"}
}