{
  "type": "Feature",
  "properties": {
    "addr:full":"Borupvej 73, Borup G\u00f8rl\u00f8se Danmark 3330",
    "addr:housenumber":"73",
    "addr:postcode":"3330",
    "addr:street":"Borupvej",
    "iso:country":"DK",
    "sg:address":"Borupvej 73, Borup",
    "sg:city":"G\u00f8rl\u00f8se",
    "sg:orig_category":"Tekstiler",
    "sg:phone":"+45 48 27 81 83",
    "sg:postcode":"3330",
    "sg:province":"Danmark",
    "wof:name":"Lille Kr\u00e6mmeri, Det",
    "wof:placetype":"venue"
},
  "geometry": {"coordinates":[-96.50723266599999,47.1803092957],"type":"Point"}
}