{
  "type": "Feature",
  "properties": {
    "addr:full":"Korsn\u00e6bsvej 66 R\u00f8dvig Stevns Danmark 4673",
    "addr:housenumber":"66",
    "addr:postcode":"4673",
    "addr:street":"Korsnaebsvej",
    "iso:country":"DK",
    "sg:address":"Korsn\u00e6bsvej 66",
    "sg:city":"R\u00f8dvig Stevns",
    "sg:orig_category":"Glarmestre og glarmagere",
    "sg:phone":"+45 56 50 60 73",
    "sg:postcode":"4673",
    "sg:province":"Danmark",
    "wof:name":"Jensen - R\u00f8dvig Glas, Knud",
    "wof:placetype":"venue"
},
  "geometry": {"coordinates":[12.4143390656,55.2688484192],"type":"Point"}
}