{
  "type": "Feature",
  "properties": {
    "addr:full":"Holmegade 35 Ulfborg Danmark 6990",
    "addr:housenumber":"35",
    "addr:postcode":"6990",
    "addr:street":"Holmegade",
    "iso:country":"DK",
    "sg:address":"Holmegade 35",
    "sg:city":"Ulfborg",
    "sg:orig_category":"Plejehjem",
    "sg:phone":"+45 97 49 12 56",
    "sg:postcode":"6990",
    "sg:province":"Danmark",
    "wof:name":"Vemb Aktiv Center",
    "wof:placetype":"venue"
},
  "geometry": {"coordinates":[8.3232316971,56.275592804],"type":"Point"}
}