{
  "type": "Feature",
  "properties": {
    "addr:full":"Granv\u00e6nget 5 Karlslunde Danmark 2690",
    "addr:housenumber":"5",
    "addr:postcode":"2690",
    "addr:street":"Granvaenget",
    "iso:country":"DK",
    "sg:address":"Granv\u00e6nget 5",
    "sg:city":"Karlslunde",
    "sg:orig_category":"Malermestre",
    "sg:phone":"+45 46 15 57 15",
    "sg:postcode":"2690",
    "sg:province":"Danmark",
    "wof:name":"Folkvardsen, J\u00f8rgen",
    "wof:placetype":"venue"
},
  "geometry": {"coordinates":[12.2294149399,55.5701599121],"type":"Point"}
}