{
  "type": "Feature",
  "properties": {
    "addr:full":"v/ Ane Funck Hemmingsen, V\u00e6vervej 3, Tostrup Stege Danmark 4780",
    "addr:housenumber":"3",
    "addr:postcode":"4780",
    "addr:street":"Vaevervej;Tostrup",
    "iso:country":"DK",
    "sg:address":"v/ Ane Funck Hemmingsen, V\u00e6vervej 3, Tostrup",
    "sg:city":"Stege",
    "sg:orig_category":"Folkedans",
    "sg:phone":"+45 55 81 31 81",
    "sg:postcode":"4780",
    "sg:province":"Danmark",
    "wof:name":"Folkedansen Hjertebjerg",
    "wof:placetype":"venue"
},
  "geometry": {"coordinates":[12.2875270844,54.9855155945],"type":"Point"}
}