{
  "type": "Feature",
  "properties": {
    "addr:full":"v/ B\u00f8rge Jensen, V. E. Gamborgs Vej 15 Frederiksberg Danmark 2000",
    "addr:housenumber":"15",
    "addr:postcode":"2000",
    "addr:street":"Gamborgs Vej",
    "iso:country":"DK",
    "sg:address":"v/ B\u00f8rge Jensen, V. E. Gamborgs Vej 15",
    "sg:city":"Frederiksberg",
    "sg:orig_category":"Grundejerforeninger",
    "sg:phone":"+45 38 87 76 73",
    "sg:postcode":"2000",
    "sg:province":"Danmark",
    "wof:name":"Lyngen - Stenager Grundejerforening",
    "wof:placetype":"venue"
},
  "geometry": {"coordinates":[12.518497467,55.6822738647],"type":"Point"}
}