{
  "type": "Feature",
  "properties": {
    "addr:full":"Louisevej 100 Brabrand Danmark 8220",
    "addr:housenumber":"100",
    "addr:postcode":"8220",
    "addr:street":"Louisevej",
    "iso:country":"DK",
    "sg:address":"Louisevej 100",
    "sg:city":"Brabrand",
    "sg:orig_category":"Dyrefoder",
    "sg:phone":"+45 86 25 68 60",
    "sg:postcode":"8220",
    "sg:province":"Danmark",
    "sg:website":"www.natursamarbejdet.dk",
    "wof:name":"Natursamarbejdet",
    "wof:placetype":"venue"
},
  "geometry": {"coordinates":[10.136390686,56.1486816406],"type":"Point"}
}