{
  "type": "Feature",
  "properties": {
    "addr:full":"v/ Serje Badal, Elsdyrl\u00f8kken 108 D, Korup Odense NV Danmark 5210",
    "addr:housenumber":"108 d",
    "addr:postcode":"5210",
    "addr:street":"Elsdyrlokken;Korup",
    "iso:country":"DK",
    "sg:address":"v/ Serje Badal, Elsdyrl\u00f8kken 108 D, Korup",
    "sg:city":"Odense NV",
    "sg:orig_category":"Musik og sang",
    "sg:phone":"+45 65 94 24 70",
    "sg:postcode":"5210",
    "sg:province":"Danmark",
    "wof:name":"Iransk Musik- og Kulturforening",
    "wof:placetype":"venue"
},
  "geometry": {"coordinates":[10.274764061,55.4303321838],"type":"Point"}
}