{
  "type": "Feature",
  "properties": {
    "iso:country":"DK",
    "sg:address":"Hyldevej 14",
    "sg:city":"Kalvehave",
    "sg:orig_category":"Boligselskaber",
    "sg:phone":"+45 55 38 82 43",
    "sg:postcode":"4771",
    "sg:province":"Danmark",
    "wof:name":"Lysson Bolig K/S",
    "wof:placetype":"venue"
},
  "geometry": {"coordinates":[12.1658115387,54.9998092651],"type":"Point"}
}