{
  "type": "Feature",
  "properties": {
    "addr:full":"Stormosevej 9 B Hasselager Danmark 8361",
    "addr:housenumber":"9 b",
    "addr:postcode":"8361",
    "addr:street":"Stormosevej",
    "iso:country":"DK",
    "sg:address":"Stormosevej 9 B",
    "sg:city":"Hasselager",
    "sg:orig_category":"Malermestre",
    "sg:phone":"+45 86 28 15 30",
    "sg:postcode":"8361",
    "sg:province":"Danmark",
    "wof:name":"\u00d8stjysk Malerforretning ApS",
    "wof:placetype":"venue"
},
  "geometry": {"coordinates":[10.091843605,56.1016540527],"type":"Point"}
}