{
  "type": "Feature",
  "properties": {
    "addr:full":"Fmd.: Preben Jensen, Klosterm\u00f8llevej 39 Vestervig Danmark 7770",
    "addr:housenumber":"39",
    "addr:postcode":"7770",
    "addr:street":"Preben;Klostermollevej",
    "iso:country":"DK",
    "sg:address":"Fmd.: Preben Jensen, Klosterm\u00f8llevej 39",
    "sg:city":"Vestervig",
    "sg:orig_category":"Hobbybetonede foreninger",
    "sg:phone":"+45 97 94 16 10",
    "sg:postcode":"7770",
    "sg:province":"Danmark",
    "wof:name":"Brevdueforeningen DAN 0130",
    "wof:placetype":"venue"
},
  "geometry": {"coordinates":[8.2376403809,56.7811546326],"type":"Point"}
}