{
  "type": "Feature",
  "properties": {
    "addr:full":"Skr\u00e6nten 2, Ulbjerg Skals Danmark 8832",
    "addr:housenumber":"2",
    "addr:postcode":"8832",
    "addr:street":"Skraenten;Ulbjerg",
    "iso:country":"DK",
    "sg:address":"Skr\u00e6nten 2, Ulbjerg",
    "sg:city":"Skals",
    "sg:orig_category":"Antikviteter",
    "sg:phone":"+45 86 69 72 60",
    "sg:postcode":"8832",
    "sg:province":"Danmark",
    "wof:name":"Nielsen, Svend \u00c5ge",
    "wof:placetype":"venue"
},
  "geometry": {"coordinates":[9.4030599594,56.5558166504],"type":"Point"}
}