{
  "type": "Feature",
  "properties": {
    "addr:full":"Fmd.: F. J\u00f8rgensen, Dyndetvej 4 Borup Danmark 4140",
    "addr:housenumber":"4",
    "addr:postcode":"4140",
    "addr:street":"Dyndetvej",
    "iso:country":"DK",
    "sg:address":"Fmd.: F. J\u00f8rgensen, Dyndetvej 4",
    "sg:city":"Borup",
    "sg:orig_category":"Legestuer",
    "sg:phone":"+45 57 52 66 25",
    "sg:postcode":"4140",
    "sg:province":"Danmark",
    "wof:name":"Borup Legestue",
    "wof:placetype":"venue"
},
  "geometry": {"coordinates":[11.9749145508,55.4920845032],"type":"Point"}
}