{
  "type": "Feature",
  "properties": {
    "addr:full":"Ribe Landevej 403 Vejle Danmark 7100",
    "addr:housenumber":"403",
    "addr:postcode":"7100",
    "addr:street":"Ribe Landevej",
    "iso:country":"DK",
    "sg:address":"Ribe Landevej 403",
    "sg:city":"Vejle",
    "sg:orig_category":"Vinduespolering",
    "sg:phone":"+45 75 72 50 35",
    "sg:postcode":"7100",
    "sg:province":"Danmark",
    "wof:name":"Frandsen's Vinduespolering",
    "wof:placetype":"venue"
},
  "geometry": {"coordinates":[9.458483696,55.6870574951],"type":"Point"}
}