{
  "type": "Feature",
  "properties": {
    "iso:country":"DK",
    "sg:address":"S\u00f8ndergade 11",
    "sg:city":"Herning",
    "sg:orig_category":"Belysning",
    "sg:phone":"+45 97 21 61 66",
    "sg:postcode":"7400",
    "sg:province":"Danmark",
    "wof:name":"City Light",
    "wof:placetype":"venue"
},
  "geometry": {"coordinates":[8.976121,56.135811],"type":"Point"}
}