{
  "type": "Feature",
  "properties": {
    "addr:full":"Juelsbergvej 1, Juelsberg Nyborg Danmark 5800",
    "addr:housenumber":"1",
    "addr:postcode":"5800",
    "addr:street":"Juelsbergvej;Juelsberg",
    "iso:country":"DK",
    "sg:address":"Juelsbergvej 1, Juelsberg",
    "sg:city":"Nyborg",
    "sg:orig_category":"Web- og Internetdesign",
    "sg:phone":"+45 28 15 43 65",
    "sg:postcode":"5800",
    "sg:province":"Danmark",
    "wof:name":"Yweb",
    "wof:placetype":"venue"
},
  "geometry": {"coordinates":[10.7923851013,55.3111801147],"type":"Point"}
}