{
  "type": "Feature",
  "properties": {
    "iso:country":"DK",
    "sg:address":"v/ Knud Husted, Oktobervej 12",
    "sg:city":"Fredericia",
    "sg:orig_category":"Hobbybetonede foreninger",
    "sg:phone":"+45 22 45 85 42",
    "sg:postcode":"7000",
    "sg:province":"Danmark",
    "wof:name":"Vejlby Walkie Klub",
    "wof:placetype":"venue"
},
  "geometry": {"coordinates":[9.7591047287,55.566368103],"type":"Point"}
}