{
  "type": "Feature",
  "properties": {
    "addr:full":"Kegn\u00e6svej 52, Skovby Sydals Danmark 6470",
    "addr:housenumber":"52",
    "addr:postcode":"6470",
    "addr:street":"Kegnaesvej;Skovby",
    "iso:country":"DK",
    "sg:address":"Kegn\u00e6svej 52, Skovby",
    "sg:city":"Sydals",
    "sg:orig_category":"Brugsforeninger",
    "sg:phone":"+45 74 40 44 19",
    "sg:postcode":"6470",
    "sg:province":"Danmark",
    "wof:name":"Dagli'Brugsen",
    "wof:placetype":"venue"
},
  "geometry": {"coordinates":[9.8924627304,54.9105377197],"type":"Point"}
}