{
  "type": "Feature",
  "properties": {
    "iso:country":"DK",
    "sg:address":"Skodsborgvej 1,3",
    "sg:city":"Virum",
    "sg:orig_category":"\u00c3\u02dcvrige institutioner",
    "sg:phone":"+45 45 85 12 13",
    "sg:postcode":"2830",
    "sg:province":"Danmark",
    "sg:website":"www.autisme.dk",
    "wof:name":"Videnscenter for Autisme",
    "wof:placetype":"venue"
},
  "geometry": {"coordinates":[12.4838695526,55.7975082397],"type":"Point"}
}