{
  "type": "Feature",
  "properties": {
    "addr:full":"S\u00f8ndre Fasanvej 34 B Frederiksberg Danmark 2000",
    "addr:housenumber":"34 b",
    "addr:postcode":"2000",
    "addr:street":"Sondre Fasanvej",
    "iso:country":"DK",
    "sg:address":"S\u00f8ndre Fasanvej 34 B",
    "sg:city":"Frederiksberg",
    "sg:orig_category":"Stenhuggere",
    "sg:phone":"+45 36 46 14 91",
    "sg:postcode":"2000",
    "sg:province":"Danmark",
    "wof:name":"Nielsens Stenhuggerier A/S, E.",
    "wof:placetype":"venue"
},
  "geometry": {"coordinates":[12.518116951,55.6721305847],"type":"Point"}
}