{
  "type": "Feature",
  "properties": {
    "iso:country":"DK",
    "sg:address":"J A Schwartzgade 23",
    "sg:city":"K\u00f8benhavn \u00d8",
    "sg:orig_category":"Arkitekter",
    "sg:phone":"+45 35 26 11 49",
    "sg:postcode":"2100",
    "sg:province":"Danmark",
    "wof:name":"Ortvig, Hans Erik",
    "wof:placetype":"venue"
},
  "geometry": {"coordinates":[11.6836299896,60.2548065186],"type":"Point"}
}