{
  "type": "Feature",
  "properties": {
    "addr:full":"Storegade 55 Haderslev Danmark 6100",
    "addr:housenumber":"55",
    "addr:postcode":"6100",
    "addr:street":"Storegade",
    "iso:country":"DK",
    "sg:address":"Storegade 55",
    "sg:city":"Haderslev",
    "sg:classifiers":[
        {
            "category":"Travel",
            "subcategory":"Hotels & Motels",
            "type":"Entertainment"
        }
    ],
    "sg:phone":"+45 74 52 40 30",
    "sg:postcode":"6100",
    "sg:province":"Danmark",
    "sg:website":"www.hotel-norden.dk",
    "wof:name":"Norden, Hotel",
    "wof:placetype":"venue"
},
  "geometry": {"coordinates":[9.4805145264,55.2520523071],"type":"Point"}
}