{
  "type": "Feature",
  "properties": {
    "addr:full":"Skolevej 5-7, Nordby Fan\u00f8 Danmark 6720",
    "addr:housenumber":"5-7",
    "addr:postcode":"6720",
    "addr:street":"Skolevej",
    "iso:country":"DK",
    "sg:address":"Skolevej 5-7, Nordby",
    "sg:city":"Fan\u00f8",
    "sg:orig_category":"Sundhedspleje",
    "sg:phone":"+45 75 16 33 10",
    "sg:postcode":"6720",
    "sg:province":"Danmark",
    "wof:name":"Sundshedsplejen i Fan\u00f8 Kommune",
    "wof:placetype":"venue"
},
  "geometry": {"coordinates":[8.4069461823,55.4484786987],"type":"Point"}
}