{
  "type": "Feature",
  "properties": {
    "addr:full":"Islandsgade 34 Haslev Danmark 4690",
    "addr:housenumber":"34",
    "addr:postcode":"4690",
    "addr:street":"Islandsgade",
    "iso:country":"DK",
    "sg:address":"Islandsgade 34",
    "sg:city":"Haslev",
    "sg:orig_category":"El-motorer",
    "sg:phone":"+45 56 31 21 63",
    "sg:postcode":"4690",
    "sg:province":"Danmark",
    "sg:website":"www.haslevelektro.dk",
    "wof:name":"Haslev Elektro ApS",
    "wof:placetype":"venue"
},
  "geometry": {"coordinates":[11.9371356964,55.3232574463],"type":"Point"}
}