{
  "type": "Feature",
  "properties": {
    "addr:full":"Brem\u00e5revej 15 Lystrup Danmark 8520",
    "addr:housenumber":"15",
    "addr:postcode":"8520",
    "addr:street":"Bremaarevej",
    "iso:country":"DK",
    "sg:address":"Brem\u00e5revej 15",
    "sg:city":"Lystrup",
    "sg:orig_category":"Tekstiltrykkerier",
    "sg:phone":"+45 86 22 88 33",
    "sg:postcode":"8520",
    "sg:province":"Danmark",
    "wof:name":"Zacho Serigrafi",
    "wof:placetype":"venue"
},
  "geometry": {"coordinates":[10.2381649017,56.2281608582],"type":"Point"}
}