{
  "type": "Feature",
  "properties": {
    "iso:country":"DK",
    "sg:address":"Strandhusevej 43",
    "sg:city":"Juelsminde",
    "sg:orig_category":"Maskinfabrikker",
    "sg:phone":"+45 75 69 37 22",
    "sg:postcode":"7130",
    "sg:province":"Danmark",
    "wof:name":"Compac Hydraulik A/S",
    "wof:placetype":"venue"
},
  "geometry": {"coordinates":[10.0109329224,55.7071609497],"type":"Point"}
}