{
  "type": "Feature",
  "properties": {
    "addr:full":"Hasselvej 8 Kirke Eskilstrup Danmark 4360",
    "addr:housenumber":"8",
    "addr:postcode":"4360",
    "addr:street":"Hasselvej",
    "iso:country":"DK",
    "sg:address":"Hasselvej 8",
    "sg:city":"Kirke Eskilstrup",
    "sg:orig_category":"Antenneforeninger",
    "sg:phone":"+45 59 17 12 34",
    "sg:postcode":"4360",
    "sg:province":"Danmark",
    "wof:name":"Kirkebyens Antennelaug af 1980",
    "wof:placetype":"venue"
},
  "geometry": {"coordinates":[11.7662639618,55.5756721497],"type":"Point"}
}