{
  "type": "Feature",
  "properties": {
    "iso:country":"DK",
    "sg:address":"Kr\u00f8geb\u00e6kvej 25",
    "sg:city":"Hovborg",
    "sg:orig_category":"Vandrensning, SPILDEVAND",
    "sg:phone":"+45 75 39 65 00",
    "sg:postcode":"6682",
    "sg:province":"Danmark",
    "wof:name":"AL - 2 Teknik A/S",
    "wof:placetype":"venue"
},
  "geometry": {"coordinates":[8.9379148483,55.6087341309],"type":"Point"}
}