{
  "type": "Feature",
  "properties": {
    "addr:full":"Tulsmarkvej 15 Varde Danmark 6800",
    "addr:housenumber":"15",
    "addr:postcode":"6800",
    "addr:street":"Tulsmarkvej",
    "iso:country":"DK",
    "sg:address":"Tulsmarkvej 15",
    "sg:city":"Varde",
    "sg:orig_category":"Psykologer, praktiserende",
    "sg:phone":"+45 20 99 99 02",
    "sg:postcode":"6800",
    "sg:province":"Danmark",
    "sg:website":"www.svennild.dk",
    "wof:name":"Svennild, Ib",
    "wof:placetype":"venue"
},
  "geometry": {"coordinates":[8.416768074,55.5664176941],"type":"Point"}
}