{
  "type": "Feature",
  "properties": {
    "addr:full":"S\u00f8ndergade 13 Saltum Danmark 9493",
    "addr:housenumber":"13",
    "addr:postcode":"9493",
    "addr:street":"Sondergade",
    "iso:country":"DK",
    "sg:address":"S\u00f8ndergade 13",
    "sg:city":"Saltum",
    "sg:orig_category":"Kunsthandlere",
    "sg:phone":"+45 98 88 17 18",
    "sg:postcode":"9493",
    "sg:province":"Danmark",
    "wof:name":"Saltum Antik",
    "wof:placetype":"venue"
},
  "geometry": {"coordinates":[9.6976566315,57.2702293396],"type":"Point"}
}