{
  "type": "Feature",
  "properties": {
    "addr:full":"Vestergade 53 \u00c5rhus C Danmark 8000",
    "addr:housenumber":"53",
    "addr:postcode":"8000",
    "addr:street":"Vestergade",
    "iso:country":"DK",
    "sg:address":"Vestergade 53",
    "sg:city":"\u00c5rhus C",
    "sg:orig_category":"Garn",
    "sg:phone":"+45 86 19 09 66",
    "sg:postcode":"8000",
    "sg:province":"Danmark",
    "wof:name":"Isager, Marianne",
    "wof:placetype":"venue"
},
  "geometry": {"coordinates":[9.5455904007,56.1682090759],"type":"Point"}
}