{
  "type": "Feature",
  "properties": {
    "addr:full":"Kirkeh\u00f8jvej 9 A, N\u00f8rre Bork Hemmet Danmark 6893",
    "addr:housenumber":"9 a",
    "addr:postcode":"6893",
    "addr:street":"Kirkehojvej;Norre Bork",
    "iso:country":"DK",
    "sg:address":"Kirkeh\u00f8jvej 9 A, N\u00f8rre Bork",
    "sg:city":"Hemmet",
    "sg:orig_category":"Campingpladser",
    "sg:phone":"+45 75 28 00 37",
    "sg:postcode":"6893",
    "sg:province":"Danmark",
    "sg:website":"www.sitecenter.dk/bork_havn_camping",
    "wof:name":"Bork Havn Camping",
    "wof:placetype":"venue"
},
  "geometry": {"coordinates":[8.2862300873,55.8409957886],"type":"Point"}
}