{
  "type": "Feature",
  "properties": {
    "addr:full":"Sallvej 39 Hammel Danmark 8450",
    "addr:housenumber":"39",
    "addr:postcode":"8450",
    "addr:street":"Sallvej",
    "iso:country":"DK",
    "sg:address":"Sallvej 39",
    "sg:city":"Hammel",
    "sg:orig_category":"Integrerede institutioner",
    "sg:phone":"+45 86 96 37 27",
    "sg:postcode":"8450",
    "sg:province":"Danmark",
    "wof:name":"G\u00e5rden",
    "wof:placetype":"venue"
},
  "geometry": {"coordinates":[9.8555679321,56.2600708008],"type":"Point"}
}