{
  "type": "Feature",
  "properties": {
    "addr:full":"Middelfartvej 50, Bolbro Odense V Danmark 5200",
    "addr:housenumber":"50",
    "addr:postcode":"5200",
    "addr:street":"Middelfartvej;Bolbro",
    "iso:country":"DK",
    "sg:address":"Middelfartvej 50, Bolbro",
    "sg:city":"Odense V",
    "sg:orig_category":"Bilpleje",
    "sg:phone":"+45 66 12 41 13",
    "sg:postcode":"5200",
    "sg:province":"Danmark",
    "wof:name":"Tidy Car Odense ApS",
    "wof:placetype":"venue"
},
  "geometry": {"coordinates":[10.262955,55.407085],"type":"Point"}
}