{
  "type": "Feature",
  "properties": {
    "addr:full":"Spragelsevej 19 Herlufmagle Danmark 4160",
    "addr:housenumber":"19",
    "addr:postcode":"4160",
    "addr:street":"Spragelsevej",
    "iso:country":"DK",
    "sg:address":"Spragelsevej 19",
    "sg:city":"Herlufmagle",
    "sg:orig_category":"Kirker",
    "sg:postcode":"4160",
    "sg:province":"Danmark",
    "wof:name":"Herlufmagle Kirke",
    "wof:placetype":"venue"
},
  "geometry": {"coordinates":[11.7571563721,55.3124008179],"type":"Point"}
}