{
  "type": "Feature",
  "properties": {
    "addr:full":"Forr.f\u00f8rer.: Peter Boy Birck, Kallemosen 5 Aabenraa Danmark 6200",
    "addr:housenumber":"5",
    "addr:postcode":"6200",
    "addr:street":"Kallemosen",
    "iso:country":"DK",
    "sg:address":"Forr.f\u00f8rer.: Peter Boy Birck, Kallemosen 5",
    "sg:city":"Aabenraa",
    "sg:orig_category":"Borger- og beboerforeninger",
    "sg:phone":"+45 74 62 10 55",
    "sg:postcode":"6200",
    "sg:province":"Danmark",
    "wof:name":"B\u00fcrgerverein Apenrade",
    "wof:placetype":"venue"
},
  "geometry": {"coordinates":[9.4213867188,55.0449562073],"type":"Point"}
}