{
  "type": "Feature",
  "properties": {
    "addr:full":"Konvalvej 5 Dronninglund Danmark 9330",
    "addr:housenumber":"5",
    "addr:postcode":"9330",
    "addr:street":"Konvalvej",
    "iso:country":"DK",
    "sg:address":"Konvalvej 5",
    "sg:city":"Dronninglund",
    "sg:orig_category":"Murermestre",
    "sg:phone":"+45 98 84 10 73",
    "sg:postcode":"9330",
    "sg:province":"Danmark",
    "wof:name":"Rasmussen & S\u00f8n, Chr.",
    "wof:placetype":"venue"
},
  "geometry": {"coordinates":[10.2962284088,57.1628837585],"type":"Point"}
}