{
  "type": "Feature",
  "properties": {
    "addr:full":"R\u00f8dh\u00f8j 35 Asn\u00e6s Danmark 4550",
    "addr:housenumber":"35",
    "addr:postcode":"4550",
    "addr:street":"Rodhoj",
    "iso:country":"DK",
    "sg:address":"R\u00f8dh\u00f8j 35",
    "sg:city":"Asn\u00e6s",
    "sg:orig_category":"Betonvarefabrikker",
    "sg:phone":"+45 59 65 04 00",
    "sg:postcode":"4550",
    "sg:province":"Danmark",
    "wof:name":"Dragsholm Beton- og Murervirksomhed ApS",
    "wof:placetype":"venue"
},
  "geometry": {"coordinates":[-98.57666015620001,47.9187011719],"type":"Point"}
}