{
  "type": "Feature",
  "properties": {
    "addr:full":"Skelmosevej 77, Stadil Tim Danmark 6980",
    "addr:housenumber":"77",
    "addr:postcode":"6980",
    "addr:street":"Skelmosevej",
    "iso:country":"DK",
    "sg:address":"Skelmosevej 77, Stadil",
    "sg:city":"Tim",
    "sg:orig_category":"Plejehjem",
    "sg:phone":"+45 96 74 75 38",
    "sg:postcode":"6980",
    "sg:province":"Danmark",
    "wof:name":"De Gamles Hjem i Stadil",
    "wof:placetype":"venue"
},
  "geometry": {"coordinates":[8.3066711426,56.1961898804],"type":"Point"}
}