{
  "type": "Feature",
  "properties": {
    "addr:full":"Vandmanden 36 Aalborg SV Danmark 9200",
    "addr:housenumber":"36",
    "addr:postcode":"9200",
    "addr:street":"Vandmanden",
    "iso:country":"DK",
    "sg:address":"Vandmanden 36",
    "sg:city":"Aalborg SV",
    "sg:orig_category":"Skibsklassificering",
    "sg:phone":"+45 98 79 08 33",
    "sg:postcode":"9200",
    "sg:province":"Danmark",
    "wof:name":"Norske Veritas, Det",
    "wof:placetype":"venue"
},
  "geometry": {"coordinates":[9.869477272,57.003326416],"type":"Point"}
}