{
  "type": "Feature",
  "properties": {
    "addr:full":"v/ Birthe Schnoor, Vesterled 3 A, Ramten \u00d8rum Danmark 8586",
    "addr:housenumber":"3 a",
    "addr:postcode":"8586",
    "addr:street":"Schnoor Vesterled;Ramten;Danmark",
    "iso:country":"DK",
    "sg:address":"v/ Birthe Schnoor, Vesterled 3 A, Ramten",
    "sg:city":"\u00d8rum",
    "sg:orig_category":"Borger- og beboerforeninger",
    "sg:phone":"+45 86 38 14 95",
    "sg:postcode":"8586",
    "sg:province":"Danmark",
    "wof:name":"Ramten Borgerforening",
    "wof:placetype":"venue"
},
  "geometry": {"coordinates":[10.6754999161,56.4425544739],"type":"Point"}
}