{
  "type": "Feature",
  "properties": {
    "addr:full":"Nyborgvej 184 Odense S\u00d8 Danmark 5220",
    "addr:housenumber":"184",
    "addr:postcode":"5220",
    "addr:street":"Nyborgvej",
    "iso:country":"DK",
    "sg:address":"Nyborgvej 184",
    "sg:city":"Odense S\u00d8",
    "sg:orig_category":"Bagere",
    "sg:phone":"+45 66 12 64 01",
    "sg:postcode":"5220",
    "sg:province":"Danmark",
    "wof:name":"Froms Conditori",
    "wof:placetype":"venue"
},
  "geometry": {"coordinates":[10.418592453,55.3933296204],"type":"Point"}
}