{
  "type": "Feature",
  "properties": {
    "addr:full":"Simmerstedvej 71 Haderslev Danmark 6100",
    "addr:housenumber":"71",
    "addr:postcode":"6100",
    "addr:street":"Simmerstedvej",
    "iso:country":"DK",
    "sg:address":"Simmerstedvej 71",
    "sg:city":"Haderslev",
    "sg:orig_category":"Emballage",
    "sg:phone":"+45 74 52 21 18",
    "sg:postcode":"6100",
    "sg:province":"Danmark",
    "sg:website":"www.mesko.dk",
    "wof:name":"Mesko",
    "wof:placetype":"venue"
},
  "geometry": {"coordinates":[9.4641017914,55.2515258789],"type":"Point"}
}