{
  "type": "Feature",
  "properties": {
    "iso:country":"DK",
    "sg:address":"T\u00f8rvelodsvej 1",
    "sg:city":"Liseleje",
    "sg:orig_category":"Campingvogne",
    "sg:phone":"+45 47 74 79 08",
    "sg:postcode":"3360",
    "sg:province":"Danmark",
    "wof:name":"Asserbo Campingudlejning",
    "wof:placetype":"venue"
},
  "geometry": {"coordinates":[11.9824790955,56.0044174194],"type":"Point"}
}