{
  "type": "Feature",
  "properties": {
    "addr:full":"Vestergade 2 Randers Danmark 8900",
    "addr:housenumber":"2",
    "addr:postcode":"8900",
    "addr:street":"Vestergade",
    "iso:country":"DK",
    "sg:address":"Vestergade 2",
    "sg:city":"Randers",
    "sg:orig_category":"\u00c3\u2020ldreorganisationer og klubber",
    "sg:phone":"+45 86 42 84 56",
    "sg:postcode":"8900",
    "sg:province":"Danmark",
    "wof:name":"\u00c6ldre Sagen",
    "wof:placetype":"venue"
},
  "geometry": {"coordinates":[10.0328111649,56.460308075],"type":"Point"}
}