{
  "type": "Feature",
  "properties": {
    "addr:full":"Floras Alle 14 Vanl\u00f8se Danmark 2720",
    "addr:housenumber":"14",
    "addr:postcode":"2720",
    "addr:street":"Floras Alle",
    "iso:country":"DK",
    "sg:address":"Floras Alle 14",
    "sg:city":"Vanl\u00f8se",
    "sg:orig_category":"Reklamebureauer",
    "sg:phone":"+45 38 74 05 99",
    "sg:postcode":"2720",
    "sg:province":"Danmark",
    "wof:name":"OEST Reklame ApS",
    "wof:placetype":"venue"
},
  "geometry": {"coordinates":[10.4985952377,60.3006744385],"type":"Point"}
}