{
  "type": "Feature",
  "properties": {
    "iso:country":"DK",
    "sg:address":"Stokrosevej 9",
    "sg:city":"Nyk\u00f8bing",
    "sg:orig_category":"Vagtbureauer",
    "sg:phone":"+45 59 93 09 59",
    "sg:postcode":"4500",
    "sg:province":"Danmark",
    "sg:website":"www.raahage.dk",
    "wof:name":"Raahage Vagtservice",
    "wof:placetype":"venue"
},
  "geometry": {"coordinates":[16.0969600677,78.3159866333],"type":"Point"}
}