{
  "type": "Feature",
  "properties": {
    "addr:full":"Krusemyntegade 19 K\u00f8benhavn Danmark 1318",
    "addr:housenumber":"19;1318",
    "addr:street":"Krusemyntegade",
    "iso:country":"DK",
    "sg:address":"Krusemyntegade 19",
    "sg:city":"K\u00f8benhavn",
    "sg:orig_category":"Arkitekter",
    "sg:phone":"+45 33 32 62 99",
    "sg:postcode":"1318",
    "sg:province":"Danmark",
    "wof:name":"Schultz, Ole",
    "wof:placetype":"venue"
},
  "geometry": {"coordinates":[12.5872001648,55.6876983643],"type":"Point"}
}