{
  "type": "Feature",
  "properties": {
    "addr:full":"v/ Henning Biil, Dronning Olgas Vej 1, 1. Frederiksberg Danmark 2000",
    "addr:housenumber":"1 1",
    "addr:postcode":"2000",
    "addr:street":"Dronning Olgas Vej",
    "iso:country":"DK",
    "sg:address":"v/ Henning Biil, Dronning Olgas Vej 1, 1.",
    "sg:city":"Frederiksberg",
    "sg:orig_category":"Grundejerforeninger",
    "sg:phone":"+45 38 34 44 08",
    "sg:postcode":"2000",
    "sg:province":"Danmark",
    "wof:name":"Grundejerforeningen Enghellen",
    "wof:placetype":"venue"
},
  "geometry": {"coordinates":[12.513299942,55.6789207458],"type":"Point"}
}