{
  "type": "Feature",
  "properties": {
    "addr:full":"Vibevej 31 K\u00f8benhavn NV Danmark 2400",
    "addr:housenumber":"31",
    "addr:postcode":"2400",
    "addr:street":"Vibevej",
    "iso:country":"DK",
    "sg:address":"Vibevej 31",
    "sg:city":"K\u00f8benhavn NV",
    "sg:orig_category":"Papirvarer",
    "sg:phone":"+45 38 34 73 05",
    "sg:postcode":"2400",
    "sg:province":"Danmark",
    "wof:name":"IVA/REGAL ApS, Papirvarefabrikken",
    "wof:placetype":"venue"
},
  "geometry": {"coordinates":[-117.02272033689999,38.5024604797],"type":"Point"}
}