{
  "type": "Feature",
  "properties": {
    "addr:full":"Krystalv\u00e6nget 10 Ferritslev Danmark 5863",
    "addr:housenumber":"10",
    "addr:postcode":"5863",
    "addr:street":"Krystalvaenget",
    "iso:country":"DK",
    "sg:address":"Krystalv\u00e6nget 10",
    "sg:city":"Ferritslev",
    "sg:orig_category":"Varmeforsyning",
    "sg:postcode":"5863",
    "sg:province":"Danmark",
    "wof:name":"Varmecentralen i Ferritslev",
    "wof:placetype":"venue"
},
  "geometry": {"coordinates":[10.5848035812,55.3093643188],"type":"Point"}
}