{
  "type": "Feature",
  "properties": {
    "iso:country":"DK",
    "sg:address":"Riddergade 6",
    "sg:city":"Fredericia",
    "sg:orig_category":"Zoneterapeuter",
    "sg:phone":"+45 75 92 98 39",
    "sg:postcode":"7000",
    "sg:province":"Danmark",
    "sg:website":"www.m-vonsild.subnet.dk",
    "wof:name":"Riddergades Fodklinik",
    "wof:placetype":"venue"
},
  "geometry": {"coordinates":[9.7558641434,55.5682106018],"type":"Point"}
}