{
  "type": "Feature",
  "properties": {
    "addr:full":"Landpolitiass.: Ellef Bender, M\u00f8llevej 2 Haarby Danmark 5683",
    "addr:housenumber":"2",
    "addr:postcode":"5683",
    "addr:street":"Mollevej",
    "iso:country":"DK",
    "sg:address":"Landpolitiass.: Ellef Bender, M\u00f8llevej 2",
    "sg:city":"Haarby",
    "sg:orig_category":"Politi",
    "sg:phone":"+45 64 72 14 48",
    "sg:postcode":"5683",
    "sg:province":"Danmark",
    "wof:name":"Politikontoret p\u00e5 Haarby R\u00e5dhus",
    "wof:placetype":"venue"
},
  "geometry": {"coordinates":[10.1234750748,55.2234535217],"type":"Point"}
}