{
  "type": "Feature",
  "properties": {
    "addr:full":"Egevej 16, Skuldelev Skibby Danmark 4050",
    "addr:housenumber":"16",
    "addr:postcode":"4050",
    "addr:street":"Egevej",
    "iso:country":"DK",
    "sg:address":"Egevej 16, Skuldelev",
    "sg:city":"Skibby",
    "sg:orig_category":"Finmekanikere",
    "sg:phone":"+45 47 52 05 01",
    "sg:postcode":"4050",
    "sg:province":"Danmark",
    "wof:name":"Nielsen, J\u00f8rgen",
    "wof:placetype":"venue"
},
  "geometry": {"coordinates":[11.9594116211,55.7502975464],"type":"Point"}
}