{
  "type": "Feature",
  "properties": {
    "addr:full":"Tibberup Alle 2 Esperg\u00e6rde Danmark 3060",
    "addr:housenumber":"2",
    "addr:postcode":"3060",
    "addr:street":"Tibberup Alle",
    "iso:country":"DK",
    "sg:address":"Tibberup Alle 2",
    "sg:city":"Esperg\u00e6rde",
    "sg:orig_category":"Engros handel",
    "sg:phone":"+45 49 13 03 23",
    "sg:postcode":"3060",
    "sg:province":"Danmark",
    "wof:name":"Direct Link Merchandising",
    "wof:placetype":"venue"
},
  "geometry": {"coordinates":[11.6512403488,47.8390617371],"type":"Point"}
}