{
  "type": "Feature",
  "properties": {
    "addr:full":"Tingstedvej 42, Reerslev Hedehusene Danmark 2640",
    "addr:housenumber":"42",
    "addr:postcode":"2640",
    "addr:street":"Tingstedvej",
    "iso:country":"DK",
    "sg:address":"Tingstedvej 42, Reerslev",
    "sg:city":"Hedehusene",
    "sg:orig_category":"Fritidsklubber",
    "sg:phone":"+45 43 35 35 60",
    "sg:postcode":"2640",
    "sg:province":"Danmark",
    "wof:name":"Reerslev Fritids- og Ungdomsklub",
    "wof:placetype":"venue"
},
  "geometry": {"coordinates":[12.1993551254,55.6496009827],"type":"Point"}
}