{
  "type": "Feature",
  "properties": {
    "addr:full":"Hedeskovvej 30 Lystrup Danmark 8520",
    "addr:housenumber":"30",
    "addr:postcode":"8520",
    "addr:street":"Hedeskovvej",
    "iso:country":"DK",
    "sg:address":"Hedeskovvej 30",
    "sg:city":"Lystrup",
    "sg:orig_category":"Dentallaboratorier",
    "sg:phone":"+45 86 22 15 78",
    "sg:postcode":"8520",
    "sg:province":"Danmark",
    "wof:name":"Kops, Alice",
    "wof:placetype":"venue"
},
  "geometry": {"coordinates":[10.2279996872,56.236869812],"type":"Point"}
}