{
  "type": "Feature",
  "properties": {
    "addr:full":"F\u00e6r\u00f8vej 12 Herning Danmark 7400",
    "addr:housenumber":"12",
    "addr:postcode":"7400",
    "addr:street":"Faerovej",
    "iso:country":"DK",
    "sg:address":"F\u00e6r\u00f8vej 12",
    "sg:city":"Herning",
    "sg:orig_category":"Skilte",
    "sg:phone":"+45 21 25 23 58",
    "sg:postcode":"7400",
    "sg:province":"Danmark",
    "wof:name":"Bogh Skilte",
    "wof:placetype":"venue"
},
  "geometry": {"coordinates":[8.9768896103,56.1374168396],"type":"Point"}
}