{
  "type": "Feature",
  "properties": {
    "addr:full":"Hestetorvet 7 Roskilde Danmark 4000",
    "addr:housenumber":"7",
    "addr:postcode":"4000",
    "addr:street":"Hestetorvet",
    "iso:country":"DK",
    "sg:address":"Hestetorvet 7",
    "sg:city":"Roskilde",
    "sg:orig_category":"Bodegaer",
    "sg:phone":"+45 46 35 71 33",
    "sg:postcode":"4000",
    "sg:province":"Danmark",
    "wof:name":"Georges Bodega",
    "wof:placetype":"venue"
},
  "geometry": {"coordinates":[12.089094162,55.6395606995],"type":"Point"}
}