{
  "type": "Feature",
  "properties": {
    "addr:full":"Hjortdalvej 5, Arnborg Herning Danmark 7400",
    "addr:housenumber":"5",
    "addr:postcode":"7400",
    "addr:street":"Hjortdalvej;Arnborg",
    "iso:country":"DK",
    "sg:address":"Hjortdalvej 5, Arnborg",
    "sg:city":"Herning",
    "sg:orig_category":"Overfladebehandling",
    "sg:phone":"+45 97 14 98 16",
    "sg:postcode":"7400",
    "sg:province":"Danmark",
    "wof:name":"Alb\u00e6k Sandbl\u00e6sning",
    "wof:placetype":"venue"
},
  "geometry": {"coordinates":[8.9768896103,56.1374168396],"type":"Point"}
}