{
  "type": "Feature",
  "properties": {
    "addr:full":"Folehaven 2 Valby Danmark 2500",
    "addr:housenumber":"2",
    "addr:postcode":"2500",
    "addr:street":"Folehaven",
    "iso:country":"DK",
    "sg:address":"Folehaven 2",
    "sg:city":"Valby",
    "sg:orig_category":"Bagere",
    "sg:phone":"+45 36 17 95 10",
    "sg:postcode":"2500",
    "sg:province":"Danmark",
    "wof:name":"Rigtige Bager, Den",
    "wof:placetype":"venue"
},
  "geometry": {"coordinates":[12.506582,55.650776],"type":"Point"}
}