{
  "type": "Feature",
  "properties": {
    "addr:full":"Kirkegade 7 Ikast Danmark 7430",
    "addr:housenumber":"7",
    "addr:postcode":"7430",
    "addr:street":"Kirkegade",
    "iso:country":"DK",
    "sg:address":"Kirkegade 7",
    "sg:city":"Ikast",
    "sg:orig_category":"Ungdomscentre",
    "sg:phone":"+45 97 25 09 11",
    "sg:postcode":"7430",
    "sg:province":"Danmark",
    "sg:website":"www.hedebocentret.dk",
    "wof:name":"Hedebocentret",
    "wof:placetype":"venue"
},
  "geometry": {"coordinates":[9.1537380219,56.1371421814],"type":"Point"}
}