{
  "type": "Feature",
  "properties": {
    "addr:full":"Arne Poulsens Vej 7, st. mf Vejle Danmark 7100",
    "addr:housenumber":"7",
    "addr:postcode":"7100",
    "addr:street":"Arne Poulsens Vej",
    "iso:country":"DK",
    "sg:address":"Arne Poulsens Vej 7, st. mf",
    "sg:city":"Vejle",
    "sg:classifiers":[
        {
            "category":"Retail",
            "subcategory":"Storage",
            "type":"Services"
        }
    ],
    "sg:phone":"+45 75 83 61 06",
    "sg:postcode":"7100",
    "sg:province":"Danmark",
    "sg:tags":[
        "edb",
        "hardware",
        "-"
    ],
    "wof:name":"PR-Computer",
    "wof:placetype":"venue"
},
  "geometry": {"coordinates":[9.5368051529,55.7113952637],"type":"Point"}
}