{
  "type": "Feature",
  "properties": {
    "addr:full":"Skyttebjerg 69 N\u00e6rum Danmark 2850",
    "addr:housenumber":"69",
    "addr:postcode":"2850",
    "addr:street":"Skyttebjerg",
    "iso:country":"DK",
    "sg:address":"Skyttebjerg 69",
    "sg:city":"N\u00e6rum",
    "sg:orig_category":"Vinduespolering",
    "sg:phone":"+45 45 80 22 63",
    "sg:postcode":"2850",
    "sg:province":"Danmark",
    "wof:name":"S\u00f8ller\u00f8d-N\u00e6rum Vinduespolering",
    "wof:placetype":"venue"
},
  "geometry": {"coordinates":[-89.99810791020001,38.1321372986],"type":"Point"}
}