{
  "type": "Feature",
  "properties": {
    "addr:full":"Lars Kuhlmanns Vej 1, Postboks 67 Hornb\u00e6k Danmark 3100",
    "addr:housenumber":"1;67",
    "addr:postcode":"3100",
    "addr:street":"Lars Kuhlmanns Vej;Hornbaek Danmark",
    "iso:country":"DK",
    "sg:address":"Lars Kuhlmanns Vej 1, Postboks 67",
    "sg:city":"Hornb\u00e6k",
    "sg:orig_category":"Arkitekter",
    "sg:phone":"+45 49 70 44 66",
    "sg:postcode":"3100",
    "sg:province":"Danmark",
    "wof:name":"Sjodt, P.",
    "wof:placetype":"venue"
},
  "geometry": {"coordinates":[12.4300451279,56.0916366577],"type":"Point"}
}