{
  "type": "Feature",
  "properties": {
    "addr:full":"Mindevej 10, 1., Postboks 183 Vejen Danmark 6600",
    "addr:housenumber":"10 1;183",
    "addr:postcode":"6600",
    "addr:street":"Mindevej;Postboks",
    "iso:country":"DK",
    "sg:address":"Mindevej 10, 1., Postboks 183",
    "sg:city":"Vejen",
    "sg:orig_category":"Lejerforeninger",
    "sg:phone":"+45 75 36 45 99",
    "sg:postcode":"6600",
    "sg:province":"Danmark",
    "wof:name":"Lejernes Landsorg. i Ribe Amt",
    "wof:placetype":"venue"
},
  "geometry": {"coordinates":[9.1396121979,55.4778175354],"type":"Point"}
}