{
  "type": "Feature",
  "properties": {
    "addr:full":"Gingsholmvej 1 Dronninglund Danmark 9330",
    "addr:housenumber":"1",
    "addr:postcode":"9330",
    "addr:street":"Gingsholmvej",
    "iso:country":"DK",
    "sg:address":"Gingsholmvej 1",
    "sg:city":"Dronninglund",
    "sg:orig_category":"Tagrenovering",
    "sg:phone":"+45 98 86 17 11",
    "sg:postcode":"9330",
    "sg:province":"Danmark",
    "wof:name":"NHK Service & Tagrenovering ApS",
    "wof:placetype":"venue"
},
  "geometry": {"coordinates":[10.2344369888,57.1398620605],"type":"Point"}
}