{
  "type": "Feature",
  "properties": {
    "addr:full":"Ryesgade 90 A K\u00f8benhavn \u00d8 Danmark 2100",
    "addr:housenumber":"90 a",
    "addr:postcode":"2100",
    "addr:street":"Ryesgade;Kobenhavn O Danmark",
    "iso:country":"DK",
    "sg:address":"Ryesgade 90 A",
    "sg:city":"K\u00f8benhavn \u00d8",
    "sg:orig_category":"Kulturelle foreninger",
    "sg:phone":"+45 35 43 66 90",
    "sg:postcode":"2100",
    "sg:province":"Danmark",
    "sg:website":"www.tibetkomite.dk",
    "wof:name":"St\u00f8ttekomiteen for Tibet",
    "wof:placetype":"venue"
},
  "geometry": {"coordinates":[11.6836299896,60.2548065186],"type":"Point"}
}