{
  "type": "Feature",
  "properties": {
    "addr:full":"\u00d8stergade 2 Assens Danmark 5610",
    "addr:housenumber":"2",
    "addr:postcode":"5610",
    "addr:street":"Ostergade",
    "iso:country":"DK",
    "sg:address":"\u00d8stergade 2",
    "sg:city":"Assens",
    "sg:orig_category":"Kontorartikler",
    "sg:phone":"+45 64 71 24 12",
    "sg:postcode":"5610",
    "sg:province":"Danmark",
    "wof:name":"K. Hammer Hansen A/S",
    "wof:placetype":"venue"
},
  "geometry": {"coordinates":[9.8931713104,55.2698860168],"type":"Point"}
}