{
  "type": "Feature",
  "properties": {
    "addr:full":"Uhrevej 13 Jordrup Danmark 6064",
    "addr:housenumber":"13",
    "addr:postcode":"6064",
    "addr:street":"Uhrevej",
    "iso:country":"DK",
    "sg:address":"Uhrevej 13",
    "sg:city":"Jordrup",
    "sg:orig_category":"Maskinstationer",
    "sg:phone":"+45 75 55 80 38",
    "sg:postcode":"6064",
    "sg:province":"Danmark",
    "wof:name":"Uhre Maskinstation",
    "wof:placetype":"venue"
},
  "geometry": {"coordinates":[9.3249607086,55.5346107483],"type":"Point"}
}