{
  "type": "Feature",
  "properties": {
    "addr:full":"Mejerivej 2, \u00d8dis Vamdrup Danmark 6580",
    "addr:housenumber":"2",
    "addr:postcode":"6580",
    "addr:street":"Mejerivej",
    "iso:country":"DK",
    "sg:address":"Mejerivej 2, \u00d8dis",
    "sg:city":"Vamdrup",
    "sg:orig_category":"Revisorer",
    "sg:phone":"+45 75 59 84 82",
    "sg:postcode":"6580",
    "sg:province":"Danmark",
    "wof:name":"Petersen, Kjeld Kyhl",
    "wof:placetype":"venue"
},
  "geometry": {"coordinates":[9.2839107513,55.4266548157],"type":"Point"}
}