{
  "type": "Feature",
  "properties": {
    "iso:country":"DK",
    "sg:address":"Birkeh\u00f8jvej 11",
    "sg:city":"Gelsted",
    "sg:orig_category":"Korn og foderstoffer",
    "sg:phone":"+45 64 49 12 23",
    "sg:postcode":"5591",
    "sg:province":"Danmark",
    "wof:name":"Gelsted Foderstofforretning",
    "wof:placetype":"venue"
},
  "geometry": {"coordinates":[9.9756994247,55.3959960938],"type":"Point"}
}