{
  "type": "Feature",
  "properties": {
    "addr:full":"Toftegaardsvej 1 Aalestrup Danmark 9620",
    "addr:housenumber":"1",
    "addr:postcode":"9620",
    "addr:street":"Toftegaardsvej",
    "iso:country":"DK",
    "sg:address":"Toftegaardsvej 1",
    "sg:city":"Aalestrup",
    "sg:orig_category":"Revisorer",
    "sg:phone":"+45 98 64 17 11",
    "sg:postcode":"9620",
    "sg:province":"Danmark",
    "wof:name":"Aalestrup Landbocenter",
    "wof:placetype":"venue"
},
  "geometry": {"coordinates":[9.489068985,56.6963272095],"type":"Point"}
}