{
  "type": "Feature",
  "properties": {
    "addr:full":"Hovedgaden 29 Fakse Ladeplads Danmark 4654",
    "addr:housenumber":"29",
    "addr:postcode":"4654",
    "addr:street":"Hovedgaden",
    "iso:country":"DK",
    "sg:address":"Hovedgaden 29",
    "sg:city":"Fakse Ladeplads",
    "sg:orig_category":"Turistbureau og -information",
    "sg:phone":"+45 56 71 60 34",
    "sg:postcode":"4654",
    "sg:province":"Danmark",
    "sg:website":"www.faksekysten.dk",
    "wof:name":"Fakse Kystens Turistbureau",
    "wof:placetype":"venue"
},
  "geometry": {"coordinates":[12.1675262451,55.2180252075],"type":"Point"}
}