{
  "type": "Feature",
  "properties": {
    "iso:country":"DK",
    "sg:address":"Bylderup-Bov Bygade 7",
    "sg:city":"Bylderup-Bov",
    "sg:orig_category":"Bagere",
    "sg:phone":"+45 74 76 23 10",
    "sg:postcode":"6372",
    "sg:province":"Danmark",
    "wof:name":"Nissens Bageri",
    "wof:placetype":"venue"
},
  "geometry": {"coordinates":[9.086152,54.941536],"type":"Point"}
}