{
  "type": "Feature",
  "properties": {
    "iso:country":"DK",
    "sg:address":"Bredgade 10",
    "sg:city":"Kolding",
    "sg:classifiers":[
        {
            "category":"Banks & Credit Unions",
            "subcategory":"Bank",
            "type":"Services"
        }
    ],
    "sg:phone":"+45 76 30 86 30",
    "sg:postcode":"6000",
    "sg:province":"Danmark",
    "sg:tags":[
        "banker"
    ],
    "sg:website":"www.sparbankvest.dk",
    "wof:name":"Sparbank Vest",
    "wof:placetype":"venue"
},
  "geometry": {"coordinates":[9.4720277786,55.4889068604],"type":"Point"}
}