{
  "type": "Feature",
  "properties": {
    "addr:full":"Absalonsgade 6 Sor\u00f8 Danmark 4180",
    "addr:housenumber":"6",
    "addr:postcode":"4180",
    "addr:street":"Absalonsgade",
    "iso:country":"DK",
    "sg:address":"Absalonsgade 6",
    "sg:city":"Sor\u00f8",
    "sg:orig_category":"Fodterapeuter",
    "sg:phone":"+45 57 83 59 16",
    "sg:postcode":"4180",
    "sg:province":"Danmark",
    "wof:name":"Klinik for Fodterapi",
    "wof:placetype":"venue"
},
  "geometry": {"coordinates":[11.5585355759,55.4343910217],"type":"Point"}
}