{
  "type": "Feature",
  "properties": {
    "addr:full":"\u00d8stre Stationsvej 43 Odense C Danmark 5000",
    "addr:housenumber":"43",
    "addr:postcode":"5000",
    "addr:street":"Ostre Stationsvej",
    "iso:country":"DK",
    "sg:address":"\u00d8stre Stationsvej 43",
    "sg:city":"Odense C",
    "sg:classifiers":[
        {
            "category":"Arts & Performance",
            "subcategory":"Art Gallery",
            "type":"Entertainment"
        }
    ],
    "sg:phone":"+45 66 14 24 12",
    "sg:postcode":"5000",
    "sg:province":"Danmark",
    "sg:tags":[
        "ventilation"
    ],
    "wof:name":"Ventilationsgruppen ApS",
    "wof:placetype":"venue"
},
  "geometry": {"coordinates":[10.3821115494,55.4002037048],"type":"Point"}
}