{
  "type": "Feature",
  "properties": {
    "addr:full":"Ole R\u00f8mers Vej 12 Kolding Danmark 6000",
    "addr:housenumber":"12",
    "addr:postcode":"6000",
    "addr:street":"Ole Romers Vej",
    "iso:country":"DK",
    "sg:address":"Ole R\u00f8mers Vej 12",
    "sg:city":"Kolding",
    "sg:orig_category":"Autoreparation og -service",
    "sg:phone":"+45 75 53 53 11",
    "sg:postcode":"6000",
    "sg:province":"Danmark",
    "wof:name":"Buchvaldts Autoservice",
    "wof:placetype":"venue"
},
  "geometry": {"coordinates":[9.4604682922,55.5064315796],"type":"Point"}
}