{
  "type": "Feature",
  "properties": {
    "iso:country":"DK",
    "sg:address":"Tannisbugtvej 103, Tversted",
    "sg:city":"Bindslev",
    "sg:orig_category":"Gallerier",
    "sg:phone":"+45 98 93 19 90",
    "sg:postcode":"9881",
    "sg:province":"Danmark",
    "wof:name":"Solkilde, Galleri",
    "wof:placetype":"venue"
},
  "geometry": {"coordinates":[10.1876945496,57.5861968994],"type":"Point"}
}