{
  "type": "Feature",
  "properties": {
    "addr:full":"Vestergade 30 Ikast Danmark 7430",
    "addr:housenumber":"30",
    "addr:postcode":"7430",
    "addr:street":"Vestergade",
    "iso:country":"DK",
    "sg:address":"Vestergade 30",
    "sg:city":"Ikast",
    "sg:orig_category":"Diskoteker",
    "sg:phone":"+45 97 25 20 82",
    "sg:postcode":"7430",
    "sg:province":"Danmark",
    "wof:name":"Charly's Diskotek - Bar",
    "wof:placetype":"venue"
},
  "geometry": {"coordinates":[9.150680542,56.139251709],"type":"Point"}
}