{
  "type": "Feature",
  "properties": {
    "addr:full":"Petersmindevej 8 Juelsminde Danmark 7130",
    "addr:housenumber":"8",
    "addr:postcode":"7130",
    "addr:street":"Petersmindevej",
    "iso:country":"DK",
    "sg:address":"Petersmindevej 8",
    "sg:city":"Juelsminde",
    "sg:orig_category":"Musik og sang",
    "sg:phone":"+45 21 92 41 02",
    "sg:postcode":"7130",
    "sg:province":"Danmark",
    "wof:name":"Juelsminde Pigegarde",
    "wof:placetype":"venue"
},
  "geometry": {"coordinates":[9.9951686859,55.7047424316],"type":"Point"}
}