{
  "type": "Feature",
  "properties": {
    "iso:country":"DK",
    "sg:address":"Fmd.: Ruth de Place, Jordbrovej 23 st. th",
    "sg:city":"\u00c5rhus N",
    "sg:orig_category":"Grundejerforeninger",
    "sg:phone":"+45 86 10 17 41",
    "sg:postcode":"8200",
    "sg:province":"Danmark",
    "wof:name":"Grundejerforeningen Elleh\u00f8j",
    "wof:placetype":"venue"
},
  "geometry": {"coordinates":[-94.23114776609999,47.9078102112],"type":"Point"}
}