{
  "type": "Feature",
  "properties": {
    "iso:country":"DK",
    "sg:address":"Smedegade 11, R\u00e5rup",
    "sg:city":"Juelsminde",
    "sg:orig_category":"Konservatorer",
    "sg:phone":"+45 75 68 51 73",
    "sg:postcode":"7130",
    "sg:province":"Danmark",
    "wof:name":"Jensen, Palle Libner",
    "wof:placetype":"venue"
},
  "geometry": {"coordinates":[10.0143985748,55.7135848999],"type":"Point"}
}