{
  "type": "Feature",
  "properties": {
    "addr:full":"Flinterupvej 17, Flinterup Sor\u00f8 Danmark 4180",
    "addr:housenumber":"17",
    "addr:postcode":"4180",
    "addr:street":"Flinterupvej",
    "iso:country":"DK",
    "sg:address":"Flinterupvej 17, Flinterup",
    "sg:city":"Sor\u00f8",
    "sg:orig_category":"Kirker",
    "sg:postcode":"4180",
    "sg:province":"Danmark",
    "wof:name":"Flinterup Kirke",
    "wof:placetype":"venue"
},
  "geometry": {"coordinates":[11.556344986,55.432800293],"type":"Point"}
}