{
  "type": "Feature",
  "properties": {
    "addr:full":"Lindeparken 1 Silkeborg Danmark 8600",
    "addr:housenumber":"1",
    "addr:postcode":"8600",
    "addr:street":"Lindeparken",
    "iso:country":"DK",
    "sg:address":"Lindeparken 1",
    "sg:city":"Silkeborg",
    "sg:orig_category":"Kollegier",
    "sg:postcode":"8600",
    "sg:province":"Danmark",
    "wof:name":"S\u00f8holt Kollegiet",
    "wof:placetype":"venue"
},
  "geometry": {"coordinates":[9.5658922195,56.1826171875],"type":"Point"}
}