{
  "type": "Feature",
  "properties": {
    "addr:full":"B\u00f8gevang 41 Vejle Danmark 7100",
    "addr:housenumber":"41",
    "addr:postcode":"7100",
    "addr:street":"Bogevang",
    "iso:country":"DK",
    "sg:address":"B\u00f8gevang 41",
    "sg:city":"Vejle",
    "sg:orig_category":"Fotografer",
    "sg:phone":"+45 75 83 17 68",
    "sg:postcode":"7100",
    "sg:province":"Danmark",
    "wof:name":"Bentes Foto",
    "wof:placetype":"venue"
},
  "geometry": {"coordinates":[9.528260231,55.6998710632],"type":"Point"}
}