{
  "type": "Feature",
  "properties": {
    "addr:full":"Sn\u00e6bumvej 9, Sn\u00e6bum Hobro Danmark 9500",
    "addr:housenumber":"9",
    "addr:postcode":"9500",
    "addr:street":"Snaebumvej",
    "iso:country":"DK",
    "sg:address":"Sn\u00e6bumvej 9, Sn\u00e6bum",
    "sg:city":"Hobro",
    "sg:orig_category":"Murermestre",
    "sg:phone":"+45 98 54 84 96",
    "sg:postcode":"9500",
    "sg:province":"Danmark",
    "sg:website":"www.verner-hk.dk",
    "wof:name":"Kristiansen ApS, Murer- og kloakfirmaet Verner H.",
    "wof:placetype":"venue"
},
  "geometry": {"coordinates":[9.7946596146,56.6382789612],"type":"Point"}
}