{
  "type": "Feature",
  "properties": {
    "addr:full":"Follerup M\u00f8llevej 6, Follerup Mark Fredericia Danmark 7000",
    "addr:housenumber":"6",
    "addr:postcode":"7000",
    "addr:street":"Mollevej;Follerup Mark",
    "iso:country":"DK",
    "sg:address":"Follerup M\u00f8llevej 6, Follerup Mark",
    "sg:city":"Fredericia",
    "sg:orig_category":"Asfalt",
    "sg:phone":"+45 75 95 42 22",
    "sg:postcode":"7000",
    "sg:province":"Danmark",
    "wof:name":"Colas Danmark A/S",
    "wof:placetype":"venue"
},
  "geometry": {"coordinates":[9.7591047287,55.566368103],"type":"Point"}
}