{
  "type": "Feature",
  "properties": {
    "addr:full":"Nyk\u00f8bingvej 219, Radsted Saksk\u00f8bing Danmark 4990",
    "addr:housenumber":"219",
    "addr:postcode":"4990",
    "addr:street":"Nykobingvej",
    "iso:country":"DK",
    "sg:address":"Nyk\u00f8bingvej 219, Radsted",
    "sg:city":"Saksk\u00f8bing",
    "sg:orig_category":"Zoneterapeuter",
    "sg:phone":"+45 54 70 53 77",
    "sg:postcode":"4990",
    "sg:province":"Danmark",
    "wof:name":"Andersen, Sonja",
    "wof:placetype":"venue"
},
  "geometry": {"coordinates":[11.6875448227,54.7894821167],"type":"Point"}
}