{
  "type": "Feature",
  "properties": {
    "addr:full":"\u00d8ver\u00f8dvej 11 Holte Danmark 2840",
    "addr:housenumber":"11",
    "addr:postcode":"2840",
    "addr:street":"Overodvej",
    "iso:country":"DK",
    "sg:address":"\u00d8ver\u00f8dvej 11",
    "sg:city":"Holte",
    "sg:orig_category":"Ejendomshandel",
    "sg:phone":"+45 45 41 20 41",
    "sg:postcode":"2840",
    "sg:province":"Danmark",
    "wof:name":"DanBolig",
    "wof:placetype":"venue"
},
  "geometry": {"coordinates":[12.4706554413,55.8122367859],"type":"Point"}
}