{
  "type": "Feature",
  "properties": {
    "iso:country":"DK",
    "sg:address":"Houmeden 6",
    "sg:city":"Randers",
    "sg:orig_category":"Sko",
    "sg:phone":"+45 86 40 35 26",
    "sg:postcode":"8900",
    "sg:province":"Danmark",
    "wof:name":"Bianco Footwear",
    "wof:placetype":"venue"
},
  "geometry": {"coordinates":[10.0353507996,56.4606781006],"type":"Point"}
}