{
  "type": "Feature",
  "properties": {
    "addr:full":"\u00d8stervej 2 Holeby Danmark 4960",
    "addr:housenumber":"2",
    "addr:postcode":"4960",
    "addr:street":"Ostervej",
    "iso:country":"DK",
    "sg:address":"\u00d8stervej 2",
    "sg:city":"Holeby",
    "sg:orig_category":"Motorfabrikker",
    "sg:phone":"+45 54 69 31 00",
    "sg:postcode":"4960",
    "sg:province":"Danmark",
    "wof:name":"MAN B&W Diesel A/S",
    "wof:placetype":"venue"
},
  "geometry": {"coordinates":[11.4749298096,54.7086029053],"type":"Point"}
}