{
  "type": "Feature",
  "properties": {
    "addr:full":"Tryghusvej 9 Nakskov Danmark 4900",
    "addr:housenumber":"9",
    "addr:postcode":"4900",
    "addr:street":"Tryghusvej",
    "iso:country":"DK",
    "sg:address":"Tryghusvej 9",
    "sg:city":"Nakskov",
    "sg:orig_category":"Autoreparation og -service",
    "sg:phone":"+45 54 92 40 40",
    "sg:postcode":"4900",
    "sg:province":"Danmark",
    "wof:name":"Tryghus Auto",
    "wof:placetype":"venue"
},
  "geometry": {"coordinates":[11.1275453568,54.7895469666],"type":"Point"}
}