{
  "type": "Feature",
  "properties": {
    "iso:country":"DK",
    "sg:address":"Piledamsvej 80",
    "sg:city":"Kolding",
    "sg:orig_category":"Bodegaer",
    "sg:phone":"+45 75 50 38 69",
    "sg:postcode":"6000",
    "sg:province":"Danmark",
    "wof:name":"Snapstinget",
    "wof:placetype":"venue"
},
  "geometry": {"coordinates":[9.46916008,55.4796943665],"type":"Point"}
}