{
  "type": "Feature",
  "properties": {
    "addr:full":"Vestre Skovvej 1 Grenaa Danmark 8500",
    "addr:housenumber":"1",
    "addr:postcode":"8500",
    "addr:street":"Vestre Skovvej",
    "iso:country":"DK",
    "sg:address":"Vestre Skovvej 1",
    "sg:city":"Grenaa",
    "sg:orig_category":"Motorkontorer",
    "sg:phone":"+45 86 32 10 11",
    "sg:postcode":"8500",
    "sg:province":"Danmark",
    "wof:name":"Motorkontoret i Grenaa.",
    "wof:placetype":"venue"
},
  "geometry": {"coordinates":[10.8766469955,56.4037132263],"type":"Point"}
}