{
  "type": "Feature",
  "properties": {
    "addr:full":"\u00c5vej 2 Dianalund Danmark 4293",
    "addr:housenumber":"2",
    "addr:postcode":"4293",
    "addr:street":"Aavej",
    "iso:country":"DK",
    "sg:address":"\u00c5vej 2",
    "sg:city":"Dianalund",
    "sg:orig_category":"Beslagsmede",
    "sg:phone":"+45 58 28 67 17",
    "sg:postcode":"4293",
    "sg:province":"Danmark",
    "wof:name":"Street Smeden",
    "wof:placetype":"venue"
},
  "geometry": {"coordinates":[11.4872293472,55.534450531],"type":"Point"}
}