{
  "type": "Feature",
  "properties": {
    "addr:full":"Digesvalevej 1 Svenstrup Danmark 9230",
    "addr:housenumber":"1",
    "addr:postcode":"9230",
    "addr:street":"Digesvalevej",
    "iso:country":"DK",
    "sg:address":"Digesvalevej 1",
    "sg:city":"Svenstrup",
    "sg:orig_category":"Engros handel",
    "sg:phone":"+45 98 38 00 47",
    "sg:postcode":"9230",
    "sg:province":"Danmark",
    "wof:name":"NaviCom Marine",
    "wof:placetype":"venue"
},
  "geometry": {"coordinates":[9.8142557144,56.9622497559],"type":"Point"}
}