{
  "type": "Feature",
  "properties": {
    "addr:full":"Svanem\u00f8llevej 70 Hellerup Danmark 2900",
    "addr:housenumber":"70",
    "addr:postcode":"2900",
    "addr:street":"Svanemollevej",
    "iso:country":"DK",
    "sg:address":"Svanem\u00f8llevej 70",
    "sg:city":"Hellerup",
    "sg:orig_category":"Frankeringsmaskiner",
    "sg:phone":"+45 39 61 18 04",
    "sg:postcode":"2900",
    "sg:province":"Danmark",
    "sg:website":"www.danastar.dk",
    "wof:name":"Danastar ApS",
    "wof:placetype":"venue"
},
  "geometry": {"coordinates":[12.5745992661,55.7248687744],"type":"Point"}
}