{
  "type": "Feature",
  "properties": {
    "addr:full":"Vestervej 23 Ringsted Danmark 4100",
    "addr:housenumber":"23",
    "addr:postcode":"4100",
    "addr:street":"Vestervej",
    "iso:country":"DK",
    "sg:address":"Vestervej 23",
    "sg:city":"Ringsted",
    "sg:orig_category":"Faglige organisationer og foreninger",
    "sg:phone":"+45 57 66 05 50",
    "sg:postcode":"4100",
    "sg:province":"Danmark",
    "sg:website":"www.hk.dk/ringsted",
    "wof:name":"HK, Ringsted-Sor\u00f8",
    "wof:placetype":"venue"
},
  "geometry": {"coordinates":[11.7824401855,55.4402694702],"type":"Point"}
}