{
  "type": "Feature",
  "properties": {
    "iso:country":"DK",
    "sg:address":"Fraugde Fritidscenter, Stat-Ene-Vej 18 - 22, Fraugde",
    "sg:city":"Odense S\u00d8",
    "sg:orig_category":"Lokalarkiver",
    "sg:postcode":"5220",
    "sg:province":"Danmark",
    "wof:name":"Lokalhistorisk Arkiv for Fraugde Sogn",
    "wof:placetype":"venue"
},
  "geometry": {"coordinates":[10.4583454132,55.3316917419],"type":"Point"}
}