{
  "type": "Feature",
  "properties": {
    "iso:country":"DK",
    "sg:address":"Tv\u00e6rgade 135",
    "sg:city":"Malling",
    "sg:orig_category":"INGENI\u00c3\u02dcRER",
    "sg:phone":"+45 86 93 38 02",
    "sg:postcode":"8340",
    "sg:province":"Danmark",
    "wof:name":"Caddi",
    "wof:placetype":"venue"
},
  "geometry": {"coordinates":[10.20225811,56.0350914001],"type":"Point"}
}