{
  "type": "Feature",
  "properties": {
    "addr:full":"v/Erik Grodtkj\u00e6r, Sprog\u00f8vej 13, 4. Frederiksberg Danmark 2000",
    "addr:housenumber":"13 4",
    "addr:postcode":"2000",
    "addr:street":"Sprogovej",
    "iso:country":"DK",
    "sg:address":"v/Erik Grodtkj\u00e6r, Sprog\u00f8vej 13, 4.",
    "sg:city":"Frederiksberg",
    "sg:orig_category":"Musik og sang",
    "sg:phone":"+45 38 86 08 64",
    "sg:postcode":"2000",
    "sg:province":"Danmark",
    "wof:name":"Concord Brass Band",
    "wof:placetype":"venue"
},
  "geometry": {"coordinates":[12.5131654739,55.6791915894],"type":"Point"}
}