{
  "type": "Feature",
  "properties": {
    "addr:full":"N\u00f8rremarken 37-39 Sk\u00e5rup Danmark 5881",
    "addr:housenumber":"37-39",
    "addr:postcode":"5881",
    "addr:street":"Norremarken",
    "iso:country":"DK",
    "sg:address":"N\u00f8rremarken 37-39",
    "sg:city":"Sk\u00e5rup",
    "sg:orig_category":"Typehuse",
    "sg:phone":"+45 62 23 11 28",
    "sg:postcode":"5881",
    "sg:province":"Danmark",
    "wof:name":"Jensen Sk\u00e5rup A/S, J\u00f8rgen",
    "wof:placetype":"venue"
},
  "geometry": {"coordinates":[10.6812353134,55.0959205627],"type":"Point"}
}