{
  "type": "Feature",
  "properties": {
    "addr:full":"Fmd.: Ulla Ditlevsen, Parkvej 2, Sdr. H\u00f8e Bramming Danmark 6740",
    "addr:housenumber":"2",
    "addr:postcode":"6740",
    "addr:street":"Parkvej;Sdr. Hoe",
    "iso:country":"DK",
    "sg:address":"Fmd.: Ulla Ditlevsen, Parkvej 2, Sdr. H\u00f8e",
    "sg:city":"Bramming",
    "sg:orig_category":"Kulturelle foreninger",
    "sg:phone":"+45 75 17 38 20",
    "sg:postcode":"6740",
    "sg:province":"Danmark",
    "wof:name":"Sydvestjyske Venner af Israel",
    "wof:placetype":"venue"
},
  "geometry": {"coordinates":[8.6974096298,55.4655303955],"type":"Point"}
}