{
  "type": "Feature",
  "properties": {
    "addr:full":"Kl\u00f8vervang 1 Grenaa Danmark 8500",
    "addr:housenumber":"1",
    "addr:postcode":"8500",
    "addr:street":"Klovervang",
    "iso:country":"DK",
    "sg:address":"Kl\u00f8vervang 1",
    "sg:city":"Grenaa",
    "sg:orig_category":"Misbrugscentre",
    "sg:phone":"+45 86 32 28 51",
    "sg:postcode":"8500",
    "sg:province":"Danmark",
    "wof:name":"Alkoholr\u00e5dgivningen.",
    "wof:placetype":"venue"
},
  "geometry": {"coordinates":[10.8661165237,56.4182891846],"type":"Point"}
}