{
  "type": "Feature",
  "properties": {
    "addr:full":"Nebelvej 42 Vorbasse Danmark 6623",
    "addr:housenumber":"42",
    "addr:postcode":"6623",
    "addr:street":"Nebelvej",
    "iso:country":"DK",
    "sg:address":"Nebelvej 42",
    "sg:city":"Vorbasse",
    "sg:orig_category":"Vinduespolering",
    "sg:phone":"+45 75 33 38 12",
    "sg:postcode":"6623",
    "sg:province":"Danmark",
    "wof:name":"Vick's Reng\u00f8ring og vinduespolering",
    "wof:placetype":"venue"
},
  "geometry": {"coordinates":[9.0229625702,55.6358566284],"type":"Point"}
}