{
  "type": "Feature",
  "properties": {
    "addr:full":"Poseidonvej 33 Aalborg S\u00d8 Danmark 9210",
    "addr:housenumber":"33",
    "addr:postcode":"9210",
    "addr:street":"Poseidonvej",
    "iso:country":"DK",
    "sg:address":"Poseidonvej 33",
    "sg:city":"Aalborg S\u00d8",
    "sg:orig_category":"Arkitekter",
    "sg:phone":"+45 98 14 37 30",
    "sg:postcode":"9210",
    "sg:province":"Danmark",
    "wof:name":"Jakobsen, Hans",
    "wof:placetype":"venue"
},
  "geometry": {"coordinates":[9.9360237122,57.0040016174],"type":"Point"}
}