{
  "type": "Feature",
  "properties": {
    "addr:full":"Jessensgade 3 Horsens Danmark 8700",
    "addr:housenumber":"3",
    "addr:postcode":"8700",
    "addr:street":"Jessensgade",
    "iso:country":"DK",
    "sg:address":"Jessensgade 3",
    "sg:city":"Horsens",
    "sg:orig_category":"Kiropraktorer",
    "sg:phone":"+45 75 61 14 15",
    "sg:postcode":"8700",
    "sg:province":"Danmark",
    "wof:name":"Nielsen, Kenny E.",
    "wof:placetype":"venue"
},
  "geometry": {"coordinates":[9.84420681,55.8621559143],"type":"Point"}
}