{
  "type": "Feature",
  "properties": {
    "addr:full":"Toldbodgade 1 Thisted Danmark 7700",
    "addr:housenumber":"1",
    "addr:postcode":"7700",
    "addr:street":"Toldbodgade",
    "iso:country":"DK",
    "sg:address":"Toldbodgade 1",
    "sg:city":"Thisted",
    "sg:orig_category":"Revisorer",
    "sg:phone":"+45 96 19 43 00",
    "sg:postcode":"7700",
    "sg:province":"Danmark",
    "sg:website":"www.bdo.dk",
    "wof:name":"BDO ScanRevision",
    "wof:placetype":"venue"
},
  "geometry": {"coordinates":[8.6918087006,56.9540672302],"type":"Point"}
}