{
  "type": "Feature",
  "properties": {
    "addr:full":"Br\u00f8dregade 1 Randers Danmark 8900",
    "addr:housenumber":"1",
    "addr:postcode":"8900",
    "addr:street":"Brodregade",
    "iso:country":"DK",
    "sg:address":"Br\u00f8dregade 1",
    "sg:city":"Randers",
    "sg:orig_category":"Lingeri",
    "sg:phone":"+45 86 42 08 33",
    "sg:postcode":"8900",
    "sg:province":"Danmark",
    "wof:name":"Hunkem\u00f6ller",
    "wof:placetype":"venue"
},
  "geometry": {"coordinates":[10.0381422043,56.4604797363],"type":"Point"}
}