{
  "type": "Feature",
  "properties": {
    "addr:full":"M\u00f8llevej 20 Give Danmark 7323",
    "addr:housenumber":"20",
    "addr:postcode":"7323",
    "addr:street":"Mollevej",
    "iso:country":"DK",
    "sg:address":"M\u00f8llevej 20",
    "sg:city":"Give",
    "sg:orig_category":"Autoforhandlere",
    "sg:phone":"+45 75 73 13 33",
    "sg:postcode":"7323",
    "sg:province":"Danmark",
    "wof:name":"Autocentrum-Citro\u00ebn Give",
    "wof:placetype":"venue"
},
  "geometry": {"coordinates":[9.2414493561,55.8420600891],"type":"Point"}
}