{
  "type": "Feature",
  "properties": {
    "addr:full":"Havneplads 1 Grenaa Danmark 8500",
    "addr:housenumber":"1",
    "addr:postcode":"8500",
    "addr:street":"Havneplads",
    "iso:country":"DK",
    "sg:address":"Havneplads 1",
    "sg:city":"Grenaa",
    "sg:orig_category":"HOTELS: OG MOTELLER",
    "sg:phone":"+45 86 32 68 14",
    "sg:postcode":"8500",
    "sg:province":"Danmark",
    "wof:name":"Grenaa Strand, Hotel",
    "wof:placetype":"venue"
},
  "geometry": {"coordinates":[10.9191093445,56.4083328247],"type":"Point"}
}