{
  "type": "Feature",
  "properties": {
    "iso:country":"DK",
    "sg:address":"Holmegade 2",
    "sg:city":"Ulfborg",
    "sg:classifiers":[
        {
            "category":"Banks & Credit Unions",
            "subcategory":"Bank",
            "type":"Services"
        }
    ],
    "sg:phone":"+45 96 93 03 33",
    "sg:postcode":"6990",
    "sg:province":"Danmark",
    "sg:tags":[
        "banker"
    ],
    "sg:website":"www.jyskebank.dk",
    "wof:name":"Jyske Bank Ulfborg",
    "wof:placetype":"venue"
},
  "geometry": {"coordinates":[8.321048,56.2724],"type":"Point"}
}