{
  "type": "Feature",
  "properties": {
    "addr:full":"Kokbjerg 10 Kolding Danmark 6000",
    "addr:housenumber":"10",
    "addr:postcode":"6000",
    "addr:street":"Kokbjerg",
    "iso:country":"DK",
    "sg:address":"Kokbjerg 10",
    "sg:city":"Kolding",
    "sg:orig_category":"Kurerservice",
    "sg:phone":"+45 80 30 22 22",
    "sg:postcode":"6000",
    "sg:province":"Danmark",
    "wof:name":"United Parcel Service",
    "wof:placetype":"venue"
},
  "geometry": {"coordinates":[9.4743728638,55.5346832275],"type":"Point"}
}