{
  "type": "Feature",
  "properties": {
    "addr:full":"Adelgade 24 Hobro Danmark 9500",
    "addr:housenumber":"24",
    "addr:postcode":"9500",
    "addr:street":"Adelgade",
    "iso:country":"DK",
    "sg:address":"Adelgade 24",
    "sg:city":"Hobro",
    "sg:orig_category":"Fotografer",
    "sg:phone":"+45 98 52 16 20",
    "sg:postcode":"9500",
    "sg:province":"Danmark",
    "wof:name":"Kehlet's Eftf./Ingeborg Johansen",
    "wof:placetype":"venue"
},
  "geometry": {"coordinates":[9.7932739258,56.6390914917],"type":"Point"}
}