{
  "type": "Feature",
  "properties": {
    "addr:full":"N\u00f8rreport 18 Randers Danmark 8900",
    "addr:housenumber":"18",
    "addr:postcode":"8900",
    "addr:street":"Norreport",
    "iso:country":"DK",
    "sg:address":"N\u00f8rreport 18",
    "sg:city":"Randers",
    "sg:orig_category":"Pizzeriaer",
    "sg:phone":"+45 86 41 48 44",
    "sg:postcode":"8900",
    "sg:province":"Danmark",
    "wof:name":"Rosa, Pizza",
    "wof:placetype":"venue"
},
  "geometry": {"coordinates":[10.0331039429,56.4634208679],"type":"Point"}
}