{
  "type": "Feature",
  "properties": {
    "addr:full":"L\u00e6ss\u00f8esgade 5 1. K\u00f8benhavn N Danmark 2200",
    "addr:housenumber":"5 1",
    "addr:postcode":"2200",
    "addr:street":"Laessoesgade;Kobenhavn N Danmark",
    "iso:country":"DK",
    "sg:address":"L\u00e6ss\u00f8esgade 5 1.",
    "sg:city":"K\u00f8benhavn N",
    "sg:orig_category":"Reklamebureauer",
    "sg:phone":"+45 35 37 09 82",
    "sg:postcode":"2200",
    "sg:province":"Danmark",
    "wof:name":"B\u00f6rsch Public Relations, J\u00f6rgen",
    "wof:placetype":"venue"
},
  "geometry": {"coordinates":[-76.4168395996,37.452419281],"type":"Point"}
}