{
  "type": "Feature",
  "properties": {
    "iso:country":"DK",
    "sg:address":"Fmd.: J\u00f8rgen Fink, \u00c5vej 1, Hodsager",
    "sg:city":"Aulum",
    "sg:orig_category":"Kirkelige foreninger",
    "sg:phone":"+45 97 47 61 85",
    "sg:postcode":"7490",
    "sg:province":"Danmark",
    "wof:name":"Indre Mission i Hodsager",
    "wof:placetype":"venue"
},
  "geometry": {"coordinates":[8.7971401215,56.2653999329],"type":"Point"}
}