{
  "type": "Feature",
  "properties": {
    "iso:country":"DK",
    "sg:address":"Vestre Tv\u00e6rmole 32",
    "sg:city":"Skagen",
    "sg:orig_category":"Gallerier",
    "sg:phone":"+45 98 45 17 02",
    "sg:postcode":"9990",
    "sg:province":"Danmark",
    "wof:name":"Katedralen, Galleri",
    "wof:placetype":"venue"
},
  "geometry": {"coordinates":[10.5907249451,57.7175369263],"type":"Point"}
}