{
  "type": "Feature",
  "properties": {
    "addr:full":"Fmd.: Bo Mouritzen, Suserupvej 53 Sor\u00f8 Danmark 4180",
    "addr:housenumber":"53",
    "addr:postcode":"4180",
    "addr:street":"Suserupvej",
    "iso:country":"DK",
    "sg:address":"Fmd.: Bo Mouritzen, Suserupvej 53",
    "sg:city":"Sor\u00f8",
    "sg:orig_category":"Politiske foreninger, \u00c3\u02dcvrige",
    "sg:phone":"+45 57 64 84 62",
    "sg:postcode":"4180",
    "sg:province":"Danmark",
    "wof:name":"Folkebev\u00e6gelsen Mod EF-Unionen - Sor\u00f8",
    "wof:placetype":"venue"
},
  "geometry": {"coordinates":[-102.94467926030001,45.4534721375],"type":"Point"}
}