{
  "type": "Feature",
  "properties": {
    "addr:full":"Baldersbuen 16 A, Baldersbr\u00f8nde Hedehusene Danmark 2640",
    "addr:housenumber":"16 a",
    "addr:postcode":"2640",
    "addr:street":"Baldersbuen;Baldersbronde",
    "iso:country":"DK",
    "sg:address":"Baldersbuen 16 A, Baldersbr\u00f8nde",
    "sg:city":"Hedehusene",
    "sg:orig_category":"Grusgrave",
    "sg:phone":"+45 46 56 07 08",
    "sg:postcode":"2640",
    "sg:province":"Danmark",
    "wof:name":"Kallerup Grusgrav A/S",
    "wof:placetype":"venue"
},
  "geometry": {"coordinates":[12.1993551254,55.6496009827],"type":"Point"}
}