{
  "type": "Feature",
  "properties": {
    "addr:full":"Holmekrogen 59 Virum Danmark 2830",
    "addr:housenumber":"59",
    "addr:postcode":"2830",
    "addr:street":"Holmekrogen",
    "iso:country":"DK",
    "sg:address":"Holmekrogen 59",
    "sg:city":"Virum",
    "sg:orig_category":"Kontorartikler",
    "sg:phone":"+45 45 85 62 22",
    "sg:postcode":"2830",
    "sg:province":"Danmark",
    "wof:name":"Gigantkalenderen Krogsgaard",
    "wof:placetype":"venue"
},
  "geometry": {"coordinates":[12.4849052429,55.7961120605],"type":"Point"}
}