{
  "type": "Feature",
  "properties": {
    "addr:full":"Hiller\u00f8dgade 72 K\u00f8benhavn N Danmark 2200",
    "addr:housenumber":"72",
    "addr:postcode":"2200",
    "addr:street":"Hillerodgade;Kobenhavn N Danmark",
    "iso:country":"DK",
    "sg:address":"Hiller\u00f8dgade 72",
    "sg:city":"K\u00f8benhavn N",
    "sg:orig_category":"Alternativ behandling",
    "sg:phone":"+45 38 87 62 21",
    "sg:postcode":"2200",
    "sg:province":"Danmark",
    "wof:name":"Helseklinikken",
    "wof:placetype":"venue"
},
  "geometry": {"coordinates":[-94.444190979,47.9254951477],"type":"Point"}
}