{
  "type": "Feature",
  "properties": {
    "addr:full":"Steng\u00e5rds Plads 6 B \u00d8lstykke Danmark 3650",
    "addr:housenumber":"6 b",
    "addr:postcode":"3650",
    "addr:street":"Stengaards Plads",
    "iso:country":"DK",
    "sg:address":"Steng\u00e5rds Plads 6 B",
    "sg:city":"\u00d8lstykke",
    "sg:orig_category":"Ungdomsklubber",
    "sg:phone":"+45 47 17 56 68",
    "sg:postcode":"3650",
    "sg:province":"Danmark",
    "wof:name":"Juniorklub Steng\u00e5rden",
    "wof:placetype":"venue"
},
  "geometry": {"coordinates":[77.2480392456,14.1354398727],"type":"Point"}
}