{
  "type": "Feature",
  "properties": {
    "addr:full":"Mosede Strandvej 68 Greve Danmark 2670",
    "addr:housenumber":"68",
    "addr:postcode":"2670",
    "addr:street":"Mosede Strandvej",
    "iso:country":"DK",
    "sg:address":"Mosede Strandvej 68",
    "sg:city":"Greve",
    "sg:orig_category":"Ildfaste materialer",
    "sg:phone":"+45 43 60 13 47",
    "sg:postcode":"2670",
    "sg:province":"Danmark",
    "wof:name":"Pollux Import/Eksport ApS",
    "wof:placetype":"venue"
},
  "geometry": {"coordinates":[12.280081749,55.5682411194],"type":"Point"}
}