{
  "type": "Feature",
  "properties": {
    "addr:full":"Gl. Feggesundvej 29 Vesl\u00f8s Danmark 7742",
    "addr:housenumber":"29",
    "addr:postcode":"7742",
    "addr:street":"Gl. Feggesundvej",
    "iso:country":"DK",
    "sg:address":"Gl. Feggesundvej 29",
    "sg:city":"Vesl\u00f8s",
    "sg:orig_category":"Cafeterier",
    "sg:phone":"+45 97 99 33 06",
    "sg:postcode":"7742",
    "sg:province":"Danmark",
    "wof:name":"Hann\u00e6s Hallen",
    "wof:placetype":"venue"
},
  "geometry": {"coordinates":[-82.51066589360001,38.4133300781],"type":"Point"}
}