{
  "type": "Feature",
  "properties": {
    "addr:full":"N\u00f8rregade 48 K\u00f8ge Danmark 4600",
    "addr:housenumber":"48",
    "addr:postcode":"4600",
    "addr:street":"Norregade",
    "iso:country":"DK",
    "sg:address":"N\u00f8rregade 48",
    "sg:city":"K\u00f8ge",
    "sg:orig_category":"Renserier",
    "sg:phone":"+45 56 65 28 28",
    "sg:postcode":"4600",
    "sg:province":"Danmark",
    "wof:name":"Rekord-Rens",
    "wof:placetype":"venue"
},
  "geometry": {"coordinates":[12.1843709946,55.4599151611],"type":"Point"}
}