{
  "type": "Feature",
  "properties": {
    "addr:full":"v/ Bent Nielsen, Bakkegaardsvej 7, Veddum Hadsund Danmark 9560",
    "addr:housenumber":"7",
    "addr:postcode":"9560",
    "addr:street":"Bakkegaardsvej;Veddum",
    "iso:country":"DK",
    "sg:address":"v/ Bent Nielsen, Bakkegaardsvej 7, Veddum",
    "sg:city":"Hadsund",
    "sg:orig_category":"Hobbybetonede foreninger",
    "sg:phone":"+45 98 58 51 12",
    "sg:postcode":"9560",
    "sg:province":"Danmark",
    "wof:name":"Veddum Husflidsforening Thor",
    "wof:placetype":"venue"
},
  "geometry": {"coordinates":[10.115904808,56.7150764465],"type":"Point"}
}