{
  "type": "Feature",
  "properties": {
    "addr:full":"Lokesvej 1 Viborg Danmark 8800",
    "addr:housenumber":"1",
    "addr:postcode":"8800",
    "addr:street":"Lokesvej",
    "iso:country":"DK",
    "sg:address":"Lokesvej 1",
    "sg:city":"Viborg",
    "sg:orig_category":"Fritidsklubber",
    "sg:phone":"+45 87 25 33 93",
    "sg:postcode":"8800",
    "sg:province":"Danmark",
    "wof:name":"Klubben Lokesvej",
    "wof:placetype":"venue"
},
  "geometry": {"coordinates":[9.4157800674,56.4703903198],"type":"Point"}
}