{
  "type": "Feature",
  "properties": {
    "iso:country":"DK",
    "sg:address":"Fmd.: Erik Konrad Nielsen, Halk\u00e6rvej 67 B, Halk\u00e6r",
    "sg:city":"Nibe",
    "sg:orig_category":"Hobbybetonede foreninger",
    "sg:phone":"+45 98 66 92 35",
    "sg:postcode":"9240",
    "sg:province":"Danmark",
    "wof:name":"Nibe Brevdueforening",
    "wof:placetype":"venue"
},
  "geometry": {"coordinates":[9.6393280029,56.982421875],"type":"Point"}
}