{
  "type": "Feature",
  "properties": {
    "iso:country":"DK",
    "sg:address":"Lindekrogvej 24, Vinstrup",
    "sg:city":"Fuglebjerg",
    "sg:orig_category":"Psykologer, praktiserende",
    "sg:phone":"+45 57 84 99 24",
    "sg:postcode":"4250",
    "sg:province":"Danmark",
    "wof:name":"Larsen, Lisbet R.",
    "wof:placetype":"venue"
},
  "geometry": {"coordinates":[11.5452251434,55.3061332703],"type":"Point"}
}