{
  "type": "Feature",
  "properties": {
    "addr:full":"Lyseg\u00e5rdsvej 4, Hyrup Stouby Danmark 7140",
    "addr:housenumber":"4",
    "addr:postcode":"7140",
    "addr:street":"Lysegaardsvej",
    "iso:country":"DK",
    "sg:address":"Lyseg\u00e5rdsvej 4, Hyrup",
    "sg:city":"Stouby",
    "sg:orig_category":"Forsamlingshuse",
    "sg:phone":"+45 23 43 87 50",
    "sg:postcode":"7140",
    "sg:province":"Danmark",
    "wof:name":"Hyrup Forsamlingshus I/S",
    "wof:placetype":"venue"
},
  "geometry": {"coordinates":[9.7896795273,55.7045059204],"type":"Point"}
}