{
  "type": "Feature",
  "properties": {
    "addr:full":"B\u00e6ksg\u00e5rdvej 7 Give Danmark 7323",
    "addr:housenumber":"7",
    "addr:postcode":"7323",
    "addr:street":"Baeksgaardvej",
    "iso:country":"DK",
    "sg:address":"B\u00e6ksg\u00e5rdvej 7",
    "sg:city":"Give",
    "sg:orig_category":"Autoreparation og -service",
    "sg:phone":"+45 75 73 22 11",
    "sg:postcode":"7323",
    "sg:province":"Danmark",
    "wof:name":"Laursen, Karl Peter F.",
    "wof:placetype":"venue"
},
  "geometry": {"coordinates":[9.2362060547,55.845413208],"type":"Point"}
}