{
  "type": "Feature",
  "properties": {
    "addr:full":"Fmd.: T. Thymark, Gadstrupparken 41 Gadstrup Danmark 4621",
    "addr:housenumber":"41",
    "addr:postcode":"4621",
    "addr:street":"Gadstrupparken",
    "iso:country":"DK",
    "sg:address":"Fmd.: T. Thymark, Gadstrupparken 41",
    "sg:city":"Gadstrup",
    "sg:orig_category":"Grundejerforeninger",
    "sg:postcode":"4621",
    "sg:province":"Danmark",
    "wof:name":"Gadstrupparken, Grundejerforeningen",
    "wof:placetype":"venue"
},
  "geometry": {"coordinates":[12.0978450775,55.5737800598],"type":"Point"}
}