{
  "type": "Feature",
  "properties": {
    "addr:full":"Hedelyparken 100 Greve Danmark 2670",
    "addr:housenumber":"100",
    "addr:postcode":"2670",
    "addr:street":"Hedelyparken",
    "iso:country":"DK",
    "sg:address":"Hedelyparken 100",
    "sg:city":"Greve",
    "sg:orig_category":"Fritidshuse",
    "sg:phone":"+45 43 69 06 12",
    "sg:postcode":"2670",
    "sg:province":"Danmark",
    "wof:name":"\u00d8ernes Sommerhus Udlejning",
    "wof:placetype":"venue"
},
  "geometry": {"coordinates":[12.2908000946,55.5908966064],"type":"Point"}
}