{
  "type": "Feature",
  "properties": {
    "addr:full":"Fmd.: Leif Overgaard, Skelskovvej 39, Tommerup St Tommerup Danmark 5690",
    "addr:housenumber":"39",
    "addr:postcode":"5690",
    "addr:street":"Skelskovvej;St",
    "iso:country":"DK",
    "sg:address":"Fmd.: Leif Overgaard, Skelskovvej 39, Tommerup St",
    "sg:city":"Tommerup",
    "sg:orig_category":"Hobbybetonede foreninger",
    "sg:phone":"+45 64 76 20 96",
    "sg:postcode":"5690",
    "sg:province":"Danmark",
    "wof:name":"Danmarks Fjerkr\u00e6avlerforening for Raceavl, Dansk Landh\u00f8nsekl",
    "wof:placetype":"venue"
},
  "geometry": {"coordinates":[10.2489509583,55.3236503601],"type":"Point"}
}