{
  "type": "Feature",
  "properties": {
    "addr:full":"L\u00f8ven\u00f8rnsgade 9 A Horsens Danmark 8700",
    "addr:housenumber":"9 a",
    "addr:postcode":"8700",
    "addr:street":"Lovenornsgade",
    "iso:country":"DK",
    "sg:address":"L\u00f8ven\u00f8rnsgade 9 A",
    "sg:city":"Horsens",
    "sg:orig_category":"Genbrugsbutikker",
    "sg:phone":"+45 75 61 31 31",
    "sg:postcode":"8700",
    "sg:province":"Danmark",
    "wof:name":"Bl\u00e5 Kors",
    "wof:placetype":"venue"
},
  "geometry": {"coordinates":[9.8432445526,55.8621063232],"type":"Point"}
}