{
  "type": "Feature",
  "properties": {
    "addr:full":"\u00c5lbrobuen 10 Herlev Danmark 2730",
    "addr:housenumber":"10",
    "addr:postcode":"2730",
    "addr:street":"Aalbrobuen",
    "iso:country":"DK",
    "sg:address":"\u00c5lbrobuen 10",
    "sg:city":"Herlev",
    "sg:orig_category":"Malermestre",
    "sg:phone":"+45 44 53 06 99",
    "sg:postcode":"2730",
    "sg:province":"Danmark",
    "wof:name":"Bengtsen, Freddy",
    "wof:placetype":"venue"
},
  "geometry": {"coordinates":[12.4147291183,55.7264595032],"type":"Point"}
}