{
  "type": "Feature",
  "properties": {
    "addr:full":"Brogade 28 Kjellerup Danmark 8620",
    "addr:housenumber":"28",
    "addr:postcode":"8620",
    "addr:street":"Brogade",
    "iso:country":"DK",
    "sg:address":"Brogade 28",
    "sg:city":"Kjellerup",
    "sg:orig_category":"Murermestre",
    "sg:phone":"+45 86 88 27 43",
    "sg:postcode":"8620",
    "sg:province":"Danmark",
    "sg:website":"www.byggaranti.dk",
    "wof:name":"Br\u00f8dl\u00f8s ApS, J\u00f8rgen",
    "wof:placetype":"venue"
},
  "geometry": {"coordinates":[9.4354305267,56.2870674133],"type":"Point"}
}