{
  "type": "Feature",
  "properties": {
    "addr:full":"Odinparken 6 Viborg Danmark 8800",
    "addr:housenumber":"6",
    "addr:postcode":"8800",
    "addr:street":"Odinparken",
    "iso:country":"DK",
    "sg:address":"Odinparken 6",
    "sg:city":"Viborg",
    "sg:orig_category":"EDB - udstyr",
    "sg:phone":"+45 86 60 00 56",
    "sg:postcode":"8800",
    "sg:province":"Danmark",
    "wof:name":"PC - H\u00e5ndv\u00e6rkeren",
    "wof:placetype":"venue"
},
  "geometry": {"coordinates":[9.4217309952,56.4654159546],"type":"Point"}
}