{
  "type": "Feature",
  "properties": {
    "addr:full":"Randersvej 11 Viborg Danmark 8800",
    "addr:housenumber":"11",
    "addr:postcode":"8800",
    "addr:street":"Randersvej",
    "iso:country":"DK",
    "sg:address":"Randersvej 11",
    "sg:city":"Viborg",
    "sg:orig_category":"Cykler",
    "sg:phone":"+45 86 67 23 56",
    "sg:postcode":"8800",
    "sg:province":"Danmark",
    "wof:name":"Overlund Cykel- & Pl\u00e6neklipperservice",
    "wof:placetype":"venue"
},
  "geometry": {"coordinates":[9.4204082489,56.4511528015],"type":"Point"}
}