{
  "type": "Feature",
  "properties": {
    "addr:full":"Kongstedsvej 15 Slagelse Danmark 4200",
    "addr:housenumber":"15",
    "addr:postcode":"4200",
    "addr:street":"Kongstedsvej",
    "iso:country":"DK",
    "sg:address":"Kongstedsvej 15",
    "sg:city":"Slagelse",
    "sg:orig_category":"Dyrefoder",
    "sg:phone":"+45 58 52 63 53",
    "sg:postcode":"4200",
    "sg:province":"Danmark",
    "wof:name":"Dyrenes Eldorado",
    "wof:placetype":"venue"
},
  "geometry": {"coordinates":[11.3385362625,55.3921356201],"type":"Point"}
}