{
  "type": "Feature",
  "properties": {
    "addr:full":"Bygaden 14 Lystrup Danmark 8520",
    "addr:housenumber":"14",
    "addr:postcode":"8520",
    "addr:street":"Bygaden",
    "iso:country":"DK",
    "sg:address":"Bygaden 14",
    "sg:city":"Lystrup",
    "sg:orig_category":"INGENI\u00c3\u02dcRER",
    "sg:phone":"+45 86 22 87 55",
    "sg:postcode":"8520",
    "sg:province":"Danmark",
    "wof:name":"Aaen",
    "wof:placetype":"venue"
},
  "geometry": {"coordinates":[10.2335920334,56.2317237854],"type":"Point"}
}