{
  "type": "Feature",
  "properties": {
    "addr:full":"Alexandragade 8C, 2. Odense C Danmark 5000",
    "addr:housenumber":"8c 2",
    "addr:postcode":"5000",
    "addr:street":"Alexandragade",
    "iso:country":"DK",
    "sg:address":"Alexandragade 8C, 2.",
    "sg:city":"Odense C",
    "sg:classifiers":[
        {
            "category":"Professional",
            "subcategory":"Computer Services",
            "type":"Services"
        }
    ],
    "sg:phone":"+45 66 11 25 07",
    "sg:postcode":"5000",
    "sg:province":"Danmark",
    "sg:tags":[
        "edb",
        "-",
        "software"
    ],
    "wof:name":"Soccer Update",
    "wof:placetype":"venue"
},
  "geometry": {"coordinates":[10.3952131271,55.3925132751],"type":"Point"}
}