{
  "type": "Feature",
  "properties": {
    "iso:country":"DK",
    "sg:address":"Ulstedvej 15",
    "sg:city":"Hals",
    "sg:orig_category":"Genbrugspladser",
    "sg:phone":"+45 24 28 29 17",
    "sg:postcode":"9370",
    "sg:province":"Danmark",
    "wof:name":"Hals Genbrugsplads",
    "wof:placetype":"venue"
},
  "geometry": {"coordinates":[10.2990322113,57.0036048889],"type":"Point"}
}