{
  "type": "Feature",
  "properties": {
    "addr:full":"Dronningensgade 44 Odense C Danmark 5000",
    "addr:housenumber":"44",
    "addr:postcode":"5000",
    "addr:street":"Dronningensgade",
    "iso:country":"DK",
    "sg:address":"Dronningensgade 44",
    "sg:city":"Odense C",
    "sg:classifiers":[
        {
            "category":"Communications",
            "type":"Services"
        }
    ],
    "sg:phone":"+45 66 12 29 58",
    "sg:postcode":"5000",
    "sg:province":"Danmark",
    "sg:tags":[
        "og",
        "tv",
        "radio"
    ],
    "wof:name":"Wilsons Radio",
    "wof:placetype":"venue"
},
  "geometry": {"coordinates":[10.3747377396,55.3962745667],"type":"Point"}
}