{
  "type": "Feature",
  "properties": {
    "addr:full":"\u00d8resundsvej 28 K\u00f8benhavn S Danmark 2300",
    "addr:housenumber":"28",
    "addr:postcode":"2300",
    "addr:street":"Oresundsvej;S Danmark",
    "iso:country":"DK",
    "sg:address":"\u00d8resundsvej 28",
    "sg:city":"K\u00f8benhavn S",
    "sg:orig_category":"Kiosker",
    "sg:phone":"+45 32 58 26 50",
    "sg:postcode":"2300",
    "sg:province":"Danmark",
    "wof:name":"D\u00f8gncenter",
    "wof:placetype":"venue"
},
  "geometry": {"coordinates":[-82.5031585693,38.4148597717],"type":"Point"}
}