{
  "type": "Feature",
  "properties": {
    "iso:country":"DK",
    "sg:address":"Lichtenbergsgade 3 C",
    "sg:city":"Horsens",
    "sg:orig_category":"Advokater",
    "sg:phone":"+45 75 62 37 55",
    "sg:postcode":"8700",
    "sg:province":"Danmark",
    "wof:name":"Advokaterne Posthuscentret",
    "wof:placetype":"venue"
},
  "geometry": {"coordinates":[9.8426713943,55.8610877991],"type":"Point"}
}