{
  "type": "Feature",
  "properties": {
    "addr:full":"Industrivej 6 Lunderskov Danmark 6640",
    "addr:housenumber":"6",
    "addr:postcode":"6640",
    "addr:street":"Industrivej",
    "iso:country":"DK",
    "sg:address":"Industrivej 6",
    "sg:city":"Lunderskov",
    "sg:orig_category":"Elektronik",
    "sg:phone":"+45 75 58 58 22",
    "sg:postcode":"6640",
    "sg:province":"Danmark",
    "wof:name":"Tantec A/S",
    "wof:placetype":"venue"
},
  "geometry": {"coordinates":[9.2983627319,55.4793586731],"type":"Point"}
}