{
  "type": "Feature",
  "properties": {
    "addr:full":"Grarupvej 31 Haderslev Danmark 6100",
    "addr:housenumber":"31",
    "addr:postcode":"6100",
    "addr:street":"Grarupvej",
    "iso:country":"DK",
    "sg:address":"Grarupvej 31",
    "sg:city":"Haderslev",
    "sg:orig_category":"Kirker",
    "sg:postcode":"6100",
    "sg:province":"Danmark",
    "wof:name":"Grarup Kirke",
    "wof:placetype":"venue"
},
  "geometry": {"coordinates":[9.5981254578,55.2408103943],"type":"Point"}
}