{
  "type": "Feature",
  "properties": {
    "iso:country":"DK",
    "sg:address":"Frejaparken 12",
    "sg:city":"Aalborg",
    "sg:classifiers":[
        {
            "category":"Home & Garden",
            "subcategory":"Home Furnishings",
            "type":"Retail Goods"
        }
    ],
    "sg:phone":"+45 98 16 49 96",
    "sg:postcode":"9000",
    "sg:province":"Danmark",
    "sg:tags":[
        "gardiner"
    ],
    "wof:name":"H\u00f8gsted Gardiner",
    "wof:placetype":"venue"
},
  "geometry": {"coordinates":[9.8921012878,57.0508308411],"type":"Point"}
}