{
  "type": "Feature",
  "properties": {
    "addr:full":"Br\u00f8nsholmdalsvej 42 Kokkedal Danmark 2980",
    "addr:housenumber":"42",
    "addr:postcode":"2980",
    "addr:street":"Bronsholmdalsvej",
    "iso:country":"DK",
    "sg:address":"Br\u00f8nsholmdalsvej 42",
    "sg:city":"Kokkedal",
    "sg:orig_category":"Integrerede institutioner",
    "sg:phone":"+45 45 86 70 83",
    "sg:postcode":"2980",
    "sg:province":"Danmark",
    "wof:name":"\u00c5dalen, Vuggestue / B\u00f8rnehave",
    "wof:placetype":"venue"
},
  "geometry": {"coordinates":[12.4906005859,55.9034767151],"type":"Point"}
}