{
  "type": "Feature",
  "properties": {
    "addr:full":"Fmd.: Ove Nielsen, S\u00f8ndervang 13 Bredebro Danmark 6261",
    "addr:housenumber":"13",
    "addr:postcode":"6261",
    "addr:street":"Ove",
    "iso:country":"DK",
    "sg:address":"Fmd.: Ove Nielsen, S\u00f8ndervang 13",
    "sg:city":"Bredebro",
    "sg:orig_category":"Kirkelige foreninger",
    "sg:phone":"+45 74 71 18 75",
    "sg:postcode":"6261",
    "sg:province":"Danmark",
    "wof:name":"Indre Missions Samfund, Bredebro",
    "wof:placetype":"venue"
},
  "geometry": {"coordinates":[8.8284835815,55.0566978455],"type":"Point"}
}