{
  "type": "Feature",
  "properties": {
    "addr:full":"Bredgade 101 Pandrup Danmark 9490",
    "addr:housenumber":"101",
    "addr:postcode":"9490",
    "addr:street":"Bredgade",
    "iso:country":"DK",
    "sg:address":"Bredgade 101",
    "sg:city":"Pandrup",
    "sg:orig_category":"Plejecentre",
    "sg:phone":"+45 98 24 72 33",
    "sg:postcode":"9490",
    "sg:province":"Danmark",
    "wof:name":"Pandrup Plejecenter",
    "wof:placetype":"venue"
},
  "geometry": {"coordinates":[9.6759290695,57.2152404785],"type":"Point"}
}