{
  "type": "Feature",
  "properties": {
    "iso:country":"DK",
    "sg:address":"Njalsgade 21 F",
    "sg:city":"K\u00f8benhavn S",
    "sg:orig_category":"Reklamebureauer",
    "sg:phone":"+45 32 64 11 11",
    "sg:postcode":"2300",
    "sg:province":"Danmark",
    "wof:name":"Podium",
    "wof:placetype":"venue"
},
  "geometry": {"coordinates":[-72.4185409546,41.0425262451],"type":"Point"}
}