{
  "type": "Feature",
  "properties": {
    "addr:full":"Vestergade 30 Vejle Danmark 7100",
    "addr:housenumber":"30",
    "addr:postcode":"7100",
    "addr:street":"Vestergade",
    "iso:country":"DK",
    "sg:address":"Vestergade 30",
    "sg:city":"Vejle",
    "sg:orig_category":"Antikvariater",
    "sg:phone":"+45 75 83 85 75",
    "sg:postcode":"7100",
    "sg:province":"Danmark",
    "wof:name":"Bogcentralen/Vejle Antikvariat",
    "wof:placetype":"venue"
},
  "geometry": {"coordinates":[9.5370082855,55.7133750916],"type":"Point"}
}