{
  "type": "Feature",
  "properties": {
    "addr:full":"S\u00f8ndergade 28, 1 Kolding Danmark 6000",
    "addr:housenumber":"28 1",
    "addr:postcode":"6000",
    "addr:street":"Sondergade",
    "iso:country":"DK",
    "sg:address":"S\u00f8ndergade 28, 1",
    "sg:city":"Kolding",
    "sg:classifiers":[
        {
            "category":"Personal",
            "subcategory":"Massage",
            "type":"Services"
        }
    ],
    "sg:phone":"+45 75 50 14 65",
    "sg:postcode":"6000",
    "sg:province":"Danmark",
    "wof:name":"Caribian Sun and Massage",
    "wof:placetype":"venue"
},
  "geometry": {"coordinates":[9.4723491669,55.4869842529],"type":"Point"}
}