{
  "type": "Feature",
  "properties": {
    "addr:full":"Lystrupvej 250 Lystrup Danmark 8520",
    "addr:housenumber":"250",
    "addr:postcode":"8520",
    "addr:street":"Lystrupvej",
    "iso:country":"DK",
    "sg:address":"Lystrupvej 250",
    "sg:city":"Lystrup",
    "sg:orig_category":"Zoneterapeuter",
    "sg:phone":"+45 86 22 00 35",
    "sg:postcode":"8520",
    "sg:province":"Danmark",
    "wof:name":"Appel, Else",
    "wof:placetype":"venue"
},
  "geometry": {"coordinates":[10.2308921814,56.2335205078],"type":"Point"}
}