{
  "type": "Feature",
  "properties": {
    "addr:full":"Holl\u00e6nderdybet 2 K\u00f8benhavn S Danmark 2300",
    "addr:housenumber":"2",
    "addr:postcode":"2300",
    "addr:street":"Hollaenderdybet;S Danmark",
    "iso:country":"DK",
    "sg:address":"Holl\u00e6nderdybet 2",
    "sg:city":"K\u00f8benhavn S",
    "sg:orig_category":"Fotokopiering",
    "sg:phone":"+45 32 57 70 18",
    "sg:postcode":"2300",
    "sg:province":"Danmark",
    "wof:name":"Copy Print",
    "wof:placetype":"venue"
},
  "geometry": {"coordinates":[-78.1299133301,36.7267417908],"type":"Point"}
}