{
  "type": "Feature",
  "properties": {
    "addr:full":"Fredensgade 3 Frederikssund Danmark 3600",
    "addr:housenumber":"3",
    "addr:postcode":"3600",
    "addr:street":"Fredensgade",
    "iso:country":"DK",
    "sg:address":"Fredensgade 3",
    "sg:city":"Frederikssund",
    "sg:orig_category":"Ejendomsadministration",
    "sg:phone":"+45 47 37 38 28",
    "sg:postcode":"3600",
    "sg:province":"Danmark",
    "sg:website":"www.freja-udlejning.dk",
    "wof:name":"Freja Ejendomsadministration",
    "wof:placetype":"venue"
},
  "geometry": {"coordinates":[12.0585050583,55.8386421204],"type":"Point"}
}