{
  "type": "Feature",
  "properties": {
    "iso:country":"DK",
    "sg:address":"Frederiksberggade 16",
    "sg:city":"K\u00f8benhavn",
    "sg:orig_category":"Advokater",
    "sg:phone":"+45 33 11 45 46",
    "sg:postcode":"1459",
    "sg:province":"Danmark",
    "wof:name":"Stolt, Marianne Kj\u00e6r",
    "wof:placetype":"venue"
},
  "geometry": {"coordinates":[12.5700597763,55.6768302917],"type":"Point"}
}