{
  "type": "Feature",
  "properties": {
    "addr:full":"Tingvej 8 - 10 Herning Danmark 7400",
    "addr:housenumber":"8 10",
    "addr:postcode":"7400",
    "addr:street":"Tingvej",
    "iso:country":"DK",
    "sg:address":"Tingvej 8 - 10",
    "sg:city":"Herning",
    "sg:orig_category":"Autoreparation og -service",
    "sg:phone":"+45 97 12 03 11",
    "sg:postcode":"7400",
    "sg:province":"Danmark",
    "wof:name":"Pedersen & Graversen",
    "wof:placetype":"venue"
},
  "geometry": {"coordinates":[8.9898824692,56.1451454163],"type":"Point"}
}