{
  "type": "Feature",
  "properties": {
    "iso:country":"DK",
    "sg:address":"Skolegade 3",
    "sg:city":"Herning",
    "sg:orig_category":"Bagere",
    "sg:phone":"+45 97 12 06 24",
    "sg:postcode":"7400",
    "sg:province":"Danmark",
    "wof:name":"Skolegades Bageri",
    "wof:placetype":"venue"
},
  "geometry": {"coordinates":[8.972284,56.136513],"type":"Point"}
}