{
  "type": "Feature",
  "properties": {
    "iso:country":"DK",
    "sg:address":"Viborgvej 289, Hasle",
    "sg:city":"\u00c5rhus V",
    "sg:orig_category":"Autoelektro",
    "sg:phone":"+45 86 24 02 44",
    "sg:postcode":"8210",
    "sg:province":"Danmark",
    "wof:name":"Ketner A/S, Axel",
    "wof:placetype":"venue"
},
  "geometry": {"coordinates":[14.7065896988,55.1830787659],"type":"Point"}
}