{
  "type": "Feature",
  "properties": {
    "iso:country":"DK",
    "sg:address":"Alrunevej 2 A",
    "sg:city":"Hellerup",
    "sg:orig_category":"Advokater",
    "sg:phone":"+45 39 76 17 80",
    "sg:postcode":"2900",
    "sg:province":"Danmark",
    "wof:name":"Ottosen-St\u00f8tt, Jens E.",
    "wof:placetype":"venue"
},
  "geometry": {"coordinates":[12.5404815674,55.735912323],"type":"Point"}
}