{
  "type": "Feature",
  "properties": {
    "addr:full":"Vestergade 12 Vojens Danmark 6500",
    "addr:housenumber":"12",
    "addr:postcode":"6500",
    "addr:street":"Vestergade",
    "iso:country":"DK",
    "sg:address":"Vestergade 12",
    "sg:city":"Vojens",
    "sg:orig_category":"Servicestationer",
    "sg:phone":"+45 74 54 21 38",
    "sg:postcode":"6500",
    "sg:province":"Danmark",
    "wof:name":"Q8 service",
    "wof:placetype":"venue"
},
  "geometry": {"coordinates":[9.3020324707,55.2463340759],"type":"Point"}
}