{
  "type": "Feature",
  "properties": {
    "addr:full":"Onsild skole, Pr\u00e6stemarken 2, Sdr. Onsild Hobro Danmark 9500",
    "addr:housenumber":"2",
    "addr:postcode":"9500",
    "addr:street":"Praestemarken;Sdr. Onsild",
    "iso:country":"DK",
    "sg:address":"Onsild skole, Pr\u00e6stemarken 2, Sdr. Onsild",
    "sg:city":"Hobro",
    "sg:orig_category":"Ungdomsklubber",
    "sg:postcode":"9500",
    "sg:province":"Danmark",
    "wof:name":"Onsild Ungdomsklub",
    "wof:placetype":"venue"
},
  "geometry": {"coordinates":[9.7946596146,56.6382789612],"type":"Point"}
}