{
  "type": "Feature",
  "properties": {
    "iso:country":"DK",
    "sg:address":"Fmd.: Karin Skov, Gyvelv\u00e6nget 16",
    "sg:city":"Bedsted",
    "sg:orig_category":"Kulturelle foreninger",
    "sg:phone":"+45 97 94 55 70",
    "sg:postcode":"7755",
    "sg:province":"Danmark",
    "wof:name":"Fyrspillene i Sydthy",
    "wof:placetype":"venue"
},
  "geometry": {"coordinates":[8.4905691147,56.8179664612],"type":"Point"}
}