{
  "type": "Feature",
  "properties": {
    "addr:full":"Buen 14 Gadbjerg Danmark 7321",
    "addr:housenumber":"14",
    "addr:postcode":"7321",
    "addr:street":"Buen",
    "iso:country":"DK",
    "sg:address":"Buen 14",
    "sg:city":"Gadbjerg",
    "sg:orig_category":"Isolering",
    "sg:phone":"+45 75 87 63 00",
    "sg:postcode":"7321",
    "sg:province":"Danmark",
    "wof:name":"Gadbjerg Teknisk Isolering",
    "wof:placetype":"venue"
},
  "geometry": {"coordinates":[9.3182382584,55.7687988281],"type":"Point"}
}