{
  "type": "Feature",
  "properties": {
    "addr:full":"Havnegade 9 A Frederikshavn Danmark 9900",
    "addr:housenumber":"9 a",
    "addr:postcode":"9900",
    "addr:street":"Havnegade",
    "iso:country":"DK",
    "sg:address":"Havnegade 9 A",
    "sg:city":"Frederikshavn",
    "sg:orig_category":"Stoffer",
    "sg:phone":"+45 98 42 97 60",
    "sg:postcode":"9900",
    "sg:province":"Danmark",
    "wof:name":"Reumert, Per",
    "wof:placetype":"venue"
},
  "geometry": {"coordinates":[10.535782814,57.4374008179],"type":"Point"}
}