{
  "type": "Feature",
  "properties": {
    "addr:full":"Borgergade 39 Gandrup Danmark 9362",
    "addr:housenumber":"39",
    "addr:postcode":"9362",
    "addr:street":"Borgergade",
    "iso:country":"DK",
    "sg:address":"Borgergade 39",
    "sg:city":"Gandrup",
    "sg:orig_category":"Sundhedspleje",
    "sg:phone":"+45 99 54 99 99",
    "sg:postcode":"9362",
    "sg:province":"Danmark",
    "wof:name":"Sundhedsplejen",
    "wof:placetype":"venue"
},
  "geometry": {"coordinates":[10.1806678772,57.0582771301],"type":"Point"}
}