{
  "type": "Feature",
  "properties": {
    "addr:full":"Bredgade 18 Thybor\u00f8n Danmark 7680",
    "addr:housenumber":"18",
    "addr:postcode":"7680",
    "addr:street":"Bredgade",
    "iso:country":"DK",
    "sg:address":"Bredgade 18",
    "sg:city":"Thybor\u00f8n",
    "sg:orig_category":"Belysning",
    "sg:phone":"+45 97 83 14 51",
    "sg:postcode":"7680",
    "sg:province":"Danmark",
    "wof:name":"Andersen, H. H.",
    "wof:placetype":"venue"
},
  "geometry": {"coordinates":[8.2175827026,56.7046546936],"type":"Point"}
}