{
  "type": "Feature",
  "properties": {
    "addr:full":"\u00d8rnevej 6 Taastrup Danmark 2630",
    "addr:housenumber":"6",
    "addr:postcode":"2630",
    "addr:street":"Ornevej",
    "iso:country":"DK",
    "sg:address":"\u00d8rnevej 6",
    "sg:city":"Taastrup",
    "sg:orig_category":"Biopater",
    "sg:phone":"+45 43 52 45 70",
    "sg:postcode":"2630",
    "sg:province":"Danmark",
    "wof:name":"Rohr, Hanne",
    "wof:placetype":"venue"
},
  "geometry": {"coordinates":[12.314949,55.646248],"type":"Point"}
}