{
  "type": "Feature",
  "properties": {
    "addr:full":"Gr\u00e6sted Stationsvej 33 Gr\u00e6sted Danmark 3230",
    "addr:housenumber":"33",
    "addr:postcode":"3230",
    "addr:street":"Stationsvej",
    "iso:country":"DK",
    "sg:address":"Gr\u00e6sted Stationsvej 33",
    "sg:city":"Gr\u00e6sted",
    "sg:orig_category":"Benzinstationer",
    "sg:phone":"+45 48 39 28 11",
    "sg:postcode":"3230",
    "sg:province":"Danmark",
    "wof:name":"Statoil Servicenter",
    "wof:placetype":"venue"
},
  "geometry": {"coordinates":[-78.6975326538,35.0151481628],"type":"Point"}
}