{
  "type": "Feature",
  "properties": {
    "addr:full":"Havnegade 12 Vejle Danmark 7100",
    "addr:housenumber":"12",
    "addr:postcode":"7100",
    "addr:street":"Havnegade",
    "iso:country":"DK",
    "sg:address":"Havnegade 12",
    "sg:city":"Vejle",
    "sg:classifiers":[
        {
            "category":"Restaurant",
            "type":"Food & Drink"
        }
    ],
    "sg:phone":"+45 75 72 19 88",
    "sg:postcode":"7100",
    "sg:province":"Danmark",
    "wof:name":"Canton Restaurant - Kinesisk Specialitet",
    "wof:placetype":"venue"
},
  "geometry": {"coordinates":[9.5387420654,55.7071342468],"type":"Point"}
}