{
  "type": "Feature",
  "properties": {
    "addr:full":"Georg Brandes Vej 4 Kolding Danmark 6000",
    "addr:housenumber":"4",
    "addr:postcode":"6000",
    "addr:street":"Georg Brandes Vej",
    "iso:country":"DK",
    "sg:address":"Georg Brandes Vej 4",
    "sg:city":"Kolding",
    "sg:classifiers":[
        {
            "category":"Utilities",
            "subcategory":"Refuse",
            "type":"Services"
        }
    ],
    "sg:phone":"+45 75 50 88 30",
    "sg:postcode":"6000",
    "sg:province":"Danmark",
    "sg:tags":[
        "catering"
    ],
    "sg:website":"www.speedtsberg-catering.dk",
    "wof:name":"Speedtsberg Catering",
    "wof:placetype":"venue"
},
  "geometry": {"coordinates":[9.455704689,55.4874153137],"type":"Point"}
}