{
  "type": "Feature",
  "properties": {
    "addr:full":"\u00d8stre Alle 37 Nakskov Danmark 4900",
    "addr:housenumber":"37",
    "addr:postcode":"4900",
    "addr:street":"Ostre Alle",
    "iso:country":"DK",
    "sg:address":"\u00d8stre Alle 37",
    "sg:city":"Nakskov",
    "sg:orig_category":"Hundetrimning",
    "sg:phone":"+45 54 92 74 16",
    "sg:postcode":"4900",
    "sg:province":"Danmark",
    "wof:name":"Annettes Hundesalon",
    "wof:placetype":"venue"
},
  "geometry": {"coordinates":[11.1576242447,54.8360061646],"type":"Point"}
}