{
  "type": "Feature",
  "properties": {
    "iso:country":"DK",
    "sg:address":"Limfjordsvej 19",
    "sg:city":"Thisted",
    "sg:orig_category":"Diskoteker",
    "sg:phone":"+45 97 92 15 96",
    "sg:postcode":"7700",
    "sg:province":"Danmark",
    "wof:name":"Toppen, Diskotek",
    "wof:placetype":"venue"
},
  "geometry": {"coordinates":[8.7167863846,56.9530792236],"type":"Point"}
}