{
  "type": "Feature",
  "properties": {
    "addr:full":"N\u00f8rregade 17 B Eskilstrup Danmark 4863",
    "addr:housenumber":"17 b",
    "addr:postcode":"4863",
    "addr:street":"Norregade",
    "iso:country":"DK",
    "sg:address":"N\u00f8rregade 17 B",
    "sg:city":"Eskilstrup",
    "sg:orig_category":"Museer",
    "sg:phone":"+45 54 43 70 07",
    "sg:postcode":"4863",
    "sg:province":"Danmark",
    "sg:website":"www.traktormuseum.dk",
    "wof:name":"Lolland-Falsters Traktor og Motormuseum",
    "wof:placetype":"venue"
},
  "geometry": {"coordinates":[11.8864383698,54.8581428528],"type":"Point"}
}