{
  "type": "Feature",
  "properties": {
    "addr:full":"All\u00e9gade 20A Odense C Danmark 5000",
    "addr:housenumber":"20a",
    "addr:postcode":"5000",
    "addr:street":"Alle\u0301Gade",
    "iso:country":"DK",
    "sg:address":"All\u00e9gade 20A",
    "sg:city":"Odense C",
    "sg:orig_category":"Virksomhedskonsulenter",
    "sg:phone":"+45 66 17 84 94",
    "sg:postcode":"5000",
    "sg:province":"Danmark",
    "wof:name":"Oxo-Design ApS",
    "wof:placetype":"venue"
},
  "geometry": {"coordinates":[10.3948669434,55.3908920288],"type":"Point"}
}