{
  "type": "Feature",
  "properties": {
    "iso:country":"DK",
    "sg:address":"Bredgade 55 D",
    "sg:city":"Herning",
    "sg:classifiers":[
        {
            "category":"Restaurant",
            "type":"Food & Drink"
        }
    ],
    "sg:phone":"+45 97 21 22 00",
    "sg:postcode":"7400",
    "sg:province":"Danmark",
    "wof:name":"Bone's",
    "wof:placetype":"venue"
},
  "geometry": {"coordinates":[8.9682540894,56.1361885071],"type":"Point"}
}