{
  "type": "Feature",
  "properties": {
    "iso:country":"DK",
    "sg:address":"Leder: Erik Geertz, M\u00f8llehaven 13",
    "sg:city":"Karlslunde",
    "sg:orig_category":"Specialskoler for handicappede",
    "sg:phone":"+45 46 15 57 16",
    "sg:postcode":"2690",
    "sg:province":"Danmark",
    "wof:name":"Jonstrupvangskolen",
    "wof:placetype":"venue"
},
  "geometry": {"coordinates":[12.2294149399,55.5701599121],"type":"Point"}
}