{
  "type": "Feature",
  "properties": {
    "addr:full":"Besser Kirkevej 3 Sams\u00f8 Danmark 8305",
    "addr:housenumber":"3",
    "addr:postcode":"8305",
    "addr:street":"Besser Kirkevej",
    "iso:country":"DK",
    "sg:address":"Besser Kirkevej 3",
    "sg:city":"Sams\u00f8",
    "sg:orig_category":"Kirker",
    "sg:postcode":"8305",
    "sg:province":"Danmark",
    "wof:name":"Besser Kirke",
    "wof:placetype":"venue"
},
  "geometry": {"coordinates":[-86.1480712891,31.1830692291],"type":"Point"}
}