{
  "type": "Feature",
  "properties": {
    "addr:full":"Vardevej 26 Tistrup Danmark 6862",
    "addr:housenumber":"26",
    "addr:postcode":"6862",
    "addr:street":"Vardevej",
    "iso:country":"DK",
    "sg:address":"Vardevej 26",
    "sg:city":"Tistrup",
    "sg:orig_category":"Telte",
    "sg:phone":"+45 75 24 11 24",
    "sg:postcode":"6862",
    "sg:province":"Danmark",
    "wof:name":"Holmegaard, Olav",
    "wof:placetype":"venue"
},
  "geometry": {"coordinates":[8.6171579361,55.7373771667],"type":"Point"}
}