{
  "type": "Feature",
  "properties": {
    "addr:full":"Skt. Ann\u00e6 Plads 7, 4 K\u00f8benhavn Danmark 1250",
    "addr:housenumber":"7 4;1250",
    "addr:street":"Skt. Annae Plads",
    "iso:country":"DK",
    "sg:address":"Skt. Ann\u00e6 Plads 7, 4",
    "sg:city":"K\u00f8benhavn",
    "sg:orig_category":"Pressebureauer",
    "sg:phone":"+45 33 11 15 04",
    "sg:postcode":"1250",
    "sg:province":"Danmark",
    "wof:name":"The Associated Press Ltd.",
    "wof:placetype":"venue"
},
  "geometry": {"coordinates":[76.3070983887,14.277130127],"type":"Point"}
}