{
  "type": "Feature",
  "properties": {
    "addr:full":"Fmd.: Bent Fodgaard, Nyvangsvej 3 Snedsted Danmark 7752",
    "addr:housenumber":"3",
    "addr:postcode":"7752",
    "addr:street":"Nyvangsvej",
    "iso:country":"DK",
    "sg:address":"Fmd.: Bent Fodgaard, Nyvangsvej 3",
    "sg:city":"Snedsted",
    "sg:orig_category":"Kirkelige foreninger",
    "sg:phone":"+45 97 93 30 57",
    "sg:postcode":"7752",
    "sg:province":"Danmark",
    "wof:name":"Frikirken, Det Danske Missionsforbund",
    "wof:placetype":"venue"
},
  "geometry": {"coordinates":[8.5276002884,56.8460388184],"type":"Point"}
}