{
  "type": "Feature",
  "properties": {
    "addr:full":"Storegade 3 D  Hinnerup Danmark 8382",
    "addr:housenumber":"3 d",
    "addr:postcode":"8382",
    "addr:street":"Storegade",
    "iso:country":"DK",
    "sg:address":"Storegade 3 D ",
    "sg:city":"Hinnerup",
    "sg:classifiers":[
        {
            "category":"Bars & Pubs",
            "subcategory":"Nightclub",
            "type":"Food & Drink"
        }
    ],
    "sg:phone":"+45 86 98 81 00",
    "sg:postcode":"8382",
    "sg:province":"Danmark",
    "sg:tags":[
        "cake",
        "bread"
    ],
    "wof:name":"BAGERG\u00c5RDEN",
    "wof:placetype":"venue"
},
  "geometry": {"coordinates":[10.0617837906,56.2637634277],"type":"Point"}
}