{
  "type": "Feature",
  "properties": {
    "iso:country":"DK",
    "sg:address":"Holte Stationsvej 12 A",
    "sg:city":"Holte",
    "sg:orig_category":"Bagere",
    "sg:phone":"+45 45 42 01 50",
    "sg:postcode":"2840",
    "sg:province":"Danmark",
    "wof:name":"Rubow's",
    "wof:placetype":"venue"
},
  "geometry": {"coordinates":[12.470609,55.810535],"type":"Point"}
}