{
  "type": "Feature",
  "properties": {
    "addr:full":"Merkurvej 202 Herning Danmark 7400",
    "addr:housenumber":"202",
    "addr:postcode":"7400",
    "addr:street":"Merkurvej",
    "iso:country":"DK",
    "sg:address":"Merkurvej 202",
    "sg:city":"Herning",
    "sg:orig_category":"Vikarbureauer",
    "sg:phone":"+45 97 21 69 21",
    "sg:postcode":"7400",
    "sg:province":"Danmark",
    "sg:website":"www.temp-team.dk",
    "wof:name":"Temp-Team A/S",
    "wof:placetype":"venue"
},
  "geometry": {"coordinates":[8.9993495941,56.1350402832],"type":"Point"}
}