{
  "type": "Feature",
  "properties": {
    "addr:full":"Steng\u00e5rdsvej 313-315 Esbjerg \u00d8 Danmark 6705",
    "addr:housenumber":"313-315",
    "addr:postcode":"6705",
    "addr:street":"Stengaardsvej;Danmark",
    "iso:country":"DK",
    "sg:address":"Steng\u00e5rdsvej 313-315",
    "sg:city":"Esbjerg \u00d8",
    "sg:orig_category":"Integrerede institutioner",
    "sg:phone":"+45 75 14 44 87",
    "sg:postcode":"6705",
    "sg:province":"Danmark",
    "wof:name":"Ringg\u00e5rden - \u00d8st, Aldersintegreret",
    "wof:placetype":"venue"
},
  "geometry": {"coordinates":[8.4911336899,55.485080719],"type":"Point"}
}