{
  "type": "Feature",
  "properties": {
    "addr:full":"Udbyh\u00f8jvej 557, \u00d8. T\u00f8rslev Gjerlev Danmark 8983",
    "addr:housenumber":"557 o.",
    "addr:postcode":"8983",
    "addr:street":"Udbyhojvej;Torslev Gjerlev Danmark",
    "iso:country":"DK",
    "sg:address":"Udbyh\u00f8jvej 557, \u00d8. T\u00f8rslev",
    "sg:city":"Gjerlev",
    "sg:orig_category":"Bodegaer",
    "sg:phone":"+45 86 47 61 26",
    "sg:postcode":"8983",
    "sg:province":"Danmark",
    "wof:name":"\u00c5stedet",
    "wof:placetype":"venue"
},
  "geometry": {"coordinates":[10.1887750626,56.5788421631],"type":"Point"}
}