{
  "type": "Feature",
  "properties": {
    "iso:country":"DK",
    "sg:address":"Bygmestervej 4",
    "sg:city":"Faaborg",
    "sg:orig_category":"Bilinspektion",
    "sg:phone":"+45 62 61 99 15",
    "sg:postcode":"5600",
    "sg:province":"Danmark",
    "sg:website":"www.bilsyn.dk",
    "wof:name":"Statens Bilinspektion",
    "wof:placetype":"venue"
},
  "geometry": {"coordinates":[10.238494,55.109573],"type":"Point"}
}