{
  "type": "Feature",
  "properties": {
    "iso:country":"DK",
    "sg:address":"Vesterlundvej 4",
    "sg:city":"Herlev",
    "sg:orig_category":"Gummi",
    "sg:phone":"+45 44 85 81 00",
    "sg:postcode":"2730",
    "sg:province":"Danmark",
    "wof:name":"Betech Seals",
    "wof:placetype":"venue"
},
  "geometry": {"coordinates":[12.4260625839,55.7236938477],"type":"Point"}
}