{
  "type": "Feature",
  "properties": {
    "iso:country":"DK",
    "sg:address":"v/Annette Hill-Madsen, Lindalsbakken 29",
    "sg:city":"Hadsund",
    "sg:orig_category":"Kulturelle foreninger",
    "sg:phone":"+45 98 57 32 39",
    "sg:postcode":"9560",
    "sg:province":"Danmark",
    "wof:name":"LOF",
    "wof:placetype":"venue"
},
  "geometry": {"coordinates":[10.115904808,56.7150764465],"type":"Point"}
}