{
  "type": "Feature",
  "properties": {
    "addr:full":"Vandmanden 26 B Aalborg SV Danmark 9200",
    "addr:housenumber":"26 b",
    "addr:postcode":"9200",
    "addr:street":"Vandmanden",
    "iso:country":"DK",
    "sg:address":"Vandmanden 26 B",
    "sg:city":"Aalborg SV",
    "sg:orig_category":"EDB-reparation og -service",
    "sg:phone":"+45 98 79 19 99",
    "sg:postcode":"9200",
    "sg:province":"Danmark",
    "wof:name":"Service-Gruppen A/S",
    "wof:placetype":"venue"
},
  "geometry": {"coordinates":[9.8687009811,57.0032463074],"type":"Point"}
}