{
  "type": "Feature",
  "properties": {
    "addr:full":"v/ Karl Jensen, N\u00f8rregade 84 Hundested Danmark 3390",
    "addr:housenumber":"84",
    "addr:postcode":"3390",
    "addr:street":"Norregade",
    "iso:country":"DK",
    "sg:address":"v/ Karl Jensen, N\u00f8rregade 84",
    "sg:city":"Hundested",
    "sg:orig_category":"Grundejerforeninger",
    "sg:phone":"+45 47 93 70 76",
    "sg:postcode":"3390",
    "sg:province":"Danmark",
    "wof:name":"Hundested Grundejerforening",
    "wof:placetype":"venue"
},
  "geometry": {"coordinates":[11.8530349731,55.958530426],"type":"Point"}
}