{
  "type": "Feature",
  "properties": {
    "addr:full":"Tokesvej 3 Sor\u00f8 Danmark 4180",
    "addr:housenumber":"3",
    "addr:postcode":"4180",
    "addr:street":"Tokesvej",
    "iso:country":"DK",
    "sg:address":"Tokesvej 3",
    "sg:city":"Sor\u00f8",
    "sg:orig_category":"Plejeboliger",
    "sg:phone":"+45 57 86 45 00",
    "sg:postcode":"4180",
    "sg:province":"Danmark",
    "wof:name":"Holbergcentret",
    "wof:placetype":"venue"
},
  "geometry": {"coordinates":[-102.94467926030001,45.4534721375],"type":"Point"}
}