{
  "type": "Feature",
  "properties": {
    "iso:country":"DK",
    "sg:address":"\u00d8stergade 12",
    "sg:city":"Give",
    "sg:orig_category":"Optikere",
    "sg:phone":"+45 75 73 10 32",
    "sg:postcode":"7323",
    "sg:province":"Danmark",
    "wof:name":"T\u00f8ttrup Guld-S\u00f8lv-Ure-Optik",
    "wof:placetype":"venue"
},
  "geometry": {"coordinates":[9.2389011383,55.8457946777],"type":"Point"}
}