{
  "type": "Feature",
  "properties": {
    "addr:full":"Industrivej 12 Lynge Danmark 3540",
    "addr:housenumber":"12",
    "addr:postcode":"3540",
    "addr:street":"Industrivej",
    "iso:country":"DK",
    "sg:address":"Industrivej 12",
    "sg:city":"Lynge",
    "sg:classifiers":[
        {
            "category":"Banks & Credit Unions",
            "subcategory":"Financial Services",
            "type":"Services"
        }
    ],
    "sg:phone":"+45 48 18 88 77",
    "sg:postcode":"3540",
    "sg:province":"Danmark",
    "sg:tags":[
        "banking",
        "finance",
        "insurance"
    ],
    "wof:name":"BIFO INVEST A/S",
    "wof:placetype":"venue"
},
  "geometry": {"coordinates":[12.3058443069,55.8313903809],"type":"Point"}
}