{
  "type": "Feature",
  "properties": {
    "iso:country":"DK",
    "sg:address":"Nybogade 6",
    "sg:city":"Hedensted",
    "sg:orig_category":"Kommunale folkeskoler",
    "sg:phone":"+45 75 89 11 22",
    "sg:postcode":"8722",
    "sg:province":"Danmark",
    "wof:name":"Hedensted Skole",
    "wof:placetype":"venue"
},
  "geometry": {"coordinates":[9.7052898407,55.7708473206],"type":"Point"}
}