{
  "type": "Feature",
  "properties": {
    "addr:full":"Hovedgaden Regstrup 68 Regstrup Danmark 4420",
    "addr:housenumber":"68",
    "addr:postcode":"4420",
    "addr:street":"Hovedgaden",
    "iso:country":"DK",
    "sg:address":"Hovedgaden Regstrup 68",
    "sg:city":"Regstrup",
    "sg:orig_category":"Farve og tapet",
    "sg:phone":"+45 59 47 17 01",
    "sg:postcode":"4420",
    "sg:province":"Danmark",
    "wof:name":"Regstrup Farvehandel",
    "wof:placetype":"venue"
},
  "geometry": {"coordinates":[11.6133670807,55.6744499207],"type":"Point"}
}