{
  "type": "Feature",
  "properties": {
    "iso:country":"DK",
    "sg:address":"Baneg\u00e5rdspladsen 1",
    "sg:city":"Maribo",
    "sg:orig_category":"Grillbarer",
    "sg:phone":"+45 54 78 32 55",
    "sg:postcode":"4930",
    "sg:province":"Danmark",
    "wof:name":"Stationsgrillen",
    "wof:placetype":"venue"
},
  "geometry": {"coordinates":[11.4998922348,54.7760505676],"type":"Point"}
}