{
  "type": "Feature",
  "properties": {
    "addr:full":"N\u00f8rregade 7 Vordingborg Danmark 4760",
    "addr:housenumber":"7",
    "addr:postcode":"4760",
    "addr:street":"Norregade",
    "iso:country":"DK",
    "sg:address":"N\u00f8rregade 7",
    "sg:city":"Vordingborg",
    "sg:orig_category":"Revisorer",
    "sg:phone":"+45 55 37 10 50",
    "sg:postcode":"4760",
    "sg:province":"Danmark",
    "sg:website":"www.frr.dk/dietz-larsen",
    "wof:name":"Revisionsfirmaet Dietz & Larsen A/S",
    "wof:placetype":"venue"
},
  "geometry": {"coordinates":[11.902384758,55.0143547058],"type":"Point"}
}