{
  "type": "Feature",
  "properties": {
    "addr:full":"Hasserisgade 43 Aalborg Danmark 9000",
    "addr:housenumber":"43",
    "addr:postcode":"9000",
    "addr:street":"Hasserisgade",
    "iso:country":"DK",
    "sg:address":"Hasserisgade 43",
    "sg:city":"Aalborg",
    "sg:orig_category":"Psykologer, praktiserende",
    "sg:phone":"+45 98 16 16 99",
    "sg:postcode":"9000",
    "sg:province":"Danmark",
    "wof:name":"N\u00f8rg\u00e5rd, Mette",
    "wof:placetype":"venue"
},
  "geometry": {"coordinates":[9.9027261734,57.045124054],"type":"Point"}
}