{
  "type": "Feature",
  "properties": {
    "iso:country":"DK",
    "sg:address":"Vibevej 110",
    "sg:city":"Brande",
    "sg:orig_category":"Integrerede institutioner",
    "sg:phone":"+45 97 18 11 43",
    "sg:postcode":"7330",
    "sg:province":"Danmark",
    "wof:name":"Vibereden",
    "wof:placetype":"venue"
},
  "geometry": {"coordinates":[9.1085700989,55.9514884949],"type":"Point"}
}