{
  "type": "Feature",
  "properties": {
    "addr:full":"Vestergade 34 - 38 Ikast Danmark 7430",
    "addr:housenumber":"34 38",
    "addr:postcode":"7430",
    "addr:street":"Vestergade",
    "iso:country":"DK",
    "sg:address":"Vestergade 34 - 38",
    "sg:city":"Ikast",
    "sg:orig_category":"Servicestationer",
    "sg:phone":"+45 97 15 11 08",
    "sg:postcode":"7430",
    "sg:province":"Danmark",
    "wof:name":"Statoil Servicenter",
    "wof:placetype":"venue"
},
  "geometry": {"coordinates":[9.1495885849,56.1391601562],"type":"Point"}
}