{
  "type": "Feature",
  "properties": {
    "addr:full":"Vestergade 69 Odense C Danmark 5000",
    "addr:housenumber":"69",
    "addr:postcode":"5000",
    "addr:street":"Vestergade",
    "iso:country":"DK",
    "sg:address":"Vestergade 69",
    "sg:city":"Odense C",
    "sg:classifiers":[
        {
            "category":"Banks & Credit Unions",
            "subcategory":"Bank",
            "type":"Services"
        }
    ],
    "sg:phone":"+45 63 11 47 50",
    "sg:postcode":"5000",
    "sg:province":"Danmark",
    "sg:tags":[
        "banker"
    ],
    "sg:website":"www.danskebank.dk",
    "wof:name":"Danske Bank",
    "wof:placetype":"venue"
},
  "geometry": {"coordinates":[10.382413,55.394699],"type":"Point"}
}