{
  "type": "Feature",
  "properties": {
    "addr:full":"\u00d8sterbro 11 Skive Danmark 7800",
    "addr:housenumber":"11",
    "addr:postcode":"7800",
    "addr:street":"Osterbro",
    "iso:country":"DK",
    "sg:address":"\u00d8sterbro 11",
    "sg:city":"Skive",
    "sg:orig_category":"Mobiltelefoner",
    "sg:phone":"+45 96 14 05 40",
    "sg:postcode":"7800",
    "sg:province":"Danmark",
    "wof:name":"Sonofon Partner",
    "wof:placetype":"venue"
},
  "geometry": {"coordinates":[9.0344638824,56.5643310547],"type":"Point"}
}