{
  "type": "Feature",
  "properties": {
    "iso:country":"DK",
    "sg:address":"Fmd.: Jens Bo Nielsen, Mejeribakken 25, S\u00f8strup",
    "sg:city":"Holb\u00e6k",
    "sg:orig_category":"Grundejerforeninger",
    "sg:phone":"+45 59 47 17 66",
    "sg:postcode":"4300",
    "sg:province":"Danmark",
    "wof:name":"Mejeribakken Grundejerforening",
    "wof:placetype":"venue"
},
  "geometry": {"coordinates":[-112.9990615845,46.6049995422],"type":"Point"}
}