{
  "type": "Feature",
  "properties": {
    "addr:full":"Amerikavej 5 Hobro Danmark 9500",
    "addr:housenumber":"5",
    "addr:postcode":"9500",
    "addr:street":"Amerikavej",
    "iso:country":"DK",
    "sg:address":"Amerikavej 5",
    "sg:city":"Hobro",
    "sg:orig_category":"Gymnasier og HF-kurser",
    "sg:phone":"+45 98 52 08 55",
    "sg:postcode":"9500",
    "sg:province":"Danmark",
    "wof:name":"Hobro Gymnasium og HF-kursus",
    "wof:placetype":"venue"
},
  "geometry": {"coordinates":[9.8139266968,56.6336097717],"type":"Point"}
}