{
  "type": "Feature",
  "properties": {
    "addr:full":"Meinungsgade 8 C K\u00f8benhavn N Danmark 2200",
    "addr:housenumber":"8 c",
    "addr:postcode":"2200",
    "addr:street":"Meinungsgade;Kobenhavn N Danmark",
    "iso:country":"DK",
    "sg:address":"Meinungsgade 8 C",
    "sg:city":"K\u00f8benhavn N",
    "sg:orig_category":"Fotografer",
    "sg:phone":"+45 35 37 36 32",
    "sg:postcode":"2200",
    "sg:province":"Danmark",
    "wof:name":"Kirkeg\u00e5rd, S\u00f8ren",
    "wof:placetype":"venue"
},
  "geometry": {"coordinates":[-94.2737731934,47.7952270508],"type":"Point"}
}