{
  "type": "Feature",
  "properties": {
    "addr:full":"Mineralvej 19, Postboks 857 9100",
    "addr:housenumber":"19;857",
    "addr:postcode":"9100",
    "addr:street":"Mineralvej",
    "iso:country":"DK",
    "sg:address":"Mineralvej 19, Postboks 857",
    "sg:orig_category":"Fabrikker",
    "sg:phone":"+45 98 12 33 77",
    "sg:postcode":"9100",
    "wof:name":"Jydsk Barberblade-Fabrik A/S",
    "wof:placetype":"venue"
},
  "geometry": {"coordinates":[9.9162597656,57.0493583679],"type":"Point"}
}