{
  "type": "Feature",
  "properties": {
    "addr:full":"Ingridsvej 44, Ejby Kirke Hyllinge Danmark 4070",
    "addr:housenumber":"44",
    "addr:postcode":"4070",
    "addr:street":"Ingridsvej",
    "iso:country":"DK",
    "sg:address":"Ingridsvej 44, Ejby",
    "sg:city":"Kirke Hyllinge",
    "sg:orig_category":"Elektronik",
    "sg:phone":"+45 46 40 54 39",
    "sg:postcode":"4070",
    "sg:province":"Danmark",
    "wof:name":"Relax",
    "wof:placetype":"venue"
},
  "geometry": {"coordinates":[11.9004745483,55.7080039978],"type":"Point"}
}