{
  "type": "Feature",
  "properties": {
    "iso:country":"DK",
    "sg:address":"Leder: Margit Larsen, Pontoppidanskolen, Blok 2, Skovvej 2, Brobyv\u00e6rk",
    "sg:city":"Broby",
    "sg:orig_category":"Lokalarkiver",
    "sg:postcode":"5672",
    "sg:province":"Danmark",
    "wof:name":"Sdr. Broby Lokalhistoriske Arkiv",
    "wof:placetype":"venue"
},
  "geometry": {"coordinates":[10.3131303787,55.2695846558],"type":"Point"}
}