{
  "type": "Feature",
  "properties": {
    "addr:full":"\u00d8rnevej 55, st. K\u00f8benhavn NV Danmark 2400",
    "addr:housenumber":"55",
    "addr:postcode":"2400",
    "addr:street":"Ornevej",
    "iso:country":"DK",
    "sg:address":"\u00d8rnevej 55, st.",
    "sg:city":"K\u00f8benhavn NV",
    "sg:orig_category":"Distriktsbiblioteker",
    "sg:phone":"+45 33 66 74 00",
    "sg:postcode":"2400",
    "sg:province":"Danmark",
    "wof:name":"\u00d8rnevej, Biblioteket",
    "wof:placetype":"venue"
},
  "geometry": {"coordinates":[-117.02272033689999,38.5024604797],"type":"Point"}
}