{
  "type": "Feature",
  "properties": {
    "addr:full":"Fmd.: Kaj Buch Jensen, Bakkehaven 21 Kalundborg Danmark 4400",
    "addr:housenumber":"21",
    "addr:postcode":"4400",
    "addr:street":"Fmd. Kaj;Bakkehaven",
    "iso:country":"DK",
    "sg:address":"Fmd.: Kaj Buch Jensen, Bakkehaven 21",
    "sg:city":"Kalundborg",
    "sg:orig_category":"\u00c3\u02dcvrige foreninger",
    "sg:phone":"+45 59 51 45 19",
    "sg:postcode":"4400",
    "sg:province":"Danmark",
    "wof:name":"Kalundborg og Omegns Museumsforening",
    "wof:placetype":"venue"
},
  "geometry": {"coordinates":[11.0934085846,55.6797485352],"type":"Point"}
}