{
  "type": "Feature",
  "properties": {
    "addr:full":"Farum Hovedgade 48 Farum Danmark 3520",
    "addr:housenumber":"48",
    "addr:postcode":"3520",
    "addr:street":"Farum Hovedgade",
    "iso:country":"DK",
    "sg:address":"Farum Hovedgade 48",
    "sg:city":"Farum",
    "sg:orig_category":"Supermarkeder",
    "sg:phone":"+45 44 95 00 94",
    "sg:postcode":"3520",
    "sg:province":"Danmark",
    "wof:name":"Super Spar Farum",
    "wof:placetype":"venue"
},
  "geometry": {"coordinates":[12.3667030334,55.8108291626],"type":"Point"}
}