{
  "type": "Feature",
  "properties": {
    "addr:full":"Jernbanegade 5 Sk\u00e6rb\u00e6k Danmark 6780",
    "addr:housenumber":"5",
    "addr:postcode":"6780",
    "addr:street":"Jernbanegade",
    "iso:country":"DK",
    "sg:address":"Jernbanegade 5",
    "sg:city":"Sk\u00e6rb\u00e6k",
    "sg:orig_category":"Tandteknikere, Kliniske",
    "sg:phone":"+45 74 75 25 85",
    "sg:postcode":"6780",
    "sg:province":"Danmark",
    "wof:name":"Steen, O.",
    "wof:placetype":"venue"
},
  "geometry": {"coordinates":[8.7272148132,55.1943397522],"type":"Point"}
}