{
  "type": "Feature",
  "properties": {
    "addr:full":"Lerskovvej 23, Enderslev H\u00e5rlev Danmark 4652",
    "addr:housenumber":"23",
    "addr:postcode":"4652",
    "addr:street":"Lerskovvej",
    "iso:country":"DK",
    "sg:address":"Lerskovvej 23, Enderslev",
    "sg:city":"H\u00e5rlev",
    "sg:orig_category":"Forsamlingshuse",
    "sg:phone":"+45 56 28 52 18",
    "sg:postcode":"4652",
    "sg:province":"Danmark",
    "wof:name":"Endeslev Forsamlingshus",
    "wof:placetype":"venue"
},
  "geometry": {"coordinates":[12.2393083572,55.3467025757],"type":"Point"}
}