{
  "type": "Feature",
  "properties": {
    "addr:full":"N\u00f8rregade 11 Hundested Danmark 3390",
    "addr:housenumber":"11",
    "addr:postcode":"3390",
    "addr:street":"Norregade",
    "iso:country":"DK",
    "sg:address":"N\u00f8rregade 11",
    "sg:city":"Hundested",
    "sg:orig_category":"Supermarkeder",
    "sg:phone":"+45 47 93 79 79",
    "sg:postcode":"3390",
    "sg:province":"Danmark",
    "wof:name":"Hundested Supermarked",
    "wof:placetype":"venue"
},
  "geometry": {"coordinates":[11.8502073288,55.9647254944],"type":"Point"}
}