{
  "type": "Feature",
  "properties": {
    "addr:full":"Egestubben 19, N\u00e6sby Odense N Danmark 5270",
    "addr:housenumber":"19",
    "addr:postcode":"5270",
    "addr:street":"Egestubben;Naesby",
    "iso:country":"DK",
    "sg:address":"Egestubben 19, N\u00e6sby",
    "sg:city":"Odense N",
    "sg:orig_category":"Sliberier",
    "sg:phone":"+45 66 18 12 45",
    "sg:postcode":"5270",
    "sg:province":"Danmark",
    "wof:name":"Tub\u00e6ks Slibecentral",
    "wof:placetype":"venue"
},
  "geometry": {"coordinates":[10.3306798935,55.4711418152],"type":"Point"}
}