{
  "type": "Feature",
  "properties": {
    "addr:full":"Peter Bangs Vej 62 Frederiksberg Danmark 2000",
    "addr:housenumber":"62",
    "addr:postcode":"2000",
    "addr:street":"Peter Bangs Vej",
    "iso:country":"DK",
    "sg:address":"Peter Bangs Vej 62",
    "sg:city":"Frederiksberg",
    "sg:orig_category":"Farve og tapet",
    "sg:phone":"+45 38 88 30 30",
    "sg:postcode":"2000",
    "sg:province":"Danmark",
    "wof:name":"Fl\u00fcgger farver",
    "wof:placetype":"venue"
},
  "geometry": {"coordinates":[12.50760746,55.6788291931],"type":"Point"}
}