{
  "type": "Feature",
  "properties": {
    "iso:country":"DK",
    "sg:address":"K\u00f8gevej 106",
    "sg:city":"Taastrup",
    "sg:orig_category":"Bagere",
    "sg:phone":"+45 43 99 03 88",
    "sg:postcode":"2630",
    "sg:province":"Danmark",
    "wof:name":"Hj\u00f8rnebageriet",
    "wof:placetype":"venue"
},
  "geometry": {"coordinates":[12.30209,55.650677],"type":"Point"}
}