{
  "type": "Feature",
  "properties": {
    "addr:full":"Sogneg\u00e5rdsvej 7, Lindved Vejle Danmark 7100",
    "addr:housenumber":"7",
    "addr:postcode":"7100",
    "addr:street":"Sognegaardsvej",
    "iso:country":"DK",
    "sg:address":"Sogneg\u00e5rdsvej 7, Lindved",
    "sg:city":"Vejle",
    "sg:orig_category":"Distriktsbiblioteker",
    "sg:phone":"+45 75 85 12 46",
    "sg:postcode":"7100",
    "sg:province":"Danmark",
    "sg:website":"www.toerringbib.dk",
    "wof:name":"Lindved Bibliotek",
    "wof:placetype":"venue"
},
  "geometry": {"coordinates":[9.5368051529,55.7113952637],"type":"Point"}
}