{
  "type": "Feature",
  "properties": {
    "addr:full":"Klattrup Bygade 52 A Fredericia Danmark 7000",
    "addr:housenumber":"52 a",
    "addr:postcode":"7000",
    "addr:street":"Klattrup Bygade",
    "iso:country":"DK",
    "sg:address":"Klattrup Bygade 52 A",
    "sg:city":"Fredericia",
    "sg:orig_category":"Fodplejere",
    "sg:phone":"+45 76 86 04 09",
    "sg:postcode":"7000",
    "sg:province":"Danmark",
    "wof:name":"Pedersen, Birthe",
    "wof:placetype":"venue"
},
  "geometry": {"coordinates":[9.5299863815,55.6437301636],"type":"Point"}
}