{
  "type": "Feature",
  "properties": {
    "addr:full":"Sognepr\u00e6st: Jenny Kinch (K/B), Lemmingvej 2 Silkeborg Danmark 8600",
    "addr:housenumber":"2",
    "addr:postcode":"8600",
    "addr:street":"Lemmingvej",
    "iso:country":"DK",
    "sg:address":"Sognepr\u00e6st: Jenny Kinch (K/B), Lemmingvej 2",
    "sg:city":"Silkeborg",
    "sg:orig_category":"Kirkesogne",
    "sg:phone":"+45 86 85 50 24",
    "sg:postcode":"8600",
    "sg:province":"Danmark",
    "wof:name":"Sejling Og Sinding Sogne",
    "wof:placetype":"venue"
},
  "geometry": {"coordinates":[9.5524425507,56.1693305969],"type":"Point"}
}