{
  "type": "Feature",
  "properties": {
    "iso:country":"DK",
    "sg:address":"Havnevej 158",
    "sg:city":"Grenaa",
    "sg:orig_category":"Blikkenslagere",
    "sg:phone":"+45 86 32 41 11",
    "sg:postcode":"8500",
    "sg:province":"Danmark",
    "wof:name":"Rytter, Kjeld",
    "wof:placetype":"venue"
},
  "geometry": {"coordinates":[10.912255,56.410774],"type":"Point"}
}