{
  "type": "Feature",
  "properties": {
    "addr:full":"Rams\u00f8vejen 18 Gadstrup Danmark 4621",
    "addr:housenumber":"18",
    "addr:postcode":"4621",
    "addr:street":"Ramsovejen",
    "iso:country":"DK",
    "sg:address":"Rams\u00f8vejen 18",
    "sg:city":"Gadstrup",
    "sg:orig_category":"Murermestre",
    "sg:phone":"+45 46 19 09 48",
    "sg:postcode":"4621",
    "sg:province":"Danmark",
    "wof:name":"Multibyg",
    "wof:placetype":"venue"
},
  "geometry": {"coordinates":[12.0671024323,55.5682296753],"type":"Point"}
}