{
  "type": "Feature",
  "properties": {
    "addr:full":"\u00d8stergade 23 Aabybro Danmark 9440",
    "addr:housenumber":"23",
    "addr:postcode":"9440",
    "addr:street":"Ostergade",
    "iso:country":"DK",
    "sg:address":"\u00d8stergade 23",
    "sg:city":"Aabybro",
    "sg:orig_category":"Autoreparation og -service",
    "sg:phone":"+45 98 24 46 33",
    "sg:postcode":"9440",
    "sg:province":"Danmark",
    "wof:name":"Bilhuset i Centrum",
    "wof:placetype":"venue"
},
  "geometry": {"coordinates":[9.7319488525,57.1605796814],"type":"Point"}
}