{
  "type": "Feature",
  "properties": {
    "iso:country":"DK",
    "sg:address":"Viek\u00e6rvej 1B, Diern\u00e6s",
    "sg:city":"Faaborg",
    "sg:orig_category":"Kunstmalere",
    "sg:phone":"+45 62 61 47 07",
    "sg:postcode":"5600",
    "sg:province":"Danmark",
    "wof:name":"Harboe, Poul",
    "wof:placetype":"venue"
},
  "geometry": {"coordinates":[10.2400531769,55.0950622559],"type":"Point"}
}