{
  "type": "Feature",
  "properties": {
    "addr:full":"Sindalsvej 4 Risskov Danmark 8240",
    "addr:housenumber":"4",
    "addr:postcode":"8240",
    "addr:street":"Sindalsvej",
    "iso:country":"DK",
    "sg:address":"Sindalsvej 4",
    "sg:city":"Risskov",
    "sg:orig_category":"Marmor",
    "sg:phone":"+45 89 44 88 88",
    "sg:postcode":"8240",
    "sg:province":"Danmark",
    "wof:name":"ENC Natursten A/S",
    "wof:placetype":"venue"
},
  "geometry": {"coordinates":[10.2223377228,56.2092094421],"type":"Point"}
}