{
  "type": "Feature",
  "properties": {
    "addr:full":"Solbakken 5 Lynge Danmark 3540",
    "addr:housenumber":"5",
    "addr:postcode":"3540",
    "addr:street":"Solbakken",
    "iso:country":"DK",
    "sg:address":"Solbakken 5",
    "sg:city":"Lynge",
    "sg:orig_category":"Forlag",
    "sg:phone":"+45 48 18 75 75",
    "sg:postcode":"3540",
    "sg:province":"Danmark",
    "wof:name":"Morton, J",
    "wof:placetype":"venue"
},
  "geometry": {"coordinates":[12.2652769089,55.8371276855],"type":"Point"}
}