{
  "type": "Feature",
  "properties": {
    "addr:full":"Vongevej 64, \u00c5dal Jelling Danmark 7300",
    "addr:housenumber":"64",
    "addr:postcode":"7300",
    "addr:street":"Vongevej",
    "iso:country":"DK",
    "sg:address":"Vongevej 64, \u00c5dal",
    "sg:city":"Jelling",
    "sg:orig_category":"Slagterier",
    "sg:phone":"+45 75 87 38 00",
    "sg:postcode":"7300",
    "sg:province":"Danmark",
    "wof:name":"\u00c5dal Slagteri",
    "wof:placetype":"venue"
},
  "geometry": {"coordinates":[9.4184103012,55.7558555603],"type":"Point"}
}