{
  "type": "Feature",
  "properties": {
    "addr:full":"Gr\u00f8nlandsvej 24 Frederikshavn Danmark 9900",
    "addr:housenumber":"24",
    "addr:postcode":"9900",
    "addr:street":"Gronlandsvej",
    "iso:country":"DK",
    "sg:address":"Gr\u00f8nlandsvej 24",
    "sg:city":"Frederikshavn",
    "sg:orig_category":"Non-Classified Establishments",
    "sg:phone":"+45 98 43 38 30",
    "sg:postcode":"9900",
    "sg:province":"Danmark",
    "wof:name":"Dagtilbudet",
    "wof:placetype":"venue"
},
  "geometry": {"coordinates":[10.5011529922,57.4452209473],"type":"Point"}
}