{
  "type": "Feature",
  "properties": {
    "addr:full":"Lilliendalsvej 32 B Mern Danmark 4735",
    "addr:housenumber":"32 b",
    "addr:postcode":"4735",
    "addr:street":"Lilliendalsvej",
    "iso:country":"DK",
    "sg:address":"Lilliendalsvej 32 B",
    "sg:city":"Mern",
    "sg:orig_category":"Genbrugspladser",
    "sg:phone":"+45 55 93 08 08",
    "sg:postcode":"4735",
    "sg:province":"Danmark",
    "wof:name":"Mern Genbrugsplads",
    "wof:placetype":"venue"
},
  "geometry": {"coordinates":[12.0567293167,55.0439186096],"type":"Point"}
}