{
  "type": "Feature",
  "properties": {
    "addr:full":"Birkevej 37, V. H\u00e6singe Broby Danmark 5672",
    "addr:housenumber":"37",
    "addr:postcode":"5672",
    "addr:street":"Birkevej;Haesinge",
    "iso:country":"DK",
    "sg:address":"Birkevej 37, V. H\u00e6singe",
    "sg:city":"Broby",
    "sg:orig_category":"Slagter og viktualie",
    "sg:phone":"+45 62 63 13 53",
    "sg:postcode":"5672",
    "sg:province":"Danmark",
    "wof:name":"Vester H\u00e6singe Slagterforretning ApS",
    "wof:placetype":"venue"
},
  "geometry": {"coordinates":[10.3131303787,55.2695846558],"type":"Point"}
}