{
  "type": "Feature",
  "properties": {
    "iso:country":"DK",
    "sg:address":"M\u00f8lleg\u00e5rdsvej 33",
    "sg:city":"Silkeborg",
    "sg:orig_category":"Malermestre",
    "sg:phone":"+45 86 85 39 77",
    "sg:postcode":"8600",
    "sg:province":"Danmark",
    "wof:name":"TK, Malerfirmaet",
    "wof:placetype":"venue"
},
  "geometry": {"coordinates":[9.5524425507,56.1693305969],"type":"Point"}
}