{
  "type": "Feature",
  "properties": {
    "iso:country":"DK",
    "sg:address":"Toftek\u00e6rsvej 50, Sk\u00e5strup",
    "sg:city":"Bogense",
    "sg:orig_category":"Maskinstationer",
    "sg:phone":"+45 64 44 11 25",
    "sg:postcode":"5400",
    "sg:province":"Danmark",
    "wof:name":"Frigaardens Maskinstation",
    "wof:placetype":"venue"
},
  "geometry": {"coordinates":[10.0943098068,55.5637893677],"type":"Point"}
}