{
  "type": "Feature",
  "properties": {
    "addr:full":"Tingskovhedevej 21 Christiansfeld Danmark 6070",
    "addr:housenumber":"21",
    "addr:postcode":"6070",
    "addr:street":"Tingskovhedevej",
    "iso:country":"DK",
    "sg:address":"Tingskovhedevej 21",
    "sg:city":"Christiansfeld",
    "sg:orig_category":"Antikviteter",
    "sg:phone":"+45 75 57 32 92",
    "sg:postcode":"6070",
    "sg:province":"Danmark",
    "wof:name":"Rasch, Klaus",
    "wof:placetype":"venue"
},
  "geometry": {"coordinates":[9.4839982986,55.3861732483],"type":"Point"}
}