{
  "type": "Feature",
  "properties": {
    "addr:full":"Rengegade 5-7 Store Heddinge Danmark 4660",
    "addr:housenumber":"5-7",
    "addr:postcode":"4660",
    "addr:street":"Rengegade",
    "iso:country":"DK",
    "sg:address":"Rengegade 5-7",
    "sg:city":"Store Heddinge",
    "sg:classifiers":[
        {
            "category":"Communications",
            "type":"Services"
        }
    ],
    "sg:phone":"+45 56 50 42 40",
    "sg:postcode":"4660",
    "sg:province":"Danmark",
    "sg:tags":[
        "radio-",
        "og",
        "tv-stationer"
    ],
    "wof:name":"Stevns Lokalradio",
    "wof:placetype":"venue"
},
  "geometry": {"coordinates":[12.3891191483,55.3084945679],"type":"Point"}
}