{
  "type": "Feature",
  "properties": {
    "iso:country":"DK",
    "sg:address":"Vestergade 29",
    "sg:city":"Maribo",
    "sg:orig_category":"Optikere",
    "sg:phone":"+45 54 78 18 53",
    "sg:postcode":"4930",
    "sg:province":"Danmark",
    "wof:name":"Olsen, S\u00f8ren",
    "wof:placetype":"venue"
},
  "geometry": {"coordinates":[11.4969472885,54.7749252319],"type":"Point"}
}