{
  "type": "Feature",
  "properties": {
    "addr:full":"Elmevej 10 Karup Danmark 7470",
    "addr:housenumber":"10",
    "addr:postcode":"7470",
    "addr:street":"Elmevej",
    "iso:country":"DK",
    "sg:address":"Elmevej 10",
    "sg:city":"Karup",
    "sg:classifiers":[
        {
            "category":"Taxi",
            "type":"Transportation"
        }
    ],
    "sg:phone":"+45 97 10 14 15",
    "sg:postcode":"7470",
    "sg:province":"Danmark",
    "sg:website":"www.karuptaxi.dk",
    "wof:name":"Karup Taxi",
    "wof:placetype":"venue"
},
  "geometry": {"coordinates":[9.1727218628,56.308757782],"type":"Point"}
}