{
  "type": "Feature",
  "properties": {
    "addr:full":"N\u00f8rreport 4 Ebeltoft Danmark 8400",
    "addr:housenumber":"4",
    "addr:postcode":"8400",
    "addr:street":"Norreport",
    "iso:country":"DK",
    "sg:address":"N\u00f8rreport 4",
    "sg:city":"Ebeltoft",
    "sg:orig_category":"Arkitekter",
    "sg:phone":"+45 86 34 66 44",
    "sg:postcode":"8400",
    "sg:province":"Danmark",
    "wof:name":"Gr\u00f8n Hans A/S, Arkitektfirmaet",
    "wof:placetype":"venue"
},
  "geometry": {"coordinates":[10.6812486649,56.2022972107],"type":"Point"}
}