{
  "type": "Feature",
  "properties": {
    "addr:full":"Peter Kaads Vej 5, Vollerup S\u00f8nderborg Danmark 6400",
    "addr:housenumber":"5",
    "addr:postcode":"6400",
    "addr:street":"Peter Kaads Vej",
    "iso:country":"DK",
    "sg:address":"Peter Kaads Vej 5, Vollerup",
    "sg:city":"S\u00f8nderborg",
    "sg:orig_category":"Murermestre",
    "sg:phone":"+45 74 42 70 38",
    "sg:postcode":"6400",
    "sg:province":"Danmark",
    "wof:name":"Skovby , Ib",
    "wof:placetype":"venue"
},
  "geometry": {"coordinates":[9.7899465561,54.9100151062],"type":"Point"}
}