{
  "type": "Feature",
  "properties": {
    "addr:full":"R\u00e5sted Kirkevej 18 B Vemb Danmark 7570",
    "addr:housenumber":"18 b",
    "addr:postcode":"7570",
    "addr:street":"Raasted Kirkevej",
    "iso:country":"DK",
    "sg:address":"R\u00e5sted Kirkevej 18 B",
    "sg:city":"Vemb",
    "sg:orig_category":"Kirker",
    "sg:postcode":"7570",
    "sg:province":"Danmark",
    "wof:name":"R\u00e5sted Kirke",
    "wof:placetype":"venue"
},
  "geometry": {"coordinates":[8.4177904129,56.3214378357],"type":"Point"}
}