{
  "type": "Feature",
  "properties": {
    "addr:full":"Leder: Gunda Odgaard, \u00d8rhagevej 171, Klitm\u00f8ller Thisted Danmark 7700",
    "addr:housenumber":"171",
    "addr:postcode":"7700",
    "addr:street":"Orhagevej;Klitmoller",
    "iso:country":"DK",
    "sg:address":"Leder: Gunda Odgaard, \u00d8rhagevej 171, Klitm\u00f8ller",
    "sg:city":"Thisted",
    "sg:orig_category":"Oplysningsforbund",
    "sg:phone":"+45 97 97 53 94",
    "sg:postcode":"7700",
    "sg:province":"Danmark",
    "wof:name":"LOF - Liberalt Oplysnings Forbund",
    "wof:placetype":"venue"
},
  "geometry": {"coordinates":[8.6919784546,56.9556121826],"type":"Point"}
}