{
  "type": "Feature",
  "properties": {
    "addr:full":"Helgolandsgade 5 Holstebro Danmark 7500",
    "addr:housenumber":"5",
    "addr:postcode":"7500",
    "addr:street":"Helgolandsgade",
    "iso:country":"DK",
    "sg:address":"Helgolandsgade 5",
    "sg:city":"Holstebro",
    "sg:orig_category":"Renserier",
    "sg:phone":"+45 97 42 52 89",
    "sg:postcode":"7500",
    "sg:province":"Danmark",
    "wof:name":"Wium's Renseri & M\u00f8ntvask",
    "wof:placetype":"venue"
},
  "geometry": {"coordinates":[8.6170396805,56.3553657532],"type":"Point"}
}