{
  "type": "Feature",
  "properties": {
    "addr:full":"Vigerslev Alle 18 Valby Danmark 2500",
    "addr:housenumber":"18",
    "addr:postcode":"2500",
    "addr:street":"Vigerslev Alle",
    "iso:country":"DK",
    "sg:address":"Vigerslev Alle 18",
    "sg:city":"Valby",
    "sg:orig_category":"Dag- og distriktsblade",
    "sg:phone":"+45 36 15 20 00",
    "sg:postcode":"2500",
    "sg:province":"Danmark",
    "sg:website":"www.aller.dk",
    "wof:name":"Aller Press A/S",
    "wof:placetype":"venue"
},
  "geometry": {"coordinates":[12.521478653,55.6624526978],"type":"Point"}
}