{
  "type": "Feature",
  "properties": {
    "addr:full":"Fmd.: Thorkil Brouer, Svinget 3 Ebeltoft Danmark 8400",
    "addr:housenumber":"3",
    "addr:postcode":"8400",
    "addr:street":"Svinget",
    "iso:country":"DK",
    "sg:address":"Fmd.: Thorkil Brouer, Svinget 3",
    "sg:city":"Ebeltoft",
    "sg:orig_category":"Faglige organisationer og foreninger",
    "sg:phone":"+45 86 34 27 42",
    "sg:postcode":"8400",
    "sg:province":"Danmark",
    "wof:name":"BYG - S\u00f8nder Herreds Mesterforening",
    "wof:placetype":"venue"
},
  "geometry": {"coordinates":[10.6778745651,56.199798584],"type":"Point"}
}