{
  "type": "Feature",
  "properties": {
    "addr:full":"Flegmade 9 D Vejle Danmark 7100",
    "addr:housenumber":"9 d",
    "addr:postcode":"7100",
    "addr:street":"Flegmade",
    "iso:country":"DK",
    "sg:address":"Flegmade 9 D",
    "sg:city":"Vejle",
    "sg:orig_category":"Bogtrykkerier",
    "sg:phone":"+45 75 72 73 33",
    "sg:postcode":"7100",
    "sg:province":"Danmark",
    "wof:name":"Trekantens Lyntryk I/S",
    "wof:placetype":"venue"
},
  "geometry": {"coordinates":[9.5269870758,55.7091522217],"type":"Point"}
}