{
  "type": "Feature",
  "properties": {
    "iso:country":"DK",
    "sg:address":"Br\u00f8ndumvej 14",
    "sg:city":"Fjerritslev",
    "sg:orig_category":"Vandrerhjem",
    "sg:phone":"+45 98 21 18 55",
    "sg:postcode":"9690",
    "sg:province":"Danmark",
    "wof:name":"Fjerritslev Vandrerhjem",
    "wof:placetype":"venue"
},
  "geometry": {"coordinates":[9.2648591995,57.0900230408],"type":"Point"}
}