{
  "type": "Feature",
  "properties": {
    "addr:full":"Havnepladsen 3 A Svendborg Danmark 5700",
    "addr:housenumber":"3 a",
    "addr:postcode":"5700",
    "addr:street":"Havnepladsen",
    "iso:country":"DK",
    "sg:address":"Havnepladsen 3 A",
    "sg:city":"Svendborg",
    "sg:orig_category":"Non-Classified Establishments",
    "sg:phone":"+45 62 22 99 66",
    "sg:postcode":"5700",
    "sg:province":"Danmark",
    "sg:website":"www.edelbo.dk",
    "wof:name":"RevisionsFirmaet Edelbo",
    "wof:placetype":"venue"
},
  "geometry": {"coordinates":[10.6145973206,55.0580101013],"type":"Point"}
}