{
  "type": "Feature",
  "properties": {
    "addr:full":"Langgade 2 Hesselager Danmark 5874",
    "addr:housenumber":"2",
    "addr:postcode":"5874",
    "addr:street":"Langgade",
    "iso:country":"DK",
    "sg:address":"Langgade 2",
    "sg:city":"Hesselager",
    "sg:orig_category":"Plejehjem",
    "sg:phone":"+45 62 25 16 96",
    "sg:postcode":"5874",
    "sg:province":"Danmark",
    "wof:name":"Hesselager plejehjem",
    "wof:placetype":"venue"
},
  "geometry": {"coordinates":[10.7338142395,55.1720733643],"type":"Point"}
}