{
  "type": "Feature",
  "properties": {
    "addr:full":"Hamarvej 1 - 3 Viborg Danmark 8800",
    "addr:housenumber":"1 3",
    "addr:postcode":"8800",
    "addr:street":"Hamarvej",
    "iso:country":"DK",
    "sg:address":"Hamarvej 1 - 3",
    "sg:city":"Viborg",
    "sg:orig_category":"Handicapboliger",
    "sg:phone":"+45 86 60 06 00",
    "sg:postcode":"8800",
    "sg:province":"Danmark",
    "wof:name":"Ulriksdal",
    "wof:placetype":"venue"
},
  "geometry": {"coordinates":[9.3767871857,56.4622879028],"type":"Point"}
}