{
  "type": "Feature",
  "properties": {
    "addr:full":"Juniorsgade 35 Saksk\u00f8bing Danmark 4990",
    "addr:housenumber":"35",
    "addr:postcode":"4990",
    "addr:street":"Juniorsgade",
    "iso:country":"DK",
    "sg:address":"Juniorsgade 35",
    "sg:city":"Saksk\u00f8bing",
    "sg:orig_category":"Handicapboliger",
    "sg:phone":"+45 54 78 47 82",
    "sg:postcode":"4990",
    "sg:province":"Danmark",
    "wof:name":"BN/Vibo St\u00f8ttekorpset i Saksk\u00f8bing",
    "wof:placetype":"venue"
},
  "geometry": {"coordinates":[-114.0767440796,46.4432487488],"type":"Point"}
}