{
  "type": "Feature",
  "properties": {
    "iso:country":"DK",
    "sg:address":"v/ B\u00f8rge Uhrenholt, Spodsbjergvej 205, Gl. Skr\u00f8belev",
    "sg:city":"Rudk\u00f8bing",
    "sg:orig_category":"Kulturelle foreninger",
    "sg:phone":"+45 62 51 18 43",
    "sg:postcode":"5900",
    "sg:province":"Danmark",
    "wof:name":"Venneforeningen B\u00f8getr\u00e6et Skr\u00f8belev Center",
    "wof:placetype":"venue"
},
  "geometry": {"coordinates":[-114.0767440796,46.4432487488],"type":"Point"}
}