{
  "type": "Feature",
  "properties": {
    "addr:full":"\u00d8strupvej 22 Kalundborg Danmark 4400",
    "addr:housenumber":"22",
    "addr:postcode":"4400",
    "addr:street":"Ostrupvej",
    "iso:country":"DK",
    "sg:address":"\u00d8strupvej 22",
    "sg:city":"Kalundborg",
    "sg:orig_category":"Keramik",
    "sg:phone":"+45 59 56 00 60",
    "sg:postcode":"4400",
    "sg:province":"Danmark",
    "wof:name":"Kramp, Carin",
    "wof:placetype":"venue"
},
  "geometry": {"coordinates":[11.0563297272,55.6463661194],"type":"Point"}
}