{
  "type": "Feature",
  "properties": {
    "addr:full":"S\u00f8nderballevej 4 Skals Danmark 8832",
    "addr:housenumber":"4",
    "addr:postcode":"8832",
    "addr:street":"Sonderballevej",
    "iso:country":"DK",
    "sg:address":"S\u00f8nderballevej 4",
    "sg:city":"Skals",
    "sg:classifiers":[
        {
            "category":"Personal",
            "subcategory":"Massage",
            "type":"Services"
        }
    ],
    "sg:phone":"+45 86 69 46 24",
    "sg:postcode":"8832",
    "sg:province":"Danmark",
    "wof:name":"Johannsdottir, Arna",
    "wof:placetype":"venue"
},
  "geometry": {"coordinates":[9.4022827148,56.5543632507],"type":"Point"}
}