{
  "type": "Feature",
  "properties": {
    "iso:country":"DK",
    "sg:address":"Stevnsvej 74, Str\u00f8by Egede",
    "sg:city":"K\u00f8ge",
    "sg:orig_category":"Bagere",
    "sg:phone":"+45 56 26 65 49",
    "sg:postcode":"4600",
    "sg:province":"Danmark",
    "wof:name":"Bageren, Hos",
    "wof:placetype":"venue"
},
  "geometry": {"coordinates":[43.365791,42.31152],"type":"Point"}
}