{
  "type": "Feature",
  "properties": {
    "addr:full":"Gormsgade 2 Vejle Danmark 7100",
    "addr:housenumber":"2",
    "addr:postcode":"7100",
    "addr:street":"Gormsgade",
    "iso:country":"DK",
    "sg:address":"Gormsgade 2",
    "sg:city":"Vejle",
    "sg:orig_category":"Revisorer",
    "sg:phone":"+45 75 82 91 12",
    "sg:postcode":"7100",
    "sg:province":"Danmark",
    "wof:name":"Center Revision",
    "wof:placetype":"venue"
},
  "geometry": {"coordinates":[9.5370950699,55.714225769],"type":"Point"}
}