{
  "type": "Feature",
  "properties": {
    "addr:full":"Fmd.: Lasse Olsen, Hasselhegnet 36 Greve Danmark 2670",
    "addr:housenumber":"36",
    "addr:postcode":"2670",
    "addr:street":"Fmd.;Hasselhegnet",
    "iso:country":"DK",
    "sg:address":"Fmd.: Lasse Olsen, Hasselhegnet 36",
    "sg:city":"Greve",
    "sg:orig_category":"Grundejerforeninger",
    "sg:phone":"+45 43 40 47 43",
    "sg:postcode":"2670",
    "sg:province":"Danmark",
    "wof:name":"Hasselhegnet Grundejerforening",
    "wof:placetype":"venue"
},
  "geometry": {"coordinates":[12.2941808701,55.5844078064],"type":"Point"}
}