{
  "type": "Feature",
  "properties": {
    "addr:full":"Friskolevej 13, Bjergby Erslev Danmark 7950",
    "addr:housenumber":"13",
    "addr:postcode":"7950",
    "addr:street":"Friskolevej;Bjergby",
    "iso:country":"DK",
    "sg:address":"Friskolevej 13, Bjergby",
    "sg:city":"Erslev",
    "sg:orig_category":"Private- og friskoler",
    "sg:phone":"+45 97 74 05 88",
    "sg:postcode":"7950",
    "sg:province":"Danmark",
    "sg:website":"www.bjergby-friskole",
    "wof:name":"Bjergby Friskole",
    "wof:placetype":"venue"
},
  "geometry": {"coordinates":[8.7200698853,56.8354682922],"type":"Point"}
}