{
  "type": "Feature",
  "properties": {
    "addr:full":"Jernbanegade 10 S\u00f8nderborg Danmark 6400",
    "addr:housenumber":"10",
    "addr:postcode":"6400",
    "addr:street":"Jernbanegade",
    "iso:country":"DK",
    "sg:address":"Jernbanegade 10",
    "sg:city":"S\u00f8nderborg",
    "sg:orig_category":"Apoteker og -udsalg",
    "sg:phone":"+45 74 42 35 02",
    "sg:postcode":"6400",
    "sg:province":"Danmark",
    "wof:name":"Jernbane Apoteket",
    "wof:placetype":"venue"
},
  "geometry": {"coordinates":[9.7932987213,54.910533905],"type":"Point"}
}