{
  "type": "Feature",
  "properties": {
    "addr:full":"Vesterhavsvej 24 Blokhus Danmark 9492",
    "addr:housenumber":"24",
    "addr:postcode":"9492",
    "addr:street":"Vesterhavsvej",
    "iso:country":"DK",
    "sg:address":"Vesterhavsvej 24",
    "sg:city":"Blokhus",
    "sg:orig_category":"Bodegaer",
    "sg:phone":"+45 98 24 82 99",
    "sg:postcode":"9492",
    "sg:province":"Danmark",
    "wof:name":"Gasten",
    "wof:placetype":"venue"
},
  "geometry": {"coordinates":[9.6014223099,57.2563858032],"type":"Point"}
}