{
  "type": "Feature",
  "properties": {
    "addr:full":"Tomsg\u00e5rdsvej 17 - 19 K\u00f8benhavn NV Danmark 2400",
    "addr:housenumber":"17 19",
    "addr:postcode":"2400",
    "addr:street":"Tomsgaardsvej",
    "iso:country":"DK",
    "sg:address":"Tomsg\u00e5rdsvej 17 - 19",
    "sg:city":"K\u00f8benhavn NV",
    "sg:orig_category":"Kurve",
    "sg:phone":"+45 38 34 33 88",
    "sg:postcode":"2400",
    "sg:province":"Danmark",
    "sg:website":"www.blindes-arbejde.dk",
    "wof:name":"Blindes Arbejde",
    "wof:placetype":"venue"
},
  "geometry": {"coordinates":[-117.02272033689999,38.5024604797],"type":"Point"}
}