{
  "type": "Feature",
  "properties": {
    "addr:full":"Grundvej 49, Grund Alling\u00e5bro Danmark 8961",
    "addr:housenumber":"49",
    "addr:postcode":"8961",
    "addr:street":"Grundvej;Grund;Danmark",
    "iso:country":"DK",
    "sg:address":"Grundvej 49, Grund",
    "sg:city":"Alling\u00e5bro",
    "sg:classifiers":[
        {
            "category":"Taxi",
            "type":"Transportation"
        }
    ],
    "sg:phone":"+45 86 48 13 90",
    "sg:postcode":"8961",
    "sg:province":"Danmark",
    "wof:name":"Grund Taxi",
    "wof:placetype":"venue"
},
  "geometry": {"coordinates":[10.3230552673,56.4639511108],"type":"Point"}
}