{
  "type": "Feature",
  "properties": {
    "iso:country":"DK",
    "sg:address":"Industrivej 13",
    "sg:city":"Thors\u00f8",
    "sg:orig_category":"Blikkenslagere",
    "sg:phone":"+45 86 96 67 98",
    "sg:postcode":"8881",
    "sg:province":"Danmark",
    "wof:name":"Thors\u00f8 Blikkenslagerforretning ApS",
    "wof:placetype":"venue"
},
  "geometry": {"coordinates":[9.782715,56.297577],"type":"Point"}
}