{
  "type": "Feature",
  "properties": {
    "addr:full":"R\u00e5dhusgade 10 Saksk\u00f8bing Danmark 4990",
    "addr:housenumber":"10",
    "addr:postcode":"4990",
    "addr:street":"Raadhusgade",
    "iso:country":"DK",
    "sg:address":"R\u00e5dhusgade 10",
    "sg:city":"Saksk\u00f8bing",
    "sg:orig_category":"Tandklinikker, Kommunale",
    "sg:phone":"+45 54 70 44 15",
    "sg:postcode":"4990",
    "sg:province":"Danmark",
    "wof:name":"Den Kommunale Tandpleje",
    "wof:placetype":"venue"
},
  "geometry": {"coordinates":[-114.0767440796,46.4432487488],"type":"Point"}
}