{
  "type": "Feature",
  "properties": {
    "iso:country":"DK",
    "sg:address":"Helligkorsgade 5",
    "sg:city":"Kolding",
    "sg:orig_category":"Boghandlere",
    "sg:phone":"+45 75 52 03 77",
    "sg:postcode":"6000",
    "sg:province":"Danmark",
    "wof:name":"Munk BOG & IDE",
    "wof:placetype":"venue"
},
  "geometry": {"coordinates":[9.473323822,55.4892120361],"type":"Point"}
}