{
  "type": "Feature",
  "properties": {
    "addr:full":"Egeparken 156m Odense N\u00d8 Danmark 5240",
    "addr:housenumber":"156m",
    "addr:postcode":"5240",
    "addr:street":"Egeparken",
    "iso:country":"DK",
    "sg:address":"Egeparken 156m",
    "sg:city":"Odense N\u00d8",
    "sg:orig_category":"Boligselskaber",
    "sg:phone":"+45 66 10 44 50",
    "sg:postcode":"5240",
    "sg:province":"Danmark",
    "wof:name":"Andelsboligforeningen H\u00f8jstrup afd. 14",
    "wof:placetype":"venue"
},
  "geometry": {"coordinates":[10.4411592484,55.4084014893],"type":"Point"}
}