{
  "type": "Feature",
  "properties": {
    "addr:full":"Butikstorvet, Carlsh\u00f8jvej 49 Kongens Lyngby Danmark 2800",
    "addr:housenumber":"49",
    "addr:postcode":"2800",
    "addr:street":"Carlshojvej",
    "iso:country":"DK",
    "sg:address":"Butikstorvet, Carlsh\u00f8jvej 49",
    "sg:city":"Kongens Lyngby",
    "sg:orig_category":"Fodterapeuter",
    "sg:phone":"+45 45 93 01 12",
    "sg:postcode":"2800",
    "sg:province":"Danmark",
    "wof:name":"Pickering, Malene",
    "wof:placetype":"venue"
},
  "geometry": {"coordinates":[12.5368299484,55.7949905396],"type":"Point"}
}