{
  "type": "Feature",
  "properties": {
    "addr:full":"I. C. Modewegs Vej 1, Postboks 260 Kongens Lyngby Danmark 2800",
    "addr:housenumber":"1;260",
    "addr:postcode":"2800",
    "addr:street":"I. C. Modewegs Vej",
    "iso:country":"DK",
    "sg:address":"I. C. Modewegs Vej 1, Postboks 260",
    "sg:city":"Kongens Lyngby",
    "sg:orig_category":"Museer",
    "sg:phone":"+45 33 13 44 11",
    "sg:postcode":"2800",
    "sg:province":"Danmark",
    "wof:name":"Brede V\u00e6rk",
    "wof:placetype":"venue"
},
  "geometry": {"coordinates":[12.5368299484,55.7949905396],"type":"Point"}
}