{
  "type": "Feature",
  "properties": {
    "iso:country":"DK",
    "sg:address":"Odinsvej 29",
    "sg:city":"Silkeborg",
    "sg:orig_category":"Skovbrug",
    "sg:phone":"+45 86 81 10 09",
    "sg:postcode":"8600",
    "sg:province":"Danmark",
    "wof:name":"Madsen, Tina Juul",
    "wof:placetype":"venue"
},
  "geometry": {"coordinates":[9.4969835281,56.1634902954],"type":"Point"}
}