{
  "type": "Feature",
  "properties": {
    "addr:full":"\u00d8stergade 2, Kr. Helsinge G\u00f8rlev Danmark 4281",
    "addr:housenumber":"2",
    "addr:postcode":"4281",
    "addr:street":"Ostergade",
    "iso:country":"DK",
    "sg:address":"\u00d8stergade 2, Kr. Helsinge",
    "sg:city":"G\u00f8rlev",
    "sg:orig_category":"Tandklinikker, Kommunale",
    "sg:phone":"+45 58 85 58 50",
    "sg:postcode":"4281",
    "sg:province":"Danmark",
    "wof:name":"G\u00f8rlev kommunale tandpleje",
    "wof:placetype":"venue"
},
  "geometry": {"coordinates":[11.1143903732,55.5207710266],"type":"Point"}
}