{
  "type": "Feature",
  "properties": {
    "iso:country":"DK",
    "sg:address":"v/ Erling J\u00f8rgensen, Hasselvej 7",
    "sg:city":"Havdrup",
    "sg:orig_category":"Grundejerforeninger",
    "sg:postcode":"4622",
    "sg:province":"Danmark",
    "wof:name":"Birkevangen, Vejlauget",
    "wof:placetype":"venue"
},
  "geometry": {"coordinates":[12.1158895493,55.5443534851],"type":"Point"}
}