{
  "type": "Feature",
  "properties": {
    "addr:full":"Kastetvej 55 Aalborg Danmark 9000",
    "addr:housenumber":"55",
    "addr:postcode":"9000",
    "addr:street":"Kastetvej",
    "iso:country":"DK",
    "sg:address":"Kastetvej 55",
    "sg:city":"Aalborg",
    "sg:orig_category":"Bagere",
    "sg:phone":"+45 98 12 72 55",
    "sg:postcode":"9000",
    "sg:province":"Danmark",
    "wof:name":"Vestbyens Bageri",
    "wof:placetype":"venue"
},
  "geometry": {"coordinates":[9.902637,57.05381],"type":"Point"}
}