{
  "type": "Feature",
  "properties": {
    "addr:full":"Fmd.: Bo Thayzen Lerche, T\u00e5rnbjergg\u00e5rdsvej 7, Allerslev Lejre Danmark 4320",
    "addr:housenumber":"7",
    "addr:postcode":"4320",
    "addr:street":"Taarnbjerggaardsvej;Allerslev",
    "iso:country":"DK",
    "sg:address":"Fmd.: Bo Thayzen Lerche, T\u00e5rnbjergg\u00e5rdsvej 7, Allerslev",
    "sg:city":"Lejre",
    "sg:orig_category":"Grundejerforeninger",
    "sg:phone":"+45 46 48 22 20",
    "sg:postcode":"4320",
    "sg:province":"Danmark",
    "wof:name":"T\u00e5rnbjergg\u00e5rdsvej Grundejerforening",
    "wof:placetype":"venue"
},
  "geometry": {"coordinates":[11.9678316116,55.6005630493],"type":"Point"}
}