{
  "type": "Feature",
  "properties": {
    "addr:full":"Str\u00f8get 12 B Ikast Danmark 7430",
    "addr:housenumber":"12 b",
    "addr:postcode":"7430",
    "addr:street":"Stroget",
    "iso:country":"DK",
    "sg:address":"Str\u00f8get 12 B",
    "sg:city":"Ikast",
    "sg:classifiers":[
        {
            "category":"Communications",
            "type":"Services"
        }
    ],
    "sg:phone":"+45 97 15 73 33",
    "sg:postcode":"7430",
    "sg:province":"Danmark",
    "sg:tags":[
        "og",
        "tv",
        "radio"
    ],
    "wof:name":"City Radio & TV",
    "wof:placetype":"venue"
},
  "geometry": {"coordinates":[9.1551160812,56.1403160095],"type":"Point"}
}