{
  "type": "Feature",
  "properties": {
    "addr:full":"v/ Jan S\u00f8rensen, Guld\u00f8jev\u00e6nget 52, Hjallese Odense S Danmark 5260",
    "addr:housenumber":"52",
    "addr:postcode":"5260",
    "addr:street":"Hjallese",
    "iso:country":"DK",
    "sg:address":"v/ Jan S\u00f8rensen, Guld\u00f8jev\u00e6nget 52, Hjallese",
    "sg:city":"Odense S",
    "sg:orig_category":"Hobbybetonede foreninger",
    "sg:phone":"+45 66 15 21 41",
    "sg:postcode":"5260",
    "sg:province":"Danmark",
    "wof:name":"Eksperimenterende Danske Radioamat\u00f8rer - Odense City Afd.",
    "wof:placetype":"venue"
},
  "geometry": {"coordinates":[10.3157806396,55.3122825623],"type":"Point"}
}