{
  "type": "Feature",
  "properties": {
    "addr:full":"Fmd.: Jakob Hellerup, Hesselbjergvej 6 Viborg Danmark 8800",
    "addr:housenumber":"6",
    "addr:postcode":"8800",
    "addr:street":"Jakob;Hesselbjergvej",
    "iso:country":"DK",
    "sg:address":"Fmd.: Jakob Hellerup, Hesselbjergvej 6",
    "sg:city":"Viborg",
    "sg:orig_category":"Spejderkorps",
    "sg:phone":"+45 86 64 73 42",
    "sg:postcode":"8800",
    "sg:province":"Danmark",
    "wof:name":"Danske, Det Spejderkorps - 1. og 3. Viborg Gruppe",
    "wof:placetype":"venue"
},
  "geometry": {"coordinates":[9.4071502686,56.452671051],"type":"Point"}
}