{
  "type": "Feature",
  "properties": {
    "addr:full":"N\u00f8rregade 25 Eskilstrup Danmark 4863",
    "addr:housenumber":"25",
    "addr:postcode":"4863",
    "addr:street":"Norregade",
    "iso:country":"DK",
    "sg:address":"N\u00f8rregade 25",
    "sg:city":"Eskilstrup",
    "sg:orig_category":"Malermestre",
    "sg:phone":"+45 54 43 67 87",
    "sg:postcode":"4863",
    "sg:province":"Danmark",
    "wof:name":"J\u00f8rgensen, Poul Roland",
    "wof:placetype":"venue"
},
  "geometry": {"coordinates":[11.886756897,54.8598823547],"type":"Point"}
}