{
  "type": "Feature",
  "properties": {
    "addr:full":"Svendborgvej 4 Ringe Danmark 5750",
    "addr:housenumber":"4",
    "addr:postcode":"5750",
    "addr:street":"Svendborgvej",
    "iso:country":"DK",
    "sg:address":"Svendborgvej 4",
    "sg:city":"Ringe",
    "sg:orig_category":"Murermestre",
    "sg:phone":"+45 62 62 17 00",
    "sg:postcode":"5750",
    "sg:province":"Danmark",
    "wof:name":"Nielsen, Erik",
    "wof:placetype":"venue"
},
  "geometry": {"coordinates":[10.4797277451,55.2344017029],"type":"Point"}
}