{
  "type": "Feature",
  "properties": {
    "addr:full":"T\u00e5rsvej 13 Saksk\u00f8bing Danmark 4990",
    "addr:housenumber":"13",
    "addr:postcode":"4990",
    "addr:street":"Taarsvej",
    "iso:country":"DK",
    "sg:address":"T\u00e5rsvej 13",
    "sg:city":"Saksk\u00f8bing",
    "sg:orig_category":"Autoreparation og -service",
    "sg:phone":"+45 54 77 22 44",
    "sg:postcode":"4990",
    "sg:province":"Danmark",
    "wof:name":"P.A.M. Service",
    "wof:placetype":"venue"
},
  "geometry": {"coordinates":[-114.0767440796,46.4432487488],"type":"Point"}
}