{
  "type": "Feature",
  "properties": {
    "addr:full":"Vestergade 4 Kjellerup Danmark 8620",
    "addr:housenumber":"4",
    "addr:postcode":"8620",
    "addr:street":"Vestergade",
    "iso:country":"DK",
    "sg:address":"Vestergade 4",
    "sg:city":"Kjellerup",
    "sg:orig_category":"Optikere",
    "sg:phone":"+45 86 88 11 64",
    "sg:postcode":"8620",
    "sg:province":"Danmark",
    "wof:name":"T\u00e6kke, Kim Erland",
    "wof:placetype":"venue"
},
  "geometry": {"coordinates":[9.4296398163,56.2894744873],"type":"Point"}
}