{
  "type": "Feature",
  "properties": {
    "addr:full":"Virkelyst 54, Gjellerup Herning Danmark 7400",
    "addr:housenumber":"54",
    "addr:postcode":"7400",
    "addr:street":"Virkelyst",
    "iso:country":"DK",
    "sg:address":"Virkelyst 54, Gjellerup",
    "sg:city":"Herning",
    "sg:orig_category":"Tekstilindustri",
    "sg:phone":"+45 97 11 64 44",
    "sg:postcode":"7400",
    "sg:province":"Danmark",
    "wof:name":"Sejtex Trikotagev\u00e6veri",
    "wof:placetype":"venue"
},
  "geometry": {"coordinates":[8.9768896103,56.1374168396],"type":"Point"}
}