{
  "type": "Feature",
  "properties": {
    "addr:full":"Illeris\u00f8revej 9, Hvalpsund Fars\u00f8 Danmark 9640",
    "addr:housenumber":"9",
    "addr:postcode":"9640",
    "addr:street":"Illerisorevej",
    "iso:country":"DK",
    "sg:address":"Illeris\u00f8revej 9, Hvalpsund",
    "sg:city":"Fars\u00f8",
    "sg:orig_category":"Fisk og vildt",
    "sg:phone":"+45 98 63 81 04",
    "sg:postcode":"9640",
    "sg:province":"Danmark",
    "wof:name":"Mortensen, Kristian",
    "wof:placetype":"venue"
},
  "geometry": {"coordinates":[9.1937885284,56.6945037842],"type":"Point"}
}