{
  "type": "Feature",
  "properties": {
    "addr:full":"Sindalsvej 37 Risskov Danmark 8240",
    "addr:housenumber":"37",
    "addr:postcode":"8240",
    "addr:street":"Sindalsvej",
    "iso:country":"DK",
    "sg:address":"Sindalsvej 37",
    "sg:city":"Risskov",
    "sg:classifiers":[
        {
            "category":"Airport",
            "type":"Transportation"
        }
    ],
    "sg:phone":"+45 86 21 22 33",
    "sg:postcode":"8240",
    "sg:province":"Danmark",
    "sg:tags":[
        "automation"
    ],
    "sg:website":"www.flog.dk",
    "wof:name":"Flog Electric",
    "wof:placetype":"venue"
},
  "geometry": {"coordinates":[10.2172336578,56.2087249756],"type":"Point"}
}