{
  "type": "Feature",
  "properties": {
    "addr:full":"Fjordparken 23 Hals Danmark 9370",
    "addr:housenumber":"23",
    "addr:postcode":"9370",
    "addr:street":"Fjordparken",
    "iso:country":"DK",
    "sg:address":"Fjordparken 23",
    "sg:city":"Hals",
    "sg:orig_category":"Dagcentre",
    "sg:postcode":"9370",
    "sg:province":"Danmark",
    "wof:name":"Dagtilbud for demente",
    "wof:placetype":"venue"
},
  "geometry": {"coordinates":[10.3044300079,56.9951820374],"type":"Point"}
}