{
  "type": "Feature",
  "properties": {
    "iso:country":"DK",
    "sg:address":"Asylgade 3",
    "sg:city":"Odense C",
    "sg:classifiers":[
        {
            "category":"Communications",
            "type":"Services"
        }
    ],
    "sg:phone":"+45 66 14 22 32",
    "sg:postcode":"5000",
    "sg:province":"Danmark",
    "sg:tags":[
        "og",
        "tv",
        "radio"
    ],
    "sg:website":"www.kt-radio.dk",
    "wof:name":"KT Radio Odense A/S",
    "wof:placetype":"venue"
},
  "geometry": {"coordinates":[10.3874015808,55.3965110779],"type":"Point"}
}