{
  "type": "Feature",
  "properties": {
    "addr:full":"S\u00f8gade 2 Skibby Danmark 4050",
    "addr:housenumber":"2",
    "addr:postcode":"4050",
    "addr:street":"Sogade",
    "iso:country":"DK",
    "sg:address":"S\u00f8gade 2",
    "sg:city":"Skibby",
    "sg:orig_category":"El-artikler",
    "sg:phone":"+45 70 23 04 44",
    "sg:postcode":"4050",
    "sg:province":"Danmark",
    "wof:name":"Sej-Tech",
    "wof:placetype":"venue"
},
  "geometry": {"coordinates":[11.8628911972,55.7432861328],"type":"Point"}
}