{
  "type": "Feature",
  "properties": {
    "iso:country":"DK",
    "sg:address":"N\u00f8rrev\u00e6nget 4, Givskud",
    "sg:city":"Give",
    "sg:orig_category":"Drejere",
    "sg:phone":"+45 75 73 05 11",
    "sg:postcode":"7323",
    "sg:province":"Danmark",
    "wof:name":"Skov's M\u00f8belknopper",
    "wof:placetype":"venue"
},
  "geometry": {"coordinates":[9.2362060547,55.845413208],"type":"Point"}
}