{
  "type": "Feature",
  "properties": {
    "addr:full":"Fmd.: Peter Thomasen, Stationsvej 14 C, 1., lej. 4 Dianalund Danmark 4293",
    "addr:housenumber":"14 c 1;4",
    "addr:postcode":"4293",
    "addr:street":"Stationsvej;Lej.",
    "iso:country":"DK",
    "sg:address":"Fmd.: Peter Thomasen, Stationsvej 14 C, 1., lej. 4",
    "sg:city":"Dianalund",
    "sg:orig_category":"Kirkelige foreninger",
    "sg:phone":"+45 58 26 58 13",
    "sg:postcode":"4293",
    "sg:province":"Danmark",
    "wof:name":"KFUM og KFUK i Dianalund",
    "wof:placetype":"venue"
},
  "geometry": {"coordinates":[11.4945745468,55.5332489014],"type":"Point"}
}