{
  "type": "Feature",
  "properties": {
    "addr:full":"Ahlgade 1 B Holb\u00e6k Danmark 4300",
    "addr:housenumber":"1 b",
    "addr:postcode":"4300",
    "addr:street":"Ahlgade",
    "iso:country":"DK",
    "sg:address":"Ahlgade 1 B",
    "sg:city":"Holb\u00e6k",
    "sg:orig_category":"\u00c3\u02dcvrige foreninger",
    "sg:phone":"+45 59 44 29 19",
    "sg:postcode":"4300",
    "sg:province":"Danmark",
    "sg:website":"www.sidesporet.dk",
    "wof:name":"Sidesporet",
    "wof:placetype":"venue"
},
  "geometry": {"coordinates":[77.2480392456,14.1354398727],"type":"Point"}
}