{
  "type": "Feature",
  "properties": {
    "addr:full":"Transvej 49, Ferring Lemvig Danmark 7620",
    "addr:housenumber":"49",
    "addr:postcode":"7620",
    "addr:street":"Transvej",
    "iso:country":"DK",
    "sg:address":"Transvej 49, Ferring",
    "sg:city":"Lemvig",
    "sg:orig_category":"Pensionater",
    "sg:phone":"+45 97 89 52 50",
    "sg:postcode":"7620",
    "sg:province":"Danmark",
    "wof:name":"Transvej 49, I/S",
    "wof:placetype":"venue"
},
  "geometry": {"coordinates":[8.3073654175,56.5505104065],"type":"Point"}
}