{
  "type": "Feature",
  "properties": {
    "iso:country":"DK",
    "sg:address":"Grynderupvejen 56, R\u00f8rb\u00e6k",
    "sg:city":"Hobro",
    "sg:orig_category":"Kirker",
    "sg:postcode":"9500",
    "sg:province":"Danmark",
    "wof:name":"R\u00f8rb\u00e6k Kirke",
    "wof:placetype":"venue"
},
  "geometry": {"coordinates":[9.7946596146,56.6382789612],"type":"Point"}
}