{
  "type": "Feature",
  "properties": {
    "addr:full":"Lyngmosevej 40 Torrig Danmark 4943",
    "addr:housenumber":"40",
    "addr:postcode":"4943",
    "addr:street":"Lyngmosevej",
    "iso:country":"DK",
    "sg:address":"Lyngmosevej 40",
    "sg:city":"Torrig",
    "sg:orig_category":"Bogtrykkerier",
    "sg:phone":"+45 54 93 74 07",
    "sg:postcode":"4943",
    "sg:province":"Danmark",
    "wof:name":"Lindet Bogtryk & Offset",
    "wof:placetype":"venue"
},
  "geometry": {"coordinates":[11.3237533569,54.8925933838],"type":"Point"}
}