{
  "type": "Feature",
  "properties": {
    "addr:full":"\u00d8stergade 1 A Ikast Danmark 7430",
    "addr:housenumber":"1 a",
    "addr:postcode":"7430",
    "addr:street":"Ostergade",
    "iso:country":"DK",
    "sg:address":"\u00d8stergade 1 A",
    "sg:city":"Ikast",
    "sg:orig_category":"Selskabslokaler",
    "sg:phone":"+45 97 25 03 88",
    "sg:postcode":"7430",
    "sg:province":"Danmark",
    "wof:name":"Ph\u00f8nix Huset",
    "wof:placetype":"venue"
},
  "geometry": {"coordinates":[9.1546468735,56.1395339966],"type":"Point"}
}