{
  "type": "Feature",
  "properties": {
    "addr:full":"Toftevej 65, S\u00f8borg Gilleleje Danmark 3250",
    "addr:housenumber":"65",
    "addr:postcode":"3250",
    "addr:street":"Toftevej;Soborg",
    "iso:country":"DK",
    "sg:address":"Toftevej 65, S\u00f8borg",
    "sg:city":"Gilleleje",
    "sg:orig_category":"Vinduespolering",
    "sg:phone":"+45 49 71 87 66",
    "sg:postcode":"3250",
    "sg:province":"Danmark",
    "wof:name":"VM-Husservice",
    "wof:placetype":"venue"
},
  "geometry": {"coordinates":[12.3087387085,56.123462677],"type":"Point"}
}