{
  "type": "Feature",
  "properties": {
    "iso:country":"DK",
    "sg:address":"Leder: Rasmus Viuff, \u00c5gade 44",
    "sg:city":"Kjellerup",
    "sg:orig_category":"Kulturelle foreninger",
    "sg:phone":"+45 86 88 20 50",
    "sg:postcode":"8620",
    "sg:province":"Danmark",
    "sg:website":"www.aof-viborgamt.dk",
    "wof:name":"AOF - Arbejdernes Oplysningsforbund",
    "wof:placetype":"venue"
},
  "geometry": {"coordinates":[9.430934906,56.2877655029],"type":"Point"}
}