{
  "type": "Feature",
  "properties": {
    "addr:full":"Minervavej 63 Randers Danmark 8900",
    "addr:housenumber":"63",
    "addr:postcode":"8900",
    "addr:street":"Minervavej",
    "iso:country":"DK",
    "sg:address":"Minervavej 63",
    "sg:city":"Randers",
    "sg:orig_category":"Erhvervsskoler",
    "sg:phone":"+45 87 11 44 00",
    "sg:postcode":"8900",
    "sg:province":"Danmark",
    "wof:name":"Det Danske Erhvervsakademi",
    "wof:placetype":"venue"
},
  "geometry": {"coordinates":[10.0357952118,56.4593734741],"type":"Point"}
}