{
  "type": "Feature",
  "properties": {
    "iso:country":"DK",
    "sg:address":"Munklindevej 33 ",
    "sg:city":"Bording",
    "sg:classifiers":[
        {
            "category":"Personal",
            "subcategory":"Shoe Repair & Shine",
            "type":"Services"
        }
    ],
    "sg:phone":"+45 86 86 12 45",
    "sg:postcode":"7441",
    "sg:province":"Danmark",
    "sg:tags":[
        "leather"
    ],
    "wof:name":"H\u00d8KA, IMPORT OG HANDEL APS",
    "wof:placetype":"venue"
},
  "geometry": {"coordinates":[9.2033376694,56.2002792358],"type":"Point"}
}