{
  "type": "Feature",
  "properties": {
    "addr:full":"S\u00f8borg Hovedgade 213, 1. th S\u00f8borg Danmark 2860",
    "addr:housenumber":"213 1 th",
    "addr:postcode":"2860",
    "addr:street":"Soborg Hovedgade;Danmark",
    "iso:country":"DK",
    "sg:address":"S\u00f8borg Hovedgade 213, 1. th",
    "sg:city":"S\u00f8borg",
    "sg:orig_category":"Distriktspsykiatri",
    "sg:phone":"+45 39 66 21 51",
    "sg:postcode":"2860",
    "sg:province":"Danmark",
    "wof:name":"Distriktspsykiatrisk Center i Gladsaxe",
    "wof:placetype":"venue"
},
  "geometry": {"coordinates":[-101.39041900629999,35.6679611206],"type":"Point"}
}