{
  "type": "Feature",
  "properties": {
    "addr:full":"Valmuevej 27  Horsens Danmark 8700",
    "addr:housenumber":"27",
    "addr:postcode":"8700",
    "addr:street":"Valmuevej",
    "iso:country":"DK",
    "sg:address":"Valmuevej 27 ",
    "sg:city":"Horsens",
    "sg:classifiers":[
        {
            "category":"Autos & Motor Vehicles",
            "subcategory":"Automobile Sales",
            "type":"Retail Goods"
        }
    ],
    "sg:phone":"+45 75 64 40 64",
    "sg:postcode":"8700",
    "sg:province":"Danmark",
    "sg:tags":[
        "industrial"
    ],
    "wof:name":"DAFETA TRANS APS",
    "wof:placetype":"venue"
},
  "geometry": {"coordinates":[9.8466739655,55.8294830322],"type":"Point"}
}