{
  "type": "Feature",
  "properties": {
    "iso:country":"DK",
    "sg:address":"Borgergade 58",
    "sg:city":"Esbjerg",
    "sg:orig_category":"Barnevogne",
    "sg:phone":"+45 75 13 22 63",
    "sg:postcode":"6700",
    "sg:province":"Danmark",
    "wof:name":"Babysam",
    "wof:placetype":"venue"
},
  "geometry": {"coordinates":[8.449561,55.465298],"type":"Point"}
}