{
  "type": "Feature",
  "properties": {
    "addr:full":"\u00d8resundsvej 10 B K\u00f8benhavn S Danmark 2300",
    "addr:housenumber":"10 b",
    "addr:postcode":"2300",
    "addr:street":"Oresundsvej;Kobenhavn S Danmark",
    "iso:country":"DK",
    "sg:address":"\u00d8resundsvej 10 B",
    "sg:city":"K\u00f8benhavn S",
    "sg:orig_category":"Integrerede institutioner",
    "sg:phone":"+45 32 84 05 56",
    "sg:postcode":"2300",
    "sg:province":"Danmark",
    "wof:name":"Den Intregrerede Institutioin",
    "wof:placetype":"venue"
},
  "geometry": {"coordinates":[-78.1299133301,36.7267417908],"type":"Point"}
}