{
  "type": "Feature",
  "properties": {
    "addr:full":"Toldbodgade 6 \u00c5rhus C Danmark 8000",
    "addr:housenumber":"6",
    "addr:postcode":"8000",
    "addr:street":"Toldbodgade",
    "iso:country":"DK",
    "sg:address":"Toldbodgade 6",
    "sg:city":"\u00c5rhus C",
    "sg:orig_category":"Spillesteder, Rytmiske",
    "sg:phone":"+45 86 13 47 22",
    "sg:postcode":"8000",
    "sg:province":"Danmark",
    "wof:name":"Train",
    "wof:placetype":"venue"
},
  "geometry": {"coordinates":[4.717400074,49.7588005066],"type":"Point"}
}