{
  "type": "Feature",
  "properties": {
    "iso:country":"DK",
    "sg:address":"Valby Langgade 58",
    "sg:city":"Valby",
    "sg:classifiers":[
        {
            "category":"Restaurant",
            "type":"Food & Drink"
        }
    ],
    "sg:phone":"+45 36 30 45 67",
    "sg:postcode":"2500",
    "sg:province":"Danmark",
    "wof:name":"Caf\u00e9 Cir\u00e9",
    "wof:placetype":"venue"
},
  "geometry": {"coordinates":[12.5147943497,55.6664352417],"type":"Point"}
}