{
  "type": "Feature",
  "properties": {
    "addr:full":"Nordre Ringvej 38 Vojens Danmark 6500",
    "addr:housenumber":"38",
    "addr:postcode":"6500",
    "addr:street":"Nordre Ringvej",
    "iso:country":"DK",
    "sg:address":"Nordre Ringvej 38",
    "sg:city":"Vojens",
    "sg:orig_category":"Psykoterapi",
    "sg:phone":"+45 74 54 19 49",
    "sg:postcode":"6500",
    "sg:province":"Danmark",
    "sg:website":"www.livskilden-vojens.dk",
    "wof:name":"Livskilden",
    "wof:placetype":"venue"
},
  "geometry": {"coordinates":[9.3020706177,55.2518768311],"type":"Point"}
}