{
  "type": "Feature",
  "properties": {
    "addr:full":"Fmd.: Niels Aage Pedersen, H\u00e6rvigsgade 6 Kalundborg Danmark 4400",
    "addr:housenumber":"6",
    "addr:postcode":"4400",
    "addr:street":"Aage;Haervigsgade",
    "iso:country":"DK",
    "sg:address":"Fmd.: Niels Aage Pedersen, H\u00e6rvigsgade 6",
    "sg:city":"Kalundborg",
    "sg:orig_category":"Grundejerforeninger",
    "sg:phone":"+45 59 51 53 34",
    "sg:postcode":"4400",
    "sg:province":"Danmark",
    "wof:name":"Haveforeningen af 1929 Kalundborg Virkelyst",
    "wof:placetype":"venue"
},
  "geometry": {"coordinates":[11.0934085846,55.6797485352],"type":"Point"}
}