{
  "type": "Feature",
  "properties": {
    "addr:full":"H\u00f8yersvej 10, Vester\u00f8 Havn L\u00e6s\u00f8 Danmark 9940",
    "addr:housenumber":"10",
    "addr:postcode":"9940",
    "addr:street":"Hoyersvej;Vestero Havn;Danmark",
    "iso:country":"DK",
    "sg:address":"H\u00f8yersvej 10, Vester\u00f8 Havn",
    "sg:city":"L\u00e6s\u00f8",
    "sg:orig_category":"Faglige organisationer og foreninger",
    "sg:phone":"+45 98 49 93 32",
    "sg:postcode":"9940",
    "sg:province":"Danmark",
    "wof:name":"Vester\u00f8 Havn Fiskeriforening",
    "wof:placetype":"venue"
},
  "geometry": {"coordinates":[-82.57898712159999,38.4234962463],"type":"Point"}
}