{
  "type": "Feature",
  "properties": {
    "addr:full":"Ordrupvej 121 Charlottenlund Danmark 2920",
    "addr:housenumber":"121",
    "addr:postcode":"2920",
    "addr:street":"Ordrupvej",
    "iso:country":"DK",
    "sg:address":"Ordrupvej 121",
    "sg:city":"Charlottenlund",
    "sg:orig_category":"Filialbiblioteker",
    "sg:phone":"+45 39 64 14 40",
    "sg:postcode":"2920",
    "sg:province":"Danmark",
    "wof:name":"Ordrup Filialbibliotek",
    "wof:placetype":"venue"
},
  "geometry": {"coordinates":[12.5695066452,55.7594833374],"type":"Point"}
}