{
  "type": "Feature",
  "properties": {
    "addr:full":"C. E. Christiansens Vej 29 Maribo Danmark 4930",
    "addr:housenumber":"29",
    "addr:postcode":"4930",
    "addr:street":"C. E. Christiansens Vej",
    "iso:country":"DK",
    "sg:address":"C. E. Christiansens Vej 29",
    "sg:city":"Maribo",
    "sg:orig_category":"Posthuse",
    "sg:phone":"+45 54 84 81 00",
    "sg:postcode":"4930",
    "sg:province":"Danmark",
    "wof:name":"Post Danmark, Maribo Distributionscenter",
    "wof:placetype":"venue"
},
  "geometry": {"coordinates":[11.5139503479,54.7801818848],"type":"Point"}
}