{
  "type": "Feature",
  "properties": {
    "addr:full":"Bethaniagade 11, 2. th Kjellerup Danmark 8620",
    "addr:housenumber":"11 2 th",
    "addr:postcode":"8620",
    "addr:street":"Bethaniagade",
    "iso:country":"DK",
    "sg:address":"Bethaniagade 11, 2. th",
    "sg:city":"Kjellerup",
    "sg:orig_category":"Kirkelige foreninger",
    "sg:phone":"+45 23 72 40 48",
    "sg:postcode":"8620",
    "sg:province":"Danmark",
    "wof:name":"KFUM & KFUK i Kjellerup",
    "wof:placetype":"venue"
},
  "geometry": {"coordinates":[9.430934906,56.2877655029],"type":"Point"}
}