{
  "type": "Feature",
  "properties": {
    "addr:full":"Fmd.: S\u00f8ren Nerl\u00f8e, Brogade 16 K\u00f8ge Danmark 4600",
    "addr:housenumber":"16",
    "addr:postcode":"4600",
    "addr:street":"Brogade",
    "iso:country":"DK",
    "sg:address":"Fmd.: S\u00f8ren Nerl\u00f8e, Brogade 16",
    "sg:city":"K\u00f8ge",
    "sg:orig_category":"Soldaterforeninger",
    "sg:phone":"+45 56 65 19 86",
    "sg:postcode":"4600",
    "sg:province":"Danmark",
    "wof:name":"K\u00f8ge Marineforening",
    "wof:placetype":"venue"
},
  "geometry": {"coordinates":[-76.7760009766,35.8064613342],"type":"Point"}
}