{
  "type": "Feature",
  "properties": {
    "iso:country":"DK",
    "sg:address":"Ulvevej 110",
    "sg:city":"Esbjerg N",
    "sg:orig_category":"Kirkesogne",
    "sg:phone":"+45 75 13 70 00",
    "sg:postcode":"6715",
    "sg:province":"Danmark",
    "wof:name":"Gjesing Sogns Kirkekontor",
    "wof:placetype":"venue"
},
  "geometry": {"coordinates":[8.448094368,55.5075912476],"type":"Point"}
}