{
  "type": "Feature",
  "properties": {
    "iso:country":"DK",
    "sg:address":"v/ Karen Nisbeth, Kirkebakken 1",
    "sg:city":"Svaneke",
    "sg:orig_category":"Hobbybetonede foreninger",
    "sg:phone":"+45 56 49 69 69",
    "sg:postcode":"3740",
    "sg:province":"Danmark",
    "wof:name":"Svampevennerne",
    "wof:placetype":"venue"
},
  "geometry": {"coordinates":[15.140504837,55.1364555359],"type":"Point"}
}