{
  "type": "Feature",
  "properties": {
    "iso:country":"DK",
    "sg:address":"Algade 25",
    "sg:city":"Roskilde",
    "sg:orig_category":"Skomagere",
    "sg:phone":"+45 46 36 50 72",
    "sg:postcode":"4000",
    "sg:province":"Danmark",
    "wof:name":"Skottens Skomager",
    "wof:placetype":"venue"
},
  "geometry": {"coordinates":[12.0854387283,55.6411972046],"type":"Point"}
}