{
  "type": "Feature",
  "properties": {
    "addr:full":"Sm\u00f8rumvej 197 Br\u00f8nsh\u00f8j Danmark 2700",
    "addr:housenumber":"197",
    "addr:postcode":"2700",
    "addr:street":"Smorumvej",
    "iso:country":"DK",
    "sg:address":"Sm\u00f8rumvej 197",
    "sg:city":"Br\u00f8nsh\u00f8j",
    "sg:orig_category":"Ungdomsklubber",
    "sg:phone":"+45 38 28 44 88",
    "sg:postcode":"2700",
    "sg:province":"Danmark",
    "wof:name":"Fritids- og ungdomsklub v/Ungdomsg\u00e5rden",
    "wof:placetype":"venue"
},
  "geometry": {"coordinates":[30.0104103088,60.1411018372],"type":"Point"}
}