{
  "type": "Feature",
  "properties": {
    "addr:full":"Helsingevej 91 Helsinge Danmark 3200",
    "addr:housenumber":"91",
    "addr:postcode":"3200",
    "addr:street":"Helsingevej",
    "iso:country":"DK",
    "sg:address":"Helsingevej 91",
    "sg:city":"Helsinge",
    "sg:orig_category":"Konsulentvirksomheder",
    "sg:phone":"+45 48 79 50 50",
    "sg:postcode":"3200",
    "sg:province":"Danmark",
    "wof:name":"Bregnbak Consults",
    "wof:placetype":"venue"
},
  "geometry": {"coordinates":[12.190990448,56.001159668],"type":"Point"}
}