{
  "type": "Feature",
  "properties": {
    "addr:full":"Bredgade 65 Skjern Danmark 6900",
    "addr:housenumber":"65",
    "addr:postcode":"6900",
    "addr:street":"Bredgade",
    "iso:country":"DK",
    "sg:address":"Bredgade 65",
    "sg:city":"Skjern",
    "sg:orig_category":"Genbrugsbutikker",
    "sg:phone":"+45 97 35 41 11",
    "sg:postcode":"6900",
    "sg:province":"Danmark",
    "wof:name":"Dansk R\u00f8de Kors",
    "wof:placetype":"venue"
},
  "geometry": {"coordinates":[8.4920959473,55.9482383728],"type":"Point"}
}