{
  "type": "Feature",
  "properties": {
    "addr:full":"Gemsevej 15 Skive Danmark 7800",
    "addr:housenumber":"15",
    "addr:postcode":"7800",
    "addr:street":"Gemsevej",
    "iso:country":"DK",
    "sg:address":"Gemsevej 15",
    "sg:city":"Skive",
    "sg:orig_category":"Glas en gros",
    "sg:phone":"+45 97 52 47 11",
    "sg:postcode":"7800",
    "sg:province":"Danmark",
    "wof:name":"VG Glas A/S",
    "wof:placetype":"venue"
},
  "geometry": {"coordinates":[9.0343122482,56.5362663269],"type":"Point"}
}