{
  "type": "Feature",
  "properties": {
    "addr:full":"Torvet \u00c6r\u00f8sk\u00f8bing Danmark 5970",
    "addr:postcode":"5970",
    "addr:street":"Torvet;Danmark",
    "iso:country":"DK",
    "sg:address":"Torvet",
    "sg:city":"\u00c6r\u00f8sk\u00f8bing",
    "sg:orig_category":"Lokalarkiver",
    "sg:phone":"+45 62 52 13 44",
    "sg:postcode":"5970",
    "sg:province":"Danmark",
    "wof:name":"\u00c6r\u00f8sk\u00f8bing Kommunes Lokalhistorisk Arkiv",
    "wof:placetype":"venue"
},
  "geometry": {"coordinates":[-114.0767440796,46.4432487488],"type":"Point"}
}