{
  "type": "Feature",
  "properties": {
    "addr:full":"L\u00f8vk\u00e6rsvej 2 A Jyllinge Danmark 4040",
    "addr:housenumber":"2 a",
    "addr:postcode":"4040",
    "addr:street":"Lovkaersvej",
    "iso:country":"DK",
    "sg:address":"L\u00f8vk\u00e6rsvej 2 A",
    "sg:city":"Jyllinge",
    "sg:orig_category":"Fodplejere",
    "sg:phone":"+45 46 73 25 13",
    "sg:postcode":"4040",
    "sg:province":"Danmark",
    "wof:name":"Tina's Fodklinik",
    "wof:placetype":"venue"
},
  "geometry": {"coordinates":[12.1163625717,55.7643737793],"type":"Point"}
}