{
  "type": "Feature",
  "properties": {
    "addr:full":"Thomas Helsteds Vej 7 Skanderborg Danmark 8660",
    "addr:housenumber":"7",
    "addr:postcode":"8660",
    "addr:street":"Thomas Helsteds Vej",
    "iso:country":"DK",
    "sg:address":"Thomas Helsteds Vej 7",
    "sg:city":"Skanderborg",
    "sg:classifiers":[
        {
            "category":"Arts & Performance",
            "subcategory":"Art Gallery",
            "type":"Entertainment"
        }
    ],
    "sg:phone":"+45 86 52 44 00",
    "sg:postcode":"8660",
    "sg:province":"Danmark",
    "sg:tags":[
        "ventilation"
    ],
    "wof:name":"Belimo A/S",
    "wof:placetype":"venue"
},
  "geometry": {"coordinates":[9.9424200058,56.0473327637],"type":"Point"}
}