{
  "type": "Feature",
  "properties": {
    "addr:full":"Vossvej 5 Aalborg Danmark 9000",
    "addr:housenumber":"5",
    "addr:postcode":"9000",
    "addr:street":"Vossvej",
    "iso:country":"DK",
    "sg:address":"Vossvej 5",
    "sg:city":"Aalborg",
    "sg:orig_category":"INGENI\u00c3\u02dcRER",
    "sg:phone":"+45 98 12 55 67",
    "sg:postcode":"9000",
    "sg:province":"Danmark",
    "wof:name":"Bang, Knud",
    "wof:placetype":"venue"
},
  "geometry": {"coordinates":[9.9013023376,57.0421638489],"type":"Point"}
}