{
  "type": "Feature",
  "properties": {
    "addr:full":"Fmd.: Per Hvid, Stenvadpark 30 Farum Danmark 3520",
    "addr:housenumber":"30",
    "addr:postcode":"3520",
    "addr:street":"Stenvadpark",
    "iso:country":"DK",
    "sg:address":"Fmd.: Per Hvid, Stenvadpark 30",
    "sg:city":"Farum",
    "sg:orig_category":"Grundejerforeninger",
    "sg:phone":"+45 44 95 96 32",
    "sg:postcode":"3520",
    "sg:province":"Danmark",
    "wof:name":"Stenvadpark Grundejerforening",
    "wof:placetype":"venue"
},
  "geometry": {"coordinates":[12.3755493164,55.8150291443],"type":"Point"}
}