{
  "type": "Feature",
  "properties": {
    "addr:full":"Ermelundsvej 123 Gentofte Danmark 2820",
    "addr:housenumber":"123",
    "addr:postcode":"2820",
    "addr:street":"Ermelundsvej",
    "iso:country":"DK",
    "sg:address":"Ermelundsvej 123",
    "sg:city":"Gentofte",
    "sg:orig_category":"Pianostemmere",
    "sg:phone":"+45 39 68 19 59",
    "sg:postcode":"2820",
    "sg:province":"Danmark",
    "wof:name":"Hauber, Bernhard",
    "wof:placetype":"venue"
},
  "geometry": {"coordinates":[12.5351648331,55.767074585],"type":"Point"}
}