{
  "type": "Feature",
  "properties": {
    "addr:full":"Kildevej 1 Havdrup Danmark 4622",
    "addr:housenumber":"1",
    "addr:postcode":"4622",
    "addr:street":"Kildevej",
    "iso:country":"DK",
    "sg:address":"Kildevej 1",
    "sg:city":"Havdrup",
    "sg:orig_category":"Murermestre",
    "sg:phone":"+45 46 18 68 43",
    "sg:postcode":"4622",
    "sg:province":"Danmark",
    "sg:website":"www.jensensten.dk",
    "wof:name":"Jensen, Tommy",
    "wof:placetype":"venue"
},
  "geometry": {"coordinates":[12.1123123169,55.54246521],"type":"Point"}
}