{
  "type": "Feature",
  "properties": {
    "addr:full":"Prins Buris Vej 1 Vejle Danmark 7100",
    "addr:housenumber":"1",
    "addr:postcode":"7100",
    "addr:street":"Prins Buris Vej",
    "iso:country":"DK",
    "sg:address":"Prins Buris Vej 1",
    "sg:city":"Vejle",
    "sg:orig_category":"Rejsebureauer",
    "sg:phone":"+45 75 72 80 63",
    "sg:postcode":"7100",
    "sg:province":"Danmark",
    "wof:name":"HW Travel Service",
    "wof:placetype":"venue"
},
  "geometry": {"coordinates":[9.5443630219,55.6808547974],"type":"Point"}
}