{
  "type": "Feature",
  "properties": {
    "addr:full":"N\u00f8hr S\u00f8rensens Vej 1 Aalborg S\u00d8 Danmark 9210",
    "addr:housenumber":"1",
    "addr:postcode":"9210",
    "addr:street":"Sorensens Vej",
    "iso:country":"DK",
    "sg:address":"N\u00f8hr S\u00f8rensens Vej 1",
    "sg:city":"Aalborg S\u00d8",
    "sg:orig_category":"Legestuer",
    "sg:phone":"+45 99 31 52 90",
    "sg:postcode":"9210",
    "sg:province":"Danmark",
    "wof:name":"Legestuen Gug Kirke",
    "wof:placetype":"venue"
},
  "geometry": {"coordinates":[9.9318265915,57.0157775879],"type":"Point"}
}