{
  "type": "Feature",
  "properties": {
    "addr:full":"Bl\u00e6senborg Alle 10 Maribo Danmark 4930",
    "addr:housenumber":"10",
    "addr:postcode":"4930",
    "addr:street":"Blaesenborg Alle",
    "iso:country":"DK",
    "sg:address":"Bl\u00e6senborg Alle 10",
    "sg:city":"Maribo",
    "sg:orig_category":"Tandklinikker, Kommunale",
    "sg:phone":"+45 54 78 31 51",
    "sg:postcode":"4930",
    "sg:province":"Danmark",
    "wof:name":"Kommunale tandklinik i Bl\u00e6senborg, Den",
    "wof:placetype":"venue"
},
  "geometry": {"coordinates":[11.5347194672,54.7722091675],"type":"Point"}
}