{
  "type": "Feature",
  "properties": {
    "addr:full":"Gr\u00f8nningen 17 Ebeltoft Danmark 8400",
    "addr:housenumber":"17",
    "addr:postcode":"8400",
    "addr:street":"Gronningen",
    "iso:country":"DK",
    "sg:address":"Gr\u00f8nningen 17",
    "sg:city":"Ebeltoft",
    "sg:orig_category":"Museer",
    "sg:phone":"+45 86 34 21 40",
    "sg:postcode":"8400",
    "sg:province":"Danmark",
    "wof:name":"Missers Dukke- og Leget\u00f8jsmuseum",
    "wof:placetype":"venue"
},
  "geometry": {"coordinates":[10.6778745651,56.199798584],"type":"Point"}
}