{
  "type": "Feature",
  "properties": {
    "addr:full":"Fmd.: Bjarne Frederiksen, Aarestrupvej 51, Aarestrup Sk\u00f8rping Danmark 9520",
    "addr:housenumber":"51",
    "addr:postcode":"9520",
    "addr:street":"Bjarne Frederiksen Aarestrupvej",
    "iso:country":"DK",
    "sg:address":"Fmd.: Bjarne Frederiksen, Aarestrupvej 51, Aarestrup",
    "sg:city":"Sk\u00f8rping",
    "sg:orig_category":"Landboorganisationer",
    "sg:phone":"+45 98 37 87 01",
    "sg:postcode":"9520",
    "sg:province":"Danmark",
    "wof:name":"Midthimmerlands Familiebrug",
    "wof:placetype":"venue"
},
  "geometry": {"coordinates":[9.8477077484,56.8337860107],"type":"Point"}
}