{
  "type": "Feature",
  "properties": {
    "addr:full":"R\u00f8llikev\u00e6nget 11, Dyrup Odense SV Danmark 5250",
    "addr:housenumber":"11",
    "addr:postcode":"5250",
    "addr:street":"Rollikevaenget;Dyrup",
    "iso:country":"DK",
    "sg:address":"R\u00f8llikev\u00e6nget 11, Dyrup",
    "sg:city":"Odense SV",
    "sg:orig_category":"Hudpleje",
    "sg:phone":"+45 66 17 58 54",
    "sg:postcode":"5250",
    "sg:province":"Danmark",
    "wof:name":"Clinique Visage",
    "wof:placetype":"venue"
},
  "geometry": {"coordinates":[10.3153953552,55.3362998962],"type":"Point"}
}