{
  "type": "Feature",
  "properties": {
    "addr:full":"Baneg\u00e5rdsvej 30 Grindsted Danmark 7200",
    "addr:housenumber":"30",
    "addr:postcode":"7200",
    "addr:street":"Banegaardsvej",
    "iso:country":"DK",
    "sg:address":"Baneg\u00e5rdsvej 30",
    "sg:city":"Grindsted",
    "sg:orig_category":"EDB-reparation og -service",
    "sg:phone":"+45 75 32 38 52",
    "sg:postcode":"7200",
    "sg:province":"Danmark",
    "wof:name":"Dansk Kontorteknik",
    "wof:placetype":"venue"
},
  "geometry": {"coordinates":[8.9313459396,55.7575302124],"type":"Point"}
}