{
  "type": "Feature",
  "properties": {
    "addr:full":"Randersvej 90 Ry Danmark 8680",
    "addr:housenumber":"90",
    "addr:postcode":"8680",
    "addr:street":"Randersvej",
    "iso:country":"DK",
    "sg:address":"Randersvej 90",
    "sg:city":"Ry",
    "sg:orig_category":"Vandrerhjem",
    "sg:phone":"+45 86 89 14 07",
    "sg:postcode":"8680",
    "sg:province":"Danmark",
    "wof:name":"Ry Vandrerhjem Knudhule",
    "wof:placetype":"venue"
},
  "geometry": {"coordinates":[9.7848720551,56.1028213501],"type":"Point"}
}