{
  "type": "Feature",
  "properties": {
    "addr:full":"Jens Winthers Vej 29 Skagen Danmark 9990",
    "addr:housenumber":"29",
    "addr:postcode":"9990",
    "addr:street":"Jens Winthers Vej",
    "iso:country":"DK",
    "sg:address":"Jens Winthers Vej 29",
    "sg:city":"Skagen",
    "sg:orig_category":"Forsvaret",
    "sg:phone":"+45 98 44 21 00",
    "sg:postcode":"9990",
    "sg:province":"Danmark",
    "wof:name":"Flyvestation Skagen",
    "wof:placetype":"venue"
},
  "geometry": {"coordinates":[10.5976085663,57.7297935486],"type":"Point"}
}