{
  "type": "Feature",
  "properties": {
    "addr:full":"Tofteb\u00e6ksvej 30 Kongens Lyngby Danmark 2800",
    "addr:housenumber":"30",
    "addr:postcode":"2800",
    "addr:street":"Toftebaeksvej",
    "iso:country":"DK",
    "sg:address":"Tofteb\u00e6ksvej 30",
    "sg:city":"Kongens Lyngby",
    "sg:orig_category":"Private skoler",
    "sg:phone":"+45 45 87 62 40",
    "sg:postcode":"2800",
    "sg:province":"Danmark",
    "sg:website":"www.skt-knud-lavard.dk",
    "wof:name":"Skt. Knud Lavard Skole",
    "wof:placetype":"venue"
},
  "geometry": {"coordinates":[12.5070972443,55.775932312],"type":"Point"}
}