{
  "type": "Feature",
  "properties": {
    "addr:full":"N\u00f8rregade 49 Horsens Danmark 8700",
    "addr:housenumber":"49",
    "addr:postcode":"8700",
    "addr:street":"Norregade",
    "iso:country":"DK",
    "sg:address":"N\u00f8rregade 49",
    "sg:city":"Horsens",
    "sg:orig_category":"Dyrehandlere",
    "sg:phone":"+45 75 60 23 00",
    "sg:postcode":"8700",
    "sg:province":"Danmark",
    "wof:name":"Horsens Dyrecenter",
    "wof:placetype":"venue"
},
  "geometry": {"coordinates":[9.8518362045,55.8626747131],"type":"Point"}
}