{
  "type": "Feature",
  "properties": {
    "addr:full":"Birkedommervej 35 K\u00f8benhavn NV Danmark 2400",
    "addr:housenumber":"35",
    "addr:postcode":"2400",
    "addr:street":"Birkedommervej",
    "iso:country":"DK",
    "sg:address":"Birkedommervej 35",
    "sg:city":"K\u00f8benhavn NV",
    "sg:orig_category":"Industrilakering",
    "sg:phone":"+45 38 87 00 32",
    "sg:postcode":"2400",
    "sg:province":"Danmark",
    "sg:website":"www.elvin-karlsson.dk",
    "wof:name":"Karlsson, Elvin",
    "wof:placetype":"venue"
},
  "geometry": {"coordinates":[-117.02272033689999,38.5024604797],"type":"Point"}
}