{
  "type": "Feature",
  "properties": {
    "iso:country":"DK",
    "sg:address":"Hj\u00f8rringgade 5",
    "sg:city":"Hirtshals",
    "sg:orig_category":"Slagter og viktualie",
    "sg:phone":"+45 98 94 16 11",
    "sg:postcode":"9850",
    "sg:province":"Danmark",
    "sg:website":"www.slagterwinther.dk",
    "wof:name":"Winther A/S, Slagter",
    "wof:placetype":"venue"
},
  "geometry": {"coordinates":[9.9556436539,57.5906181335],"type":"Point"}
}