{
  "type": "Feature",
  "properties": {
    "addr:full":"Smedeland 8 Glostrup Danmark 2600",
    "addr:housenumber":"8",
    "addr:postcode":"2600",
    "addr:street":"Smedeland",
    "iso:country":"DK",
    "sg:address":"Smedeland 8",
    "sg:city":"Glostrup",
    "sg:orig_category":"Skovbrugsudstyr",
    "sg:phone":"+45 43 42 00 30",
    "sg:postcode":"2600",
    "sg:province":"Danmark",
    "wof:name":"STIHL",
    "wof:placetype":"venue"
},
  "geometry": {"coordinates":[12.3929672241,55.677406311],"type":"Point"}
}