{
  "type": "Feature",
  "properties": {
    "iso:country":"DK",
    "sg:address":"Sall\u00f8vvej 3",
    "sg:city":"Gadstrup",
    "sg:orig_category":"Bogtrykkerier",
    "sg:phone":"+45 46 19 02 46",
    "sg:postcode":"4621",
    "sg:province":"Danmark",
    "wof:name":"OBS Tryk ApS",
    "wof:placetype":"venue"
},
  "geometry": {"coordinates":[12.0978450775,55.5737800598],"type":"Point"}
}