{
  "type": "Feature",
  "properties": {
    "addr:full":"Lykkeg\u00e5rdsvej 75 Kolding Danmark 6000",
    "addr:housenumber":"75",
    "addr:postcode":"6000",
    "addr:street":"Lykkegaardsvej",
    "iso:country":"DK",
    "sg:address":"Lykkeg\u00e5rdsvej 75",
    "sg:city":"Kolding",
    "sg:orig_category":"Private skoler",
    "sg:phone":"+45 75 53 22 66",
    "sg:postcode":"6000",
    "sg:province":"Danmark",
    "wof:name":"Lykkeg\u00e5rdskolen",
    "wof:placetype":"venue"
},
  "geometry": {"coordinates":[9.4502019882,55.4808540344],"type":"Point"}
}