{
  "type": "Feature",
  "properties": {
    "addr:full":"S\u00f8ndergade 37 Ejstrupholm Danmark 7361",
    "addr:housenumber":"37",
    "addr:postcode":"7361",
    "addr:street":"Sondergade",
    "iso:country":"DK",
    "sg:address":"S\u00f8ndergade 37",
    "sg:city":"Ejstrupholm",
    "sg:orig_category":"Autoforhandlere",
    "sg:phone":"+45 75 77 21 53",
    "sg:postcode":"7361",
    "sg:province":"Danmark",
    "wof:name":"D. S. Biler",
    "wof:placetype":"venue"
},
  "geometry": {"coordinates":[9.2845506668,55.9829673767],"type":"Point"}
}