{
  "type": "Feature",
  "properties": {
    "iso:country":"DK",
    "sg:address":"Jens Baggesens Vej 53",
    "sg:city":"\u00c5rhus N",
    "sg:orig_category":"Vagtbureauer",
    "sg:phone":"+45 87 39 58 00",
    "sg:postcode":"8200",
    "sg:province":"Danmark",
    "wof:name":"Falck Securitas A/S",
    "wof:placetype":"venue"
},
  "geometry": {"coordinates":[-76.4168395996,37.452419281],"type":"Point"}
}