{
  "type": "Feature",
  "properties": {
    "addr:full":"Adelgade 3 Randers Danmark 8900",
    "addr:housenumber":"3",
    "addr:postcode":"8900",
    "addr:street":"Adelgade",
    "iso:country":"DK",
    "sg:address":"Adelgade 3",
    "sg:city":"Randers",
    "sg:orig_category":"Fotografer",
    "sg:phone":"+45 86 42 34 98",
    "sg:postcode":"8900",
    "sg:province":"Danmark",
    "wof:name":"Multifoto",
    "wof:placetype":"venue"
},
  "geometry": {"coordinates":[10.0347833633,56.4620933533],"type":"Point"}
}