{
  "type": "Feature",
  "properties": {
    "addr:full":"Tofteledet 3 Beder Danmark 8330",
    "addr:housenumber":"3",
    "addr:postcode":"8330",
    "addr:street":"Tofteledet",
    "iso:country":"DK",
    "sg:address":"Tofteledet 3",
    "sg:city":"Beder",
    "sg:orig_category":"Stilladser",
    "sg:phone":"+45 86 93 86 66",
    "sg:postcode":"8330",
    "sg:province":"Danmark",
    "wof:name":"Witca SGB Stillads A/S",
    "wof:placetype":"venue"
},
  "geometry": {"coordinates":[10.1984834671,56.055847168],"type":"Point"}
}