{
  "type": "Feature",
  "properties": {
    "iso:country":"DK",
    "sg:address":"Husmandsvej 13",
    "sg:city":"Taastrup",
    "sg:orig_category":"Bogbinderier",
    "sg:phone":"+45 43 71 43 92",
    "sg:postcode":"2630",
    "sg:province":"Danmark",
    "wof:name":"Cova Aps, Bogbinderiet",
    "wof:placetype":"venue"
},
  "geometry": {"coordinates":[12.2873067856,55.6392173767],"type":"Point"}
}