{
  "type": "Feature",
  "properties": {
    "iso:country":"DK",
    "sg:address":"Gyvelvej 5",
    "sg:city":"Aulum",
    "sg:orig_category":"Revisorer",
    "sg:phone":"+45 97 47 22 22",
    "sg:postcode":"7490",
    "sg:province":"Danmark",
    "wof:name":"Blach, Revisionsfirmaet J\u00f8rgen",
    "wof:placetype":"venue"
},
  "geometry": {"coordinates":[8.7940149307,56.2622413635],"type":"Point"}
}