{
  "type": "Feature",
  "properties": {
    "addr:full":"Fmd.: C. O. Rachlitz, Bavne\u00e5sen 56, Fl\u00f8ng Hedehusene Danmark 2640",
    "addr:housenumber":"56",
    "addr:postcode":"2640",
    "addr:street":"Bavneaasen;Flong",
    "iso:country":"DK",
    "sg:address":"Fmd.: C. O. Rachlitz, Bavne\u00e5sen 56, Fl\u00f8ng",
    "sg:city":"Hedehusene",
    "sg:orig_category":"Grundejerforeninger",
    "sg:phone":"+45 46 56 41 54",
    "sg:postcode":"2640",
    "sg:province":"Danmark",
    "wof:name":"Baune\u00e5sen/Hovmarken Grundejerforening",
    "wof:placetype":"venue"
},
  "geometry": {"coordinates":[12.1993551254,55.6496009827],"type":"Point"}
}