{
  "type": "Feature",
  "properties": {
    "iso:country":"DK",
    "sg:address":"H\u00f8jsvej 1, Ullerup",
    "sg:city":"S\u00f8nderborg",
    "sg:orig_category":"Korn og foderstoffer",
    "sg:phone":"+45 74 46 13 42",
    "sg:postcode":"6400",
    "sg:province":"Danmark",
    "wof:name":"SAF",
    "wof:placetype":"venue"
},
  "geometry": {"coordinates":[9.7899465561,54.9100151062],"type":"Point"}
}