{
  "type": "Feature",
  "properties": {
    "addr:full":"N\u00f8rregade 2 Hirtshals Danmark 9850",
    "addr:housenumber":"2",
    "addr:postcode":"9850",
    "addr:street":"Norregade",
    "iso:country":"DK",
    "sg:address":"N\u00f8rregade 2",
    "sg:city":"Hirtshals",
    "sg:orig_category":"Materialister",
    "sg:phone":"+45 98 94 12 66",
    "sg:postcode":"9850",
    "sg:province":"Danmark",
    "wof:name":"Matas",
    "wof:placetype":"venue"
},
  "geometry": {"coordinates":[9.9563827515,57.590713501],"type":"Point"}
}