{
  "type": "Feature",
  "properties": {
    "addr:full":"Starup Kirkevej 30 Haderslev Danmark 6100",
    "addr:housenumber":"30",
    "addr:postcode":"6100",
    "addr:street":"Starup Kirkevej",
    "iso:country":"DK",
    "sg:address":"Starup Kirkevej 30",
    "sg:city":"Haderslev",
    "sg:orig_category":"Kirker",
    "sg:postcode":"6100",
    "sg:province":"Danmark",
    "wof:name":"S\u00f8nder Starup Kirke",
    "wof:placetype":"venue"
},
  "geometry": {"coordinates":[9.5321502686,55.2481384277],"type":"Point"}
}