{
  "type": "Feature",
  "properties": {
    "iso:country":"DK",
    "sg:address":"Skovvej 77 A",
    "sg:city":"Charlottenlund",
    "sg:orig_category":"Kinesiologi",
    "sg:phone":"+45 39 63 64 70",
    "sg:postcode":"2920",
    "sg:province":"Danmark",
    "wof:name":"Kbh's Psykokinesiologi",
    "wof:placetype":"venue"
},
  "geometry": {"coordinates":[12.5486869812,55.768371582],"type":"Point"}
}