{
  "type": "Feature",
  "properties": {
    "addr:full":"Filosofgangen 16 Odense C Danmark 5000",
    "addr:housenumber":"16",
    "addr:postcode":"5000",
    "addr:street":"Filosofgangen",
    "iso:country":"DK",
    "sg:address":"Filosofgangen 16",
    "sg:city":"Odense C",
    "sg:orig_category":"Forsikringer",
    "sg:phone":"+45 70 10 04 12",
    "sg:postcode":"5000",
    "sg:province":"Danmark",
    "wof:name":"Trekroner Forsikring, Center Odense",
    "wof:placetype":"venue"
},
  "geometry": {"coordinates":[10.3844118118,55.3930130005],"type":"Point"}
}