{
  "type": "Feature",
  "properties": {
    "addr:full":"Danmarksgade 65M Odense C Danmark 5000",
    "addr:housenumber":"65m",
    "addr:postcode":"5000",
    "addr:street":"Danmarksgade",
    "iso:country":"DK",
    "sg:address":"Danmarksgade 65M",
    "sg:city":"Odense C",
    "sg:orig_category":"Boligudlejning",
    "sg:phone":"+45 66 11 45 69",
    "sg:postcode":"5000",
    "sg:province":"Danmark",
    "wof:name":"Andelsboligforeningen H\u00f8jstrup",
    "wof:placetype":"venue"
},
  "geometry": {"coordinates":[10.4011993408,55.4004325867],"type":"Point"}
}