{
  "type": "Feature",
  "properties": {
    "iso:country":"DK",
    "sg:address":"Hovedgaden 15, st.",
    "sg:city":"Alling\u00e5bro",
    "sg:orig_category":"Genbrugsbutikker",
    "sg:phone":"+45 86 48 17 56",
    "sg:postcode":"8961",
    "sg:province":"Danmark",
    "wof:name":"Dansk R\u00f8de Kors Genbrugsbutik",
    "wof:placetype":"venue"
},
  "geometry": {"coordinates":[-95.96017456049999,40.4734992981],"type":"Point"}
}