{
  "type": "Feature",
  "properties": {
    "addr:full":"Lindenborgvej 10 Aalborg SV Danmark 9200",
    "addr:housenumber":"10",
    "addr:postcode":"9200",
    "addr:street":"Lindenborgvej",
    "iso:country":"DK",
    "sg:address":"Lindenborgvej 10",
    "sg:city":"Aalborg SV",
    "sg:orig_category":"Psykologer, praktiserende",
    "sg:phone":"+45 98 18 96 78",
    "sg:postcode":"9200",
    "sg:province":"Danmark",
    "wof:name":"Thomsen, Sven",
    "wof:placetype":"venue"
},
  "geometry": {"coordinates":[9.8782272339,57.0167808533],"type":"Point"}
}