{
  "type": "Feature",
  "properties": {
    "addr:full":"Dahl\u00e9nsstr\u00e6de 6 A - D Gentofte Danmark 2820",
    "addr:housenumber":"6 a d",
    "addr:postcode":"2820",
    "addr:street":"Dahle\u0301Nsstraede",
    "iso:country":"DK",
    "sg:address":"Dahl\u00e9nsstr\u00e6de 6 A - D",
    "sg:city":"Gentofte",
    "sg:orig_category":"Dagcentre",
    "sg:phone":"+45 39 75 01 61",
    "sg:postcode":"2820",
    "sg:province":"Danmark",
    "wof:name":"Kl\u00f8ckershave",
    "wof:placetype":"venue"
},
  "geometry": {"coordinates":[12.5409173965,55.7482719421],"type":"Point"}
}