{
  "type": "Feature",
  "properties": {
    "addr:full":"Kirketerpvej 60, Kirketerp Suldrup Danmark 9541",
    "addr:housenumber":"60",
    "addr:postcode":"9541",
    "addr:street":"Kirketerpvej",
    "iso:country":"DK",
    "sg:address":"Kirketerpvej 60, Kirketerp",
    "sg:city":"Suldrup",
    "sg:orig_category":"Forsamlingshuse",
    "sg:phone":"+45 98 38 72 07",
    "sg:postcode":"9541",
    "sg:province":"Danmark",
    "sg:website":"www.veggerbysogn.dk",
    "wof:name":"Hjeds Forsamlingshus",
    "wof:placetype":"venue"
},
  "geometry": {"coordinates":[9.701379776,56.8489303589],"type":"Point"}
}