{
  "type": "Feature",
  "properties": {
    "iso:country":"DK",
    "sg:address":"Center Boulevard 5",
    "sg:city":"K\u00f8benhavn S",
    "sg:orig_category":"Kursusudbydere",
    "sg:phone":"+45 70 25 80 90",
    "sg:postcode":"2300",
    "sg:province":"Danmark",
    "sg:website":"www.human-development.com",
    "wof:name":"Human Development",
    "wof:placetype":"venue"
},
  "geometry": {"coordinates":[12.5774450302,55.6380653381],"type":"Point"}
}