{
  "type": "Feature",
  "properties": {
    "addr:full":"\u00d8stre Alle 16 Hadsund Danmark 9560",
    "addr:housenumber":"16",
    "addr:postcode":"9560",
    "addr:street":"Ostre Alle",
    "iso:country":"DK",
    "sg:address":"\u00d8stre Alle 16",
    "sg:city":"Hadsund",
    "sg:orig_category":"Industridesign",
    "sg:phone":"+45 98 57 52 00",
    "sg:postcode":"9560",
    "sg:province":"Danmark",
    "wof:name":"Kj\u00e6rulff Design, Lars",
    "wof:placetype":"venue"
},
  "geometry": {"coordinates":[10.1175336838,56.7163124084],"type":"Point"}
}