{
  "type": "Feature",
  "properties": {
    "addr:full":"Ejstrupvej 14 Skals Danmark 8832",
    "addr:housenumber":"14",
    "addr:postcode":"8832",
    "addr:street":"Ejstrupvej",
    "iso:country":"DK",
    "sg:address":"Ejstrupvej 14",
    "sg:city":"Skals",
    "sg:orig_category":"Menighedshuse",
    "sg:postcode":"8832",
    "sg:province":"Danmark",
    "wof:name":"Skals Menighedshus",
    "wof:placetype":"venue"
},
  "geometry": {"coordinates":[9.4055595398,56.5580863953],"type":"Point"}
}