{
  "type": "Feature",
  "properties": {
    "addr:full":"Storeg\u00e5rdsvej 102 Vejle Danmark 7100",
    "addr:housenumber":"102",
    "addr:postcode":"7100",
    "addr:street":"Storegaardsvej",
    "iso:country":"DK",
    "sg:address":"Storeg\u00e5rdsvej 102",
    "sg:city":"Vejle",
    "sg:orig_category":"Plejehjem",
    "sg:phone":"+45 76 44 54 00",
    "sg:postcode":"7100",
    "sg:province":"Danmark",
    "wof:name":"Omr\u00e5de 2, Hover Urh\u00f8j, Grejsdalen",
    "wof:placetype":"venue"
},
  "geometry": {"coordinates":[9.5171527863,55.7280426025],"type":"Point"}
}