{
  "type": "Feature",
  "properties": {
    "iso:country":"DK",
    "sg:address":"Lyngby STORcenter 29",
    "sg:city":"Kongens Lyngby",
    "sg:orig_category":"Slagter og viktualie",
    "sg:phone":"+45 45 88 78 98",
    "sg:postcode":"2800",
    "sg:province":"Danmark",
    "wof:name":"Melhede, Slagter",
    "wof:placetype":"venue"
},
  "geometry": {"coordinates":[12.503950119,55.7720336914],"type":"Point"}
}