{
  "type": "Feature",
  "properties": {
    "iso:country":"DK",
    "sg:address":"Fmd.: Bent Andersen, Egely Alle 6, Slagslunde",
    "sg:city":"Stenl\u00f8se",
    "sg:orig_category":"Grundejerforeninger",
    "sg:phone":"+45 48 18 37 30",
    "sg:postcode":"3660",
    "sg:province":"Danmark",
    "wof:name":"Egely Alle Vejlaug",
    "wof:placetype":"venue"
},
  "geometry": {"coordinates":[12.2635259628,55.7919006348],"type":"Point"}
}