{
  "type": "Feature",
  "properties": {
    "addr:full":"Hvidevej 29, Vedhoved Karup Danmark 7470",
    "addr:housenumber":"29",
    "addr:postcode":"7470",
    "addr:street":"Hvidevej;Vedhoved Karup Danmark",
    "iso:country":"DK",
    "sg:address":"Hvidevej 29, Vedhoved",
    "sg:city":"Karup",
    "sg:orig_category":"Landbrugsmaskiner",
    "sg:phone":"+45 86 66 10 57",
    "sg:postcode":"7470",
    "sg:province":"Danmark",
    "sg:website":"www.hvidevejs-traktor.dk",
    "wof:name":"Hvidevejs Traktor- & Maskinv\u00e6rksted",
    "wof:placetype":"venue"
},
  "geometry": {"coordinates":[9.2525548935,56.3398017883],"type":"Point"}
}