{
  "type": "Feature",
  "properties": {
    "iso:country":"DK",
    "sg:address":"Parallelvej 38",
    "sg:city":"Hvide Sande",
    "sg:orig_category":"Snedkermestre",
    "sg:phone":"+45 97 31 10 63",
    "sg:postcode":"6960",
    "sg:province":"Danmark",
    "wof:name":"Frich I/S, R\u00f8ikj\u00e6r",
    "wof:placetype":"venue"
},
  "geometry": {"coordinates":[8.1273374557,56.0128936768],"type":"Point"}
}