{
  "type": "Feature",
  "properties": {
    "addr:full":"Fan\u00f8gade 36 Jerslev Danmark 9740",
    "addr:housenumber":"36",
    "addr:postcode":"9740",
    "addr:street":"Fanogade",
    "iso:country":"DK",
    "sg:address":"Fan\u00f8gade 36",
    "sg:city":"Jerslev",
    "sg:orig_category":"Blikkenslagere",
    "sg:phone":"+45 98 83 14 86",
    "sg:postcode":"9740",
    "sg:province":"Danmark",
    "wof:name":"Jerslev Smedie & VVS Center",
    "wof:placetype":"venue"
},
  "geometry": {"coordinates":[10.099195,57.287125],"type":"Point"}
}