{
  "type": "Feature",
  "properties": {
    "addr:full":"Damager 1 Randers Danmark 8900",
    "addr:housenumber":"1",
    "addr:postcode":"8900",
    "addr:street":"Damager",
    "iso:country":"DK",
    "sg:address":"Damager 1",
    "sg:city":"Randers",
    "sg:orig_category":"Dyrepensioner",
    "sg:phone":"+45 86 44 39 09",
    "sg:postcode":"8900",
    "sg:province":"Danmark",
    "wof:name":"Svejstrup Vestergaard Dyrepension",
    "wof:placetype":"venue"
},
  "geometry": {"coordinates":[9.9478940964,56.4876174927],"type":"Point"}
}