{
  "type": "Feature",
  "properties": {
    "iso:country":"DK",
    "sg:address":"Gr\u00f8nlandsvej 22 C",
    "sg:city":"Frederikshavn",
    "sg:orig_category":"Telebutikker",
    "sg:phone":"+45 96 20 05 44",
    "sg:postcode":"9900",
    "sg:province":"Danmark",
    "wof:name":"Tele K\u00e6den",
    "wof:placetype":"venue"
},
  "geometry": {"coordinates":[10.5162878036,57.4234313965],"type":"Point"}
}