{
  "type": "Feature",
  "properties": {
    "iso:country":"DK",
    "sg:address":"Fmd.: Johannes Poulsen, Bakken 11, Ulbjerg",
    "sg:city":"Skals",
    "sg:orig_category":"Kulturelle foreninger",
    "sg:phone":"+45 86 69 70 22",
    "sg:postcode":"8832",
    "sg:province":"Danmark",
    "wof:name":"Ulbjerg Kristelige Lytterforening",
    "wof:placetype":"venue"
},
  "geometry": {"coordinates":[9.4030599594,56.5558166504],"type":"Point"}
}