{
  "type": "Feature",
  "properties": {
    "addr:full":"Slotsgade 19 Vordingborg Danmark 4760",
    "addr:housenumber":"19",
    "addr:postcode":"4760",
    "addr:street":"Slotsgade",
    "iso:country":"DK",
    "sg:address":"Slotsgade 19",
    "sg:city":"Vordingborg",
    "sg:orig_category":"Arkitekter",
    "sg:phone":"+45 55 34 17 40",
    "sg:postcode":"4760",
    "sg:province":"Danmark",
    "sg:website":"www.vesterlund-vibede.dk",
    "wof:name":"Vesterlund & Vibede, Arkitektfirma M.A.A.",
    "wof:placetype":"venue"
},
  "geometry": {"coordinates":[11.9141569138,55.0082740784],"type":"Point"}
}