{
  "type": "Feature",
  "properties": {
    "addr:full":"Bredgade 67 T\u00f8rring Danmark 7160",
    "addr:housenumber":"67",
    "addr:postcode":"7160",
    "addr:street":"Bredgade",
    "iso:country":"DK",
    "sg:address":"Bredgade 67",
    "sg:city":"T\u00f8rring",
    "sg:orig_category":"Campingpladser",
    "sg:phone":"+45 75 80 20 85",
    "sg:postcode":"7160",
    "sg:province":"Danmark",
    "sg:website":"www.toerring-camping.dk",
    "wof:name":"T\u00f8rring Camping- og Kanoplads",
    "wof:placetype":"venue"
},
  "geometry": {"coordinates":[9.4845476151,55.853061676],"type":"Point"}
}