{
  "type": "Feature",
  "properties": {
    "addr:full":"Blommegrenen 17 Ejby Danmark 5592",
    "addr:housenumber":"17",
    "addr:postcode":"5592",
    "addr:street":"Blommegrenen",
    "iso:country":"DK",
    "sg:address":"Blommegrenen 17",
    "sg:city":"Ejby",
    "sg:orig_category":"Vinduespolering",
    "sg:phone":"+45 64 46 18 80",
    "sg:postcode":"5592",
    "sg:province":"Danmark",
    "wof:name":"Blommegrenens Vinduespolering",
    "wof:placetype":"venue"
},
  "geometry": {"coordinates":[9.9366397858,55.4272422791],"type":"Point"}
}