{
  "type": "Feature",
  "properties": {
    "addr:full":"Christiansfeldvej 2 Haderslev Danmark 6100",
    "addr:housenumber":"2",
    "addr:postcode":"6100",
    "addr:street":"Christiansfeldvej",
    "iso:country":"DK",
    "sg:address":"Christiansfeldvej 2",
    "sg:city":"Haderslev",
    "sg:orig_category":"Servicestationer",
    "sg:phone":"+45 74 52 28 12",
    "sg:postcode":"6100",
    "sg:province":"Danmark",
    "wof:name":"Shell Service",
    "wof:placetype":"venue"
},
  "geometry": {"coordinates":[9.4909076691,55.2553596497],"type":"Point"}
}