{
  "type": "Feature",
  "properties": {
    "addr:full":"Knuthenborgvej 3 Valby Danmark 2500",
    "addr:housenumber":"3",
    "addr:postcode":"2500",
    "addr:street":"Knuthenborgvej",
    "iso:country":"DK",
    "sg:address":"Knuthenborgvej 3",
    "sg:city":"Valby",
    "sg:orig_category":"Psykologer, praktiserende",
    "sg:phone":"+45 36 30 10 93",
    "sg:postcode":"2500",
    "sg:province":"Danmark",
    "wof:name":"Leunbach, Sonja",
    "wof:placetype":"venue"
},
  "geometry": {"coordinates":[12.4911909103,55.6690826416],"type":"Point"}
}