{
  "type": "Feature",
  "properties": {
    "addr:full":"M\u00f8llergade 92 Svendborg Danmark 5700",
    "addr:housenumber":"92",
    "addr:postcode":"5700",
    "addr:street":"Mollergade",
    "iso:country":"DK",
    "sg:address":"M\u00f8llergade 92",
    "sg:city":"Svendborg",
    "sg:orig_category":"Forsikringer",
    "sg:phone":"+45 70 13 79 13",
    "sg:postcode":"5700",
    "sg:province":"Danmark",
    "sg:website":"www.topdanmark.dk",
    "wof:name":"Topdanmark",
    "wof:placetype":"venue"
},
  "geometry": {"coordinates":[10.6134147644,55.0637321472],"type":"Point"}
}