{
  "type": "Feature",
  "properties": {
    "addr:full":"Sandholtvej 36, Sh Lyndelse Broby Danmark 5672",
    "addr:housenumber":"36",
    "addr:postcode":"sh;5672",
    "addr:street":"Sandholtvej;Lyndelse",
    "iso:country":"DK",
    "sg:address":"Sandholtvej 36, Sh Lyndelse",
    "sg:city":"Broby",
    "sg:orig_category":"Landbrugsmaskiner",
    "sg:phone":"+45 62 64 12 14",
    "sg:postcode":"5672",
    "sg:province":"Danmark",
    "wof:name":"Sandholt Lyndelse Smede",
    "wof:placetype":"venue"
},
  "geometry": {"coordinates":[10.3131303787,55.2695846558],"type":"Point"}
}