{
  "type": "Feature",
  "properties": {
    "addr:full":"Torvet 6, 1. Frederikssund Danmark 3600",
    "addr:housenumber":"6 1",
    "addr:postcode":"3600",
    "addr:street":"Torvet",
    "iso:country":"DK",
    "sg:address":"Torvet 6, 1.",
    "sg:city":"Frederikssund",
    "sg:orig_category":"Forsikringer",
    "sg:phone":"+45 47 36 03 00",
    "sg:postcode":"3600",
    "sg:province":"Danmark",
    "wof:name":"Tryg-Baltica",
    "wof:placetype":"venue"
},
  "geometry": {"coordinates":[12.0604934692,55.8395996094],"type":"Point"}
}