{
  "type": "Feature",
  "properties": {
    "addr:full":"Suhrs Gade 11 A Maribo Danmark 4930",
    "addr:housenumber":"11 a",
    "addr:postcode":"4930",
    "addr:street":"Suhrs Gade",
    "iso:country":"DK",
    "sg:address":"Suhrs Gade 11 A",
    "sg:city":"Maribo",
    "sg:orig_category":"Psykologer, praktiserende",
    "sg:phone":"+45 54 78 00 59",
    "sg:postcode":"4930",
    "sg:province":"Danmark",
    "wof:name":"Mc. Laughlin, John",
    "wof:placetype":"venue"
},
  "geometry": {"coordinates":[11.4987726212,54.7756690979],"type":"Point"}
}