{
  "type": "Feature",
  "properties": {
    "addr:full":"Vigerslev Alle 42 Valby Danmark 2500",
    "addr:housenumber":"42",
    "addr:postcode":"2500",
    "addr:street":"Vigerslev Alle",
    "iso:country":"DK",
    "sg:address":"Vigerslev Alle 42",
    "sg:city":"Valby",
    "sg:orig_category":"Blomsterhandlere",
    "sg:phone":"+45 36 17 14 92",
    "sg:postcode":"2500",
    "sg:province":"Danmark",
    "wof:name":"Blomsterforretningen",
    "wof:placetype":"venue"
},
  "geometry": {"coordinates":[12.5178804398,55.6618652344],"type":"Point"}
}