{
  "type": "Feature",
  "properties": {
    "addr:full":"Fmd.: Erich Lorenzen, Garverland 8 Bylderup-Bov Danmark 6372",
    "addr:housenumber":"8",
    "addr:postcode":"6372",
    "addr:street":"Garverland",
    "iso:country":"DK",
    "sg:address":"Fmd.: Erich Lorenzen, Garverland 8",
    "sg:city":"Bylderup-Bov",
    "sg:orig_category":"Hobbybetonede foreninger",
    "sg:phone":"+45 74 76 21 35",
    "sg:postcode":"6372",
    "sg:province":"Danmark",
    "wof:name":"Ringriderforeningen for Bylderup-Bov og Omegn",
    "wof:placetype":"venue"
},
  "geometry": {"coordinates":[9.0861902237,54.941783905],"type":"Point"}
}