{
  "type": "Feature",
  "properties": {
    "iso:country":"DK",
    "sg:address":"Vejleg\u00e5rdsvej 6, Vejle",
    "sg:city":"Broby",
    "sg:orig_category":"Benzinstationer",
    "sg:postcode":"5672",
    "sg:province":"Danmark",
    "wof:name":"OK D\u00f8gntank",
    "wof:placetype":"venue"
},
  "geometry": {"coordinates":[10.31313,55.269585],"type":"Point"}
}