{
  "type": "Feature",
  "properties": {
    "addr:full":"Borgergade 21 A Silkeborg Danmark 8600",
    "addr:housenumber":"21 a",
    "addr:postcode":"8600",
    "addr:street":"Borgergade",
    "iso:country":"DK",
    "sg:address":"Borgergade 21 A",
    "sg:city":"Silkeborg",
    "sg:orig_category":"Ejendomshandel",
    "sg:phone":"+45 86 82 94 11",
    "sg:postcode":"8600",
    "sg:province":"Danmark",
    "sg:website":"www.realmaeglerne.dk",
    "wof:name":"RealM\u00e6glerne",
    "wof:placetype":"venue"
},
  "geometry": {"coordinates":[9.5539216995,56.1773223877],"type":"Point"}
}