{
  "type": "Feature",
  "properties": {
    "addr:full":"Viborgvej 169, Hasle \u00c5rhus V Danmark 8210",
    "addr:housenumber":"169",
    "addr:postcode":"8210",
    "addr:street":"Viborgvej",
    "iso:country":"DK",
    "sg:address":"Viborgvej 169, Hasle",
    "sg:city":"\u00c5rhus V",
    "sg:orig_category":"Politi",
    "sg:phone":"+45 86 15 14 48",
    "sg:postcode":"8210",
    "sg:province":"Danmark",
    "wof:name":"N\u00e6rpolitiet Hasle",
    "wof:placetype":"venue"
},
  "geometry": {"coordinates":[14.7065896988,55.1830787659],"type":"Point"}
}