{
  "type": "Feature",
  "properties": {
    "addr:full":"Roskildevej 328 Taastrup Danmark 2630",
    "addr:housenumber":"328",
    "addr:postcode":"2630",
    "addr:street":"Roskildevej",
    "iso:country":"DK",
    "sg:address":"Roskildevej 328",
    "sg:city":"Taastrup",
    "sg:orig_category":"Autoreparation og -service",
    "sg:phone":"+45 43 99 20 99",
    "sg:postcode":"2630",
    "sg:province":"Danmark",
    "wof:name":"Brink Autov\u00e6rksted, Hans",
    "wof:placetype":"venue"
},
  "geometry": {"coordinates":[12.3039503098,55.6582984924],"type":"Point"}
}