{
  "type": "Feature",
  "properties": {
    "addr:full":"Fmd.: Erling Jensen, \u00c6girsvej 39 Holb\u00e6k Danmark 4300",
    "addr:housenumber":"39",
    "addr:postcode":"4300",
    "addr:street":"Erling;Aegirsvej",
    "iso:country":"DK",
    "sg:address":"Fmd.: Erling Jensen, \u00c6girsvej 39",
    "sg:city":"Holb\u00e6k",
    "sg:orig_category":"\u00c3\u2020ldreorganisationer og klubber",
    "sg:phone":"+45 59 43 58 46",
    "sg:postcode":"4300",
    "sg:province":"Danmark",
    "wof:name":"Butterup-Tuse og Hagested Pensionistforening",
    "wof:placetype":"venue"
},
  "geometry": {"coordinates":[-109.33489990229999,40.3696899414],"type":"Point"}
}