{
  "type": "Feature",
  "properties": {
    "iso:country":"DK",
    "sg:address":"\u00d8stergade 29 - 31",
    "sg:city":"Aabybro",
    "sg:orig_category":"Supermarkeder",
    "sg:phone":"+45 43 56 88 11",
    "sg:postcode":"9440",
    "sg:province":"Danmark",
    "wof:name":"Netto",
    "wof:placetype":"venue"
},
  "geometry": {"coordinates":[9.7324066162,57.1600532532],"type":"Point"}
}