{
  "type": "Feature",
  "properties": {
    "addr:full":"Peder Skrams Vej 29 Odense S\u00d8 Danmark 5220",
    "addr:housenumber":"29",
    "addr:postcode":"5220",
    "addr:street":"Peder Skrams Vej",
    "iso:country":"DK",
    "sg:address":"Peder Skrams Vej 29",
    "sg:city":"Odense S\u00d8",
    "sg:orig_category":"Konservatorer",
    "sg:phone":"+45 66 15 90 57",
    "sg:postcode":"5220",
    "sg:province":"Danmark",
    "wof:name":"Johansen Aps, Jens",
    "wof:placetype":"venue"
},
  "geometry": {"coordinates":[10.4365282059,55.3841056824],"type":"Point"}
}