{
  "type": "Feature",
  "properties": {
    "addr:full":"Tingg\u00e5rdsparken 15, Tune Roskilde Danmark 4000",
    "addr:housenumber":"15",
    "addr:postcode":"4000",
    "addr:street":"Tinggaardsparken",
    "iso:country":"DK",
    "sg:address":"Tingg\u00e5rdsparken 15, Tune",
    "sg:city":"Roskilde",
    "sg:orig_category":"Ergonomi",
    "sg:phone":"+45 46 13 75 50",
    "sg:postcode":"4000",
    "sg:province":"Danmark",
    "sg:website":"www.hoegsbo.dk",
    "wof:name":"H\u00f8gsbo Kontor og Arbejdsmilj\u00f8",
    "wof:placetype":"venue"
},
  "geometry": {"coordinates":[12.0909376144,55.6404838562],"type":"Point"}
}