{
  "type": "Feature",
  "properties": {
    "addr:full":"Kongevejs-Centret 8 H\u00f8rsholm Danmark 2970",
    "addr:housenumber":"8",
    "addr:postcode":"2970",
    "addr:street":"Kongevejs-Centret",
    "iso:country":"DK",
    "sg:address":"Kongevejs-Centret 8",
    "sg:city":"H\u00f8rsholm",
    "sg:orig_category":"Materialister",
    "sg:phone":"+45 45 76 39 10",
    "sg:postcode":"2970",
    "sg:province":"Danmark",
    "wof:name":"Matas",
    "wof:placetype":"venue"
},
  "geometry": {"coordinates":[12.4976701736,55.8879013062],"type":"Point"}
}