{
  "type": "Feature",
  "properties": {
    "addr:full":"H\u00f8je Gladsaxe 30 S\u00f8borg Danmark 2860",
    "addr:housenumber":"30",
    "addr:postcode":"2860",
    "addr:street":"Gladsaxe",
    "iso:country":"DK",
    "sg:address":"H\u00f8je Gladsaxe 30",
    "sg:city":"S\u00f8borg",
    "sg:orig_category":"Kosmetik",
    "sg:phone":"+45 39 67 00 80",
    "sg:postcode":"2860",
    "sg:province":"Danmark",
    "wof:name":"Thorfelt-Consult Cosmetics",
    "wof:placetype":"venue"
},
  "geometry": {"coordinates":[12.4881801605,55.7302436829],"type":"Point"}
}