{
  "type": "Feature",
  "properties": {
    "iso:country":"DK",
    "sg:address":"PO Box 11, R\u00f8sn\u00e6svej 349",
    "sg:city":"Kalundborg",
    "sg:classifiers":[
        {
            "category":"Banks & Credit Unions",
            "subcategory":"Bank",
            "type":"Services"
        }
    ],
    "sg:phone":"+45 53 50 92 56",
    "sg:postcode":"4400",
    "sg:province":"Danmark",
    "wof:name":"Refsn\u00e6s Sogns Spare-og Lanekasse",
    "wof:placetype":"venue"
},
  "geometry": {"coordinates":[11.093409,55.679749],"type":"Point"}
}