{
  "type": "Feature",
  "properties": {
    "addr:full":"Jernbanegade 16 Fredensborg Danmark 3480",
    "addr:housenumber":"16",
    "addr:postcode":"3480",
    "addr:street":"Jernbanegade",
    "iso:country":"DK",
    "sg:address":"Jernbanegade 16",
    "sg:city":"Fredensborg",
    "sg:classifiers":[
        {
            "category":"Communications",
            "type":"Services"
        }
    ],
    "sg:phone":"+45 48 47 55 25",
    "sg:postcode":"3480",
    "sg:province":"Danmark",
    "sg:tags":[
        "og",
        "tv",
        "radio"
    ],
    "sg:website":"www.2tal.dk/fredensborg",
    "wof:name":"2tal",
    "wof:placetype":"venue"
},
  "geometry": {"coordinates":[12.3986959457,55.978843689],"type":"Point"}
}