{
  "type": "Feature",
  "properties": {
    "addr:full":"Liselejevej 7 Liseleje Danmark 3360",
    "addr:housenumber":"7",
    "addr:postcode":"3360",
    "addr:street":"Liselejevej",
    "iso:country":"DK",
    "sg:address":"Liselejevej 7",
    "sg:city":"Liseleje",
    "sg:orig_category":"Cafeer",
    "sg:phone":"+45 47 74 61 28",
    "sg:postcode":"3360",
    "sg:province":"Danmark",
    "wof:name":"St\u00f8berled Butik & Caf\u00e9",
    "wof:placetype":"venue"
},
  "geometry": {"coordinates":[11.9859399796,56.0071372986],"type":"Point"}
}