{
  "type": "Feature",
  "properties": {
    "addr:full":"Algade 42 Aalborg Danmark 9000",
    "addr:housenumber":"42",
    "addr:postcode":"9000",
    "addr:street":"Algade",
    "iso:country":"DK",
    "sg:address":"Algade 42",
    "sg:city":"Aalborg",
    "sg:orig_category":"Posthuse",
    "sg:phone":"+45 99 35 44 00",
    "sg:postcode":"9000",
    "sg:province":"Danmark",
    "wof:name":"Post Danmark, Posthuset i Algade",
    "wof:placetype":"venue"
},
  "geometry": {"coordinates":[9.9186267853,57.0483665466],"type":"Point"}
}