{
  "type": "Feature",
  "properties": {
    "addr:full":"N\u00f8rregade 26 Vejen Danmark 6600",
    "addr:housenumber":"26",
    "addr:postcode":"6600",
    "addr:street":"Norregade",
    "iso:country":"DK",
    "sg:address":"N\u00f8rregade 26",
    "sg:city":"Vejen",
    "sg:orig_category":"Materialister",
    "sg:phone":"+45 75 36 02 85",
    "sg:postcode":"6600",
    "sg:province":"Danmark",
    "wof:name":"Matas",
    "wof:placetype":"venue"
},
  "geometry": {"coordinates":[9.1387224197,55.4774360657],"type":"Point"}
}