{
  "type": "Feature",
  "properties": {
    "iso:country":"DK",
    "sg:address":"Kv\u00e6dehaven 60",
    "sg:city":"Glostrup",
    "sg:orig_category":"Revisorer",
    "sg:phone":"+45 43 96 97 65",
    "sg:postcode":"2600",
    "sg:province":"Danmark",
    "wof:name":"S\u00f8rensen, Hans Otto",
    "wof:placetype":"venue"
},
  "geometry": {"coordinates":[12.3957901001,55.6654663086],"type":"Point"}
}