{
  "type": "Feature",
  "properties": {
    "addr:full":"Gammelbyvej 1, Mejrup Holstebro Danmark 7500",
    "addr:housenumber":"1",
    "addr:postcode":"7500",
    "addr:street":"Gammelbyvej;Mejrup",
    "iso:country":"DK",
    "sg:address":"Gammelbyvej 1, Mejrup",
    "sg:city":"Holstebro",
    "sg:orig_category":"Malermestre",
    "sg:phone":"+45 97 42 48 24",
    "sg:postcode":"7500",
    "sg:province":"Danmark",
    "wof:name":"L\u00e6g\u00e5rd, Helge",
    "wof:placetype":"venue"
},
  "geometry": {"coordinates":[8.6202583313,56.3625221252],"type":"Point"}
}