{
  "type": "Feature",
  "properties": {
    "addr:full":"Tvedvej 50, Nr. Nissum Lemvig Danmark 7620",
    "addr:housenumber":"50",
    "addr:postcode":"7620",
    "addr:street":"Tvedvej",
    "iso:country":"DK",
    "sg:address":"Tvedvej 50, Nr. Nissum",
    "sg:city":"Lemvig",
    "sg:orig_category":"Autoreparation og -service",
    "sg:phone":"+45 97 89 14 22",
    "sg:postcode":"7620",
    "sg:province":"Danmark",
    "wof:name":"Jensen Auto",
    "wof:placetype":"venue"
},
  "geometry": {"coordinates":[8.3073654175,56.5505104065],"type":"Point"}
}