{
  "type": "Feature",
  "properties": {
    "addr:full":"Jegind\u00f8vej 11, Helligkilde Thyholm Danmark 7790",
    "addr:housenumber":"11",
    "addr:postcode":"7790",
    "addr:street":"Jegindovej",
    "iso:country":"DK",
    "sg:address":"Jegind\u00f8vej 11, Helligkilde",
    "sg:city":"Thyholm",
    "sg:orig_category":"Autoreparation og -service",
    "sg:phone":"+45 97 87 10 29",
    "sg:postcode":"7790",
    "sg:province":"Danmark",
    "wof:name":"Kroghs Auto",
    "wof:placetype":"venue"
},
  "geometry": {"coordinates":[8.525765419,56.6507072449],"type":"Point"}
}