{
  "type": "Feature",
  "properties": {
    "addr:full":"K\u00f8bmagergade 2 K\u00f8benhavn Danmark 1150",
    "addr:housenumber":"2",
    "addr:postcode":"1150",
    "addr:street":"Kobmagergade",
    "iso:country":"DK",
    "sg:address":"K\u00f8bmagergade 2",
    "sg:city":"K\u00f8benhavn",
    "sg:orig_category":"Vikarbureauer",
    "sg:phone":"+45 33 22 36 88",
    "sg:postcode":"1150",
    "sg:province":"Danmark",
    "sg:website":"www.activ-lagervikar.dk",
    "wof:name":"Activ Lagervikar",
    "wof:placetype":"venue"
},
  "geometry": {"coordinates":[76.3070983887,14.277130127],"type":"Point"}
}