{
  "type": "Feature",
  "properties": {
    "addr:full":"v/ Ole Olsen, Vibevej 20 Ringsted Danmark 4100",
    "addr:housenumber":"20",
    "addr:postcode":"4100",
    "addr:street":"Vibevej",
    "iso:country":"DK",
    "sg:address":"v/ Ole Olsen, Vibevej 20",
    "sg:city":"Ringsted",
    "sg:orig_category":"Naturgas install. og -service",
    "sg:phone":"+45 57 67 46 89",
    "sg:postcode":"4100",
    "sg:province":"Danmark",
    "sg:website":"www.ingoolsen-vvs.dk",
    "wof:name":"VVS Ingo Olsen",
    "wof:placetype":"venue"
},
  "geometry": {"coordinates":[11.7875862122,55.4458961487],"type":"Point"}
}