{
  "type": "Feature",
  "properties": {
    "addr:full":"Fmd.: Ejvind Haubjerg, Rydbjergvej 8 A, Velling Ringk\u00f8bing Danmark 6950",
    "addr:housenumber":"8 a",
    "addr:postcode":"6950",
    "addr:street":"Rydbjergvej;Velling Ringkobing Danmark",
    "iso:country":"DK",
    "sg:address":"Fmd.: Ejvind Haubjerg, Rydbjergvej 8 A, Velling",
    "sg:city":"Ringk\u00f8bing",
    "sg:orig_category":"Borger- og beboerforeninger",
    "sg:phone":"+45 97 32 16 59",
    "sg:postcode":"6950",
    "sg:province":"Danmark",
    "wof:name":"Velling Sogneforening",
    "wof:placetype":"venue"
},
  "geometry": {"coordinates":[8.2507953644,56.0878334045],"type":"Point"}
}