{
  "type": "Feature",
  "properties": {
    "addr:full":"Dalgade 27 Egtved Danmark 6040",
    "addr:housenumber":"27",
    "addr:postcode":"6040",
    "addr:street":"Dalgade",
    "iso:country":"DK",
    "sg:address":"Dalgade 27",
    "sg:city":"Egtved",
    "sg:orig_category":"Posthuse",
    "sg:phone":"+45 79 43 50 00",
    "sg:postcode":"6040",
    "sg:province":"Danmark",
    "wof:name":"Post Danmark, Egtved Posthus",
    "wof:placetype":"venue"
},
  "geometry": {"coordinates":[9.3053512573,55.6150970459],"type":"Point"}
}