{
  "type": "Feature",
  "properties": {
    "addr:full":"L\u00f8gtenvej 3 Hornslet Danmark 8543",
    "addr:housenumber":"3",
    "addr:postcode":"8543",
    "addr:street":"Logtenvej",
    "iso:country":"DK",
    "sg:address":"L\u00f8gtenvej 3",
    "sg:city":"Hornslet",
    "sg:orig_category":"Autoreparation og -service",
    "sg:phone":"+45 86 99 49 56",
    "sg:postcode":"8543",
    "sg:province":"Danmark",
    "wof:name":"Hedemann, Ove",
    "wof:placetype":"venue"
},
  "geometry": {"coordinates":[10.3198776245,56.3122367859],"type":"Point"}
}