{
  "type": "Feature",
  "properties": {
    "addr:full":"Gl. Landevej 139 Herning Danmark 7400",
    "addr:housenumber":"139",
    "addr:postcode":"7400",
    "addr:street":"Gl. Landevej",
    "iso:country":"DK",
    "sg:address":"Gl. Landevej 139",
    "sg:city":"Herning",
    "sg:orig_category":"Genbrugsbutikker",
    "sg:phone":"+45 97 21 27 40",
    "sg:postcode":"7400",
    "sg:province":"Danmark",
    "wof:name":"Danmission Genbrug",
    "wof:placetype":"venue"
},
  "geometry": {"coordinates":[8.9621429443,56.1402397156],"type":"Point"}
}