{
  "type": "Feature",
  "properties": {
    "addr:full":"Kirkevej 8, Gullev Bjerringbro Danmark 8850",
    "addr:housenumber":"8",
    "addr:postcode":"8850",
    "addr:street":"Kirkevej;Gullev",
    "iso:country":"DK",
    "sg:address":"Kirkevej 8, Gullev",
    "sg:city":"Bjerringbro",
    "sg:orig_category":"Kirker",
    "sg:postcode":"8850",
    "sg:province":"Danmark",
    "wof:name":"Gullev Kirke",
    "wof:placetype":"venue"
},
  "geometry": {"coordinates":[9.6546850204,56.3754692078],"type":"Point"}
}