{
  "type": "Feature",
  "properties": {
    "addr:full":"\u00c5rhusvej 79, Stilling Skanderborg Danmark 8660",
    "addr:housenumber":"79",
    "addr:postcode":"8660",
    "addr:street":"Aarhusvej",
    "iso:country":"DK",
    "sg:address":"\u00c5rhusvej 79, Stilling",
    "sg:city":"Skanderborg",
    "sg:orig_category":"Korrosionsforhindring, BRUGSVAND",
    "sg:phone":"+45 87 93 83 00",
    "sg:postcode":"8660",
    "sg:province":"Danmark",
    "sg:website":"www.silhorko.dk",
    "wof:name":"Silhorko-Eurowater A/S",
    "wof:placetype":"venue"
},
  "geometry": {"coordinates":[9.929974556,56.0380249023],"type":"Point"}
}