{
  "type": "Feature",
  "properties": {
    "addr:full":"Fmd.: Bodil \u00c5berg, Centrumgaden 25, 3.th. Ballerup Danmark 2750",
    "addr:housenumber":"25 3.th",
    "addr:postcode":"2750",
    "addr:street":"Centrumgaden",
    "iso:country":"DK",
    "sg:address":"Fmd.: Bodil \u00c5berg, Centrumgaden 25, 3.th.",
    "sg:city":"Ballerup",
    "sg:orig_category":"Husflidsforeninger",
    "sg:phone":"+45 44 97 00 46",
    "sg:postcode":"2750",
    "sg:province":"Danmark",
    "wof:name":"DDH-Ballerup Forening af Aktive Kvinder",
    "wof:placetype":"venue"
},
  "geometry": {"coordinates":[12.361000061,55.7301216125],"type":"Point"}
}