{
  "type": "Feature",
  "properties": {
    "addr:full":"Vinkelvej 6, Stilling Skanderborg Danmark 8660",
    "addr:housenumber":"6",
    "addr:postcode":"8660",
    "addr:street":"Vinkelvej;Stilling",
    "iso:country":"DK",
    "sg:address":"Vinkelvej 6, Stilling",
    "sg:city":"Skanderborg",
    "sg:orig_category":"Glarmestre og glarmagere",
    "sg:phone":"+45 86 57 16 45",
    "sg:postcode":"8660",
    "sg:province":"Danmark",
    "wof:name":"Vinkelvejens T\u00f8mrer- & Snedkerforretning",
    "wof:placetype":"venue"
},
  "geometry": {"coordinates":[9.929974556,56.0380249023],"type":"Point"}
}