{
  "type": "Feature",
  "properties": {
    "addr:full":"Kongensgade 36 Marstal Danmark 5960",
    "addr:housenumber":"36",
    "addr:postcode":"5960",
    "addr:street":"Kongensgade",
    "iso:country":"DK",
    "sg:address":"Kongensgade 36",
    "sg:city":"Marstal",
    "sg:orig_category":"Sko",
    "sg:phone":"+45 62 53 17 44",
    "sg:postcode":"5960",
    "sg:province":"Danmark",
    "wof:name":"Freddy Sko",
    "wof:placetype":"venue"
},
  "geometry": {"coordinates":[10.5168876648,54.8553161621],"type":"Point"}
}