{
  "type": "Feature",
  "properties": {
    "iso:country":"DK",
    "sg:address":"Leder: P. V. D. Osten, Dyrhave 37",
    "sg:city":"Aabenraa",
    "sg:orig_category":"Musik og sang",
    "sg:phone":"+45 74 62 72 79",
    "sg:postcode":"6200",
    "sg:province":"Danmark",
    "sg:website":"www.bdn.dk",
    "wof:name":"Nordschleswigsche Musikvereinigung",
    "wof:placetype":"venue"
},
  "geometry": {"coordinates":[9.4213867188,55.0449562073],"type":"Point"}
}