{
  "type": "Feature",
  "properties": {
    "addr:full":"Vesterbrogade 63 Holstebro Danmark 7500",
    "addr:housenumber":"63",
    "addr:postcode":"7500",
    "addr:street":"Vesterbrogade",
    "iso:country":"DK",
    "sg:address":"Vesterbrogade 63",
    "sg:city":"Holstebro",
    "sg:orig_category":"Bagere",
    "sg:phone":"+45 97 42 02 19",
    "sg:postcode":"7500",
    "sg:province":"Danmark",
    "wof:name":"Max, Bageriet",
    "wof:placetype":"venue"
},
  "geometry": {"coordinates":[8.606355,56.352936],"type":"Point"}
}