{
  "type": "Feature",
  "properties": {
    "addr:full":"Industrivej 3-5 Slangerup Danmark 3550",
    "addr:housenumber":"3-5",
    "addr:postcode":"3550",
    "addr:street":"Industrivej",
    "iso:country":"DK",
    "sg:address":"Industrivej 3-5",
    "sg:city":"Slangerup",
    "sg:classifiers":[
        {
            "category":"Food & Beverages",
            "subcategory":"Liquor & Beverages",
            "type":"Retail Goods"
        }
    ],
    "sg:phone":"+45 47 33 99 99",
    "sg:postcode":"3550",
    "sg:province":"Danmark",
    "sg:tags":[
        "vin"
    ],
    "wof:name":"UDV Denmark A/S",
    "wof:placetype":"venue"
},
  "geometry": {"coordinates":[12.1909265518,55.845451355],"type":"Point"}
}