{
  "type": "Feature",
  "properties": {
    "addr:full":"Jernbanegade 7 Saksk\u00f8bing Danmark 4990",
    "addr:housenumber":"7",
    "addr:postcode":"4990",
    "addr:street":"Jernbanegade",
    "iso:country":"DK",
    "sg:address":"Jernbanegade 7",
    "sg:city":"Saksk\u00f8bing",
    "sg:orig_category":"Integrerede institutioner",
    "sg:phone":"+45 54 70 45 71",
    "sg:postcode":"4990",
    "sg:province":"Danmark",
    "wof:name":"Saxtorp",
    "wof:placetype":"venue"
},
  "geometry": {"coordinates":[11.6367549896,54.7970314026],"type":"Point"}
}