{
  "type": "Feature",
  "properties": {
    "addr:full":"Peter Bangs Vej 91 Frederiksberg Danmark 2000",
    "addr:housenumber":"91",
    "addr:postcode":"2000",
    "addr:street":"Peter Bangs Vej",
    "iso:country":"DK",
    "sg:address":"Peter Bangs Vej 91",
    "sg:city":"Frederiksberg",
    "sg:orig_category":"Fotohandlere",
    "sg:phone":"+45 38 71 40 22",
    "sg:postcode":"2000",
    "sg:province":"Danmark",
    "wof:name":"Smico Foto",
    "wof:placetype":"venue"
},
  "geometry": {"coordinates":[12.5031604767,55.6784896851],"type":"Point"}
}