{
  "type": "Feature",
  "properties": {
    "addr:full":"Krystalgade 16, 1. K\u00f8benhavn Danmark 1172",
    "addr:housenumber":"16 1;1172",
    "addr:street":"Krystalgade",
    "iso:country":"DK",
    "sg:address":"Krystalgade 16, 1.",
    "sg:city":"K\u00f8benhavn",
    "sg:orig_category":"Aviser",
    "sg:phone":"+45 35 32 28 98",
    "sg:postcode":"1172",
    "sg:province":"Danmark",
    "sg:website":"www.ku.dk",
    "wof:name":"Universitetsavisen",
    "wof:placetype":"venue"
},
  "geometry": {"coordinates":[12.5739002228,55.6805992126],"type":"Point"}
}