{
  "type": "Feature",
  "properties": {
    "iso:country":"DK",
    "sg:address":"Fiskerihavnsgade 6",
    "sg:city":"Esbjerg",
    "sg:classifiers":[
        {
            "category":"Restaurant",
            "type":"Food & Drink"
        }
    ],
    "sg:phone":"+45 75 12 82 88",
    "sg:postcode":"6700",
    "sg:province":"Danmark",
    "wof:name":"Sydvesten",
    "wof:placetype":"venue"
},
  "geometry": {"coordinates":[8.4260568619,55.4743804932],"type":"Point"}
}