{
  "type": "Feature",
  "properties": {
    "addr:full":"Fmd.: Birthe Frydenlund, Fagerholtvej 13, Ferslev Skibby Danmark 4050",
    "addr:housenumber":"13",
    "addr:postcode":"4050",
    "addr:street":"Fagerholtvej;Ferslev",
    "iso:country":"DK",
    "sg:address":"Fmd.: Birthe Frydenlund, Fagerholtvej 13, Ferslev",
    "sg:city":"Skibby",
    "sg:orig_category":"Kulturelle foreninger",
    "sg:phone":"+45 47 52 94 43",
    "sg:postcode":"4050",
    "sg:province":"Danmark",
    "wof:name":"Horns Herreds Folkedansere",
    "wof:placetype":"venue"
},
  "geometry": {"coordinates":[11.9594116211,55.7502975464],"type":"Point"}
}