{
  "type": "Feature",
  "properties": {
    "iso:country":"DK",
    "sg:address":"Fmd.: Margrethe Willumsen, S\u00f8nderparken 11, st. tv.",
    "sg:city":"Holstebro",
    "sg:orig_category":"\u00c3\u2020ldreorganisationer og klubber",
    "sg:phone":"+45 97 42 39 62",
    "sg:postcode":"7500",
    "sg:province":"Danmark",
    "wof:name":"Kvindeligt Arbejderforbunds efterl\u00f8nsklub",
    "wof:placetype":"venue"
},
  "geometry": {"coordinates":[8.6202583313,56.3625221252],"type":"Point"}
}