{
  "type": "Feature",
  "properties": {
    "addr:full":"Blangstedg\u00e5rdsvej 66 Odense S\u00d8 Danmark 5220",
    "addr:housenumber":"66",
    "addr:postcode":"5220",
    "addr:street":"Blangstedgaardsvej",
    "iso:country":"DK",
    "sg:address":"Blangstedg\u00e5rdsvej 66",
    "sg:city":"Odense S\u00d8",
    "sg:orig_category":"Non-Classified Establishments",
    "sg:phone":"+45 66 15 84 22",
    "sg:postcode":"5220",
    "sg:province":"Danmark",
    "wof:name":"Kansas Workwear A/S",
    "wof:placetype":"venue"
},
  "geometry": {"coordinates":[10.4412307739,55.3860626221],"type":"Point"}
}