{
  "type": "Feature",
  "properties": {
    "iso:country":"DK",
    "sg:address":"Jordsmonnet 6",
    "sg:city":"Randers",
    "sg:orig_category":"INGENI\u00c3\u02dcRER",
    "sg:phone":"+45 86 42 72 22",
    "sg:postcode":"8900",
    "sg:province":"Danmark",
    "wof:name":"Reeholm og Bredahl A/S R\u00e5dgivende Ingeni\u00f8rer F.R.I.",
    "wof:placetype":"venue"
},
  "geometry": {"coordinates":[10.0361471176,56.4585456848],"type":"Point"}
}