{
  "type": "Feature",
  "properties": {
    "addr:full":"Sydvestvej 65 Glostrup Danmark 2600",
    "addr:housenumber":"65",
    "addr:postcode":"2600",
    "addr:street":"Sydvestvej",
    "iso:country":"DK",
    "sg:address":"Sydvestvej 65",
    "sg:city":"Glostrup",
    "sg:orig_category":"Malermestre",
    "sg:phone":"+45 43 96 21 94",
    "sg:postcode":"2600",
    "sg:province":"Danmark",
    "wof:name":"Hansen A/S, Kurt",
    "wof:placetype":"venue"
},
  "geometry": {"coordinates":[12.3831100464,55.6619377136],"type":"Point"}
}