{
  "type": "Feature",
  "properties": {
    "addr:full":"Fmd.: Solvejg Heeb\u00f8ll, F\u00e6rgevej 36, Aar\u00f8sund Haderslev Danmark 6100",
    "addr:housenumber":"36",
    "addr:postcode":"6100",
    "addr:street":"Faergevej;Aarosund",
    "iso:country":"DK",
    "sg:address":"Fmd.: Solvejg Heeb\u00f8ll, F\u00e6rgevej 36, Aar\u00f8sund",
    "sg:city":"Haderslev",
    "sg:orig_category":"Musik og sang",
    "sg:phone":"+45 74 58 46 17",
    "sg:postcode":"6100",
    "sg:province":"Danmark",
    "wof:name":"Spillemandskredsen S\u00f8nderjyllands Amt",
    "wof:placetype":"venue"
},
  "geometry": {"coordinates":[9.4879703522,55.2505493164],"type":"Point"}
}