{
  "type": "Feature",
  "properties": {
    "addr:full":"P\u00e6rg\u00e5rdsvej 9, S\u00f8nderby Horsens Danmark 8700",
    "addr:housenumber":"9",
    "addr:postcode":"8700",
    "addr:street":"Paergaardsvej;Sonderby",
    "iso:country":"DK",
    "sg:address":"P\u00e6rg\u00e5rdsvej 9, S\u00f8nderby",
    "sg:city":"Horsens",
    "sg:orig_category":"Planteskoler",
    "sg:phone":"+45 75 68 37 37",
    "sg:postcode":"8700",
    "sg:province":"Danmark",
    "wof:name":"Havlykke Planteskole",
    "wof:placetype":"venue"
},
  "geometry": {"coordinates":[9.8432445526,55.8621063232],"type":"Point"}
}