{
  "type": "Feature",
  "properties": {
    "addr:full":"Magleh\u00f8jvej 10 Kalundborg Danmark 4400",
    "addr:housenumber":"10",
    "addr:postcode":"4400",
    "addr:street":"Maglehojvej",
    "iso:country":"DK",
    "sg:address":"Magleh\u00f8jvej 10",
    "sg:city":"Kalundborg",
    "sg:orig_category":"Jordrensning",
    "sg:phone":"+45 59 50 46 68",
    "sg:postcode":"4400",
    "sg:province":"Danmark",
    "sg:website":"www.soilrem.com",
    "wof:name":"Bioteknisk Jordrens - SOILREM, A-S",
    "wof:placetype":"venue"
},
  "geometry": {"coordinates":[11.1308584213,55.6618461609],"type":"Point"}
}