{
  "type": "Feature",
  "properties": {
    "addr:full":"Assensvej 4 Faaborg Danmark 5600",
    "addr:housenumber":"4",
    "addr:postcode":"5600",
    "addr:street":"Assensvej",
    "iso:country":"DK",
    "sg:address":"Assensvej 4",
    "sg:city":"Faaborg",
    "sg:orig_category":"Revisorer",
    "sg:phone":"+45 63 61 41 00",
    "sg:postcode":"5600",
    "sg:province":"Danmark",
    "wof:name":"BDO ScanRevision statsaut. revisionsaktieselskab",
    "wof:placetype":"venue"
},
  "geometry": {"coordinates":[10.2311420441,55.1014671326],"type":"Point"}
}