{
  "type": "Feature",
  "properties": {
    "addr:full":"Fmd.: Elsebeth N. Pedersen, Vestertorp 35, Gjellerup Herning Danmark 7400",
    "addr:housenumber":"35",
    "addr:postcode":"7400",
    "addr:street":"N.;Vestertorp",
    "iso:country":"DK",
    "sg:address":"Fmd.: Elsebeth N. Pedersen, Vestertorp 35, Gjellerup",
    "sg:city":"Herning",
    "sg:orig_category":"Musik og sang",
    "sg:phone":"+45 97 20 90 01",
    "sg:postcode":"7400",
    "sg:province":"Danmark",
    "wof:name":"Hedekoret - Herning blandet kor",
    "wof:placetype":"venue"
},
  "geometry": {"coordinates":[8.9768896103,56.1374168396],"type":"Point"}
}