{
  "type": "Feature",
  "properties": {
    "addr:full":"Mylius Erichsens Vej 164 Aalborg S\u00d8 Danmark 9210",
    "addr:housenumber":"164",
    "addr:postcode":"9210",
    "addr:street":"Mylius Erichsens Vej",
    "iso:country":"DK",
    "sg:address":"Mylius Erichsens Vej 164",
    "sg:city":"Aalborg S\u00d8",
    "sg:orig_category":"Autoophug",
    "sg:phone":"+45 98 14 02 11",
    "sg:postcode":"9210",
    "sg:province":"Danmark",
    "wof:name":"Aalborg Autoophug",
    "wof:placetype":"venue"
},
  "geometry": {"coordinates":[9.9531106949,57.0164833069],"type":"Point"}
}