{
  "type": "Feature",
  "properties": {
    "addr:full":"Hvidovrevej 105 Hvidovre Danmark 2650",
    "addr:housenumber":"105",
    "addr:postcode":"2650",
    "addr:street":"Hvidovrevej",
    "iso:country":"DK",
    "sg:address":"Hvidovrevej 105",
    "sg:city":"Hvidovre",
    "sg:orig_category":"Blomsterhandlere",
    "sg:phone":"+45 36 75 01 35",
    "sg:postcode":"2650",
    "sg:province":"Danmark",
    "wof:name":"Kirkely Blomster",
    "wof:placetype":"venue"
},
  "geometry": {"coordinates":[12.473402977,55.6565437317],"type":"Point"}
}