{
  "type": "Feature",
  "properties": {
    "iso:country":"DK",
    "sg:address":"J. P. Larsens Vej 17 A",
    "sg:city":"Brabrand",
    "sg:orig_category":"Offsettrykkerier",
    "sg:phone":"+45 86 26 31 60",
    "sg:postcode":"8220",
    "sg:province":"Danmark",
    "wof:name":"Offset-Tryk ApS",
    "wof:placetype":"venue"
},
  "geometry": {"coordinates":[10.109287262,56.1543464661],"type":"Point"}
}