{
  "type": "Feature",
  "properties": {
    "addr:full":"Clausholmvej 24 Randers Danmark 8900",
    "addr:housenumber":"24",
    "addr:postcode":"8900",
    "addr:street":"Clausholmvej",
    "iso:country":"DK",
    "sg:address":"Clausholmvej 24",
    "sg:city":"Randers",
    "sg:orig_category":"Autoreparation og -service",
    "sg:phone":"+45 86 44 72 92",
    "sg:postcode":"8900",
    "sg:province":"Danmark",
    "wof:name":"HMK Auto",
    "wof:placetype":"venue"
},
  "geometry": {"coordinates":[10.0746822357,56.4376907349],"type":"Point"}
}