{
  "type": "Feature",
  "properties": {
    "addr:full":"Produktvej 5 Hadsund Danmark 9560",
    "addr:housenumber":"5",
    "addr:postcode":"9560",
    "addr:street":"Produktvej",
    "iso:country":"DK",
    "sg:address":"Produktvej 5",
    "sg:city":"Hadsund",
    "sg:orig_category":"Maskinfabrikker",
    "sg:phone":"+45 98 57 40 70",
    "sg:postcode":"9560",
    "sg:province":"Danmark",
    "wof:name":"FKN Teknik",
    "wof:placetype":"venue"
},
  "geometry": {"coordinates":[10.1027965546,56.7323760986],"type":"Point"}
}