{
  "type": "Feature",
  "properties": {
    "addr:full":"Vestergade 20 Faaborg Danmark 5600",
    "addr:housenumber":"20",
    "addr:postcode":"5600",
    "addr:street":"Vestergade",
    "iso:country":"DK",
    "sg:address":"Vestergade 20",
    "sg:city":"Faaborg",
    "sg:orig_category":"Handicapboliger",
    "sg:phone":"+45 62 61 24 58",
    "sg:postcode":"5600",
    "sg:province":"Danmark",
    "wof:name":"St\u00f8ttecentret",
    "wof:placetype":"venue"
},
  "geometry": {"coordinates":[10.238735199,55.0971221924],"type":"Point"}
}