{
  "type": "Feature",
  "properties": {
    "addr:full":"N\u00f8rregade 26 Bramming Danmark 6740",
    "addr:housenumber":"26",
    "addr:postcode":"6740",
    "addr:street":"Norregade",
    "iso:country":"DK",
    "sg:address":"N\u00f8rregade 26",
    "sg:city":"Bramming",
    "sg:classifiers":[
        {
            "category":"Communications",
            "type":"Services"
        }
    ],
    "sg:phone":"+45 75 17 20 82",
    "sg:postcode":"6740",
    "sg:province":"Danmark",
    "sg:tags":[
        "og",
        "tv",
        "radio"
    ],
    "wof:name":"KC-Radio",
    "wof:placetype":"venue"
},
  "geometry": {"coordinates":[8.6997213364,55.4660606384],"type":"Point"}
}