{
  "type": "Feature",
  "properties": {
    "iso:country":"DK",
    "sg:address":"Snedkervej 17",
    "sg:city":"Esbjerg V",
    "sg:orig_category":"Revisorer",
    "sg:phone":"+45 75 15 22 22",
    "sg:postcode":"6710",
    "sg:province":"Danmark",
    "wof:name":"S\u00e6dding Revision",
    "wof:placetype":"venue"
},
  "geometry": {"coordinates":[8.4142398834,55.5045280457],"type":"Point"}
}