{
  "type": "Feature",
  "properties": {
    "iso:country":"DK",
    "sg:address":"Industriparken 20 ",
    "sg:city":"Bredsten",
    "sg:classifiers":[
        {
            "category":"Parking",
            "subcategory":"Lot",
            "type":"Transportation"
        }
    ],
    "sg:phone":"+45 75 88 15 11",
    "sg:postcode":"7182",
    "sg:province":"Danmark",
    "sg:tags":[
        "transport",
        "road"
    ],
    "wof:name":"J.T.T. JYDSK TRANSPORT TEKNIK APS",
    "wof:placetype":"venue"
},
  "geometry": {"coordinates":[9.3781967163,55.7004013062],"type":"Point"}
}