{
  "type": "Feature",
  "properties": {
    "addr:full":"Kl\u00f8vk\u00e6rvej 15  Kolding Danmark 6000",
    "addr:housenumber":"15",
    "addr:postcode":"6000",
    "addr:street":"Klovkaervej",
    "iso:country":"DK",
    "sg:address":"Kl\u00f8vk\u00e6rvej 15 ",
    "sg:city":"Kolding",
    "sg:classifiers":[
        {
            "category":"Wholesale",
            "subcategory":"Drugs",
            "type":"Manufacturing & Wholesale Goods"
        }
    ],
    "sg:phone":"+45 75 52 20 22",
    "sg:postcode":"6000",
    "sg:province":"Danmark",
    "sg:tags":[
        "chemical",
        "pharmaceutical"
    ],
    "wof:name":"NP JOHNSENS FYRV\u00c6KERIFABRIK A/S",
    "wof:placetype":"venue"
},
  "geometry": {"coordinates":[9.4733953476,55.4863586426],"type":"Point"}
}