{
  "type": "Feature",
  "properties": {
    "addr:full":"\u00d8ster Torv 8, Esperg\u00e6rde Centret Esperg\u00e6rde Danmark 3060",
    "addr:housenumber":"8",
    "addr:postcode":"3060",
    "addr:street":"Oster Torv",
    "iso:country":"DK",
    "sg:address":"\u00d8ster Torv 8, Esperg\u00e6rde Centret",
    "sg:city":"Esperg\u00e6rde",
    "sg:orig_category":"Sko",
    "sg:phone":"+45 49 13 17 13",
    "sg:postcode":"3060",
    "sg:province":"Danmark",
    "wof:name":"Skot\u00f8jshuset",
    "wof:placetype":"venue"
},
  "geometry": {"coordinates":[11.6512403488,47.8390617371],"type":"Point"}
}