{
  "type": "Feature",
  "properties": {
    "addr:full":"Damagervej 26 Viby Danmark 8260",
    "addr:housenumber":"26",
    "addr:postcode":"8260",
    "addr:street":"Damagervej",
    "iso:country":"DK",
    "sg:address":"Damagervej 26",
    "sg:city":"Viby",
    "sg:orig_category":"Handicapboliger",
    "sg:phone":"+45 87 33 89 00",
    "sg:postcode":"8260",
    "sg:province":"Danmark",
    "wof:name":"H\u00f8skov-Kollegiet",
    "wof:placetype":"venue"
},
  "geometry": {"coordinates":[10.1481952667,56.1324119568],"type":"Point"}
}