{
  "type": "Feature",
  "properties": {
    "iso:country":"DK",
    "sg:address":"Tofteg\u00e5rds Plads 1",
    "sg:city":"Valby",
    "sg:orig_category":"Sko",
    "sg:phone":"+45 36 44 43 33",
    "sg:postcode":"2500",
    "sg:province":"Danmark",
    "wof:name":"Company Sko Mode",
    "wof:placetype":"venue"
},
  "geometry": {"coordinates":[12.5165910721,55.6617851257],"type":"Point"}
}