{
  "type": "Feature",
  "properties": {
    "addr:full":"Fmd.: Bjarne Bleicken, Lyngbakken 8, Klejtrup Hobro Danmark 9500",
    "addr:housenumber":"8",
    "addr:postcode":"9500",
    "addr:street":"Lyngbakken",
    "iso:country":"DK",
    "sg:address":"Fmd.: Bjarne Bleicken, Lyngbakken 8, Klejtrup",
    "sg:city":"Hobro",
    "sg:orig_category":"Grundejerforeninger",
    "sg:phone":"+45 98 54 64 00",
    "sg:postcode":"9500",
    "sg:province":"Danmark",
    "wof:name":"Lyngbakken",
    "wof:placetype":"venue"
},
  "geometry": {"coordinates":[9.7946596146,56.6382789612],"type":"Point"}
}