{
  "type": "Feature",
  "properties": {
    "addr:full":"Herrestr\u00e6de 11 Slagelse Danmark 4200",
    "addr:housenumber":"11",
    "addr:postcode":"4200",
    "addr:street":"Herrestraede",
    "iso:country":"DK",
    "sg:address":"Herrestr\u00e6de 11",
    "sg:city":"Slagelse",
    "sg:orig_category":"Voksenuddannelsescentre",
    "sg:phone":"+45 58 55 50 50",
    "sg:postcode":"4200",
    "sg:province":"Danmark",
    "sg:website":"www.vuc-vestamt.dk",
    "wof:name":"VUC Vestsj\u00e6lland",
    "wof:placetype":"venue"
},
  "geometry": {"coordinates":[11.4328155518,55.4791374207],"type":"Point"}
}