{
  "type": "Feature",
  "properties": {
    "addr:full":"Thorstedvej 86 Thisted Danmark 7700",
    "addr:housenumber":"86",
    "addr:postcode":"7700",
    "addr:street":"Thorstedvej",
    "iso:country":"DK",
    "sg:address":"Thorstedvej 86",
    "sg:city":"Thisted",
    "sg:orig_category":"Flytteforretninger",
    "sg:phone":"+45 97 92 11 48",
    "sg:postcode":"7700",
    "sg:province":"Danmark",
    "wof:name":"Thisted Flytteforretning",
    "wof:placetype":"venue"
},
  "geometry": {"coordinates":[8.6613302231,56.9616203308],"type":"Point"}
}