{
  "type": "Feature",
  "properties": {
    "addr:full":"Sognepr\u00e6st: Leni U. Hansen, Langgade 34, Fleml\u00f8se Glamsbjerg Danmark 5620",
    "addr:housenumber":"34",
    "addr:postcode":"5620",
    "addr:street":"Langgade;Flemlose",
    "iso:country":"DK",
    "sg:address":"Sognepr\u00e6st: Leni U. Hansen, Langgade 34, Fleml\u00f8se",
    "sg:city":"Glamsbjerg",
    "sg:orig_category":"Kirkesogne",
    "sg:phone":"+45 64 72 10 23",
    "sg:postcode":"5620",
    "sg:province":"Danmark",
    "wof:name":"S\u00f8by sogn",
    "wof:placetype":"venue"
},
  "geometry": {"coordinates":[10.1052503586,55.2783317566],"type":"Point"}
}