{
  "type": "Feature",
  "properties": {
    "addr:full":"Skovlundvej 7, Skovlund Ansager Danmark 6823",
    "addr:housenumber":"7",
    "addr:postcode":"6823",
    "addr:street":"Skovlundvej;Skovlund",
    "iso:country":"DK",
    "sg:address":"Skovlundvej 7, Skovlund",
    "sg:city":"Ansager",
    "sg:orig_category":"Akupunktur",
    "sg:phone":"+45 75 29 22 87",
    "sg:postcode":"6823",
    "sg:province":"Danmark",
    "wof:name":"B\u00f8gevangs Akupunktur",
    "wof:placetype":"venue"
},
  "geometry": {"coordinates":[8.7533082962,55.7048492432],"type":"Point"}
}