{
  "type": "Feature",
  "properties": {
    "addr:full":"Torvet 9 Faaborg Danmark 5600",
    "addr:housenumber":"9",
    "addr:postcode":"5600",
    "addr:street":"Torvet",
    "iso:country":"DK",
    "sg:address":"Torvet 9",
    "sg:city":"Faaborg",
    "sg:classifiers":[
        {
            "category":"Home & Garden",
            "subcategory":"Home Furnishings",
            "type":"Retail Goods"
        }
    ],
    "sg:phone":"+45 62 61 36 36",
    "sg:postcode":"5600",
    "sg:province":"Danmark",
    "sg:tags":[
        "gardiner"
    ],
    "wof:name":"Gardin-Nyt",
    "wof:placetype":"venue"
},
  "geometry": {"coordinates":[10.2422037125,55.0948257446],"type":"Point"}
}