{
  "type": "Feature",
  "properties": {
    "iso:country":"DK",
    "sg:address":"Tisvildevej 3",
    "sg:city":"Vejby",
    "sg:orig_category":"Alternativ behandling",
    "sg:phone":"+45 48 70 55 99",
    "sg:postcode":"3210",
    "sg:province":"Danmark",
    "wof:name":"Klinik Reiki",
    "wof:placetype":"venue"
},
  "geometry": {"coordinates":[12.1384820938,56.066078186],"type":"Point"}
}