{
  "type": "Feature",
  "properties": {
    "addr:full":"Hylstrupvej 18 Fjenneslev Danmark 4173",
    "addr:housenumber":"18",
    "addr:postcode":"4173",
    "addr:street":"Hylstrupvej",
    "iso:country":"DK",
    "sg:address":"Hylstrupvej 18",
    "sg:city":"Fjenneslev",
    "sg:orig_category":"Murermestre",
    "sg:phone":"+45 57 80 96 86",
    "sg:postcode":"4173",
    "sg:province":"Danmark",
    "sg:website":"www.kastanien.dk",
    "wof:name":"Kastanien Byggefirma",
    "wof:placetype":"venue"
},
  "geometry": {"coordinates":[11.6564769745,55.419303894],"type":"Point"}
}