{
  "type": "Feature",
  "properties": {
    "addr:full":"Langevad 3 Aabenraa Danmark 6200",
    "addr:housenumber":"3",
    "addr:postcode":"6200",
    "addr:street":"Langevad",
    "iso:country":"DK",
    "sg:address":"Langevad 3",
    "sg:city":"Aabenraa",
    "sg:orig_category":"Autoforhandlere",
    "sg:phone":"+45 74 62 61 65",
    "sg:postcode":"6200",
    "sg:province":"Danmark",
    "wof:name":"Moshage Automobiler, Per",
    "wof:placetype":"venue"
},
  "geometry": {"coordinates":[9.4227762222,55.0490036011],"type":"Point"}
}