{
  "type": "Feature",
  "properties": {
    "addr:full":"Bredgade 26 N\u00f8rre Nebel Danmark 6830",
    "addr:housenumber":"26",
    "addr:postcode":"6830",
    "addr:street":"Bredgade",
    "iso:country":"DK",
    "sg:address":"Bredgade 26",
    "sg:city":"N\u00f8rre Nebel",
    "sg:orig_category":"Kiosker",
    "sg:phone":"+45 75 28 81 25",
    "sg:postcode":"6830",
    "sg:province":"Danmark",
    "wof:name":"N\u00f8rre-Nebel Kiosk",
    "wof:placetype":"venue"
},
  "geometry": {"coordinates":[8.288599968,55.7792358398],"type":"Point"}
}