{
  "type": "Feature",
  "properties": {
    "addr:full":"Ringstedvej 117 Haslev Danmark 4690",
    "addr:housenumber":"117",
    "addr:postcode":"4690",
    "addr:street":"Ringstedvej",
    "iso:country":"DK",
    "sg:address":"Ringstedvej 117",
    "sg:city":"Haslev",
    "sg:orig_category":"Murermestre",
    "sg:phone":"+45 56 31 35 14",
    "sg:postcode":"4690",
    "sg:province":"Danmark",
    "sg:website":"www.dahrup.dk",
    "wof:name":"Dahrup, Birger",
    "wof:placetype":"venue"
},
  "geometry": {"coordinates":[11.9446544647,55.3369598389],"type":"Point"}
}