{
  "type": "Feature",
  "properties": {
    "iso:country":"DK",
    "sg:address":"Havnekontoret, Siimtoften 13",
    "sg:city":"Ry",
    "sg:orig_category":"Havne",
    "sg:phone":"+45 86 89 29 90",
    "sg:postcode":"8680",
    "sg:province":"Danmark",
    "wof:name":"Ry Marina",
    "wof:placetype":"venue"
},
  "geometry": {"coordinates":[9.7593002319,56.0920562744],"type":"Point"}
}