{
  "type": "Feature",
  "properties": {
    "addr:full":"Fmd.: Ingrid Lorentzen, Lundvej 40 Varde Danmark 6800",
    "addr:housenumber":"40",
    "addr:postcode":"6800",
    "addr:street":"Lundvej",
    "iso:country":"DK",
    "sg:address":"Fmd.: Ingrid Lorentzen, Lundvej 40",
    "sg:city":"Varde",
    "sg:orig_category":"Husflidsforeninger",
    "sg:postcode":"6800",
    "sg:province":"Danmark",
    "wof:name":"Mejls Husholdningsforening",
    "wof:placetype":"venue"
},
  "geometry": {"coordinates":[8.482629776,55.6220741272],"type":"Point"}
}