{
  "type": "Feature",
  "properties": {
    "iso:country":"DK",
    "sg:address":"Storegade 27",
    "sg:city":"Lunderskov",
    "sg:orig_category":"Autoreparation og -service",
    "sg:phone":"+45 75 58 51 36",
    "sg:postcode":"6640",
    "sg:province":"Danmark",
    "wof:name":"Madsen, H. K.",
    "wof:placetype":"venue"
},
  "geometry": {"coordinates":[9.2991724014,55.4793205261],"type":"Point"}
}