{
  "type": "Feature",
  "properties": {
    "addr:full":"R\u00f8de M\u00f8llevej 4, Gravlev Sk\u00f8rping Danmark 9520",
    "addr:housenumber":"4",
    "addr:postcode":"9520",
    "addr:street":"Rode Mollevej",
    "iso:country":"DK",
    "sg:address":"R\u00f8de M\u00f8llevej 4, Gravlev",
    "sg:city":"Sk\u00f8rping",
    "sg:orig_category":"Museer",
    "sg:phone":"+45 98 37 51 12",
    "sg:postcode":"9520",
    "sg:province":"Danmark",
    "wof:name":"Thingb\u00e6k Kalkminer",
    "wof:placetype":"venue"
},
  "geometry": {"coordinates":[9.8477077484,56.8337860107],"type":"Point"}
}