{
  "type": "Feature",
  "properties": {
    "iso:country":"DK",
    "sg:address":"Lemming Bygade 1",
    "sg:city":"Lemming",
    "sg:orig_category":"Kirker",
    "sg:postcode":"8632",
    "sg:province":"Danmark",
    "wof:name":"Lemming Kirke",
    "wof:placetype":"venue"
},
  "geometry": {"coordinates":[9.5465602875,56.2361488342],"type":"Point"}
}