{
  "type": "Feature",
  "properties": {
    "addr:full":"Lucernemarken 18, Hjallese Odense S Danmark 5260",
    "addr:housenumber":"18",
    "addr:postcode":"5260",
    "addr:street":"Lucernemarken;Hjallese",
    "iso:country":"DK",
    "sg:address":"Lucernemarken 18, Hjallese",
    "sg:city":"Odense S",
    "sg:orig_category":"Fabrikker",
    "sg:phone":"+45 66 14 36 61",
    "sg:postcode":"5260",
    "sg:province":"Danmark",
    "wof:name":"Fyens B\u00f8rste- og Kostefabrik",
    "wof:placetype":"venue"
},
  "geometry": {"coordinates":[10.3157806396,55.3122825623],"type":"Point"}
}