{
  "type": "Feature",
  "properties": {
    "addr:full":"Baneg\u00e5rdsgade 29 \u00c5rhus C Danmark 8000",
    "addr:housenumber":"29",
    "addr:postcode":"8000",
    "addr:street":"Banegaardsgade",
    "iso:country":"DK",
    "sg:address":"Baneg\u00e5rdsgade 29",
    "sg:city":"\u00c5rhus C",
    "sg:orig_category":"Antikvariater",
    "sg:phone":"+45 86 12 55 61",
    "sg:postcode":"8000",
    "sg:province":"Danmark",
    "wof:name":"Hinge's Antikvariat",
    "wof:placetype":"venue"
},
  "geometry": {"coordinates":[4.717400074,49.7588005066],"type":"Point"}
}