{
  "type": "Feature",
  "properties": {
    "addr:full":"Kalkv\u00e6rksvej 9 B Frederikshavn Danmark 9900",
    "addr:housenumber":"9 b",
    "addr:postcode":"9900",
    "addr:street":"Kalkvaerksvej",
    "iso:country":"DK",
    "sg:address":"Kalkv\u00e6rksvej 9 B",
    "sg:city":"Frederikshavn",
    "sg:classifiers":[
        {
            "category":"Communications",
            "subcategory":"Film & Video Production",
            "type":"Services"
        }
    ],
    "sg:phone":"+45 98 42 74 37",
    "sg:postcode":"9900",
    "sg:province":"Danmark",
    "sg:tags":[
        "radio-",
        "og",
        "tv-service"
    ],
    "wof:name":"Elektronik-Service",
    "wof:placetype":"venue"
},
  "geometry": {"coordinates":[10.5289621353,57.4363822937],"type":"Point"}
}