{
  "type": "Feature",
  "properties": {
    "addr:full":"Kongensgade 0 Kongerslev Danmark 9293",
    "addr:housenumber":"0",
    "addr:postcode":"9293",
    "addr:street":"Kongensgade",
    "iso:country":"DK",
    "sg:address":"Kongensgade 0",
    "sg:city":"Kongerslev",
    "sg:orig_category":"Kirker",
    "sg:postcode":"9293",
    "sg:province":"Danmark",
    "wof:name":"Sdr. Kongerslev Kirke",
    "wof:placetype":"venue"
},
  "geometry": {"coordinates":[10.1198301315,56.8894500732],"type":"Point"}
}