{
  "type": "Feature",
  "properties": {
    "addr:full":"Algade 92, Ramme Lemvig Danmark 7620",
    "addr:housenumber":"92",
    "addr:postcode":"7620",
    "addr:street":"Algade",
    "iso:country":"DK",
    "sg:address":"Algade 92, Ramme",
    "sg:city":"Lemvig",
    "sg:orig_category":"Kommunale folkeskoler",
    "sg:phone":"+45 97 88 93 09",
    "sg:postcode":"7620",
    "sg:province":"Danmark",
    "wof:name":"Ramme Centralskole",
    "wof:placetype":"venue"
},
  "geometry": {"coordinates":[8.3073654175,56.5505104065],"type":"Point"}
}