{
  "type": "Feature",
  "properties": {
    "addr:full":"Sor\u00f8vej 35 Stenlille Danmark 4295",
    "addr:housenumber":"35",
    "addr:postcode":"4295",
    "addr:street":"Sorovej",
    "iso:country":"DK",
    "sg:address":"Sor\u00f8vej 35",
    "sg:city":"Stenlille",
    "sg:orig_category":"Skolefritidsordninger",
    "sg:phone":"+45 57 80 48 88",
    "sg:postcode":"4295",
    "sg:province":"Danmark",
    "wof:name":"Oasen og Sahara, Stenmagle Skoles Fritidsordning",
    "wof:placetype":"venue"
},
  "geometry": {"coordinates":[11.6191053391,55.5524215698],"type":"Point"}
}