{
  "type": "Feature",
  "properties": {
    "addr:full":"Limfjordsgade 5, Lyngs Thyholm Danmark 7790",
    "addr:housenumber":"5",
    "addr:postcode":"7790",
    "addr:street":"Limfjordsgade;Lyngs",
    "iso:country":"DK",
    "sg:address":"Limfjordsgade 5, Lyngs",
    "sg:city":"Thyholm",
    "sg:orig_category":"Maskinstationer",
    "sg:phone":"+45 97 87 81 85",
    "sg:postcode":"7790",
    "sg:province":"Danmark",
    "wof:name":"Lyngs Maskinstation",
    "wof:placetype":"venue"
},
  "geometry": {"coordinates":[8.525765419,56.6507072449],"type":"Point"}
}