{
  "type": "Feature",
  "properties": {
    "addr:full":"Skolev\u00e6nget 19, Knabstrup M\u00f8rk\u00f8v Danmark 4440",
    "addr:housenumber":"19",
    "addr:postcode":"4440",
    "addr:street":"Skolevaenget",
    "iso:country":"DK",
    "sg:address":"Skolev\u00e6nget 19, Knabstrup",
    "sg:city":"M\u00f8rk\u00f8v",
    "sg:orig_category":"Alternativ behandling",
    "sg:phone":"+45 59 27 33 20",
    "sg:postcode":"4440",
    "sg:province":"Danmark",
    "wof:name":"Napier, Hanne",
    "wof:placetype":"venue"
},
  "geometry": {"coordinates":[11.4997396469,55.6530609131],"type":"Point"}
}