{
  "type": "Feature",
  "properties": {
    "addr:full":"A. C. Illums Vej 29 Silkeborg Danmark 8600",
    "addr:housenumber":"29",
    "addr:postcode":"8600",
    "addr:street":"A. C. Illums Vej",
    "iso:country":"DK",
    "sg:address":"A. C. Illums Vej 29",
    "sg:city":"Silkeborg",
    "sg:orig_category":"El-tavler",
    "sg:phone":"+45 86 81 75 00",
    "sg:postcode":"8600",
    "sg:province":"Danmark",
    "wof:name":"Toka El-Teknik A/S",
    "wof:placetype":"venue"
},
  "geometry": {"coordinates":[9.5853090286,56.2017211914],"type":"Point"}
}