{
  "type": "Feature",
  "properties": {
    "addr:full":"Industrivej 7 Langeskov Danmark 5550",
    "addr:housenumber":"7",
    "addr:postcode":"5550",
    "addr:street":"Industrivej",
    "iso:country":"DK",
    "sg:address":"Industrivej 7",
    "sg:city":"Langeskov",
    "sg:orig_category":"Autoreparation og -service",
    "sg:phone":"+45 65 38 10 94",
    "sg:postcode":"5550",
    "sg:province":"Danmark",
    "sg:website":"www.langeskovauto.dk",
    "wof:name":"Langeskov Autov\u00e6rksted",
    "wof:placetype":"venue"
},
  "geometry": {"coordinates":[10.5790653229,55.3533592224],"type":"Point"}
}