{
  "type": "Feature",
  "properties": {
    "addr:full":"Ribe Landevej 3 Vejle Danmark 7100",
    "addr:housenumber":"3",
    "addr:postcode":"7100",
    "addr:street":"Ribe Landevej",
    "iso:country":"DK",
    "sg:address":"Ribe Landevej 3",
    "sg:city":"Vejle",
    "sg:orig_category":"Trossamfund uden for folkekirken",
    "sg:phone":"+45 75 82 26 40",
    "sg:postcode":"7100",
    "sg:province":"Danmark",
    "wof:name":"Jehovas Vidners Rigssal - Centrum og Syd",
    "wof:placetype":"venue"
},
  "geometry": {"coordinates":[9.5219106674,55.7023162842],"type":"Point"}
}