{
  "type": "Feature",
  "properties": {
    "addr:full":"S\u00f8ndervangs Alle 26 Valby Danmark 2500",
    "addr:housenumber":"26",
    "addr:postcode":"2500",
    "addr:street":"Sondervangs Alle",
    "iso:country":"DK",
    "sg:address":"S\u00f8ndervangs Alle 26",
    "sg:city":"Valby",
    "sg:orig_category":"Malermestre",
    "sg:phone":"+45 36 46 62 08",
    "sg:postcode":"2500",
    "sg:province":"Danmark",
    "wof:name":"Larsen, Werner",
    "wof:placetype":"venue"
},
  "geometry": {"coordinates":[12.4953670502,55.6543617249],"type":"Point"}
}