{
  "type": "Feature",
  "properties": {
    "addr:full":"Laurids Skaus Gade 26 Haderslev Danmark 6100",
    "addr:housenumber":"26",
    "addr:postcode":"6100",
    "addr:street":"Laurids Skaus Gade",
    "iso:country":"DK",
    "sg:address":"Laurids Skaus Gade 26",
    "sg:city":"Haderslev",
    "sg:orig_category":"Filmproduktion",
    "sg:postcode":"6100",
    "sg:province":"Danmark",
    "wof:name":"Apostolsk Video Produktion",
    "wof:placetype":"venue"
},
  "geometry": {"coordinates":[9.4836874008,55.254737854],"type":"Point"}
}