{
  "type": "Feature",
  "properties": {
    "addr:full":"Arres\u00f8vej 5 Risskov Danmark 8240",
    "addr:housenumber":"5",
    "addr:postcode":"8240",
    "addr:street":"Arresovej",
    "iso:country":"DK",
    "sg:address":"Arres\u00f8vej 5",
    "sg:city":"Risskov",
    "sg:orig_category":"Autoreservedele",
    "sg:phone":"+45 86 17 27 99",
    "sg:postcode":"8240",
    "sg:province":"Danmark",
    "sg:website":"www.nap.dk",
    "wof:name":"Nordic AutoParts",
    "wof:placetype":"venue"
},
  "geometry": {"coordinates":[10.2357530594,56.2020301819],"type":"Point"}
}