{
  "type": "Feature",
  "properties": {
    "addr:full":"Nygade 26 Ikast Danmark 7430",
    "addr:housenumber":"26",
    "addr:postcode":"7430",
    "addr:street":"Nygade",
    "iso:country":"DK",
    "sg:address":"Nygade 26",
    "sg:city":"Ikast",
    "sg:orig_category":"Revisorer",
    "sg:phone":"+45 97 15 25 33",
    "sg:postcode":"7430",
    "sg:province":"Danmark",
    "wof:name":"Hedens AgroR\u00e5dgivning",
    "wof:placetype":"venue"
},
  "geometry": {"coordinates":[9.1611413956,56.1432342529],"type":"Point"}
}