{
  "type": "Feature",
  "properties": {
    "addr:full":"Fmd.: S\u00fckr\u00fc Ertosun, \u00d8stervold 2 Randers Danmark 8900",
    "addr:housenumber":"2",
    "addr:postcode":"8900",
    "addr:street":"Ostervold",
    "iso:country":"DK",
    "sg:address":"Fmd.: S\u00fckr\u00fc Ertosun, \u00d8stervold 2",
    "sg:city":"Randers",
    "sg:orig_category":"Kulturcentre",
    "sg:phone":"+45 86 43 90 03",
    "sg:postcode":"8900",
    "sg:province":"Danmark",
    "wof:name":"Tyrkisk kultur- og undervisningscenter",
    "wof:placetype":"venue"
},
  "geometry": {"coordinates":[10.0357952118,56.4593734741],"type":"Point"}
}