{
  "type": "Feature",
  "properties": {
    "addr:full":"Troelsevej 211, Troelse Blommenslyst Danmark 5491",
    "addr:housenumber":"211",
    "addr:postcode":"5491",
    "addr:street":"Troelsevej",
    "iso:country":"DK",
    "sg:address":"Troelsevej 211, Troelse",
    "sg:city":"Blommenslyst",
    "sg:classifiers":[
        {
            "category":"Professional",
            "subcategory":"Computer Services",
            "type":"Services"
        }
    ],
    "sg:phone":"+45 65 96 78 24",
    "sg:postcode":"5491",
    "sg:province":"Danmark",
    "sg:tags":[
        "edb",
        "-",
        "software"
    ],
    "wof:name":"LC Consult",
    "wof:placetype":"venue"
},
  "geometry": {"coordinates":[10.2299203873,55.3889007568],"type":"Point"}
}