{
  "type": "Feature",
  "properties": {
    "addr:full":"Palsg\u00e5rdvej 38 K, Kirkholm Juelsminde Danmark 7130",
    "addr:housenumber":"38 k",
    "addr:postcode":"7130",
    "addr:street":"Palsgaardvej;Kirkholm",
    "iso:country":"DK",
    "sg:address":"Palsg\u00e5rdvej 38 K, Kirkholm",
    "sg:city":"Juelsminde",
    "sg:orig_category":"Kirker",
    "sg:postcode":"7130",
    "sg:province":"Danmark",
    "wof:name":"As Kirke",
    "wof:placetype":"venue"
},
  "geometry": {"coordinates":[10.0143985748,55.7135848999],"type":"Point"}
}