{
  "type": "Feature",
  "properties": {
    "iso:country":"DK",
    "sg:address":"Edithsvej 23",
    "sg:city":"Glostrup",
    "sg:orig_category":"Glarmestre og glarmagere",
    "sg:phone":"+45 43 45 46 02",
    "sg:postcode":"2600",
    "sg:province":"Danmark",
    "wof:name":"Andersen, J\u00f8rgen",
    "wof:placetype":"venue"
},
  "geometry": {"coordinates":[12.4059791565,55.6647605896],"type":"Point"}
}