{
  "type": "Feature",
  "properties": {
    "iso:country":"DK",
    "sg:address":"Store Kongensgade 63",
    "sg:city":"K\u00f8benhavn",
    "sg:orig_category":"Belysning",
    "sg:phone":"+45 33 93 17 01",
    "sg:postcode":"1264",
    "sg:province":"Danmark",
    "wof:name":"Lysmesteren",
    "wof:placetype":"venue"
},
  "geometry": {"coordinates":[12.5924,55.686501],"type":"Point"}
}