{
  "type": "Feature",
  "properties": {
    "iso:country":"DK",
    "sg:address":"Gildemester: P.E.Christensen, Hegnsk\u00e6r 5, Sm\u00f8rumnedre",
    "sg:city":"Sm\u00f8rum",
    "sg:orig_category":"\u00c3\u02dcvrige foreninger",
    "sg:phone":"+45 44 97 47 32",
    "sg:postcode":"2765",
    "sg:province":"Danmark",
    "wof:name":"Sct.Georgs Gildet i Led\u00f8je- Sm\u00f8rum",
    "wof:placetype":"venue"
},
  "geometry": {"coordinates":[-89.99810791020001,38.1321372986],"type":"Point"}
}