{
  "type": "Feature",
  "properties": {
    "addr:full":"Egil Fischers Vej 25 Ebeltoft Danmark 8400",
    "addr:housenumber":"25",
    "addr:postcode":"8400",
    "addr:street":"Egil Fischers Vej",
    "iso:country":"DK",
    "sg:address":"Egil Fischers Vej 25",
    "sg:city":"Ebeltoft",
    "sg:orig_category":"INGENI\u00c3\u02dcRER",
    "sg:phone":"+45 86 36 22 22",
    "sg:postcode":"8400",
    "sg:province":"Danmark",
    "wof:name":"J\u00f8rgensen Ingeni\u00f8rfirma, Kiel",
    "wof:placetype":"venue"
},
  "geometry": {"coordinates":[10.598941803,56.23254776],"type":"Point"}
}