{
  "type": "Feature",
  "properties": {
    "addr:full":"Fabersvej 1 Holstebro Danmark 7500",
    "addr:housenumber":"1",
    "addr:postcode":"7500",
    "addr:street":"Fabersvej",
    "iso:country":"DK",
    "sg:address":"Fabersvej 1",
    "sg:city":"Holstebro",
    "sg:orig_category":"Revisorer",
    "sg:phone":"+45 97 41 22 11",
    "sg:postcode":"7500",
    "sg:province":"Danmark",
    "sg:website":"www.rvt.dk",
    "wof:name":"RVT Revision Statsaut. Revisionsaktieselskab",
    "wof:placetype":"venue"
},
  "geometry": {"coordinates":[8.6355104446,56.3722801208],"type":"Point"}
}