{
  "type": "Feature",
  "properties": {
    "iso:country":"DK",
    "sg:address":"Fmd.: Elsebeth Millen Voxen, Godth\u00e5bsvej 65",
    "sg:city":"Skive",
    "sg:orig_category":"Hobbybetonede foreninger",
    "sg:phone":"+45 97 51 26 90",
    "sg:postcode":"7800",
    "sg:province":"Danmark",
    "wof:name":"Viborg V\u00e6verlaug",
    "wof:placetype":"venue"
},
  "geometry": {"coordinates":[9.0320358276,56.5666427612],"type":"Point"}
}