{
  "type": "Feature",
  "properties": {
    "iso:country":"DK",
    "sg:address":"Skolevej 1",
    "sg:city":"Hjerm",
    "sg:orig_category":"Tandklinikker, Kommunale",
    "sg:phone":"+45 97 46 47 85",
    "sg:postcode":"7560",
    "sg:province":"Danmark",
    "wof:name":"Hjerm Skoles Tandklinik",
    "wof:placetype":"venue"
},
  "geometry": {"coordinates":[8.6365776062,56.4382591248],"type":"Point"}
}