{
  "type": "Feature",
  "properties": {
    "addr:full":"Vestre Alle 5 Aalborg Danmark 9000",
    "addr:housenumber":"5",
    "addr:postcode":"9000",
    "addr:street":"Vestre Alle",
    "iso:country":"DK",
    "sg:address":"Vestre Alle 5",
    "sg:city":"Aalborg",
    "sg:orig_category":"Blomsterhandlere",
    "sg:phone":"+45 98 11 54 66",
    "sg:postcode":"9000",
    "sg:province":"Danmark",
    "wof:name":"Skipperens Blomster",
    "wof:placetype":"venue"
},
  "geometry": {"coordinates":[9.9073629379,57.0334281921],"type":"Point"}
}