{
  "type": "Feature",
  "properties": {
    "addr:full":"v/ Hans Hansen, Grindstedvej 22 A Billund Danmark 7190",
    "addr:housenumber":"22 a",
    "addr:postcode":"7190",
    "addr:street":"Grindstedvej",
    "iso:country":"DK",
    "sg:address":"v/ Hans Hansen, Grindstedvej 22 A",
    "sg:city":"Billund",
    "sg:orig_category":"Hobbybetonede foreninger",
    "sg:phone":"+45 75 33 22 29",
    "sg:postcode":"7190",
    "sg:province":"Danmark",
    "wof:name":"Grindsted og Omegns Biavlerforening",
    "wof:placetype":"venue"
},
  "geometry": {"coordinates":[9.1138372421,55.7316017151],"type":"Point"}
}