{
  "type": "Feature",
  "properties": {
    "addr:full":"Hovedgaden 39, Tornemark Sandved Danmark 4262",
    "addr:housenumber":"39",
    "addr:postcode":"4262",
    "addr:street":"Hovedgaden",
    "iso:country":"DK",
    "sg:address":"Hovedgaden 39, Tornemark",
    "sg:city":"Sandved",
    "sg:orig_category":"Maskinudlejning",
    "sg:phone":"+45 55 45 63 17",
    "sg:postcode":"4262",
    "sg:province":"Danmark",
    "wof:name":"Svendsen, Dan Terp",
    "wof:placetype":"venue"
},
  "geometry": {"coordinates":[11.5230302811,55.2632255554],"type":"Point"}
}