{
  "type": "Feature",
  "properties": {
    "iso:country":"DK",
    "sg:address":"Storegade 10",
    "sg:city":"Stege",
    "sg:classifiers":[
        {
            "category":"Restaurant",
            "type":"Food & Drink"
        }
    ],
    "sg:phone":"+45 55 81 81 90",
    "sg:postcode":"4780",
    "sg:province":"Danmark",
    "wof:name":"Delfino",
    "wof:placetype":"venue"
},
  "geometry": {"coordinates":[12.2836818695,54.9830818176],"type":"Point"}
}