{
  "type": "Feature",
  "properties": {
    "addr:full":"Skibstedvej 32, Skibsted Kongerslev Danmark 9293",
    "addr:housenumber":"32",
    "addr:postcode":"9293",
    "addr:street":"Skibstedvej",
    "iso:country":"DK",
    "sg:address":"Skibstedvej 32, Skibsted",
    "sg:city":"Kongerslev",
    "sg:orig_category":"Kirker",
    "sg:postcode":"9293",
    "sg:province":"Danmark",
    "wof:name":"Skibsted Kirke",
    "wof:placetype":"venue"
},
  "geometry": {"coordinates":[10.1150007248,56.8851165771],"type":"Point"}
}