{
  "type": "Feature",
  "properties": {
    "addr:full":"Kammersg\u00e5rdsvej 4, Ydby Hurup Danmark 7760",
    "addr:housenumber":"4",
    "addr:postcode":"7760",
    "addr:street":"Kammersgaardsvej;Ydby",
    "iso:country":"DK",
    "sg:address":"Kammersg\u00e5rdsvej 4, Ydby",
    "sg:city":"Hurup",
    "sg:orig_category":"Psykologer, praktiserende",
    "sg:phone":"+45 97 95 64 74",
    "sg:postcode":"7760",
    "sg:province":"Danmark",
    "wof:name":"Psykologerne Thy/Mors",
    "wof:placetype":"venue"
},
  "geometry": {"coordinates":[8.4233045578,56.7485847473],"type":"Point"}
}