{
  "type": "Feature",
  "properties": {
    "addr:full":"Marsvej 5 Hadsten Danmark 8370",
    "addr:housenumber":"5",
    "addr:postcode":"8370",
    "addr:street":"Marsvej",
    "iso:country":"DK",
    "sg:address":"Marsvej 5",
    "sg:city":"Hadsten",
    "sg:orig_category":"Engros handel",
    "sg:phone":"+45 86 98 18 98",
    "sg:postcode":"8370",
    "sg:province":"Danmark",
    "wof:name":"I J Handel ApS",
    "wof:placetype":"venue"
},
  "geometry": {"coordinates":[10.0331325531,56.3245010376],"type":"Point"}
}