{
  "type": "Feature",
  "properties": {
    "iso:country":"DK",
    "sg:address":"Herredsvej 45",
    "sg:city":"Vamdrup",
    "sg:orig_category":"Skolefritidsordninger",
    "sg:phone":"+45 75 58 34 66",
    "sg:postcode":"6580",
    "sg:province":"Danmark",
    "wof:name":"Vester Vamdrup Skole",
    "wof:placetype":"venue"
},
  "geometry": {"coordinates":[9.2766122818,55.4288330078],"type":"Point"}
}