{
  "type": "Feature",
  "properties": {
    "addr:full":"Nytorv 2 Sk\u00e6lsk\u00f8r Danmark 4230",
    "addr:housenumber":"2",
    "addr:postcode":"4230",
    "addr:street":"Nytorv",
    "iso:country":"DK",
    "sg:address":"Nytorv 2",
    "sg:city":"Sk\u00e6lsk\u00f8r",
    "sg:orig_category":"Ejendomshandel",
    "sg:phone":"+45 58 19 02 68",
    "sg:postcode":"4230",
    "sg:province":"Danmark",
    "sg:website":"www.home.dk",
    "wof:name":"home",
    "wof:placetype":"venue"
},
  "geometry": {"coordinates":[11.1915035248,55.2119750977],"type":"Point"}
}