{
  "type": "Feature",
  "properties": {
    "addr:full":"Fmd.: C. Hebel, Gieseg\u00e5rdsvej 26 Hvidovre Danmark 2650",
    "addr:housenumber":"26",
    "addr:postcode":"2650",
    "addr:street":"Giesegaardsvej",
    "iso:country":"DK",
    "sg:address":"Fmd.: C. Hebel, Gieseg\u00e5rdsvej 26",
    "sg:city":"Hvidovre",
    "sg:orig_category":"Grundejerforeninger",
    "sg:phone":"+45 36 49 96 52",
    "sg:postcode":"2650",
    "sg:province":"Danmark",
    "wof:name":"Gieseg\u00e5rd Grundejerforening",
    "wof:placetype":"venue"
},
  "geometry": {"coordinates":[12.474360466,55.6366386414],"type":"Point"}
}