{
  "type": "Feature",
  "properties": {
    "addr:full":"H\u00e6rvejen 87 F R\u00f8dekro Danmark 6230",
    "addr:housenumber":"87 f",
    "addr:postcode":"6230",
    "addr:street":"Haervejen;Rodekro Danmark",
    "iso:country":"DK",
    "sg:address":"H\u00e6rvejen 87 F",
    "sg:city":"R\u00f8dekro",
    "sg:classifiers":[
        {
            "category":"Taxi",
            "type":"Transportation"
        }
    ],
    "sg:phone":"+45 74 66 20 09",
    "sg:postcode":"6230",
    "sg:province":"Danmark",
    "wof:name":"H\u00f8eg's Taxa",
    "wof:placetype":"venue"
},
  "geometry": {"coordinates":[-59.9538612366,-24.6677494049],"type":"Point"}
}