{
  "type": "Feature",
  "properties": {
    "addr:full":"Norgesvej 5 Haderslev Danmark 6100",
    "addr:housenumber":"5",
    "addr:postcode":"6100",
    "addr:street":"Norgesvej",
    "iso:country":"DK",
    "sg:address":"Norgesvej 5",
    "sg:city":"Haderslev",
    "sg:orig_category":"Bilinspektion",
    "sg:phone":"+45 74 52 12 15",
    "sg:postcode":"6100",
    "sg:province":"Danmark",
    "sg:website":"www.bilsyn.dk",
    "wof:name":"Statens Bilinspektion",
    "wof:placetype":"venue"
},
  "geometry": {"coordinates":[9.475007,55.262737],"type":"Point"}
}