{
  "type": "Feature",
  "properties": {
    "addr:full":"Kettevej 3 Hvidovre Danmark 2650",
    "addr:housenumber":"3",
    "addr:postcode":"2650",
    "addr:street":"Kettevej",
    "iso:country":"DK",
    "sg:address":"Kettevej 3",
    "sg:city":"Hvidovre",
    "sg:classifiers":[
        {
            "category":"Restaurant",
            "type":"Food & Drink"
        }
    ],
    "sg:phone":"+45 36 77 00 82",
    "sg:postcode":"2650",
    "sg:province":"Danmark",
    "wof:name":"Mc Donald's",
    "wof:placetype":"venue"
},
  "geometry": {"coordinates":[12.460351944,55.6450920105],"type":"Point"}
}