{
  "type": "Feature",
  "properties": {
    "iso:country":"DK",
    "sg:address":"v/Ib Hejnfelt, Bramdrup Vestergade 2",
    "sg:city":"Haderslev",
    "sg:orig_category":"Borger- og beboerforeninger",
    "sg:phone":"+45 74 53 49 28",
    "sg:postcode":"6100",
    "sg:province":"Danmark",
    "wof:name":"Moltrup Sogneforening",
    "wof:placetype":"venue"
},
  "geometry": {"coordinates":[9.4879703522,55.2505493164],"type":"Point"}
}