{
  "type": "Feature",
  "properties": {
    "addr:full":"Ungdomsskoleinspekt\u00f8r: Andrea T\u00f8nder, Skolegade 2 Br\u00f8rup Danmark 6650",
    "addr:housenumber":"2",
    "addr:postcode":"6650",
    "addr:street":"Skolegade",
    "iso:country":"DK",
    "sg:address":"Ungdomsskoleinspekt\u00f8r: Andrea T\u00f8nder, Skolegade 2",
    "sg:city":"Br\u00f8rup",
    "sg:orig_category":"Kommunale ungdomsskoler",
    "sg:phone":"+45 75 38 18 69",
    "sg:postcode":"6650",
    "sg:province":"Danmark",
    "sg:website":"www.ungbr.dk",
    "wof:name":"Br\u00f8rup Ungdomsskole",
    "wof:placetype":"venue"
},
  "geometry": {"coordinates":[-93.1630935669,32.8507347107],"type":"Point"}
}