{
  "type": "Feature",
  "properties": {
    "iso:country":"DK",
    "sg:address":"Sundbjergvej 4, Diern\u00e6s",
    "sg:city":"Faaborg",
    "sg:orig_category":"Malermestre",
    "sg:phone":"+45 62 61 30 69",
    "sg:postcode":"5600",
    "sg:province":"Danmark",
    "wof:name":"Kristensen, Carsten",
    "wof:placetype":"venue"
},
  "geometry": {"coordinates":[10.2400531769,55.0950622559],"type":"Point"}
}