{
  "type": "Feature",
  "properties": {
    "addr:full":"Langebjergv\u00e6nget 14 Roskilde Danmark 4000",
    "addr:housenumber":"14",
    "addr:postcode":"4000",
    "addr:street":"Langebjergvaenget",
    "iso:country":"DK",
    "sg:address":"Langebjergv\u00e6nget 14",
    "sg:city":"Roskilde",
    "sg:orig_category":"Bogtrykkerier",
    "sg:phone":"+45 46 75 64 64",
    "sg:postcode":"4000",
    "sg:province":"Danmark",
    "wof:name":"Gr\u00f8nagers Grafisk Produktion",
    "wof:placetype":"venue"
},
  "geometry": {"coordinates":[12.1425962448,55.6471214294],"type":"Point"}
}