{
  "type": "Feature",
  "properties": {
    "addr:full":"\u00d8stergade 69 Hadsund Danmark 9560",
    "addr:housenumber":"69",
    "addr:postcode":"9560",
    "addr:street":"Ostergade",
    "iso:country":"DK",
    "sg:address":"\u00d8stergade 69",
    "sg:city":"Hadsund",
    "sg:orig_category":"Maskinfabrikker",
    "sg:phone":"+45 98 57 18 22",
    "sg:postcode":"9560",
    "sg:province":"Danmark",
    "wof:name":"Aagaard",
    "wof:placetype":"venue"
},
  "geometry": {"coordinates":[10.1234531403,56.7231826782],"type":"Point"}
}