{
  "type": "Feature",
  "properties": {
    "addr:full":"Kastanie Alle 2 Augustenborg Danmark 6440",
    "addr:housenumber":"2",
    "addr:postcode":"6440",
    "addr:street":"Kastanie Alle",
    "iso:country":"DK",
    "sg:address":"Kastanie Alle 2",
    "sg:city":"Augustenborg",
    "sg:orig_category":"Arkitekter",
    "sg:phone":"+45 74 47 14 03",
    "sg:postcode":"6440",
    "sg:province":"Danmark",
    "wof:name":"Arkitekttegnestuen Augustenborg A/S",
    "wof:placetype":"venue"
},
  "geometry": {"coordinates":[9.8764038086,54.9470596313],"type":"Point"}
}