{
  "type": "Feature",
  "properties": {
    "addr:full":"Industrivej 35 A Ribe Danmark 6760",
    "addr:housenumber":"35 a",
    "addr:postcode":"6760",
    "addr:street":"Industrivej",
    "iso:country":"DK",
    "sg:address":"Industrivej 35 A",
    "sg:city":"Ribe",
    "sg:orig_category":"Autoopretning",
    "sg:phone":"+45 75 42 31 56",
    "sg:postcode":"6760",
    "sg:province":"Danmark",
    "wof:name":"Ribe Karossericenter",
    "wof:placetype":"venue"
},
  "geometry": {"coordinates":[8.7758741379,55.3519363403],"type":"Point"}
}