{
  "type": "Feature",
  "properties": {
    "addr:full":"\u00d8ster Uttrup Vej 1  Aalborg Danmark 9000",
    "addr:housenumber":"1",
    "addr:postcode":"9000",
    "addr:street":"Uttrup Vej",
    "iso:country":"DK",
    "sg:address":"\u00d8ster Uttrup Vej 1 ",
    "sg:city":"Aalborg",
    "sg:classifiers":[
        {
            "category":"Professional",
            "subcategory":"Business Services",
            "type":"Services"
        }
    ],
    "sg:phone":"+45 99 33 11 11",
    "sg:postcode":"9000",
    "sg:province":"Danmark",
    "sg:tags":[
        "advice"
    ],
    "wof:name":"AALBORG TEKNISKE SKOLE",
    "wof:placetype":"venue"
},
  "geometry": {"coordinates":[9.9662179947,57.0481529236],"type":"Point"}
}