{
  "type": "Feature",
  "properties": {
    "addr:full":"Kongensgade 17 Christiansfeld Danmark 6070",
    "addr:housenumber":"17",
    "addr:postcode":"6070",
    "addr:street":"Kongensgade",
    "iso:country":"DK",
    "sg:address":"Kongensgade 17",
    "sg:city":"Christiansfeld",
    "sg:orig_category":"Keramik",
    "sg:phone":"+45 74 56 14 47",
    "sg:postcode":"6070",
    "sg:province":"Danmark",
    "wof:name":"Hansen, Birte Bentzon",
    "wof:placetype":"venue"
},
  "geometry": {"coordinates":[9.482998848,55.3567810059],"type":"Point"}
}