{
  "type": "Feature",
  "properties": {
    "addr:full":"\u00c5sbjerg 23 Give Danmark 7323",
    "addr:housenumber":"23",
    "addr:postcode":"7323",
    "addr:street":"Aasbjerg",
    "iso:country":"DK",
    "sg:address":"\u00c5sbjerg 23",
    "sg:city":"Give",
    "sg:classifiers":[
        {
            "category":"Personal",
            "subcategory":"Massage",
            "type":"Services"
        }
    ],
    "sg:phone":"+45 75 73 23 53",
    "sg:postcode":"7323",
    "sg:province":"Danmark",
    "wof:name":"Body Comfort",
    "wof:placetype":"venue"
},
  "geometry": {"coordinates":[9.3323812485,55.8909187317],"type":"Point"}
}