{
  "type": "Feature",
  "properties": {
    "addr:full":"Enghave Plads 9 st. K\u00f8benhavn Danmark 1670",
    "addr:housenumber":"9;1670",
    "addr:street":"Enghave Plads",
    "iso:country":"DK",
    "sg:address":"Enghave Plads 9 st.",
    "sg:city":"K\u00f8benhavn",
    "sg:classifiers":[
        {
            "category":"Restaurant",
            "type":"Food & Drink"
        }
    ],
    "sg:phone":"+45 33 31 84 19",
    "sg:postcode":"1670",
    "sg:province":"Danmark",
    "wof:name":"Oonas K\u00f8kken & Koktail",
    "wof:placetype":"venue"
},
  "geometry": {"coordinates":[12.5459003448,55.6660003662],"type":"Point"}
}