{
  "type": "Feature",
  "properties": {
    "addr:full":"Hjaltesvej 15 Randers Danmark 8900",
    "addr:housenumber":"15",
    "addr:postcode":"8900",
    "addr:street":"Hjaltesvej",
    "iso:country":"DK",
    "sg:address":"Hjaltesvej 15",
    "sg:city":"Randers",
    "sg:orig_category":"Maskinfabrikker",
    "sg:phone":"+45 86 43 34 88",
    "sg:postcode":"8900",
    "sg:province":"Danmark",
    "wof:name":"Lanng Maskinindustri ApS, J\u00f8rgen M.",
    "wof:placetype":"venue"
},
  "geometry": {"coordinates":[10.0733327866,56.4415626526],"type":"Point"}
}