{
  "type": "Feature",
  "properties": {
    "addr:full":"Frederiksgade 58 \u00c5rhus C Danmark 8000",
    "addr:housenumber":"58",
    "addr:postcode":"8000",
    "addr:street":"Frederiksgade",
    "iso:country":"DK",
    "sg:address":"Frederiksgade 58",
    "sg:city":"\u00c5rhus C",
    "sg:orig_category":"Sko",
    "sg:phone":"+45 86 20 29 22",
    "sg:postcode":"8000",
    "sg:province":"Danmark",
    "wof:name":"Shoe Collection",
    "wof:placetype":"venue"
},
  "geometry": {"coordinates":[10.204249382,56.1549110413],"type":"Point"}
}