{
  "type": "Feature",
  "properties": {
    "addr:full":"\u00d8stergade 17 Auning Danmark 8963",
    "addr:housenumber":"17",
    "addr:postcode":"8963",
    "addr:street":"Ostergade",
    "iso:country":"DK",
    "sg:address":"\u00d8stergade 17",
    "sg:city":"Auning",
    "sg:orig_category":"Genbrugsbutikker",
    "sg:phone":"+45 86 43 91 90",
    "sg:postcode":"8963",
    "sg:province":"Danmark",
    "wof:name":"Kirkens Korsh\u00e6r",
    "wof:placetype":"venue"
},
  "geometry": {"coordinates":[10.3797130585,56.4299697876],"type":"Point"}
}