{
  "type": "Feature",
  "properties": {
    "addr:full":"Svends Alle 40 Kongens Lyngby Danmark 2800",
    "addr:housenumber":"40",
    "addr:postcode":"2800",
    "addr:street":"Svends Alle",
    "iso:country":"DK",
    "sg:address":"Svends Alle 40",
    "sg:city":"Kongens Lyngby",
    "sg:orig_category":"Emballage",
    "sg:phone":"+45 44 44 77 43",
    "sg:postcode":"2800",
    "sg:province":"Danmark",
    "wof:name":"\u00d8sdal",
    "wof:placetype":"venue"
},
  "geometry": {"coordinates":[12.4851236343,55.7525215149],"type":"Point"}
}