{
  "type": "Feature",
  "properties": {
    "iso:country":"DK",
    "sg:address":"Bl\u00e5klokkevej 75, Dyrup",
    "sg:city":"Odense SV",
    "sg:orig_category":"Bladmontage",
    "sg:phone":"+45 66 17 50 99",
    "sg:postcode":"5250",
    "sg:province":"Danmark",
    "wof:name":"Informationsbladet af 1993",
    "wof:placetype":"venue"
},
  "geometry": {"coordinates":[10.315395,55.3363],"type":"Point"}
}