{
  "type": "Feature",
  "properties": {
    "addr:full":"Kildehusvej 35 Randers Danmark 8900",
    "addr:housenumber":"35",
    "addr:postcode":"8900",
    "addr:street":"Kildehusvej",
    "iso:country":"DK",
    "sg:address":"Kildehusvej 35",
    "sg:city":"Randers",
    "sg:orig_category":"Maskinfabrikker",
    "sg:phone":"+45 86 42 08 38",
    "sg:postcode":"8900",
    "sg:province":"Danmark",
    "wof:name":"Munksgaard-Nielsen Maskinfabrik, O.",
    "wof:placetype":"venue"
},
  "geometry": {"coordinates":[9.9954080582,56.4324913025],"type":"Point"}
}