{
  "type": "Feature",
  "properties": {
    "iso:country":"DK",
    "sg:address":"Kongensgade 10 A",
    "sg:city":"Slangerup",
    "sg:classifiers":[
        {
            "category":"Banks & Credit Unions",
            "subcategory":"Bank",
            "type":"Services"
        }
    ],
    "sg:phone":"+45 47 33 77 00",
    "sg:postcode":"3550",
    "sg:province":"Danmark",
    "sg:tags":[
        "banker"
    ],
    "wof:name":"Lokalbanken i Slangerup",
    "wof:placetype":"venue"
},
  "geometry": {"coordinates":[12.172228,55.845467],"type":"Point"}
}