{
  "type": "Feature",
  "properties": {
    "iso:country":"DK",
    "sg:address":"Floravej 12, Dr\u00e5by",
    "sg:city":"Ebeltoft",
    "sg:orig_category":"Vejledningscentre",
    "sg:phone":"+45 86 34 02 49",
    "sg:postcode":"8400",
    "sg:province":"Danmark",
    "wof:name":"Ejleb\u00e6k - \u00d8kologi & Ern\u00e6ring",
    "wof:placetype":"venue"
},
  "geometry": {"coordinates":[10.6778745651,56.199798584],"type":"Point"}
}