{
  "type": "Feature",
  "properties": {
    "addr:full":"Fyrrevej 1, S\u00f8rup Fredensborg Danmark 3480",
    "addr:housenumber":"1",
    "addr:postcode":"3480",
    "addr:street":"Fyrrevej",
    "iso:country":"DK",
    "sg:address":"Fyrrevej 1, S\u00f8rup",
    "sg:city":"Fredensborg",
    "sg:orig_category":"Revisorer",
    "sg:phone":"+45 48 48 18 60",
    "sg:postcode":"3480",
    "sg:province":"Danmark",
    "wof:name":"Just HD, Svend E.",
    "wof:placetype":"venue"
},
  "geometry": {"coordinates":[12.4020547867,55.9782943726],"type":"Point"}
}