{
  "type": "Feature",
  "properties": {
    "iso:country":"DK",
    "sg:address":"Hovedgaden 2 D",
    "sg:city":"Skibby",
    "sg:orig_category":"Glarmestre og glarmagere",
    "sg:phone":"+45 47 52 70 66",
    "sg:postcode":"4050",
    "sg:province":"Danmark",
    "wof:name":"Skibby Glarmesteren",
    "wof:placetype":"venue"
},
  "geometry": {"coordinates":[11.9573469162,55.7587356567],"type":"Point"}
}