{
  "type": "Feature",
  "properties": {
    "addr:full":"Terslev Skolevej 15 Haslev Danmark 4690",
    "addr:housenumber":"15",
    "addr:postcode":"4690",
    "addr:street":"Terslev Skolevej",
    "iso:country":"DK",
    "sg:address":"Terslev Skolevej 15",
    "sg:city":"Haslev",
    "sg:orig_category":"Hundepsykologer",
    "sg:phone":"+45 56 38 18 80",
    "sg:postcode":"4690",
    "sg:province":"Danmark",
    "sg:website":"www.hundeadfaerdsspecialist.dk",
    "wof:name":"Hundeadf\u00e6rdsspecialisten",
    "wof:placetype":"venue"
},
  "geometry": {"coordinates":[11.9791488647,55.3653907776],"type":"Point"}
}