{
  "type": "Feature",
  "properties": {
    "addr:full":"Fmd.: Ingerlise Hein, Filtenborggade 7 Nyk\u00f8bing Danmark 7900",
    "addr:housenumber":"7",
    "addr:postcode":"7900",
    "addr:street":"Filtenborggade",
    "iso:country":"DK",
    "sg:address":"Fmd.: Ingerlise Hein, Filtenborggade 7",
    "sg:city":"Nyk\u00f8bing",
    "sg:orig_category":"Hobbybetonede foreninger",
    "sg:phone":"+45 97 71 09 12",
    "sg:postcode":"7900",
    "sg:province":"Danmark",
    "wof:name":"Danmarks Civile Hundef\u00f8rerforening, Mors\u00f8 Afdeling",
    "wof:placetype":"venue"
},
  "geometry": {"coordinates":[-114.0768203735,46.4432411194],"type":"Point"}
}