{
  "type": "Feature",
  "properties": {
    "addr:full":"Fmd.: Olav Christensen, Kirkevej 2 B Vemmelev Danmark 4241",
    "addr:housenumber":"2 b",
    "addr:postcode":"4241",
    "addr:street":"Olav Christensen Kirkevej",
    "iso:country":"DK",
    "sg:address":"Fmd.: Olav Christensen, Kirkevej 2 B",
    "sg:city":"Vemmelev",
    "sg:orig_category":"Faglige organisationer og foreninger",
    "sg:phone":"+45 58 38 23 75",
    "sg:postcode":"4241",
    "sg:province":"Danmark",
    "wof:name":"Lokalforeningen af Frie B\u00f8rnehaver og Fritidshjem",
    "wof:placetype":"venue"
},
  "geometry": {"coordinates":[11.2580623627,55.363407135],"type":"Point"}
}