{
  "type": "Feature",
  "properties": {
    "addr:full":"Skibbrogade 43 Kalundborg Danmark 4400",
    "addr:housenumber":"43",
    "addr:postcode":"4400",
    "addr:street":"Skibbrogade",
    "iso:country":"DK",
    "sg:address":"Skibbrogade 43",
    "sg:city":"Kalundborg",
    "sg:orig_category":"Spilleautomater",
    "sg:phone":"+45 59 51 14 19",
    "sg:postcode":"4400",
    "sg:province":"Danmark",
    "wof:name":"Spillehallen",
    "wof:placetype":"venue"
},
  "geometry": {"coordinates":[11.0866346359,55.6800422668],"type":"Point"}
}