{
  "type": "Feature",
  "properties": {
    "addr:full":"Hovborgvej 6 Grindsted Danmark 7200",
    "addr:housenumber":"6",
    "addr:postcode":"7200",
    "addr:street":"Hovborgvej",
    "iso:country":"DK",
    "sg:address":"Hovborgvej 6",
    "sg:city":"Grindsted",
    "sg:orig_category":"Pizzeriaer",
    "sg:phone":"+45 75 33 78 78",
    "sg:postcode":"7200",
    "sg:province":"Danmark",
    "wof:name":"Milano's Pizzaria",
    "wof:placetype":"venue"
},
  "geometry": {"coordinates":[8.8136367798,55.6485176086],"type":"Point"}
}