{
  "type": "Feature",
  "properties": {
    "addr:full":"Mester Eriks Vej 85 Aalborg Danmark 9000",
    "addr:housenumber":"85",
    "addr:postcode":"9000",
    "addr:street":"Mester Eriks Vej",
    "iso:country":"DK",
    "sg:address":"Mester Eriks Vej 85",
    "sg:city":"Aalborg",
    "sg:orig_category":"Tandklinikker, Kommunale",
    "sg:phone":"+45 98 18 51 91",
    "sg:postcode":"9000",
    "sg:province":"Danmark",
    "wof:name":"Tandklinikken ved Gl. Hasseris Skole",
    "wof:placetype":"venue"
},
  "geometry": {"coordinates":[9.8703279495,57.0340995789],"type":"Point"}
}