{
  "type": "Feature",
  "properties": {
    "iso:country":"DK",
    "sg:address":"Hadsundvej 39",
    "sg:city":"Aalborg",
    "sg:classifiers":[
        {
            "category":"Banks & Credit Unions",
            "subcategory":"Bank",
            "type":"Services"
        }
    ],
    "sg:phone":"+45 98 13 05 77",
    "sg:postcode":"9000",
    "sg:province":"Danmark",
    "sg:tags":[
        "banker"
    ],
    "wof:name":"Arbejdernes Landsbank A/S",
    "wof:placetype":"venue"
},
  "geometry": {"coordinates":[9.951811,57.041042],"type":"Point"}
}