{
  "type": "Feature",
  "properties": {
    "addr:full":"Vester Farimagsgade 7, 6. K\u00f8benhavn Danmark 1606",
    "addr:housenumber":"7 6",
    "addr:postcode":"1606",
    "addr:street":"Vester Farimagsgade",
    "iso:country":"DK",
    "sg:address":"Vester Farimagsgade 7, 6.",
    "sg:city":"K\u00f8benhavn",
    "sg:orig_category":"Flyvning",
    "sg:phone":"+45 33 12 04 44",
    "sg:postcode":"1606",
    "sg:province":"Danmark",
    "wof:name":"Ceskoslovensk\u00e9 Aerolinie",
    "wof:placetype":"venue"
},
  "geometry": {"coordinates":[12.5636997223,55.6749992371],"type":"Point"}
}