{
  "type": "Feature",
  "properties": {
    "iso:country":"DK",
    "sg:address":"Bredvigvej 16, S\u00f8nderby",
    "sg:city":"Skibby",
    "sg:orig_category":"Liftudlejning",
    "sg:phone":"+45 47 52 00 92",
    "sg:postcode":"4050",
    "sg:province":"Danmark",
    "wof:name":"Buer's Liftudlejning",
    "wof:placetype":"venue"
},
  "geometry": {"coordinates":[11.9594116211,55.7502975464],"type":"Point"}
}