{
  "type": "Feature",
  "properties": {
    "addr:full":"K\u00e6rlund 2 Hirtshals Danmark 9850",
    "addr:housenumber":"2",
    "addr:postcode":"9850",
    "addr:street":"Kaerlund",
    "iso:country":"DK",
    "sg:address":"K\u00e6rlund 2",
    "sg:city":"Hirtshals",
    "sg:classifiers":[
        {
            "category":"Professional",
            "subcategory":"Computer Services",
            "type":"Services"
        }
    ],
    "sg:phone":"+45 98 94 18 66",
    "sg:postcode":"9850",
    "sg:province":"Danmark",
    "sg:tags":[
        "edb",
        "-",
        "software"
    ],
    "wof:name":"Jensen-Com",
    "wof:placetype":"venue"
},
  "geometry": {"coordinates":[9.9628448486,57.571849823],"type":"Point"}
}