{
  "type": "Feature",
  "properties": {
    "addr:full":"Havnegade 14 Lemvig Danmark 7620",
    "addr:housenumber":"14",
    "addr:postcode":"7620",
    "addr:street":"Havnegade",
    "iso:country":"DK",
    "sg:address":"Havnegade 14",
    "sg:city":"Lemvig",
    "sg:orig_category":"Havne",
    "sg:phone":"+45 97 82 01 06",
    "sg:postcode":"7620",
    "sg:province":"Danmark",
    "wof:name":"Havnekontoret",
    "wof:placetype":"venue"
},
  "geometry": {"coordinates":[8.3072681427,56.5503845215],"type":"Point"}
}