{
  "type": "Feature",
  "properties": {
    "addr:full":"Havnegade 2 Nakskov Danmark 4900",
    "addr:housenumber":"2",
    "addr:postcode":"4900",
    "addr:street":"Havnegade",
    "iso:country":"DK",
    "sg:address":"Havnegade 2",
    "sg:city":"Nakskov",
    "sg:orig_category":"Faglige organisationer og foreninger",
    "sg:postcode":"4900",
    "sg:province":"Danmark",
    "wof:name":"Senior Malerne, Nakskov",
    "wof:placetype":"venue"
},
  "geometry": {"coordinates":[11.1314439774,54.8308792114],"type":"Point"}
}