{
  "type": "Feature",
  "properties": {
    "iso:country":"DK",
    "sg:address":"Kjeldg\u00e5rdsvej 2 ",
    "sg:city":"S\u00e6by",
    "sg:classifiers":[
        {
            "category":"Shopping",
            "subcategory":"Clothing, Apparel, & Fashions",
            "type":"Retail Goods"
        }
    ],
    "sg:phone":"+45 98 46 30 00",
    "sg:postcode":"9300",
    "sg:province":"Danmark",
    "sg:tags":[
        "clothes"
    ],
    "wof:name":"BRYNJE A/S",
    "wof:placetype":"venue"
},
  "geometry": {"coordinates":[-78.0637512207,43.0498466492],"type":"Point"}
}