{
  "type": "Feature",
  "properties": {
    "addr:full":"Literbuen 1 Skovlunde Danmark 2740",
    "addr:housenumber":"1",
    "addr:postcode":"2740",
    "addr:street":"Literbuen",
    "iso:country":"DK",
    "sg:address":"Literbuen 1",
    "sg:city":"Skovlunde",
    "sg:classifiers":[
        {
            "category":"Harbor",
            "type":"Transportation"
        }
    ],
    "sg:phone":"+45 44 57 05 70",
    "sg:postcode":"2740",
    "sg:province":"Danmark",
    "sg:tags":[
        "shipping"
    ],
    "wof:name":"Blue Water Shipping A/S",
    "wof:placetype":"venue"
},
  "geometry": {"coordinates":[12.4232625961,55.7167167664],"type":"Point"}
}