{
  "type": "Feature",
  "properties": {
    "iso:country":"DK",
    "sg:address":"S\u00f8nderballevej 3",
    "sg:city":"Skals",
    "sg:orig_category":"Hudpleje",
    "sg:phone":"+45 86 69 52 44",
    "sg:postcode":"8832",
    "sg:province":"Danmark",
    "wof:name":"Bodil's Hudplejeklinik",
    "wof:placetype":"venue"
},
  "geometry": {"coordinates":[9.4017238617,56.5547103882],"type":"Point"}
}