{
  "type": "Feature",
  "properties": {
    "iso:country":"DK",
    "sg:address":"Fabersvej 43",
    "sg:city":"Randers",
    "sg:orig_category":"Kirker",
    "sg:postcode":"8900",
    "sg:province":"Danmark",
    "wof:name":"Sct. Peders Kirke",
    "wof:placetype":"venue"
},
  "geometry": {"coordinates":[10.0312261581,56.465549469],"type":"Point"}
}