{
  "type": "Feature",
  "properties": {
    "addr:full":"N\u00f8rreskovparken 105 Aabenraa Danmark 6200",
    "addr:housenumber":"105",
    "addr:postcode":"6200",
    "addr:street":"Norreskovparken",
    "iso:country":"DK",
    "sg:address":"N\u00f8rreskovparken 105",
    "sg:city":"Aabenraa",
    "sg:orig_category":"Fodterapeuter",
    "sg:phone":"+45 74 62 70 30",
    "sg:postcode":"6200",
    "sg:province":"Danmark",
    "wof:name":"Klinik for fodterapi",
    "wof:placetype":"venue"
},
  "geometry": {"coordinates":[9.4094209671,55.0575141907],"type":"Point"}
}