{
  "type": "Feature",
  "properties": {
    "addr:full":"Centervej 5, Bramdrupdam Kolding Danmark 6000",
    "addr:housenumber":"5",
    "addr:postcode":"6000",
    "addr:street":"Centervej",
    "iso:country":"DK",
    "sg:address":"Centervej 5, Bramdrupdam",
    "sg:city":"Kolding",
    "sg:orig_category":"Brugsforeninger",
    "sg:phone":"+45 75 56 82 77",
    "sg:postcode":"6000",
    "sg:province":"Danmark",
    "wof:name":"Super Brugsen",
    "wof:placetype":"venue"
},
  "geometry": {"coordinates":[9.4733953476,55.4863586426],"type":"Point"}
}