{
  "type": "Feature",
  "properties": {
    "addr:full":"Ringvejen 30 Arden Danmark 9510",
    "addr:housenumber":"30",
    "addr:postcode":"9510",
    "addr:street":"Ringvejen",
    "iso:country":"DK",
    "sg:address":"Ringvejen 30",
    "sg:city":"Arden",
    "sg:orig_category":"Transport",
    "sg:phone":"+45 98 56 14 55",
    "sg:postcode":"9510",
    "sg:province":"Danmark",
    "sg:website":"www.ats-arden.dk",
    "wof:name":"Arden Transport & Spedition",
    "wof:placetype":"venue"
},
  "geometry": {"coordinates":[9.8425512314,56.7622413635],"type":"Point"}
}