{
  "type": "Feature",
  "properties": {
    "addr:full":"Fmd.: Ib Holeby, Axel Meiersvej 12 Greve Danmark 2670",
    "addr:housenumber":"12",
    "addr:postcode":"2670",
    "addr:street":"Axel Meiersvej",
    "iso:country":"DK",
    "sg:address":"Fmd.: Ib Holeby, Axel Meiersvej 12",
    "sg:city":"Greve",
    "sg:orig_category":"Grundejerforeninger",
    "sg:phone":"+45 43 90 23 46",
    "sg:postcode":"2670",
    "sg:province":"Danmark",
    "wof:name":"Sammeslutning af Grundejere p\u00e5 \u00d8ren-, Niels Juels-, Marie-, Lyng- og Axel Meiers",
    "wof:placetype":"venue"
},
  "geometry": {"coordinates":[12.2941808701,55.5844078064],"type":"Point"}
}