{
  "type": "Feature",
  "properties": {
    "addr:full":"Torvegade 2 \u00d8stermarie Danmark 3751",
    "addr:housenumber":"2",
    "addr:postcode":"3751",
    "addr:street":"Torvegade",
    "iso:country":"DK",
    "sg:address":"Torvegade 2",
    "sg:city":"\u00d8stermarie",
    "sg:orig_category":"Korn og foderstoffer",
    "sg:phone":"+45 56 47 01 27",
    "sg:postcode":"3751",
    "sg:province":"Danmark",
    "wof:name":"BAF \u00d8stermarie Afdeling",
    "wof:placetype":"venue"
},
  "geometry": {"coordinates":[15.009560585,55.1418075562],"type":"Point"}
}