{
  "type": "Feature",
  "properties": {
    "addr:full":"Gl Skolevej 29, Uggerslev Otterup Danmark 5450",
    "addr:housenumber":"29",
    "addr:postcode":"5450",
    "addr:street":"Gl Skolevej",
    "iso:country":"DK",
    "sg:address":"Gl Skolevej 29, Uggerslev",
    "sg:city":"Otterup",
    "sg:orig_category":"Oliefyr og service",
    "sg:phone":"+45 64 85 12 24",
    "sg:postcode":"5450",
    "sg:province":"Danmark",
    "wof:name":"Uggerslev Oliefyrservice",
    "wof:placetype":"venue"
},
  "geometry": {"coordinates":[10.4545049667,55.5641746521],"type":"Point"}
}