{
  "type": "Feature",
  "properties": {
    "addr:full":"S\u00f8ndre Fasanvej 99 Valby Danmark 2500",
    "addr:housenumber":"99",
    "addr:postcode":"2500",
    "addr:street":"Sondre Fasanvej",
    "iso:country":"DK",
    "sg:address":"S\u00f8ndre Fasanvej 99",
    "sg:city":"Valby",
    "sg:orig_category":"Advokater",
    "sg:phone":"+45 36 46 65 00",
    "sg:postcode":"2500",
    "sg:province":"Danmark",
    "wof:name":"Urs\u00f8, M.C.",
    "wof:placetype":"venue"
},
  "geometry": {"coordinates":[12.517367363,55.6667556763],"type":"Point"}
}