{
  "type": "Feature",
  "properties": {
    "addr:full":"Fmd.: Metha Kristiansen, M\u00f8llegade 25 Holsted Danmark 6670",
    "addr:housenumber":"25",
    "addr:postcode":"6670",
    "addr:street":"Mollegade",
    "iso:country":"DK",
    "sg:address":"Fmd.: Metha Kristiansen, M\u00f8llegade 25",
    "sg:city":"Holsted",
    "sg:orig_category":"Husflidsforeninger",
    "sg:phone":"+45 75 39 28 85",
    "sg:postcode":"6670",
    "sg:province":"Danmark",
    "wof:name":"Tirslund Husholdningsforening",
    "wof:placetype":"venue"
},
  "geometry": {"coordinates":[8.9169273376,55.5111999512],"type":"Point"}
}