{
  "type": "Feature",
  "properties": {
    "addr:full":"Hessgade 2 Middelfart Danmark 5500",
    "addr:housenumber":"2",
    "addr:postcode":"5500",
    "addr:street":"Hessgade",
    "iso:country":"DK",
    "sg:address":"Hessgade 2",
    "sg:city":"Middelfart",
    "sg:orig_category":"Servicestationer",
    "sg:phone":"+45 64 41 22 64",
    "sg:postcode":"5500",
    "sg:province":"Danmark",
    "wof:name":"Shell Service",
    "wof:placetype":"venue"
},
  "geometry": {"coordinates":[9.727891922,55.5040588379],"type":"Point"}
}