{
  "type": "Feature",
  "properties": {
    "addr:full":"Hovvej 37 A, Ubby Jerslev Sj\u00e6lland Danmark 4490",
    "addr:housenumber":"37 a",
    "addr:postcode":"4490",
    "addr:street":"Hovvej;Ubby Jerslev Sjaelland Danmark",
    "iso:country":"DK",
    "sg:address":"Hovvej 37 A, Ubby",
    "sg:city":"Jerslev Sj\u00e6lland",
    "sg:orig_category":"Varmeforsyning",
    "sg:phone":"+45 59 59 56 38",
    "sg:postcode":"4490",
    "sg:province":"Danmark",
    "wof:name":"Hvideb\u00e6k Fjernvarmeforsyning A.M.B.A.",
    "wof:placetype":"venue"
},
  "geometry": {"coordinates":[11.213265419,55.619178772],"type":"Point"}
}