{
  "type": "Feature",
  "properties": {
    "addr:full":"Djursvang 4 Albertslund Danmark 2620",
    "addr:housenumber":"4",
    "addr:postcode":"2620",
    "addr:street":"Djursvang",
    "iso:country":"DK",
    "sg:address":"Djursvang 4",
    "sg:city":"Albertslund",
    "sg:orig_category":"Autoreparation og -service",
    "sg:phone":"+45 43 62 60 66",
    "sg:postcode":"2620",
    "sg:province":"Danmark",
    "wof:name":"Tj\u00f8rnely Auto A/S",
    "wof:placetype":"venue"
},
  "geometry": {"coordinates":[12.3596782684,55.666015625],"type":"Point"}
}