{
  "type": "Feature",
  "properties": {
    "addr:full":"Tangevej 1, Agger Vestervig Danmark 7770",
    "addr:housenumber":"1",
    "addr:postcode":"7770",
    "addr:street":"Tangevej",
    "iso:country":"DK",
    "sg:address":"Tangevej 1, Agger",
    "sg:city":"Vestervig",
    "sg:orig_category":"Feriecentre",
    "sg:phone":"+45 97 94 17 55",
    "sg:postcode":"7770",
    "sg:province":"Danmark",
    "sg:website":"www.aggertangeferiecenter.dk",
    "wof:name":"Agger Tange Feriecenter",
    "wof:placetype":"venue"
},
  "geometry": {"coordinates":[8.2376403809,56.7811546326],"type":"Point"}
}