{
  "type": "Feature",
  "properties": {
    "addr:full":"Krakvej 13 Hasle Danmark 3790",
    "addr:housenumber":"13",
    "addr:postcode":"3790",
    "addr:street":"Krakvej",
    "iso:country":"DK",
    "sg:address":"Krakvej 13",
    "sg:city":"Hasle",
    "sg:orig_category":"Kontorservice",
    "sg:phone":"+45 56 96 92 15",
    "sg:postcode":"3790",
    "sg:province":"Danmark",
    "wof:name":"Basis Int",
    "wof:placetype":"venue"
},
  "geometry": {"coordinates":[14.7595834732,55.2370033264],"type":"Point"}
}