{
  "type": "Feature",
  "properties": {
    "iso:country":"DK",
    "sg:address":"Engkrogen 9, Stevnstrup",
    "sg:city":"Lang\u00e5",
    "sg:orig_category":"Skorstensfejere",
    "sg:phone":"+45 86 46 71 06",
    "sg:postcode":"8870",
    "sg:province":"Danmark",
    "wof:name":"Thomsen, S\u00f8ren",
    "wof:placetype":"venue"
},
  "geometry": {"coordinates":[9.8955049515,56.3900756836],"type":"Point"}
}