{
  "type": "Feature",
  "properties": {
    "addr:full":"Hovedvejen 94 Glostrup Danmark 2600",
    "addr:housenumber":"94",
    "addr:postcode":"2600",
    "addr:street":"Hovedvejen",
    "iso:country":"DK",
    "sg:address":"Hovedvejen 94",
    "sg:city":"Glostrup",
    "sg:orig_category":"Revisorer",
    "sg:phone":"+45 43 45 40 00",
    "sg:postcode":"2600",
    "sg:province":"Danmark",
    "wof:name":"Mortensen A/S, N. K.",
    "wof:placetype":"venue"
},
  "geometry": {"coordinates":[12.4016580582,55.6664199829],"type":"Point"}
}