{
  "type": "Feature",
  "properties": {
    "addr:full":"H. V. Nyholms Vej 21 Frederiksberg Danmark 2000",
    "addr:housenumber":"21",
    "addr:postcode":"2000",
    "addr:street":"H. V. Nyholms Vej",
    "iso:country":"DK",
    "sg:address":"H. V. Nyholms Vej 21",
    "sg:city":"Frederiksberg",
    "sg:orig_category":"Private hospitaler and klinikker",
    "sg:phone":"+45 38 17 04 00",
    "sg:postcode":"2000",
    "sg:province":"Danmark",
    "sg:website":"www.hamlet.dk",
    "wof:name":"Hamlet, Privathospitalet",
    "wof:placetype":"venue"
},
  "geometry": {"coordinates":[12.5132389069,55.6794471741],"type":"Point"}
}