{
  "type": "Feature",
  "properties": {
    "addr:full":"Kvistskovvej 6, Lidemark Bj\u00e6verskov Danmark 4632",
    "addr:housenumber":"6",
    "addr:postcode":"4632",
    "addr:street":"Kvistskovvej",
    "iso:country":"DK",
    "sg:address":"Kvistskovvej 6, Lidemark",
    "sg:city":"Bj\u00e6verskov",
    "sg:orig_category":"Vinduespolering",
    "sg:phone":"+45 56 87 00 96",
    "sg:postcode":"4632",
    "sg:province":"Danmark",
    "wof:name":"Andersen, Carl \u00c5ge",
    "wof:placetype":"venue"
},
  "geometry": {"coordinates":[12.032699585,55.461265564],"type":"Point"}
}