{
  "type": "Feature",
  "properties": {
    "iso:country":"DK",
    "sg:address":"Gr\u00f8nttorvet 5",
    "sg:city":"Valby",
    "sg:orig_category":"Revisorer",
    "sg:phone":"+45 36 30 20 65",
    "sg:postcode":"2500",
    "sg:province":"Danmark",
    "sg:website":"www.revision-sjaelland.dk",
    "wof:name":"Revision Sj\u00e6lland A/S",
    "wof:placetype":"venue"
},
  "geometry": {"coordinates":[12.5026521683,55.654624939],"type":"Point"}
}