{
  "type": "Feature",
  "properties": {
    "addr:full":"Grydergade 7 Ribe Danmark 6760",
    "addr:housenumber":"7",
    "addr:postcode":"6760",
    "addr:street":"Grydergade",
    "iso:country":"DK",
    "sg:address":"Grydergade 7",
    "sg:city":"Ribe",
    "sg:orig_category":"Zoneterapeuter",
    "sg:phone":"+45 75 41 14 00",
    "sg:postcode":"6760",
    "sg:province":"Danmark",
    "wof:name":"Petersen, Anna Marie",
    "wof:placetype":"venue"
},
  "geometry": {"coordinates":[8.7599096298,55.3279724121],"type":"Point"}
}