{
  "type": "Feature",
  "properties": {
    "addr:full":"Skovlunden 81, Thyregod Give Danmark 7323",
    "addr:housenumber":"81",
    "addr:postcode":"7323",
    "addr:street":"Skovlunden",
    "iso:country":"DK",
    "sg:address":"Skovlunden 81, Thyregod",
    "sg:city":"Give",
    "sg:orig_category":"Musik- og sangundervisning",
    "sg:phone":"+45 75 73 47 47",
    "sg:postcode":"7323",
    "sg:province":"Danmark",
    "wof:name":"Rathleff, Maren Skovh\u00f8j",
    "wof:placetype":"venue"
},
  "geometry": {"coordinates":[9.2362060547,55.845413208],"type":"Point"}
}