{
  "type": "Feature",
  "properties": {
    "addr:full":"Lyngby Hovedgade 44 Kongens Lyngby Danmark 2800",
    "addr:housenumber":"44",
    "addr:postcode":"2800",
    "addr:street":"Lyngby Hovedgade",
    "iso:country":"DK",
    "sg:address":"Lyngby Hovedgade 44",
    "sg:city":"Kongens Lyngby",
    "sg:orig_category":"Blomsterhandlere",
    "sg:phone":"+45 45 93 01 63",
    "sg:postcode":"2800",
    "sg:province":"Danmark",
    "wof:name":"Blomster Caf\u00e9en",
    "wof:placetype":"venue"
},
  "geometry": {"coordinates":[12.5011491776,55.7720794678],"type":"Point"}
}