{
  "type": "Feature",
  "properties": {
    "addr:full":"Fmd.: Karen Vinderslev, Krogen 1, Vridsted Skive Danmark 7800",
    "addr:housenumber":"1",
    "addr:postcode":"7800",
    "addr:street":"Krogen;Vridsted",
    "iso:country":"DK",
    "sg:address":"Fmd.: Karen Vinderslev, Krogen 1, Vridsted",
    "sg:city":"Skive",
    "sg:orig_category":"Kulturelle foreninger",
    "sg:phone":"+45 97 54 71 44",
    "sg:postcode":"7800",
    "sg:province":"Danmark",
    "wof:name":"Aktiv Vestfjends ApS",
    "wof:placetype":"venue"
},
  "geometry": {"coordinates":[9.0320358276,56.5666427612],"type":"Point"}
}