{
  "type": "Feature",
  "properties": {
    "iso:country":"DK",
    "sg:address":"Vejg\u00e5rd M\u00f8llevej 3, Postboks 2036",
    "sg:classifiers":[
        {
            "category":"Banks & Credit Unions",
            "subcategory":"Bank",
            "type":"Services"
        }
    ],
    "sg:phone":"+45 98 10 18 35",
    "sg:postcode":"9100",
    "sg:tags":[
        "banker"
    ],
    "wof:name":"Merkur, Den Almennyttige Andelskasse",
    "wof:placetype":"venue"
},
  "geometry": {"coordinates":[9.9162597656,57.0493583679],"type":"Point"}
}