{
  "type": "Feature",
  "properties": {
    "addr:full":"Vestergade 2 Holstebro Danmark 7500",
    "addr:housenumber":"2",
    "addr:postcode":"7500",
    "addr:street":"Vestergade",
    "iso:country":"DK",
    "sg:address":"Vestergade 2",
    "sg:city":"Holstebro",
    "sg:orig_category":"Advokater",
    "sg:phone":"+45 97 42 05 00",
    "sg:postcode":"7500",
    "sg:province":"Danmark",
    "wof:name":"Munk-Poulsen / Brendstrup og Vium",
    "wof:placetype":"venue"
},
  "geometry": {"coordinates":[8.6066236496,56.3542404175],"type":"Point"}
}