{
  "type": "Feature",
  "properties": {
    "addr:full":"R\u00e5gelundevej 9 Kettinge Danmark 4892",
    "addr:housenumber":"9",
    "addr:postcode":"4892",
    "addr:street":"Raagelundevej",
    "iso:country":"DK",
    "sg:address":"R\u00e5gelundevej 9",
    "sg:city":"Kettinge",
    "sg:orig_category":"Kunstmalere",
    "sg:phone":"+45 54 87 35 65",
    "sg:postcode":"4892",
    "sg:province":"Danmark",
    "wof:name":"Arndt, Heike",
    "wof:placetype":"venue"
},
  "geometry": {"coordinates":[11.7273807526,54.6979484558],"type":"Point"}
}