{
  "type": "Feature",
  "properties": {
    "iso:country":"DK",
    "sg:address":"\u00d8rhagevej 117, Klitm\u00f8ller",
    "sg:city":"Thisted",
    "sg:orig_category":"Sommerhusudlejning",
    "sg:phone":"+45 97 97 53 50",
    "sg:postcode":"7700",
    "sg:province":"Danmark",
    "wof:name":"Klitm\u00f8ller Sommerhusudlejning",
    "wof:placetype":"venue"
},
  "geometry": {"coordinates":[8.6919784546,56.9556121826],"type":"Point"}
}