{
  "type": "Feature",
  "properties": {
    "iso:country":"DK",
    "sg:address":"Oliefabriksvej 2",
    "sg:city":"Kastrup",
    "sg:orig_category":"Isolering",
    "sg:phone":"+45 32 51 56 77",
    "sg:postcode":"2770",
    "sg:province":"Danmark",
    "wof:name":"Brdr. Svensson A/S",
    "wof:placetype":"venue"
},
  "geometry": {"coordinates":[12.5918474197,55.621547699],"type":"Point"}
}