{
  "type": "Feature",
  "properties": {
    "addr:full":"Toldbodgade 4 Odense C Danmark 5000",
    "addr:housenumber":"4",
    "addr:postcode":"5000",
    "addr:street":"Toldbodgade",
    "iso:country":"DK",
    "sg:address":"Toldbodgade 4",
    "sg:city":"Odense C",
    "sg:orig_category":"Konsulentvirksomheder",
    "sg:phone":"+45 66 14 34 70",
    "sg:postcode":"5000",
    "sg:province":"Danmark",
    "wof:name":"Jensen And Partners International ApS, H",
    "wof:placetype":"venue"
},
  "geometry": {"coordinates":[10.3685073853,55.4026451111],"type":"Point"}
}