{
  "type": "Feature",
  "properties": {
    "addr:full":"Ulstedvej 6 Dronninglund Danmark 9330",
    "addr:housenumber":"6",
    "addr:postcode":"9330",
    "addr:street":"Ulstedvej",
    "iso:country":"DK",
    "sg:address":"Ulstedvej 6",
    "sg:city":"Dronninglund",
    "sg:orig_category":"Maskinstationer",
    "sg:phone":"+45 98 84 18 33",
    "sg:postcode":"9330",
    "sg:province":"Danmark",
    "wof:name":"Diget, Maskinstation",
    "wof:placetype":"venue"
},
  "geometry": {"coordinates":[10.2834033966,57.1435890198],"type":"Point"}
}