{
  "type": "Feature",
  "properties": {
    "addr:full":"Borgerdiget 109 Herlev Danmark 2730",
    "addr:housenumber":"109",
    "addr:postcode":"2730",
    "addr:street":"Borgerdiget",
    "iso:country":"DK",
    "sg:address":"Borgerdiget 109",
    "sg:city":"Herlev",
    "sg:orig_category":"Undervisning, diverse",
    "sg:phone":"+45 44 53 21 16",
    "sg:postcode":"2730",
    "sg:province":"Danmark",
    "wof:name":"Herlev Dykkerklub",
    "wof:placetype":"venue"
},
  "geometry": {"coordinates":[12.4280385971,55.7322998047],"type":"Point"}
}