{
  "type": "Feature",
  "properties": {
    "addr:full":"S\u00f8ndermarksvej 150 Fredericia Danmark 7000",
    "addr:housenumber":"150",
    "addr:postcode":"7000",
    "addr:street":"Sondermarksvej",
    "iso:country":"DK",
    "sg:address":"S\u00f8ndermarksvej 150",
    "sg:city":"Fredericia",
    "sg:orig_category":"Kursussteder",
    "sg:phone":"+45 76 20 21 00",
    "sg:postcode":"7000",
    "sg:province":"Danmark",
    "wof:name":"Fuglsangcentret",
    "wof:placetype":"venue"
},
  "geometry": {"coordinates":[9.7070865631,55.5638427734],"type":"Point"}
}