{
  "type": "Feature",
  "properties": {
    "addr:full":"N\u00f8rre Alle 64 \u00c5rhus C Danmark 8000",
    "addr:housenumber":"64",
    "addr:postcode":"8000",
    "addr:street":"Norre Alle",
    "iso:country":"DK",
    "sg:address":"N\u00f8rre Alle 64",
    "sg:city":"\u00c5rhus C",
    "sg:classifiers":[
        {
            "category":"Personal",
            "subcategory":"Piercing",
            "type":"Services"
        }
    ],
    "sg:phone":"+45 86 12 13 15",
    "sg:postcode":"8000",
    "sg:province":"Danmark",
    "wof:name":"Glad's Body Piercing Studio",
    "wof:placetype":"venue"
},
  "geometry": {"coordinates":[4.717400074,49.7588005066],"type":"Point"}
}