{
  "type": "Feature",
  "properties": {
    "addr:full":"Niels Jernes Vej 6 Aalborg \u00d8 Danmark 9220",
    "addr:housenumber":"6",
    "addr:postcode":"9220",
    "addr:street":"Niels Jernes Vej;Danmark",
    "iso:country":"DK",
    "sg:address":"Niels Jernes Vej 6",
    "sg:city":"Aalborg \u00d8",
    "sg:orig_category":"Telekommunikation",
    "sg:phone":"+45 96 35 43 00",
    "sg:postcode":"9220",
    "sg:province":"Danmark",
    "wof:name":"L. M. Erichsson A/S",
    "wof:placetype":"venue"
},
  "geometry": {"coordinates":[9.9880418777,57.0130081177],"type":"Point"}
}