{
  "type": "Feature",
  "properties": {
    "addr:full":"Vermlandsgade 8 K\u00f8benhavn S Danmark 2300",
    "addr:housenumber":"8",
    "addr:postcode":"2300",
    "addr:street":"Vermlandsgade;S Danmark",
    "iso:country":"DK",
    "sg:address":"Vermlandsgade 8",
    "sg:city":"K\u00f8benhavn S",
    "sg:classifiers":[
        {
            "category":"Professional",
            "subcategory":"Business Services",
            "type":"Services"
        }
    ],
    "sg:phone":"+45 32 95 13 00",
    "sg:postcode":"2300",
    "sg:province":"Danmark",
    "sg:tags":[
        "import",
        "vin"
    ],
    "wof:name":"Olsen, Ulrichs",
    "wof:placetype":"venue"
},
  "geometry": {"coordinates":[-78.1299133301,36.7267417908],"type":"Point"}
}