{
  "type": "Feature",
  "properties": {
    "iso:country":"DK",
    "sg:address":"Fmd.: Hans Kurt Kjeldsen, N\u00f8rrebakken 12",
    "sg:city":"Gjern",
    "sg:orig_category":"Soldaterforeninger",
    "sg:phone":"+45 86 87 51 39",
    "sg:postcode":"8883",
    "sg:province":"Danmark",
    "wof:name":"St\u00f8tteforeningen af 1986 for Hjemmev\u00e6rnskompagni 2505",
    "wof:placetype":"venue"
},
  "geometry": {"coordinates":[9.7394037247,56.2305335999],"type":"Point"}
}