{
  "type": "Feature",
  "properties": {
    "addr:full":"\u00d8stergade 12, 1. Silkeborg Danmark 8600",
    "addr:housenumber":"12 1",
    "addr:postcode":"8600",
    "addr:street":"Ostergade",
    "iso:country":"DK",
    "sg:address":"\u00d8stergade 12, 1.",
    "sg:city":"Silkeborg",
    "sg:orig_category":"Psykologer, praktiserende",
    "sg:phone":"+45 86 80 62 40",
    "sg:postcode":"8600",
    "sg:province":"Danmark",
    "wof:name":"Schultz, Jytte",
    "wof:placetype":"venue"
},
  "geometry": {"coordinates":[9.5508394241,56.1701202393],"type":"Point"}
}