{
  "type": "Feature",
  "properties": {
    "addr:full":"Ved Volden 2 Randers Danmark 8900",
    "addr:housenumber":"2",
    "addr:postcode":"8900",
    "addr:street":"Ved Volden",
    "iso:country":"DK",
    "sg:address":"Ved Volden 2",
    "sg:city":"Randers",
    "sg:orig_category":"Kontorartikler",
    "sg:phone":"+45 86 41 01 66",
    "sg:postcode":"8900",
    "sg:province":"Danmark",
    "wof:name":"SN Kontorcenter",
    "wof:placetype":"venue"
},
  "geometry": {"coordinates":[10.0387172699,56.461643219],"type":"Point"}
}