{
  "type": "Feature",
  "properties": {
    "iso:country":"DK",
    "sg:address":"F\u00e5rtoftvej 4, Solbjerg",
    "sg:city":"Erslev",
    "sg:orig_category":"Reklamebureauer",
    "sg:phone":"+45 97 74 14 88",
    "sg:postcode":"7950",
    "sg:province":"Danmark",
    "wof:name":"Tingstrup Reklame",
    "wof:placetype":"venue"
},
  "geometry": {"coordinates":[8.7200698853,56.8354682922],"type":"Point"}
}