{
  "type": "Feature",
  "properties": {
    "addr:full":"Agerb\u00e6kvej 16 Hvidovre Danmark 2650",
    "addr:housenumber":"16",
    "addr:postcode":"2650",
    "addr:street":"Agerbaekvej",
    "iso:country":"DK",
    "sg:address":"Agerb\u00e6kvej 16",
    "sg:city":"Hvidovre",
    "sg:orig_category":"Video- og TV-produktion",
    "sg:phone":"+45 36 78 56 34",
    "sg:postcode":"2650",
    "sg:province":"Danmark",
    "wof:name":"Young Production",
    "wof:placetype":"venue"
},
  "geometry": {"coordinates":[12.4688577652,55.6301002502],"type":"Point"}
}