{
  "type": "Feature",
  "properties": {
    "addr:full":"Kirkebakken 13 Vejle \u00d8 Danmark 7120",
    "addr:housenumber":"13",
    "addr:postcode":"7120",
    "addr:street":"Kirkebakken",
    "iso:country":"DK",
    "sg:address":"Kirkebakken 13",
    "sg:city":"Vejle \u00d8",
    "sg:orig_category":"Integrerede institutioner",
    "sg:phone":"+45 75 71 12 22",
    "sg:postcode":"7120",
    "sg:province":"Danmark",
    "wof:name":"Kirkebakken",
    "wof:placetype":"venue"
},
  "geometry": {"coordinates":[9.6065530777,55.714012146],"type":"Point"}
}