{
  "type": "Feature",
  "properties": {
    "iso:country":"DK",
    "sg:address":"v/ Lars Peter Kruse, Havremarken 24",
    "sg:city":"Hanstholm",
    "sg:orig_category":"Hobbybetonede foreninger",
    "sg:phone":"+45 97 96 25 66",
    "sg:postcode":"7730",
    "sg:province":"Danmark",
    "wof:name":"Saab V4 og Sonett Klub Danmark",
    "wof:placetype":"venue"
},
  "geometry": {"coordinates":[8.6066236496,57.115940094],"type":"Point"}
}