{
  "type": "Feature",
  "properties": {
    "addr:full":"Hovmarksvej 184 Horsens Danmark 8700",
    "addr:housenumber":"184",
    "addr:postcode":"8700",
    "addr:street":"Hovmarksvej",
    "iso:country":"DK",
    "sg:address":"Hovmarksvej 184",
    "sg:city":"Horsens",
    "sg:orig_category":"Murermestre",
    "sg:phone":"+45 75 65 74 10",
    "sg:postcode":"8700",
    "sg:province":"Danmark",
    "wof:name":"Jensen & Friis Pedersen A/S",
    "wof:placetype":"venue"
},
  "geometry": {"coordinates":[9.9225120544,55.8642883301],"type":"Point"}
}