{
  "type": "Feature",
  "properties": {
    "iso:country":"DK",
    "sg:address":"Kirseb\u00e6rhaven 10, Himmelev",
    "sg:city":"Roskilde",
    "sg:orig_category":"Reklamebureauer",
    "sg:phone":"+45 46 36 91 09",
    "sg:postcode":"4000",
    "sg:province":"Danmark",
    "wof:name":"Ida Design & Reklame",
    "wof:placetype":"venue"
},
  "geometry": {"coordinates":[12.0909376144,55.6404838562],"type":"Point"}
}