{
  "type": "Feature",
  "properties": {
    "iso:country":"DK",
    "sg:address":"Bredgade 45 B",
    "sg:city":"K\u00f8benhavn",
    "sg:orig_category":"Reklamebureauer",
    "sg:phone":"+45 33 11 30 07",
    "sg:postcode":"1260",
    "sg:province":"Danmark",
    "sg:website":"www.denbaek.dk",
    "wof:name":"Denb\u00e6k Reklame",
    "wof:placetype":"venue"
},
  "geometry": {"coordinates":[12.5931997299,55.6845016479],"type":"Point"}
}