{
  "type": "Feature",
  "properties": {
    "iso:country":"DK",
    "sg:address":"Birkholmsvej 9",
    "sg:city":"Virum",
    "sg:orig_category":"INGENI\u00c3\u02dcRER",
    "sg:phone":"+45 45 83 13 47",
    "sg:postcode":"2830",
    "sg:province":"Danmark",
    "wof:name":"Reitzel A/S, Erik",
    "wof:placetype":"venue"
},
  "geometry": {"coordinates":[12.4785165787,55.7992515564],"type":"Point"}
}