{
  "type": "Feature",
  "properties": {
    "addr:full":"Provsteh\u00f8jen 16 Holb\u00e6k Danmark 4300",
    "addr:housenumber":"16",
    "addr:postcode":"4300",
    "addr:street":"Provstehojen",
    "iso:country":"DK",
    "sg:address":"Provsteh\u00f8jen 16",
    "sg:city":"Holb\u00e6k",
    "sg:orig_category":"Murermestre",
    "sg:phone":"+45 59 43 47 82",
    "sg:postcode":"4300",
    "sg:province":"Danmark",
    "wof:name":"Janholm, Finn",
    "wof:placetype":"venue"
},
  "geometry": {"coordinates":[114.6686172485,37.117401123],"type":"Point"}
}