{
  "type": "Feature",
  "properties": {
    "addr:full":"Linnebjergvej 14 Sunds Danmark 7451",
    "addr:housenumber":"14",
    "addr:postcode":"7451",
    "addr:street":"Linnebjergvej",
    "iso:country":"DK",
    "sg:address":"Linnebjergvej 14",
    "sg:city":"Sunds",
    "sg:orig_category":"Rugerier",
    "sg:phone":"+45 97 14 43 44",
    "sg:postcode":"7451",
    "sg:province":"Danmark",
    "wof:name":"Rug-Kon Service",
    "wof:placetype":"venue"
},
  "geometry": {"coordinates":[9.0758533478,56.2091674805],"type":"Point"}
}