{
  "type": "Feature",
  "properties": {
    "iso:country":"DK",
    "sg:address":"Vilhelm Becks Vej 79",
    "sg:city":"Viby",
    "sg:orig_category":"Bagere",
    "sg:phone":"+45 86 11 29 33",
    "sg:postcode":"8260",
    "sg:province":"Danmark",
    "wof:name":"Lind's Bageri",
    "wof:placetype":"venue"
},
  "geometry": {"coordinates":[10.17662,56.130421],"type":"Point"}
}