{
  "type": "Feature",
  "properties": {
    "addr:full":"Henv.: Gurli Christiansen, H\u00f8je Gladsaxe 21, 14. S\u00f8borg Danmark 2860",
    "addr:housenumber":"21 14",
    "addr:postcode":"2860",
    "addr:street":"Gladsaxe",
    "iso:country":"DK",
    "sg:address":"Henv.: Gurli Christiansen, H\u00f8je Gladsaxe 21, 14.",
    "sg:city":"S\u00f8borg",
    "sg:orig_category":"Hobbybetonede foreninger",
    "sg:phone":"+45 39 67 03 28",
    "sg:postcode":"2860",
    "sg:province":"Danmark",
    "wof:name":"Gyngemoselauget",
    "wof:placetype":"venue"
},
  "geometry": {"coordinates":[12.4819698334,55.7465934753],"type":"Point"}
}