{
  "type": "Feature",
  "properties": {
    "addr:full":"\u00c5dalen 10 Haslev Danmark 4690",
    "addr:housenumber":"10",
    "addr:postcode":"4690",
    "addr:street":"Aadalen",
    "iso:country":"DK",
    "sg:address":"\u00c5dalen 10",
    "sg:city":"Haslev",
    "sg:orig_category":"INGENI\u00c3\u02dcRER",
    "sg:phone":"+45 56 31 35 80",
    "sg:postcode":"4690",
    "sg:province":"Danmark",
    "wof:name":"S\u00f8rensen, Ingeni\u00f8rfirmaet Bent",
    "wof:placetype":"venue"
},
  "geometry": {"coordinates":[11.9515533447,55.3245811462],"type":"Point"}
}