{
  "type": "Feature",
  "properties": {
    "addr:full":"Storegade 47 Klovborg Danmark 8765",
    "addr:housenumber":"47",
    "addr:postcode":"8765",
    "addr:street":"Storegade",
    "iso:country":"DK",
    "sg:address":"Storegade 47",
    "sg:city":"Klovborg",
    "sg:orig_category":"Fodplejere",
    "sg:phone":"+45 75 76 11 46",
    "sg:postcode":"8765",
    "sg:province":"Danmark",
    "wof:name":"Krogh, Elly",
    "wof:placetype":"venue"
},
  "geometry": {"coordinates":[9.4918642044,55.9309501648],"type":"Point"}
}