{
  "type": "Feature",
  "properties": {
    "addr:full":"Nymarken 7 Munkebo Danmark 5330",
    "addr:housenumber":"7",
    "addr:postcode":"5330",
    "addr:street":"Nymarken",
    "iso:country":"DK",
    "sg:address":"Nymarken 7",
    "sg:city":"Munkebo",
    "sg:classifiers":[
        {
            "category":"Taxi",
            "type":"Transportation"
        }
    ],
    "sg:phone":"+45 65 97 43 10",
    "sg:postcode":"5330",
    "sg:province":"Danmark",
    "wof:name":"Ivar's Biler's Eftf. I/S",
    "wof:placetype":"venue"
},
  "geometry": {"coordinates":[10.5502080917,55.460144043],"type":"Point"}
}