{
  "type": "Feature",
  "properties": {
    "addr:full":"Birkedam 14  Kolding Danmark 6000",
    "addr:housenumber":"14",
    "addr:postcode":"6000",
    "addr:street":"Birkedam",
    "iso:country":"DK",
    "sg:address":"Birkedam 14 ",
    "sg:city":"Kolding",
    "sg:classifiers":[
        {
            "category":"Autos & Motor Vehicles",
            "subcategory":"Automobile Sales",
            "type":"Retail Goods"
        }
    ],
    "sg:phone":"+45 70 10 59 60",
    "sg:postcode":"6000",
    "sg:province":"Danmark",
    "sg:tags":[
        "industrial"
    ],
    "wof:name":"DIESEL-G\u00c5RDEN A/S",
    "wof:placetype":"venue"
},
  "geometry": {"coordinates":[9.4443292618,55.5180091858],"type":"Point"}
}