{
  "type": "Feature",
  "properties": {
    "iso:country":"DK",
    "sg:address":"Mars All\u00e9 50 ",
    "sg:city":"Horsens",
    "sg:classifiers":[
        {
            "category":"Home & Garden",
            "subcategory":"Home Furnishings",
            "type":"Retail Goods"
        }
    ],
    "sg:phone":"+45 76 26 10 00",
    "sg:postcode":"8700",
    "sg:province":"Danmark",
    "sg:tags":[
        "household"
    ],
    "wof:name":"A/S MODULIA",
    "wof:placetype":"venue"
},
  "geometry": {"coordinates":[9.8432445526,55.8621063232],"type":"Point"}
}