{
  "type": "Feature",
  "properties": {
    "addr:full":"Vr\u00e5lyngen 4 Lynge Danmark 3540",
    "addr:housenumber":"4",
    "addr:postcode":"3540",
    "addr:street":"Vraalyngen",
    "iso:country":"DK",
    "sg:address":"Vr\u00e5lyngen 4",
    "sg:city":"Lynge",
    "sg:orig_category":"Malermestre",
    "sg:phone":"+45 48 19 21 21",
    "sg:postcode":"3540",
    "sg:province":"Danmark",
    "wof:name":"Christiansen & S\u00f8n ApS, \u00c5ge",
    "wof:placetype":"venue"
},
  "geometry": {"coordinates":[12.3042898178,55.8474388123],"type":"Point"}
}