{
  "type": "Feature",
  "properties": {
    "iso:country":"DK",
    "sg:address":"Fmd.: Henning Christensen, \u00c6r\u00f8vej 4",
    "sg:city":"H\u00f8ng",
    "sg:orig_category":"Grundejerforeninger",
    "sg:postcode":"4270",
    "sg:province":"Danmark",
    "wof:name":"Lynglodsvej Ejerlaug (omr. II)",
    "wof:placetype":"venue"
},
  "geometry": {"coordinates":[-89.5733413696,35.6730995178],"type":"Point"}
}