{
  "type": "Feature",
  "properties": {
    "addr:full":"v/ Carl Henrik Petersen, K\u00e6ret 1, Langvadbjerg Herning Danmark 7400",
    "addr:housenumber":"1",
    "addr:postcode":"7400",
    "addr:street":"Kaeret;Langvadbjerg",
    "iso:country":"DK",
    "sg:address":"v/ Carl Henrik Petersen, K\u00e6ret 1, Langvadbjerg",
    "sg:city":"Herning",
    "sg:orig_category":"Politiske foreninger, \u00c3\u02dcvrige",
    "sg:phone":"+45 97 21 51 43",
    "sg:postcode":"7400",
    "sg:province":"Danmark",
    "wof:name":"Demokratisk Fornyelse, Valgsamarbejde imod Unionen.",
    "wof:placetype":"venue"
},
  "geometry": {"coordinates":[8.9768896103,56.1374168396],"type":"Point"}
}