{
  "type": "Feature",
  "properties": {
    "addr:full":"v/ Lejf Hummelsh\u00f8j, R\u00f8llikevej 21, Hillerslev Thisted Danmark 7700",
    "addr:housenumber":"21",
    "addr:postcode":"7700",
    "addr:street":"Rollikevej;Hillerslev",
    "iso:country":"DK",
    "sg:address":"v/ Lejf Hummelsh\u00f8j, R\u00f8llikevej 21, Hillerslev",
    "sg:city":"Thisted",
    "sg:orig_category":"Ungdomsklubber",
    "sg:phone":"+45 97 98 11 85",
    "sg:postcode":"7700",
    "sg:province":"Danmark",
    "wof:name":"Hillerslev Ungdomsklub",
    "wof:placetype":"venue"
},
  "geometry": {"coordinates":[8.6919784546,56.9556121826],"type":"Point"}
}