{
  "type": "Feature",
  "properties": {
    "iso:country":"DK",
    "sg:address":"Tovesvej 12, S\u00f8ller\u00f8d",
    "sg:city":"N\u00e6rum",
    "sg:orig_category":"INGENI\u00c3\u02dcRER",
    "sg:phone":"+45 45 80 09 36",
    "sg:postcode":"2850",
    "sg:province":"Danmark",
    "wof:name":"Br\u00f8ndum-Nielsen, Troels",
    "wof:placetype":"venue"
},
  "geometry": {"coordinates":[-89.9986038208,38.1303901672],"type":"Point"}
}