{
  "type": "Feature",
  "properties": {
    "addr:full":"Storegade 5 Bramming Danmark 6740",
    "addr:housenumber":"5",
    "addr:postcode":"6740",
    "addr:street":"Storegade",
    "iso:country":"DK",
    "sg:address":"Storegade 5",
    "sg:city":"Bramming",
    "sg:orig_category":"Arkitekter",
    "sg:phone":"+45 75 10 23 20",
    "sg:postcode":"6740",
    "sg:province":"Danmark",
    "wof:name":"Bramming Tegnestue ApS",
    "wof:placetype":"venue"
},
  "geometry": {"coordinates":[8.701581955,55.4647789001],"type":"Point"}
}