{
  "type": "Feature",
  "properties": {
    "addr:full":"Rosen\u00f8rns Alle 22 Frederiksberg Danmark 1970",
    "addr:housenumber":"22",
    "addr:postcode":"1970",
    "addr:street":"Rosenorns Alle",
    "iso:country":"DK",
    "sg:address":"Rosen\u00f8rns Alle 22",
    "sg:city":"Frederiksberg",
    "sg:orig_category":"Kulturelle organisationer og -foreninger",
    "sg:phone":"+45 35 20 30 40",
    "sg:postcode":"1970",
    "sg:province":"Danmark",
    "wof:name":"Radios Underholdningsorkester, Danmarks",
    "wof:placetype":"venue"
},
  "geometry": {"coordinates":[12.5522689819,55.6822013855],"type":"Point"}
}