{
  "type": "Feature",
  "properties": {
    "addr:full":"Algade 15 D Roskilde Danmark 4000",
    "addr:housenumber":"15 d",
    "addr:postcode":"4000",
    "addr:street":"Algade",
    "iso:country":"DK",
    "sg:address":"Algade 15 D",
    "sg:city":"Roskilde",
    "sg:orig_category":"Arkitekter",
    "sg:phone":"+45 46 35 35 85",
    "sg:postcode":"4000",
    "sg:province":"Danmark",
    "wof:name":"Br\u00f8ndsted, Kirsten",
    "wof:placetype":"venue"
},
  "geometry": {"coordinates":[12.0838985443,55.6411781311],"type":"Point"}
}