{
  "type": "Feature",
  "properties": {
    "addr:full":"\u00c5have Alle 9 C Silkeborg Danmark 8600",
    "addr:housenumber":"9 c",
    "addr:postcode":"8600",
    "addr:street":"Aahave Alle",
    "iso:country":"DK",
    "sg:address":"\u00c5have Alle 9 C",
    "sg:city":"Silkeborg",
    "sg:classifiers":[
        {
            "category":"Restaurant",
            "type":"Food & Drink"
        }
    ],
    "sg:phone":"+45 86 82 61 79",
    "sg:postcode":"8600",
    "sg:province":"Danmark",
    "wof:name":"Indelukkests Spisested",
    "wof:placetype":"venue"
},
  "geometry": {"coordinates":[9.5594110489,56.1618652344],"type":"Point"}
}