{
  "type": "Feature",
  "properties": {
    "addr:full":"v/ Lis Michelsen, Vester Skivumvej 28, Skivum Nibe Danmark 9240",
    "addr:housenumber":"28",
    "addr:postcode":"9240",
    "addr:street":"Vester Skivumvej;Skivum",
    "iso:country":"DK",
    "sg:address":"v/ Lis Michelsen, Vester Skivumvej 28, Skivum",
    "sg:city":"Nibe",
    "sg:orig_category":"\u00c3\u02dcvrig fritidsundervisning",
    "sg:phone":"+45 98 66 61 73",
    "sg:postcode":"9240",
    "sg:province":"Danmark",
    "wof:name":"Skivum Husholdningsudvalg",
    "wof:placetype":"venue"
},
  "geometry": {"coordinates":[9.6393280029,56.982421875],"type":"Point"}
}