{
  "type": "Feature",
  "properties": {
    "addr:full":"M\u00f8llegade 5, Ramsing Sp\u00f8ttrup Danmark 7860",
    "addr:housenumber":"5",
    "addr:postcode":"7860",
    "addr:street":"Mollegade",
    "iso:country":"DK",
    "sg:address":"M\u00f8llegade 5, Ramsing",
    "sg:city":"Sp\u00f8ttrup",
    "sg:orig_category":"Forsamlingshuse",
    "sg:phone":"+45 97 56 69 14",
    "sg:postcode":"7860",
    "sg:province":"Danmark",
    "wof:name":"Ramsing Forsamlingshus",
    "wof:placetype":"venue"
},
  "geometry": {"coordinates":[8.7428588867,56.5733261108],"type":"Point"}
}