{
  "type": "Feature",
  "properties": {
    "addr:full":"Farverland 5 A Glostrup Danmark 2600",
    "addr:housenumber":"5 a",
    "addr:postcode":"2600",
    "addr:street":"Farverland",
    "iso:country":"DK",
    "sg:address":"Farverland 5 A",
    "sg:city":"Glostrup",
    "sg:orig_category":"Vinduer",
    "sg:phone":"+45 43 43 32 00",
    "sg:postcode":"2600",
    "sg:province":"Danmark",
    "wof:name":"NBT Vinduet A/S",
    "wof:placetype":"venue"
},
  "geometry": {"coordinates":[12.3826169968,55.6820335388],"type":"Point"}
}