{
  "type": "Feature",
  "properties": {
    "addr:full":"Frejasvej 2, Allerup Holb\u00e6k Danmark 4300",
    "addr:housenumber":"2",
    "addr:postcode":"4300",
    "addr:street":"Frejasvej",
    "iso:country":"DK",
    "sg:address":"Frejasvej 2, Allerup",
    "sg:city":"Holb\u00e6k",
    "sg:orig_category":"Have- og parkmaskiner",
    "sg:phone":"+45 59 43 45 22",
    "sg:postcode":"4300",
    "sg:province":"Danmark",
    "sg:website":"www.holbaek-agro-center.dk",
    "wof:name":"Holb\u00e6k Agro Center",
    "wof:placetype":"venue"
},
  "geometry": {"coordinates":[11.7100753784,55.717956543],"type":"Point"}
}