{
  "type": "Feature",
  "properties": {
    "addr:full":"Algade 62 - 64 Middelfart Danmark 5500",
    "addr:housenumber":"62 64",
    "addr:postcode":"5500",
    "addr:street":"Algade",
    "iso:country":"DK",
    "sg:address":"Algade 62 - 64",
    "sg:city":"Middelfart",
    "sg:orig_category":"Forsikringer",
    "sg:phone":"+45 63 41 41 00",
    "sg:postcode":"5500",
    "sg:province":"Danmark",
    "wof:name":"Alm. Brand af 1792",
    "wof:placetype":"venue"
},
  "geometry": {"coordinates":[9.7338523865,55.5047111511],"type":"Point"}
}