{
  "type": "Feature",
  "properties": {
    "addr:full":"Storegade 1 Stege Danmark 4780",
    "addr:housenumber":"1",
    "addr:postcode":"4780",
    "addr:street":"Storegade",
    "iso:country":"DK",
    "sg:address":"Storegade 1",
    "sg:city":"Stege",
    "sg:orig_category":"Posthuse",
    "sg:phone":"+45 55 81 40 31",
    "sg:postcode":"4780",
    "sg:province":"Danmark",
    "wof:name":"Post Danmark, Stege Postkontor",
    "wof:placetype":"venue"
},
  "geometry": {"coordinates":[12.282781601,54.9829406738],"type":"Point"}
}