{
  "type": "Feature",
  "properties": {
    "iso:country":"DK",
    "sg:address":"Chr. M. \u00d8stergaards Vej 2",
    "sg:city":"Horsens",
    "sg:orig_category":"Kollegier",
    "sg:phone":"+45 75 62 65 16",
    "sg:postcode":"8700",
    "sg:province":"Danmark",
    "wof:name":"Teknisk Kollegium",
    "wof:placetype":"venue"
},
  "geometry": {"coordinates":[9.8859071732,55.8701210022],"type":"Point"}
}