{
  "type": "Feature",
  "properties": {
    "addr:full":"Vestre Skovvej 3 Risskov Danmark 8240",
    "addr:housenumber":"3",
    "addr:postcode":"8240",
    "addr:street":"Vestre Skovvej",
    "iso:country":"DK",
    "sg:address":"Vestre Skovvej 3",
    "sg:city":"Risskov",
    "sg:orig_category":"Psykoterapi",
    "sg:phone":"+45 86 17 30 77",
    "sg:postcode":"8240",
    "sg:province":"Danmark",
    "wof:name":"Thestrup, Grethe",
    "wof:placetype":"venue"
},
  "geometry": {"coordinates":[10.2246780396,56.1823501587],"type":"Point"}
}