{
  "type": "Feature",
  "properties": {
    "iso:country":"DK",
    "sg:address":"Rolighedsvej 31",
    "sg:city":"Slagelse",
    "sg:orig_category":"Skoler",
    "sg:phone":"+45 58 50 11 11",
    "sg:postcode":"4200",
    "sg:province":"Danmark",
    "sg:website":"www.nymarkskolen.dk",
    "wof:name":"Nymarkskolen",
    "wof:placetype":"venue"
},
  "geometry": {"coordinates":[11.3658924103,55.4107131958],"type":"Point"}
}