{
  "type": "Feature",
  "properties": {
    "addr:full":"\u00d8stergade 28, 1. Skjern Danmark 6900",
    "addr:housenumber":"28 1",
    "addr:postcode":"6900",
    "addr:street":"Ostergade",
    "iso:country":"DK",
    "sg:address":"\u00d8stergade 28, 1.",
    "sg:city":"Skjern",
    "sg:orig_category":"Kulturelle organisationer og -foreninger",
    "sg:phone":"+45 97 35 20 99",
    "sg:postcode":"6900",
    "sg:province":"Danmark",
    "sg:website":"www.kristne-friskoler.dk",
    "wof:name":"Kristne Friskoler, Foreningen af",
    "wof:placetype":"venue"
},
  "geometry": {"coordinates":[8.4958057404,55.949054718],"type":"Point"}
}