{
  "type": "Feature",
  "properties": {
    "addr:full":"Alperosevej 13 K\u00f8benhavn S Danmark 2300",
    "addr:housenumber":"13",
    "addr:postcode":"2300",
    "addr:street":"Alperosevej;S Danmark",
    "iso:country":"DK",
    "sg:address":"Alperosevej 13",
    "sg:city":"K\u00f8benhavn S",
    "sg:orig_category":"Malermestre",
    "sg:phone":"+45 32 58 94 94",
    "sg:postcode":"2300",
    "sg:province":"Danmark",
    "wof:name":"Munk, Malermester Kenneth",
    "wof:placetype":"venue"
},
  "geometry": {"coordinates":[-80.03601074220001,40.3886909485],"type":"Point"}
}