{
  "type": "Feature",
  "properties": {
    "addr:full":"N\u00f8rregade 40 A Vemb Danmark 7570",
    "addr:housenumber":"40 a",
    "addr:postcode":"7570",
    "addr:street":"Norregade",
    "iso:country":"DK",
    "sg:address":"N\u00f8rregade 40 A",
    "sg:city":"Vemb",
    "sg:orig_category":"Autoreservedele",
    "sg:phone":"+45 97 48 18 01",
    "sg:postcode":"7570",
    "sg:province":"Danmark",
    "wof:name":"J. B. Import",
    "wof:placetype":"venue"
},
  "geometry": {"coordinates":[8.3422641754,56.3465461731],"type":"Point"}
}