{
  "type": "Feature",
  "properties": {
    "addr:full":"Torvet 1, 2. th. Ringsted Danmark 4100",
    "addr:housenumber":"1 2 th.",
    "addr:postcode":"4100",
    "addr:street":"Torvet",
    "iso:country":"DK",
    "sg:address":"Torvet 1, 2. th.",
    "sg:city":"Ringsted",
    "sg:orig_category":"Advokater",
    "sg:phone":"+45 57 67 67 75",
    "sg:postcode":"4100",
    "sg:province":"Danmark",
    "sg:website":"www.advodan.dk/ringsted",
    "wof:name":"Advodan",
    "wof:placetype":"venue"
},
  "geometry": {"coordinates":[11.7875862122,55.4458961487],"type":"Point"}
}