{
  "type": "Feature",
  "properties": {
    "addr:full":"Hvidovrevej 272 Hvidovre Danmark 2650",
    "addr:housenumber":"272",
    "addr:postcode":"2650",
    "addr:street":"Hvidovrevej",
    "iso:country":"DK",
    "sg:address":"Hvidovrevej 272",
    "sg:city":"Hvidovre",
    "sg:orig_category":"Posthuse",
    "sg:phone":"+45 36 34 49 49",
    "sg:postcode":"2650",
    "sg:province":"Danmark",
    "wof:name":"Post Danmark, Hvidovre Postkontor",
    "wof:placetype":"venue"
},
  "geometry": {"coordinates":[12.4779815674,55.6443634033],"type":"Point"}
}