{
  "type": "Feature",
  "properties": {
    "addr:full":"Bredgade 15 Struer Danmark 7600",
    "addr:housenumber":"15",
    "addr:postcode":"7600",
    "addr:street":"Bredgade",
    "iso:country":"DK",
    "sg:address":"Bredgade 15",
    "sg:city":"Struer",
    "sg:orig_category":"Bogtrykkerier",
    "sg:phone":"+45 97 85 22 44",
    "sg:postcode":"7600",
    "sg:province":"Danmark",
    "wof:name":"Ekspres-Trykkeriet",
    "wof:placetype":"venue"
},
  "geometry": {"coordinates":[8.5963373184,56.49036026],"type":"Point"}
}