{
  "type": "Feature",
  "properties": {
    "addr:full":"Fmd.: H.P.S. Kristiansen, Skjoldbjergvej 52 Vorbasse Danmark 6623",
    "addr:housenumber":"52",
    "addr:postcode":"6623",
    "addr:street":"Skjoldbjergvej",
    "iso:country":"DK",
    "sg:address":"Fmd.: H.P.S. Kristiansen, Skjoldbjergvej 52",
    "sg:city":"Vorbasse",
    "sg:orig_category":"Medborgerhuse",
    "sg:phone":"+45 75 33 46 38",
    "sg:postcode":"6623",
    "sg:province":"Danmark",
    "wof:name":"Skjoldbjerg Medborgerhus",
    "wof:placetype":"venue"
},
  "geometry": {"coordinates":[9.0800552368,55.6312217712],"type":"Point"}
}