{
  "type": "Feature",
  "properties": {
    "addr:full":"Ndr. Ringvej 4 Nyk\u00f8bing Danmark 4800",
    "addr:housenumber":"4",
    "addr:postcode":"4800",
    "addr:street":"Ndr. Ringvej",
    "iso:country":"DK",
    "sg:address":"Ndr. Ringvej 4",
    "sg:city":"Nyk\u00f8bing",
    "sg:orig_category":"Mobiltelefoner",
    "sg:phone":"+45 54 85 28 44",
    "sg:postcode":"4800",
    "sg:province":"Danmark",
    "wof:name":"Hoffmeyer & J\u00f8rgensen A/S",
    "wof:placetype":"venue"
},
  "geometry": {"coordinates":[14.2974796295,36.0507698059],"type":"Point"}
}