{
  "type": "Feature",
  "properties": {
    "addr:full":"Fmd.: Flemming Klitg\u00e5rd Nielsen, H\u00f8rbylundvej 111, Stenh\u00f8j Frederikshavn Danmark 9900",
    "addr:housenumber":"111",
    "addr:postcode":"9900",
    "addr:street":"Fmd.;Horbylundvej",
    "iso:country":"DK",
    "sg:address":"Fmd.: Flemming Klitg\u00e5rd Nielsen, H\u00f8rbylundvej 111, Stenh\u00f8j",
    "sg:city":"Frederikshavn",
    "sg:orig_category":"Hobbybetonede foreninger",
    "sg:phone":"+45 98 47 52 58",
    "sg:postcode":"9900",
    "sg:province":"Danmark",
    "wof:name":"Dronninglund-Dybvad Havekreds",
    "wof:placetype":"venue"
},
  "geometry": {"coordinates":[10.5362997055,57.4396400452],"type":"Point"}
}