{
  "type": "Feature",
  "properties": {
    "addr:full":"Bispeengen 5, Anderup Odense N Danmark 5270",
    "addr:housenumber":"5",
    "addr:postcode":"5270",
    "addr:street":"Bispeengen;Anderup",
    "iso:country":"DK",
    "sg:address":"Bispeengen 5, Anderup",
    "sg:city":"Odense N",
    "sg:orig_category":"Fritidsklubber",
    "sg:phone":"+45 66 18 56 18",
    "sg:postcode":"5270",
    "sg:province":"Danmark",
    "wof:name":"S\u00f8hus Fritidsklub V\u00e6dderen",
    "wof:placetype":"venue"
},
  "geometry": {"coordinates":[10.3306798935,55.4711418152],"type":"Point"}
}