{
  "type": "Feature",
  "properties": {
    "addr:full":"S\u00f8vang Alle 10, 2. Kastrup Danmark 2770",
    "addr:housenumber":"10 2",
    "addr:postcode":"2770",
    "addr:street":"Sovang Alle",
    "iso:country":"DK",
    "sg:address":"S\u00f8vang Alle 10, 2.",
    "sg:city":"Kastrup",
    "sg:orig_category":"Vinduespolering",
    "sg:phone":"+45 32 51 20 25",
    "sg:postcode":"2770",
    "sg:province":"Danmark",
    "wof:name":"Halberg Service",
    "wof:placetype":"venue"
},
  "geometry": {"coordinates":[12.6472015381,55.6371002197],"type":"Point"}
}