{
  "type": "Feature",
  "properties": {
    "addr:full":"Nyvej 16, Mel\u00f8se Sk\u00e6vinge Danmark 3320",
    "addr:housenumber":"16",
    "addr:postcode":"3320",
    "addr:street":"Nyvej",
    "iso:country":"DK",
    "sg:address":"Nyvej 16, Mel\u00f8se",
    "sg:city":"Sk\u00e6vinge",
    "sg:orig_category":"Oliefyr og service",
    "sg:phone":"+45 48 21 01 02",
    "sg:postcode":"3320",
    "sg:province":"Danmark",
    "wof:name":"E.B. V.V.S. og Oliefyrsservice",
    "wof:placetype":"venue"
},
  "geometry": {"coordinates":[12.1152973175,55.9365768433],"type":"Point"}
}