{
  "type": "Feature",
  "properties": {
    "addr:full":"Yderholmen 3 Ballerup Danmark 2750",
    "addr:housenumber":"3",
    "addr:postcode":"2750",
    "addr:street":"Yderholmen",
    "iso:country":"DK",
    "sg:address":"Yderholmen 3",
    "sg:city":"Ballerup",
    "sg:orig_category":"Autolakering",
    "sg:phone":"+45 44 65 63 30",
    "sg:postcode":"2750",
    "sg:province":"Danmark",
    "wof:name":"Yderholmens Autolakering",
    "wof:placetype":"venue"
},
  "geometry": {"coordinates":[12.3261823654,55.7266044617],"type":"Point"}
}