{
  "type": "Feature",
  "properties": {
    "addr:full":"Possementmagervej 9 Pandrup Danmark 9490",
    "addr:housenumber":"9",
    "addr:postcode":"9490",
    "addr:street":"Possementmagervej",
    "iso:country":"DK",
    "sg:address":"Possementmagervej 9",
    "sg:city":"Pandrup",
    "sg:orig_category":"Fabrikker",
    "sg:phone":"+45 98 24 73 70",
    "sg:postcode":"9490",
    "sg:province":"Danmark",
    "wof:name":"Brima M\u00f8bler ApS",
    "wof:placetype":"venue"
},
  "geometry": {"coordinates":[9.680557251,57.2123184204],"type":"Point"}
}