{
  "type": "Feature",
  "properties": {
    "addr:full":"Leder: Claus K\u00f8lln, P. A. Wedels Vej 2 Sk\u00e5rup Danmark 5881",
    "addr:housenumber":"2",
    "addr:postcode":"5881",
    "addr:street":"P. A. Wedels Vej",
    "iso:country":"DK",
    "sg:address":"Leder: Claus K\u00f8lln, P. A. Wedels Vej 2",
    "sg:city":"Sk\u00e5rup",
    "sg:orig_category":"Lokalarkiver",
    "sg:postcode":"5881",
    "sg:province":"Danmark",
    "wof:name":"Sk\u00e5rup Sogn Lokalhistoriske Arkiv",
    "wof:placetype":"venue"
},
  "geometry": {"coordinates":[10.7372999191,55.0686836243],"type":"Point"}
}