{
  "type": "Feature",
  "properties": {
    "iso:country":"DK",
    "sg:address":"Adelgade 6",
    "sg:city":"Ebeltoft",
    "sg:classifiers":[
        {
            "category":"Restaurant",
            "type":"Food & Drink"
        }
    ],
    "sg:phone":"+45 86 34 43 11",
    "sg:postcode":"8400",
    "sg:province":"Danmark",
    "wof:name":"Torvets Steak & Burger",
    "wof:placetype":"venue"
},
  "geometry": {"coordinates":[10.6777830124,56.1982841492],"type":"Point"}
}