{
  "type": "Feature",
  "properties": {
    "addr:full":"Fmd.: Lone Pedersen, Seminarievej 119 Ribe Danmark 6760",
    "addr:housenumber":"119",
    "addr:postcode":"6760",
    "addr:street":"Seminarievej",
    "iso:country":"DK",
    "sg:address":"Fmd.: Lone Pedersen, Seminarievej 119",
    "sg:city":"Ribe",
    "sg:orig_category":"Hobbybetonede foreninger",
    "sg:phone":"+45 75 42 23 85",
    "sg:postcode":"6760",
    "sg:province":"Danmark",
    "wof:name":"Det Jydske Haveselskab - Ribekredsen",
    "wof:placetype":"venue"
},
  "geometry": {"coordinates":[8.7656240463,55.3297042847],"type":"Point"}
}