{
  "type": "Feature",
  "properties": {
    "addr:full":"Louisevej 4 Brabrand Danmark 8220",
    "addr:housenumber":"4",
    "addr:postcode":"8220",
    "addr:street":"Louisevej",
    "iso:country":"DK",
    "sg:address":"Louisevej 4",
    "sg:city":"Brabrand",
    "sg:orig_category":"Slagter og viktualie",
    "sg:phone":"+45 86 25 25 35",
    "sg:postcode":"8220",
    "sg:province":"Danmark",
    "wof:name":"S\u00f8vangens Slagter",
    "wof:placetype":"venue"
},
  "geometry": {"coordinates":[10.1333990097,56.1524391174],"type":"Point"}
}