{
  "type": "Feature",
  "properties": {
    "addr:full":"Lerchenfeldtvej 102  Kalundborg Danmark 4400",
    "addr:housenumber":"102",
    "addr:postcode":"4400",
    "addr:street":"Lerchenfeldtvej",
    "iso:country":"DK",
    "sg:address":"Lerchenfeldtvej 102 ",
    "sg:city":"Kalundborg",
    "sg:classifiers":[
        {
            "category":"Farming",
            "subcategory":"Livestock Farm",
            "type":"Manufacturing & Wholesale Goods"
        }
    ],
    "sg:phone":"+45 59 51 01 57",
    "sg:postcode":"4400",
    "sg:province":"Danmark",
    "sg:tags":[
        "agriculture"
    ],
    "wof:name":"LERCHENFELD GODS I/S V/S\u00d8REN HOLM & JENS HOLM",
    "wof:placetype":"venue"
},
  "geometry": {"coordinates":[11.1009597778,55.7011413574],"type":"Point"}
}