{
  "type": "Feature",
  "properties": {
    "addr:full":"Mariagervej 354 Spentrup Danmark 8981",
    "addr:housenumber":"354",
    "addr:postcode":"8981",
    "addr:street":"Mariagervej",
    "iso:country":"DK",
    "sg:address":"Mariagervej 354",
    "sg:city":"Spentrup",
    "sg:orig_category":"Forsamlingshuse",
    "sg:phone":"+45 86 47 77 19",
    "sg:postcode":"8981",
    "sg:province":"Danmark",
    "wof:name":"Bjergby Forsamlingshus",
    "wof:placetype":"venue"
},
  "geometry": {"coordinates":[10.0095796585,56.5209999084],"type":"Point"}
}