{
  "type": "Feature",
  "properties": {
    "iso:country":"DK",
    "sg:address":"Uggel\u00f8se Bygade 108",
    "sg:city":"Lynge",
    "sg:orig_category":"Kirker",
    "sg:postcode":"3540",
    "sg:province":"Danmark",
    "wof:name":"Uggel\u00f8se Kirke",
    "wof:placetype":"venue"
},
  "geometry": {"coordinates":[12.2594127655,55.8389358521],"type":"Point"}
}