{
  "type": "Feature",
  "properties": {
    "addr:full":"Brovejen 35 Maribo Danmark 4930",
    "addr:housenumber":"35",
    "addr:postcode":"4930",
    "addr:street":"Brovejen",
    "iso:country":"DK",
    "sg:address":"Brovejen 35",
    "sg:city":"Maribo",
    "sg:orig_category":"Faglige organisationer og foreninger",
    "sg:phone":"+45 54 78 05 83",
    "sg:postcode":"4930",
    "sg:province":"Danmark",
    "wof:name":"Tr\u00e6-Industri-Byg afd. 31 Lolland-Falster",
    "wof:placetype":"venue"
},
  "geometry": {"coordinates":[11.4892301559,54.7764015198],"type":"Point"}
}