{
  "type": "Feature",
  "properties": {
    "addr:full":"Skivevej 61 Holstebro Danmark 7500",
    "addr:housenumber":"61",
    "addr:postcode":"7500",
    "addr:street":"Skivevej",
    "iso:country":"DK",
    "sg:address":"Skivevej 61",
    "sg:city":"Holstebro",
    "sg:orig_category":"Indramning",
    "sg:phone":"+45 97 41 48 00",
    "sg:postcode":"7500",
    "sg:province":"Danmark",
    "wof:name":"Maleri Huset",
    "wof:placetype":"venue"
},
  "geometry": {"coordinates":[8.6284093857,56.3688735962],"type":"Point"}
}