{
  "type": "Feature",
  "properties": {
    "addr:full":"S\u00f8ndergade 13 A Kolding Danmark 6000",
    "addr:housenumber":"13 a",
    "addr:postcode":"6000",
    "addr:street":"Sondergade",
    "iso:country":"DK",
    "sg:address":"S\u00f8ndergade 13 A",
    "sg:city":"Kolding",
    "sg:orig_category":"Lingeri",
    "sg:phone":"+45 75 53 17 25",
    "sg:postcode":"6000",
    "sg:province":"Danmark",
    "wof:name":"Columbine",
    "wof:placetype":"venue"
},
  "geometry": {"coordinates":[9.4729299545,55.4875526428],"type":"Point"}
}