{
  "type": "Feature",
  "properties": {
    "iso:country":"DK",
    "sg:address":"Eskildsgade 14",
    "sg:city":"Aakirkeby",
    "sg:orig_category":"Solcentre",
    "sg:phone":"+45 56 97 06 01",
    "sg:postcode":"3720",
    "sg:province":"Danmark",
    "wof:name":"Aakirkeby Solcenter",
    "wof:placetype":"venue"
},
  "geometry": {"coordinates":[14.9239835739,55.0706138611],"type":"Point"}
}