{
  "type": "Feature",
  "properties": {
    "addr:full":"Ved Skolen 2 Hirtshals Danmark 9850",
    "addr:housenumber":"2",
    "addr:postcode":"9850",
    "addr:street":"Ved Skolen",
    "iso:country":"DK",
    "sg:address":"Ved Skolen 2",
    "sg:city":"Hirtshals",
    "sg:orig_category":"Skolefritidsordninger",
    "sg:phone":"+45 99 56 52 30",
    "sg:postcode":"9850",
    "sg:province":"Danmark",
    "wof:name":"Hirtshals Skoles Fritidsordning Spiren",
    "wof:placetype":"venue"
},
  "geometry": {"coordinates":[9.9612541199,57.5877189636],"type":"Point"}
}