{
  "type": "Feature",
  "properties": {
    "addr:full":"v/ Ba Lam, Fr\u00f8g\u00e5rdsvej 16, st. th. Haslev Danmark 4690",
    "addr:housenumber":"16",
    "addr:postcode":"4690",
    "addr:street":"Frogaardsvej;St. Th.",
    "iso:country":"DK",
    "sg:address":"v/ Ba Lam, Fr\u00f8g\u00e5rdsvej 16, st. th.",
    "sg:city":"Haslev",
    "sg:orig_category":"Kulturelle foreninger",
    "sg:phone":"+45 56 31 35 96",
    "sg:postcode":"4690",
    "sg:province":"Danmark",
    "wof:name":"Vietnamesisk Kultur-Idr\u00e6tsforening i Haslev",
    "wof:placetype":"venue"
},
  "geometry": {"coordinates":[11.9678049088,55.3230895996],"type":"Point"}
}