{
  "type": "Feature",
  "properties": {
    "addr:full":"Hirsevej 23-25 Haderslev Danmark 6100",
    "addr:postcode":"23-25;6100",
    "addr:street":"Hirsevej",
    "iso:country":"DK",
    "sg:address":"Hirsevej 23-25",
    "sg:city":"Haderslev",
    "sg:orig_category":"Autoreparation og -service",
    "sg:phone":"+45 74 52 11 48",
    "sg:postcode":"6100",
    "sg:province":"Danmark",
    "wof:name":"Lageri-Schmidt",
    "wof:placetype":"venue"
},
  "geometry": {"coordinates":[9.4995031357,55.233795166],"type":"Point"}
}