{
  "type": "Feature",
  "properties": {
    "addr:full":"Gr\u00f8nsundsvej 266, Karleby Nyk\u00f8bing Danmark 4800",
    "addr:housenumber":"266",
    "addr:postcode":"4800",
    "addr:street":"Gronsundsvej",
    "iso:country":"DK",
    "sg:address":"Gr\u00f8nsundsvej 266, Karleby",
    "sg:city":"Nyk\u00f8bing",
    "sg:orig_category":"Fabrikker",
    "sg:phone":"+45 54 44 70 12",
    "sg:postcode":"4800",
    "sg:province":"Danmark",
    "sg:website":"www.bccn.dk",
    "wof:name":"BC Catering Nyk\u00f8bing F.",
    "wof:placetype":"venue"
},
  "geometry": {"coordinates":[23.2116909027,63.8170204163],"type":"Point"}
}