{
  "type": "Feature",
  "properties": {
    "addr:full":"Skolevej 6 B\u00e6lum Danmark 9574",
    "addr:housenumber":"6",
    "addr:postcode":"9574",
    "addr:street":"Skolevej",
    "iso:country":"DK",
    "sg:address":"Skolevej 6",
    "sg:city":"B\u00e6lum",
    "sg:orig_category":"Tandklinikker, Kommunale",
    "sg:phone":"+45 99 82 85 47",
    "sg:postcode":"9574",
    "sg:province":"Danmark",
    "wof:name":"B\u00f8rnetandklinikken",
    "wof:placetype":"venue"
},
  "geometry": {"coordinates":[-83.14971160890001,43.0994567871],"type":"Point"}
}