{
  "type": "Feature",
  "properties": {
    "addr:full":"Randersvej 56 Hobro Danmark 9500",
    "addr:housenumber":"56",
    "addr:postcode":"9500",
    "addr:street":"Randersvej",
    "iso:country":"DK",
    "sg:address":"Randersvej 56",
    "sg:city":"Hobro",
    "sg:orig_category":"Servicestationer",
    "sg:phone":"+45 98 52 07 78",
    "sg:postcode":"9500",
    "sg:province":"Danmark",
    "wof:name":"Statoil Servicecenter",
    "wof:placetype":"venue"
},
  "geometry": {"coordinates":[9.8022165298,56.6288566589],"type":"Point"}
}