{
  "type": "Feature",
  "properties": {
    "iso:country":"DK",
    "sg:address":"Gr\u00f8nnegade 3",
    "sg:city":"Horsens",
    "sg:classifiers":[
        {
            "category":"Restaurant",
            "type":"Food & Drink"
        }
    ],
    "sg:phone":"+45 75 62 69 00",
    "sg:postcode":"8700",
    "sg:province":"Danmark",
    "wof:name":"Oksen",
    "wof:placetype":"venue"
},
  "geometry": {"coordinates":[9.8453712463,55.8631324768],"type":"Point"}
}