{
  "type": "Feature",
  "properties": {
    "iso:country":"DK",
    "sg:address":"Holmensvej 2",
    "sg:city":"Frederikssund",
    "sg:orig_category":"Bilinspektion",
    "sg:phone":"+45 47 31 09 08",
    "sg:postcode":"3600",
    "sg:province":"Danmark",
    "sg:website":"www.bilsyn.dk",
    "wof:name":"Statens Bilinspektion",
    "wof:placetype":"venue"
},
  "geometry": {"coordinates":[12.065765,55.847839],"type":"Point"}
}