{
  "type": "Feature",
  "properties": {
    "addr:full":"Leder: Poul Knudsen, Genner Bygade 3, Genner R\u00f8dekro Danmark 6230",
    "addr:housenumber":"3",
    "addr:postcode":"6230",
    "addr:street":"Knudsen Genner Bygade",
    "iso:country":"DK",
    "sg:address":"Leder: Poul Knudsen, Genner Bygade 3, Genner",
    "sg:city":"R\u00f8dekro",
    "sg:orig_category":"Skolefritidsordninger",
    "sg:phone":"+45 74 69 86 66",
    "sg:postcode":"6230",
    "sg:province":"Danmark",
    "wof:name":"Genner Skoles Skolepasningsordning",
    "wof:placetype":"venue"
},
  "geometry": {"coordinates":[9.307510376,55.0235786438],"type":"Point"}
}