{
  "type": "Feature",
  "properties": {
    "iso:country":"DK",
    "sg:address":"K\u00f8gevej 52, 2.tv.",
    "sg:city":"Roskilde",
    "sg:orig_category":"Kunstmalere",
    "sg:phone":"+45 46 37 03 13",
    "sg:postcode":"4000",
    "sg:province":"Danmark",
    "sg:website":"www.hanne-kunst.dk",
    "wof:name":"R\u00f8rbech, Hanne",
    "wof:placetype":"venue"
},
  "geometry": {"coordinates":[12.0909376144,55.6404838562],"type":"Point"}
}