{
  "type": "Feature",
  "properties": {
    "iso:country":"DK",
    "sg:address":"Adm.: Lejerbo Lokalkontor, Nyg\u00e5rds Plads 9",
    "sg:city":"Br\u00f8ndby",
    "sg:orig_category":"Boligselskaber",
    "sg:phone":"+45 70 12 13 10",
    "sg:postcode":"2605",
    "sg:province":"Danmark",
    "wof:name":"Br\u00f8ndby Kommunes Boligselskab",
    "wof:placetype":"venue"
},
  "geometry": {"coordinates":[-97.02810668950001,34.2937583923],"type":"Point"}
}