{
  "type": "Feature",
  "properties": {
    "addr:full":"R\u00f8rsangervej 3 Viborg Danmark 8800",
    "addr:housenumber":"3",
    "addr:postcode":"8800",
    "addr:street":"Rorsangervej",
    "iso:country":"DK",
    "sg:address":"R\u00f8rsangervej 3",
    "sg:city":"Viborg",
    "sg:orig_category":"Daginstitution for voksne",
    "sg:phone":"+45 86 62 74 22",
    "sg:postcode":"8800",
    "sg:province":"Danmark",
    "wof:name":"Aktivitetshuset Ekkoh\u00f8j",
    "wof:placetype":"venue"
},
  "geometry": {"coordinates":[9.376241684,56.4441947937],"type":"Point"}
}