{
  "type": "Feature",
  "properties": {
    "addr:full":"Holmboes Alle 1 Horsens Danmark 8700",
    "addr:housenumber":"1",
    "addr:postcode":"8700",
    "addr:street":"Holmboes Alle",
    "iso:country":"DK",
    "sg:address":"Holmboes Alle 1",
    "sg:city":"Horsens",
    "sg:orig_category":"Finansiering",
    "sg:phone":"+45 70 22 25 52",
    "sg:postcode":"8700",
    "sg:province":"Danmark",
    "sg:website":"www.capitalis.dk",
    "wof:name":"Capitalis A/S",
    "wof:placetype":"venue"
},
  "geometry": {"coordinates":[9.8472757339,55.857749939],"type":"Point"}
}