{
  "type": "Feature",
  "properties": {
    "iso:country":"DK",
    "sg:address":"Middelfartvej 1",
    "sg:city":"Vissenbjerg",
    "sg:orig_category":"Servicestationer",
    "sg:phone":"+45 64 47 12 33",
    "sg:postcode":"5492",
    "sg:province":"Danmark",
    "wof:name":"Q8 Servicecenter",
    "wof:placetype":"venue"
},
  "geometry": {"coordinates":[10.1362199783,55.3897361755],"type":"Point"}
}