{
  "type": "Feature",
  "properties": {
    "addr:full":"Sofievej 5 Slagelse Danmark 4200",
    "addr:housenumber":"5",
    "addr:postcode":"4200",
    "addr:street":"Sofievej",
    "iso:country":"DK",
    "sg:address":"Sofievej 5",
    "sg:city":"Slagelse",
    "sg:classifiers":[
        {
            "category":"Professional",
            "subcategory":"Business Services",
            "type":"Services"
        }
    ],
    "sg:phone":"+45 58 50 00 60",
    "sg:postcode":"4200",
    "sg:province":"Danmark",
    "sg:tags":[
        "import",
        "vin"
    ],
    "wof:name":"Tiro Wine-Import",
    "wof:placetype":"venue"
},
  "geometry": {"coordinates":[11.321146965,55.3982276917],"type":"Point"}
}