{
  "type": "Feature",
  "properties": {
    "iso:country":"DK",
    "sg:address":"Skolevej 46, Herborg",
    "sg:city":"Videb\u00e6k",
    "sg:orig_category":"Kommunale folkeskoler",
    "sg:phone":"+45 97 17 17 01",
    "sg:postcode":"6920",
    "sg:province":"Danmark",
    "sg:website":"www.herborg-skole.dk",
    "wof:name":"Herborg Skole",
    "wof:placetype":"venue"
},
  "geometry": {"coordinates":[8.7436800003,55.9904136658],"type":"Point"}
}