{
  "type": "Feature",
  "properties": {
    "addr:full":"St\u00e5lvej 3 Kolding Danmark 6000",
    "addr:housenumber":"3",
    "addr:postcode":"6000",
    "addr:street":"Staalvej",
    "iso:country":"DK",
    "sg:address":"St\u00e5lvej 3",
    "sg:city":"Kolding",
    "sg:orig_category":"Fabrikker",
    "sg:phone":"+45 75 50 33 11",
    "sg:postcode":"6000",
    "sg:province":"Danmark",
    "wof:name":"Decra A/S",
    "wof:placetype":"venue"
},
  "geometry": {"coordinates":[9.4397735596,55.5102043152],"type":"Point"}
}