{
  "type": "Feature",
  "properties": {
    "addr:full":"Assensvej 129 Stenstrup Danmark 5771",
    "addr:housenumber":"129",
    "addr:postcode":"5771",
    "addr:street":"Assensvej",
    "iso:country":"DK",
    "sg:address":"Assensvej 129",
    "sg:city":"Stenstrup",
    "sg:orig_category":"Non-Classified Establishments",
    "sg:phone":"+45 62 26 11 60",
    "sg:postcode":"5771",
    "sg:province":"Danmark",
    "wof:name":"Daghjemmet Egebjerghus",
    "wof:placetype":"venue"
},
  "geometry": {"coordinates":[10.5099620819,55.1233329773],"type":"Point"}
}