{
  "type": "Feature",
  "properties": {
    "addr:full":"Koldingvej 52, Kalvslund Ribe Danmark 6760",
    "addr:housenumber":"52",
    "addr:postcode":"6760",
    "addr:street":"Koldingvej",
    "iso:country":"DK",
    "sg:address":"Koldingvej 52, Kalvslund",
    "sg:city":"Ribe",
    "sg:orig_category":"Havebrugsmaskiner",
    "sg:phone":"+45 75 43 70 98",
    "sg:postcode":"6760",
    "sg:province":"Danmark",
    "wof:name":"Klavslund Pl\u00e6neklipper",
    "wof:placetype":"venue"
},
  "geometry": {"coordinates":[8.7656240463,55.3297042847],"type":"Point"}
}