{
  "type": "Feature",
  "properties": {
    "iso:country":"DK",
    "sg:address":"Storegade 32",
    "sg:city":"Outrup",
    "sg:classifiers":[
        {
            "category":"Banks & Credit Unions",
            "subcategory":"Bank",
            "type":"Services"
        }
    ],
    "sg:phone":"+45 75 25 13 77",
    "sg:postcode":"6855",
    "sg:province":"Danmark",
    "sg:tags":[
        "banker"
    ],
    "wof:name":"Outrup Andelskasse",
    "wof:placetype":"venue"
},
  "geometry": {"coordinates":[8.3438138962,55.720287323],"type":"Point"}
}