{
  "type": "Feature",
  "properties": {
    "addr:full":"Vestre Landevej 118 N\u00f8rreballe Danmark 4951",
    "addr:housenumber":"118",
    "addr:postcode":"4951",
    "addr:street":"Vestre Landevej",
    "iso:country":"DK",
    "sg:address":"Vestre Landevej 118",
    "sg:city":"N\u00f8rreballe",
    "sg:orig_category":"Autoforhandlere",
    "sg:phone":"+45 54 78 90 35",
    "sg:postcode":"4951",
    "sg:province":"Danmark",
    "wof:name":"M. J. Automobiler N\u00f8rreballe ApS",
    "wof:placetype":"venue"
},
  "geometry": {"coordinates":[6.8762898445,62.4602813721],"type":"Point"}
}