{
  "type": "Feature",
  "properties": {
    "iso:country":"DK",
    "sg:address":"Kredsleder: Carl G\u00f8rlyk, Hyldebjerg 50",
    "sg:city":"Kirke Hvals\u00f8",
    "sg:orig_category":"Spejderkorps",
    "sg:phone":"+45 46 40 70 01",
    "sg:postcode":"4330",
    "sg:province":"Danmark",
    "wof:name":"FDF Hvals\u00f8",
    "wof:placetype":"venue"
},
  "geometry": {"coordinates":[-83.8121185303,34.0058288574],"type":"Point"}
}