{
  "type": "Feature",
  "properties": {
    "addr:full":"Hvedev\u00e6nget 2 N\u00e6stved Danmark 4700",
    "addr:housenumber":"2",
    "addr:postcode":"4700",
    "addr:street":"Hvedevaenget",
    "iso:country":"DK",
    "sg:address":"Hvedev\u00e6nget 2",
    "sg:city":"N\u00e6stved",
    "sg:orig_category":"Diners transportables",
    "sg:phone":"+45 55 72 79 13",
    "sg:postcode":"4700",
    "sg:province":"Danmark",
    "sg:website":"www.gourmet-hjornet.dk",
    "wof:name":"Gourmet-Hj\u00f8rnet",
    "wof:placetype":"venue"
},
  "geometry": {"coordinates":[-73.5254440308,41.9771537781],"type":"Point"}
}