{
  "type": "Feature",
  "properties": {
    "iso:country":"DK",
    "sg:address":"Fmd.: Kjeld N\u00f8rbye Jensen, Egerisvej 17, Faster",
    "sg:city":"Skjern",
    "sg:orig_category":"Hobbybetonede foreninger",
    "sg:phone":"+45 97 36 40 34",
    "sg:postcode":"6900",
    "sg:province":"Danmark",
    "wof:name":"Skjern og Omegns Fjerkr\u00e6klub",
    "wof:placetype":"venue"
},
  "geometry": {"coordinates":[8.492972374,55.9485740662],"type":"Point"}
}