{
  "type": "Feature",
  "properties": {
    "addr:full":"Fladbjergg\u00e5rdvej 17, Ravnebjerg Odense SV Danmark 5250",
    "addr:housenumber":"17",
    "addr:postcode":"5250",
    "addr:street":"Fladbjerggaardvej;Ravnebjerg",
    "iso:country":"DK",
    "sg:address":"Fladbjergg\u00e5rdvej 17, Ravnebjerg",
    "sg:city":"Odense SV",
    "sg:orig_category":"Erhvervslokaler, Udlejning af",
    "sg:phone":"+45 65 96 77 71",
    "sg:postcode":"5250",
    "sg:province":"Danmark",
    "wof:name":"Pedersen, Keld og Dorte Bolving I/S",
    "wof:placetype":"venue"
},
  "geometry": {"coordinates":[10.3153953552,55.3362998962],"type":"Point"}
}