{
  "type": "Feature",
  "properties": {
    "addr:full":"Silkeborgvej 54 Them Danmark 8653",
    "addr:housenumber":"54",
    "addr:postcode":"8653",
    "addr:street":"Silkeborgvej",
    "iso:country":"DK",
    "sg:address":"Silkeborgvej 54",
    "sg:city":"Them",
    "sg:orig_category":"Advokater",
    "sg:phone":"+45 87 22 80 80",
    "sg:postcode":"8653",
    "sg:province":"Danmark",
    "wof:name":"Kaalund & Partnere, Advokataktieselskabet",
    "wof:placetype":"venue"
},
  "geometry": {"coordinates":[9.5488100052,56.0947608948],"type":"Point"}
}