{
  "type": "Feature",
  "properties": {
    "iso:country":"DK",
    "sg:address":"Hunderupvej 17, Postboks 1219",
    "sg:orig_category":"Gymnasier og HF-kurser",
    "sg:phone":"+45 66 14 18 38",
    "sg:postcode":"5100",
    "wof:name":"Fyns HF-kursus",
    "wof:placetype":"venue"
},
  "geometry": {"coordinates":[10.3908996582,55.3960914612],"type":"Point"}
}