{
  "type": "Feature",
  "properties": {
    "addr:full":"Sludstrupvej 1 B, Sludstrup Slagelse Danmark 4200",
    "addr:housenumber":"1 b",
    "addr:postcode":"4200",
    "addr:street":"Sludstrupvej;Sludstrup",
    "iso:country":"DK",
    "sg:address":"Sludstrupvej 1 B, Sludstrup",
    "sg:city":"Slagelse",
    "sg:orig_category":"Forsamlingshuse",
    "sg:phone":"+45 58 58 41 22",
    "sg:postcode":"4200",
    "sg:province":"Danmark",
    "wof:name":"Sludstrup Forsamlingshus",
    "wof:placetype":"venue"
},
  "geometry": {"coordinates":[11.3569850922,55.4050865173],"type":"Point"}
}