{
  "type": "Feature",
  "properties": {
    "addr:full":"Elmegade 33 Kalundborg Danmark 4400",
    "addr:housenumber":"33",
    "addr:postcode":"4400",
    "addr:street":"Elmegade",
    "iso:country":"DK",
    "sg:address":"Elmegade 33",
    "sg:city":"Kalundborg",
    "sg:orig_category":"Autoforhandlere",
    "sg:phone":"+45 59 51 09 46",
    "sg:postcode":"4400",
    "sg:province":"Danmark",
    "wof:name":"Nissan/Daewoo Kalundborg",
    "wof:placetype":"venue"
},
  "geometry": {"coordinates":[11.1026639938,55.6793174744],"type":"Point"}
}