{
  "type": "Feature",
  "properties": {
    "addr:full":"N\u00f8rregade 1 Fjerritslev Danmark 9690",
    "addr:housenumber":"1",
    "addr:postcode":"9690",
    "addr:street":"Norregade",
    "iso:country":"DK",
    "sg:address":"N\u00f8rregade 1",
    "sg:city":"Fjerritslev",
    "sg:orig_category":"Autoreparation og -service",
    "sg:phone":"+45 98 21 15 88",
    "sg:postcode":"9690",
    "sg:province":"Danmark",
    "wof:name":"Frederiksen, Poul A.",
    "wof:placetype":"venue"
},
  "geometry": {"coordinates":[9.2656440735,57.0884666443],"type":"Point"}
}