{
  "type": "Feature",
  "properties": {
    "addr:full":"\u00c5boulevarden 88 st \u00c5rhus C Danmark 8000",
    "addr:housenumber":"88",
    "addr:postcode":"8000",
    "addr:street":"Aaboulevarden;St",
    "iso:country":"DK",
    "sg:address":"\u00c5boulevarden 88 st",
    "sg:city":"\u00c5rhus C",
    "sg:orig_category":"Alternativ behandling",
    "sg:phone":"+45 86 15 04 84",
    "sg:postcode":"8000",
    "sg:province":"Danmark",
    "wof:name":"Rolfing \u00c5rhus",
    "wof:placetype":"venue"
},
  "geometry": {"coordinates":[4.717400074,49.7588005066],"type":"Point"}
}