{
  "type": "Feature",
  "properties": {
    "iso:country":"DK",
    "sg:address":"S\u00f8ndergade 15",
    "sg:city":"Stubbek\u00f8bing",
    "sg:orig_category":"Broderi",
    "sg:phone":"+45 54 44 14 11",
    "sg:postcode":"4850",
    "sg:province":"Danmark",
    "wof:name":"Hanne's Broderi- og Sycenter",
    "wof:placetype":"venue"
},
  "geometry": {"coordinates":[-114.0767440796,46.4432487488],"type":"Point"}
}