{
  "type": "Feature",
  "properties": {
    "iso:country":"DK",
    "sg:address":"Hovedvejen 118",
    "sg:city":"Glostrup",
    "sg:orig_category":"Diskoteker",
    "sg:phone":"+45 43 45 31 38",
    "sg:postcode":"2600",
    "sg:province":"Danmark",
    "wof:name":"Mirrow",
    "wof:placetype":"venue"
},
  "geometry": {"coordinates":[12.3972597122,55.665977478],"type":"Point"}
}