{
  "type": "Feature",
  "properties": {
    "addr:full":"Hovedgaden 60 Svinninge Danmark 4520",
    "addr:housenumber":"60",
    "addr:postcode":"4520",
    "addr:street":"Hovedgaden",
    "iso:country":"DK",
    "sg:address":"Hovedgaden 60",
    "sg:city":"Svinninge",
    "sg:orig_category":"Revisorer",
    "sg:phone":"+45 59 26 59 11",
    "sg:postcode":"4520",
    "sg:province":"Danmark",
    "sg:website":"www.fdr.dk/abm-revision",
    "wof:name":"ABM-Revision",
    "wof:placetype":"venue"
},
  "geometry": {"coordinates":[11.4590587616,55.7218933105],"type":"Point"}
}