{
  "type": "Feature",
  "properties": {
    "addr:full":"Trymsvej 14 Silkeborg Danmark 8600",
    "addr:housenumber":"14",
    "addr:postcode":"8600",
    "addr:street":"Trymsvej",
    "iso:country":"DK",
    "sg:address":"Trymsvej 14",
    "sg:city":"Silkeborg",
    "sg:orig_category":"Engros handel",
    "sg:phone":"+45 86 82 75 14",
    "sg:postcode":"8600",
    "sg:province":"Danmark",
    "wof:name":"Jensen, Anna Charlotte",
    "wof:placetype":"venue"
},
  "geometry": {"coordinates":[9.5135850906,56.1721153259],"type":"Point"}
}