{
  "type": "Feature",
  "properties": {
    "iso:country":"DK",
    "sg:address":"Vestergade 3, Guderup",
    "sg:city":"Nordborg",
    "sg:orig_category":"Bagere",
    "sg:phone":"+45 74 45 83 28",
    "sg:postcode":"6430",
    "sg:province":"Danmark",
    "wof:name":"Henrik's Bageri",
    "wof:placetype":"venue"
},
  "geometry": {"coordinates":[9.749623,55.054276],"type":"Point"}
}