{
  "type": "Feature",
  "properties": {
    "iso:country":"DK",
    "sg:address":"Strandvejen 4",
    "sg:city":"Slagelse",
    "sg:orig_category":"Bogbinderier",
    "sg:phone":"+45 58 52 10 07",
    "sg:postcode":"4200",
    "sg:province":"Danmark",
    "wof:name":"Binderup's Bogbinderi",
    "wof:placetype":"venue"
},
  "geometry": {"coordinates":[11.3379526138,55.3998451233],"type":"Point"}
}