{
  "type": "Feature",
  "properties": {
    "addr:full":"Fuglevangsvej 58 Horsens Danmark 8700",
    "addr:housenumber":"58",
    "addr:postcode":"8700",
    "addr:street":"Fuglevangsvej",
    "iso:country":"DK",
    "sg:address":"Fuglevangsvej 58",
    "sg:city":"Horsens",
    "sg:orig_category":"Maskinfabrikker",
    "sg:phone":"+45 75 62 03 88",
    "sg:postcode":"8700",
    "sg:province":"Danmark",
    "wof:name":"Dan-Tubes - BRS A/S",
    "wof:placetype":"venue"
},
  "geometry": {"coordinates":[9.8110103607,55.8586883545],"type":"Point"}
}