{
  "type": "Feature",
  "properties": {
    "addr:full":"Fmd.: Claus J. M\u00f8ller, Skivevej 163, Hvam Holstebro Danmark 7500",
    "addr:housenumber":"163",
    "addr:postcode":"7500",
    "addr:street":"Skivevej",
    "iso:country":"DK",
    "sg:address":"Fmd.: Claus J. M\u00f8ller, Skivevej 163, Hvam",
    "sg:city":"Holstebro",
    "sg:orig_category":"Husflidsforeninger",
    "sg:phone":"+45 97 46 13 87",
    "sg:postcode":"7500",
    "sg:province":"Danmark",
    "wof:name":"Hjerm Husflidsskole",
    "wof:placetype":"venue"
},
  "geometry": {"coordinates":[8.6202583313,56.3625221252],"type":"Point"}
}