{
  "type": "Feature",
  "properties": {
    "iso:country":"DK",
    "sg:address":"F\u00e6lledvej 61",
    "sg:city":"Roskilde",
    "sg:orig_category":"Slagter og viktualie",
    "sg:phone":"+45 46 35 26 78",
    "sg:postcode":"4000",
    "sg:province":"Danmark",
    "wof:name":"F\u00e6lledvejens Slagterforretning",
    "wof:placetype":"venue"
},
  "geometry": {"coordinates":[12.0623893738,55.6352233887],"type":"Point"}
}