{
  "type": "Feature",
  "properties": {
    "addr:full":"Danmarksgade 12 Frederikshavn Danmark 9900",
    "addr:housenumber":"12",
    "addr:postcode":"9900",
    "addr:street":"Danmarksgade",
    "iso:country":"DK",
    "sg:address":"Danmarksgade 12",
    "sg:city":"Frederikshavn",
    "sg:orig_category":"Advokater",
    "sg:phone":"+45 70 15 10 00",
    "sg:postcode":"9900",
    "sg:province":"Danmark",
    "sg:website":"www.hjulmand-kaptain.dk",
    "wof:name":"Hjulmand & Kaptain, Advokatfirma",
    "wof:placetype":"venue"
},
  "geometry": {"coordinates":[10.5387678146,57.4446029663],"type":"Point"}
}