{
  "type": "Feature",
  "properties": {
    "iso:country":"DK",
    "sg:address":"v/ Henning Larsen, S\u00f8vangvej 6, Hjortlund",
    "sg:city":"Grindsted",
    "sg:orig_category":"Soldaterforeninger",
    "sg:phone":"+45 75 34 81 65",
    "sg:postcode":"7200",
    "sg:province":"Danmark",
    "wof:name":"KFUM' Soldatervennekreds for Sdr. Omme og Filskov",
    "wof:placetype":"venue"
},
  "geometry": {"coordinates":[8.9288702011,55.7560272217],"type":"Point"}
}