{
  "type": "Feature",
  "properties": {
    "addr:full":"Energivej 10 Esbjerg Danmark 6700",
    "addr:housenumber":"10",
    "addr:postcode":"6700",
    "addr:street":"Energivej",
    "iso:country":"DK",
    "sg:address":"Energivej 10",
    "sg:city":"Esbjerg",
    "sg:classifiers":[
        {
            "category":"Building & Trades",
            "subcategory":"Electrical",
            "type":"Services"
        }
    ],
    "sg:phone":"+45 75 13 64 16",
    "sg:postcode":"6700",
    "sg:province":"Danmark",
    "sg:tags":[
        "distributor"
    ],
    "wof:name":"B.T. Centralen A/S",
    "wof:placetype":"venue"
},
  "geometry": {"coordinates":[8.4985980988,55.4641265869],"type":"Point"}
}