{
  "type": "Feature",
  "properties": {
    "iso:country":"DK",
    "sg:address":"Klemenskervej 40, R\u00f8",
    "sg:city":"Gudhjem",
    "sg:orig_category":"Smedemestre",
    "sg:phone":"+45 56 48 40 14",
    "sg:postcode":"3760",
    "sg:province":"Danmark",
    "wof:name":"R\u00f8 Smedeforretning",
    "wof:placetype":"venue"
},
  "geometry": {"coordinates":[15.1870470047,55.3205566406],"type":"Point"}
}