{
  "type": "Feature",
  "properties": {
    "iso:country":"DK",
    "sg:address":"Langagervej 17",
    "sg:city":"Kalundborg",
    "sg:orig_category":"Bilinspektion",
    "sg:postcode":"4400",
    "sg:province":"Danmark",
    "wof:name":"Statens Bilinspektion",
    "wof:placetype":"venue"
},
  "geometry": {"coordinates":[11.120631,55.664234],"type":"Point"}
}