{
  "type": "Feature",
  "properties": {
    "addr:full":"Knagm\u00f8llevej 17, Skudstrup R\u00f8dding Danmark 6630",
    "addr:housenumber":"17",
    "addr:postcode":"6630",
    "addr:street":"Knagmollevej",
    "iso:country":"DK",
    "sg:address":"Knagm\u00f8llevej 17, Skudstrup",
    "sg:city":"R\u00f8dding",
    "sg:orig_category":"Stenhuggere",
    "sg:phone":"+45 74 84 87 81",
    "sg:postcode":"6630",
    "sg:province":"Danmark",
    "wof:name":"Jessen T\u00f8mrer- og Snedkerforretning, Bent Riis",
    "wof:placetype":"venue"
},
  "geometry": {"coordinates":[9.2022953033,55.3564414978],"type":"Point"}
}