{
  "type": "Feature",
  "properties": {
    "iso:country":"DK",
    "sg:address":"Klampenborgvej 215 B",
    "sg:city":"Kongens Lyngby",
    "sg:orig_category":"Kulturcentre",
    "sg:phone":"+45 45 97 37 00",
    "sg:postcode":"2800",
    "sg:province":"Danmark",
    "wof:name":"Lyngby Kulturhus",
    "wof:placetype":"venue"
},
  "geometry": {"coordinates":[12.5073356628,55.7714042664],"type":"Point"}
}