{
  "type": "Feature",
  "properties": {
    "addr:full":"v/ Niels N\u00f8rgaard, Viggo Rothes Vej 23 Charlottenlund Danmark 2920",
    "addr:housenumber":"23",
    "addr:postcode":"2920",
    "addr:street":"Viggo Rothes Vej",
    "iso:country":"DK",
    "sg:address":"v/ Niels N\u00f8rgaard, Viggo Rothes Vej 23",
    "sg:city":"Charlottenlund",
    "sg:orig_category":"Hobbybetonede foreninger",
    "sg:phone":"+45 39 40 66 52",
    "sg:postcode":"2920",
    "sg:province":"Danmark",
    "wof:name":"Austin A30/35 Owners Club",
    "wof:placetype":"venue"
},
  "geometry": {"coordinates":[12.5721197128,55.7532615662],"type":"Point"}
}