{
  "type": "Feature",
  "properties": {
    "addr:full":"Jellebakken 2 - 8 Risskov Danmark 8240",
    "addr:housenumber":"2 8",
    "addr:postcode":"8240",
    "addr:street":"Jellebakken",
    "iso:country":"DK",
    "sg:address":"Jellebakken 2 - 8",
    "sg:city":"Risskov",
    "sg:orig_category":"Fritidshjem",
    "sg:phone":"+45 86 21 41 33",
    "sg:postcode":"8240",
    "sg:province":"Danmark",
    "wof:name":"Jellebakken, Fritidshjem",
    "wof:placetype":"venue"
},
  "geometry": {"coordinates":[10.2137956619,56.2026062012],"type":"Point"}
}