{
  "type": "Feature",
  "properties": {
    "addr:full":"Magisterparken 24 Aalborg Danmark 9000",
    "addr:housenumber":"24",
    "addr:postcode":"9000",
    "addr:street":"Magisterparken",
    "iso:country":"DK",
    "sg:address":"Magisterparken 24",
    "sg:city":"Aalborg",
    "sg:orig_category":"Fritidscentre",
    "sg:phone":"+45 98 14 38 65",
    "sg:postcode":"9000",
    "sg:province":"Danmark",
    "wof:name":"Fritidscentret Griffen",
    "wof:placetype":"venue"
},
  "geometry": {"coordinates":[9.9406356812,57.0282249451],"type":"Point"}
}