{
  "type": "Feature",
  "properties": {
    "addr:full":"v/Tove Guldb\u00e6k, Sofievej 8 Hellerup Danmark 2900",
    "addr:housenumber":"8",
    "addr:postcode":"2900",
    "addr:street":"Sofievej",
    "iso:country":"DK",
    "sg:address":"v/Tove Guldb\u00e6k, Sofievej 8",
    "sg:city":"Hellerup",
    "sg:orig_category":"Loger",
    "sg:phone":"+45 49 17 64 14",
    "sg:postcode":"2900",
    "sg:province":"Danmark",
    "wof:name":"Esperg\u00e6rde-Humleb\u00e6k Rotary Klub",
    "wof:placetype":"venue"
},
  "geometry": {"coordinates":[12.5788497925,55.7413787842],"type":"Point"}
}