{
  "type": "Feature",
  "properties": {
    "addr:full":"Rypehusene 19 Albertslund Danmark 2620",
    "addr:housenumber":"19",
    "addr:postcode":"2620",
    "addr:street":"Rypehusene",
    "iso:country":"DK",
    "sg:address":"Rypehusene 19",
    "sg:city":"Albertslund",
    "sg:orig_category":"Fritidshjem",
    "sg:phone":"+45 43 64 88 67",
    "sg:postcode":"2620",
    "sg:province":"Danmark",
    "sg:website":"www.kastanjehuset.dk",
    "wof:name":"Kastanjehuset Fritidshjem",
    "wof:placetype":"venue"
},
  "geometry": {"coordinates":[12.3538827896,55.6747093201],"type":"Point"}
}