{
  "type": "Feature",
  "properties": {
    "iso:country":"DK",
    "sg:address":"Henrik Rungs Vej 3",
    "sg:city":"Frederikshavn",
    "sg:orig_category":"Blikkenslagere",
    "sg:phone":"+45 98 43 95 55",
    "sg:postcode":"9900",
    "sg:province":"Danmark",
    "wof:name":"VVS Energi - Ole Madsen",
    "wof:placetype":"venue"
},
  "geometry": {"coordinates":[10.502977,57.433777],"type":"Point"}
}