{
  "type": "Feature",
  "properties": {
    "addr:full":"Dosseringen 3 Stubbek\u00f8bing Danmark 4850",
    "addr:housenumber":"3",
    "addr:postcode":"4850",
    "addr:street":"Dosseringen",
    "iso:country":"DK",
    "sg:address":"Dosseringen 3",
    "sg:city":"Stubbek\u00f8bing",
    "sg:orig_category":"Biblioteker",
    "sg:phone":"+45 54 44 15 29",
    "sg:postcode":"4850",
    "sg:province":"Danmark",
    "sg:website":"www.stubbekoebingkom.dk/biblio/main.htm",
    "wof:name":"Stubbek\u00f8bing bibliotek",
    "wof:placetype":"venue"
},
  "geometry": {"coordinates":[-114.0767440796,46.4432487488],"type":"Point"}
}