{
  "type": "Feature",
  "properties": {
    "addr:full":"Jens Warmings Vej 59 K\u00f8benhavn S Danmark 2300",
    "addr:housenumber":"59",
    "addr:postcode":"2300",
    "addr:street":"Jens Warmings Vej;Kobenhavn S Danmark",
    "iso:country":"DK",
    "sg:address":"Jens Warmings Vej 59",
    "sg:city":"K\u00f8benhavn S",
    "sg:orig_category":"Alternativ behandling",
    "sg:phone":"+45 32 55 36 63",
    "sg:postcode":"2300",
    "sg:province":"Danmark",
    "wof:name":"Lohse, Lillian",
    "wof:placetype":"venue"
},
  "geometry": {"coordinates":[-82.591506958,38.4456291199],"type":"Point"}
}