{
  "type": "Feature",
  "properties": {
    "addr:full":"Dronning Margrethes Vej 4 D Roskilde Danmark 4000",
    "addr:housenumber":"4 d",
    "addr:postcode":"4000",
    "addr:street":"Dronning Margrethes Vej",
    "iso:country":"DK",
    "sg:address":"Dronning Margrethes Vej 4 D",
    "sg:city":"Roskilde",
    "sg:orig_category":"Antikvariater",
    "sg:phone":"+45 46 35 89 13",
    "sg:postcode":"4000",
    "sg:province":"Danmark",
    "wof:name":"Hedenborgs Antikvariat",
    "wof:placetype":"venue"
},
  "geometry": {"coordinates":[12.0841169357,55.6430015564],"type":"Point"}
}