{
  "type": "Feature",
  "properties": {
    "addr:full":"Tangmosevej 1 K\u00f8ge Danmark 4600",
    "addr:housenumber":"1",
    "addr:postcode":"4600",
    "addr:street":"Tangmosevej",
    "iso:country":"DK",
    "sg:address":"Tangmosevej 1",
    "sg:city":"K\u00f8ge",
    "sg:orig_category":"Skolefritidsordninger",
    "sg:phone":"+45 56 63 03 45",
    "sg:postcode":"4600",
    "sg:province":"Danmark",
    "wof:name":"Strandg\u00e5rdens SFO I og II, Sponk",
    "wof:placetype":"venue"
},
  "geometry": {"coordinates":[12.187163353,55.465171814],"type":"Point"}
}