{
  "type": "Feature",
  "properties": {
    "iso:country":"DK",
    "sg:address":"Vestergade 13",
    "sg:city":"Grindsted",
    "sg:orig_category":"Supermarkeder",
    "sg:phone":"+45 76 72 00 95",
    "sg:postcode":"7200",
    "sg:province":"Danmark",
    "wof:name":"Rema 1000",
    "wof:placetype":"venue"
},
  "geometry": {"coordinates":[8.9255914688,55.7577285767],"type":"Point"}
}