{
  "type": "Feature",
  "properties": {
    "addr:full":"S\u00f8nder Hjermvej 4 Hjerm Danmark 7560",
    "addr:housenumber":"4",
    "addr:postcode":"7560",
    "addr:street":"Hjermvej",
    "iso:country":"DK",
    "sg:address":"S\u00f8nder Hjermvej 4",
    "sg:city":"Hjerm",
    "sg:orig_category":"Hundepensioner",
    "sg:phone":"+45 97 46 42 54",
    "sg:postcode":"7560",
    "sg:province":"Danmark",
    "wof:name":"Hunde- og Kattepension Hvidbjerg",
    "wof:placetype":"venue"
},
  "geometry": {"coordinates":[8.6731557846,56.4065093994],"type":"Point"}
}