{
  "type": "Feature",
  "properties": {
    "addr:full":"Vestergade 2 Otterup Danmark 5450",
    "addr:housenumber":"2",
    "addr:postcode":"5450",
    "addr:street":"Vestergade",
    "iso:country":"DK",
    "sg:address":"Vestergade 2",
    "sg:city":"Otterup",
    "sg:orig_category":"Servicestationer",
    "sg:phone":"+45 64 82 16 40",
    "sg:postcode":"5450",
    "sg:province":"Danmark",
    "wof:name":"Haahr Benzin A/S",
    "wof:placetype":"venue"
},
  "geometry": {"coordinates":[10.3988962173,55.5124168396],"type":"Point"}
}