{
  "type": "Feature",
  "properties": {
    "addr:full":"Rolf Krakes Vej 55, Bolbro Odense V Danmark 5200",
    "addr:housenumber":"55",
    "addr:postcode":"5200",
    "addr:street":"Rolf Krakes Vej",
    "iso:country":"DK",
    "sg:address":"Rolf Krakes Vej 55, Bolbro",
    "sg:city":"Odense V",
    "sg:orig_category":"Autoreparation og -service",
    "sg:phone":"+45 66 16 85 20",
    "sg:postcode":"5200",
    "sg:province":"Danmark",
    "wof:name":"Bolbro Autov\u00e6rksted",
    "wof:placetype":"venue"
},
  "geometry": {"coordinates":[10.2629547119,55.4070854187],"type":"Point"}
}