{
  "type": "Feature",
  "properties": {
    "iso:country":"DK",
    "sg:address":"Finsensvej 39 A, 3.",
    "sg:city":"Frederiksberg",
    "sg:orig_category":"Kulturelle foreninger",
    "sg:phone":"+45 38 10 97 96",
    "sg:postcode":"2000",
    "sg:province":"Danmark",
    "sg:website":"www.thorvaldsenteatret.dk",
    "wof:name":"Thorvaldsenteatret",
    "wof:placetype":"venue"
},
  "geometry": {"coordinates":[12.5137529373,55.68151474],"type":"Point"}
}