{
  "type": "Feature",
  "properties": {
    "addr:full":"Skyggevej 8 Bording Danmark 7441",
    "addr:housenumber":"8",
    "addr:postcode":"7441",
    "addr:street":"Skyggevej",
    "iso:country":"DK",
    "sg:address":"Skyggevej 8",
    "sg:city":"Bording",
    "sg:orig_category":"Murermestre",
    "sg:phone":"+45 40 79 14 11",
    "sg:postcode":"7441",
    "sg:province":"Danmark",
    "wof:name":"BJ Byg",
    "wof:placetype":"venue"
},
  "geometry": {"coordinates":[9.2266511917,56.1499176025],"type":"Point"}
}