{
  "type": "Feature",
  "properties": {
    "addr:full":"Fmd.: Jens Hansen, Nyvangvej 5, Toghale T\u00f8nder Danmark 6270",
    "addr:housenumber":"5",
    "addr:postcode":"6270",
    "addr:street":"Nyvangvej",
    "iso:country":"DK",
    "sg:address":"Fmd.: Jens Hansen, Nyvangvej 5, Toghale",
    "sg:city":"T\u00f8nder",
    "sg:orig_category":"Spejderkorps",
    "sg:phone":"+45 74 73 81 89",
    "sg:postcode":"6270",
    "sg:province":"Danmark",
    "wof:name":"M\u00f8gelt\u00f8nder kreds FDF",
    "wof:placetype":"venue"
},
  "geometry": {"coordinates":[8.8009996414,54.9552383423],"type":"Point"}
}