{
  "type": "Feature",
  "properties": {
    "iso:country":"DK",
    "sg:address":"Engvej",
    "sg:city":"Ejstrupholm",
    "sg:orig_category":"Kirker",
    "sg:postcode":"7361",
    "sg:province":"Danmark",
    "wof:name":"Gludsted Kirke",
    "wof:placetype":"venue"
},
  "geometry": {"coordinates":[9.3080396652,56.0324134827],"type":"Point"}
}