{
  "type": "Feature",
  "properties": {
    "iso:country":"DK",
    "sg:address":"Gotlandsvej 8",
    "sg:city":"Horsens",
    "sg:orig_category":"Kolonial en gros",
    "sg:phone":"+45 75 64 80 55",
    "sg:postcode":"8700",
    "sg:province":"Danmark",
    "wof:name":"Dagrofa S/Engros A/S",
    "wof:placetype":"venue"
},
  "geometry": {"coordinates":[9.814655304,55.8521003723],"type":"Point"}
}