{
  "type": "Feature",
  "properties": {
    "addr:full":"Fmd.: Ole Kornum, Hjortdalvej 62, Hjortdal Fjerritslev Danmark 9690",
    "addr:housenumber":"62",
    "addr:postcode":"9690",
    "addr:street":"Hjortdalvej;Hjortdal",
    "iso:country":"DK",
    "sg:address":"Fmd.: Ole Kornum, Hjortdalvej 62, Hjortdal",
    "sg:city":"Fjerritslev",
    "sg:orig_category":"Transformatorforeninger",
    "sg:phone":"+45 98 21 71 61",
    "sg:postcode":"9690",
    "sg:province":"Danmark",
    "wof:name":"Transformatorforeningen, Hjortdal",
    "wof:placetype":"venue"
},
  "geometry": {"coordinates":[9.2667350769,57.0882301331],"type":"Point"}
}