{
  "type": "Feature",
  "properties": {
    "addr:full":"Jellebakken 17 Risskov Danmark 8240",
    "addr:housenumber":"17",
    "addr:postcode":"8240",
    "addr:street":"Jellebakken",
    "iso:country":"DK",
    "sg:address":"Jellebakken 17",
    "sg:city":"Risskov",
    "sg:orig_category":"Tandklinikker, Kommunale",
    "sg:phone":"+45 86 21 23 75",
    "sg:postcode":"8240",
    "sg:province":"Danmark",
    "wof:name":"Tandklinikken Jellebakkeskolen",
    "wof:placetype":"venue"
},
  "geometry": {"coordinates":[10.21737957,56.2028541565],"type":"Point"}
}