{
  "type": "Feature",
  "properties": {
    "addr:full":"Adelgade 56 Skanderborg Danmark 8660",
    "addr:housenumber":"56",
    "addr:postcode":"8660",
    "addr:street":"Adelgade",
    "iso:country":"DK",
    "sg:address":"Adelgade 56",
    "sg:city":"Skanderborg",
    "sg:orig_category":"Fodterapeuter",
    "sg:phone":"+45 86 52 27 12",
    "sg:postcode":"8660",
    "sg:province":"Danmark",
    "wof:name":"S\u00f8rensen, Bodil",
    "wof:placetype":"venue"
},
  "geometry": {"coordinates":[9.9326086044,56.032169342],"type":"Point"}
}