{
  "type": "Feature",
  "properties": {
    "addr:full":"Strandgade 30 Grenaa Danmark 8500",
    "addr:housenumber":"30",
    "addr:postcode":"8500",
    "addr:street":"Strandgade",
    "iso:country":"DK",
    "sg:address":"Strandgade 30",
    "sg:city":"Grenaa",
    "sg:orig_category":"Dyrehandlere",
    "sg:phone":"+45 87 79 90 20",
    "sg:postcode":"8500",
    "sg:province":"Danmark",
    "wof:name":"Dyrenes ABC",
    "wof:placetype":"venue"
},
  "geometry": {"coordinates":[10.9173536301,56.4096488953],"type":"Point"}
}