{
  "type": "Feature",
  "properties": {
    "addr:full":"L\u00f8ven 25 Aalborg SV Danmark 9200",
    "addr:housenumber":"25",
    "addr:postcode":"9200",
    "addr:street":"Loven",
    "iso:country":"DK",
    "sg:address":"L\u00f8ven 25",
    "sg:city":"Aalborg SV",
    "sg:orig_category":"Revisorer",
    "sg:phone":"+45 98 18 70 00",
    "sg:postcode":"9200",
    "sg:province":"Danmark",
    "wof:name":"Deloitte & Touche",
    "wof:placetype":"venue"
},
  "geometry": {"coordinates":[9.8752765656,57.0024261475],"type":"Point"}
}