{
  "type": "Feature",
  "properties": {
    "addr:full":"N\u00f8rregade 25 Kjellerup Danmark 8620",
    "addr:housenumber":"25",
    "addr:postcode":"8620",
    "addr:street":"Norregade",
    "iso:country":"DK",
    "sg:address":"N\u00f8rregade 25",
    "sg:city":"Kjellerup",
    "sg:orig_category":"Hestehandlere",
    "sg:phone":"+45 86 88 13 18",
    "sg:postcode":"8620",
    "sg:province":"Danmark",
    "wof:name":"Pedersen, Niels",
    "wof:placetype":"venue"
},
  "geometry": {"coordinates":[9.4290657043,56.2916183472],"type":"Point"}
}