{
  "type": "Feature",
  "properties": {
    "addr:full":"Munkerisvej 15 Odense M Danmark 5230",
    "addr:housenumber":"15",
    "addr:postcode":"5230",
    "addr:street":"Munkerisvej",
    "iso:country":"DK",
    "sg:address":"Munkerisvej 15",
    "sg:city":"Odense M",
    "sg:orig_category":"Pizzeriaer",
    "sg:phone":"+45 66 11 58 06",
    "sg:postcode":"5230",
    "sg:province":"Danmark",
    "wof:name":"Valentino Pizza Bar",
    "wof:placetype":"venue"
},
  "geometry": {"coordinates":[10.3979091644,55.381526947],"type":"Point"}
}