{
  "type": "Feature",
  "properties": {
    "iso:country":"DK",
    "sg:address":"v/ Susanne Vonsgart, Tved 164",
    "sg:city":"T\u00f8nder",
    "sg:orig_category":"Loger",
    "sg:phone":"+45 74 72 53 48",
    "sg:postcode":"6270",
    "sg:province":"Danmark",
    "wof:name":"S\u00f8sterloge nr. 45 Tre Gyldne Ringe",
    "wof:placetype":"venue"
},
  "geometry": {"coordinates":[8.6816797256,57.055480957],"type":"Point"}
}