{
  "type": "Feature",
  "properties": {
    "iso:country":"DK",
    "sg:address":"Torvestr\u00e6det 4",
    "sg:city":"Skovlunde",
    "sg:orig_category":"Cykler",
    "sg:phone":"+45 44 84 12 34",
    "sg:postcode":"2740",
    "sg:province":"Danmark",
    "wof:name":"Skovlunde Cykler",
    "wof:placetype":"venue"
},
  "geometry": {"coordinates":[12.4006900787,55.7212486267],"type":"Point"}
}