{
  "type": "Feature",
  "properties": {
    "addr:full":"Jomfrustien 25 Haderslev Danmark 6100",
    "addr:housenumber":"25",
    "addr:postcode":"6100",
    "addr:street":"Jomfrustien",
    "iso:country":"DK",
    "sg:address":"Jomfrustien 25",
    "sg:city":"Haderslev",
    "sg:orig_category":"Solcentre",
    "sg:postcode":"6100",
    "sg:province":"Danmark",
    "wof:name":"Koala Sun",
    "wof:placetype":"venue"
},
  "geometry": {"coordinates":[9.4954891205,55.2512130737],"type":"Point"}
}