{
  "type": "Feature",
  "properties": {
    "iso:country":"DK",
    "sg:address":"\u00d8rb\u00e6kvej 10",
    "sg:city":"Ferritslev",
    "sg:orig_category":"Arkitekter",
    "sg:phone":"+45 65 98 10 89",
    "sg:postcode":"5863",
    "sg:province":"Danmark",
    "sg:website":"www.poul-e-kristensen.dk",
    "wof:name":"Kristensen, Arkitektfirmaet Poul E.",
    "wof:placetype":"venue"
},
  "geometry": {"coordinates":[10.5689496994,55.3201446533],"type":"Point"}
}