{
  "type": "Feature",
  "properties": {
    "addr:full":"Pilevej 11 Sunds Danmark 7451",
    "addr:housenumber":"11",
    "addr:postcode":"7451",
    "addr:street":"Pilevej",
    "iso:country":"DK",
    "sg:address":"Pilevej 11",
    "sg:city":"Sunds",
    "sg:orig_category":"Fotografer",
    "sg:phone":"+45 97 14 17 60",
    "sg:postcode":"7451",
    "sg:province":"Danmark",
    "wof:name":"Sunds Foto",
    "wof:placetype":"venue"
},
  "geometry": {"coordinates":[9.0205621719,56.2054595947],"type":"Point"}
}