{
  "type": "Feature",
  "properties": {
    "addr:full":"Viborggade 27 Frederikshavn Danmark 9900",
    "addr:housenumber":"27",
    "addr:postcode":"9900",
    "addr:street":"Viborggade",
    "iso:country":"DK",
    "sg:address":"Viborggade 27",
    "sg:city":"Frederikshavn",
    "sg:orig_category":"Systuer",
    "sg:phone":"+45 98 42 38 37",
    "sg:postcode":"9900",
    "sg:province":"Danmark",
    "wof:name":"Strikkestue",
    "wof:placetype":"venue"
},
  "geometry": {"coordinates":[10.5208492279,57.454875946],"type":"Point"}
}