{
  "type": "Feature",
  "properties": {
    "addr:full":"Roskildevej 262, Kongstrup Vipper\u00f8d Danmark 4390",
    "addr:housenumber":"262",
    "addr:postcode":"4390",
    "addr:street":"Roskildevej;Kongstrup Vipperod Danmark",
    "iso:country":"DK",
    "sg:address":"Roskildevej 262, Kongstrup",
    "sg:city":"Vipper\u00f8d",
    "sg:orig_category":"Legestuer",
    "sg:phone":"+45 59 18 16 81",
    "sg:postcode":"4390",
    "sg:province":"Danmark",
    "wof:name":"Vipper\u00f8d Legestue (Vipper\u00f8d Boldklub)",
    "wof:placetype":"venue"
},
  "geometry": {"coordinates":[11.770031929,55.6723098755],"type":"Point"}
}