{
  "type": "Feature",
  "properties": {
    "addr:full":"Br\u00f8ddegade 8 Gudhjem Danmark 3760",
    "addr:housenumber":"8",
    "addr:postcode":"3760",
    "addr:street":"Broddegade",
    "iso:country":"DK",
    "sg:address":"Br\u00f8ddegade 8",
    "sg:city":"Gudhjem",
    "sg:orig_category":"Murermestre",
    "sg:phone":"+45 56 48 54 03",
    "sg:postcode":"3760",
    "sg:province":"Danmark",
    "sg:website":"www.gudhjem-murerforretning.dk",
    "wof:name":"Gudhjem Murerforretning",
    "wof:placetype":"venue"
},
  "geometry": {"coordinates":[14.9718294144,55.2090377808],"type":"Point"}
}