{
  "type": "Feature",
  "properties": {
    "iso:country":"DK",
    "sg:address":"Fyrrev\u00e6nget 14",
    "sg:city":"Hirtshals",
    "sg:orig_category":"Malermestre",
    "sg:phone":"+45 98 94 41 91",
    "sg:postcode":"9850",
    "sg:province":"Danmark",
    "wof:name":"M\u00f8ller, Malerfirmaet Flemming",
    "wof:placetype":"venue"
},
  "geometry": {"coordinates":[9.9599866867,57.5884933472],"type":"Point"}
}