{
  "type": "Feature",
  "properties": {
    "iso:country":"DK",
    "sg:address":"Sommerfuglevej 8 ",
    "sg:city":"Kolding",
    "sg:classifiers":[
        {
            "category":"Utilities",
            "subcategory":"Telephone",
            "type":"Services"
        }
    ],
    "sg:phone":"+45 75 52 62 33",
    "sg:postcode":"6000",
    "sg:province":"Danmark",
    "sg:tags":[
        "telecommunication"
    ],
    "wof:name":"KOLDING TRIKOTAGEFABRIK 2000 APS",
    "wof:placetype":"venue"
},
  "geometry": {"coordinates":[9.5070991516,55.5066757202],"type":"Point"}
}