{
  "type": "Feature",
  "properties": {
    "addr:full":"Fmd.: Knud Gormose, H\u00f8jlandsvej 9 Kalundborg Danmark 4400",
    "addr:housenumber":"9",
    "addr:postcode":"4400",
    "addr:street":"Knud Gormose Hojlandsvej",
    "iso:country":"DK",
    "sg:address":"Fmd.: Knud Gormose, H\u00f8jlandsvej 9",
    "sg:city":"Kalundborg",
    "sg:orig_category":"Politiske foreninger, \u00c3\u02dcvrige",
    "sg:phone":"+45 59 51 60 24",
    "sg:postcode":"4400",
    "sg:province":"Danmark",
    "wof:name":"Venstreforeningernes Samarbejdsudvalg for Kalundborg Kommune",
    "wof:placetype":"venue"
},
  "geometry": {"coordinates":[11.0934085846,55.6797485352],"type":"Point"}
}