{
  "type": "Feature",
  "properties": {
    "addr:full":"Bykildevej 1 Valby Danmark 2500",
    "addr:housenumber":"1",
    "addr:postcode":"2500",
    "addr:street":"Bykildevej",
    "iso:country":"DK",
    "sg:address":"Bykildevej 1",
    "sg:city":"Valby",
    "sg:orig_category":"Hundetrimning",
    "sg:phone":"+45 36 16 22 13",
    "sg:postcode":"2500",
    "sg:province":"Danmark",
    "sg:website":"www.valbyhundesalon.dk",
    "wof:name":"Valby Hundesalon",
    "wof:placetype":"venue"
},
  "geometry": {"coordinates":[12.5187416077,55.6666793823],"type":"Point"}
}