{
  "type": "Feature",
  "properties": {
    "addr:full":"Kai Lindbergs Gade 61 Hanstholm Danmark 7730",
    "addr:housenumber":"61",
    "addr:postcode":"7730",
    "addr:street":"Kai Lindbergs Gade",
    "iso:country":"DK",
    "sg:address":"Kai Lindbergs Gade 61",
    "sg:city":"Hanstholm",
    "sg:orig_category":"Non-Classified Establishments",
    "sg:phone":"+45 97 96 12 75",
    "sg:postcode":"7730",
    "sg:province":"Danmark",
    "wof:name":"Mobil Marineservice",
    "wof:placetype":"venue"
},
  "geometry": {"coordinates":[8.5999670029,57.1191711426],"type":"Point"}
}