{
  "type": "Feature",
  "properties": {
    "iso:country":"DK",
    "sg:address":"Dalgas Alle 36",
    "sg:city":"Skive",
    "sg:orig_category":"Kiosker",
    "sg:phone":"+45 97 51 06 60",
    "sg:postcode":"7800",
    "sg:province":"Danmark",
    "wof:name":"Superd\u00f8gneren",
    "wof:placetype":"venue"
},
  "geometry": {"coordinates":[9.0160503387,56.5499382019],"type":"Point"}
}