{
  "type": "Feature",
  "properties": {
    "iso:country":"DK",
    "sg:address":"Stationstorvet, Centervej 76, 1.",
    "sg:city":"Vallensb\u00e6k Strand",
    "sg:orig_category":"Gymnastikskoler",
    "sg:phone":"+45 43 53 00 65",
    "sg:postcode":"2665",
    "sg:province":"Danmark",
    "sg:website":"www.hardwork.dk",
    "wof:name":"Hard Work Studio",
    "wof:placetype":"venue"
},
  "geometry": {"coordinates":[-122.35903167719999,48.9091377258],"type":"Point"}
}