{
  "type": "Feature",
  "properties": {
    "addr:full":"Niels Finsensvej 2 Vejle Danmark 7100",
    "addr:housenumber":"2",
    "addr:postcode":"7100",
    "addr:street":"Niels Finsensvej",
    "iso:country":"DK",
    "sg:address":"Niels Finsensvej 2",
    "sg:city":"Vejle",
    "sg:orig_category":"Autoforhandlere",
    "sg:phone":"+45 72 11 66 00",
    "sg:postcode":"7100",
    "sg:province":"Danmark",
    "wof:name":"Hessel A/S, Ejner",
    "wof:placetype":"venue"
},
  "geometry": {"coordinates":[9.570982933,55.7228279114],"type":"Point"}
}