{
  "type": "Feature",
  "properties": {
    "addr:full":"Danmarksgade 50 Fredericia Danmark 7000",
    "addr:housenumber":"50",
    "addr:postcode":"7000",
    "addr:street":"Danmarksgade",
    "iso:country":"DK",
    "sg:address":"Danmarksgade 50",
    "sg:city":"Fredericia",
    "sg:orig_category":"Begravelsesforretninger",
    "sg:phone":"+45 75 91 31 14",
    "sg:postcode":"7000",
    "sg:province":"Danmark",
    "wof:name":"Begravelseforretningen Danmark",
    "wof:placetype":"venue"
},
  "geometry": {"coordinates":[9.760239,55.566959],"type":"Point"}
}