{
  "type": "Feature",
  "properties": {
    "iso:country":"DK",
    "sg:address":"S\u00f8ndergade 1",
    "sg:city":"Vildbjerg",
    "sg:orig_category":"Sundhedspleje",
    "sg:phone":"+45 99 92 92 92",
    "sg:postcode":"7480",
    "sg:province":"Danmark",
    "wof:name":"Sundhedsplejen i Treh\u00f8je Kommune",
    "wof:placetype":"venue"
},
  "geometry": {"coordinates":[8.7672424316,56.196937561],"type":"Point"}
}