{
  "type": "Feature",
  "properties": {
    "addr:full":"Tobaksvejen 21 S\u00f8borg Danmark 2860",
    "addr:housenumber":"21",
    "addr:postcode":"2860",
    "addr:street":"Tobaksvejen",
    "iso:country":"DK",
    "sg:address":"Tobaksvejen 21",
    "sg:city":"S\u00f8borg",
    "sg:classifiers":[
        {
            "category":"Building & Trades",
            "subcategory":"Construction",
            "type":"Services"
        }
    ],
    "sg:phone":"+45 39 57 83 00",
    "sg:postcode":"2860",
    "sg:province":"Danmark",
    "sg:tags":[
        "ventilation"
    ],
    "sg:website":"www.sibt.dk",
    "wof:name":"Siemens Building Technologies A/S Building Automation/HVAC Products",
    "wof:placetype":"venue"
},
  "geometry": {"coordinates":[-101.26155090330001,35.6824836731],"type":"Point"}
}