{
  "type": "Feature",
  "properties": {
    "addr:full":"Lillegade 31 Grenaa Danmark 8500",
    "addr:housenumber":"31",
    "addr:postcode":"8500",
    "addr:street":"Lillegade",
    "iso:country":"DK",
    "sg:address":"Lillegade 31",
    "sg:city":"Grenaa",
    "sg:orig_category":"Bagere",
    "sg:phone":"+45 86 32 01 27",
    "sg:postcode":"8500",
    "sg:province":"Danmark",
    "wof:name":"Ib's Bageri",
    "wof:placetype":"venue"
},
  "geometry": {"coordinates":[10.8722038269,56.4147872925],"type":"Point"}
}