{
  "type": "Feature",
  "properties": {
    "iso:country":"DK",
    "sg:address":"Algade 46",
    "sg:city":"Middelfart",
    "sg:orig_category":"Biografer",
    "sg:phone":"+45 64 41 00 24",
    "sg:postcode":"5500",
    "sg:province":"Danmark",
    "wof:name":"Middelfart Bio 1 + 2",
    "wof:placetype":"venue"
},
  "geometry": {"coordinates":[9.732116,55.505234],"type":"Point"}
}