{
  "type": "Feature",
  "properties": {
    "addr:full":"Teglg\u00e5rdsvej 21 B Charlottenlund Danmark 2920",
    "addr:housenumber":"21 b",
    "addr:postcode":"2920",
    "addr:street":"Teglgaardsvej",
    "iso:country":"DK",
    "sg:address":"Teglg\u00e5rdsvej 21 B",
    "sg:city":"Charlottenlund",
    "sg:orig_category":"Integrerede institutioner",
    "sg:phone":"+45 39 64 64 11",
    "sg:postcode":"2920",
    "sg:province":"Danmark",
    "wof:name":"Galaksen Daginstitution",
    "wof:placetype":"venue"
},
  "geometry": {"coordinates":[12.5916633606,55.761756897],"type":"Point"}
}