{
  "type": "Feature",
  "properties": {
    "addr:full":"Tofteb\u00e6ksvej 8, 2. Kongens Lyngby Danmark 2800",
    "addr:housenumber":"8 2",
    "addr:postcode":"2800",
    "addr:street":"Toftebaeksvej",
    "iso:country":"DK",
    "sg:address":"Tofteb\u00e6ksvej 8, 2.",
    "sg:city":"Kongens Lyngby",
    "sg:orig_category":"Tandklinikker, Kommunale",
    "sg:phone":"+45 45 97 32 43",
    "sg:postcode":"2800",
    "sg:province":"Danmark",
    "wof:name":"Tandreguleringsklinikken",
    "wof:placetype":"venue"
},
  "geometry": {"coordinates":[12.5039319992,55.7720069885],"type":"Point"}
}