{
  "type": "Feature",
  "properties": {
    "addr:full":"S\u00e6byholmsvej 43 Valby Danmark 2500",
    "addr:housenumber":"43",
    "addr:postcode":"2500",
    "addr:street":"Saebyholmsvej",
    "iso:country":"DK",
    "sg:address":"S\u00e6byholmsvej 43",
    "sg:city":"Valby",
    "sg:orig_category":"Arkitekter",
    "sg:phone":"+45 38 71 31 63",
    "sg:postcode":"2500",
    "sg:province":"Danmark",
    "wof:name":"Gaard, K V Jensen",
    "wof:placetype":"venue"
},
  "geometry": {"coordinates":[12.4905700684,55.6764602661],"type":"Point"}
}