{
  "type": "Feature",
  "properties": {
    "addr:full":"Flyndervej 6, Havneby R\u00f8m\u00f8 Danmark 6792",
    "addr:housenumber":"6",
    "addr:postcode":"6792",
    "addr:street":"Flyndervej",
    "iso:country":"DK",
    "sg:address":"Flyndervej 6, Havneby",
    "sg:city":"R\u00f8m\u00f8",
    "sg:orig_category":"Maskinfabrikker",
    "sg:phone":"+45 74 75 52 46",
    "sg:postcode":"6792",
    "sg:province":"Danmark",
    "wof:name":"R\u00f8m\u00f8 V\u00e6rft og Maskinfabrik",
    "wof:placetype":"venue"
},
  "geometry": {"coordinates":[8.5544652939,55.0871963501],"type":"Point"}
}