{
  "type": "Feature",
  "properties": {
    "addr:full":"Assensvej 8, Nr. Broby Broby Danmark 5672",
    "addr:housenumber":"8",
    "addr:postcode":"5672",
    "addr:street":"Assensvej",
    "iso:country":"DK",
    "sg:address":"Assensvej 8, Nr. Broby",
    "sg:city":"Broby",
    "sg:orig_category":"Autoreparation og -service",
    "sg:phone":"+45 62 63 20 70",
    "sg:postcode":"5672",
    "sg:province":"Danmark",
    "wof:name":"Autog\u00e5rden",
    "wof:placetype":"venue"
},
  "geometry": {"coordinates":[10.3131303787,55.2695846558],"type":"Point"}
}