{
  "type": "Feature",
  "properties": {
    "iso:country":"DK",
    "sg:address":"Rimmersvej 58",
    "sg:city":"Ry",
    "sg:orig_category":"Kontormontering",
    "sg:phone":"+45 86 89 88 01",
    "sg:postcode":"8680",
    "sg:province":"Danmark",
    "wof:name":"Ry Kontor-Center - Hans & Grete",
    "wof:placetype":"venue"
},
  "geometry": {"coordinates":[9.6986732483,56.0673751831],"type":"Point"}
}