{
  "type": "Feature",
  "properties": {
    "addr:full":"Sct. Michaels Gade 4 Kolding Danmark 6000",
    "addr:housenumber":"4",
    "addr:postcode":"6000",
    "addr:street":"Sct. Michaels Gade",
    "iso:country":"DK",
    "sg:address":"Sct. Michaels Gade 4",
    "sg:city":"Kolding",
    "sg:orig_category":"Private skoler",
    "sg:phone":"+45 75 52 28 34",
    "sg:postcode":"6000",
    "sg:province":"Danmark",
    "wof:name":"Sct. Michaels Skole",
    "wof:placetype":"venue"
},
  "geometry": {"coordinates":[9.4664916992,55.4861984253],"type":"Point"}
}