{
  "type": "Feature",
  "properties": {
    "iso:country":"DK",
    "sg:address":"L\u00e6rkebakken 10",
    "sg:city":"K\u00f8benhavn NV",
    "sg:orig_category":"Designere",
    "sg:phone":"+45 38 28 47 67",
    "sg:postcode":"2400",
    "sg:province":"Danmark",
    "wof:name":"Gudiksen, L.M.",
    "wof:placetype":"venue"
},
  "geometry": {"coordinates":[-117.02272033689999,38.5024604797],"type":"Point"}
}