{
  "type": "Feature",
  "properties": {
    "addr:full":"Fortebakken 1 Risskov Danmark 8240",
    "addr:housenumber":"1",
    "addr:postcode":"8240",
    "addr:street":"Fortebakken",
    "iso:country":"DK",
    "sg:address":"Fortebakken 1",
    "sg:city":"Risskov",
    "sg:orig_category":"Biblioteker",
    "sg:phone":"+45 87 41 93 00",
    "sg:postcode":"8240",
    "sg:province":"Danmark",
    "wof:name":"Risskov Bibliotek",
    "wof:placetype":"venue"
},
  "geometry": {"coordinates":[10.2233753204,56.1937484741],"type":"Point"}
}