{
  "type": "Feature",
  "properties": {
    "addr:full":"Storegade 7 Broager Danmark 6310",
    "addr:housenumber":"7",
    "addr:postcode":"6310",
    "addr:street":"Storegade",
    "iso:country":"DK",
    "sg:address":"Storegade 7",
    "sg:city":"Broager",
    "sg:orig_category":"Ejendomshandel",
    "sg:phone":"+45 74 44 16 98",
    "sg:postcode":"6310",
    "sg:province":"Danmark",
    "wof:name":"home Broager/S\u00f8nderborg",
    "wof:placetype":"venue"
},
  "geometry": {"coordinates":[9.6747140884,54.8895683289],"type":"Point"}
}