{
  "type": "Feature",
  "properties": {
    "addr:full":"Jernbanegade 2 A Bramming Danmark 6740",
    "addr:housenumber":"2 a",
    "addr:postcode":"6740",
    "addr:street":"Jernbanegade",
    "iso:country":"DK",
    "sg:address":"Jernbanegade 2 A",
    "sg:city":"Bramming",
    "sg:orig_category":"Kiosker",
    "sg:phone":"+45 75 17 29 73",
    "sg:postcode":"6740",
    "sg:province":"Danmark",
    "wof:name":"City Kiosken",
    "wof:placetype":"venue"
},
  "geometry": {"coordinates":[8.7020196915,55.4648399353],"type":"Point"}
}