{
  "type": "Feature",
  "properties": {
    "iso:country":"DK",
    "sg:address":"Idr\u00e6tsvej 9",
    "sg:city":"Hurup",
    "sg:orig_category":"Legestuer",
    "sg:phone":"+45 26 56 68 58",
    "sg:postcode":"7760",
    "sg:province":"Danmark",
    "wof:name":"Hurup Legestue",
    "wof:placetype":"venue"
},
  "geometry": {"coordinates":[8.4147863388,56.7543945312],"type":"Point"}
}