{
  "type": "Feature",
  "properties": {
    "addr:full":"Pile Alle 6 Ribe Danmark 6760",
    "addr:housenumber":"6",
    "addr:postcode":"6760",
    "addr:street":"Pile Alle",
    "iso:country":"DK",
    "sg:address":"Pile Alle 6",
    "sg:city":"Ribe",
    "sg:orig_category":"Handicap-daginstitutioner",
    "sg:phone":"+45 75 42 08 11",
    "sg:postcode":"6760",
    "sg:province":"Danmark",
    "wof:name":"Dagcentret \u00c5holmen",
    "wof:placetype":"venue"
},
  "geometry": {"coordinates":[8.7714986801,55.3252792358],"type":"Point"}
}