{
  "type": "Feature",
  "properties": {
    "addr:full":"\u00d8stergaards Plads 14 Glamsbjerg Danmark 5620",
    "addr:housenumber":"14",
    "addr:postcode":"5620",
    "addr:street":"Ostergaards Plads",
    "iso:country":"DK",
    "sg:address":"\u00d8stergaards Plads 14",
    "sg:city":"Glamsbjerg",
    "sg:orig_category":"Arkitekter",
    "sg:phone":"+45 64 72 11 14",
    "sg:postcode":"5620",
    "sg:province":"Danmark",
    "wof:name":"Christian ApS, Arkitektfirmaet S\u00f8ren",
    "wof:placetype":"venue"
},
  "geometry": {"coordinates":[10.1063137054,55.2780151367],"type":"Point"}
}