{
  "type": "Feature",
  "properties": {
    "addr:full":"Boelsmosevej 7 Oure Danmark 5883",
    "addr:housenumber":"7",
    "addr:postcode":"5883",
    "addr:street":"Boelsmosevej",
    "iso:country":"DK",
    "sg:address":"Boelsmosevej 7",
    "sg:city":"Oure",
    "sg:orig_category":"Kattepensioner",
    "sg:phone":"+45 62 28 28 29",
    "sg:postcode":"5883",
    "sg:province":"Danmark",
    "wof:name":"Garfields Kattepension",
    "wof:placetype":"venue"
},
  "geometry": {"coordinates":[10.7468948364,55.1261444092],"type":"Point"}
}