{
  "type": "Feature",
  "properties": {
    "addr:full":"Industrivej 16  Ringe Danmark 5750",
    "addr:housenumber":"16",
    "addr:postcode":"5750",
    "addr:street":"Industrivej",
    "iso:country":"DK",
    "sg:address":"Industrivej 16 ",
    "sg:city":"Ringe",
    "sg:classifiers":[
        {
            "category":"Manufacturing",
            "subcategory":"Tools & Machinery",
            "type":"Manufacturing & Wholesale Goods"
        }
    ],
    "sg:phone":"+45 62 62 12 16",
    "sg:postcode":"5750",
    "sg:province":"Danmark",
    "sg:tags":[
        "environment",
        "equipment",
        "-"
    ],
    "wof:name":"ST\u00c5L & PLAST A/S",
    "wof:placetype":"venue"
},
  "geometry": {"coordinates":[10.4855051041,55.2498321533],"type":"Point"}
}