{
  "type": "Feature",
  "properties": {
    "addr:full":"Taastrupg\u00e5rdsvej 32 Taastrup Danmark 2630",
    "addr:housenumber":"32",
    "addr:postcode":"2630",
    "addr:street":"Taastrupgaardsvej",
    "iso:country":"DK",
    "sg:address":"Taastrupg\u00e5rdsvej 32",
    "sg:city":"Taastrup",
    "sg:orig_category":"Lastvogne",
    "sg:phone":"+45 43 55 58 00",
    "sg:postcode":"2630",
    "sg:province":"Danmark",
    "wof:name":"Sommer A/S, O.",
    "wof:placetype":"venue"
},
  "geometry": {"coordinates":[12.2848043442,55.6548538208],"type":"Point"}
}