{
  "type": "Feature",
  "properties": {
    "addr:full":"Brog\u00e5rdsvej 44 - 46 Gentofte Danmark 2820",
    "addr:housenumber":"44 46",
    "addr:postcode":"2820",
    "addr:street":"Brogaardsvej",
    "iso:country":"DK",
    "sg:address":"Brog\u00e5rdsvej 44 - 46",
    "sg:city":"Gentofte",
    "sg:orig_category":"Autoforhandlere",
    "sg:phone":"+45 39 75 00 00",
    "sg:postcode":"2820",
    "sg:province":"Danmark",
    "wof:name":"Krogsgaard-Jensen Automobiler A/S, Toyota",
    "wof:placetype":"venue"
},
  "geometry": {"coordinates":[12.535243988,55.7541465759],"type":"Point"}
}