{
  "type": "Feature",
  "properties": {
    "addr:full":"Vadestedet 15, R\u00e5dvad Kolding Danmark 6000",
    "addr:housenumber":"15",
    "addr:postcode":"6000",
    "addr:street":"Vadestedet;Raadvad",
    "iso:country":"DK",
    "sg:address":"Vadestedet 15, R\u00e5dvad",
    "sg:city":"Kolding",
    "sg:orig_category":"Fotografer",
    "sg:phone":"+45 75 56 85 75",
    "sg:postcode":"6000",
    "sg:province":"Danmark",
    "wof:name":"Sig Fotografi, Steen",
    "wof:placetype":"venue"
},
  "geometry": {"coordinates":[9.4733953476,55.4863586426],"type":"Point"}
}