{
  "type": "Feature",
  "properties": {
    "addr:full":"Storegade 5 B Hinnerup Danmark 8382",
    "addr:housenumber":"5 b",
    "addr:postcode":"8382",
    "addr:street":"Storegade",
    "iso:country":"DK",
    "sg:address":"Storegade 5 B",
    "sg:city":"Hinnerup",
    "sg:orig_category":"Optikere",
    "sg:phone":"+45 86 91 14 16",
    "sg:postcode":"8382",
    "sg:province":"Danmark",
    "wof:name":"Hinnerup Specialoptik",
    "wof:placetype":"venue"
},
  "geometry": {"coordinates":[10.061917305,56.2639579773],"type":"Point"}
}