{
  "type": "Feature",
  "properties": {
    "addr:full":"L\u00e5sbygade 15 - 17 Kolding Danmark 6000",
    "addr:housenumber":"15 17",
    "addr:postcode":"6000",
    "addr:street":"Laasbygade",
    "iso:country":"DK",
    "sg:address":"L\u00e5sbygade 15 - 17",
    "sg:city":"Kolding",
    "sg:orig_category":"Farve og tapet",
    "sg:phone":"+45 75 52 08 33",
    "sg:postcode":"6000",
    "sg:province":"Danmark",
    "wof:name":"Ove's Farver & Gardiner",
    "wof:placetype":"venue"
},
  "geometry": {"coordinates":[9.4708919525,55.4919586182],"type":"Point"}
}