{
  "type": "Feature",
  "properties": {
    "iso:country":"DK",
    "sg:address":"Bispevej 4",
    "sg:city":"K\u00f8benhavn NV",
    "sg:orig_category":"Ventiler",
    "sg:phone":"+45 38 10 44 77",
    "sg:postcode":"2400",
    "sg:province":"Danmark",
    "sg:website":"www.dikkers.dk",
    "wof:name":"Dikkers G & Co",
    "wof:placetype":"venue"
},
  "geometry": {"coordinates":[-117.02272033689999,38.5024604797],"type":"Point"}
}