{
  "type": "Feature",
  "properties": {
    "addr:full":"Fmd.: Bodil Thomsen, Vardevej 76 Skjern Danmark 6900",
    "addr:housenumber":"76",
    "addr:postcode":"6900",
    "addr:street":"Vardevej",
    "iso:country":"DK",
    "sg:address":"Fmd.: Bodil Thomsen, Vardevej 76",
    "sg:city":"Skjern",
    "sg:orig_category":"Husflidsforeninger",
    "sg:phone":"+45 97 35 23 69",
    "sg:postcode":"6900",
    "sg:province":"Danmark",
    "wof:name":"Skjern Husmoderforening",
    "wof:placetype":"venue"
},
  "geometry": {"coordinates":[8.492972374,55.9485740662],"type":"Point"}
}