{
  "type": "Feature",
  "properties": {
    "addr:full":"v/ Kim Saxman, Vedb\u00e6kgade 13, st. K\u00f8benhavn N Danmark 2200",
    "addr:housenumber":"13",
    "addr:postcode":"2200",
    "addr:street":"Vedbaekgade",
    "iso:country":"DK",
    "sg:address":"v/ Kim Saxman, Vedb\u00e6kgade 13, st.",
    "sg:city":"K\u00f8benhavn N",
    "sg:orig_category":"Marskandisere",
    "sg:phone":"+45 35 82 23 91",
    "sg:postcode":"2200",
    "sg:province":"Danmark",
    "wof:name":"Midg\u00e5rd Milj\u00f8",
    "wof:placetype":"venue"
},
  "geometry": {"coordinates":[-94.2628860474,47.8184127808],"type":"Point"}
}