{
  "type": "Feature",
  "properties": {
    "iso:country":"DK",
    "sg:address":"v/ Teknisk Forvaltning, Ravnsgade 5",
    "sg:city":"Aakirkeby",
    "sg:orig_category":"Redningsberedskab",
    "sg:phone":"+45 56 97 47 47",
    "sg:postcode":"3720",
    "sg:province":"Danmark",
    "wof:name":"Aakirkeby Kommunale Brandv\u00e6sen",
    "wof:placetype":"venue"
},
  "geometry": {"coordinates":[14.9202880859,55.070110321],"type":"Point"}
}