{
  "type": "Feature",
  "properties": {
    "addr:full":"Danmarksgade 58 Frederikshavn Danmark 9900",
    "addr:housenumber":"58",
    "addr:postcode":"9900",
    "addr:street":"Danmarksgade",
    "iso:country":"DK",
    "sg:address":"Danmarksgade 58",
    "sg:city":"Frederikshavn",
    "sg:orig_category":"Sko",
    "sg:phone":"+45 98 43 29 66",
    "sg:postcode":"9900",
    "sg:province":"Danmark",
    "wof:name":"Bianco Footwear",
    "wof:placetype":"venue"
},
  "geometry": {"coordinates":[10.5360860825,57.4401893616],"type":"Point"}
}