{
  "type": "Feature",
  "properties": {
    "addr:full":"Parallelvej 11 Ry Danmark 8680",
    "addr:housenumber":"11",
    "addr:postcode":"8680",
    "addr:street":"Parallelvej",
    "iso:country":"DK",
    "sg:address":"Parallelvej 11",
    "sg:city":"Ry",
    "sg:classifiers":[
        {
            "category":"Autos & Motor Vehicles",
            "subcategory":"Fuel & Gas Station",
            "type":"Retail Goods"
        }
    ],
    "sg:phone":"+45 87 88 07 77",
    "sg:postcode":"8680",
    "sg:province":"Danmark",
    "sg:tags":[
        "pumper"
    ],
    "sg:website":"www.busch.dk",
    "wof:name":"Busch Vakuumteknik A/S",
    "wof:placetype":"venue"
},
  "geometry": {"coordinates":[9.7826004028,56.0897026062],"type":"Point"}
}