{
  "type": "Feature",
  "properties": {
    "addr:full":"Sk\u00e6lsk\u00f8rvej 3 Sor\u00f8 Danmark 4180",
    "addr:housenumber":"3",
    "addr:postcode":"4180",
    "addr:street":"Skaelskorvej",
    "iso:country":"DK",
    "sg:address":"Sk\u00e6lsk\u00f8rvej 3",
    "sg:city":"Sor\u00f8",
    "sg:orig_category":"Malermestre",
    "sg:phone":"+45 23 43 09 25",
    "sg:postcode":"4180",
    "sg:province":"Danmark",
    "wof:name":"Kongstads Malerservice",
    "wof:placetype":"venue"
},
  "geometry": {"coordinates":[-102.94467926030001,45.4534721375],"type":"Point"}
}