{
  "type": "Feature",
  "properties": {
    "addr:full":"V\u00e6rkstedvej 75 Valby Danmark 2500",
    "addr:housenumber":"75",
    "addr:postcode":"2500",
    "addr:street":"Vaerkstedvej",
    "iso:country":"DK",
    "sg:address":"V\u00e6rkstedvej 75",
    "sg:city":"Valby",
    "sg:orig_category":"Metalvarefabrikker",
    "sg:phone":"+45 36 16 25 55",
    "sg:postcode":"2500",
    "sg:province":"Danmark",
    "wof:name":"Gi\u00f8rtz & Mandel A/S",
    "wof:placetype":"venue"
},
  "geometry": {"coordinates":[12.5075159073,55.6535415649],"type":"Point"}
}