{
  "type": "Feature",
  "properties": {
    "iso:country":"DK",
    "sg:address":"Ordrupvej 64",
    "sg:city":"Charlottenlund",
    "sg:orig_category":"Sko",
    "sg:phone":"+45 39 63 50 51",
    "sg:postcode":"2920",
    "sg:province":"Danmark",
    "wof:name":"Balschmidt, Boutique Ib",
    "wof:placetype":"venue"
},
  "geometry": {"coordinates":[12.5764713287,55.7626342773],"type":"Point"}
}