{
  "type": "Feature",
  "properties": {
    "addr:full":"Tolstrup Byvej 17 Aars Danmark 9600",
    "addr:housenumber":"17",
    "addr:postcode":"9600",
    "addr:street":"Tolstrup Byvej",
    "iso:country":"DK",
    "sg:address":"Tolstrup Byvej 17",
    "sg:city":"Aars",
    "sg:orig_category":"Campingpladser",
    "sg:phone":"+45 98 62 36 03",
    "sg:postcode":"9600",
    "sg:province":"Danmark",
    "wof:name":"Aars Camping",
    "wof:placetype":"venue"
},
  "geometry": {"coordinates":[9.5072393417,56.8158035278],"type":"Point"}
}