{
  "type": "Feature",
  "properties": {
    "iso:country":"DK",
    "sg:address":"Vigebakke 1 A",
    "sg:city":"Svaneke",
    "sg:orig_category":"Slagterier",
    "sg:phone":"+45 56 49 61 69",
    "sg:postcode":"3740",
    "sg:province":"Danmark",
    "wof:name":"Svaneke Slagterforretning",
    "wof:placetype":"venue"
},
  "geometry": {"coordinates":[15.1392822266,55.1372528076],"type":"Point"}
}