{
  "type": "Feature",
  "properties": {
    "iso:country":"DK",
    "sg:address":"Kulgade 6",
    "sg:city":"Struer",
    "sg:orig_category":"Korn og foderstoffer",
    "sg:phone":"+45 97 85 16 99",
    "sg:postcode":"7600",
    "sg:province":"Danmark",
    "wof:name":"Vestjydsk Agro",
    "wof:placetype":"venue"
},
  "geometry": {"coordinates":[8.5999412537,56.4926757812],"type":"Point"}
}