{
  "type": "Feature",
  "properties": {
    "iso:country":"DK",
    "sg:address":"H\u00f8jen Kirkevej 1",
    "sg:city":"Vejle",
    "sg:orig_category":"Brugsforeninger",
    "sg:phone":"+45 75 86 31 11",
    "sg:postcode":"7100",
    "sg:province":"Danmark",
    "wof:name":"Brugsen, H\u00f8jen",
    "wof:placetype":"venue"
},
  "geometry": {"coordinates":[9.4935503006,55.6588287354],"type":"Point"}
}