{
  "type": "Feature",
  "properties": {
    "addr:full":"\u00d8lsmosevej 12, Sorterup Slagelse Danmark 4200",
    "addr:housenumber":"12",
    "addr:postcode":"4200",
    "addr:street":"Olsmosevej;Sorterup",
    "iso:country":"DK",
    "sg:address":"\u00d8lsmosevej 12, Sorterup",
    "sg:city":"Slagelse",
    "sg:orig_category":"Kirker",
    "sg:postcode":"4200",
    "sg:province":"Danmark",
    "wof:name":"Kindertofte Kirke",
    "wof:placetype":"venue"
},
  "geometry": {"coordinates":[11.3569850922,55.4050865173],"type":"Point"}
}