{
  "type": "Feature",
  "properties": {
    "iso:country":"DK",
    "sg:address":"M\u00f8llegade 41, Lyngs",
    "sg:city":"Thyholm",
    "sg:orig_category":"Regnskabsassistance",
    "sg:phone":"+45 97 87 81 74",
    "sg:postcode":"7790",
    "sg:province":"Danmark",
    "wof:name":"Kontorhj\u00e6lpen",
    "wof:placetype":"venue"
},
  "geometry": {"coordinates":[8.525765419,56.6507072449],"type":"Point"}
}