{
  "type": "Feature",
  "properties": {
    "iso:country":"DK",
    "sg:address":"Krus\u00e5vej 37, Alslev",
    "sg:city":"L\u00f8gumkloster",
    "sg:orig_category":"Landbrugsmaskiner",
    "sg:phone":"+45 74 77 51 29",
    "sg:postcode":"6240",
    "sg:province":"Danmark",
    "wof:name":"Haba Maskiner L\u00f8gumkloster Aps",
    "wof:placetype":"venue"
},
  "geometry": {"coordinates":[8.9515838623,55.058506012],"type":"Point"}
}