{
  "type": "Feature",
  "properties": {
    "addr:full":"Glasmagervej 6, Fensmark N\u00e6stved Danmark 4700",
    "addr:housenumber":"6",
    "addr:postcode":"4700",
    "addr:street":"Glasmagervej",
    "iso:country":"DK",
    "sg:address":"Glasmagervej 6, Fensmark",
    "sg:city":"N\u00e6stved",
    "sg:orig_category":"Malermestre",
    "sg:phone":"+45 55 54 65 86",
    "sg:postcode":"4700",
    "sg:province":"Danmark",
    "wof:name":"Poul Eriks Malerservice",
    "wof:placetype":"venue"
},
  "geometry": {"coordinates":[11.7542486191,55.2315444946],"type":"Point"}
}