{
  "type": "Feature",
  "properties": {
    "addr:full":"Anderupv\u00e6nget 51, Anderup Odense N Danmark 5270",
    "addr:housenumber":"51",
    "addr:postcode":"5270",
    "addr:street":"Anderupvaenget",
    "iso:country":"DK",
    "sg:address":"Anderupv\u00e6nget 51, Anderup",
    "sg:city":"Odense N",
    "sg:orig_category":"Kurerservice",
    "sg:phone":"+45 66 18 94 85",
    "sg:postcode":"5270",
    "sg:province":"Danmark",
    "wof:name":"Roccato, Joan",
    "wof:placetype":"venue"
},
  "geometry": {"coordinates":[10.3306798935,55.4711418152],"type":"Point"}
}