{
  "type": "Feature",
  "properties": {
    "addr:full":"Fmd.: S\u00f8ren Espersen, M\u00f8llevej 20, Birkede Viby Sj\u00e6lland Danmark 4130",
    "addr:housenumber":"20",
    "addr:postcode":"4130",
    "addr:street":"Mollevej",
    "iso:country":"DK",
    "sg:address":"Fmd.: S\u00f8ren Espersen, M\u00f8llevej 20, Birkede",
    "sg:city":"Viby Sj\u00e6lland",
    "sg:orig_category":"Kulturelle foreninger",
    "sg:phone":"+45 46 19 36 00",
    "sg:postcode":"4130",
    "sg:province":"Danmark",
    "wof:name":"Rams\u00f8 Lokalhistoriske Forening",
    "wof:placetype":"venue"
},
  "geometry": {"coordinates":[12.024274826,55.5473709106],"type":"Point"}
}