{
  "type": "Feature",
  "properties": {
    "addr:full":"Fr. Leyels Vej 4 Snekkersten Danmark 3070",
    "addr:housenumber":"4",
    "addr:postcode":"3070",
    "addr:street":"Fr. Leyels Vej",
    "iso:country":"DK",
    "sg:address":"Fr. Leyels Vej 4",
    "sg:city":"Snekkersten",
    "sg:orig_category":"Musikere",
    "sg:phone":"+45 49 22 17 55",
    "sg:postcode":"3070",
    "sg:province":"Danmark",
    "wof:name":"Schi\u00f8dt, Preben",
    "wof:placetype":"venue"
},
  "geometry": {"coordinates":[12.5690412521,56.0146522522],"type":"Point"}
}