{
  "type": "Feature",
  "properties": {
    "iso:country":"DK",
    "sg:address":"Fmd.: Erik B. Madsen, Stejlbjergvej 5, Asdal",
    "sg:city":"Hirtshals",
    "sg:orig_category":"\u00c3\u2020ldreorganisationer og klubber",
    "sg:phone":"+45 98 97 12 45",
    "sg:postcode":"9850",
    "sg:province":"Danmark",
    "wof:name":"\u00c6ldre Sagen",
    "wof:placetype":"venue"
},
  "geometry": {"coordinates":[9.9599866867,57.5884933472],"type":"Point"}
}