{
  "type": "Feature",
  "properties": {
    "addr:full":"Fmd.: Helle Knudsen, Skodsborgvej 61 B Klarup Danmark 9270",
    "addr:housenumber":"61 b",
    "addr:postcode":"9270",
    "addr:street":"Helle Knudsen Skodsborgvej",
    "iso:country":"DK",
    "sg:address":"Fmd.: Helle Knudsen, Skodsborgvej 61 B",
    "sg:city":"Klarup",
    "sg:orig_category":"Spejderkorps",
    "sg:phone":"+45 98 31 92 45",
    "sg:postcode":"9270",
    "sg:province":"Danmark",
    "wof:name":"DDS Klarup",
    "wof:placetype":"venue"
},
  "geometry": {"coordinates":[10.0475549698,57.0136489868],"type":"Point"}
}