{
  "type": "Feature",
  "properties": {
    "addr:full":"Sigurdsgade 34 K\u00f8benhavn N Danmark 2200",
    "addr:housenumber":"34",
    "addr:postcode":"2200",
    "addr:street":"Sigurdsgade;Kobenhavn N Danmark",
    "iso:country":"DK",
    "sg:address":"Sigurdsgade 34",
    "sg:city":"K\u00f8benhavn N",
    "sg:orig_category":"Erhvervsskoler",
    "sg:phone":"+45 35 86 06 86",
    "sg:postcode":"2200",
    "sg:province":"Danmark",
    "sg:website":"www.laborantskolen.dk",
    "wof:name":"Laborantskolen",
    "wof:placetype":"venue"
},
  "geometry": {"coordinates":[-97.5596694946,47.7357215881],"type":"Point"}
}