{
  "type": "Feature",
  "properties": {
    "addr:full":"Vognmandsmarken 2 Roskilde Danmark 4000",
    "addr:housenumber":"2",
    "addr:postcode":"4000",
    "addr:street":"Vognmandsmarken",
    "iso:country":"DK",
    "sg:address":"Vognmandsmarken 2",
    "sg:city":"Roskilde",
    "sg:orig_category":"Malermestre",
    "sg:phone":"+45 46 32 60 38",
    "sg:postcode":"4000",
    "sg:province":"Danmark",
    "wof:name":"Christensen, John*",
    "wof:placetype":"venue"
},
  "geometry": {"coordinates":[12.0908126831,55.6310119629],"type":"Point"}
}