{
  "type": "Feature",
  "properties": {
    "iso:country":"DK",
    "sg:address":"Smedeland 1",
    "sg:city":"Glostrup",
    "sg:orig_category":"Benzinstationer",
    "sg:phone":"+45 43 96 00 60",
    "sg:postcode":"2600",
    "sg:province":"Danmark",
    "wof:name":"Statoil",
    "wof:placetype":"venue"
},
  "geometry": {"coordinates":[12.389237,55.67683],"type":"Point"}
}