{
  "type": "Feature",
  "properties": {
    "addr:full":"Fmd.: Asger Vagn Andersen, Rosvangsvej 134, Nr. Harritslev Hj\u00f8rring Danmark 9800",
    "addr:housenumber":"134",
    "addr:postcode":"9800",
    "addr:street":"Rosvangsvej",
    "iso:country":"DK",
    "sg:address":"Fmd.: Asger Vagn Andersen, Rosvangsvej 134, Nr. Harritslev",
    "sg:city":"Hj\u00f8rring",
    "sg:orig_category":"Musik og sang",
    "sg:phone":"+45 98 92 61 05",
    "sg:postcode":"9800",
    "sg:province":"Danmark",
    "wof:name":"Sindal Bl\u00e6serne",
    "wof:placetype":"venue"
},
  "geometry": {"coordinates":[9.9885387421,57.4594764709],"type":"Point"}
}