{
  "type": "Feature",
  "properties": {
    "addr:full":"Engl\u00f8kke 5 A, Agtrup Bjert Danmark 6091",
    "addr:housenumber":"5 a",
    "addr:postcode":"6091",
    "addr:street":"Englokke;Agtrup",
    "iso:country":"DK",
    "sg:address":"Engl\u00f8kke 5 A, Agtrup",
    "sg:city":"Bjert",
    "sg:orig_category":"Tandklinikker, Kommunale",
    "sg:phone":"+45 75 57 26 21",
    "sg:postcode":"6091",
    "sg:province":"Danmark",
    "wof:name":"Klinikken",
    "wof:placetype":"venue"
},
  "geometry": {"coordinates":[9.5557050705,55.4597244263],"type":"Point"}
}