{
  "type": "Feature",
  "properties": {
    "addr:full":"Syrenv\u00e6nget 3, Thyregod Give Danmark 7323",
    "addr:housenumber":"3",
    "addr:postcode":"7323",
    "addr:street":"Syrenvaenget;Thyregod",
    "iso:country":"DK",
    "sg:address":"Syrenv\u00e6nget 3, Thyregod",
    "sg:city":"Give",
    "sg:classifiers":[
        {
            "category":"Personal",
            "subcategory":"Massage",
            "type":"Services"
        }
    ],
    "sg:phone":"+45 75 73 73 03",
    "sg:postcode":"7323",
    "sg:province":"Danmark",
    "wof:name":"Klinik for massage og skadeterapi",
    "wof:placetype":"venue"
},
  "geometry": {"coordinates":[9.2362060547,55.845413208],"type":"Point"}
}