{
  "type": "Feature",
  "properties": {
    "addr:full":"Hjedsb\u00e6kvej 271 Suldrup Danmark 9541",
    "addr:housenumber":"271",
    "addr:postcode":"9541",
    "addr:street":"Hjedsbaekvej",
    "iso:country":"DK",
    "sg:address":"Hjedsb\u00e6kvej 271",
    "sg:city":"Suldrup",
    "sg:orig_category":"Solcentre",
    "sg:phone":"+45 98 37 80 98",
    "sg:postcode":"9541",
    "sg:province":"Danmark",
    "wof:name":"Lundgrens Solcenter",
    "wof:placetype":"venue"
},
  "geometry": {"coordinates":[9.7057914734,56.8536682129],"type":"Point"}
}