{
  "type": "Feature",
  "properties": {
    "addr:full":"M\u00f8lleg\u00e5rdsvej 12 kld., Bramdrup Kolding Danmark 6000",
    "addr:housenumber":"12 kld.",
    "addr:postcode":"6000",
    "addr:street":"Mollegaardsvej;Bramdrup",
    "iso:country":"DK",
    "sg:address":"M\u00f8lleg\u00e5rdsvej 12 kld., Bramdrup",
    "sg:city":"Kolding",
    "sg:orig_category":"Ungdomsklubber",
    "sg:phone":"+45 75 51 90 44",
    "sg:postcode":"6000",
    "sg:province":"Danmark",
    "sg:website":"www.vaerested.dk",
    "wof:name":"KFUM-Spejdernes V\u00e6rested",
    "wof:placetype":"venue"
},
  "geometry": {"coordinates":[9.4733953476,55.4863586426],"type":"Point"}
}