{
  "type": "Feature",
  "properties": {
    "addr:full":"Br\u00e5byvej 25 Haslev Danmark 4690",
    "addr:housenumber":"25",
    "addr:postcode":"4690",
    "addr:street":"Braabyvej",
    "iso:country":"DK",
    "sg:address":"Br\u00e5byvej 25",
    "sg:city":"Haslev",
    "sg:orig_category":"Dykkere",
    "sg:phone":"+45 56 31 41 30",
    "sg:postcode":"4690",
    "sg:province":"Danmark",
    "wof:name":"Dykkerskolen i Haslev",
    "wof:placetype":"venue"
},
  "geometry": {"coordinates":[11.9686326981,55.3181838989],"type":"Point"}
}