{
  "type": "Feature",
  "properties": {
    "addr:full":"Vestergade 15 Odense C Danmark 5000",
    "addr:housenumber":"15",
    "addr:postcode":"5000",
    "addr:street":"Vestergade",
    "iso:country":"DK",
    "sg:address":"Vestergade 15",
    "sg:city":"Odense C",
    "sg:orig_category":"Ejendomshandel",
    "sg:phone":"+45 66 13 80 60",
    "sg:postcode":"5000",
    "sg:province":"Danmark",
    "wof:name":"Nybolig Erhverv Blomberg",
    "wof:placetype":"venue"
},
  "geometry": {"coordinates":[10.3878135681,55.3962402344],"type":"Point"}
}