{
  "type": "Feature",
  "properties": {
    "iso:country":"DK",
    "sg:address":"Langbyg\u00e5rdsvej 10",
    "sg:city":"Glamsbjerg",
    "sg:orig_category":"Biografer",
    "sg:phone":"+45 64 72 17 60",
    "sg:postcode":"5620",
    "sg:province":"Danmark",
    "wof:name":"Glamsbjerg Biograf",
    "wof:placetype":"venue"
},
  "geometry": {"coordinates":[10.112947,55.272671],"type":"Point"}
}