{
  "type": "Feature",
  "properties": {
    "addr:full":"Fmd.: Henning Nielsen, St. Ajstrupvej 57, St. Ajstrup Nibe Danmark 9240",
    "addr:housenumber":"57",
    "addr:postcode":"9240",
    "addr:street":"Nielsen St. Ajstrupvej;Ajstrup",
    "iso:country":"DK",
    "sg:address":"Fmd.: Henning Nielsen, St. Ajstrupvej 57, St. Ajstrup",
    "sg:city":"Nibe",
    "sg:orig_category":"Borger- og beboerforeninger",
    "sg:phone":"+45 98 35 51 49",
    "sg:postcode":"9240",
    "sg:province":"Danmark",
    "wof:name":"St. Ajstrup Borgerforening",
    "wof:placetype":"venue"
},
  "geometry": {"coordinates":[9.6393280029,56.982421875],"type":"Point"}
}