{
  "type": "Feature",
  "properties": {
    "addr:full":"Hovedvejen 90 Glostrup Danmark 2600",
    "addr:housenumber":"90",
    "addr:postcode":"2600",
    "addr:street":"Hovedvejen",
    "iso:country":"DK",
    "sg:address":"Hovedvejen 90",
    "sg:city":"Glostrup",
    "sg:orig_category":"Autoforhandlere",
    "sg:phone":"+45 70 15 80 50",
    "sg:postcode":"2600",
    "sg:province":"Danmark",
    "wof:name":"Fiat Glostrup",
    "wof:placetype":"venue"
},
  "geometry": {"coordinates":[12.4022655487,55.6664772034],"type":"Point"}
}