{
  "type": "Feature",
  "properties": {
    "addr:full":"Kronprinsensgade 36 Esbjerg Danmark 6700",
    "addr:housenumber":"36",
    "addr:postcode":"6700",
    "addr:street":"Kronprinsensgade",
    "iso:country":"DK",
    "sg:address":"Kronprinsensgade 36",
    "sg:city":"Esbjerg",
    "sg:orig_category":"Hobbyartikler",
    "sg:phone":"+45 75 12 13 32",
    "sg:postcode":"6700",
    "sg:province":"Danmark",
    "wof:name":"Sannes Hobby",
    "wof:placetype":"venue"
},
  "geometry": {"coordinates":[8.4456720352,55.4685592651],"type":"Point"}
}