{
  "type": "Feature",
  "properties": {
    "addr:full":"T\u00e5rngade 45 Struer Danmark 7600",
    "addr:housenumber":"45",
    "addr:postcode":"7600",
    "addr:street":"Taarngade",
    "iso:country":"DK",
    "sg:address":"T\u00e5rngade 45",
    "sg:city":"Struer",
    "sg:orig_category":"Konsulentvirksomheder",
    "sg:phone":"+45 97 84 11 77",
    "sg:postcode":"7600",
    "sg:province":"Danmark",
    "wof:name":"Reliability Consultants",
    "wof:placetype":"venue"
},
  "geometry": {"coordinates":[8.6029043198,56.4853591919],"type":"Point"}
}