{
  "type": "Feature",
  "properties": {
    "addr:full":"Korsgade 72 1 tv K\u00f8benhavn N Danmark 2200",
    "addr:housenumber":"72 1 tv",
    "addr:postcode":"2200",
    "addr:street":"Korsgade;N Danmark",
    "iso:country":"DK",
    "sg:address":"Korsgade 72 1 tv",
    "sg:city":"K\u00f8benhavn N",
    "sg:orig_category":"Kurerservice",
    "sg:phone":"+45 22 14 46 09",
    "sg:postcode":"2200",
    "sg:province":"Danmark",
    "wof:name":"CPH-Transport",
    "wof:placetype":"venue"
},
  "geometry": {"coordinates":[-94.444190979,47.9254951477],"type":"Point"}
}