{
  "type": "Feature",
  "properties": {
    "addr:full":"Hvidovrevej 245 Hvidovre Danmark 2650",
    "addr:housenumber":"245",
    "addr:postcode":"2650",
    "addr:street":"Hvidovrevej",
    "iso:country":"DK",
    "sg:address":"Hvidovrevej 245",
    "sg:city":"Hvidovre",
    "sg:classifiers":[
        {
            "category":"Taxi",
            "type":"Transportation"
        }
    ],
    "sg:phone":"+45 36 78 79 13",
    "sg:postcode":"2650",
    "sg:province":"Danmark",
    "sg:website":"www.7-9-13-bilen.dk",
    "wof:name":"Taxi 7-9-13 Bilen",
    "wof:placetype":"venue"
},
  "geometry": {"coordinates":[12.4786729813,55.6425819397],"type":"Point"}
}