{
  "type": "Feature",
  "properties": {
    "addr:full":"Industriarealet 42 Ulfborg Danmark 6990",
    "addr:housenumber":"42",
    "addr:postcode":"6990",
    "addr:street":"Industriarealet",
    "iso:country":"DK",
    "sg:address":"Industriarealet 42",
    "sg:city":"Ulfborg",
    "sg:orig_category":"Engros handel",
    "sg:phone":"+45 97 49 21 44",
    "sg:postcode":"6990",
    "sg:province":"Danmark",
    "sg:website":"www.rexholm.dk",
    "wof:name":"Rex & Holm A/S",
    "wof:placetype":"venue"
},
  "geometry": {"coordinates":[8.3188533783,56.2607269287],"type":"Point"}
}