{
  "type": "Feature",
  "properties": {
    "addr:full":"Kyseborgstr\u00e6de 5 Svendborg Danmark 5700",
    "addr:housenumber":"5",
    "addr:postcode":"5700",
    "addr:street":"Kyseborgstraede",
    "iso:country":"DK",
    "sg:address":"Kyseborgstr\u00e6de 5",
    "sg:city":"Svendborg",
    "sg:orig_category":"Private skoler",
    "sg:phone":"+45 62 21 11 29",
    "sg:postcode":"5700",
    "sg:province":"Danmark",
    "sg:website":"www.idaholst.dk",
    "wof:name":"Ida Holsts Skole",
    "wof:placetype":"venue"
},
  "geometry": {"coordinates":[10.608540535,55.0579910278],"type":"Point"}
}