{
  "type": "Feature",
  "properties": {
    "addr:full":"Ryg\u00e5rdsv\u00e6nget 6 Hellerup Danmark 2900",
    "addr:housenumber":"6",
    "addr:postcode":"2900",
    "addr:street":"Rygaardsvaenget",
    "iso:country":"DK",
    "sg:address":"Ryg\u00e5rdsv\u00e6nget 6",
    "sg:city":"Hellerup",
    "sg:orig_category":"Dommerkontorer",
    "sg:phone":"+45 39 45 89 00",
    "sg:postcode":"2900",
    "sg:province":"Danmark",
    "wof:name":"Retten i Gentofte.",
    "wof:placetype":"venue"
},
  "geometry": {"coordinates":[12.5788497925,55.7413787842],"type":"Point"}
}