{
  "type": "Feature",
  "properties": {
    "addr:full":"Fmd.: Johnny Knudsen, Leer-Ager 5, Blistrup Gr\u00e6sted Danmark 3230",
    "addr:housenumber":"5",
    "addr:postcode":"3230",
    "addr:street":"Leer-Ager",
    "iso:country":"DK",
    "sg:address":"Fmd.: Johnny Knudsen, Leer-Ager 5, Blistrup",
    "sg:city":"Gr\u00e6sted",
    "sg:orig_category":"Hobbybetonede foreninger",
    "sg:phone":"+45 48 71 82 84",
    "sg:postcode":"3230",
    "sg:province":"Danmark",
    "wof:name":"Privatradioklubben S.A.",
    "wof:placetype":"venue"
},
  "geometry": {"coordinates":[12.3426475525,56.048500061],"type":"Point"}
}