{
  "type": "Feature",
  "properties": {
    "addr:full":"Frederiks All\u00e9 149 \u00c5rhus C Danmark 8000",
    "addr:housenumber":"149",
    "addr:postcode":"8000",
    "addr:street":"Frederiks Alle\u0301",
    "iso:country":"DK",
    "sg:address":"Frederiks All\u00e9 149",
    "sg:city":"\u00c5rhus C",
    "sg:orig_category":"Rejsebureauer",
    "sg:phone":"+45 86 13 91 55",
    "sg:postcode":"8000",
    "sg:province":"Danmark",
    "wof:name":"J\u00f8rgensen Busser A/S",
    "wof:placetype":"venue"
},
  "geometry": {"coordinates":[10.193359375,56.1458625793],"type":"Point"}
}