{
  "type": "Feature",
  "properties": {
    "addr:full":"Klokkestabelen 38 Aalborg Danmark 9000",
    "addr:housenumber":"38",
    "addr:postcode":"9000",
    "addr:street":"Klokkestabelen",
    "iso:country":"DK",
    "sg:address":"Klokkestabelen 38",
    "sg:city":"Aalborg",
    "sg:orig_category":"Psykologer, praktiserende",
    "sg:phone":"+45 98 18 92 91",
    "sg:postcode":"9000",
    "sg:province":"Danmark",
    "wof:name":"Ahlgren, Kirsten",
    "wof:placetype":"venue"
},
  "geometry": {"coordinates":[9.8743886948,57.0254440308],"type":"Point"}
}