{
  "type": "Feature",
  "properties": {
    "addr:full":"Kastrup Strandpark 31 Kastrup Danmark 2770",
    "addr:housenumber":"31",
    "addr:postcode":"2770",
    "addr:street":"Kastrup Strandpark",
    "iso:country":"DK",
    "sg:address":"Kastrup Strandpark 31",
    "sg:city":"Kastrup",
    "sg:orig_category":"Havne",
    "sg:phone":"+45 32 50 21 27",
    "sg:postcode":"2770",
    "sg:province":"Danmark",
    "sg:website":"www.taarnby.dk",
    "wof:name":"Kastrup Lystb\u00e5dehavn",
    "wof:placetype":"venue"
},
  "geometry": {"coordinates":[12.6486997604,55.6398162842],"type":"Point"}
}