{
  "type": "Feature",
  "properties": {
    "addr:full":"Peberhaven 22 Herlev Danmark 2730",
    "addr:housenumber":"22",
    "addr:postcode":"2730",
    "addr:street":"Peberhaven",
    "iso:country":"DK",
    "sg:address":"Peberhaven 22",
    "sg:city":"Herlev",
    "sg:orig_category":"Hatte",
    "sg:phone":"+45 44 53 02 37",
    "sg:postcode":"2730",
    "sg:province":"Danmark",
    "wof:name":"Juul, Susanne",
    "wof:placetype":"venue"
},
  "geometry": {"coordinates":[12.4358558655,55.7425079346],"type":"Point"}
}