{
  "type": "Feature",
  "properties": {
    "addr:full":"Bredgade 25 Pandrup Danmark 9490",
    "addr:housenumber":"25",
    "addr:postcode":"9490",
    "addr:street":"Bredgade",
    "iso:country":"DK",
    "sg:address":"Bredgade 25",
    "sg:city":"Pandrup",
    "sg:orig_category":"Blomsterhandlere",
    "sg:phone":"+45 98 24 77 11",
    "sg:postcode":"9490",
    "sg:province":"Danmark",
    "wof:name":"Sevilla",
    "wof:placetype":"venue"
},
  "geometry": {"coordinates":[9.6770353317,57.2230911255],"type":"Point"}
}