{
  "type": "Feature",
  "properties": {
    "addr:full":"Cypresvej 6 Herning Danmark 7400",
    "addr:housenumber":"6",
    "addr:postcode":"7400",
    "addr:street":"Cypresvej",
    "iso:country":"DK",
    "sg:address":"Cypresvej 6",
    "sg:city":"Herning",
    "sg:orig_category":"Elektronik",
    "sg:phone":"+45 97 22 10 33",
    "sg:postcode":"7400",
    "sg:province":"Danmark",
    "sg:website":"kk-electronic.dk",
    "wof:name":"kk-electronic a/s",
    "wof:placetype":"venue"
},
  "geometry": {"coordinates":[8.9328546524,56.1326942444],"type":"Point"}
}