{
  "type": "Feature",
  "properties": {
    "addr:full":"Ebstrupvej 6 Silkeborg Danmark 8600",
    "addr:housenumber":"6",
    "addr:postcode":"8600",
    "addr:street":"Ebstrupvej",
    "iso:country":"DK",
    "sg:address":"Ebstrupvej 6",
    "sg:city":"Silkeborg",
    "sg:orig_category":"Forsamlingshuse",
    "sg:phone":"+45 86 85 51 37",
    "sg:postcode":"8600",
    "sg:province":"Danmark",
    "wof:name":"Sejling Forsamlingshus",
    "wof:placetype":"venue"
},
  "geometry": {"coordinates":[9.5232000351,56.2172088623],"type":"Point"}
}