{
  "type": "Feature",
  "properties": {
    "addr:full":"R\u00f8gerivej 6 Skagen Danmark 9990",
    "addr:housenumber":"6",
    "addr:postcode":"9990",
    "addr:street":"Rogerivej",
    "iso:country":"DK",
    "sg:address":"R\u00f8gerivej 6",
    "sg:city":"Skagen",
    "sg:orig_category":"Plastemballage",
    "sg:phone":"+45 98 44 38 77",
    "sg:postcode":"9990",
    "sg:province":"Danmark",
    "wof:name":"Skagen Kasse og Plastfabrik A/S",
    "wof:placetype":"venue"
},
  "geometry": {"coordinates":[10.5966682434,57.7205505371],"type":"Point"}
}