{
  "type": "Feature",
  "properties": {
    "addr:full":"Torvegade 58 Esbjerg Danmark 6700",
    "addr:housenumber":"58",
    "addr:postcode":"6700",
    "addr:street":"Torvegade",
    "iso:country":"DK",
    "sg:address":"Torvegade 58",
    "sg:city":"Esbjerg",
    "sg:orig_category":"Pizzeriaer",
    "sg:phone":"+45 76 10 03 30",
    "sg:postcode":"6700",
    "sg:province":"Danmark",
    "wof:name":"US Pizza",
    "wof:placetype":"venue"
},
  "geometry": {"coordinates":[8.4529972076,55.470123291],"type":"Point"}
}