{
  "type": "Feature",
  "properties": {
    "addr:full":"Veddingevej 4, H\u00f8ve Asn\u00e6s Danmark 4550",
    "addr:housenumber":"4",
    "addr:postcode":"4550",
    "addr:street":"Veddingevej",
    "iso:country":"DK",
    "sg:address":"Veddingevej 4, H\u00f8ve",
    "sg:city":"Asn\u00e6s",
    "sg:orig_category":"Private- og friskoler",
    "sg:phone":"+45 59 65 06 10",
    "sg:postcode":"4550",
    "sg:province":"Danmark",
    "wof:name":"H\u00f8ve Friskole",
    "wof:placetype":"venue"
},
  "geometry": {"coordinates":[-78.1299133301,36.7267417908],"type":"Point"}
}