{
  "type": "Feature",
  "properties": {
    "addr:full":"Hovedgaden 30 Billund Danmark 7190",
    "addr:housenumber":"30",
    "addr:postcode":"7190",
    "addr:street":"Hovedgaden",
    "iso:country":"DK",
    "sg:address":"Hovedgaden 30",
    "sg:city":"Billund",
    "sg:orig_category":"Sparekasser",
    "sg:phone":"+45 76 50 03 22",
    "sg:postcode":"7190",
    "sg:province":"Danmark",
    "sg:website":"www.sparvorbasse.dk",
    "wof:name":"Vorbasse - Hejnsvig Sparekasse",
    "wof:placetype":"venue"
},
  "geometry": {"coordinates":[9.1116838455,55.732837677],"type":"Point"}
}