{
  "type": "Feature",
  "properties": {
    "addr:full":"Jernbanegade 39 Kolding Danmark 6000",
    "addr:housenumber":"39",
    "addr:postcode":"6000",
    "addr:street":"Jernbanegade",
    "iso:country":"DK",
    "sg:address":"Jernbanegade 39",
    "sg:city":"Kolding",
    "sg:orig_category":"Kursussteder",
    "sg:phone":"+45 75 52 12 00",
    "sg:postcode":"6000",
    "sg:province":"Danmark",
    "wof:name":"Saxildhus, Hotel",
    "wof:placetype":"venue"
},
  "geometry": {"coordinates":[9.4795923233,55.490524292],"type":"Point"}
}