{
  "type": "Feature",
  "properties": {
    "iso:country":"DK",
    "sg:address":"Sognepr\u00e6st: Thomas Uhre Fenger, Hoven pr\u00e6steg\u00e5rd, Bredgade 1, Hoven",
    "sg:city":"Tarm",
    "sg:orig_category":"Kirkesogne",
    "sg:phone":"+45 75 34 30 52",
    "sg:postcode":"6880",
    "sg:province":"Danmark",
    "wof:name":"Hoven og Ilderhede Sogne",
    "wof:placetype":"venue"
},
  "geometry": {"coordinates":[8.5200052261,55.9060554504],"type":"Point"}
}