{
  "type": "Feature",
  "properties": {
    "addr:full":"Bredgade 49, st.th. K\u00f8benhavn Danmark 1260",
    "addr:housenumber":"49",
    "addr:postcode":"1260",
    "addr:street":"Bredgade",
    "iso:country":"DK",
    "sg:address":"Bredgade 49, st.th.",
    "sg:city":"K\u00f8benhavn",
    "sg:orig_category":"Advokater",
    "sg:phone":"+45 33 11 05 01",
    "sg:postcode":"1260",
    "sg:province":"Danmark",
    "wof:name":"Andersen, Niels Arthur",
    "wof:placetype":"venue"
},
  "geometry": {"coordinates":[12.5931997299,55.6845016479],"type":"Point"}
}