{
  "type": "Feature",
  "properties": {
    "addr:full":"Vesterled 50 Janderup Danmark 6851",
    "addr:housenumber":"50",
    "addr:postcode":"6851",
    "addr:street":"Vesterled",
    "iso:country":"DK",
    "sg:address":"Vesterled 50",
    "sg:city":"Janderup",
    "sg:orig_category":"Omsorgscentre",
    "sg:postcode":"6851",
    "sg:province":"Danmark",
    "wof:name":"Distrikt 5, Omr\u00e5de Syd",
    "wof:placetype":"venue"
},
  "geometry": {"coordinates":[8.3692436218,55.6236801147],"type":"Point"}
}