{
  "type": "Feature",
  "properties": {
    "iso:country":"DK",
    "sg:address":"R\u00f8rdalsvej 27",
    "sg:city":"Aalborg \u00d8",
    "sg:orig_category":"Kontormaskiner",
    "sg:phone":"+45 96 31 46 66",
    "sg:postcode":"9220",
    "sg:province":"Danmark",
    "wof:name":"Sharp IT Partner",
    "wof:placetype":"venue"
},
  "geometry": {"coordinates":[9.9658670425,57.0571365356],"type":"Point"}
}