{
  "type": "Feature",
  "properties": {
    "addr:full":"Adelgade 30 B Assens Danmark 5610",
    "addr:housenumber":"30 b",
    "addr:postcode":"5610",
    "addr:street":"Adelgade",
    "iso:country":"DK",
    "sg:address":"Adelgade 30 B",
    "sg:city":"Assens",
    "sg:orig_category":"Faglige organisationer og foreninger",
    "sg:phone":"+45 64 71 11 35",
    "sg:postcode":"5610",
    "sg:province":"Danmark",
    "wof:name":"SID",
    "wof:placetype":"venue"
},
  "geometry": {"coordinates":[9.8955802917,55.2688026428],"type":"Point"}
}