{
  "type": "Feature",
  "properties": {
    "addr:full":"Adelgade 12, 1. Ebeltoft Danmark 8400",
    "addr:housenumber":"12 1",
    "addr:postcode":"8400",
    "addr:street":"Adelgade",
    "iso:country":"DK",
    "sg:address":"Adelgade 12, 1.",
    "sg:city":"Ebeltoft",
    "sg:orig_category":"Gaveartikler",
    "sg:phone":"+45 86 34 62 88",
    "sg:postcode":"8400",
    "sg:province":"Danmark",
    "wof:name":"Sm\u00f8rhullet",
    "wof:placetype":"venue"
},
  "geometry": {"coordinates":[10.6781721115,56.1985015869],"type":"Point"}
}