{
  "type": "Feature",
  "properties": {
    "addr:full":"Vinkel Alle 1 Aalborg Danmark 9000",
    "addr:housenumber":"1",
    "addr:postcode":"9000",
    "addr:street":"Vinkel Alle",
    "iso:country":"DK",
    "sg:address":"Vinkel Alle 1",
    "sg:city":"Aalborg",
    "sg:orig_category":"Kursusudbydere",
    "sg:phone":"+45 98 11 71 60",
    "sg:postcode":"9000",
    "sg:province":"Danmark",
    "sg:website":"www.akticonsulting.dk",
    "wof:name":"AKTI Ledelsesudvikling",
    "wof:placetype":"venue"
},
  "geometry": {"coordinates":[9.902671814,57.0463294983],"type":"Point"}
}