{
  "type": "Feature",
  "properties": {
    "iso:country":"DK",
    "sg:address":"Lanciavej 2",
    "sg:city":"Vejle",
    "sg:orig_category":"Engros handel",
    "sg:phone":"+45 76 40 88 88",
    "sg:postcode":"7100",
    "sg:province":"Danmark",
    "wof:name":"Aabling Handel A/S-Vest",
    "wof:placetype":"venue"
},
  "geometry": {"coordinates":[9.5368051529,55.7113952637],"type":"Point"}
}