{
  "type": "Feature",
  "properties": {
    "addr:full":"Storegade 9 Randers Danmark 8900",
    "addr:housenumber":"9",
    "addr:postcode":"8900",
    "addr:street":"Storegade",
    "iso:country":"DK",
    "sg:address":"Storegade 9",
    "sg:city":"Randers",
    "sg:classifiers":[
        {
            "category":"Restaurant",
            "type":"Food & Drink"
        }
    ],
    "sg:phone":"+45 86 41 65 33",
    "sg:postcode":"8900",
    "sg:province":"Danmark",
    "wof:name":"Brasserie Belli",
    "wof:placetype":"venue"
},
  "geometry": {"coordinates":[10.0382623672,56.4581413269],"type":"Point"}
}