{
  "type": "Feature",
  "properties": {
    "addr:full":"Gl. Landevej 137 Herning Danmark 7400",
    "addr:housenumber":"137",
    "addr:postcode":"7400",
    "addr:street":"Gl. Landevej",
    "iso:country":"DK",
    "sg:address":"Gl. Landevej 137",
    "sg:city":"Herning",
    "sg:classifiers":[
        {
            "category":"Communications",
            "type":"Services"
        }
    ],
    "sg:phone":"+45 97 12 78 21",
    "sg:postcode":"7400",
    "sg:province":"Danmark",
    "sg:tags":[
        "og",
        "tv",
        "radio"
    ],
    "wof:name":"M. A. S. Radio & TV",
    "wof:placetype":"venue"
},
  "geometry": {"coordinates":[8.9627103806,56.1403045654],"type":"Point"}
}