{
  "type": "Feature",
  "properties": {
    "iso:country":"DK",
    "sg:address":"Lundvej 8 ",
    "sg:city":"Herning",
    "sg:classifiers":[
        {
            "category":"Travel",
            "subcategory":"Travel Agent",
            "type":"Entertainment"
        }
    ],
    "sg:phone":"+45 96 27 73 00",
    "sg:postcode":"7400",
    "sg:province":"Danmark",
    "sg:tags":[
        "business"
    ],
    "wof:name":"AAGE DAMGAARD APS",
    "wof:placetype":"venue"
},
  "geometry": {"coordinates":[9.0194959641,56.1536636353],"type":"Point"}
}