{
  "type": "Feature",
  "properties": {
    "addr:full":"Stamhuset, Digehuset 9 Greve Danmark 2670",
    "addr:housenumber":"9",
    "addr:postcode":"2670",
    "addr:street":"Digehuset",
    "iso:country":"DK",
    "sg:address":"Stamhuset, Digehuset 9",
    "sg:city":"Greve",
    "sg:orig_category":"Grundejerforeninger",
    "sg:phone":"+45 43 69 04 44",
    "sg:postcode":"2670",
    "sg:province":"Danmark",
    "wof:name":"Beboern\u00e6vnet i Asker\u00f8d",
    "wof:placetype":"venue"
},
  "geometry": {"coordinates":[12.2941808701,55.5844078064],"type":"Point"}
}