{
  "type": "Feature",
  "properties": {
    "addr:full":"Soldalen 2, Niver\u00f8d, Postboks 44 Niv\u00e5 Danmark 2990",
    "addr:housenumber":"2;44",
    "addr:postcode":"2990",
    "addr:street":"Soldalen;Postboks",
    "iso:country":"DK",
    "sg:address":"Soldalen 2, Niver\u00f8d, Postboks 44",
    "sg:city":"Niv\u00e5",
    "sg:orig_category":"Malermestre",
    "sg:phone":"+45 49 14 56 17",
    "sg:postcode":"2990",
    "sg:province":"Danmark",
    "wof:name":"Str\u00f8b\u00e6k's Malerfirma ApS",
    "wof:placetype":"venue"
},
  "geometry": {"coordinates":[12.4865503311,55.9370956421],"type":"Point"}
}