{
  "type": "Feature",
  "properties": {
    "addr:full":"Birkevej 27 Engesvang Danmark 7442",
    "addr:housenumber":"27",
    "addr:postcode":"7442",
    "addr:street":"Birkevej",
    "iso:country":"DK",
    "sg:address":"Birkevej 27",
    "sg:city":"Engesvang",
    "sg:orig_category":"Murermestre",
    "sg:phone":"+45 86 86 51 48",
    "sg:postcode":"7442",
    "sg:province":"Danmark",
    "wof:name":"M\u00f8ller, Meinert",
    "wof:placetype":"venue"
},
  "geometry": {"coordinates":[9.3503713608,56.1701393127],"type":"Point"}
}