{
  "type": "Feature",
  "properties": {
    "iso:country":"DK",
    "sg:address":"v/ Rita Hansen, Teglbr\u00e6ndervej 28, Lillebr\u00e6nde",
    "sg:city":"Stubbek\u00f8bing",
    "sg:orig_category":"Spejderkorps",
    "sg:phone":"+45 54 43 32 90",
    "sg:postcode":"4850",
    "sg:province":"Danmark",
    "wof:name":"Det Danske Spejderkorps, N\u00f8rre Alslev gruppe",
    "wof:placetype":"venue"
},
  "geometry": {"coordinates":[-114.0767440796,46.4432487488],"type":"Point"}
}