{
  "type": "Feature",
  "properties": {
    "addr:full":"Rolighedsvej 16 Bogense Danmark 5400",
    "addr:housenumber":"16",
    "addr:postcode":"5400",
    "addr:street":"Rolighedsvej",
    "iso:country":"DK",
    "sg:address":"Rolighedsvej 16",
    "sg:city":"Bogense",
    "sg:orig_category":"Plejehjem",
    "sg:phone":"+45 64 81 10 81",
    "sg:postcode":"5400",
    "sg:province":"Danmark",
    "wof:name":"S\u00f8bo Plejehjem for S\u00f8nders\u00f8 og Bogense kommuner",
    "wof:placetype":"venue"
},
  "geometry": {"coordinates":[10.0929613113,55.5688972473],"type":"Point"}
}