{
  "type": "Feature",
  "properties": {
    "addr:full":"Skoletoften 7, Sinding Herning Danmark 7400",
    "addr:housenumber":"7",
    "addr:postcode":"7400",
    "addr:street":"Skoletoften;Sinding",
    "iso:country":"DK",
    "sg:address":"Skoletoften 7, Sinding",
    "sg:city":"Herning",
    "sg:orig_category":"Lokalarkiver",
    "sg:phone":"+45 97 13 62 52",
    "sg:postcode":"7400",
    "sg:province":"Danmark",
    "wof:name":"\u00d8rre-Sinding Sognearkiv",
    "wof:placetype":"venue"
},
  "geometry": {"coordinates":[8.9768896103,56.1374168396],"type":"Point"}
}