{
  "type": "Feature",
  "properties": {
    "addr:full":"Gr\u00f8nnevej 7 Bogense Danmark 5400",
    "addr:housenumber":"7",
    "addr:postcode":"5400",
    "addr:street":"Gronnevej",
    "iso:country":"DK",
    "sg:address":"Gr\u00f8nnevej 7",
    "sg:city":"Bogense",
    "sg:orig_category":"Campingpladser",
    "sg:phone":"+45 64 81 14 43",
    "sg:postcode":"5400",
    "sg:province":"Danmark",
    "wof:name":"Kirkebakkens Camping",
    "wof:placetype":"venue"
},
  "geometry": {"coordinates":[10.0923128128,55.5692558289],"type":"Point"}
}