{
  "type": "Feature",
  "properties": {
    "iso:country":"DK",
    "sg:address":"Klakringvej 43, Klakring",
    "sg:city":"Juelsminde",
    "sg:orig_category":"Blikkenslagere",
    "sg:phone":"+45 75 69 44 99",
    "sg:postcode":"7130",
    "sg:province":"Danmark",
    "sg:website":"www.juelsmindevvs.dk",
    "wof:name":"Juelsminde VVS & Blik ApS",
    "wof:placetype":"venue"
},
  "geometry": {"coordinates":[10.014399,55.713585],"type":"Point"}
}