{
  "type": "Feature",
  "properties": {
    "iso:country":"DK",
    "sg:address":"N\u00f8rregade 38",
    "sg:city":"Skive",
    "sg:orig_category":"Supermarkeder",
    "sg:phone":"+45 97 52 96 60",
    "sg:postcode":"7800",
    "sg:province":"Danmark",
    "wof:name":"REMA 1000",
    "wof:placetype":"venue"
},
  "geometry": {"coordinates":[9.0282068253,56.5692863464],"type":"Point"}
}