{
  "type": "Feature",
  "properties": {
    "addr:full":"Jernbanegade 75 - 77 Middelfart Danmark 5500",
    "addr:housenumber":"75 77",
    "addr:postcode":"5500",
    "addr:street":"Jernbanegade",
    "iso:country":"DK",
    "sg:address":"Jernbanegade 75 - 77",
    "sg:city":"Middelfart",
    "sg:orig_category":"Autoreparation og -service",
    "sg:phone":"+45 63 41 89 88",
    "sg:postcode":"5500",
    "sg:province":"Danmark",
    "sg:website":"www.automester.dk",
    "wof:name":"AutoMester ApS",
    "wof:placetype":"venue"
},
  "geometry": {"coordinates":[9.7360467911,55.5019035339],"type":"Point"}
}