{
  "type": "Feature",
  "properties": {
    "addr:full":"Mindebrogade 5 \u00c5rhus C Danmark 8000",
    "addr:housenumber":"5",
    "addr:postcode":"8000",
    "addr:street":"Mindebrogade",
    "iso:country":"DK",
    "sg:address":"Mindebrogade 5",
    "sg:city":"\u00c5rhus C",
    "sg:classifiers":[
        {
            "category":"Restaurant",
            "type":"Food & Drink"
        }
    ],
    "sg:phone":"+45 86 13 14 79",
    "sg:postcode":"8000",
    "sg:province":"Danmark",
    "wof:name":"La Pampa",
    "wof:placetype":"venue"
},
  "geometry": {"coordinates":[4.717400074,49.7588005066],"type":"Point"}
}