{
  "type": "Feature",
  "properties": {
    "iso:country":"DK",
    "sg:address":"Askelundsvej 1",
    "sg:city":"Frederikssund",
    "sg:orig_category":"Benzinstationer",
    "sg:phone":"+45 47 31 19 45",
    "sg:postcode":"3600",
    "sg:province":"Danmark",
    "wof:name":"Shell",
    "wof:placetype":"venue"
},
  "geometry": {"coordinates":[12.073994,55.844105],"type":"Point"}
}