{
  "type": "Feature",
  "properties": {
    "addr:full":"v/ Poul Nielsen, Selk\u00e6rvej 9 Glesborg Danmark 8585",
    "addr:housenumber":"9",
    "addr:postcode":"8585",
    "addr:street":"Selkaervej",
    "iso:country":"DK",
    "sg:address":"v/ Poul Nielsen, Selk\u00e6rvej 9",
    "sg:city":"Glesborg",
    "sg:orig_category":"Folkedans",
    "sg:phone":"+45 86 38 72 17",
    "sg:postcode":"8585",
    "sg:province":"Danmark",
    "wof:name":"Glesborg Folkedanserforening",
    "wof:placetype":"venue"
},
  "geometry": {"coordinates":[10.5884723663,56.5124320984],"type":"Point"}
}