{
  "type": "Feature",
  "properties": {
    "addr:full":"St. Sct. Hans Gade 10 Viborg Danmark 8800",
    "addr:housenumber":"10",
    "addr:postcode":"8800",
    "addr:street":"Hans Gade",
    "iso:country":"DK",
    "sg:address":"St. Sct. Hans Gade 10",
    "sg:city":"Viborg",
    "sg:orig_category":"Dyrehandlere",
    "sg:phone":"+45 86 62 74 10",
    "sg:postcode":"8800",
    "sg:province":"Danmark",
    "wof:name":"\u00c6kvator",
    "wof:placetype":"venue"
},
  "geometry": {"coordinates":[9.4096736908,56.4520568848],"type":"Point"}
}