{
  "type": "Feature",
  "properties": {
    "addr:full":"S\u00f8ndergade 33, Otterup Otterup Danmark 5450",
    "addr:housenumber":"33",
    "addr:postcode":"5450",
    "addr:street":"Sondergade",
    "iso:country":"DK",
    "sg:address":"S\u00f8ndergade 33, Otterup",
    "sg:city":"Otterup",
    "sg:classifiers":[
        {
            "category":"Professional",
            "subcategory":"Computer Services",
            "type":"Services"
        }
    ],
    "sg:phone":"+45 45 82 20 40",
    "sg:postcode":"5450",
    "sg:province":"Danmark",
    "sg:tags":[
        "edb",
        "-",
        "software"
    ],
    "sg:website":"www.sejer.dk",
    "wof:name":"Johansen Informatik ApS, Sejer",
    "wof:placetype":"venue"
},
  "geometry": {"coordinates":[10.4545049667,55.5641746521],"type":"Point"}
}