{
  "type": "Feature",
  "properties": {
    "addr:full":"Thorvaldsensgade 23 \u00c5rhus C Danmark 8000",
    "addr:housenumber":"23",
    "addr:postcode":"8000",
    "addr:street":"Thorvaldsensgade",
    "iso:country":"DK",
    "sg:address":"Thorvaldsensgade 23",
    "sg:city":"\u00c5rhus C",
    "sg:classifiers":[
        {
            "category":"Banks & Credit Unions",
            "subcategory":"Bank",
            "type":"Services"
        }
    ],
    "sg:phone":"+45 87 31 43 70",
    "sg:postcode":"8000",
    "sg:province":"Danmark",
    "sg:tags":[
        "banker"
    ],
    "sg:website":"www.danskebank.dk",
    "wof:name":"Danske Bank",
    "wof:placetype":"venue"
},
  "geometry": {"coordinates":[4.717400074,49.7588005066],"type":"Point"}
}