{
  "type": "Feature",
  "properties": {
    "iso:country":"DK",
    "sg:address":"Havnevej 8",
    "sg:city":"Struer",
    "sg:orig_category":"Slagterier",
    "sg:phone":"+45 97 85 07 00",
    "sg:postcode":"7600",
    "sg:province":"Danmark",
    "wof:name":"Danish Crown",
    "wof:placetype":"venue"
},
  "geometry": {"coordinates":[8.6035337448,56.4933052063],"type":"Point"}
}