{
  "type": "Feature",
  "properties": {
    "addr:full":"Jernbanegade 23 Agerb\u00e6k Danmark 6753",
    "addr:housenumber":"23",
    "addr:postcode":"6753",
    "addr:street":"Jernbanegade",
    "iso:country":"DK",
    "sg:address":"Jernbanegade 23",
    "sg:city":"Agerb\u00e6k",
    "sg:orig_category":"Rutebiler",
    "sg:phone":"+45 75 19 63 32",
    "sg:postcode":"6753",
    "sg:province":"Danmark",
    "wof:name":"Thykj\u00e6rs Turistbusser, Bent",
    "wof:placetype":"venue"
},
  "geometry": {"coordinates":[8.802646637,55.6009178162],"type":"Point"}
}