{
  "type": "Feature",
  "properties": {
    "addr:full":"T\u00e5rnparken 42 Nyborg Danmark 5800",
    "addr:housenumber":"42",
    "addr:postcode":"5800",
    "addr:street":"Taarnparken",
    "iso:country":"DK",
    "sg:address":"T\u00e5rnparken 42",
    "sg:city":"Nyborg",
    "sg:orig_category":"Plejecentre",
    "sg:phone":"+45 65 31 70 10",
    "sg:postcode":"5800",
    "sg:province":"Danmark",
    "wof:name":"\u00c6ldrecentret T\u00e5rnparken",
    "wof:placetype":"venue"
},
  "geometry": {"coordinates":[10.7852592468,55.3097076416],"type":"Point"}
}