{
  "type": "Feature",
  "properties": {
    "addr:full":"Sdr. Alslev Strandvej 12, Sdr. Alslev Nyk\u00f8bing Danmark 4800",
    "addr:housenumber":"12",
    "addr:postcode":"4800",
    "addr:street":"Sdr. Alslev Strandvej;Sdr. Alslev;Danmark",
    "iso:country":"DK",
    "sg:address":"Sdr. Alslev Strandvej 12, Sdr. Alslev",
    "sg:city":"Nyk\u00f8bing",
    "sg:orig_category":"Kirker",
    "sg:postcode":"4800",
    "sg:province":"Danmark",
    "wof:name":"Sdr. Alslev Kirke",
    "wof:placetype":"venue"
},
  "geometry": {"coordinates":[-3.8237500191,43.423210144],"type":"Point"}
}