{
  "type": "Feature",
  "properties": {
    "iso:country":"DK",
    "sg:address":"Randersvej 586, Sp\u00f8rring",
    "sg:city":"Trige",
    "sg:orig_category":"Lastvogne",
    "sg:phone":"+45 86 98 91 05",
    "sg:postcode":"8380",
    "sg:province":"Danmark",
    "sg:website":"www.karrosserifabrik.dk",
    "wof:name":"Sp\u00f8rring Karrosserifabrik",
    "wof:placetype":"venue"
},
  "geometry": {"coordinates":[10.1453504562,56.2532615662],"type":"Point"}
}