{
  "type": "Feature",
  "properties": {
    "iso:country":"DK",
    "sg:address":"Hold-An Vej 5",
    "sg:city":"Ballerup",
    "sg:orig_category":"Jordemodercentre",
    "sg:phone":"+45 44 65 26 08",
    "sg:postcode":"2750",
    "sg:province":"Danmark",
    "wof:name":"Jordemodercentret i Ballerup.",
    "wof:placetype":"venue"
},
  "geometry": {"coordinates":[12.3629779816,55.7352409363],"type":"Point"}
}