{
  "type": "Feature",
  "properties": {
    "iso:country":"DK",
    "sg:address":"Gruppeleder: Flemming Nielsen, Svalevej 10",
    "sg:city":"Fars\u00f8",
    "sg:orig_category":"Spejderkorps",
    "sg:phone":"+45 98 63 25 20",
    "sg:postcode":"9640",
    "sg:province":"Danmark",
    "wof:name":"KFUM-spejderne - Fars\u00f8 Graneborg",
    "wof:placetype":"venue"
},
  "geometry": {"coordinates":[-109.44831848139999,42.1062355042],"type":"Point"}
}