{
  "type": "Feature",
  "properties": {
    "addr:full":"Store R\u00e5dhusgade 1 S\u00f8nderborg Danmark 6400",
    "addr:housenumber":"1",
    "addr:postcode":"6400",
    "addr:street":"Raadhusgade",
    "iso:country":"DK",
    "sg:address":"Store R\u00e5dhusgade 1",
    "sg:city":"S\u00f8nderborg",
    "sg:orig_category":"Cafeer",
    "sg:phone":"+45 74 43 43 90",
    "sg:postcode":"6400",
    "sg:province":"Danmark",
    "wof:name":"Cafe Druen",
    "wof:placetype":"venue"
},
  "geometry": {"coordinates":[15.3213195801,46.2218589783],"type":"Point"}
}