{
  "type": "Feature",
  "properties": {
    "addr:full":"Teknisk Afdeling, Egevangsvej 2 Ullerslev Danmark 5540",
    "addr:housenumber":"2",
    "addr:postcode":"5540",
    "addr:street":"Egevangsvej",
    "iso:country":"DK",
    "sg:address":"Teknisk Afdeling, Egevangsvej 2",
    "sg:city":"Ullerslev",
    "sg:orig_category":"Varmeforsyning",
    "sg:phone":"+45 63 35 11 57",
    "sg:postcode":"5540",
    "sg:province":"Danmark",
    "wof:name":"Ullerslev Kommunale Fjernvarmeforsyning",
    "wof:placetype":"venue"
},
  "geometry": {"coordinates":[10.6675348282,55.3605728149],"type":"Point"}
}