{
  "type": "Feature",
  "properties": {
    "addr:full":"Sadelmagervej 2-4 K\u00f8benhavn NV Danmark 2400",
    "addr:housenumber":"2-4",
    "addr:postcode":"2400",
    "addr:street":"Sadelmagervej",
    "iso:country":"DK",
    "sg:address":"Sadelmagervej 2-4",
    "sg:city":"K\u00f8benhavn NV",
    "sg:orig_category":"Vuggestuer",
    "sg:phone":"+45 35 81 20 08",
    "sg:postcode":"2400",
    "sg:province":"Danmark",
    "wof:name":"Bispebjerg vuggestue",
    "wof:placetype":"venue"
},
  "geometry": {"coordinates":[-117.02272033689999,38.5024604797],"type":"Point"}
}