{
  "type": "Feature",
  "properties": {
    "iso:country":"DK",
    "sg:address":"Slagelsevej 15",
    "sg:city":"Ruds Vedby",
    "sg:orig_category":"Malermestre",
    "sg:phone":"+45 21 75 31 01",
    "sg:postcode":"4291",
    "sg:province":"Danmark",
    "wof:name":"Nielsen's Eftf., Poul",
    "wof:placetype":"venue"
},
  "geometry": {"coordinates":[11.3712234497,55.5381011963],"type":"Point"}
}