{
  "type": "Feature",
  "properties": {
    "iso:country":"DK",
    "sg:address":"Vestergade 6",
    "sg:city":"Svaneke",
    "sg:orig_category":"Grafiske tegnestuer",
    "sg:phone":"+45 56 49 66 36",
    "sg:postcode":"3740",
    "sg:province":"Danmark",
    "wof:name":"Hamilton, Jane",
    "wof:placetype":"venue"
},
  "geometry": {"coordinates":[15.1407337189,55.134765625],"type":"Point"}
}