{
  "type": "Feature",
  "properties": {
    "addr:full":"Vesterbro 63 Odense C Danmark 5000",
    "addr:housenumber":"63",
    "addr:postcode":"5000",
    "addr:street":"Vesterbro",
    "iso:country":"DK",
    "sg:address":"Vesterbro 63",
    "sg:city":"Odense C",
    "sg:orig_category":"Cykler",
    "sg:phone":"+45 66 14 48 48",
    "sg:postcode":"5000",
    "sg:province":"Danmark",
    "wof:name":"J. R.-Dele",
    "wof:placetype":"venue"
},
  "geometry": {"coordinates":[10.3741979599,55.3942909241],"type":"Point"}
}