{
  "type": "Feature",
  "properties": {
    "addr:full":"Bernstorffsvej 172 Charlottenlund Danmark 2920",
    "addr:housenumber":"172",
    "addr:postcode":"2920",
    "addr:street":"Bernstorffsvej",
    "iso:country":"DK",
    "sg:address":"Bernstorffsvej 172",
    "sg:city":"Charlottenlund",
    "sg:orig_category":"Ejendomshandel",
    "sg:phone":"+45 39 64 10 33",
    "sg:postcode":"2920",
    "sg:province":"Danmark",
    "wof:name":"Strand, Anne",
    "wof:placetype":"venue"
},
  "geometry": {"coordinates":[12.55747509,55.7474555969],"type":"Point"}
}