{
  "type": "Feature",
  "properties": {
    "addr:full":"Kystvej 52, Egense Storvorde Danmark 9280",
    "addr:housenumber":"52",
    "addr:postcode":"9280",
    "addr:street":"Kystvej",
    "iso:country":"DK",
    "sg:address":"Kystvej 52, Egense",
    "sg:city":"Storvorde",
    "sg:orig_category":"Private- og friskoler",
    "sg:phone":"+45 98 31 18 07",
    "sg:postcode":"9280",
    "sg:province":"Danmark",
    "sg:website":"home6.inet.tele.dk/egefrisk/index.htm",
    "wof:name":"Egense Friskole",
    "wof:placetype":"venue"
},
  "geometry": {"coordinates":[10.1014204025,57.0045547485],"type":"Point"}
}