{
  "type": "Feature",
  "properties": {
    "iso:country":"DK",
    "sg:address":"Gartnerv\u00e6nget 31 ",
    "sg:city":"Outrup",
    "sg:classifiers":[
        {
            "category":"Farming",
            "subcategory":"Livestock Farm",
            "type":"Manufacturing & Wholesale Goods"
        }
    ],
    "sg:phone":"+45 76 52 23 00",
    "sg:postcode":"6855",
    "sg:province":"Danmark",
    "sg:tags":[
        "agriculture"
    ],
    "wof:name":"NORLAX A/S",
    "wof:placetype":"venue"
},
  "geometry": {"coordinates":[8.3726921082,55.692855835],"type":"Point"}
}