{
  "type": "Feature",
  "properties": {
    "addr:full":"Gammelmosevej 180 Kongens Lyngby Danmark 2800",
    "addr:housenumber":"180",
    "addr:postcode":"2800",
    "addr:street":"Gammelmosevej",
    "iso:country":"DK",
    "sg:address":"Gammelmosevej 180",
    "sg:city":"Kongens Lyngby",
    "sg:orig_category":"Fotografer",
    "sg:phone":"+45 44 37 37 37",
    "sg:postcode":"2800",
    "sg:province":"Danmark",
    "wof:name":"Dansk Skolefoto ApS",
    "wof:placetype":"venue"
},
  "geometry": {"coordinates":[12.4840106964,55.7557373047],"type":"Point"}
}