{
  "type": "Feature",
  "properties": {
    "addr:full":"Efter\u00e5rsvej 9 Fakse Ladeplads Danmark 4654",
    "addr:housenumber":"9",
    "addr:postcode":"4654",
    "addr:street":"Efteraarsvej",
    "iso:country":"DK",
    "sg:address":"Efter\u00e5rsvej 9",
    "sg:city":"Fakse Ladeplads",
    "sg:orig_category":"Erhvervslokaler, Udlejning af",
    "sg:phone":"+45 56 71 75 56",
    "sg:postcode":"4654",
    "sg:province":"Danmark",
    "wof:name":"S\u00f8lunds Ejendomsselskab, J.",
    "wof:placetype":"venue"
},
  "geometry": {"coordinates":[12.1833677292,55.2222480774],"type":"Point"}
}