{
  "type": "Feature",
  "properties": {
    "addr:full":"Louisevej 8 Haderslev Danmark 6100",
    "addr:housenumber":"8",
    "addr:postcode":"6100",
    "addr:street":"Louisevej",
    "iso:country":"DK",
    "sg:address":"Louisevej 8",
    "sg:city":"Haderslev",
    "sg:orig_category":"Specialskoler for handicappede",
    "sg:phone":"+45 74 52 21 39",
    "sg:postcode":"6100",
    "sg:province":"Danmark",
    "wof:name":"Skolen ved Stadion",
    "wof:placetype":"venue"
},
  "geometry": {"coordinates":[9.4869203568,55.2602348328],"type":"Point"}
}