{
  "type": "Feature",
  "properties": {
    "addr:full":"Willemoesvej 5 Svendborg Danmark 5700",
    "addr:housenumber":"5",
    "addr:postcode":"5700",
    "addr:street":"Willemoesvej",
    "iso:country":"DK",
    "sg:address":"Willemoesvej 5",
    "sg:city":"Svendborg",
    "sg:classifiers":[
        {
            "category":"Wholesale",
            "subcategory":"Chemicals & Plastics",
            "type":"Manufacturing & Wholesale Goods"
        }
    ],
    "sg:phone":"+45 62 21 02 93",
    "sg:postcode":"5700",
    "sg:province":"Danmark",
    "sg:website":"www.groenbeck.dk",
    "wof:name":"Gr\u00f8nbeck Formkonstruktion",
    "wof:placetype":"venue"
},
  "geometry": {"coordinates":[10.6092739105,55.0550575256],"type":"Point"}
}