{
  "type": "Feature",
  "properties": {
    "iso:country":"DK",
    "sg:address":"v/ Svend B. Dall, Troldk\u00e6rvej 14, Skudstr Mark",
    "sg:city":"R\u00f8dding",
    "sg:orig_category":"Kulturelle foreninger",
    "sg:phone":"+45 74 84 84 55",
    "sg:postcode":"6630",
    "sg:province":"Danmark",
    "wof:name":"R\u00f8dding Mandskor",
    "wof:placetype":"venue"
},
  "geometry": {"coordinates":[77.2480392456,14.1354398727],"type":"Point"}
}