{
  "type": "Feature",
  "properties": {
    "addr:full":"Strandvejen 16, Aarsdale Svaneke Danmark 3740",
    "addr:housenumber":"16",
    "addr:postcode":"3740",
    "addr:street":"Strandvejen;Aarsdale",
    "iso:country":"DK",
    "sg:address":"Strandvejen 16, Aarsdale",
    "sg:city":"Svaneke",
    "sg:orig_category":"Alternativ behandling",
    "sg:phone":"+45 56 49 64 35",
    "sg:postcode":"3740",
    "sg:province":"Danmark",
    "wof:name":"Aarsdale Helseklinik",
    "wof:placetype":"venue"
},
  "geometry": {"coordinates":[15.140504837,55.1364555359],"type":"Point"}
}