{
  "type": "Feature",
  "properties": {
    "iso:country":"DK",
    "sg:address":"Aalborgvej 219",
    "sg:city":"Vesl\u00f8s",
    "sg:orig_category":"Servicestationer",
    "sg:phone":"+45 97 99 31 77",
    "sg:postcode":"7742",
    "sg:province":"Danmark",
    "wof:name":"DK-Benzin \u00d8sl\u00f8s",
    "wof:placetype":"venue"
},
  "geometry": {"coordinates":[-78.129913,36.726742],"type":"Point"}
}