{
  "type": "Feature",
  "properties": {
    "addr:full":"Sankt Knuds Vej 27 Frederiksberg Danmark 1903",
    "addr:housenumber":"27",
    "addr:postcode":"1903",
    "addr:street":"Sankt Knuds Vej",
    "iso:country":"DK",
    "sg:address":"Sankt Knuds Vej 27",
    "sg:city":"Frederiksberg",
    "sg:orig_category":"\u00c3\u02dcvrige foreninger",
    "sg:phone":"+45 33 23 27 21",
    "sg:postcode":"1903",
    "sg:province":"Danmark",
    "wof:name":"Teosofisk Forening Skandinavien",
    "wof:placetype":"venue"
},
  "geometry": {"coordinates":[12.549290657,55.6775665283],"type":"Point"}
}