{
  "type": "Feature",
  "properties": {
    "addr:full":"Trehusevej 34, Frederiks Karup Danmark 7470",
    "addr:housenumber":"34",
    "addr:postcode":"7470",
    "addr:street":"Trehusevej",
    "iso:country":"DK",
    "sg:address":"Trehusevej 34, Frederiks",
    "sg:city":"Karup",
    "sg:orig_category":"Flytteforretninger",
    "sg:phone":"+45 86 66 22 22",
    "sg:postcode":"7470",
    "sg:province":"Danmark",
    "wof:name":"Frederiks Flytteforretning",
    "wof:placetype":"venue"
},
  "geometry": {"coordinates":[9.2525548935,56.3398017883],"type":"Point"}
}