{
  "type": "Feature",
  "properties": {
    "iso:country":"DK",
    "sg:address":"Vigerslev Alle 80",
    "sg:city":"Valby",
    "sg:orig_category":"Bagere",
    "sg:phone":"+45 36 17 42 65",
    "sg:postcode":"2500",
    "sg:province":"Danmark",
    "wof:name":"All\u00e9 Konditoriet",
    "wof:placetype":"venue"
},
  "geometry": {"coordinates":[12.511881,55.661476],"type":"Point"}
}