{
  "type": "Feature",
  "properties": {
    "addr:full":"v/ Niels-Ulrik Bugge, S\u00f8krogen 69 Odder Danmark 8300",
    "addr:housenumber":"69",
    "addr:postcode":"8300",
    "iso:country":"DK",
    "sg:address":"v/ Niels-Ulrik Bugge, S\u00f8krogen 69",
    "sg:city":"Odder",
    "sg:orig_category":"Grundejerforeninger",
    "sg:phone":"+45 86 54 31 88",
    "sg:postcode":"8300",
    "sg:province":"Danmark",
    "wof:name":"Rude & Saksild Strands Hus- og Grundejerforening",
    "wof:placetype":"venue"
},
  "geometry": {"coordinates":[10.1497612,55.9733161926],"type":"Point"}
}