{
  "type": "Feature",
  "properties": {
    "iso:country":"DK",
    "sg:address":"Kontaktpers.: Preben Christensen, M\u00f8llebakken 16",
    "sg:city":"Aarup",
    "sg:orig_category":"Spejderkorps",
    "sg:phone":"+45 64 43 21 93",
    "sg:postcode":"5560",
    "sg:province":"Danmark",
    "wof:name":"Det danske Spejderkorps Aarup pigegruppe",
    "wof:placetype":"venue"
},
  "geometry": {"coordinates":[10.0490245819,55.3808059692],"type":"Point"}
}