{
  "type": "Feature",
  "properties": {
    "addr:full":"Fmd.: Gerda Nissen, Plougstrupvej 53, Jernvedlund Gredstedbro Danmark 6771",
    "addr:housenumber":"53",
    "addr:postcode":"6771",
    "addr:street":"Plougstrupvej",
    "iso:country":"DK",
    "sg:address":"Fmd.: Gerda Nissen, Plougstrupvej 53, Jernvedlund",
    "sg:city":"Gredstedbro",
    "sg:orig_category":"Husflidsforeninger",
    "sg:phone":"+45 75 43 52 31",
    "sg:postcode":"6771",
    "sg:province":"Danmark",
    "wof:name":"Jernved Husholdningsforening",
    "wof:placetype":"venue"
},
  "geometry": {"coordinates":[8.7442560196,55.3970336914],"type":"Point"}
}