{
  "type": "Feature",
  "properties": {
    "addr:full":"Forskerparken 10 Odense M Danmark 5230",
    "addr:housenumber":"10",
    "addr:postcode":"5230",
    "addr:street":"Forskerparken",
    "iso:country":"DK",
    "sg:address":"Forskerparken 10",
    "sg:city":"Odense M",
    "sg:orig_category":"Erhvervslokaler, Udlejning af",
    "sg:phone":"+45 63 15 71 00",
    "sg:postcode":"5230",
    "sg:province":"Danmark",
    "wof:name":"Fonden International Science Park Odense",
    "wof:placetype":"venue"
},
  "geometry": {"coordinates":[10.4131202698,55.3696708679],"type":"Point"}
}