{
  "type": "Feature",
  "properties": {
    "addr:full":"Lundagervej 20 Hedensted Danmark 8722",
    "addr:housenumber":"20",
    "addr:postcode":"8722",
    "addr:street":"Lundagervej",
    "iso:country":"DK",
    "sg:address":"Lundagervej 20",
    "sg:city":"Hedensted",
    "sg:orig_category":"Isoleringsmateriel",
    "sg:phone":"+45 76 74 16 11",
    "sg:postcode":"8722",
    "sg:province":"Danmark",
    "sg:website":"www.thermisol.dk",
    "wof:name":"Thermisol Denmark A/S",
    "wof:placetype":"venue"
},
  "geometry": {"coordinates":[9.6745767593,55.7902832031],"type":"Point"}
}