{
  "type": "Feature",
  "properties": {
    "addr:full":"Fmd.: Lis J\u00fctte Jensen, Krog\u00e5rdsvej 46 Greve Danmark 2670",
    "addr:housenumber":"46",
    "addr:postcode":"2670",
    "addr:street":"Fmd.;Juette;Krogaardsvej",
    "iso:country":"DK",
    "sg:address":"Fmd.: Lis J\u00fctte Jensen, Krog\u00e5rdsvej 46",
    "sg:city":"Greve",
    "sg:orig_category":"Grundejerforeninger",
    "sg:phone":"+45 43 90 28 82",
    "sg:postcode":"2670",
    "sg:province":"Danmark",
    "wof:name":"Krog\u00e5rdsvejens Grundejerforening",
    "wof:placetype":"venue"
},
  "geometry": {"coordinates":[12.2941808701,55.5844078064],"type":"Point"}
}