{
  "type": "Feature",
  "properties": {
    "addr:full":"Hovedgaden 31 Tinglev Danmark 6360",
    "addr:housenumber":"31",
    "addr:postcode":"6360",
    "addr:street":"Hovedgaden",
    "iso:country":"DK",
    "sg:address":"Hovedgaden 31",
    "sg:city":"Tinglev",
    "sg:orig_category":"Pizzeriaer",
    "sg:phone":"+45 74 64 27 87",
    "sg:postcode":"6360",
    "sg:province":"Danmark",
    "wof:name":"Pizza & Kebab Huset",
    "wof:placetype":"venue"
},
  "geometry": {"coordinates":[9.2529630661,54.9368858337],"type":"Point"}
}