{
  "type": "Feature",
  "properties": {
    "addr:full":"Blumersgade 8 Horsens Danmark 8700",
    "addr:housenumber":"8",
    "addr:postcode":"8700",
    "addr:street":"Blumersgade",
    "iso:country":"DK",
    "sg:address":"Blumersgade 8",
    "sg:city":"Horsens",
    "sg:orig_category":"Danseundervisning",
    "sg:phone":"+45 75 61 89 00",
    "sg:postcode":"8700",
    "sg:province":"Danmark",
    "wof:name":"Juliussens Danseinstitut",
    "wof:placetype":"venue"
},
  "geometry": {"coordinates":[9.838602066,55.8600540161],"type":"Point"}
}