{
  "type": "Feature",
  "properties": {
    "addr:full":"Bavnestien 5 N\u00e6rum Danmark 2850",
    "addr:housenumber":"5",
    "addr:postcode":"2850",
    "addr:street":"Bavnestien",
    "iso:country":"DK",
    "sg:address":"Bavnestien 5",
    "sg:city":"N\u00e6rum",
    "sg:orig_category":"Psykologer, praktiserende",
    "sg:phone":"+45 45 80 15 45",
    "sg:postcode":"2850",
    "sg:province":"Danmark",
    "wof:name":"Winkel, Birgitte",
    "wof:placetype":"venue"
},
  "geometry": {"coordinates":[-89.99810791020001,38.1321372986],"type":"Point"}
}