{
  "type": "Feature",
  "properties": {
    "addr:full":"Nordre Fasanvej 91 Frederiksberg Danmark 2000",
    "addr:housenumber":"91",
    "addr:postcode":"2000",
    "addr:street":"Nordre Fasanvej",
    "iso:country":"DK",
    "sg:address":"Nordre Fasanvej 91",
    "sg:city":"Frederiksberg",
    "sg:orig_category":"Reklamebureauer",
    "sg:phone":"+45 38 32 22 22",
    "sg:postcode":"2000",
    "sg:province":"Danmark",
    "sg:website":"www.sylvester-hvid.dk",
    "wof:name":"sylvester-hvid & partners a/s",
    "wof:placetype":"venue"
},
  "geometry": {"coordinates":[12.5277204514,55.6884498596],"type":"Point"}
}