{
  "type": "Feature",
  "properties": {
    "iso:country":"DK",
    "sg:address":"Gothersgade 143",
    "sg:city":"K\u00f8benhavn",
    "sg:orig_category":"Billedhuggere",
    "sg:phone":"+45 33 15 89 05",
    "sg:postcode":"1123",
    "sg:province":"Danmark",
    "wof:name":"Grut, Jeanne",
    "wof:placetype":"venue"
},
  "geometry": {"coordinates":[12.57723,55.683849],"type":"Point"}
}