{
  "type": "Feature",
  "properties": {
    "addr:full":"Vestergade 11 A Saksk\u00f8bing Danmark 4990",
    "addr:housenumber":"11 a",
    "addr:postcode":"4990",
    "addr:street":"Vestergade",
    "iso:country":"DK",
    "sg:address":"Vestergade 11 A",
    "sg:city":"Saksk\u00f8bing",
    "sg:orig_category":"Zoneterapeuter",
    "sg:phone":"+45 54 70 71 91",
    "sg:postcode":"4990",
    "sg:province":"Danmark",
    "wof:name":"Klinik for Zoneterapi & Massage",
    "wof:placetype":"venue"
},
  "geometry": {"coordinates":[9.5455904007,56.1682090759],"type":"Point"}
}