{
  "type": "Feature",
  "properties": {
    "addr:full":"Vesterbrogade 12, 1. Grindsted Danmark 7200",
    "addr:housenumber":"12 1",
    "addr:postcode":"7200",
    "addr:street":"Vesterbrogade",
    "iso:country":"DK",
    "sg:address":"Vesterbrogade 12, 1.",
    "sg:city":"Grindsted",
    "sg:orig_category":"Advokater",
    "sg:phone":"+45 75 32 07 00",
    "sg:postcode":"7200",
    "sg:province":"Danmark",
    "wof:name":"Advokatkontoret Thomsen & Storgaard",
    "wof:placetype":"venue"
},
  "geometry": {"coordinates":[8.9265975952,55.7549591064],"type":"Point"}
}