{
  "type": "Feature",
  "properties": {
    "addr:full":"Nyborgvej 4 Odense C Danmark 5000",
    "addr:housenumber":"4",
    "addr:postcode":"5000",
    "addr:street":"Nyborgvej",
    "iso:country":"DK",
    "sg:address":"Nyborgvej 4",
    "sg:city":"Odense C",
    "sg:orig_category":"Reparationer",
    "sg:phone":"+45 66 14 15 34",
    "sg:postcode":"5000",
    "sg:province":"Danmark",
    "wof:name":"J.N. Teknik",
    "wof:placetype":"venue"
},
  "geometry": {"coordinates":[10.4012537003,55.3945808411],"type":"Point"}
}