{
  "type": "Feature",
  "properties": {
    "addr:full":"S\u00f8ndergade 27, Onsbjerg Sams\u00f8 Danmark 8305",
    "addr:housenumber":"27",
    "addr:postcode":"8305",
    "addr:street":"Sondergade",
    "iso:country":"DK",
    "sg:address":"S\u00f8ndergade 27, Onsbjerg",
    "sg:city":"Sams\u00f8",
    "sg:classifiers":[
        {
            "category":"Personal",
            "subcategory":"Massage",
            "type":"Services"
        }
    ],
    "sg:phone":"+45 86 59 13 12",
    "sg:postcode":"8305",
    "sg:province":"Danmark",
    "wof:name":"Rasmussen, Joan Lykke",
    "wof:placetype":"venue"
},
  "geometry": {"coordinates":[10.5885000229,55.8320198059],"type":"Point"}
}