{
  "type": "Feature",
  "properties": {
    "addr:full":"Kongevej 13 Gram Danmark 6510",
    "addr:housenumber":"13",
    "addr:postcode":"6510",
    "addr:street":"Kongevej",
    "iso:country":"DK",
    "sg:address":"Kongevej 13",
    "sg:city":"Gram",
    "sg:orig_category":"Autoforhandlere",
    "sg:phone":"+45 74 82 07 17",
    "sg:postcode":"6510",
    "sg:province":"Danmark",
    "wof:name":"Centrum Biler",
    "wof:placetype":"venue"
},
  "geometry": {"coordinates":[9.0471000671,55.2878303528],"type":"Point"}
}