{
  "type": "Feature",
  "properties": {
    "addr:full":"Hvidkildevej 1 K\u00f8benhavn NV Danmark 2400",
    "addr:housenumber":"1",
    "addr:postcode":"2400",
    "addr:street":"Hvidkildevej",
    "iso:country":"DK",
    "sg:address":"Hvidkildevej 1",
    "sg:city":"K\u00f8benhavn NV",
    "sg:orig_category":"Dykkerudstyr",
    "sg:phone":"+45 38 88 80 86",
    "sg:postcode":"2400",
    "sg:province":"Danmark",
    "sg:website":"www.adventurewarehouse.dk",
    "wof:name":"Adventure Warehouse",
    "wof:placetype":"venue"
},
  "geometry": {"coordinates":[-117.02272033689999,38.5024604797],"type":"Point"}
}