{
  "type": "Feature",
  "properties": {
    "addr:full":"Koustrupparken 40 Herning Danmark 7400",
    "addr:housenumber":"40",
    "addr:postcode":"7400",
    "addr:street":"Koustrupparken",
    "iso:country":"DK",
    "sg:address":"Koustrupparken 40",
    "sg:city":"Herning",
    "sg:orig_category":"Reklamebureauer",
    "sg:phone":"+45 97 12 50 10",
    "sg:postcode":"7400",
    "sg:province":"Danmark",
    "wof:name":"Baxx Reklamebureau ApS",
    "wof:placetype":"venue"
},
  "geometry": {"coordinates":[8.9852924347,56.112739563],"type":"Point"}
}