{
  "type": "Feature",
  "properties": {
    "addr:full":"M\u00f8lleg\u00e5rdsvej 52 Silkeborg Danmark 8600",
    "addr:housenumber":"52",
    "addr:postcode":"8600",
    "addr:street":"Mollegaardsvej",
    "iso:country":"DK",
    "sg:address":"M\u00f8lleg\u00e5rdsvej 52",
    "sg:city":"Silkeborg",
    "sg:orig_category":"Autoreparation og -service",
    "sg:phone":"+45 86 85 30 88",
    "sg:postcode":"8600",
    "sg:province":"Danmark",
    "wof:name":"Resenbro Auto",
    "wof:placetype":"venue"
},
  "geometry": {"coordinates":[9.5524425507,56.1693305969],"type":"Point"}
}