{
  "type": "Feature",
  "properties": {
    "addr:full":"Fmd.: Hans Andersen, Spurvelunden 2, Vejle Broby Danmark 5672",
    "addr:housenumber":"2",
    "addr:postcode":"5672",
    "addr:street":"Spurvelunden",
    "iso:country":"DK",
    "sg:address":"Fmd.: Hans Andersen, Spurvelunden 2, Vejle",
    "sg:city":"Broby",
    "sg:orig_category":"Hobbybetonede foreninger",
    "sg:phone":"+45 62 69 18 48",
    "sg:postcode":"5672",
    "sg:province":"Danmark",
    "wof:name":"Nr. S\u00f8by Og Omegns Bridgeklub",
    "wof:placetype":"venue"
},
  "geometry": {"coordinates":[10.3131303787,55.2695846558],"type":"Point"}
}