{
  "type": "Feature",
  "properties": {
    "addr:full":"v/ Annette Fuhr, L\u00e6ss\u00f8egade 9 B, st. Odense C Danmark 5000",
    "addr:housenumber":"9 b",
    "addr:postcode":"5000",
    "addr:street":"Laessoegade;St.",
    "iso:country":"DK",
    "sg:address":"v/ Annette Fuhr, L\u00e6ss\u00f8egade 9 B, st.",
    "sg:city":"Odense C",
    "sg:orig_category":"\u00c3\u02dcvrig fritidsundervisning",
    "sg:phone":"+45 66 19 04 03",
    "sg:postcode":"5000",
    "sg:province":"Danmark",
    "wof:name":"Atelier Artilleriet",
    "wof:placetype":"venue"
},
  "geometry": {"coordinates":[10.390794754,55.3961715698],"type":"Point"}
}