{
  "type": "Feature",
  "properties": {
    "addr:full":"Vodskovvej 10 Vodskov Danmark 9310",
    "addr:housenumber":"10",
    "addr:postcode":"9310",
    "addr:street":"Vodskovvej",
    "iso:country":"DK",
    "sg:address":"Vodskovvej 10",
    "sg:city":"Vodskov",
    "sg:orig_category":"Autoophug",
    "sg:phone":"+45 98 29 10 00",
    "sg:postcode":"9310",
    "sg:province":"Danmark",
    "wof:name":"Opeldele",
    "wof:placetype":"venue"
},
  "geometry": {"coordinates":[10.0181455612,57.1004676819],"type":"Point"}
}