{
  "type": "Feature",
  "properties": {
    "addr:full":"Fmd.: Finn Hass, Kernev\u00e6nget 4 Snekkersten Danmark 3070",
    "addr:housenumber":"4",
    "addr:postcode":"3070",
    "iso:country":"DK",
    "sg:address":"Fmd.: Finn Hass, Kernev\u00e6nget 4",
    "sg:city":"Snekkersten",
    "sg:orig_category":"Faglige organisationer og foreninger",
    "sg:phone":"+45 49 22 19 78",
    "sg:postcode":"3070",
    "sg:province":"Danmark",
    "wof:name":"Ledernes Hovedorganisation",
    "wof:placetype":"venue"
},
  "geometry": {"coordinates":[12.5851154327,56.0076637268],"type":"Point"}
}