{
  "type": "Feature",
  "properties": {
    "addr:full":"Agerstien 2, T\u00e5rup Gelsted Danmark 5591",
    "addr:housenumber":"2",
    "addr:postcode":"5591",
    "addr:street":"Agerstien",
    "iso:country":"DK",
    "sg:address":"Agerstien 2, T\u00e5rup",
    "sg:city":"Gelsted",
    "sg:orig_category":"Planteskoler",
    "sg:phone":"+45 64 49 12 06",
    "sg:postcode":"5591",
    "sg:province":"Danmark",
    "wof:name":"Gartneriet T\u00e5ruplund",
    "wof:placetype":"venue"
},
  "geometry": {"coordinates":[9.9734048843,55.3995094299],"type":"Point"}
}