{
  "type": "Feature",
  "properties": {
    "iso:country":"DK",
    "sg:address":"Odinsvej 11",
    "sg:city":"Glostrup",
    "sg:orig_category":"Databehandling",
    "sg:phone":"+45 43 44 10 70",
    "sg:postcode":"2600",
    "sg:province":"Danmark",
    "wof:name":"Gtech Nothern Europe Corporation",
    "wof:placetype":"venue"
},
  "geometry": {"coordinates":[12.3753957748,55.6628379822],"type":"Point"}
}