{
  "type": "Feature",
  "properties": {
    "addr:full":"Gersonsvej 75 - 77 Hellerup Danmark 2900",
    "addr:housenumber":"75 77",
    "addr:postcode":"2900",
    "addr:street":"Gersonsvej",
    "iso:country":"DK",
    "sg:address":"Gersonsvej 75 - 77",
    "sg:city":"Hellerup",
    "sg:orig_category":"Danseundervisning",
    "sg:phone":"+45 39 62 45 47",
    "sg:postcode":"2900",
    "sg:province":"Danmark",
    "sg:website":"www.komogdans.dk",
    "wof:name":"Kom og Dans",
    "wof:placetype":"venue"
},
  "geometry": {"coordinates":[12.5659790039,55.7394447327],"type":"Point"}
}