{
  "type": "Feature",
  "properties": {
    "addr:full":"Holmbladsvej 5 Silkeborg Danmark 8600",
    "addr:housenumber":"5",
    "addr:postcode":"8600",
    "addr:street":"Holmbladsvej",
    "iso:country":"DK",
    "sg:address":"Holmbladsvej 5",
    "sg:city":"Silkeborg",
    "sg:orig_category":"Golfudstyr",
    "sg:phone":"+45 86 81 61 12",
    "sg:postcode":"8600",
    "sg:province":"Danmark",
    "wof:name":"Danish Golf Trading",
    "wof:placetype":"venue"
},
  "geometry": {"coordinates":[9.5616197586,56.1996650696],"type":"Point"}
}