{
  "type": "Feature",
  "properties": {
    "addr:full":"Fmd.: J\u00f8rgen Madsen, Bangsvej 5 Sorring Danmark 8641",
    "addr:housenumber":"5",
    "addr:postcode":"8641",
    "addr:street":"Madsen Bangsvej",
    "iso:country":"DK",
    "sg:address":"Fmd.: J\u00f8rgen Madsen, Bangsvej 5",
    "sg:city":"Sorring",
    "sg:orig_category":"\u00c3\u2020ldreorganisationer og klubber",
    "sg:phone":"+45 86 95 70 07",
    "sg:postcode":"8641",
    "sg:province":"Danmark",
    "wof:name":"Sorring og Toustrup Pensionistforening",
    "wof:placetype":"venue"
},
  "geometry": {"coordinates":[9.7754774094,56.1770935059],"type":"Point"}
}