{
  "type": "Feature",
  "properties": {
    "iso:country":"DK",
    "sg:address":"Holmev\u00e6nget 8 ",
    "sg:city":"Aarup",
    "sg:classifiers":[
        {
            "category":"Home & Garden",
            "subcategory":"Home Furnishings",
            "type":"Retail Goods"
        }
    ],
    "sg:phone":"+45 62 50 16 16",
    "sg:postcode":"5560",
    "sg:province":"Danmark",
    "sg:tags":[
        "household"
    ],
    "wof:name":"TRANEK\u00c6R FURNITURE A/S",
    "wof:placetype":"venue"
},
  "geometry": {"coordinates":[-93.1630935669,32.8507347107],"type":"Point"}
}