{
  "type": "Feature",
  "properties": {
    "iso:country":"DK",
    "sg:address":"Kongevejen 39",
    "sg:city":"Holte",
    "sg:orig_category":"Begravelsesforretninger",
    "sg:phone":"+45 45 42 08 08",
    "sg:postcode":"2840",
    "sg:province":"Danmark",
    "sg:website":"www.begravelsesfirma.dk",
    "wof:name":"Begravelsesforretningen Holte/S\u00f8ller\u00f8d",
    "wof:placetype":"venue"
},
  "geometry": {"coordinates":[12.470319,55.814194],"type":"Point"}
}