{
  "type": "Feature",
  "properties": {
    "iso:country":"DK",
    "sg:address":"Storegade 85",
    "sg:city":"Esbjerg",
    "sg:orig_category":"Grillbarer",
    "sg:phone":"+45 75 13 10 58",
    "sg:postcode":"6700",
    "sg:province":"Danmark",
    "wof:name":"Aladdin Grillen",
    "wof:placetype":"venue"
},
  "geometry": {"coordinates":[8.4714355469,55.4725112915],"type":"Point"}
}