{
  "type": "Feature",
  "properties": {
    "iso:country":"DK",
    "sg:address":"Pilev\u00e6nget 1, Skelstrup",
    "sg:city":"Maribo",
    "sg:orig_category":"Blikkenslagere",
    "sg:phone":"+45 54 78 05 42",
    "sg:postcode":"4930",
    "sg:province":"Danmark",
    "wof:name":"Hunseby Smedie",
    "wof:placetype":"venue"
},
  "geometry": {"coordinates":[11.502035,54.774384],"type":"Point"}
}