{
  "type": "Feature",
  "properties": {
    "addr:full":"H\u00e5ndv\u00e6rkervej 63 Esbjerg V Danmark 6710",
    "addr:housenumber":"63",
    "addr:postcode":"6710",
    "addr:street":"Haandvaerkervej",
    "iso:country":"DK",
    "sg:address":"H\u00e5ndv\u00e6rkervej 63",
    "sg:city":"Esbjerg V",
    "sg:orig_category":"Pelsdyravl",
    "sg:phone":"+45 75 15 21 18",
    "sg:postcode":"6710",
    "sg:province":"Danmark",
    "wof:name":"Mathiesen, Poul Erik",
    "wof:placetype":"venue"
},
  "geometry": {"coordinates":[8.4009799957,55.5313110352],"type":"Point"}
}