{
  "type": "Feature",
  "properties": {
    "addr:full":"N\u00f8rhaven 8, Over Draaby J\u00e6gerspris Danmark 3630",
    "addr:housenumber":"8",
    "addr:postcode":"3630",
    "addr:street":"Norhaven;Over Draaby;Danmark",
    "iso:country":"DK",
    "sg:address":"N\u00f8rhaven 8, Over Draaby",
    "sg:city":"J\u00e6gerspris",
    "sg:orig_category":"Genbrugspladser",
    "sg:postcode":"3630",
    "sg:province":"Danmark",
    "wof:name":"Genbrugs- og Modtageplads",
    "wof:placetype":"venue"
},
  "geometry": {"coordinates":[11.9136800766,55.9269866943],"type":"Point"}
}