{
  "type": "Feature",
  "properties": {
    "addr:full":"Skuderl\u00f8sevej 44 Haslev Danmark 4690",
    "addr:housenumber":"44",
    "addr:postcode":"4690",
    "addr:street":"Skuderlosevej",
    "iso:country":"DK",
    "sg:address":"Skuderl\u00f8sevej 44",
    "sg:city":"Haslev",
    "sg:orig_category":"Autoforhandlere",
    "sg:phone":"+45 56 32 62 17",
    "sg:postcode":"4690",
    "sg:province":"Danmark",
    "wof:name":"Skuderl\u00f8se Auto",
    "wof:placetype":"venue"
},
  "geometry": {"coordinates":[11.8801584244,55.3004684448],"type":"Point"}
}