{
  "type": "Feature",
  "properties": {
    "addr:full":"Langen\u00e6s Alle 29 \u00c5rhus C Danmark 8000",
    "addr:housenumber":"29",
    "addr:postcode":"8000",
    "addr:street":"Langenaes Alle",
    "iso:country":"DK",
    "sg:address":"Langen\u00e6s Alle 29",
    "sg:city":"\u00c5rhus C",
    "sg:orig_category":"Integrerede institutioner",
    "sg:phone":"+45 86 14 87 55",
    "sg:postcode":"8000",
    "sg:province":"Danmark",
    "wof:name":"B\u00f8rnehuset 29",
    "wof:placetype":"venue"
},
  "geometry": {"coordinates":[4.717400074,49.7588005066],"type":"Point"}
}