{
  "type": "Feature",
  "properties": {
    "addr:full":"Navergangen 12 Karlslunde Danmark 2690",
    "addr:housenumber":"12",
    "addr:postcode":"2690",
    "addr:street":"Navergangen",
    "iso:country":"DK",
    "sg:address":"Navergangen 12",
    "sg:city":"Karlslunde",
    "sg:orig_category":"Emballage",
    "sg:phone":"+45 46 15 51 11",
    "sg:postcode":"2690",
    "sg:province":"Danmark",
    "sg:website":"www.kwcases.dk.",
    "wof:name":"KW Cases Aps",
    "wof:placetype":"venue"
},
  "geometry": {"coordinates":[12.2338485718,55.569984436],"type":"Point"}
}