{
  "type": "Feature",
  "properties": {
    "addr:full":"Socialforvaltningen, Kirkegade 14 Gudme Danmark 5884",
    "addr:housenumber":"14",
    "addr:postcode":"5884",
    "addr:street":"Kirkegade",
    "iso:country":"DK",
    "sg:address":"Socialforvaltningen, Kirkegade 14",
    "sg:city":"Gudme",
    "sg:orig_category":"Dagplejeformidling",
    "sg:phone":"+45 63 25 13 00",
    "sg:postcode":"5884",
    "sg:province":"Danmark",
    "wof:name":"Dagplejeformidlingen",
    "wof:placetype":"venue"
},
  "geometry": {"coordinates":[10.7078762054,55.1509132385],"type":"Point"}
}