{
  "type": "Feature",
  "properties": {
    "addr:full":"Hobrovej 75, \u00d8. Doense Hobro Danmark 9500",
    "addr:housenumber":"75 o.",
    "addr:postcode":"9500",
    "addr:street":"Hobrovej",
    "iso:country":"DK",
    "sg:address":"Hobrovej 75, \u00d8. Doense",
    "sg:city":"Hobro",
    "sg:orig_category":"Minidozere og -gravere",
    "sg:phone":"+45 98 55 44 31",
    "sg:postcode":"9500",
    "sg:province":"Danmark",
    "sg:website":"www.vebbestrup-minidozer.dk",
    "wof:name":"Vebbestrup Minidozer",
    "wof:placetype":"venue"
},
  "geometry": {"coordinates":[9.7946596146,56.6382789612],"type":"Point"}
}