{
  "type": "Feature",
  "properties": {
    "iso:country":"DK",
    "sg:address":"Fmd.: Kathrine Pedersen, Rish\u00f8jvej 19",
    "sg:city":"Bedsted",
    "sg:orig_category":"Spejderkorps",
    "sg:phone":"+45 97 94 53 95",
    "sg:postcode":"7755",
    "sg:province":"Danmark",
    "wof:name":"DDS, 1. Ash\u00f8je Gruppe",
    "wof:placetype":"venue"
},
  "geometry": {"coordinates":[8.4905691147,56.8179664612],"type":"Point"}
}