{
  "type": "Feature",
  "properties": {
    "addr:full":"Hovedgaden 19 Kirke Hvals\u00f8 Danmark 4330",
    "addr:housenumber":"19",
    "addr:postcode":"4330",
    "addr:street":"Hovedgaden",
    "iso:country":"DK",
    "sg:address":"Hovedgaden 19",
    "sg:city":"Kirke Hvals\u00f8",
    "sg:orig_category":"Kiosker",
    "sg:phone":"+45 46 40 82 21",
    "sg:postcode":"4330",
    "sg:province":"Danmark",
    "wof:name":"N\u00e6rK\u00f8b, D\u00f8gneren",
    "wof:placetype":"venue"
},
  "geometry": {"coordinates":[9.2555503845,54.9375686646],"type":"Point"}
}