{
  "type": "Feature",
  "properties": {
    "iso:country":"DK",
    "sg:address":"Havnen 10",
    "sg:city":"K\u00f8ge",
    "sg:orig_category":"Stevedorer",
    "sg:phone":"+45 56 65 16 19",
    "sg:postcode":"4600",
    "sg:province":"Danmark",
    "wof:name":"K\u00f8ge Stevedore A/S",
    "wof:placetype":"venue"
},
  "geometry": {"coordinates":[12.2430353165,55.4170417786],"type":"Point"}
}