{
  "type": "Feature",
  "properties": {
    "addr:full":"B\u00f8dkervej 16 Hanstholm Danmark 7730",
    "addr:housenumber":"16",
    "addr:postcode":"7730",
    "addr:street":"Bodkervej",
    "iso:country":"DK",
    "sg:address":"B\u00f8dkervej 16",
    "sg:city":"Hanstholm",
    "sg:classifiers":[
        {
            "category":"Taxi",
            "type":"Transportation"
        }
    ],
    "sg:phone":"+45 97 96 21 11",
    "sg:postcode":"7730",
    "sg:province":"Danmark",
    "wof:name":"Falke Taxi",
    "wof:placetype":"venue"
},
  "geometry": {"coordinates":[8.6271209717,57.1169700623],"type":"Point"}
}