{
  "type": "Feature",
  "properties": {
    "addr:full":"Vejlevej 171, Riis Give Danmark 7323",
    "addr:housenumber":"171",
    "addr:postcode":"7323",
    "addr:street":"Vejlevej;Riis",
    "iso:country":"DK",
    "sg:address":"Vejlevej 171, Riis",
    "sg:city":"Give",
    "sg:orig_category":"Murermestre",
    "sg:phone":"+45 75 73 02 24",
    "sg:postcode":"7323",
    "sg:province":"Danmark",
    "wof:name":"Egsg\u00e5rd ApS, Murerfirmaet E.",
    "wof:placetype":"venue"
},
  "geometry": {"coordinates":[9.2362060547,55.845413208],"type":"Point"}
}