{
  "type": "Feature",
  "properties": {
    "addr:full":"\u00d8stergade 60 Ikast Danmark 7430",
    "addr:housenumber":"60",
    "addr:postcode":"7430",
    "addr:street":"Ostergade",
    "iso:country":"DK",
    "sg:address":"\u00d8stergade 60",
    "sg:city":"Ikast",
    "sg:orig_category":"Benzinstationer",
    "sg:phone":"+45 97 15 38 29",
    "sg:postcode":"7430",
    "sg:province":"Danmark",
    "sg:website":"www.hydrotexaco.dk",
    "wof:name":"Uno-X",
    "wof:placetype":"venue"
},
  "geometry": {"coordinates":[9.1638622284,56.1399536133],"type":"Point"}
}