{
  "type": "Feature",
  "properties": {
    "addr:full":"Bogensevej 16 Randers Danmark 8900",
    "addr:housenumber":"16",
    "addr:postcode":"8900",
    "addr:street":"Bogensevej",
    "iso:country":"DK",
    "sg:address":"Bogensevej 16",
    "sg:city":"Randers",
    "sg:classifiers":[
        {
            "category":"Food & Beverages",
            "subcategory":"Liquor & Beverages",
            "type":"Retail Goods"
        }
    ],
    "sg:phone":"+45 86 40 21 11",
    "sg:postcode":"8900",
    "sg:province":"Danmark",
    "sg:tags":[
        "vin"
    ],
    "wof:name":"J. J. Vinimport I/S",
    "wof:placetype":"venue"
},
  "geometry": {"coordinates":[10.0320701599,56.4365577698],"type":"Point"}
}