{
  "type": "Feature",
  "properties": {
    "addr:full":"Marselis Boulevard 52 \u00c5rhus C Danmark 8000",
    "addr:housenumber":"52",
    "addr:postcode":"8000",
    "addr:street":"Marselis Boulevard",
    "iso:country":"DK",
    "sg:address":"Marselis Boulevard 52",
    "sg:city":"\u00c5rhus C",
    "sg:orig_category":"Fritidshjem",
    "sg:phone":"+45 86 13 94 88",
    "sg:postcode":"8000",
    "sg:province":"Danmark",
    "wof:name":"Marselisparken, Fritidshjem",
    "wof:placetype":"venue"
},
  "geometry": {"coordinates":[-116.27327728269999,32.6635398865],"type":"Point"}
}