{
  "type": "Feature",
  "properties": {
    "addr:full":"Holmeg\u00e5rdsvej 101 Kokkedal Danmark 2980",
    "addr:housenumber":"101",
    "addr:postcode":"2980",
    "addr:street":"Holmegaardsvej",
    "iso:country":"DK",
    "sg:address":"Holmeg\u00e5rdsvej 101",
    "sg:city":"Kokkedal",
    "sg:orig_category":"Skolefritidsordninger",
    "sg:phone":"+45 45 17 50 56",
    "sg:postcode":"2980",
    "sg:province":"Danmark",
    "wof:name":"SFO-45, Egedalsskolen",
    "wof:placetype":"venue"
},
  "geometry": {"coordinates":[12.4894657135,55.9083023071],"type":"Point"}
}