{
  "type": "Feature",
  "properties": {
    "addr:full":"Vangede Bygade 45 Gentofte Danmark 2820",
    "addr:housenumber":"45",
    "addr:postcode":"2820",
    "addr:street":"Vangede Bygade",
    "iso:country":"DK",
    "sg:address":"Vangede Bygade 45",
    "sg:city":"Gentofte",
    "sg:orig_category":"Filialbiblioteker",
    "sg:phone":"+45 39 65 38 47",
    "sg:postcode":"2820",
    "sg:province":"Danmark",
    "wof:name":"Vangede Filialbibliotek",
    "wof:placetype":"venue"
},
  "geometry": {"coordinates":[12.5187110901,55.7511672974],"type":"Point"}
}