{
  "type": "Feature",
  "properties": {
    "addr:full":"v/ Birthe Jensen, Havn\u00f8vej 33, Visborg Hadsund Danmark 9560",
    "addr:housenumber":"33",
    "addr:postcode":"9560",
    "addr:street":"Havnovej",
    "iso:country":"DK",
    "sg:address":"v/ Birthe Jensen, Havn\u00f8vej 33, Visborg",
    "sg:city":"Hadsund",
    "sg:orig_category":"Borger- og beboerforeninger",
    "sg:phone":"+45 98 57 43 98",
    "sg:postcode":"9560",
    "sg:province":"Danmark",
    "wof:name":"Visborg Borgerforening",
    "wof:placetype":"venue"
},
  "geometry": {"coordinates":[10.115904808,56.7150764465],"type":"Point"}
}