{
  "type": "Feature",
  "properties": {
    "addr:full":"Skovm\u00f8llevej 22 Vejle Danmark 7100",
    "addr:housenumber":"22",
    "addr:postcode":"7100",
    "addr:street":"Skovmollevej",
    "iso:country":"DK",
    "sg:address":"Skovm\u00f8llevej 22",
    "sg:city":"Vejle",
    "sg:orig_category":"Murermestre",
    "sg:phone":"+45 75 82 59 17",
    "sg:postcode":"7100",
    "sg:province":"Danmark",
    "wof:name":"Jensen, Kjeld E.",
    "wof:placetype":"venue"
},
  "geometry": {"coordinates":[9.4873857498,55.6937255859],"type":"Point"}
}