{
  "type": "Feature",
  "properties": {
    "iso:country":"DK",
    "sg:address":"Produktionvej 3 ",
    "sg:city":"Glostrup",
    "sg:classifiers":[
        {
            "category":"Wholesale",
            "subcategory":"Medical Equipment & Supplies",
            "type":"Manufacturing & Wholesale Goods"
        }
    ],
    "sg:phone":"+45 36 41 58 00",
    "sg:postcode":"2600",
    "sg:province":"Danmark",
    "sg:tags":[
        "-",
        "health",
        "instrument"
    ],
    "wof:name":"SANTAX MEDICO",
    "wof:placetype":"venue"
},
  "geometry": {"coordinates":[12.4246530533,55.6984596252],"type":"Point"}
}