{
  "type": "Feature",
  "properties": {
    "iso:country":"DK",
    "sg:address":"Vester Voldgade 102 4 th",
    "sg:city":"K\u00f8benhavn",
    "sg:orig_category":"Konsulentvirksomheder",
    "sg:phone":"+45 33 93 86 36",
    "sg:postcode":"1552",
    "sg:province":"Danmark",
    "wof:name":"Bowmtan, Thomas",
    "wof:placetype":"venue"
},
  "geometry": {"coordinates":[12.570400238,55.6759986877],"type":"Point"}
}