{
  "type": "Feature",
  "properties": {
    "addr:full":"Nygade 9 Nakskov Danmark 4900",
    "addr:housenumber":"9",
    "addr:postcode":"4900",
    "addr:street":"Nygade",
    "iso:country":"DK",
    "sg:address":"Nygade 9",
    "sg:city":"Nakskov",
    "sg:orig_category":"Optikere",
    "sg:phone":"+45 54 92 05 21",
    "sg:postcode":"4900",
    "sg:province":"Danmark",
    "wof:name":"H\u00f8j, Lau",
    "wof:placetype":"venue"
},
  "geometry": {"coordinates":[11.1401720047,54.8302612305],"type":"Point"}
}