{
  "type": "Feature",
  "properties": {
    "addr:full":"Idr\u00e6tsvej 11 Hurup Danmark 7760",
    "addr:housenumber":"11",
    "addr:postcode":"7760",
    "addr:street":"Idraetsvej",
    "iso:country":"DK",
    "sg:address":"Idr\u00e6tsvej 11",
    "sg:city":"Hurup",
    "sg:orig_category":"Kommunale folkeskoler",
    "sg:phone":"+45 97 95 15 99",
    "sg:postcode":"7760",
    "sg:province":"Danmark",
    "wof:name":"Hurup Skole",
    "wof:placetype":"venue"
},
  "geometry": {"coordinates":[8.4165763855,56.7535591125],"type":"Point"}
}