{
  "type": "Feature",
  "properties": {
    "addr:full":"Gadek\u00e6rsvej 11, Sejlflod Storvorde Danmark 9280",
    "addr:housenumber":"11",
    "addr:postcode":"9280",
    "addr:street":"Gadekaersvej;Sejlflod",
    "iso:country":"DK",
    "sg:address":"Gadek\u00e6rsvej 11, Sejlflod",
    "sg:city":"Storvorde",
    "sg:orig_category":"Autoreparation og -service",
    "sg:phone":"+45 98 31 65 51",
    "sg:postcode":"9280",
    "sg:province":"Danmark",
    "wof:name":"Peters Autov\u00e6rksted",
    "wof:placetype":"venue"
},
  "geometry": {"coordinates":[10.1014204025,57.0045547485],"type":"Point"}
}