{
  "type": "Feature",
  "properties": {
    "addr:full":"Firhuse 9 Bording Danmark 7441",
    "addr:housenumber":"9",
    "addr:postcode":"7441",
    "addr:street":"Firhuse",
    "iso:country":"DK",
    "sg:address":"Firhuse 9",
    "sg:city":"Bording",
    "sg:orig_category":"Genbrugscentre",
    "sg:phone":"+45 86 86 52 79",
    "sg:postcode":"7441",
    "sg:province":"Danmark",
    "wof:name":"Genbrugspladsen Julianehede",
    "wof:placetype":"venue"
},
  "geometry": {"coordinates":[9.3015050888,56.1582641602],"type":"Point"}
}